{
    "original": "Lindgren, Leonard Ferdinand\nValfrid, musikdirektör, Malmö, f. 30/1/99\nIi Lund av Alfred L. o-. Anna Maria\nKjäll. G. 23 m. Olga Gunhild Linnea\nBrandoné. Barn: Kjell, Lennart,\nInga-lillll. — Mil. musikdir :ex. v. musikkors.\n212, stud. viollin f. Peder Möller o.\ndii-rig.1 If. Georg Sclhnéevoigt. Andre\ndii-rig. i konsierthusistift. ork. o&gt;. v.\nMall-mö stadsteater, chef f. Máltmö\nmusikköns, fr. 34 samt lär. där i violin,\ninstrumentation, dirig., ensemble- o.\nor-ik :’S&gt;pe’lnlng.\n\nLindgren, Joel Gottfrid,\nhamnkapten, Trelleborg, f. 26/4/86 i\nNederka-lix, Norrb. 1., av ångb :befälh. Anders\nL. o. Johanna Nilsson. G. 15 m. Emma\nStjernberg. Barn: Gun f. 16, g. m.\nförsäljn xhef C. A. Almarker, Gbg, Märta\n.21. — Sjökapt:ex. 07, res :off :asp\n:-kurs 07-08, löjtn. i Flottans res. Tjg.\ns. styrm, 08-12, ångf :befälh. 12-20,\nhamnkapten o. arb xhef i Trelleb. sed.\n21. Sjömanshusomb :man sed. 22, ordf.\ni hand:- o. sjöf :nd. RVO 39.\n\nLindgren, John Vilhelm Fredrik,\nmajor i Flygv. res., Malmö, f. 18/7/96\ni Malmö av grossh. Vilhelm L. o.\nJohanna Persson. G. 27 m. Matilda\nLindholm. Barn: Lennart f. 30, Märit\n35. — Stud:ex. 16, off:ex. 19,\nflyg-spansk. 21, AIHS 22, gymn:dir:ex.\n26, int:ex. 34. Stud. v. franska arméns\ngymn:- o. fäktsk. i Joinville le Pont\n29. Fänr. v. Gotl. art :kår 20, löjtn.\ndär 22, kapten 35, i int :befattn. v.\nFlygv. 38, major i Flygv. 44, avsk. m.\npens. 47. Deläg. i Lindeborgs gård i\nMalmö, i firma Lindgren o.\nMårtenssons Eftr. i Malmö o. i Verkst. A-B\nLindgren &amp; Ohlsson i Malmö,\nstyr:-led. i sistnämnda samt i\nMarknadsplatsens Dragare A-B i Malmö o.\nSkånes Vapenhist. fören. Hobbies:\nsegelflygn, (C-dipl. 45), gamla vapen\n(sv.  armémodeller).   RSO 40.\n\nLindgren, Martin Ludvig Oscar,\nmed. lic, Lund, f. 24/9/10 i Berlin av\nkörsn. Jobn Martin L. o. Eva\nJaenic-ke. G. 39 m. gymn :dir. Elsa\nAndersson. Barn: Olas f. 40, Eva 41, Martám\n44. — Studiex. i Berlin 29, tysk\nlak:-ex. v. Berlins univ. 36, Dr. med. där\n318, disp. fr. med. kand:ex., med. lic.\ni Lund 38. Vol :assist. v.\nUniv.-Frauen-klinik der Charité i Berlin 3 mån.\n317, assist :ilak. v. kir. klin. i Lund 4\nmån. 38, tif. andre und :läk. v. las. i\nLandskr. 9 mån. 38-39, annan1, o. und:-\n\nläk. v. Lunds ’l!as, röntgendiagn. avd.\njan. 40-april1 43, ’förste und riliäk. o. sen,\nblitr. läk. v. Hallmistads das.\nröntgeni-avd. maj 4l3Lokt. 4*6, aman. o. und :läk.\nv. centrranst. f. radioterapi i Lund\nsed. 46.\n\n",
    "structured": {
        "1": {
            "full_name": "Leonard Ferdinand Lindgren",
            "location": "Malmö",
            "occupation": "Mil. musikdirektör",
            "birth_details": {
                "date": "30/01/1899",
                "place": "Lund",
                "parents": "Alfred L. Lindgren, Anna Maria Kjäll"
            },
            "education": [
                {
                    "degree": "Mil. musikdir",
                    "year": "212",
                    "institution": "Peder Möller"
                },
                {
                    "degree": "ex. v. musikkors",
                    "year": "NULL",
                    "institution": "NULL"
                },
                {
                    "degree": "stud. viollin",
                    "year": "NULL",
                    "institution": "NULL"
                },
                {
                    "degree": "dii-rig",
                    "year": "NULL",
                    "institution": "Georg Sclhnéevoigt"
                }
            ],
            "career": [
                {
                    "position": "dir. i konsierthusist. ork.",
                    "years": {
                        "start_year": 34,
                        "end_year": "NULL"
                    },
                    "organization": "NULL"
                }
            ],
            "family": {
                "spouse": "Olga Gunhild Linnea Brandoné",
                "marriage_year": "23",
                "children": [
                    {
                        "name": "Kjell",
                        "birth_year": "NULL"
                    },
                    {
                        "name": "Lennart",
                        "birth_year": "NULL"
                    },
                    {
                        "name": "Inga-lillll",
                        "birth_year": "NULL"
                    }
                ]
            }
        },
        "2": {
            "full_name": "Joel Gottfrid Lindgren",
            "location": "Trelleborg",
            "occupation": "Sjökapt",
            "birth_details": {
                "date": "26/04/1886",
                "place": "Nederkalix, Norrbottens län",
                "parents": "ångb :befälh. Anders Lindgren, Johanna Nilsson"
            },
            "education": [
                {
                    "degree": "Sjökapt",
                    "year": "07",
                    "institution": "NULL"
                },
                {
                    "degree": "NULL",
                    "year": "NULL",
                    "institution": "NULL"
                }
            ],
            "career": [
                {
                    "position": "hamnkapten o. arb xhef",
                    "years": {
                        "start_year": 21,
                        "end_year": "NULL"
                    },
                    "organization": "Trelleborg"
                }
            ],
            "family": {
                "spouse": "Emma Stjernberg",
                "marriage_year": "15",
                "children": [
                    {
                        "name": "Gun",
                        "birth_year": "16"
                    }
                ]
            }
        },
        "3": {
            "full_name": "John Vilhelm Fredrik Lindgren",
            "location": "Malmö",
            "occupation": "major i Flygv. res",
            "birth_details": {
                "date": "18/07/1896",
                "place": "Malmö",
                "parents": "grossh. Vilhelm Lindgren, Johanna Persson"
            },
            "education": [
                {
                    "degree": "Stud",
                    "year": "16",
                    "institution": "NULL"
                },
                {
                    "degree": "int",
                    "year": "34",
                    "institution": "NULL"
                }
            ],
            "career": [
                {
                    "position": "avsk. m. pens",
                    "years": {
                        "start_year": 47,
                        "end_year": "NULL"
                    },
                    "organization": "NULL"
                }
            ],
            "family": {
                "spouse": "Matilda Lindholm",
                "marriage_year": "27",
                "children": [
                    {
                        "name": "Lennart",
                        "birth_year": "30"
                    },
                    {
                        "name": "Märit",
                        "birth_year": "35"
                    }
                ]
            }
        },
        "4": {
            "full_name": "Martin Ludvig Oscar Lindgren",
            "location": "Lund",
            "occupation": "med. lic",
            "birth_details": {
                "date": "24/09/1910",
                "place": "Berlin",
                "parents": "körsn. Jobn Martin Lindgren, Eva Jaenicke"
            },
            "education": [
                {
                    "degree": "Studiex",
                    "year": "29",
                    "institution": "Berlin"
                },
                {
                    "degree": "Dr. med",
                    "year": "318",
                    "institution": "Berlins univ"
                }
            ],
            "career": [
                {
                    "position": "aman. o. und :läk",
                    "years": {
                        "start_year": 46,
                        "end_year": "NULL"
                    },
                    "organization": "centrranst. f. radioterapi i Lund"
                }
            ],
            "family": {
                "spouse": "NULL",
                "marriage_year": "39",
                "children": [
                    {
                        "name": "Olas",
                        "birth_year": "40"
                    },
                    {
                        "name": "Eva",
                        "birth_year": "41"
                    },
                    {
                        "name": "Martám",
                        "birth_year": "44"
                    }
                ]
            }
        }
    }
}