{
    "original": "Löfkvist, Amandus Gotthard,\ndirektör, Hälsing-borg, f. 8/11/83 i Uråsa,\nKroniofo. 1., av trädg:mäst. Sven L. o.\nMaria Johansson.. G. 07 m. Amanda\nPettersson. Barn: Walter f. OS,\nAnna-Lisa 09, Karin 11, Kjell-Erik; 14,\nEdit 16, Stig-Äke 19, Nils-Ture 21,\nBritta 22, Stina 24, Kerstin 25,\nMaja-Greta 27, Karl-Holger 29. — Stud: res.\n:s. hantv:inst. stip. t. Tysikl; 14, åter t.\nTyskl. 36 o. 39. Anst. s. verfcmäst.\nv. Scania Vabis i Södertälje 17, i\nHäl-siingb. 118-21, inneh. tills, m. E,\nCeder-vall Hälsingb. Automobilverkstäder\n21-25, verks t. dir. f. Hälsingb.\nAuto-miobilverikstäder A-B (Habil) sed. 25.\nStyr:led. i Skånes\nautomobdlhandl:-ifören. sed. 40, ordf. i Skånes\nbilverkstad, fören. avd. 1 Hälsingb., ded. av\n’bilmek. koimm. f. B. R. F. sed. 3S2.\nHobbies■■: fiske, bridge.\n\nLöfkvist, Sigfrid, direktör, Malmö, f.\n6/5/90 i Lena, Upps. 1, av Per Adolf o.\nAnna L. G. 36 m. Svea Löfwall. —\nHand :sk., und :off :sk., SS, LOK.\nStud:resa i Tyskl. 22, uppf. resor i\nDanm. Anst. v. Wendes art :reg.\n09-17, bokhåll. v. fattigv. i Kristianstad\n18-19, försäljn :chef v. Sv.-Eng.\nMine-ralolje A-B 19-21, bokför, v. AMI\n21-22, egen reklambyrå i Malmö 22-25,\ninneh. av o. dir. f. transp :firma i\nMalmö 25-45, lstkapt. 35, komp:- o. tjf.\nbat :chef 40-46, dir. i o. jämte hustrun\ninneh. av Anna Lindgren Eftr. i\nMalmö fr. 46. Ordf. i Samlarfören.\nNordstjärnans lokalavd. i Malmö, fd. ordf.\ni Logen Skåne nr 570 av Wasaorden,\nv. ordf. o. kassör i Wendistfören.\nlokalavd. i Malmö, rev. i Malmö\nbef:-utb :fören., ordf,, i kamratfören. B öste\nkompaniet. Hobbies: filateli,\nnumis-matik, ex libris o. antikviteter. Södra\nskånska landst :fören. SM, Gustav\nPet-ri SM, CFB hed:jetong i guld, CFB\nlstGm, ovala, PistolskGm, Mil.\nfältidr-Gm, Civ. gevärs skGm, Ksp-Sm,\nR-TyskÖO.\n\n",
    "structured": {
        "1": {
            "full_name": "Amandus Gotthard Löfkvist",
            "location": "Hälsingborg",
            "occupation": "Direktör",
            "birth_details": {
                "date": "8/11/1883",
                "place": "Uråsa"
            },
            "education": [
                {
                    "degree": "Stud:res",
                    "year": "1914",
                    "institution": "Hantv:inst"
                },
                {
                    "degree": "Stip",
                    "year": "1914",
                    "institution": "Tysikl"
                },
                {
                    "degree": "Tyskl",
                    "year": "1936",
                    "institution": "NULL"
                },
                {
                    "degree": "Tyskl",
                    "year": "1939",
                    "institution": "NULL"
                }
            ],
            "career": [
                {
                    "position": "Verfcmäst",
                    "years": {
                        "start_year": 1917,
                        "end_year": 1921
                    },
                    "organization": "Scania Vabis i Södertälje"
                },
                {
                    "position": "Inneh",
                    "years": {
                        "start_year": 1921,
                        "end_year": 1925
                    },
                    "organization": "tills, m. E, Cedervall Hälsingb. Automobilverkstäder"
                },
                {
                    "position": "Verks t. dir. f. Hälsingb.",
                    "years": {
                        "start_year": 1925,
                        "end_year": "NULL"
                    },
                    "organization": "Auto-mobilverikstäder A-B (Habil)"
                }
            ],
            "family": {
                "spouse": "Amanda Pettersson",
                "marriage_year": "1907",
                "children": [
                    {
                        "name": "Walter",
                        "birth_year": "NULL"
                    },
                    {
                        "name": "Anna-Lisa",
                        "birth_year": "1909"
                    },
                    {
                        "name": "Karin",
                        "birth_year": "1911"
                    },
                    {
                        "name": "Kjell-Erik",
                        "birth_year": "1914"
                    },
                    {
                        "name": "Edit",
                        "birth_year": "1916"
                    },
                    {
                        "name": "Stig-Äke",
                        "birth_year": "1919"
                    },
                    {
                        "name": "Nils-Ture",
                        "birth_year": "1921"
                    },
                    {
                        "name": "Britta",
                        "birth_year": "1922"
                    },
                    {
                        "name": "Stina",
                        "birth_year": "1924"
                    },
                    {
                        "name": "Kerstin",
                        "birth_year": "1925"
                    },
                    {
                        "name": "Maja-Greta",
                        "birth_year": "1927"
                    },
                    {
                        "name": "Karl-Holger",
                        "birth_year": "1929"
                    }
                ]
            },
            "hobbies": [
                "Fiske",
                "Bridge"
            ]
        },
        "2": {
            "full_name": "Sigfrid Löfkvist",
            "location": "Malmö",
            "occupation": "Direktör",
            "birth_details": {
                "date": "6/5/1890",
                "place": "Lena"
            },
            "education": [
                {
                    "degree": "Stud:resa i Tyskl",
                    "year": "1922",
                    "institution": "NULL"
                }
            ],
            "career": [
                {
                    "position": "Bokför",
                    "years": {
                        "start_year": 1921,
                        "end_year": 1922
                    },
                    "organization": "AMI"
                },
                {
                    "position": "Dir. i o. jämte hustrun inneh",
                    "years": {
                        "start_year": 1946,
                        "end_year": "NULL"
                    },
                    "organization": "Anna Lindgren Eftr. i Malmö"
                }
            ],
            "family": {
                "spouse": "Svea Löfwall",
                "marriage_year": "1936",
                "children": []
            },
            "community_involvement": [
                {
                    "role": "Ordf",
                    "organization": "Samlarfören. Nordstjärnans lokalavd. i Malmö",
                    "years": "NULL"
                },
                {
                    "role": "Fd. ordf",
                    "organization": "Logen Skåne nr 570 av Wasaorden",
                    "years": "NULL"
                },
                {
                    "role": "V. ordf. o. kassör",
                    "organization": "Wendistfören. lokalavd. i Malmö",
                    "years": "NULL"
                },
                {
                    "role": "Rev",
                    "organization": "Malmö bef:-utb :fören.",
                    "years": "NULL"
                },
                {
                    "role": "Ordf",
                    "organization": "Kamratfören. B öste kompaniet",
                    "years": "NULL"
                }
            ],
            "hobbies": [
                "Filateli",
                "Numismatik",
                "Ex libris",
                "Antikviteter"
            ],
            "honorary_titles": [
                {
                    "title": "SM",
                    "institution": "Södra skånska landst :fören.",
                    "year": "NULL"
                },
                {
                    "title": "SM",
                    "institution": "Gustav Petri",
                    "year": "NULL"
                },
                {
                    "title": "CFB hed",
                    "institution": "jetong i guld",
                    "year": "NULL"
                },
                {
                    "title": "CFB lstGm",
                    "institution": "ovala",
                    "year": "NULL"
                },
                {
                    "title": "PistolskGm",
                    "institution": "NULL",
                    "year": "NULL"
                },
                {
                    "title": "Mil. fältidr-Gm",
                    "institution": "NULL",
                    "year": "NULL"
                },
                {
                    "title": "Civ. gevärs skGm",
                    "institution": "NULL",
                    "year": "NULL"
                },
                {
                    "title": "Ksp-Sm",
                    "institution": "NULL",
                    "year": "NULL"
                },
                {
                    "title": "R-TyskÖO",
                    "institution": "NULL",
                    "year": "NULL"
                }
            ]
        }
    }
}