{
    "original": "Larsson, Gunnar Hugo, tandläkare,\nOsby, f. 20/9/05 i Dala, Malmöh. 1.,\nav dir. Nils L. o. Maria Andersson.\nG. 33 m. Berta Svensson. — Stud:ex.\ni Eslöv 24, Cand. med. dent. i\nGreifs-wald 25, tysk tandl. i Leipzig 28, sv.\ntandl. 31. Prakt, i Hallstavik o.\nskol-tandl. där 31-32, prakt, i Osby o.\nskoltandl.  där  sed.  33.\n\nLarsson, Helga Petronella,\nfolkskollärarinna, Vadensjö, f. 19/2/92 i\nVadensjö, Malmöh. 1. — Folkskoll :ex. i\nLandskr. 14. Vik. folkskoll. i Träne\n14-15, i Tings-Nöbbelöv 15-16, ord. i\nHärslöv sed. 16, underv. i slöjd.\nLär:-kår. repr. i skolstyr., omb. f.\nRönne-bergskrets. av SvRK, ordf. i\nHärslövs-ort. Lottaavd. sed. 44.\n\nLarsson, Karl Ivar, signalingenjör,\nkapten VVK, Malmö, f. 14/9/88 i\nHusby-Oppunda, Södermani. 1., av\nJohan Axel L. o. Anna Larsson. G.\n1. 15 m. Ruth Dalman, d. 40; 2. 44 m.\nKarin Bergman. Barn: Marianne f.\n21, g. m. fil. kand. Sven-Georg\nLund-qvist, Sthlm, Kerstin 22, g. m. ing.\nEbbe Larsson, Sthlm, Britta 25,\nKarin 27, Gunilla 31. — Stud:ex. i\nNy-köp. 07, avg:ex. fr. KTH (V) 12,\nres:-off:ex. 09. Anst. v. SJs järnvägsbyggn.\ni Östersund 13-14, i Brunflo 15,\nund:-ing. v. ST i Storvik 16-18,\nsign:-ing. i Malmö fr. 19. Löjtn. VVK 18,\nkapten 26.   RVO 35.\n\nLarsson, Johan, ’folkskollärare, Östra\nKaraby, Marieholm, f. 8/2/86 i\nFå-igeltofta, Kristianstads 1, av\nkvarnägare Lars Mårtensson o. Hanna\nNilsson. G. 16 m. lär. Kerstin\nJönsson. Barn: Britt f. 20, fil. mag.,\nLund, Elsie 23, fil. kand., g. m. fil.\nmag.   Torkel   Markström,   Lund,   Siv\n\n26,   sem:stud., Hälsingb. — Folkskoll\n:-ex. i Lund 07. Vik. folkskoll. i\nGlem-minge 07-08, i Fågeltofta 08, ord. i\nÖstra Karaby sed. 09. Kyrkovärd, led.\nav kyrkoråd, ordf. i skolråd o.\nkyrkostämma,   i   Majfol :komm.  o.  i   Rönne-\n\nbergs, Onsjö o. Harjagers lokalfören.\nav Sv:es kyrkl. lär:förb., insp. i.\nRes-lövs föreläsn rfören., styr :led. i Onsjö\nhär. hemb : för en.\n\n",
    "structured": {
        "1": {
            "full_name": "Larsson, Gunnar Hugo",
            "location": "Osby",
            "occupation": "tandläkare",
            "birth_details": {
                "date": "20/09/1905",
                "place": "Dala, Malmöh",
                "parents": "Nils L. o. Maria Andersson"
            },
            "education": [
                {
                    "degree": "Stud:ex.",
                    "year": "1924",
                    "institution": "Eslöv"
                },
                {
                    "degree": "Cand. med. dent.",
                    "year": "1925",
                    "institution": "Greifswald"
                },
                {
                    "degree": "Tysk tandl.",
                    "year": "1928",
                    "institution": "Leipzig"
                },
                {
                    "degree": "Sv. tandl.",
                    "year": "1931",
                    "institution": "Osby"
                }
            ],
            "career": [
                {
                    "position": "Prakt, i Hallstavik",
                    "years": {
                        "start_year": 1931,
                        "end_year": 1932
                    },
                    "organization": "skol-tandl."
                },
                {
                    "position": "Prakt, i Osby",
                    "years": {
                        "start_year": 1933
                    },
                    "organization": "skoltandl."
                }
            ],
            "family": {
                "spouse": "Berta Svensson",
                "marriage_year": "1933",
                "children": []
            }
        },
        "2": {
            "full_name": "Larsson, Helga Petronella",
            "location": "Vadensjö",
            "occupation": "folkskollärarinna",
            "birth_details": {
                "date": "19/02/1892",
                "place": "Vadensjö, Malmöh",
                "parents": null
            },
            "education": [
                {
                    "degree": "Folkskoll :ex.",
                    "year": "1914",
                    "institution": "Landskr."
                }
            ],
            "career": [
                {
                    "position": "Vik. folkskoll.",
                    "years": {
                        "start_year": 1914,
                        "end_year": 1915
                    },
                    "organization": "Träne"
                },
                {
                    "position": "Vik. folkskoll.",
                    "years": {
                        "start_year": 1915,
                        "end_year": 1916
                    },
                    "organization": "Tings-Nöbbelöv"
                },
                {
                    "position": "Ord. i Härslöv",
                    "years": {
                        "start_year": 1916
                    },
                    "organization": null
                }
            ],
            "family": {
                "spouse": null,
                "marriage_year": null,
                "children": []
            }
        },
        "3": {
            "full_name": "Larsson, Karl Ivar",
            "location": "Malmö",
            "occupation": "signalingenjör, kapten VVK",
            "birth_details": {
                "date": "14/09/1888",
                "place": "Husby-Oppunda, Södermani.",
                "parents": "Johan Axel L. o. Anna Larsson"
            },
            "education": [
                {
                    "degree": "Stud:ex.",
                    "year": "1907",
                    "institution": "Ny-köp."
                },
                {
                    "degree": "Avg:ex.",
                    "year": "1912",
                    "institution": "KTH (V)"
                }
            ],
            "career": [
                {
                    "position": "Anst. v. SJs järnvägsbyggn.",
                    "years": {
                        "start_year": 1913,
                        "end_year": 1914
                    },
                    "organization": "Östersund"
                },
                {
                    "position": "Löjtn. VVK",
                    "years": {
                        "start_year": 1918
                    },
                    "organization": null
                },
                {
                    "position": "Kapten",
                    "years": {
                        "start_year": 1926
                    },
                    "organization": null
                }
            ],
            "family": {
                "spouse": "Ruth Dalman, d. 1940; Karin Bergman",
                "marriage_year": "1915; 1944",
                "children": [
                    {
                        "name": "Marianne",
                        "birth_year": "1921"
                    },
                    {
                        "name": "Kerstin",
                        "birth_year": "1922"
                    },
                    {
                        "name": "Britta",
                        "birth_year": "1925"
                    },
                    {
                        "name": "Karin",
                        "birth_year": "1927"
                    },
                    {
                        "name": "Gunilla",
                        "birth_year": "1931"
                    }
                ]
            }
        },
        "4": {
            "full_name": "Larsson, Johan",
            "location": "Östra Karaby, Marieholm",
            "occupation": "folkskollärare",
            "birth_details": {
                "date": "08/02/1886",
                "place": "Fåigeltofta, Kristianstads 1",
                "parents": "kvarnägare Lars Mårtensson o. Hanna Nilsson"
            },
            "education": [
                {
                    "degree": "Folkskoll :-ex.",
                    "year": "1907",
                    "institution": "Lund"
                }
            ],
            "career": [
                {
                    "position": "Vik. folkskoll.",
                    "years": {
                        "start_year": 1907,
                        "end_year": 1908
                    },
                    "organization": "Glem-minge"
                },
                {
                    "position": "Vik. folkskoll.",
                    "years": {
                        "start_year": 1908
                    },
                    "organization": "Fågeltofta"
                },
                {
                    "position": "Ord. i Östra Karaby",
                    "years": {
                        "start_year": 1909
                    },
                    "organization": null
                }
            ],
            "family": {
                "spouse": "Kerstin Jönsson",
                "marriage_year": "1916",
                "children": [
                    {
                        "name": "Britt",
                        "birth_year": "1920"
                    },
                    {
                        "name": "Elsie",
                        "birth_year": "1923"
                    },
                    {
                        "name": "Siv",
                        "birth_year": "1926"
                    }
                ]
            }
        }
    }
}