{
    "original": "Leijonhufvud, Svante K:son,\nfriherre, ingenjör, Lund, f. 3/11/11 i\nSträngnäs av översten frih. K.^ G. A.\nL. o. Anna Tham. G. 39 m. Ingegerd\nRydeman. Barn: Jan f. 41, Åke 45. —\nIng. STI 3’3. Föredr:res. rör.\nrationella jordbr :byggn. i Finl. o. Danm.\nRitkont :chef v. Ekonomibyggnader\nA-Bs huv:kont. i Sthlm 36-44, chef f.\nsamma föret. Skånefil. i Lund 45-47,\neget föret, i Lund fr. 47. Skr.: div. art.\ni facklitt.\n\nLejefors, Arne Gustav August,\ncivilingenjör, Malmö, f. 20/3/10 i\nFuring-stad, Östergötl. 1., av godsäg. Ernst. o.\nBertha Andersson. G. 38 m. Elsa\nScheutz. Barn: Ann-Sofi f. 38,\nMarianne 41. — Stud:ex. i Norrköp. 28,\navg:ex. fr. KTH 33. Res. i Schweiz o.\nTyskl. 36. Anst. i Borås Wäfveri A-B\n33-47, prodxhef f. bomullstillv. h.\nMab o. Mya i Malmö fr. 47. Led. av\nSv.  tekn:fören.  sed. 33.\n\nLejman, Artur Elof Fritjof\nRichard, professor, Lund, f. 19/3/07 i\nJönköp. G. 39 m. fil. mag. Eva\nAm-néus. Barn: Richard f. 40, Gunnar 43,\nMarianne 46. — Stud:ex. i Jönköp.\n25, jur. kand. i Sthlm 30, jur. lic. 39,\njur. dr s. å. Tingstjg. i Åse m. fl. här.\ndoms. 30-33, aman. v. Sthlms högsk.\njur. bibi. 34-35, spec :lär. i rättslära v.\nKTH 43-45, docent v. Sthlms högsk.\n39-47, prof. v. Lunds univ. fr. 47. Skr.:\nBidr. t. läran om återvinn. i konkurs\n(39), Om begrepp, nyttj :rätt t. fast\negend.   (44), upps. i tidskr. o.  festskr.\n\nLekholm, Carl Gustaf, amanuens,\nLund, f. 7/6/09 i Bjuv, Malmöh. 1., av\nförv.  Carl L.  o.  Clara Nilsson.  G. 41\n\nm. gymn:dir. Märta Koch. Barn: Carl\nf. 42, Ulf 44. — Studiex. i Lund 30,\nfil. kand. 47. Löjtn. i 1.7 res. 44. E. o.\naman. v. Kulturen i Lund 37, v.\nHäl-singb. stads museum 38-39, v.\nKulturen i Lund 44-47, ord. aman. där fr. 47.\n",
    "structured": {
        "0": {
            "full_name": "Svante K:son Leijonhufvud",
            "location": "Lund",
            "occupation": "ingenjör",
            "birth_details": {
                "date": "03/11/1911",
                "place": "Strängnäs",
                "parents": "översten frih. K. G. A. L. o. Anna Tham"
            },
            "education": [
                {
                    "degree": "ingenjör",
                    "year": "1933",
                    "institution": "STI"
                }
            ],
            "career": [
                {
                    "position": "Ritkont chef",
                    "years": {
                        "start_year": 1936,
                        "end_year": 1944
                    },
                    "organization": "Ekonomibyggnader A-Bs huv:kont"
                },
                {
                    "position": "chef",
                    "years": {
                        "start_year": 1945,
                        "end_year": 1947
                    },
                    "organization": "Skånefil."
                },
                {
                    "position": "eget föret",
                    "years": {
                        "start_year": 1947
                    },
                    "organization": "Lund"
                }
            ],
            "family": {
                "spouse": "Ingegerd Rydeman",
                "marriage_year": "1939",
                "children": [
                    {
                        "name": "Jan",
                        "birth_year": "1941"
                    },
                    {
                        "name": "Åke",
                        "birth_year": "1945"
                    }
                ]
            }
        },
        "1": {
            "full_name": "Arne Gustav August Lejefors",
            "location": "Malmö",
            "occupation": "civilingenjör",
            "birth_details": {
                "date": "20/03/1910",
                "place": "Furingstad, Östergötland",
                "parents": "godsäg. Ernst. o. Bertha Andersson"
            },
            "education": [
                {
                    "degree": "Stud:ex.",
                    "year": "1928",
                    "institution": "Norrköp"
                },
                {
                    "degree": "avg:ex.",
                    "year": "1933",
                    "institution": "KTH"
                }
            ],
            "career": [
                {
                    "position": "Anst.",
                    "years": {
                        "start_year": 1933,
                        "end_year": 1947
                    },
                    "organization": "Borås Wäfveri A-B"
                },
                {
                    "position": "prodxhef",
                    "years": {
                        "start_year": 1947
                    },
                    "organization": "bomullstillv. h. Mab o. Mya i Malmö"
                }
            ],
            "family": {
                "spouse": "Elsa Scheutz",
                "marriage_year": "1938",
                "children": [
                    {
                        "name": "Ann-Sofi",
                        "birth_year": "1938"
                    },
                    {
                        "name": "Marianne",
                        "birth_year": "1941"
                    }
                ]
            }
        },
        "2": {
            "full_name": "Artur Elof Fritjof Richard Lejman",
            "location": "Lund",
            "occupation": "professor",
            "birth_details": {
                "date": "19/03/1907",
                "place": "Jönköping"
            },
            "education": [
                {
                    "degree": "Stud:ex.",
                    "year": "1925",
                    "institution": "Jönköping"
                },
                {
                    "degree": "jur. kand.",
                    "year": "1930",
                    "institution": "Sthlm"
                },
                {
                    "degree": "jur. lic.",
                    "year": "1939",
                    "institution": "Sthlm"
                },
                {
                    "degree": "jur. dr",
                    "year": "1939",
                    "institution": "Sthlm"
                }
            ],
            "career": [
                {
                    "position": "Tingstjg.",
                    "years": {
                        "start_year": 1930,
                        "end_year": 1933
                    },
                    "organization": "Åse m. fl. här. doms."
                },
                {
                    "position": "aman.",
                    "years": {
                        "start_year": 1934,
                        "end_year": 1935
                    },
                    "organization": "Sthlms högsk. jur. bibi."
                },
                {
                    "position": "spec :lär.",
                    "years": {
                        "start_year": 1943,
                        "end_year": 1945
                    },
                    "organization": "KTH"
                }
            ],
            "family": {
                "spouse": "fil. mag. Eva Am-néus",
                "marriage_year": "1939",
                "children": [
                    {
                        "name": "Richard",
                        "birth_year": "1940"
                    },
                    {
                        "name": "Gunnar",
                        "birth_year": "1943"
                    },
                    {
                        "name": "Marianne",
                        "birth_year": "1946"
                    }
                ]
            }
        },
        "3": {
            "full_name": "Carl Gustaf Lekholm",
            "location": "Lund",
            "occupation": "amanuens",
            "birth_details": {
                "date": "07/06/1909",
                "place": "Bjuv, Malmöh",
                "parents": "förv. Carl L.  o.  Clara Nilsson"
            },
            "education": [
                {
                    "degree": "Studiex.",
                    "year": "1930",
                    "institution": "Lund"
                },
                {
                    "degree": "fil. kand.",
                    "year": "1947",
                    "institution": "Lund"
                }
            ],
            "career": [
                {
                    "position": "E. o. aman.",
                    "years": {
                        "start_year": 1937,
                        "end_year": 1939
                    },
                    "organization": "Kulturen i Lund"
                },
                {
                    "position": "v. Hällsingb. stads museum",
                    "years": {
                        "start_year": 1938,
                        "end_year": 1939
                    },
                    "organization": "Kulturen i Lund"
                },
                {
                    "position": "ord. aman.",
                    "years": {
                        "start_year": 1947
                    },
                    "organization": "Kulturen i Lund"
                }
            ],
            "family": {
                "spouse": "gymn:dir. Märta Koch",
                "marriage_year": "1941",
                "children": [
                    {
                        "name": "Carl",
                        "birth_year": "1942"
                    },
                    {
                        "name": "Ulf",
                        "birth_year": "1944"
                    }
                ]
            }
        }
    }
}