{
    "original": "Johansson, Knut Wilhelm, direktör,\nSthlm, f. 29/1/83 i Sthlm. G. 07 m.\nGreta Sågström. Barn: Greta, g. m.\nkomm :kapt. Lind af Hageby. Eft.\navsl, skolstudier anst. i f :an Aug. Holts\nPäls- o. Mössfabr. A-B, Sthlm, 1900\noch bolagets verkst, dir. efter 9 års\ntjänst, övertagit samtl. aktier i\nbolaget 20. Borgare 25, medl. av\nborgar-gillet samma år, medl. av\nFrimurareorden 21. Hobbies: trav o. galopp\nsamt allm. idrott. RVO 25.\nJohansson, Laurentius Cyrillus,\narkitekt SAR, Lidingö, f. 9/7/84 i Gävle\nav byggmäst. Magnus J. o. Johanna\nBohlin. G. 32 m. Lisbeth Thornsson.\nSkolgång i Gävle, utex. från Chalmers\ntekn. inst. 05 o. fr. Konstakad.\nbygg-nadssk. 08, anst. på ritkont. 08-10,\negen verksamh, i Sthlm sed. 10, ark.\ni Byggn :styr. sed. 16, stadsark, i\nSödertälje 17-25, i Ludvika 31-41, i\nVaxholm 35-40, ark. h. Järnvägsstyr, f.\nÅrstabrobygget 23-24, led. av byggn\n:-nd, i Sthlm 35-39. Bl. större arb.: ritn.\nt. affärshuset Centrum i Sthlm,\nVin-o. Spritcentr :s lagerhus, S :t Görans\nförsaml :hus i Sthlm, museet i\nKarlstad, stadshus i Ludvika o. Mjölby,\nPatologiska Inst. i Upps., badhus o.\ntennishall i Östersund, ett flert.\nboningshus, affärshus, vattentorn,\nstadsplaner m. m. Stud:res. t. Ital., Tyskl.,\nFrankr. Skr.: Byggnaden och staden,\nUr en arkitekts verksamhet 36.\nJohansson, Martin Leonard,\ncivilingenjör, överingenjör, Sthlm, f. 3/10/03\ni Barkåkra, Kristianstads L, av\nsjökapten C. A. J. o. Emma Andersson.\nEx. v. Tekn, Elem :sk. i Norrköp. 25,\navg:ex. v. KTH 30. Anst. v.\nHesselman Motor Corp. A-B, Sthlm, sed. 30.\nJohansson, Per Birger, envoyé,\nSthlm, f. 3/11/87. G. 17 m. Signe\nThornquist. Tjg. i utr :dep. 11, attaché\ni Hfors 12, Hamburg 13, t. f. 2 :e sekr.\n14-16, tjg. i Petrograd 16, kons :ex. 17,\nt. f. v. kons. i Narvik 17, t. f. kons. i\nVasa 18, i Rouen 18, i Mariehamn 19,\nkons. o. ch. f. arvs- o. ers :byr. å\nrätts-avd. i utridep. 23, kons. i Reval 25,\nlegiråd i Moskva 27, byråch, i\nutr:-dep. 29, utr:råd o. ch. f. pers. o.\nadmin, avd. i utr:dep. 31, envoyé i Riga,\nReval o. Kovno 35-40, ch. f. UD :s\nB-avd. 41. KNOlkl, StkEVSO,\nStkLett-TSO, StkLitGedO, KFinlVROlkl,\nSt-OffRumKrO, FFrKSkl, OffTjslVLO.\n",
    "structured": {
        "1": {
            "full_name": "Johansson, Knut Wilhelm",
            "location": "Sthlm",
            "occupation": "Direktör",
            "birth_details": {
                "date": "29/01/1883",
                "place": "Sthlm"
            },
            "family": {
                "spouse": "Greta Sågström",
                "marriage_year": "1907",
                "children": [
                    {
                        "name": "Greta",
                        "birth_year": "NULL"
                    }
                ]
            },
            "education": [
                {
                    "degree": "NULL",
                    "year": "NULL",
                    "institution": "Aug. Holts Päls- o. Mössfabr. A-B, Sthlm"
                }
            ],
            "career": [
                {
                    "position": "NULL",
                    "years": {
                        "start_year": 1900,
                        "end_year": "NULL"
                    },
                    "organization": "Aug. Holts Päls- o. Mössfabr. A-B, Sthlm"
                }
            ],
            "hobbies": [
                "trav o. galopp",
                "allm. idrott"
            ]
        },
        "2": {
            "full_name": "Johansson, Laurentius Cyrillus",
            "location": "Lidingö",
            "occupation": "Arkitekt SAR",
            "birth_details": {
                "date": "09/07/1884",
                "place": "Gävle"
            },
            "family": {
                "spouse": "Lisbeth Thornsson",
                "marriage_year": "1932",
                "children": []
            },
            "education": [
                {
                    "degree": "NULL",
                    "year": "1905",
                    "institution": "Chalmers tekn. inst."
                },
                {
                    "degree": "NULL",
                    "year": "1908",
                    "institution": "Konstakad. byggnadssk."
                }
            ],
            "career": [
                {
                    "position": "NULL",
                    "years": {
                        "start_year": 1910,
                        "end_year": "NULL"
                    },
                    "organization": "NULL"
                }
            ],
            "publications": [
                {
                    "title": "Byggnaden och staden",
                    "year": "1936",
                    "type": "NULL"
                },
                {
                    "title": "Ur en arkitekts verksamhet",
                    "year": "1936",
                    "type": "NULL"
                }
            ],
            "hobbies": [
                "trav o. galopp",
                "allm. idrott"
            ]
        },
        "3": {
            "full_name": "Johansson, Martin Leonard",
            "location": "Sthlm",
            "occupation": "Civilingenjör, överingenjör",
            "birth_details": {
                "date": "03/10/1903",
                "place": "Barkåkra, Kristianstads L"
            },
            "family": {
                "spouse": "NULL",
                "marriage_year": "NULL",
                "children": []
            },
            "education": [
                {
                    "degree": "NULL",
                    "year": "1925",
                    "institution": "Tekn, Elem: sk. i Norrköp."
                },
                {
                    "degree": "NULL",
                    "year": "1930",
                    "institution": "KTH"
                }
            ],
            "career": [
                {
                    "position": "NULL",
                    "years": {
                        "start_year": 1930,
                        "end_year": "NULL"
                    },
                    "organization": "Hesselman Motor Corp. A-B, Sthlm"
                }
            ]
        },
        "4": {
            "full_name": "Johansson, Per Birger",
            "location": "Sthlm",
            "occupation": "Envoyé",
            "birth_details": {
                "date": "03/11/1887",
                "place": "NULL"
            },
            "family": {
                "spouse": "Signe Thornquist",
                "marriage_year": "1917",
                "children": []
            },
            "education": [],
            "career": [
                {
                    "position": "NULL",
                    "years": {
                        "start_year": 1911,
                        "end_year": "NULL"
                    },
                    "organization": "tjg. i utr:dep."
                },
                {
                    "position": "NULL",
                    "years": {
                        "start_year": 1923,
                        "end_year": "NULL"
                    },
                    "organization": "legiråd i Moskva"
                },
                {
                    "position": "NULL",
                    "years": {
                        "start_year": 1931,
                        "end_year": "NULL"
                    },
                    "organization": "envoyé i Riga, Reval o. Kovno"
                }
            ],
            "honorary_titles": [
                {
                    "title": "KNOlkl",
                    "institution": "NULL",
                    "year": "NULL"
                },
                {
                    "title": "StkEVSO",
                    "institution": "NULL",
                    "year": "NULL"
                },
                {
                    "title": "StkLett-TSO",
                    "institution": "NULL",
                    "year": "NULL"
                },
                {
                    "title": "StkLitGedO",
                    "institution": "NULL",
                    "year": "NULL"
                },
                {
                    "title": "KFinlVROlkl",
                    "institution": "NULL",
                    "year": "NULL"
                },
                {
                    "title": "St-OffRumKrO",
                    "institution": "NULL",
                    "year": "NULL"
                },
                {
                    "title": "FFrKSkl",
                    "institution": "NULL",
                    "year": "NULL"
                },
                {
                    "title": "OffTjslVLO",
                    "institution": "NULL",
                    "year": "NULL"
                }
            ]
        }
    }
}