{
    "original": "Jakobson, Bernt Gösta, förste\nstatsgeotekniker, civilingenjör, kapten,\nSthlm, f. 18/11/09 i Fagerhults förs.,\nKristianstads 1., av disp. Carl\nWalfrid J. o. Maria Teresia Gemmel. G.\n44 m. Rosie Gauffin. Barn: Claes f.\n44. Avg :ex. v. Tekn. gymnasiet i\nÖrebro 28, avg:ex. v. KTH (VoV) 33.\nFänr. i Fortif, res. 31, und-.löjtn. 33,\nlöjtn. 35, kapt. i Kgl. Väg- o.\nVatten-byggnrkår. 41. Bitr. ing. v. Väg- o.\nVattenbyggn :styr :s hamnarb :s södra\ndistr., Ängelholm, 34 o. v. östra distr.,\nKalmar, 35-36, anst. v. Kgl.\nVattenfallsstyr. 36-39, v. Kgl. Väg- o.\nVattenbyggn :styr. 39-43, v. Statens\ngeo-tekn. inst. fr. 44. Led. Sv.\nTeknol:-fören.\nJacobson, Carl Emanuel, direktör,\nÄppelviken, f. 15/2/81. G. 11 m. Clara\nJohansson. Barn: Carl Herbert f. 13,\nciv:ing., Anna-Greta f. 15, Nils Bertil\nf. 23, med. stud. 5 kl. lärov., hand:sk.\nAnst. h. Gust. Rydström, Eskilstuna,\n96-98, h. Silvanders herrekip., Sthlm,\n98-99, i öl. f:or i Tyskl., Frankr, o.\nU. S. A. 00-09, h. Hjalmar Söderström,\nSthlm, 09-13, Broman &amp; Co., Sthlm,\n13, ag. av detta föret. und. f :a A-B J.\nR. Broman &amp; Co. sed. 30, verkst, dir.\no. ag. t. A-B Färgfabr. Skandia, gr.\n18. Res.: Tyskl., Frankr., U. S. A.\nJacobsson, Carl Fr., civilingenjör,\nverkställande direktör, Sthlm, f.\n24/5/05 i Halmstad av kassör J. B. J.\no. Maria Pahlberg. G. 33 m. Britta\nHedlund. Barn: Stina f. 39, Kerstin\nf. 42. Stud:ex. i Kristianstad 24, KTH\n24-26, 27-29. Anst. v. A-B Atlas Diesel\ni Sthlm 29-32, v. A-B Imo-Industri,\nSthlm, sed. 32, v. dir. sed. 44.\nJacobson, Carl Gustaf Emanuel,\nlektor, Sthlm, f. 12/1/81 i Nyköp. av\nbankkass. Victor J. o. Elisabet\nAxelsson. G. 19 m. Elsa Sundström. Fil.\nkand. i Upps. 02, fil. lic. 08, fil. dr 11,\ndocent i hist. i Upps. 11, adj. v. Upps.\nh. allm. lärov. 13, lekt. v. h. allm.\nlärov, å Österm. 19, timlär. v. Palmgr.\nsamsk. 29. Sekr. i Karl Johans förb.\n17-21, led. av lärov :lär. riksförb :s\nstyr. 30-33, kyrkofullm. 31-40,\nkyrkoråd 33-40, sakk. i eckl:dep. 31-32.\nSkr.: Sv:e o. Frankr. 1648-1652 (11),\nSv:e o. Frankr. 1652-1654 (12), Harald\nHjärne (22), Gustav Vasa (23),\nNäfveqvarn under 300 år (23), Den\nfranska hegemoniens tid, Norstedts\nvärlds-hist. IX (33), Sv. konungar o.\nstormän (35), Sv. kvinnor (36), Lärob. i\nallm. hist. f. gymnas., ny uppl. tills,\nm. E. Söderlund (42), f. realsk, ny\nuppl. tills. m. S. Erlandsson (39),\nBismarck (42), upps. o. rec. i tidskr, o.\ntidn., biografier i Sv. biografiskt lex.,\nart. i Bonniers konv :lex., Nord. fam :b.\no. Kunskapens bok. RNO, LSkS.\n",
    "structured": {
        "0": {
            "full_name": "Jakobson, Bernt Gösta",
            "location": "Sthlm",
            "occupation": "förste statsgeotekniker, civilingenjör, kapten",
            "birth_details": {
                "date": "18/11/1909",
                "place": "Fagerhults förs., Kristianstads 1.",
                "parents": "disp. Carl Walfrid J. o. Maria Teresia Gemmel"
            },
            "education": [
                {
                    "degree": "Tekn. gymnasiet",
                    "year": "1928",
                    "institution": "Örebro"
                },
                {
                    "degree": "KTH (VoV)",
                    "year": "1933",
                    "institution": "KTH"
                }
            ],
            "career": [
                {
                    "position": "Fänr. i Fortif",
                    "years": {
                        "start_year": 1931,
                        "end_year": 1933
                    },
                    "organization": "res."
                },
                {
                    "position": "und-.löjtn.",
                    "years": {
                        "start_year": 1933,
                        "end_year": 1935
                    }
                },
                {
                    "position": "löjtn.",
                    "years": {
                        "start_year": 1935,
                        "end_year": 1941
                    },
                    "organization": "Kgl. Väg- o. Vatten-byggnrkår"
                },
                {
                    "position": "Bitr. ing. v. Väg- o. Vattenbyggn :styr",
                    "years": {
                        "start_year": 1934,
                        "end_year": 1934
                    },
                    "organization": "södra distr., Ängelholm"
                },
                {
                    "position": "Bitr. ing. v. Väg- o. Vattenbyggn :styr",
                    "years": {
                        "start_year": 1935,
                        "end_year": 1936
                    },
                    "organization": "östra distr., Kalmar"
                },
                {
                    "position": "anst. v. Kgl. Vattenfallsstyr.",
                    "years": {
                        "start_year": 1936,
                        "end_year": 1939
                    }
                },
                {
                    "position": "anst. v. Kgl. Väg- o. Vattenbyggn :styr.",
                    "years": {
                        "start_year": 1939,
                        "end_year": 1943
                    }
                },
                {
                    "position": "anst. v. Statens geo-tekn. inst.",
                    "years": {
                        "start_year": 1944
                    }
                }
            ],
            "family": {
                "spouse": "Rosie Gauffin",
                "marriage_year": "1944",
                "children": [
                    {
                        "name": "Claes",
                        "birth_year": "1944"
                    }
                ]
            }
        },
        "1": {
            "full_name": "Jacobson, Carl Emanuel",
            "location": "Äppelviken",
            "occupation": "direktör",
            "birth_details": {
                "date": "15/2/1881"
            },
            "family": {
                "spouse": "Clara Johansson",
                "marriage_year": "1911",
                "children": [
                    {
                        "name": "Carl Herbert",
                        "birth_year": "1913"
                    },
                    {
                        "name": "Anna-Greta",
                        "birth_year": "1915"
                    },
                    {
                        "name": "Nils Bertil",
                        "birth_year": "1923"
                    }
                ]
            },
            "publications": [
                {
                    "title": "Sv:e o. Frankr. 1648-1652",
                    "year": "1911",
                    "type": "book"
                },
                {
                    "title": "Sv:e o. Frankr. 1652-1654",
                    "year": "1912",
                    "type": "book"
                },
                {
                    "title": "Harald Hjärne",
                    "year": "1922",
                    "type": "book"
                }
            ]
        },
        "2": {
            "full_name": "Jacobsson, Carl Fr.",
            "location": "Sthlm",
            "occupation": "civilingenjör, verkställande direktör",
            "birth_details": {
                "date": "24/5/1905",
                "place": "Halmstad"
            },
            "family": {
                "spouse": "Britta Hedlund",
                "marriage_year": "1933",
                "children": [
                    {
                        "name": "Stina",
                        "birth_year": "1939"
                    },
                    {
                        "name": "Kerstin",
                        "birth_year": "1942"
                    }
                ]
            }
        },
        "3": {
            "full_name": "Jacobson, Carl Gustaf Emanuel",
            "location": "Sthlm",
            "occupation": "lektor",
            "birth_details": {
                "date": "12/1/1881",
                "place": "Nyköp."
            },
            "family": {
                "spouse": "Elsa Sundström",
                "marriage_year": "1919"
            },
            "education": [
                {
                    "degree": "Fil. kand.",
                    "year": "1902",
                    "institution": "Upps."
                },
                {
                    "degree": "Fil. lic.",
                    "year": "1908",
                    "institution": "Upps."
                },
                {
                    "degree": "Fil. dr",
                    "year": "1911",
                    "institution": "Upps."
                }
            ],
            "publications": [
                {
                    "title": "Sv:e o. Frankr. 1648-1652",
                    "year": "1911",
                    "type": "book"
                }
            ],
            "community_involvement": [
                {
                    "role": "Sekr.",
                    "organization": "Karl Johans förb.",
                    "years": "1917-1921"
                }
            ],
            "honorary_titles": [
                {
                    "title": "RNO",
                    "institution": "NULL",
                    "year": "NULL"
                },
                {
                    "title": "LSkS",
                    "institution": "NULL",
                    "year": "NULL"
                }
            ]
        }
    }
}