{
    "original": "Johnsson, Johan-Wiktor (Jive),\npastor, Äppelviken, f. 19/9/94 i Osby,\nKristianst. 1. G. 23 m. Olga Kristina\nIngeborg Normann. Barn: Britta\nKristina f. 25, Bo Viktor f. 26, Ulf\nGud-mår f. 29, Anna Gudrun Ingeborg f.\n33. Teol. kand. i Lund 21, kommin. i\nSöderköp. 21-24, förest, f. Sthlms\nstadsmiss, sed. 24, ordf. f. Sv. kristl,\ngymnasistförb. mellansv. avd. 29-33,\nledare av Sthlms kyrkl. ungd :förb.\n32-40 samt fr. 42, v. ordf. i Sthlms\nkyrkl. sjöm :v. sed. 24, led. av styr. f.\nSthlms prästsällsk. sed. 31, f. de\nkristna samf:s nykterh :rör. 32, f.\nBlasieh :kyrkostift. 36, f.\nMälargår-dens o. Ribbingebäcks alkoholisthem,\nSkarviks skyddshem, stat. anst. f.\npojkar å Löfsta, v. ordf. i Sthlms\nfattigv:nd, Stadsfullm. 42 m. m. Skr.:\nTro o. gärning 28, Andaktsböcker 37,\n38,   41,  soc.  översikter.   LVO,\nRFinl-LOlkl.\nJohnsson, Karl Erik,\nläroverksadjunkt, Sthlm, f. 14/9/98 i Falköping.\nG. 36 m. Gurli Lindqvist. Stud:ex. i\nSkara 17, fil. mag. i Upps. 23, provar\nv. Högre allm. lärov, i Upps. 26.\nEx-tralär. v. H. Allm. lärov, i Nyköping\n24-25 o. v. Samrealsk. i Falköping\n27-32, adj. v. Samrealsk. i Falköp. 32\nsamt bitr. å rektorsexp. fr. 30, adj. v.\nH. Allm. lärov, å Östermalm i Sthlm\n39,   lär.  v.   Svensk-Engelska\nföreningens sommarkurser i Hove 35, 36 o. 37.\nSekr. v. H. Allm. lärov, å österm. o.\ni lärov :s lokalstyr.\nJohnson, Karl-Gerhard Emil,\nförfattare, skådespelare, Saltsjöbaden, f.\ni Sthlm 14/4/91 av byggmäst. F. E. J.\nG. 1. 14 m. skådesp :an Mary Johnson,\n2. 22 m. skådesp :an o. dansösen\nValborg Geyron, 3. 30 m. skådesp :an\nBrita Werner, österm. h. allm. lärov.,\nv. landsortsteat. 08-14, h. Selanders\nsällsk. Gtbg 14-17, uppf. egna revyer\n(sed. 19) i Sthlm, Gtbg, Malmö,\nKö-penh. m. m. Skr. visor, kuplett., art.\ni veckopr.: Och så kommer där en\ngosse (memoar.). Sign.:\nKarl-Gerhard. Av. teat.- o. filmroll.\n",
    "structured": {
        "0": {
            "full_name": "Johnsson, Johan-Wiktor",
            "location": "Äppelviken",
            "occupation": "pastor",
            "birth_details": {
                "date": "19/09/1894",
                "place": "Osby"
            },
            "education": [
                {
                    "degree": "Teol. kand.",
                    "year": "1921",
                    "institution": "Lund"
                }
            ],
            "career": [
                {
                    "position": "kommin.",
                    "years": {
                        "start_year": 1921,
                        "end_year": 1924
                    },
                    "organization": "Söderköp"
                },
                {
                    "position": "förest.",
                    "years": {
                        "start_year": 1924
                    },
                    "organization": "Sthlms stadsmiss"
                },
                {
                    "position": "ordf.",
                    "years": {
                        "start_year": 1929,
                        "end_year": 1933
                    },
                    "organization": "Sv. kristl, gymnasistförb. mellansv. avd."
                },
                {
                    "position": "ledare",
                    "years": {
                        "start_year": 1932,
                        "end_year": 1940
                    },
                    "organization": "Sthlms kyrkl. ungd :förb."
                },
                {
                    "position": "v. ordf.",
                    "years": {
                        "start_year": 1924
                    },
                    "organization": "Sthlms kyrkl. sjöm :v."
                },
                {
                    "position": "led.",
                    "years": {
                        "start_year": 1931
                    },
                    "organization": "styr. f. Sthlms prästsällsk."
                },
                {
                    "position": "v. ordf.",
                    "years": {
                        "start_year": 1942
                    },
                    "organization": "Sthlms kyrkl. sjöm :v."
                },
                {
                    "position": "led.",
                    "years": {
                        "start_year": 1932
                    },
                    "organization": "de kristna samf:s nykterh :rör."
                },
                {
                    "position": "led.",
                    "years": {
                        "start_year": 1936
                    },
                    "organization": "Blasieh :kyrkostift."
                },
                {
                    "position": "led.",
                    "years": {
                        "start_year": 1936
                    },
                    "organization": "Mälargår-dens o. Ribbingebäcks alkoholisthem"
                },
                {
                    "position": "stat. anst.",
                    "years": {
                        "start_year": 1936
                    },
                    "organization": "pojkar å Löfsta"
                },
                {
                    "position": "v. ordf.",
                    "years": {
                        "start_year": 1942
                    },
                    "organization": "Sthlms fattigv:nd"
                },
                {
                    "position": "Stadsfullm.",
                    "years": {
                        "start_year": 1942
                    }
                }
            ],
            "family": {
                "spouse": "Olga Kristina Ingeborg Normann",
                "marriage_year": "1923",
                "children": [
                    {
                        "name": "Britta Kristina",
                        "birth_year": "1925"
                    },
                    {
                        "name": "Bo Viktor",
                        "birth_year": "1926"
                    },
                    {
                        "name": "Ulf Gud-mår",
                        "birth_year": "1929"
                    },
                    {
                        "name": "Anna Gudrun Ingeborg",
                        "birth_year": "1933"
                    }
                ]
            }
        },
        "1": {
            "full_name": "Johnsson, Karl Erik",
            "location": "Sthlm",
            "occupation": "läroverksadjunkt",
            "birth_details": {
                "date": "14/09/1898",
                "place": "Falköping"
            },
            "education": [
                {
                    "degree": "Stud:ex.",
                    "year": "1917",
                    "institution": "Skara"
                },
                {
                    "degree": "fil. mag.",
                    "year": "1923",
                    "institution": "Upps."
                }
            ],
            "career": [
                {
                    "position": "Ex-tralär.",
                    "years": {
                        "start_year": 1924,
                        "end_year": 1925
                    },
                    "organization": "H. Allm. lärov, i Nyköping"
                },
                {
                    "position": "Ex-tralär.",
                    "years": {
                        "start_year": 1927,
                        "end_year": 1932
                    },
                    "organization": "Samrealsk. i Falköping"
                },
                {
                    "position": "adj.",
                    "years": {
                        "start_year": 1932
                    },
                    "organization": "Samrealsk. i Falköping"
                },
                {
                    "position": "adj.",
                    "years": {
                        "start_year": 1939
                    },
                    "organization": "H. Allm. lärov, å Östermalm i Sthlm"
                }
            ],
            "family": {
                "spouse": "Gurli Lindqvist",
                "marriage_year": "1936"
            }
        },
        "2": {
            "full_name": "Johnson, Karl-Gerhard Emil",
            "location": "Saltsjöbaden",
            "occupation": "författare, skådespelare",
            "birth_details": {
                "date": "14/04/1891",
                "place": "Sthlm"
            },
            "family": {
                "spouse": "1. Mary Johnson",
                "marriage_year": "1914",
                "children": [
                    {
                        "name": "Valborg Geyron",
                        "birth_year": "1922"
                    },
                    {
                        "name": "Brita Werner",
                        "birth_year": "1930"
                    }
                ]
            }
        }
    }
}