{
    "original": "THERMAENIUS, LARS E F, direktör,\nNorrköping, f i Upps 28/12/23 av prof\nEdvard T o Ruth Kallenberg.\nStud:ex Gbg 42, res:off:ex 46, jur kand\nUpps 48, tjg landsfogden Upps l o\nsjö-försäkr:bol Engl 49, tingstjg Tössbo o\n\nVedbo doms 49-51, tjg Gbgs rådhusr 52,\nfiskal hovr f V Sv :e 52, omb :man\nHolmens bruks o fabr ab Norrkpg 53, dir\ndär sed 65 o ch dess pappersbruk\nHallstavik sed 66. - Styr :led Norrkpgs komm\nbost ab, huvudm Norrkpgs sparbk sed\n\n60,    led   Östergötl   ensk   bks   lokalstyr\nNorrkpg  sed 64.  - Led DK sed 59 o\nStadsfullm Norrkpg sed 64. - Medl\nJuve-nalO, SHT.\n\nGift 52 m leg sjukgymn Mait Larsson\nf 28, dtr t Einar L o Alice Eriksson.\n-Barn: Marie f 54, Änne f 57.\n\nTHESSLIN, C VOLGER,\nförsäljningschef, Hjo, f i Eskilstuna 27/3/18.\nIng :ex maskinfacksk Eskilstuna 45, ing\nab Gusums bruk 45, offerting ab Nybro\nwellkartong 47, exporten ab Sture\nLjungdahl   &amp;   Co   49,   försäljn:ch   f:a   Josef\nKihlberg Hjo sed 59. - Hobby: bridge.\nGift 39 m Sonja Carlsson f 15, dtr t\nConrad C o Elin C. - Barn: Roland f 40,\nRolf f 45, Ann-Sofi f 49.\n\nTHIBERG,   CARL   R,   överingenjör,\n\nGbg, f i Gbg 17/3/07 av handl Gustaf T\n\n0 Lizzie Mortensen.\n\nStud:ex  25,   KTH  29,   DHG   31,   stud\n\n1  USA bl a v Harvard Business School;\növering ab Volvo Gbg. - Fd ordf\nstud:-kåren HHG, v ordf Tekn samf Gbg\n59-60 (sekr 50-55). - Hobbies: golf, tennis.\nGift m Birgit Theodorson.\n\nTHILEN,   ASTRID,   bitr   överläkare,\n\nJönköping, f i Dundee, Sydafr, 18/7/23\nav missionär Gustaf Sernander o\nElisabeth Svenning.\n\nStud:ex Sigtuna 42, med kand 46 o med\nlic Upps 51, öl läk:förordn 47-51,\nunderläk med avd Kronpr Lovisas barnsjh\n52-58, bitr överläk barnklin Jönkpgs las sed\n\n61.  - Hobby: skönlitteratur.\n\nGift 49 m civ:ing Bo Thilen f 24. - Barn:\nUlf Johan f 52, Mats Göran f 56, Astrid\nElisabeth f 58.\n\n",
    "structured": {
        "0": {
            "full_name": "THERMAENIUS, LARS E F",
            "location": "Norrköping",
            "occupation": "Direktör",
            "birth_details": {
                "date": "28/12/1923",
                "place": "Uppsala"
            },
            "education": [
                {
                    "degree": "Stud:ex",
                    "year": "1942",
                    "institution": "Göteborg"
                },
                {
                    "degree": "Res:off:ex",
                    "year": "1946",
                    "institution": "Unknown"
                },
                {
                    "degree": "Jur kand",
                    "year": "1948",
                    "institution": "Uppsala"
                }
            ],
            "career": [
                {
                    "position": "Tjg landsfogden",
                    "years": {
                        "start_year": 1948,
                        "end_year": 1951
                    },
                    "organization": "Uppsala"
                },
                {
                    "position": "Tjg Gbgs rådhusr",
                    "years": {
                        "start_year": 1952,
                        "end_year": 1952
                    },
                    "organization": "Gbgs"
                },
                {
                    "position": "Fiskal hovr f V Sv :e",
                    "years": {
                        "start_year": 1952,
                        "end_year": null
                    },
                    "organization": null
                }
            ],
            "family": {
                "spouse": "Mait Larsson",
                "marriage_year": "1952",
                "children": [
                    {
                        "name": "Marie",
                        "birth_year": "1954"
                    },
                    {
                        "name": "Änne",
                        "birth_year": "1957"
                    }
                ]
            }
        },
        "1": {
            "full_name": "THESSLIN, C VOLGER",
            "location": "Hjo",
            "occupation": "Försäljningschef",
            "birth_details": {
                "date": "27/3/1918",
                "place": "Eskilstuna"
            },
            "education": [
                {
                    "degree": "Ing :ex maskinfacksk",
                    "year": "1945",
                    "institution": "Eskilstuna"
                }
            ],
            "career": [
                {
                    "position": "Försäljningschef",
                    "years": {
                        "start_year": 1959,
                        "end_year": null
                    },
                    "organization": "f:a Josef Kihlberg Hjo"
                }
            ],
            "family": {
                "spouse": "Sonja Carlsson",
                "marriage_year": "1939",
                "children": [
                    {
                        "name": "Roland",
                        "birth_year": "1940"
                    },
                    {
                        "name": "Rolf",
                        "birth_year": "1945"
                    },
                    {
                        "name": "Ann-Sofi",
                        "birth_year": "1949"
                    }
                ]
            },
            "hobbies": [
                "Bridge"
            ]
        },
        "2": {
            "full_name": "THIBERG, CARL R",
            "location": "Göteborg",
            "occupation": "Överingenjör",
            "birth_details": {
                "date": "17/3/1907",
                "place": "Göteborg"
            },
            "education": [
                {
                    "degree": "Stud:ex",
                    "year": "1925",
                    "institution": "Unknown"
                },
                {
                    "degree": "KTH",
                    "year": "1929",
                    "institution": "Unknown"
                },
                {
                    "degree": "DHG",
                    "year": "1931",
                    "institution": "Unknown"
                }
            ],
            "career": [
                {
                    "position": "Övering ab Volvo",
                    "years": {
                        "start_year": null,
                        "end_year": null
                    },
                    "organization": "Göteborg"
                }
            ],
            "family": {
                "spouse": "Birgit Theodorson",
                "marriage_year": null,
                "children": null
            },
            "hobbies": [
                "Golf",
                "Tennis"
            ]
        },
        "3": {
            "full_name": "THILEN, ASTRID",
            "location": "Jönköping",
            "occupation": "Bitr överläkare",
            "birth_details": {
                "date": "18/7/1923",
                "place": "Dundee, Sydafrika"
            },
            "education": [
                {
                    "degree": "Stud:ex",
                    "year": "1942",
                    "institution": "Sigtuna"
                },
                {
                    "degree": "Med kand",
                    "year": "1946",
                    "institution": "Uppsala"
                },
                {
                    "degree": "Med lic",
                    "year": "1951",
                    "institution": "Uppsala"
                }
            ],
            "career": [
                {
                    "position": "Underläk med avd",
                    "years": {
                        "start_year": 1952,
                        "end_year": 1958
                    },
                    "organization": "Kronpr Lovisas barnsjh"
                },
                {
                    "position": "Bitr överläk barnklin Jönkpgs las",
                    "years": {
                        "start_year": 1961,
                        "end_year": null
                    },
                    "organization": null
                }
            ],
            "family": {
                "spouse": "Bo Thilen",
                "marriage_year": "1949",
                "children": [
                    {
                        "name": "Ulf Johan",
                        "birth_year": "1952"
                    },
                    {
                        "name": "Mats Göran",
                        "birth_year": "1956"
                    },
                    {
                        "name": "Astrid Elisabeth",
                        "birth_year": "1958"
                    }
                ]
            },
            "hobbies": [
                "Skönlitteratur"
            ]
        }
    }
}