{
    "original": "TÖRNBLOM, HARALD J L, disponent, \nFinspång, f i Uttersberg, Västmanl\nl, 24/4/07 av disp Emil T o Anna Löfvén.\n\nStud:ex Örebro 27, KTH (bergs) 34, anst\nFinspongs metallverks ab 34, disp o\nplatsch ab Sv Metallverken Finspångverken \nsed 53. - Kapt Lv-art res. - LIVA\n61. - Utm: RVO.\n\nGift 36 m Greta Bergqvist f 12, dtr t\nkamr Herman B o Anna Johannesson.\n-Barn: Margareta f 38, Christina f 41,\nHans f 42.\n\nTÖRNBLOM, ÅKE L, fd överläkare,\nEksjö, f i Eksjö 17/4/90 av handl Samuel\nJohansson o Sofia Törnblom.\n\nStud:ex Linkpg 08, med kand Upps 15,\nmed lic Sthlm 21; underläk Hålahult\nsanat 16, Eksjö sanat 17 o 20-22, Sävsjö\nsanat 17-18, Varbergs las 22-23, Barkåkra\nkustsanat 23-24, röntgenavd Sabbatsb sjh\n24-25, överläk Sandträsk sanat o förest\nNorrb l dispensärer 26-36, överläk Eksjö\nsanat o förest Jönkpgs l dispensärer\n36-55. - Sekr o verkst led Norrb l sjv:styr\n26-36, styr.ied Sv sanat :läk :f ören 37-50.\n- Utm: RNO, RFinlVRO1kl,\nPatrSst-GM, FMpbh. - Hobby: träsnideri.\n\nGift 19 m Ingrid Hanström f 90, dtr t\ngodsäg Anders H o Galathea Berendt.\n- Barn: Rose f 20.\n\nTÖRNEBERG, K GEORGE, ingenjör,\nGbg, f i Stamford, Conn, USA 22/2/24\nav lantbr Birger Johansson o Anna\nHallqvist.\n\nIng:ex tekn gymn Borås 46, ing\nMölnlycke ab 47, prod:ch Galon ab sed 56.\nGift 51 m Solveig Svensson, dtr t disp\nGustaf S o Dagmar Karlsson. - Barn:\nEva f 52, Lars f 56.\n\nTÖRNEBOHM, HILDING V, direktör,\nGbg, f i Ljungby, Kalmar l, 25/5/91 av\nstat :insp Jakob Erikson o Hedvig\nTörnebohm.\n\nStud:ex 09, KTH 13, ing Söderhamns\nnya verkst ab, ab Frank Hirschs\nmaskiner, ab Sv maskinverken o ab Sv\nkugg-hjulsfabr 13-19, SKF 19, ch tekn\ndirektionsbyrån där 30, tekn dir där 41-56.\n-Styr:ordf Lidkpgs mek verkst ab 29-58,\nstyr:led ab Volvo 35-61, Köpings mek\nverkst ab 43-62, ab Klafreströms bruk\n57-64, Sv:es mekanförb 41-55. - Lär\nKTH 17-18, ordf SIS 41-49, led AU\nTekn nomenklaturcentr 41-53, president\ninternat standardis:komm 53-55, ordf\nlokalstyr CTH o styr f Tekn gymn Gbg\n47-59, styr f Stat skeppsprovn:anst 48-52\n(led 43). - LIVA 38, LVVS 44, hed:dr\nStevens Inst of Technology USA o\nTechn Hochschule Zürich 42, hedL\nASME 55. - Skr: tekn art i sv o utl\ntidskr. - Utm: KVO, RNO, KDDO,\nKNS:tOO, RFinlVRO1kl, SISftjM, GsFtjM.\n\n<i>Gift</i> 18 m Karin Erikson f 94, dtr t\ngen :ma jör Conrad E o Signe Ekman.\n- barn: Håkan f 19, Stig f 21.\n\n",
    "structured": {
        "1": {
            "full_name": "TÖRNBLOM, HARALD J L",
            "location": "Finspång",
            "occupation": "Disponent",
            "birth_details": {
                "date": "24/04/1907",
                "place": "Uttersberg, Västmanland"
            },
            "education": [
                {
                    "degree": "Stud:ex",
                    "year": "1927",
                    "institution": "Örebro"
                },
                {
                    "degree": "KTH (bergs)",
                    "year": "1934",
                    "institution": "KTH"
                }
            ],
            "career": [
                {
                    "position": "Anst Finspongs metallverks ab",
                    "years": {
                        "start_year": 1934,
                        "end_year": 1953
                    },
                    "organization": "Finspongs metallverks ab"
                },
                {
                    "position": "Disp o platsch ab Sv Metallverken Finspångverken",
                    "years": {
                        "start_year": 1953
                    },
                    "organization": "Sv Metallverken Finspångverken"
                }
            ],
            "family": {
                "spouse": "Greta Bergqvist",
                "marriage_year": "1936",
                "children": [
                    {
                        "name": "Margareta",
                        "birth_year": "1938"
                    },
                    {
                        "name": "Christina",
                        "birth_year": "1941"
                    },
                    {
                        "name": "Hans",
                        "birth_year": "1942"
                    }
                ]
            }
        },
        "2": {
            "full_name": "TÖRNBLOM, ÅKE L",
            "location": "Eksjö",
            "occupation": "Fd överläkare",
            "birth_details": {
                "date": "17/04/1890",
                "place": "Eksjö"
            },
            "education": [
                {
                    "degree": "Stud:ex",
                    "year": "1908",
                    "institution": "Linkpg"
                },
                {
                    "degree": "Med kand",
                    "year": "1915",
                    "institution": "Upps"
                },
                {
                    "degree": "Med lic",
                    "year": "1921",
                    "institution": "Sthlm"
                }
            ],
            "career": [
                {
                    "position": "Överläk Eksjö sanat",
                    "years": {
                        "start_year": 1936,
                        "end_year": 1955
                    },
                    "organization": "Eksjö sanat"
                },
                {
                    "position": "Förest Jönkpgs l dispensärer",
                    "years": {
                        "start_year": 1936,
                        "end_year": 1955
                    },
                    "organization": "Jönkpgs l dispensärer"
                }
            ],
            "family": {
                "spouse": "Ingrid Hanström",
                "marriage_year": "1919",
                "children": [
                    {
                        "name": "Rose",
                        "birth_year": "1920"
                    }
                ]
            },
            "hobbies": [
                "Träsnideri"
            ]
        },
        "3": {
            "full_name": "TÖRNEBERG, K GEORGE",
            "location": "Gbg",
            "occupation": "Ingenjör",
            "birth_details": {
                "date": "22/02/1924",
                "place": "Stamford, Connecticut, USA"
            },
            "education": [
                {
                    "degree": "Ing:ex",
                    "year": "1946",
                    "institution": "Tekn gymn Borås"
                }
            ],
            "career": [
                {
                    "position": "Prod:ch Galon ab",
                    "years": {
                        "start_year": 1956
                    },
                    "organization": "Galon ab"
                }
            ],
            "family": {
                "spouse": "Solveig Svensson",
                "marriage_year": "1951",
                "children": [
                    {
                        "name": "Eva",
                        "birth_year": "1952"
                    },
                    {
                        "name": "Lars",
                        "birth_year": "1956"
                    }
                ]
            }
        },
        "4": {
            "full_name": "TÖRNEBOHM, HILDING V",
            "location": "Gbg",
            "occupation": "Direktör",
            "birth_details": {
                "date": "25/05/1891",
                "place": "Ljungby, Kalmar l"
            },
            "education": [
                {
                    "degree": "Stud:ex",
                    "year": "1909"
                },
                {
                    "degree": "KTH",
                    "year": "1913"
                }
            ],
            "career": [
                {
                    "position": "Ing Söderhamns nya verkst ab, ab Frank Hirschs maskiner, ab Sv maskinverken, ab Sv kugg-hjulsfabr",
                    "years": {
                        "start_year": 1913,
                        "end_year": 1919
                    }
                },
                {
                    "position": "SKF",
                    "years": {
                        "start_year": 1919
                    }
                },
                {
                    "position": "Tekn dir",
                    "years": {
                        "start_year": 1941,
                        "end_year": 1956
                    },
                    "organization": "SKF"
                }
            ],
            "family": {
                "spouse": "Karin Erikson",
                "marriage_year": "1918",
                "children": [
                    {
                        "name": "Håkan",
                        "birth_year": "1919"
                    },
                    {
                        "name": "Stig",
                        "birth_year": "1921"
                    }
                ]
            }
        }
    }
}