{
    "original": "THOMSEN, NILS E, distriktsåklagare,\nStenstorp, f i Sthlm 10/10/22 av lekt\nHans T o Ruth Hägglund.\nStud:ex Skövde 43, distr:åkl:ex StHS 48,\nlandsfisk :ass Hasslerörs distr 49, bitr\nlandsfisk där 53, landsfisk Gudhems distr\n61, distr:åkl Skövde sed 65. - Led\nStens-torps komm:fullm 62-64, ordf byggn :ndn\nsed 64. - Medl Odd Fellow, Round\nTab-le. - Hobbies: sport, bridge, filateli,\nnaturskydd.\n\nGift 49 m Ulla Berglund f 26, dtr t\nboktr Gunnar B o Lisa Carlsson. - Barn:\nPeter f 53, Katarina f 55, Marie f 58.\n\nTHORBURN, BERTIL W, direktör,\nGbg, f i Uddevalla 12/8/07 av\nvicekonsul William T o Sigrid Agrell.\nStud:ex 25, DHS 27, kansliex StHS 28,\nanst Sthlms ensk bk 29-31, And Smiths\nkolimp ab Sthlm 31-33, AEF 33-35,\nTu-ritz &amp; Co ab Gbg 35-41, verkst dir ab\nFerd Lundquist &amp; Co Gbg 41-47, ab\nImpo sed 45. - l:e v ordf Gbgs\nStadsfullm sed 51 (fp), led stadskoll, ordf\nhdlskamm Gbg sed 61, styr :ordf Gbgs o\nBoh l turisttrafikförb sed 46, Riksbkns\navd :kont Gbg sed 52, ab Ferd Lundquist\n&amp; Co sed 55, BASF Sv ab o Granit ab\nC A Kullgrens Enka sed 58, Gbgs o Boh\nl sparbk sed 60, Rederi ab\nGbg-Frede-rikshavn-linjen sed 60, Thorburns Söner\nab sed 61, Försäkr ab Atlantica sed 61,\nv ordf styr Fastigh ab Göta Lejon sed\n60, ab Aritmos sed 61, styr :led\nFöret:-fören i Gbgs o Boh l, Älvsb m fi l\nhyp:-fören, Bohusläningens ab m fi; led 45\nårs skärgårdsutredn, 61 års\nstorstadsut-redn. - Skr: Detaljhandelns kundtjänst\n(34), Will :m Thorburns Söner, ett blad\nur den sv havreexportens hist (51).\n-Utm: KVO, KItMerRO, KDDO,\nKNed-ONO, OffFrHL.\n\nGift 1) 33 m Gerd Sanne, 2} 45 m\nKarina Sanne f 23, döttrar t godsäg\nGunnar S o Karin Bildt. - Barn: i l:a\nakt Ann f 35, Ingegerd f 37, i 2:a akt\nJane f 47, Maud f 49, Jon f 53.\n\n",
    "structured": {
        "1": {
            "full_name": "NILS E THOMSEN",
            "location": "Stenstorp",
            "occupation": "distriktsåklagare",
            "birth_details": {
                "date": "10/10/1922",
                "place": "Sthlm",
                "parents": "Hans T o Ruth Hägglund"
            },
            "education": [
                {
                    "degree": "Stud:ex",
                    "year": "1943",
                    "institution": "Skövde"
                },
                {
                    "degree": "distr:åkl:ex",
                    "year": "1948",
                    "institution": "StHS"
                }
            ],
            "career": [
                {
                    "position": "landsfisk :ass",
                    "years": {
                        "start_year": 1949,
                        "end_year": 1953
                    },
                    "organization": "Hasslerörs distr"
                },
                {
                    "position": "bitr landsfisk",
                    "years": {
                        "start_year": 1953,
                        "end_year": 1961
                    },
                    "organization": "Gudhems distr"
                },
                {
                    "position": "distr:åkl",
                    "years": {
                        "start_year": 1965,
                        "end_year": null
                    },
                    "organization": "Skövde"
                }
            ],
            "family": {
                "spouse": "Ulla Berglund",
                "marriage_year": "1949",
                "children": [
                    {
                        "name": "Peter",
                        "birth_year": "1953"
                    },
                    {
                        "name": "Katarina",
                        "birth_year": "1955"
                    },
                    {
                        "name": "Marie",
                        "birth_year": "1958"
                    }
                ]
            },
            "hobbies": [
                "sport",
                "bridge",
                "filateli",
                "naturskydd"
            ]
        },
        "2": {
            "full_name": "BERTIL W THORBURN",
            "location": "Gbg",
            "occupation": "direktör",
            "birth_details": {
                "date": "12/8/1907",
                "place": "Uddevalla",
                "parents": "vicekonsul William T o Sigrid Agrell"
            },
            "education": [
                {
                    "degree": "Stud:ex",
                    "year": "1925",
                    "institution": null
                },
                {
                    "degree": "DHS",
                    "year": "1927",
                    "institution": null
                },
                {
                    "degree": "kansliex",
                    "year": "1928",
                    "institution": "StHS"
                }
            ],
            "career": [
                {
                    "position": "vd",
                    "years": {
                        "start_year": 1961,
                        "end_year": null
                    },
                    "organization": "Försäkr ab Atlantica"
                }
            ],
            "family": {
                "spouse": "Gerd Sanne",
                "marriage_year": "1933",
                "children": [
                    {
                        "name": "Ann",
                        "birth_year": "1935"
                    },
                    {
                        "name": "Ingegerd",
                        "birth_year": "1937"
                    }
                ]
            },
            "publications": [
                {
                    "title": "Detaljhandelns kundtjänst",
                    "year": "1934",
                    "type": null
                },
                {
                    "title": "Will :m Thorburns Söner, ett blad ur den sv havreexportens hist",
                    "year": "1951",
                    "type": null
                }
            ],
            "honorary_titles": [
                "KVO",
                "KItMerRO",
                "KDDO",
                "KNed-ONO",
                "OffFrHL"
            ]
        }
    }
}