{
    "original": "THAM, N J CARL-HENRIK,\ntaxeringsintendent, Kalmar, f i Västerås\n9/11/12 av öv:löjtn Henrik T o Else\nTreschow.\n\nStud:ex Falun 32, res:off:ex 34, DHS 37,\ne tjm ÖÄ 38, tax:rev Norrb l 40,\nKris-tianst l 44, bitr tax:intend där 52,\ntax:-intend Kalmar l sed 61 (tf 59). - Rev f\n\nsparbk, stift o yrkessk, tax:ndsordf\nab:-distr o öl rörelsedistr 44-52, tax\n:konsulent 44 o 48, ordf beredn:nd 52. - Sakk\nh Kristianst l landst rev :er 45-58. - Kapt\nI l res 47. - Skr: upps i \"Sv skattetidn o\nTax:ndn. - Hobby: genealogi.\nGift 40 m Karin Wattrang f 14, dtr t\nmajor Adolf W o grev:an Elisabeth\nHamilton. - Barn: Catharina f 41, Elisabeth\nf 42, Hugo f 44, Sebastian f 46, Ulrika\nf 47.\n\nTHAM, G FREDRIK, tandläkare,\nMotala, f i Karlskrona 23/3/37 av civiling\nHarry T o Clary Lemon.\nStud:ex Malmö 57, tandl:ex Malmö 62,\nprivatprakt Motala sed 62. - Medl FDI,\nKSAK, M. - Hobbies: ridning, flygning\n(inneh A-certif), golf, skidåkning.\nGift 62 m Barbro Tingemar f 36, dtr t\ntandl Birger T o Maud Westerberg.\n\nTHAM,   H   SEBASTIAN,   disponent,\n\nHällekis, f i Skövde 12/10/00 av öv:löjtn\nHarry T o Amelie Blom.\nKTH 22, ing El Bond &amp; Share Co USA\n24-26, ab Vattenbyggn :byrån (m tjg \\Y^\når i Bortre Indien o y^ år i London)\n27-30, ch ab Electro-Invests verksamh i\nJugosl 30-37, verkst dir Sthlms\nSiporex-fabr ab samt Internat Siporex ab o ab\nBetongklinker 37-43, disp Skånska\ncement ab :s Hällekisförvaltn 43-65. - Sv\nvicekonsul Belgrad 34-37. - Styr :ordf\nGullspångs kraft ab, Gullspångs\nelektro-kem ab, Latorps ab, styr :led o verkst dir\nHidinge kalkverks ab, styr :led Internat\nSiporex ab, Intercemex ab, Cementa,\nByggn :ämnesförb, Vänerns seglationsstyr,\nVänerns hamnförb. - Utm: RVO,\nFFrK-4kl&lt;, RJugS:tSO. - Hobbies: jakt, fiske,\nbridge, golf.\n\nGift 29 m Märta Tisell f 03, dtr t\nliv-förs :insp Iwan T o Maria Palm. - Barn:\nHelena f 31, Christer f 32, Carl-Johan\nf 40.\n\n",
    "structured": {
        "1": {
            "full_name": "N J Carl-Henrik Tham",
            "location": "Kalmar",
            "occupation": "Taxeringsintendent",
            "birth_details": {
                "date": "09/11/1912",
                "place": "Västerås",
                "parents": "öv:löjtn Henrik T o Else Treschow"
            },
            "education": [
                {
                    "degree": "Stud:ex",
                    "year": "1932",
                    "institution": "Falun"
                },
                {
                    "degree": "Res:off:ex",
                    "year": "1934",
                    "institution": "N/A"
                },
                {
                    "degree": "DHS",
                    "year": "1937",
                    "institution": "N/A"
                }
            ],
            "career": [
                {
                    "position": "Tjm ÖÄ",
                    "years": {
                        "start_year": 1938,
                        "end_year": 1938
                    },
                    "organization": "N/A"
                },
                {
                    "position": "Tax:rev",
                    "years": {
                        "start_year": 1940,
                        "end_year": 1940
                    },
                    "organization": "Norrb l"
                },
                {
                    "position": "Bitr tax:intend",
                    "years": {
                        "start_year": 1952,
                        "end_year": 1952
                    },
                    "organization": "Kr istianst l"
                },
                {
                    "position": "Tax:-intend",
                    "years": {
                        "start_year": 1961,
                        "end_year": 1961
                    },
                    "organization": "Kalmar l"
                }
            ],
            "family": {
                "spouse": "Karin Wattrang",
                "marriage_year": "1940",
                "children": [
                    {
                        "name": "Catharina",
                        "birth_year": "1941"
                    },
                    {
                        "name": "Elisabeth",
                        "birth_year": "1942"
                    },
                    {
                        "name": "Hugo",
                        "birth_year": "1944"
                    },
                    {
                        "name": "Sebastian",
                        "birth_year": "1946"
                    },
                    {
                        "name": "Ulrika",
                        "birth_year": "1947"
                    }
                ]
            }
        },
        "2": {
            "full_name": "G Fredrik Tham",
            "location": "Motala",
            "occupation": "Tandläkare",
            "birth_details": {
                "date": "23/03/1937",
                "place": "Karlskrona",
                "parents": "civiling Harry T o Clary Lemon"
            },
            "education": [
                {
                    "degree": "Stud:ex",
                    "year": "1957",
                    "institution": "Malmö"
                },
                {
                    "degree": "Tandl:ex",
                    "year": "1962",
                    "institution": "Malmö"
                }
            ],
            "family": {
                "spouse": "Barbro Tingemar",
                "marriage_year": "1962",
                "children": []
            },
            "hobbies": [
                "ridning",
                "flygning (inneh A-certif)",
                "golf",
                "skidåkning"
            ]
        },
        "3": {
            "full_name": "H Sebastian Tham",
            "location": "Hällekis",
            "occupation": "Disponent",
            "birth_details": {
                "date": "12/10/1900",
                "place": "Skövde",
                "parents": "öv:löjtn Harry T o Amelie Blom"
            },
            "education": [
                {
                    "degree": "KTH",
                    "year": "1922",
                    "institution": "N/A"
                }
            ],
            "career": [
                {
                    "position": "Ing El Bond & Share Co USA",
                    "years": {
                        "start_year": 1924,
                        "end_year": 1926
                    },
                    "organization": "N/A"
                },
                {
                    "position": "Verkst dir",
                    "years": {
                        "start_year": 1937,
                        "end_year": 1943
                    },
                    "organization": "Sthlms Siporex-fabr ab samt Internat Siporex ab o ab Betongklinker"
                },
                {
                    "position": "Disp",
                    "years": {
                        "start_year": 1943,
                        "end_year": 1965
                    },
                    "organization": "Skånska cement ab :s Hällekisförvaltn"
                }
            ],
            "family": {
                "spouse": "Märta Tisell",
                "marriage_year": "1929",
                "children": [
                    {
                        "name": "Helena",
                        "birth_year": "1931"
                    },
                    {
                        "name": "Christer",
                        "birth_year": "1932"
                    },
                    {
                        "name": "Carl-Johan",
                        "birth_year": "1940"
                    }
                ]
            },
            "honorary_titles": [
                {
                    "title": "RVO",
                    "institution": "N/A",
                    "year": "N/A"
                },
                {
                    "title": "FFrK-4kl",
                    "institution": "N/A",
                    "year": "N/A"
                },
                {
                    "title": "RJugS:tSO",
                    "institution": "N/A",
                    "year": "N/A"
                }
            ],
            "hobbies": [
                "jakt",
                "fiske",
                "bridge",
                "golf"
            ]
        }
    }
}