{
    "original": "THULIN, RUDOLF T, major,\nJönköping, f i Örebro 23/6/14 av bergsing Otto\nT o Matilda Niemi.\nStud:ex Sthlm 33, off :ex 38, KHS 46-48.\n\n-  Anst apot Övertorneå 33-34, off A 5\n38, A 8 51, A 6 54, major o div:ch där\nsed 56. - Utm: RSO, SkytteM, Skidl:m.\n-Hobbies: orientering, skidsport, foto.\nGift 42 m Kersti Höijer f 20, dtr t dir\nWalter H o Hanna Broms. - Barn: Anna\nf 43, Karin f 47, Lena f 54.\n\nTHULIN, STEN G, försäljningschef,\nNorrköping, f i Lund 16/6/14 av Gustav\nT o Anna Hansson.\n\nStud:ex 32 o hdlsgymn Hbg 33, DHS\n37, inköpare Hbgs gummifabr ab 37,\ndisp ab Parajett-Celloprint ab\nLandskrona 46, försäljn :ch ab Celloplast\nNorr-kpg sed 54.\n\nGift 1) 42 m Birgit Westrup f 12 d 62,\n2) 62 m Maureen Binney f 26. - Barn:\n\ni l:a akt Olle f 44, Staffan f 49, i 2:a\nakt Simon f 64.\n\nTHULIN, SVEN GÖSTA H, driftschef,\n\nLinköping, f i Hbg 29/8/06 av överkonst\nSven T o Hilda Moberg.\nJur kand Lund 41, tingstjg 41-43,\ndir:-aman länsarb:ndn Linkpg 44, dir :ass\nÖstergötl l landst 45, landst :sekr 64,\ndrifts-ch där sed 65. - Led div utredn :komm\ninom landst, ordf dess konstnd sed 62.\n-Medl Uardaakad, FrimO, SHT, CC.\n-Utm: Lunds stud:sångförenSM,\nChX:s-FrM. - Hobbies: musik, konst, foto,\nfilateli, botanik, bokkonst.\nGift 41 m Astrid Jepsson. - Barn: Ola\nf 46.\n\nTHULIN, WALTER E, direktör,\nJönköping, f i Sollefteå 17/10/00 av handl\nAdam T o Erika Eriksson.\nStud:ex Upps 19, CTH 22, disp STAB :s\nfabr i Britt Indien o Burma 26-32, lab :ch\nSTAB Jönkpg 33-49, verkst dir ab\nJönkpg-Vulcan 49-65. - Dansk vicekonsul\nsed 58. - Styr:led Länssparbkn Jönkpg.\n- Utm: KVO, SCFGM. - Hobbies: jakt,\ngolf.\n\nGift 29 m Margareta Petersson f 99,\ndtr t handl August P o Amanda\nHåkansson. - Barn: Brita f 31, Claes-Göran f 35.\n\n",
    "structured": {
        "1": {
            "full_name": "Rudolf T Thulin",
            "location": "Jönköping",
            "occupation": "Major",
            "birth_details": {
                "date": "23/06/1914",
                "place": "Örebro"
            },
            "education": [
                {
                    "degree": "Stud:ex",
                    "year": "1933",
                    "institution": "Sthlm"
                },
                {
                    "degree": "Off :ex",
                    "year": "1938",
                    "institution": "KHS"
                }
            ],
            "career": [
                {
                    "position": "Anst apot",
                    "years": {
                        "start_year": 1933,
                        "end_year": 1934
                    },
                    "organization": "Övertorneå"
                },
                {
                    "position": "off A 5",
                    "years": {
                        "start_year": 1938,
                        "end_year": 1951
                    }
                },
                {
                    "position": "A 8",
                    "years": {
                        "start_year": 1951,
                        "end_year": 1954
                    }
                },
                {
                    "position": "A 6",
                    "years": {
                        "start_year": 1954
                    }
                },
                {
                    "position": "major o div:ch",
                    "years": {
                        "start_year": 1956
                    }
                }
            ],
            "family": {
                "spouse": "Kersti Höijer",
                "marriage_year": "1942",
                "children": [
                    {
                        "name": "Anna",
                        "birth_year": "1943"
                    },
                    {
                        "name": "Karin",
                        "birth_year": "1947"
                    },
                    {
                        "name": "Lena",
                        "birth_year": "1954"
                    }
                ]
            },
            "hobbies": [
                "orientering",
                "skidsport",
                "foto"
            ]
        },
        "2": {
            "full_name": "Sten G Thulin",
            "location": "Norrköping",
            "occupation": "försäljningschef",
            "birth_details": {
                "date": "16/06/1914",
                "place": "Lund"
            },
            "education": [
                {
                    "degree": "Stud:ex",
                    "year": "1932"
                }
            ],
            "career": [
                {
                    "position": "disp ab Parajett-Celloprint ab",
                    "years": {
                        "start_year": 1946
                    },
                    "organization": "Landskrona"
                },
                {
                    "position": "försäljn :ch ab Celloplast Norr-kpg",
                    "years": {
                        "start_year": 1954
                    }
                }
            ],
            "family": {
                "spouse": "Birgit Westrup",
                "marriage_year": "1942",
                "children": [
                    {
                        "name": "Olle",
                        "birth_year": "1944"
                    },
                    {
                        "name": "Staffan",
                        "birth_year": "1949"
                    },
                    {
                        "name": "Simon",
                        "birth_year": "1964"
                    }
                ]
            }
        },
        "3": {
            "full_name": "Sven Gösta H Thulin",
            "location": "Linköping",
            "occupation": "driftschef",
            "birth_details": {
                "date": "29/08/1906",
                "place": "Hbg"
            },
            "education": [
                {
                    "degree": "Jur kand",
                    "year": "1941",
                    "institution": "Lund"
                }
            ],
            "career": [
                {
                    "position": "tingstjg",
                    "years": {
                        "start_year": 1941,
                        "end_year": 1943
                    }
                },
                {
                    "position": "dir:-aman länsarb:ndn Linkpg",
                    "years": {
                        "start_year": 1944
                    }
                },
                {
                    "position": "dir :ass Östergötl l landst",
                    "years": {
                        "start_year": 1945
                    }
                },
                {
                    "position": "landst :sekr",
                    "years": {
                        "start_year": 1964
                    }
                },
                {
                    "position": "drifts-ch",
                    "years": {
                        "start_year": 1965
                    }
                }
            ],
            "family": {
                "spouse": "Astrid Jepsson",
                "marriage_year": "1941",
                "children": [
                    {
                        "name": "Ola",
                        "birth_year": "1946"
                    }
                ]
            },
            "hobbies": [
                "musik",
                "konst",
                "foto",
                "filateli",
                "botanik",
                "bokkonst"
            ]
        },
        "4": {
            "full_name": "Walter E Thulin",
            "location": "Jönköping",
            "occupation": "direktör",
            "birth_details": {
                "date": "17/10/1900",
                "place": "Sollefteå"
            },
            "education": [
                {
                    "degree": "Stud:ex",
                    "year": "1919",
                    "institution": "Upps"
                },
                {
                    "degree": "CTH",
                    "year": "1922"
                }
            ],
            "career": [
                {
                    "position": "disp STAB :s fabr i Britt Indien o Burma",
                    "years": {
                        "start_year": 1926,
                        "end_year": 1932
                    }
                },
                {
                    "position": "lab :ch STAB Jönkpg",
                    "years": {
                        "start_year": 1933,
                        "end_year": 1949
                    }
                },
                {
                    "position": "verkst dir ab Jönkpg-Vulcan",
                    "years": {
                        "start_year": 1949,
                        "end_year": 1965
                    }
                }
            ],
            "family": {
                "spouse": "Margareta Petersson",
                "marriage_year": "1929",
                "children": [
                    {
                        "name": "Brita",
                        "birth_year": "1931"
                    },
                    {
                        "name": "Claes-Göran",
                        "birth_year": "1935"
                    }
                ]
            },
            "hobbies": [
                "jakt",
                "golf"
            ]
        }
    }
}