{
    "original": "Viggbyholm, f i Skatelöv, Kronob l,\n23/6/15 av köpman Ernst W o Sigrid\nNorrlin.\n\nStud:ex Växjö 33, tjg postverket 33,\nl:e byråsekr stat avtalsnd 47, sekr o\nomb :man Sv:es verkstadsfören 48-49, dir\nSNS 50-51, verkst dir Städernas vakt\nab 51-58, dir o ch admin avd SAF sed\n58. - Res:off:ex 40. - Styr:led RFV\nsed 61, expert internat arb :konf Geneve\n60, ordf högerns ungd :distr Sthlm 45-\n\n48,   l:e v ordf högerns ungd:förb 45-\n\n49,    Stadsfullm   Sthlm   46-50   (h),   led\nIdr:- o friluftsstyri Sthlm 47-54.\n\nGift 36 m Ebbagreta Holmberg f 15,\ndtr t köpman Tage H o Ebba Obitz.\n-Barn: Bo f 37, Christina f 40, Hans\nf 42, Bengt f 46, Ulf f 59.\n\nVALBERG, WALBERG se\nWAHLBERG\n\nWALDÉN, SVEN G, förste\nförsvarstandläkare, Saltsjöbaden, f i\nÄlvkarleby, Upps l, 5/11/04 av trafikchef Otto\nW o Maria Monie.\n\nStud:ex Saltsjöbaden 23, med kand 27,\ntandläk:ex 29, prakt tandläk Sthlm sed\n29, l:e försv:tandläk IV milostaben sed\n45. - Styr :ordf Sv:es f örsv:\ntandläk:-fören 48-50, Sv:es tandläk:förb 54-59\n(led 48, v ordf 50-53), styr:led Sv\ntandläk :sällsk 60 m fi, komm uppdr\nSaltsjöbaden 39-58, hedL Den norske\ntannlaegefören, Dansk tandlaegefören,\nFellow Amer Coll of Dentists. - Skr:\nart i fackpress. - Utm: RVO, Sthlms\n\n1   skytteförb   ftjSM,   Finl   tandläk:förb\nHtG, Saltsjöb köpings ftJM.\n\nGift 29 m  Birgit Lundquist f 05,  dtr\n\nt dir Viktor L o Anna Nyquist.\n-Barn: Britt-Marie f 31, Björn f 34,\nSvante f 43.\n\nWALDENSTRÖM, ERLAND,\ndirektör, Sthlm, f i Malmö 4/6/11 av dir\nMartin W o Hedvig Lion.\nStud:ex Nykpg 29, KTH 33, ing\nKorsnäs sågverk ab 34, tekn sekr Ind:förb\n40, förestånd tekn byrån Sv cellulosa ab\n42, övering 47-49, verkst dir LKAB\n50-57, Grängesbergsbol sed 50. - Led ind\nNorrl :utredn 40-46, sakk o sekr statl\nutredn f tekn forskn 41-42, ind\nrådgiv FN :s ekon Europakomm 48, fullm\nJernkontoret 55, ordf Sv gruvfören\n57-60, styr:led Sv traforskn:inst 48-49, Sv:es\nind:förb, SAF, HHS, Kungl teat ab,\nKonsertfören. - Skr: Till frågan om\ndet industr framåtskrid i Sv:e (42),\nAvfalls- o biprod i skogsind (42),\nUt-veckl :lin jer inom skogsind (46), ett flert\nupps tekn o ekon frågor. - Utm: KVO,\nRNO, LIVA.\n\nGift 45 m jur kand Dorothy Boleyn\nDrewry f 19, dtr t rektor Emil Melle\n\n0  Dorothy B D. - Barn: Hedda f 46,\nMartin f 48, Cecilia f 50.\n\nWALDENSTRÖM, J HENNING,\nprofessor emeritus, Lidingö, f i Upps\n14/8/77 av prof Johan W o Elisabeth\nGibson.\n\nStud:ex Sthlm 96, med kand Ol, med lic\n06, med dr 10, doc i ortopedi Karol inst\n10, prof 36-42. - Underkir Kronpr\nLovisas barnsjh 07, överläk kir tbcavd S:t\nGörans sjh 10, Vanföreanst Sthlm\n36-42, försäkr:ab Fylgia 14-57. - Led\nmed:-styr vetensk råd 36-47, styr :led Gustaf\nV:s 80-årsfond 38-50, hedL British\nOrthop Assoc, Amer Acad of Orthop\nSur-geons, Soc frän? d’orthopédie, Deutsche\northopäd Geseilsch, Soc Ital di Orthop,\nSoc Orthop Scand, Sv kir fören. - Skr:\n\n1  kir o ortop, medarb Nord lärob i kir.\n-    Utm:   GV:sJmtll,   KNO,   KFrdeSp,\nFFrK3kl,   RFrHL,   S:tEM.\n\nGift 1) 05-27 m Elsa Laurin f 70, dtr t\nboktryckare Gustav L o Agnes Rothlieb,\n2) 27 m Ella Wijk f 80, dtr t grosshandl\nOlof W o Caroline Dickson. - Barn:\ni l:a akt Jan f 06.\n\nWALDENSTRÖM, JOHAN A, fd\nlasarettsläkare, Lidingö, f i Upps 5/1/80 av\nprof Johan W o Elisabeth Gibson.\nStud:ex Sthlm 97, med kand 03, med\nlic 07, med hed:dr Upps 27. - Ol\nläk:-förordn 05^12, vik lasdäk ol las 13^15,\nlas:läk kir avd Falu las 14-45. - Led\ncentralstyr SLF 33-39, fullm Läk:förb\n34-40, medl med :styr vetensk råd 44-52,\nSLF o dess kir sekt sed 08, sekr o\n\nordf Dalarnas läk:fören 17-36. - Skr\nom cancer o collumfrakturer. - Utm:\nKVO, RNO. - Hobby: jakt.\n\nWALDENSTRÖM,   LARS,   direktör,\n\nLidingö, f i Malmö 13/11/12 av dir\nMartin W o Hedvig Lion.\nJur kand 37, språkstud o prakt Engl\no Frankr 37-38, sekr stat\nkrigsförsäkr:-nd 39-46, omb :man o sekr Sv\nfoderämnes- o spannmålsimportörers fören\n\n42,  verkst dir dess inköpsab 44-47, Sv\nKvarnfören 47-53, eget företag Juvelen\nlivs 53-54, verkst dir Lawal hdls ab o\nTre Rosor hdls ab  sed  54.  - Styr :led\nKeLiFa,   ab   Bagerikredit   o   ab\nHdls-kredit 47-53, Sv:es skiljend f\nspannmåls-o foderämneshdln 48-53.\n\nGift 44 m Viveca Enell f 17, dtr t aukt\nrev Knut E o Carrie Lindström. - Barn:\nCarola f 45, Urban f 46, Patrik f 50,\nAnita f 54.\n\nWALDENSTRÖM, NILS G, direktör,\njur kand, Bromma, f i Antwerpen 9/1/05\nav köpman Valdemar W o Gertrud\nSan-delin.\n\nJur kand 32, tingstjg 32-35, adv\n:verksamh Norrkpg 36, omb :man Hellefors\nbruks ab 36, dir :ass Järnbr:förb 42, dir\n49, v verkst dir sed 57. - Omb:man\nSv järnbrukens träkolsfören 42, ordf sed\n57 (v 52). - Medl S :té Örjenis gille sed\n\n43,  S* SälUskapet sed 43, SSS sed 60.\n-Hobbies:  botanik,  ent’omologi,   segling,\nfotografi, målning.\n\nGift m Karin Persson f 11, dtr t Nils\nP o Alma Nordell. - Barn: Inger f 39,\nTorbjörn f 41, Gerhard f 43, Mats f\n46, Anders f 48.\n\nWALDENSTRÖM, OLOF A, konsul,\nLidingö, f i Ljungby, Kalmar l, 17/2/00\nav häradsh Alfred W o Gabriella\nRom-dahl.\nJur kand Upps 26, sekr stat socker komm\n\n28,   anst Sv hdlsbkn 29, sekr SAF\n30-39,   kanslich   40-47,   finsk   konsul   sed\n48.  -  Sekr  komm f arb :hjälp  åt Finl,\nhjälpkomm   f  Finl   invalider,   styr :ordf\nB    Waldenströms    konsthdl    ab,    ordf\nSpånga S:e tax:nd sed 57. - Utm: RVO,\nKFinlLO l kl, FFrK3kl, RFinlVROlkl.\nGift 25 m Brita Elmquist f Ol, dtr t\növerståthållare Henning E o Brita\nBoberg.  -  Barn:  Johan  f  26,   Magnus  f\n\n29,  Christina f 33.\nWALDENSTRÖM, TORSTEN E,\n\ntandläkare, Djursholm, f i Sthlm 15/11/\n11 av civiling Einar W o Hill\nSandström.\n\nStud:ex Nykpg 32, odont kand 36,\ntand-läk :ex 39, prakt Sthlm sed 42.\n\nWALDIMIR,   SUNE,   kapellmästare,\n\nSthlm, f i Västerås 15/11/07 av förman\nEmil Engström o Jenny Aspman.\nRealex, repetitör K teat 26-30, stud\nmusikkonservat, ledare\nWiggerskvartetten 29-35, varit anst Sv:es radio, leder\negen ensemble, dirig Marshallkonsert\nParis. - Kompon populär- o filmmusik,\ngästdirig Norge, Danmark, Finl o Engl.\n- Medl TSO, Odd Fellow, BifrostO,\nPB.\n\nGift 1) 29 m Anna Stina Alling, 2) 46\nm Ulla Söderwall, 3) 51 m Lolita Russel\nJones. - Barn: i l:a akt Birgit f 31,\nAnders f 34, Lars f 39, Lillemor f 42.\n\n",
    "structured": {
        "1": {
            "full_name": "Viggbyholm, Ernst W Norrlin",
            "location": "Skatelöv, Kronob l",
            "occupation": "verkst dir Städernas vakt ab",
            "birth_details": {
                "date": "23/06/1915",
                "place": "Skatelöv, Kronob l",
                "parents": "köpman Ernst W o Sigrid Norrlin"
            },
            "education": [
                {
                    "degree": "Stud:ex",
                    "year": "1933",
                    "institution": "Växjö"
                }
            ],
            "career": [
                {
                    "position": "byråsekr stat",
                    "years": {
                        "start_year": 1947,
                        "end_year": 1947
                    },
                    "organization": "postverket"
                },
                {
                    "position": "sekr o omb :man",
                    "years": {
                        "start_year": 1948,
                        "end_year": 1949
                    },
                    "organization": "Sv:es verkstadsfören"
                },
                {
                    "position": "dir",
                    "years": {
                        "start_year": 1950,
                        "end_year": 1951
                    },
                    "organization": "SNS"
                },
                {
                    "position": "verkst dir",
                    "years": {
                        "start_year": 1951,
                        "end_year": 1958
                    },
                    "organization": "Städernas vakt ab"
                },
                {
                    "position": "dir o ch admin avd",
                    "years": {
                        "start_year": 1958
                    },
                    "organization": "SAF"
                }
            ],
            "family": {
                "spouse": "Ebbagreta Holmberg",
                "marriage_year": "1936",
                "children": [
                    {
                        "name": "Bo",
                        "birth_year": "1937"
                    },
                    {
                        "name": "Christina",
                        "birth_year": "1940"
                    },
                    {
                        "name": "Hans",
                        "birth_year": "1942"
                    },
                    {
                        "name": "Bengt",
                        "birth_year": "1946"
                    },
                    {
                        "name": "Ulf",
                        "birth_year": "1959"
                    }
                ]
            }
        },
        "2": {
            "full_name": "Waldén, Sven G",
            "location": "Saltsjöbaden",
            "occupation": "l:e försv:tandläk IV milostaben",
            "birth_details": {
                "date": "05/11/1904",
                "place": "Älvkarleby, Upps l",
                "parents": "trafikchef Otto W o Maria Monie"
            },
            "education": [
                {
                    "degree": "Stud:ex",
                    "year": "1923",
                    "institution": "Saltsjöbaden"
                },
                {
                    "degree": "med kand",
                    "year": "1927"
                },
                {
                    "degree": "tandläk:ex",
                    "year": "1929"
                }
            ],
            "career": [
                {
                    "position": "l:e försv:tandläk IV milostaben",
                    "years": {
                        "start_year": 1945
                    }
                }
            ],
            "family": {
                "spouse": "Birgit Lundquist",
                "marriage_year": "1929",
                "children": [
                    {
                        "name": "Britt-Marie",
                        "birth_year": "1931"
                    },
                    {
                        "name": "Björn",
                        "birth_year": "1934"
                    },
                    {
                        "name": "Svante",
                        "birth_year": "1943"
                    }
                ]
            }
        },
        "3": {
            "full_name": "Waldenström, Erland",
            "location": "Sthlm",
            "occupation": "verkst dir LKAB, Grängesbergsbol",
            "birth_details": {
                "date": "04/06/1911",
                "place": "Malmö",
                "parents": "dir Martin W o Hedvig Lion"
            },
            "education": [
                {
                    "degree": "Stud:ex",
                    "year": "1929",
                    "institution": "Nykpg"
                },
                {
                    "degree": "KTH",
                    "year": "1933"
                }
            ],
            "career": [
                {
                    "position": "ing Korsnäs sågverk ab",
                    "years": {
                        "start_year": 1934
                    }
                },
                {
                    "position": "tekn sekr Ind:förb",
                    "years": {
                        "start_year": 1940
                    }
                },
                {
                    "position": "förestånd tekn byrån Sv cellulosa ab",
                    "years": {
                        "start_year": 1942
                    }
                },
                {
                    "position": "övering",
                    "years": {
                        "start_year": 1947,
                        "end_year": 1949
                    },
                    "organization": "LKAB"
                },
                {
                    "position": "verkst dir",
                    "years": {
                        "start_year": 1950,
                        "end_year": 1957
                    },
                    "organization": "Grängesbergsbol"
                }
            ],
            "family": {
                "spouse": "Dorothy Boleyn Drewry",
                "marriage_year": "1945",
                "children": [
                    {
                        "name": "Hedda",
                        "birth_year": "1946"
                    },
                    {
                        "name": "Martin",
                        "birth_year": "1948"
                    },
                    {
                        "name": "Cecilia",
                        "birth_year": "1950"
                    }
                ]
            }
        },
        "4": {
            "full_name": "Waldenström, J Henning",
            "location": "Lidingö",
            "occupation": "professor emeritus",
            "birth_details": {
                "date": "14/08/1877",
                "place": "Upps",
                "parents": "prof Johan W o Elisabeth Gibson"
            },
            "education": [
                {
                    "degree": "Stud:ex",
                    "year": "1896",
                    "institution": "Sthlm"
                },
                {
                    "degree": "med kand",
                    "year": "NULL"
                },
                {
                    "degree": "med lic",
                    "year": "NULL"
                },
                {
                    "degree": "med dr",
                    "year": "NULL"
                }
            ],
            "career": [
                {
                    "position": "doc i ortopedi",
                    "years": {
                        "start_year": 1936,
                        "end_year": 1942
                    },
                    "organization": "Karol inst"
                }
            ],
            "family": {
                "spouse": "Elsa Laurin",
                "marriage_year": "1905",
                "children": [
                    {
                        "name": "Jan",
                        "birth_year": "1906"
                    }
                ]
            }
        },
        "5": {
            "full_name": "Waldenström, Johan A",
            "location": "Lidingö",
            "occupation": "fd lasarettsläkare",
            "birth_details": {
                "date": "5/1/1880",
                "place": "Upps",
                "parents": "prof Johan W o Elisabeth Gibson"
            },
            "education": [
                {
                    "degree": "Stud:ex",
                    "year": "1897",
                    "institution": "Sthlm"
                },
                {
                    "degree": "med kand",
                    "year": "1903"
                },
                {
                    "degree": "med lic",
                    "year": "1907"
                },
                {
                    "degree": "med hed:dr",
                    "year": "1927"
                }
            ],
            "career": [
                {
                    "position": "ol las:läk kir avd",
                    "years": {
                        "start_year": 1913,
                        "end_year": 1915
                    }
                },
                {
                    "position": "las:läk kir avd",
                    "years": {
                        "start_year": 1914,
                        "end_year": 1945
                    },
                    "organization": "Falu las"
                }
            ]
        },
        "6": {
            "full_name": "Waldenström, Lars",
            "location": "Lidingö",
            "occupation": "direktör",
            "birth_details": {
                "date": "13/11/1912",
                "place": "Malmö",
                "parents": "dir Martin W o Hedvig Lion"
            },
            "education": [
                {
                    "degree": "Jur kand",
                    "year": "1937"
                }
            ],
            "career": [
                {
                    "position": "eget företag",
                    "years": {
                        "start_year": 1954
                    },
                    "organization": "Tre Rosor hdls ab"
                }
            ],
            "family": {
                "spouse": "Viveca Enell",
                "marriage_year": "1944",
                "children": [
                    {
                        "name": "Carola",
                        "birth_year": "1945"
                    },
                    {
                        "name": "Urban",
                        "birth_year": "1946"
                    },
                    {
                        "name": "Patrik",
                        "birth_year": "1950"
                    },
                    {
                        "name": "Anita",
                        "birth_year": "1954"
                    }
                ]
            }
        },
        "7": {
            "full_name": "Waldenström, Nils G",
            "location": "Bromma",
            "occupation": "direktör",
            "birth_details": {
                "date": "9/1/1905",
                "place": "Antwerpen",
                "parents": "köpman Valdemar W o Gertrud Sandelin"
            },
            "education": [
                {
                    "degree": "Jur kand",
                    "year": "1932"
                }
            ],
            "career": [
                {
                    "position": "adv :verksamhet",
                    "years": {
                        "start_year": 1936
                    },
                    "organization": "Norrkpg"
                }
            ],
            "family": {
                "spouse": "Karin Persson",
                "marriage_year": "NULL"
            }
        },
        "8": {
            "full_name": "Waldenström, Olof A",
            "location": "Lidingö",
            "occupation": "konsul",
            "birth_details": {
                "date": "17/2/1900",
                "place": "Ljungby, Kalmar l",
                "parents": "häradsh Alfred W o Gabriella Romdahl"
            },
            "education": [
                {
                    "degree": "Jur kand",
                    "year": "1926",
                    "institution": "Upps"
                }
            ],
            "career": [
                {
                    "position": "finsk konsul",
                    "years": {
                        "start_year": 1948
                    }
                }
            ],
            "family": {
                "spouse": "Brita Elmquist",
                "marriage_year": "1925",
                "children": [
                    {
                        "name": "Johan",
                        "birth_year": "1926"
                    },
                    {
                        "name": "Magnus",
                        "birth_year": "1929"
                    },
                    {
                        "name": "Christina",
                        "birth_year": "1933"
                    }
                ]
            }
        },
        "9": {
            "full_name": "Waldenström, Torsten E",
            "location": "Djursholm",
            "occupation": "tandläkare",
            "birth_details": {
                "date": "15/11/1911",
                "place": "Sthlm",
                "parents": "civiling Einar W o Hill Sandström"
            },
            "education": [
                {
                    "degree": "Stud:ex",
                    "year": "1932",
                    "institution": "Nykpg"
                }
            ],
            "career": [
                {
                    "position": "prakt",
                    "years": {
                        "start_year": 1942
                    }
                }
            ]
        },
        "10": {
            "full_name": "Waldimir, Sune",
            "location": "Sthlm",
            "occupation": "kapellmästare",
            "birth_details": {
                "date": "15/11/1907",
                "place": "Västerås",
                "parents": "förman Emil Engström o Jenny Aspman"
            },
            "education": [
                {
                    "degree": "realex",
                    "year": "NULL"
                }
            ],
            "career": [
                {
                    "position": "ledare Wiggerskvartetten",
                    "years": {
                        "start_year": 1929,
                        "end_year": 1935
                    }
                }
            ],
            "family": {
                "spouse": "Lolita Russel Jones",
                "marriage_year": "1951",
                "children": [
                    {
                        "name": "Birgit",
                        "birth_year": "1931"
                    },
                    {
                        "name": "Anders",
                        "birth_year": "1934"
                    },
                    {
                        "name": "Lars",
                        "birth_year": "1939"
                    },
                    {
                        "name": "Lillemor",
                        "birth_year": "1942"
                    }
                ]
            }
        }
    }
}