{
    "original": "Dillner, Harald Johannes, tf.\nkansliråd, Sthlm, f. i Skellefteå 9/1/03 av\növerste Herman D. o. Anna Odelberg.\nG. 36 m. grev :an Madeleine Hamilton.\nJur. kand. Sthlm 27, aman. i eckl :dep.\n32, e, 2:e kanslisekr. 33, ord. 36, l :e\nkanslisekr. å ex. stat 38, ord. 39, föredr.\nh. reger:rätt. 35, tf. kansliråd i\neckl:-dep. o. ch. f. dess folksk :byrå sed. 35.\nLed. i verkstadssk :utredn. 38, sekr. i\nfi. komm. m. m. RNO, RFinlVROlkl.\nDillner, Hedvig Maria, f. d.\nflick-scoutchef, Sthlm, f. i Skellefteå av\növerste Herm. D. o. Anna Odelberg.\nLär:na i Margarethask., Sthlm, 18-19,\nBrummerska sk. 20-21, ch. f. Sv:es\nfl:-scoutförb. 31-35, ordf. i Sv:es\nflrscout-råd 35-37, styr rmedl. i The World\nAssoc, of Girl Guides 32-38.\nDillström, Torbjörn Viktor, direktör,\nSthlm, f. i Ovansjö, Gävleb. L, 8/4/04\nav ing. Karl D. o. Elin Bergman. G.\n38 m. Gurli Ekerfors. KTH 27, assist.\nv. KTH i förbränn :mot. 28-29, ing. v.\nHesselman Motor Corp. A-B o. ch. f.\nritkont. 29-35, övering. 35-41, verkst,\ndir. fr. 42.\nDilot, Gari Håkon, civilingenjör,\nÄppelviken, f. 30/10/93 i Bjuf, Malmöh. 1.\nStud:ex. Hrborg 125 civ ring., mekanist,\nCTH 17. Studrres. t. U. S. A. 20-23,\nHoll. 28, 31, 36, Engl. 28-36. Anst. v.\nHöganäs-Billesholms A-B 19-20 ss.\ngruving., Hudson Motor Gar Co., New\nYork, 20-21, Stanley Steam Gar Co.,\nNewton, Mass., 21-23, Nydqvist &amp; Holm\nA-B, Trollhättan, 23-26, A-B Elektrolux\nfr. 27, ch. f. experimentverkst. 40.\nSekr. i Trädgårdsstadsför.\nÄppelviken-Smedslätten, styr :led. o. blockled, i\nBromma Luftsk:fören. Hobby:\nFotografering. Luftskyddsförb :s förtj :t.\nDiver, May, danskonstnärinna, Sthlm.\nEft. stud. f. Anna Behle grmg. Operans\nbalettsk. o. eng. därst. 19-27, eng. v.\nSödra teat., Folhets hus teat. m. fi.\nGästspel i Norge o. Danmark samt\nturnéer i Sv:e. Bedr. numera dansped.\nverksamh, i Sthlm enl. Borneviellska\nskolans metod. Stud:res. i Tyskland,\nFrankr, o. Engl.\n",
    "structured": {
        "0": {
            "full_name": "Dillner, Harald Johannes",
            "location": "Sthlm",
            "occupation": "tf. Kansliråd",
            "birth_details": {
                "date": "09/01/1903",
                "place": "Skellefteå",
                "parents": "överste Herman D. o. Anna Odelberg"
            },
            "education": [
                {
                    "degree": "Jur. kand.",
                    "year": "1927",
                    "institution": "Sthlm"
                },
                {
                    "degree": "aman. i eckl :dep.",
                    "year": "1932",
                    "institution": "N/A"
                }
            ],
            "career": [
                {
                    "position": "tf. kansliråd i eckl:-dep. o. ch. f. dess folksk :byrå",
                    "years": {
                        "start_year": 1935,
                        "end_year": 1971
                    },
                    "organization": "N/A"
                }
            ],
            "family": {
                "spouse": "grev :an Madeleine Hamilton",
                "marriage_year": "1936",
                "children": []
            }
        },
        "1": {
            "full_name": "Dillner, Hedvig Maria",
            "location": "Sthlm",
            "occupation": "f. d. flick-scoutchef",
            "birth_details": {
                "date": "N/A",
                "place": "Skellefteå",
                "parents": "överste Herm. D. o. Anna Odelberg"
            },
            "education": [
                {
                    "degree": "Lär:na",
                    "year": "N/A",
                    "institution": "Margarethask., Sthlm"
                },
                {
                    "degree": "Lär:na",
                    "year": "N/A",
                    "institution": "Brummerska sk."
                }
            ],
            "career": [
                {
                    "position": "ch. f. Sv:es fl:-scoutförb.",
                    "years": {
                        "start_year": 1931,
                        "end_year": 1935
                    },
                    "organization": "N/A"
                }
            ],
            "family": {
                "spouse": "N/A",
                "marriage_year": "N/A",
                "children": []
            }
        },
        "2": {
            "full_name": "Dillström, Torbjörn Viktor",
            "location": "Sthlm",
            "occupation": "direktör",
            "birth_details": {
                "date": "08/04/1904",
                "place": "Ovansjö, Gävleb. L",
                "parents": "ing. Karl D. o. Elin Bergman"
            },
            "education": [
                {
                    "degree": "N/A",
                    "year": "N/A",
                    "institution": "KTH"
                }
            ],
            "career": [
                {
                    "position": "verkst, dir.",
                    "years": {
                        "start_year": 1942,
                        "end_year": 1971
                    },
                    "organization": "N/A"
                }
            ],
            "family": {
                "spouse": "Gurli Ekerfors",
                "marriage_year": "1938",
                "children": []
            }
        },
        "3": {
            "full_name": "Dilot, Gari Håkon",
            "location": "Äppelviken",
            "occupation": "civilingenjör",
            "birth_details": {
                "date": "30/10/1893",
                "place": "Bjuf, Malmöh. 1",
                "parents": "N/A"
            },
            "education": [
                {
                    "degree": "Stud:ex. Hrborg",
                    "year": "1925",
                    "institution": "N/A"
                },
                {
                    "degree": "civ ring., mekanist",
                    "year": "N/A",
                    "institution": "CTH"
                }
            ],
            "career": [
                {
                    "position": "ch. f. experimentverkst.",
                    "years": {
                        "start_year": 1940,
                        "end_year": 1971
                    },
                    "organization": "N/A"
                }
            ],
            "family": {
                "spouse": "N/A",
                "marriage_year": "N/A",
                "children": []
            },
            "hobbies": [
                "Fotografering"
            ]
        },
        "4": {
            "full_name": "Diver, May",
            "location": "Sthlm",
            "occupation": "danskonstnärinna",
            "birth_details": {
                "date": "N/A",
                "place": "N/A",
                "parents": "N/A"
            },
            "education": [
                {
                    "degree": "N/A",
                    "year": "N/A",
                    "institution": "N/A"
                }
            ],
            "career": [],
            "family": {
                "spouse": "N/A",
                "marriage_year": "N/A",
                "children": []
            },
            "community_involvement": [
                {
                    "role": "dansped. verksam",
                    "organization": "Borneviellska skolans metod",
                    "years": "N/A"
                }
            ],
            "hobbies": [
                "Stud:res. i Tyskland, Frankr, o. Engl."
            ]
        }
    }
}