{
    "original": "Christiansen, Jörgen Richard,\ndiplomingenjör, Norrköping, f. 14/3/86 i\nHesslunda, Malmöh. 1., av godsäg.\nEduard C. o. Marie Knutzen. G. 16\nm. Gertrud Perless. Barn: Gertrud\nEbba Maria f. 17, g. m. tj :man Elis\nNordin, Carl-Eduard Jörgen Richard\n20, banktj :man. — Stud:ex. i Lund 05,\ningiex. v. tekn. högsk. i Dresden 12.\nIng. v. AEG i Berlin 13, övering. v.\nSiemens-Schuckert Werke A-G i\nBerlin 14-43, pens. 43.\n\nChristiansen, Vilhelm, överingenjör,\nFinspång, f. 27/6/9S i Vitsand, Värml.\n1., av H. C. o. Emilia Enocksen. G.\n22 m. Karin Tisell. Barn: Ulla f. 25,\nsitud. v. univ. i Edinburgh, Bo\n27, Kerstin 29, Per 34. — Stud:ex.\ni Karlstad 14, KTH (metallurgi) 16-20.\nVärmetekn. und:sökn. v. IVAsi\nkraft-o. bräns’leutredn, 20-23, metallurg o.\nlab :chef v. Finspångs Metallverks\nA-B sed. 23, nu A-B Sv. Metallverken,\nFinspong-verken, övering. där sed. 41.\nSkr.: upps. i facktidskr.\n\nChristiansson, Einar Vilhehn,\nkonstnär, Göteborg, f. 8/6/01 i Gbg av\nHerman Valdemar Kristiansson o. Anna\nGustava K. — Stud. v. h. avd. f.\ngrafisk teckn. v. slöjdfören. sk. i Gbg\n25-27, Valands målarsk. i Gbg 32-36,\nkonstakad. i Köpenhamn 39-40. Res.\nt. Paris 37 o. 38-39, Sydfrankr. 39.\nV. klubbmäst. i Gbgs konstnärskl, led.\nav Gbgs friluftsällsk. Hobbies :\nkonstböcker, friluftsliv.\n\nChristiansson, Erik Holger, jur.\nkand., länsnotarie. Mariestad, f. 30/3/03\ni Osby, Krist. 1., av Joh. Chr. o.\nMathilda Nilsson. G. 30 m. folkskoll.\nInez Troedsson. Barn: Inger f. 31,\nJarl 36, Gunnar 45. — Stud:ex. 25, jur.\nkand. 30. Res. t. Tyskl. 21, 22, 23,\nFinl. 36, Polen 37, Danm., Norge 39.\nAnst. v. dom:kansli 30-33, polistjg. i\n\nMalmö 33-34, länsnot. h. länsstyr. i\nSkarab. 1. i Mariestad fr. 35.\nDistr:-sekr. i SvRK 36-43, lok :omb., sekr;\no. ’kassaförv. i Mariest. f. Rrksfören.\nf. svenskh. bev. i uti. fr. 38, tax:ordf.\ni Töreboda köp. fr. 41, alim. omb. i\nSkövde sparb. sed. 45. Hobbies:\nety-mologi, slav. språk.\n\n",
    "structured": {
        "1": {
            "full_name": "Jörgen Richard Christiansen",
            "location": "Norrköping",
            "occupation": "Diplomingenjör",
            "birth_details": {
                "date": "14/03/1886",
                "place": "Hesslunda, Malmöh. 1.",
                "parents": "Eduard C. o. Marie Knutzen"
            },
            "education": [
                {
                    "degree": "Stud:ex.",
                    "year": "1905",
                    "institution": "Lund"
                },
                {
                    "degree": "Ing:ex.",
                    "year": "1912",
                    "institution": "Tekn. högsk. i Dresden"
                }
            ],
            "career": [
                {
                    "position": "Ing. v. AEG i Berlin",
                    "years": {
                        "start_year": 1913,
                        "end_year": 1913
                    },
                    "organization": "AEG"
                },
                {
                    "position": "Övering. v. Siemens-Schuckert Werke A-G i Berlin",
                    "years": {
                        "start_year": 1914,
                        "end_year": 1943
                    },
                    "organization": "Siemens-Schuckert Werke A-G"
                },
                {
                    "position": "Pens.",
                    "years": {
                        "start_year": 1943,
                        "end_year": 1943
                    }
                }
            ],
            "family": {
                "spouse": "Gertrud Perless",
                "marriage_year": "1916",
                "children": [
                    {
                        "name": "Gertrud Ebba Maria",
                        "birth_year": "1917"
                    },
                    {
                        "name": "Carl-Eduard Jörgen Richard",
                        "birth_year": "1920"
                    }
                ]
            }
        },
        "2": {
            "full_name": "Vilhelm Christiansen",
            "location": "Finspång",
            "occupation": "Överingenjör",
            "birth_details": {
                "date": "27/06/1895",
                "place": "Vitsand, Värml. 1.",
                "parents": "H. C. o. Emilia Enocksen"
            },
            "education": [
                {
                    "degree": "Stud:ex.",
                    "year": "1914",
                    "institution": "Karlstad"
                },
                {
                    "degree": "KTH (metallurgi)",
                    "year": "1916-1920"
                }
            ],
            "career": [
                {
                    "position": "Värmetekn. und:sökn. v. IVAsi kraft-o. bräns’leutredn",
                    "years": {
                        "start_year": 1920,
                        "end_year": 1923
                    }
                },
                {
                    "position": "Metallurg o. lab:chef v. Finspångs Metallverks A-B",
                    "years": {
                        "start_year": 1923
                    }
                },
                {
                    "position": "Överingenjör",
                    "years": {
                        "start_year": 1941
                    },
                    "organization": "A-B Sv. Metallverken, Finspong-verken"
                }
            ],
            "family": {
                "spouse": "Karin Tisell",
                "marriage_year": "1922",
                "children": [
                    {
                        "name": "Ulla",
                        "birth_year": "1925"
                    },
                    {
                        "name": "Bo",
                        "birth_year": "1927"
                    },
                    {
                        "name": "Kerstin",
                        "birth_year": "1929"
                    },
                    {
                        "name": "Per",
                        "birth_year": "1934"
                    }
                ]
            }
        },
        "3": {
            "full_name": "Einar Vilhelm Christiansson",
            "location": "Göteborg",
            "occupation": "Konstnär",
            "birth_details": {
                "date": "8/6/1901",
                "place": "Göteborg",
                "parents": "Herman Valdemar Kristiansson o. Anna Gustava K."
            },
            "education": [
                {
                    "degree": "Stud. v. h. avd. f. grafisk teckn",
                    "year": "25-27",
                    "institution": "slöjdfören. sk. i Gbg"
                },
                {
                    "degree": "Valands målarsk.",
                    "year": "32-36",
                    "institution": "Valands målarsk. i Gbg"
                },
                {
                    "degree": "Konstakad.",
                    "year": "39-40",
                    "institution": "konstakad. i Köpenhamn"
                }
            ],
            "hobbies": [
                "konstböcker",
                "friluftsliv"
            ]
        },
        "4": {
            "full_name": "Erik Holger Christiansson",
            "location": "Mariestad",
            "occupation": "Jur. kand., länsnotarie",
            "birth_details": {
                "date": "30/3/1903",
                "place": "Osby, Krist. 1.",
                "parents": "Joh. Chr. o. Mathilda Nilsson"
            },
            "education": [
                {
                    "degree": "Stud:ex.",
                    "year": "1925"
                },
                {
                    "degree": "Jur. kand.",
                    "year": "1930"
                }
            ],
            "career": [
                {
                    "position": "Anst. v. dom:kansli",
                    "years": {
                        "start_year": 1930,
                        "end_year": 1933
                    }
                },
                {
                    "position": "Polistjg. i Malmö",
                    "years": {
                        "start_year": 1933,
                        "end_year": 1934
                    }
                },
                {
                    "position": "Länsnot. h. länsstyr. i Skarab. 1. i Mariestad",
                    "years": {
                        "start_year": 1935
                    }
                }
            ],
            "family": {
                "spouse": "Inez Troedsson",
                "marriage_year": "1930",
                "children": [
                    {
                        "name": "Inger",
                        "birth_year": "1931"
                    },
                    {
                        "name": "Jarl",
                        "birth_year": "1936"
                    },
                    {
                        "name": "Gunnar",
                        "birth_year": "1945"
                    }
                ]
            },
            "hobbies": [
                "ety-mologi",
                "slav. språk"
            ]
        }
    }
}