{
    "original": "Cavalli-Björkman, Leif Erik,\npraktiserande läkare, Motala, f. 3(1/12/05 i\nStrömstad av konsul Oscar C.-B. o.\nMinna Torp. G. 34 m. Gerd Linnér.\nBarn: Ulf f. 36, Ragnhild 39, Christer\n41. — Studrex. i Vänersborg 27, med.\nkand. i Sthlm 32 o. med. lic. där 37.\nUndiläk. v. Strömstads havskuranst.\n32-36, marinläk :stip. över stat 37, tf.\nund :läk. v. Strömstads o. Backa las.\nkort. tider s. å., skepp-släk. på m/s\nAxel Johnson 38, e. läk. samt tf. andre\nund:läk. v. Eksjö las. 38, ord. andre,\ntf. förste o. tf. överläk. v.\nOskarshamns las. 38-41, priv. prakt, i Motala\nsed. 42, verksläk. v. centr.\ntorped-verkst. där sed. 42.\n\nCedell, Bertil Gottfrid Thorsten,\nkyrkoherde, Lenhovda, f. 4/1/03 i\nRyssby, Kalmar 1., av nämndeman\nGoittfrid C. o. Elmdnia Andersdtr. G.\n33 m. Alma Adler. Barn: Torsten f.\n35, Bengt 38, Karin 44. — Stud:ex. i\nKalmar 23, teol. fil. ex. i Lund 25,\nteol. kand., prakt. teol. ex. samt prästv.\nf. Växjö stift 28. Tjg. s. past:adj. o.\nv. pastor i Bankeryd, kommin. i\nMönsterås 29, vik. lär. v. Mönsterås\nsamrealsk., kyrkoh. i Lenhovda sed.\n44. Skr.: betrakt. i Oskarshamnstidn.\no. Barometern. Hemv. förtj :pl. i\nsilver 44.\n\nCedell; Herbert Gustiav M’a;uiritz,\nliäro’-verksadjunkt, Nybro, f. 1/9/99 i Ryssby,\nKalmar k, av Gottfrid C. o. Elmina\nAndersdötter. G. 23 m. Emmy\nTörnblad. Barn: Lars-Ingvar f. 28,\nGun-Britt 30, Karl-Axel 32. — Stud:ex. i\nKalm. 20, folkskoll :ex. i Växjö 21, fil.\nkand. i Lund 27, fil. mag. 30.\nFolkskoll. i Ronneby 21-40, vik.\nfolkskol-insp. i Blek. o. Sydsmål. mellersta\ninsp :omr. periodvis 34-39, extralär. i\nLandskr. 31-32, timlär. v. Ronneby\nyr-kessk. 37-40, ord. ämneslär. i Nybro\n40, adj. där 47. Ornitoilog.\n\nCeder, Erik Verner, komminister,\nIsums, f. 14/12/00 i Kattunga, Älvsb.\n1., av Emil C. o. Amanda Johansson.\nG. 38 m. Signe Hedén. — Stud:ex. v.\nLunds priv. elem:sk. 33, teol. fil. ex.\nv. Lunds univ. 35, teol. kand. där 38,\nprästv. 39. V. pastor i Vänge 39-42,\nkommin. i Stenkumla sed. 42. Ordf.\ni kyrkostämma o. skolstyr.\n\n",
    "structured": {
        "0": {
            "full_name": "Cavalli-Björkman, Leif Erik",
            "location": "Motala",
            "occupation": "praktiserande läkare",
            "birth_details": {
                "date": "03/12/1905",
                "place": "Strömstad",
                "parents": "konsul Oscar C.-B. o. Minna Torp"
            },
            "education": [
                {
                    "degree": "Studrex.",
                    "year": "1927",
                    "institution": "Vänersborg"
                },
                {
                    "degree": "med. kand.",
                    "year": "1932",
                    "institution": "Sthlm"
                },
                {
                    "degree": "med. lic.",
                    "year": "1937",
                    "institution": "Sthlm"
                }
            ],
            "career": [
                {
                    "position": "Undiläk. v. Strömstads havskuranst.",
                    "years": {
                        "start_year": 1932,
                        "end_year": 1936
                    },
                    "organization": "Strömstads havskuranst."
                },
                {
                    "position": "marinläk :stip. över stat",
                    "years": {
                        "start_year": 1937,
                        "end_year": 1937
                    }
                },
                {
                    "position": "tf. und :läk. v. Strömstads o. Backa las.",
                    "years": {
                        "start_year": 1937,
                        "end_year": 1937
                    }
                },
                {
                    "position": "skepp-släk. på m/s Axel Johnson",
                    "years": {
                        "start_year": 1938,
                        "end_year": 1938
                    },
                    "organization": "m/s Axel Johnson"
                },
                {
                    "position": "e. läk. samt tf. andre und:läk. v. Eksjö las.",
                    "years": {
                        "start_year": 1938,
                        "end_year": 1938
                    },
                    "organization": "Eksjö las."
                },
                {
                    "position": "ord. andre, tf. förste o. tf. överläk. v. Oskarshamns las.",
                    "years": {
                        "start_year": 1938,
                        "end_year": 1941
                    },
                    "organization": "Oskarshamns las."
                },
                {
                    "position": "priv. prakt, i Motala",
                    "years": {
                        "start_year": 1942
                    }
                },
                {
                    "position": "verksläk. v. centr. torped-verkst. där",
                    "years": {
                        "start_year": 1942
                    },
                    "organization": "centr. torped-verkst."
                }
            ],
            "family": {
                "spouse": "Gerd Linnér",
                "marriage_year": "1934",
                "children": [
                    {
                        "name": "Ulf",
                        "birth_year": "1936"
                    },
                    {
                        "name": "Ragnhild",
                        "birth_year": "1939"
                    },
                    {
                        "name": "Christer",
                        "birth_year": "1941"
                    }
                ]
            }
        },
        "1": {
            "full_name": "Cedell, Bertil Gottfrid Thorsten",
            "location": "Lenhovda",
            "occupation": "kyrkoherde",
            "birth_details": {
                "date": "04/01/1903",
                "place": "Ryssby, Kalmar 1."
            },
            "education": [
                {
                    "degree": "Stud:ex.",
                    "year": "1923",
                    "institution": "Kalmar"
                },
                {
                    "degree": "teol. fil. ex.",
                    "year": "1925",
                    "institution": "Lund"
                },
                {
                    "degree": "teol. kand.",
                    "year": "1928"
                }
            ],
            "career": [
                {
                    "position": "v. pastor",
                    "years": {
                        "start_year": 1944
                    },
                    "organization": "Lenhovda"
                }
            ],
            "family": {
                "spouse": "Alma Adler",
                "marriage_year": "1933",
                "children": [
                    {
                        "name": "Torsten",
                        "birth_year": "1935"
                    },
                    {
                        "name": "Bengt",
                        "birth_year": "1938"
                    },
                    {
                        "name": "Karin",
                        "birth_year": "1944"
                    }
                ]
            },
            "publications": [
                {
                    "title": "betrakt. i Oskarshamnstidn. o. Barometern"
                }
            ],
            "honorary_titles": [
                {
                    "title": "silver",
                    "year": "1944"
                }
            ]
        },
        "2": {
            "full_name": "Cedell, Herbert Gustiav M’a;uiritz",
            "location": "Nybro",
            "occupation": "liäro’-verksadjunkt",
            "birth_details": {
                "date": "01/09/1899",
                "place": "Ryssby, Kalmar k"
            },
            "education": [
                {
                    "degree": "Stud:ex.",
                    "year": "1920",
                    "institution": "Kalm"
                },
                {
                    "degree": "folkskoll :ex.",
                    "year": "1921",
                    "institution": "Växjö"
                },
                {
                    "degree": "fil. kand.",
                    "year": "1927",
                    "institution": "Lund"
                },
                {
                    "degree": "fil. mag.",
                    "year": "1930"
                }
            ],
            "career": [
                {
                    "position": "Folkskoll.",
                    "years": {
                        "start_year": 1921,
                        "end_year": 1940
                    },
                    "organization": "Ronneby"
                },
                {
                    "position": "vik. folkskol-insp.",
                    "years": {
                        "start_year": 1934,
                        "end_year": 1939
                    },
                    "organization": "Blek. o. Sydsmål. mellersta insp :omr."
                },
                {
                    "position": "ord. ämneslär. i Nybro",
                    "years": {
                        "start_year": 1940
                    }
                },
                {
                    "position": "adj.",
                    "years": {
                        "start_year": 1947
                    },
                    "organization": "Nybro"
                }
            ],
            "family": {
                "spouse": "Emmy Törnblad",
                "marriage_year": "1923",
                "children": [
                    {
                        "name": "Lars-Ingvar",
                        "birth_year": "1928"
                    },
                    {
                        "name": "Gun-Britt",
                        "birth_year": "1930"
                    },
                    {
                        "name": "Karl-Axel",
                        "birth_year": "1932"
                    }
                ]
            },
            "hobbies": [
                "Ornitoilog"
            ]
        },
        "3": {
            "full_name": "Ceder, Erik Verner",
            "location": "Isums",
            "occupation": "komminister",
            "birth_details": {
                "date": "14/12/1900",
                "place": "Kattunga, Älvsb. 1."
            },
            "education": [
                {
                    "degree": "Stud:ex.",
                    "year": "1933",
                    "institution": "Lunds priv. elem:sk."
                },
                {
                    "degree": "teol. fil. ex.",
                    "year": "1935",
                    "institution": "Lunds univ."
                },
                {
                    "degree": "teol. kand.",
                    "year": "1938",
                    "institution": "Lunds univ."
                }
            ],
            "career": [
                {
                    "position": "v. pastor",
                    "years": {
                        "start_year": 1939,
                        "end_year": 1942
                    },
                    "organization": "Vänge"
                },
                {
                    "position": "kommin.",
                    "years": {
                        "start_year": 1942
                    },
                    "organization": "Stenkumla"
                }
            ],
            "family": {
                "spouse": "Signe Hedén",
                "marriage_year": "1938"
            },
            "community_involvement": [
                {
                    "role": "Ordf. i kyrkostämma",
                    "organization": "kyrkostämma",
                    "years": "NULL"
                },
                {
                    "role": "skolstyr",
                    "organization": "skolstyr",
                    "years": "NULL"
                }
            ]
        }
    }
}