{
    "original": "BANCK,   PER   ÅKE  D,   inköpschef,\n\nLinköping, f i Linkpg 12/10/26 av disp\n\nSture B o Stina Stillström.\n\nStud:ex 46, DHG 53; tf lånekamrer öst-\n\ngötabkn 48-50, rationaliser:man ASJ 53,\n\ninköpsch där sed 60. - Hobbies: jakt,\n\nbridge, foto.\n\nGift 49 m Margaretha Eckers f 24, dtr\n\nt godsäg Walfrid E o Sigrid Karlsson. -\n\nBarn: Lena f 50, Mats f 53.\n\nBANDLING,   GUSTAV  E,   ingenjör,\n\nHuskvarna, f i Skellefteå 14/9/14 av\nhemm:äg Johan Andersson o Johanna\nLundström.\n\nIng :ex Tekn inst Sthlm 40, konstr stat\nammun:nd 40, LME 43, ritkont:ch\nkrigs-materielverket 44, ch vapentillverkn\nHus-qvarna vapenfabr sed 45. - Led\nnyk-terh:nd, tax:nd. - Medl Odd Fellow.\n-Hobbies: jakt, fiske.\n\nGift 40 m Margareta Ström f 19.\n-Barn: Gunilla f 42.\n\nBANE, PER A, civilingenjör, Gbg, f i\nSt Köpinge, Malmöh l, 24/7/16 av kamr\nOscar Persson o Elvira Persson.\nTekn lärov Malmö 36, CTH 41, forskn:-\n\ning Sv oljeslageri ab Mölndal 42,\növering där sed 52.\n\nGift 42 m Eivor Almer f 17, dtr t\nstadsing Edvin A o Mary Johansson. - Barn:\nKristina f 43, Olof f 44, Peter f 54.\nBANEFELT, ÅKE J V, prakt läkare,\napotekare, Linköping, f i Linkpg 20/8/\n14 av sem:rekt Gustaf Janzon o Thérese\nBroström.\n\nStud:ex Linkpg 33, farm kand 38,\napot:-ex 41, med kand Sthlm 45, med lic Lund\n49, farmaceut, tjg apot o apot :f örest\npe-riodv 38-48, vik underläk, prov:läk,\nepid :sjh :läk, stadsdistr:läk samt l :e\nstads-läk m m 49-51, prakt läk Linkpg sed 51.\nGift 41 m Ann-Mari Edström f 16, dtr t\nkyrkoh Johan Olow E o Hanna Maria\nCederberg. - Barn: Ann f 43, Eva f 44.\n\n",
    "structured": {
        "0": {
            "full_name": "Per Åke Banck",
            "location": "Linköping",
            "occupation": "inköpschef",
            "birth_details": {
                "date": "12/10/1926",
                "place": "Linköping",
                "parents": "disp Sture B och Stina Stillström"
            },
            "education": [
                {
                    "degree": "Stud:ex",
                    "year": "1946",
                    "institution": "DHG"
                }
            ],
            "career": [
                {
                    "position": "tf lånekamrer",
                    "years": {
                        "start_year": 1948,
                        "end_year": 1950
                    },
                    "organization": "östgötabkn"
                },
                {
                    "position": "rationaliser:man",
                    "years": {
                        "start_year": 1953,
                        "end_year": 1953
                    },
                    "organization": "ASJ"
                },
                {
                    "position": "inköpsch",
                    "years": {
                        "start_year": 1960,
                        "end_year": null
                    },
                    "organization": "där"
                }
            ],
            "family": {
                "spouse": "Margaretha Eckers",
                "marriage_year": "1949",
                "children": [
                    {
                        "name": "Lena",
                        "birth_year": "1950"
                    },
                    {
                        "name": "Mats",
                        "birth_year": "1953"
                    }
                ]
            },
            "hobbies": [
                "jakt",
                "bridge",
                "foto"
            ]
        },
        "1": {
            "full_name": "Gustav E Bandling",
            "location": "Huskvarna",
            "occupation": "ingenjör",
            "birth_details": {
                "date": "14/9/1914",
                "place": "Skellefteå",
                "parents": "hemm:äg Johan Andersson o Johanna Lundström"
            },
            "education": [
                {
                    "degree": "Ing :ex",
                    "year": "1940",
                    "institution": "Tekn inst Sthlm"
                }
            ],
            "career": [
                {
                    "position": "konstr stat",
                    "years": {
                        "start_year": 1940,
                        "end_year": 1940
                    },
                    "organization": "ammun:nd"
                },
                {
                    "position": "ch vapentillverkn",
                    "years": {
                        "start_year": 1945,
                        "end_year": null
                    },
                    "organization": "Huskvarna vapenfabr"
                }
            ],
            "family": {
                "spouse": "Margareta Ström",
                "marriage_year": "1940",
                "children": [
                    {
                        "name": "Gunilla",
                        "birth_year": "1942"
                    }
                ]
            },
            "community_involvement": [
                {
                    "role": "Led",
                    "organization": "nyk-terh:nd",
                    "years": "NULL"
                },
                {
                    "role": "Led",
                    "organization": "tax:nd",
                    "years": "NULL"
                }
            ],
            "hobbies": [
                "jakt",
                "fiske"
            ]
        },
        "2": {
            "full_name": "Per A Banefelt",
            "location": "Gbg",
            "occupation": "civilingenjör",
            "birth_details": {
                "date": "24/7/1916",
                "place": "St Köpinge, Malmöh l",
                "parents": "kamr Oscar Persson o Elvira Persson"
            },
            "education": [
                {
                    "degree": "Tekn lärov",
                    "year": "1936",
                    "institution": "Malmö"
                },
                {
                    "degree": "CTH",
                    "year": "1941",
                    "institution": "NULL"
                }
            ],
            "career": [
                {
                    "position": "forskn:-ing",
                    "years": {
                        "start_year": 1942,
                        "end_year": 1952
                    },
                    "organization": "Sv oljeslageri ab Mölndal"
                },
                {
                    "position": "övering",
                    "years": {
                        "start_year": 1952,
                        "end_year": null
                    },
                    "organization": "där"
                }
            ],
            "family": {
                "spouse": "Eivor Almer",
                "marriage_year": "1942",
                "children": [
                    {
                        "name": "Kristina",
                        "birth_year": "1943"
                    },
                    {
                        "name": "Olof",
                        "birth_year": "1944"
                    },
                    {
                        "name": "Peter",
                        "birth_year": "1954"
                    }
                ]
            }
        },
        "3": {
            "full_name": "Åke J V Banefelt",
            "location": "Linköping",
            "occupation": "prakt läkare, apotekare",
            "birth_details": {
                "date": "20/8/1914",
                "place": "Linköping",
                "parents": "sem:rekt Gustaf Janzon o Thérese Broström"
            },
            "education": [
                {
                    "degree": "Stud:ex",
                    "year": "1933",
                    "institution": "Linköping"
                },
                {
                    "degree": "farm kand",
                    "year": "1938",
                    "institution": "NULL"
                },
                {
                    "degree": "apot:-ex",
                    "year": "1941",
                    "institution": "NULL"
                },
                {
                    "degree": "med kand",
                    "year": "1945",
                    "institution": "Sthlm"
                },
                {
                    "degree": "med lic",
                    "year": "1949",
                    "institution": "Lund"
                }
            ],
            "career": [
                {
                    "position": "vik underläk, prov:läk, epid :sjh :läk, stadsdistr:läk samt l :e stads-läk m m",
                    "years": {
                        "start_year": 1949,
                        "end_year": 1951
                    },
                    "organization": "Linköping"
                }
            ],
            "family": {
                "spouse": "Ann-Mari Edström",
                "marriage_year": "1941",
                "children": [
                    {
                        "name": "Ann",
                        "birth_year": "1943"
                    },
                    {
                        "name": "Eva",
                        "birth_year": "1944"
                    }
                ]
            }
        }
    }
}