{
    "original": "BERGLUND, ARNE H, advokat,\nMotala, f i Dalarö, Sthlms l, 4/7/21 av\nchefred Helmer B o Ester Persson.\nStud:ex Motala 40, jur kand Upps 47,\ntingstjg öl doms 47-50, bitr jur adv\nArnold Andersson Motala 50, ekon :ch\nMotala tidn ab 53, inneh Motala jurid\nbyrå sed 58. - LSA 59. - Styr:led SHAB,\nab Motala motorkompani. - Medl\nFrim-O, Lions club.\n\nGift 44 m Margareta Wernehed f 20,\ndtr t verkm Werner Svensson o Sigrid\nNilsson. - Barn: Anders f 45, Eva f 50.\n\nBERGLUND, BJÖRN N J G,\nskådespelare, Gbg, f i Jörn, Västerb l, 16/10/\n04 av prov:läk Nils B o Maja Ullström.\nDram teat elevsk 25-28, öl eng i Sthlm,\nGbg, Malmö, Hbg o v Riksteat, eng\nGbgs stadsteat sed 56. - Verksam inom\nfilm, radio o TV.\n\nGift 31 m skådesp Lisskulla Jobs f 06,\ndtr t musikdir Anders J o Elisabet\nWisén.\n\nBERGLUND, CARL ARNE A,\ntandläkare, Kalmar, f i Upps 21/5/27 av\ntandl Hjalmar B o Stina Sandberg.\nStud:ex Kalmar 46, tandl :ex Malmö 59,\ntandl folktandv Östersund 59, priv :prakt\nKalmar sed 59.\n\nBERGLUND, ELOF U, kapten,\ndirektör, Gbg, f i Gbg 13/8/17 av skeppsred\nC A B o Beda Andersson.\nGbgHdlI 37, stud Schweiz o Frankr\n38-38, ch ab Strannes konserver 47-57,\nverkst dir o ag ab Ström\nskeppsfourne-ring sed 57, Sv ostronkomp ab sed 54.\n\n-   Styr :led  Fastigh  ab  Orion m  dtrbol\n45, styr:suppl Gbgs torskmjölsfabr 55.\n-Styr:led Flottans res:off:förb 44. - Medl\nGbgs golfkl, GKSS, Rotary, PB, TSO,\nGSK, Bärsärkarna. - Res:off:ex 41, kapt\nmarinint:kårens res 50.\n\nGift 52 m Britt Kyllerfeldt f 29, dtr t\n\ning Georg K o h h. - Barn: Jonas f 55,\nMarie f 63, Klas f 65.\n\n",
    "structured": {
        "1": {
            "full_name": "ARNE H BERGLUND",
            "location": "Motala",
            "occupation": "advokat",
            "birth_details": {
                "date": "04/07/1921",
                "place": "Dalarö, Sthlms l",
                "parents": "chefred Helmer B o Ester Persson"
            },
            "education": [
                {
                    "degree": "Stud:ex",
                    "year": "1940",
                    "institution": "Motala"
                },
                {
                    "degree": "jur kand",
                    "year": "1947",
                    "institution": "Upps"
                }
            ],
            "career": [
                {
                    "position": "tingstjg öl",
                    "years": {
                        "start_year": 1947,
                        "end_year": 1950
                    },
                    "organization": "doms"
                },
                {
                    "position": "bitr jur adv",
                    "years": {
                        "start_year": 1950,
                        "end_year": null
                    },
                    "organization": "Arnold Andersson Motala"
                },
                {
                    "position": "ekon :ch",
                    "years": {
                        "start_year": 1953,
                        "end_year": null
                    },
                    "organization": "Motala tidn ab"
                },
                {
                    "position": "inneh",
                    "years": {
                        "start_year": 1958,
                        "end_year": null
                    },
                    "organization": "Motala jurid byrå"
                }
            ],
            "family": {
                "spouse": "Margareta Wernehed",
                "marriage_year": "1944",
                "children": [
                    {
                        "name": "Anders",
                        "birth_year": "1945"
                    },
                    {
                        "name": "Eva",
                        "birth_year": "1950"
                    }
                ]
            }
        },
        "2": {
            "full_name": "BJÖRN N J G BERGLUND",
            "location": "Gbg",
            "occupation": "skådespelare",
            "birth_details": {
                "date": "16/10/1904",
                "place": "Jörn, Västerb l",
                "parents": "prov:läk Nils B o Maja Ullström"
            },
            "education": [
                {
                    "degree": "Dram teat elevsk",
                    "year": "1925-1928",
                    "institution": null
                }
            ],
            "career": [
                {
                    "position": "eng",
                    "years": {
                        "start_year": null,
                        "end_year": null
                    },
                    "organization": "Gbgs stadsteat"
                }
            ],
            "family": {
                "spouse": "Lisskulla Jobs",
                "marriage_year": "1931",
                "children": []
            }
        },
        "3": {
            "full_name": "CARL ARNE A BERGLUND",
            "location": "Kalmar",
            "occupation": "tandläkare",
            "birth_details": {
                "date": "21/05/1927",
                "place": "Upps",
                "parents": "tandl Hjalmar B o Stina Sandberg"
            },
            "education": [
                {
                    "degree": "Stud:ex",
                    "year": "1946",
                    "institution": "Kalmar"
                },
                {
                    "degree": "tandl :ex",
                    "year": "1959",
                    "institution": "Malmö"
                }
            ],
            "career": [
                {
                    "position": "tandl folktandv",
                    "years": {
                        "start_year": 1959,
                        "end_year": null
                    },
                    "organization": "Östersund"
                },
                {
                    "position": "priv :prakt",
                    "years": {
                        "start_year": 1959,
                        "end_year": null
                    },
                    "organization": "Kalmar"
                }
            ],
            "family": {
                "spouse": null,
                "marriage_year": null,
                "children": []
            }
        },
        "4": {
            "full_name": "ELOF U BERGLUND",
            "location": "Gbg",
            "occupation": "kapten, direktör",
            "birth_details": {
                "date": "13/8/1917",
                "place": "Gbg",
                "parents": "skeppsred C A B o Beda Andersson"
            },
            "education": [],
            "career": [
                {
                    "position": "ch",
                    "years": {
                        "start_year": 1947,
                        "end_year": 1957
                    },
                    "organization": "ab Strannes konserver"
                },
                {
                    "position": "verkst dir",
                    "years": {
                        "start_year": 1957,
                        "end_year": null
                    },
                    "organization": "ab Ström skeppsfourne-ring"
                }
            ],
            "family": {
                "spouse": "Britt Kyllerfeldt",
                "marriage_year": "1952",
                "children": [
                    {
                        "name": "Jonas",
                        "birth_year": "1955"
                    },
                    {
                        "name": "Marie",
                        "birth_year": "1963"
                    },
                    {
                        "name": "Klas",
                        "birth_year": "1965"
                    }
                ]
            }
        }
    }
}