{
    "original": "BJERSTAF, A LENNART E,\növerläkare, Vänersborg, f i Nässjö 9/11/12 av\nfabr Carl Nilsson o Rosa Hesselsten.\nStud:ex Lund 32, med kand 36 o med\nlic Upps 43, underläk Finspångs las 43,\nkir avd Halmstads las 44, Filipstads las\n44-48, med avd Vänersborgs las 49-51,\nl:e underläk där 51-55, 2:e stadsläk\nVänersborg sed 55, överläk internmed o\npersonalsjukv Restads sjh sed 59.\nGift 39 m Vera Ohlén f 16. - Barn: Lars\nLennart f 40, Eva Margareta f 45, Ulf\nLennart f 47.\n\nBJERSTRÖM, YNGVE T,\nbankdirektör, fd borgmästare, Jönköping, f i\nEksjö 24/7/02 av handl August B o\nAlbertina Tillberg.\n\nJur kand Uppsala 28, tingstjg 28-30, eo\nnot Sthlms rådh :rätt 31, omb :man\ndrät-selkamm Gävle 33-39, magistr:rådm 36,\nciv:rådm 48, borgm Gävle 53-59, verkst\ndir Smålands bk sed 59. - Auditör\n39-43, krigsdom 43-48, sekr Stadsfullm\n40-53, ordf Uplandsbkns avd :kont 44-59,\nbyggn:ndn 53-59, v ordf barnav:ndn\n43-59, insp folksk:sem Gävle 46-59, ordf\npoliskoll Gävle 53-59, led kyrkomöten\n57, 58. - Styr:led Jönkpgs l\nhembygds-förb, v ordf dess trafiksäkerh:förb.\n-Utm: RNO, Gävle stads ftJM. -\nHobby: golf.\n\nGift 34 m Elsa Hahr f 06, dtr t prof\nAugust H o Elisabeth Larsson. - Barn:\nEva f 36, Bengt f 39, Sten f 43, Ingrid\nf 46.\n\nBJUGGREN, STEN O A, överläkare,\n\nVärnamo, f i Karlsborg, Skarab l, 21/1/\n\n05 av överste Erik B o Ketty Elisen.\nStud:ex Sthlm 24, med kand 27 o med\nlic Sthlm 31, öl aman:- p\nunderläk:för-ordn med avd Sthlm o Östersund 32-43,\ntf överläk Bodens garn :sjh 44, underläk\no bitr överläk S:t Görans sjh 45,\növerläk med avd o styresman Värnamo las\nsed 49. - Bat:läk flk res 37-54. - Skr om\nmåg-, hjärt- o blodsjukd samt idr:med.\n-Utm: RNO.\n\nGift 33 m Britta Maijström f 08, dtr t\növ:löjtn Wilhelm M o Tyra Trägårdh.\n-Barn: Elisabet f 33, Margareta f 35,\nMagnus f 39, Katarina f 45.\n",
    "structured": {
        "0": {
            "full_name": "Lennart E Bjerstaf",
            "location": "Vänersborg",
            "occupation": "överläkare",
            "birth_details": {
                "date": "09/11/1912",
                "place": "Nässjö",
                "parents": "fabr Carl Nilsson o Rosa Hesselsten"
            },
            "education": [
                {
                    "degree": "Stud",
                    "year": "1932",
                    "institution": "Lund"
                },
                {
                    "degree": "med kand",
                    "year": "1936",
                    "institution": "NULL"
                },
                {
                    "degree": "med lic",
                    "year": "1943",
                    "institution": "Upps"
                }
            ],
            "career": [
                {
                    "position": "underläk Finspångs las",
                    "years": {
                        "start_year": 1943,
                        "end_year": 1943
                    },
                    "organization": "NULL"
                },
                {
                    "position": "kir avd Halmstads las",
                    "years": {
                        "start_year": 1944,
                        "end_year": 1944
                    },
                    "organization": "NULL"
                },
                {
                    "position": "Filipstads las",
                    "years": {
                        "start_year": 1944,
                        "end_year": 1948
                    },
                    "organization": "NULL"
                },
                {
                    "position": "med avd Vänersborgs las",
                    "years": {
                        "start_year": 1949,
                        "end_year": 1951
                    },
                    "organization": "NULL"
                },
                {
                    "position": "l:e underläk",
                    "years": {
                        "start_year": 1951,
                        "end_year": 1955
                    },
                    "organization": "Vänersborg"
                },
                {
                    "position": "2:e stadsläk",
                    "years": {
                        "start_year": 1955,
                        "end_year": "NULL"
                    },
                    "organization": "Vänersborg"
                },
                {
                    "position": "överläk internmed o personalsjukv Restads sjh",
                    "years": {
                        "start_year": 1959,
                        "end_year": "NULL"
                    },
                    "organization": "Restads sjh"
                }
            ],
            "family": {
                "spouse": "Vera Ohlén",
                "marriage_year": "1939",
                "children": [
                    {
                        "name": "Lars Lennart",
                        "birth_year": "1940"
                    },
                    {
                        "name": "Eva Margareta",
                        "birth_year": "1945"
                    },
                    {
                        "name": "Ulf Lennart",
                        "birth_year": "1947"
                    }
                ]
            }
        },
        "1": {
            "full_name": "Yngve T Bjerström",
            "location": "Jönköping",
            "occupation": "bankdirektör, fd borgmästare",
            "birth_details": {
                "date": "24/07/1902",
                "place": "Eksjö",
                "parents": "handl August B o Albertina Tillberg"
            },
            "education": [
                {
                    "degree": "Jur kand",
                    "year": "1928",
                    "institution": "Uppsala"
                }
            ],
            "career": [
                {
                    "position": "eo not Sthlms rådh :rätt",
                    "years": {
                        "start_year": 1931,
                        "end_year": "NULL"
                    },
                    "organization": "Sthlms rådh :rätt"
                },
                {
                    "position": "verkst dir Smålands bk",
                    "years": {
                        "start_year": 1959,
                        "end_year": "NULL"
                    },
                    "organization": "Smålands bk"
                }
            ],
            "family": {
                "spouse": "Elsa Hahr",
                "marriage_year": "1934",
                "children": [
                    {
                        "name": "Eva",
                        "birth_year": "1936"
                    },
                    {
                        "name": "Bengt",
                        "birth_year": "1939"
                    },
                    {
                        "name": "Sten",
                        "birth_year": "1943"
                    },
                    {
                        "name": "Ingrid",
                        "birth_year": "1946"
                    }
                ]
            },
            "hobbies": [
                "golf"
            ]
        },
        "2": {
            "full_name": "Sten O A Bjuggren",
            "location": "Värnamo",
            "occupation": "överläkare",
            "birth_details": {
                "date": "21/01/1905",
                "place": "Karlsborg, Skarab l",
                "parents": "överste Erik B o Ketty Elisen"
            },
            "education": [
                {
                    "degree": "Stud",
                    "year": "1924",
                    "institution": "Sthlm"
                },
                {
                    "degree": "med kand",
                    "year": "1927",
                    "institution": "NULL"
                },
                {
                    "degree": "med lic",
                    "year": "1931",
                    "institution": "Sthlm"
                }
            ],
            "career": [
                {
                    "position": "tf överläk Bodens garn :sjh",
                    "years": {
                        "start_year": 1944,
                        "end_year": 1945
                    },
                    "organization": "Bodens garn :sjh"
                },
                {
                    "position": "överläk med avd o styresman Värnamo las",
                    "years": {
                        "start_year": 1949,
                        "end_year": "NULL"
                    },
                    "organization": "Värnamo las"
                }
            ],
            "family": {
                "spouse": "Britta Maijström",
                "marriage_year": "1933",
                "children": [
                    {
                        "name": "Elisabet",
                        "birth_year": "1933"
                    },
                    {
                        "name": "Margareta",
                        "birth_year": "1935"
                    },
                    {
                        "name": "Magnus",
                        "birth_year": "1939"
                    },
                    {
                        "name": "Katarina",
                        "birth_year": "1945"
                    }
                ]
            }
        }
    }
}