{
    "original": "BJERNED, GÖSTA (GUST) N,\nrevisor, fd bankkamrer, Trollhättan, f i\nPiteå 17/11/91 av byggm G A Larson\no Maria Jansson.\n\nHdlssk Kristinehamn 05, div\nutbildn:-kurser; anst Werml ensk bk 05, kamr där\n23 o rev 32, kamr o styr :led Gbgs\nhdls-bk 36-49, kamr, kont:förest o styr:led\nSkand bkn 49-52, rev o förest Bjerneds\nrev:byrås filial Trollhättan sed 52. - Tid\nled ett antal komm ndr o styr. - Medl\nOdd Fellow, TempelrO. - Utm: trafik-,\nSkytte- o försäkringsutm. - Hobby:\nfilateli.\n\nGift 16 m Mimmie Rendahl f 93, dtr t\nErnst R o Josefina Frisk. - Barn: Bengt\nf 18, Hjördis f 21, Arnold f 24.\n\nBJERNEKULL, BO A G, kapten,\nNorrköping, f i Hbg 4/4/20 av dir Eugen\nB o Edit Engenfeldt.\nStud:ex Sthlm 42, res:off:ex FV 45,\noff:-ex 49, kapt F 8 res 55; flygstyrman SAS\n46-48, off FV 49-54, provflyg Saab\n55-59, avd :ch där sed 60. - Medl Rotary.\n-Hobby: ridning.\n\nGift 47 m Eva Leijonhufvud f 25, dtr t\njägm Valter L o Anna Dyberg. - Barn:\nUlf f 48, Gunilla f 50, Claes f 52,\nBirgitta f 59.\n\nBJERNER, NILS I, chefsåklagare,\nGbg, f i Färlöv, Kristianst l, 12/2/10 av\nlantbr Nils-Emil B o Sigrid Bjerner.\nStud:ex Gävle 29, jur kand Upps 33,\ntingstjg Gästrikl v o Kalix doms :or\n33-36, polisch :kurs 41-42; landsfogdeass, tf\nlandsfogde, tf polismäst o tf stadsfiskal\nöl län 37-44, stadsfisk Gbg 46 (eo 44),\nchefsåkl där sed 65. - Utm: RNO.\n-Hobbies: skidåkning, fjällvandringar.\nGift 40 m Gerd Dyster-Aas f 18, dtr t\ndir Hans D-A o Ruth Bjerner. - Barn:\nLars f 41, Ove f 43, Svante f 50.\n\nBJERRE, STIG T, stadsnotarie,\nKalmar, f i Landskrona 24/5/11 av\npostmast Fabian B o Hulda Nilsson.\nStud:ex Kalmar 29, jur kand Lund 40,\ntingstjg 40-42, tjg å adv:byrå 43, e\nlänsnot 44, stadsnot Kalmar sed 48. -\nHobbies: silversmide, arkivforskning,\nsportdykning.\n\nGift 42 m Ingrid Beding f 14, dtr t\nträ v :handl Edvard Bengtsén o Gurli\nRoos. - Barn: Bo f 43, Jörgen f 47.\n\n",
    "structured": {
        "1": {
            "full_name": "Gösta (Gust) N Bjerned",
            "location": "Trollhättan",
            "occupation": "revisor, fd bankkamrer",
            "birth_details": {
                "date": "17/11/1891",
                "place": "Piteå",
                "parents": "byggm G A Larson o Maria Jansson"
            },
            "education": [
                {
                    "degree": "Hdlssk",
                    "year": "1905",
                    "institution": "Kristinehamn"
                }
            ],
            "career": [
                {
                    "position": "kamr",
                    "years": {
                        "start_year": 1923,
                        "end_year": 1932
                    },
                    "organization": "Werml ensk bk"
                },
                {
                    "position": "kamr o styr :led",
                    "years": {
                        "start_year": 1936,
                        "end_year": 1949
                    },
                    "organization": "Gbgs hdls-bk"
                },
                {
                    "position": "kamr, kont:förest o styr:led",
                    "years": {
                        "start_year": 1949,
                        "end_year": 1952
                    },
                    "organization": "Skand bkn"
                },
                {
                    "position": "rev o förest",
                    "years": {
                        "start_year": 1952
                    },
                    "organization": "Bjerneds rev:byrås filial Trollhättan"
                }
            ],
            "family": {
                "spouse": "Mimmie Rendahl",
                "marriage_year": "1916",
                "children": [
                    {
                        "name": "Bengt",
                        "birth_year": "1918"
                    },
                    {
                        "name": "Hjördis",
                        "birth_year": "1921"
                    },
                    {
                        "name": "Arnold",
                        "birth_year": "1924"
                    }
                ]
            },
            "hobbies": [
                "filateli"
            ]
        },
        "2": {
            "full_name": "Bo A G Bjernekull",
            "location": "Norrköping",
            "occupation": "kapten",
            "birth_details": {
                "date": "4/4/1920",
                "place": "Hbg",
                "parents": "dir Eugen B o Edit Engenfeldt"
            },
            "education": [
                {
                    "degree": "Stud:ex",
                    "year": "1942",
                    "institution": "Sthlm"
                },
                {
                    "degree": "res:off:ex",
                    "year": "1945",
                    "institution": "FV"
                },
                {
                    "degree": "off:-ex",
                    "year": "1949"
                }
            ],
            "career": [
                {
                    "position": "kapt F 8",
                    "years": {
                        "start_year": 1955
                    }
                },
                {
                    "position": "flygstyrman",
                    "years": {
                        "start_year": 1946,
                        "end_year": 1948
                    },
                    "organization": "SAS"
                },
                {
                    "position": "provflyg",
                    "years": {
                        "start_year": 1955,
                        "end_year": 1959
                    },
                    "organization": "Saab"
                },
                {
                    "position": "avd :ch",
                    "years": {
                        "start_year": 1960
                    }
                }
            ],
            "family": {
                "spouse": "Eva Leijonhufvud",
                "marriage_year": "1947",
                "children": [
                    {
                        "name": "Ulf",
                        "birth_year": "1948"
                    },
                    {
                        "name": "Gunilla",
                        "birth_year": "1950"
                    },
                    {
                        "name": "Claes",
                        "birth_year": "1952"
                    },
                    {
                        "name": "Birgitta",
                        "birth_year": "1959"
                    }
                ]
            },
            "hobbies": [
                "ridning"
            ]
        },
        "3": {
            "full_name": "Nils I Bjerner",
            "location": "Gbg",
            "occupation": "chefsåklagare",
            "birth_details": {
                "date": "12/2/1910",
                "place": "Färlöv, Kristianst l",
                "parents": "lantbr Nils-Emil B o Sigrid Bjerner"
            },
            "education": [
                {
                    "degree": "Stud:ex",
                    "year": "1929",
                    "institution": "Gävle"
                },
                {
                    "degree": "jur kand",
                    "year": "1933",
                    "institution": "Upps"
                },
                {
                    "degree": "polisch :kurs",
                    "year": "1941-1942"
                }
            ],
            "career": [
                {
                    "position": "tingsjg",
                    "years": {
                        "start_year": 1933,
                        "end_year": 1936
                    },
                    "organization": "Gästrikl v o Kalix doms :or"
                },
                {
                    "position": "landsfogdeass, tf landsfogde, tf polismäst o tf stadsfiskal",
                    "years": {
                        "start_year": 1937,
                        "end_year": 1944
                    },
                    "organization": "öl län"
                },
                {
                    "position": "stadsfisk",
                    "years": {
                        "start_year": 1946
                    },
                    "organization": "Gbg"
                },
                {
                    "position": "chefsåkl",
                    "years": {
                        "start_year": 1965
                    }
                }
            ],
            "family": {
                "spouse": "Gerd Dyster-Aas",
                "marriage_year": "1940",
                "children": [
                    {
                        "name": "Lars",
                        "birth_year": "1941"
                    },
                    {
                        "name": "Ove",
                        "birth_year": "1943"
                    },
                    {
                        "name": "Svante",
                        "birth_year": "1950"
                    }
                ]
            },
            "hobbies": [
                "skidåkning",
                "fjällvandringar"
            ]
        },
        "4": {
            "full_name": "Stig T Bjerre",
            "location": "Kalmar",
            "occupation": "stadsnotarie",
            "birth_details": {
                "date": "24/5/1911",
                "place": "Landskrona",
                "parents": "postmast Fabian B o Hulda Nilsson"
            },
            "education": [
                {
                    "degree": "Stud:ex",
                    "year": "1929",
                    "institution": "Kalmar"
                },
                {
                    "degree": "jur kand",
                    "year": "1940",
                    "institution": "Lund"
                }
            ],
            "career": [
                {
                    "position": "tingstjg",
                    "years": {
                        "start_year": 1940,
                        "end_year": 1942
                    }
                },
                {
                    "position": "e länsnot",
                    "years": {
                        "start_year": 1944
                    }
                },
                {
                    "position": "stadsnot",
                    "years": {
                        "start_year": 1948
                    },
                    "organization": "Kalmar"
                }
            ],
            "family": {
                "spouse": "Ingrid Beding",
                "marriage_year": "1942",
                "children": [
                    {
                        "name": "Bo",
                        "birth_year": "1943"
                    },
                    {
                        "name": "Jörgen",
                        "birth_year": "1947"
                    }
                ]
            },
            "hobbies": [
                "silversmide",
                "arkivforskning",
                "sportdykning"
            ]
        }
    }
}