{
    "original": "BITTMANN, FRIEDRICH,\nprovinsialläkare, Tranemo, f i Wien 15/2/14 av\nkvarnäg Anton B o Theresia Scipal.\nLäk:ex Wien 39, KMts tillst att i Sv:e\nutöva läkekonsten 56, sv medb 57,\nmil:-läk tyska armén o rysk fångenskap\n39-47, underläk öl las Wien 48-51, underläk\nkir avd Uddevalla las 52, Lysekils las\n53, l:e underläk där 54-57, bitr prov:läk\nL:a Edets distr 58, prov:läk Tranemo\ndistr sed 60.\n\nGift 55 m Gabrielle Löning f 31, dtr t\nköpm Alfons L o Alma Kollern. - Barn:\nSusanne f 56, Thomas f 59, Werner\nf 60.\n\nBIÖRNERUD, L TAGE N, direktör,\nGbg, f i Landvetter, Gbgs o Bohus l,\n13/8/08 av stat :insp Carl O Olsson o\nSelma Olsson.\n\nStud:ex Borås 28, GbgHdlI 30, korresp\nab C Fr Waern &amp; Co Gbg 30, avd :ch\nO Chr Olsen &amp; Co ab 34, prokurist\nfirma Nils Troedsson &amp; Co 40, dir o\nstyr :suppl Nils Troedsson Paper Co ab\n44-52, dir o ag Magnolia Paper\nCom-pany Tage Biörnerud k/b o Mango\nProducts Co Ltd ab sed 52. - Vidsträckta\nresor i Nord-, Central- o Sydamerika.\n-Medl Travellers’ club Gbg. - Hobbies:\nfilateli, fruktodling.\n\nGift 35 m Elsa Biörnerud. - Barn: Ingela\nf 38, Ylva f 43, Lars f 44.\n\nBJARNEGÅRD, GUSTAF B,\nkyrkoherde, Läckeby, f i Kalmar 9/5/07 av\nverkmäst Carl Johansson o Bertha\nLindell.\n\nStud:ex 26, teol kand Lund 32, kommin\nSöderåkra 37, kyrkoh Åby sed 52.\n-Hobby: kyrkomusik.\nGift 35 m Anna-Greta Sjöblom fil, dtr\nt kontr :prost Ernst S o Ester L Jungner.\n- Barn: Lärs-Ingmar f 36, Viveka f 39,\nStefan f 43, Göran f 47.\n\n",
    "structured": {
        "0": {
            "full_name": "Friedrich Bittmann",
            "location": "Tranemo",
            "occupation": "provinsialläkare",
            "birth_details": {
                "date": "15/02/1914",
                "place": "Wien"
            },
            "education": [
                {
                    "degree": "Läk:ex",
                    "year": "1939",
                    "institution": "Wien"
                }
            ],
            "career": [
                {
                    "position": "mil:-läk tyska armén",
                    "years": {
                        "start_year": 1939,
                        "end_year": 1947
                    },
                    "organization": "tyska armén"
                },
                {
                    "position": "russisk fångenskap",
                    "years": {
                        "start_year": 1939,
                        "end_year": 1947
                    },
                    "organization": "rysk fångenskap"
                },
                {
                    "position": "underläk",
                    "years": {
                        "start_year": 1948,
                        "end_year": 1951
                    },
                    "organization": "öl las Wien"
                },
                {
                    "position": "underläk",
                    "years": {
                        "start_year": 1952,
                        "end_year": 1953
                    },
                    "organization": "kir avd Uddevalla las"
                },
                {
                    "position": "l:e underläk",
                    "years": {
                        "start_year": 1953,
                        "end_year": 1957
                    },
                    "organization": "Lysekils las"
                },
                {
                    "position": "bitr prov:läk",
                    "years": {
                        "start_year": 1958,
                        "end_year": 1960
                    },
                    "organization": "L:a Edets distr"
                },
                {
                    "position": "prov:läk",
                    "years": {
                        "start_year": 1960,
                        "end_year": null
                    },
                    "organization": "Tranemo distr"
                }
            ],
            "family": {
                "spouse": "Gabrielle Löning",
                "marriage_year": "1955",
                "children": [
                    {
                        "name": "Susanne",
                        "birth_year": "1956"
                    },
                    {
                        "name": "Thomas",
                        "birth_year": "1959"
                    },
                    {
                        "name": "Werner",
                        "birth_year": "1960"
                    }
                ]
            }
        },
        "1": {
            "full_name": "L Tage N Biörnerud",
            "location": "Gbg",
            "occupation": "direktör",
            "birth_details": {
                "date": "13/08/1908",
                "place": "Landvetter, Gbgs o Bohus l"
            },
            "education": [
                {
                    "degree": "Stud:ex",
                    "year": "1928",
                    "institution": "Borås"
                },
                {
                    "degree": "GbgHdlI",
                    "year": "1930",
                    "institution": "GbgHdlI"
                }
            ],
            "career": [
                {
                    "position": "prokurist",
                    "years": {
                        "start_year": 1940,
                        "end_year": null
                    },
                    "organization": "firma Nils Troedsson & Co"
                }
            ],
            "family": {
                "spouse": "Elsa Biörnerud",
                "marriage_year": "1935",
                "children": [
                    {
                        "name": "Ingela",
                        "birth_year": "1938"
                    },
                    {
                        "name": "Ylva",
                        "birth_year": "1943"
                    },
                    {
                        "name": "Lars",
                        "birth_year": "1944"
                    }
                ]
            },
            "hobbies": [
                "filateli",
                "fruktodling"
            ]
        },
        "2": {
            "full_name": "Gustaf B Bjarnegård",
            "location": "Läckeby",
            "occupation": "kyrkoherde",
            "birth_details": {
                "date": "09/05/1907",
                "place": "Kalmar"
            },
            "education": [
                {
                    "degree": "Stud:ex",
                    "year": "1926",
                    "institution": "Kalmar"
                },
                {
                    "degree": "teol kand",
                    "year": "1932",
                    "institution": "Lund"
                }
            ],
            "career": [
                {
                    "position": "kommin",
                    "years": {
                        "start_year": 1937,
                        "end_year": 1952
                    },
                    "organization": "Söderåkra"
                },
                {
                    "position": "kyrkoh",
                    "years": {
                        "start_year": 1952,
                        "end_year": null
                    },
                    "organization": "Åby"
                }
            ],
            "family": {
                "spouse": "Anna-Greta Sjöblom",
                "marriage_year": "1935",
                "children": [
                    {
                        "name": "Lärs-Ingmar",
                        "birth_year": "1936"
                    },
                    {
                        "name": "Viveka",
                        "birth_year": "1939"
                    },
                    {
                        "name": "Stefan",
                        "birth_year": "1943"
                    },
                    {
                        "name": "Göran",
                        "birth_year": "1947"
                    }
                ]
            },
            "hobbies": [
                "kyrkomusik"
            ]
        }
    }
}