{
    "original": "BERNHARDT, C CHRISTER B,\növerläkare, Axvall, f i Sthlm 31/12/08  av\nmajor Bertil B o Inez Bohlin.\nStud:ex Strängnäs 27, med kand 30 o\n\nmed lic Sthlm 35, underläk Styrsö\nkust-sanat 36, Österåsens sanat 39 o 41-44;\nÅre kuranst 40, Kungshults sanat 44,\nLunds las 48, med avd Hässleholms las\n49, tf överläk Spenshults sanat 50, bitr\növerläk Sollidens sanat Östersund 52,\növerläk o centraldisp:läk St Ekebergs sjh\nsed 63. - Medl Sv läk:sällsk 38, Soc\nFranc de Pathol respir 56. - Medl\nRo-tary. - Hobbies: filateli, golf, schack.\nGift 39 m Märtha Bilen f 06, dtr t\nträ-varuh Carl B o Hulda Wulcan. - Barn:\nAnders f 41, Fredrik f 43, Eva f 51.\n\nBERNHARDTZ, BERNDT K S,\ningenjör, Mölndal, f i Karlskrona 4/3/24\nav fabr Gösta B o Eva Antonsson.\nIng:ex GTI 43, deläg ab Sörgårdens\nrör-läggeri Mölndal 44, ch där sed 54.\n-Ordf Mölndals ind:- o hantv:fören sed\n63, led Bohusläns hantv:distr sed 64,\nstyr :led gbgsavd Rörledn:firm riksförb\nsed 59, led trafiksäk:komm sed 60.\n-Medl Odd Fellow, Lions Club.\nGift 49 m Ella Hansson, dtr t Edvin H\no Elsa Hallberg. - Barn: Ann f 51,\nThomas f 54.\n\nBERNHULT, BERTIL Y L, disponent,\nAlingsås, f i Öttum, Skarab l, 5/8/09 av\ngodsäg Alfred Johansson o Amanda\nEngblad.\n\nAnst Lindahl &amp; Nermark ab Alingsås\n37, försäljn:ch där sed 45  (styr:led).\n-Medl Odd Fellow. - Hobby: fiske.\nGift   39   m   Sigrid   Swensson.   -   Barn:\nIngemar f 43.\n\nBERNLING, OLLE G, advokat,\nVänersborg, f i Töreboda 26/6/22 av köpm\nKarl B o Gunhild Larson.\nStud:ex Linkpg 42, jur kand StHS 49,\neg jur byrå Töreboda 50, anst Englunds\nadv :byrå Trollhättan 54, eg ad v\n:verksamh Vänersborg sed 62. - LSA 56.\n-Medl FrimO, Lions Club.\nGift 56 rn sjuksköt Teresia Josefsson\nf 25, dtr t lantbr G J o h h. - Barn:\nKarl f 57, Joakim f 60.\n\n",
    "structured": {
        "0": {
            "full_name": "C Christer B Bernhardt",
            "location": "Axvall",
            "occupation": "överläkare",
            "birth_details": {
                "date": "31/12/1908",
                "place": "Stockholm",
                "parents": "major Bertil B o Inez Bohlin"
            },
            "education": [
                {
                    "degree": "Stud",
                    "year": "1927",
                    "institution": "Strängnäs"
                },
                {
                    "degree": "med kand",
                    "year": "1930",
                    "institution": "NULL"
                },
                {
                    "degree": "med lic",
                    "year": "1935",
                    "institution": "Stockholm"
                }
            ],
            "career": [
                {
                    "position": "underläk",
                    "years": {
                        "start_year": 1936,
                        "end_year": 1936
                    },
                    "organization": "Styrsö kust-sanat"
                },
                {
                    "position": "överläk",
                    "years": {
                        "start_year": 1963,
                        "end_year": 1963
                    },
                    "organization": "St Ekebergs sjh"
                }
            ],
            "family": {
                "spouse": "Märtha Bilen",
                "marriage_year": "1939",
                "children": [
                    {
                        "name": "Anders",
                        "birth_year": "1941"
                    },
                    {
                        "name": "Fredrik",
                        "birth_year": "1943"
                    },
                    {
                        "name": "Eva",
                        "birth_year": "1951"
                    }
                ]
            },
            "hobbies": [
                "filateli",
                "golf",
                "schack"
            ]
        },
        "1": {
            "full_name": "Berndt K S Bernhardtz",
            "location": "Mölndal",
            "occupation": "ingenjör",
            "birth_details": {
                "date": "4/3/1924",
                "place": "Karlskrona",
                "parents": "fabr Gösta B o Eva Antonsson"
            },
            "education": [
                {
                    "degree": "Ing",
                    "year": "1943",
                    "institution": "GTI"
                }
            ],
            "career": [
                {
                    "position": "ch",
                    "years": {
                        "start_year": 1954,
                        "end_year": 1954
                    },
                    "organization": "Sörgårdens rör-läggeri Mölndal"
                }
            ],
            "family": {
                "spouse": "Ella Hansson",
                "marriage_year": "1949",
                "children": [
                    {
                        "name": "Ann",
                        "birth_year": "1951"
                    },
                    {
                        "name": "Thomas",
                        "birth_year": "1954"
                    }
                ]
            }
        },
        "2": {
            "full_name": "Bertil Y L Bernhult",
            "location": "Alingsås",
            "occupation": "disponent",
            "birth_details": {
                "date": "5/8/1909",
                "place": "Öttum, Skarab l",
                "parents": "godsäg Alfred Johansson o Amanda Engblad"
            },
            "career": [
                {
                    "position": "försäljn:ch",
                    "years": {
                        "start_year": 1945,
                        "end_year": 1945
                    },
                    "organization": "Lindahl & Nermark ab Alingsås"
                }
            ],
            "family": {
                "spouse": "Sigrid Swensson",
                "marriage_year": "1939",
                "children": [
                    {
                        "name": "Ingemar",
                        "birth_year": "1943"
                    }
                ]
            },
            "hobbies": [
                "fiske"
            ]
        },
        "3": {
            "full_name": "Olle G Bernling",
            "location": "Vänersborg",
            "occupation": "advokat",
            "birth_details": {
                "date": "26/6/1922",
                "place": "Töreboda",
                "parents": "köpm Karl B o Gunhild Larson"
            },
            "education": [
                {
                    "degree": "Stud",
                    "year": "1942",
                    "institution": "Linkpg"
                },
                {
                    "degree": "jur kand",
                    "year": "1949",
                    "institution": "StHS"
                }
            ],
            "career": [
                {
                    "position": "eg jur byrå",
                    "years": {
                        "start_year": 1950,
                        "end_year": 1950
                    },
                    "organization": "Töreboda"
                },
                {
                    "position": "eg ad v :verksam",
                    "years": {
                        "start_year": 1962,
                        "end_year": 1962
                    },
                    "organization": "Vänersborg"
                }
            ],
            "family": {
                "spouse": "Teresia Josefsson",
                "marriage_year": "1956",
                "children": [
                    {
                        "name": "Karl",
                        "birth_year": "1957"
                    },
                    {
                        "name": "Joakim",
                        "birth_year": "1960"
                    }
                ]
            }
        }
    }
}