{
    "original": "Persson, Per Artur, diretktör,\nFri-■stad, f. 22/4/89 i MoWa, Älvsfb. iL, av\nE. P. o. Emelia Tyrén. G. m. Stina\nSvensson. Barn: Ingrid f. 22, g. m.\ndisp. Daig Rydin, Jonas 24, Ulla 25,\nKerstin 29, stud. — Anst. li. Knut\nEvers &amp; Co. fr. 07, prokuriist där fr.\n31, dir. i A-B Borås Koiksaffär fr. 23,\ni Petersbergs A-B fr. 37, i A-B Wolds\nBoikhand. fr. 37, kamrer i Borås\nKol-imp. A-B. Styr:led. i Fören. Kod- &amp;\nKok’simp. A-B i Gbg, i Skand. Banik.\ni Borås, i A-B Marks Jacquardväfveri\ni Björketorp, Skånska Granit A-B o.\nKürzels Fabr. A-B i Malmö, led. av\nkomm:- o. kyrkofullm. i Fristad samt\nkomm :nd o. kyrkoråd.\n\nPersson, Arvid Petrus,\nläroverksadjunkt, Karlshamn, f. 27/3/93 i Rinkaby,\nÖrebro 1., av Per P. o. Sofia Per&amp;son.\nG. 28 m. Elinda (Ella) Olsson. Barn:\nKarl-Gustav f. 29, Karin 36. — Stud :ex.\ni Lund 15, fri. ikand. 19, fil. mag. 22,\nfik lic. 32, delt. i Genitrailfönb. f.\nnyk-terh : under v. so c. fortb :kurs 31,\nprov-år 32. Förest, f. Asele priv. samsk.\n25-26, f. Sävsjö prakt, sk, 26-27, e.o.\näm-neislär. i Söderköp. 27-32, 33, e. lär. i\nVäxjö 33-34, ord. ämne slår. i Nora 34,\nadjunkt v. samrealsk. i Karls’hamn fr.\n36. E. geolog h. Sv :es geol.\nunder-sökn. somm. o. liöst 20-23. Sikr.:\n(Till-s. m. L. Smith) über d. Hydrolyse d.\nZinnchlorids u. d. Ohlorostannate, Zs.\nf. anorg. u. allg. Chem.\n\nPersson, Ebba Maria, rektor,\nGöte-boTg, f. 20/8/83 i Hälsingborg av Sven\nP. o. Miaria Nilsson. — Ex. v. h.\nlär:-nesem. i St him 04, fjärde avd. 07-08 o.\n12-13. Anst. v. nya elem :sk. i Hälsingb.\n04-12, M. Halls sk. i Gbg 13-38, rektor\ndär 35-38, ord. ämneslär. o. rektor v.\nVasa komm. filicksk. i Gbg sed. 38.\n\nPersson, Ebbe Anders Reinhold,\nbyggnadsingenjör, Linköping, f. 10/7/\n15 i Arrie, Malmöh. 1., av byggm.\nAnders P. o. Joisefina Pettersson. G. 37\nm. Annie Hansson. Barn: Ulla f. 39,\nGöran 41, Elsie 43. — Genomg. Malmö\ntekn. yrkessk. 37. Mätn:m:an f. Malmö\nbyggm ifören. 37-39, ombudsm. o.\nmät-n :man f. Linköp. byggm :föiren. 39-44,\negen firma. Betong- &amp; Byggn :byrån.\nLinköp., sed. 44. Medl. av Linköp.\nbyggmäst:fören. sed. 44.\n\n",
    "structured": {
        "1": {
            "full_name": "Persson, Per Artur",
            "location": "Fri-■stad",
            "occupation": "direktör",
            "birth_details": {
                "date": "22/04/1889",
                "place": "MoWa, Älvsfb. iL",
                "parents": "E. P. o. Emelia Tyrén"
            },
            "education": [
                {
                    "degree": "Stud",
                    "year": "07",
                    "institution": "Knut Evers & Co."
                },
                {
                    "degree": "Prokuriist",
                    "year": "31",
                    "institution": "Knut Evers & Co."
                },
                {
                    "degree": "Direktör",
                    "year": "23",
                    "institution": "A-B Borås Koiksaffär"
                }
            ],
            "career": [
                {
                    "position": "dir. i A-B Borås Koiksaffär",
                    "years": {
                        "start_year": 1923,
                        "end_year": 1931
                    },
                    "organization": "A-B Borås Koiksaffär"
                },
                {
                    "position": "dir. i A-B Borås Koiksaffär",
                    "years": {
                        "start_year": 1937,
                        "end_year": null
                    },
                    "organization": "i A-B Wolds Boikhand."
                },
                {
                    "position": "dir. i A-B Borås Koiksaffär",
                    "years": {
                        "start_year": 1937,
                        "end_year": null
                    },
                    "organization": "Borås Kol-imp. A-B"
                }
            ],
            "family": {
                "spouse": "Stina Svensson",
                "marriage_year": null,
                "children": [
                    {
                        "name": "Ingrid",
                        "birth_year": "22"
                    },
                    {
                        "name": "Jonas",
                        "birth_year": "24"
                    },
                    {
                        "name": "Ulla",
                        "birth_year": "25"
                    },
                    {
                        "name": "Kerstin",
                        "birth_year": "29"
                    }
                ]
            }
        },
        "2": {
            "full_name": "Persson, Arvid Petrus",
            "location": "Karlshamn",
            "occupation": "läroverksadjunkt",
            "birth_details": {
                "date": "27/03/1893",
                "place": "Rinkaby, Örebro 1.",
                "parents": "Per P. o. Sofia Per&amp;son"
            },
            "education": [
                {
                    "degree": "Stud :ex.",
                    "year": "15",
                    "institution": "Lund"
                },
                {
                    "degree": "fri. ikand.",
                    "year": "19",
                    "institution": null
                },
                {
                    "degree": "fil. mag.",
                    "year": "22",
                    "institution": null
                },
                {
                    "degree": "fik lic.",
                    "year": "32",
                    "institution": null
                }
            ],
            "career": [
                {
                    "position": "adjunkt v. samrealsk.",
                    "years": {
                        "start_year": 1936,
                        "end_year": null
                    },
                    "organization": "Karls'hamn"
                }
            ],
            "family": {
                "spouse": "Elinda (Ella) Olsson",
                "marriage_year": "28",
                "children": [
                    {
                        "name": "Karl-Gustav",
                        "birth_year": "29"
                    },
                    {
                        "name": "Karin",
                        "birth_year": "36"
                    }
                ]
            }
        },
        "3": {
            "full_name": "Persson, Ebba Maria",
            "location": "Göte-boTg",
            "occupation": "rektor",
            "birth_details": {
                "date": "20/08/1883",
                "place": "Hälsingborg",
                "parents": "Sven P. o. Miaria Nilsson"
            },
            "education": [
                {
                    "degree": "helm :nesem.",
                    "year": "04",
                    "institution": "St him"
                }
            ],
            "career": [
                {
                    "position": "rektor där",
                    "years": {
                        "start_year": 1935,
                        "end_year": 1938
                    },
                    "organization": "M. Halls sk. i Gbg"
                }
            ],
            "family": {
                "spouse": null,
                "marriage_year": null,
                "children": null
            }
        },
        "4": {
            "full_name": "Persson, Ebbe Anders Reinhold",
            "location": "Linköping",
            "occupation": "byggnadsingenjör",
            "birth_details": {
                "date": "10/07/1915",
                "place": "Arrie, Malmöh. 1.",
                "parents": "byggm. Anders P. o. Joisefina Pettersson"
            },
            "education": [
                {
                    "degree": "Mätn:m:an",
                    "year": "37",
                    "institution": "Malmö tekn. yrkessk."
                }
            ],
            "career": [
                {
                    "position": "mätn :man",
                    "years": {
                        "start_year": 1939,
                        "end_year": 1944
                    },
                    "organization": "Linköp. byggm :föiren."
                }
            ],
            "family": {
                "spouse": "Annie Hansson",
                "marriage_year": "37",
                "children": [
                    {
                        "name": "Ulla",
                        "birth_year": "39"
                    },
                    {
                        "name": "Göran",
                        "birth_year": "41"
                    },
                    {
                        "name": "Elsie",
                        "birth_year": "43"
                    }
                ]
            }
        }
    }
}