{
    "original": "RAHM, S LENNART, professor,\nBromma, f i Bollnäs 5/7/18 av\nskolkassor Hans R o Ida Larsson.\nStud:ex Malmö 37, KTH 42, tekn lic\n50, tekn dr 53, ing jvstyr 43-45, l:e ass\no v lab:ch vatt :byggn :lab KTH 46, doc\no tf prof KTH 53-60, prof i\nvattenbyggnad CTH sed 60. - Huv:lär stat\nMeteorol:- hydrografiska inst, konsult\nab Sv kraftkontoret Sthlm sed 54.\n-Medl SvTF, Sv betongfören, Sv\nvatten-kraftfören, Sv geotekn fören, Fören f\ninre vattenvägar, Internat Ass for\nHyd-raulic Research 48, Amer Soc Civil\nEng (New York). - Skr:\nFriktionsförluster i oinklädda bergtunnlar (50),\nFlow Problems with respect to intakes\nand tunnels of Swedish hydro-electric\npower plants, Acta Polytechnica, 131\n(drsavh 53), Friction losses in Swedish\nrock tunnels, Water Power (58),\ntidskr-o tidn:art m m.\n\nGift 45 m Ann-Stin Brodén f 17, dtr t\nLeander B o Ida Henriksson. - Barn:\nChristina f 46, Torbjörn f 48, Maria f 55.\n\nRAHM, PER-WILHELM,\nkammarmusiker, Stuvsta, f i Nykpg 23/12/24\nav skräddarmäst Oskar R o\nWilhelmina Pettersson.\n\nStud MA 45-52, pianostämmareex 52.\n-Mil:musiker I 10 Strängnäs 40-50,\nfa-gottist hovkapellet, l:e fagottist sed 52,\nlär MA sed 58. - Utm: MAjeton.\nGift 48 m Anna-Greta Ståbis, dtr t\nbyggmäst Anders S o Emma S. - Barn:\nBirgitta f 48, Per-Olov f 50, Solveig\nf 52, Kerstin f 58.\n\nRAHMQVIST, C A SIGURD, fd\ngeneralmajor, Sthlm, f i Kärnbo,\nSödermani l, 11/1/87 av slottsbyggmäst August\nR o Rosalie Fagerström.\nStud:ex Nykpg 05, underlöjtn fortifik\n07, löjtn 10, kapt 18, major 30, överste-\n\nlo jtn 34, överste 40, gen :major 45.\n-Ch Ing 2 34-37, fortifik bef Boden\n38-41, insp ing:trupperna 41-46. - Verkst\ndir Hjulisbro ab, Hjulsbro. - Styr:led\nSt Kors fastigh ab. - LKrVA 30.\n-Utm: KSOlkl, RVO, KNS:tOOmstj.\n-Hobby: segling.\n\nGift lim Ingeborg Nilson, dtr t\nbank-dir Jonn N o Agnes During. - Barn:\nTore f 12, Sune f 13, Birgit f 18, Börje\nf 22.\n\n",
    "structured": {
        "0": {
            "full_name": "RAHM, S LENNART",
            "location": "Bromma",
            "occupation": "Professor",
            "birth_details": {
                "date": "05/07/1918",
                "place": "Bollnäs",
                "parents": "skolkassor Hans R o Ida Larsson"
            },
            "education": [
                {
                    "degree": "Stud:ex",
                    "year": "1937",
                    "institution": "Malmö"
                },
                {
                    "degree": "KTH",
                    "year": "1942",
                    "institution": "Kungliga Tekniska Högskolan"
                },
                {
                    "degree": "tekn lic",
                    "year": "1950",
                    "institution": "KTH"
                },
                {
                    "degree": "tekn dr",
                    "year": "1953",
                    "institution": "KTH"
                }
            ],
            "career": [
                {
                    "position": "ing jvstyr",
                    "years": {
                        "start_year": 1943,
                        "end_year": 1945
                    },
                    "organization": "l:e ass o v lab:ch vatt :byggn :lab KTH"
                },
                {
                    "position": "doc o tf prof",
                    "years": {
                        "start_year": 1953,
                        "end_year": 1960
                    },
                    "organization": "KTH"
                },
                {
                    "position": "prof i vattenbyggnad",
                    "years": {
                        "start_year": 1960
                    },
                    "organization": "CTH"
                }
            ],
            "family": {
                "spouse": "Ann-Stin Brodén",
                "marriage_year": "1945",
                "children": [
                    {
                        "name": "Christina",
                        "birth_year": "1946"
                    },
                    {
                        "name": "Torbjörn",
                        "birth_year": "1948"
                    },
                    {
                        "name": "Maria",
                        "birth_year": "1955"
                    }
                ]
            }
        },
        "1": {
            "full_name": "RAHM, PER-WILHELM",
            "location": "Stuvsta",
            "occupation": "Kammarmusiker",
            "birth_details": {
                "date": "23/12/1924",
                "place": "Nyköping",
                "parents": "skräddarmäst Oskar R o Wilhelmina Pettersson"
            },
            "education": [
                {
                    "degree": "Stud MA",
                    "year": "1945-1952"
                },
                {
                    "degree": "pianostämmareex",
                    "year": "1952"
                }
            ],
            "career": [
                {
                    "position": "mil:musiker I 10",
                    "years": {
                        "start_year": 1940,
                        "end_year": 1950
                    },
                    "organization": "Strängnäs"
                },
                {
                    "position": "fagottist hovkapellet",
                    "years": {
                        "start_year": 1952
                    }
                },
                {
                    "position": "l:e fagottist",
                    "years": {
                        "start_year": 1952
                    }
                },
                {
                    "position": "lär MA",
                    "years": {
                        "start_year": 1958
                    }
                }
            ],
            "family": {
                "spouse": "Anna-Greta Ståbis",
                "marriage_year": "1948",
                "children": [
                    {
                        "name": "Birgitta",
                        "birth_year": "1948"
                    },
                    {
                        "name": "Per-Olov",
                        "birth_year": "1950"
                    },
                    {
                        "name": "Solveig",
                        "birth_year": "1952"
                    },
                    {
                        "name": "Kerstin",
                        "birth_year": "1958"
                    }
                ]
            }
        },
        "2": {
            "full_name": "RAHMQVIST, C A SIGURD",
            "location": "Sthlm",
            "occupation": "Fd generalmajor",
            "birth_details": {
                "date": "11/01/1887",
                "place": "Kärnbo, Södermanland",
                "parents": "slottsbyggmäst August R o Rosalie Fagerström"
            },
            "education": [
                {
                    "degree": "Stud:ex",
                    "year": "1905",
                    "institution": "Nyköping"
                }
            ],
            "career": [
                {
                    "position": "underlöjtn fortifik",
                    "years": {
                        "start_year": 1907
                    }
                },
                {
                    "position": "löjtn",
                    "years": {
                        "start_year": 1910
                    }
                },
                {
                    "position": "kapt",
                    "years": {
                        "start_year": 1918
                    }
                },
                {
                    "position": "major",
                    "years": {
                        "start_year": 1930
                    }
                },
                {
                    "position": "överstelöjtn",
                    "years": {
                        "start_year": 1934
                    }
                },
                {
                    "position": "överste",
                    "years": {
                        "start_year": 1940
                    }
                },
                {
                    "position": "gen :major",
                    "years": {
                        "start_year": 1945
                    }
                },
                {
                    "position": "ch Ing 2",
                    "years": {
                        "start_year": 1934,
                        "end_year": 1937
                    }
                },
                {
                    "position": "fortifik bef Boden",
                    "years": {
                        "start_year": 1938,
                        "end_year": 1941
                    }
                },
                {
                    "position": "insp ing:trupperna",
                    "years": {
                        "start_year": 1941,
                        "end_year": 1946
                    }
                },
                {
                    "position": "verkst dir",
                    "organization": "Hjulisbro ab, Hjulsbro"
                }
            ],
            "family": {
                "spouse": "Ingeborg Nilson",
                "marriage_year": "NULL",
                "children": [
                    {
                        "name": "Tore",
                        "birth_year": "1912"
                    },
                    {
                        "name": "Sune",
                        "birth_year": "1913"
                    },
                    {
                        "name": "Birgit",
                        "birth_year": "1918"
                    },
                    {
                        "name": "Börje",
                        "birth_year": "1922"
                    }
                ]
            },
            "hobbies": [
                "segling"
            ]
        }
    }
}