{
    "original": "RÅDSTRÖM,    HANS   V,    laborator,\nDanderyd,  f  i  Sthlm  26/3/19   av  förf\nKarl-Johan R o Berta Genander.\nFil   lic   Sthlm  46,  Inst  for  Advanced\n\nStudy Princeton USA 48-50, fil dr\n52, doc i matematik StU sed 52,\nlaborator KTH sed 54. - Visiting prof Univ\nof Minnesota 57-58. - Medl Sv\nmatema-tikersamf. - Skr: vetensk arb inom\nmatematiken.\n\nGift 43 m Karin Åkerblad f 19, dtr t\ndisp Nils Å o Svea Bolin. - Barn:\nLena f 50, Anders f 53.\n\nRÅDSTRÖM, PÄR K, författare,\nSthlm, f i Sthlm 29/8/25 av förf\nKarl-Johan R o Berta Genander.\nMedarb Sv Morgonbl 43, Expressen\n44-45, Gbgs Morgonpost 49, Sv:es radio\n55-56. - Medl Förf:fören, PK, AIK,\nSKÅP. - Skr: Men inga blommor\nvissnade (46), Stjärnan under kavajsilaget (49),\nTiden väntar inte (52), Greg\nBengtsson &amp; kärleken (53), Ärans portar (54),\nParis. En kärleksroman (55), Det\nKlara som försvinner (55), Ballong t\nmånen (58), Sommargästerna (60), Rö\nutan åror (61), Översten (61), Mordet (62).\n\nRÅLAMB, LOUISE E C, friherrinna,\nfd överhovmästarinna, Sthlm, f på Fånö,\nUpps l, 27/5/75 av bruksptr Hugo Tamm\no frih:an Thérese af Ugglas.\nÖverhovmästarinna 38-56. - Utm: GV:s\nJmtll,   GV:sJmt,   GV:sMt,   KmstkNO,\nStkNedOHO,   StkStbVO.\nGift   96   m   överhovjägmäst,   frih  Eric\nR  f 68  d  40.\n\nRÅNBY, BENGT G, professor,\nDjursholm, f i Niemisel, Norrb l 5/4/20 av\nmejeriförest Gustaf Andersson o\nsmå-skollär Berta Ling.\n\nStud:ex Lund 38, fil kand Upps 40,\nfil måg 45, fil lic 50, fil dr 52. - Aman\nAstronom observat Upps univ 40, forskn\n:-ass fysikal:-kem inst 43-52, du Pont\nResearch Fellow Brooklyn Polytechnic\nInst New York USA 52-53, doc i\nfysikalisk kemi Upps univ 52, bitr lär 53,\neo doc 54-55, konsult f orsk Sv traf\norskn:-inst Sthlm 53-55, research specialist o\ngroup leader Amer Viscose Corp USA\n56, prof of Pulp and Paper Techn o\nDirector of the Empire State Paper\nResearch Inst State Univ of New York\nUSA 59, prof i polymerteknologi KTH\nsed 61. - Stud :res Europa, Kanada, USA\no Sovjetunionen m gästföreläsn v univ,\nhögsk o forskn :inst. - Förest Upps\nstud:-kårs intressebyrå 43-45, medl Upps\nstud:-kårs direkt 44-45, styr :ordf\nNykterhetsvännernas stud :hem Upps 54-55, led\nkomm f Verdandis småskr 48-55, led\nSIS 61, medl Sv kemistsamf 45, The\nFaraday Soc 51, The Amer Chem\nSoc 52, Sigma Xi 59, The Amer Ass\nfor the Advancement of Science 60,\n\nLVSU 60. - Skr: Fine Structure and\nReactions of Native Cellulose (drsavh\n52) ett 70-tal upps i facklitt. - Hobbies:\nbotanik, fiske, fjäl:lvandring.\nGift 45 m Aina Hultcrantz f 21, dtr t\nagron Einar H o Magda Ackzén.\n-Barn: Mats f 47, Birgitta f 49, Hans f 56.\n",
    "structured": {
        "1": {
            "full_name": "Hans V Rådström",
            "location": "Danderyd",
            "occupation": "Laborator",
            "birth_details": {
                "date": "26/03/1919",
                "place": "Sthlm",
                "parents": "Karl-Johan R o Berta Genander"
            },
            "education": [
                {
                    "degree": "Filosofie licentiat",
                    "year": "1946",
                    "institution": "Sthlm"
                },
                {
                    "degree": "Filosofie doktor",
                    "year": "1952",
                    "institution": "NULL"
                }
            ],
            "career": [
                {
                    "position": "Doc i matematik",
                    "years": {
                        "start_year": 1952,
                        "end_year": "NULL"
                    },
                    "organization": "StU"
                },
                {
                    "position": "Laborator",
                    "years": {
                        "start_year": 1954,
                        "end_year": "NULL"
                    },
                    "organization": "KTH"
                },
                {
                    "position": "Visiting prof",
                    "years": {
                        "start_year": 1957,
                        "end_year": 1958
                    },
                    "organization": "Univ of Minnesota"
                }
            ],
            "family": {
                "spouse": "Karin Åkerblad",
                "marriage_year": "1943",
                "children": [
                    {
                        "name": "Lena",
                        "birth_year": "1950"
                    },
                    {
                        "name": "Anders",
                        "birth_year": "1953"
                    }
                ]
            }
        },
        "2": {
            "full_name": "Pär K Rådström",
            "location": "Sthlm",
            "occupation": "Författare",
            "birth_details": {
                "date": "29/08/1925",
                "place": "Sthlm",
                "parents": "Karl-Johan R o Berta Genander"
            },
            "education": [],
            "career": [],
            "family": {
                "spouse": "NULL",
                "marriage_year": "NULL",
                "children": []
            },
            "publications": [
                {
                    "title": "Men inga blommor vissnade",
                    "year": "1946",
                    "type": "NULL"
                },
                {
                    "title": "Stjärnan under kavajsilaget",
                    "year": "1949",
                    "type": "NULL"
                },
                {
                    "title": "Tiden väntar inte",
                    "year": "1952",
                    "type": "NULL"
                },
                {
                    "title": "Greg Bengtsson & kärleken",
                    "year": "1953",
                    "type": "NULL"
                },
                {
                    "title": "Ärans portar",
                    "year": "1954",
                    "type": "NULL"
                },
                {
                    "title": "Paris. En kärleksroman",
                    "year": "1955",
                    "type": "NULL"
                },
                {
                    "title": "Det Klara som försvinner",
                    "year": "1955",
                    "type": "NULL"
                },
                {
                    "title": "Ballong t månen",
                    "year": "1958",
                    "type": "NULL"
                },
                {
                    "title": "Sommargästerna",
                    "year": "1960",
                    "type": "NULL"
                },
                {
                    "title": "Rö utan åror",
                    "year": "1961",
                    "type": "NULL"
                },
                {
                    "title": "Översten",
                    "year": "1961",
                    "type": "NULL"
                },
                {
                    "title": "Mordet",
                    "year": "1962",
                    "type": "NULL"
                }
            ]
        },
        "3": {
            "full_name": "Louise E C Rålamb",
            "location": "Sthlm",
            "occupation": "Friherrinna, fd överhovmästarinna",
            "birth_details": {
                "date": "27/05/1875",
                "place": "Fånö, Upps l",
                "parents": "Hugo Tamm o frih:an Thérese af Ugglas"
            },
            "education": [],
            "career": [],
            "family": {
                "spouse": "frih Eric R",
                "marriage_year": "1896",
                "children": []
            },
            "honorary_titles": [
                {
                    "title": "GV:s Jmtll",
                    "institution": "NULL",
                    "year": "NULL"
                },
                {
                    "title": "GV:sJmt",
                    "institution": "NULL",
                    "year": "NULL"
                },
                {
                    "title": "GV:sMt",
                    "institution": "NULL",
                    "year": "NULL"
                },
                {
                    "title": "KmstkNO",
                    "institution": "NULL",
                    "year": "NULL"
                },
                {
                    "title": "StkNedOHO",
                    "institution": "NULL",
                    "year": "NULL"
                },
                {
                    "title": "StkStbVO",
                    "institution": "NULL",
                    "year": "NULL"
                }
            ]
        },
        "4": {
            "full_name": "Bengt G Rånby",
            "location": "Djursholm",
            "occupation": "Professor",
            "birth_details": {
                "date": "05/04/1920",
                "place": "Niemisel, Norrb l",
                "parents": "Gustaf Andersson o Berta Ling"
            },
            "education": [
                {
                    "degree": "Stud:ex",
                    "year": "1938",
                    "institution": "Lund"
                },
                {
                    "degree": "Filosofie kandidat",
                    "year": "1940",
                    "institution": "Upps"
                },
                {
                    "degree": "Filosofie magister",
                    "year": "1945",
                    "institution": "NULL"
                },
                {
                    "degree": "Filosofie licentiat",
                    "year": "1950",
                    "institution": "NULL"
                },
                {
                    "degree": "Filosofie doktor",
                    "year": "1952",
                    "institution": "NULL"
                }
            ],
            "career": [
                {
                    "position": "Aman Astronom observat",
                    "years": {
                        "start_year": 1940,
                        "end_year": "NULL"
                    },
                    "organization": "Upps univ"
                },
                {
                    "position": "Forskn:-ass fysikal:-kem inst",
                    "years": {
                        "start_year": 1943,
                        "end_year": 1952
                    },
                    "organization": "NULL"
                },
                {
                    "position": "Du Pont Research Fellow",
                    "years": {
                        "start_year": 1952,
                        "end_year": 1953
                    },
                    "organization": "Brooklyn Polytechnic Inst New York USA"
                },
                {
                    "position": "Research specialist o group leader",
                    "years": {
                        "start_year": 1956,
                        "end_year": "NULL"
                    },
                    "organization": "Amer Viscose Corp USA"
                },
                {
                    "position": "Prof of Pulp and Paper Techn o Director",
                    "years": {
                        "start_year": 1959,
                        "end_year": "NULL"
                    },
                    "organization": "Empire State Paper Research Inst State Univ of New York USA"
                },
                {
                    "position": "Prof i polymerteknologi",
                    "years": {
                        "start_year": 1961,
                        "end_year": "NULL"
                    },
                    "organization": "KTH"
                }
            ],
            "family": {
                "spouse": "Aina Hultcrantz",
                "marriage_year": "1945",
                "children": [
                    {
                        "name": "Mats",
                        "birth_year": "1947"
                    },
                    {
                        "name": "Birgitta",
                        "birth_year": "1949"
                    },
                    {
                        "name": "Hans",
                        "birth_year": "1956"
                    }
                ]
            },
            "community_involvement": [
                {
                    "role": "Förest Upps stud:-kårs intressebyrå",
                    "organization": "NULL",
                    "years": "1943-1945"
                }
            ],
            "board_memberships": [
                {
                    "position": "NULL",
                    "organization": "NULL",
                    "years": "NULL"
                }
            ],
            "hobbies": [
                "botanik",
                "fiske",
                "fjäl:lvandring"
            ]
        }
    }
}