{
    "original": "ROSSEL, KARIN E, bitr överläkare,\n\nBromma, f i Sthlm 18/4/27 av dir\nEduard Sjöbäck o Edith\nBagger-Jörgensen.\n\nStud:ex Malmö 45, med kand Lund 49,\nmed lic Sthlm 54, e läk barnbyn Ska\n50, vik l:e underläk där 53, vik l:e\nunderläk psykiatr klin Södersjh 54,\npsy-kiatr klin Karoi sjh 54, l :e underläk\nBec-komberga sjh 57, vik l:e underläk\npsykiatr klin Karol sjh 58, vik l:e\nunderläk neurol klin Seraf:las 59, l:e\nunderläk Beckomberga sjh 60, vik l:e\nunderläk med Min S:t Eriks sjh 61, bitr\növerläk Beckomberga sjh sed 62. -\nHobbies: musik, lyrik.\n\nGift 56 m förf James Rossel f 12.\n-Barn: Martin f 59.\n\nRÖSTIN, HILDING N, agronom,\nSthlm, f i Voxtorp, Hall l, 30/6/01 av\nsjökapten Alfred Nilsson o Hilda\nSvensson.\n\nStud:ex Halmstad 21, agr:ex Alnarp 27,\nlär Dingle lantm:sk 27, anst\nMjölkpropagandan Sthlm 28, GHT 28, Sv:es\nallm lantbr:sällsk/Sv lantbr:förb Sthlm\n36, studierektor o ch Lantbr:förb\nstud:-avd sed 40. - Skr: Fören :stämman (39),\nFören:rör inom jordbr (51), Från\nlantm:-fören t SLR (55), Jordbr fören:rör (56),\nDe första slakferif ören :na - bakgrund o\nidéer (58) m m.\n\nGift m Kerstin Pettersson f 06. - Barn:\nNils-Hilding f 33, Eva f 35, Sven Peter f\n38, Margareta f 42.\n\n",
    "structured": {
        "1": {
            "full_name": "ROSSEL, KARIN E",
            "location": "Bromma",
            "occupation": "bitr överläkare",
            "birth_details": {
                "date": "18/04/1927",
                "place": "Stockholm",
                "parents": "Eduard Sjöbäck o Edith Bagger-Jörgensen"
            },
            "education": [
                {
                    "degree": "Stud:ex",
                    "year": "1945",
                    "institution": "Malmö"
                },
                {
                    "degree": "med kand",
                    "year": "1949",
                    "institution": "Lund"
                },
                {
                    "degree": "med lic",
                    "year": "1954",
                    "institution": "Sthlm"
                }
            ],
            "career": [
                {
                    "position": "e läk barnbyn",
                    "years": {
                        "start_year": 1950,
                        "end_year": 1953
                    },
                    "organization": "Ska"
                },
                {
                    "position": "vik l:e underläk",
                    "years": {
                        "start_year": 1953,
                        "end_year": 1954
                    },
                    "organization": "Södersjh"
                },
                {
                    "position": "l :e underläk",
                    "years": {
                        "start_year": 1954,
                        "end_year": 1954
                    },
                    "organization": "Karoi sjh"
                },
                {
                    "position": "l:e underläk",
                    "years": {
                        "start_year": 1957,
                        "end_year": 1958
                    },
                    "organization": "Beckomberga sjh"
                },
                {
                    "position": "l:e underläk neurol klin",
                    "years": {
                        "start_year": 1959,
                        "end_year": 1959
                    },
                    "organization": "Seraf:las"
                },
                {
                    "position": "l:e underläk",
                    "years": {
                        "start_year": 1960,
                        "end_year": 1960
                    },
                    "organization": "Beckomberga sjh"
                },
                {
                    "position": "vik l:e underläk med Min",
                    "years": {
                        "start_year": 1961,
                        "end_year": 1961
                    },
                    "organization": "S:t Eriks sjh"
                },
                {
                    "position": "bitr överläk",
                    "years": {
                        "start_year": 1962,
                        "end_year": null
                    },
                    "organization": "Beckomberga sjh"
                }
            ],
            "family": {
                "spouse": "James Rossel",
                "marriage_year": "1956",
                "children": [
                    {
                        "name": "Martin",
                        "birth_year": "1959"
                    }
                ]
            },
            "hobbies": [
                "musik",
                "lyrik"
            ]
        },
        "2": {
            "full_name": "RÖSTIN, HILDING N",
            "location": "Sthlm",
            "occupation": "agronom",
            "birth_details": {
                "date": "30/06/1901",
                "place": "Voxtorp, Hall l",
                "parents": "sjökapten Alfred Nilsson o Hilda Svensson"
            },
            "education": [
                {
                    "degree": "Stud:ex",
                    "year": "1921",
                    "institution": "Halmstad"
                },
                {
                    "degree": "agr:ex",
                    "year": "1927",
                    "institution": "Alnarp"
                }
            ],
            "career": [
                {
                    "position": "lär Dingle lantm:sk",
                    "years": {
                        "start_year": 1927,
                        "end_year": null
                    },
                    "organization": null
                },
                {
                    "position": "anst Mjölkpropagandan",
                    "years": {
                        "start_year": 1928,
                        "end_year": null
                    },
                    "organization": "Sthlm"
                },
                {
                    "position": "GHT",
                    "years": {
                        "start_year": 1928,
                        "end_year": null
                    },
                    "organization": null
                },
                {
                    "position": "Sv:es allm lantbr:sällsk/Sv lantbr:förb",
                    "years": {
                        "start_year": 1936,
                        "end_year": null
                    },
                    "organization": "Sthlm"
                },
                {
                    "position": "studierektor o ch Lantbr:förb stud:-avd",
                    "years": {
                        "start_year": 1940,
                        "end_year": null
                    },
                    "organization": null
                }
            ],
            "family": {
                "spouse": "Kerstin Pettersson",
                "marriage_year": null,
                "children": [
                    {
                        "name": "Nils-Hilding",
                        "birth_year": "1933"
                    },
                    {
                        "name": "Eva",
                        "birth_year": "1935"
                    },
                    {
                        "name": "Sven Peter",
                        "birth_year": "1938"
                    },
                    {
                        "name": "Margareta",
                        "birth_year": "1942"
                    }
                ]
            }
        }
    }
}