{
    "original": "Ehrenborg, Theodor, major,\nHalm-Stad, f. 4/2/87 i Stoby, Krist. 1., av\nmajor Casper E. o. Hilda Santesson.\nG. 15 m. Amelie Harriet Susanna\nTham. Barn: Fredrik f. 15, Amelie\n17, Susanna 22. — Stud :ex. i Lund 07,\noff:ex. 10. Und:.löjtn. v. Hall. reg. 10,\nlöjtn. 15, kapt. 25, major 36. Hemv:-\n\nof’f. 40, Kgl. Maj:ts omb. i styr. f.\nHall. skytteförb. 32-45, sekr. i Röda\nkorsets Hall.-avd. sed. 36. Hobby:\ngammak si’lver. RSO, RVO, SvRKSM,\nLands’t :GM, SvsbfSM, Halil.-Nordv.\nSkånes landst:förb. GM, Halk\nskvtte-förb :GM, Skyttem.’\n\nEhrenkrona, Erik Gustaf Claes,\nmajor, friherre, Hulterstad, Mjölby, f. 9/\n9/04 i Mjölby av öv:löjtn., frih.\nCarl-Erik E. o. Signe Westman. G. 29 m.\nKate von der Lancken, d. 39. Barn:\nClaes Erik f. 29. — Stud:€x. 22, off :ex.\n25, KHS 40-42. Fänrik v. 2. Livgren\n:-reg. 25, kapt. v. Livgren :reg. 39, major\npå res:-stat 44. Stud:reis. t. Finl. 39-40.\nFörv. o. äger tills. m. syskon\nHulterstad i öistergötl. FFrK4kl m sv, FMM.\n\nEhrenkrona, Signe Emmy Andrea,\nfriherrinna, Hulterstad, Mjölby, f. 27/\n10/77 i Jönköp. av konsul Anders\nGustaf Westman o. Emmy Maria Sofia\nWestring. G. 99 m. öv :löjtn., frih.\nCarl-Erik E. Barn: Anna f. 03, g. m.\nutrikesråd., jur. kand. Gösta Engzelil,\nErik 04, major, Märta 05, g. m. doc.\nv. Sthlm-s högsk., arkiv. Olof\nJäger-skiöld, Carl-Gustaf 09, anst. h.\nclea-ringndn, Sthlm, Henrik 14, fil. mag.,\ng. m. Veronica Martin. — Västra\nelem:lärov. f. fl., fortsättn :kurs v.\nAhlinska sk. i Sthlm. Fd. ordf. i\nMjölby högerkvinnor, ordf. i\nMjö’1’by-Vi-foilka lokalf ören. av Fören. ö^stergötl.\nbarn, v. ordf. i Mjöilbykreitis. av Röda\nKor&amp;et, fd. ordf. i Mjölby lottakår,\nled. av kyrkofuMm. i Mjölby. SvRKM,\nFMM.\n\n",
    "structured": {
        "1": {
            "full_name": "Theodor Ehrenborg",
            "location": "Halm-Stad",
            "occupation": "Major",
            "birth_details": {
                "date": "04/02/1887",
                "place": "Stoby",
                "parents": "Major Casper E. and Hilda Santesson",
                "place_coordinates": {
                    "Latitude": 56.17505019999999,
                    "Longitude": 13.828094
                }
            },
            "education": [
                {
                    "degree": "Stud",
                    "year": "1907",
                    "institution": "Lund",
                    "institution_coordinates": {
                        "Latitude": 55.7046601,
                        "Longitude": 13.1910073
                    }
                },
                {
                    "degree": "Off",
                    "year": "1910",
                    "institution": "Ex",
                    "institution_coordinates": {
                        "Latitude": -1.2882556,
                        "Longitude": 36.904657
                    }
                }
            ],
            "career": [
                {
                    "position": "Und: löjtn. v. Hall. reg.",
                    "years": {
                        "start_year": 1910,
                        "end_year": 1915
                    },
                    "organization": "Hall"
                },
                {
                    "position": "Löjtn.",
                    "years": {
                        "start_year": 1915,
                        "end_year": 1925
                    }
                },
                {
                    "position": "Kapt.",
                    "years": {
                        "start_year": 1925,
                        "end_year": 1936
                    }
                },
                {
                    "position": "Major",
                    "years": {
                        "start_year": 1936
                    }
                }
            ],
            "family": {
                "spouse": "Amelie Harriet Susanna Tham",
                "marriage_year": "15",
                "children": [
                    {
                        "name": "Fredrik",
                        "birth_year": "15"
                    },
                    {
                        "name": "Amelie",
                        "birth_year": "17"
                    },
                    {
                        "name": "Susanna",
                        "birth_year": "22"
                    }
                ]
            },
            "publications": null,
            "community_involvement": [
                {
                    "role": "Kgl. Maj:ts omb.",
                    "organization": "styr. f. Hall. skytteförb.",
                    "years": "32-45"
                },
                {
                    "role": "Sekr.",
                    "organization": "Röda korsets Hall.-avd.",
                    "years": "36"
                }
            ],
            "board_memberships": null,
            "honorary_titles": [
                {
                    "title": "RSO"
                },
                {
                    "title": "RVO"
                },
                {
                    "title": "SvRKSM"
                },
                {
                    "title": "Lands't :GM"
                },
                {
                    "title": "SvsbfSM"
                },
                {
                    "title": "Halil.-Nordv. Skånes landst:förb. GM"
                },
                {
                    "title": "Halk skvtte-förb :GM"
                },
                {
                    "title": "Skyttem."
                }
            ],
            "hobbies": [
                "Gammak si’lver"
            ],
            "location_coordinates": {
                "Latitude": 56.67238159999999,
                "Longitude": 12.7623281
            }
        },
        "2": {
            "full_name": "Erik Gustaf Claes Ehrenkrona",
            "location": "Hulterstad, Mjölby",
            "occupation": "Major, Friherre",
            "birth_details": {
                "date": "09/09/1904",
                "place": "Mjölby",
                "parents": "Öv:löjtn., Frih. Carl-Erik E. and Signe Westman",
                "place_coordinates": {
                    "Latitude": 58.3226908,
                    "Longitude": 15.1335348
                }
            },
            "education": [
                {
                    "degree": "Stud:€x.",
                    "year": "22"
                },
                {
                    "degree": "Off:ex.",
                    "year": "25"
                },
                {
                    "degree": "KHS",
                    "year": "40-42"
                }
            ],
            "career": [
                {
                    "position": "Fänrik v. 2. Livgren :reg.",
                    "years": {
                        "start_year": 1925
                    }
                },
                {
                    "position": "Kapt. v. Livgren :reg.",
                    "years": {
                        "start_year": 1939
                    }
                },
                {
                    "position": "Major på res:-stat",
                    "years": {
                        "start_year": 1944
                    }
                }
            ],
            "family": {
                "spouse": "Kate von der Lancken",
                "marriage_year": "29",
                "children": [
                    {
                        "name": "Claes Erik",
                        "birth_year": "29"
                    }
                ]
            },
            "publications": null,
            "community_involvement": null,
            "board_memberships": null,
            "honorary_titles": [
                "Hulterstad i öistergötl. FFrK4kl m sv",
                "FMM"
            ],
            "hobbies": null,
            "location_coordinates": {
                "Latitude": 58.3226908,
                "Longitude": 15.1335348
            }
        },
        "3": {
            "full_name": "Signe Emmy Andrea Ehrenkrona",
            "location": "Hulterstad, Mjölby",
            "occupation": "Friherrinna",
            "birth_details": {
                "date": "27/10/1877",
                "place": "Jönköp",
                "place_coordinates": {
                    "Latitude": 57.8017484,
                    "Longitude": 14.2188324
                }
            },
            "education": [
                {
                    "degree": "Västra elem:lärov. f. fl."
                },
                {
                    "degree": "Fortsättn :kurs v. Ahlinska sk. i Sthlm"
                }
            ],
            "career": [
                {
                    "position": "Fd. ordf. i Mjölby högerkvinnor"
                },
                {
                    "position": "Ordf. i Mjö’1’by-Vi-foilka lokalf, "
                },
                {
                    "position": "V. ordf. i Mjöilbykreitis. av Röda Kor&amp;et"
                },
                {
                    "position": "Fd. ordf. i Mjölby lottakår"
                },
                {
                    "position": "Led. av kyrkofuMm. i Mjölby"
                }
            ],
            "family": {
                "spouse": "Öv :löjtn., Frih. Carl-Erik E.",
                "marriage_year": "99",
                "children": [
                    {
                        "name": "Anna",
                        "birth_year": "03"
                    },
                    {
                        "name": "Erik",
                        "birth_year": "04"
                    },
                    {
                        "name": "Märta",
                        "birth_year": "05"
                    },
                    {
                        "name": "Carl-Gustaf",
                        "birth_year": "09"
                    },
                    {
                        "name": "Henrik",
                        "birth_year": "14"
                    }
                ]
            },
            "publications": null,
            "community_involvement": null,
            "board_memberships": null,
            "honorary_titles": [
                "SvRKM",
                "FMM"
            ],
            "hobbies": null,
            "location_coordinates": {
                "Latitude": 58.3226908,
                "Longitude": 15.1335348
            }
        }
    }
}