{
    "original": "Eklund, Karl (Kalle) Oskar,\nkonstnär, Vadstena, f. 13/7/91 i Örebro av\nErnst E. o. Karin Forsberg. G. 20\nm. Maria Welin. Barn: Karl-Göran\nf. 21, Kajsa 22, Ulla 29. — Stud. v.\nAlthins målarsk. o. v. konstakad. i\nSthlm. Stud:res. t. Danm., Tyskl,\nHolL, Belg., Frankr. o. Ital. Debut, i\nSthlm 17. Repr. i Nat :mus., Örebro\n1., Norrköp. o. Linköp. mus.\n\nEklund, Per Gustav Ragnar, fil.\nmag., läroverksadjunkt, Göteborg, f.\n18/2/06 i Sthlm av bokhåll. August E.\no. Gustava Forsmark. G. 42 m. Irma\nSandahl. — Stud:ex. i Södertälje 25,\nfil. mag. i Upps. 29, provår v. södra\nlatin i Sthlm 34. Vik. adj. i Skellefteå\n30, i Falun 31-33, e. lär. i Falun 33,\nv. östra real i Sthlm 35, vik. adj. v.\n\nsödra latin där 35-37, adj. i modersm.\no. hist. m. samh:lära v. Vasa h. a. 1.\ni Gbg sed. 37. Sekr. i Modersm :lär.\nfören. i Gbg’sed. 40 o. i Gbgs\nlär:-sälisk. sed. 41.\n\nEklund, Sture Gustav Edvin, andre\nläkare, Vänersborg, f. 26/6/09 i Gbg\nav J. E. E. o. Annie Karlson. G. 39\nm. Anna-Greta Åkeson. Barn:\nAnn-Ohristine f. 42. — Stud:ex. i Gbg 28,\nmed. kand. i Lund 33 o. med. lic. där\n38. Kort. förordn. s. e. läk. v. S:ta\nMaria sjukh. 37 o. 38, andre läk. v.\nRestads sjukh. v. Vänersborg sed. 44.\n\nEklund, Sven Ake, tandläkare,\nTrollhättan, f. 8/5/03 i Karlskoga av\nköpm. Adrian E. o. Eufemia Persson.\nG. 31 m. Dagny Florence Andersson.\nBarn: Sven Gunnar f. 33, Florence\nMargareta 37, Lars Ake 45. —\nStud:-ex. i Karlstad 23, med. kand. i Upps.\n28, tandl. 31. Assist, i Växjö 31, i\nKramfors 32, prakt, i Sthlm tills. m.\ntandl., med. lic. B. Dahlberg 31-32,\negen prakt, i Trollhättan sed. 32.\n\nEklund, Uno Ragnar Emanuel,\nkomminister, Göteborg, f. 4/12/06 i Eksjö\nav metodistpastor C. J. E. o. Emilia\nPersson. G. 37 m. Inger Sofia\nKristina Svenæus. Barn : Monika Barbro\nKristina f. 38. — Stud:ex. i Kalmar\n26, teol. fii. ex. 29, teol. kand., prakt,\nteol. prov o. prästv. f. Linköp. stift\n3’2. Past :adj. i Linköp. 33’, bitr.\nstifts-adj. där s. å., stiftsadj. 34, kommin. i\nRumskulla 37, pred. v.\nJohanneskyr-kan i Gbg 38, kommin. i Johannebergs\nförs. i Gbg sed. 44, mil:pastor v.\nVästkustens marindistr. sed. 42, pred. v.\nCarlanderska sjukhemm. sed. 43. Ordf.\ni Gbgs kristl. ungd:råd o. i\nJohannebergs scoutkårråd, led. av S:t\nJohan-neskyrkans kyrkoråd, av styr. f. Gbgs\nkyrkl. sjöm:vård o. av styr. f. sällsk.\nJultomtarna i Gbg, led. av kyrkofullm.\nsed. 47. Skr.: Soli Deo Gloria (41),\nPå heligt rum (43), medv. i Epistel\npostilla (42), Aftonsångspostilla (46),\nmedarb. i Stiftskrönikan m. fl. tidskr.\n\n",
    "structured": {
        "1": {
            "full_name": "Eklund, Karl (Kalle) Oskar",
            "location": "Vadstena",
            "occupation": "Konstnär",
            "birth_details": {
                "date": "13/07/1891",
                "place": "Örebro",
                "place_coordinates": {
                    "Latitude": 59.2752626,
                    "Longitude": 15.2134105
                }
            },
            "education": [
                {
                    "degree": "Stud",
                    "year": "17",
                    "institution": "Althins målarsk.",
                    "institution_coordinates": {
                        "Latitude": 60.12816100000001,
                        "Longitude": 18.643501
                    }
                },
                {
                    "degree": "Konstakad.",
                    "year": "17",
                    "institution": "Sthlm",
                    "institution_coordinates": {
                        "Latitude": 59.32932349999999,
                        "Longitude": 18.0685808
                    }
                }
            ],
            "career": [
                {
                    "position": "Debut",
                    "years": {
                        "start_year": 17,
                        "end_year": null
                    },
                    "organization": "Sthlm"
                }
            ],
            "family": {
                "spouse": "Maria Welin",
                "marriage_year": "20",
                "children": [
                    {
                        "name": "Karl-Göran",
                        "birth_year": "21"
                    },
                    {
                        "name": "Kajsa",
                        "birth_year": "22"
                    },
                    {
                        "name": "Ulla",
                        "birth_year": "29"
                    }
                ]
            },
            "location_coordinates": {
                "Latitude": 58.44760219999999,
                "Longitude": 14.8902335
            }
        },
        "2": {
            "full_name": "Eklund, Per Gustav Ragnar",
            "location": "Göteborg",
            "occupation": "Fil. mag., Läroverksadjunkt",
            "birth_details": {
                "date": "18/02/1906",
                "place": "Sthlm",
                "place_coordinates": {
                    "Latitude": 59.32932349999999,
                    "Longitude": 18.0685808
                }
            },
            "education": [
                {
                    "degree": "Stud",
                    "year": "25",
                    "institution": "Södertälje",
                    "institution_coordinates": {
                        "Latitude": 59.197762,
                        "Longitude": 17.6201942
                    }
                },
                {
                    "degree": "Fil. mag.",
                    "year": "29",
                    "institution": "Upps.",
                    "institution_coordinates": {
                        "Latitude": 60.12816100000001,
                        "Longitude": 18.643501
                    }
                }
            ],
            "career": [
                {
                    "position": "Sekr. i Modersm :lär. fören. i Gbg",
                    "years": {
                        "start_year": 40,
                        "end_year": null
                    },
                    "organization": "NULL"
                }
            ],
            "family": {
                "spouse": "Irma Sandahl",
                "marriage_year": "42",
                "children": null
            },
            "location_coordinates": {
                "Latitude": 57.70887,
                "Longitude": 11.97456
            }
        },
        "3": {
            "full_name": "Eklund, Sture Gustav Edvin",
            "location": "Vänersborg",
            "occupation": "Andre läkare",
            "birth_details": {
                "date": "26/06/1909",
                "place": "Gbg",
                "place_coordinates": {
                    "Latitude": 57.70887,
                    "Longitude": 11.97456
                }
            },
            "education": null,
            "career": [
                {
                    "position": "Andre läk. v. Restads sjukh. v. Vänersborg",
                    "years": {
                        "start_year": 44,
                        "end_year": null
                    },
                    "organization": "NULL"
                }
            ],
            "family": {
                "spouse": "Anna-Greta Åkeson",
                "marriage_year": "39",
                "children": [
                    {
                        "name": "Ann-Ohristine",
                        "birth_year": "42"
                    }
                ]
            },
            "location_coordinates": {
                "Latitude": 58.3797283,
                "Longitude": 12.3248032
            }
        },
        "4": {
            "full_name": "Eklund, Sven Ake",
            "location": "Trollhättan",
            "occupation": "Tandläkare",
            "birth_details": {
                "date": "08/05/1903",
                "place": "Karlskoga",
                "place_coordinates": {
                    "Latitude": 59.32863399999999,
                    "Longitude": 14.536414
                }
            },
            "education": [
                {
                    "degree": "Stud",
                    "year": "23",
                    "institution": "Karlstad",
                    "institution_coordinates": {
                        "Latitude": 59.4021806,
                        "Longitude": 13.5114977
                    }
                },
                {
                    "degree": "Med. kand.",
                    "year": "28",
                    "institution": "Upps.",
                    "institution_coordinates": {
                        "Latitude": 60.12816100000001,
                        "Longitude": 18.643501
                    }
                },
                {
                    "degree": "Tandl.",
                    "year": "31",
                    "institution": "NULL",
                    "institution_coordinates": {
                        "Latitude": 60.12816100000001,
                        "Longitude": 18.643501
                    }
                }
            ],
            "career": [
                {
                    "position": "Egen prakt, i Trollhättan sed.",
                    "years": {
                        "start_year": 32,
                        "end_year": null
                    },
                    "organization": "NULL"
                }
            ],
            "family": {
                "spouse": "Dagny Florence Andersson",
                "marriage_year": "31",
                "children": [
                    {
                        "name": "Sven Gunnar",
                        "birth_year": "33"
                    },
                    {
                        "name": "Florence Margareta",
                        "birth_year": "37"
                    },
                    {
                        "name": "Lars Ake",
                        "birth_year": "45"
                    }
                ]
            },
            "location_coordinates": {
                "Latitude": 58.28348939999999,
                "Longitude": 12.2858206
            }
        },
        "5": {
            "full_name": "Eklund, Uno Ragnar Emanuel",
            "location": "Göteborg",
            "occupation": "Komminister",
            "birth_details": {
                "date": "04/12/1906",
                "place": "Eksjö",
                "place_coordinates": {
                    "Latitude": 57.6172,
                    "Longitude": 15.22155
                }
            },
            "education": [
                {
                    "degree": "Teol. fii. ex.",
                    "year": "29",
                    "institution": "Linköp.",
                    "institution_coordinates": {
                        "Latitude": 58.41080700000001,
                        "Longitude": 15.6213727
                    }
                },
                {
                    "degree": "Teol. kand.",
                    "year": "32",
                    "institution": "Linköp.",
                    "institution_coordinates": {
                        "Latitude": 58.41080700000001,
                        "Longitude": 15.6213727
                    }
                }
            ],
            "career": [
                {
                    "position": "Pred. v. Johannebergs förs. i Gbg",
                    "years": {
                        "start_year": 44,
                        "end_year": null
                    },
                    "organization": "NULL"
                }
            ],
            "family": {
                "spouse": "Inger Sofia Kristina Svenæus",
                "marriage_year": "37",
                "children": [
                    {
                        "name": "Monika Barbro Kristina",
                        "birth_year": "38"
                    }
                ]
            },
            "location_coordinates": {
                "Latitude": 57.70887,
                "Longitude": 11.97456
            }
        }
    }
}