{
    "original": "Cederwall, Sten Wilhelm,\ncivilingenjör, Borås, f. 19/9/01 i Norrköp.\nav kamr. Carl Wilhelm C. o. Anna\nGraneli. G. 31 m. Mrlanka Hultqvist.\nBarn: Christer f. 32, Klas-Ivan 36,\nMargareta 42. — Stud:ex. i Norrköp.\n\n20,\tciv:ing:ex. v. KTH 24. Res. t.\nTyskl. 22, 32, 36 o. 39. Anst. h.\nciv:-ing. Martin Ljungberg i Norrköp. 25\no. distr :ing. Ekwall i Jönköp. 26, v.\nciv:ing. Robert Mo’ssbergs Konsult.\nIng:firma i Sthlm 26, tekn. bitr. h.\ndistr :lantmät. Sven Liedbeck i Sthlm\n27, kontr. f. kraftstat :byggn. o.\nbro-byggn. samt utförde vägund :sökn. m.\nm. v. Flöda säteri 29-30, driftsing. v.\n\nSv. Yllekoncernen A-B i Borås 30-42,\nchef f. civ:tekn. avd. där ised. 42. Ordf.\ni styr. f. Valboåns kraftverksfören.,\nverkst. led. i styr. f. Tidans\nreglerings-fören. sed. 46, suppl. i styr. f.\nLånghalsens regleringsföret. o. A-B\nNyköpingsåns Kraftintressenter, led. av\nstyr. f. A-B Koncernhus, skattmäst. i\nTekn. förb. i Borås 41. Led. av Sv.\ntekn:fören. sed. 24.\n\nCelander, Karl Hildingr» professor,\nfd. rektor, Göteborg, f. 17/7/76 i\nArboga av folksk :lär. G. M. C. o. Elise\nSörman. G. 14 m. Vera Hoffmann.\nBarn: Bengt f. 15, Inga 17, Sven 18,\nKarin 20, Gösta o. Olov 23. —\nStud:-ex. i Örebro 94, fil. kand. i Upps. 97,\nfil. lic. 04, fil. dr 06. Res. t. dåv.\nKristiania s. inneh. av fjärdenov :stip.\n05, Tyskl. 06, Frankr. m. statsstip. f.\nstud. av modersm :und :visn. v. de\nfranska lycéerna 20, Frankr. o. Ital.\n30, Norge, Danm. o. Finl., särsk. f.\nspråk- o. folklorist. stud. uppr. ggr. fr.\n01, medv. i lär:kurser i Köpenhamn 09\no. 13, i Ribe 19, i Borgå 22, i\nHinds-gavl 23, t. Norge f. föredr. o. uppläsn.\npå uppdr. av fören. Norden 25, 27 o.\n28. Doc. i nord. språk i Upps. 07-10,\ndoc. v. Gbgs högsk. 11-32, förest, f.\nUpps. univ. föreläsn :byrå 09-10, vik.\nadj. v. Upps. folksk :sem. 05, lektor v.\nGbgs real 10-42, studirektor v. Gbgs\nlyc. f. fl. 17-38, rektor v. h. a. 1. f. fl.\ni Gbg 29-42, tillades professors namn\n46. Sekr. i Modersm :lär. fören.\n12-27, led. av styr. f. Aug. Abrahamssons\nstift, på Nääs 24-29, ordf. i styr. f.\ninst. f. folkminnesforskn. v. Gbgs\nhögsk. 26-46. Skr.: Lokes mytiska\nursprung (11), Studentexamen (17),\nGymnasiereformen (tills. m. Malte\nJacobsson 19), Närkiska folkminnen (22),\nNord. jul I (28), Barfotaspringningen\nv. vårdagjämningstiden (44), Några\ndanska o. svenska julvisor (46),\ntid-skr :upps., utg. Saga o. sanning, Vers\no. prosa o. Nord. läsn. (tills. m.\nJeanna Oterdahl). KN02kl, HedLGAA,\nLVVS.\n\n",
    "structured": {
        "0": {
            "full_name": "Sten Wilhelm Cederwall",
            "location": "Borås",
            "occupation": "Civilingenjör",
            "birth_details": {
                "date": "19/09/1901",
                "place": "Norrköping",
                "parents": "CarL Wilhelm C. o. Anna Graneli",
                "place_coordinates": {
                    "Latitude": 58.587745,
                    "Longitude": 16.192421
                }
            },
            "education": [
                {
                    "degree": "Stud :ex. i Norrköp",
                    "year": "20",
                    "institution": "NULL",
                    "institution_coordinates": {
                        "Latitude": 60.12816100000001,
                        "Longitude": 18.643501
                    }
                },
                {
                    "degree": "Civ:ing:ex. v. KTH",
                    "year": "24",
                    "institution": "NULL",
                    "institution_coordinates": {
                        "Latitude": 60.12816100000001,
                        "Longitude": 18.643501
                    }
                }
            ],
            "career": [
                {
                    "position": "Res. t. Tyskl.",
                    "years": {
                        "start_year": 22,
                        "end_year": 22
                    },
                    "organization": "NULL"
                },
                {
                    "position": "Anst. h. civ:-ing. Martin Ljungberg i Norrköp.",
                    "years": {
                        "start_year": 25,
                        "end_year": 25
                    },
                    "organization": "NULL"
                },
                {
                    "position": "Distr :lantmät. Sven Liedbeck i Sthlm",
                    "years": {
                        "start_year": 27,
                        "end_year": 27
                    },
                    "organization": "NULL"
                },
                {
                    "position": "NULL",
                    "years": {
                        "start_year": 29,
                        "end_year": 30
                    },
                    "organization": "Flöda säteri"
                },
                {
                    "position": "Chef f. civ:tekn. avd. där ised.",
                    "years": {
                        "start_year": 42,
                        "end_year": 42
                    },
                    "organization": "NULL"
                }
            ],
            "family": {
                "spouse": "Mrlanka Hultqvist",
                "marriage_year": "31",
                "children": [
                    {
                        "name": "Christer",
                        "birth_year": "32"
                    },
                    {
                        "name": "Klas-Ivan",
                        "birth_year": "36"
                    },
                    {
                        "name": "Margareta",
                        "birth_year": "42"
                    }
                ]
            },
            "location_coordinates": {
                "Latitude": 57.72103500000001,
                "Longitude": 12.939819
            }
        },
        "1": {
            "full_name": "Karl Hilding Celander",
            "location": "Göteborg",
            "occupation": "Professor, FD. Rektor",
            "birth_details": {
                "date": "17/07/1876",
                "place": "Arboga",
                "parents": "Folksk :lär.",
                "place_coordinates": {
                    "Latitude": 59.39368829999999,
                    "Longitude": 15.8381747
                }
            },
            "education": [
                {
                    "degree": "Stud:-ex. i Örebro",
                    "year": "94",
                    "institution": "NULL",
                    "institution_coordinates": {
                        "Latitude": 60.12816100000001,
                        "Longitude": 18.643501
                    }
                },
                {
                    "degree": "Fil. kand. i Upps.",
                    "year": "97",
                    "institution": "NULL",
                    "institution_coordinates": {
                        "Latitude": 60.12816100000001,
                        "Longitude": 18.643501
                    }
                },
                {
                    "degree": "Fil. lic.",
                    "year": "04",
                    "institution": "NULL",
                    "institution_coordinates": {
                        "Latitude": 60.12816100000001,
                        "Longitude": 18.643501
                    }
                },
                {
                    "degree": "Fil. dr",
                    "year": "06",
                    "institution": "NULL",
                    "institution_coordinates": {
                        "Latitude": 60.12816100000001,
                        "Longitude": 18.643501
                    }
                }
            ],
            "career": [
                {
                    "position": "Doc. i nord. språk i Upps.",
                    "years": {
                        "start_year": 7,
                        "end_year": 10
                    },
                    "organization": "NULL"
                },
                {
                    "position": "Doc. v. Gbgs högsk.",
                    "years": {
                        "start_year": 11,
                        "end_year": 32
                    },
                    "organization": "NULL"
                },
                {
                    "position": "Förest, f. Upps. univ. föreläsn :byrå",
                    "years": {
                        "start_year": 9,
                        "end_year": 10
                    },
                    "organization": "NULL"
                },
                {
                    "position": "Lektor v. Gbgs real",
                    "years": {
                        "start_year": 10,
                        "end_year": 42
                    },
                    "organization": "NULL"
                },
                {
                    "position": "NULL",
                    "years": {
                        "start_year": 29,
                        "end_year": 42
                    },
                    "organization": "Rektor v"
                }
            ],
            "family": {
                "spouse": "Vera Hoffmann",
                "marriage_year": "14",
                "children": [
                    {
                        "name": "Bengt",
                        "birth_year": "15"
                    },
                    {
                        "name": "Inga",
                        "birth_year": "17"
                    },
                    {
                        "name": "Sven",
                        "birth_year": "18"
                    },
                    {
                        "name": "Karin",
                        "birth_year": "20"
                    },
                    {
                        "name": "Gösta o. Olov",
                        "birth_year": "23"
                    }
                ]
            },
            "location_coordinates": {
                "Latitude": 57.70887,
                "Longitude": 11.97456
            }
        }
    }
}