{
    "original": "Melflby, Krist. 1., av Sven M. o.\nPernilla Nilsson. — Stud:ex. i Lund 13,\ning: el ev v. ASEA i Västerås 14,\nciv:-img:ex. v. KTH (E) 20, stud: v. HHS.\n21-24, IVAs kurs i mat em. statistik 25,\nstud:res. i Tyskl. 27 o. 30. Korrnlmers.\nverks, i led. stäfc. 16-28, egen firma\ni Sthilm f. konsult, org: verks, o. lev.\nav org material, imp. o. exp., 27-30,\nkonsult, i ekon.-j(ur. ärend. o. org\n:frå-gor fr. 30, egen imp:- o. exp -.verks.\nOrg. utjgiv. v. KTH av sv. tekn.-veten-\n\nsk. lärob :litt. o. standardis. tekn.\nmaterial m. m. 15-27, startat o. ordn.\nKTHs stud: kårs kat al :bibl. öv.\nkatal:-litt. fr. de flesta sv. ind. 18-20, bidr.\nt. inlför. av DIN-form. i Sv:e fr. 23.\nMedll. i Sv. tekn:fören. fr. 20, i\nGesell-sch. f. 0,r.g,., Berlin, fr. 27. Skr.:\nVi n d elektr icit et sv erk (20), Vi ndkr af\n-ten o. á&amp;ss ekon. utnyttj. (23), En\nhel-aiutom. bokför :maskin (30), Vem.’ äger\nskogsbären? (42) jämte ett st. ant.\nförlags redlig, av tekn.-ve t ens k. litt.\nHobby : (filateli.\n\nMårtensson, Harald Emanuel,\nfollk-skolllärare, Ystad, f. 29/10/93 i Ystad\nav form. August M. o. Emma Jepsson.\nG. 22 m. Anna Vitalia Wall Barn:\nKjell f. 25, odont. kand., Malmö. —\nStud:ex. i Ystad 12, folkskoll:ex. i\nSträngnäs l!3, fik kand. 18 i Lund. E.\no. follkskoll. i Grängesberg 13-15, ord.\ni Rävvåla 15-18, i Ystad sed. 19.\nUn-derv. i Ystads stads yrkessk. o.\nSödra skånska inlf:reg. furir- o.\nkorpr:-skölor. Led. av stadsfullrn., fd. led.\nav kyrkoifulllm.\n\nMårtensson, Bror Johan, docent,\nLund, f. 24/12/08 i Spjutstorp, Krist.\n1., av Per M. o. Karna Nilsson. G.\n37 m. Vindy Sörenson. Barn:\nMaja-Lena f. 41, Per-Sören 43’, Hans\nFredrik 46. — Stud:ex. i Ystad 28, med.\nlic. i Lund 3*9, med. dr 40. Doc. i\nfarmakol. 40, aman. o. undoläk. v. med.\nMin. fr. 41, doc. i prakt. med. 46. Skr.:\nOn the citric acid metabolism in\nmam-mallis (grad:avh.) samt ett flert. arb.\ninom if armakol., fysiol. o. intern\nmedicin.\n\n",
    "structured": {
        "0": {
            "full_name": "Melflby, Krist. 1.",
            "location": "Sthilm",
            "occupation": "ingenjör och konsult",
            "birth_details": {
                "date": "13/XX/YYYY",
                "place": "Lund"
            },
            "education": [
                {
                    "degree": "Stud:ex.",
                    "year": "13",
                    "institution": "Lund"
                },
                {
                    "degree": "ing: el ev v. ASEA",
                    "year": "14",
                    "institution": "Västerås"
                },
                {
                    "degree": "civ:-img:ex. v. KTH (E)",
                    "year": "20",
                    "institution": "KTH"
                },
                {
                    "degree": "stud: v. HHS.",
                    "year": "21-24",
                    "institution": "HHS"
                },
                {
                    "degree": "IVAs kurs i mat em. statistik",
                    "year": "25",
                    "institution": "IVAs"
                },
                {
                    "degree": "stud:res. i Tyskl.",
                    "year": "27, 30",
                    "institution": "Tyskland"
                }
            ],
            "career": [
                {
                    "position": "Korrnlmers. verks., led. stäfc.",
                    "years": {
                        "start_year": 16,
                        "end_year": 28
                    },
                    "organization": "stäfc."
                },
                {
                    "position": "eget firma i Sthilm",
                    "years": {
                        "start_year": 27,
                        "end_year": 30
                    },
                    "organization": "Sthilm"
                },
                {
                    "position": "konsult",
                    "years": {
                        "start_year": 30,
                        "end_year": null
                    },
                    "organization": "NULL"
                }
            ],
            "family": {
                "spouse": "Pernilla Nilsson",
                "marriage_year": "NULL",
                "children": [],
                "parents": "Sven M. Melflby"
            }
        },
        "1": {
            "full_name": "Mårtensson, Harald Emanuel",
            "location": "Ystad",
            "occupation": "folkskollärare",
            "birth_details": {
                "date": "29/10/1893",
                "place": "Ystad"
            },
            "education": [
                {
                    "degree": "Stud:ex.",
                    "year": "12",
                    "institution": "Ystad"
                },
                {
                    "degree": "folkskoll:ex.",
                    "year": "13",
                    "institution": "Strängnäs"
                },
                {
                    "degree": "fik kand.",
                    "year": "18",
                    "institution": "Lund"
                }
            ],
            "career": [
                {
                    "position": "folkskollärare",
                    "years": {
                        "start_year": 13,
                        "end_year": 15
                    },
                    "organization": "Grängesberg"
                },
                {
                    "position": "folkskollärare",
                    "years": {
                        "start_year": 15,
                        "end_year": 18
                    },
                    "organization": "Rävvåla"
                },
                {
                    "position": "folkskollärare",
                    "years": {
                        "start_year": 19,
                        "end_year": null
                    },
                    "organization": "Ystad"
                }
            ],
            "family": {
                "spouse": "Anna Vitalia Wall",
                "marriage_year": "22",
                "children": [
                    {
                        "name": "Kjell",
                        "birth_year": "25"
                    }
                ],
                "parents": "August M. Mårtensson, Emma Jepsson"
            }
        },
        "2": {
            "full_name": "Mårtensson, Bror Johan",
            "location": "Lund",
            "occupation": "docent",
            "birth_details": {
                "date": "24/12/1908",
                "place": "Spjutstorp, Kristianstad"
            },
            "education": [
                {
                    "degree": "Stud:ex.",
                    "year": "28",
                    "institution": "Ystad"
                },
                {
                    "degree": "med. lic.",
                    "year": "39",
                    "institution": "Lund"
                },
                {
                    "degree": "med. dr",
                    "year": "40",
                    "institution": "Lund"
                }
            ],
            "career": [
                {
                    "position": "aman. o. undoläk.",
                    "years": {
                        "start_year": 41,
                        "end_year": 46
                    },
                    "organization": "med. Min."
                },
                {
                    "position": "docent i prakt. med.",
                    "years": {
                        "start_year": 46,
                        "end_year": null
                    },
                    "organization": "NULL"
                }
            ],
            "family": {
                "spouse": "Vindy Sörenson",
                "marriage_year": "37",
                "children": [
                    {
                        "name": "Maja-Lena",
                        "birth_year": "41"
                    },
                    {
                        "name": "Per-Sören",
                        "birth_year": "43"
                    },
                    {
                        "name": "Hans Fredrik",
                        "birth_year": "46"
                    }
                ],
                "parents": "Per M. Mårtensson, Karna Nilsson"
            }
        }
    }
}