{
    "original": "Möller, Albin Jacob, grosshandlare,\nÄngelholm, f. 18/7/84 i Ängelholm av\nJ. J. M. o. Hilda Pettersson.. G. 10\nm. Louise Klinker. Barn:\nAnna-Louise f. 11, d. 40, Margit 13, g. m. förv.\nHans Lundibladh, Vallens gods,\nVåx-torp, Vera 17, g. m. hand :trädg:mäst.\nRobert Lundbladh, Skälderhus, Ture\n18, kontorschef, Ängelholm, Brita 23,\nsjuk sköt er ska, Malmö. — Stud. v.\nIlä-rov. o. hand :sk. Res. t. Tysk! 2¾\nEnigil., Frankr. o. Schweiz 27, Ital. 30,\nHöll. o. Belg. 35, Norge 38. Anst. i\ngross : firmor i Ängelholm o. Hälsingb.\n00-12, egen gross :firnia i Ängelholm\nfr. 13. Led. av sitadsfulltm.,\nfattigv:-styr., hälsovmd, fam:bidr :nd, tax:nd,\nkyrkoråd, ordlf. i kyrkofulilm.\nStyr:-led. i Skand. Bankens avd :komt,\nÄng-ellhotlttns höge rf ören., förs ifören.,\nförs:-bemm. and :fören., hemib:- o.\nfornmi:-fören.    Medl.    av    Frimurarordlen    o.\n\nOdd Fellow. RVO, Brand- o.\nLifför-säkr. A-B Sveas GM, Försäkr. A-B\nNornans GM.\n\nMöller, Axel Bernhard Gottfrid,\nhovrättsråd, Malmö, f. 29/6/01 i\nIils-torp, Malmöh. il, av kontr :prost. Axel\nM. o. Mania Herrsitröm. — Stud:ex.\ni Lund 19, jur. kand. 24. E. o. not.\ni Skånska (hovr. 24, tingstjg. i Färs! här.\ndoms. 27-301, tjg. i Skånska hovr. 31\no. 32, e. o. fiskal där 32, bitr. dbm.\ni Frosta o. Eslövs doms. 33, sekr. där\n33-34 o. 35, assess. i Skånska hovr. 37,\nslekr. i Östra o. Medelst a doms. 39-40,\nhovr:råd fr. 44, tf. rev:sekr. 41-46.\nRNO.\n\nMöller, Bertil Anton Wilhelm1,\nliin-jeingenjör, Hälsingborg, f. 1/12/09 i\nMalmö av Ifalhr. Kristian M. o. Ida\nPersson. G. 38 m. Lillly Persson.\nBarn: Björn if. 39, Inger 412, Eva 44.\n—■ Tekn. stud:ex. i Malmö 29, avg:ex.\n(fr. KTH 35. Ing. v. Waggonfalbr. i\nArlöv 29’ o. 311, bitr. ing. h. bergsing.\nE. A. Åkerman i Ängelholm v. el.\nmadmletn. i Jugoslav, o. Tjeckoslo v. 30.\nIng.  v. telegr :verket  sed.  35.\n\n",
    "structured": {
        "1": {
            "full_name": "Möller, Albin Jacob",
            "location": "Ängelholm",
            "occupation": "grosshandlare",
            "birth_details": {
                "date": "18/07/1884",
                "place": "Ängelholm",
                "parents": "J. J. M. o. Hilda Pettersson"
            },
            "family": {
                "spouse": "Louise Klinker",
                "marriage_year": "NULL",
                "children": [
                    {
                        "name": "Anna-Louise",
                        "birth_year": "1911"
                    },
                    {
                        "name": "Margit",
                        "birth_year": "1913"
                    },
                    {
                        "name": "Vera",
                        "birth_year": "1917"
                    },
                    {
                        "name": "Ture",
                        "birth_year": "1918"
                    },
                    {
                        "name": "Brita",
                        "birth_year": "1923"
                    }
                ]
            },
            "education": [
                {
                    "degree": "Stud.",
                    "year": "NULL",
                    "institution": "Ilä-rov. o. hand :sk."
                },
                {
                    "degree": "Enigil.",
                    "year": "27",
                    "institution": "Tysk!"
                },
                {
                    "degree": "Frankr.",
                    "year": "27",
                    "institution": "NULL"
                },
                {
                    "degree": "Schweiz",
                    "year": "27",
                    "institution": "NULL"
                },
                {
                    "degree": "Ital.",
                    "year": "1930",
                    "institution": "NULL"
                },
                {
                    "degree": "Höll.",
                    "year": "1935",
                    "institution": "NULL"
                },
                {
                    "degree": "Belg.",
                    "year": "1935",
                    "institution": "NULL"
                },
                {
                    "degree": "Norge",
                    "year": "1938",
                    "institution": "NULL"
                }
            ],
            "career": [
                {
                    "position": "Anst. i gross : firmor i Ängelholm o. Hälsingb.",
                    "years": {
                        "start_year": 1900,
                        "end_year": 1912
                    },
                    "organization": "NULL"
                },
                {
                    "position": "egen gross :firnia i Ängelholm",
                    "years": {
                        "start_year": 1913,
                        "end_year": "NULL"
                    },
                    "organization": "NULL"
                }
            ]
        },
        "2": {
            "full_name": "Möller, Axel Bernhard Gottfrid",
            "location": "Malmö",
            "occupation": "hovrättsråd",
            "birth_details": {
                "date": "29/06/1901",
                "place": "Iilstorp, Malmöh",
                "parents": "Axel M. o. Mania Herrsitröm"
            },
            "family": {
                "spouse": "NULL",
                "marriage_year": "NULL",
                "children": []
            },
            "education": [
                {
                    "degree": "Stud:ex.",
                    "year": "1919",
                    "institution": "Lund"
                },
                {
                    "degree": "jur. kand.",
                    "year": "1924",
                    "institution": "NULL"
                }
            ],
            "career": [
                {
                    "position": "e. o. not. i Skånska (hovr.",
                    "years": {
                        "start_year": 1924,
                        "end_year": 1924
                    },
                    "organization": "NULL"
                },
                {
                    "position": "tingstjg. i Färs! här. doms.",
                    "years": {
                        "start_year": 1927,
                        "end_year": 1930
                    },
                    "organization": "NULL"
                },
                {
                    "position": "e. o. fiskal där",
                    "years": {
                        "start_year": 1932,
                        "end_year": 1932
                    },
                    "organization": "NULL"
                },
                {
                    "position": "bitr. dbm. i Frosta o. Eslövs doms.",
                    "years": {
                        "start_year": 1933,
                        "end_year": 1933
                    },
                    "organization": "NULL"
                },
                {
                    "position": "sekr. där",
                    "years": {
                        "start_year": 1933,
                        "end_year": 1934
                    },
                    "organization": "NULL"
                },
                {
                    "position": "assess. i Skånska hovr.",
                    "years": {
                        "start_year": 1937,
                        "end_year": 1937
                    },
                    "organization": "NULL"
                }
            ]
        },
        "3": {
            "full_name": "Möller, Bertil Anton Wilhelm1",
            "location": "Hälsingborg",
            "occupation": "linjeingenjör",
            "birth_details": {
                "date": "01/12/1909",
                "place": "Malmö",
                "parents": "Ifalhr. Kristian M. o. Ida Persson"
            },
            "family": {
                "spouse": "Lily Persson",
                "marriage_year": "1938",
                "children": [
                    {
                        "name": "Björn",
                        "birth_year": "1939"
                    },
                    {
                        "name": "Inger",
                        "birth_year": "1942"
                    },
                    {
                        "name": "Eva",
                        "birth_year": "1944"
                    }
                ]
            },
            "education": [
                {
                    "degree": "Tekn. stud:ex.",
                    "year": "1929",
                    "institution": "Malmö"
                },
                {
                    "degree": "avg:ex. (fr. KTH",
                    "year": "1935",
                    "institution": "NULL"
                }
            ],
            "career": [
                {
                    "position": "Ing. v. Waggonfabr. i Arlöv",
                    "years": {
                        "start_year": 1929,
                        "end_year": 1931
                    },
                    "organization": "NULL"
                },
                {
                    "position": "bitr. ing. h. bergsing. E. A. Åkerman i Ängelholm v. el.",
                    "years": {
                        "start_year": "NULL",
                        "end_year": "NULL"
                    },
                    "organization": "madmletn. i Jugoslav, o. Tjeckoslo v. 30. Ing.  v. telegr :verket  sed.  35"
                }
            ]
        }
    }
}