{
    "original": "Göteborg, f. 14/3/10 i Gbg av Hans G.\no. Selma Andersdotter. ■— Stud:ex. 29.\nHar utf. en mängd karikatyrer i\ndagspress o. veckotidskr. Teckn. i D. N. fr.\n32, i Morgontidn. i Gbg 33-40. Utger\nårl. ett teckn:album fr. 33.\n\nGahm, John Arthur, direktör,\nGöteborg, f. 2W8/86 i Gbg av överdir. John\nA. G. o. Emilia Wennermark. G. 10\nm. Edith Estberg. Barn: Gunvor, g.\nWeissenrieder. — Genomg. Gbgs\nhand :inst. ’Resande i firma John A.\nGahm 06-07, ink :chef i A-B John A.\nGahm 07-19, verkst. dir. där sed. 19.\nOrdf. i styr. f. A-B John A. Gahm,\nled. av .styr. f. Gbgs Sparbank,\nRänte-o. Kapitalförsäkr :anst., Gbgs\nträdg:-fören. o. Sv. arb :giv :fören. allm.\ngrupp.\n\nGamstedt, Erik Vilhe|lm,\npolismästare, Halmstad, f. 30/9/09’ i Malmö. G.\n38 m. Alice Ternby. Barn: Bengt f.\n39, Karin 46. — Stud:ex. 28., jurl\nkand. 34, poHischefskurs 38-39.\nTings-tjg. 34-37, landsfogdeassist. i Malmöh.,\nVästernorrl. o. Sthlms 1. 37-38,\nlands-fogdeassist. i Sthlms 1. 39, polismäst.\n\n0.\tstadsfiskall i Halmstad sed. 40. V.\nkrigsfiskal v. Hall. reg. o. Halll.\nflygflott. sed. 41.\n\nGarby, Karl Elias, prakt, läkare,\nBorås, f. 18/7/91 i Forserum, Jönköp.\n\n1.\tG. 21 m. Ragnhild Grindal. Barn:\nLena f. 22, Lars 24, Britta 25. —\nStud:-ex. i Skara 11, med. kand. i Upp.s. 17,\nmed. lic. i Sthlm 23. Stud:res. t.\ndanska kurorter 26 o. t. tyska dito 27.\nE. läk. v. Mora las. 19, v. Domnarvets\nJärnverk, i Alfta o. Burträsks distr.\nkort. tider 20, i Alfta o. Orsa distr.\nkort. tider 21-22, åter v. Domnarvets\n\nJärnverk 22, e. aman. v. Seraf :ilas.\nklin. f. nervsjukd. 22-23, tf. andre\nlas:-und :lläk. i Kallmar 23-24, uppr. förordn.\ns. e. läk., und:läk. o. tf. överläk. v.\nMössebergs sanat. 25-26, prakt. läk. i\nBorås o. överläk. v. Hultafors sanat.\nsed. 26.\n\n",
    "structured": {
        "1": {
            "full_name": "Gahm, John Arthur",
            "location": "Göteborg",
            "occupation": "Direktör",
            "birth_details": {
                "date": "28/08/1886",
                "place": "Göteborg",
                "parents": "John A. G. o. Emilia Wennermark",
                "place_coordinates": {
                    "Latitude": 57.70887,
                    "Longitude": 11.97456
                }
            },
            "education": [
                {
                    "degree": "Genomg.",
                    "year": "06-07",
                    "institution": "Gbgs hand :inst.",
                    "institution_coordinates": {
                        "Latitude": 60.12816100000001,
                        "Longitude": 18.643501
                    }
                },
                {
                    "degree": "Ink :chef",
                    "year": "07-19",
                    "institution": "A-B John A. Gahm",
                    "institution_coordinates": {
                        "Latitude": 60.12816100000001,
                        "Longitude": 18.643501
                    }
                }
            ],
            "career": [
                {
                    "position": "Resande",
                    "years": {
                        "start_year": 1906,
                        "end_year": 1907
                    },
                    "organization": "firma John A. Gahm"
                },
                {
                    "position": "Ink :chef",
                    "years": {
                        "start_year": 1907,
                        "end_year": 1919
                    },
                    "organization": "A-B John A. Gahm"
                },
                {
                    "position": "Verkst. dir.",
                    "years": {
                        "start_year": 1919,
                        "end_year": null
                    },
                    "organization": "A-B John A. Gahm"
                }
            ],
            "family": {
                "spouse": "Edith Estberg",
                "marriage_year": "10",
                "children": [
                    {
                        "name": "Gunvor",
                        "birth_year": null
                    }
                ]
            },
            "location_coordinates": {
                "Latitude": 57.70887,
                "Longitude": 11.97456
            }
        },
        "2": {
            "full_name": "Gamstedt, Erik Vilhelm",
            "location": "Halmstad",
            "occupation": "Polismästare",
            "birth_details": {
                "date": "30/09/1909",
                "place": "Malmö",
                "parents": null,
                "place_coordinates": {
                    "Latitude": 55.604981,
                    "Longitude": 13.003822
                }
            },
            "education": [
                {
                    "degree": "Stud",
                    "year": "28",
                    "institution": null
                },
                {
                    "degree": "Jurl kand.",
                    "year": "34",
                    "institution": null
                },
                {
                    "degree": "PolHischefskurs",
                    "year": "38-39",
                    "institution": null
                }
            ],
            "career": [
                {
                    "position": "Tings-tjg.",
                    "years": {
                        "start_year": 1934,
                        "end_year": 1937
                    },
                    "organization": null
                },
                {
                    "position": "Polismäst",
                    "years": {
                        "start_year": 1940,
                        "end_year": null
                    },
                    "organization": "Halmstad"
                }
            ],
            "family": {
                "spouse": "Alice Ternby",
                "marriage_year": "38",
                "children": [
                    {
                        "name": "Bengt",
                        "birth_year": "39"
                    },
                    {
                        "name": "Karin",
                        "birth_year": "46"
                    }
                ]
            },
            "location_coordinates": {
                "Latitude": 56.6743748,
                "Longitude": 12.8577884
            }
        },
        "3": {
            "full_name": "Garby, Karl Elias",
            "location": "Borås",
            "occupation": "Prakt. läkare",
            "birth_details": {
                "date": "18/07/1891",
                "place": "Forserum, Jönköp.",
                "parents": null,
                "place_coordinates": {
                    "Latitude": 57.69932780000001,
                    "Longitude": 14.475408
                }
            },
            "education": [
                {
                    "degree": "Stud:-ex.",
                    "year": "11",
                    "institution": "Skara",
                    "institution_coordinates": {
                        "Latitude": 58.3860128,
                        "Longitude": 13.4393282
                    }
                },
                {
                    "degree": "Med. kand.",
                    "year": "17",
                    "institution": "Upp.s.",
                    "institution_coordinates": {
                        "Latitude": 60.12816100000001,
                        "Longitude": 18.643501
                    }
                },
                {
                    "degree": "Med. lic.",
                    "year": "23",
                    "institution": "Sthlm",
                    "institution_coordinates": {
                        "Latitude": 59.32932349999999,
                        "Longitude": 18.0685808
                    }
                }
            ],
            "career": [
                {
                    "position": "E. läk.",
                    "years": {
                        "start_year": 1919,
                        "end_year": null
                    },
                    "organization": "Mora las."
                },
                {
                    "position": "Prakt. läk.",
                    "years": {
                        "start_year": 1926,
                        "end_year": null
                    },
                    "organization": "Borås"
                },
                {
                    "position": "Överläk.",
                    "years": {
                        "start_year": 1926,
                        "end_year": null
                    },
                    "organization": "Hultafors sanat."
                }
            ],
            "family": {
                "spouse": "Ragnhild Grindal",
                "marriage_year": "21",
                "children": [
                    {
                        "name": "Lena",
                        "birth_year": "22"
                    },
                    {
                        "name": "Lars",
                        "birth_year": "24"
                    },
                    {
                        "name": "Britta",
                        "birth_year": "25"
                    }
                ]
            },
            "location_coordinates": {
                "Latitude": 57.72103500000001,
                "Longitude": 12.939819
            }
        }
    }
}