{
    "original": "OLAUSSON, FRANZ E, överingenjör,\n\nSundsvall,  f  i  Trollhättan  25/1/18   av\nbergsing Ernfrid O o Mona Krönlein.\nStud:ex Gbg 38, CTH 42, anst SJ 42,\nbandistr:ch o övering Sundsvall sed 63.\n\n-  Ordf Sundsvalls tjm:sällsk sed 59, medl\nRotary. - Utm: RNO, HvGM, SJ\ndriftv-SM. - Hobbies: fiske, sport.\n\nGift 43 m Iwa Asplöf f 20, dtr t\ndom-kyrkoorg Herman A o Wendla Skytte af\nSätra. - Barn: Hans f 44, John f 48.\n\nOLAVI, BENGT J A, förste\nlänsno-tarie, Härnösand, f i Skara 14/10/23.\nStud:ex Kristianstad 42, jur kand Lund\n51, tingstjg Hammarkinds, Stegeborgs o\nSkärkinds doms 52-54, anst länsstyr\nVnorrl l 55, eo länsnot 56, l:e länsnot\nsed 62.\n\nGift 53 m Kerstin Petersson f 29.\n-Barn: Sten Mikael f 58, Inger Marie\nf 63.\n\nOLDBY, NILS A, överläkare, Piteå, f\ni Gbg 17/9/11 av skatteexekutor Arvid\nHanson o h h.\n\nStud:ex Gbg 29, med kand Upps 32,\nmed lic Sthlm 38, öl läk:förordn 39-41,\nunderläk kir avd Maria sjh o Södersjh\n42-45, tf överläk o sjukstugeläk öl\nplatser 45-47, l:e underläk Varbergs las\n48-50, kir avd Ängelholms las 51-54, e läk\nkir o ortop klin Lunds las 54-57, bitr\növerläk kir avd Luleå las 57-58, överläk\nkir avd Piteå las sed 58. - Stud:resa\nSydamer 45. - Medl Rotary. - Skr i kir,\nortop, fackl o sjh:org frågor. - Hobby:\ngolf.\n\nGift 1) 41-47 m Ingeborg Norrby, 2) 48\nm Ingrid Robähr. - Barn: i l:a akt Eva\nf 41, i 2:a akt Mikael f 49, Hans-Otto\nf 50, Kerstin f 52, Fredrik f 56, Christer\nf 60.\n\n",
    "structured": {
        "0": {
            "full_name": "Franz E Olausson",
            "location": "Sundsvall",
            "occupation": "Överingenjör",
            "birth_details": {
                "date": "25/01/1918",
                "place": "Trollhättan"
            },
            "education": [
                {
                    "degree": "Stud:ex",
                    "year": "1938",
                    "institution": "Gbg"
                },
                {
                    "degree": "CTH",
                    "year": "1942",
                    "institution": "SJ"
                }
            ],
            "career": [
                {
                    "position": "Bandistr:ch",
                    "years": {
                        "start_year": 1942,
                        "end_year": 1963
                    },
                    "organization": "SJ"
                },
                {
                    "position": "Övering",
                    "years": {
                        "start_year": 1963,
                        "end_year": null
                    },
                    "organization": "Sundsvall"
                }
            ],
            "family": {
                "spouse": "Iwa Asplöf",
                "marriage_year": "1943",
                "children": [
                    {
                        "name": "Hans",
                        "birth_year": "1944"
                    },
                    {
                        "name": "John",
                        "birth_year": "1948"
                    }
                ]
            },
            "hobbies": [
                "fiske",
                "sport"
            ]
        },
        "1": {
            "full_name": "Bengt J A Olavi",
            "location": "Härnösand",
            "occupation": "Förste länsnotarie",
            "birth_details": {
                "date": "14/10/1923",
                "place": "Skara"
            },
            "education": [
                {
                    "degree": "Stud:ex",
                    "year": "1942",
                    "institution": "Kristianstad"
                },
                {
                    "degree": "Jur kand",
                    "year": "1951",
                    "institution": "Lund"
                }
            ],
            "career": [
                {
                    "position": "Tingstjg",
                    "years": {
                        "start_year": 1952,
                        "end_year": 1954
                    },
                    "organization": "Hammarkinds, Stegeborgs, Skärkinds doms"
                },
                {
                    "position": "Anst länsstyr",
                    "years": {
                        "start_year": 1955,
                        "end_year": 1955
                    },
                    "organization": "Vnorrl l"
                },
                {
                    "position": "Eo länsnot",
                    "years": {
                        "start_year": 1956,
                        "end_year": 1962
                    },
                    "organization": null
                }
            ],
            "family": {
                "spouse": "Kerstin Petersson",
                "marriage_year": "1953",
                "children": [
                    {
                        "name": "Sten Mikael",
                        "birth_year": "1958"
                    },
                    {
                        "name": "Inger Marie",
                        "birth_year": "1963"
                    }
                ]
            }
        },
        "2": {
            "full_name": "Nils A Oldby",
            "location": "Piteå",
            "occupation": "Överläkare",
            "birth_details": {
                "date": "17/09/1911",
                "place": "Göteborg"
            },
            "education": [
                {
                    "degree": "Stud:ex",
                    "year": "1929",
                    "institution": "Göteborg"
                },
                {
                    "degree": "Med kand",
                    "year": "1932",
                    "institution": "Upps"
                },
                {
                    "degree": "Med lic",
                    "year": "1938",
                    "institution": "Sthlm"
                }
            ],
            "career": [
                {
                    "position": "Öl läk:förordn",
                    "years": {
                        "start_year": 1939,
                        "end_year": 1941
                    },
                    "organization": null
                },
                {
                    "position": "Underläk",
                    "years": {
                        "start_year": 1942,
                        "end_year": 1945
                    },
                    "organization": "Kir avd Maria sjh o Södersjh"
                },
                {
                    "position": "Tf överläk",
                    "years": {
                        "start_year": 1945,
                        "end_year": 1947
                    },
                    "organization": "Öl platser"
                },
                {
                    "position": "L:e underläk",
                    "years": {
                        "start_year": 1948,
                        "end_year": 1950
                    },
                    "organization": "Varbergs las"
                },
                {
                    "position": "Kir avd",
                    "years": {
                        "start_year": 1951,
                        "end_year": 1954
                    },
                    "organization": "Ängelholms las"
                },
                {
                    "position": "E läk kir o ortop klin",
                    "years": {
                        "start_year": 1954,
                        "end_year": 1957
                    },
                    "organization": "Lunds las"
                },
                {
                    "position": "Bitr överläk kir avd",
                    "years": {
                        "start_year": 1957,
                        "end_year": 1958
                    },
                    "organization": "Luleå las"
                },
                {
                    "position": "Överläk kir avd",
                    "years": {
                        "start_year": 1958,
                        "end_year": null
                    },
                    "organization": "Piteå las"
                }
            ],
            "family": {
                "spouse": "1) Ingeborg Norrby, 2) Ingrid Robähr",
                "marriage_year": "1) 1941-1947, 2) 1948",
                "children": [
                    {
                        "name": "Eva",
                        "birth_year": "1941"
                    },
                    {
                        "name": "Mikael",
                        "birth_year": "1949"
                    },
                    {
                        "name": "Hans-Otto",
                        "birth_year": "1950"
                    },
                    {
                        "name": "Kerstin",
                        "birth_year": "1952"
                    },
                    {
                        "name": "Fredrik",
                        "birth_year": "1956"
                    },
                    {
                        "name": "Christer",
                        "birth_year": "1960"
                    }
                ],
                "hobbies": [
                    "golf"
                ]
            }
        }
    }
}