{
    "original": "SJÖGREN, JAN-ERIK G H, intendent,\n\nSandviken, f i Sthlm 21/4/28 av kamr\nErie S o Hertha Jönsson.\nStud:ex 47, DHS 53, sortim:ch\nMaskin-aff Carl Lamm ab 58, markn:ch inom\nstålförsäljn Sandvikens jernv ab sed 64.\nGift 54 m Barbro Norringe f 28, dtr t\nrev   Hilbert   N   o   Judith   Broström.\n-Barn: Håkan f 57.\n\nSJÖGREN,   PAUL,   överbibliotekarie,\n\nUmeå, f i Nydala, Jönkpgs l, 22/8/11 av\nkyrkoh Håkan S o Sigrid Karlsson.\nStud:ex Jönkpg 29, fil mag 35, fil lic 40,\nfil dr o doc i historia Upps 44; öl\nlär:-förordn 37-45, aman Upps univ :bibl 45,\nbibl:ie 49, l:e bibl:ie där 57, överbibl:ie\nUmeå univ :bibl sed 64. - LSkS 52,\nLHVS 62. - Skr: Släkten Trolles historia\nintill år 1505 (drsavh 44), Ätten Posses\nhistoria intill år 1500 (50), Sv hist\nbibliografi 1921-1935 (56), art i tidskr, tidn\no uppsl :verk.\n\nGift 40 m fil mag Birgit Väjne f 16, dtr\nt folksk :insp Oscar V o Alma Lindsten.\n\n-  Barn: Birgitta f 40, Sven f 45, Mats\nf 47, Jan f 51, Per f 57.\n\nSJÖGREN, ROLF J O, direktör, Umeå,\nf  i  Vännäs,  Västerb l, 24/6/09 av dir\nJohan S o Alma Ohlsson.\nStud:ex Umeå 29, DHS 33, verkst dir\nab  Västerb   Odéonbiografer Umeå  sed\n35. - Hobbies: litteratur, konst.\nGift 42 m Karin Pettersson, dtr t\nsjö-kapt Helmer P  o Hilda Nordström.\n-Barn: Olle f 43, Anders f 47.\n\nSJÖGREN, M SUNE, tandläkare,\nGävle, f i Åskilje, Västerb l, 7/1/31 av\nhemul :äg Magnus S o Jenny Persson.\nStud:ex  Skellefteå  52,  tandl:ex  Malmö\n57, priv:prakt Gävle sed 59.\nGift 56 m Sonja Carlsson f 32. - Barn:\nAgneta f 56, Magnus f 62, Eva o Maria\nff 64.\n\n",
    "structured": {
        "1": {
            "full_name": "Jan-Erik G H Sjögren",
            "location": "Sandviken",
            "occupation": "Intendent",
            "birth_details": {
                "date": "21/04/1928",
                "place": "Stockholm"
            },
            "education": [
                {
                    "degree": "Stud:ex",
                    "year": "1947",
                    "institution": "Not found"
                },
                {
                    "degree": "DHS",
                    "year": "1953",
                    "institution": "Not found"
                }
            ],
            "career": [
                {
                    "position": "Sortim:ch Maskin-aff Carl Lamm ab",
                    "years": {
                        "start_year": 1958,
                        "end_year": 1964
                    },
                    "organization": "Not found"
                },
                {
                    "position": "Markn:ch inom stålförsäljn Sandvikens jernv ab",
                    "years": {
                        "start_year": 1964,
                        "end_year": null
                    },
                    "organization": "Not found"
                }
            ],
            "family": {
                "spouse": "Barbro Norringe",
                "marriage_year": "1954",
                "children": [
                    {
                        "name": "Håkan",
                        "birth_year": "1957"
                    }
                ]
            }
        },
        "2": {
            "full_name": "Paul Sjögren",
            "location": "Umeå",
            "occupation": "Överbibliotekarie",
            "birth_details": {
                "date": "22/08/1911",
                "place": "Nydala, Jönkpgs l"
            },
            "education": [
                {
                    "degree": "Stud:ex",
                    "year": "1929",
                    "institution": "Jönkpg"
                },
                {
                    "degree": "Fil mag",
                    "year": "1935",
                    "institution": "Not found"
                },
                {
                    "degree": "Fil lic",
                    "year": "1940",
                    "institution": "Not found"
                },
                {
                    "degree": "Fil dr o doc i historia",
                    "year": "Not found",
                    "institution": "Upps"
                }
            ],
            "career": [
                {
                    "position": "lär:-förordn",
                    "years": {
                        "start_year": 1937,
                        "end_year": 1945
                    },
                    "organization": "Not found"
                },
                {
                    "position": "aman Upps univ :bibl",
                    "years": {
                        "start_year": 1945,
                        "end_year": null
                    },
                    "organization": "Not found"
                },
                {
                    "position": "bibl:ie",
                    "years": {
                        "start_year": 1949,
                        "end_year": null
                    },
                    "organization": "Not found"
                },
                {
                    "position": "l:e bibl:ie där",
                    "years": {
                        "start_year": 1957,
                        "end_year": null
                    },
                    "organization": "Not found"
                },
                {
                    "position": "överbibl:ie Umeå univ :bibl",
                    "years": {
                        "start_year": 1964,
                        "end_year": null
                    },
                    "organization": "Not found"
                }
            ],
            "family": {
                "spouse": "Birgit Väjne",
                "marriage_year": "1940",
                "children": [
                    {
                        "name": "Birgitta",
                        "birth_year": "1940"
                    },
                    {
                        "name": "Sven",
                        "birth_year": "1945"
                    },
                    {
                        "name": "Mats",
                        "birth_year": "1947"
                    },
                    {
                        "name": "Jan",
                        "birth_year": "1951"
                    },
                    {
                        "name": "Per",
                        "birth_year": "1957"
                    }
                ]
            }
        },
        "3": {
            "full_name": "Rolf J O Sjögren",
            "location": "Umeå",
            "occupation": "Direktör",
            "birth_details": {
                "date": "24/06/1909",
                "place": "Vännäs, Västerb l"
            },
            "education": [],
            "career": [
                {
                    "position": "verkst dir ab Västerb Odéonbiografer Umeå",
                    "years": {
                        "start_year": 1935,
                        "end_year": null
                    },
                    "organization": "Not found"
                }
            ],
            "family": {
                "spouse": "Karin Pettersson",
                "marriage_year": "1942",
                "children": [
                    {
                        "name": "Olle",
                        "birth_year": "1943"
                    },
                    {
                        "name": "Anders",
                        "birth_year": "1947"
                    }
                ]
            }
        },
        "4": {
            "full_name": "M Sune Sjögren",
            "location": "Gävle",
            "occupation": "Tandläkare",
            "birth_details": {
                "date": "07/01/1931",
                "place": "Åskilje, Västerb l"
            },
            "education": [
                {
                    "degree": "Stud:ex",
                    "year": "1952",
                    "institution": "Skellefteå"
                },
                {
                    "degree": "Tandl:ex",
                    "year": "1957",
                    "institution": "Malmö"
                }
            ],
            "career": [
                {
                    "position": "Priv:prakt Gävle",
                    "years": {
                        "start_year": 1959
                    },
                    "organization": "Not found"
                }
            ],
            "family": {
                "spouse": "Sonja Carlsson",
                "marriage_year": "1956",
                "children": [
                    {
                        "name": "Agneta",
                        "birth_year": "1956"
                    },
                    {
                        "name": "Magnus",
                        "birth_year": "1962"
                    },
                    {
                        "name": "Eva",
                        "birth_year": "1964"
                    },
                    {
                        "name": "Maria",
                        "birth_year": "1964"
                    }
                ]
            }
        }
    }
}