{
    "original": "SANDELIN, TURE J B, länsassessor,\n\nUmeå, f i Falun 22/5/15 av distr:lantmät\nBirger S o Ingeborg Millqvist.\nStud:ex Skara 33, jur kand Upps 37,\ntingstjg Jösse doms 37-40, tjg Göta hovr\n40-41, e länsnot Gotl l 41, eo länsnot där\n44, Älvsb l 51, l:e länsnot där 53,\nläns-assess Västerb l doms sed 61. - Rev\nsparbk, ordf hyresnd o hyresmedl:nd,\nsekr Älvsb l naturskyddsråd.\nGift 43 m Dagmar Alyhr f 16, dtr t fabr\nHenrik A o Anna-Maria Lutteman.\n-Barn: Anna Christina f 44, Ingeborg\nElisabeth f 46, Astri Margareta f 53.\n\nSANDELL, CARL-HENRIK A,\nläroverksadjunkt, Haparanda, f i Luleå 13/1 Ö/\n27 av lärov:adj Carl S o Ingrid Wikén.\nFil mag Upps 56, adj hal Haparanda\nsed 56, eo lekt i ty o f ra där sed 63.\nGift 56 m Kerstin Andersson f 31, dtr t\nfil lic Hugo A o Brita Weibull. - Barn:\nAnders f 57, Birgitta f 61.\n\nSANDER, S BARBRO, adjunkt, Umeå,\nf i Nordmaling, Västerb l, 12/4/37 av\nmål Georg Andersson o Svea Söderberg.\n\nStud:ex Umeå 58, fil måg Upps 63, lär\nBureå centralsk 63, eo adj Tegs\ncentral-sk sed 64.\nGift 65 m ämneslär Gunnar Sander f 36.\n\n- Barn: Christina f 66.\n\nSANDER, TORSTEN A O,\növerlantmätare, Umeå, f i Karesuando, Norrb l,\n23/2/W av vägmäst Oscar S o Emma\nMarklund.\n\nLantmät:ex 33, lantmät Norrbotten\n33-40, 43-48, tjg lantmät:styr 41-43, bitr\növerlantmät Luleå 48-51, överlantmät\nVästerb l sed 51. - Ordf o led olika\nplaner :komm o ndr 47-51, expert 51 års\njordbr:rationaliser:utredn o 54 års\nfas-tighetsbildn :komm, styr :ordf ab\nBetong-Sänder o ab Västerb :bryggerier. - Utm:\nRNO.\n\nGift 38 m Gun Lindquist f 17, dtr t\nkonsul Melcher L o Aiwa Hedberg.\n-Barn: Lena f 40, Lars f 44, Annika f 50.\n\n",
    "structured": {
        "0": {
            "full_name": "TURE J B SANDELIN",
            "location": "Umeå",
            "occupation": "Länsassessor",
            "birth_details": {
                "date": "22/05/1915",
                "place": "Falun",
                "parents": "Birger S och Ingeborg Millqvist"
            },
            "education": [
                {
                    "degree": "Stud:ex",
                    "year": "1933",
                    "institution": "Skara"
                },
                {
                    "degree": "Jur kand",
                    "year": "1937",
                    "institution": "Upps"
                }
            ],
            "career": [
                {
                    "position": "Tingstjg",
                    "years": {
                        "start_year": 1937,
                        "end_year": 1940
                    },
                    "organization": "Jösse doms"
                },
                {
                    "position": "Tjg",
                    "years": {
                        "start_year": 1940,
                        "end_year": 1941
                    },
                    "organization": "Göta hovr"
                },
                {
                    "position": "E länsnot",
                    "years": {
                        "start_year": 1941,
                        "end_year": 1944
                    },
                    "organization": "Gotl"
                },
                {
                    "position": "Eo länsnot",
                    "years": {
                        "start_year": 1944,
                        "end_year": 1951
                    },
                    "organization": "Älvsb l"
                },
                {
                    "position": "L:e länsnot",
                    "years": {
                        "start_year": 1951,
                        "end_year": 1953
                    },
                    "organization": "Älvsb l"
                },
                {
                    "position": "Läns-assess",
                    "years": {
                        "start_year": 1961
                    },
                    "organization": "Västerb l doms"
                }
            ],
            "family": {
                "spouse": "Dagmar Alyhr",
                "marriage_year": "1943",
                "children": [
                    {
                        "name": "Anna Christina",
                        "birth_year": "1944"
                    },
                    {
                        "name": "Ingeborg Elisabeth",
                        "birth_year": "1946"
                    },
                    {
                        "name": "Astri Margareta",
                        "birth_year": "1953"
                    }
                ]
            }
        },
        "1": {
            "full_name": "CARL-HENRIK A SANDELL",
            "location": "Haparanda",
            "occupation": "Läroverksadjunkt",
            "birth_details": {
                "date": "13/01/1927",
                "place": "Luleå",
                "parents": "Lärov:adj Carl S och Ingrid Wikén"
            },
            "education": [
                {
                    "degree": "Fil mag",
                    "year": "1956",
                    "institution": "Upps"
                }
            ],
            "career": [
                {
                    "position": "Adj",
                    "years": {
                        "start_year": 1956
                    },
                    "organization": "Haparanda"
                },
                {
                    "position": "Eo lekt",
                    "years": {
                        "start_year": 1963
                    },
                    "organization": "Haparanda"
                }
            ],
            "family": {
                "spouse": "Kerstin Andersson",
                "marriage_year": "1956",
                "children": [
                    {
                        "name": "Anders",
                        "birth_year": "1957"
                    },
                    {
                        "name": "Birgitta",
                        "birth_year": "1961"
                    }
                ]
            }
        },
        "2": {
            "full_name": "S BARBRO SANDER",
            "location": "Umeå",
            "occupation": "Adjunkt",
            "birth_details": {
                "date": "12/04/1937",
                "place": "Nordmaling, Västerb l",
                "parents": "Georg Andersson och Svea Söderberg"
            },
            "education": [
                {
                    "degree": "Stud:ex",
                    "year": "1958",
                    "institution": "Umeå"
                },
                {
                    "degree": "Fil måg",
                    "year": "1963",
                    "institution": "Upps"
                }
            ],
            "career": [
                {
                    "position": "Lär",
                    "years": {
                        "start_year": 1964
                    },
                    "organization": "Tegs central-sk"
                }
            ],
            "family": {
                "spouse": "Gunnar Sander",
                "marriage_year": "1965",
                "children": [
                    {
                        "name": "Christina",
                        "birth_year": "1966"
                    }
                ]
            }
        },
        "3": {
            "full_name": "TORSTEN A O SANDER",
            "location": "Umeå",
            "occupation": "Överlantmätare",
            "birth_details": {
                "date": "23/02/????",
                "place": "Karesuando, Norrb l",
                "parents": "Oscar S och Emma Marklund"
            },
            "education": [
                {
                    "degree": "Lantmät:ex",
                    "year": "1933"
                }
            ],
            "career": [
                {
                    "position": "Lantmät",
                    "years": {
                        "start_year": 1933,
                        "end_year": 1940
                    },
                    "organization": "Norrbotten"
                },
                {
                    "position": "Bitr överlantmät",
                    "years": {
                        "start_year": 1948,
                        "end_year": 1951
                    },
                    "organization": "Luleå"
                },
                {
                    "position": "Överlantmät",
                    "years": {
                        "start_year": 1951
                    },
                    "organization": "Västerb l"
                }
            ],
            "family": {
                "spouse": "Gun Lindquist",
                "marriage_year": "1938",
                "children": [
                    {
                        "name": "Lena",
                        "birth_year": "1940"
                    },
                    {
                        "name": "Lars",
                        "birth_year": "1944"
                    },
                    {
                        "name": "Annika",
                        "birth_year": "1950"
                    }
                ]
            }
        }
    }
}