{
    "original": "SUNDVALL, N GÖSTA, tandläkare,\n\nLuleå, f i Kalix, Norrb l, 1/7/22 av Axel\nS o Josefina Johansson.\nStud:ex Luleå  33, tandl:ex  Malmö  50,\ndistr:tandl  Luleå  50-52,  Härads   52-54,\nl:e distr:tandl Boden 54-55, priv:prakt\n\nÄlvsbyn 55-65, Luleå sed 65. - Ordf\nNorrb tjänstetandl:fören 54-55, styr:led\nNorrb tandl:fören 57-58. - Medl W-sex,\nLions club. - Hobbies: sport, fiske.\nGift 51 m Ester Tapani f 24, dtr t\nGustaf T o Vendia Kitti. - Barn: Kjell f 53,\nKarin f 56.\n\nSUNDWALL,   J   HÅKAN,   direktör,\n\nSkellefteå, f i Älvsbyn, Norrb l, 26/4/23\nav köpm John S o Agda Wiklund.\nInsp Livförsäkr ab Framtiden 52,\ndistr:-ch 53, konsulent 56, org:ch 57,\nförsäljn:-ch där 60, ab Bröd Forslund Skellefteå\n62, dir o inneh Bil-Sundwall ab sed 65.\n-Gen :sekr SM på skidor Umeå 61, medl\nSkellefteå AIK/IF; Odd Fellow. - Hobby:\nsport.\n\nGift 43 m Britt Lindgren f 23, dtr t\nBernhard L o Betty L. - Barn: Kurt\nf 44, Anders f 51.\n\nSUNNBERG, TAGE G, civilingenjör,\n\nSöderhamn,  f   i   Gnesta,   Södermani  l,\n\n3/12/04  av  köpm  Gustaf  S  o Amalia\n\nJanzon.\n\nStud:ex Södertälje 23, KTH 28, ass inst\n\nf oorg kemi KTH 32, drifting ab Tan-\n\nnin 35, försäljn:dir Bergvik o Ala ab sed\n\n40. - Verkst dir Bergviks hartsprodukter\n\nab sed 52, Kem ab Weibull sed 66, styr:-\n\nled   Garvämnes   ab   Weibull  sed  66.   -\n\nMedl   Odd   Fellow.   -   Hobbies:   foto,\n\nmusik.\n\nGift 34 m Kate Möller f 10. - Barn:\n\nUlla f 38, Jan f 40, Inga f 45.\n\n",
    "structured": {
        "1": {
            "full_name": "Sundvall, N Gösta",
            "location": "Luleå",
            "occupation": "tandläkare",
            "birth_details": {
                "date": "01/07/1922",
                "place": "Kalix, Norrbottens län",
                "parents": "Axel S och Josefina Johansson"
            },
            "education": [
                {
                    "degree": "Stud:ex",
                    "year": "1933",
                    "institution": "Luleå"
                },
                {
                    "degree": "tandl:ex",
                    "year": "1950",
                    "institution": "Malmö"
                }
            ],
            "career": [
                {
                    "position": "distr:tandl",
                    "years": {
                        "start_year": 1950,
                        "end_year": 1952
                    },
                    "organization": "Luleå"
                },
                {
                    "position": "Härads",
                    "years": {
                        "start_year": 1952,
                        "end_year": 1954
                    }
                },
                {
                    "position": "l:e distr:tandl",
                    "years": {
                        "start_year": 1954,
                        "end_year": 1955
                    },
                    "organization": "Boden"
                },
                {
                    "position": "priv:prakt",
                    "years": {
                        "start_year": 1955,
                        "end_year": 1965
                    },
                    "organization": "Älvsbyn"
                },
                {
                    "position": "priv:prakt",
                    "years": {
                        "start_year": 1965
                    },
                    "organization": "Luleå"
                }
            ],
            "family": {
                "spouse": "Ester Tapani",
                "marriage_year": "1951",
                "children": [
                    {
                        "name": "Kjell",
                        "birth_year": "1953"
                    },
                    {
                        "name": "Karin",
                        "birth_year": "1956"
                    }
                ]
            },
            "hobbies": [
                "sport",
                "fiske"
            ]
        },
        "2": {
            "full_name": "Sundwall, J Håkan",
            "location": "Skellefteå",
            "occupation": "direktör",
            "birth_details": {
                "date": "26/04/1923",
                "place": "Älvsbyn, Norrbottens län",
                "parents": "köpm John S o Agda Wiklund"
            },
            "career": [
                {
                    "position": "Insp Livförsäkr ab Framtiden",
                    "years": {
                        "start_year": 1952
                    }
                },
                {
                    "position": "distr:-ch",
                    "years": {
                        "start_year": 1953
                    }
                },
                {
                    "position": "konsulent",
                    "years": {
                        "start_year": 1956
                    }
                },
                {
                    "position": "org:ch",
                    "years": {
                        "start_year": 1957
                    }
                },
                {
                    "position": "försäljn:-ch",
                    "years": {
                        "start_year": 1960
                    },
                    "organization": "ab Bröd Forslund Skellefteå"
                },
                {
                    "position": "dir o inneh Bil-Sundwall ab",
                    "years": {
                        "start_year": 1965
                    }
                }
            ],
            "family": {
                "spouse": "Britt Lindgren",
                "marriage_year": "1943",
                "children": [
                    {
                        "name": "Kurt",
                        "birth_year": "1944"
                    },
                    {
                        "name": "Anders",
                        "birth_year": "1951"
                    }
                ]
            },
            "community_involvement": [
                {
                    "role": "Gen :sekr",
                    "organization": "SM på skidor Umeå",
                    "years": "1961"
                }
            ],
            "hobbies": [
                "sport"
            ]
        },
        "3": {
            "full_name": "Sunnberg, Tage G",
            "location": "Söderhamn",
            "occupation": "civilingenjör",
            "birth_details": {
                "date": "03/12/1904",
                "place": "Gnesta, Södermanlands län",
                "parents": "köpm Gustaf S o Amalia Janzon"
            },
            "education": [
                {
                    "degree": "Stud:ex",
                    "year": "1923",
                    "institution": "Södertälje"
                },
                {
                    "degree": "ass inst f oorg kemi",
                    "year": "1932",
                    "institution": "KTH"
                }
            ],
            "career": [
                {
                    "position": "drifting ab Tannin",
                    "years": {
                        "start_year": 1935
                    }
                },
                {
                    "position": "försäljn:dir",
                    "organization": "Bergvik o Ala ab",
                    "years": {
                        "start_year": 1940
                    }
                },
                {
                    "position": "Verkst dir",
                    "organization": "Bergviks hartsprodukter ab",
                    "years": {
                        "start_year": 1952
                    }
                },
                {
                    "position": "Verkst dir",
                    "organization": "Kem ab Weibull",
                    "years": {
                        "start_year": 1966
                    }
                }
            ],
            "family": {
                "spouse": "Kate Möller",
                "marriage_year": "1934",
                "children": [
                    {
                        "name": "Ulla",
                        "birth_year": "1938"
                    },
                    {
                        "name": "Jan",
                        "birth_year": "1940"
                    },
                    {
                        "name": "Inga",
                        "birth_year": "1945"
                    }
                ]
            },
            "community_involvement": [
                {
                    "role": "Medl",
                    "organization": "Odd Fellow"
                }
            ],
            "hobbies": [
                "foto",
                "musik"
            ]
        }
    }
}