{
    "original": "Schmidt, Torsten Andreas,\növerstelöjtnant, Djursholm, f. 23/2/99 i\nLandskrona av bankdir., v.\nhärads-hövd. Martin S. o. Elisabeth Bruzelius.\nG. 1. 26-36 m. Elsa Vult von Steyern,\n2. 38 m. Karen Bruun von Neergaard.\nBarn: Holger f. 40, Harald f. 41,\nChrister f. 42. Stud :ex. 17, fänr. 19,\nlöjtn. v. Wendes art :reg. 23, kapt. 34,\nmajor o. styresm. f. försv :väs :s kem.\nanst. fr. 37, överstelöjtn. 42. Löjtn.\nv. luftv:art. 28-29, art:- o. ing: högsk.\n21-24 o. bitr. lär. där 34-38,\nart:stabs-off. 32-37, utl. kommend. 31, 36-39, 41,\nbitr. civ. luftskyddsutredn. 36,\nkansli-ch. i försvarets forskn :nd 43. Skr.:\nDet civila luftskyddet i Europa (tills,\nm. Å. Kretz, 37) samt div. tidskr :art.\nRSO, FFrKSkl m sv, RLSFGftjt,\nLKr-VA.\nSchmidt, Wilhelm Georg, direktör,\nSaltsjöbaden, f. 25/12/75 i öved,\nMalmöh. L, av godsförv. Otto Viktor S. o.\nMarie Ducommun. G. 05 m. Frieda\nFanghänel. Barn: Helga Elisabet f.\n07, gymn :dir.; Werner Paul f. 09,\ning.; Erik Wilhelm f. 14, Vera f. 15,\nElsa Marianne f. 19. Stud. v. h. allm.\nlärov, i Lund, elev v. CTL\n(maskin-byggn. o. mek. tekn.) 91-95, stud. v.\nTechn. Hochschule i Karlsruhe.\nKonstr, v. Brown Boveri &amp; Co. i Baden,\nSchweiz, 98-00, konstr, o. senare ch. f.\nmaskinberäkn:avd. o. provrum h.\nHelios Elektrizitäts Gesellschaft i Köln\n00-05, ch. f. elektr, avd. v. Union\nEisen u. Hüttenwerk i Dortmund 05-08,\nverkst, dir. f. ASEA:s norska\ndotter-fabr., Norsk Motor- og Dynamofabr.,\n08-17, dir. o. ch. f. Luth &amp; Roséns\nElektr. A-B :s försäljn:avd. 17-31,\nverkst, dir. f. Sv. Elektrobil A-B fr.\n31. Hobbies: friluftsliv,\nträdgårdsskötsel, golf.\nSchmidt, Viva (Maja) Charlotta,\nfru, Sthlm, f. i ö :a Ed, Kalmar L, av\ndir. Jesper Södergren o. Viva\nBeckeman. G. 01 m. gen:major Tell S., d.\n34. Ordf. i Riksförb. Sv :es\nLottakårer. KFinlLO, FinlVRO, FFrK,\n",
    "structured": {
        "1": {
            "full_name": "Schmidt, Torsten Andreas",
            "location": "Djursholm",
            "occupation": "överstelöjtnant",
            "birth_details": {
                "date": "23/02/1899",
                "place": "Landskrona"
            },
            "education": [
                {
                    "degree": "Stud. ex.",
                    "year": "1917",
                    "institution": "NULL"
                },
                {
                    "degree": "fänr.",
                    "year": "1919",
                    "institution": "NULL"
                }
            ],
            "career": [
                {
                    "position": "löjtn.",
                    "years": {
                        "start_year": 1923,
                        "end_year": 1923
                    },
                    "organization": "Wendes art. reg."
                },
                {
                    "position": "kapt.",
                    "years": {
                        "start_year": 1934,
                        "end_year": 1934
                    },
                    "organization": "NULL"
                },
                {
                    "position": "major",
                    "years": {
                        "start_year": 1937,
                        "end_year": "NULL"
                    },
                    "organization": "styresm. f. försv. väs. kem. anst."
                },
                {
                    "position": "överstelöjtn.",
                    "years": {
                        "start_year": 1942,
                        "end_year": 1942
                    },
                    "organization": "NULL"
                }
            ],
            "family": {
                "spouse": "Elsa Vult von Steyern",
                "marriage_year": "26/03/1936",
                "children": [
                    {
                        "name": "Holger",
                        "birth_year": "1940"
                    },
                    {
                        "name": "Harald",
                        "birth_year": "1941"
                    },
                    {
                        "name": "Christer",
                        "birth_year": "1942"
                    }
                ]
            }
        },
        "2": {
            "full_name": "Schmidt, Wilhelm Georg",
            "location": "Saltsjöbaden",
            "occupation": "direktör",
            "birth_details": {
                "date": "25/12/1875",
                "place": "öved, Malmöh. L"
            },
            "education": [
                {
                    "degree": "NULL",
                    "year": "NULL",
                    "institution": "h. allm. lärov, i Lund"
                },
                {
                    "degree": "elev",
                    "year": "91-95",
                    "institution": "CTL (maskin-byggn. o. mek. tekn.)"
                },
                {
                    "degree": "NULL",
                    "year": "NULL",
                    "institution": "Techn. Hochschule i Karlsruhe"
                }
            ],
            "career": [
                {
                    "position": "Konstr.",
                    "years": {
                        "start_year": 1898,
                        "end_year": 1900
                    },
                    "organization": "Brown Boveri & Co. i Baden, Schweiz"
                },
                {
                    "position": "NULL",
                    "years": {
                        "start_year": 1900,
                        "end_year": 1905
                    },
                    "organization": "Helios Elektrizitäts Gesellschaft i Köln"
                },
                {
                    "position": "ch.",
                    "years": {
                        "start_year": 1905,
                        "end_year": 1908
                    },
                    "organization": "Union Eisen u. Hüttenwerk i Dortmund"
                },
                {
                    "position": "verkst, dir.",
                    "years": {
                        "start_year": 1908,
                        "end_year": 1917
                    },
                    "organization": "Norsk Motor- og Dynamofabr."
                },
                {
                    "position": "NULL",
                    "years": {
                        "start_year": 1917,
                        "end_year": 1931
                    },
                    "organization": "Sv. Elektrobil A-B"
                }
            ],
            "family": {
                "spouse": "Frieda Fanghänel",
                "marriage_year": "NULL",
                "children": [
                    {
                        "name": "Helga Elisabet",
                        "birth_year": "1907"
                    },
                    {
                        "name": "Werner Paul",
                        "birth_year": "1909"
                    },
                    {
                        "name": "Erik Wilhelm",
                        "birth_year": "1914"
                    },
                    {
                        "name": "Vera",
                        "birth_year": "1915"
                    },
                    {
                        "name": "Elsa Marianne",
                        "birth_year": "1919"
                    }
                ]
            },
            "hobbies": [
                "friluftsliv",
                "trädgårdsskötsel",
                "golf"
            ]
        },
        "3": {
            "full_name": "Schmidt, Viva (Maja) Charlotta",
            "location": "Sthlm",
            "occupation": "fru",
            "birth_details": {
                "date": "NULL",
                "place": "NULL"
            },
            "family": {
                "spouse": "gen:major Tell S.",
                "marriage_year": "NULL",
                "children": []
            },
            "community_involvement": [
                {
                    "role": "Ordf.",
                    "organization": "Riksförb. Sv :es Lottakårer",
                    "years": "NULL"
                }
            ],
            "honorary_titles": [
                {
                    "title": "KFinlLO",
                    "institution": "NULL",
                    "year": "NULL"
                },
                {
                    "title": "FinlVRO",
                    "institution": "NULL",
                    "year": "NULL"
                },
                {
                    "title": "FFrK",
                    "institution": "NULL",
                    "year": "NULL"
                }
            ]
        }
    }
}