{
    "original": "Säger, John-Henry Edvard Magnus,\ncivilingenjör, Sthlm, f. 26/10/04 av\nförste hovstallmäst, John Edvard\nMagnus S. o. Ida Fock. Studrex. i\nSthlm 23, avg:ex. v. KTH 30\n(fack-avdeln. f. elektrotekn.). Kurser i arb\n:-ledn. o. arb :stud. v. Sv :es\nIndustri-förbrs arb :led :inst. 33 o. 35. Bitr.\nprof. H. Kreuger i forskningsarb.\ninom det byggn: akustiska omr. v. KTH\ni Sthlm fr. 31, bitr. dir. O. Kärnekull\ni fråg. inom omr. f.\nverkstadsorganisation v. A-B Industribyrån fr. 35,\narb:stud:ch, v. Trafikförv.\nGtbg-Da-larne-Gävle fr. 45. Förv. egna fastigh,\ni kvarteret Hästen m. fl. i Sthlm o.\negen lantgård m. skogsbruk m. m.\nbenämnd Ryfors Bruk övre i Nykyrke\nsn i Västergötl. sed. 39. FFrKSkl.\nSäger, Leo Magnus Johan,\nlegationsråd, Sthlm-Mullsjö, f. 28/6/89 i Paris\nav överstekammarjunkare, envoyé\nCarl Daniel Robert S. o. grev :an\nElisabeth Berthe Marie Aibine\nMoltke-Huitfeldt. G. 22 m. Vera Brunner.\nKansliex. v. Sthlms Högsk. 11,\nstat-offiex. 11. Legationstj :man i Engl.,\nRyssl., U.S.A., Lettl. o. Egypt. Ägare\nav Ryfors Bruk Nedre, Mullsjö.\nKommunalfullm, o. led. av kommunalndn i\nSandhems s :n. Hobby: hist. studier.\nRVO, OffBulgCfO, OffLettTSO,\nOff-MonS:tCO, FFrK2kl, RFrHL,\nRPr-Kr03kl.\nSägner, Harry Robert Emanuel,\nkyrkosångare, Sthlm, f. 21/6/96 i\nNorrköp. G. 31 m. Margit Elisabeth\nHernlund. Folkskollär :ex. 19,\nkyrkosång:-ex. 20, sångstud. f. prof. J. Forsell\n21-23, i utl. 23, 30, 31, bl. a. f. Guglielmo\nCecconi i Wien. Lär. i säng v. Hamra\n17-19, folkskoll. 19-20, t. f. rekt. v. sem.\ni östers. 21, t. f. kantor o. kördir. i\nGust. Vasa förs. i Sthlm 31-33, anst.\nss. kyrkosångare h. Sv. kyrkans diak\n:-styr. fr. 23, fältkantor fr. 40, egna\nkonserter, medv. i radio fr. 25,\ngram-mofoninsjungningar.\nSahlberg, Nils Gärdar, fil. dr, Sthlm,\nf. S/6/08 i Gudmundrå, Västernorrl. L,\nav disp. Axel S. o. Jenny Qvist. G. 37\nm. Ingrid Lindblom. Barn: Bertil f.\n39, Margareta f. 42. Stud :ex. v.\nLundsbergs sk. 26, fil. kand. i Upps. 30, fil.\nlic. 36, fil. dr 43. Anst. i bokförl.\nNatur och Kultur i Sthlm 37-40, v. Svensk\nFilmindustri 41. Ordf. i\nÅngermanlands Gille, styr:suppl, i Norrlands\nGille. Skr.: Vår underliga historia,\nMälardrottningens underliga öden,\nGustaf Fredrik Gyllenborg (akad.\navh.).\nSahlén, Artur Oliver Julianus,\nkonstnär, Sthlm, f. i Sam, Älvsb. L, 16/2/82\nav organ. Wilh. S. o. Johanna\nJosefsson. G. 11 m. Tyra Dahlman. Barn:\nMarianne f. 18, g. m. försäkr :tj :man\nBjörn Wiman. Carin Wästbergs mål\n:-sk. 03, stud. teckn. v. Konstn:förb. sk.,\nmåln. f. Karl Nordström, stud. på\nAcad. Colarossi i Paris f. Christian\nKrogh 07, grund, tills. m. Harriet\nSundström fören. Originalträsnitt 11,\ngrund. A-B Handpresstryck 16. Stud\n:-res. t. Tyskl. 14, v. ordf. i Graf. sällsk.\nsed. 29. Repr. m. träsnitt i Natrmus.,\nmus. i Malmö, Gtbg, Norrköp.,\nVästerås, konstind :mus. i Oslo o. Köpenh.,\nmus. i Hfors, Åbo, Dresden, Wien,\nNew York, Brit. Mus. o. Prince Albert\nand Victoria Mus. i London, Honolulu\nAcad. of Arts, utf. portr, i olja, i\nträsnitt bl. a.: prof. Frits Läffler o.\nMit-tag-Leffler, adj. Nils Ångström, kapt.\nE. Malmberg, dr Karl Widstrand m.\nfl.; uppf. tryckapparat f. träsnitt 31.\nUtg. skr. om träsnitt, träsnittsaml.\nm. m., upps. i Nord. Fam :bok, Ord o.\nBild, Hantvrs Bok m. fl.\nSahlén, Jakob Fredrik, aktuarie,\nÄppelviken, f. 30/1/92 i Varola fs.,\nSkarab. 1. G, 25 m. Signe Viktoria\nHoff-ström. Barn: Lärs-Jakob f. 26, Per\nFredrik f. 28, Jan f. 32. Stud:ex. 11,\nfil. kand. 14, fil. mag. 15, fil. lic. 17 v.\nSthlms Högsk. Anst. v. Livförsäkr\n:-bol. Balder 18, aktuarie sed. 19,\naktuarie h. Läkarnas s jukf örsäkr: anst.\nSalus sed. 29, aktuarie h.\nFörsäkr:-bol. Hermes sed. 39.\n",
    "structured": {
        "0": {
            "full_name": "Säger, John-Henry Edvard Magnus",
            "location": "Sthlm",
            "occupation": "Civilingenjör",
            "birth_details": {
                "date": "26/10/1904",
                "place": "Sthlm"
            },
            "education": [
                {
                    "degree": "Studrex.",
                    "year": "1923",
                    "institution": "Sthlm"
                },
                {
                    "degree": "Avg:ex. v. KTH",
                    "year": "1930",
                    "institution": "KTH"
                }
            ],
            "career": [
                {
                    "position": "Bitr. prof.",
                    "years": {
                        "start_year": 1931,
                        "end_year": 1933
                    },
                    "organization": "KTH i Sthlm"
                },
                {
                    "position": "Bitr. dir.",
                    "years": {
                        "start_year": 1935,
                        "end_year": 1935
                    },
                    "organization": "A-B Industribyrån"
                }
            ],
            "family": {
                "spouse": "NULL",
                "marriage_year": "NULL",
                "children": []
            }
        },
        "1": {
            "full_name": "Säger, Leo Magnus Johan",
            "location": "Sthlm-Mullsjö",
            "occupation": "Legationsråd",
            "birth_details": {
                "date": "28/6/1889",
                "place": "Paris"
            },
            "education": [
                {
                    "degree": "Kansliex. v. Sthlms Högsk.",
                    "year": "1911",
                    "institution": "Sthlms Högsk."
                },
                {
                    "degree": "Stat-offiex.",
                    "year": "1911",
                    "institution": "Sthlms Högsk."
                }
            ],
            "career": [],
            "family": {
                "spouse": "Vera Brunner",
                "marriage_year": "1922",
                "children": []
            }
        },
        "2": {
            "full_name": "Sägner, Harry Robert Emanuel",
            "location": "Sthlm",
            "occupation": "Kyrkosångare",
            "birth_details": {
                "date": "21/6/1896",
                "place": "Norrköp."
            },
            "education": [
                {
                    "degree": "Folkskollär :ex.",
                    "year": "1919",
                    "institution": "NULL"
                },
                {
                    "degree": "Kyrkosång :ex.",
                    "year": "1920",
                    "institution": "NULL"
                }
            ],
            "career": [
                {
                    "position": "Lär.",
                    "years": {
                        "start_year": 1921,
                        "end_year": 1923
                    },
                    "organization": "Hamra"
                }
            ],
            "family": {
                "spouse": "Margit Elisabeth Hernlund",
                "marriage_year": "1931",
                "children": []
            }
        },
        "3": {
            "full_name": "Sahlberg, Nils Gärdar",
            "location": "Sthlm",
            "occupation": "Fil. dr",
            "birth_details": {
                "date": "5/6/1908",
                "place": "Gudmundrå, Västernorrl. L"
            },
            "education": [
                {
                    "degree": "Stud :ex. v. Lundsbergs sk.",
                    "year": "1926",
                    "institution": "Lundsbergs sk."
                },
                {
                    "degree": "Fil. kand. i Upps.",
                    "year": "1930",
                    "institution": "Upps."
                }
            ],
            "career": [
                {
                    "position": "Anst. i bokförl.",
                    "years": {
                        "start_year": 1937,
                        "end_year": 1940
                    },
                    "organization": "Natur och Kultur i Sthlm"
                }
            ],
            "family": {
                "spouse": "Ingrid Lindblom",
                "marriage_year": "1937",
                "children": [
                    {
                        "name": "Bertil",
                        "birth_year": "1939"
                    },
                    {
                        "name": "Margareta",
                        "birth_year": "1942"
                    }
                ]
            }
        },
        "4": {
            "full_name": "Sahlén, Artur Oliver Julianus",
            "location": "Sthlm",
            "occupation": "Konstnär",
            "birth_details": {
                "date": "16/2/1882",
                "place": "Sam, Älvsb. L"
            },
            "education": [],
            "career": [
                {
                    "position": "Ordf.",
                    "years": {
                        "start_year": 1929,
                        "end_year": null
                    },
                    "organization": "Graf. sällsk."
                }
            ],
            "family": {
                "spouse": "Tyra Dahlman",
                "marriage_year": "1911",
                "children": [
                    {
                        "name": "Marianne",
                        "birth_year": "1918"
                    }
                ]
            }
        },
        "5": {
            "full_name": "Sahlén, Jakob Fredrik",
            "location": "Äppelviken",
            "occupation": "Aktuarie",
            "birth_details": {
                "date": "30/1/1892",
                "place": "Varola fs., Skarab. l."
            },
            "education": [
                {
                    "degree": "Stud:ex.",
                    "year": "1911",
                    "institution": "NULL"
                },
                {
                    "degree": "Fil. kand.",
                    "year": "1914",
                    "institution": "NULL"
                },
                {
                    "degree": "Fil. mag.",
                    "year": "1915",
                    "institution": "Sthlms Högsk."
                }
            ],
            "career": [
                {
                    "position": "Anst. v. Livförsäkr",
                    "years": {
                        "start_year": 1918,
                        "end_year": null
                    },
                    "organization": "Balder"
                },
                {
                    "position": "Aktuarie",
                    "years": {
                        "start_year": 1929,
                        "end_year": null
                    },
                    "organization": "Salus"
                }
            ],
            "family": {
                "spouse": "Signe Viktoria Hoff-ström",
                "marriage_year": "1925",
                "children": [
                    {
                        "name": "Lärs-Jakob",
                        "birth_year": "1926"
                    },
                    {
                        "name": "Per Fredrik",
                        "birth_year": "1928"
                    },
                    {
                        "name": "Jan",
                        "birth_year": "1932"
                    }
                ]
            }
        }
    }
}