{
    "original": "DAVIDSSON, NILS-ÅKE W, kamrer,\nKarlstad, f i Karlstad 8/11/20 av kassör\nDavid Petersson o Sofia Andersson.\nRealex 37, bktjm Venersborgs ensk bk\n39,    Werml    stadshyp:fören   o   Werml\nbost:kred:fören sed 42, kamr sed 54.\n-Hobbies: fiske, filateli.\nGift 44 m Gunvor Löfstrand, dtr t köpm\nArvid L o Olga Karlsson. - Barn: Hans\nf 48, Bengt f 49.\n\nDAVIDSSON, ÅKE, förste\nbibliotekarie, docent, Uppsala, f i Örebro 4/3/13\nav skoarb David Larsson o Martina\nGustafsson.\n\nFil kand Upps 42, fil lic 43, fil dr 57,\ndoc i musikhistoriens hjälpvetenskaper\nUpps 57-62, i bok- o bibliotekskunskap\nsed 62, organist- o kantorsex Falun 39.\n- Anst Oscaria 29-33, organ Örebro\n31-39, tjg Örebro stadsbibl ol perioder\n35-41, aman KTH:s bibl 44-45, Upps\nuniv:-bibl 46, bibl där 48, l :e bibl sed 60 (eo\n57). - Sekr OD 41-44, 46-47, v ordf\n47-51. - LVSU 61. - Medl Rotary. - Skr:\nPeriodica technica abbreviata (46), Biogr\növer sv musiklitt 1800-1945 (48),\nCata-logue critique et descriptif des imprimés\nde musique des 16e et 17e siécles\ncon-servés å la Bibliothéque de l’Université\nRoyale d’Upsala. 2-3. (51), Catalogue\ncritique et descriptif des imprimés de\nmusique des 16e et 17e siécles conservés\ndans les bibliothéques suédoises (52),\nCatalogue des ouvrages théoriques sur\nla musique conservés dans les\nbibliothéques suédoises (53),\nMusikbibliogra-phische Beiträge (54), Handritade kartor\növer Sv:e (56) o Finl (57) i Upps univ:\n-bibl, Elias Martins teckningar t Sv:es\nhist (56), Stud rör sv musiktryck f år\n1750 (drsavh 57), Sv handteck:ar Upps\nuniv :bibl (58), Här och där små krogar\n(61), Danskt musiktryck intill 1700-talets\nmitt (62), Catalogue of the Gimo\nCol-lection of Italian manuscript music (33)\nm fi, musikhist upps i tidskr o\nupp-slagsb.\n\nGift 44 m doc Carin Olerud f 20, dtr t\nlekt Carl O o Nilla Andersson. - Barn:\nGöran f 46.\n\nde GEER, CARL G L, friherre,\nbankdirektör, Upplands Väsby o Sthlm, f i\nSthlm 20/9/18 av överceremonimäst, frih\nLouis de G o frih:an Beth Tersmeden.\n\nStud:ex Sigtuna 38, jur kand Upps 44,\nstud HHS 45-47, anst Sthlms ensk bk\n47, bitr dir 51, dir 54, v verkst dir sed\n56. - Ordf Barnängens tekn fabr ab,\nLiljeholmens stearinfabr ab, Rederi ab\nSalenia, Sv Bull maskin ab, Återförsäkr\nab Atlas, styr :led Sthlms ensk bk, Stora\nKopparb bergsl ab, Sthlms superfosfat\nfabr ab, Unifos kemi ab, ab Sv\nexportkredit, ab Diligentia, Scandinvest Trust\nCo; skattmäst Chambre de Commerce\nFrancaise en Suéde, Fi-sv hdlskamm;\nordf Sv tennisförb, Sthlms l o stads\ncentr kontr :f ören, v ordf o sekr\nNationalmusei vänner, styr :led Ups l\nturist-trafikfören, Avelsfören f sv röd o vit\nboskap, Soc Belgo-Suédoise, Sv:es centr\n:-fören f idr främj, sekr\nFideikommissa-riernås intresseorg; kommunal- o\nkyrko-fullm Österlövsta. - Inneh Leufsta o\nStora Wäsby fideikommiss. - Utm: RVOlkl,\nRFrHL, KFinlLO. - Hobbies: tennis, jakt.\nGift 42 m Maud Mörner f 21, dtr t\nmajoren, greve Göran M o Dorothy\nBolinder. - Barn: Louis f 44, Carl f 45.\n\nDE  GEER, J G  GERARD, friherre,\n\nbruksdisponent, Lesjöfors, f i\nSkagershult, Örebro l, 8/9/89 av landsh, frih\nFabian De G o grev:an Agathe\nWachtmeister.\n\nOff:ex 10, KTH (bergsing) 14, löjtn K 3\nres 15, ing Domnarfvets jernverk 15,\ndisp Nyhammars bruks ab o Lesjöfors\nab 21-23, Klosters ab 23, Lesjöfors ab\n26-51. - AK 37-43 (fp), FK 50-57,\nlandstingsman 36-47; led Europarådet 54-59.\n-Styr :ord Lesjöfors ab sed 52, Norrb\njärnverks ab 48-60, ab Julius Slöör, Sv\nhdlsbkn Karlstad 50-61. - Utg: Bergs- o\njärnhanteringen (23), Järnets cirkulation\n(28), Sveriges andra stormaktstid (29),\nJordbrukskrisen (30), Järnet i Sveriges\nnäringsliv (33), Sveriges naturrikedomar\nI-II (46, 50), Genombrottstider i\nBergslagen (51), Bergslagsrapsodi (53),\nAfrikansk rapsodi (55), Dalkarlssjön (57),\nJakt med o utan bössa m fi. - Hobbies:\njakt, skidåkning, ridning.\nGift 16 m Karin Höggläf f 94 d 59,\ndtr t v häradsh Richard H o Sigrid\nRyding. - Barn: Margareta f 17, Louise\nf 19, Lars-Gerard f 22.\n\nDE GEER, LARS G G, friherre,\nbruksdisponent, Lesjöfors, f i Grangärde,\nKopparb l, 3/9/22 av disp, frih Gerard\nDe G o Karin Hägglöf.\nStud:ex 39, fänr A l 43, löjtn 45, AIHS\n45, res:stat 46, kapt 55, B Se Carnegie\nInst of Techn 47, Harvard Business\n\nSchool 60, ing Lesjöfors ab 47-49, US\nSteel Corp 49-51, disp Lesjöfors ab sed\n52. - Styr:led ab Sv metallverken, ab\nBromsregulator, ab Sv spiralfabr.\nGift 1) 48-61 m Ingeborg Cederschiöld\nf 23, dtr t gen:löjtn Hugo C o frih:an\nMargareta Wrangel, 2) 63 m Birgit\nKarlebo f 28, dtr t ing Selim K o Ebba\nNordmark. - Barn: i l:a akt Gerard\nf 49, Ingeborg f 51, Gusta f 54, Louis\nf 59, i 2:a akt Lars f 63.\n\n",
    "structured": {
        "1": {
            "full_name": "DAVIDSSON, NILS-ÅKE W",
            "location": "Karlstad",
            "occupation": "kamrer",
            "birth_details": {
                "date": "08/11/1920",
                "place": "Karlstad",
                "parents": "David Petersson o Sofia Andersson",
                "place_coordinates": {
                    "Latitude": 59.4021806,
                    "Longitude": 13.5114977
                }
            },
            "education": [
                {
                    "degree": "Realex",
                    "year": "1937",
                    "institution": "NULL",
                    "institution_coordinates": {
                        "Latitude": 60.12816100000001,
                        "Longitude": 18.643501
                    }
                },
                {
                    "degree": "bktjm",
                    "year": "1939",
                    "institution": "Venersborgs ensk bank",
                    "institution_coordinates": {
                        "Latitude": 58.4628601,
                        "Longitude": 12.3561291
                    }
                }
            ],
            "career": [
                {
                    "position": "Werml stadshyp:fören",
                    "years": {
                        "start_year": 1942,
                        "end_year": "NULL"
                    },
                    "organization": "NULL"
                },
                {
                    "position": "Werml bost:kred:fören",
                    "years": {
                        "start_year": 1942,
                        "end_year": "NULL"
                    },
                    "organization": "NULL"
                },
                {
                    "position": "kamr",
                    "years": {
                        "start_year": 1954,
                        "end_year": "NULL"
                    },
                    "organization": "NULL"
                }
            ],
            "family": {
                "spouse": "Gunvor Löfstrand",
                "marriage_year": "1944",
                "children": [
                    {
                        "name": "Hans",
                        "birth_year": "1948"
                    },
                    {
                        "name": "Bengt",
                        "birth_year": "1949"
                    }
                ]
            },
            "publications": [],
            "community_involvement": [],
            "board_memberships": [],
            "honorary_titles": [],
            "hobbies": [
                "fiske",
                "filateli"
            ],
            "location_coordinates": {
                "Latitude": 59.4021806,
                "Longitude": 13.5114977
            }
        },
        "2": {
            "full_name": "DAVIDSSON, ÅKE",
            "location": "Uppsala",
            "occupation": "förste bibliotekarie, docent",
            "birth_details": {
                "date": "04/03/1913",
                "place": "Örebro",
                "parents": "David Larsson o Martina Gustafsson",
                "place_coordinates": {
                    "Latitude": 59.2752626,
                    "Longitude": 15.2134105
                }
            },
            "education": [
                {
                    "degree": "Fil kand",
                    "year": "1942",
                    "institution": "Uppsala universitet",
                    "institution_coordinates": {
                        "Latitude": 59.8575453,
                        "Longitude": 17.6294865
                    }
                },
                {
                    "degree": "fil lic",
                    "year": "1943",
                    "institution": "NULL",
                    "institution_coordinates": {
                        "Latitude": 60.12816100000001,
                        "Longitude": 18.643501
                    }
                },
                {
                    "degree": "fil dr",
                    "year": "1957",
                    "institution": "NULL",
                    "institution_coordinates": {
                        "Latitude": 60.12816100000001,
                        "Longitude": 18.643501
                    }
                }
            ],
            "career": [
                {
                    "position": "organist- o kantorsex",
                    "years": {
                        "start_year": 1939,
                        "end_year": "NULL"
                    },
                    "organization": "Falun"
                },
                {
                    "position": "aman KTH:s bibl",
                    "years": {
                        "start_year": 1944,
                        "end_year": 1945
                    },
                    "organization": "NULL"
                },
                {
                    "position": "Upps univ:-bibl",
                    "years": {
                        "start_year": 1946,
                        "end_year": "NULL"
                    },
                    "organization": "NULL"
                },
                {
                    "position": "bibl där",
                    "years": {
                        "start_year": 1948,
                        "end_year": "NULL"
                    },
                    "organization": "NULL"
                },
                {
                    "position": "l :e bibl",
                    "years": {
                        "start_year": 1960,
                        "end_year": "NULL"
                    },
                    "organization": "NULL"
                }
            ],
            "family": {
                "spouse": "doc Carin Olerud",
                "marriage_year": "1944",
                "children": [
                    {
                        "name": "Göran",
                        "birth_year": "1946"
                    }
                ]
            },
            "publications": [
                {
                    "title": "Periodica technica abbreviata",
                    "year": "1946",
                    "type": "NULL"
                },
                {
                    "title": "Biogr över sv musiklitt 1800-1945",
                    "year": "1948",
                    "type": "NULL"
                },
                {
                    "title": "Catalogue critique et descriptif des imprimés de musique des 16e et 17e siécles conservés å la Bibliothéque de l’Université Royale d’Upsala. 2-3.",
                    "year": "1951",
                    "type": "NULL"
                },
                {
                    "title": "Catalogue critique et descriptif des imprimés de musique des 16e et 17e siécles conservés dans les bibliothéques suédoises",
                    "year": "1952",
                    "type": "NULL"
                },
                {
                    "title": "Catalogue des ouvrages théoriques sur la musique conservés dans les bibliothéques suédoises",
                    "year": "1953",
                    "type": "NULL"
                },
                {
                    "title": "Musikbibliographische Beiträge",
                    "year": "1954",
                    "type": "NULL"
                },
                {
                    "title": "Handritade kartor över Sv:e",
                    "year": "1956",
                    "type": "NULL"
                },
                {
                    "title": "o Finl",
                    "year": "1957",
                    "type": "NULL"
                },
                {
                    "title": "Elias Martins teckningar t Sv:es hist",
                    "year": "1956",
                    "type": "NULL"
                },
                {
                    "title": "Stud rör sv musiktryck f år 1750",
                    "year": "1957",
                    "type": "drsavh"
                },
                {
                    "title": "Sv handteck:ar Upps univ :bibl",
                    "year": "1958",
                    "type": "NULL"
                },
                {
                    "title": "Här och där små krogar",
                    "year": "1961",
                    "type": "NULL"
                },
                {
                    "title": "Danskt musiktryck intill 1700-talets mitt",
                    "year": "1962",
                    "type": "NULL"
                },
                {
                    "title": "Catalogue of the Gimo Collection of Italian manuscript music",
                    "year": "1933",
                    "type": "NULL"
                }
            ],
            "community_involvement": [
                {
                    "role": "Sekr",
                    "organization": "OD",
                    "years": "1941-1944"
                },
                {
                    "role": "LVSU",
                    "organization": "NULL",
                    "years": "1961"
                }
            ],
            "board_memberships": [
                {
                    "position": "styr :led",
                    "organization": "Sthlms ensk bk",
                    "years": "NULL"
                },
                {
                    "position": "styr :led",
                    "organization": "Stora Kopparb bergsl ab",
                    "years": "NULL"
                }
            ],
            "honorary_titles": [],
            "hobbies": [],
            "location_coordinates": {
                "Latitude": 59.85856380000001,
                "Longitude": 17.6389267
            }
        },
        "3": {
            "full_name": "de GEER, CARL G L",
            "location": "Upplands Väsby o Sthlm",
            "occupation": "friherre, bankdirektör",
            "birth_details": {
                "date": "20/09/1918",
                "place": "Sthlm",
                "parents": "överceremonimäst, frih Louis de G o frih:an Beth Tersmeden",
                "place_coordinates": {
                    "Latitude": 59.32932349999999,
                    "Longitude": 18.0685808
                }
            },
            "education": [
                {
                    "degree": "Stud:ex",
                    "year": "1938",
                    "institution": "Sigtuna",
                    "institution_coordinates": {
                        "Latitude": 59.6191463,
                        "Longitude": 17.7234191
                    }
                },
                {
                    "degree": "jur kand",
                    "year": "1944",
                    "institution": "Uppsala universitet",
                    "institution_coordinates": {
                        "Latitude": 59.8575453,
                        "Longitude": 17.6294865
                    }
                },
                {
                    "degree": "stud HHS",
                    "year": "1947",
                    "institution": "NULL",
                    "institution_coordinates": {
                        "Latitude": 60.12816100000001,
                        "Longitude": 18.643501
                    }
                }
            ],
            "career": [
                {
                    "position": "anst Sthlms ensk bk",
                    "years": {
                        "start_year": 1947,
                        "end_year": "NULL"
                    },
                    "organization": "NULL"
                },
                {
                    "position": "bitr dir",
                    "years": {
                        "start_year": 1951,
                        "end_year": "NULL"
                    },
                    "organization": "NULL"
                },
                {
                    "position": "dir",
                    "years": {
                        "start_year": 1954,
                        "end_year": "NULL"
                    },
                    "organization": "NULL"
                },
                {
                    "position": "v verkst dir",
                    "years": {
                        "start_year": 1956,
                        "end_year": "NULL"
                    },
                    "organization": "NULL"
                }
            ],
            "family": {
                "spouse": "Maud Mörner",
                "marriage_year": "1942",
                "children": [
                    {
                        "name": "Louis",
                        "birth_year": "1944"
                    },
                    {
                        "name": "Carl",
                        "birth_year": "1945"
                    }
                ]
            },
            "publications": [],
            "community_involvement": [
                {
                    "role": "ordf",
                    "organization": "Sv tennisförb",
                    "years": "NULL"
                }
            ],
            "board_memberships": [
                {
                    "position": "ordf",
                    "organization": "Sv tennisförb",
                    "years": "NULL"
                }
            ],
            "honorary_titles": [],
            "hobbies": [
                "tennis",
                "jakt"
            ],
            "location_coordinates": {
                "Latitude": 59.51961,
                "Longitude": 17.92834
            }
        },
        "4": {
            "full_name": "DE GEER, J G GERARD",
            "location": "Lesjöfors",
            "occupation": "friherre, bruksdisponent",
            "birth_details": {
                "date": "08/09/1889",
                "place": "Skagershult, Örebro l",
                "parents": "landsh, frih Fabian De G o grev:an Agathe Wachtmeister",
                "place_coordinates": {
                    "Latitude": 59.2752626,
                    "Longitude": 15.2134105
                }
            },
            "education": [
                {
                    "degree": "Off:ex",
                    "year": "1910",
                    "institution": "NULL",
                    "institution_coordinates": {
                        "Latitude": 60.12816100000001,
                        "Longitude": 18.643501
                    }
                },
                {
                    "degree": "KTH (bergsing)",
                    "year": "1914",
                    "institution": "NULL",
                    "institution_coordinates": {
                        "Latitude": 60.12816100000001,
                        "Longitude": 18.643501
                    }
                }
            ],
            "career": [
                {
                    "position": "löjtn K 3 res",
                    "years": {
                        "start_year": 1915,
                        "end_year": "NULL"
                    },
                    "organization": "NULL"
                },
                {
                    "position": "ing Domnarfvets jernverk",
                    "years": {
                        "start_year": 1915,
                        "end_year": "NULL"
                    },
                    "organization": "NULL"
                }
            ],
            "family": {
                "spouse": "Karin Höggläf",
                "marriage_year": "1916",
                "children": [
                    {
                        "name": "Margareta",
                        "birth_year": "1917"
                    },
                    {
                        "name": "Louise",
                        "birth_year": "1919"
                    },
                    {
                        "name": "Lars-Gerard",
                        "birth_year": "1922"
                    }
                ]
            },
            "publications": [
                {
                    "title": "Bergs- o järnhanteringen",
                    "year": "1923",
                    "type": "NULL"
                },
                {
                    "title": "Järnets cirkulation",
                    "year": "1928",
                    "type": "NULL"
                },
                {
                    "title": "Sveriges andra stormaktstid",
                    "year": "1929",
                    "type": "NULL"
                },
                {
                    "title": "Jordbrukskrisen",
                    "year": "1930",
                    "type": "NULL"
                },
                {
                    "title": "Järnet i Sveriges näringsliv",
                    "year": "1933",
                    "type": "NULL"
                },
                {
                    "title": "Sveriges naturrikedomar I-II",
                    "year": "1946-1950",
                    "type": "NULL"
                },
                {
                    "title": "Genombrottstider i Bergslagen",
                    "year": "1951",
                    "type": "NULL"
                },
                {
                    "title": "Bergslagsrapsodi",
                    "year": "1953",
                    "type": "NULL"
                },
                {
                    "title": "Afrikansk rapsodi",
                    "year": "1955",
                    "type": "NULL"
                },
                {
                    "title": "Dalkarlssjön",
                    "year": "1957",
                    "type": "NULL"
                }
            ],
            "community_involvement": [],
            "board_memberships": [],
            "honorary_titles": [],
            "hobbies": [
                "jakt",
                "skidåkning",
                "ridning"
            ],
            "location_coordinates": {
                "Latitude": 59.97705449999999,
                "Longitude": 14.184545
            }
        },
        "5": {
            "full_name": "DE GEER, LARS G G",
            "location": "Lesjöfors",
            "occupation": "friherre, bruksdisponent",
            "birth_details": {
                "date": "03/09/1922",
                "place": "Grangärde, Kopparb l",
                "parents": "disp, frih Gerard De G o Karin Hägglöf",
                "place_coordinates": {
                    "Latitude": 60.2681,
                    "Longitude": 14.9796
                }
            },
            "education": [
                {
                    "degree": "Stud:ex",
                    "year": "1939",
                    "institution": "NULL",
                    "institution_coordinates": {
                        "Latitude": 60.12816100000001,
                        "Longitude": 18.643501
                    }
                },
                {
                    "degree": "fänr A l",
                    "year": "1943",
                    "institution": "NULL",
                    "institution_coordinates": {
                        "Latitude": 60.12816100000001,
                        "Longitude": 18.643501
                    }
                },
                {
                    "degree": "AIHS",
                    "year": "1945",
                    "institution": "NULL",
                    "institution_coordinates": {
                        "Latitude": 60.12816100000001,
                        "Longitude": 18.643501
                    }
                }
            ],
            "career": [
                {
                    "position": "ing Lesjöfors ab",
                    "years": {
                        "start_year": 1947,
                        "end_year": 1949
                    },
                    "organization": "NULL"
                },
                {
                    "position": "US Steel Corp",
                    "years": {
                        "start_year": 1949,
                        "end_year": 1951
                    },
                    "organization": "NULL"
                },
                {
                    "position": "disp Lesjöfors ab",
                    "years": {
                        "start_year": 1952,
                        "end_year": "NULL"
                    },
                    "organization": "NULL"
                }
            ],
            "family": {
                "spouse": "Ingeborg Cederschiöld",
                "marriage_year": "1948-1961",
                "children": [
                    {
                        "name": "Gerard",
                        "birth_year": "1949"
                    },
                    {
                        "name": "Ingeborg",
                        "birth_year": "1951"
                    },
                    {
                        "name": "Gusta",
                        "birth_year": "1954"
                    },
                    {
                        "name": "Louis",
                        "birth_year": "1959"
                    }
                ]
            },
            "publications": [],
            "community_involvement": [],
            "board_memberships": [],
            "honorary_titles": [],
            "hobbies": [],
            "location_coordinates": {
                "Latitude": 59.97705449999999,
                "Longitude": 14.184545
            }
        }
    }
}