{
    "original": "LINDELL, B ARNE L, aukt revisor,\nUppsala, f i Skövde 21/7/28 av köpman\nCarl L o Gerda Svensson.\nStud:ex 47, DHG 50, aukt revisor 59,\nanst Semplers rev :byrå Upps sed 52.\n-Hobby: golf.\n\nGift 55 m Meit Wallin f 26. - Barn:\nBjörn f 61.\n\nLINDELL, O ARNE, med dr, docent,\nUppsala, f i Upps 15/1/11 av köpman\nOscar L o Elisabet Edlund.\nStud:ex Upps 30, med kand 34, med lic\n40, med dr Sthlm 52, doc i obstetrik o\ngynekolog! Upps univ 54. - Ass :läk o e\nläk kir klin Akad sjh 40, tf 2:e underläk\n\nkir avd Södertälje las 41, ass :läk o e läk\nKK Akad sjh 43, underläk kir avd\nStocksunds las 45, l:e underläk gynekol\navd Radiumhemmet 48, l:e underläk\nKK Karol sjh 49, l:e underläk KK\nAkad sjh 53, bitr överläk där sed 53.\n-Utg: skr i obstetrik o gynekol.\nGift 1) 42 m Elsa Ahlström, 2) 50 m\nMaj-Britt Weigård f 22. - Barn: i l:a\nakt Anders f 43, Karin f 48, i 2:a akt\nGunnar f 53.\n\nLINDELL,   CARL-GUSTAV,   rektor,\n\nSörvik, f i Sthlm 23/3/21 av sjökapt\nGustaf L o Elsa Hedberg.\nOff:ex KSS 44, löjtn 46, kapt 52, pol\nmag o fil kand StHS 49, lär Stensunds\nfolkhögsk 50, sekr TCO 51-57, ch\ninfor-mationsavd där 52, stats- o\nkommunal-tjmavd 55, lär Brunnsviks folkhögsk 57,\nrektor där sed 59. - Styr :led Sv\nfolkhögsk lär:fören (ordf 61-63). - Skr:\nTjänstemannarörelsen (52), Hur\nstatsförvaltningen arbetar (60).\nGift 47 m Britt Sellén f 26, dtr t Nils\nS o Ester Johansson. - Barn: Greger\nf 48, Annica f 51.\n\nLINDELL, HARALD, konsul, fd\nlandskamrerare, Karlstad, f i Norrkpg 1/2/93\nav civiling August L o Alice Nordström.\nJur kand Upps 19, hdlsgymn 19, 2:e\nlänsbokh Värml l 22, l:e 29, länsassess\nKopparb l 36, landskamr Gotl l 42,\nVärml l 48-58. - Fransk konsul sed 58.\n-Ordf Karlstads ork:fören 47-58, Alliance\nFran?aise du Värml 48, Bibl vänner\nKarlstad 58-63, styr :led Gbgs bk Karlstad\n47-63, verkst styr:led Fören f det folkl\nmusiklivets befrämj 48, Folkl musiksk\nIngesund 54, Sv:es allm hyp:bks omb h\nWerml hyp:fören 54, medl FrimO, SHT.\n- Skr: tidn:art i kult o skönlitt ämnen,\növers fr franska o ryska. - Utm: KNO,\nKFinlLO, RFrHL, HazeliusM, SORM,\nWermlsällskftjM, FMpbh,\nFGM\"för-uppoffrgärn\". - Hobbies: franska,\nryska, genealogi.\n\nGift 21 m Ingrid Johnzon f 91, dtr t\ngrossh Oscar J o Selma Nilsson. - Barn:\nGöran f 23.\n\n",
    "structured": {
        "0": {
            "full_name": "B Arne L Lindell",
            "location": "Uppsala",
            "occupation": "aukt revisor",
            "birth_details": {
                "date": "21/07/1928",
                "place": "Skövde",
                "parents": "Carl L o Gerda Svensson"
            },
            "education": [
                {
                    "degree": "Stud:ex",
                    "year": "1947",
                    "institution": "DHG 50"
                }
            ],
            "career": [
                {
                    "position": "aukt revisor",
                    "years": {
                        "start_year": 1959
                    },
                    "organization": "Semplers rev :byrå Upps"
                }
            ],
            "family": {
                "spouse": "Meit Wallin",
                "marriage_year": "1955",
                "children": [
                    {
                        "name": "Björn",
                        "birth_year": "1961"
                    }
                ]
            },
            "hobbies": [
                "golf"
            ]
        },
        "1": {
            "full_name": "O Arne Lindell",
            "location": "Uppsala",
            "occupation": "med dr, docent",
            "birth_details": {
                "date": "15/01/1911",
                "place": "Uppsala",
                "parents": "Oscar L o Elisabet Edlund"
            },
            "education": [
                {
                    "degree": "Stud:ex",
                    "year": "1930",
                    "institution": "Upps"
                },
                {
                    "degree": "med kand",
                    "year": "1934",
                    "institution": null
                },
                {
                    "degree": "med lic",
                    "year": "1940",
                    "institution": null
                },
                {
                    "degree": "med dr",
                    "year": "1952",
                    "institution": "Sthlm"
                }
            ],
            "career": [
                {
                    "position": "Ass :läk",
                    "years": {
                        "start_year": 1940
                    },
                    "organization": "Akad sjh"
                },
                {
                    "position": "bitr överläk",
                    "years": {
                        "start_year": 1953,
                        "end_year": null
                    },
                    "organization": "KK Akad sjh"
                }
            ],
            "family": {
                "spouse": "1) Elsa Ahlström, 2) Maj-Britt Weigård",
                "marriage_year": "1) 1942, 2) 1950",
                "children": [
                    {
                        "name": "Anders",
                        "birth_year": "1943"
                    },
                    {
                        "name": "Karin",
                        "birth_year": "1948"
                    },
                    {
                        "name": "Gunnar",
                        "birth_year": "1953"
                    }
                ]
            }
        },
        "2": {
            "full_name": "Carl-Gustav Lindell",
            "location": "Sörvik",
            "occupation": "rektor",
            "birth_details": {
                "date": "23/03/1921",
                "place": "Sthlm",
                "parents": "Gustaf L o Elsa Hedberg"
            },
            "education": [
                {
                    "degree": "Off:ex",
                    "year": "1944",
                    "institution": "KSS"
                },
                {
                    "degree": "pol mag o fil kand",
                    "year": "1949",
                    "institution": "StHS"
                }
            ],
            "career": [
                {
                    "position": "lär",
                    "years": {
                        "start_year": 1957,
                        "end_year": null
                    },
                    "organization": "Brunnsviks folkhögsk"
                },
                {
                    "position": "rektor",
                    "years": {
                        "start_year": 1959,
                        "end_year": null
                    },
                    "organization": "Brunnsviks folkhögsk"
                }
            ],
            "family": {
                "spouse": "Britt Sellén",
                "marriage_year": "1947",
                "children": [
                    {
                        "name": "Greger",
                        "birth_year": "1948"
                    },
                    {
                        "name": "Annica",
                        "birth_year": "1951"
                    }
                ]
            }
        },
        "3": {
            "full_name": "Harald Lindell",
            "location": "Karlstad",
            "occupation": "konsul, fd landskamrerare",
            "birth_details": {
                "date": "01/02/1893",
                "place": "Norrkpg",
                "parents": "August L o Alice Nordström"
            },
            "education": [
                {
                    "degree": "Jur kand",
                    "year": "1919",
                    "institution": "Upps"
                },
                {
                    "degree": "hdlsgymn",
                    "year": "1919",
                    "institution": null
                }
            ],
            "career": [
                {
                    "position": "2:e länsbokh",
                    "years": {
                        "start_year": 1922,
                        "end_year": 1929
                    },
                    "organization": "Värml l"
                },
                {
                    "position": "l:e länsbokh",
                    "years": {
                        "start_year": 1929,
                        "end_year": 1936
                    },
                    "organization": "Värml l"
                },
                {
                    "position": "landskamr",
                    "years": {
                        "start_year": 1948,
                        "end_year": 1958
                    },
                    "organization": "Värml l"
                }
            ],
            "family": {
                "spouse": "Ingrid Johnzon",
                "marriage_year": "1921",
                "children": [
                    {
                        "name": "Göran",
                        "birth_year": "1923"
                    }
                ]
            },
            "hobbies": [
                "franska",
                "ryska",
                "genealogi"
            ]
        }
    }
}