{
    "original": "LENGQUIST, CARL-ERIK V,\nbergs-ingenjör, Grängesberg, f i Borås 30/7/18\nav agr Per L o Gerda Smedberg.\nStud:ex  37,  KTH  45,  gruvmät  LKAB\nMalmberget 45, gruving där 46, l:e ing\nTGO sed 53.\n\nGift 41 m Margareta Hårde f 18, dtr t\ning Harald H o Inez Saldéen. - Barn:\nBjörn f 44, Kristina f 46, Gunnel f 53.\n\nLENNE, CURT Y, apotekare,\nKarlskoga, f i St Tuna, Kopparb l, 11/2/23\nav bryggeriäg Herman L o Gerda\nHedström.\n\nFarm kand 46, apot:ex 52; anst Malung\n46, apot Örnen Karlstad 49-50, apot\nTorsby 52, ch galeniska lab forskn :avd\nab Bofors Nobelkrut sed 57. - Styr:led\nNärke-Värml :kretsen av Sv:es\nfarma-cevtförb sed 55, Ind:farmacevtklubben\nsed 62. - Medl Lions Club. - Hobbies:\nsport, fiske.\n\nGift 47 m Sigrid Jommo f 22, dtr t\nJommo Erik Eriksson o Elida Olsson.\n- Barn: Kerstin f 51, Erik f 54.\n\nLENNMALM-PLANTIN,\nMARGARETA, konstnärinna, Ludvika, f i\nMariefred 10/3/03 av landsfisk Emil\nLenn-malm o Helena Lövgren.\nStud HKS,  teckn:lär:sem,  Otte Skölds\nmålarsk, akad Paris o München;\nteckn:-lär Skara o Kristinehamn 26-33. - Utst\nSthlm,   Karlstad,   Västerås,   Halmstad,\nEskilstuna m fi. - Repr i mus Karlstad,\nHalmstad, Västerås, Eskilstuna. - Medl\nKRO.\nGift 50 m konstn Åke Plantin.\n\nLENTZ, WALDTRAUT H M, Dr med\ndent, tandläkare, Nora stad, f i\nGüst-row/Mecklbg, Tyskl, 24/9/24 av agr\nKarl Lentz o Charlotte Grotrian.\n\nStud:ex Rostock 43, tysk tandläk:ex 50,\ndr med dent 51, sv tandläk:ex Malmö\n58; ass:tandläk 50, avd:tandläk\nUniv:-klin Rostock 52, distr :tandläk Karlskoga\no Kopparb 53, skol- o distr :tandläk\nÖrebro 61, l:e distr:tandläk folktandv Nora\nstad sed 63. - Skr: Penicillin und\nSulfo-namide in der Zahn- Mund- und Kief\ner-heilkunde (drsavh 51).\n\n",
    "structured": {
        "0": {
            "full_name": "Carl-Erik V Lengquist",
            "location": "Grängesberg",
            "occupation": "bergs-ingenjör",
            "birth_details": {
                "date": "30/07/1918",
                "place": "Borås",
                "parents": "agr Per L o Gerda Smedberg"
            },
            "education": [
                {
                    "degree": "Stud:ex",
                    "year": "1937",
                    "institution": "NULL"
                },
                {
                    "degree": "KTH",
                    "year": "1945",
                    "institution": "NULL"
                },
                {
                    "degree": "gruvmät",
                    "year": "LKAB Malmberget 1945",
                    "institution": "NULL"
                }
            ],
            "career": [
                {
                    "position": "gruving",
                    "years": {
                        "start_year": 1946,
                        "end_year": 1946
                    },
                    "organization": "LKAB Malmberget"
                },
                {
                    "position": "l:e ing TGO",
                    "years": {
                        "start_year": 1953,
                        "end_year": 1953
                    },
                    "organization": "NULL"
                }
            ],
            "family": {
                "spouse": "Margareta Hårde",
                "marriage_year": "1941",
                "children": [
                    {
                        "name": "Björn",
                        "birth_year": "1944"
                    },
                    {
                        "name": "Kristina",
                        "birth_year": "1946"
                    },
                    {
                        "name": "Gunnel",
                        "birth_year": "1953"
                    }
                ]
            }
        },
        "1": {
            "full_name": "Curt Y Lenne",
            "location": "Karlskoga",
            "occupation": "apotekare",
            "birth_details": {
                "date": "11/02/1923",
                "place": "St Tuna, Kopparb l",
                "parents": "bryggeriäg Herman L o Gerda Hedström"
            },
            "education": [
                {
                    "degree": "Farm kand",
                    "year": "1946",
                    "institution": "NULL"
                },
                {
                    "degree": "apot:ex",
                    "year": "1952",
                    "institution": "NULL"
                }
            ],
            "career": [
                {
                    "position": "anst Malung",
                    "years": {
                        "start_year": 1946,
                        "end_year": 1946
                    },
                    "organization": "NULL"
                },
                {
                    "position": "apot Örnen Karlstad",
                    "years": {
                        "start_year": 1949,
                        "end_year": 1950
                    },
                    "organization": "NULL"
                },
                {
                    "position": "apot Torsby",
                    "years": {
                        "start_year": 1952,
                        "end_year": 1952
                    },
                    "organization": "NULL"
                },
                {
                    "position": "ch galeniska lab forskn :avd ab Bofors Nobelkrut",
                    "years": {
                        "start_year": 1957,
                        "end_year": 1957
                    },
                    "organization": "NULL"
                }
            ],
            "family": {
                "spouse": "Sigrid Jommo",
                "marriage_year": "1947",
                "children": [
                    {
                        "name": "Kerstin",
                        "birth_year": "1951"
                    },
                    {
                        "name": "Erik",
                        "birth_year": "1954"
                    }
                ]
            },
            "hobbies": [
                "sport",
                "fiske"
            ]
        },
        "2": {
            "full_name": "Margareta Lennmalm-Plantin",
            "location": "Ludvika",
            "occupation": "konstnärinna",
            "birth_details": {
                "date": "10/03/1903",
                "place": "Mariefred",
                "parents": "landsfisk Emil Lenn-malm o Helena Lövgren"
            },
            "education": [
                {
                    "degree": "Stud HKS,  teckn:lär:sem,  Otte Skölds målarsk",
                    "year": "26-33",
                    "institution": "NULL"
                }
            ],
            "career": [
                {
                    "position": "teckn:-lär",
                    "years": {
                        "start_year": null,
                        "end_year": null
                    },
                    "organization": "Skara o Kristinehamn"
                }
            ],
            "family": {
                "spouse": "konstn Åke Plantin",
                "marriage_year": "1950",
                "children": []
            }
        },
        "3": {
            "full_name": "Waldtraut H M Lentz",
            "location": "Nora stad",
            "occupation": "Dr med dent, tandläkare",
            "birth_details": {
                "date": "24/09/1924",
                "place": "Güst-row/Mecklbg, Tyskl",
                "parents": "agr Karl Lentz o Charlotte Grotrian"
            },
            "education": [
                {
                    "degree": "Stud:ex Rostock",
                    "year": "1943",
                    "institution": "NULL"
                },
                {
                    "degree": "tysk tandläk:ex",
                    "year": "1950",
                    "institution": "NULL"
                },
                {
                    "degree": "dr med dent",
                    "year": "1951",
                    "institution": "NULL"
                },
                {
                    "degree": "sv tandläk:ex",
                    "year": "Malmö 1958",
                    "institution": "NULL"
                }
            ],
            "career": [
                {
                    "position": "ass:tandläk",
                    "years": {
                        "start_year": 1950,
                        "end_year": 1950
                    },
                    "organization": "NULL"
                },
                {
                    "position": "avd:tandläk Univ:-klin Rostock",
                    "years": {
                        "start_year": 1952,
                        "end_year": 1952
                    },
                    "organization": "NULL"
                },
                {
                    "position": "distr :tandläk",
                    "years": {
                        "start_year": 1961,
                        "end_year": 1961
                    },
                    "organization": "Örebro"
                },
                {
                    "position": "l:e distr:tandläk folktandv",
                    "years": {
                        "start_year": 1963,
                        "end_year": 1963
                    },
                    "organization": "Nora stad"
                }
            ],
            "publications": [
                {
                    "title": "Penicillin und Sulfonamide in der Zahn- Mund- und Kieferheilkunde",
                    "year": "1951",
                    "type": "drsavh"
                }
            ]
        }
    }
}