{
    "original": "LINDEBERG, ALLAN, kyrkoherde\nemeritus, Dalarö, f i Kungälv 19/2/97\nav dir Hugo L o Emma Ahlberger.\nStud:ex Eskilstuna 16, teol kand 23,\nprästv Strängnäs 24, v past Bettna 24,\nv sjöm:past Hull 25, kommin Svärta\n25, sjöm :past Rotterdam 26, kyrkoh\nDalarö 33-63, stabspast v kustfl 40, ch:past\nv marinen 50, eo hovpred 55. -\nKorresp-LÖS. - Utm: LVO.\n\nGift 1) 27 m Elsa Knutsson f 02 d 59,\ndtr t maskinmäst Johan K o Inez\nSelemus, 2) 61 m Kerstin Mannerstråle f 19,\ndtr t disp Harald Almström o Agda\nNorinder. - Barn: i l:a akt Karin f 28,\nBengt f 29, Anna f 38.\n\nLINDEBERG, BENGT A, förste\nväg-ingenjör, Västerås, f i Nykpg 31/3/09\nav byggn:ing Sven L o Anna Paulig.\nStud:ex Nykpg 27, KTH 32, anst Stat\narb :lösh:kommiss 32, VV-verket sed 34,\navd:ch projekt:avd vägförvaltn\nVästmanl 1. - Utm: RNO. - Hobbies:\nfjällsport, foto, bridge.\n\nGift 35 m Sigrun Wennevik. - Barn:\nSten f 38, Kjell f 42.\n\nLINDEBERG, A HILLA-BRITTA,\nrektor, Örebro, f i Malmö 29/1/16 av disp\nEmil Bengtsson o Hilda Jonson.\n\nStud:ex Örebro 34, fil mag Lund 39,\nadj Karol lärov Örebro 56, rekt\nRisbergska sk sed 54. - V ordf LR Örebro\nl distr, led Sv:es h flicksk lär:förb\ncentralstyr. - Styr:led YKR, medl FBF,\nConcordia.\n\nGift 42 m adv Åke Lindeberg f 12.\n-Barn: Anders f 44, Henrik f 49.\n\nLINDEBERG, P IVAR, direktör,\nÖrebro, f i Nykpg 1/10/87 av patron\nEdvard L o Amalia Krogh.\nAg, verkst dir o styr :led Andrew\nHal-lingworth ab (rör, värme, sanitet)\nÖrebro sed 27.\n\nGift 17 m Lotten Andersson f 91, dtr t\nfabr Malcom A o h h. - Barn: Per Olof\nf 18, Gunnar f 21.\n\n",
    "structured": {
        "1": {
            "full_name": "Allan Lindeberg",
            "location": "Dalarö",
            "occupation": "Kyrkoherde emeritus",
            "birth_details": {
                "date": "19/02/1897",
                "place": "Kungälv",
                "parents": "dir Hugo L o Emma Ahlberger"
            },
            "education": [
                {
                    "degree": "Stud",
                    "year": "1916",
                    "institution": "Eskilstuna"
                },
                {
                    "degree": "teol kand",
                    "year": "1923",
                    "institution": "Strängnäs"
                }
            ],
            "career": [
                {
                    "position": "v past",
                    "years": {
                        "start_year": 1924,
                        "end_year": 1924
                    },
                    "organization": "Bettna"
                },
                {
                    "position": "v sjöm:past",
                    "years": {
                        "start_year": 1925,
                        "end_year": 1925
                    },
                    "organization": "Hull"
                },
                {
                    "position": "kommin",
                    "years": {
                        "start_year": 1925,
                        "end_year": 1925
                    },
                    "organization": "Svärta"
                },
                {
                    "position": "sjöm :past",
                    "years": {
                        "start_year": 1926,
                        "end_year": 1926
                    },
                    "organization": "Rotterdam"
                },
                {
                    "position": "kyrkoh",
                    "years": {
                        "start_year": 1933,
                        "end_year": 1963
                    },
                    "organization": "Dalarö"
                },
                {
                    "position": "stabspast v kustfl",
                    "years": {
                        "start_year": 1940,
                        "end_year": null
                    },
                    "organization": null
                },
                {
                    "position": "ch:past v marinen",
                    "years": {
                        "start_year": 1950,
                        "end_year": null
                    },
                    "organization": null
                },
                {
                    "position": "eo hovpred",
                    "years": {
                        "start_year": 1955,
                        "end_year": null
                    },
                    "organization": null
                }
            ],
            "family": {
                "spouse": "Elsa Knutsson",
                "marriage_year": "1927",
                "children": [
                    {
                        "name": "Karin",
                        "birth_year": "1928"
                    },
                    {
                        "name": "Bengt",
                        "birth_year": "1929"
                    },
                    {
                        "name": "Anna",
                        "birth_year": "1938"
                    }
                ]
            }
        },
        "2": {
            "full_name": "Bengt A Lindeberg",
            "location": "Västerås",
            "occupation": "förste väg-ingenjör",
            "birth_details": {
                "date": "31/03/1909",
                "place": "Nyköping",
                "parents": "byggn:ing Sven L o Anna Paulig"
            },
            "education": [
                {
                    "degree": "Stud",
                    "year": "1927",
                    "institution": "Nyköping"
                },
                {
                    "degree": null,
                    "year": "1932",
                    "institution": "KTH"
                }
            ],
            "career": [
                {
                    "position": "anst Stat arb :lösh:kommiss",
                    "years": {
                        "start_year": 1932,
                        "end_year": null
                    },
                    "organization": null
                },
                {
                    "position": "VV-verket",
                    "years": {
                        "start_year": 1934,
                        "end_year": null
                    },
                    "organization": null
                },
                {
                    "position": "avd:ch projekt:avd vägförvaltn Västmanl 1",
                    "years": {
                        "start_year": null,
                        "end_year": null
                    },
                    "organization": null
                }
            ],
            "family": {
                "spouse": "Sigrun Wennevik",
                "marriage_year": "1935",
                "children": [
                    {
                        "name": "Sten",
                        "birth_year": "1938"
                    },
                    {
                        "name": "Kjell",
                        "birth_year": "1942"
                    }
                ]
            },
            "hobbies": [
                "fjällsport",
                "foto",
                "bridge"
            ]
        },
        "3": {
            "full_name": "Hilla-Britta A Lindeberg",
            "location": "Örebro",
            "occupation": "rektor",
            "birth_details": {
                "date": "29/01/1916",
                "place": "Malmö",
                "parents": "disp Emil Bengtsson o Hilda Jonson"
            },
            "education": [
                {
                    "degree": "Stud",
                    "year": "1934",
                    "institution": "Örebro"
                },
                {
                    "degree": "fil mag",
                    "year": "1939",
                    "institution": "Lund"
                }
            ],
            "career": [
                {
                    "position": "adj Karol lärov Örebro",
                    "years": {
                        "start_year": 1956,
                        "end_year": null
                    },
                    "organization": null
                },
                {
                    "position": "rekt",
                    "years": {
                        "start_year": 1954,
                        "end_year": null
                    },
                    "organization": "Risbergska sk"
                }
            ],
            "family": {
                "spouse": "adv Åke Lindeberg",
                "marriage_year": "1942",
                "children": [
                    {
                        "name": "Anders",
                        "birth_year": "1944"
                    },
                    {
                        "name": "Henrik",
                        "birth_year": "1949"
                    }
                ]
            }
        },
        "4": {
            "full_name": "Ivar P Lindeberg",
            "location": "Örebro",
            "occupation": "direktör",
            "birth_details": {
                "date": "01/10/1887",
                "place": "Nyköping",
                "parents": "patron Edvard L o Amalia Krogh"
            },
            "education": [],
            "career": [
                {
                    "position": "Ag, verkst dir",
                    "years": {
                        "start_year": 1927,
                        "end_year": null
                    },
                    "organization": "Andrew Hallingworth ab (rör, värme, sanitet) Örebro"
                }
            ],
            "family": {
                "spouse": "Lotten Andersson",
                "marriage_year": "1917",
                "children": [
                    {
                        "name": "Per Olof",
                        "birth_year": "1918"
                    },
                    {
                        "name": "Gunnar",
                        "birth_year": "1921"
                    }
                ]
            }
        }
    }
}