{
    "original": "Lindesberg, Linkpg o Örebro. -\nHobbies: jakt, fiske.\n\nGift 41 m Ragnhild Ericsson f 16.\n-Barn: Rikard f 41, Anita f 45, Anders\nf 47.\n\nLINDÉN-HÖKEBERG,  GUDRUN E\n\nM, leg läkare, Uppsala, f i Kiruna 10/4/\n15 av trävaruhandl Leonard L o Edith\nMarkgren.\n\nStud:ex Umeå 35, med kand Upps 40,\nmed lic Sthlm 45, ass:läk Akad sjh 46,\n2:e läk Ulleråkers sjh 48, l:e läk v\nhjälpverksamh o familjevård där sed 56.\n- Sekr Sinnessjukndn 52-53.\n\n33 ms\n\nGift 46 m adv Hugo Hökeberg. - Barn:\nIngegerd f 47, Göran f 49, Margareta\nf 53, Ulf f 58.\n\nLINDEQVIST, KARL-HENRIK,\ndirektör, Enköping, f i Knutby, Sthlms l,\n18/3/16 av snickarmäst Owen L o Siri\nEngberg.\n\nFolkhögsk, möbelsnick o metallarb t 52,\nförrådsförvalt ab Bahco Enkpg 52,\nfastigh :förvalt ab Enkpgs hyresbostäder 58,\nverkst dir där sed 62. - Ordf Stadsfullm\nsed 60 (led 47), led drätselkamm o dess\nAU. - Led landst sed 62 o dess\nfritidsstyr. - Ordf Enkpgs arb :kommun o\nEnkpgs konsum:fören. - Medl Rotary.\nGift 42 m Inga Isaksson f 19. - Barn:\nLeif f 44, Kristina f 47.\n\nLINDER,   H   BRUNO,   civilingenjör,\n\nMärsta, f i Fyllebro, Hall l, 31/12/26\nav folkskollär Harald L o Anna\nJohansson.\n\nStud:ex Halmstad 46, CTH 51,\nrationaliser:ing vattenf:styr 51, org:ch ab Sv\nShell sed 58. - Hobbies: astronomi,\nsvampkännedom.\n\nGift 52 m Ann-Mari Lidbrink f 30,\ndtr t dir Peter Jönsson o Hilma\nNilsson. - Barn: Annie f 56, Åsa f 58,\nGöran f 62.\n\n",
    "structured": {
        "0": {
            "full_name": "Gudrun E Lindén-Hökeberg",
            "location": "Uppsala",
            "occupation": "leg läkare",
            "birth_details": {
                "date": "10/4/1915",
                "place": "Kiruna"
            },
            "education": [
                {
                    "degree": "stud:ex",
                    "year": "1935",
                    "institution": "Umeå"
                },
                {
                    "degree": "med kand",
                    "year": "1940",
                    "institution": "Uppsala"
                },
                {
                    "degree": "med lic",
                    "year": "1945",
                    "institution": "Sthlm"
                }
            ],
            "career": [
                {
                    "position": "ass:läk",
                    "years": {
                        "start_year": 1946,
                        "end_year": 1948
                    },
                    "organization": "Akad sjh"
                },
                {
                    "position": "2:e läk",
                    "years": {
                        "start_year": 1948,
                        "end_year": 1956
                    },
                    "organization": "Ulleråkers sjh"
                },
                {
                    "position": "l:e läk",
                    "years": {
                        "start_year": 1956,
                        "end_year": null
                    },
                    "organization": "hjälpverksamh o familjevård"
                }
            ],
            "family": {
                "spouse": "adv Hugo Hökeberg",
                "marriage_year": "1946",
                "children": [
                    {
                        "name": "Ingegerd",
                        "birth_year": "1947"
                    },
                    {
                        "name": "Göran",
                        "birth_year": "1949"
                    },
                    {
                        "name": "Margareta",
                        "birth_year": "1953"
                    },
                    {
                        "name": "Ulf",
                        "birth_year": "1958"
                    }
                ]
            }
        },
        "1": {
            "full_name": "Karl-Henrik Lindeqvist",
            "location": "Enköping",
            "occupation": "direktör",
            "birth_details": {
                "date": "18/3/1916",
                "place": "Knutby, Sthlms l"
            },
            "education": [
                {
                    "degree": "Folkhögsk",
                    "year": "1952",
                    "institution": "möbelsnick o metallarb"
                }
            ],
            "career": [
                {
                    "position": "förrådsförvalt",
                    "years": {
                        "start_year": 1952,
                        "end_year": 1958
                    },
                    "organization": "ab Bahco Enkpg"
                },
                {
                    "position": "fastigh :förvalt",
                    "years": {
                        "start_year": 1958,
                        "end_year": 1962
                    },
                    "organization": "ab Enkpgs hyresbostäder"
                },
                {
                    "position": "verkst dir",
                    "years": {
                        "start_year": 1962,
                        "end_year": null
                    },
                    "organization": "ab Enkpgs hyresbostäder"
                }
            ],
            "family": {
                "spouse": "Inga Isaksson",
                "marriage_year": "1942",
                "children": [
                    {
                        "name": "Leif",
                        "birth_year": "1944"
                    },
                    {
                        "name": "Kristina",
                        "birth_year": "1947"
                    }
                ]
            }
        },
        "2": {
            "full_name": "H Bruno Linder",
            "location": "Märsta",
            "occupation": "civilingenjör",
            "birth_details": {
                "date": "31/12/1926",
                "place": "Fyllebro, Hall l"
            },
            "education": [
                {
                    "degree": "Stud:ex",
                    "year": "1946",
                    "institution": "Halmstad"
                },
                {
                    "degree": "CTH",
                    "year": "1951",
                    "institution": "rationaliser:ing vattenf:styr"
                }
            ],
            "career": [
                {
                    "position": "org:ch",
                    "years": {
                        "start_year": 1958,
                        "end_year": null
                    },
                    "organization": "ab Sv Shell"
                }
            ],
            "family": {
                "spouse": "Ann-Mari Lidbrink",
                "marriage_year": "1952",
                "children": [
                    {
                        "name": "Annie",
                        "birth_year": "1956"
                    },
                    {
                        "name": "Åsa",
                        "birth_year": "1958"
                    },
                    {
                        "name": "Göran",
                        "birth_year": "1962"
                    }
                ]
            },
            "hobbies": [
                "astronomi",
                "svampkännedom"
            ]
        }
    }
}