{
    "original": "LJUNGSTRÖM, GUSTAF H,\nstads-fiskal, Uppsala, f i Fleninge, Malmöh l,\n21/1/99 av stat:insp Gustaf L o Louise\nLarsson.\n\nStud:ex Hbg 17, jur kand Lund 25,\ntingstjg Sevede o Tunaläns doms 25-27,\ntjg Svea hovr 28, polisassess o sekr Hbg\n32-33, bitr jur där 32-34, stadsfisk\nKarlshamn 35, polismäst o stadsfisk Karlstad\n40, stadsfisk Upps sed 55. - Utm: RNO.\n\n-  Hobbies: schack, historisk litteratur.\nGift 33 m Margareta Lindmark f 05,\ndtr t förrådsförv Carl Gustaf L o\nSigrid Lundeberg. - Barn: Claes f 33,\nAnne-Marie f 36, Anders f 39, Louise f 43.\n\nLJUNGSTRÖM, LÄRS-FREDRIK E,\nläroTerksadjunkt, Uppsala, f i Sthlm\n1/12/25 av dir:ass Einar L o folkskollär\nStina Carlsson.\n\nStud:ex 45, fil måg Upps 51, e adj Upps\nensk lärov 51, adj Katedralsk Upps sed\n56. - Utg: Läroböcker i matematik (tills\nm S Thörnqvist).\n\nGift 52 m Ingrid Nordenbäck f 28, dtr t\nbankkamr Hjalmar N o Clara\nDanielsson. - Barn: Anders f 54, Einar f 57,\nLennart f 62.\n\nLJUNGSTRÖM,   VALTER,   direktör,\n\nVingåker, f i Vingåker, Södermani l,\n21/5/06 av skräddarmäst Joel L o Hilma\nJohansson.\n\nRealex Katrineholm 23, dir ab\nLjungströms konf :fabr Vingåker sed 34, Sirita\nab sed 55, Strands konf:fabr\nKatrineholm sed 57. - Styr:ordf Skand bkn\nVingåker, Håkanstorp yrkessk 61,\nVingåkers hotell ab 62. - Medl Rotary 59.\n-Utm: RVO. - Hobbies: bridge, golf.\nGift 36 m Karin Larsson f 11, dtr t\nskräddare Emil L o Ida L. - Barn: Karl\nReidar f 37, Inga-Lill f 39.\n\n",
    "structured": {
        "0": {
            "full_name": "Gustaf H. Ljungström",
            "location": "Uppsala",
            "occupation": "stads-fiskal",
            "birth_details": {
                "date": "21/01/1899",
                "place": "Fleninge, Malmö"
            },
            "education": [
                {
                    "degree": "Stud:ex",
                    "year": "1917",
                    "institution": "Hbg"
                },
                {
                    "degree": "jur kand",
                    "year": "1925",
                    "institution": "Lund"
                }
            ],
            "career": [
                {
                    "position": "tingstjg",
                    "years": {
                        "start_year": 1925,
                        "end_year": 1927
                    },
                    "organization": "Sevede o Tunaläns doms"
                },
                {
                    "position": "tjg",
                    "years": {
                        "start_year": 1928,
                        "end_year": null
                    },
                    "organization": "Svea hovr"
                },
                {
                    "position": "polisassess o sekr",
                    "years": {
                        "start_year": 1932,
                        "end_year": 1933
                    },
                    "organization": "Hbg"
                },
                {
                    "position": "bitr jur",
                    "years": {
                        "start_year": 1932,
                        "end_year": 1934
                    },
                    "organization": "Hbg"
                },
                {
                    "position": "stadsfisk",
                    "years": {
                        "start_year": 1935,
                        "end_year": null
                    },
                    "organization": "Uppsala"
                }
            ],
            "family": {
                "spouse": "Margareta Lindmark",
                "marriage_year": "1933",
                "children": [
                    {
                        "name": "Claes",
                        "birth_year": "1933"
                    },
                    {
                        "name": "Anne-Marie",
                        "birth_year": "1936"
                    },
                    {
                        "name": "Anders",
                        "birth_year": "1939"
                    },
                    {
                        "name": "Louise",
                        "birth_year": "1943"
                    }
                ]
            },
            "hobbies": [
                "schack",
                "historisk litteratur"
            ]
        },
        "1": {
            "full_name": "Lärs-Fredrik E. Ljungström",
            "location": "Uppsala",
            "occupation": "läroTerksadjunkt",
            "birth_details": {
                "date": "01/12/1925",
                "place": "Sthlm"
            },
            "education": [
                {
                    "degree": "Stud:ex",
                    "year": "1945",
                    "institution": null
                },
                {
                    "degree": "fil måg",
                    "year": "1951",
                    "institution": "Upps"
                }
            ],
            "career": [
                {
                    "position": "e adj",
                    "years": {
                        "start_year": 1951,
                        "end_year": null
                    },
                    "organization": "Upps"
                },
                {
                    "position": "adj",
                    "years": {
                        "start_year": null,
                        "end_year": null
                    },
                    "organization": "Katedralsk Upps"
                }
            ],
            "family": {
                "spouse": "Ingrid Nordenbäck",
                "marriage_year": "1952",
                "children": [
                    {
                        "name": "Anders",
                        "birth_year": "1954"
                    },
                    {
                        "name": "Einar",
                        "birth_year": "1957"
                    },
                    {
                        "name": "Lennart",
                        "birth_year": "1962"
                    }
                ]
            }
        },
        "2": {
            "full_name": "Valter Ljungström",
            "location": "Vingåker",
            "occupation": "direktör",
            "birth_details": {
                "date": "21/05/1906",
                "place": "Vingåker, Södermanland"
            },
            "education": [
                {
                    "degree": "Realex",
                    "year": "1923",
                    "institution": "Katrineholm"
                }
            ],
            "career": [
                {
                    "position": null,
                    "years": {
                        "start_year": 1934,
                        "end_year": null
                    },
                    "organization": "Ljungströms konf:fabr Vingåker"
                },
                {
                    "position": null,
                    "years": {
                        "start_year": 1955,
                        "end_year": null
                    },
                    "organization": "Sirita ab"
                },
                {
                    "position": null,
                    "years": {
                        "start_year": 1957,
                        "end_year": null
                    },
                    "organization": "Strands konf:fabr Katrineholm"
                }
            ],
            "family": {
                "spouse": "Karin Larsson",
                "marriage_year": "1936",
                "children": [
                    {
                        "name": "Karl Reidar",
                        "birth_year": "1937"
                    },
                    {
                        "name": "Inga-Lill",
                        "birth_year": "1939"
                    }
                ]
            },
            "hobbies": [
                "bridge",
                "golf"
            ]
        }
    }
}