{
    "original": "LINDSKOG, TORSTEN R,\nkyrkoherde, Gunnarskog, f i Halmstad 10/7/07\nav löjtn Rudolf L o Anna Gustafsdtr.\nStud:ex Gbg 26, teol kand Lund 32, v\nkommin Bogen 32, kommin S Råda 33,\nkyrkoh Bjurtjärn 43, Gunnarskog sed 60.\n\n-  Utm: LNO.\n\nGift 34 m Margareta Hector, dtr t\nkontr :prost Olof H o Elin Christiansson.\n-Barn: Margareta f 36, Gunnar f 37, Erik\nf 39, Erling f 41, Anna f 47.\n\nLINDSTEDT, JAN A, leg läkare,\nSödertälje, f i Skövde 2/3/30 av bankkamr\nArthur L o Dagmar Nohlgren.\nStud:ex 49, med kand Sthlm 52, med\nlic 57, läk övervakn:kommiss Korea 54,\nass patol avd Seraf:las 56, underläk\nanestesiavd Sabbatsb sjh 58, vik\nunderläk KK Sabbatsb sjh 58, underläk kir\navd Södertälje las sed 59.\nGift 55 m sjuksköt Astrid Åberg f 26,\ndtr t Henning Å o h h. - Barn: Fredrik\nf 60, Britta f 61.\n\nLINDSTEN, BO C G, rådman,\nSödertälje, f i Skara 11/1/16 av lekt Gustaf L\no Ingrid Born.\n\nStud:ex Landskrona 33, jur kand Lund\n38, tingstjg Rönnebergs, Onsjö o\nHar-jagers doms :or 38-41, fiskal Skånska\nhovr 47 (e 42), assess rådhusr\nLandskrona o Karlskrona 48-53, rådman\nrådhusr Södertälje sed 53. - Suppl stat\nhyresråd 56, v ordf anst:ndrna f Hall o\nHåga 59, ordf tax:nd 55-58.\nGift 43 m Brita Bäckström f 16, dtr t\nsjökapt Torgny B o Signe Adolfson. -\n\nBarn: Ingrid o Per ff 44, Magnus f 47,\nBodil f 50.\n\nLINDSTEN, C GUNNAR, bitr\nlänsarkitekt, Sköllersta, f i Gbg 25/11/09 av\nrekt Carl L o Georgina Sandberg.\nKTH 39, anst flygförvaltn 39, h arkit\nA V Brunskog Linkpg 40, länsarkit:kont\nLinkpg 43, ass länsarkit:kont Karlskrona\n44, bitr länsarkit Kalmar 46, Örebro sed\n62; expropr :tekniker. - Huvudman\nKalmar stads sparbk 62. - Hobbies: språk,\nsamhällsvetenskap, litteratur,\nträdgårdsskötsel.\n\nGift 42 m Ann-Sofi Schotte f 11, dtr t\nprof Gunnar S o Anna Drake af\nHa-gelsrum. - Barn: Thomas f 43,\nAnna-Märta f 49.\n\n",
    "structured": {
        "1": {
            "full_name": "TORSTEN R LINDSKOG",
            "location": "Gunnarskog",
            "occupation": "Kyrkoherde",
            "birth_details": {
                "date": "10/07/1907",
                "place": "Halmstad",
                "parents": "löjtn Rudolf L o Anna Gustafsdtr"
            },
            "education": [
                {
                    "degree": "Stud:ex",
                    "year": "1926",
                    "institution": "Gbg"
                },
                {
                    "degree": "teol kand",
                    "year": "1932",
                    "institution": "Lund"
                }
            ],
            "career": [
                {
                    "position": "v kommin",
                    "years": {
                        "start_year": 1932,
                        "end_year": 1933
                    },
                    "organization": "Bogen"
                },
                {
                    "position": "kommin",
                    "years": {
                        "start_year": 1933,
                        "end_year": 1943
                    },
                    "organization": "S Råda"
                },
                {
                    "position": "kyrkoh",
                    "years": {
                        "start_year": 1943,
                        "end_year": 1960
                    },
                    "organization": "Bjurtjärn"
                },
                {
                    "position": "kyrkoherde",
                    "years": {
                        "start_year": 1960,
                        "end_year": null
                    },
                    "organization": "Gunnarskog"
                }
            ],
            "family": {
                "spouse": "Margareta Hector",
                "marriage_year": "1934",
                "children": [
                    {
                        "name": "Margareta",
                        "birth_year": "1936"
                    },
                    {
                        "name": "Gunnar",
                        "birth_year": "1937"
                    },
                    {
                        "name": "Erik",
                        "birth_year": "1939"
                    },
                    {
                        "name": "Erling",
                        "birth_year": "1941"
                    },
                    {
                        "name": "Anna",
                        "birth_year": "1947"
                    }
                ]
            }
        },
        "2": {
            "full_name": "JAN A LINDSTEDT",
            "location": "Södertälje",
            "occupation": "Leg läkare",
            "birth_details": {
                "date": "02/03/1930",
                "place": "Skövde",
                "parents": "bankkamr Arthur L o Dagmar Nohlgren"
            },
            "education": [
                {
                    "degree": "Stud:ex",
                    "year": "1949",
                    "institution": "Sthlm"
                },
                {
                    "degree": "med kand",
                    "year": "1952",
                    "institution": "Sthlm"
                },
                {
                    "degree": "med lic",
                    "year": "1957",
                    "institution": "Sthlm"
                }
            ],
            "career": [
                {
                    "position": "läk övervakn:kommiss",
                    "years": {
                        "start_year": 1954,
                        "end_year": null
                    },
                    "organization": "Korea"
                },
                {
                    "position": "ass patol avd",
                    "years": {
                        "start_year": 1956,
                        "end_year": null
                    },
                    "organization": "Seraf:las"
                },
                {
                    "position": "underläk",
                    "years": {
                        "start_year": 1958,
                        "end_year": 1959
                    },
                    "organization": "Sabbatsb sjh"
                },
                {
                    "position": "underläk",
                    "years": {
                        "start_year": 1958,
                        "end_year": null
                    },
                    "organization": "Sabbatsb sjh"
                },
                {
                    "position": "underläk",
                    "years": {
                        "start_year": null,
                        "end_year": null
                    },
                    "organization": "kir avd Södertälje las"
                }
            ],
            "family": {
                "spouse": "sjuksköt Astrid Åberg",
                "marriage_year": "1955",
                "children": [
                    {
                        "name": "Fredrik",
                        "birth_year": "1960"
                    },
                    {
                        "name": "Britta",
                        "birth_year": "1961"
                    }
                ]
            }
        },
        "3": {
            "full_name": "BO C G LINDSTEN",
            "location": "Södertälje",
            "occupation": "Rådman",
            "birth_details": {
                "date": "11/01/1916",
                "place": "Skara",
                "parents": "lekt Gustaf L o Ingrid Born"
            },
            "education": [
                {
                    "degree": "Stud:ex",
                    "year": "1933",
                    "institution": "Landskrona"
                },
                {
                    "degree": "jur kand",
                    "year": "1938",
                    "institution": "Lund"
                }
            ],
            "career": [
                {
                    "position": "tingstjg",
                    "years": {
                        "start_year": 1938,
                        "end_year": 1941
                    },
                    "organization": "Rönnebergs, Onsjö o Har-jagers doms :or"
                },
                {
                    "position": "fiskal",
                    "years": {
                        "start_year": 1947,
                        "end_year": null
                    },
                    "organization": "Skånska hovr"
                },
                {
                    "position": "assess",
                    "years": {
                        "start_year": 1948,
                        "end_year": 1953
                    },
                    "organization": "rådhusr Landskrona o Karlskrona"
                },
                {
                    "position": "rådman",
                    "years": {
                        "start_year": 1953,
                        "end_year": null
                    },
                    "organization": "rådhusr Södertälje"
                }
            ],
            "family": {
                "spouse": "Brita Bäckström",
                "marriage_year": "1943",
                "children": [
                    {
                        "name": "Ingrid",
                        "birth_year": "1944"
                    },
                    {
                        "name": "Per",
                        "birth_year": "1944"
                    },
                    {
                        "name": "Magnus",
                        "birth_year": "1947"
                    },
                    {
                        "name": "Bodil",
                        "birth_year": "1950"
                    }
                ]
            }
        },
        "4": {
            "full_name": "C GUNNAR LINDSTEN",
            "location": "Sköllersta",
            "occupation": "Bitr länsarkitekt",
            "birth_details": {
                "date": "25/11/1909",
                "place": "Gbg",
                "parents": "rekt Carl L o Georgina Sandberg"
            },
            "education": [
                {
                    "degree": "KTH",
                    "year": "1939",
                    "institution": "KTH"
                }
            ],
            "career": [
                {
                    "position": "anst flygförvaltn",
                    "years": {
                        "start_year": 1939,
                        "end_year": null
                    },
                    "organization": null
                },
                {
                    "position": "h arkit",
                    "years": {
                        "start_year": 1940,
                        "end_year": 1943
                    },
                    "organization": "A V Brunskog Linkpg"
                },
                {
                    "position": "länsarkit:kont",
                    "years": {
                        "start_year": 1946,
                        "end_year": 1962
                    },
                    "organization": "Örebro"
                }
            ],
            "family": {
                "spouse": "Ann-Sofi Schotte",
                "marriage_year": "1942",
                "children": [
                    {
                        "name": "Thomas",
                        "birth_year": "1943"
                    },
                    {
                        "name": "Anna-Märta",
                        "birth_year": "1949"
                    }
                ]
            },
            "hobbies": [
                "språk",
                "samhällsvetenskap",
                "litteratur",
                "trädgårdsskötsel"
            ]
        }
    }
}