{
    "original": "LINDQVIST, A IVAR H, rådman,\nUppsala, f i Ekeberga, Kronob l, 11/4/10\nav riksg:fullm Axel L o Ester Elmgren.\nStud:ex Halmstad 29, jur kand Lund 35,\ntingstjg Hall s doms 35-38, tjg hovr f\nÖ :e Norrl 38, fiskal där 38, tingssekr\nVästerb v doms 41, Gällivare doms 43,\nmagistr :rådman o not publ Upps 44-57,\nrådman o överexekutor där sed 57.\n-Sekr hälsov:nd 47, led byggn:nd 56-60\n(suppl 47-56), led o sekr direkt f Stift\nGillbergska barnhemmet 57, rev Stift\nUpps hemsystersk 49, Borgarhemmet i\nUpps 52. - Utm: RNO.\nGift 44 m Kerstin Anderberg f 16, dtr t\nred Nikolas A o Anna Leth. - Barn:\nGöran f 45, Bo f 47, Anna Brita f 51.\n\nLINDQVIST, LARS G, bibliotekschef,\nVästerås, f i Sthlm 26/12/13 av intend\nKlas G L o Elvira Hamer.\nStud:ex 32, fil mag Sthlm 41, bibliot:ch\nAsea sed 53.\n\nGift 44 m Inez Nilsson f 11. - Barn:\nMargret f 47.\n\nLINDQUIST, LÄRS-ERIK,\nbyggnadsingenjör, Avesta, f i Varde, Ribe amt,\nDanm, 10/8/21 av verkm Emil L o\nGerda Fridström.\n\nByggn:ing:ex Katrineholms tekn sk 46,\nanst byggn :firma A Nilsson Köping 47,\nAvesta jernverks ab 48, Uddeholms ab\nPersberg 52, SIAB Sthlm 54, Korsnäs ab\nGävle 56, Morgårdshammar mek verkst\nab 58, ch byggn :avd Avesta jernverks ab\nsed 60. - Hobbies: bridge, fiske\nfriluftsliv, slöjd.\n\nGift 50 m Ingrid Weidlitz f 20, dtr t\nbankkamr Per W o Anna Svan. - Barn:\nMats f 51, Jonas f 52.\n\nLINDQVIST, LÄRS-OLOF, verkst\ndirektör, Uppsala, f i Upps 3/2/23 av dir\nEinar L o Märta Ahlström,\n\nStud:ex 41, anst ab Wilh Becker Sthlm\n45, ab Ups färghdl 46, disp 52, verkst\ndir där sed 61, ab Söderbergs färghdl\nsed 62. - Inneh sjv:aff Svanen Upps sed\n34, Svanens uthyrn :central sed 51. - V\nordf Ups hdlsfören, styr :led ab Ups\nfärghdl, ab Söderbergs färghdl, ab\nFärg-sam. - Sekr Ups golfkl, medl JuvenalO,\nRotary, Mercurii-sällsk, MBS, Carl\nJo-hans-förb, Borgersk Upps, IF\nKamraterna, Ups curling gille, Ups tennisklubb,\nUps simsällsk. - Res:off:ex 44, kapt\nmarinint :kåren 55. - Hobbies: golf,\nspråk.\n\nGift 47 m Gun Wahlberg f 28, dtr t\nköpm Joel W o Ninnie Andersson.\n-Barn: Håkan f 48, Lena f 51, Johan\nf 59.\n\n",
    "structured": {
        "1": {
            "full_name": "Ivar H Lindqvist",
            "location": "Uppsala",
            "occupation": "Rådman",
            "birth_details": {
                "date": "11/04/1910",
                "place": "Ekeberga, Kronob l",
                "parents": "Axel L o Ester Elmgren"
            },
            "education": [
                {
                    "degree": "Stud:ex",
                    "year": "1929",
                    "institution": "Halmstad"
                },
                {
                    "degree": "Jur kand",
                    "year": "1935",
                    "institution": "Lund"
                }
            ],
            "career": [
                {
                    "position": "Tingssekr",
                    "years": {
                        "start_year": 1943,
                        "end_year": 1944
                    },
                    "organization": "Västerb v doms"
                },
                {
                    "position": "Magistr :rådman o not publ",
                    "years": {
                        "start_year": 1944,
                        "end_year": 1957
                    },
                    "organization": "Upps"
                },
                {
                    "position": "Rådman o överexekutor",
                    "years": {
                        "start_year": 1957
                    },
                    "organization": "Upps"
                }
            ],
            "family": {
                "spouse": "Kerstin Anderberg",
                "marriage_year": "1944",
                "children": [
                    {
                        "name": "Göran",
                        "birth_year": "1945"
                    },
                    {
                        "name": "Bo",
                        "birth_year": "1947"
                    },
                    {
                        "name": "Anna Brita",
                        "birth_year": "1951"
                    }
                ]
            }
        },
        "2": {
            "full_name": "Lars G Lindqvist",
            "location": "Västerås",
            "occupation": "Bibliotekschef",
            "birth_details": {
                "date": "26/12/1913",
                "place": "Sthlm",
                "parents": "Klas G L o Elvira Hamer"
            },
            "education": [
                {
                    "degree": "Stud:ex",
                    "year": "1932",
                    "institution": null
                },
                {
                    "degree": "Fil mag",
                    "year": "1941",
                    "institution": "Sthlm"
                }
            ],
            "career": [
                {
                    "position": "Bibliot:ch",
                    "years": {
                        "start_year": 1953
                    },
                    "organization": "Asea"
                }
            ],
            "family": {
                "spouse": "Inez Nilsson",
                "marriage_year": "1944",
                "children": [
                    {
                        "name": "Margret",
                        "birth_year": "1947"
                    }
                ]
            }
        },
        "3": {
            "full_name": "Lärs-Erik Lindquist",
            "location": "Avesta",
            "occupation": "Byggnadsingenjör",
            "birth_details": {
                "date": "10/08/1921",
                "place": "Varde, Ribe amt, Danm",
                "parents": "Emil L o Gerda Fridström"
            },
            "education": [
                {
                    "degree": "Byggn:ing:ex",
                    "year": "1946",
                    "institution": "Katrineholms tekn sk"
                }
            ],
            "career": [
                {
                    "position": null,
                    "years": {
                        "start_year": 1954
                    },
                    "organization": "Korsnäs ab"
                }
            ],
            "family": {
                "spouse": "Ingrid Weidlitz",
                "marriage_year": "1950",
                "children": [
                    {
                        "name": "Mats",
                        "birth_year": "1951"
                    },
                    {
                        "name": "Jonas",
                        "birth_year": "1952"
                    }
                ]
            },
            "hobbies": [
                "Bridge",
                "Fiske",
                "Friluftsliv",
                "Slöjd"
            ]
        },
        "4": {
            "full_name": "Lärs-Olof Lindqvist",
            "location": "Uppsala",
            "occupation": "Verkst direktör",
            "birth_details": {
                "date": "03/02/1923",
                "place": "Upps",
                "parents": "Einar L o Märta Ahlström"
            },
            "education": [
                {
                    "degree": "Stud:ex",
                    "year": "1941",
                    "institution": "ab Wilh Becker Sthlm"
                }
            ],
            "career": [
                {
                    "position": "Inneh sjv:aff Svanen",
                    "years": {
                        "start_year": 1951
                    },
                    "organization": "Upps"
                }
            ],
            "family": {
                "spouse": "Gun Wahlberg",
                "marriage_year": "1947",
                "children": [
                    {
                        "name": "Håkan",
                        "birth_year": "1948"
                    },
                    {
                        "name": "Lena",
                        "birth_year": "1951"
                    },
                    {
                        "name": "Johan",
                        "birth_year": "1959"
                    }
                ]
            },
            "hobbies": [
                "Golf",
                "Språk"
            ],
            "community_involvement": [
                {
                    "role": "Sekr",
                    "organization": "Ups golfkl"
                },
                {
                    "role": "Medl",
                    "organization": "Ups simsällsk"
                }
            ]
        }
    }
}