{
    "original": "LISSDANIELS, M OSKAR M,\nstiftsjägmästare, Västerås, f i Malung,\nKopparb l, 20/6/98 av hemm:äg L M\nMattsson o Brita Andersson.\nStud:ex Lund 20, SkHS 25, stud StHS.\n-Stiftsjägm Västerås t 63. - Utm: RNO.\nGift 41 m farm kand Brita Weng.\n\nLISSEL, E PONTUS, ingenjör, förste\nbilinspektör, Falun, f i Falun 21/2/99\nav kronolänsm Mathias L o Malin\nCarlström.\n\nIng:ex Tekn gymn Örebro 19, ing gruv\nab Dalarna Idkerberget 19, Falu mek\nverkst 20, T P Larsson &amp; Co mek verkst\nNås 22, besiktn :man f motorfordon 24,\nbilinsp 48, l:e bilinsp sed 55. - Led\nKopparb l trafiksäkerh:komm. - Medl\nFrimO. - Skr: Handbok för besiktning o\nflygande inspektion (55). - Utm: RVO.\n- Hobbies: jakt, fiske, filateli,\nnumis-matik.\n\nGift 34 m Anna Nilsson, dtr t hemm:äg\nB N N o Anna Nilsson. - Barn: Kerstin\nf 36.\n\nLISSEL, E WALFRID,\nförsäljningschef, Ludvika, f i Björbo, Kopparb l,\n12/1/17 av hantverkare Edvard L o Elin\nHallqvist.\n\nRealex 34, hdlsgymn :ex Malmö 48\n(priv). - Anst Asea 34, Sv\nträimpregne-rings ab Ludvika 36, försäljn :ch där sed\n57. - Medl FrimO, Odd Fellow. -\nHobbies: fiske, sport.\n\nGift 41 m Karin Norgren, dtr t C N o\nAnna Gustafsson. - Barn: Kristina f 45.\n\nLITHAMMER, P-A (PELLE),\nfolkskollärare, Månkarbo, f i Lit, Jämtl l,\n29/4/24 av mål Adolf Jansson o Ida\nOlsson.\n\nStud:ex Upps 44, folkskollär :ex där 47,\nungd:sekr Uppl Ansgariiförb 47,\nfolkskollär Tegelsmora 49, Västland 53,\nungd:instr SMU 55, folkskollär Västland\n\n56, red SMU 58, folkskollär Månkarbo\nsed 60. - Styr:led SMF:s juniorer 52-56,\nSMU 56-58, Uppl Ansgariiförb 56, led\nbarnav:ndn Västland 56-58. - Skr;\nPelles program (55), Programtips för\nfritidsgrupper (del I 55, del II 56), Trons\nutvandrare (57), Petrus fiskaren (58),\nMed pennan i hand (58), Ledarskolan\n(58).\n\nGift 54 m Birgit Hillgren f 27, dtr t\nlantbr Anton H o Klara Holmgren.\n-Barn: Hans f 55, Lars f 57, Per f 60,\nAnna Carin f 61.\n\n",
    "structured": {
        "1": {
            "full_name": "LISSDANIELS, M OSKAR M",
            "location": "Västerås",
            "occupation": "stiftsjägmästare",
            "birth_details": {
                "date": "20/06/1898",
                "place": "Malung"
            },
            "education": [
                {
                    "degree": "Stud:ex",
                    "year": "1920",
                    "institution": "Lund"
                },
                {
                    "degree": "SkHS",
                    "year": "1925",
                    "institution": "Stud StHS"
                }
            ],
            "career": [
                {
                    "position": "Stiftsjägm Västerås",
                    "years": {
                        "start_year": 1963,
                        "end_year": null
                    },
                    "organization": null
                }
            ],
            "family": {
                "spouse": "Brita Weng",
                "marriage_year": "1941",
                "children": []
            }
        },
        "2": {
            "full_name": "LISSEL, E PONTUS",
            "location": "Falun",
            "occupation": "ingenjör, förste bilinspektör",
            "birth_details": {
                "date": "21/02/1899",
                "place": "Falun"
            },
            "education": [
                {
                    "degree": "Ing:ex Tekn gymn",
                    "year": "1919",
                    "institution": "Örebro"
                }
            ],
            "career": [
                {
                    "position": "besiktn :man f motorfordon",
                    "years": {
                        "start_year": 1924,
                        "end_year": null
                    },
                    "organization": null
                },
                {
                    "position": "bilinsp",
                    "years": {
                        "start_year": 1948,
                        "end_year": null
                    },
                    "organization": null
                }
            ],
            "family": {
                "spouse": "Anna Nilsson",
                "marriage_year": "1934",
                "children": [
                    {
                        "name": "Kerstin",
                        "birth_year": "1936"
                    }
                ]
            },
            "publications": [
                {
                    "title": "Handbok för besiktning o flygande inspektion",
                    "year": "1955",
                    "type": null
                }
            ],
            "hobbies": [
                "jakt",
                "fiske",
                "filateli",
                "numismatik"
            ]
        },
        "3": {
            "full_name": "LISSEL, E WALFRID",
            "location": "Ludvika",
            "occupation": "försäljningschef",
            "birth_details": {
                "date": "12/01/1917",
                "place": "Björbo, Kopparb l"
            },
            "education": [
                {
                    "degree": "Realex",
                    "year": "1934",
                    "institution": null
                },
                {
                    "degree": "hdlsgymn :ex",
                    "year": "1948",
                    "institution": "Malmö"
                }
            ],
            "career": [
                {
                    "position": "anst Asea",
                    "years": {
                        "start_year": 1934,
                        "end_year": null
                    },
                    "organization": null
                },
                {
                    "position": "försäljn :ch",
                    "years": {
                        "start_year": 1957,
                        "end_year": null
                    },
                    "organization": "Sv träimpregnerings ab Ludvika"
                }
            ],
            "family": {
                "spouse": "Karin Norgren",
                "marriage_year": "1941",
                "children": [
                    {
                        "name": "Kristina",
                        "birth_year": "1945"
                    }
                ]
            },
            "hobbies": [
                "fiske",
                "sport"
            ]
        },
        "4": {
            "full_name": "LITHAMMER, P-A (PELLE)",
            "location": "Månkarbo",
            "occupation": "folkskollärare",
            "birth_details": {
                "date": "29/04/1924",
                "place": "Lit, Jämtl l"
            },
            "education": [
                {
                    "degree": "Stud:ex",
                    "year": "1944",
                    "institution": "Upps"
                },
                {
                    "degree": "folkskollär",
                    "year": "1947",
                    "institution": "Upps"
                }
            ],
            "career": [
                {
                    "position": "folkskollär Tegelsmora",
                    "years": {
                        "start_year": 1949,
                        "end_year": 1953
                    },
                    "organization": null
                },
                {
                    "position": "ungd:instr SMU",
                    "years": {
                        "start_year": 1955,
                        "end_year": null
                    },
                    "organization": null
                },
                {
                    "position": "folkskollär Månkarbo",
                    "years": {
                        "start_year": 1960,
                        "end_year": null
                    },
                    "organization": null
                }
            ],
            "family": {
                "spouse": "Birgit Hillgren",
                "marriage_year": "1954",
                "children": [
                    {
                        "name": "Hans",
                        "birth_year": "1955"
                    },
                    {
                        "name": "Lars",
                        "birth_year": "1957"
                    },
                    {
                        "name": "Per",
                        "birth_year": "1960"
                    },
                    {
                        "name": "Anna Carin",
                        "birth_year": "1961"
                    }
                ]
            },
            "publications": [
                {
                    "title": "Pelles program",
                    "year": "1955",
                    "type": null
                },
                {
                    "title": "Programtips för fritidsgrupper (del I, II)",
                    "year": "1955, 1956",
                    "type": null
                },
                {
                    "title": "Trons utvandrare",
                    "year": "1957",
                    "type": null
                },
                {
                    "title": "Petrus fiskaren",
                    "year": "1958",
                    "type": null
                },
                {
                    "title": "Med pennan i hand",
                    "year": "1958",
                    "type": null
                },
                {
                    "title": "Ledarskolan",
                    "year": "1958",
                    "type": null
                }
            ]
        }
    }
}