{
    "original": "LJUNGBERG, UNO C, tandläkare,\nSala, f i Hässleby, Jönkpgs l, 12/9/07 av\nstat :insp Hjalmar L o Frida Hallgren.\nStud:ex Eksjö 28, med kand Upps 32,\ntandläk:ex 35, prakt Sala 35-61,\nskol-tandläk 39-42, tandläk:konsult Sala las\nsed 56, l:e distr:tandläk folktandv Sala.\n\n-  Sekr Västmanl l tandläk:fören 40-43,\ngillesvärd Smal gille 37-57. - Skr i\nfackämnen.\n\nGift 35 m Britta Grönbeck f 06, dtr t\nbankkamr Gösta G o Agnes Fromell.\n-Barn: Anders f 40.\n\nLJUNGBERT, HANS Å, fil mag,\nläroverksadjunkt, Karlstad, f i Borås 22/9/23\nav folkskollär Ernst L o Maja\nJohansson.\n\nStud:ex Karlstad 43, fil mag Upps 54,\neo adj hal Luleå 53, adj hal Karlstad\nsed 57. - Medl Sv kemistsamf, OD.\n-Hobbies: sång, musik, friluftsliv.\nGift 53 m jur kand Irma Malmgren f\n25, dtr t prost Folke M o Hertha\nAndersson. - Barn: Åke f 54, Pär f 58.\n\nLJUNGDAHL, BJÖRN J,\nläroverksadjunkt, Eskilstuna, f i Flen 10/8/25 av\nkamr John L o Greta Eckerberg.\nStud:ex 44, fil mag Upps 53, lär Enkpg\n53, hal Eskilstuna 55, adj där sed 59.\n-Hobby: segling.\n\nGift 53 m Kerstin Ekdahl f 28, dtr t\ntandläk Otto E o Sassa Sundberg.\n\nLJUNGDAHL, CARL H, kantor,\nJärna, f i Höör, Malmöh l, 7/10/92 av\nspelman Carl L o Sophia Henriksdotter.\n\nFolkskollär :ex Lund 13, org:- o\nkyrkosång :ex Kalmar 19, folkskollär Vånevik\n13, folkskollär, org, kant o klockare\nGullabo 15, Glimåkra 20, Över-Järna\n30-59. - Omb :man Kyrkomusikernas\nriksförb o led dess centralstyr 38-56\n(ordf centralstyr 52-56, hedL), hed:ordf\nSträngnäs stifts kyrkomusikerfören.\n-Inneh ett flert komm uppdr 30-50, ordf\nkomm:fullm o komm:nd sed 52, start\nJärna vattenverk 40, Stift Järnabost 49\n(ordf o verkst led 49-62). - Medl S:ta\nRagnhilds gille, charterpresid Lions\nClub. - Medarb fackl tidn o kårpubl,\nFolksk årsb, Sv:es allm org:- o\nkant:-fören minnesskr 1901—1951. - Utm:\nRVO, PatrSGM, Sv kyrkosångsfbM,\nSRKplak, Svrifbdipl, Södermani gymnfb\ndipl o plak. - Hobby: trädgårdsskötsel.\nGift 1) 15 m Alfhild Arnold f 93 d 50,\ndtr t med dr A A o Anna Röhl, 2) 51\nm Dagmar Lagergren, i h 2:a akt, f 00,\ndtr t postmast Harald L o Maria\nKorsgren. - Barn: Gunborg f 16, Birgitta\nf 33.\n\n",
    "structured": {
        "1": {
            "full_name": "LJUNGBERG, UNO C",
            "location": "Sala",
            "occupation": "tandläkare",
            "birth_details": {
                "date": "12/09/1907",
                "place": "Hässleby, Jönköpings län",
                "parents": "stat:insp Hjalmar L o Frida Hallgren"
            },
            "education": [
                {
                    "degree": "Stud:ex",
                    "year": "1928",
                    "institution": "Eksjö"
                },
                {
                    "degree": "med kand",
                    "year": "1932",
                    "institution": "Uppsala"
                },
                {
                    "degree": "tandläk:ex",
                    "year": "1935",
                    "institution": "NULL"
                }
            ],
            "career": [
                {
                    "position": "prakt",
                    "years": {
                        "start_year": 1935,
                        "end_year": 1961
                    },
                    "organization": "Sala"
                },
                {
                    "position": "skol-tandläk",
                    "years": {
                        "start_year": 1939,
                        "end_year": 1942
                    },
                    "organization": "NULL"
                },
                {
                    "position": "tandläk:konsult",
                    "years": {
                        "start_year": 1956,
                        "end_year": 1961
                    },
                    "organization": "Sala las"
                },
                {
                    "position": "l:e distr:tandläk folktandv",
                    "years": {
                        "start_year": "NULL",
                        "end_year": "NULL"
                    },
                    "organization": "Sala"
                }
            ],
            "family": {
                "spouse": "Britta Grönbeck",
                "marriage_year": "1935",
                "children": [
                    {
                        "name": "Anders",
                        "birth_year": "1940"
                    }
                ]
            }
        },
        "2": {
            "full_name": "LJUNGBERT, HANS Å",
            "location": "Karlstad",
            "occupation": "fil mag, läroverksadjunkt",
            "birth_details": {
                "date": "22/09/1923",
                "place": "Borås",
                "parents": "folkskollär Ernst L o Maja Johansson"
            },
            "education": [
                {
                    "degree": "Stud:ex",
                    "year": "1943",
                    "institution": "Karlstad"
                },
                {
                    "degree": "fil mag",
                    "year": "1954",
                    "institution": "Uppsala"
                }
            ],
            "career": [
                {
                    "position": "eo adj hal",
                    "years": {
                        "start_year": 1953,
                        "end_year": "NULL"
                    },
                    "organization": "Luleå"
                },
                {
                    "position": "adj hal",
                    "years": {
                        "start_year": 1957,
                        "end_year": "NULL"
                    },
                    "organization": "Karlstad"
                }
            ],
            "family": {
                "spouse": "Irma Malmgren",
                "marriage_year": "1953",
                "children": [
                    {
                        "name": "Åke",
                        "birth_year": "1954"
                    },
                    {
                        "name": "Pär",
                        "birth_year": "1958"
                    }
                ]
            },
            "hobbies": [
                "sång",
                "musik",
                "friluftsliv"
            ]
        },
        "3": {
            "full_name": "LJUNGDAHL, BJÖRN J",
            "location": "Eskilstuna",
            "occupation": "läroverksadjunkt",
            "birth_details": {
                "date": "10/08/1925",
                "place": "Flen",
                "parents": "kamr John L o Greta Eckerberg"
            },
            "education": [
                {
                    "degree": "Stud:ex",
                    "year": "1944",
                    "institution": "NULL"
                },
                {
                    "degree": "fil mag",
                    "year": "1953",
                    "institution": "Uppsala"
                }
            ],
            "career": [
                {
                    "position": "lär",
                    "years": {
                        "start_year": 1953,
                        "end_year": 1955
                    },
                    "organization": "Enköping"
                },
                {
                    "position": "hal",
                    "years": {
                        "start_year": 1955,
                        "end_year": "NULL"
                    },
                    "organization": "Eskilstuna"
                }
            ],
            "family": {
                "spouse": "Kerstin Ekdahl",
                "marriage_year": "1953",
                "children": [
                    {
                        "name": "NULL",
                        "birth_year": "NULL"
                    }
                ]
            },
            "hobby": "segling"
        },
        "4": {
            "full_name": "LJUNGDAHL, CARL H",
            "location": "Järna",
            "occupation": "kantor",
            "birth_details": {
                "date": "07/10/1892",
                "place": "Höör, Malmöhus län",
                "parents": "spelman Carl L o Sophia Henriksdotter"
            },
            "education": [
                {
                    "degree": "Folkskollär :ex",
                    "year": "1913",
                    "institution": "Lund"
                },
                {
                    "degree": "org:- o kyrkosång :ex",
                    "year": "1919",
                    "institution": "Kalmar"
                }
            ],
            "career": [
                {
                    "position": "folkskollär",
                    "years": {
                        "start_year": 1913,
                        "end_year": "NULL"
                    },
                    "organization": "Vånevik"
                },
                {
                    "position": "folkskollär, org, kant o klockare",
                    "years": {
                        "start_year": 1915,
                        "end_year": "NULL"
                    },
                    "organization": "Gullabo"
                },
                {
                    "position": "Omb :man",
                    "years": {
                        "start_year": 1930,
                        "end_year": 1950
                    },
                    "organization": "Kyrkomusikernas riksförb"
                },
                {
                    "position": "ordf",
                    "years": {
                        "start_year": 1952,
                        "end_year": 1956
                    },
                    "organization": "centralstyr"
                },
                {
                    "position": "hed:ordf",
                    "years": {
                        "start_year": "NULL",
                        "end_year": "NULL"
                    },
                    "organization": "Strängnäs stifts kyrkomusikerfören"
                },
                {
                    "position": "ordf o verkst led",
                    "years": {
                        "start_year": 1949,
                        "end_year": 1962
                    },
                    "organization": "Stift Järnabost"
                },
                {
                    "position": "NULL",
                    "years": {
                        "start_year": "NULL",
                        "end_year": "NULL"
                    },
                    "organization": "S:ta Ragnhilds gille"
                }
            ],
            "family": {
                "spouse": "1) Alfhild Arnold, 2) Dagmar Lagergren",
                "marriage_year": "1) 1915, 2) 1951",
                "children": [
                    {
                        "name": "Gunborg",
                        "birth_year": "1916"
                    },
                    {
                        "name": "Birgitta",
                        "birth_year": "1933"
                    }
                ]
            },
            "hobby": "trädgårdsskötsel"
        }
    }
}