{
    "original": "LILLIESKÖLD, STEN G O,\nintendent, Uppsala, f i Sthlm 27/9/16 av adv\nOscar L o Greta von Schéele.\nStud:ex 36, ch Fenix-Heimdalls kundtj\n41, distr:ch Hansa Upps 48, intend o ch\nfastigh :avd Ups adv :byrå sed 62. - Medl\nFrimO, Odd Fellow, Mercuriisällsk.\n-Utm: MstSM. - Hobby: filateli.\nGift 43 m Ulla Mårtensson f 23, dtr t\nfastigh :äg Reinhold M o Lisa Eriksson.\n- Barn: Jan f 44, Clemens f 48.\n\nLINDH, BENGT G, ekonomichef,\nTorshälla, f i Borås 9/5/29 av\nförsäljn:-ch Ture L o Elsa Johansson.\nRealex 45, dipl föret:ekon 53; anst\nByggn ab Oscar Ohlsson Borås 46,\nkassör ab Trikåfabr Elit 52, fastigh:förv\nSv riksbyggen 54, kamr Mälardalens\nbyggn ab Eskilstuna 56, ekon :ch där sed\n62. - Medl TempelriddarO.\nGift 59 m Birgit Tilander f 34. - Barn:\nBörje f 60.\n\nLINDH, ELIS W, landsfiskal,\nNorrtälje, f i Ludvika 22/3/07 av\nnämndeman Carl L o Anna Johnsson.\n\nStud:ex Västerås 27, kansliex Upps 32,\ne landsfiskal o landsfiskalsass Borlänge\n34-48, landsfiskal Nätra 48, Norrtälje\nsed 55. - Medl Rotary.\nGift 36 m Anna-Lisa Rune f 10, dtr t\ndisp Lars R o Maja Johnsson. - Barn:\nAnders f 44, Gunnar f 46, Britta f 50.\n\nLIND, EVA, läroverksadjunkt,\nVästerås, f i Sthlm 15/4/13 av dir Fritz L o\nElisabet Malmberg.\nFil måg Sthlm  38,  e adj  hal Västerås\n\n44,   eo  adj hal Växjö 45,  ord  adj  hal\nVästerås  sed 48, vik lekt  61.  -  Deläg\nAlfred    Lundins    bokbinderiab    Sthlm,\nstyr :led sed 54. - Hobbies: resor,\nskidåkning, bridge.\n\nLINDH, A H FOLKE, bankdirektör,\n\nEskilstuna, f i Grängesberg, Kopparb l,\n25121 OS av stat: kar Isf orm C G L o Anna\nÅnberg.\n\nRealex 24, hdlssk 26, anst Sv hdlsbkn\n26, kamr dess avd :kont Älvdalen 36,\nÖrnsköldsvik 45, avd :kamr o pers :ch\nSundsvall 47, Gävle 48, Örebro 53, dir\navd :kont Boden 54, dir o styr :led\nEskilstuna sed 61. - Medl Rotary, Odd\nFellow, Sällsk B 7. - Hobby: friluftsliv.\nGift 32 m Frida Pettersson f 09, dtr t\nPer Emil P o Emma Persson. - Barn:\nOlle f 34.\n\n",
    "structured": {
        "0": {
            "full_name": "Sten G O Lilliesköld",
            "location": "Uppsala",
            "occupation": "intendent",
            "birth_details": {
                "date": "27/09/1916",
                "place": "Stockholm"
            },
            "education": [
                {
                    "degree": "Stud:ex",
                    "year": "1936",
                    "institution": "Fenix-Heimdalls kundtj"
                }
            ],
            "career": [
                {
                    "position": "distr:ch",
                    "years": {
                        "start_year": 1948,
                        "end_year": 1948
                    },
                    "organization": "Hansa Upps"
                },
                {
                    "position": "intend o ch fastigh",
                    "years": {
                        "start_year": 1962,
                        "end_year": null
                    },
                    "organization": "Ups adv :byrå"
                }
            ],
            "family": {
                "spouse": "Ulla Mårtensson",
                "marriage_year": "1943",
                "children": [
                    {
                        "name": "Jan",
                        "birth_year": "1944"
                    },
                    {
                        "name": "Clemens",
                        "birth_year": "1948"
                    }
                ]
            },
            "hobbies": [
                "filateli"
            ]
        },
        "1": {
            "full_name": "Bengt G Lindh",
            "location": "Torshälla",
            "occupation": "ekonomichef",
            "birth_details": {
                "date": "09/05/1929",
                "place": "Borås"
            },
            "education": [
                {
                    "degree": "Realex",
                    "year": "1945",
                    "institution": null
                },
                {
                    "degree": "dipl föret:ekon",
                    "year": "1953",
                    "institution": null
                }
            ],
            "career": [
                {
                    "position": "kassör",
                    "years": {
                        "start_year": 1952,
                        "end_year": null
                    },
                    "organization": "ab Trikåfabr Elit"
                },
                {
                    "position": "ekon :ch",
                    "years": {
                        "start_year": 1962,
                        "end_year": null
                    },
                    "organization": "Mälardalens byggn ab Eskilstuna"
                }
            ],
            "family": {
                "spouse": "Birgit Tilander",
                "marriage_year": "1959",
                "children": [
                    {
                        "name": "Börje",
                        "birth_year": "1960"
                    }
                ]
            }
        },
        "2": {
            "full_name": "Elis W Lindh",
            "location": "Norrtälje",
            "occupation": "landsfiskal",
            "birth_details": {
                "date": "22/03/1907",
                "place": "Ludvika"
            },
            "education": [
                {
                    "degree": "Stud:ex",
                    "year": "1927",
                    "institution": "Västerås"
                },
                {
                    "degree": "kansliex",
                    "year": "1932",
                    "institution": "Upps"
                }
            ],
            "career": [
                {
                    "position": "landsfiskal o landsfiskalsass",
                    "years": {
                        "start_year": 1934,
                        "end_year": 1948
                    },
                    "organization": "Borlänge"
                },
                {
                    "position": "landsfiskal",
                    "years": {
                        "start_year": 1955,
                        "end_year": null
                    },
                    "organization": "Norrtälje"
                }
            ],
            "family": {
                "spouse": "Anna-Lisa Rune",
                "marriage_year": "1936",
                "children": [
                    {
                        "name": "Anders",
                        "birth_year": "1944"
                    },
                    {
                        "name": "Gunnar",
                        "birth_year": "1946"
                    },
                    {
                        "name": "Britta",
                        "birth_year": "1950"
                    }
                ]
            }
        },
        "3": {
            "full_name": "Eva Lindh",
            "location": "Västerås",
            "occupation": "läroverksadjunkt",
            "birth_details": {
                "date": "15/04/1913",
                "place": "Stockholm"
            },
            "education": [
                {
                    "degree": "Filosofie magister",
                    "year": "1938",
                    "institution": "Sthlm"
                }
            ],
            "career": [
                {
                    "position": "eo adj hal",
                    "years": {
                        "start_year": 1948,
                        "end_year": null
                    },
                    "organization": "Västerås"
                },
                {
                    "position": "ord adj hal",
                    "years": {
                        "start_year": 1961,
                        "end_year": null
                    },
                    "organization": "Västerås"
                }
            ],
            "family": null,
            "hobbies": [
                "resor",
                "skidåkning",
                "bridge"
            ]
        },
        "4": {
            "full_name": "A H Folke Lindh",
            "location": "Eskilstuna",
            "occupation": "bankdirektör",
            "birth_details": {
                "date": null,
                "place": "Grängesberg, Kopparbergs län"
            },
            "education": [
                {
                    "degree": "Realex",
                    "year": "1924",
                    "institution": null
                },
                {
                    "degree": "hdlssk",
                    "year": "1926",
                    "institution": null
                }
            ],
            "career": [
                {
                    "position": "Örnsköldsvik",
                    "years": {
                        "start_year": 1945,
                        "end_year": 1945
                    },
                    "organization": "avd :kamr o pers :ch Sundsvall"
                },
                {
                    "position": "dir avd :kont",
                    "years": {
                        "start_year": 1954,
                        "end_year": null
                    },
                    "organization": "Boden"
                },
                {
                    "position": "dir o styr :led",
                    "years": {
                        "start_year": 1961,
                        "end_year": null
                    },
                    "organization": "Eskilstuna"
                }
            ],
            "family": {
                "spouse": "Frida Pettersson",
                "marriage_year": "1932",
                "children": [
                    {
                        "name": "Olle",
                        "birth_year": "1934"
                    }
                ]
            },
            "hobbies": [
                "friluftsliv"
            ]
        }
    }
}