{
    "original": "LOSELL, GUNNAR E, överläkare,\nNorrtälje, f i Gbg 6/2/02 av red John\nL o Ellen Brandt.\n\nStud:ex Sthlm 21, med lic där 31, tf\naman Allm BB Sthlm 28-30, aman kir\nklin Seraf:las 31-32, 2:e underläk kir\nklin Östersunds las 32-33, l:e underläk\ndär 33-36, aman o underläk kir klin\nSeraf:las 37-40, bitr överläk Östersunds\nlas 40-48, överläk kir klin Norrtälje las\nsed 48. - Medl FrimO, Lions Club, SHT,\nTSO. - Skr: i kir o obstetrik. - Utm:\nRNO, Sv:es ork:fören GM. - Hobby:\nmusik.\n\nGift 31 m Rakel Johansson, dtr t Anton\nJ o Amanda Folke. - Barn: Helena\nf 32, Lars f 35, Hans f 39, Mats f 42.\n\nLOTHIGIUS, WILHELM S J, major,\nNyköping, f i Sthlm 4/3/07 av öv:löjtn\nCarl L o Annie Tidholm.\nStud:ex Upps 25, Off:ex 27, fänrik A 8\n28, AIHS 30-32, löjtn 32, GCI 32-34,\nflygutbildn 36-37, kapt FV 38, FKHS\n\n39-40, major 47, ämneslär matem, fysik\n\n0  biol Nykpgs hal sed 62. - Ordf\nSö-dermanl pistsk sed 52. - Medl W :sex.\n-Sign: Löt. - Utm: RSO, SMIGM,\nSv-PistsfbGM,  Södermani  bfbSM,\nSödermani pistskSM. - Hobbies: jakt, fiske,\nsport, orientering, trädgårdsskötsel.\nGift 37 m Marianne von Döbeln f 15,\ndtr t major Kurt v D o Märta\nNorrman. - Barn: Barbro f 38, Carl f 41,\nPer f 44, Ann-Marie f 49,\n\nLOVÉN, G (GÖSTA) H C C, konstnär,\nValla, f i Sthlm 28/11/17 av major Carl\nL o Lucie Rudolph.\n\nOtte Skölds målarsk 34-37, Stat\nkonst-akad Oslo 37-40. - Utf bl a portr o\nkyrkodekor Norge. - Medl KRO. -\nHobby: musik.\n\nGift 1) 46-48 m Cecilie Aall f 14\n(Norge), 2) 55 m Kari B ordewick-Jensen f\n25, dtr t Rolf B-J o Ingrid Wahl\n(Norge). - Barn: i l:a akt Lucie f 47, i 2:a\nakt Christian f 56, Svante f 59.\n\n",
    "structured": {
        "0": {
            "full_name": "Gunnar E Losell",
            "location": "Norrtälje",
            "occupation": "överläkare",
            "birth_details": {
                "date": "06/02/1902",
                "place": "Göteborg",
                "parents": "red John L o Ellen Brandt"
            },
            "education": [
                {
                    "degree": "Stud:ex",
                    "year": "1921",
                    "institution": "Sthlm"
                },
                {
                    "degree": "med lic",
                    "year": "1931",
                    "institution": "Sthlm"
                }
            ],
            "career": [
                {
                    "position": "tf aman",
                    "years": {
                        "start_year": 1928,
                        "end_year": 1930
                    },
                    "organization": "Allm BB Sthlm"
                },
                {
                    "position": "aman kir klin",
                    "years": {
                        "start_year": 1931,
                        "end_year": 1932
                    },
                    "organization": "Seraf:las"
                },
                {
                    "position": "2:e underläk kir klin",
                    "years": {
                        "start_year": 1932,
                        "end_year": 1933
                    },
                    "organization": "Östersunds las"
                },
                {
                    "position": "l:e underläk",
                    "years": {
                        "start_year": 1933,
                        "end_year": 1936
                    },
                    "organization": "där"
                },
                {
                    "position": "aman o underläk kir klin",
                    "years": {
                        "start_year": 1937,
                        "end_year": 1940
                    },
                    "organization": "Seraf:las"
                },
                {
                    "position": "bitr överläk",
                    "years": {
                        "start_year": 1940,
                        "end_year": 1948
                    },
                    "organization": "Östersunds las"
                },
                {
                    "position": "överläk kir klin",
                    "years": {
                        "start_year": 1948,
                        "end_year": null
                    },
                    "organization": "Norrtälje las"
                }
            ],
            "family": {
                "spouse": "Rakel Johansson",
                "marriage_year": "1931",
                "children": [
                    {
                        "name": "Helena",
                        "birth_year": "1932"
                    },
                    {
                        "name": "Lars",
                        "birth_year": "1935"
                    },
                    {
                        "name": "Hans",
                        "birth_year": "1939"
                    },
                    {
                        "name": "Mats",
                        "birth_year": "1942"
                    }
                ]
            },
            "hobbies": [
                "musik"
            ]
        },
        "1": {
            "full_name": "Wilhelm S J Lothigius",
            "location": "Nyköping",
            "occupation": "major",
            "birth_details": {
                "date": "04/03/1907",
                "place": "Sthlm",
                "parents": "öv:löjtn Carl L o Annie Tidholm"
            },
            "education": [
                {
                    "degree": "Stud:ex",
                    "year": "1925",
                    "institution": "Upps"
                },
                {
                    "degree": "Off:ex",
                    "year": "1927",
                    "institution": null
                }
            ],
            "career": [
                {
                    "position": "fänrik",
                    "years": {
                        "start_year": 1928,
                        "end_year": null
                    },
                    "organization": "A 8"
                },
                {
                    "position": "ämneslär matem, fysik biol",
                    "years": {
                        "start_year": 1962,
                        "end_year": null
                    },
                    "organization": "Nykpgs hal"
                }
            ],
            "family": {
                "spouse": "Marianne von Döbeln",
                "marriage_year": "1937",
                "children": [
                    {
                        "name": "Barbro",
                        "birth_year": "1938"
                    },
                    {
                        "name": "Carl",
                        "birth_year": "1941"
                    },
                    {
                        "name": "Per",
                        "birth_year": "1944"
                    },
                    {
                        "name": "Ann-Marie",
                        "birth_year": "1949"
                    }
                ]
            },
            "hobbies": [
                "jakt",
                "fiske",
                "sport",
                "orientering",
                "trädgårdsskötsel"
            ]
        },
        "2": {
            "full_name": "G (Gösta) H C C Lovén",
            "location": "Valla",
            "occupation": "konstnär",
            "birth_details": {
                "date": "28/11/1917",
                "place": "Sthlm",
                "parents": "major Carl L o Lucie Rudolph"
            },
            "education": [
                {
                    "degree": null,
                    "year": null,
                    "institution": "Otte Skölds målarsk 34-37"
                },
                {
                    "degree": null,
                    "year": null,
                    "institution": "Stat konst-akad Oslo 37-40"
                }
            ],
            "family": {
                "spouse": "1) Cecilie Aall",
                "marriage_year": "1946-1948",
                "children": [
                    {
                        "name": "Lucie",
                        "birth_year": "1947"
                    }
                ]
            },
            "hobbies": [
                "musik"
            ]
        }
    }
}