{
    "original": "Forslund, Johannes Albert, förutv,\n-statsråd, Spånga, f. i Ovansjö, Gävleb.\nL, 11/4/81. Ordf. i sv. järnv\n:manna-förb. 18-36, led. av soc. råd. (sekt. f.\narbrskydd) 28-36, av arb :domst. 29-36,\nLandsorg :s ordf. under 36, därefter\nstatsr o. ch. f. kommunikidep. 28/9\n36-16/12 38, statsr. o. ch. f. soc :dep. 16/12\n38-*3/12 39, F. K. sed. 31 (s), medl. av\nlandst., led. av direkt, f. Karol. sjukh.\no. Seraf :las. fr. 41, f. Allm. BB., Sthlm,\nfr. 42, ordf. i stat. utrymn :komm. 40-41.\nForssman, Gösta Fredrik, med. lic.,\nSthlm, f. 9/1/03 i Mariestad. G. 30 m.\nIngrid Dagmar Nilsén. Barn: Lars\nGösta Fredrik f. 32, Anna-Lena f. 35.\nUnd:läk. v. S:t Görans sjukh. 32-40,\nläk. v. Gustaf V:s jub :klin., Radiumh.,\nSthlm, 40-43 samt därefter v. Karol.\n.sjukh. röntgendiagnostiska avd.,\nlas:-läk. i Landskrona sed. 1/11/44.\nForssman, John Christer Ragnar,\ncivilingenjör, Sthlm, f. 21/8/07 i Lund.\nO. 34 m. Mona Sauber. Barn: Gunnel f.\n39, Magnus f. 42. Studiex. 25 v. Lunds\npriv. elemrsk., avgiex. fr. KTH (E) 30.\nV. verkst, dir. i A-B Rylander &amp;\nAsplund, Sthlm. Förutv, anst.: reklamch.\ni Telefon A-B L. M. Ericsson.\nForsman, Karl Harald Gunnar,\ndirektör, Sthlm, f. 20/9/92 i Sthlm av tj :m.\nAlbin F. o. Theresia Holmgren. G. 18\nm. Götha Sauer. Barn: Bo f. 20, Bengt\nf. 23. Kat. Realskola, Söderm. h. a.\nlärov. 02-09, Sthlms Hdlsgymn. 09-10.\nKorresp., kont:ch., deläg. i A-B G. A.\nDu Rietz 10-30, sektionsch. i\nfolkhush:-kommissionen 16-18, verkst, dir. i Sv.\nLantm:s Riksförb. sed. 30. Led. av\nex-portkreditndn, hästvärder :ndn samt\nmagistr :besiktn:man, ordf. i Sv:a\nMe-lassengr :fören., A-B örbyhus\nLantbr.-mask., A-B Bollnäs Lantbr :byrå o. A-B\nJohn A. Fors. Led. av styr. f. Sveriges\nskilj’end f. spannm. o. foderämn\n:han-deln, Sv:a Spannmåls A-B, A-B Örebro\nKvarn, Fröintr:fören., Foderintr :fören.\nResor: Tyskl., Frankr., Schweiz 21,\nItal. 26, Engl. 35, Ryssl. 40. RVO,\nRFinlVROlkl.\n",
    "structured": {
        "1": {
            "full_name": "Forslund, Johannes Albert",
            "location": "Spånga",
            "occupation": "Förutv, Statsråd",
            "birth_details": {
                "date": "11/04/1881",
                "place": "Ovansjö, Gävleb."
            },
            "education": [
                {
                    "degree": "F. K. sed. 31",
                    "year": "1931",
                    "institution": "s"
                }
            ],
            "career": [
                {
                    "position": "Ordf. i sv. järnv :manna-förb.",
                    "years": {
                        "start_year": 1918,
                        "end_year": 1936
                    },
                    "organization": null
                },
                {
                    "position": "Led. av soc. råd. (sekt. f. arbrskydd)",
                    "years": {
                        "start_year": 1928,
                        "end_year": 1936
                    },
                    "organization": null
                },
                {
                    "position": "Av arb :domst.",
                    "years": {
                        "start_year": 1929,
                        "end_year": 1936
                    },
                    "organization": null
                },
                {
                    "position": "Landsorg :s ordf.",
                    "years": {
                        "start_year": 1936,
                        "end_year": null
                    },
                    "organization": null
                },
                {
                    "position": "Statsr o. ch. f. kommunikidep.",
                    "years": {
                        "start_year": 28,
                        "end_year": 38
                    },
                    "organization": null
                },
                {
                    "position": "Statsr. o. ch. f. soc :dep.",
                    "years": {
                        "start_year": 16,
                        "end_year": 39
                    },
                    "organization": null
                },
                {
                    "position": "Ordf. i stat. utrymn :komm.",
                    "years": {
                        "start_year": 1940,
                        "end_year": 1941
                    },
                    "organization": null
                }
            ],
            "family": {
                "spouse": "",
                "marriage_year": "NULL",
                "children": []
            }
        },
        "2": {
            "full_name": "Forssman, Gösta Fredrik",
            "location": "Sthlm",
            "occupation": "Med. Lic.",
            "birth_details": {
                "date": "09/01/1903",
                "place": "Mariestad"
            },
            "education": null,
            "career": [
                {
                    "position": "Und:läk. v. S:t Görans sjukh.",
                    "years": {
                        "start_year": 1932,
                        "end_year": 1940
                    },
                    "organization": null
                },
                {
                    "position": "Läk. v. Gustaf V:s jub :klin., Radiumh.",
                    "years": {
                        "start_year": 1940,
                        "end_year": 1943
                    },
                    "organization": "Sthlm"
                },
                {
                    "position": "V. Karol. sjukh. röntgendiagnostiska avd., las:-läk.",
                    "years": {
                        "start_year": 1943,
                        "end_year": null
                    },
                    "organization": "Landskrona"
                }
            ],
            "family": {
                "spouse": "Ingrid Dagmar Nilsén",
                "marriage_year": "30",
                "children": [
                    {
                        "name": "Lars Gösta Fredrik",
                        "birth_year": "32"
                    },
                    {
                        "name": "Anna-Lena",
                        "birth_year": "35"
                    }
                ]
            }
        },
        "3": {
            "full_name": "Forssman, John Christer Ragnar",
            "location": "Sthlm",
            "occupation": "Civilingenjör",
            "birth_details": {
                "date": "21/08/1907",
                "place": "Lund"
            },
            "education": [
                {
                    "degree": "Studiex.",
                    "year": "1925",
                    "institution": "Lunds priv. elemrsk."
                },
                {
                    "degree": "Avgiex. fr. KTH (E)",
                    "year": "1930",
                    "institution": "Kungliga Tekniska Högskolan"
                }
            ],
            "career": [
                {
                    "position": "V. verkst, dir. i A-B Rylander & Asplund, Sthlm",
                    "years": {
                        "start_year": null,
                        "end_year": null
                    },
                    "organization": "A-B Rylander & Asplund"
                },
                {
                    "position": "Reklamch. i Telefon A-B L. M. Ericsson",
                    "years": {
                        "start_year": null,
                        "end_year": null
                    },
                    "organization": "Telefon A-B L. M. Ericsson"
                }
            ],
            "family": {
                "spouse": "Mona Sauber",
                "marriage_year": "34",
                "children": [
                    {
                        "name": "Gunnel",
                        "birth_year": "39"
                    },
                    {
                        "name": "Magnus",
                        "birth_year": "42"
                    }
                ]
            }
        },
        "4": {
            "full_name": "Forsman, Karl Harald Gunnar",
            "location": "Sthlm",
            "occupation": "Direktör",
            "birth_details": {
                "date": "20/09/1892",
                "place": "Sthlm"
            },
            "education": [
                {
                    "degree": "Kat. Realskola",
                    "year": "1902-1909",
                    "institution": "Söderm. H. A. Lärov."
                },
                {
                    "degree": "Sthlms Hdlsgymn.",
                    "year": "1909-1910",
                    "institution": null
                }
            ],
            "career": [
                {
                    "position": "Korresp., kont:ch., deläg. i A-B G. A. Du Rietz",
                    "years": {
                        "start_year": 1910,
                        "end_year": 1930
                    },
                    "organization": "A-B G. A. Du Rietz"
                },
                {
                    "position": "Sektionsch. i folkhush:-kommissionen",
                    "years": {
                        "start_year": 1916,
                        "end_year": 1918
                    },
                    "organization": null
                },
                {
                    "position": "Verkst, dir. i Sv. Lantm:s Riksförb.",
                    "years": {
                        "start_year": 1930,
                        "end_year": null
                    },
                    "organization": "Sv. Lantm:s Riksförb."
                }
            ],
            "family": {
                "spouse": "Götha Sauer",
                "marriage_year": "18",
                "children": [
                    {
                        "name": "Bo",
                        "birth_year": "20"
                    },
                    {
                        "name": "Bengt",
                        "birth_year": "23"
                    }
                ]
            }
        }
    }
}