{
    "original": "SJÖGREN,  LARS E G, byråingenjör,\nSthlm, f i Sthlm 4/7/16 av förste\npostass Einar S o Signe Gustafsson.\nStud:ex    36,   Tekn   gymn   Sthlm   40,\nspec:stud   KTH   55,   anst   Ekensbergs\nvarv  Sthlm  40,   Sthlms  örlogsvarv  43,\nFinnboda varv 44, marinförvaltn 46, l:e\nbyråing där sed 56.\n\nGift m Gunvor Lindgren. - Barn:\nSören f 46, Göran f 48.\n\nSJÖGREN,   MARGARETA   W:DTR,\n\njournalist, Lidingö, f i Madesjö, Kalmar\nl, 1/7/19 av jägmäst Waldemar S o\nRuth Jansson.\n\nFil kand 44; medarb Expressen 44-53,\nSvD sed 53. - Sign: Jolanta. - Skr:\nBiljett till balett (57); tills m Jan Olof\nOlsson: Onkel Sams stuga (52),\nDrottningens England (54), Irland, den\nomöjliga ön (57).\nGift 45 m journ Jan Olof Olsson, f 20.\n\n-  Barn: Elizabeth Ann f 55, Vibeke f 58.\nSJÖGREN,  G  T  F  PEDER,\nförfattare,  Bromma,  f  i  Kronob   l,  29/4/05\nav godsäg Carl Otto S o Elin Gleisner.\nLärov:stud. - Resor i Span, Bal’kanländ\n29-39. - Skr: Bar Barbar (37),  Svarta\npalmkronor (44), Kärlekens bröd (45),\nJag vill gå ned till Thimnat (47),\nMannen   som  försökte  smita   (49),   Damen\n(51),   Bikten   (54),   Ta   ner   stjärnorna\n(57),  Till minne (59).  -  Hobby:  fiske.\nGift 54 m Lilian Fidler f 08, dtr t dir\nNorman F o Signe Pettersson.\n\nSJÖGREN, PER A H, verkst direktör,\nBromma, f i Sthlm 25/6/21 av\nhovr:rå-det John S o Käte Bernhardt.\nStud:ex 41, stud StHS 42-45, anst\nAlbert Bonniers förlag Sthlm 45, verkst\ndir ab P A Sjögren 55-60, verkst dir\nab Anders Beckman sed 61. - Ordf\nSthlms försäljn:- o reklamfören 59-62,\npresid Round Table Internat 59-61,\nstift Sällsk bokvännerna.\nGift m Eyvor Hedenström. - Barn:\nPeter f 44, Jan f 46, Jonas f 53, Mattias\nf 55.\n\n",
    "structured": {
        "0": {
            "full_name": "LARS E G SJÖGREN",
            "location": "Sthlm",
            "occupation": "byråingenjör",
            "birth_details": {
                "date": "04/07/1916",
                "place": "Sthlm",
                "parents": "förste postass Einar S o Signe Gustafsson"
            },
            "education": [
                {
                    "degree": "Stud:ex",
                    "year": "1936",
                    "institution": "Tekn gymn Sthlm"
                },
                {
                    "degree": "spec:stud",
                    "year": "1955",
                    "institution": "KTH"
                }
            ],
            "career": [
                {
                    "position": "anst Ekensbergs varv Sthlm",
                    "years": {
                        "start_year": 1940,
                        "end_year": 1943
                    },
                    "organization": "Ekensbergs varv Sthlm"
                },
                {
                    "position": "Sthlms örlogsvarv",
                    "years": {
                        "start_year": 1943,
                        "end_year": 1944
                    },
                    "organization": "Sthlms örlogsvarv"
                },
                {
                    "position": "Finnboda varv",
                    "years": {
                        "start_year": 1944,
                        "end_year": 1946
                    },
                    "organization": "Finnboda varv"
                },
                {
                    "position": "marinförvaltn",
                    "years": {
                        "start_year": 1946,
                        "end_year": 1956
                    },
                    "organization": "marinförvaltn"
                }
            ],
            "family": {
                "spouse": "Gunvor Lindgren",
                "marriage_year": "NULL",
                "children": [
                    {
                        "name": "Sören",
                        "birth_year": "1946"
                    },
                    {
                        "name": "Göran",
                        "birth_year": "1948"
                    }
                ]
            }
        },
        "1": {
            "full_name": "MARGARETA SJÖGREN",
            "location": "Lidingö",
            "occupation": "journalist",
            "birth_details": {
                "date": "01/07/1919",
                "place": "Madesjö, Kalmar l",
                "parents": "jägmäst Waldemar S o Ruth Jansson"
            },
            "education": [
                {
                    "degree": "Fil kand",
                    "year": "1944",
                    "institution": "NULL"
                }
            ],
            "career": [
                {
                    "position": "medarb Expressen",
                    "years": {
                        "start_year": 1944,
                        "end_year": 1953
                    },
                    "organization": "Expressen"
                },
                {
                    "position": "SvD",
                    "years": {
                        "start_year": 1953,
                        "end_year": "NULL"
                    },
                    "organization": "SvD"
                }
            ],
            "family": {
                "spouse": "Jan Olof Olsson",
                "marriage_year": "1945",
                "children": [
                    {
                        "name": "Elizabeth Ann",
                        "birth_year": "1955"
                    },
                    {
                        "name": "Vibeke",
                        "birth_year": "1958"
                    }
                ]
            }
        },
        "2": {
            "full_name": "G T F PEDER SJÖGREN",
            "location": "Bromma",
            "occupation": "författare",
            "birth_details": {
                "date": "29/04/1905",
                "place": "Kronob l",
                "parents": "godsäg Carl Otto S o Elin Gleisner"
            },
            "education": [],
            "career": [],
            "family": {
                "spouse": "Lilian Fidler",
                "marriage_year": "1954",
                "children": "NULL"
            }
        },
        "3": {
            "full_name": "PER A H SJÖGREN",
            "location": "Bromma",
            "occupation": "verkst direktör",
            "birth_details": {
                "date": "25/06/1921",
                "place": "Sthlm",
                "parents": "hovr:rå-det John S o Käte Bernhardt"
            },
            "education": [
                {
                    "degree": "Stud:ex",
                    "year": "1941",
                    "institution": "NULL"
                },
                {
                    "degree": "stud StHS",
                    "year": "1942-1945",
                    "institution": "NULL"
                }
            ],
            "career": [
                {
                    "position": "anst Albert Bonniers förlag Sthlm",
                    "years": {
                        "start_year": 1945,
                        "end_year": 1955
                    },
                    "organization": "Albert Bonniers förlag Sthlm"
                },
                {
                    "position": "verkst dir ab P A Sjögren",
                    "years": {
                        "start_year": 1955,
                        "end_year": 1960
                    },
                    "organization": "ab P A Sjögren"
                },
                {
                    "position": "verkst dir ab Anders Beckman",
                    "years": {
                        "start_year": 1961,
                        "end_year": "NULL"
                    },
                    "organization": "ab Anders Beckman"
                }
            ],
            "family": {
                "spouse": "Eyvor Hedenström",
                "marriage_year": "NULL",
                "children": [
                    {
                        "name": "Peter",
                        "birth_year": "1944"
                    },
                    {
                        "name": "Jan",
                        "birth_year": "1946"
                    },
                    {
                        "name": "Jonas",
                        "birth_year": "1953"
                    },
                    {
                        "name": "Mattias",
                        "birth_year": "1955"
                    }
                ]
            }
        }
    }
}