{
    "original": "SJÖDING, BÖRJE, leg läkare, Farsta,\nf i Sthlm 17/2/16 av fabr John S o\nBerta Larsson.\n\nStud:ex 35, med kand 39, med lic 47,\nvik 2:e läk Sundby sjh 44, e läk Pro\nPatria 45, tf jv:läk Storlien 47, l:e\nunderläk Sabbatsb vård- o ålderdomsh\n53-56, l:e underläk Stureby vård- o\nålderdomsh 56-58, läk Stadshagsgårdens\nålderdomsh sed 58.\n\nSJÖFORS,  C  IVAR  V,  fd  byråchef,\nStocksund, f i Pjätteryd, Kronobergs l,\n20/4/88 av kyrkoh Claes S o Mathilda\nSchéle.\nStud:ex 06, stud Tyskl 07-08, kansliex\n\n18, aman RFA 18, byråch 47-54. - Föredr\nel tf led pen :styr 19-29 o 35-38, ordf\nSthlms II distr pens:nd 32-33, RFA:s\npersonalfören 32-37, ordf kommun :f ullm\nStocksund 44-49, ordf Stocksunds\nfad-derortskomm. - Solist Lunds\nstud:sång-f ören :s konserter o sång :färder 10-24.\n- Förel soc :försäkr v univ :n o Karol\ninst 24-47. - Utm: RNO, RVO, Otto\nLindbladsGM, FHMM.\nGift 27 m Lolo Setterwall f 94, dtr\nt bibliotekarie Kristian S o Birgithe\nAall Hansen. - Barn: Birgitta f 28,\nAnn-Mari f 29.\n\nSJÖGREEN se SJÖGREN\n\nSJÖGREN, BENGT G I:SON,\ndirektör, Stocksund, f i Stocksund 9/1/22 av\nförsäkr:dir Iwar S o Elisabeth Hägge.\nStud:ex Sthlm 41, fil kand Lund 43,\npol mag 44, jur kand 45, DHS 46, anst\nSv Esso ab 46, försäljn :dir där sed 57.\nGift 47 m Gerd Nilsson f 23, dtr t dir\nHerman N o Hanna Ekberg. - Barn:\nBengt f 49, Iwar f 52.\n\nSJÖGREN, BO G, docent, Näsbypark,\nf i Falun 18/3/30 av Gustaf S o\nEllen Lindqvist.\n\nStud:ex 49, KTH 54, tekn lic 57, tekn\ndr 61. - Forskn:as’s KTH 54,\nForskn-inst f fysik Sthlm 55, dtoc där sed 61.\n-Skr: Éxperimental investigations of\nnuclear reactions with a special emphasis\nön magnetic analysis (drsavh 61).\n\n",
    "structured": {
        "0": {
            "full_name": "SJÖDING, BÖRJE",
            "location": "Farsta",
            "occupation": "Leg läkare",
            "birth_details": {
                "date": "17/02/1916",
                "place": "Sthlm",
                "parents": "fabr John S o Berta Larsson"
            },
            "education": [
                {
                    "degree": "Stud:ex",
                    "year": "1935",
                    "institution": "NULL"
                },
                {
                    "degree": "med kand",
                    "year": "1939",
                    "institution": "NULL"
                },
                {
                    "degree": "med lic",
                    "year": "1947",
                    "institution": "NULL"
                }
            ],
            "career": [
                {
                    "position": "vik 2:e läk Sundby sjh",
                    "years": {
                        "start_year": 1944,
                        "end_year": 1945
                    },
                    "organization": "NULL"
                },
                {
                    "position": "e läk Pro Patria",
                    "years": {
                        "start_year": 1945,
                        "end_year": 1945
                    },
                    "organization": "NULL"
                },
                {
                    "position": "tf jv:läk Storlien",
                    "years": {
                        "start_year": 1947,
                        "end_year": 1947
                    },
                    "organization": "NULL"
                },
                {
                    "position": "l:e underläk Sabbatsb vård- o ålderdomsh",
                    "years": {
                        "start_year": 1953,
                        "end_year": 1956
                    },
                    "organization": "NULL"
                },
                {
                    "position": "l:e underläk Stureby vård- o ålderdomsh",
                    "years": {
                        "start_year": 1956,
                        "end_year": 1958
                    },
                    "organization": "NULL"
                },
                {
                    "position": "läk Stadshagsgårdens ålderdomsh",
                    "years": {
                        "start_year": 1958,
                        "end_year": "NULL"
                    },
                    "organization": "NULL"
                }
            ],
            "family": {
                "spouse": "NULL",
                "marriage_year": "NULL",
                "children": []
            }
        },
        "1": {
            "full_name": "SJÖFORS, C IVAR V",
            "location": "Stocksund",
            "occupation": "fd byråchef",
            "birth_details": {
                "date": "20/04/1888",
                "place": "Pjätteryd, Kronobergs l",
                "parents": "kyrkoh Claes S o Mathilda Schéle"
            },
            "education": [],
            "career": [
                {
                    "position": "kansliex",
                    "years": {
                        "start_year": 1918,
                        "end_year": "NULL"
                    },
                    "organization": "NULL"
                },
                {
                    "position": "aman RFA",
                    "years": {
                        "start_year": 1918,
                        "end_year": "NULL"
                    },
                    "organization": "NULL"
                },
                {
                    "position": "byråch",
                    "years": {
                        "start_year": 1947,
                        "end_year": 1954
                    },
                    "organization": "NULL"
                }
            ],
            "family": {
                "spouse": "Lolo Setterwall",
                "marriage_year": "1927",
                "children": [
                    {
                        "name": "Birgitta",
                        "birth_year": "1928"
                    },
                    {
                        "name": "Ann-Mari",
                        "birth_year": "1929"
                    }
                ]
            }
        },
        "2": {
            "full_name": "SJÖGREEN",
            "location": "NULL",
            "occupation": "NULL",
            "birth_details": {
                "date": "NULL",
                "place": "NULL",
                "parents": "NULL"
            },
            "education": [],
            "career": [],
            "family": {
                "spouse": "NULL",
                "marriage_year": "NULL",
                "children": []
            }
        },
        "3": {
            "full_name": "SJÖGREN, BENGT G I:SON",
            "location": "Stocksund",
            "occupation": "direktör",
            "birth_details": {
                "date": "09/01/1922",
                "place": "Stocksund",
                "parents": "försäkr:dir Iwar S o Elisabeth Hägge"
            },
            "education": [
                {
                    "degree": "Stud:ex",
                    "year": "1941",
                    "institution": "Sthlm"
                },
                {
                    "degree": "fil kand",
                    "year": "1943",
                    "institution": "Lund"
                },
                {
                    "degree": "pol mag",
                    "year": "1944",
                    "institution": "NULL"
                },
                {
                    "degree": "jur kand",
                    "year": "1945",
                    "institution": "NULL"
                },
                {
                    "degree": "DHS",
                    "year": "1946",
                    "institution": "NULL"
                }
            ],
            "career": [
                {
                    "position": "anst Sv Esso ab",
                    "years": {
                        "start_year": 1946,
                        "end_year": "NULL"
                    },
                    "organization": "NULL"
                },
                {
                    "position": "försäljn :dir",
                    "years": {
                        "start_year": 1957,
                        "end_year": "NULL"
                    },
                    "organization": "Sv Esso ab"
                }
            ],
            "family": {
                "spouse": "Gerd Nilsson",
                "marriage_year": "1947",
                "children": [
                    {
                        "name": "Bengt",
                        "birth_year": "1949"
                    },
                    {
                        "name": "Iwar",
                        "birth_year": "1952"
                    }
                ]
            }
        },
        "4": {
            "full_name": "SJÖGREN, BO G",
            "location": "Näsbypark",
            "occupation": "docent",
            "birth_details": {
                "date": "18/03/1930",
                "place": "Falun",
                "parents": "Gustaf S o Ellen Lindqvist"
            },
            "education": [
                {
                    "degree": "Stud:ex",
                    "year": "1949",
                    "institution": "NULL"
                },
                {
                    "degree": "KTH",
                    "year": "1954",
                    "institution": "NULL"
                },
                {
                    "degree": "tekn lic",
                    "year": "1957",
                    "institution": "NULL"
                },
                {
                    "degree": "tekn dr",
                    "year": "1961",
                    "institution": "NULL"
                }
            ],
            "career": [
                {
                    "position": "dtoc",
                    "years": {
                        "start_year": 1961,
                        "end_year": "NULL"
                    },
                    "organization": "NULL"
                }
            ],
            "family": {
                "spouse": "NULL",
                "marriage_year": "NULL",
                "children": []
            }
        }
    }
}