{
    "original": "JELKE, C HUGO, fd överläkare,\nGävle, f i Hedemora 12/8/99 av handl\nAugust Carlson o Anna Gustafson.\nStud:ex Upps 19, med kand 24 o med lic\ndär 29, öl ass:-, aman:- o\nunderläk:-förordn 29-32, underläk med avd\nSundsvalls las 33-35, med avd Halmstads las\n36-38, Barnsjh Samariten 38-39, l:e\nunderläk Sthlms epid:sjh 40-41, Barnsjh\nSamariten 41-43, e läk Gävle las 44-45,\növerläk barnavd där 45-65, prakt läk sed\n65. - Skr i inv med o pediatrik. - Utm:\nRNO, RFinlVROlkl.\nGift 36 m Margareta Berggren f 04, dtr\nt lantbr :ing Emil B o Anna Holmström.\n- Barn: Gunilla f 38, Kristina f 45.\n\nJENHOFF, A M (ANNIE) G,\nteater-pedagog, Östersund, f i Nykpg 2/7/29 av\nköpm Gunnar J o Signe J.\nBraintree Dramatic Soc, Terserus\nteater-sk 48-50, Dramat teat elevsk 50-53, skå-\n\ndesp Dramat teat 53-54, Alléteat,\nKam-marteat, Drottningholms slottsteat,\nRiks-teat, Pionjärteat, Sthlms skolbarnsteat,\nNorrkpgs stadsteat, mit:tag, konstnär!\nled o regissör Östersunds ungd :teat.\n-Konstnärl led o regissör kyrkospel, led\nteatercirklar, lär i tal- o röstvård,\nstu-dietekn o dramatik. - Medl Sv\nteater-förb. - Skr: dikter p kulturart i\nÖstersundsposten o Länstidn. - Hobbies:\nteckning, målning, ridning.\nGift 1) 51 m köpm Bertil örnklint, 2) 60\nm skådesp Sven Wollter. - Barn: i l:a\nakt Simone f 52, Tom f 55, i 2:a akt\nYlva f 62, Stina f 64.\n\nJENNISCHE,   G  SIGNHILD,  lektor,\n\nGävle, f i Umeå 15/7/05 av bankkamr\nGustaf J o Anna Ungman.\nStud:ex Sthlm 33, fil lic Upps 39, e adj\nfolksk:sem Kalmar 39-40, hal Kalmar\n42, småsk:sem Strängnäs 43, hal Gävle\n44, adj 45, lekt i sv o eng där sed 60.\n-Skr: Två i världen (diktsaml 37),\nKarlfeldt o Petöfi (Samlaren, 43). - Utm:\nLNO. - Hobby: fiske.\n\nJERDÉN, SVEN, jägmästare,\nSkellefteå, f i Malmö 9/6/17 av civ:ing Alfred\nJ o Anna Sandblad.\n\nStud:ex 37, SkHS 44, anst Domänverket\n48, revirförv Burträsks revir sed 59.\n-Rekt Älvsby skogssk 56-58. - Hobbies:\njakt, fiske.\n\nGift 49 m Annalisa Stalin f 18, dtr t\njärnhandl Alexis S o Märta Nordström.\n- Barn: Anna f 50, Lars f 52.\n\n",
    "structured": {
        "1": {
            "full_name": "C Hugo Jelke",
            "location": "Gävle",
            "occupation": "fd överläkare",
            "birth_details": {
                "date": "12/08/1899",
                "place": "Hedemora",
                "parents": "handl August Carlson o Anna Gustafson"
            },
            "education": [
                {
                    "degree": "Stud:ex",
                    "year": "1919",
                    "institution": "Upps"
                },
                {
                    "degree": "med kand",
                    "year": "1924",
                    "institution": "Upps"
                },
                {
                    "degree": "med lic",
                    "year": "1929",
                    "institution": "Upps"
                }
            ],
            "career": [
                {
                    "position": "öl ass",
                    "years": {
                        "start_year": 1929,
                        "end_year": 1932
                    },
                    "organization": null
                },
                {
                    "position": "aman",
                    "years": {
                        "start_year": 1929,
                        "end_year": null
                    },
                    "organization": null
                },
                {
                    "position": "underläk",
                    "years": {
                        "start_year": 1933,
                        "end_year": 1935
                    },
                    "organization": "Sundsvalls las"
                },
                {
                    "position": "underläk",
                    "years": {
                        "start_year": 1936,
                        "end_year": 1938
                    },
                    "organization": "Halmstads las"
                },
                {
                    "position": "Barnsjh Samariten",
                    "years": {
                        "start_year": 1938,
                        "end_year": 1939
                    },
                    "organization": null
                },
                {
                    "position": "l:e underläk",
                    "years": {
                        "start_year": 1940,
                        "end_year": 1941
                    },
                    "organization": "Sthlms epid:sjh"
                },
                {
                    "position": "Barnsjh Samariten",
                    "years": {
                        "start_year": 1941,
                        "end_year": 1943
                    },
                    "organization": null
                },
                {
                    "position": "e läk",
                    "years": {
                        "start_year": 1944,
                        "end_year": 1945
                    },
                    "organization": "Gävle las"
                },
                {
                    "position": "överläk",
                    "years": {
                        "start_year": 1945,
                        "end_year": 1965
                    },
                    "organization": "Gävle las"
                },
                {
                    "position": "prakt läk",
                    "years": {
                        "start_year": 1965,
                        "end_year": null
                    },
                    "organization": null
                }
            ],
            "family": {
                "spouse": "Margareta Berggren",
                "marriage_year": "1936",
                "children": [
                    {
                        "name": "Gunilla",
                        "birth_year": "1938"
                    },
                    {
                        "name": "Kristina",
                        "birth_year": "1945"
                    }
                ]
            }
        },
        "2": {
            "full_name": "A M (Annie) G Jenhoff",
            "location": "Östersund",
            "occupation": "teater-pedagog",
            "birth_details": {
                "date": "2/7/1929",
                "place": "Nykpg",
                "parents": "köpm Gunnar J o Signe J"
            },
            "education": null,
            "career": [
                {
                    "position": "teater-sk",
                    "years": {
                        "start_year": 1948,
                        "end_year": 1950
                    },
                    "organization": "Braintree Dramatic Soc"
                },
                {
                    "position": "skådesp",
                    "years": {
                        "start_year": 1953,
                        "end_year": 1954
                    },
                    "organization": "Dramat teat"
                }
            ],
            "family": {
                "spouse": "Sven Wollter",
                "marriage_year": "1960",
                "children": [
                    {
                        "name": "Simone",
                        "birth_year": "1952"
                    },
                    {
                        "name": "Tom",
                        "birth_year": "1955"
                    },
                    {
                        "name": "Ylva",
                        "birth_year": "1962"
                    },
                    {
                        "name": "Stina",
                        "birth_year": "1964"
                    }
                ]
            },
            "hobbies": [
                "teckning",
                "målning",
                "ridning"
            ]
        },
        "3": {
            "full_name": "G Signhild Jennische",
            "location": "Gävle",
            "occupation": "lektor",
            "birth_details": {
                "date": "15/07/1905",
                "place": "Umeå",
                "parents": "bankkamr Gustaf J o Anna Ungman"
            },
            "education": [
                {
                    "degree": "Stud:ex",
                    "year": "1933",
                    "institution": "Sthlm"
                },
                {
                    "degree": "fil lic",
                    "year": "1939",
                    "institution": "Upps"
                }
            ],
            "career": [
                {
                    "position": "e adj",
                    "years": {
                        "start_year": 1943,
                        "end_year": 1944
                    },
                    "organization": "småsk:sem Strängnäs"
                },
                {
                    "position": "hal",
                    "years": {
                        "start_year": 1944,
                        "end_year": null
                    },
                    "organization": "Gävle"
                },
                {
                    "position": "adj",
                    "years": {
                        "start_year": 1945,
                        "end_year": null
                    },
                    "organization": "Gävle"
                },
                {
                    "position": "lekt i sv o eng",
                    "years": {
                        "start_year": 1960,
                        "end_year": null
                    },
                    "organization": "Gävle"
                }
            ],
            "family": null,
            "hobbies": [
                "fiske"
            ]
        },
        "4": {
            "full_name": "Sven Jerdén",
            "location": "Skellefteå",
            "occupation": "jägmästare",
            "birth_details": {
                "date": "9/6/1917",
                "place": "Malmö",
                "parents": "civ:ing Alfred J o Anna Sandblad"
            },
            "education": [
                {
                    "degree": "Stud:ex",
                    "year": "1937",
                    "institution": null
                },
                {
                    "degree": "SkHS",
                    "year": "1944",
                    "institution": null
                }
            ],
            "career": [
                {
                    "position": "anst Domänverket",
                    "years": {
                        "start_year": 1948,
                        "end_year": null
                    },
                    "organization": null
                },
                {
                    "position": "revirförv",
                    "years": {
                        "start_year": 1959,
                        "end_year": null
                    },
                    "organization": "Burträsks revir"
                },
                {
                    "position": "rekt",
                    "years": {
                        "start_year": 1956,
                        "end_year": 1958
                    },
                    "organization": "Älvsby skogssk"
                }
            ],
            "family": {
                "spouse": "Annalisa Stalin",
                "marriage_year": "1949",
                "children": [
                    {
                        "name": "Anna",
                        "birth_year": "1950"
                    },
                    {
                        "name": "Lars",
                        "birth_year": "1952"
                    }
                ]
            },
            "hobbies": [
                "jakt",
                "fiske"
            ]
        }
    }
}