{
    "original": "PERSSON, P BERTIL S,\nläroverksadjunkt, bitr rektor, Avesta, f i Ronneby\n5/10/09 av överlär Per P o Hilda\nNilsson.\n\nStud:ex Malmö 28, fil mag Lund 34, e\nlär Ronneby 34, Karlskrona 36, Malmö\n37, Strängnäs 38, Lundsberg 38-42, eo\nadj Varberg 43, Molkom 46, lekt komm\ngymn Avesta 47, adj hal Avesta sed 51,\nbitr rekt sed 58. - Led Stadsfullm o\nbe-redn:utsk 54-58, skolstyr 58, styr:led\nHSB Avesta 49-55 o sed 61. - Medl\nRotary (presid 57-58), FrimO.\nGift 39 m Maj Ingmanson f 09, dtr t\nstat :skriv Gustaf I o Tyra Bergström.\n-Barn: Per f 42.\n\nPERSSON, BROR, byggmästare,\nKarlstad, f i Lit, Jämtl l, 23/8/19 av byggm\nAlfred P o Maria Viklund.\nKristinehamns tekn sk 49, verkm o\narb:-ch firma Byggtjänst Kristinehamn 49-53,\ndeläg firma Karlenäs o Persson\nKarlstad  sed  53.   -  Hobby:  fiske.\nGift 51 m Nora Halvorsen f 25, dtr t\nAxel H o Andrea H (Norge). - Barn:\nJan f 52.\n\nPERSSON, DAG G, bankjurist,\nKarlstad, f i Gbg 5/5/26 av köpm Axel P o\nGerda P.\n\nStud:ex 45, jur kand Sthlm 50, tingstjg\nFalu doms 50-53, bitr jur å adv:byrå\nFalun 53, Örebro 53-54, tjg Svea hovr\n54-55, bitr jur Adv :firma Jansson o Gedda\nSthlm 55, anst jurid avd Sv:es\nlantbr:-förb 57, eg adv:byrå Sthlm 59, bankjur\nWerml ensk bk sed 61.\nGift 50 m Lilian Frantz f 28, dtr t Nils\nF o Margaretha Roos. - Barn: Agneta\nf 55.\n\nPERSSON, V EINAR, riksdagsman,\nÄlvdalsåsen, f i Älvdalsåsen, Kopparb l,\n8/6/02 av Gröt Per Larsson o Anna\nLarsson.\n\nBrunnsviks folkhögsk 27-28, LO-sk 34,\nanst ol skogsbol 16-43. - Led FK (s) sed\n44, statsutsk, landst:man, ordf\nkomm:fullm, länssk:ndn, soc:dem arb :komm,\n\nv ordf skolstyr, skogsv:styr, led Sv\nhdlsbkn* lokalstyr. - Medl IOGT. - Hobby:\nfiske.\n\nGift 32 m Ingrid Eriksson, dtr t\nskomak :mast Carl Vilhelm E o Emilia\nEriksson, - Barn: Elis f 39, Christina\nf 43.\n\n",
    "structured": {
        "0": {
            "full_name": "PERSSON, P BERTIL S",
            "location": "Avesta",
            "occupation": "läroverksadjunkt, bitr rektor",
            "birth_details": {
                "date": "5/10/1909",
                "place": "Ronneby",
                "parents": "överlär Per P o Hilda Nilsson"
            },
            "education": [
                {
                    "degree": "Stud:ex",
                    "year": "1928",
                    "institution": "Malmö"
                },
                {
                    "degree": "fil mag",
                    "year": "1934",
                    "institution": "Lund"
                }
            ],
            "career": [
                {
                    "position": "lärare",
                    "years": {
                        "start_year": 1934,
                        "end_year": 1936
                    },
                    "organization": "Ronneby"
                },
                {
                    "position": "eo adjunkt",
                    "years": {
                        "start_year": 1943,
                        "end_year": 1946
                    },
                    "organization": "Varberg"
                }
            ],
            "family": {
                "spouse": "Maj Ingmanson",
                "marriage_year": "1939",
                "children": [
                    {
                        "name": "Per",
                        "birth_year": "1942"
                    }
                ]
            }
        },
        "1": {
            "full_name": "PERSSON, BROR",
            "location": "Karlstad",
            "occupation": "byggmästare",
            "birth_details": {
                "date": "23/8/1919",
                "place": "Lit, Jämtl l",
                "parents": "byggm Alfred P o Maria Viklund"
            },
            "education": [
                {
                    "degree": "tekn sk",
                    "year": "1949",
                    "institution": "Kristinehamn"
                }
            ],
            "career": [
                {
                    "position": "verkmästare",
                    "years": {
                        "start_year": 1949,
                        "end_year": 1953
                    },
                    "organization": "Byggtjänst Kristinehamn"
                }
            ],
            "family": {
                "spouse": "Nora Halvorsen",
                "marriage_year": "1951",
                "children": [
                    {
                        "name": "Jan",
                        "birth_year": "1952"
                    }
                ]
            },
            "hobbies": [
                "fiske"
            ]
        },
        "2": {
            "full_name": "PERSSON, DAG G",
            "location": "Karlstad",
            "occupation": "bankjurist",
            "birth_details": {
                "date": "5/5/1926",
                "place": "Gbg",
                "parents": "köpm Axel P o Gerda P"
            },
            "education": [
                {
                    "degree": "jur kand",
                    "year": "1950",
                    "institution": "Sthlm"
                }
            ],
            "career": [
                {
                    "position": "tingstjg",
                    "years": {
                        "start_year": 1950,
                        "end_year": 1953
                    },
                    "organization": "Falu doms"
                },
                {
                    "position": "eg advokatbyrå",
                    "years": {
                        "start_year": 1959
                    },
                    "organization": "Sthlm"
                }
            ],
            "family": {
                "spouse": "Lilian Frantz",
                "marriage_year": "1950",
                "children": [
                    {
                        "name": "Agneta",
                        "birth_year": "1955"
                    }
                ]
            }
        },
        "3": {
            "full_name": "PERSSON, V EINAR",
            "location": "Älvdalsåsen",
            "occupation": "riksdagsman",
            "birth_details": {
                "date": "8/6/1902",
                "place": "Älvdalsåsen, Kopparb l",
                "parents": "Gröt Per Larsson o Anna Larsson"
            },
            "education": [
                {
                    "degree": "folkhögsk",
                    "year": "1927-1928",
                    "institution": "Brunnsvik"
                },
                {
                    "degree": "LO-sk",
                    "year": "1934",
                    "institution": "LO-sk"
                }
            ],
            "career": [
                {
                    "position": "anställd",
                    "years": {
                        "start_year": 1916,
                        "end_year": 1943
                    },
                    "organization": "skogsbol"
                }
            ],
            "family": {
                "spouse": "Ingrid Eriksson",
                "marriage_year": "1932",
                "children": [
                    {
                        "name": "Elis",
                        "birth_year": "1939"
                    },
                    {
                        "name": "Christina",
                        "birth_year": "1943"
                    }
                ]
            },
            "community_involvement": [
                {
                    "role": "statsutsk",
                    "organization": null,
                    "years": "44"
                }
            ],
            "board_memberships": [
                {
                    "position": "lokalstyr",
                    "organization": "Sv hdlsbkn",
                    "years": "NULL"
                }
            ],
            "hobbies": [
                "fiske"
            ]
        }
    }
}