{
    "original": "PARLING, NILS O, författare,\nSilverhöjden, f i Säfsnäs, Kopparb l, 27/12/14\n\nav diversearb Arvid Po Mina Meurling.\nSkr: Motorsågen (50), Huset som var en\nljuddosa (51), I nöd o lusta (53),\nFinn-bastu (55), Sodom (56), FinnbäcksrLars\nVisor (56), Korset (57), I detta tillstånd\n(58), Klockor ur mörkret (58) samt ett\nflert djur- o naturskildr. - Medl Sv\nförf :f ören. - Hobbies: fiske,\nvildmarksliv.\n\nGift 1) 49 m Kerstin Tillman f 29, dtr t\nskogsarb Karl-Johan T o Ester\nAndersson, 2) 59 m Ingegerd Bergdahl f 28,\ndtr t fotograf Axel Nilsson o h h f\nBergdahl. -Barn: i l:a akt Inger f 48,\nJan Felix f 55, i 2:a akt Angelika f 60.\n\nPÄRMEN, C ERIK, direktör, Buenos\nAires, f i Ockelbo, Gävleb l, 9/5/25 av\nHarry P o Hanna Eriksson.\nStud:ex Strängnäs 44, DHG 47, pol mag\nStHS 48, attaché UD 48, sv amb\nWashington 48, leg :sekr sv leg Rio de\nJaneiro 50, dir :ass Cia Astral Quito\nEcuador 53, tf vicekonsul Quito 54, bitr ch\nutl:avd ab Astra 56, verkst dir Astra S\nA Argentina sed 61. - Utm: EcAM.\n-Hobbies: segling, ridning.\nGift 62 m Karin Gustafsson, dtr t fanj\nC W G o Elsa Nilsson.\n\nPARROW, ANDERS F, med dr,\ndocent, Uppsala, f i Madesjö, Kalmar l,\n26/1/26 av disp Sture Kahr o Stina\nParrow.\n\nStud:ex Kalmar 45, med kand Upps 49,\nmed lic 55, med dr 62. - Vik underläk\nbarnavd Akad sjh o Borås las samt Gbgs\nbarnsjh 55, öronklin o med klin Akad\nsjh 56i, l:e underläk med klin Akad sjh\n56, bitr överläk där sed 62. - Hobby:\nsegling.\n\nGift 50 m leg läk Ragna Dahlberg f 28,\ndtr t prof Gunnar D o Stina Westberg.\n-Barn: Joachim f 56, Vendela f 58,\nHelena f 62.\n\n",
    "structured": {
        "0": {
            "full_name": "Nils O Parling",
            "location": "Silverhöjden, Säfsnäs, Kopparb l",
            "occupation": "författare",
            "birth_details": {
                "date": "27/12/1914",
                "place": "Säfsnäs, Kopparbergs län"
            },
            "education": null,
            "career": [
                {
                    "position": "diversearb",
                    "years": {
                        "start_year": null,
                        "end_year": null
                    },
                    "organization": null
                }
            ],
            "family": {
                "spouse": "Kerstin Tillman",
                "marriage_year": "1949",
                "children": [
                    {
                        "name": "Inger",
                        "birth_year": "1948"
                    },
                    {
                        "name": "Jan Felix",
                        "birth_year": "1955"
                    },
                    {
                        "name": "Angelika",
                        "birth_year": "1960"
                    }
                ]
            }
        },
        "1": {
            "full_name": "C Erik Pärmen",
            "location": "Buenos Aires, Ockelbo, Gävleb l",
            "occupation": "direktör",
            "birth_details": {
                "date": "09/05/1925",
                "place": "Ockelbo, Gävleborgs län"
            },
            "education": [
                {
                    "degree": "Stud:ex",
                    "year": "1944",
                    "institution": "Strängnäs"
                },
                {
                    "degree": "DHG",
                    "year": "1947",
                    "institution": null
                },
                {
                    "degree": "pol mag",
                    "year": "1948",
                    "institution": "StHS"
                }
            ],
            "career": [
                {
                    "position": "attaché",
                    "years": {
                        "start_year": 1948,
                        "end_year": 1948
                    },
                    "organization": "UD"
                },
                {
                    "position": "sv amb",
                    "years": {
                        "start_year": 1948,
                        "end_year": null
                    },
                    "organization": "Washington"
                },
                {
                    "position": "leg :sekr",
                    "years": {
                        "start_year": 1950,
                        "end_year": null
                    },
                    "organization": "sv leg Rio de Janeiro"
                },
                {
                    "position": "dir :ass",
                    "years": {
                        "start_year": 1953,
                        "end_year": null
                    },
                    "organization": "Cia Astral Quito Ecuador"
                },
                {
                    "position": "tf vicekonsul",
                    "years": {
                        "start_year": 1954,
                        "end_year": null
                    },
                    "organization": "Quito"
                },
                {
                    "position": "bitr ch utl:avd",
                    "years": {
                        "start_year": 1956,
                        "end_year": null
                    },
                    "organization": "ab Astra"
                },
                {
                    "position": "verkst dir",
                    "years": {
                        "start_year": 1961,
                        "end_year": null
                    },
                    "organization": "Astra S A Argentina"
                }
            ],
            "family": {
                "spouse": "Karin Gustafsson",
                "marriage_year": "1962",
                "children": []
            },
            "publications": null,
            "community_involvement": null,
            "board_memberships": null,
            "honorary_titles": null,
            "hobbies": [
                "segling",
                "ridning"
            ]
        },
        "2": {
            "full_name": "Anders F Parrow",
            "location": "Uppsala, Madesjö, Kalmar l",
            "occupation": "med dr, docent",
            "birth_details": {
                "date": "26/01/1926",
                "place": "Madesjö, Kalmar län"
            },
            "education": [
                {
                    "degree": "Stud:ex",
                    "year": "1945",
                    "institution": "Kalmar"
                },
                {
                    "degree": "med kand",
                    "year": "1949",
                    "institution": "Upps"
                },
                {
                    "degree": "med lic",
                    "year": "1955",
                    "institution": null
                },
                {
                    "degree": "med dr",
                    "year": "1962",
                    "institution": null
                }
            ],
            "career": [
                {
                    "position": "Vik underläk",
                    "years": {
                        "start_year": null,
                        "end_year": null
                    },
                    "organization": "Akad sjh o Borås las samt Gbgs barnsjh"
                },
                {
                    "position": "l:e underläk",
                    "years": {
                        "start_year": 1956,
                        "end_year": null
                    },
                    "organization": "Akad sjh"
                },
                {
                    "position": "bitr överläk",
                    "years": {
                        "start_year": 1962,
                        "end_year": null
                    },
                    "organization": "Akad sjh"
                }
            ],
            "family": {
                "spouse": "Ragna Dahlberg",
                "marriage_year": "1950",
                "children": [
                    {
                        "name": "Joachim",
                        "birth_year": "1956"
                    },
                    {
                        "name": "Vendela",
                        "birth_year": "1958"
                    },
                    {
                        "name": "Helena",
                        "birth_year": "1962"
                    }
                ]
            },
            "publications": null,
            "community_involvement": null,
            "board_memberships": null,
            "honorary_titles": null,
            "hobbies": [
                "segling"
            ]
        }
    }
}