{
    "original": "HELLSTRÖM, C ALVAR, tandläkare,\n\nKarlshamn, f i Asker, Örebro l, 13/3/09\nav kassör Carl H o Agnes Carlsson.\n\nStud:ex Upps 29, tandl:ex Sthlm 38, vik\nLenhovda 39-42, pri v :prakt Karlshamn\nsed 42.\n\nGift 56 m Gunborg Hansson. - Barn:\nUlla-Lis f 48.\n\nHELLSTRÖM,  ANDERS  O,\nlantmätare, Simrishamn, f i Sthlm 22/12/35 av\navd:dir Harry H o Valborg Larsson.\nKTH 5$, lantmät Mora 58, Vänersborg\n62, Si’mrishamn sed 64. - Hobby: fiske.\nGift 60 m Madeleine Candés, dtr t dir\nLucien C o Ruth Rossander. - Barn:\nCa-roline f 62, Helena f 64.\n\nHELLSTRÖM, CARL-AXEL P,\ningenjör, Landskrona, f i Tidaholm 12/10/07\nav hdlstjm Robert H o Lisa Agander.\nReal’ex 24, in’g :ex Hässleholms tekn sk\n29; ing ab Tidaholms bruk 30, SKF\nHofors bruk 34, ab Landsverk Landskrona\nsed 3’5t, ass åt övering på\nstridsfordons-avd där. - Lär Landskrona städs yrkessk\n38-58.\n\nGift 34 m Siv Throedson f 11, dtr t\nbyggm Carl T o Karolina Olsson.\n-Barn: Birgititia f 38, Peter f 42.\n\nHELLSTRÖM, ERIC R, ingenjör,\nMalmö, f i Svedala, Malmöh l, 20/10/19 av\nbageriförest Ragnar H o Nina\nAndersson.\n\nIng:ex HTL Malmö 40, konstr SSA 41,\nkemist där 43;, ing Kockums mek verkst\nab Malmö 45, ch driftsavd där sed 62.\n-Led Sv mekanförb:s forskn:utsk VE 3\n(plåtbearbetning). - Medl SVIF, Skånska\ning :klubben. - Hobby: golf.\nGift 5® m Ulla Aastrup f 28, dtr t kamr\nCarl A o Sigrid Peterson. - Barn:\nPer-Eric f 59, Mats f 612.\n\n",
    "structured": {
        "1": {
            "full_name": "C Alvar Hellström",
            "location": "Karlshamn",
            "occupation": "tandläkare",
            "birth_details": {
                "date": "13/03/1909",
                "place": "Asker, Örebro l"
            },
            "education": [
                {
                    "degree": "Stud:ex",
                    "year": "1929",
                    "institution": "Upps"
                },
                {
                    "degree": "tandl:ex",
                    "year": "1938",
                    "institution": "Sthlm"
                }
            ],
            "career": [
                {
                    "position": "vik Lenhovda",
                    "years": {
                        "start_year": 1939,
                        "end_year": 1942
                    },
                    "organization": "NULL"
                },
                {
                    "position": "pri v :prakt",
                    "years": {
                        "start_year": 1942,
                        "end_year": "NULL"
                    },
                    "organization": "Karlshamn"
                }
            ],
            "family": {
                "spouse": "Gunborg Hansson",
                "marriage_year": "1956",
                "children": [
                    {
                        "name": "Ulla-Lis",
                        "birth_year": "1948"
                    }
                ]
            }
        },
        "2": {
            "full_name": "Anders O Hellström",
            "location": "Simrishamn",
            "occupation": "lantmätare",
            "birth_details": {
                "date": "22/12/1935",
                "place": "Sthlm"
            },
            "education": [
                {
                    "degree": "KTH",
                    "year": "NULL",
                    "institution": "5$"
                }
            ],
            "career": [
                {
                    "position": "lantmät",
                    "years": {
                        "start_year": 1958,
                        "end_year": "NULL"
                    },
                    "organization": "Mora"
                },
                {
                    "position": "Vänersborg",
                    "years": {
                        "start_year": 1962,
                        "end_year": "NULL"
                    },
                    "organization": "NULL"
                },
                {
                    "position": "Si’mrishamn",
                    "years": {
                        "start_year": 1964,
                        "end_year": "NULL"
                    },
                    "organization": "NULL"
                }
            ],
            "family": {
                "spouse": "Madeleine Candés",
                "marriage_year": "1960",
                "children": [
                    {
                        "name": "Ca-roline",
                        "birth_year": "1962"
                    },
                    {
                        "name": "Helena",
                        "birth_year": "1964"
                    }
                ]
            },
            "hobbies": [
                "fiske"
            ]
        },
        "3": {
            "full_name": "Carl-Axel P Hellström",
            "location": "Landskrona",
            "occupation": "ingenjör",
            "birth_details": {
                "date": "12/10/1907",
                "place": "Tidaholm"
            },
            "education": [
                {
                    "degree": "Real’ex",
                    "year": "1924",
                    "institution": "NULL"
                },
                {
                    "degree": "in’g :ex",
                    "year": "1929",
                    "institution": "Hässleholms tekn sk"
                }
            ],
            "career": [
                {
                    "position": "ing ab Tidaholms bruk",
                    "years": {
                        "start_year": 1930,
                        "end_year": "NULL"
                    },
                    "organization": "NULL"
                },
                {
                    "position": "SKF Hofors bruk",
                    "years": {
                        "start_year": 1934,
                        "end_year": "NULL"
                    },
                    "organization": "NULL"
                },
                {
                    "position": "ab Landsverk",
                    "years": {
                        "start_year": 1935,
                        "end_year": "NULL"
                    },
                    "organization": "Landskrona"
                },
                {
                    "position": "ass åt övering på stridsfordons-avd",
                    "years": {
                        "start_year": "NULL",
                        "end_year": "NULL"
                    },
                    "organization": "NULL"
                }
            ],
            "family": {
                "spouse": "Siv Throedson",
                "marriage_year": "1934",
                "children": [
                    {
                        "name": "Birgititia",
                        "birth_year": "1938"
                    },
                    {
                        "name": "Peter",
                        "birth_year": "1942"
                    }
                ]
            }
        },
        "4": {
            "full_name": "Eric R Hellström",
            "location": "Malmö",
            "occupation": "ingenjör",
            "birth_details": {
                "date": "20/10/1919",
                "place": "Svedala, Malmöh l"
            },
            "education": [
                {
                    "degree": "Ing:ex",
                    "year": "1940",
                    "institution": "HTL Malmö"
                },
                {
                    "degree": "konstr",
                    "year": "1941",
                    "institution": "SSA"
                },
                {
                    "degree": "kemist",
                    "year": "1943",
                    "institution": "NULL"
                }
            ],
            "career": [
                {
                    "position": "ing Kockums mek verkst ab",
                    "years": {
                        "start_year": 1945,
                        "end_year": "NULL"
                    },
                    "organization": "Malmö"
                },
                {
                    "position": "ch driftsavd",
                    "years": {
                        "start_year": 1962,
                        "end_year": "NULL"
                    },
                    "organization": "Kockums mek verkst ab"
                }
            ],
            "family": {
                "spouse": "Ulla Aastrup",
                "marriage_year": "5®",
                "children": [
                    {
                        "name": "Per-Eric",
                        "birth_year": "1959"
                    },
                    {
                        "name": "Mats",
                        "birth_year": "612"
                    }
                ]
            },
            "hobbies": [
                "golf"
            ]
        }
    }
}