{
    "original": "HANSSON, NILS H, rektor, lektor,\nÄngelholm, f i Mölleberga, Malmöh l,\n13/4/19 av lantbr Nils H o Hanna\nNilsson.\n\nStud:ex Malmö 39, fil kand Lund 43,\nfil mag 44, fil lic 47, fil dr 50, provar\n51, eo adj Lunds katedralsk 51-52,\nMalmö latinsk 52-53, lekt hal Mariestad\n53-55, hal Ängelholm 55-60, rekt där sed\n60, lekt i högstad metodik i klassiska\nspråk lärarhögsk Malmö sed 62. -\nTryck-frih:omb Krist l sed 66. - Skr:\nTextkri-tisches zu Juvencus (drsavh 50).\nGift 48 m Ingeborg Hyllner f 21, dtr t\nkyrkoh Otto H o Asta Paulsson. - Barn:\nEva f 53, Christina f 54, Marianne f 57.\n\nHANSSON, NILS J, fd tullförvaltare,\nMalmö, f i Landskrona 27/12/88 av\nlok-för Anders H o Bengta Nilsson.\nStud:ex Hbg 071, anst tullv 07-54. - Ordf\nMalmö musi’ksällsk 40-57. - Medl’ Odd\nFellow. - Utm: RVO. - Hobby: musik.\nGift 16 m Ellen Algren, dtr t sem:lär\nWilhelm A o Eva Lind. - Barn: Ingrid\nf 19 d 34, Bengt f 22.\n\nHANSSON, PER-BERTIL, kamrer,\nMalmö, f i Lomma, Malmöh l, 14/12/\n19 av trädg :mast Edvard H o Gerda\nBillqvist.\n\nStud’:ex Malmö 38, Telesk Sthlm 39-41;\nanst Malmö telestat 39, l:e telekontr 54,\nkamr där sed1 65.\n\nGift 54 m Maj-Britt Olsson f 27, dtr t\nbussäg Edvin O o Olga Hum. - Barn:\nAstrid f 57.\n\nHANSSON, SETH A, intendent, Hbg,\nf i Svenljunga, Älvsb l, 30/12/04 av\nkonduktör Hugo H o Selma H.\nStud:ex Borås 26, anst Systembol Borås\n27, kamrer dess kont Hbg 3&amp;, bitr intend\nNya system ab 55, distr :ch o intend1 f\nut-skänkn:ärend Malmöh l sed’ 641 - Sakk\ni org:- o rationalis:fr LK, bränslekomm\n\n0  överrev f krisförvaltn, sekr Malmöh l\nn kristidsstyr 42-49 o ch dess kontr:byrå\n40-49; led komm f omorg av Hbgs städs\nexekut :verk 56^5$, komm f samordn av\nHbgs stads socialv 59-62. - Nämndteman\nHbg 59-64. - Medl Rotary (presid\n63-64). - Utm: ProPstGM. - Hobbies:\nfiske, filateli.\n\nGift m Märta Moberg f 16, dtr t\nciviling Wilhelm M o Elisabet Herdin.\n-Barn: Rut-Marie f 44.\n\n",
    "structured": {
        "1": {
            "full_name": "HANSSON, NILS H",
            "location": "Ängelholm",
            "occupation": "Rektor, lektor",
            "birth_details": {
                "date": "13/04/1919",
                "place": "Mölleberga, Malmö"
            },
            "education": [
                {
                    "degree": "Stud:ex",
                    "year": "1939",
                    "institution": "Malmö"
                },
                {
                    "degree": "filosofie kandidat",
                    "year": "1943",
                    "institution": "Lund"
                },
                {
                    "degree": "filosofie magister",
                    "year": "1944",
                    "institution": ""
                },
                {
                    "degree": "filosofie licentiat",
                    "year": "1947",
                    "institution": ""
                },
                {
                    "degree": "filosofie doktor",
                    "year": "1950",
                    "institution": ""
                },
                {
                    "degree": "provar",
                    "year": "1951",
                    "institution": ""
                }
            ],
            "career": [
                {
                    "position": "eo adjunkt",
                    "years": {
                        "start_year": 1951,
                        "end_year": 1952
                    },
                    "organization": "Lunds katedralsk"
                },
                {
                    "position": "lektor",
                    "years": {
                        "start_year": 1952,
                        "end_year": 1953
                    },
                    "organization": "Malmö latinsk"
                },
                {
                    "position": "lekt hal",
                    "years": {
                        "start_year": 1953,
                        "end_year": 1955
                    },
                    "organization": "Mariestad"
                },
                {
                    "position": "hal",
                    "years": {
                        "start_year": 1955,
                        "end_year": 1960
                    },
                    "organization": "Ängelholm"
                },
                {
                    "position": "rekt",
                    "years": {
                        "start_year": 1960,
                        "end_year": null
                    },
                    "organization": "Ängelholm"
                },
                {
                    "position": "lekt i högstad metodik i klassiska språk",
                    "years": {
                        "start_year": 1962,
                        "end_year": null
                    },
                    "organization": "lärarhögsk Malmö"
                }
            ],
            "family": {
                "spouse": "Ingeborg Hyllner",
                "marriage_year": "1948",
                "children": [
                    {
                        "name": "Eva",
                        "birth_year": "1953"
                    },
                    {
                        "name": "Christina",
                        "birth_year": "1954"
                    },
                    {
                        "name": "Marianne",
                        "birth_year": "1957"
                    }
                ]
            }
        },
        "2": {
            "full_name": "HANSSON, NILS J",
            "location": "Malmö",
            "occupation": "Fd tullförvaltare",
            "birth_details": {
                "date": "27/12/1888",
                "place": "Landskrona"
            },
            "career": [
                {
                    "position": "anst tullv",
                    "years": {
                        "start_year": 1907,
                        "end_year": 1954
                    },
                    "organization": null
                }
            ],
            "family": {
                "spouse": "Ellen Algren",
                "marriage_year": "1916",
                "children": [
                    {
                        "name": "Ingrid",
                        "birth_year": "1919"
                    },
                    {
                        "name": "Bengt",
                        "birth_year": "1922"
                    }
                ]
            },
            "hobbies": [
                "musik"
            ]
        },
        "3": {
            "full_name": "HANSSON, PER-BERTIL",
            "location": "Malmö",
            "occupation": "Kamrer",
            "birth_details": {
                "date": "14/12/1919",
                "place": "Lomma, Malmöh l"
            },
            "education": [
                {
                    "degree": "Stud’:ex",
                    "year": "1938",
                    "institution": "Malmö"
                },
                {
                    "degree": "Telesk",
                    "year": "1941",
                    "institution": "Sthlm"
                }
            ],
            "career": [
                {
                    "position": "anst Malmö telestat",
                    "years": {
                        "start_year": 1939,
                        "end_year": null
                    },
                    "organization": null
                },
                {
                    "position": "l:e telekontr",
                    "years": {
                        "start_year": 1954,
                        "end_year": null
                    },
                    "organization": "Malmö telestat"
                },
                {
                    "position": "kamr",
                    "years": {
                        "start_year": 1965,
                        "end_year": null
                    },
                    "organization": null
                }
            ],
            "family": {
                "spouse": "Maj-Britt Olsson",
                "marriage_year": "1954",
                "children": [
                    {
                        "name": "Astrid",
                        "birth_year": "1957"
                    }
                ]
            }
        },
        "4": {
            "full_name": "HANSSON, SETH A",
            "location": "Hbg",
            "occupation": "Intendent",
            "birth_details": {
                "date": "30/12/1904",
                "place": "Svenljunga, Älvsb l"
            },
            "career": [
                {
                    "position": "bitr intend",
                    "years": {
                        "start_year": 1955,
                        "end_year": null
                    },
                    "organization": "Nya system ab"
                }
            ],
            "family": {
                "spouse": "Märta Moberg",
                "marriage_year": "NULL",
                "children": [
                    {
                        "name": "Rut-Marie",
                        "birth_year": "1944"
                    }
                ]
            },
            "hobbies": [
                "fiske",
                "filateli"
            ]
        }
    }
}