{
    "original": "HAVENTON, FRED A, direktör,\nMalmö, f i Lund 10/12/21 av sjökapt\nFredrik H o Nancy Rosvall.\nMalmö hdlsgymn 41, f öret :ekon :ex 52;\nkamr o kont :ch Hedströms motor ab\nUpps 5/1-571, rev o org :konsult ab Volvo\nGbg 571-63,, verkst dir Frode Lund ab\nLund sed 631 - Styr:led Lundbolagen i\nMalmö ab, Frode Lund ab. - Medl\nRo-tary. - Hobbies: foto, golf, resor.\nGift 44 m Gunnel Näsberg f 23, dtr t\növerlär Gustaf N o Signe Svensson.\n-Barn: Peter f 48.\n\nHAVLAND, AXEL F, förste\nförsvarstandläkare, Kristianstad, f i Sthlm 16/7/\n08 av civ :ing Carl Albert Hansson o Ida\nRundqvist.\n\nStud:ex Saltsjöbaden 27, med kand 33 o\ntandl:ex 37 Sthlm, ass:tandl Eastmaninst\n37-38, tandl RK Jämtl 39, distr:tandl\nGnesta 39-48, ass avd f tandkir o avd f\nproteslära THS Sthlm 48-50, priv:prakt\nSthlm 51-61, Kristianstad sed 61. -\nFör-sv:tandl Signalreg 49-56, Krigssk 56-61,\nl:e försv:tandl i I mil:omr sed 61. - Sekr\nOdont fören 36, init:tag t Odont fören\ntidskr o dess l :e red 37, red Odont fören\nfestskr 38, medl red :ndn f \"Sveriges\nTandläkareförbund 1908-1958\". - Sekr\nSv:es försvarstandl:fören 60-64. - HedL\nOdont fören. - Medarb i\nTandläkarprak-tik o tandläkarekonomi (57).\nGift 37 m tandl Maj Erikson f 11.\n-Barn: Jerker f 38, Lena f 41, Tomas\nf 44.\n\nHAVLAND,   MAJ   E   I,   tandläkare,\n\nKristianstad, f i Lund 10/5/11 av apot\nJohan Axel Erikson o Elsa Hyllen.\nStud:ex Södertälje 31, tandl:ex Sthlm 37,\nass:tandl Eastmaninst 37-39, distr:tandl\nGnesta 39-55, priv:prakt Sthlm 55-63,\nKristianstad sed 64.\n\nGift 37 m tandl Axel Havland f 08.\n-Barn: Jerker f 38, Lena f 41, Tomas\nf 44.\n\n",
    "structured": {
        "1": {
            "full_name": "Fred A Haventon",
            "location": "Malmö",
            "occupation": "direktör",
            "birth_details": {
                "date": "10/12/1921",
                "place": "Lund",
                "parents": "sjökapt Fredrik H o Nancy Rosvall"
            },
            "education": [
                {
                    "degree": "Malmö hdlsgymn 41",
                    "year": "1941",
                    "institution": "Malmö hdlsgymn"
                },
                {
                    "degree": "f öret :ekon",
                    "year": "1952",
                    "institution": "f öret :ekon"
                }
            ],
            "career": [
                {
                    "position": "kamr o kont :ch",
                    "years": {
                        "start_year": 1957,
                        "end_year": 1961
                    },
                    "organization": "Hedströms motor ab Upps"
                },
                {
                    "position": "rev o org :konsult",
                    "years": {
                        "start_year": 1957,
                        "end_year": 1963
                    },
                    "organization": "ab Volvo Gbg"
                },
                {
                    "position": "verkst dir",
                    "years": {
                        "start_year": 1963,
                        "end_year": null
                    },
                    "organization": "Frode Lund ab Lund"
                }
            ],
            "family": {
                "spouse": "Gunnel Näsberg",
                "marriage_year": "1944",
                "children": [
                    {
                        "name": "Peter",
                        "birth_year": "1948"
                    }
                ]
            },
            "hobbies": [
                "foto",
                "golf",
                "resor"
            ]
        },
        "2": {
            "full_name": "Axel F Havland",
            "location": "Kristianstad",
            "occupation": "förste försvarstandläkare",
            "birth_details": {
                "date": "16/07/1908",
                "place": "Sthlm",
                "parents": "civ :ing Carl Albert Hansson o Ida Rundqvist"
            },
            "education": [
                {
                    "degree": "Stud:ex Saltsjöbaden 27",
                    "year": "1927",
                    "institution": "Stud:ex Saltsjöbaden"
                },
                {
                    "degree": "med kand",
                    "year": "1933",
                    "institution": null
                },
                {
                    "degree": "tandl:ex",
                    "year": "1937",
                    "institution": "Sthlm"
                }
            ],
            "career": [
                {
                    "position": "ass:tandl",
                    "years": {
                        "start_year": 1937,
                        "end_year": 1938
                    },
                    "organization": "Eastmaninst"
                },
                {
                    "position": "tandl",
                    "years": {
                        "start_year": 1939,
                        "end_year": 1948
                    },
                    "organization": "RK Jämtl"
                },
                {
                    "position": "distr:tandl",
                    "years": {
                        "start_year": 1939,
                        "end_year": 1948
                    },
                    "organization": "Gnesta"
                }
            ],
            "family": {
                "spouse": "tandl Maj Erikson",
                "marriage_year": "1937",
                "children": [
                    {
                        "name": "Jerker",
                        "birth_year": "1938"
                    },
                    {
                        "name": "Lena",
                        "birth_year": "1941"
                    },
                    {
                        "name": "Tomas",
                        "birth_year": "1944"
                    }
                ]
            }
        },
        "3": {
            "full_name": "Maj E I Havland",
            "location": "Kristianstad",
            "occupation": "tandläkare",
            "birth_details": {
                "date": "10/05/1911",
                "place": "Lund",
                "parents": "apot Johan Axel Erikson o Elsa Hyllen"
            },
            "education": [
                {
                    "degree": "Stud:ex Södertälje 31",
                    "year": "1931",
                    "institution": "Stud:ex Södertälje"
                },
                {
                    "degree": "tandl:ex",
                    "year": "1937",
                    "institution": "Sthlm"
                }
            ],
            "career": [
                {
                    "position": "ass:tandl",
                    "years": {
                        "start_year": 1937,
                        "end_year": 1939
                    },
                    "organization": "Eastmaninst"
                },
                {
                    "position": "distr:tandl",
                    "years": {
                        "start_year": 1939,
                        "end_year": 1955
                    },
                    "organization": "Gnesta"
                }
            ],
            "family": {
                "spouse": "tandl Axel Havland",
                "marriage_year": "1937",
                "children": [
                    {
                        "name": "Jerker",
                        "birth_year": "1938"
                    },
                    {
                        "name": "Lena",
                        "birth_year": "1941"
                    },
                    {
                        "name": "Tomas",
                        "birth_year": "1944"
                    }
                ]
            }
        }
    }
}