{
    "original": "HELLBERG, N WALTER,\ncivilingenjör, Hbg, f i Mörarp, Malmöh l, 16/12/\n13 av fabr Carl H o Hilma Stenson.\nStud:ex Hbg 33’, KTH 41, avd:ch ab\nWiro Sthlm 42, ch Sthl’mskont Laxå\nbruks ab 44, föret:ledare ab Carl\nHellberg Hbg sed 46. - Deläg o styr:led ab\nCarl Hellberg, ab Kalmar maskinaffär,\nab Mörarps mek verkst).\nGift 1) 40 m Franees von Koch f 15’, dtr\nt kanslirådet G H v K o Carola Sahl’, 2)\n46 m Eleonora Dahl f 13, dtr t köpm\nErland D o Alma Johansson. - Barn:\n\n22 ska\n\ni l:a akt Sten f 40, i 2:a akt Anita f 47,\nEva-Kristina f 38.\n\nHELLBING, S LENNART O, jur\nkand, Ronneby, f i Gbg 18/S/22 av arkit\nPehr H o Hildur Hansson.\nStud:ex 42, jur kand Upps 48, tingstjg\nHall n doms 49-51, tjg Hovr f V Sv:e,\nrådhusr Varberg, Västerås o Karlskrona\n51-53, l:e byråsekr S J :s jurid avd 53-60,\ndeläg Hellbings jurid byrå sed 60. - V\nordf Bostadsr:fören Myran f SJ-anst\nSthlm 58-60. - Medl FrimO, Rotary.\nGift 56 m Kersti Dyrssen f 31, dtr t agr\nPeder D o Erna Heydemann. - Barn:\nThord f 64.\n\nHELLDAL, BENGT, provinsialläkare,\nFalkenberg, f i Falun 14/2/00 av disp\nCyrac Olsson o Bertha Ericsson.\nStud:ex 19 o med kand 23 Upps, med\nlic Sthlm 28, underläk Karlstads las\n28-32, Halmstads las 32-34, Gbgs BB 34-35,\nstadsläk Falkenberg 35-54, prov:läk\nFalkenbergs distr sed 54. - Läk Hall l\nsin-nesslöanst Heberg sed 36, skolläk lärov\nFalkenberg 44-66. - Ordf hälsov:ndn\nFalkenberg 35-54. - Medl Rotary.\n-Hobby: golf.\n\nGift 31 m Maj Lundén f 12, dtr t köpm\nHelge L o Hildegard Creutzer. - Barn:\nBirgitta f 32, Agneta f 39.\n\n",
    "structured": {
        "1": {
            "full_name": "N Walter Hellberg",
            "location": "Mörarp, Malmöh l",
            "occupation": "Civilingenjör",
            "birth_details": {
                "date": "16/12/1913",
                "place": "Mörarp, Malmöh l",
                "parents": "fabr Carl H o Hilma Stenson"
            },
            "education": [
                {
                    "degree": "Stud:ex",
                    "year": "1933",
                    "institution": "Hbg"
                },
                {
                    "degree": "KTH",
                    "year": "1941",
                    "institution": "KTH"
                }
            ],
            "career": [
                {
                    "position": "avd:ch",
                    "years": {
                        "start_year": 1942,
                        "end_year": 1942
                    },
                    "organization": "Wiro Sthlm"
                },
                {
                    "position": "ch",
                    "years": {
                        "start_year": 1944,
                        "end_year": 1944
                    },
                    "organization": "Sthl’mskont Laxå bruks ab"
                },
                {
                    "position": "föret:ledare",
                    "years": {
                        "start_year": 1946,
                        "end_year": null
                    },
                    "organization": "ab Carl Hellberg Hbg"
                }
            ],
            "family": {
                "spouse": "Franees von Koch",
                "marriage_year": "1940",
                "children": [
                    {
                        "name": "Sten",
                        "birth_year": "1940"
                    },
                    {
                        "name": "Anita",
                        "birth_year": "1947"
                    },
                    {
                        "name": "Eva-Kristina",
                        "birth_year": "1938"
                    }
                ]
            }
        },
        "2": {
            "full_name": "S Lennart O Hellbing",
            "location": "Ronneby",
            "occupation": "Jur kand",
            "birth_details": {
                "date": "18/05/1922",
                "place": "Gbg",
                "parents": "arkit Pehr H o Hildur Hansson"
            },
            "education": [
                {
                    "degree": "Stud:ex",
                    "year": "1942",
                    "institution": null
                },
                {
                    "degree": "jur kand",
                    "year": "1948",
                    "institution": "Upps"
                }
            ],
            "career": [
                {
                    "position": "tingstjg",
                    "years": {
                        "start_year": 1949,
                        "end_year": 1951
                    },
                    "organization": "Hall n doms"
                },
                {
                    "position": "rådhusr",
                    "years": {
                        "start_year": 1951,
                        "end_year": 1953
                    },
                    "organization": "Varberg, Västerås o Karlskrona"
                },
                {
                    "position": "l:e byråsekr",
                    "years": {
                        "start_year": 1953,
                        "end_year": 1960
                    },
                    "organization": "S J :s jurid avd"
                },
                {
                    "position": "deläg Hellbings jurid byrå",
                    "years": {
                        "start_year": 1960,
                        "end_year": null
                    },
                    "organization": null
                }
            ],
            "family": {
                "spouse": "Kersti Dyrssen",
                "marriage_year": "1956",
                "children": [
                    {
                        "name": "Thord",
                        "birth_year": "1964"
                    }
                ]
            }
        },
        "3": {
            "full_name": "Bengt Helldal",
            "location": "Falkenberg",
            "occupation": "Provinsialläkare",
            "birth_details": {
                "date": "14/02/1900",
                "place": "Falun",
                "parents": "disp Cyrac Olsson o Bertha Ericsson"
            },
            "education": [
                {
                    "degree": "Stud:ex",
                    "year": "1919",
                    "institution": null
                },
                {
                    "degree": "med kand",
                    "year": "1923",
                    "institution": "Upps"
                },
                {
                    "degree": "med lic",
                    "year": "1928",
                    "institution": "Sthlm"
                }
            ],
            "career": [
                {
                    "position": "underläk",
                    "years": {
                        "start_year": 1928,
                        "end_year": 1932
                    },
                    "organization": "Karlstads las"
                },
                {
                    "position": "Halmstads las",
                    "years": {
                        "start_year": 1932,
                        "end_year": 1934
                    },
                    "organization": "Halmstads las"
                },
                {
                    "position": "Gbg BB",
                    "years": {
                        "start_year": 1934,
                        "end_year": 1935
                    },
                    "organization": "Gbgs BB"
                },
                {
                    "position": "stadsläk",
                    "years": {
                        "start_year": 1935,
                        "end_year": 1954
                    },
                    "organization": "Falkenberg"
                },
                {
                    "position": "prov:läk",
                    "years": {
                        "start_year": 1954,
                        "end_year": null
                    },
                    "organization": "Falkenbergs distr"
                }
            ],
            "family": {
                "spouse": "Maj Lundén",
                "marriage_year": "1931",
                "children": [
                    {
                        "name": "Birgitta",
                        "birth_year": "1932"
                    },
                    {
                        "name": "Agneta",
                        "birth_year": "1939"
                    }
                ]
            },
            "hobbies": [
                "golf"
            ]
        }
    }
}