{
    "original": "STENSTRÖM, BO F, major, Roslags\nNäsby, f i Falun 25/7/18 av major Nils\nS o Amy Dahlqvist.\nStud:ex Upps 37, Off:ex 40, AIHS hk\n47, robotk FKHS 60, tjg arméns\nradar-komm 48, mil:ass KATF/EA 54, A 9 57,\nch försöksavd ArtSS sed 60. - Utm:\nRSO.\n\nGift 42 m Annette Lokrantz f 18, dtr t\ndir John L o Edith Laage-Peterssén.\n-Barn: Gunilla f 44, Magnus f 51.\n\nSTENSTRÖM, BO-GÖRAN A,\ntings-domare, Nyköping, f i Trollhättan 20/3/\n22 av stadsomb:man Oskar S o Signe\nNord.\n\nStud:ex Linkpg 40, jur kand Upps 46,\nfiskal Göta hovr 50, assess 58, hovr :råd\nhovr f Ö :e Norrl 60, tf rev :sekr 62,\ntings-dom Nykpgs doms sed 62. - Led Pede\nLibero 48.\n\nGift 47 m Margareta Wibling f 26, dtr t\nchefred Hilding W ö Greta Lindberg.\n-Barn: Margret f 49, Charlotte f 53,\nAnders f 57, Karin f 61.\n\nSTENSTRÖM, B GUNNAR,\nkyrkoherde, Eskilstuna, f i Karlskoga 6/10/02\nav ritsare Bror S o Tekla Nykvist.\nStud:ex Karlstad 23, teol kand 32, v past\nol orter 33-36, kommin Stenkvista-Ärla\n37, kyrkoh där sed 41. - Ordf\nkyrko-fullm, past:kyrkoråd, skolstyr, pens:nd.\n-Hobbies: målning, fotografering, musik.\nGift 38 m Märta Hallenius f 03, dtr t\nsnickare Albert H o Mathilda Sundin.\n-Barn: Sture f 39.\n\nSTENSTRÖM, K HENRIK,\ncivilingenjör, Kumla, f i Oxelösund  17/2/25 av\nbanbitr Ernst S o Ester Widén.\nStud:ex Nykpg 45,  KTH  50,  anst  ab\n\nScania Vabis Södertälje 50, ab\nBolinder-Munktell Eskilstuna 54, kontr :ch ab\nBo-linder-Munktell Hallsberg sed 61. - Medl\nSv bapt:samf. - Hobby: friluftsliv.\nGift 51 m Alice Törnblom f 29, dtr t\nsnick Vilhelm T o Lilly T. - Barn: Kajsa\nf 53, Tomas f 58.\n\n",
    "structured": {
        "1": {
            "full_name": "BO F STENSTRÖM",
            "location": "Roslags Näsby",
            "occupation": "Major",
            "birth_details": {
                "date": "25/07/1918",
                "place": "Falun",
                "parents": "Major Nils Stenström and Amy Dahlqvist"
            },
            "education": [
                {
                    "degree": "Stud:ex",
                    "year": "1937",
                    "institution": "Upps"
                },
                {
                    "degree": "Off:ex",
                    "year": "1940",
                    "institution": "AIHS"
                },
                {
                    "degree": "robotk FKHS",
                    "year": "1960",
                    "institution": "FKHS"
                }
            ],
            "career": [
                {
                    "position": "tjg arméns radar-komm",
                    "years": {
                        "start_year": 1948,
                        "end_year": 1954
                    },
                    "organization": "KATF/EA"
                },
                {
                    "position": "mil:ass",
                    "years": {
                        "start_year": 1954,
                        "end_year": 1957
                    },
                    "organization": "A 9"
                },
                {
                    "position": "ch försöksavd",
                    "years": {
                        "start_year": 1960
                    },
                    "organization": "ArtSS"
                }
            ],
            "family": {
                "spouse": "Annette Lokrantz",
                "marriage_year": "1942",
                "children": [
                    {
                        "name": "Gunilla",
                        "birth_year": "1944"
                    },
                    {
                        "name": "Magnus",
                        "birth_year": "1951"
                    }
                ]
            }
        },
        "2": {
            "full_name": "BO-GÖRAN A STENSTRÖM",
            "location": "Nyköping",
            "occupation": "Tings-domare",
            "birth_details": {
                "date": "20/03/1922",
                "place": "Trollhättan",
                "parents": "Oskar S Stenström and Signe Nord"
            },
            "education": [
                {
                    "degree": "Stud:ex",
                    "year": "1940",
                    "institution": "Linkpg"
                },
                {
                    "degree": "jur kand",
                    "year": "1946",
                    "institution": "Upps"
                }
            ],
            "career": [
                {
                    "position": "fiskal",
                    "years": {
                        "start_year": 1950
                    },
                    "organization": "Göta hovr"
                },
                {
                    "position": "assess",
                    "years": {
                        "start_year": 1958
                    },
                    "organization": "hovr :råd"
                },
                {
                    "position": "tf rev :sekr",
                    "years": {
                        "start_year": 1962
                    }
                },
                {
                    "position": "tings-dom",
                    "years": {
                        "start_year": 1962
                    },
                    "organization": "Nykpgs doms"
                }
            ],
            "family": {
                "spouse": "Margareta Wibling",
                "marriage_year": "1947",
                "children": [
                    {
                        "name": "Margret",
                        "birth_year": "1949"
                    },
                    {
                        "name": "Charlotte",
                        "birth_year": "1953"
                    },
                    {
                        "name": "Anders",
                        "birth_year": "1957"
                    },
                    {
                        "name": "Karin",
                        "birth_year": "1961"
                    }
                ]
            }
        },
        "3": {
            "full_name": "B GUNNAR STENSTRÖM",
            "location": "Eskilstuna",
            "occupation": "Kyrkoherde",
            "birth_details": {
                "date": "06/10/1902",
                "place": "Karlskoga",
                "parents": "Bror S Stenström and Tekla Nykvist"
            },
            "education": [
                {
                    "degree": "Stud:ex",
                    "year": "1923",
                    "institution": "Karlstad"
                },
                {
                    "degree": "teol kand",
                    "year": "1932"
                }
            ],
            "career": [
                {
                    "position": "v past",
                    "years": {
                        "start_year": 1933,
                        "end_year": 1936
                    },
                    "organization": "ol orter"
                },
                {
                    "position": "kommin",
                    "years": {
                        "start_year": 1937,
                        "end_year": 1941
                    },
                    "organization": "Stenkvista-Ärla"
                },
                {
                    "position": "kyrkoh",
                    "years": {
                        "start_year": 1941
                    }
                }
            ],
            "family": {
                "spouse": "Märta Hallenius",
                "marriage_year": "1938",
                "children": [
                    {
                        "name": "Sture",
                        "birth_year": "1939"
                    }
                ]
            },
            "hobbies": [
                "målning",
                "fotografering",
                "musik"
            ]
        },
        "4": {
            "full_name": "K HENRIK STENSTRÖM",
            "location": "Kumla",
            "occupation": "Civilingenjör",
            "birth_details": {
                "date": "17/02/1925",
                "place": "Oxelösund",
                "parents": "Ernst S Stenström and Ester Widén"
            },
            "education": [
                {
                    "degree": "Stud:ex",
                    "year": "1945",
                    "institution": "Nykpg"
                },
                {
                    "degree": "KTH",
                    "year": "1950"
                }
            ],
            "career": [
                {
                    "position": "anst",
                    "years": {
                        "start_year": 1950
                    },
                    "organization": "Scania Vabis Södertälje"
                },
                {
                    "position": "kontr :ch",
                    "years": {
                        "start_year": 1954
                    },
                    "organization": "Bolinder-Munktell Eskilstuna"
                },
                {
                    "position": "kontr :ch",
                    "years": {
                        "start_year": 1961
                    },
                    "organization": "Bo-linder-Munktell Hallsberg"
                }
            ],
            "family": {
                "spouse": "Alice Törnblom",
                "marriage_year": "1951",
                "children": [
                    {
                        "name": "Kajsa",
                        "birth_year": "1953"
                    },
                    {
                        "name": "Tomas",
                        "birth_year": "1958"
                    }
                ]
            },
            "community_involvement": [
                {
                    "role": "Medl",
                    "organization": "Sv bapt:samf."
                }
            ],
            "hobbies": [
                "friluftsliv"
            ]
        }
    }
}