{
    "original": "SETTERLIND, BO A I, poet,\nSträngnäs, f i Växjö 24/8/23 av civiling Alfred\nS o Augusta Konradson.\nStud:ex Västerås 44, univ:stud Upps\n46-51. - Res t Afr, USA, Fr orienten,\nMel-lanamer, Indien o Japan. - Ordf\nRomantiska förb 57. - Medl FrimO,\nTimmerm-O. - Skr: Månvagga (48), Resa i ditt\ninre (49), Brev (50), Poeternas himmel\n(50), Halleluja! (51), Hjärtat o trafiken\n(51), Alexandrine (52), Metamorphosis\n(53), Hamlet i Strängnäs (53), Dikter\nfrån San Michele (54), Dikter 47-52\n(urval 54), Poeten o samhället (54), Tabu\n\n(54), Ett underligt sällskap (55), Flickan\no binden (55), Därför är jag monarkist\n(55), Svävande över paniken (56), Jag\nhar två själar (57), Dikter i folkupplaga\n(57), Pandoras ask (57, folkuppl 60), Via\ntomheten (58), Paus i snöskottningen\n(58), Här är Joppe! (barnbok 58),\nFjorton dagar på jorden (59), Den\nförvandlade blomman (59), Det gömda Japan\n(60), Ekegårdens sagor (60), Klockorna\n(inskriptioner o namn på de 47\nklockorna i Västerås stadshus 60), Psalmer i\natomåldern? (60), Rymdpionjären (61),\nNågra ord att fästa på siden (61), Det\nljusnar (61), Långt från vårt jordiska\nhem (radiopjäs 61), Usantropen (62),\nHerrens Moder (62), Pojken som trodde\npå Djävulen (62), Dikter från Gotland\n(63), Mitt språk (dikturval 63), Via\nDo-lorosa (64); utg Närmare Dig (51), Mot\nvåldet (56), Eviga böner (antologi 56),\nSå talade Kristus (57), Boris Pasternaks\ndikter (58), Bohéme (nyövers 60), Såsom\nhjorten vid källan (61), Fågelpoesi (62),\nEn signad jul (62), Kristna lyriker (63).\n- Utm: KPFetV.\n\nGift 56 m Madeleine Grumme f 25, dtr\nt ing Carl Eduard G o Abigail\nEkström. - Barn: Carl Johan f 57, Eva\nf 60.\n\nSETTERLUND, BERTIL G A,\ndirektör, Orsa, f i Gävle 24/8/14 av grossh\nG A S o Emy Andersson.\nIng :ex tekn gymn Härnösand 36, prakt i\ncellulosabranschen, anst ab Orsakalk 45,\nverkst dir där sed 57. - Styr:led ab\nOrsakalk, Orsa plattfabr ab, Gbgs bk Orsa.\n-Led Orsa ind :komm. - Medl Rotary.\nGift 46 m Birgit Björk f 16, dtr t\nHjalmar B o Naemi Johan:sson. - Barn:\nKarin f 47, Elisabet f 54.\n\n",
    "structured": {
        "1": {
            "full_name": "BO A I SETTERLIND",
            "location": "Strängnäs",
            "occupation": "Poet",
            "birth_details": {
                "date": "24/08/1923",
                "place": "Växjö",
                "parents": "civiling Alfred S o Augusta Konradson"
            },
            "education": [
                {
                    "degree": "Stud:ex",
                    "year": "1944",
                    "institution": "Västerås"
                },
                {
                    "degree": "univ:stud",
                    "year": "1946-1951",
                    "institution": "Upps"
                }
            ],
            "career": [
                {
                    "position": "Ordf",
                    "years": {
                        "start_year": 1957,
                        "end_year": null
                    },
                    "organization": "Romantiska förb"
                }
            ],
            "family": {
                "spouse": "Madeleine Grumme",
                "marriage_year": "1956",
                "children": [
                    {
                        "name": "Carl Johan",
                        "birth_year": "1957"
                    },
                    {
                        "name": "Eva",
                        "birth_year": "1960"
                    }
                ]
            },
            "publications": [
                {
                    "title": "Månvagga",
                    "year": "1948",
                    "type": "poetry"
                },
                {
                    "title": "Resa i ditt inre",
                    "year": "1949",
                    "type": "poetry"
                },
                {
                    "title": "Brev",
                    "year": "1950",
                    "type": "poetry"
                },
                {
                    "title": "Poeternas himmel",
                    "year": "1950",
                    "type": "poetry"
                },
                {
                    "title": "Halleluja!",
                    "year": "1951",
                    "type": "poetry"
                },
                {
                    "title": "Hjärtat o trafiken",
                    "year": "1951",
                    "type": "poetry"
                },
                {
                    "title": "Alexandrine",
                    "year": "1952",
                    "type": "poetry"
                },
                {
                    "title": "Metamorphosis",
                    "year": "1953",
                    "type": "poetry"
                },
                {
                    "title": "Hamlet i Strängnäs",
                    "year": "1953",
                    "type": "poetry"
                },
                {
                    "title": "Dikter från San Michele",
                    "year": "1954",
                    "type": "poetry"
                },
                {
                    "title": "Dikter 47-52 (urval 54)",
                    "year": "1954",
                    "type": "poetry"
                },
                {
                    "title": "Poeten o samhället",
                    "year": "1954",
                    "type": "poetry"
                },
                {
                    "title": "Tabu",
                    "year": "1954",
                    "type": "poetry"
                },
                {
                    "title": "Ett underligt sällskap",
                    "year": "1955",
                    "type": "poetry"
                },
                {
                    "title": "Flickan o binden",
                    "year": "1955",
                    "type": "poetry"
                },
                {
                    "title": "Därför är jag monarkist",
                    "year": "1955",
                    "type": "poetry"
                },
                {
                    "title": "Svävande över paniken",
                    "year": "1956",
                    "type": "poetry"
                },
                {
                    "title": "Jag har två själar",
                    "year": "1957",
                    "type": "poetry"
                },
                {
                    "title": "Dikter i folkupplaga",
                    "year": "1957",
                    "type": "poetry"
                },
                {
                    "title": "Pandoras ask (folkuppl 60)",
                    "year": "1957",
                    "type": "poetry"
                },
                {
                    "title": "Via tomheten",
                    "year": "1958",
                    "type": "poetry"
                },
                {
                    "title": "Paus i snöskottningen",
                    "year": "1958",
                    "type": "poetry"
                },
                {
                    "title": "Här är Joppe! (barnbok 58)",
                    "year": "1958",
                    "type": "children's literature"
                },
                {
                    "title": "Fjorton dagar på jorden",
                    "year": "1959",
                    "type": "poetry"
                },
                {
                    "title": "Den förvandlade blomman",
                    "year": "1959",
                    "type": "poetry"
                },
                {
                    "title": "Det gömda Japan",
                    "year": "1960",
                    "type": "poetry"
                },
                {
                    "title": "Ekegårdens sagor",
                    "year": "1960",
                    "type": "poetry"
                },
                {
                    "title": "Klockorna (inskr o namn på de 47 klockorna i Västerås stadshus 60)",
                    "year": "1960",
                    "type": "poetry"
                },
                {
                    "title": "Psalmer i atomåldern?",
                    "year": "1960",
                    "type": "poetry"
                },
                {
                    "title": "Rymdpionjären",
                    "year": "1961",
                    "type": "poetry"
                },
                {
                    "title": "Några ord att fästa på siden",
                    "year": "1961",
                    "type": "poetry"
                },
                {
                    "title": "Det ljusnar",
                    "year": "1961",
                    "type": "poetry"
                },
                {
                    "title": "Långt från vårt jordiska hem (radiopjäs 61)",
                    "year": "1961",
                    "type": "radio play"
                },
                {
                    "title": "Usantropen",
                    "year": "1962",
                    "type": "poetry"
                },
                {
                    "title": "Herrens Moder",
                    "year": "1962",
                    "type": "poetry"
                },
                {
                    "title": "Pojken som trodde på Djävulen",
                    "year": "1962",
                    "type": "poetry"
                },
                {
                    "title": "Dikter från Gotland",
                    "year": "1963",
                    "type": "poetry"
                },
                {
                    "title": "Mitt språk (dikturval 63)",
                    "year": "1963",
                    "type": "poetry"
                },
                {
                    "title": "Via Do-lorosa",
                    "year": "1964",
                    "type": "poetry"
                }
            ]
        },
        "2": {
            "full_name": "BERTIL G A SETTERLUND",
            "location": "Orsa",
            "occupation": "Direktör",
            "birth_details": {
                "date": "24/08/1914",
                "place": "Gävle",
                "parents": "grossh G A S o Emy Andersson"
            },
            "education": {
                "degree": "Ing :ex tekn gymn",
                "year": "1936",
                "institution": "Härnösand"
            },
            "career": [
                {
                    "position": null,
                    "years": {
                        "start_year": 1945,
                        "end_year": 1957
                    },
                    "organization": "ab Orsakalk"
                },
                {
                    "position": "verkst dir",
                    "years": {
                        "start_year": 1957,
                        "end_year": null
                    },
                    "organization": "ab Orsakalk"
                }
            ],
            "family": {
                "spouse": "Birgit Björk",
                "marriage_year": "1946",
                "children": [
                    {
                        "name": "Karin",
                        "birth_year": "1947"
                    },
                    {
                        "name": "Elisabet",
                        "birth_year": "1954"
                    }
                ]
            }
        }
    }
}