{
    "original": "Södertälje, f i Gbg 19/6/28 av\ndir Bernhard S o Signe Gustafsson.\n\nStud:ex 46, stud Univ of Calif 46-47,\nGbgs hdlsl 48-49, jur kand Upps 55, anst\nab Sv Esso 55, Personaladm rådet 57,\nintend ab Astra Södertälje sed 61.\n- Ordf Upps stud:kår 54, led Fp:s\nrepr:skap, skolstyr o lönendn Södertälje.\nGift 50 m fil lic Kerstin Ygge f 28, dtr\nt dir Birger Y o Margit Larsson. - Barn:\nJohan f 52, Pär f 56, Mikael f 58.\n\n<b>SANGFELT, N G BERTIL, ingenjör,</b>\nUppsala, f i Fågelfors, Kalmar l, 3/3/19\nav lantbr August Jonsson o Anna\nNilsson.\n\nRealex 44, ing:ex 49, ämneslär Sala\ntek-nikersk 50, arb :ledare o ch tekn avd 55,\narb :ch Diös byggn ab 60, arb:ch Karl\nJohansson byggn ab Upps sed 63. - Utm:\nGM i Skytte o skidåkn. - Hobby:\nlitteratur.\n\nGift 50 m Birgitta Johansson f 28, dtr\nt lantbr Ferdinand J o Elsa J. - Barn:\nErland f 53, Per f 56, Sven f 63.\n\nSANICK, IVAR H, forskningskemist,\nTallberg, f i Trondheim, Norge, 18/11/02\nav Marcus S o Mathilda Heyman.\nB Se Tekn högsk Detroit, Mich, USA\n26, tekn ch Sv Total ab 47, ch Kem\nforskn :verksamh Tallberg sed 56. - Led\nSvTF, Amer Chemical Soc. - Medl\nFrimO. - Skr: art i facktidskr. - Hobby:\nsportfiske.\n\nGift 1) 31-55 m Inga Ericsson f 09, 2)\n60 m Anna-Britta Bergfors f 23, dtr t\nErik B o Anna Sjödin. - Barn: i l:a\näktUlf f 37, i2:aäktBof 61.\n\nSANNE, SVEN-DAVID H,\nhäradshövding, Västerås, f i Uddevalla 27/5/06 av\nv konsul Herman S o Ester Callmander.\nStud:ex Uddevalla 25, jur kand Upps 30,\ntingstjg Sunnervikens doms 30-33, fisk\nSvea hovr 34, eo assess där 39, assess\n41, rev:sekr 49 (tf 45), hovr:råd 51,\nhäradsh Västmanl mell doms sed 57. - Tjg\njust:dep:s lagbyrå 38, sekr S Roslags\ndoms 41-42, suppl f led o ordf stat\nhyresråd 47-57, sekr 46 års\nkommun:-lagskomm 48-52, ordf hyresnd Västerås\nsed 57, v styr :ordf Västmanl l sparbk\nsed 60. - Utm: RNO.\nGift 39 m Margareta Samuelsson f 12,\ndtr t rekt Sixten S o Ruth Andersson.\n-Barn: Christer f 40, Inger f 41, Johan\nf 44, Michael f 49.\n\n",
    "structured": {
        "0": {
            "full_name": "Södertälje",
            "location": "Göteborg",
            "birth_details": {
                "date": "19/06/1928",
                "place": "Göteborg",
                "parents": "dir Bernhard S o Signe Gustafsson"
            },
            "education": [
                {
                    "degree": "Stud",
                    "year": "1946",
                    "institution": "ex"
                },
                {
                    "degree": "Göteborgs handelshögskola",
                    "year": "1948-1949",
                    "institution": "Gbgs hdlsl"
                },
                {
                    "degree": "Jur kand",
                    "year": "1955",
                    "institution": "Upps"
                }
            ],
            "occupation": "anst ab Sv Esso 55, Personaladm rådet 57, intend ab Astra Södertälje sed 61",
            "career": [
                {
                    "position": "Ordf",
                    "years": {
                        "start_year": 1954,
                        "end_year": null
                    },
                    "organization": "Upps stud:kår"
                },
                {
                    "position": "led Fp:s repr:skap, skolstyr o lönendn Södertälje",
                    "years": {
                        "start_year": null,
                        "end_year": null
                    },
                    "organization": null
                }
            ],
            "family": {
                "spouse": "fil lic Kerstin Ygge",
                "marriage_year": "1950",
                "children": [
                    {
                        "name": "Johan",
                        "birth_year": "1952"
                    },
                    {
                        "name": "Pär",
                        "birth_year": "1956"
                    },
                    {
                        "name": "Mikael",
                        "birth_year": "1958"
                    }
                ]
            }
        },
        "1": {
            "full_name": "SANGFELT, N G BERTIL",
            "location": "Uppsala",
            "birth_details": {
                "date": "03/03/1919",
                "place": "Fågelfors, Kalmar l",
                "parents": "lantbr August Jonsson o Anna Nilsson"
            },
            "education": [
                {
                    "degree": "Realex",
                    "year": "1944",
                    "institution": null
                },
                {
                    "degree": "ing:ex",
                    "year": "1949",
                    "institution": null
                },
                {
                    "degree": "ämneslär Sala teknikersk",
                    "year": "1950",
                    "institution": null
                }
            ],
            "occupation": "arb :ledare o ch tekn avd 55, arb :ch Diös byggn ab 60, arb:ch Karl Johansson byggn ab Upps sed 63",
            "career": [],
            "family": {
                "spouse": "Birgitta Johansson",
                "marriage_year": "1950",
                "children": [
                    {
                        "name": "Erland",
                        "birth_year": "1953"
                    },
                    {
                        "name": "Per",
                        "birth_year": "1956"
                    },
                    {
                        "name": "Sven",
                        "birth_year": "1963"
                    }
                ]
            },
            "hobbies": [
                "litteratur"
            ]
        },
        "2": {
            "full_name": "SANICK, IVAR H",
            "location": "Tallberg",
            "birth_details": {
                "date": "18/11/1902",
                "place": "Trondheim, Norge",
                "parents": "Marcus S o Mathilda Heyman"
            },
            "education": [],
            "occupation": "tekn ch Sv Total ab 47, ch Kem forskn :verksamh Tallberg sed 56",
            "career": [],
            "family": {
                "spouse": "1) Inga Ericsson",
                "marriage_year": "1931-1955",
                "children": [
                    {
                        "name": "Ulf",
                        "birth_year": "1937"
                    }
                ]
            },
            "hobbies": [
                "sportfiske"
            ]
        },
        "3": {
            "full_name": "SANNE, SVEN-DAVID H",
            "location": "Västerås",
            "birth_details": {
                "date": "27/5/1906",
                "place": "Uddevalla",
                "parents": "v konsul Herman S o Ester Callmander"
            },
            "education": [
                {
                    "degree": "Stud:ex",
                    "year": "1925",
                    "institution": "Uddevalla"
                },
                {
                    "degree": "jur kand",
                    "year": "1930",
                    "institution": "Upps"
                }
            ],
            "occupation": "rev:sekr 49 (tf 45), hovr:råd 51, häradsh Västmanl mell doms sed 57",
            "career": [],
            "family": {
                "spouse": "Margareta Samuelsson",
                "marriage_year": "1939",
                "children": [
                    {
                        "name": "Christer",
                        "birth_year": "1940"
                    },
                    {
                        "name": "Inger",
                        "birth_year": "1941"
                    },
                    {
                        "name": "Johan",
                        "birth_year": "1944"
                    },
                    {
                        "name": "Michael",
                        "birth_year": "1949"
                    }
                ]
            },
            "honorary_titles": [
                {
                    "title": "RNO",
                    "institution": null,
                    "year": null
                }
            ]
        }
    }
}