{
    "original": "SANDEGÅRD, KARL J, kyrkoherde\n\nemeritus, Uppsala, f i Högbo, Gävleb l,\n6/10/80 av handl Karl Pettersson o\nEmelie Andersdtr.\n\nTeol kand Upps 05, fil kand 12, past:adj\nGävle 07, kommin Segersta 10, Högbo\n15, kyrkoh Fuxerna Gbgs stift 18, Sofia\nförs Sthlm 39-51. - FK 19-45 (led\nkonst:-utsk, statsrev 43-45, s). - Skr: Vad skola\nvi tro (33), Kring Emanuel Linderholm\no hans gärning (39), Den fortsatta\nreformationen (38).\n\nGift 07 m Jenny Rapp f 87, dtr t handl\nErik R o Margareta Nilsdotter. - Barn:\nEinar f 10, Bertil f 12, Bengt f 19.\n\nSANDELIN, KNUT A E, fd\nlandskamrerare, Uppsala, f i Frykerud, Värml\nl, 22/4/87 av kronolänsm Ferdinand S o\nDalinda Nilsson.\n\nStud:ex 05, kansliex Upps 09, eo\nlands-kont Värml l 10, e länsbokh Älvsb l\n15, länsbokh av l kl där 17, länsassess\nGävleb l 25, Älvsb l 28, landskamr\nUpps l 35-53. - Utm: KNO, RVO.\n\nSANDELIN, UDDO V S, förste läkare,\nSträngnäs, f i Luleå 1/12/11.\nMed kand 38, med lic Upps 51, l:e\nunderläk med avd Karlshamns las 54-55,\nläk Sundby sjh 57, l:e läk där sed 61.\n\nSANDELIUS, A GÖSTA, leg läkare,\nUttran, f i Hammar, Örebro l, 24/10/14\nav kyrkoh David S o Emma Staaf.\nStud:ex Norrkpg 32, med kand Sthlm\n34, med lic 40, ol läk:förordn 40-44,\nunderläk Eksjö sanat 45, Söderby sjh\n49, Sthlms centraldisp 52, Sabbatsb\nvård- o ålderdomsh 54, med avd\nNorrtälje las 56, l:e underläk Söderby sjh\nsed 59.\nGift 52 m Ruth Åhs. - Barn: Lars f 57.\n\nSANDELL, H M VIOLA, assistent,\nriksdagsman, Karlstad, f i Ö Eneby,\nÖstergötl l, 23/9/10 av byggn:snick Anders\nS o Hulda Isaksdtr.\n\nLO-skolan Brunnsvik 42, omb :man\nHembitr:fören centralkomm 41, instruk-\n\ntör i alkoholfrågor IOGT .47, ass\nläns-arb:ndn Karlstad sed 48. - AK sed 53\n(s), led 60 års semesterutredn, expert 62\nårs hembitr:utredn, ordf Sthlms\nhem-bitr:fören 37-47, Karlstads arb :kommun\n52-54, kassör Klara-Jacobs fattigv:styr\n44-48, ndeman Sthlm 47, led Karlstads\nnykterh:nd 50-55, skolstyr 57, medl\nIOGT, VasaO av Amer. - Sign: V. S-ll,\nViolet. - Hobbies: bandintervjuer (data\no röster från äldre tider), resor.\n\n",
    "structured": {
        "0": {
            "full_name": "SANDEGÅRD, KARL J",
            "location": "Uppsala",
            "occupation": "kyrkoherde emeritus",
            "birth_details": {
                "date": "06/10/1880",
                "place": "Högbo, Gävleb l"
            },
            "education": [
                {
                    "degree": "Teol kand",
                    "year": "1905",
                    "institution": "Uppsala"
                },
                {
                    "degree": "filosofie kandidat",
                    "year": "1912",
                    "institution": "Uppsala"
                }
            ],
            "career": [
                {
                    "position": "past:adj",
                    "years": {
                        "start_year": 1907,
                        "end_year": 1910
                    },
                    "organization": "Gävle"
                },
                {
                    "position": "kommin",
                    "years": {
                        "start_year": 1910,
                        "end_year": 1915
                    },
                    "organization": "Segersta"
                },
                {
                    "position": "kyrkoh",
                    "years": {
                        "start_year": 1915,
                        "end_year": 1918
                    },
                    "organization": "Högbo"
                },
                {
                    "position": "kyrkoh",
                    "years": {
                        "start_year": 1918,
                        "end_year": 1939
                    },
                    "organization": "Fuxerna, Gbgs stift"
                },
                {
                    "position": "kyrkoh",
                    "years": {
                        "start_year": 1939,
                        "end_year": 1951
                    },
                    "organization": "Sofia förs, Sthlm"
                }
            ],
            "family": {
                "spouse": "Jenny Rapp",
                "marriage_year": "1907",
                "children": [
                    {
                        "name": "Einar",
                        "birth_year": "1910"
                    },
                    {
                        "name": "Bertil",
                        "birth_year": "1912"
                    },
                    {
                        "name": "Bengt",
                        "birth_year": "1919"
                    }
                ]
            }
        },
        "1": {
            "full_name": "SANDELIN, KNUT A E",
            "location": "Uppsala",
            "occupation": "fd landskamrerare",
            "birth_details": {
                "date": "22/04/1887",
                "place": "Frykerud, Värml l"
            },
            "education": [
                {
                    "degree": "Stud:ex",
                    "year": "1905"
                },
                {
                    "degree": "kansliex",
                    "year": "1909",
                    "institution": "Uppsala"
                }
            ],
            "career": [
                {
                    "position": "eo lands-kont",
                    "years": {
                        "start_year": 1910,
                        "end_year": 1915
                    },
                    "organization": "Värml l"
                },
                {
                    "position": "länsbokh",
                    "years": {
                        "start_year": 1915,
                        "end_year": 1917
                    },
                    "organization": "Älvsb l"
                },
                {
                    "position": "länsbokh",
                    "years": {
                        "start_year": 1917,
                        "end_year": 1925
                    },
                    "organization": "Älvsb l"
                },
                {
                    "position": "länsassess",
                    "years": {
                        "start_year": 1925,
                        "end_year": 1935
                    },
                    "organization": "Gävleb l"
                },
                {
                    "position": "landskamr",
                    "years": {
                        "start_year": 1935,
                        "end_year": 1953
                    },
                    "organization": "Upps l"
                }
            ],
            "family": {
                "spouse": "NULL",
                "marriage_year": "NULL",
                "children": []
            }
        },
        "2": {
            "full_name": "SANDELIN, UDDO V S",
            "location": "Strängnäs",
            "occupation": "förste läkare",
            "birth_details": {
                "date": "01/12/1911",
                "place": "Luleå"
            },
            "education": [
                {
                    "degree": "Med kand",
                    "year": "1938"
                },
                {
                    "degree": "med lic",
                    "year": "1951",
                    "institution": "Upps"
                }
            ],
            "career": [
                {
                    "position": "l:e underläk",
                    "years": {
                        "start_year": 1954,
                        "end_year": 1955
                    },
                    "organization": "Karlshamns las"
                },
                {
                    "position": "läk",
                    "years": {
                        "start_year": 1957,
                        "end_year": 1961
                    },
                    "organization": "Sundby sjh"
                }
            ],
            "family": {
                "spouse": "NULL",
                "marriage_year": "NULL",
                "children": []
            }
        },
        "3": {
            "full_name": "SANDELIUS, A GÖSTA",
            "location": "Uttran",
            "occupation": "leg läkare",
            "birth_details": {
                "date": "24/10/1914",
                "place": "Hammar, Örebro l"
            },
            "education": [
                {
                    "degree": "Stud:ex",
                    "year": "1932",
                    "institution": "Norrkpg"
                },
                {
                    "degree": "med kand",
                    "year": "1934",
                    "institution": "Sthlm"
                },
                {
                    "degree": "med lic",
                    "year": "1940"
                }
            ],
            "career": [
                {
                    "position": "ol läk:förordn",
                    "years": {
                        "start_year": 1940,
                        "end_year": 1944
                    },
                    "organization": "NULL"
                },
                {
                    "position": "underläk",
                    "years": {
                        "start_year": 1945,
                        "end_year": 1949
                    },
                    "organization": "Eksjö sanat"
                },
                {
                    "position": "l:e underläk",
                    "years": {
                        "start_year": 1959
                    },
                    "organization": "Söderby sjh"
                }
            ],
            "family": {
                "spouse": "Ruth Åhs",
                "marriage_year": "1952",
                "children": [
                    {
                        "name": "Lars",
                        "birth_year": "1957"
                    }
                ]
            }
        },
        "4": {
            "full_name": "SANDELL, H M VIOLA",
            "location": "Karlstad",
            "occupation": "assistent, riksdagsman",
            "birth_details": {
                "date": "23/09/1910",
                "place": "Ö Eneby, Östergötl l"
            },
            "education": [
                {
                    "degree": "LO-skolan",
                    "year": "1942",
                    "institution": "Brunnsvik"
                }
            ],
            "career": [
                {
                    "position": "omb :man",
                    "organization": "Hembitr:fören centralkomm",
                    "years": "1941"
                }
            ],
            "family": {
                "spouse": "NULL",
                "marriage_year": "NULL",
                "children": []
            },
            "hobbies": [
                "bandintervjuer (data o röster från äldre tider)",
                "resor"
            ]
        }
    }
}