{
    "original": "SJÖSTRÖM, NILS V G, rektor,\nVallentuna, f i Sthlm 13/3/22 av dir Vilhelm\nS o Ester Gerlofsson.\nStud:ex Lidingö 41, folkskollär :ex Upps\n47, adj:behörigh Upps 55, folkskollär\nLidingö 47, ämneslär samrealsk\nKramfors 48, folkskollär Malå 50, tillsynslär\ndär 51, vik rektor komm realsk\nMalå-träsk 52-53, adj komm realsk Hagfors\n55-56, rektor komm realsk Sorsele 57,\nsamrealsk Munkfors 59, rekt o skolch\nVallentuna kn sed 63.\nGift 47 m Alice Pettersson f 19, dtr t\ndir Otto P o Thyra Sjögren. - Barn:\nBritt-Marie f 48, Kerstin f 50, Lena f 53,\nMats f 57.\n\nSJÖSTRÖM, SVERKER W, tekn dr,\n\nGrödinge, f i Robertsfors, Västerb l,\n9/1/20 av apot Walfrid S o Villy\nKarlsson.\n\nStud:ex Växjö 38, KTH 43, tekn dr 61,\nanst Flygtekn försöksanst 43, ab Bofors\n45, ab Scania Vabis Södertälje 47, tekn\ndir där sed 61. - Medl Rotary. - Skr: Ofo\nrandom load analysis (drsavh 61) samt\netti flert arb inom hållfasth :tekn omr.\n-Hobbies: segling, skidåkning.\nGift 43 m Britta Gustaver f 19, dtr t\nfil dr Bror G o Elsa Gillberg. - Barn:\nYlva f 45, Åsa f 47, Karla f 49, Ragna\nf 50, Staffan f 51.\n\nSJÖVALL, HELGE S, överläkare,\nÖrebro, f i Ljungby 18/11/04 av las:läk,\nmed dr Sigurd S o Kerstin Skoog.\nStud:ex Växjö 23, med kand Lund 27,\nmed lic 31, med dr 36, doc i histologi\n36-37, (eo) aman anat inst 36, e läk o\naman kir klin 30, 38, 42, aman o\nunderläk ortop klin 36-37, 39-41, doc i orto-\n\npedi 42-48, tf överläk o lär i ortopedi\n43-45, l:e underläk Vanföreanst 45,\növerläk Örebro las sed 48. - Medl\nFrim-O, Rotary. - Skr i histologi o ortopedi.\n-Utm: RNO.\n\nGift 37 m Eva Walberg f 11, dtr t\nskulptör Herman W o Clara Andersson.\n\n-  Barn: Anders f 39, Kerstin f 43, Peter\nf 47.\n\n",
    "structured": {
        "1": {
            "full_name": "NILS V G SJÖSTRÖM",
            "location": "Vallentuna",
            "occupation": "rektor",
            "birth_details": {
                "date": "13/03/1922",
                "place": "Stockholm",
                "parents": "dir Vilhelm S o Ester Gerlofsson"
            },
            "education": [
                {
                    "degree": "Stud:ex",
                    "year": "1941",
                    "institution": "Lidingö"
                },
                {
                    "degree": "folkskollär :ex",
                    "year": "1947",
                    "institution": "Upps"
                },
                {
                    "degree": "adj:behörigh",
                    "year": "1955",
                    "institution": "Upps"
                }
            ],
            "career": [
                {
                    "position": "rektor",
                    "years": {
                        "start_year": 1963,
                        "end_year": null
                    },
                    "organization": "Vallentuna kn"
                },
                {
                    "position": "vik rektor",
                    "years": {
                        "start_year": 1952,
                        "end_year": 1953
                    },
                    "organization": "komm realsk Malå-träsk"
                },
                {
                    "position": "adj",
                    "years": {
                        "start_year": 1955,
                        "end_year": 1956
                    },
                    "organization": "komm realsk Hagfors"
                },
                {
                    "position": "rektor",
                    "years": {
                        "start_year": 1957,
                        "end_year": null
                    },
                    "organization": "komm realsk Sorsele"
                },
                {
                    "position": "samrealsk Munkfors",
                    "years": {
                        "start_year": 1959,
                        "end_year": null
                    },
                    "organization": null
                }
            ],
            "family": {
                "spouse": "Alice Pettersson",
                "marriage_year": "1947",
                "children": [
                    {
                        "name": "Britt-Marie",
                        "birth_year": "1948"
                    },
                    {
                        "name": "Kerstin",
                        "birth_year": "1950"
                    },
                    {
                        "name": "Lena",
                        "birth_year": "1953"
                    },
                    {
                        "name": "Mats",
                        "birth_year": "1957"
                    }
                ]
            }
        },
        "2": {
            "full_name": "SVERKER W SJÖSTRÖM",
            "location": "Grödinge",
            "occupation": "tekn dr",
            "birth_details": {
                "date": "09/01/1920",
                "place": "Robertsfors, Västerb l"
            },
            "education": [
                {
                    "degree": "Stud:ex",
                    "year": "1938",
                    "institution": "Växjö"
                },
                {
                    "degree": null,
                    "year": "1943",
                    "institution": "KTH"
                },
                {
                    "degree": "tekn dr",
                    "year": "1961",
                    "institution": null
                }
            ],
            "career": [
                {
                    "position": "tekn dir",
                    "years": {
                        "start_year": 1961,
                        "end_year": null
                    },
                    "organization": "ab Scania Vabis Södertälje"
                },
                {
                    "position": null,
                    "years": {
                        "start_year": 1943,
                        "end_year": null
                    },
                    "organization": "Flygtekn försöksanst"
                },
                {
                    "position": null,
                    "years": {
                        "start_year": 1945,
                        "end_year": null
                    },
                    "organization": "ab Bofors"
                }
            ],
            "family": {
                "spouse": "Britta Gustaver",
                "marriage_year": "1943",
                "children": [
                    {
                        "name": "Ylva",
                        "birth_year": "1945"
                    },
                    {
                        "name": "Åsa",
                        "birth_year": "1947"
                    },
                    {
                        "name": "Karla",
                        "birth_year": "1949"
                    },
                    {
                        "name": "Ragna",
                        "birth_year": "1950"
                    },
                    {
                        "name": "Staffan",
                        "birth_year": "1951"
                    }
                ]
            },
            "hobbies": [
                "segling",
                "skidåkning"
            ]
        },
        "3": {
            "full_name": "HELGE S SJÖVALL",
            "location": "Örebro",
            "occupation": "överläkare",
            "birth_details": {
                "date": "18/11/1904",
                "place": "Ljungby",
                "parents": "las:läk, med dr Sigurd S o Kerstin Skoog"
            },
            "education": [
                {
                    "degree": "Stud:ex",
                    "year": "1923",
                    "institution": "Växjö"
                },
                {
                    "degree": "med kand",
                    "year": "1927",
                    "institution": "Lund"
                },
                {
                    "degree": "med lic",
                    "year": "1931",
                    "institution": null
                },
                {
                    "degree": "med dr",
                    "year": "1936",
                    "institution": null
                }
            ],
            "career": [
                {
                    "position": "överläk",
                    "years": {
                        "start_year": 1948,
                        "end_year": null
                    },
                    "organization": "Örebro las"
                }
            ],
            "family": {
                "spouse": "Eva Walberg",
                "marriage_year": "1937",
                "children": [
                    {
                        "name": "Anders",
                        "birth_year": "1939"
                    },
                    {
                        "name": "Kerstin",
                        "birth_year": "1943"
                    },
                    {
                        "name": "Peter",
                        "birth_year": "1947"
                    }
                ]
            },
            "community_involvement": [
                {
                    "role": "doc i histologi o ortopedi",
                    "organization": null,
                    "years": null
                }
            ],
            "honorary_titles": [
                {
                    "title": "RNO",
                    "institution": null,
                    "year": null
                }
            ]
        }
    }
}