{
    "original": "SANDBERG, HANS H, disponent,\nSödertälje, f i Nacka 8/10/00 av förvalt\nFrans S o Frida Johansson.\nStud:ex Sthlm 20, KTH 25, konstr\ning:-depån Karlskrona 26, ing Sv\ntobaksmonopolet 27, disp o ch dess fabr\nHärnösand 43, disp o fabr :ch Sv tobaks ab\nSödertälje sed 49. - Insp Södertälje\nyr-kessk 53-58. - HedL Tekn fören\nSödertälje sed 59, medl Rotary, S:ta Ragnhilds\ngille, Södertälje skyttegille. - Utm: RVO,\nSvsfbSM, RLSFftjtS, Fören f arb :skydd\nftjtG, Södertälje sfftjtG. - Hobby:\nfriluftsliv.\n\nGift 28 m Signe Larsson f Ol, dtr t tjm\nGustav L o Hilma Davidsson. - Barn:\nBengt f 31.\n\nSANDBERG,   HARRY   E,   konstnär,\n\nGrängesberg, f i Ljusnarsberg, Örebro l,\n\n28/6/04 av gruvfogde Karl S  o  Ebba\n\nHedlund.\n\nVerkst :arb Asea Ludvika 23-26, förman\n\nBolidens gruvor 26-35. - Otte Skölds må-\n\nlarsk 35-36. - Sep:utst o delt i saml:utst.\n\n-  Medl KRO, Fören Dalakonstn. -\nHobby: segling.\n\nGift 44 m Zara Nordström, dtr t\nverkst :arb Ernfrid N o Hulda Karlsson.\n-Barn: Katarina f 48.\n\nSANDBERG, S E HARRY, konstnär,\n\nKarlstad, f i Själevad, Västernorrl l,\n20/4/20 av Anton S o Edit Englund.\nKKH 44-46, anst Maggie Wibom\nkeramik Sthlm 46, Gustavsbergs studio 48,\ninneh hantverksstudio (keram konsthantv)\nsed 49, timlär hal Karlstad sed 60. - Bl\narb: polykroma keramikreliefer t\ngravkapell Själevad (54), Värml landst (57),\nHSB Karlstad (57-58), Karlstad stad (60).\n\n-  Utst Värml mus 52, Sthlm 54-57, delt\ni   saml:utst  Nat:mus  47,   49,   51-53.\n-Repr i Nat:mus o Värml mus. - Medl\n\nKRO. - Erh Värml musei vänners\nrese-stip 58.\n\nGift 49-58 m Kajsa Rulländer f 22, dtr\nt mjöln Herman K o Maja Lilja. - Barn:\nErland f 49.\n\n",
    "structured": {
        "1": {
            "full_name": "Hans H Sandberg",
            "location": "Södertälje",
            "occupation": "disponent",
            "birth_details": {
                "date": "08/10/1900",
                "place": "Nacka"
            },
            "education": [
                {
                    "degree": "Stud:ex",
                    "year": "1920",
                    "institution": "Sthlm"
                },
                {
                    "degree": "KTH",
                    "year": "1925",
                    "institution": "Kungliga Tekniska högskolan"
                }
            ],
            "career": [
                {
                    "position": "konstr ing",
                    "years": {
                        "start_year": 1926,
                        "end_year": 1927
                    },
                    "organization": "depån Karlskrona"
                },
                {
                    "position": "ing",
                    "years": {
                        "start_year": 1927,
                        "end_year": 1943
                    },
                    "organization": "Sv tobaksmonopolet"
                },
                {
                    "position": "disp o fabr",
                    "years": {
                        "start_year": 1943,
                        "end_year": 1949
                    },
                    "organization": "Härnösand"
                },
                {
                    "position": "disp o fabr :ch",
                    "years": {
                        "start_year": 1949,
                        "end_year": null
                    },
                    "organization": "Sv tobaks ab Södertälje"
                },
                {
                    "position": "Insp Södertälje yr-kessk",
                    "years": {
                        "start_year": 1953,
                        "end_year": 1958
                    },
                    "organization": "Södertälje"
                }
            ],
            "family": {
                "spouse": "Signe Larsson",
                "marriage_year": "1928",
                "children": [
                    {
                        "name": "Bengt",
                        "birth_year": "1931"
                    }
                ]
            },
            "community_involvement": [
                {
                    "role": "Insp",
                    "organization": "Södertälje",
                    "years": "1959"
                }
            ],
            "honorary_titles": [
                {
                    "title": "RVO",
                    "institution": null,
                    "year": null
                },
                {
                    "title": "SvsfbSM",
                    "institution": null,
                    "year": null
                },
                {
                    "title": "RLSFftjtS",
                    "institution": null,
                    "year": null
                },
                {
                    "title": "Fören f arb :skydd ftjtG",
                    "institution": null,
                    "year": null
                },
                {
                    "title": "Södertälje sfftjtG",
                    "institution": null,
                    "year": null
                }
            ],
            "hobbies": [
                "friluftsliv"
            ]
        },
        "2": {
            "full_name": "Harry E Sandberg",
            "location": "Grängesberg",
            "occupation": "konstnär",
            "birth_details": {
                "date": "28/06/1904",
                "place": "Ljusnarsberg, Örebro l"
            },
            "career": [
                {
                    "position": "Verkst :arb",
                    "years": {
                        "start_year": 1923,
                        "end_year": 1926
                    },
                    "organization": "Asea Ludvika"
                },
                {
                    "position": "förman",
                    "years": {
                        "start_year": 1926,
                        "end_year": 1935
                    },
                    "organization": "Bolidens gruvor"
                },
                {
                    "position": "Otte Skölds målarsk",
                    "years": {
                        "start_year": 1935,
                        "end_year": 1936
                    },
                    "organization": null
                }
            ],
            "family": {
                "spouse": "Zara Nordström",
                "marriage_year": "1944",
                "children": [
                    {
                        "name": "Katarina",
                        "birth_year": "1948"
                    }
                ]
            },
            "community_involvement": [],
            "hobbies": [
                "segling"
            ]
        },
        "3": {
            "full_name": "S E Harry Sandberg",
            "location": "Karlstad",
            "occupation": "konstnär",
            "birth_details": {
                "date": "20/04/1920",
                "place": "Själevad, Västernorrl l"
            },
            "education": [
                {
                    "degree": "KKH",
                    "year": "1944-1946",
                    "institution": "Kungliga Konsthögskolan"
                }
            ],
            "career": [
                {
                    "position": "anst",
                    "years": {
                        "start_year": 1946,
                        "end_year": 1948
                    },
                    "organization": "Maggie Wibom keramik Sthlm"
                },
                {
                    "position": "Gustavsbergs studio",
                    "years": {
                        "start_year": 1948,
                        "end_year": null
                    },
                    "organization": "Gustavsbergs studio"
                },
                {
                    "position": "inneh",
                    "years": {
                        "start_year": 1949,
                        "end_year": null
                    },
                    "organization": "hantverksstudio (keram konsthantv)"
                },
                {
                    "position": "timlär hal Karlstad",
                    "years": {
                        "start_year": 1960,
                        "end_year": null
                    },
                    "organization": "Karlstad"
                }
            ],
            "family": {
                "spouse": "Kajsa Rulländer",
                "marriage_year": "1949-1958",
                "children": [
                    {
                        "name": "Erland",
                        "birth_year": "1949"
                    }
                ]
            },
            "community_involvement": [],
            "publications": [],
            "board_memberships": [],
            "honorary_titles": [],
            "hobbies": []
        }
    }
}