{
    "original": "SJÖDELL, PER-OLOF, lantmätare,\nSödertälje, f i Halmstad 20/1/25 av\ndistr:-lantmät Carl Erik S o Frida Tjerngren.\nStud:ex Sthlm 44, KTH 50, lantmät\nÄlvsb l 50, Värml l 55, Sthlms l sed\n59. - Led byggn :nd o fastigh :tax :nd\nSödertälje sed 63. - Hobbies: tennis, bridge.\nGift 56 m Britta Landmark f 29, dtr t\nskogsförv Erik L o Gerda Jonsson.\n-Barn: Liv f 56, Erik f 60.\n\nSJÖDÉN, E BERTIL, häradsskrivare,\nLudvika, f i Särna, Kopparb l, 29/7/03\nav byggm Per S o Beata Berg.\nStud:ex Falun 23, Schartaus HdlI 25,\nanst landskansliet Kopparb l 26, bitr\nHedemora fögd häradsskr:kont 28, e\nlands-kont Kopparb l 35, landskont där 44,\nhäradsskriv Västerdals fögd 46,\nVäster-bergsl fögd sed 63. - Ordf tax:nd 34-44,\nallm fastigh :tax :nd 52 o 57, tax\n:konsulent 45-58, led skolstyr Malung 58-60.\n\n-  Utm: Dalarnas idr:förb elittecken,\nSv-rifbdipl.\n\nGift 41 m Mait Ann-Mari Nilsson f 18,\ndtr t hemm:äg Jöns N o Anna\nLarsdotter. - Barn: Olof f 54.\n\nSJÖDIN, H CARL E, ingenjör,\nUpplands Väsby, f i Sthlm 2/2/21 av sjökapt\nErik S o Gussi Videnborg.\nIng:ex STI 46; verkm ab Skånska\nce-mentgjuteriet 44, ab Vägförbättr\nUlriksdal 44, verkst :ch 58, maskininsp där 53,\nverkst:ch ab Vägförbättr Uppl Väsby 57,\nch underh:sekt maskinavd där sed 62.\n-Hobbies: smalfilm, trädgårdsskötsel.\nGift 42 m Wivan Engström f 20, dtr t\nFredrik E o Oscara Forsberg. - Barn:\nSiw f 46, Karin f 51.\n\nSJÖDIN, ROLF H, bankdirektör,\nÖrebro, f i Boden 8/9/08 av postmast\nHjalmar S o Hilda Ljungcrantz.\nRealex 24, hdlsutbildn 26-27, kamr Sv\nhdlsbkn Haparanda 41, verkst dir Luleå\nfolkbk 46, dir Sv hdlsbkn Piteå 51, Örn-\n\nsköldsvik 60, avd :dir Sv hdlsbkn Örebro\nsed 62.\n\nGift 37 m Hulan Pettersson f 12, dtr t\nköpman August P o Hulda Benjamin.\n-Barn: Per f 44.\n\n",
    "structured": {
        "0": {
            "full_name": "Per-Olof Sjödell",
            "location": "Södertälje",
            "occupation": "Lantmätare",
            "birth_details": {
                "date": "20/01/1925",
                "place": "Halmstad",
                "parents": "distr:-lantmät Carl Erik S o Frida Tjerngren"
            },
            "education": [
                {
                    "degree": "Stud:ex",
                    "year": "1944",
                    "institution": "Sthlm"
                },
                {
                    "degree": "KTH",
                    "year": "1950",
                    "institution": "KTH"
                },
                {
                    "degree": "lantmät",
                    "year": "1950",
                    "institution": "Älvsb l"
                },
                {
                    "degree": "lantmät",
                    "year": "1955",
                    "institution": "Värml l"
                }
            ],
            "career": [
                {
                    "position": "Led byggn :nd o fastigh :tax :nd",
                    "years": {
                        "start_year": 1963,
                        "end_year": null
                    },
                    "organization": "Södertälje"
                }
            ],
            "family": {
                "spouse": "Britta Landmark",
                "marriage_year": "1956",
                "children": [
                    {
                        "name": "Liv",
                        "birth_year": "1956"
                    },
                    {
                        "name": "Erik",
                        "birth_year": "1960"
                    }
                ]
            }
        },
        "1": {
            "full_name": "E Bertil Sjödén",
            "location": "Ludvika",
            "occupation": "Häradsskrivare",
            "birth_details": {
                "date": "29/07/1903",
                "place": "Särna, Kopparbergs län",
                "parents": "byggm Per S o Beata Berg"
            },
            "education": [
                {
                    "degree": "Stud:ex",
                    "year": "1923",
                    "institution": "Falun"
                },
                {
                    "degree": "Schartaus HdlI",
                    "year": "1925",
                    "institution": "Schartaus HdlI"
                }
            ],
            "career": [
                {
                    "position": "häradsskriv",
                    "years": {
                        "start_year": 1963,
                        "end_year": null
                    },
                    "organization": "Västerbergsl fögd"
                }
            ],
            "family": {
                "spouse": "Mait Ann-Mari Nilsson",
                "marriage_year": "1941",
                "children": [
                    {
                        "name": "Olof",
                        "birth_year": "1954"
                    }
                ]
            },
            "publications": null,
            "community_involvement": null,
            "board_memberships": null,
            "honorary_titles": [
                {
                    "title": "Dalarnas idr:förb elittecken",
                    "institution": null,
                    "year": null
                }
            ],
            "hobbies": null
        },
        "2": {
            "full_name": "Carl E Sjödin",
            "location": "Upplands Väsby",
            "occupation": "Ingenjör",
            "birth_details": {
                "date": "02/02/1921",
                "place": "Sthlm",
                "parents": "sjökapt Erik S o Gussi Videnborg"
            },
            "education": [
                {
                    "degree": "Ing:ex",
                    "year": "1946",
                    "institution": "STI"
                }
            ],
            "career": [
                {
                    "position": "ch underh:sekt maskinavd där",
                    "years": {
                        "start_year": 1962,
                        "end_year": null
                    },
                    "organization": "Uppl Väsby"
                }
            ],
            "family": {
                "spouse": "Wivan Engström",
                "marriage_year": "1942",
                "children": [
                    {
                        "name": "Siw",
                        "birth_year": "1946"
                    },
                    {
                        "name": "Karin",
                        "birth_year": "1951"
                    }
                ]
            },
            "publications": null,
            "community_involvement": null,
            "board_memberships": null,
            "honorary_titles": null,
            "hobbies": [
                "smalfilm",
                "trädgårdsskötsel"
            ]
        },
        "3": {
            "full_name": "Rolf H Sjödin",
            "location": "Örebro",
            "occupation": "Bankdirektör",
            "birth_details": {
                "date": "08/09/1908",
                "place": "Boden",
                "parents": "postmast Hjalmar S o Hilda Ljungcrantz"
            },
            "education": [
                {
                    "degree": "Realex",
                    "year": "1924",
                    "institution": null
                },
                {
                    "degree": "hdlsutbildn",
                    "year": "1926-27",
                    "institution": null
                }
            ],
            "career": [
                {
                    "position": "avd :dir Sv hdlsbkn Örebro",
                    "years": {
                        "start_year": 1962,
                        "end_year": null
                    },
                    "organization": "Sv hdlsbkn Örebro"
                }
            ],
            "family": {
                "spouse": "Hulan Pettersson",
                "marriage_year": "1937",
                "children": [
                    {
                        "name": "Per",
                        "birth_year": "1944"
                    }
                ]
            },
            "publications": null,
            "community_involvement": null,
            "board_memberships": null,
            "honorary_titles": null,
            "hobbies": null
        }
    }
}