{
    "original": "SERRANDER, S GUNNAR V,\nstadsfogde,   Sala,  f   i   Östervåla  förs,\nVästmanl l, 10/12/00 av folkskollär Vilhelm\nSo Elin Jonsson.\n\nStud:ex Lund  21,  jur  kand  Upps  27,\n\nstadsfogde Sala sed 34. - Omb :man o\nstyr :led Sala sparbk sed 40, v ordf\nut-skrivn:ndn Salberga sjh. - Medl Rotary.\nGift 36 m Britta Sandberg. - Barn: Olle\nf 38, Rita f 40, Sten f 48, Björn f 52.\n\nSERRANDER,   KNUT  E,  disponent,\n\nEskilstuna, f i Torshälla 29/5/14 av\nbanvakt Gustaf S o Ida Lindberg.\nBesiktn :man Carl Gustafs städs\ngevärsfaktori 41, inneh bilfirma Knut\nSerrander 46, disp Autostandard i Sörml ab 50,\nverkst dir där 54, disp ab Eskilstuna\nbilkomp sed 57, verkst dir ab Arvid\nPetterssons fastigh sed 61. - Medl IOGT,\nMHF, TempelriddO. - Hobby: sjösport.\nGift 41 m Lalla Blomberg f 15, dtr t\nförman August B o Anna Carlsson.\n-Barn: Håkan f 52.\n\nSETH, IVAR O R, rektor, Karlstad, f\ni Sthlm 31/5/10 av sekr Martin S o\nSigrid Spilhammar.\n\nStud:ex 28, fil mag 33, fil lic 42, fil dr\n52. - E aman Sthlms stadsarkiv 32, lär\nOlofsk Sthlm 37, Sigtunastift human\nlärov 41, adj där 45, lekt 48, hal\nBromma 53, rekt hal Karlstad sed 54. - Ordf\nSthlms kristl stud:förb 32, sekr\nHistorielär fören riksorg 48-55 (v ordf sed\n61), red dess årsskr sed 48, dess\nskriftserie sed 55. - Stadsfullm Karlstad\n59-62 (h). - Skr: Universitetsförhållanden i\nGreifswald v 1600-talets slut (42), En\nsvensk medborgares rättigheter o\nskyldigheter (43), Universitetet i Greifswald\no dess ställning i svensk kulturpolitik\n1637—1815 (drsavh 52, t tyska 56),\nAllmän historia f gymn (tills m E\nSöderlund 56), Medeltidens o nya tidens\nhistoria f gymn (tills m a 58), Bibliograf\nhandledn i allmän historia (61).\nGift 37 m gymn:dir Inga Thorén f 11\nd 62, dtr t förvalt Axel T o Klara\nPettersson. - Barn: Agneta f 40, Barbro\nf 42, Ingegerd f 44, Torsten f 47.\n\nvon SETH, RUTGER H, bruksägare,\n\nÅkers Styckebruk, f i Hörby, Malmöh l,\n22/12/98 av major Eduard v S o Anna\nWahlberg.\n\nStud:ex Ystad 17, KTH 22, l:e ass\nKTH:s metallurg lab 23, tf spec:lär i\nmateriallära KTH 25, metallurg\nforskn:ing Sandvikens jernv ab 26, Avesta jernv\nab 31, ch:metallurg där 33, övering\n37-43, verkst dir ab Åkers styckebruk 43-64,\nstyr :ordf sed 64. - Sakk t prof i järnets\nmetallurgi v KTH 40, fullm Jernkont\n56-59. - LIVA 51. - Skr: ett flert upps i\nsv o utl facktidskr. - Utm: KVO,\nJernkont stGM 61.\nGift 32 m Phyllis Donnison f 02, dtr t\n\nJohn D o Rosie Burt. - Barn:\nAnne-Marie f 33, Phyllis f 37.\n\n",
    "structured": {
        "1": {
            "full_name": "S Gunnar V Serrander",
            "location": "Sala",
            "occupation": "Stadsfogde",
            "birth_details": {
                "date": "10/12/1900",
                "place": "Östervåla förs, Västmanland"
            },
            "education": [
                {
                    "degree": "Stud:ex",
                    "year": "1921",
                    "institution": "Lund"
                },
                {
                    "degree": "jur kand",
                    "year": "1927",
                    "institution": "Upps"
                }
            ],
            "career": [
                {
                    "position": "stadsfogde",
                    "years": {
                        "start_year": 1934,
                        "end_year": null
                    },
                    "organization": "Sala"
                },
                {
                    "position": "Omb :man o styr :led",
                    "years": {
                        "start_year": 1940,
                        "end_year": null
                    },
                    "organization": "Sala sparbk"
                }
            ],
            "family": {
                "spouse": "Britta Sandberg",
                "marriage_year": "1936",
                "children": [
                    {
                        "name": "Olle",
                        "birth_year": "1938"
                    },
                    {
                        "name": "Rita",
                        "birth_year": "1940"
                    },
                    {
                        "name": "Sten",
                        "birth_year": "1948"
                    },
                    {
                        "name": "Björn",
                        "birth_year": "1952"
                    }
                ]
            }
        },
        "2": {
            "full_name": "Knut E Serrander",
            "location": "Eskilstuna",
            "occupation": "Disponent",
            "birth_details": {
                "date": "29/05/1914",
                "place": "Torshälla"
            },
            "education": null,
            "career": [
                {
                    "position": "Besiktn :man",
                    "years": {
                        "start_year": 1941,
                        "end_year": null
                    },
                    "organization": "Carl Gustafs städs gevärstaktori"
                },
                {
                    "position": "disp Autostandard i Sörml ab",
                    "years": {
                        "start_year": 1950,
                        "end_year": null
                    },
                    "organization": null
                }
            ],
            "family": {
                "spouse": "Lalla Blomberg",
                "marriage_year": "1941",
                "children": [
                    {
                        "name": "Håkan",
                        "birth_year": "1952"
                    }
                ]
            },
            "hobbies": [
                "sjösport"
            ]
        },
        "3": {
            "full_name": "Ivar O R Seth",
            "location": "Karlstad",
            "occupation": "Rektor",
            "birth_details": {
                "date": "31/05/1910",
                "place": "Sthlm"
            },
            "education": [
                {
                    "degree": "Stud:ex",
                    "year": "1928",
                    "institution": null
                },
                {
                    "degree": "fil mag",
                    "year": "1933",
                    "institution": null
                },
                {
                    "degree": "fil lic",
                    "year": "1942",
                    "institution": null
                },
                {
                    "degree": "fil dr",
                    "year": "1952",
                    "institution": null
                }
            ],
            "career": [
                {
                    "position": "E aman",
                    "years": {
                        "start_year": 1932,
                        "end_year": null
                    },
                    "organization": "Sthlms stadsarkiv"
                },
                {
                    "position": "lär",
                    "years": {
                        "start_year": 1937,
                        "end_year": null
                    },
                    "organization": "Olofsk Sthlm"
                }
            ],
            "family": {
                "spouse": "gymn:dir Inga Thorén",
                "marriage_year": "1937",
                "children": [
                    {
                        "name": "Agneta",
                        "birth_year": "1940"
                    },
                    {
                        "name": "Barbro",
                        "birth_year": "1942"
                    },
                    {
                        "name": "Ingegerd",
                        "birth_year": "1944"
                    },
                    {
                        "name": "Torsten",
                        "birth_year": "1947"
                    }
                ]
            }
        },
        "4": {
            "full_name": "Rutger H von Seth",
            "location": "Åkers Styckebruk",
            "occupation": "Bruksägare",
            "birth_details": {
                "date": "22/12/1898",
                "place": "Hörby, Malmö"
            },
            "education": [
                {
                    "degree": "Stud:ex",
                    "year": "1917",
                    "institution": "Ystad"
                },
                {
                    "degree": null,
                    "year": "1922",
                    "institution": "KTH"
                }
            ],
            "career": [
                {
                    "position": "l:e ass",
                    "years": {
                        "start_year": 1923,
                        "end_year": null
                    },
                    "organization": "KTH:s metallurg lab"
                }
            ],
            "family": {
                "spouse": "Phyllis Donnison",
                "marriage_year": "1932",
                "children": [
                    {
                        "name": "Anne-Marie",
                        "birth_year": "1933"
                    },
                    {
                        "name": "Phyllis",
                        "birth_year": "1937"
                    }
                ]
            }
        }
    }
}