{
    "original": "SMITH, K GUSTAF H,\nläroverksadjunkt, Eskilstuna, f i Luleå 28/10/97 av\narkit K S o Tekla Hazell.\nStud:ex Skara 17, folkskollär :ex Växjö\n19, fil kand Lund 23, fil mag 23, eo\nämneslär 24, eo lär N latin Sthlm 28,\nvik adj Sthlm 30, Gävle 33, vik lekt\nfolksk:sem Växjö 34, adj i matem o fys\nhal Eskilstuna sed 37. - Timlär H tekn\nlärov Eskilstuna 39-59. - Utm: RNO.\nGift 38 m lektor Marja Engholm f 10,\ndtr t handl Carl E o Anna Larsson.\n-Barn: Ulf f 39.\n\nSMITH, A MARJA C, lektor,\nEskilstuna, f i Erikstad, Älvsb l, 24/5/10 av\nhandl Carl Engholm o Anna Larsson.\nStud:ex Upps 28, fil mag 36, fil lic StHS\n60. - Eo adj hal Eskilstuna 47, adj där\n53, lekt i eng sed 61.  - Skr: Par Ici\n(tills m a 57), Par Ici-Suite (tills m a 60).\n- Hobbies: språk, resor.\nGift 38 m lärov:adj Gustaf Smith f 97.\n-Barn: Ulf f 39.\n\nSMITH, SVERKER A, direktör, Sthlm\no Västerås, f i Sthlm 25/3/31 av grossh\nAnders S o Helga Bley.\nSigtoinask t 49, Off:ex kav 53,\nutl:-prakt Tyskl 53-54, Engl 56; anst And\nSmith Uddevalla ab 53, Västerås\nkolimport ab Västerås 56, And Smith ab\nSthlm 56, dir Sverker Smith ab sed 60.\n-Inneh o styr:led Sverker Smith ab,\nVästerås kolimport ab, K A Söderströms\nåkeri ab, ab Smith-oljor. - Medl\nNep-tuniO. - Hobbies: jakt, segling.\nGift 49-63. - Barn: Helen» f 49, Michael\nf 53.\n\nSMITTERBERG, CARL GUSTAF,\ndirektör, Arboga, f i Fårösund, Gotl l,\n12/3/00 av köpman Karl Fredrik S o\nElisabeth Löfvenberg.\nStud:ex Visby 19, KTH 25, konstr\nflottans varv Karlskrona 26, Amer Can Co\nUSA 28, Väsby bleckemballagefabr 34,\nLidkpgs mek verkst 35, ritkont:ch\nMor-gårdshammars mek verkst ab 45,\növering där 50, platsch ab Arboga mek\nverkst sed 54. - Styr:led Sv hdlsbkn\nArboga 59, styr :suppl Morgårdshammar\nmek verkst ab o ab Arboga mek verkst.\n- Hobby: segling.\n\nGift 34 m Anna-Greta Jurell f 03, dtr t\ndisp Axel J o Hanna Gustafsson. - Barn:\nLeila f 37.\n\n",
    "structured": {
        "0": {
            "full_name": "K Gustaf H Smith",
            "location": "Eskilstuna",
            "occupation": "läroverksadjunkt",
            "birth_details": {
                "date": "28/10/1897",
                "place": "Luleå",
                "parents": "arkit K S o Tekla Hazell"
            },
            "education": [
                {
                    "degree": "Stud:ex",
                    "year": "1917",
                    "institution": "Skara"
                },
                {
                    "degree": "folkskollär:ex",
                    "year": "1919",
                    "institution": "Växjö"
                },
                {
                    "degree": "filosofie kandidat",
                    "year": "1923",
                    "institution": "Lund"
                },
                {
                    "degree": "filosofie magister",
                    "year": "1923",
                    "institution": "Lund"
                }
            ],
            "career": [
                {
                    "position": "eo ämneslär",
                    "years": {
                        "start_year": 1924,
                        "end_year": 1928
                    },
                    "organization": "N latin Sthlm"
                },
                {
                    "position": "eo lär",
                    "years": {
                        "start_year": 1928,
                        "end_year": 1930
                    },
                    "organization": "Sthlm"
                }
            ],
            "family": {
                "spouse": "Marja Engholm",
                "marriage_year": "1938",
                "children": [
                    {
                        "name": "Ulf",
                        "birth_year": "1939"
                    }
                ]
            }
        },
        "1": {
            "full_name": "A Marja C Smith",
            "location": "Eskilstuna",
            "occupation": "lektor",
            "birth_details": {
                "date": "24/05/1910",
                "place": "Erikstad, Älvsb l",
                "parents": "handl Carl Engholm o Anna Larsson"
            },
            "education": [
                {
                    "degree": "Stud:ex",
                    "year": "1928",
                    "institution": "Upps"
                },
                {
                    "degree": "filosofie magister",
                    "year": "1936",
                    "institution": "StHS"
                },
                {
                    "degree": "filosofie licentiat",
                    "year": "1960",
                    "institution": "StHS"
                }
            ],
            "career": [
                {
                    "position": "eo adj",
                    "years": {
                        "start_year": 1947,
                        "end_year": 1953
                    },
                    "organization": "hal Eskilstuna"
                },
                {
                    "position": "lekt i eng",
                    "years": {
                        "start_year": 1961
                    },
                    "organization": "hal Eskilstuna"
                }
            ],
            "family": {
                "spouse": "Gustaf Smith",
                "marriage_year": "1938",
                "children": [
                    {
                        "name": "Ulf",
                        "birth_year": "1939"
                    }
                ]
            },
            "publications": [
                {
                    "title": "Par Ici"
                },
                {
                    "title": "Par Ici-Suite"
                }
            ],
            "hobbies": [
                "språk",
                "resor"
            ]
        },
        "2": {
            "full_name": "Sverker A Smith",
            "location": "Sthlm o Västerås",
            "occupation": "direktör",
            "birth_details": {
                "date": "25/03/1931",
                "place": "Sthlm",
                "parents": "grossh Anders S o Helga Bley"
            },
            "education": [
                {
                    "degree": "Sigtoinask",
                    "year": "1949"
                },
                {
                    "degree": "Off:ex kav",
                    "year": "1953"
                }
            ],
            "career": [
                {
                    "position": "anst",
                    "years": {
                        "start_year": 1953,
                        "end_year": 1954
                    },
                    "organization": "And Smith Uddevalla ab"
                },
                {
                    "position": "dir",
                    "years": {
                        "start_year": 1960
                    },
                    "organization": "Sverker Smith ab"
                }
            ],
            "family": {
                "spouse": "NULL",
                "marriage_year": "NULL",
                "children": [
                    {
                        "name": "Helen",
                        "birth_year": "1949"
                    },
                    {
                        "name": "Michael",
                        "birth_year": "1953"
                    }
                ]
            },
            "community_involvement": [
                {
                    "role": "Medl",
                    "organization": "Nep-tuniO"
                }
            ],
            "hobbies": [
                "jakt",
                "segling"
            ]
        },
        "3": {
            "full_name": "Carl Gustaf Smitterberg",
            "location": "Arboga",
            "occupation": "direktör",
            "birth_details": {
                "date": "12/03/1900",
                "place": "Fårösund, Gotl l",
                "parents": "köpman Karl Fredrik S o Elisabeth Löfvenberg"
            },
            "education": [
                {
                    "degree": "Stud:ex",
                    "year": "1919",
                    "institution": "Visby"
                }
            ],
            "career": [
                {
                    "position": "övering",
                    "years": {
                        "start_year": 1950
                    },
                    "organization": "Morgårdshammars mek verkst ab"
                }
            ],
            "family": {
                "spouse": "Anna-Greta Jurell",
                "marriage_year": "1934",
                "children": [
                    {
                        "name": "Leila",
                        "birth_year": "1937"
                    }
                ]
            },
            "hobbies": [
                "segling"
            ]
        }
    }
}