{
    "original": "MYHR, ANDERS G, tandläkare, Piteå,\nf i Karl Gustavs församl, Norrb l, 1/8/31\nav hemm:äg Karl Suo o Alma Heiskala.\nStud:ex Haparanda 51, tandl:ex Sthlm\n56, distr:tandl Älvsbyn 56-59, priv:prakt\nPiteå sed 59.\n\nGift 55 m tandl Dagny Ericson f 32.\n-Barn: Mats f 57, Svante f 60, Niklas\nf 63.\n\nMULLER, K BERTIL P, civilingenjör,\nGävle,  f  i  Oslo   2/7/23   av  konstsmed\nBernhard M o Hermine Reimer.\nCTH 47, byggn :konstr Byggn ab\nKonstruktör 47, eg konsult verksamh inom\nbyggn :teknik o ind :planer sed 52.\nGift 52 m Margit Pettersson f 24.\n\nMULLER, LENNART J L, överläkare,\n\nHudiksvall, f i Gävle 6/2/19 av konsul\nHugo M o Kristina Kilman.\nStud:ex 39, med kand 43 o med lic Upps\n50, underläk med avd Gävle las 50-56,\nläk f den kropps! åldrings- o\nlångtidsvården Södertulls sjh Gävle 56-60, bitr\növerläk o tf överläk med klin\nHudiksvalls las 60-64, bitr överläk med klin\nÖrnsköldsviks las 64-65, överläk klin f långv\nsjuka Hudiksvalls las sed 65. - Styr :led\nGästrikl läk :f ören 54-56. - Skr i inv med.\nGift 43 m Inga-Lisa Björklund f 20, dtr\nt köpm John B o Erika Källberg. - Barn:\nClaes-Håkan f 44, Jan f 45, Lars f 47,\nTomas f 49, Elisabeth f 52.\n\nMULLER, ULF A G, disponent,\nBoden, f i Luleå 14/10/32 av dir Allan M\no Judith Eriksson.\n\nDisp o deläg Bil ab A Muller Boden sed\n52. - Medl Odd Fellow, Lions club.\n-Hobby: foto.\n\nGift 56 m Astrid Gustavsson f 30, dtr t\nAlgot G o Selma G. - Barn: Susann\nf 57, Marie f 60.\n\nMYRIN, CARL ALBERT H, ingenjör,\nÖstersund, f i Dalby, Värml l, 26/4/14\nav landsfisk Albert M o Rut Heijbel.\nRealex Torsby 31, hdlssk:ex Hermods\nMalmö 32, ing:ex STI 39; mätn:tekn\nlantmät:stat Sthlms l 37, ing\nGraninge-verkens ab 41, Indalsälvens o Faxälvens\nregl :f ören upa 42, sousch Indalsälvens\nvattenregi :f öret 55, konsult ing\nKommunernas konsultbyrå-LBF sed 67. - Sekr\nSIF:s Östersundsavd 51-54, ordf 54-57,\n\nordf IVF:s o FVF:s pers:klubb 55-65,\nskattm Curlingklubben Östersund sed 58.\n\n-   Medl FrimO, Human fören, Jämtl l\ntekn fören.  - Hobbies:  konst,  curling,\nfilateli, färgfotografering.\n\nGift 38 m Gertrud Knutson f 15, dtr t\nadv Axel K o Anna Nyman. - Barn:\nGunilla f 40, Bengt f 43.\n\n",
    "structured": {
        "0": {
            "full_name": "ANDERS G MYHR",
            "location": "Piteå",
            "occupation": "tandläkare",
            "birth_details": {
                "date": "01/08/1931",
                "place": "Karl Gustavs församling, Norrbottens län"
            },
            "education": [
                {
                    "degree": "Stud:ex",
                    "year": "1951",
                    "institution": "Haparanda"
                },
                {
                    "degree": "tandl:ex",
                    "year": "1956",
                    "institution": "Sthlm"
                }
            ],
            "career": [
                {
                    "position": "distr:tandl",
                    "years": {
                        "start_year": 1956,
                        "end_year": 1959
                    },
                    "organization": "Älvsbyn"
                },
                {
                    "position": "priv:prakt Piteå",
                    "years": {
                        "start_year": 1959
                    }
                }
            ],
            "family": {
                "spouse": "Dagny Ericson",
                "marriage_year": "1955",
                "children": [
                    {
                        "name": "Mats",
                        "birth_year": "1957"
                    },
                    {
                        "name": "Svante",
                        "birth_year": "1960"
                    },
                    {
                        "name": "Niklas",
                        "birth_year": "1963"
                    }
                ]
            }
        },
        "1": {
            "full_name": "K BERTIL P MULLER",
            "location": "Gävle",
            "occupation": "civilingenjör",
            "birth_details": {
                "date": "02/07/1923",
                "place": "Oslo"
            },
            "education": [
                {
                    "degree": "CTH",
                    "year": "1947",
                    "institution": "Chalmers"
                }
            ],
            "career": [
                {
                    "position": "Konstruktör",
                    "years": {
                        "start_year": 1947
                    },
                    "organization": "Byggn ab"
                },
                {
                    "position": "konsult verksam",
                    "years": {
                        "start_year": 1952
                    }
                }
            ],
            "family": {
                "spouse": "Margit Pettersson",
                "marriage_year": "1952"
            }
        },
        "2": {
            "full_name": "LENNART J L MULLER",
            "location": "Hudiksvall",
            "occupation": "överläkare",
            "birth_details": {
                "date": "06/02/1919",
                "place": "Gävle"
            },
            "education": [
                {
                    "degree": "Stud:ex",
                    "year": "1939"
                },
                {
                    "degree": "med kand",
                    "year": "1943",
                    "institution": "Upps"
                },
                {
                    "degree": "med lic",
                    "year": "1950"
                }
            ],
            "career": [
                {
                    "position": "underläk",
                    "years": {
                        "start_year": 1950,
                        "end_year": 1956
                    },
                    "organization": "Gävle las"
                },
                {
                    "position": "bitr överläk",
                    "years": {
                        "start_year": 1956,
                        "end_year": 1960
                    },
                    "organization": "Södertulls sjh Gävle"
                },
                {
                    "position": "bitr överläk",
                    "years": {
                        "start_year": 1964,
                        "end_year": 1965
                    },
                    "organization": "Örnsköldsviks las"
                },
                {
                    "position": "överläk",
                    "years": {
                        "start_year": 1965
                    },
                    "organization": "Hudiksvalls las"
                }
            ],
            "family": {
                "spouse": "Inga-Lisa Björklund",
                "marriage_year": "1943",
                "children": [
                    {
                        "name": "Claes-Håkan",
                        "birth_year": "1944"
                    },
                    {
                        "name": "Jan",
                        "birth_year": "1945"
                    },
                    {
                        "name": "Lars",
                        "birth_year": "1947"
                    },
                    {
                        "name": "Tomas",
                        "birth_year": "1949"
                    },
                    {
                        "name": "Elisabeth",
                        "birth_year": "1952"
                    }
                ]
            }
        },
        "3": {
            "full_name": "ULF A G MULLER",
            "location": "Boden",
            "occupation": "disponent",
            "birth_details": {
                "date": "14/10/1932",
                "place": "Luleå"
            },
            "career": [
                {
                    "position": "Disp o deläg Bil ab A Muller",
                    "years": {
                        "start_year": 1952
                    }
                }
            ],
            "family": {
                "spouse": "Astrid Gustavsson",
                "marriage_year": "1956",
                "children": [
                    {
                        "name": "Susann",
                        "birth_year": "1957"
                    },
                    {
                        "name": "Marie",
                        "birth_year": "1960"
                    }
                ]
            },
            "hobbies": [
                "foto"
            ]
        },
        "4": {
            "full_name": "CARL ALBERT H MYRIN",
            "location": "Östersund",
            "occupation": "ingenjör",
            "birth_details": {
                "date": "26/04/1914",
                "place": "Dalby, Värmlands län"
            },
            "education": [
                {
                    "degree": "Realex",
                    "year": "1931",
                    "institution": "Torsby"
                },
                {
                    "degree": "hdlssk:ex",
                    "year": "1932",
                    "institution": "Hermods, Malmö"
                },
                {
                    "degree": "ing:ex",
                    "year": "1939",
                    "institution": "STI"
                }
            ],
            "career": [
                {
                    "position": "mätn:tekn",
                    "years": {
                        "start_year": 1937
                    },
                    "organization": "lantmät:stat Sthlms l"
                },
                {
                    "position": "ing",
                    "years": {
                        "start_year": 1941
                    },
                    "organization": "Graninge-verkens ab"
                },
                {
                    "position": "sousch",
                    "years": {
                        "start_year": 1955
                    },
                    "organization": "Indalsälvens vattenregi :f öret"
                },
                {
                    "position": "konsult ing",
                    "years": {
                        "start_year": 1967
                    },
                    "organization": "Kommunernas konsultbyrå-LBF"
                }
            ],
            "family": {
                "spouse": "Gertrud Knutson",
                "marriage_year": "1938",
                "children": [
                    {
                        "name": "Gunilla",
                        "birth_year": "1940"
                    },
                    {
                        "name": "Bengt",
                        "birth_year": "1943"
                    }
                ]
            },
            "community_involvement": [
                {
                    "role": "ordf",
                    "organization": "IVF:s o FVF:s pers:klubb",
                    "years": "1955-1965"
                }
            ],
            "board_memberships": [
                {
                    "position": "ordf",
                    "organization": "SIF:s Östersundsavd",
                    "years": "1954-1957"
                }
            ],
            "hobbies": [
                "konst",
                "curling",
                "filateli",
                "färgfotografering"
            ]
        }
    }
}