{
    "original": "MALMSTIGEN, E OLOF, disponent,\n\nUmeå, f i Örebro 28/11/21 av kont Eric\nPehrson o Hilda Fisk.\n\nStud:ex 40, Örebro hdlsgymn 43, stud\nHHS 43-44, kamr Ostkustfisk\ncentral-fören upa Sthlm 45, försäljn:ch ab\nLaxen fiskredsk:fabr Umeå 50, disp o\nverkst dir där sed 58. - Styr:led\nUmeå-avd av Sv:es företag riksförb (SFR) sed\n64. - Medl Odd Fellow. - Hobbies: fiske,\nbridge.\n\nGift 45 m Gertie Kolmodin, dtr t köpm\nEinar K o Berta Larsson. - Barn:\nJan-Erik f 45, Marianne f 48.\n\nMALMSTRÖM, ERIK G,\nmusikdirektör, Gävle, f i Folkärna, Kopparb l, 6/3/\n10 av disp Ivar M o Karin Jonsson.\nH org:ex 33, h kant:- o musiklär:ex\nKMH 35, musiklär Avesta samrealsk\n36-44 o Hedemora samrealsk 37-42, Luleå\nhal 44-45, hal Ystad 45-47, Linkpgs\nfolksk :sem 47-49, ord musiklär Gävle\nfolk-sk:sem sed 49. - Utm: Bergs jeton.\n-Hobby: matematik.\n\nGift 46 m ämneslär Birgit Fischer f 14,\ndtr t tandl Sven F o Elsa Fogelberg.\n-Barn: Ann-Katrin f 47, Elsa f 50.\n\nMALMSTRÖM, E LENNART,\nkyrkoherde, Muodoslompolo, f i Malmö 25/3/\n30 av lokför John M o Anna Månsson.\nStud:ex 50, teol kand Lund 57, past:adj\nPajala  58,  v  kommin  Muodoslompolo\n58, kommin 59, kyrkoh Muonionalusta\nsed 62. -Kapt T 3 res.\nGift 54 m Berit Sandström, dtr t\nborst-bind John S o Ruth Dahlbäck. - Barn:\nJohan f 55, Lars f 57, Anna f 60.\n\nMALMSTRÖM, RAGNAR A, fd\nrektor, Kiruna, f i Luleå 3/2/98 av byggm\nAxel M o Anna Åkerström.\nFolkskollär:ex 19, folkskollär Kiruna 19,\növerlär o rekt där 50-64 (bitr 45). -\nStyr:-ordf ab Malmfältens kraftverk sed 56,\nab Kirunabost sed 57, Stift\nSvappavaara-hus sed 63. - Ordf Norrb l landst sed\n56 (led 45), led länsbost:ndn sed 63, ordf\nKiruna Stadsfullm 48-51 o 63-66, DK\n52-63. - Medl Rotary. - Utm: Kiruna\nstads ftJM, LinnéM, STF Splak.\nGift m Hildur Fridh, dtr t förrn J K F\no Matilda Sundqvist.\n\n",
    "structured": {
        "1": {
            "full_name": "E OLOF MALMSTIGEN",
            "location": "Umeå",
            "occupation": "Disponent",
            "birth_details": {
                "date": "28/11/1921",
                "place": "Örebro"
            },
            "education": [
                {
                    "degree": "Stud:ex",
                    "year": "1940",
                    "institution": "Örebro hdlsgymn"
                },
                {
                    "degree": "HHS",
                    "year": "1943-1944",
                    "institution": "Stud, kamr Ostkustfisk central-fören upa Sthlm"
                }
            ],
            "career": [
                {
                    "position": "Försäljn:ch",
                    "years": {
                        "start_year": 1945,
                        "end_year": 50
                    },
                    "organization": "ab Laxen fiskredsk:fabr Umeå"
                },
                {
                    "position": "Disp o verkst dir",
                    "years": {
                        "start_year": 1958,
                        "end_year": null
                    },
                    "organization": "ab Laxen fiskredsk:fabr Umeå"
                },
                {
                    "position": "Styr:led Umeå-avd",
                    "years": {
                        "start_year": 1964,
                        "end_year": null
                    },
                    "organization": "Sv:es företag riksförb (SFR)"
                }
            ],
            "family": {
                "spouse": "Gertie Kolmodin",
                "marriage_year": "45",
                "children": [
                    {
                        "name": "Jan-Erik",
                        "birth_year": "1945"
                    },
                    {
                        "name": "Marianne",
                        "birth_year": "1948"
                    }
                ]
            },
            "hobbies": [
                "fiske",
                "bridge"
            ]
        },
        "2": {
            "full_name": "ERIK G MALMSTRÖM",
            "location": "Gävle",
            "occupation": "Musikdirektör",
            "birth_details": {
                "date": "6/3/1910",
                "place": "Folkärna, Kopparb l"
            },
            "education": [
                {
                    "degree": "H org:ex",
                    "year": "1933",
                    "institution": "KMH"
                },
                {
                    "degree": "H kant:- o musiklär:ex",
                    "year": "1935",
                    "institution": "Avesta samrealsk"
                }
            ],
            "career": [
                {
                    "position": "Ord musiklär",
                    "years": {
                        "start_year": 1949,
                        "end_year": null
                    },
                    "organization": "Gävle folk-sk:sem"
                }
            ],
            "family": {
                "spouse": "Birgit Fischer",
                "marriage_year": "46",
                "children": [
                    {
                        "name": "Ann-Katrin",
                        "birth_year": "1947"
                    },
                    {
                        "name": "Elsa",
                        "birth_year": "1950"
                    }
                ]
            },
            "hobbies": [
                "matematik"
            ]
        },
        "3": {
            "full_name": "E LENNART MALMSTRÖM",
            "location": "Muodoslompolo",
            "occupation": "Kyrkoherde",
            "birth_details": {
                "date": "25/3/1930",
                "place": "Malmö"
            },
            "education": [
                {
                    "degree": "Stud:ex",
                    "year": "1950",
                    "institution": "teol kand Lund"
                }
            ],
            "career": [
                {
                    "position": "V kommin",
                    "years": {
                        "start_year": 1959,
                        "end_year": null
                    },
                    "organization": "Muodoslompolo"
                },
                {
                    "position": "Kyrkoh",
                    "years": {
                        "start_year": 1962,
                        "end_year": null
                    },
                    "organization": "Muonionalusta"
                }
            ],
            "family": {
                "spouse": "Berit Sandström",
                "marriage_year": "54",
                "children": [
                    {
                        "name": "Johan",
                        "birth_year": "1955"
                    },
                    {
                        "name": "Lars",
                        "birth_year": "1957"
                    },
                    {
                        "name": "Anna",
                        "birth_year": "1960"
                    }
                ]
            }
        },
        "4": {
            "full_name": "RAGNAR A MALMSTRÖM",
            "location": "Kiruna",
            "occupation": "Fd rektor",
            "birth_details": {
                "date": "3/2/1898",
                "place": "Luleå"
            },
            "career": [
                {
                    "position": "Överlär o rekt",
                    "years": {
                        "start_year": 1950,
                        "end_year": 1964
                    },
                    "organization": "Kiruna"
                }
            ],
            "family": {
                "spouse": "Hildur Fridh",
                "marriage_year": "NULL"
            }
        }
    }
}