{
    "original": "KALLSTENIUS, JOHN G A,\nadvokat, Sthlm, f i Paris 25/8/92 av prof\nGottfrid K o Gerda Roosval.\nStudrex Sthlm 12, jur kand Sthlm 17,\neo not Svea hovr 17, tingsbitr S\nRoslags doms 17-18, anst E Berglunds\nadv:-byrå 18, deläg 40, LSA 20. - Styr:led\nSA:s Sthlmsavd 31-44, ab Sleipner,\nPfizer ab, Columbia Film ab, United\nArtists ab m fi. - Skr: upps i SvJT.\n-Utm: RVO.\n\nGift 18 m Inga Ternström f 94, dtr t\nsjökapten John T o Pauline Olsson.\n-Barn: Ann-Marie f 19.\n\nKALLSTENIUS, LENNART G,\njägmästare, Danderyd, f i Flädie, Malmöh\nl, 14/5/12 av tonsättare Edvin K o\nCharlotte Brandt.\n\nSkHS 38, anst domänverket sed 38.\n-Byråch stat bränslekommiss 50-53,\njäg-mäst o ch skogliga sekt lantbrrstyr sed\n53. - Skr: Lärobok i skogsuppskattning\no skogsindelning, art i fackpress. -\nHobbies: musik, fotografering, segling.\nGift 48 m Ulla Lindgren f 26, dtr t\nverkmäst Anders L o Karin Lindgren.\n-Barn: Ove f 40, Arne f 43, Ulf f 58,\nSven f 61.\n\nKALLSTENIUS, TORSTEN K E,\ntekn lic, avdelningschef, Lidingö, f i\nLund 12/8/10 av tonsätt Edvin K o\nCharlotte Brandt.\n\nStudiex Djursholm 30, KTH 36, tekn\nlic KTH 61. - Res:off:ex 33. - Anst\nMerkantila ingibyrån Sthlm 36, ab\nRosenblads patenter 37-40, ab\nBofors-Nobelkrut 41-45, avdrch stat geotekn inst\nsed 45. - Medl Sv geotekn fören, sekr\ndess kolvborr komm o sonderingskomm\n58, medl Sv fören f lerforskn, Geol\nfören, Sv nät :fören f mekanik. - Skr: div\npubl i fackämnen. - Utm: IVAGM.\n-Hobbies: fotografering, segling, musik.\nGift 37 m Ingrid Tynelius f 08, dtr\nt postmast Gustaf T o Elin T. - Barn:\nBjörn f 39, Susanne f 42, Per f 44,\nJohan f 50.\n\n",
    "structured": {
        "0": {
            "full_name": "KALLSTENIUS, JOHN G A",
            "location": "Sthlm",
            "occupation": "advokat",
            "birth_details": {
                "date": "25/08/1892",
                "place": "Paris"
            },
            "education": [
                {
                    "degree": "Studrex",
                    "year": "1912",
                    "institution": "Sthlm"
                },
                {
                    "degree": "jur kand",
                    "year": "1917",
                    "institution": "Sthlm"
                },
                {
                    "degree": "eo not",
                    "year": "1917",
                    "institution": "Svea hovr"
                }
            ],
            "career": [
                {
                    "position": "tingsbitr",
                    "years": {
                        "start_year": 1917,
                        "end_year": 1918
                    },
                    "organization": "Roslags doms"
                },
                {
                    "position": "anst E Berglunds adv:-byrå",
                    "years": {
                        "start_year": 1918,
                        "end_year": null
                    },
                    "organization": null
                }
            ],
            "family": {
                "spouse": "Inga Ternström",
                "marriage_year": "1918",
                "children": [
                    {
                        "name": "Ann-Marie",
                        "birth_year": "1919"
                    }
                ]
            }
        },
        "1": {
            "full_name": "KALLSTENIUS, LENNART G",
            "location": "Danderyd",
            "occupation": "jägmästare",
            "birth_details": {
                "date": "14/05/1912",
                "place": "Flädie, Malmö"
            },
            "education": [
                {
                    "degree": "SkHS",
                    "year": "1938",
                    "institution": null
                }
            ],
            "career": [
                {
                    "position": "anst domänverket",
                    "years": {
                        "start_year": 1938,
                        "end_year": null
                    },
                    "organization": null
                }
            ],
            "family": {
                "spouse": "Ulla Lindgren",
                "marriage_year": "1948",
                "children": [
                    {
                        "name": "Ove",
                        "birth_year": "1940"
                    },
                    {
                        "name": "Arne",
                        "birth_year": "1943"
                    },
                    {
                        "name": "Ulf",
                        "birth_year": "1958"
                    },
                    {
                        "name": "Sven",
                        "birth_year": "1961"
                    }
                ]
            },
            "hobbies": [
                "musik",
                "fotografering",
                "segling"
            ]
        },
        "2": {
            "full_name": "KALLSTENIUS, TORSTEN K E",
            "location": "Lidingö",
            "occupation": "tekn lic, avdelningschef",
            "birth_details": {
                "date": "12/08/1910",
                "place": "Lund"
            },
            "education": [
                {
                    "degree": "Studiex",
                    "year": "1930",
                    "institution": "Djursholm"
                },
                {
                    "degree": "KTH",
                    "year": "1936",
                    "institution": null
                },
                {
                    "degree": "tekn lic",
                    "year": "1961",
                    "institution": "KTH"
                }
            ],
            "career": [
                {
                    "position": "Res:off:ex",
                    "years": {
                        "start_year": 1933,
                        "end_year": null
                    },
                    "organization": null
                },
                {
                    "position": "anst Merkantila ingibyrån Sthlm",
                    "years": {
                        "start_year": 1936,
                        "end_year": 1937
                    },
                    "organization": null
                },
                {
                    "position": "ab Rosenblads patenter",
                    "years": {
                        "start_year": 1937,
                        "end_year": 1940
                    },
                    "organization": null
                },
                {
                    "position": "ab Bofors-Nobelkrut",
                    "years": {
                        "start_year": 1941,
                        "end_year": 1945
                    },
                    "organization": null
                },
                {
                    "position": "avdrch stat geotekn inst",
                    "years": {
                        "start_year": 1945,
                        "end_year": null
                    },
                    "organization": null
                }
            ],
            "family": {
                "spouse": "Ingrid Tynelius",
                "marriage_year": "1937",
                "children": [
                    {
                        "name": "Björn",
                        "birth_year": "1939"
                    },
                    {
                        "name": "Susanne",
                        "birth_year": "1942"
                    },
                    {
                        "name": "Per",
                        "birth_year": "1944"
                    },
                    {
                        "name": "Johan",
                        "birth_year": "1950"
                    }
                ]
            },
            "hobbies": [
                "fotografering",
                "segling",
                "musik"
            ]
        }
    }
}