{
    "original": "KÖHLER, C RUNE, civilekonom,\nSolna, f i Sthlm 291W124 av vagnmäst\nCarl J K o Magnhild Thelin.\nDHS 49, kamrer ab Gunnar Collijn\nSthlm 49-52, organisatör o försälj\nLME:s driftkontroll ab 53-56, ekonich\nKungsörnen ab sed 56. - Hobbies: fiske,\nskytte, konst, litteratur.\nGift 49-51 m Barbro Arnestrand f 24,\ndtr t Gustav A o Karin Schmeling.\n-Barn: Elisabet f 50.\n\nKÖHLER, SVEN V, civilingenjör,\nBromma, f i Sthlm 8/7/10 av dir Bruno\nK o Ada Ahnström.\nStudrex 29, KTH 35, försäljning ab\nBolinder-Munktell Eskilstuna 36-44,\nLissabon 37-41, ab Atlas-Diesel Sthlm\n44-48, branding Svea-Nornan sed 48. - Led\nSvTF.\n\nGift 43 m Inga-Britta Larsson f 14,\ndtr t Jöns L o Siri Göransson. - Barn:\nElisabet f 44, Cecilia f 46.\n\nKÖHLER, URBAN C O, leg läkare,\nJohanneshov, f i Sthlm 9/3/26 av disp\nLars K o Brita Åhrberg.\nMed   lic   Sthlm   55,   vik   l:e   underläk\nöronavd Södersjh, underläk kir avd\nSödertälje las,  vik   l:e underläk  öronavd\nSödersjh  sed  57.   -   Bat:läk i Flk res\nsed 56.\nGift 57 m Birgit Hulphers.\n\nKÖHLMARK BO R, byrådirektör,\nBromma, f i Sthlm 16/9/20 av\nfolkskol-lär Ruben K o Gretchen Feldreich.\nStud:ex 38, KTH 42, ing\nvattenbyggnr-byr 42-43, SJ 43-45, stot vattenfrverk\n45-49, flygförvaltn 49-52, byrådir\nluft-fartsstyr sed 52. - Led 56 års\nflygbuller-utredn. - Skr: upps rör beläggnrfrågor o\nflygplatsbyggn bl a i fackpress.\nGift 46 m Eva Trägårdh f 24, dtr t\növering Kurt T o Margit von Heijne.\n-Barn: Mats f 48, Anders f 51, Kristina\nf 53.\n\nKÖKERITZ, S W ELISABET,\nredaktör, Johanneshov, f i Ystad 25/5/13 av\nstatskartograf Einar Peterson-Berger o\nMathilda Ammitzböll.\nStudrex Saltsjöbaden 32, konststud\nFrankr 34-35, anst Sthlms städs\narbr-förmedl 40, Gävle stads bostadsförmedl\n46, Eskilstuna-Kuriren 49, red o ansv\nutg Tidskr f Sv:es sjuksköterskor sed\n\n50. - Skr: Sjukvårdande yrken (60).\nGift 44-49 m  Olov Kökeritz.  -  Barn:\nCatharina f 45, Wilhelm f 48.\n",
    "structured": {
        "1": {
            "full_name": "C Rune Köhler",
            "location": "Solna",
            "occupation": "civilekonom",
            "birth_details": {
                "date": "29/12/1929",
                "place": "Stockholm",
                "parents": "vagnmäst Carl J K and Magnhild Thelin"
            },
            "education": [
                {
                    "degree": "DHS",
                    "year": "1949",
                    "institution": "NULL"
                }
            ],
            "career": [
                {
                    "position": "kamrer",
                    "years": {
                        "start_year": 1949,
                        "end_year": 1952
                    },
                    "organization": "ab Gunnar Collijn Sthlm"
                },
                {
                    "position": "organisatör o försälj",
                    "years": {
                        "start_year": 1953,
                        "end_year": 1956
                    },
                    "organization": "LME:s driftkontroll ab"
                },
                {
                    "position": "ekonich",
                    "years": {
                        "start_year": 1956,
                        "end_year": "NULL"
                    },
                    "organization": "Kungsörnen ab"
                }
            ],
            "family": {
                "spouse": "Barbro Arnestrand",
                "marriage_year": "1949",
                "children": [
                    {
                        "name": "Elisabet",
                        "birth_year": "1950"
                    }
                ]
            },
            "hobbies": [
                "fiske",
                "skytte",
                "konst",
                "litteratur"
            ]
        },
        "2": {
            "full_name": "Sven V Köhler",
            "location": "Bromma",
            "occupation": "civilingenjör",
            "birth_details": {
                "date": "8/7/1910",
                "place": "Stockholm",
                "parents": "dir Bruno K and Ada Ahnström"
            },
            "education": [
                {
                    "degree": "Studrex",
                    "year": "1929",
                    "institution": "NULL"
                },
                {
                    "degree": "KTH",
                    "year": "1935",
                    "institution": "NULL"
                }
            ],
            "career": [
                {
                    "position": "försäljning",
                    "years": {
                        "start_year": 1936,
                        "end_year": 1944
                    },
                    "organization": "ab Bolinder-Munktell Eskilstuna"
                },
                {
                    "position": "Lissabon",
                    "years": {
                        "start_year": 1937,
                        "end_year": 1941
                    },
                    "organization": "ab Atlas-Diesel Sthlm"
                },
                {
                    "position": "branding",
                    "years": {
                        "start_year": 1948,
                        "end_year": "NULL"
                    },
                    "organization": "Svea-Nornan"
                }
            ],
            "family": {
                "spouse": "Inga-Britta Larsson",
                "marriage_year": "1943",
                "children": [
                    {
                        "name": "Elisabet",
                        "birth_year": "1944"
                    },
                    {
                        "name": "Cecilia",
                        "birth_year": "1946"
                    }
                ]
            }
        },
        "3": {
            "full_name": "Urban C O Köhler",
            "location": "Johanneshov",
            "occupation": "leg läkare",
            "birth_details": {
                "date": "9/3/1926",
                "place": "Stockholm",
                "parents": "disp Lars K and Brita Åhrberg"
            },
            "education": [
                {
                    "degree": "Med lic",
                    "year": "1955",
                    "institution": "Sthlm"
                }
            ],
            "career": [
                {
                    "position": "vik l:e underläk",
                    "years": {
                        "start_year": "NULL",
                        "end_year": "NULL"
                    },
                    "organization": "öronavd Södersjh"
                },
                {
                    "position": "underläk kir avd",
                    "years": {
                        "start_year": "NULL",
                        "end_year": "NULL"
                    },
                    "organization": "Södertälje las"
                },
                {
                    "position": "vik l:e underläk  öronavd",
                    "years": {
                        "start_year": 1957,
                        "end_year": "NULL"
                    },
                    "organization": "Södersjh"
                },
                {
                    "position": "Bat:läk i Flk res",
                    "years": {
                        "start_year": 1956,
                        "end_year": "NULL"
                    },
                    "organization": "NULL"
                }
            ],
            "family": {
                "spouse": "Birgit Hulphers",
                "marriage_year": "1957",
                "children": []
            }
        },
        "4": {
            "full_name": "Bo R Köhlmark",
            "location": "Bromma",
            "occupation": "byrådirektör",
            "birth_details": {
                "date": "16/9/1920",
                "place": "Stockholm",
                "parents": "folkskol-lär Ruben K o Gretchen Feldreich"
            },
            "education": [
                {
                    "degree": "Stud:ex",
                    "year": "1938",
                    "institution": "NULL"
                },
                {
                    "degree": "KTH",
                    "year": "1942",
                    "institution": "NULL"
                }
            ],
            "career": [
                {
                    "position": "ing vattenbyggnr-byr",
                    "years": {
                        "start_year": 1942,
                        "end_year": 1943
                    },
                    "organization": "NULL"
                },
                {
                    "position": "SJ",
                    "years": {
                        "start_year": 1943,
                        "end_year": 1945
                    },
                    "organization": "NULL"
                },
                {
                    "position": "stot vattenfrverk",
                    "years": {
                        "start_year": 1945,
                        "end_year": 1949
                    },
                    "organization": "NULL"
                },
                {
                    "position": "flygförvaltn",
                    "years": {
                        "start_year": 1949,
                        "end_year": 1952
                    },
                    "organization": "NULL"
                },
                {
                    "position": "byrådir luft-fartsstyr",
                    "years": {
                        "start_year": 1952,
                        "end_year": "NULL"
                    },
                    "organization": "NULL"
                }
            ],
            "family": {
                "spouse": "Eva Trägårdh",
                "marriage_year": "1946",
                "children": [
                    {
                        "name": "Mats",
                        "birth_year": "1948"
                    },
                    {
                        "name": "Anders",
                        "birth_year": "1951"
                    },
                    {
                        "name": "Kristina",
                        "birth_year": "1953"
                    }
                ]
            }
        },
        "5": {
            "full_name": "S W Elisabet Kökeritz",
            "location": "Johanneshov",
            "occupation": "redaktör",
            "birth_details": {
                "date": "25/5/1913",
                "place": "Ystad",
                "parents": "statskartograf Einar Peterson-Berger o Mathilda Ammitzböll"
            },
            "education": [
                {
                    "degree": "Studrex",
                    "year": "NULL",
                    "institution": "Saltsjöbaden"
                }
            ],
            "career": [
                {
                    "position": "anst Sthlms städs arbr-förmedl",
                    "years": {
                        "start_year": 1940,
                        "end_year": 1946
                    },
                    "organization": "NULL"
                },
                {
                    "position": "Gävle stads bostadsförmedl",
                    "years": {
                        "start_year": 1946,
                        "end_year": 1949
                    },
                    "organization": "NULL"
                },
                {
                    "position": "red o ansv utg Tidskr f Sv:es sjuksköterskor",
                    "years": {
                        "start_year": 1950,
                        "end_year": "NULL"
                    },
                    "organization": "NULL"
                }
            ],
            "family": {
                "spouse": "Olov Kökeritz",
                "marriage_year": "1944",
                "children": [
                    {
                        "name": "Catharina",
                        "birth_year": "1945"
                    },
                    {
                        "name": "Wilhelm",
                        "birth_year": "1948"
                    }
                ]
            }
        }
    }
}