{
    "original": "KmstkSO, RNO, RVO, SVKGM,\nHv-GM, CFBSM, KDDO2gr, KNS:tOO,\nFFrK3klmsv, OffTyskÖO, ChX:sFrM\nNFrK.\nGift 33 m Anna Wetterling f 98, dtr t\n\nfabr Sven W o Ida Högström. - Barn:\nBritta f 35.\n\nKRISTENSEN, HANS T,\ncivilingenjör, Vällingby, f i Kalundborg, Danm,\n23/12/21 av pastor Anders K o\nHarriet Jensen.\n\nStud:ex Ribe 40, Danm tekn höjsk 45,\nforsknring lab f hydraulik Danm tekn\nhöjsk 45, ing ab Vattenbyggn: byrån\nSthlm 51, konsult ing där sed 60. - Medl\nInternat Assoc for hydraulic Research\n48, SKIF 60. - Utg: medarb Applied\nMechanics Reviews sed 48. - Hobbies:\nfotografering, hortikultur.\nGift 46 m Elise Boas f 20, dtr t\nrektor Sophus B o Herdis Jensen.\n\nKRISTENSSON, ASTRID M,\nombudsman, Sthlm, f i Sthlm 7/1/17 av häradsh\nBjörn Zetterstrand o Lisa Björkman.\nStud:ex Västerås 36, jur kand 51,\nomb:-man Sv barnmorskeförb sed 51, Sv\nekonomiföreståndarinn’ors fören sed 54,\nLeg sjukgymnasters riksförb sed 61.\n-AK (h) sed 58.\n\nGift 42 m ombiman jur kand Rune\nKristensson-. - Barn: Ulla f 43, Inger\nf 47, Ragnar f 49, Rolf f 52.\n\nKRISTENSON, N H BÖRJE,\ncivilingenjör, Sthlm, f i Västra Alstad,\nMalmöh l, 12/8/09.\n\nTekn gymn Malmö 29, KTH 34, anst\nvid flygstyr 34-36, inneh ab\nKristenson &amp; Grähs Sthlm sed 40. - LSvTF.\n\nKRISTENSSON, FOLKE, professor,\nSthlm, f i Malmö 25/5/14 av köpman\nC O K o Valborg Andrén.\nDHS 34, ekon lic, ekon dr o doc i\nföretagsekon HHS 46; stud USA 36-37;\nbefattn hdl o ind 37-43, dinass MAB o\nMYA 45-47, ch FFI 47-55, prof sed 49,\nkonsult ekonom sed 47. - Visit prof Univ\nof California Berkeley 54. - Skr: Stud\ni sv textila industrins struktur (drsavh\n46), Postorder - företagsekon stud över\nen distributionsform (49); upps i ekon\nfrågor. - Utm: RNO.\nGift 42 m Britta Björnström f 18, dtr\nt optiker Ernst B o Hildur Dahlén.\n-Barn: Ann f 44, Kaj f 46.\n\n",
    "structured": {
        "1": {
            "full_name": "KRISTENSEN, HANS T",
            "location": "Vällingby",
            "occupation": "Civilingenjör",
            "birth_details": {
                "date": "23/12/1921",
                "place": "Kalundborg, Danmark"
            },
            "education": [
                {
                    "degree": "Stud:ex Ribe",
                    "year": "1940",
                    "institution": "Danmark"
                },
                {
                    "degree": "Danm tekn höjsk",
                    "year": "1945",
                    "institution": "Danmark"
                }
            ],
            "career": [
                {
                    "position": "forsknring lab f hydraulik Danm tekn höjsk",
                    "years": {
                        "start_year": 1945,
                        "end_year": 1945
                    },
                    "organization": "Danmark"
                },
                {
                    "position": "ing ab Vattenbyggn: byrån",
                    "years": {
                        "start_year": 1951,
                        "end_year": 1960
                    },
                    "organization": "Sthlm"
                }
            ],
            "family": {
                "spouse": "Elise Boas",
                "marriage_year": "1946",
                "children": [
                    {
                        "name": "Britta",
                        "birth_year": "1935"
                    }
                ]
            }
        },
        "2": {
            "full_name": "KRISTENSSON, ASTRID M",
            "location": "Sthlm",
            "occupation": "Ombudsman",
            "birth_details": {
                "date": "7/1/1917",
                "place": "Sthlm"
            },
            "education": [
                {
                    "degree": "Stud:ex Västerås",
                    "year": "1936",
                    "institution": "Västerås"
                },
                {
                    "degree": "jur kand",
                    "year": "1951",
                    "institution": "NULL"
                }
            ],
            "career": [
                {
                    "position": "omb:-man Sv barnmorskeförb",
                    "years": {
                        "start_year": 1951,
                        "end_year": null
                    },
                    "organization": "NULL"
                },
                {
                    "position": "Sv ekonomiföreståndarinn’ors fören",
                    "years": {
                        "start_year": 1954,
                        "end_year": null
                    },
                    "organization": "NULL"
                },
                {
                    "position": "Leg sjukgymnasters riksförb",
                    "years": {
                        "start_year": 1961,
                        "end_year": null
                    },
                    "organization": "NULL"
                }
            ],
            "family": {
                "spouse": "Rune Kristensson",
                "marriage_year": "1942",
                "children": [
                    {
                        "name": "Ulla",
                        "birth_year": "1943"
                    },
                    {
                        "name": "Inger",
                        "birth_year": "1947"
                    },
                    {
                        "name": "Ragnar",
                        "birth_year": "1949"
                    },
                    {
                        "name": "Rolf",
                        "birth_year": "1952"
                    }
                ]
            }
        },
        "3": {
            "full_name": "KRISTENSON, N H BÖRJE",
            "location": "Sthlm",
            "occupation": "Civilingenjör",
            "birth_details": {
                "date": "12/8/1909",
                "place": "Västra Alstad, Malmö"
            },
            "education": [
                {
                    "degree": "Tekn gymn Malmö",
                    "year": "1929",
                    "institution": "Malmö"
                },
                {
                    "degree": "KTH",
                    "year": "1934",
                    "institution": "NULL"
                }
            ],
            "career": [
                {
                    "position": "anst vid flygstyr",
                    "years": {
                        "start_year": 1934,
                        "end_year": 1936
                    },
                    "organization": "NULL"
                },
                {
                    "position": "inneh ab Kristenson & Grähs Sthlm",
                    "years": {
                        "start_year": 1940,
                        "end_year": null
                    },
                    "organization": "NULL"
                }
            ],
            "family": {
                "spouse": "NULL",
                "marriage_year": "NULL",
                "children": []
            }
        },
        "4": {
            "full_name": "KRISTENSSON, FOLKE",
            "location": "Sthlm",
            "occupation": "Professor",
            "birth_details": {
                "date": "25/5/1914",
                "place": "Malmö"
            },
            "education": [
                {
                    "degree": "DHS",
                    "year": "1934",
                    "institution": "NULL"
                },
                {
                    "degree": "ekon lic, ekon dr o doc i företagsekon HHS",
                    "year": "1946",
                    "institution": "HHS"
                }
            ],
            "career": [
                {
                    "position": "befattn hdl o ind",
                    "years": {
                        "start_year": 1937,
                        "end_year": 1943
                    },
                    "organization": "NULL"
                },
                {
                    "position": "dinass MAB o MYA",
                    "years": {
                        "start_year": 1945,
                        "end_year": 1947
                    },
                    "organization": "NULL"
                },
                {
                    "position": "ch FFI",
                    "years": {
                        "start_year": 1947,
                        "end_year": 1955
                    },
                    "organization": "NULL"
                },
                {
                    "position": "prof",
                    "years": {
                        "start_year": 1949,
                        "end_year": null
                    },
                    "organization": "NULL"
                },
                {
                    "position": "konsult ekonom",
                    "years": {
                        "start_year": 1947,
                        "end_year": null
                    },
                    "organization": "NULL"
                }
            ],
            "family": {
                "spouse": "Britta Björnström",
                "marriage_year": "1942",
                "children": [
                    {
                        "name": "Ann",
                        "birth_year": "1944"
                    },
                    {
                        "name": "Kaj",
                        "birth_year": "1946"
                    }
                ]
            }
        }
    }
}