{
    "original": "KNSitOO, KSpCfO, OffBKrO, Off\nUngFO.\n\nGift 22 m Gunny Jepson f 93, dtr t\nhandl Gunnar J o Anna J.\n\nKASTLUND, P ÅKE, pastor, Lidingö,\nf i Avesta 22/2/16 av disp Bernhard K\no Ester Holmberg.\n\nStudiex Västerås 36, teol kand Upps\n43, kyrkoadj Västerås domkyrkoförs\n46, tjg Lutherska världsförb N Syd^\namerika, Centralamerika o Mexico\n52-56, direktor Lutherska världsförb sv\nsekt sed 56. - Led Lutherska världsförb\nkomm f Latinamerika sed 57, deleg fi\nkyrkl världskonf, utg tidskr\nLutherhjäb-pen sed 56. - Skr: Utpost i Incaland\n(56).\n\nGift 44 m Dagmar Larsson f 20, dtr t\npolisman David L o Emma Söderström.\n- Barn: Birgitta f 45, Inger f 46, Bo\nf 47, Christina f 54.\n\nKASTMAN, M M (GRETA), rektor,\nSthlm, f i Ovansjö, Gävleb l, 15/6/01 av\nmed lic Karl K o Maria K.\nAteneums skolkökssem 20-21,\nfortbildni-kurser Svie, lär Ateneums skolkökssem\n21-40 (förest 40-48), Ateneum f fi\n21-39, Norrmalms kommun flicksk 39-43,\nstat skolkökssem 44-46, skolköksinsp 46-\n\n53, rektor stat skolkökssem sed 53.\n-Ordf Sv skolkökslärrors fören,\nstyr:-led stat inst f konsumentfrågor, Sv\nf äcklar :förb, Sigtuna hum lärov, insp\nEngelbrekts barnav:- o husmoderssk.\n-Utg: red Hemvårdslära, medarb\nNutidsmat o hemhushåll. - Utm: RNO.\n\nKASTRUP, H S ALLAN, redaktör,\nNew York, f i Lund 7/4/06 av köpman\nHerman K o Alfrida Andersson.\nFil kand Lund 28, DHS 34, anst\naff:-företag Paris o Sthlm 29-30, medarb\nTT Sthlm 30, polit medarb UNT 38,\nanst American-Swedish News\nExchange Inc New York 43, verkst dir där sed\n47. - Stynled sv orgrer New York,\nForeign Press Ass 48-50. - Skr: The\nMaking of Sweden (53), Digest of\nSwe-den (59). - Utm: RVO.\n\n",
    "structured": {
        "1": {
            "full_name": "P ÅKE KASTLUND",
            "location": "Lidingö",
            "occupation": "pastor",
            "birth_details": {
                "date": "22/02/1916",
                "place": "Avesta",
                "parents": "disp Bernhard K o Ester Holmberg"
            },
            "education": [
                {
                    "degree": "teol kand",
                    "year": "1943",
                    "institution": "Upps"
                }
            ],
            "career": [
                {
                    "position": "kyrkoadj",
                    "years": {
                        "start_year": 1946,
                        "end_year": 1952
                    },
                    "organization": "Västerås domkyrkoförs"
                },
                {
                    "position": "tjg",
                    "years": {
                        "start_year": 1952,
                        "end_year": 1956
                    },
                    "organization": "Lutherska världsförb N Sydamerika, Centralamerika o Mexico"
                },
                {
                    "position": "direktor",
                    "years": {
                        "start_year": 1956
                    },
                    "organization": "Lutherska världsförb sv sekt"
                }
            ],
            "family": {
                "spouse": "Dagmar Larsson",
                "marriage_year": "1944",
                "children": [
                    {
                        "name": "Birgitta",
                        "birth_year": "1945"
                    },
                    {
                        "name": "Inger",
                        "birth_year": "1946"
                    },
                    {
                        "name": "Bo",
                        "birth_year": "1947"
                    },
                    {
                        "name": "Christina",
                        "birth_year": "1954"
                    }
                ]
            },
            "publications": [
                {
                    "title": "Utpost i Incaland",
                    "year": "1956",
                    "type": null
                }
            ]
        },
        "2": {
            "full_name": "M M (GRETA) KASTMAN",
            "location": "Sthlm",
            "occupation": "rektor",
            "birth_details": {
                "date": "15/06/1901",
                "place": "Ovansjö, Gävleb l",
                "parents": "med lic Karl K o Maria K"
            },
            "education": [
                {
                    "degree": "Ateneums skolkökssem",
                    "year": "1920-1921",
                    "institution": null
                }
            ],
            "career": [
                {
                    "position": "lär",
                    "years": {
                        "start_year": 1921,
                        "end_year": 1940
                    },
                    "organization": "Ateneums skolkökssem"
                },
                {
                    "position": "förest",
                    "years": {
                        "start_year": 1940,
                        "end_year": 1948
                    },
                    "organization": "Ateneum f fi"
                },
                {
                    "position": "insp",
                    "years": {
                        "start_year": 1946,
                        "end_year": 1953
                    },
                    "organization": "stat skolkökssem"
                }
            ],
            "family": {
                "spouse": null,
                "marriage_year": "NULL",
                "children": null
            },
            "publications": [
                {
                    "title": "Hemvårdslära",
                    "year": null,
                    "type": null
                },
                {
                    "title": "Nutidsmat o hemhushåll",
                    "year": null,
                    "type": null
                }
            ],
            "honorary_titles": [
                {
                    "title": "RNO",
                    "institution": null,
                    "year": null
                }
            ]
        },
        "3": {
            "full_name": "H S ALLAN KASTRUP",
            "location": "New York",
            "occupation": "redaktör",
            "birth_details": {
                "date": "07/04/1906",
                "place": "Lund",
                "parents": "köpman Herman K o Alfrida Andersson"
            },
            "education": null,
            "career": [
                {
                    "position": "medarb",
                    "years": {
                        "start_year": 1930,
                        "end_year": 1930
                    },
                    "organization": "TT Sthlm"
                },
                {
                    "position": "polit medarb",
                    "years": {
                        "start_year": 1938,
                        "end_year": null
                    },
                    "organization": "UNT"
                },
                {
                    "position": "verkst dir",
                    "years": {
                        "start_year": 1947,
                        "end_year": null
                    },
                    "organization": "American-Swedish News Exchange Inc New York"
                }
            ],
            "family": {
                "spouse": null,
                "marriage_year": "NULL",
                "children": null
            },
            "publications": [
                {
                    "title": "The Making of Sweden",
                    "year": "1953",
                    "type": null
                },
                {
                    "title": "Digest of Sweden",
                    "year": "1959",
                    "type": null
                }
            ],
            "honorary_titles": [
                {
                    "title": "RVO",
                    "institution": null,
                    "year": null
                }
            ]
        }
    }
}