{
    "original": "KJELLGREN,   OVE   A   V,   direktör,\nSthlm, f i Sthlm 5/6/19 av kamrer\nHarald K o Ingeborg Wallner.\nIng:ex tekn sk 41, KTH 52. - Ing\nmil:-fysiska  inst  41,  ritkontorsch  FOA  45,\npr o vn: ing   o   konstr   ab   Separator   49,\nkonstr:ch 53, övering 57,  dir sed 60.\nGift 46 m Brita Mathisson f 17, dtr t\nfabr Axel M o Ester Persson. - Barn:\nJan f 47, Lena f 55, Lars f 55.\n\nKJELLGREN-HIRSCH,   INGEBORG\nE,   operasångerska,   Sthlm,   f   i   Stode,\nVästernorrl l,  18/4/18.\nMusikhögsk   40-45,   operask,   sångstud\nRom 49, eng St teat Gbg 45^46,\ndebut-konsert Sthlm 47, debut K teat 51, eng\ndär sed 54. - Eng Kölnoperan 61-62.\n-Utm: MA:s jeton.\nGift 58 m Gerhard Hirsch f 18.\n\nKJELLIN, ALF G H, skådespelare,\nregissör, Sthlm, f i Lund 28/2/20 av prof\nHelge K o Stina Wennström.\nHal, teatersk, eng SF, Vasateat,\nRiks-teat, Radiotj m fi 37-47, Vanguard Films\nInc (Selznick Internat Piet) 47-50\n(under namnet Christopher Kent),\nTerra-fito 50, Sandrew, SF, Nya teat Sthlm,\nColumbia Film 51, åter i Sv:e 53, gästsp\nBlancheteat 56. - Ett 40-tal sv filmroller,\nbl a i Hets, regiss Flickan i regnet (54),\nTV-filmer f USA i Sydafr (56), Möte i\nskymningen (56), Det svänger på slottet\n(58), Bara en kypare (58), Lustgården\n(61), Siska (62).\n\nGift 1) 41-54 m Karin Nordgren f 19,\ndtr t kamrer Hugo N o Nanny Åkeson,\n\n2) 58 m Gun Hellberg f 38, dtr t Knut\nH o Carin H.\n\nKJELLIN, J ESKIL T,\navdelningsdirektör, Bromma, f i Backa, Gbgs o Boh\nl, 19/2/00 av notarie Lorens K o Elin\nGrauers.\n\nStud:ex Sthlm 19, postassrex 21,\npostass 28, l:e postass 38, postkontrollör\n44, överkontrollör 48, l:e byråsekr 54,\nbyrådir 58, avd:dir sed 59.\nGift m Gurli Allstrin d 59. - Barn:\nIngegerd f 31, Ulla f 33.\n\n",
    "structured": {
        "1": {
            "full_name": "KJELLGREN, OVE A V",
            "location": "Sthlm",
            "occupation": "direktör",
            "birth_details": {
                "date": "5/6/1919",
                "place": "Sthlm",
                "parents": "av kamrer Harald K o Ingeborg Wallner"
            },
            "education": [
                {
                    "degree": "Ing:ex tekn",
                    "year": "1941",
                    "institution": "KTH"
                }
            ],
            "career": [
                {
                    "position": "Ing mil:-fysiska inst",
                    "years": {
                        "start_year": 1941,
                        "end_year": 1945
                    },
                    "organization": "ritkontorsch FOA"
                },
                {
                    "position": "pr o vn: ing o konstr ab Separator",
                    "years": {
                        "start_year": 1949,
                        "end_year": 1953
                    },
                    "organization": null
                },
                {
                    "position": "konstr:ch",
                    "years": {
                        "start_year": 1953,
                        "end_year": 1957
                    },
                    "organization": null
                },
                {
                    "position": "övering",
                    "years": {
                        "start_year": 1957,
                        "end_year": 1960
                    },
                    "organization": null
                },
                {
                    "position": "dir",
                    "years": {
                        "start_year": 1960,
                        "end_year": null
                    },
                    "organization": null
                }
            ],
            "family": {
                "spouse": "Brita Mathisson",
                "marriage_year": "1946",
                "children": [
                    {
                        "name": "Jan",
                        "birth_year": "1947"
                    },
                    {
                        "name": "Lena",
                        "birth_year": "1955"
                    },
                    {
                        "name": "Lars",
                        "birth_year": "1955"
                    }
                ]
            }
        },
        "2": {
            "full_name": "KJELLGREN-HIRSCH, INGEBORG E",
            "location": "Sthlm",
            "occupation": "operasångerska",
            "birth_details": {
                "date": "18/4/1918",
                "place": "Stode, Västernorrland"
            },
            "education": [
                {
                    "degree": null,
                    "year": null,
                    "institution": "Musikhögsk 40-45"
                },
                {
                    "degree": null,
                    "year": null,
                    "institution": "operask, sångstud Rom 49"
                }
            ],
            "career": [
                {
                    "position": null,
                    "years": {
                        "start_year": 1945,
                        "end_year": 1946
                    },
                    "organization": "eng St teat Gbg"
                },
                {
                    "position": null,
                    "years": {
                        "start_year": 1947,
                        "end_year": 1951
                    },
                    "organization": "debut-konsert Sthlm"
                },
                {
                    "position": null,
                    "years": {
                        "start_year": 1951,
                        "end_year": 1954
                    },
                    "organization": "debut K teat"
                },
                {
                    "position": null,
                    "years": {
                        "start_year": 1954,
                        "end_year": 1954
                    },
                    "organization": "eng there"
                },
                {
                    "position": null,
                    "years": {
                        "start_year": 1961,
                        "end_year": 1962
                    },
                    "organization": "Eng Kölnoperan"
                }
            ],
            "family": {
                "spouse": "Gerhard Hirsch",
                "marriage_year": "1958",
                "children": []
            }
        },
        "3": {
            "full_name": "KJELLIN, ALF G H",
            "location": "Sthlm",
            "occupation": "skådespelare, regissör",
            "birth_details": {
                "date": "28/2/1920",
                "place": "Lund"
            },
            "education": [
                {
                    "degree": null,
                    "year": null,
                    "institution": "Hal, teatersk"
                }
            ],
            "career": [
                {
                    "position": null,
                    "years": {
                        "start_year": 1937,
                        "end_year": 1947
                    },
                    "organization": "eng SF, Vasateat, Riks-teat, Radiotj m fi"
                },
                {
                    "position": null,
                    "years": {
                        "start_year": 1947,
                        "end_year": 1950
                    },
                    "organization": "Vanguard Films Inc (Selznick Internat Piet)"
                },
                {
                    "position": null,
                    "years": {
                        "start_year": 1950,
                        "end_year": 1953
                    },
                    "organization": "Terra-fito"
                },
                {
                    "position": null,
                    "years": {
                        "start_year": 1953,
                        "end_year": 1956
                    },
                    "organization": "Sandrew, SF, Nya teat Sthlm"
                },
                {
                    "position": null,
                    "years": {
                        "start_year": 1956,
                        "end_year": null
                    },
                    "organization": "Columbia Film"
                }
            ],
            "family": {
                "spouse": "Karin Nordgren",
                "marriage_year": "1941",
                "children": []
            }
        },
        "4": {
            "full_name": "KJELLIN, J ESKIL T",
            "location": "Bromma",
            "occupation": "avdelningsdirektör",
            "birth_details": {
                "date": "19/2/1900",
                "place": "Backa, Gbgs o Bohus l"
            },
            "education": [
                {
                    "degree": null,
                    "year": "1919",
                    "institution": "Stud:ex Sthlm"
                },
                {
                    "degree": null,
                    "year": "1921",
                    "institution": "postassrex"
                },
                {
                    "degree": null,
                    "year": "1928",
                    "institution": "postass"
                }
            ],
            "career": [
                {
                    "position": null,
                    "years": {
                        "start_year": 1938,
                        "end_year": 1944
                    },
                    "organization": "l:e postass"
                },
                {
                    "position": null,
                    "years": {
                        "start_year": 1944,
                        "end_year": 1948
                    },
                    "organization": "postkontrollör"
                },
                {
                    "position": null,
                    "years": {
                        "start_year": 1948,
                        "end_year": 1954
                    },
                    "organization": "överkontrollör"
                },
                {
                    "position": null,
                    "years": {
                        "start_year": 1954,
                        "end_year": 1958
                    },
                    "organization": "l:e byråsekr"
                },
                {
                    "position": null,
                    "years": {
                        "start_year": 1958,
                        "end_year": null
                    },
                    "organization": "byrådir"
                }
            ],
            "family": {
                "spouse": "Gurli Allstrin",
                "marriage_year": null,
                "children": [
                    {
                        "name": "Ingegerd",
                        "birth_year": "1931"
                    },
                    {
                        "name": "Ulla",
                        "birth_year": "1933"
                    }
                ]
            }
        }
    }
}