{
    "original": "ERICSSON, E SIXTEN, bokhandlare,\n\nYstad, f i Ystad 29/4/94 av bokhandl\nRichard E o Gerda von Normann.\nBokhdlssk Il’, eg bokhdl Ystad sed 19.\n-Ordf Hdlsklassens i Ystad stiftelse sed\n50. - Medl Odd Fellow, Knutsgillet,\nsällsk WW. - Hed :ordf Ystads simsällsk,\nhedL Sv musikhandl:fören. &lt;• Utm:\nYstads simsällsk GM, Sv:es köpm:förb\nftjtG, RyttarmS.\n\nGift 26 m Inez Johnsson f 04. - Barn:\nMargit f 27, Richard f 34.\n\nERIKSSON, SIXTEN E E,\nbankdirektör, Malmö, f i Malmö 17/5/08 av dir\nEmil E o Kristina Palmqvist.\nStud:ex Malmö 2$, jur kand Lund 32,\ntingstjg 32-35, adv Malmö 351-46, bitr dir\nSv hdlsbkn Malmö 46^55, verkst dir dess\navd’:centr i Malmö sed 515. - Styr :ordf J\nE Ohlsens Enke ab, ab Resco m fi föret.\n\n-   Ordf Skånes konstfören. - Medl\nRotary. - Utm: RVO. - Hobby: golf.\nGift 65 m Kerstin Berlin, dtr t dr Emil\nB o Viola B.\n\nERIKSON, STELLAN P J,\nprovinsialläkare, Ullared, f i Oskarström 24/2/\n12 av apot Leander E o Agda Charlotta\nStern.\n\nStud:ex Halmstad 31, med kand Upps\n34, med lic Lund 44, vik underläk o tf\nprov :läk 44-50, prov :läk Ullareds distr\nsed 50.\n\nGift 50 m Dagmar Ytterberg f 29, dtr t\ndisp Birger Y o Ruth Lindén. - Barn:\nAnn-Charlotte f 51, Marita f 54.\n\nERIKSSON, STEN G, med dr, docent,\n\nLund, f i Gbg 19/5/32 av lärov:adj\nGunnar E o Ruth Wiberg.\nStud:ex Borås 51, med kand Lund 54,\nmed lic 60, med dr o doc i praktisk\nmedicin Lunds univ sed 65. - Ass o bitr lär\nmed-kem inst Lunds univ 55-60, aman o\nunderläk med klin o centrallab Malmö\nallm sjh 60-65, underläk neurol klin\nLunds las sed 66. - Skr i biokemi, inv\nmed, klin kemi o klin fysiol.\nGift 55 m byrådir, jur kand Birgitta\nLil-jedahl f 32, dtr t dir Torsten L o Elsa\n\nWihlborg. - Barn: Ola f 56, Lena f 60,\nAnna f 65.\n\n",
    "structured": {
        "0": {
            "full_name": "Ericsson, E Sixten",
            "location": "Ystad",
            "occupation": "Bokhandlare",
            "birth_details": {
                "date": "29/04/1894",
                "place": "Ystad",
                "parents": "Richard E o Gerda von Normann"
            },
            "education": [
                {
                    "degree": "Bokhdlssk Il",
                    "year": "1929",
                    "institution": "Ystad"
                }
            ],
            "career": [
                {
                    "position": "Ordf Hdlsklassens i Ystad stiftelse",
                    "years": {
                        "start_year": 1950
                    },
                    "organization": "Ystad"
                }
            ],
            "family": {
                "spouse": "Inez Johnsson",
                "marriage_year": "1926",
                "children": [
                    {
                        "name": "Margit",
                        "birth_year": "1927"
                    },
                    {
                        "name": "Richard",
                        "birth_year": "1934"
                    }
                ]
            }
        },
        "1": {
            "full_name": "Eriksson, Sixten E E",
            "location": "Malmö",
            "occupation": "Bankdirektör",
            "birth_details": {
                "date": "17/05/1908",
                "place": "Malmö",
                "parents": "Emil E o Kristina Palmqvist"
            },
            "education": [
                {
                    "degree": "Studex",
                    "year": "1925",
                    "institution": "Malmö"
                },
                {
                    "degree": "Jur kand",
                    "year": "1932",
                    "institution": "Lund"
                }
            ],
            "career": [
                {
                    "position": "Tingstjg",
                    "years": {
                        "start_year": 1932,
                        "end_year": 1935
                    }
                },
                {
                    "position": "Adv",
                    "years": {
                        "start_year": 1935,
                        "end_year": 1946
                    },
                    "organization": "Malmö"
                },
                {
                    "position": "Bitr dir Sv hdlsbkn Malmö",
                    "years": {
                        "start_year": 1946,
                        "end_year": 1955
                    },
                    "organization": "Malmö"
                },
                {
                    "position": "Verkst dir dess avd':centr i Malmö",
                    "years": {
                        "start_year": 1955,
                        "end_year": 1955
                    }
                }
            ],
            "family": {
                "spouse": "Kerstin Berlin",
                "marriage_year": "1965"
            },
            "hobbies": [
                "Golf"
            ]
        },
        "2": {
            "full_name": "Erikson, Stellan P J",
            "location": "Ullared",
            "occupation": "Provinsialläkare",
            "birth_details": {
                "date": "24/02/1912",
                "place": "Oskarström",
                "parents": "Leander E o Agda Charlotta Stern"
            },
            "education": [
                {
                    "degree": "Studex",
                    "year": "1931",
                    "institution": "Halmstad"
                },
                {
                    "degree": "Med kand",
                    "year": "1934",
                    "institution": "Upps"
                },
                {
                    "degree": "Med lic",
                    "year": "1944",
                    "institution": "Lund"
                }
            ],
            "career": [
                {
                    "position": "Vik underläk o tf prov :läk",
                    "years": {
                        "start_year": 1944,
                        "end_year": 1950
                    }
                },
                {
                    "position": "Prov :läk Ullareds distr",
                    "years": {
                        "start_year": 1950
                    }
                }
            ],
            "family": {
                "spouse": "Dagmar Ytterberg",
                "marriage_year": "1950",
                "children": [
                    {
                        "name": "Ann-Charlotte",
                        "birth_year": "1951"
                    },
                    {
                        "name": "Marita",
                        "birth_year": "1954"
                    }
                ]
            }
        },
        "3": {
            "full_name": "Eriksson, Sten G",
            "location": "Lund",
            "occupation": "Med dr, docent",
            "birth_details": {
                "date": "19/05/1932",
                "place": "Göteborg",
                "parents": "Gunnar E o Ruth Wiberg"
            },
            "education": [
                {
                    "degree": "Studex",
                    "year": "1951",
                    "institution": "Borås"
                },
                {
                    "degree": "Med kand",
                    "year": "1954",
                    "institution": "Lund"
                },
                {
                    "degree": "Med lic",
                    "year": "1960",
                    "institution": "Lund"
                },
                {
                    "degree": "Med dr o doc i praktisk medicin",
                    "year": "1965",
                    "institution": "Lunds univ"
                }
            ],
            "career": [
                {
                    "position": "Ass o bitr lär med-kem inst Lunds univ",
                    "years": {
                        "start_year": 1955,
                        "end_year": 1960
                    },
                    "organization": "Lunds univ"
                },
                {
                    "position": "Aman o underläk med klin o centrallab Malmö allm sjh",
                    "years": {
                        "start_year": 1960,
                        "end_year": 1965
                    },
                    "organization": "Malmö"
                },
                {
                    "position": "Underläk neurol klin Lunds las",
                    "years": {
                        "start_year": 1966
                    },
                    "organization": "Lunds las"
                }
            ],
            "family": {
                "spouse": "Byrådir, jur kand Birgitta Liljedahl",
                "marriage_year": "1955",
                "children": [
                    {
                        "name": "Ola",
                        "birth_year": "1956"
                    },
                    {
                        "name": "Lena",
                        "birth_year": "1960"
                    },
                    {
                        "name": "Anna",
                        "birth_year": "1965"
                    }
                ]
            }
        }
    }
}