{
    "original": "ERLANDSSON, P ROLF,\ncivilingenjör, Malmö, f i Skövde 2/9/10 av överste\nPer Adolf E o Victoria Billvall.\nStud:ex Umeå 29, KTH 3’5i, ing Rörledn\nab Celsius Malmö 3’5i, ab Såna 44;,\növering där 56, övering o regionch ab\nNordiska Värme Såna sed 64. - Medl Lions\nclub. - Hobbies: jakt, golf.\nGift 37 m Lillanna Bl’omquist f 15, dtr t\ndir Knut B o Ebba Oleén. - Barn:\nMarianne f 39, Per f 42, Héléne f 45.\n\nERLANDSSON, SVEN O E,\nrevisionsintendent, Kristianstad, f i Karlstad\n17/5/17 av lokför Gustaf E o Olga\nJohansson.\n\nStud:ex 36, DHS 41, anst länsstyr Norrb\nl 42, tax:ass Krist l 44, tax:insp Blek l\n4$, Krist l 512, rev :intend där sed 65.\n-Led Krist stads pers :nd. - Medl FrimO.\nGift 46 m Maj-Britt Mårtenson, dtr t\nstat :f örest Axel M o Anna Friman.\n-Barn: Ann-Marie f 47i, Bengt f 54, Peter\nf 55.\n\nERLING, ERNST N, fd\nkontraktsprost, Lund, f i Slättåkra, Hall l, 13/1/90\nav hemm:äg Johannes Erlandsson o\nJohanna Persson.\n\nTeol kand Lund 17, prästv l®, kommin\ndomkyrkoförs Gbg 22, kyrkoh S:t Peters\nKloster o N Nöbbelöv 28-60, kontr:prost\nTorna kontr 5-6-60. - Sekr Gustaf\nAdolfs-förem i Lund sed 31-. - Utm: LVO.\nGift 22 m Marie Schad f 01,, dtr t\nstadsmissionär Carl S o Sophie Röde. - Barn:\nMarlies f 23, Harald f 25, Torgny f 28,\nUrsula f 30, Martin o Gotthold ff 40.\n\nERLÖV, LARS H, civilingenjör,\nLandskrona, f i Lund 7/2/35 av köpm Helge\nE o Valborg Welander.\nHTL Hbg 54, CTH 62, ing Viskafors\ngummifabr 55, SSA 56, fabr:ch ab\nCello-print Landskrona sed 5’8. - Hobbies:\nfiske, fotografering.\n\nGift 59 m Iris Abrahamsson, dtr t\nhemm:äg Simon A o Elsa Fredriksson.\n-Barn: Peter f 60.\n\n",
    "structured": {
        "0": {
            "full_name": "P ROLF ERLANDSSON",
            "location": "Malmö",
            "occupation": "Civilingenjör",
            "birth_details": {
                "date": "02/09/1910",
                "place": "Skövde",
                "parents": "Per Adolf E o Victoria Billvall"
            },
            "education": [
                {
                    "degree": "Stud:ex",
                    "year": "1929",
                    "institution": "Umeå"
                },
                {
                    "degree": "KTH",
                    "year": "1935",
                    "institution": "KTH"
                }
            ],
            "career": [
                {
                    "position": "Ing Rörledn ab Celsius Malmö",
                    "years": {
                        "start_year": 1935,
                        "end_year": 1944
                    },
                    "organization": "ab Celsius Malmö"
                },
                {
                    "position": "Övering ab Såna",
                    "years": {
                        "start_year": 1944,
                        "end_year": 1956
                    },
                    "organization": "ab Såna"
                },
                {
                    "position": "Övering o regionch ab Nordiska Värme Såna",
                    "years": {
                        "start_year": 1956,
                        "end_year": 1964
                    },
                    "organization": "Nordiska Värme Såna"
                }
            ],
            "family": {
                "spouse": "Lillanna Bl’omquist",
                "marriage_year": "1937",
                "children": [
                    {
                        "name": "Marianne",
                        "birth_year": "1939"
                    },
                    {
                        "name": "Per",
                        "birth_year": "1942"
                    },
                    {
                        "name": "Héléne",
                        "birth_year": "1945"
                    }
                ]
            },
            "hobbies": [
                "Jakt",
                "Golf"
            ]
        },
        "1": {
            "full_name": "SVEN O E ERLANDSSON",
            "location": "Kristianstad",
            "occupation": "Revisionsintendent",
            "birth_details": {
                "date": "17/05/1917",
                "place": "Karlstad",
                "parents": "Gustaf E o Olga Johansson"
            },
            "education": [
                {
                    "degree": "Stud:ex",
                    "year": "1936",
                    "institution": ""
                },
                {
                    "degree": "DHS",
                    "year": "1941",
                    "institution": ""
                }
            ],
            "career": [
                {
                    "position": "Anst Länsstyr Norrb l",
                    "years": {
                        "start_year": 1942,
                        "end_year": 1944
                    },
                    "organization": "Länsstyr Norrb l"
                },
                {
                    "position": "Tax:ass Krist l",
                    "years": {
                        "start_year": 1944,
                        "end_year": 1951
                    },
                    "organization": "Krist l"
                },
                {
                    "position": "Tax:insp Blek l",
                    "years": {
                        "start_year": 1951,
                        "end_year": 1952
                    },
                    "organization": "Blek l"
                },
                {
                    "position": "Rev :intend",
                    "years": {
                        "start_year": 1965,
                        "end_year": null
                    },
                    "organization": "Krist"
                }
            ],
            "family": {
                "spouse": "Maj-Britt Mårtenson",
                "marriage_year": "1946",
                "children": [
                    {
                        "name": "Ann-Marie",
                        "birth_year": "1947"
                    },
                    {
                        "name": "Bengt",
                        "birth_year": "1954"
                    },
                    {
                        "name": "Peter",
                        "birth_year": "1955"
                    }
                ]
            }
        },
        "2": {
            "full_name": "ERNEST N ERLING",
            "location": "Lund",
            "occupation": "Fd Kontraktsprost",
            "birth_details": {
                "date": "13/01/1890",
                "place": "Slättåkra, Hall l",
                "parents": "Johannes Erlandsson o Johanna Persson"
            },
            "education": [
                {
                    "degree": "Teol kand",
                    "year": "1917",
                    "institution": "Lund"
                }
            ],
            "career": [
                {
                    "position": "Prästv l®",
                    "years": {
                        "start_year": 1922,
                        "end_year": null
                    },
                    "organization": "Domkyrkoförs Gbg"
                }
            ],
            "family": {
                "spouse": "Marie Schad",
                "marriage_year": "1922",
                "children": [
                    {
                        "name": "Marlies",
                        "birth_year": "1923"
                    },
                    {
                        "name": "Harald",
                        "birth_year": "1925"
                    },
                    {
                        "name": "Torgny",
                        "birth_year": "1928"
                    },
                    {
                        "name": "Ursula",
                        "birth_year": "1930"
                    },
                    {
                        "name": "Martin",
                        "birth_year": "1940"
                    },
                    {
                        "name": "Gotthold",
                        "birth_year": "1940"
                    }
                ]
            },
            "honorary_titles": [
                {
                    "title": "LVO",
                    "institution": null,
                    "year": null
                }
            ]
        },
        "3": {
            "full_name": "LARS H ERLÖV",
            "location": "Landskrona",
            "occupation": "Civilingenjör",
            "birth_details": {
                "date": "07/02/1935",
                "place": "Lund",
                "parents": "Helge E o Valborg Welander"
            },
            "education": [
                {
                    "degree": "HTL Hbg",
                    "year": "1954",
                    "institution": "Hbg"
                },
                {
                    "degree": "CTH",
                    "year": "1962",
                    "institution": "CTH"
                }
            ],
            "career": [
                {
                    "position": "Ing Viskafors gummifabr",
                    "years": {
                        "start_year": 1955,
                        "end_year": 1956
                    },
                    "organization": "Viskafors gummifabr"
                },
                {
                    "position": "Fabr:ch ab Cello-print Landskrona",
                    "years": {
                        "start_year": 1958,
                        "end_year": null
                    },
                    "organization": "Cello-print Landskrona"
                }
            ],
            "family": {
                "spouse": "Iris Abrahamsson",
                "marriage_year": "1959",
                "children": [
                    {
                        "name": "Peter",
                        "birth_year": "1960"
                    }
                ]
            },
            "hobbies": [
                "Fiske",
                "Fotografering"
            ]
        }
    }
}