{
    "original": "ERIKSSON, KARL-ERIK E,\nprofessor, Kungsbacka, f i S Råda, Värml l,\n19/11/35 av past Johan E o Agnes Isaks-\n\nStud:ex Enkpg 54, fil kand Upps 56, fil\nlic 59, fil dr 61, doc stat råd f atom-,\nforskn 62, prof i teoretisk fysik Gbgs\nuniv sed 63. - Stip CERN Geneve 59-62.\n\n- Skr: Ön electromagnetic scattering\npro-cesses ät high energies (drsavh 61), upps\n\n1  vetensk tidskr.\n\nGift 58 m Kristina Myrberg, dtr t lantbr\nHerbert M o Lisa Brundin. - Barn:\nGunnar f 61, Magdalena f 62, Elin f 64.\n\nERICSON, KJELL-BERTIL,\ngymna-stikdirektör, Kristianstad, f i Malmö\n8/5/30.\n\nStud:ex 50, GCI 54, gymn:lär folksk:sem\nKristianstad sed 5$, f ortbildn: konsulent\nlänsskolndn Krist l sed 64, övn:lär\nLä-rarhögsk Malmö sed 6’5. - Kapt P 6 res.\n\n- Hobbies: sportdykning, foto.\n\nGift 57! m förskollär Florence Bengtsson\nf 33, dtr t byggm Arvid B o Olga\nNilsson. - Barn: Eva f 61, Maria f 66.\n\nERIKSSON,   KURT   E,   stadskamrer,\n\nKristianstad, f i Nykpg 29/1/25 av Einar\n\nE o Magda Andersson.\n\nStud:ex  Sthlm  47,   DSI   51,   DHS   57,\n\nstadskamrer Kristianstad sed 56. - Styr:-\n\nled LSH.\n\nGift 51 m Thyra Andersson, dtr t byggm\n\nFilip A o Hilma A. - Barn: Kerstin f 58.\n\nERIKSSON,   KURT   I   E,   apotekare,\n\nHalmstad, f i Götlunda, Örebro l, 26/1 Ö/\n\n02  av handl Karl E o Elin Bergqvist.\nStud:ex Örebro 211, farm kand 25,\napot:-ex 30. - Elev Svanen Örebro 21, anst där\n25-27,, Hallsberg 31, Svalan Halmstad 31,\npriv apot Krylbo 46, Nybro 51, Svalan\nHalmstad sed 57,  - Medl W-sex, Odd\nFellow, FrimO.\n\nGift 3il m Elsie Olsson f 06, dtr t\nskepps-fourner Albert) O o Emma Nilsson.\n-Barn: Britt-Marie f 33, Hans Ivar f 44.\n\n",
    "structured": {
        "0": {
            "full_name": "Eriksson, Karl-Erik E",
            "location": "Kungsbacka",
            "occupation": "Professor",
            "birth_details": {
                "date": "19/11/1935",
                "place": "S Råda, Värml l"
            },
            "education": [
                {
                    "degree": "Stud:ex",
                    "year": "1954",
                    "institution": "Enkpg"
                },
                {
                    "degree": "filosofie kandidat",
                    "year": "1956",
                    "institution": "Upps"
                },
                {
                    "degree": "filosofie licentiat",
                    "year": "1959",
                    "institution": ""
                },
                {
                    "degree": "filosofie doktor",
                    "year": "1961",
                    "institution": ""
                }
            ],
            "career": [
                {
                    "position": "docent",
                    "years": {
                        "start_year": 1962,
                        "end_year": 1963
                    },
                    "organization": ""
                },
                {
                    "position": "professor i teoretisk fysik",
                    "years": {
                        "start_year": 1963,
                        "end_year": null
                    },
                    "organization": "Gbgs univ"
                }
            ],
            "family": {
                "spouse": "Kristina Myrberg",
                "marriage_year": "1958",
                "children": [
                    {
                        "name": "Gunnar",
                        "birth_year": "1961"
                    },
                    {
                        "name": "Magdalena",
                        "birth_year": "1962"
                    },
                    {
                        "name": "Elin",
                        "birth_year": "1964"
                    }
                ]
            }
        },
        "1": {
            "full_name": "Ericson, Kjell-Bertil",
            "location": "Kristianstad",
            "occupation": "Gymnastikdirektör",
            "birth_details": {
                "date": "08/05/1930",
                "place": "Malmö"
            },
            "education": [
                {
                    "degree": "Stud:ex",
                    "year": "1950",
                    "institution": ""
                },
                {
                    "degree": "GCI",
                    "year": "1954",
                    "institution": ""
                }
            ],
            "career": [
                {
                    "position": "gymn:lär",
                    "years": {
                        "start_year": 1954,
                        "end_year": null
                    },
                    "organization": "folksk:sem Kristianstad"
                },
                {
                    "position": "övn:lär",
                    "years": {
                        "start_year": 1965,
                        "end_year": null
                    },
                    "organization": "Lärarhögsk Malmö"
                }
            ],
            "family": {
                "spouse": "Florence Bengtsson",
                "marriage_year": "1957",
                "children": [
                    {
                        "name": "Eva",
                        "birth_year": "1961"
                    },
                    {
                        "name": "Maria",
                        "birth_year": "1966"
                    }
                ]
            },
            "hobbies": [
                "sportdykning",
                "foto"
            ]
        },
        "2": {
            "full_name": "Eriksson, Kurt E",
            "location": "Kristianstad",
            "occupation": "Stadskamrer",
            "birth_details": {
                "date": "29/01/1925",
                "place": "Nykpg"
            },
            "education": [
                {
                    "degree": "Stud:ex",
                    "year": "1947",
                    "institution": "Sthlm"
                },
                {
                    "degree": "DSI",
                    "year": "1951",
                    "institution": ""
                },
                {
                    "degree": "DHS",
                    "year": "1957",
                    "institution": ""
                }
            ],
            "career": [
                {
                    "position": "stadskamrer",
                    "years": {
                        "start_year": 1956,
                        "end_year": null
                    },
                    "organization": "Kristianstad"
                }
            ],
            "family": {
                "spouse": "Thyra Andersson",
                "marriage_year": "1951",
                "children": [
                    {
                        "name": "Kerstin",
                        "birth_year": "1958"
                    }
                ]
            }
        },
        "3": {
            "full_name": "Eriksson, Kurt I E",
            "location": "Halmstad",
            "occupation": "Apotekare",
            "birth_details": {
                "date": "26/01/1902",
                "place": "Götlunda, Örebro l"
            },
            "education": [
                {
                    "degree": "Stud:ex",
                    "year": "1921",
                    "institution": "Örebro"
                },
                {
                    "degree": "farm kand",
                    "year": "1925",
                    "institution": ""
                },
                {
                    "degree": "apot:-ex",
                    "year": "1930",
                    "institution": ""
                }
            ],
            "career": [
                {
                    "position": "elev",
                    "years": {
                        "start_year": 1921,
                        "end_year": 1921
                    },
                    "organization": "Svanen Örebro"
                },
                {
                    "position": "priv apot",
                    "years": {
                        "start_year": 1946,
                        "end_year": 1951
                    },
                    "organization": "Krylbo"
                },
                {
                    "position": "priv apot",
                    "years": {
                        "start_year": 1951,
                        "end_year": 1957
                    },
                    "organization": "Nybro"
                },
                {
                    "position": "priv apot",
                    "years": {
                        "start_year": 1957,
                        "end_year": null
                    },
                    "organization": "Svalan Halmstad"
                }
            ],
            "family": {
                "spouse": "Elsie Olsson",
                "marriage_year": "1931",
                "children": [
                    {
                        "name": "Britt-Marie",
                        "birth_year": "1933"
                    },
                    {
                        "name": "Hans Ivar",
                        "birth_year": "1944"
                    }
                ]
            }
        }
    }
}