{
    "original": "EKBLOM, D HARRY, redaktionschef,\n\nMalmö, f i Hille, Gävleb l, 10/3/21 av\narrend Simon E o Clara Pettersson.\nMedarb tidns Arbetaren 44,\nNorrlands-folket 45’-4», Nya Norrl 48-50, Västmanl\nFolkbl 51-514, Norrl Soc:dem 55-, MT\n56-58, AB 5-91-60, Arbete* 61-63\", red:ch o\nansv utgiv där sed1 63. - Led Syndikalist\nungd:förb:s VU 43, sekr Örnsköldsviks\narb :komm 49-50, ordf N Ångermani\nSSU-krets 49, stud:led Västmanl SSU\ndistr 52-531\n\nGift 48 m Thyra Stålhacke f 25f, dtr t\nbyggn :snick Hjalmar S o Hilma\nJacobsson. - Barn: Yvonne f 48, Jan-Peter f 58.\n\nEKBLOM,  S  G  INGEMAR,  konsul,\n\nHbg, f i Filipstad 17/3/03 av l:e postexp\nEmil E o Hanna Sillen.\nStud:ex Örebro 21, dipl hdlshögsk\nLeipzig 23, Sv:e-Amer-stift) ind:stip USA\n26-27; anst ab Separator USA p Tyskl 29-32,\nförsäljn :ch Almédahl-Dalsjöfors ab\n33-34, verkst dir o inneh Kävlinge väveri\nab 36-531, verkst dir Investment ab\nWig-ral. - Förb:republ Tyskl konsul Hbg sed\n\n64. - Styr :led Investment ab Wigral m\ndtrbol, Hbgs gummifabr ab Tretorn,\nTrelleborgs gummifabr ab, Junex konf\nab, Sv hdlsbkn Hbg. - V ordf DK Hbg\nsed 55. - LVSL, hedL Värml nät Lund.\n-Medl Rotary. - Utm: RVO, Lunds\nstud:-sångfören GM, Med fak Lunds univ\nstSM.\n\nGift 31 m Märta Grönvall. - Barn: Jan\nf 3’2, Anna f 315.\n\nEKBLOM, NILS A A, förste\nlänsasses-sor, Kristianstad, f i Fellingsbro,\nÖrebro l, 1/8/04 av prov:läk A E E o Elin\nAndersson.\n\nJur kand Lund 28!, tingstjg 28-32, aman\narméförvalUn o soc:styr 33–341, soc:dep\n33^36, 2:e kanslisekr där 40 (tf 37), tf l:e\nlänsnot Örebro l 41, länsassess Norrb l\n49, l :e länsassess där 5-3,- Krist l sed1 54’.\n- Not 2:a llagutsk 39, not 411 samt bitr\nsekr konstiti:utsk 41 o 48, särsk föredr\ndär 62, sekr fi offentl utredn, suppl o\njurid bitr lantbr:ndn Krist 1. - Utg:\nRedogörelse för 1948 års\nkommunallägs-reforrni, upps i facktidskr. - Utm: RNO.\nGift 36 m Birgit Länder f 13, dtr t kapt\nLennart L o Maria Geuken. - Barn: Jan\nf 3’8, Marianne f 42, Elisabet f 43’.\n\n",
    "structured": {
        "0": {
            "full_name": "EKBLOM, D HARRY",
            "location": "Malmö",
            "occupation": "redaktionschef",
            "birth_details": {
                "date": "10/03/1921",
                "place": "Hille, Gävleb l"
            },
            "education": [],
            "career": [
                {
                    "position": "red:ch o ans v utgiv",
                    "years": {
                        "start_year": 1963,
                        "end_year": 0
                    },
                    "organization": "Arbetet"
                }
            ],
            "family": {
                "spouse": "Thyra Stålhacke",
                "marriage_year": "1948",
                "children": [
                    {
                        "name": "Yvonne",
                        "birth_year": "1948"
                    },
                    {
                        "name": "Jan-Peter",
                        "birth_year": "1958"
                    }
                ]
            }
        },
        "1": {
            "full_name": "EKBLOM, S G INGEMAR",
            "location": "Hbg",
            "occupation": "konsul",
            "birth_details": {
                "date": "17/03/1903",
                "place": "Filipstad"
            },
            "education": [
                {
                    "degree": "Stud:ex",
                    "year": "1921",
                    "institution": "Örebro"
                },
                {
                    "degree": "dipl hdlshögsk",
                    "year": "1923",
                    "institution": "Leipzig"
                }
            ],
            "career": [
                {
                    "position": "förb:republ Tyskl konsul",
                    "years": {
                        "start_year": 1964,
                        "end_year": 0
                    },
                    "organization": "Hbg"
                }
            ],
            "family": {
                "spouse": "Märta Grönvall",
                "marriage_year": "1931",
                "children": [
                    {
                        "name": "Jan",
                        "birth_year": "1932"
                    },
                    {
                        "name": "Anna",
                        "birth_year": "1935"
                    }
                ]
            }
        },
        "2": {
            "full_name": "EKBLOM, NILS A A",
            "location": "Kristianstad",
            "occupation": "förste länsassessor",
            "birth_details": {
                "date": "01/08/1904",
                "place": "Fellingsbro, Örebro l"
            },
            "education": [
                {
                    "degree": "Jur kand",
                    "year": "1928",
                    "institution": "Lund"
                }
            ],
            "career": [
                {
                    "position": "l :e länsassess",
                    "years": {
                        "start_year": 1954,
                        "end_year": 0
                    },
                    "organization": "Krist l"
                }
            ],
            "family": {
                "spouse": "Birgit Länder",
                "marriage_year": "1936",
                "children": [
                    {
                        "name": "Jan",
                        "birth_year": "1938"
                    },
                    {
                        "name": "Marianne",
                        "birth_year": "1942"
                    },
                    {
                        "name": "Elisabet",
                        "birth_year": "1943"
                    }
                ]
            }
        }
    }
}