{
    "original": "ESTMAR, CARL, stadsarkitekt,\nFalkenberg, f i Hinneryd, Kronob l, 21/lÖ/\n15 av lantbr Henrik Carlsson o Hilda\nJohansson.\n\nStud:ex Malmö 40, CTH 56, eg\narkit:-verksamh 46-65, anst länsarkit:kont\nHalmstad 38-62, timlär tekn gymn 61-65,\nstadsarkit Fal’ken’berg sed 65. - Bl arb:\nålderd:hem o isstadion Halmstad. -\nHobbies: typografi, släktforskning.\nGift 42 m Berta Johansson, dtr t lantbr\nAlfred J o Judith Axelsson. -Barn:\nIngrid f 44, Bodil f 47, Kerstin f 48.\n\nEURÉN, HÅKAN P G, tullöverkon-\n\ntrollör, Trelleborg, f i Haparanda 20/10/\n99 av tullförv Georg E o Sofia Åström.\nStud:ex Luleå 181, anst tullverket 20,\ntul’l-överkontr tullkamm Trelleborg sed 55.\n-2:e v ordf Stadsfullm, v ordf gatund o\nfastigh:nd, vigselförrätt Trelleborg. -\n\nMedl Odd Fellow. - Utm: RNO. -\nHobbies: fiske, bridge.\n\nGift m Elsa Granbom f 0£. - Barn:\nKerstün f 36, Krister f 42.\n\nEURENIUS, M P WILHELM G,\nredaktör, Karlskrona, f i Karlshamn 8/8/01\nav hovfotogr Wilhelm E o Ebba Lovén.\nStud:ex Karlskrona 18’, stud StHS 19-20,\nParis 231-24; medarb Blek Läns Ticm 25,\nkulturred där 44-65. - Medarb Allhems\nkonstnärslex. - Styr :led Karlskrona\nstadsbibl, Blek musei- o hemb:fören. - Medl\nPK, SJF. - Skr: Konst o konstnärer i\nBlekinge (i En bok om Blekinge, 4(2),\nBlekinge som litterärt landskap (44&lt;), Min\nstamfar o hans bröder (i Arkiv för norrl\nhernb :forskn, 4$), Från faiakernas ö till\nNordiske näset. Studier i Georg\nStiern-hielms Bröllopps Beswärs\nIhogKom-melsze (5$), Den småländsk© Pan o det\nboiotiska svinet (i Från Småland o\nHellas, 59). - Hobbies: svenskt 1600-tal,\ngen’ealogi.\n\nGift 29 m folkskollär Märta Kloo f 03»,\ndtr t riksd:man Oskar K o Karin\nThuresson. - Barn: Lars f 30, Margareta f 33.\n\n",
    "structured": {
        "1": {
            "full_name": "ESTMAR, CARL",
            "location": "Falkenberg",
            "occupation": "Stadsarkitekt",
            "birth_details": {
                "date": "21/01/1915",
                "place": "Hinneryd, Kronoberg",
                "parents": "Lantbrukare Henrik Carlsson and Hilda Johansson"
            },
            "education": [
                {
                    "degree": "Stud:ex",
                    "year": "1940",
                    "institution": "Malmö"
                },
                {
                    "degree": "CTH",
                    "year": "1956",
                    "institution": "Chalmers tekniska högskola"
                }
            ],
            "career": [
                {
                    "position": "Eg arkit:-verksam",
                    "years": {
                        "start_year": 1946,
                        "end_year": 1965
                    },
                    "organization": "NULL"
                },
                {
                    "position": "Anst länsarkit:kont",
                    "years": {
                        "start_year": 1938,
                        "end_year": 1962
                    },
                    "organization": "Halmstad"
                },
                {
                    "position": "Timlär tekn gymn",
                    "years": {
                        "start_year": 1961,
                        "end_year": 1965
                    },
                    "organization": "NULL"
                },
                {
                    "position": "Stadsarkit",
                    "years": {
                        "start_year": 1965,
                        "end_year": "NULL"
                    },
                    "organization": "Falkenberg"
                }
            ],
            "family": {
                "spouse": "Berta Johansson",
                "marriage_year": "1942",
                "children": [
                    {
                        "name": "Ingrid",
                        "birth_year": "1944"
                    },
                    {
                        "name": "Bodil",
                        "birth_year": "1947"
                    },
                    {
                        "name": "Kerstin",
                        "birth_year": "1948"
                    }
                ]
            },
            "publications": "NULL",
            "community_involvement": "NULL",
            "board_memberships": "NULL",
            "honorary_titles": "NULL",
            "hobbies": [
                "Typografi",
                "Släktforskning"
            ]
        },
        "2": {
            "full_name": "EURÉN, HÅKAN P G",
            "location": "Trelleborg",
            "occupation": "Tullöverkontrollör",
            "birth_details": {
                "date": "20/10/1899",
                "place": "Haparanda"
            },
            "education": {
                "degree": "Stud:ex",
                "year": "181",
                "institution": "Luleå"
            },
            "career": {
                "position": "Anst tullverket",
                "years": {
                    "start_year": 1920,
                    "end_year": "NULL"
                },
                "organization": "NULL"
            },
            "family": {
                "spouse": "Elsa Granbom",
                "marriage_year": "NULL",
                "children": [
                    {
                        "name": "Kerstin",
                        "birth_year": "1936"
                    },
                    {
                        "name": "Krister",
                        "birth_year": "1942"
                    }
                ]
            },
            "publications": "NULL",
            "community_involvement": [
                "Medl Odd Fellow"
            ],
            "board_memberships": "NULL",
            "honorary_titles": [
                "RNO"
            ],
            "hobbies": [
                "Fiske",
                "Bridge"
            ]
        },
        "3": {
            "full_name": "EURENIUS, M P WILHELM G",
            "location": "Karlskrona",
            "occupation": "Redaktör",
            "birth_details": {
                "date": "8/8/1901",
                "place": "Karlshamn"
            },
            "education": {
                "degree": "Stud:ex",
                "year": "1938",
                "institution": "Karlskrona"
            },
            "career": {
                "position": "Medarb Blek Läns Ticm",
                "years": {
                    "start_year": 1925,
                    "end_year": "NULL"
                },
                "organization": "NULL"
            },
            "family": {
                "spouse": "Märta Kloo",
                "marriage_year": "1929",
                "children": [
                    {
                        "name": "Lars",
                        "birth_year": "1930"
                    },
                    {
                        "name": "Margareta",
                        "birth_year": "1933"
                    }
                ]
            },
            "publications": {
                "title": "NULL",
                "year": "NULL",
                "type": "NULL"
            },
            "community_involvement": [
                "Styr :led Karlskrona stadsbibl",
                "Blek musei- o hemb:fören"
            ],
            "board_memberships": "NULL",
            "honorary_titles": "NULL",
            "hobbies": [
                "Svenskt 1600-tal",
                "Genealogi"
            ]
        }
    }
}