{
    "original": "EKETORP, GÖRAN G H,\nkomminister, Malmö, f i Djursholm 26/7/07 av\nmusikdir Harald Ericsson o Anna\nLöwenhielm.\n\nStjud:ex 27, teol kand Lund 33’, kommin\nLjusne 36, Slottsstadens förs Malmö sed\n49. - Mil:past F 15 45-49. -\nFöreläsn:-verksamh, kårch Slottsstadens scoutkår\n5W-53. - Skr: Ljusne kyrka o församling\n(46). - Hobbies: musi’k, konst.\nGift 34 m Elisabeth Visell f 09, dtr t\nprost Hans V o Maria Frick. - Barn:\n\nGunilla f 351, Margareta f 36v\nHans-Göran f 3’9, Christina f 46.\n\nEKHOLM, ERNST M, advokat,\nKävlinge, f i Eslöv 22/7/03 av byggm Lars\nE o Alma Rask.\n\nStud:ex Eslöv 21, jur kand Lund 29,\ntingstjg Frosta o Eslövs doms 30-32,\nadv :verksamh Kävlinge sed 33. - LSA\n47. - Överförmynd sed 65.\nGift 33 m Elin Nilsson f 01. - Barn:\nInger f 36.\n\nEKHOLM, FOLKE H A, civilekonom,\nMalmö, f i Malmö 2/2/24 av dir Anders\nE o Hedvig Lundberg.\nStud:ex 43|, DHG 50, anst ab\nPlåtmanufaktur Malmö 52, budgetdi där sed 61.\n- Medl SCF. - Kapt pansartr res 63-,\n-Hobby: sport.\n\nGift 54 m Maj-Britt Carlsson f 24, dtr t\nHennig C o Thea Malm. - Barn: Anders\nf 58, Stellan f 60.\n\nEKHOLM-ERB, BERTIL, lektor,\nMalmö, f i Hfors 20 av attaché Richard Erb\no Anna-Maria Ekholm.\nStud:ex Hfors 39 o Lund’ 47, phil cand\nBonn 48, fil måg Lund 52, diplomtolk\nRegensburg 56, adj lär:högsk Sthlm 58*\nMaltaö 62, lekt där sed 65. -\nRadiokur-ser i tyska 61-62. - Skr lärob i tyska.\n-Hobbies: jakt, sport).\nGift 57 m Yvonne Hansson f 3®, dtr t\ndir Erik H o Ester H. - Barn: Kitty f 5®,\nPeter f 63’.\n\n",
    "structured": {
        "0": {
            "full_name": "EKETORP, GÖRAN G H",
            "location": "Malmö",
            "occupation": "komminister",
            "birth_details": {
                "date": "26/07/1907",
                "place": "Djursholm",
                "parents": "musikdir Harald Ericsson o Anna Löwenhielm"
            },
            "education": [
                {
                    "degree": "Stjud:ex",
                    "year": "1927",
                    "institution": "teol kand Lund 33’"
                },
                {
                    "degree": "teol kand",
                    "year": "1933",
                    "institution": "Lund"
                }
            ],
            "career": [
                {
                    "position": "kommin",
                    "years": {
                        "start_year": 1936,
                        "end_year": 1949
                    },
                    "organization": "Ljusne"
                }
            ],
            "family": {
                "spouse": "Elisabeth Visell",
                "marriage_year": "1934",
                "children": [
                    {
                        "name": "Gunilla",
                        "birth_year": "1935"
                    },
                    {
                        "name": "Margareta",
                        "birth_year": "1936"
                    },
                    {
                        "name": "Hans-Göran",
                        "birth_year": "1939"
                    },
                    {
                        "name": "Christina",
                        "birth_year": "1946"
                    }
                ]
            },
            "hobbies": [
                "musik",
                "konst"
            ]
        },
        "1": {
            "full_name": "EKHOLM, ERNST M",
            "location": "Kävlinge",
            "occupation": "advokat",
            "birth_details": {
                "date": "22/07/1903",
                "place": "Eslöv",
                "parents": "byggm Lars E o Alma Rask"
            },
            "education": [
                {
                    "degree": "Stud:ex",
                    "year": "1921",
                    "institution": "Eslöv"
                }
            ],
            "career": [
                {
                    "position": "tingstjg",
                    "years": {
                        "start_year": 1930,
                        "end_year": 1932
                    },
                    "organization": "Frosta o Eslövs doms"
                },
                {
                    "position": "adv",
                    "years": {
                        "start_year": 1933
                    },
                    "organization": "Kävlinge"
                }
            ],
            "family": {
                "spouse": "Elin Nilsson",
                "marriage_year": "1933",
                "children": [
                    {
                        "name": "Inger",
                        "birth_year": "1936"
                    }
                ]
            }
        },
        "2": {
            "full_name": "EKHOLM, FOLKE H A",
            "location": "Malmö",
            "occupation": "civilekonom",
            "birth_details": {
                "date": "02/02/1924",
                "place": "Malmö",
                "parents": "dir Anders E o Hedvig Lundberg"
            },
            "education": [
                {
                    "degree": "Stud:ex",
                    "year": "1943",
                    "institution": "DHG 50"
                },
                {
                    "degree": "DHG",
                    "year": "1950",
                    "institution": "Malmö"
                }
            ],
            "career": [
                {
                    "position": "anst ab",
                    "years": {
                        "start_year": 1952
                    },
                    "organization": "Plåtmanufaktur Malmö"
                }
            ],
            "family": {
                "spouse": "Maj-Britt Carlsson",
                "marriage_year": "1954",
                "children": [
                    {
                        "name": "Anders",
                        "birth_year": "1958"
                    },
                    {
                        "name": "Stellan",
                        "birth_year": "1960"
                    }
                ]
            },
            "hobbies": [
                "sport"
            ]
        },
        "3": {
            "full_name": "EKHOLM-ERB, BERTIL",
            "location": "Malmö",
            "occupation": "lektor",
            "birth_details": {
                "date": "20/__/19__",
                "place": "Hfors",
                "parents": "attaché Richard Erb o Anna-Maria Ekholm"
            },
            "education": [
                {
                    "degree": "Stud:ex",
                    "year": "1939",
                    "institution": "Hfors"
                },
                {
                    "degree": "phil cand",
                    "year": "1947",
                    "institution": "Lund"
                },
                {
                    "degree": "fil måg",
                    "year": "1952",
                    "institution": "Lund"
                },
                {
                    "degree": "diplomtolk",
                    "year": "1956",
                    "institution": "Regensburg"
                }
            ],
            "career": [
                {
                    "position": "adj lär",
                    "years": {
                        "start_year": 1958
                    },
                    "organization": "högsk Sthlm"
                }
            ],
            "family": {
                "spouse": "Yvonne Hansson",
                "marriage_year": "1957",
                "children": [
                    {
                        "name": "Kitty",
                        "birth_year": "1950"
                    },
                    {
                        "name": "Peter",
                        "birth_year": "1963"
                    }
                ]
            },
            "hobbies": [
                "jakt",
                "sport"
            ]
        }
    }
}