{
    "original": "EDBERG, B GUNNAR, kyrkoherde,\n\nBarsebäck, f i Ängelholm 20/7/06 av\nfolkskollär Nils E o Carolina Holmberg.\nStud:ex Lund 25, teol kand 30, prästv31, past:adj Borlunda 31, v kommin Vä\n\n33, stiftsadj 35, kyrkoh Barsebäck sed 41.\n\n- Ordf Lunds stifts prästers nykterh:- o\n\ndiakoniförb sed 53. - överförm sed 43. -\n\nMedl IOGT, TR. - Utm: LNO. - Hobby:\n\nesperanto.\n\nGift 33 m Gunnel Angberg f 09.\n\nEDE-JACOBSSON, M CARIN,\nläroverksadjunkt, Lund, f i Karlskrona 4/1/\n29 av major Gunnar Ede o Märta\nWah-rolén.\n\nStud:ex 48, fil mag Lund 43, e adj\nSlottsstadens samrealsk Malmö 53, eo adj\nrealsk Kirsberg 54, hal f g Malmö 56,\nadj Bergask 57, Lunds stads sk sed 58.\nGift 53 m doc Ulf Jacobsson. - Barn:\nAnne f 59, Hans f 62.\n\nEDEBRAND, KARL ERIK H,\ntrafikchef, Malmö, f i Örebro 9/12/10 av\nsnickarm Erik Andersson o Anna\nSvensson.\n\nStud:ex 30, trafikelevex SJ 33, stat:skr\nSJ 33’, trafikinsp Malmö städs spårvägar\n42, trafikch där sed 47i - Länstrafikled\nMalmöh l 44-46. - Inneh ett flert patent\nå biljettmaskiner o redovisn:system.\n-Skr: upps i sv o utl trafiktidskr.\nGift 36 m Svea Axelsson f 13, dtr t\nDavid A o Eva Lindström. - Barn: Inger\nf 36, Gunnar f 40, Eva f 43.\n\nEDEBRAND, B E RAGNVALD,\npostmästare, Sölvesborg, f i Örebro 6/3/15\nav snickarmäst Erik Andersson o Anna\nMaria Svensson.\n\nStud:ex Linkpg 35, Norrkpgs hdlsgymn\n36, postass :ex Sthlm 39, l:e postass\nMalmö 49, kontrollör Ludvika 52, postmast\nMalung 56, fältpostmäst sv FN-bat\nKongo 62, postmast Sölvesborg sed 63.\n-Utm: FNftjM. - Hobbies: jakt, fiske,\nfotografering.\n\nGift 3® m Ingrid Lindén f 17), dtr t fabr\nKarl L o Astrid Andersson. - Barn:\nBengt f 40, Gunilla f 41, Lars f 44.\n\n",
    "structured": {
        "0": {
            "full_name": "B Gunnar Edberg",
            "location": "Barsebäck",
            "occupation": "kyrkoherde",
            "birth_details": {
                "date": "20/07/1906",
                "place": "Ängelholm",
                "parents": "Nils E o Carolina Holmberg"
            },
            "education": [
                {
                    "degree": "Stud:ex Lund",
                    "year": "1925"
                },
                {
                    "degree": "teol kand",
                    "year": "1930"
                }
            ],
            "career": [
                {
                    "position": "past:adj Borlunda",
                    "years": {
                        "start_year": 1931,
                        "end_year": 1933
                    }
                },
                {
                    "position": "v kommin Vä",
                    "years": {
                        "start_year": 1933,
                        "end_year": "NULL"
                    }
                },
                {
                    "position": "stiftsadj",
                    "years": {
                        "start_year": 1935,
                        "end_year": "NULL"
                    }
                },
                {
                    "position": "kyrkoh Barsebäck",
                    "years": {
                        "start_year": 1941,
                        "end_year": "NULL"
                    }
                }
            ],
            "family": {
                "spouse": "Gunnel Angberg",
                "marriage_year": "1933",
                "children": "NULL"
            },
            "hobbies": [
                "esperanto"
            ]
        },
        "1": {
            "full_name": "M Carin Ede-Jacobsson",
            "location": "Lund",
            "occupation": "läroverksadjunkt",
            "birth_details": {
                "date": "4/1/1929",
                "place": "Karlskrona",
                "parents": "major Gunnar Ede o Märta Wahrolén"
            },
            "education": [
                {
                    "degree": "Stud:ex",
                    "year": "1948"
                },
                {
                    "degree": "fil mag Lund",
                    "year": "1943"
                }
            ],
            "career": [
                {
                    "position": "adj Slottsstadens samrealsk Malmö",
                    "years": {
                        "start_year": 1953,
                        "end_year": 1953
                    }
                },
                {
                    "position": "eo adj realsk Kirsberg",
                    "years": {
                        "start_year": 1954,
                        "end_year": 1956
                    }
                },
                {
                    "position": "hal f g Malmö",
                    "years": {
                        "start_year": 1956,
                        "end_year": 1957
                    }
                },
                {
                    "position": "adj Bergask",
                    "years": {
                        "start_year": 1957,
                        "end_year": 1958
                    }
                },
                {
                    "position": "Lunds stads sk",
                    "years": {
                        "start_year": 1958,
                        "end_year": "NULL"
                    }
                }
            ],
            "family": {
                "spouse": "doc Ulf Jacobsson",
                "marriage_year": "1953",
                "children": [
                    {
                        "name": "Anne",
                        "birth_year": "1959"
                    },
                    {
                        "name": "Hans",
                        "birth_year": "1962"
                    }
                ]
            }
        },
        "2": {
            "full_name": "Karl Erik H Edebrand",
            "location": "Malmö",
            "occupation": "trafikchef",
            "birth_details": {
                "date": "9/12/1910",
                "place": "Örebro",
                "parents": "snickarm Erik Andersson o Anna Svensson"
            },
            "education": [
                {
                    "degree": "Stud:ex",
                    "year": "1930"
                }
            ],
            "career": [
                {
                    "position": "stat:skr SJ",
                    "years": {
                        "start_year": 1933,
                        "end_year": 1933
                    }
                },
                {
                    "position": "trafikinsp Malmö städs spårvägar",
                    "years": {
                        "start_year": 1942,
                        "end_year": "NULL"
                    }
                }
            ],
            "family": {
                "spouse": "Svea Axelsson",
                "marriage_year": "1936",
                "children": [
                    {
                        "name": "Inger",
                        "birth_year": "1936"
                    },
                    {
                        "name": "Gunnar",
                        "birth_year": "1940"
                    },
                    {
                        "name": "Eva",
                        "birth_year": "1943"
                    }
                ]
            },
            "hobbies": [
                "NULL"
            ]
        },
        "3": {
            "full_name": "B E Ragnvald Edebrand",
            "location": "Sölvesborg",
            "occupation": "postmästare",
            "birth_details": {
                "date": "6/3/1915",
                "place": "Örebro",
                "parents": "snickarmäst Erik Andersson o Anna Maria Svensson"
            },
            "education": [
                {
                    "degree": "Stud:ex",
                    "year": "1935"
                },
                {
                    "degree": "Norrkpgs hdlsgymn",
                    "year": "1936"
                }
            ],
            "career": [
                {
                    "position": "kontrollör Ludvika",
                    "years": {
                        "start_year": 1952,
                        "end_year": 1956
                    }
                },
                {
                    "position": "fältpostmäst sv FN-bat Kongo",
                    "years": {
                        "start_year": 1962,
                        "end_year": 1963
                    }
                },
                {
                    "position": "postmast Sölvesborg",
                    "years": {
                        "start_year": 1963,
                        "end_year": "NULL"
                    }
                }
            ],
            "family": {
                "spouse": "Ingrid Lindén",
                "marriage_year": "193x",
                "children": [
                    {
                        "name": "Bengt",
                        "birth_year": "1940"
                    },
                    {
                        "name": "Gunilla",
                        "birth_year": "1941"
                    },
                    {
                        "name": "Lars",
                        "birth_year": "1944"
                    }
                ]
            },
            "hobbies": [
                "jakt",
                "fiske",
                "fotografering"
            ]
        }
    }
}