{
    "original": "ERICSON, CURT E, major, Lyckeby,\nf i Sala 7/11/16 av dir Sigfrid E o Tora\nBrodin.\n\nMajor i utbildn:off KA 2 59, ch spärrbat\nKA 2 o ch Kungsholmsfortet sed 65.\n-KSHS ak 451, stabsk 46, tekn k 47.\n-Ordf skolstyr 63, v ordf 64-65. - Medl\nColdinuO. - Utm: RSO, SvmifbSM,\nSCF-ftjtG, Friv bfb ftjt, Blek bfbSM. -\nHobbies: jakt, fiske, företagsekonomi.\nGift 41 m Britt-Louise Löwenadler f 19,\ndtr t kapt Percy L o h h, f Ekblom.\n-Barn: Lars f 43, Håkan f 47.\n\nERIKSSON, K EINAR S, kyrkoherde,\n\nBjuv, f i Hbg 18/6/08 av snick Otto E o\nMatilda Nilsson.\n\nStud:ex 28, teol kand Lund 33-, past:adj\nRingamåla 3’3i, past:adj o v past Ottarp\n3&gt;5, kyrkoadj Svalöv 40, Billesholm 48,\nkommin Bjuv 51, kyrkoh där sed 65.\nGift 37 m Sylvia Christoferson f 10, dtr\nt köpm Carl C o Johanna Persson.\n-Barn: Margareta f 42, Johannes f 44,\nLars f 45.\n\nERIKSON,    S    EINAR,    juvelerare,\n\nKarlshamn, f i Västervik 30/3/16 av\növersköt Per-Olof E o Eva Fagerberg.\nAnst h hovjuv Eric G Anderson\nVästervik 29-37 o 3’9-47-, h jur Olle Svensson\nKarlshamn 37’-3 8, h juv Axel Ohlson\nVäxjö 3’8, inneh ab Einar Erikson guld-\n\nsm :af f sed 47. - Styr :led Karlshamns\nfabr &amp; hantv:fören 5&lt;2, Karlshamns\ngym-n :f ören 52, Högadals idr sällsk 65.\n-Medl M-n, Odd Fellow. - Utm:\nKarlshamns sf SM o ftjt, Blek gymn:förb SM.\n- Hobby: sport.\n\nGift 39 m Jane Moberg f 14, dtr t\nexp:-förest Carl M o Seidi Fresk. - Barn:\nJanolow f 41, Leif f 44.\nERIKSSON, ELLY D J A, fd\nriksdagsledamot, Ängelholm, f i Nässjö S/S/\n97 av ing Johan Dahlström o Ida\nAndersson.\n\nHdlssk Jönkpg; barnav:man Ängelholm\n33’-4a - Led AK 52-65 (s), direktionen f\nKronpr Victorias kustsana t sed 57,\nhuvudman Engelholms sparbk sed1 45, v\nordf De vanföras riksförb sed 57,\nstyr:-led Soc:dem kvinnoförb sed 20. - Led\nStadsfullm 37&gt;-63i, skolsUyr 35^49,\nbarnav:-nd sed 35», ordf hemhj:nd sed 38i, Stift\npens :hem sed 47, led mödrahj:nd 38-60,\nkristidsnd! 40-45, nykterh:nd 40-50,\nlek-sk:komm sed 55’, läraskomm f bygg av\ndaghem sed 65’.\n\nGift 15 m jv:tjm Ernst Eriksson d 35.\n-Barn: Karl-Erik f 15, Anne-Marie f 18,\nKarl-Gösta f 20.\n\n",
    "structured": {
        "0": {
            "full_name": "Curt E Ericson",
            "location": "Lyckeby",
            "occupation": "Major",
            "birth_details": {
                "date": "07/11/1916",
                "place": "Sala"
            },
            "education": [
                {
                    "degree": "KSHS",
                    "year": "1951",
                    "institution": "ak 451"
                },
                {
                    "degree": "stabsk",
                    "year": "1946",
                    "institution": "NULL"
                },
                {
                    "degree": "tekn k",
                    "year": "1947",
                    "institution": "NULL"
                }
            ],
            "career": [
                {
                    "position": "Ordf skolstyr",
                    "years": {
                        "start_year": 1963,
                        "end_year": 1965
                    },
                    "organization": "NULL"
                }
            ],
            "family": {
                "spouse": "Britt-Louise Löwenadler",
                "marriage_year": "1941",
                "children": [
                    {
                        "name": "Lars",
                        "birth_year": "1943"
                    },
                    {
                        "name": "Håkan",
                        "birth_year": "1947"
                    }
                ]
            },
            "hobbies": [
                "jakt",
                "fiske",
                "företagsekonomi"
            ]
        },
        "1": {
            "full_name": "K Einar S Eriksson",
            "location": "Bjuv",
            "occupation": "Kyrkoherde",
            "birth_details": {
                "date": "18/06/1908",
                "place": "Hbg"
            },
            "education": [
                {
                    "degree": "Stud:ex",
                    "year": "1928",
                    "institution": "NULL"
                },
                {
                    "degree": "teol kand",
                    "year": "1933",
                    "institution": "Lund"
                }
            ],
            "career": [
                {
                    "position": "kommin",
                    "years": {
                        "start_year": 1951,
                        "end_year": 1965
                    },
                    "organization": "Bjuv"
                }
            ],
            "family": {
                "spouse": "Sylvia Christoferson",
                "marriage_year": "1937",
                "children": [
                    {
                        "name": "Margareta",
                        "birth_year": "1942"
                    },
                    {
                        "name": "Johannes",
                        "birth_year": "1944"
                    },
                    {
                        "name": "Lars",
                        "birth_year": "1945"
                    }
                ]
            }
        },
        "2": {
            "full_name": "S Einar Erikson",
            "location": "Karlshamn",
            "occupation": "Juvelerare",
            "birth_details": {
                "date": "30/03/1916",
                "place": "Västervik"
            },
            "education": [],
            "career": [],
            "family": {
                "spouse": "Jane Moberg",
                "marriage_year": "1939",
                "children": [
                    {
                        "name": "Janolow",
                        "birth_year": "1941"
                    },
                    {
                        "name": "Leif",
                        "birth_year": "1944"
                    }
                ]
            },
            "hobbies": [
                "sport"
            ]
        },
        "3": {
            "full_name": "Elly D J A Eriksson",
            "location": "Ängelholm",
            "occupation": "Fd riksdagsledamot",
            "birth_details": {
                "date": "NULL",
                "place": "Nässjö S/S/"
            },
            "education": [
                {
                    "degree": "Hdlssk",
                    "year": "NULL",
                    "institution": "Jönkpg"
                }
            ],
            "career": [
                {
                    "position": "direktionen f Kronpr Victorias kustsana t",
                    "years": {
                        "start_year": 1957,
                        "end_year": 1965
                    },
                    "organization": "NULL"
                }
            ],
            "family": {
                "spouse": "Ernst Eriksson",
                "marriage_year": "1915",
                "children": [
                    {
                        "name": "Karl-Erik",
                        "birth_year": "1915"
                    },
                    {
                        "name": "Anne-Marie",
                        "birth_year": "1918"
                    },
                    {
                        "name": "Karl-Gösta",
                        "birth_year": "1920"
                    }
                ]
            }
        }
    }
}