{
    "original": "EKEDAHL, NILS J, tandläkare,\nKarlskrona, f i Karlskrona 20/8/07 av dir\nJulius E o Anna Allard.\nStud:ex   Karlskrona   26,   tysk   tandl:ex\nLeipzig 30, tandl:ex Sthlm 32, ass:tandl\nSthlm 32, priv:prakt Karlskrona sed 32.\nGift 53 m Gun Arrhenius f 31. - Barn:\nClaes f 55, Stefan f 56, Mikael f 58,\nMagnus f 60, Harald f 64.\n\nEKEGREN, ERIK G I, direktör,\nMalmö, f i Malmö 17/8/28 av postkontr\nGustaf E o Edith Regnér.\nStud:ex 47, Malmö hdlsgymn 48, DHS\n53, kamr o ökon :ch ab A Påhlssons\nbageri Malmö 53-56, försäljn:ch 56, v\nverkst dir där sed 60. - Styr:led Pågens\nfamiljebageri ab, ab SB-Center, ab\nDiplomglass, Pååls bröd ab, Gottfrid\nNilsson snickerifabr ab. - Hobby: båtsport.\nGift 53 m Rigmor Nilsson f 29, dtr t\nbyggn:ing Gottfrid N o Ingeborg\nLars^-son. - Barn: Törd f 56, Eva f 61, Sten\nf 63..\n\nEKELUND,   I   AXEL   W,   konstnär,\n\nMalmö, f i Landskrona 17/11/19 av\nkammarmusiker Nils E o Ester Carlsson.\nStud v sv målarskolor, Acad de la\nGran-dö Chaumiére Paris o Konstakad\nKöpen-h. - Sep:utst Malmö 46, 54, 55,\nÖrebro 531, delt i uttst Unga tecknare Sthlm\nsed 461, Sv:es allm konstfören sed 50,\nHbgs konstfören sed 48, Skånes\nkonstfören sed 51, Den Frie Köpenh sed 54,\ngrupputst Hbg 52, Växjö 53’, Malmö 54.\n- Repr i Nät :mus, Malmö, Hbgs, Växjö\no Örebro mus. - Medl1 KRO. - Hobbies:\nfiske, schack, sport.\n\nGift 52 m Gun Håkansson, dtr t\ninköpsch Ernst H’o’ Alma Jonsson. - Barn:\nLiv f 5©.\n\nEKELUND, CARL E M,\ndistriktsveterinär, Kungsbacka, f i Knista, Örebro l,\n20/11/05 av distr:vet, vet:med dr Joel E\no Helena Kjellman.\n\nStud:ex Örebro 251, VHS 3&lt;2, ch:vet\nÖrebro l hush:sällsk 35, distr:vet Strömstad\n571, Kungsbacka sed 63’. - Stadsfullm\nStrömsitiadi 59-62. - Medl Rotary, Svarta\nÖrnsO, sällsk NN. - Skr: Veterinäryrkets\nhistoria (Bokv Örebro 1); utg tidskr Vi\nråda 55, tidskr:art m m. - Utm: RNO,\nÖrebro l hushGM. - Hobbies: målning,\nbrid’ge, fiske, jakt.\n\nGift 32 m Sonja Mårtenson f 08!, dtr t\nstatl:insp Walter M o h h. - Barn: Maj\nf 34, Björn f 37, Agneta f 41.\n\n",
    "structured": {
        "0": {
            "full_name": "NILS J EKEDAHL",
            "location": "Karlskrona",
            "occupation": "tandläkare",
            "birth_details": {
                "date": "20/08/1907",
                "place": "Karlskrona",
                "parents": "Julius E o Anna Allard"
            },
            "education": [
                {
                    "degree": "Stud:ex",
                    "year": "1926",
                    "institution": "Karlskrona"
                },
                {
                    "degree": "tysk tandl:ex",
                    "year": "1930",
                    "institution": "Leipzig"
                },
                {
                    "degree": "tandl:ex",
                    "year": "1932",
                    "institution": "Sthlm"
                }
            ],
            "career": [
                {
                    "position": "ass:tandl",
                    "years": {
                        "start_year": 1932,
                        "end_year": "NULL"
                    },
                    "organization": "Sthlm"
                },
                {
                    "position": "priv:prakt",
                    "years": {
                        "start_year": 1932,
                        "end_year": "NULL"
                    },
                    "organization": "Karlskrona"
                }
            ],
            "family": {
                "spouse": "Gun Arrhenius",
                "marriage_year": "1953",
                "children": [
                    {
                        "name": "Claes",
                        "birth_year": "1955"
                    },
                    {
                        "name": "Stefan",
                        "birth_year": "1956"
                    },
                    {
                        "name": "Mikael",
                        "birth_year": "1958"
                    },
                    {
                        "name": "Magnus",
                        "birth_year": "1960"
                    },
                    {
                        "name": "Harald",
                        "birth_year": "1964"
                    }
                ]
            }
        },
        "1": {
            "full_name": "ERIK G I EKEGREN",
            "location": "Malmö",
            "occupation": "direktör",
            "birth_details": {
                "date": "17/08/1928",
                "place": "Malmö",
                "parents": "postkontr Gustaf E o Edith Regnér"
            },
            "education": [
                {
                    "degree": "Stud:ex",
                    "year": "1947",
                    "institution": "Malmö"
                },
                {
                    "degree": "Malmö hdlsgymn",
                    "year": "1948",
                    "institution": "Malmö"
                },
                {
                    "degree": "DHS",
                    "year": "1953",
                    "institution": "NULL"
                }
            ],
            "career": [
                {
                    "position": "kamr o ökon :ch",
                    "years": {
                        "start_year": 1953,
                        "end_year": 1956
                    },
                    "organization": "ab A Påhlssons bageri Malmö"
                },
                {
                    "position": "försäljn:ch",
                    "years": {
                        "start_year": 1956,
                        "end_year": "NULL"
                    },
                    "organization": "NULL"
                },
                {
                    "position": "verkst dir",
                    "years": {
                        "start_year": 1960,
                        "end_year": "NULL"
                    },
                    "organization": "ab A Påhlssons bageri Malmö"
                }
            ],
            "family": {
                "spouse": "Rigmor Nilsson",
                "marriage_year": "1953",
                "children": [
                    {
                        "name": "Törd",
                        "birth_year": "1956"
                    },
                    {
                        "name": "Eva",
                        "birth_year": "1961"
                    },
                    {
                        "name": "Sten",
                        "birth_year": "1963"
                    }
                ]
            },
            "hobbies": [
                "båtsport"
            ]
        },
        "2": {
            "full_name": "AXEL W EKELUND",
            "location": "Malmö",
            "occupation": "konstnär",
            "birth_details": {
                "date": "17/11/1919",
                "place": "Landskrona",
                "parents": "kammarmusiker Nils E o Ester Carlsson"
            },
            "career": [
                {
                    "position": "NULL",
                    "years": {
                        "start_year": "NULL",
                        "end_year": "NULL"
                    },
                    "organization": "NULL"
                }
            ],
            "family": {
                "spouse": "Gun Håkansson",
                "marriage_year": "1952",
                "children": [
                    {
                        "name": "Liv",
                        "birth_year": "1950"
                    }
                ]
            },
            "community_involvement": [
                {
                    "role": "NULL",
                    "organization": "NULL",
                    "years": "NULL"
                }
            ],
            "hobbies": [
                "fiske",
                "schack",
                "sport"
            ]
        },
        "3": {
            "full_name": "CARL E M EKELUND",
            "location": "Kungsbacka",
            "occupation": "distriktsveterinär",
            "birth_details": {
                "date": "20/11/1905",
                "place": "Knista, Örebro l",
                "parents": "distr:vet, vet:med dr Joel E o Helena Kjellman"
            },
            "education": [
                {
                    "degree": "Stud:ex",
                    "year": "1925",
                    "institution": "Örebro"
                },
                {
                    "degree": "VHS",
                    "year": "1932",
                    "institution": "NULL"
                },
                {
                    "degree": "ch:vet",
                    "year": "NULL",
                    "institution": "Örebro l hush:sällsk"
                },
                {
                    "degree": "distr:vet",
                    "year": "1957",
                    "institution": "Strömstad"
                }
            ],
            "career": [
                {
                    "position": "distr:vet",
                    "years": {
                        "start_year": 1957,
                        "end_year": "NULL"
                    },
                    "organization": "Kungsbacka"
                }
            ],
            "family": {
                "spouse": "Sonja Mårtenson",
                "marriage_year": "1932",
                "children": [
                    {
                        "name": "Maj",
                        "birth_year": "1934"
                    },
                    {
                        "name": "Björn",
                        "birth_year": "1937"
                    },
                    {
                        "name": "Agneta",
                        "birth_year": "1941"
                    }
                ]
            },
            "publications": [
                {
                    "title": "Veterinäryrkets historia",
                    "year": "1941",
                    "type": "NULL"
                }
            ],
            "community_involvement": [
                {
                    "role": "NULL",
                    "organization": "NULL",
                    "years": "NULL"
                }
            ],
            "honorary_titles": [
                {
                    "title": "RNO",
                    "institution": "NULL",
                    "year": "NULL"
                },
                {
                    "title": "Örebro l hushGM",
                    "institution": "NULL",
                    "year": "NULL"
                }
            ],
            "hobbies": [
                "målning",
                "brid’ge",
                "fiske",
                "jakt"
            ]
        }
    }
}