{
    "original": "ADNER, CARL ADOLF, leg läkare,\nVällingby, f i Alfredshem, Västernorrl\nl, 25/7/18 av disp Edvin A o Ruth\nLund.\n\nStud’ex Umeå 36, med kand Sthlm 39,\nmed lic Lund 45, underläk Falkpgs las\n46, Flensburgska barnsjh 47, underläk\nöronklin Malmö allm sjh 47-53, kir klin\n54, e läk Trelleborgs las 55, underläk\nöronavd Södersjh 55, l:e underläk sed\n55 o bitr överläk öronavd Sabbatsb sjh\nsed 57. - Skr i otiatri.\nGift 44 m med lic Britta Redig f 19,\ndtr t skeppsred Sven R o Elin\nWestborg. - Barn: Lisbeth f 45, Nils f 47,\nSven f 52, Kerstin f 56, Gustaf f 59.ADOLFSSON, ALLAN G H,\navdelningschef, Enskede, f i Sthlm 12/7/18\nav metallarb Gustav A o Elsa Eriksson.\nIFU 37 o 41, anst Folksam 33, avd:ch\nsed 54. - Hobby: idrott.\nGift 42 m Inga Friberg f 19. - Barn:\nBo f 45, Anne f 50.\n\nADOLPHSON, G EDVIN,\nskådespelare, regissör, Solna, f i Furingstad,\nÖstergötl l, 25/2/93 av entreprenör Gustav\nA o Maria Ström.\n\nFolksk o Ebersteinska sk Norrkpg,\ndebut v arb:fören teat Norrkpg, eng\nLindroths o Karin Swanströrns sällsk,\nFolkets teat (Skådebanan) 18,\nDjurgårds-teat 20, Intima teat 20-22, Vasateat\n23-25, Lorensb:teat 26, Oscarsteat 27-32,\nDram teat 32-35, senare gästspel där o å\nandra teat i de nord huvudst:na, ledare\nav Oscarsteat 38-39. - Filmroller i Sv:e\no utl, Skandinaviens l:e\nIjudfilmsregis-sör. - Ordf Konstn:ringen 43, v ordf\nSv teaterförb 44-58, ordf förb FU,\nstormast TSO 54, hedL Kristianst nät Lund,\nÖstg nät Upps, Konstn:ringen, Sv\nteaterförb, Norsk skuespillerforb, Finl\nkonstnrförb, TSO. - Stud:res Europa s\nAnders de Wahlstip 24. - Skr:\nradiopjäser. - Utm: RNO RVO, Litt et Art,\nFinlLO, FinlFrM, ChX:sFrM, S:t\nEriksined. - Hobbies: sjö- o hästsport.\nGift 4) m Ulla Balle-Jensen f 22.\n\n",
    "structured": {
        "0": {
            "full_name": "ADNER, CARL ADOLF",
            "location": "Vällingby",
            "occupation": "leg läkare",
            "birth_details": {
                "date": "25/07/1918",
                "place": "Alfredshem, Västernorrland",
                "parents": "disp Edvin A o Ruth Lund"
            },
            "education": [
                {
                    "degree": "med kand",
                    "year": "1939",
                    "institution": "Sthlm"
                },
                {
                    "degree": "med lic",
                    "year": "1945",
                    "institution": "Lund"
                }
            ],
            "career": [
                {
                    "position": "underläk",
                    "years": {
                        "start_year": 1955,
                        "end_year": 1957
                    },
                    "organization": "öronavd Sabbatsb sjh"
                }
            ],
            "family": {
                "spouse": "Britta Redig",
                "marriage_year": "1944",
                "children": [
                    {
                        "name": "Lisbeth",
                        "birth_year": "1945"
                    },
                    {
                        "name": "Nils",
                        "birth_year": "1947"
                    },
                    {
                        "name": "Sven",
                        "birth_year": "1952"
                    },
                    {
                        "name": "Kerstin",
                        "birth_year": "1956"
                    },
                    {
                        "name": "Gustaf",
                        "birth_year": "1959"
                    }
                ]
            }
        },
        "1": {
            "full_name": "ADOLFSSON, ALLAN G H",
            "location": "Enskede",
            "occupation": "avdelningschef",
            "birth_details": {
                "date": "12/07/1918",
                "place": "Sthlm",
                "parents": "metallarb Gustav A o Elsa Eriksson"
            },
            "education": [
                {
                    "degree": "IFU",
                    "year": "1937",
                    "institution": "Sthlm"
                },
                {
                    "degree": "IFU",
                    "year": "1941",
                    "institution": "Sthlm"
                }
            ],
            "career": [
                {
                    "position": "avd:ch",
                    "years": {
                        "start_year": 1954,
                        "end_year": null
                    },
                    "organization": "Folksam"
                }
            ],
            "family": {
                "spouse": "Inga Friberg",
                "marriage_year": "1942",
                "children": [
                    {
                        "name": "Bo",
                        "birth_year": "1945"
                    },
                    {
                        "name": "Anne",
                        "birth_year": "1950"
                    }
                ]
            },
            "hobbies": [
                "idrott"
            ]
        },
        "2": {
            "full_name": "ADOLPHSON, G EDVIN",
            "location": "Solna",
            "occupation": "skådespelare, regissör",
            "birth_details": {
                "date": "25/02/1893",
                "place": "Furingstad, Östergötland",
                "parents": "entreprenör Gustav A o Maria Ström"
            },
            "education": [
                {
                    "degree": "Folksk",
                    "year": null,
                    "institution": "Norrköping"
                },
                {
                    "degree": "Ebersteinska sk",
                    "year": null,
                    "institution": "Norrköping"
                }
            ],
            "career": [
                {
                    "position": "ledare",
                    "years": {
                        "start_year": 1938,
                        "end_year": 1939
                    },
                    "organization": "Oscarsteat"
                }
            ],
            "family": {
                "spouse": "Ulla Balle-Jensen",
                "marriage_year": null,
                "children": []
            },
            "community_involvement": [
                {
                    "role": "ordf",
                    "organization": "Konstn:ringen",
                    "years": "43"
                },
                {
                    "role": "v ordf",
                    "organization": "Sv teaterförb",
                    "years": "44-58"
                }
            ],
            "honorary_titles": [
                {
                    "title": "RNO",
                    "institution": null,
                    "year": null
                },
                {
                    "title": "RVO",
                    "institution": null,
                    "year": null
                },
                {
                    "title": "Litt et Art",
                    "institution": null,
                    "year": null
                },
                {
                    "title": "FinlLO",
                    "institution": null,
                    "year": null
                },
                {
                    "title": "FinlFrM",
                    "institution": null,
                    "year": null
                },
                {
                    "title": "ChX:sFrM",
                    "institution": null,
                    "year": null
                },
                {
                    "title": "S:t Eriksined",
                    "institution": null,
                    "year": null
                }
            ],
            "hobbies": [
                "sjö- o hästsport"
            ]
        }
    }
}