{
    "original": "ANDERSSON-KOTTÖ, IRMA I,\ndocent, Lidingö, f i Enkpg 1/1/95 av dir\nP J A o Kristina Nilsson.\nStud StHS, i Berlin, Wien, Haarlem,\nErfurt, Odense, D Se London, fil\nhed:-dr Sthlm 52, doc i ärftlighetslära StU\nsed 41. - Ärftlighrforskare Univ of\nLondon 19-39, Wenner-Grens inst Sthlm\n39-61. - Skr: ang ärftlighetsförhåll\nhos ormbunkar, kloroplastkaraktärer,\nartkorsn i Dianthus,\nhöger-vänster-vridn i Limnaea, antigen i vissa\nsvampar o aminosyrebildn i mutanter o\nnormalstam av Neurospora.\n\nANDÖ, TORSTEN G, direktör, Nacka,\nf i Sthlm 15/4/16 av yrkeslär Albert A\n\n0  Elise Malmborg.\n\nStudiex 35, KTH 42, avd ring ab Tudor\n42, övering ab Nyby metallverk Nyby\nbruk 44, disp ab Sv skruv Gnosjö 50,\nverkst dir ab Industridiamanter Sthlm\nsed 54, Carl Setterwall! &amp; Co ab Sthlm\nsed 60 (vice 58). - Styr: led ab Sv\nskruv 50-54, ab Industridiamanter 54,\nCarl Setterwall &amp; Co ab 58, ab Sv\nexporttackjärn’ 60, styr:ordf\nIndustriediamanten GmbH Hamburg 56. - Medl\nRotary, S:t Örjan® gille.\nGift 42 m Ewa Johansson, dtr t\nsjökapten Edvin J o Ingrid Jonson. - Barn:\nIngegärd f 43, Göran f 49.\nANDR/E, ANDERS J, kapten,\nBandhagen, f i G:a Upps 25/9/19 av biskop\nTor A o Ellen Gustafsson.\nStud:ex 38, off:ex 42, KHS 50-52, kapt\n\n1  4 52, adjut IV milbefstab Sthlm sed\n59. - Hobby: historia.\n\nGift 47 m Kerstin Andersson, dtr t fd\nekonomichef Carl A o Jenny Ericsson.\n- Barn: Mikael f 56.\n\nANDRÉ, C BERTIL, byrådirektör,\nVällingby, f i Järpås, Skarab l, 3/6/17\nav köpman Carl A o Hulda Carlsson.\nStud:ex Gbg 37, jur kand’ Sthlm 45,\ntingstjg S Roslags döms 45^49, tjg\nvät-tenfrstyr 49, byrådir sed 54. -\nResioff:-ex 40, kapt I 12 res sed 51. - V ordf\nhyresnd sed 53. - Medl TimmermO.\nGift 46 m Margot Ekenfors, dtr t\nkapten Karl E o Lisa Holmström. - Barn:\nChristina f 50, Elisabeth f 55.\n\nANDRÉ, HARALD, fd operachef,\nSthlm, f i Motala 14/6/79 av grosshandl\nJohn Anderson o Mina A.\nStudiex Sthlm 97, stud Upps 98-99,\nelev vid konservat Leipzig 00-03’ o\nSternska konservat Berlin 04U05, pianist\n\n0   repetitör Berlin 05-07,  musikkritiker\nSvD   07   o   Sthlms   Dagbl   08-10,   l:e\nregissör  K  teat  07-08,   10-24  o   32-36,\ngästregissör   Scala   Milano   22   o   29,\nCovent Garden London 37, dir:ass ab\nElectrolux 24-26, huvudred Sthlms Dagbl\n26-28,   NDA   36-38,   ch  K  teat   39-49,\ngästregissör   där.   -   LM A  41.   -   Utm:\nKVOlkl,   RNO,   KDDOlgr,   KFinlLO\n\n1 kl,   KBLeopILsO,   KBrasSKO,   KNed\nONO,KTjslVLO, KTyskÖO, OffFrdel’Ip.\nGift 08-26 m operettsångerskan Gerda\nMalmqvist f 76 d 60 i h 2:a akt, dtr\nt kronofogde Nils M o Kristin DahlL\nbeck.\n\nANDRÉ, LARS B H, byråchef,\nLidingö, f i Skövde 12/3/97 av fabr Frans\nA o Sofia Andersson.\n\nStudiex 15, KTH 20, anst öl ind:företag\nTyskl o USA 22-27, soc:styr 28-30 o\n32-34, tf yrkesinsp Karlstad 30,\nyrkesinsp Gävle 34, byråch arb:skyddsstyr 49,\ngen:dir:s stf sed 49. - Styr:led Ahlafors\nnya spinneri ab 44, LSvTF 36. - Utm:\nRNO, RVO.\n\nGift 1) 24-36 m Gertrud Ehnberg, 2)\n39 m Lisa Leman. - Barn: Birgit f 26,\nOve f 42.\n\nANDR/E, S A INGMAR,\nkomminister, Sthlm, f i Motala 2/8/07 av kyrkoh\nEskil A o Sigrid Andersson.\nStud:ex Sthlm 25, teol fil:ex 27, teol\nkand o prästv 32, pastor Iggesunds\nbruk 32, kyrkoh\nBalingsta-Hagby-Ramsta 41, kommin Matteus Sthlm sed\n55.\n\nGift m Ingrid Hagardt. - Barn: Sten\nf 36, Gunilla f 38, Cecilia f 40,\nMargareta f 43, Bengt f 49.\n\nANDRÉASON, LOTTIE M, violinist,\nSthlm, f i Berlin 21/7/03 av\nträbildhuggare Fritz Borisch o Marie Henschke.\nStud musikkonservat Sthlm, verksam ss\nsolist sed 26, debutkonsert 28, radioork\nsed 33, medl Berwaldtrion.\nGift 24 m musikdir Martin Andreasen\nf 93.\n\nANDRÉASSON, ÅKE H, direktör,\nNäsbypark, f i Sthlm 4/7/12 av\nbok-handl Hugo A o Ester Ohlsson.\nStudiex 32, HHS 34, IFU 37, tjm\nförsäkr:bol Valland 34, Städernas\nför-säkr:bol 37, planer:ch o kamr där 46,\nskaderegi:ch o dir:ass sed 57. -\nStyr:-led Skadeförsäkr:männens\ndiskussionsklubb 50, led Ansvarigh:försäkr:s\nper-sonskadend 48-58, ersätt\nTrafikförsäkr:-anst:najs nd 49-56, led där 57-58, lär\nIFU 56-57, föreläs stat poMssk 55-58,\nmedl Sv försäkr:fören 34. - Hobby:\nsjösport.\n\nGift 41 m Ingrid Sjögren f 14, dtr t\nförste postass K S o Signe Gustafsson.\n- Barn: M’argareta f 43, Bo f 45, Hans\nf 51, Mats f 57.\n\nANDRÉASSON-BJÖRNDAHL,\nGUNNEL B S, prakt läkare, Lidingö, f i\nÖsmo, Sthlms l, 15/4/21 av kamrer Erik\nLövgren o Anna Andréasson.\nStud:ex 41, med kand 45, med lic 50,\ntf prov:läk Åsele disitr 48, vik 2:e\nunderläk med avd Jönkpgs las 50,\nunderläk Penstonsstyr sjh Tranås 51, vik\nunderläk med avd Norrkpgs las 51-53,\nBB o gynekol avd 52, röntgenavd Gävle\nlas 53-54, 2:e underläk Länssanat\nUtt-ran 54-55, prakt läk Lidingö sed 55,\nGift 54 m l:e byråass Sixten Björndahl\nf 19. - Barn: Per f 55, Lars f 57.\n\n",
    "structured": {
        "0": {
            "full_name": "ANDERSSON-KOTTÖ, IRMA I",
            "location": "Lidingö",
            "occupation": "docent",
            "birth_details": {
                "date": "01/01/1895",
                "place": "Enköping"
            },
            "education": [
                {
                    "degree": "Stud StHS",
                    "year": "1941",
                    "institution": "Stockholms Högskola"
                },
                {
                    "degree": "fil hed:-dr",
                    "year": "1952",
                    "institution": "Stockholm"
                }
            ],
            "career": [
                {
                    "position": "Ärftlighrforskare",
                    "years": {
                        "start_year": 1941,
                        "end_year": 1961
                    },
                    "organization": "Wenner-Grens inst Sthlm"
                }
            ],
            "family": {
                "spouse": "NULL",
                "marriage_year": "NULL",
                "children": []
            }
        },
        "1": {
            "full_name": "ANDÖ, TORSTEN G",
            "location": "Nacka",
            "occupation": "direktör",
            "birth_details": {
                "date": "15/04/1916",
                "place": "Stockholm"
            },
            "education": [],
            "career": [
                {
                    "position": "vice 58",
                    "years": {
                        "start_year": 1960,
                        "end_year": "NULL"
                    },
                    "organization": "Carl Setterwall! & Co ab Sthlm"
                }
            ],
            "family": {
                "spouse": "Ewa Johansson",
                "marriage_year": "1942",
                "children": [
                    {
                        "name": "Ingegärd",
                        "birth_year": "1943"
                    },
                    {
                        "name": "Göran",
                        "birth_year": "1949"
                    }
                ]
            }
        },
        "2": {
            "full_name": "ANDR/E, ANDERS J",
            "location": "Bandhagen",
            "occupation": "kapten",
            "birth_details": {
                "date": "25/09/1919",
                "place": "G:a Uppsala"
            },
            "education": [],
            "career": [],
            "family": {
                "spouse": "Kerstin Andersson",
                "marriage_year": "1947",
                "children": [
                    {
                        "name": "Mikael",
                        "birth_year": "1956"
                    }
                ]
            }
        },
        "3": {
            "full_name": "ANDRÉ, C BERTIL",
            "location": "Vällingby",
            "occupation": "byrådirektör",
            "birth_details": {
                "date": "03/06/1917",
                "place": "Järpås, Skaraborgs län"
            },
            "education": [
                {
                    "degree": "Stud:ex Gbg",
                    "year": "1937",
                    "institution": "Göteborg"
                },
                {
                    "degree": "jur kand’",
                    "year": "1945",
                    "institution": "Stockholm"
                }
            ],
            "career": [
                {
                    "position": "byrådir",
                    "years": {
                        "start_year": 1954,
                        "end_year": "NULL"
                    },
                    "organization": "NULL"
                }
            ],
            "family": {
                "spouse": "Margot Ekenfors",
                "marriage_year": "1946",
                "children": [
                    {
                        "name": "Christina",
                        "birth_year": "1950"
                    },
                    {
                        "name": "Elisabeth",
                        "birth_year": "1955"
                    }
                ]
            }
        },
        "4": {
            "full_name": "ANDRÉ, HARALD",
            "location": "Sthlm",
            "occupation": "fd operachef",
            "birth_details": {
                "date": "14/06/1879",
                "place": "Motala"
            },
            "education": [],
            "career": [],
            "family": {
                "spouse": "Gerda Malmqvist",
                "marriage_year": "1908",
                "children": []
            }
        },
        "5": {
            "full_name": "ANDRÉ, LARS B H",
            "location": "Lidingö",
            "occupation": "byråchef",
            "birth_details": {
                "date": "12/03/1897",
                "place": "Skövde"
            },
            "education": [],
            "career": [],
            "family": {
                "spouse": "Gertrud Ehnberg",
                "marriage_year": "1924",
                "children": [
                    {
                        "name": "Birgit",
                        "birth_year": "1926"
                    },
                    {
                        "name": "Ove",
                        "birth_year": "1942"
                    }
                ]
            }
        },
        "6": {
            "full_name": "ANDR/E, S A INGMAR",
            "location": "Sthlm",
            "occupation": "komminister",
            "birth_details": {
                "date": "02/08/1907",
                "place": "Motala"
            },
            "education": [],
            "career": [],
            "family": {
                "spouse": "Ingrid Hagardt",
                "marriage_year": "NULL",
                "children": [
                    {
                        "name": "Sten",
                        "birth_year": "1936"
                    },
                    {
                        "name": "Gunilla",
                        "birth_year": "1938"
                    },
                    {
                        "name": "Cecilia",
                        "birth_year": "1940"
                    },
                    {
                        "name": "Margareta",
                        "birth_year": "1943"
                    },
                    {
                        "name": "Bengt",
                        "birth_year": "1949"
                    }
                ]
            }
        },
        "7": {
            "full_name": "ANDRÉASON, LOTTIE M",
            "location": "Sthlm",
            "occupation": "violinist",
            "birth_details": {
                "date": "21/07/1903",
                "place": "Berlin"
            },
            "education": [],
            "career": [],
            "family": {
                "spouse": "Martin Andreasen",
                "marriage_year": "1924",
                "children": []
            }
        },
        "8": {
            "full_name": "ANDRÉASSON, ÅKE H",
            "location": "Näsbypark",
            "occupation": "direktör",
            "birth_details": {
                "date": "04/07/1912",
                "place": "Stockholm"
            },
            "education": [
                {
                    "degree": "Studiex 32",
                    "year": "1932",
                    "institution": "NULL"
                }
            ],
            "career": [
                {
                    "position": "skaderegi:ch o dir:ass",
                    "years": {
                        "start_year": 1957,
                        "end_year": "NULL"
                    },
                    "organization": "NULL"
                }
            ],
            "family": {
                "spouse": "Ingrid Sjögren",
                "marriage_year": "1941",
                "children": [
                    {
                        "name": "Margareta",
                        "birth_year": "1943"
                    },
                    {
                        "name": "Bo",
                        "birth_year": "1945"
                    },
                    {
                        "name": "Hans",
                        "birth_year": "1951"
                    },
                    {
                        "name": "Mats",
                        "birth_year": "1957"
                    }
                ]
            }
        },
        "9": {
            "full_name": "ANDRÉASSON-BJÖRNDAHL, GUNNEL B S",
            "location": "Lidingö",
            "occupation": "prakt läkare",
            "birth_details": {
                "date": "15/04/1921",
                "place": "Ösmo, Sthlms län"
            },
            "education": [
                {
                    "degree": "med kand",
                    "year": "1945",
                    "institution": "NULL"
                },
                {
                    "degree": "med lic",
                    "year": "1950",
                    "institution": "NULL"
                }
            ],
            "career": [],
            "family": {
                "spouse": "Sixten Björndahl",
                "marriage_year": "1954",
                "children": [
                    {
                        "name": "Per",
                        "birth_year": "1955"
                    },
                    {
                        "name": "Lars",
                        "birth_year": "1957"
                    }
                ]
            }
        }
    }
}