{
    "original": "ACKERFELDT, ALLAN E, verkst\ndirektör, Danderyd, f i Flen 6/4/13 av\ndir Emil A o Elisabeth Jansson.\nSkogssk Härnösand 33, avdxh Flens\nskogsbyrå 35-39, bränslechefsass\nSödermani l 42, tf bränslech där 43, verkst\ndir virkes ab Aspa 44, Powell Duffryn\nScand Timber Ltd ab sed 50, ab\nSin-dia (stynled), ab Nord Timber (styr:led).\nStynled oy Suomen Powell Duffryn Co\no oy Lindblom &amp; Co Finl, Deutsche\nDuffryn Import-Export\nHandelsgesell-schaft mbH Tyskl.\n\nGift 40 m Ellis Harri. - Barn: Krister\nf 41, Marita f 44, Kitty f 51, Mikael f\n55.\n\nACKEVI, STIG A V, arkitekt SIR,\nVällingby, f i Växjö 22/10/28 av fabr\nAxel Pettersson o Agnes Gustavsson.\nHKS, möbelsnickare Sthlms stads\nyr-kessk, Swansons snickerifabr 43-53,\ninrednrarkit Zimdals arkitrkontor ab 55,\nGustav Kaunitz arkit SAR ab sed 59.\n-Hobbies: musik, fiske.\nGift 53 m Vera Dahlman f 29, dtr t\nglasarb Frans D o Hulda Nilsson.\n-Barn: Sivonne f 55, Jan f 59.\n\nACKING, CARL-AXEL, arkitekt SAR,\nDjursholm, f i Hbg 8/3/10.\nHKS 34, KTH 39, spec:lär KTH\n42-47 o sed 58, huvudhär Konstfacksk\n47-57, eg arkit:verksamh Sthlm sed 41.\n-Styr:led ab’ Sv möbelfabnna Bodafors,\nSSF 47, Sv arkit:fören 41-56, ordf SID\n60. - Stud:res i Europa, USA, Mexico,\nJapan o Indien. - Bl arb: paviljonger\nHbgsutställn, Hässelby familjehotell,\nte-lebyggn Strängnäs, Eslöv o Upps, bank-byggn Hässleholm. - Repr: m möbler\nNatimus o Nord mus. - Skr: art i\nfackämnen i Form, Byggmästaren, Ord\no Bild m fi. - Utm: RVO,\nLunning-priset 52.\n\nGift 35 m Gulan Dahlström f 11.\n-Barn: Bengt f 40, Eva f 43, Lena f\n45, Inger f 47.\n\n",
    "structured": {
        "0": {
            "full_name": "ALLAN E ACKERFELDT",
            "location": "Danderyd",
            "occupation": "verkst direktör",
            "birth_details": {
                "date": "06/04/1913",
                "place": "Flen",
                "parents": "dir Emil A o Elisabeth Jansson"
            },
            "education": [
                {
                    "degree": "Skogssk",
                    "year": "1933",
                    "institution": "Härnösand"
                },
                {
                    "degree": "avdxh",
                    "year": "1935",
                    "institution": "Flens skogsbyrå"
                },
                {
                    "degree": "bränslechefsass",
                    "year": "NULL",
                    "institution": "Södermani l"
                }
            ],
            "career": [
                {
                    "position": "tf bränslech",
                    "years": {
                        "start_year": 1943,
                        "end_year": 1943
                    },
                    "organization": "Södermani l"
                },
                {
                    "position": "verkst dir",
                    "years": {
                        "start_year": 1944,
                        "end_year": 1949
                    },
                    "organization": "virkes ab Aspa"
                }
            ],
            "family": {
                "spouse": "Ellis Harri",
                "marriage_year": "1940",
                "children": [
                    {
                        "name": "Krister",
                        "birth_year": "1941"
                    },
                    {
                        "name": "Marita",
                        "birth_year": "1944"
                    },
                    {
                        "name": "Kitty",
                        "birth_year": "1951"
                    },
                    {
                        "name": "Mikael",
                        "birth_year": "1955"
                    }
                ]
            }
        },
        "1": {
            "full_name": "STIG A V ACKEVI",
            "location": "Vällingby",
            "occupation": "arkitekt SIR",
            "birth_details": {
                "date": "22/10/1928",
                "place": "Växjö",
                "parents": "fabr Axel Pettersson o Agnes Gustavsson"
            },
            "education": [
                {
                    "degree": "HKS",
                    "year": "NULL",
                    "institution": "Sthlms stads yrkessk"
                }
            ],
            "career": [
                {
                    "position": "inrednrarkit",
                    "years": {
                        "start_year": 1955,
                        "end_year": 1959
                    },
                    "organization": "Zimdals arkitrkontor ab"
                }
            ],
            "family": {
                "spouse": "Vera Dahlman",
                "marriage_year": "1953",
                "children": [
                    {
                        "name": "Sivonne",
                        "birth_year": "1955"
                    },
                    {
                        "name": "Jan",
                        "birth_year": "1959"
                    }
                ]
            },
            "hobbies": [
                "musik",
                "fiske"
            ]
        },
        "2": {
            "full_name": "CARL-AXEL ACKING",
            "location": "Djursholm",
            "occupation": "arkitekt SAR",
            "birth_details": {
                "date": "08/03/1910",
                "place": "Hbg",
                "parents": "NULL"
            },
            "education": [
                {
                    "degree": "HKS",
                    "year": "1934",
                    "institution": "NULL"
                }
            ],
            "career": [
                {
                    "position": "eg arkit:verksamh",
                    "years": {
                        "start_year": 1941,
                        "end_year": 1941
                    },
                    "organization": "Sthlm"
                }
            ],
            "family": {
                "spouse": "Gulan Dahlström",
                "marriage_year": "1935",
                "children": [
                    {
                        "name": "Bengt",
                        "birth_year": "1940"
                    },
                    {
                        "name": "Eva",
                        "birth_year": "1943"
                    },
                    {
                        "name": "Lena",
                        "birth_year": "1945"
                    },
                    {
                        "name": "Inger",
                        "birth_year": "1947"
                    }
                ]
            },
            "honorary_titles": [
                {
                    "title": "RVO",
                    "institution": "NULL",
                    "year": "NULL"
                },
                {
                    "title": "Lunningpriset",
                    "institution": "NULL",
                    "year": "1952"
                }
            ]
        }
    }
}