{
    "original": "AGNER,   KJELL,   med   dr,   docent,\n\nDrottningholm, f i Gbg 8/7/13 av\nfolk-skoleinsp, reg:pastorn Carl A o Stina\nSundberg.\n\nStud:ex Uddevalla 32, med kand Sthlm\n35, med lic Sthlm 43, doc i medicinsk\nkemi 42, med dr 45, eo aman, aman o tf\nlaborator Karol inst kem inst 33-40,\nass Med Nobelinst 40-42, doc:stip\n42-49, laborator i klinisk kemi Karol inst\n\n0  ö ver läk klin kem centrallab Seraf:las\n49-57, överläk klin kem lab S:t Görans\nsjh sed 57. - Rockef eller stip New York\nUniv   Department   of   Microbiology   o\nUniv of Wisconsin Department of\nChe-mistry  47-49.   -  Sekr  Sv  fören  f  klin\nkemi sed  54.  -   Utg: ett  100-tal skr  i\nenzymkemi   o   klin   kemi.   -   Utm:   Sv\nLäk:sällsk Alvarengapris 43.\n\nGift 47 m Ingegerd Sandefeldt f 24,\ndtr t distr:veterinär Harry S o Inez\nLönngren. - Barn: Carl f 50, Anders\nf 52, Erik f 55, Olof f 59.\n\nAGNESTIG, A RUBEN, ombudsman,\n\nNacka, f i Nora 17/12/97 av L\nAndersson o Olga Ekeblom.\nÖrebro tekn elem:sk 21, l:e omb:raan\nTjmförb f hotell o rest sed 37. - V ordf\nNacka Stadsfullm o dräts:kamm sed 50,\nlandst:man sed 51, ordf Saltsjöbadens\nbadhotell, kassaförvalt Hotell^ o\nrest:-tjm erkända arb:lösh:kassa sed 51.\n-Ansv utg av Restaurangtjänstemannen\nsed 37. - Sign: A-g.\n\nGift 23 m Karin Grahn f 04, dtr t Per\nJohan G o Greta Eklund.\n\nAGRELL, JAN G K,\nmilitäröverpsy-kolog, docent, Danderyd, f i Lund 6/8/18\nav prof Sigurd A o Anna Österman.\nStud:ex 38, fil kand Lund 43, fil lic\n46, fil dr 49, doc pedagogik o pedagog\npsykologi Upps sed 50, tf prof 50, FHS\n56, mil.’överpsykol o ch mil:psykolog inst\nSthlm sed 55. - Ordf Sv:es doc:förb\n54-56, sekr Sv psykologsamf 52-53,\nstyr:-led Målsmännens riksförb 54-58. - Skr:\nNyinrättade professurer inom filosof fak\n\n1   Lund  under   1800-talets   första   hälft\n(drsavh   49),   Skolreformen   o\nförsöks-verksamh (50), Den nya skolan o\nför-söksverksamh (56), Bidrag t den äldre\nspråkjämförelsens allm o  sv hist fram\nt  1827  (55), Försvarets  lärov (57),  art\nsv o  utl press.  -  LKrVA  59.  -   Utm:\nRNO.\n\nGift 44 m fil kand Ester Ehrenberg\nf 16, dtr t godsäg Nils E o DagmarMatthiesen. - Barn: Harald f 47,\nWilhelm f 50.\nÅGREN, OLOF, förste byråinspektör,\n\nBromma, f i Norrkpg 19/2/11 av ing\nNils A o Alfhild Hultgren.\nStud:ex Sthlm 30, stud HHS 30-32,\nkontorsförest centralsjukkassan Sthlm\n34, avd:ass fst 41, arkivarie UD 43, l:c\nbyråinsp o ch dess kurirexp sed 48.\n-Medl Sthlms segelsällsk. - Ulm:\nRGrFen-O, FNM. - Hobbies: segling, filateli.\nGift 1) 34 m Greta Roos f 12, d 51,\n2) 52 m Louise Dahlerus f 26, dtr t\ndir Håkan D o Erna Grafström.\n-Barn: i l:a akt Jan f 35, Kerstin f\n48, i 2:a akt Nils f 55.\n\n",
    "structured": {
        "0": {
            "full_name": "AGNER, KJELL",
            "location": "Drottningholm",
            "occupation": "med dr, docent",
            "birth_details": {
                "date": "08/07/1913",
                "place": "Göteborg",
                "parents": "folk-skoleinsp, reg:pastorn Carl A o Stina Sundberg"
            },
            "education": [
                {
                    "degree": "Stud:ex",
                    "year": "1932",
                    "institution": "Uddevalla"
                },
                {
                    "degree": "med kand",
                    "year": "1935",
                    "institution": "Stockholm"
                },
                {
                    "degree": "med lic",
                    "year": "1943",
                    "institution": "Stockholm"
                },
                {
                    "degree": "med dr",
                    "year": "1945",
                    "institution": "Stockholm"
                }
            ],
            "career": [
                {
                    "position": "eo aman, aman o tf laborator",
                    "years": {
                        "start_year": 1933,
                        "end_year": 1940
                    },
                    "organization": "Karol inst kem inst"
                },
                {
                    "position": "ass Med Nobelinst",
                    "years": {
                        "start_year": 1940,
                        "end_year": 1942
                    },
                    "organization": null
                },
                {
                    "position": "doc:stip",
                    "years": {
                        "start_year": 1942,
                        "end_year": 1949
                    },
                    "organization": null
                },
                {
                    "position": "laborator i klinisk kemi",
                    "years": {
                        "start_year": null,
                        "end_year": null
                    },
                    "organization": "Karol inst"
                },
                {
                    "position": "över läk klin kem centrallab Seraf:las",
                    "years": {
                        "start_year": 1949,
                        "end_year": 1957
                    },
                    "organization": null
                },
                {
                    "position": "överläk klin kem lab S:t Görans sjh",
                    "years": {
                        "start_year": 1957,
                        "end_year": null
                    },
                    "organization": null
                }
            ],
            "family": {
                "spouse": "Ingegerd Sandefeldt",
                "marriage_year": "1947",
                "children": [
                    {
                        "name": "Carl",
                        "birth_year": "1950"
                    },
                    {
                        "name": "Anders",
                        "birth_year": "1952"
                    },
                    {
                        "name": "Erik",
                        "birth_year": "1955"
                    },
                    {
                        "name": "Olof",
                        "birth_year": "1959"
                    }
                ]
            }
        },
        "1": {
            "full_name": "AGNESTIG, A RUBEN",
            "location": "Nacka",
            "occupation": "ombudsman",
            "birth_details": {
                "date": "17/12/1897",
                "place": "Nora",
                "parents": "L Andersson o Olga Ekeblom"
            },
            "education": [
                {
                    "degree": "Örebro tekn elem:sk",
                    "year": "1921",
                    "institution": null
                }
            ],
            "career": [
                {
                    "position": "l:e omb:raan Tjmförb f hotell o rest",
                    "years": {
                        "start_year": 1937,
                        "end_year": null
                    },
                    "organization": null
                }
            ],
            "family": {
                "spouse": "Karin Grahn",
                "marriage_year": "1923",
                "children": null
            }
        },
        "2": {
            "full_name": "AGRELL, JAN G K",
            "location": "Danderyd",
            "occupation": "militäröverpsykolog, docent",
            "birth_details": {
                "date": "06/08/1918",
                "place": "Lund",
                "parents": "prof Sigurd A o Anna Österman"
            },
            "education": [
                {
                    "degree": "Stud:ex",
                    "year": "1938",
                    "institution": null
                },
                {
                    "degree": "fil kand",
                    "year": "1943",
                    "institution": "Lund"
                },
                {
                    "degree": "fil lic",
                    "year": "1946",
                    "institution": null
                },
                {
                    "degree": "fil dr",
                    "year": "1949",
                    "institution": null
                }
            ],
            "career": [],
            "family": {
                "spouse": "fil kand Ester Ehrenberg",
                "marriage_year": "1944",
                "children": [
                    {
                        "name": "Harald",
                        "birth_year": "1947"
                    },
                    {
                        "name": "Wilhelm",
                        "birth_year": "1950"
                    }
                ]
            },
            "publications": [
                {
                    "title": "Nyinrättade professurer inom filosof fak",
                    "year": "1949",
                    "type": "drsavh"
                },
                {
                    "title": "Skolreformen o försöksverksamh",
                    "year": "1950",
                    "type": null
                },
                {
                    "title": "Den nya skolan o försöksverksamh",
                    "year": "1956",
                    "type": null
                },
                {
                    "title": "Bidrag t den äldre språkjämförelsens allm o sv hist fram t 1827",
                    "year": "1955",
                    "type": null
                },
                {
                    "title": "Försvarets lärov",
                    "year": "1957",
                    "type": null
                }
            ],
            "honorary_titles": [
                {
                    "title": "LKrVA",
                    "institution": null,
                    "year": "1959"
                }
            ]
        },
        "3": {
            "full_name": "ÅGREN, OLOF",
            "location": "Bromma",
            "occupation": "förste byråinspektör",
            "birth_details": {
                "date": "19/02/1911",
                "place": "Norrköping",
                "parents": "ing Nils A o Alfhild Hultgren"
            },
            "education": [
                {
                    "degree": "Stud:ex",
                    "year": "1930",
                    "institution": "Stockholm"
                }
            ],
            "career": [
                {
                    "position": "kontorsförest centralsjukkassan",
                    "years": {
                        "start_year": 1934,
                        "end_year": 1941
                    },
                    "organization": "Stockholm"
                },
                {
                    "position": "avd:ass fst",
                    "years": {
                        "start_year": 1941,
                        "end_year": 1943
                    },
                    "organization": null
                },
                {
                    "position": "arkivarie UD",
                    "years": {
                        "start_year": 1943,
                        "end_year": null
                    },
                    "organization": null
                },
                {
                    "position": "l:c byråinsp o ch dess kurirexp",
                    "years": {
                        "start_year": 1948,
                        "end_year": null
                    },
                    "organization": null
                }
            ],
            "family": {
                "spouse": "1) Greta Roos",
                "marriage_year": "1934",
                "children": [
                    {
                        "name": "Jan",
                        "birth_year": "1935"
                    },
                    {
                        "name": "Kerstin",
                        "birth_year": "1948"
                    }
                ]
            },
            "hobbies": [
                "segling",
                "filateli"
            ]
        }
    }
}