{
    "original": "APPELGREN, BRITA D, fd\npremiärdansös,  Sthlm,  f  i  Sthlm  21/12/12  av\nPatrik  A  o  Beda  Hult.\nK teat balettsk 21, premiärelev 31,\npremiärdansös K teat 34-55, filmroller (av\ntysk  film).   -   Utm:  Kon:sGM.\nGift m jur kand Sten Hermansson f 15.\n- Barn: i tid akt Malou f 41,  Bellita\nf 53.\n\nAPPELGREN, CARL W O C J,\nbitr direktör, Saltsjöbaden, f i Västra\nSallerup, Malmöh l, 29/6/99 av\ndistr:-lantmät Nils A o Ernestine\nClemens-son.\n\nStud:ex 17, res:off:ex 20, offrex 22,\npå övergångsstat 25, kapt 35; anst\nSkandiakonc 25, avd:ch 26, kamr 32,\nbitr dir sed 59. - Sv försäkr.fören\nRubensonsstip o hdlshögsk stip USA\n30, Kommerskoll Possehlstip Tyskl 34.\n-Utm: RSO.\n\nGift 28 m Birgit v Sydow f 03. - Barn:\nWolter f 29, Tullia f 33, Fingal f 37.\n\nAPPELGREN, ERNST ORVAR,\ntandläkare, Sthlm, f i Ängelholm 7/10/04.\nStudrex 25, Hdlsgymn Hbg 26, Dr Dent\nSurg, Northwest Univ Chicago 30, prakt\nChicago 30-31, sv tandhex 32, prakt\nSöderåkra 33, Sthlm sed 36.\n\nAPPELGREN, E HARRY H, förste\nrevisor, Sthlm, f i Sthlm 25/6/08 av dir\nHenning A o Gerda Körner.\nStud:ex 28, DHS 31, jur kand Sthlm\n39, tingstjg Sthlms rådhusr 39-40, aman\nflygförvaltn 40, tf rev där 44 (e 42),\nrev riksräkenskaps v 47, l:e byråsekr\nkontrollstyr 48, rikets allm kartverk 48,\nl:e rev riksräkenskapsv 54 (tf 53),\nl:e rev riksrevisionsv sed 61. - Sekr\nkartverkskommiss 48-53.\nGift m Lenah Brettvall. - Barn: Kurt\nf 43, Erik f 45, Björn f 49.\n\nAPPELLÖF, OLGA S L,\nskådespelerska, Sthlm, f i Bergen, Norge, 14/1/\n98 av prof Adolf A o Caroline\nKökeritz.\n\nStud:ex Upps 17, elev Julia Håkansson\n29-30, anst Nya intima teat Sthlm\n30-32, kortare eng Dram teat, stadsteat\nJSorrkpg-Linkpg m fi. - Filmat o upp-\n\ntr i TV, uppläsn:turnéer i Sv:e,\nNorge o Danm.\n\nGift  34  m  skådesp  Olle  Hilding.\n",
    "structured": {
        "1": {
            "full_name": "APPELGREN, BRITA D",
            "location": "Sthlm",
            "occupation": "fd premiärdansös",
            "birth_details": {
                "date": "21/12/1912",
                "place": "Stockholm",
                "parents": "Patrik A o Beda Hult"
            },
            "education": [
                {
                    "degree": "teat balettsk",
                    "year": "1921",
                    "institution": "Kungliga teatern"
                }
            ],
            "career": [
                {
                    "position": "premiärelev",
                    "years": {
                        "start_year": 1931,
                        "end_year": 1931
                    },
                    "organization": "Kungliga teatern"
                },
                {
                    "position": "premiärdansös",
                    "years": {
                        "start_year": 1934,
                        "end_year": 1955
                    },
                    "organization": "Kungliga teatern"
                }
            ],
            "family": {
                "spouse": "Sten Hermansson",
                "marriage_year": "NULL",
                "children": [
                    {
                        "name": "Malou",
                        "birth_year": "1941"
                    },
                    {
                        "name": "Bellita",
                        "birth_year": "1953"
                    }
                ]
            }
        },
        "2": {
            "full_name": "APPELGREN, CARL W O C J",
            "location": "Saltsjöbaden",
            "occupation": "bitr direktör",
            "birth_details": {
                "date": "29/06/1899",
                "place": "Västra Sallerup, Malmöh l",
                "parents": "Nils A o Ernestine Clemensson"
            },
            "education": [
                {
                    "degree": "Stud:ex",
                    "year": "1917",
                    "institution": "NULL"
                },
                {
                    "degree": "res:off:ex",
                    "year": "1920",
                    "institution": "NULL"
                },
                {
                    "degree": "offrex",
                    "year": "1922",
                    "institution": "NULL"
                }
            ],
            "career": [
                {
                    "position": "anst Skandiakonc",
                    "years": {
                        "start_year": 1925,
                        "end_year": 1926
                    },
                    "organization": "Skandiakonc"
                },
                {
                    "position": "avd:ch",
                    "years": {
                        "start_year": 1926,
                        "end_year": 1932
                    },
                    "organization": "NULL"
                },
                {
                    "position": "kamr",
                    "years": {
                        "start_year": 1932,
                        "end_year": 1959
                    },
                    "organization": "NULL"
                },
                {
                    "position": "bitr dir",
                    "years": {
                        "start_year": 1959,
                        "end_year": "NULL"
                    },
                    "organization": "NULL"
                }
            ],
            "family": {
                "spouse": "Birgit v Sydow",
                "marriage_year": "1928",
                "children": [
                    {
                        "name": "Wolter",
                        "birth_year": "1929"
                    },
                    {
                        "name": "Tullia",
                        "birth_year": "1933"
                    },
                    {
                        "name": "Fingal",
                        "birth_year": "1937"
                    }
                ]
            }
        },
        "3": {
            "full_name": "APPELGREN, ERNST ORVAR",
            "location": "Sthlm",
            "occupation": "tandläkare",
            "birth_details": {
                "date": "7/10/1904",
                "place": "Ängelholm",
                "parents": "NULL"
            },
            "education": [
                {
                    "degree": "Studrex",
                    "year": "1925",
                    "institution": "NULL"
                },
                {
                    "degree": "Hdlsgymn",
                    "year": "1926",
                    "institution": "Hbg"
                },
                {
                    "degree": "Dr Dent Surg",
                    "year": "1930",
                    "institution": "Northwest Univ Chicago"
                }
            ],
            "career": [
                {
                    "position": "prakt",
                    "years": {
                        "start_year": 1936,
                        "end_year": "NULL"
                    },
                    "organization": "Söderåkra, Stockholm"
                }
            ],
            "family": {
                "spouse": "NULL",
                "marriage_year": "NULL",
                "children": "NULL"
            }
        },
        "4": {
            "full_name": "APPELGREN, E HARRY H",
            "location": "Sthlm",
            "occupation": "förste revisor",
            "birth_details": {
                "date": "25/6/1908",
                "place": "Stockholm",
                "parents": "Henning A o Gerda Körner"
            },
            "education": [
                {
                    "degree": "Stud:ex",
                    "year": "1928",
                    "institution": "NULL"
                },
                {
                    "degree": "DHS",
                    "year": "1931",
                    "institution": "Sthlm"
                },
                {
                    "degree": "jur kand",
                    "year": "1939",
                    "institution": "Sthlm"
                }
            ],
            "career": [
                {
                    "position": "tingstjg",
                    "years": {
                        "start_year": 1939,
                        "end_year": 1940
                    },
                    "organization": "Sthlms rådhusr"
                },
                {
                    "position": "aman flygförvaltn",
                    "years": {
                        "start_year": 1940,
                        "end_year": "NULL"
                    },
                    "organization": "NULL"
                },
                {
                    "position": "tf rev",
                    "years": {
                        "start_year": 1944,
                        "end_year": 1944
                    },
                    "organization": "där"
                },
                {
                    "position": "rev riksräkenskaps v",
                    "years": {
                        "start_year": 1947,
                        "end_year": "NULL"
                    },
                    "organization": "NULL"
                },
                {
                    "position": "l:e byråsekr kontrollstyr",
                    "years": {
                        "start_year": 1948,
                        "end_year": "NULL"
                    },
                    "organization": "rikets allm kartverk"
                },
                {
                    "position": "l:e rev riksräkenskapsv",
                    "years": {
                        "start_year": 1954,
                        "end_year": "NULL"
                    },
                    "organization": "riktr"
                }
            ],
            "family": {
                "spouse": "Lenah Brettvall",
                "marriage_year": "NULL",
                "children": [
                    {
                        "name": "Kurt",
                        "birth_year": "1943"
                    },
                    {
                        "name": "Erik",
                        "birth_year": "1945"
                    },
                    {
                        "name": "Björn",
                        "birth_year": "1949"
                    }
                ]
            }
        },
        "5": {
            "full_name": "APPELLÖF, OLGA S L",
            "location": "Sthlm",
            "occupation": "skådespelerska",
            "birth_details": {
                "date": "14/01/1898",
                "place": "Bergen, Norge",
                "parents": "Adolf A o Caroline Kökeritz"
            },
            "education": [
                {
                    "degree": "Stud:ex",
                    "year": "1917",
                    "institution": "Upps"
                }
            ],
            "career": [
                {
                    "position": "anst",
                    "years": {
                        "start_year": 1930,
                        "end_year": 1932
                    },
                    "organization": "Nya intima teat Sthlm"
                }
            ],
            "family": {
                "spouse": "Olle Hilding",
                "marriage_year": "1934",
                "children": "NULL"
            }
        }
    }
}