{
    "original": "BERGQVIST, K GÖSTA   advokat,   f\n\ni Sthlm 14/3/14 av ing Karl B o Lilly\nBrinkman.\n\nStud:ex 35, jur kand 44, tingstj Sthlms\nrådhusr 44, bitr jur h adv Klas\nWijkander Sthlm 46, eg adv:verksamh Sthlm\nsed 48. - LSA 50.\n\nGift m Barbro Tholin. - Barn: Ulla\nf 46, Klas Göran f 50.\n\nBERGQUIST, K IVAR, fd\nbankdirektör, Sthlm, f i Hyltinge, Södermani l,\n16/7/96 av kyrkoh Rickard B o Elin\nEdlund.\n\nStud:ex Nykpg 14, anst Södermani ensk\nbk 14, kassör kontoret i Strängnäs 19,\ntjrman kontoret i Sthlm 21, kamrer 26,\ndiriass 27, jourh dir 33, dir Skand bkn\n45-61. - Utm: RVO.\n\nBERGQUIST, JOHN A, civilingenjör,\nLidingö, f i Hallen 211196 av\ngrosshandl Per B o Kristina Andersdtr.\nStudrex Örebro 16, KTH 22, anst AGA\nLidingö sed 17, offerting 24, avd:ch 54.\n-Ordf stud:ndn, v ordf hälsovindn 42-46,\nled bibhndn, kyrkofullm 43-58, tax:ndn\n54-56, verkst led Lidingö hemvärns\nga-rantfören sed 41, medl Sv\nbelysnings-sällsk, The illuminating soc, Sv\nuppfinn:-fören. - Inneh patent på ett flert\nsignal-tekn uppfinningar. - Utm: PatrGM,\nPetrimed, Lidingö hvo ftjGM.\nGift 21 m Martha Selin. Barn:\nPer-Marcus f 31, Göran f 33.\n\nBERGKVIST, SVEN O, författare,\nSollentuna, f i Njutånger, Gävleb l,\n22/4/27 av fabnarb Gustav B o Ester\nÖstlin.\n\nFolkhögsk. - Skr: Vandring till\nLjusbacken (50), Sommarbarn (51),\nFamiljebiljett (53), Höstmässa (55), Sommar\ni världen (56), Den mörke främlingen\n(56), Änglar på jorden (57), Vilse i\negna landskap (58), Fågelvägen (59),\nRastställe (60), Gränsmarker (61).\nGift 54 m Barbro Ekström f 30, dtr t\nmålarmäst Josef E o Signe Strenbohm.\n\n",
    "structured": {
        "0": {
            "full_name": "BERGQVIST, K GÖSTA",
            "occupation": "advokat",
            "birth_details": {
                "date": "14/03/1914",
                "place": "Sthlm"
            },
            "education": [
                {
                    "degree": "Stud:ex",
                    "year": "1935",
                    "institution": "unknown"
                },
                {
                    "degree": "jur kand",
                    "year": "1944",
                    "institution": "unknown"
                }
            ],
            "career": [
                {
                    "position": "tingstj",
                    "years": {
                        "start_year": 1944,
                        "end_year": 1944
                    },
                    "organization": "Sthlms rådhusr"
                },
                {
                    "position": "bitr jur h adv",
                    "years": {
                        "start_year": 1946,
                        "end_year": 1948
                    },
                    "organization": "Klas Wijkander Sthlm"
                },
                {
                    "position": "eg adv:verksamh",
                    "years": {
                        "start_year": 1948,
                        "end_year": null
                    },
                    "organization": "Sthlm"
                }
            ],
            "family": {
                "spouse": "Barbro Tholin",
                "marriage_year": "unknown",
                "children": [
                    {
                        "name": "Ulla",
                        "birth_year": "1946"
                    },
                    {
                        "name": "Klas Göran",
                        "birth_year": "1950"
                    }
                ]
            }
        },
        "1": {
            "full_name": "BERGQUIST, K IVAR",
            "occupation": "fd bankdirektör",
            "birth_details": {
                "date": "16/07/1896",
                "place": "Hyltinge, Södermani l"
            },
            "education": [
                {
                    "degree": "Stud:ex",
                    "year": "1914",
                    "institution": "Nykpg"
                }
            ],
            "career": [
                {
                    "position": "anst Södermani ensk bk",
                    "years": {
                        "start_year": 1914,
                        "end_year": 1921
                    },
                    "organization": "unknown"
                },
                {
                    "position": "kassör",
                    "years": {
                        "start_year": 1921,
                        "end_year": 1926
                    },
                    "organization": "kontoret i Strängnäs"
                },
                {
                    "position": "tjrman",
                    "years": {
                        "start_year": 1921,
                        "end_year": 1926
                    },
                    "organization": "kontoret i Sthlm"
                },
                {
                    "position": "kamrer",
                    "years": {
                        "start_year": 1926,
                        "end_year": 1927
                    },
                    "organization": "kontoret i Sthlm"
                },
                {
                    "position": "diriass",
                    "years": {
                        "start_year": 1927,
                        "end_year": 1933
                    },
                    "organization": "unknown"
                },
                {
                    "position": "jourh dir",
                    "years": {
                        "start_year": 1933,
                        "end_year": 1945
                    },
                    "organization": "unknown"
                },
                {
                    "position": "dir Skand bkn",
                    "years": {
                        "start_year": 1945,
                        "end_year": 1961
                    },
                    "organization": "unknown"
                }
            ],
            "family": {
                "spouse": "unknown",
                "marriage_year": "unknown",
                "children": [
                    {
                        "name": "Per-Marcus",
                        "birth_year": "1931"
                    },
                    {
                        "name": "Göran",
                        "birth_year": "1933"
                    }
                ]
            }
        },
        "2": {
            "full_name": "BERGQUIST, JOHN A",
            "occupation": "civilingenjör",
            "birth_details": {
                "date": "21/11/1966",
                "place": "Hallen"
            },
            "education": [
                {
                    "degree": "Studrex",
                    "year": "1916",
                    "institution": "Örebro"
                },
                {
                    "degree": "KTH",
                    "year": "1922",
                    "institution": "unknown"
                }
            ],
            "career": [
                {
                    "position": "anst AGA Lidingö",
                    "years": {
                        "start_year": 1917,
                        "end_year": null
                    },
                    "organization": "unknown"
                }
            ],
            "family": {
                "spouse": "unknown",
                "marriage_year": "unknown",
                "children": [
                    {
                        "name": "Per-Marcus",
                        "birth_year": "1931"
                    },
                    {
                        "name": "Göran",
                        "birth_year": "1933"
                    }
                ]
            }
        },
        "3": {
            "full_name": "BERGKVIST, SVEN O",
            "occupation": "författare",
            "birth_details": {
                "date": "22/04/1927",
                "place": "Njutånger, Gävleb l"
            },
            "education": [
                {
                    "degree": "Folkhögsk",
                    "year": "unknown",
                    "institution": "unknown"
                }
            ],
            "publications": [
                {
                    "title": "Vandring till Ljusbacken",
                    "year": "1950",
                    "type": "unknown"
                },
                {
                    "title": "Sommarbarn",
                    "year": "1951",
                    "type": "unknown"
                },
                {
                    "title": "Familjebiljett",
                    "year": "1953",
                    "type": "unknown"
                },
                {
                    "title": "Höstmässa",
                    "year": "1955",
                    "type": "unknown"
                },
                {
                    "title": "Sommar i världen",
                    "year": "1956",
                    "type": "unknown"
                },
                {
                    "title": "Den mörke främlingen",
                    "year": "1956",
                    "type": "unknown"
                },
                {
                    "title": "Änglar på jorden",
                    "year": "1957",
                    "type": "unknown"
                },
                {
                    "title": "Vilse i egna landskap",
                    "year": "1958",
                    "type": "unknown"
                },
                {
                    "title": "Fågelvägen",
                    "year": "1959",
                    "type": "unknown"
                },
                {
                    "title": "Rastställe",
                    "year": "1960",
                    "type": "unknown"
                },
                {
                    "title": "Gränsmarker",
                    "year": "1961",
                    "type": "unknown"
                }
            ],
            "family": {
                "spouse": "Barbro Ekström",
                "marriage_year": "1954",
                "children": []
            }
        }
    }
}