{
    "original": "BAKOS, C KARL, vetimed dr,\nlaborator, Solna, f i Budapest 26/2/09.\nStud:ex 27, Dr vet:med Budapest 34,\nvet:med dr VHS Sthlm 55, laborator\nstat vet:med inst Budapest t 44, lab:led\nv Serag Seruminst München 46, ass\nSVA Sthlm 48, laborator SVA o led\ndess viruslab sed 49. - Medl öl med o\nvet:med f ören. - Skr: ett 50-tal arb i\nvet:bakteriol o virol ämnen.\nGift 52 m Margot Larsson f 23. - Barn:\nStefan f 56.\n\nBALK-MÖLLER, STIG C E,\nbankjurist, Sthlm, f i Aarhus, Danm 21 /lÖ/\n13 av dir Christian B-M o Siv\nOhlsson.\n\nStud:ex Sthlm 32, jur kand 39, tingstjg\n39-43, anst stat byggn:lånebyrå\nomb:-mannasektion 43, omb:man Sthlms\nsparbk 50 (bitr 44), bkjurist Sv\nsparbksför-en sed 61. - Res:off:ex 40, off I 20 res.\n- Lär o styr:led Sparbkssk, omb:man\nlänsbost:ndn Sthlms l samt Ränte- o\nkapitalförsäkr:anst, v ordf Sv\nsparbks-fören studieråd, styr:led I 20 off:fören\n\n1  Sthlm, Västerb gille.\n\nGift m Margit Lindström. - Barn:\nChristina f 53.\n\nBALTSCHEFFSKY, HERRICK G\nT, docent, Sollentuna, f i Hfors 15/7/28\nav med lic Herbert B o Marika Bolinder.\nStudrex Åbo 46, fil kand Åbo 53, fil lic\n57, fil dr Sthlm 60, research fel’lüw\nUniv of Pennsylvania Philadelphia 54,\nass Wenner-Grens inst Sthlm 57, doc i\nbiokemi StU sed 60. - Skr i biokemi,\n\nbi a Electron Transport and Electron\nTransport-Linked Phosphorylation\n(drs-avh 60). - Hobby: segling.\nGift 53 m fil mag Margareta Vilén, dtr\nt in’g Harald V o Birgit Söderbaum.\n-Barn: Patrick f 53, Henrik f 57,\nSusanna f 59.\n\n",
    "structured": {
        "0": {
            "full_name": "C KARL BAKOS",
            "location": "Solna",
            "occupation": "vetimed dr, laborator",
            "birth_details": {
                "date": "26/02/1909",
                "place": "Budapest"
            },
            "education": [
                {
                    "degree": "Stud:ex",
                    "year": "1927",
                    "institution": "NULL"
                },
                {
                    "degree": "Dr vet:med",
                    "year": "1934",
                    "institution": "Budapest"
                },
                {
                    "degree": "Vet:med dr",
                    "year": "1955",
                    "institution": "VHS Sthlm"
                }
            ],
            "career": [
                {
                    "position": "lab:led",
                    "years": {
                        "start_year": 1944,
                        "end_year": 1946
                    },
                    "organization": "stat vet:med inst Budapest"
                },
                {
                    "position": "ass",
                    "years": {
                        "start_year": 1948,
                        "end_year": 1955
                    },
                    "organization": "SVA Sthlm"
                }
            ],
            "family": {
                "spouse": "Margot Larsson",
                "marriage_year": "1952",
                "children": [
                    {
                        "name": "Stefan",
                        "birth_year": "1956"
                    }
                ]
            }
        },
        "1": {
            "full_name": "STIG C E BALK-MÖLLER",
            "location": "Sthlm",
            "occupation": "bankjurist",
            "birth_details": {
                "date": "21/01/1913",
                "place": "Aarhus, Danm"
            },
            "education": [
                {
                    "degree": "Stud:ex",
                    "year": "1932",
                    "institution": "Sthlm"
                },
                {
                    "degree": "jur kand",
                    "year": "1939",
                    "institution": "NULL"
                }
            ],
            "career": [
                {
                    "position": "omb:man",
                    "years": {
                        "start_year": 1943,
                        "end_year": 1950
                    },
                    "organization": "Sthlms sparbk"
                }
            ],
            "family": {
                "spouse": "Margit Lindström",
                "marriage_year": "NULL",
                "children": [
                    {
                        "name": "Christina",
                        "birth_year": "1953"
                    }
                ]
            }
        },
        "2": {
            "full_name": "HERRICK G T BALTSCHEFFSKY",
            "location": "Sollentuna",
            "occupation": "docent",
            "birth_details": {
                "date": "15/07/1928",
                "place": "Hfors"
            },
            "education": [
                {
                    "degree": "Studrex",
                    "year": "1946",
                    "institution": "Åbo"
                },
                {
                    "degree": "fil kand",
                    "year": "1953",
                    "institution": "Åbo"
                },
                {
                    "degree": "fil lic",
                    "year": "1957",
                    "institution": "NULL"
                },
                {
                    "degree": "fil dr",
                    "year": "1960",
                    "institution": "Sthlm"
                }
            ],
            "career": [
                {
                    "position": "doc i biokemi",
                    "years": {
                        "start_year": 1960,
                        "end_year": "NULL"
                    },
                    "organization": "StU"
                }
            ],
            "family": {
                "spouse": "fil mag Margareta Vilén",
                "marriage_year": "1953",
                "children": [
                    {
                        "name": "Patrick",
                        "birth_year": "1953"
                    },
                    {
                        "name": "Henrik",
                        "birth_year": "1957"
                    },
                    {
                        "name": "Susanna",
                        "birth_year": "1959"
                    }
                ]
            },
            "hobbies": [
                "segling"
            ]
        }
    }
}