{
    "original": "DIRKE, LARS E, civilingenjör,\nMölndal, f i Lindesberg 27/5/22 av fil mag\nErik Johansson o Rut Johnson.\nStud:ex Kristinehamn 41, KTH 47, l:e\nass KTH 47, ing Gbgs elverk 51,\nWS-ch GAKO Gbg sed 58. - Styr:led\nVVS-tekn fören, Tekn samf 58-62. - Skr: art\ni fackpr.\n\nGift 57 m Birgit Roman f 35, dtr t\nkassör Malte R o Ingrid Frick. - Barn:\nMagnus f 58, Boel f 62.\n\nDISE, VICTOR, fabrikör, Gbg, f i\nÅmål 9/4/93.\n\nInneh Dragspelsfabr Skandia Gbg sed\n18. - Utm: Motormännens ftjt f 25 års\nprickfri körning. - Hobby: trädg:skötsel.\nGift 19 m Elsa Göransson. - Barn:\nBirgit f 20, Leif f 22.\n\nDIURLIN, J YNGVE, överste,\nLinköping, f i Sthlm 6/9/03 av sjökapt Gustaf\nD o Gerda Wahlquist.\nStud:ex Gbg 24, fänr I 9* 26, löjtn 30,\nKHS 34-36, kapt gst 40, I 16 44, major\ni armén 44, I 16 45, gst 46, ö v :löjtn gst\n49, vid trängtrupperna 51, överste o ch\nT 3 55-58, T l 58-63. - FHS 55. - Sekr\nÖstergötl distr av SRK sed 64. - Utm:\nKSOlkl, RVO, SRKftjt, SCFftjt,\nSkyt-teM.\n\nGift 33 m Signhild Berg f 10, dtr t\növerste Theodor B o Ellen Thorell.\n-Barn: Per f 39, Gustaf f 42, Ylva f 46.\n\nDJUPE, DAN S, postmästare, Skövde,\nf i Ekeberga, Kronob l, 13/3/99 av\nbryg-geriäg Frans Johansson o Lisa\nJohansson.\n\nStud:ex Lund 20, postex Sthlm 22,\npostass o l:e postass Jönkpg 26-48, kontr\nLudvika 48, l:e kontr Umeå 51, post-\n\nmast Lidkpg 56, Skövde sed 58. - Led\npostverkets skatteutredn 45-46, styr :led\nPosttjm fören 37-41. - Medl PB. - Utm:\nRNO, GMnor, HvGplak.\nGift 26 m Siri Gothilander f 03, dtr t\nEvald G o Alma Karlsson. - Barn: Gun\nf 31.\n\n",
    "structured": {
        "0": {
            "full_name": "Dirke, Lars E",
            "location": "Mölndal",
            "occupation": "Civilingenjör",
            "birth_details": {
                "date": "27/05/1922",
                "place": "Lindesberg",
                "parents": "Erik Johansson och Rut Johnson"
            },
            "education": [
                {
                    "degree": "Stud:ex",
                    "year": "1941",
                    "institution": "Kristinehamn"
                },
                {
                    "degree": "KTH",
                    "year": "1947",
                    "institution": "KTH"
                }
            ],
            "career": [
                {
                    "position": "L:e ass KTH",
                    "years": {
                        "start_year": 1947,
                        "end_year": 1947
                    },
                    "organization": "KTH"
                },
                {
                    "position": "Ing Gbgs elverk",
                    "years": {
                        "start_year": 1951,
                        "end_year": null
                    },
                    "organization": "Gbgs elverk"
                }
            ],
            "family": {
                "spouse": "Birgit Roman",
                "marriage_year": "1957",
                "children": [
                    {
                        "name": "Magnus",
                        "birth_year": "1958"
                    },
                    {
                        "name": "Boel",
                        "birth_year": "1962"
                    }
                ]
            }
        },
        "1": {
            "full_name": "Dise, Victor",
            "location": "Gbg",
            "occupation": "Fabrikör",
            "birth_details": {
                "date": "09/04/1893",
                "place": "Åmål",
                "parents": null
            },
            "education": null,
            "career": [
                {
                    "position": "Inneh Dragspelsfabr Skandia Gbg",
                    "years": {
                        "start_year": 1918,
                        "end_year": null
                    },
                    "organization": "Skandia Gbg"
                }
            ],
            "family": {
                "spouse": "Elsa Göransson",
                "marriage_year": "1919",
                "children": [
                    {
                        "name": "Birgit",
                        "birth_year": "1920"
                    },
                    {
                        "name": "Leif",
                        "birth_year": "1922"
                    }
                ]
            }
        },
        "2": {
            "full_name": "Diurlin, J Yngve",
            "location": "Linköping",
            "occupation": "Överste",
            "birth_details": {
                "date": "06/09/1903",
                "place": "Sthlm",
                "parents": "Sjökapt Gustaf D och Gerda Wahlquist"
            },
            "education": [
                {
                    "degree": "Stud:ex",
                    "year": "1924",
                    "institution": "Gbg"
                },
                {
                    "degree": "Fänr I 9*",
                    "year": "1926",
                    "institution": "I 9"
                }
            ],
            "career": [
                {
                    "position": "Överste och ch T 3",
                    "years": {
                        "start_year": 1955,
                        "end_year": 1958
                    },
                    "organization": "T 3"
                },
                {
                    "position": "T l",
                    "years": {
                        "start_year": 1958,
                        "end_year": 1963
                    },
                    "organization": null
                }
            ],
            "family": {
                "spouse": "Signhild Berg",
                "marriage_year": "1933",
                "children": [
                    {
                        "name": "Per",
                        "birth_year": "1939"
                    },
                    {
                        "name": "Gustaf",
                        "birth_year": "1942"
                    },
                    {
                        "name": "Ylva",
                        "birth_year": "1946"
                    }
                ]
            }
        },
        "3": {
            "full_name": "Djupe, Dan S",
            "location": "Skövde",
            "occupation": "Postmästare",
            "birth_details": {
                "date": "13/03/1899",
                "place": "Ekeberga, Kronob l",
                "parents": "Bryggeriäg Frans Johansson och Lisa Johansson"
            },
            "education": [
                {
                    "degree": "Stud:ex",
                    "year": "1920",
                    "institution": "Lund"
                },
                {
                    "degree": "Postex",
                    "year": "1922",
                    "institution": "Sthlm"
                }
            ],
            "career": [
                {
                    "position": "Postass och l:e postass Jönkpg",
                    "years": {
                        "start_year": 1926,
                        "end_year": 1948
                    },
                    "organization": "Jönkpg"
                },
                {
                    "position": "Kontr Ludvika",
                    "years": {
                        "start_year": 1948,
                        "end_year": 1951
                    },
                    "organization": "Ludvika"
                },
                {
                    "position": "L:e kontr Umeå",
                    "years": {
                        "start_year": 1951,
                        "end_year": null
                    },
                    "organization": "Umeå"
                },
                {
                    "position": "Postmast",
                    "years": {
                        "start_year": 1956,
                        "end_year": null
                    },
                    "organization": "Lidkpg"
                },
                {
                    "position": null,
                    "years": null,
                    "organization": "Skövde"
                }
            ],
            "family": {
                "spouse": "Siri Gothilander",
                "marriage_year": "1926",
                "children": [
                    {
                        "name": "Gun",
                        "birth_year": "1931"
                    }
                ]
            }
        }
    }
}