{
    "original": "DANHEIM, TORE, tandläkare,\nKalmar, f i Virserum, Kalmar l, 25/5/17 av\nfabr Josef Danielson o Ruth Johansson.\nStud:ex Växjö 38, tandl:ex Sthlm 42,\nass:tandl Karlsborg 42-43, priv:prakt\nKalmar sed 43. - Ordf Kalmar l\ntandl:-sällsk 56-60. - Medl SHT. - Hobby:\ntennis.\n\nGift 43 m Git Sjögren, dtr t musikdir\nAug S o Anna S. - Barn: Annika f 48,\nGun f 51.\n\nDANIELSON, ALVAR,\nciviljägmästare, Skövde, f i Lundsberg, Värml l,\n5/6/13 av rekt Frits D o Malin\nAndersson.\n\nStud:ex 33, SkHS 39, ass skogsv:styr\nKopparb l 39, omb :man Skarab\nskogs-äg :f ören sed 45, skogsförvalt Grytens o\nRolkens häradsallm:ar sed 56. -\nStyr:-ordf Skarab skytteförb sed 55. - Utm:\nSkarab skytteförbGM, Skytteförb\növer-styrSM.\n\nGift 42 m Lisa Bengtsson f 16, dtr t\nKarl B o Anna Pettersson. - Barn:\nMaria f 57.\n\nDANIELSSON, T H ARNE, direktör,\n\nGbg, f i Tveta, Kalmar l, 4/8/13 av\nköpm Gunnar D o Hilma Palm.\nHdlssk, folkhögsk:kurser, dir o inneh\nArne Danielsson fastigh :byrå ab sed 61,\ninneh ab Tomt o Mark sed 61. - Medl\nOdd Fellow, Smal gille. - Hobbies: jakt,\nfiske, trädgårdsskötsel.\nGift 1) ni Svea Karlsson, 2) m May\nLillemor Aronsson. - Barn: i l:a akt\nKerstin f 44, Jonas f 47, i 2:a akt\nAnders f 59.\n\nDANIELSON, BARBRO G,\nkonstnärinna, Borgholm, f i Sjuntorp, Älvsb l,\n6/5/23 av disp Hans Mjörne o Vanja\nLilljegren.\n\nRealex Lilla Edet 40, Konstind:sk Gbg\n44. - Utst: Sthlm 52 o 56, Gbg 58,\nkonstmus Kalmar, Borgholm; delt i ett flert\nsaml:utst. - Repr: konstmus Kalmar.\n-Hobbies: tennis, bridge.\nGift 45 m disp Sune Danielson f 10.\n-Barn: Ulla f 46, Karl Olof f 47.\n\n",
    "structured": {
        "1": {
            "full_name": "DANHEIM, TORE",
            "location": "Kalmar",
            "occupation": "tandläkare",
            "birth_details": {
                "date": "25/05/1917",
                "place": "Virserum, Kalmar l",
                "parents": "fabr Josef Danielson o Ruth Johansson"
            },
            "education": [
                {
                    "degree": "Stud",
                    "year": "1938",
                    "institution": "Växjö"
                },
                {
                    "degree": "tandl",
                    "year": "1942",
                    "institution": "Sthlm"
                }
            ],
            "career": [
                {
                    "position": "ass:tandl",
                    "years": {
                        "start_year": 1942,
                        "end_year": 1943
                    },
                    "organization": "Karlsborg"
                },
                {
                    "position": "priv:prakt",
                    "years": {
                        "start_year": 1943
                    },
                    "organization": "Kalmar"
                }
            ],
            "family": {
                "spouse": "Git Sjögren",
                "marriage_year": "1943",
                "children": [
                    {
                        "name": "Annika",
                        "birth_year": "1948"
                    },
                    {
                        "name": "Gun",
                        "birth_year": "1951"
                    }
                ]
            },
            "hobbies": [
                "tennis"
            ]
        },
        "2": {
            "full_name": "DANIELSON, ALVAR",
            "location": "Skövde",
            "occupation": "civiljägmästare",
            "birth_details": {
                "date": "05/06/1913",
                "place": "Lundsberg, Värml l",
                "parents": "rekt Frits D o Malin Andersson"
            },
            "education": [
                {
                    "degree": "Stud",
                    "year": "1933"
                },
                {
                    "degree": "SkHS",
                    "year": "1939"
                }
            ],
            "career": [
                {
                    "position": "ass skogsv:styr",
                    "years": {
                        "start_year": 1939
                    },
                    "organization": "Kopparb l"
                },
                {
                    "position": "omb :man Skarab skogs-äg :f",
                    "years": {
                        "start_year": 1945
                    },
                    "organization": "f ören"
                },
                {
                    "position": "skogsförvalt Grytens o Rolkens häradsallm:ar",
                    "years": {
                        "start_year": 1956
                    }
                }
            ],
            "family": {
                "spouse": "Lisa Bengtsson",
                "marriage_year": "1942",
                "children": [
                    {
                        "name": "Maria",
                        "birth_year": "1957"
                    }
                ]
            }
        },
        "3": {
            "full_name": "DANIELSSON, T H ARNE",
            "location": "Gbg",
            "occupation": "direktör",
            "birth_details": {
                "date": "04/08/1913",
                "place": "Tveta, Kalmar l",
                "parents": "köpm Gunnar D o Hilma Palm"
            },
            "education": [
                {
                    "degree": "hdlssk"
                }
            ],
            "career": [
                {
                    "position": "dir o inneh Arne Danielsson fastigh :byrå ab",
                    "years": {
                        "start_year": 1961
                    }
                },
                {
                    "position": "inneh ab Tomt o Mark",
                    "years": {
                        "start_year": 1961
                    }
                }
            ],
            "community_involvement": [
                {
                    "role": "Medl",
                    "organization": "Odd Fellow"
                },
                {
                    "role": "Medl",
                    "organization": "Smal gille"
                }
            ],
            "hobbies": [
                "jakt",
                "fiske",
                "trädgårdsskötsel"
            ],
            "family": {
                "spouse": "May Lillemor Aronsson",
                "children": [
                    {
                        "name": "Kerstin",
                        "birth_year": "1944"
                    },
                    {
                        "name": "Jonas",
                        "birth_year": "1947"
                    },
                    {
                        "name": "Anders",
                        "birth_year": "1959"
                    }
                ]
            }
        },
        "4": {
            "full_name": "DANIELSON, BARBRO G",
            "location": "Borgholm",
            "occupation": "konstnärinna",
            "birth_details": {
                "date": "06/05/1923",
                "place": "Sjuntorp, Älvsb l",
                "parents": "disp Hans Mjörne o Vanja Lilljegren"
            },
            "education": [
                {
                    "degree": "Realex",
                    "year": "1940",
                    "institution": "Lilla Edet"
                },
                {
                    "degree": "Konstind:sk",
                    "year": "1944",
                    "institution": "Gbg"
                }
            ],
            "career": [
                {
                    "organization": "konstmus Kalmar"
                },
                {
                    "organization": "Borgholm"
                }
            ],
            "hobbies": [
                "tennis",
                "bridge"
            ],
            "family": {
                "spouse": "disp Sune Danielson",
                "marriage_year": "1945",
                "children": [
                    {
                        "name": "Ulla",
                        "birth_year": "1946"
                    },
                    {
                        "name": "Karl Olof",
                        "birth_year": "1947"
                    }
                ]
            }
        }
    }
}