{
    "original": "DAHLBORG, NILS, kyrkoherde,\nBroakulla, f i Ljungby 20/1/07 av byggmäst\nEmil D o Hildur Buhre.\nStud:ex Kalmar 27, teol kand Lund 35,\nkyrkoadj Traryd 42, kommm Algutsboda\n42, kyrkoh där sed 60. - Ordf\nkyrko-fullm, kyrkoråd o skolstyr sed 60.\nGift 40  m  Stina  Emborg f   17,  dtr  t\nstat :insp Fritiof E o Emma Svensson.\n-Barn: Nils-Olof f 44, Kerstin f 47.\n\nDAHLBÄCK,    GUSTAF    A,   rektor,\n\nVäxjö, f i Alvesta, Kronob l, 1/3/11 av\npastor August D o Anna Mattsson.\nStud:ex Ekenäs (Finl) 28, teol kand\nLund 34, fil kand 44, teol lic 47, teol dr\n50; kommin Svanstein 36-41, kyrkoh\nGrevbäck 42-48, lekt folksk:sem Luleå\n48-51, Växjö sed 51, rekt där sed 56.\n-Ordf kyrkofullm sed 56. - Skr: Den\ngamla o den nya människan i Lars Levi\n\nLaestadius’ teologi (drsavh 50),\nLektions-handledn f konfirmandundervisningen\n(tills m a 60), Laestadius o hans gärning\n(tills m P Boreman 65) m m. - Medl\nFrimO, Lions club.\n\nGift 36 m Anna Stina Kindberg f 16, dtr\nt glasmäst Fritiof K o Elin Svensson.\n-Barn: Britta f 37, Bengt f 38, Kerstin\nf 42, Karin f 45, Anders f 50.\n\nDAHLBÄCK, NILS A, lantmästare,\nHangvar, f i Visby 26/10/12 av bankdir\nAdolf D o Agnes Nyström.\nRealex 29, Hemse lantm:sk 30,\nBjärka-Säby lantbr :sk 34, lantmäst :kurs Alnarp\n35, insp Ihre gård 36, ag o brukar Ihre\ngård sed 41 (fårskötsel). - Ordf Gotl\nhypot:fören, Gotl fåravelsfören, styr :led\nGotl lantm centralfören. - Led\nkomm:-nd, komm:fullm, ordf skolstyr Lärbro.\n-Medl Odd Fellow, Rotary. - Hobbies:\njakt, bridge.\n\nGift 40 m Mait Forsmark f 16, dtr t\nkamr Götrik F o Maria Mattsson.\n-Barn: Ragnhild f 41, Ingrid f 44, Maj\nf 49, Mats f 58.\n\n",
    "structured": {
        "1": {
            "full_name": "NILS DAHLBORG",
            "location": "Broakulla",
            "occupation": "kyrkoherde",
            "birth_details": {
                "date": "20/01/1907",
                "place": "Ljungby",
                "parents": "byggmäst Emil D o Hildur Buhre"
            },
            "education": [
                {
                    "degree": "Stud:ex",
                    "year": "1927",
                    "institution": "Kalmar"
                },
                {
                    "degree": "teol kand",
                    "year": "1935",
                    "institution": "Lund"
                }
            ],
            "career": [
                {
                    "position": "kyrkoadj",
                    "years": {
                        "start_year": 1942,
                        "end_year": 1942
                    },
                    "organization": "Traryd"
                },
                {
                    "position": "kommm",
                    "years": {
                        "start_year": 1942,
                        "end_year": 1942
                    },
                    "organization": "Algutsboda"
                },
                {
                    "position": "kyrkoh",
                    "years": {
                        "start_year": 1960,
                        "end_year": null
                    },
                    "organization": "Alvesta"
                }
            ],
            "family": {
                "spouse": "Stina Emborg",
                "marriage_year": "1940",
                "children": [
                    {
                        "name": "Nils-Olof",
                        "birth_year": "1944"
                    },
                    {
                        "name": "Kerstin",
                        "birth_year": "1947"
                    }
                ]
            }
        },
        "2": {
            "full_name": "GUSTAF A DAHLBÄCK",
            "location": "Växjö",
            "occupation": "rektor",
            "birth_details": {
                "date": "01/03/1911",
                "place": "Alvesta, Kronob l",
                "parents": "pastor August D o Anna Mattsson"
            },
            "education": [
                {
                    "degree": "Stud:ex",
                    "year": "1928",
                    "institution": "Ekenäs (Finl)"
                },
                {
                    "degree": "teol kand",
                    "year": "1934",
                    "institution": "Lund"
                },
                {
                    "degree": "filosofie kandidat",
                    "year": "1944",
                    "institution": null
                },
                {
                    "degree": "teol lic",
                    "year": "1947",
                    "institution": null
                },
                {
                    "degree": "teol dr",
                    "year": "1950",
                    "institution": null
                }
            ],
            "career": [
                {
                    "position": "kommin",
                    "years": {
                        "start_year": 1936,
                        "end_year": 1941
                    },
                    "organization": "Svanstein"
                },
                {
                    "position": "kyrkoh",
                    "years": {
                        "start_year": 1942,
                        "end_year": 1948
                    },
                    "organization": "Grevbäck"
                },
                {
                    "position": "lekt",
                    "years": {
                        "start_year": 1948,
                        "end_year": 1951
                    },
                    "organization": "folksk:sem Luleå"
                },
                {
                    "position": "rekt",
                    "years": {
                        "start_year": 1951,
                        "end_year": null
                    },
                    "organization": "Växjö"
                }
            ],
            "family": {
                "spouse": "Anna Stina Kindberg",
                "marriage_year": "1936",
                "children": [
                    {
                        "name": "Britta",
                        "birth_year": "1937"
                    },
                    {
                        "name": "Bengt",
                        "birth_year": "1938"
                    },
                    {
                        "name": "Kerstin",
                        "birth_year": "1942"
                    },
                    {
                        "name": "Karin",
                        "birth_year": "1945"
                    },
                    {
                        "name": "Anders",
                        "birth_year": "1950"
                    }
                ]
            }
        },
        "3": {
            "full_name": "NILS A DAHLBÄCK",
            "location": "Hangvar",
            "occupation": "lantmästare",
            "birth_details": {
                "date": "26/10/1912",
                "place": "Visby",
                "parents": "bankdir Adolf D o Agnes Nyström"
            },
            "education": [
                {
                    "degree": "Realex",
                    "year": "1929",
                    "institution": null
                },
                {
                    "degree": "lantm:sk",
                    "year": "1930",
                    "institution": "Hemse"
                },
                {
                    "degree": "lantbr :sk",
                    "year": "1934",
                    "institution": "Bjärka-Säby"
                },
                {
                    "degree": "lantmäst :kurs",
                    "year": "1935",
                    "institution": "Alnarp"
                }
            ],
            "career": [
                {
                    "position": "insp",
                    "years": {
                        "start_year": 1936,
                        "end_year": null
                    },
                    "organization": "Ihre gård"
                },
                {
                    "position": "ag o brukar",
                    "years": {
                        "start_year": 1941,
                        "end_year": null
                    },
                    "organization": "Ihre gård (fårskötsel)"
                }
            ],
            "family": {
                "spouse": "Mait Forsmark",
                "marriage_year": "1940",
                "children": [
                    {
                        "name": "Ragnhild",
                        "birth_year": "1941"
                    },
                    {
                        "name": "Ingrid",
                        "birth_year": "1944"
                    },
                    {
                        "name": "Maj",
                        "birth_year": "1949"
                    },
                    {
                        "name": "Mats",
                        "birth_year": "1958"
                    }
                ]
            },
            "hobbies": [
                "jakt",
                "bridge"
            ]
        }
    }
}