{
    "original": "DAFGÅRD, K GUNNAR W,\ndirektör, Källby, f i Vänersborg 9/1/19 av\nhandl Gustaf D o Jenny Andersson.\nVerkst dir o ag Gunnar Dafgård ab sed\n37, deläg ab Jordgubbar Finnerödja, ag\nSwedish Food Co AS Helsingör.\n-Styr :led Köttbranschens riksförb,\nSkarab l slakteri- o chark:idk:fören, SHB\nLidkpg. - Medl Odd Fellow, Rotary,\nSvarta ÖrnarsO. - Hobbies: golf,\nskid-sport.\n\nGift 43 m Nancy Johansson f 20, dtr t\nfabr Albert J o Signe J. - Barn: Thomas\nf 49, Ulf f 55.\n\nDAHL, EINAR W R, rektor,\nUddevalla, f i Falun 1/3/04 av stadsvaktm\nAxel D o Signe Steen.\nStud:ex 24, folkskollär :ex Karlstad 26,\nfolkskollär Uddevalla 31 (eo 27),\növerlär 51, rekt där sed 55. - AK 54-57, FK\nsed 58 (suppl konst :utsk sed 54).\n-Landst:man sed 39, ordf landst sed 52,\nled Stadsfullm 30, ordf sed 59. -\nStyr:-led Universala Esperanto Asocio o dess\nkomm. - Medl IOGT, NTO, TempelrO.\n- Skr: Lärobok i esperanto för skolan,\nbarnpjäser, tidn:art.\n\nGift 31 m Maja Lundberg f 04, dtr t\nbrevbär Johan L o Augusta L. - Barn:\nMarianne f 34, Jan-Axel f 37.\n\nDAHL, ERIK F, arkitekt SAR,\nNorrköping, f i Upps 14/2/17 av häradsh\nEmil D o Elisabeth Åmark.\nStud:ex 35, KTH 41, anst öl firmor\n42-47, byggn :styr 48, fastigh :kont Sthlm 49,\ntekn byrån bost:styr 53, konsult\narkit:-verksamh tills m arkit SAR Arne\nStröm-dahl Norrkpg o Malmö sed 54. - Bl utf\narb: bost:omr Skönstaholm Sthlm,\nGuldkullen Motala, H tekn lärov o Komm\nflicksk Norrkpg, central förvaltn :byggn\nFinspång, idr:anläggn, varmbadhus o\nfriluftsbad Norrkpg. - Ett flert pris o\ninköp i arkit :tävl. - Hobbies: tennis,\nmusik.\n\nGift 42 m Gunlög Thullberg f 20, dtr t\napot Fritz T o Svea Johannesén. - Barn:\nKristina f 44, Torbjörn f 48.\n\n",
    "structured": {
        "0": {
            "full_name": "GUNNAR W DAFGÅRD",
            "location": "Källby",
            "occupation": "direktör",
            "birth_details": {
                "date": "09/01/1919",
                "place": "Vänersborg",
                "parents": "handl Gustaf D o Jenny Andersson"
            },
            "education": [],
            "career": [
                {
                    "position": "verkst dir",
                    "years": {
                        "start_year": 1937,
                        "end_year": null
                    },
                    "organization": "Gunnar Dafgård ab"
                }
            ],
            "family": {
                "spouse": "Nancy Johansson",
                "marriage_year": "1943",
                "children": [
                    {
                        "name": "Thomas",
                        "birth_year": "1949"
                    },
                    {
                        "name": "Ulf",
                        "birth_year": "1955"
                    }
                ]
            },
            "hobbies": [
                "golf",
                "skid-sport"
            ]
        },
        "1": {
            "full_name": "EINAR W R DAHL",
            "location": "Uddevalla",
            "occupation": "rektor",
            "birth_details": {
                "date": "01/03/1904",
                "place": "Falun",
                "parents": "stadsvaktm Axel D o Signe Steen"
            },
            "education": [
                {
                    "degree": "Stud:ex",
                    "year": "1924",
                    "institution": null
                },
                {
                    "degree": "folkskollär :ex",
                    "year": "1926",
                    "institution": "Karlstad"
                }
            ],
            "career": [
                {
                    "position": "folkskollär",
                    "years": {
                        "start_year": 1931,
                        "end_year": 1955
                    },
                    "organization": "Uddevalla"
                },
                {
                    "position": "överlär",
                    "years": {
                        "start_year": 1951,
                        "end_year": null
                    },
                    "organization": null
                },
                {
                    "position": "rekt",
                    "years": {
                        "start_year": 1955,
                        "end_year": null
                    },
                    "organization": "Uddevalla"
                }
            ],
            "family": {
                "spouse": "Maja Lundberg",
                "marriage_year": "1931",
                "children": [
                    {
                        "name": "Marianne",
                        "birth_year": "1934"
                    },
                    {
                        "name": "Jan-Axel",
                        "birth_year": "1937"
                    }
                ]
            },
            "publications": [
                "Lärobok i esperanto för skolan",
                "barnpjäser",
                "tidn:art"
            ],
            "community_involvement": [
                "Universala Esperanto Asocio o dess komm."
            ],
            "hobbies": []
        },
        "2": {
            "full_name": "ERIK F DAHL",
            "location": "Norrköping",
            "occupation": "arkitekt SAR",
            "birth_details": {
                "date": "14/02/1917",
                "place": "Upps",
                "parents": "häradsh Emil D o Elisabeth Åmark"
            },
            "education": [
                {
                    "degree": "Stud:ex",
                    "year": "1935",
                    "institution": null
                },
                {
                    "degree": null,
                    "year": "1941",
                    "institution": "KTH"
                }
            ],
            "career": [
                {
                    "position": null,
                    "years": {
                        "start_year": 1942,
                        "end_year": 1947
                    },
                    "organization": "ölr firmor"
                },
                {
                    "position": "byggn :styr",
                    "years": {
                        "start_year": 1948,
                        "end_year": null
                    },
                    "organization": null
                },
                {
                    "position": "fastigh :kont",
                    "years": {
                        "start_year": 1949,
                        "end_year": null
                    },
                    "organization": "Sthlm"
                },
                {
                    "position": "tekn byrån",
                    "years": {
                        "start_year": 1953,
                        "end_year": null
                    },
                    "organization": "bost:styr"
                }
            ],
            "family": {
                "spouse": "Gunlög Thullberg",
                "marriage_year": "1942",
                "children": [
                    {
                        "name": "Kristina",
                        "birth_year": "1944"
                    },
                    {
                        "name": "Torbjörn",
                        "birth_year": "1948"
                    }
                ]
            },
            "hobbies": [
                "tennis",
                "musik"
            ]
        }
    }
}