{
    "original": "DOBROWSKY, ROBERT K,\nprovinsialläkare, Söderköping, f i Wien 20/1/\n\n17 av bankdir Josef D o Maria\nPö-singer.\n\nStud:ex 36, läk:ex o Dr Med Wien 41,\nKungl Maj:ts tillst att i Sv:e utöva\nläkekonsten 54; båt:- o reg:läk fronten\n41-45, läk öl krigsfångeläger 45-47,\nklinik-läk Wien 48-51, underläk las Kalmar o\nUddevalla 51-53, l:e underläk Söderkpgs\nlas 54, pro v :läk Söderkpgs inre distr sed\n58. - Led hälso- o barnav:nd. - Led\nÖst-g:kr av Sv pro v :läk :f ören, medl Österg\nö läk:fören, Odd Fellow. - Utm: 8\nordnar från andra världskriget. - Hobbies:\nfiske, schack, filateli.\nGift 50 m Milde Buchner-Santinelli.\n-Barn: Leo f 39, Verner f 51.\n\nDOHLMAN, F GÖSTA, professor em,\nSolberga, f i Sthlm 5/10/90 av med lic\nFritz Svensson o Agnes Stenberg.\nMed lic Sthlm 20, med dr Upps 25, doc\ni oto-rhino-laryngologi Upps 25, överläk\noto-laryngolog klin Lund 30-56, prof i\nöron-, näs- o halssjukdomar Lund 38-56.\n- Forskn :uppdr USA 56-61, vik prof\nUniv of Toronto Canada sed 61. -\nMa-rinläk l:a gr 22-45. - Sekt :ordf SLF\n39-45. - LFS 38, hedL ett flert sv o utl\nvetensk sällsk. - Skr i otolog ämnen.\n-Utm: KNO, FFrK3o4kl, RNS:tOO.\nGift 21 m Ebba Ribbing f 98, dtr t\növ :löjtn Sven R o frih:an Ebba\nSilfverschiöld. - Barn: Claes-Henrik f 22,\nAgneta f 26, Gunilla f 27.\n\nDOHRMANN, C ÅKE, advokat,\nVetlanda, f i Söndrum, Hall l, 12/10/18 av\ngrossh Curt D o Signe Olsson.\nStud:ex Halmstad 39, jur kand Lund 48,\ntingstjg Njudungs doms 48-51, bitr jur\nadv Boo Stenbäck Vetlanda 51, eg\nadv:-verksamh där sed 52. - LSA 56. - Led\nStadsfullm sed 59, ordf barnav:ndn sed\n53, styr :led soc:v:byrån sed 55.\nGift 51 m Inga Freyson f 26. - Barn:\nLena f 54, Ulrika f 55.\n\n",
    "structured": {
        "0": {
            "full_name": "ROBERT K DOBROWSKY",
            "location": "Söderköping",
            "occupation": "Provinsialläkare",
            "birth_details": {
                "date": "20/01/1917",
                "place": "Wien"
            },
            "education": [
                {
                    "degree": "Stud:ex",
                    "year": "1936",
                    "institution": "NULL"
                },
                {
                    "degree": "Läk:ex",
                    "year": "1941",
                    "institution": "Wien"
                },
                {
                    "degree": "Dr Med",
                    "year": "NULL",
                    "institution": "Wien"
                }
            ],
            "career": [
                {
                    "position": "Båt:- o reg:läk",
                    "years": {
                        "start_year": 1941,
                        "end_year": 1945
                    },
                    "organization": "Fronten"
                },
                {
                    "position": "Läk öl krigsfångeläger",
                    "years": {
                        "start_year": 1945,
                        "end_year": 1947
                    },
                    "organization": "NULL"
                },
                {
                    "position": "Klinik-läk",
                    "years": {
                        "start_year": 1948,
                        "end_year": 1951
                    },
                    "organization": "Wien"
                },
                {
                    "position": "Underläk",
                    "years": {
                        "start_year": 1951,
                        "end_year": 1953
                    },
                    "organization": "Las Kalmar o Uddevalla"
                },
                {
                    "position": "L:e underläk",
                    "years": {
                        "start_year": 1954,
                        "end_year": 1954
                    },
                    "organization": "Söderkpgs las"
                },
                {
                    "position": "Pro v :läk",
                    "years": {
                        "start_year": 1958,
                        "end_year": "NULL"
                    },
                    "organization": "Söderkpgs inre distr"
                }
            ],
            "family": {
                "spouse": "Milde Buchner-Santinelli",
                "marriage_year": "1950",
                "children": [
                    {
                        "name": "Leo",
                        "birth_year": "1939"
                    },
                    {
                        "name": "Verner",
                        "birth_year": "1951"
                    }
                ]
            },
            "hobbies": [
                "Fiske",
                "Schack",
                "Filateli"
            ]
        },
        "1": {
            "full_name": "F GÖSTA DOHLMAN",
            "location": "Solberga",
            "occupation": "Professor em",
            "birth_details": {
                "date": "5/10/1890",
                "place": "Sthlm"
            },
            "education": [
                {
                    "degree": "Med lic",
                    "year": "1920",
                    "institution": "Sthlm"
                },
                {
                    "degree": "Med dr",
                    "year": "1925",
                    "institution": "Upps"
                }
            ],
            "career": [
                {
                    "position": "Överläk",
                    "years": {
                        "start_year": 1930,
                        "end_year": 1956
                    },
                    "organization": "Oto-laryngolog klin Lund"
                },
                {
                    "position": "Prof i öron-, näs- o halssjukdomar",
                    "years": {
                        "start_year": 1938,
                        "end_year": 1956
                    },
                    "organization": "Lund"
                },
                {
                    "position": "Vik prof",
                    "years": {
                        "start_year": 1961,
                        "end_year": "NULL"
                    },
                    "organization": "Univ of Toronto Canada"
                }
            ],
            "family": {
                "spouse": "Ebba Ribbing",
                "marriage_year": "1921",
                "children": [
                    {
                        "name": "Claes-Henrik",
                        "birth_year": "1922"
                    },
                    {
                        "name": "Agneta",
                        "birth_year": "1926"
                    },
                    {
                        "name": "Gunilla",
                        "birth_year": "1927"
                    }
                ]
            },
            "honorary_titles": [
                {
                    "title": "KNO",
                    "institution": "NULL",
                    "year": "NULL"
                },
                {
                    "title": "FFrK3o4kl",
                    "institution": "NULL",
                    "year": "NULL"
                },
                {
                    "title": "RNS:tOO",
                    "institution": "NULL",
                    "year": "NULL"
                }
            ]
        },
        "2": {
            "full_name": "C ÅKE DOHRMANN",
            "location": "Vetlanda",
            "occupation": "Advokat",
            "birth_details": {
                "date": "12/10/1918",
                "place": "Söndrum, Hall l"
            },
            "education": [
                {
                    "degree": "Stud:ex",
                    "year": "1939",
                    "institution": "Halmstad"
                },
                {
                    "degree": "Jur kand",
                    "year": "1948",
                    "institution": "Lund"
                }
            ],
            "career": [
                {
                    "position": "Tingstjg",
                    "years": {
                        "start_year": 1948,
                        "end_year": 1951
                    },
                    "organization": "Njudungs doms"
                },
                {
                    "position": "Bitr jur adv",
                    "years": {
                        "start_year": 1951,
                        "end_year": "NULL"
                    },
                    "organization": "Boo Stenbäck Vetlanda"
                },
                {
                    "position": "Eg adv:-verksam",
                    "years": {
                        "start_year": 1952,
                        "end_year": "NULL"
                    },
                    "organization": "Vetlanda"
                }
            ],
            "family": {
                "spouse": "Inga Freyson",
                "marriage_year": "1951",
                "children": [
                    {
                        "name": "Lena",
                        "birth_year": "1954"
                    },
                    {
                        "name": "Ulrika",
                        "birth_year": "1955"
                    }
                ]
            }
        }
    }
}