{
    "original": "HORNEWALL, SVEN M,\ncivilingenjör, Sundsvall, f i Kristinehamn 17/3/25\nav dir Magnus Janson o Ebba Banck.\nStud:ex Karlstad 43, KTH 50, DHS 51,\ning ab Separator (Alfa-Laval) Sthlm 51,\nab Casco Sickla 52, sekr SNS Sthlm 54,\nanst pers :admin avd SCA Sundsvall 57,\ntjg avd f admin o utveckl av utl dtrbol\ndär sed 61. - Tjg OECD Paris 61.\n-Styr:led Sv seglarförb 60-64, presid\nInternat OK-jolleförb 62-65. - Hobbies:\nsegling, golf, skidsport.\nGift 49 m lärov:adj Brita Maria\nCederberg f 25, dtr t sågv:äg Johan C o Ellen\nSunne. - Barn: Per f 50, Kerstin f 52,\nHans f 55.\n\nHOVEUUS, KARL A, prost,\nSundsvall, f i Torpa, Kronob l, 20/1/10 av\nhemm:äg Johan Petersson o Karolina\nSvensson.\n\nStud:ex 28 o teol kand Lund 33, prästv\nLuleå 34, v past Åsele 34, kyrkoadj\nHolmsund 36, kommin Överkalix 39,\nkyrkoh Överlännäs-Sånga förs 50,\nSundsvalls Gustav Adolfs o Skönsmons förs\nsed 59, prost över egna förs sed 63.\n-Ordf kyrkorådet Sundsvall sed 59, led\nHärnösands stiftsting sed 65, led\nstiftsrådet o ordf dess ekon:nd sed 66. - Medl\nFrimO, Rotary. - Utm: LNO.\nGift 37 m Anna-Brita Nettelbladt, dtr t\njägm Teodor N o Helena Engman.\n-Barn: Lennart f 39, Lena f 41, Ylva\nf 46.\n\nHUGOSSON, S TORSTEN,\növeringenjör, Stockviksverken, f i Mörarp,\nMalmöh l, 17/1/27 av Hugo Svensson o\nElin Bengtsson.\n\nStud:ex Hbg 46, KTH 51, lab:ing\nFos-fatbol ab Stockviksverken 51, avd :ch 57,\növering där sed 62. - Medl Rotary.\nGift 55 m Kerstin Nordgren f 29, dtr t\nkonsul Hugo N o Anna-Greta N. - Barn:\nSvante f 56, Katarina o Torbjörn ff 59.\n\n13 norr\n\nHULDT se HULT\n\n",
    "structured": {
        "0": {
            "full_name": "Sven M Hornewall",
            "location": "Sundsvall",
            "occupation": "Civilingenjör",
            "birth_details": {
                "date": "17/03/1925",
                "place": "Kristinehamn",
                "parents": "Direktör Magnus Janson och Ebba Banck"
            },
            "education": [
                {
                    "degree": "Stud:ex",
                    "year": "1943",
                    "institution": "Karlstad"
                },
                {
                    "degree": "KTH",
                    "year": "1950",
                    "institution": "KTH"
                },
                {
                    "degree": "DHS",
                    "year": "1951",
                    "institution": "DHS"
                }
            ],
            "career": [
                {
                    "position": "Ing ab Separator (Alfa-Laval) Sthlm",
                    "years": {
                        "start_year": 1951,
                        "end_year": 1951
                    },
                    "organization": "Alfa-Laval"
                },
                {
                    "position": "ab Casco Sickla",
                    "years": {
                        "start_year": 1952,
                        "end_year": 1952
                    },
                    "organization": "Casco Sickla"
                },
                {
                    "position": "Sekr SNS Sthlm",
                    "years": {
                        "start_year": 1954,
                        "end_year": 1954
                    },
                    "organization": "SNS Sthlm"
                },
                {
                    "position": "Anst Pers :admin avd SCA Sundsvall",
                    "years": {
                        "start_year": 1957,
                        "end_year": 1957
                    },
                    "organization": "SCA Sundsvall"
                },
                {
                    "position": "Tjg avd f admin o utveckl av utl dtrbol",
                    "years": {
                        "start_year": 1961,
                        "end_year": 1961
                    }
                },
                {
                    "position": "Tjg OECD Paris",
                    "years": {
                        "start_year": 1961,
                        "end_year": 1961
                    },
                    "organization": "OECD Paris"
                }
            ],
            "family": {
                "spouse": "Brita Maria Cederberg",
                "marriage_year": "1949",
                "children": [
                    {
                        "name": "Per",
                        "birth_year": "1950"
                    },
                    {
                        "name": "Kerstin",
                        "birth_year": "1952"
                    },
                    {
                        "name": "Hans",
                        "birth_year": "1955"
                    }
                ]
            },
            "hobbies": [
                "Segling",
                "Golf",
                "Skidsport"
            ]
        },
        "1": {
            "full_name": "Karl A Hoveuus",
            "location": "Sundsvall",
            "occupation": "Prost",
            "birth_details": {
                "date": "20/01/1910",
                "place": "Torpa, Kronob l",
                "parents": "Hemm:äg Johan Petersson och Karolina Svensson"
            },
            "education": [
                {
                    "degree": "Stud:ex",
                    "year": "1928",
                    "institution": "Lund"
                },
                {
                    "degree": "Teol kand",
                    "year": "1933",
                    "institution": "Lund"
                }
            ],
            "career": [
                {
                    "position": "Prästv Luleå",
                    "years": {
                        "start_year": 1934,
                        "end_year": 1934
                    }
                },
                {
                    "position": "V past Åsele",
                    "years": {
                        "start_year": 1934,
                        "end_year": 1934
                    }
                },
                {
                    "position": "Kyrkoadj Holmsund",
                    "years": {
                        "start_year": 1936,
                        "end_year": 1936
                    }
                },
                {
                    "position": "Kommin Överkalix",
                    "years": {
                        "start_year": 1939,
                        "end_year": 1939
                    }
                },
                {
                    "position": "Kyrkoh Överlännäs-Sånga förs",
                    "years": {
                        "start_year": 1950,
                        "end_year": 1950
                    },
                    "organization": "Överlännäs-Sånga förs"
                },
                {
                    "position": "Prost över egna förs",
                    "years": {
                        "start_year": 1963,
                        "end_year": 1963
                    }
                }
            ],
            "family": {
                "spouse": "Anna-Brita Nettelbladt",
                "marriage_year": "1937",
                "children": [
                    {
                        "name": "Lennart",
                        "birth_year": "1939"
                    },
                    {
                        "name": "Lena",
                        "birth_year": "1941"
                    },
                    {
                        "name": "Ylva",
                        "birth_year": "1946"
                    }
                ]
            },
            "community_involvement": [
                {
                    "role": "Ordf kyrkorådet Sundsvall",
                    "organization": "Sundsvall"
                }
            ],
            "honorary_titles": [
                {
                    "title": "LNO"
                }
            ]
        },
        "2": {
            "full_name": "S Torsten Hugosson",
            "occupation": "Överingenjör",
            "location": "Stockviksverken",
            "birth_details": {
                "date": "17/01/1927",
                "place": "Mörarp, Malmöh l",
                "parents": "Hugo Svensson och Elin Bengtsson"
            },
            "education": [
                {
                    "degree": "Stud:ex",
                    "year": "1946",
                    "institution": "Malmö"
                },
                {
                    "degree": "KTH",
                    "year": "1951",
                    "institution": "KTH"
                }
            ],
            "career": [
                {
                    "position": "Lab:ing Fos-fatbol ab Stockviksverken",
                    "years": {
                        "start_year": 1951,
                        "end_year": 1951
                    },
                    "organization": "Stockviksverken"
                },
                {
                    "position": "Avd :ch",
                    "years": {
                        "start_year": 1957,
                        "end_year": 1957
                    }
                },
                {
                    "position": "Övering",
                    "years": {
                        "start_year": 1962,
                        "end_year": 1962
                    }
                }
            ],
            "family": {
                "spouse": "Kerstin Nordgren",
                "marriage_year": "1955",
                "children": [
                    {
                        "name": "Svante",
                        "birth_year": "1956"
                    },
                    {
                        "name": "Katarina",
                        "birth_year": "1959"
                    },
                    {
                        "name": "Torbjörn",
                        "birth_year": "1959"
                    }
                ]
            },
            "community_involvement": [
                {
                    "role": "Medl Rotary",
                    "organization": "Rotary"
                }
            ]
        }
    }
}