{
    "original": "HOFF, SVEN H, mejeriingenjör,\nÖstersund, f i Tönsberg, Norge, 28/11/16 av\nred Jörgen H o Oline Madsen.\nStud:ex Tönsberg 38, Mejerisk\nTrondheim 41, Katrineholms tekn sk 42, h\nmejerikurs Alnarp 46, anst Sv\nmejeriernas riksfören 46-47 o 49-51, Vetlanda\nmejerifören 47-48, Riksost 52-53,\nprod:-ch Jämtl l mejerifören Östersund sed 53.\nGift 54 m Anne-Marie Gustafsson, dtr t\nHelge G o Thyra Holmqvist. - Barn:\nLennart.\n\nHOFFMAN, WITOLD E,\nprovinsialläkare, Ramvik, f i Zakopane, Polen,\n21/3/20 av Dr jur Mikael H o Matilda\nSiess.\n\nStud:ex Krakow 37, med kand Warszawa\n39, läk:ex Innsbruck 48, Kungl Maj:ts\ntillst att i Sv:e utöva läkekonsten 53; tjg\nmed avd Allgemeines Krankenhaus Stadt\nLinz a d Donau 48-52, underläk kir o\nmed avd Umeå las 52-58, prov:läk\nHögsjö distr Ramvik sed 58. - Medl Lions\nclub. - Hobbies: jakt, fiske, skidsport.\nGift. 56 m folkskollär Ulla Pettersson\nf 32, dtr t hemm:äg Oscar P o Ruth P.\n- Barn: Kristina f 57, Jan f 60, Anna\nMaria f 63.\n\nHOFVERBERG, SIMON, rektor,\nBurträsk, f i Furunäs, Västerb l, 16/12/15\nav köpm Wlnof H o Fanny Sjölund.\nStud:ex 36 o teol kand Upps 41; lär\nMellansel folkhögsk 36-41, rekt\nEdel-viks folkhögsk Burträsk sed 41 (tji\n52-53), rekt Hellidens folkhögsk Tidaholm\n52-53. - Tf undervisn:råd, tf\nfolkhögsk:-insp, tf konsulent f nykterh:undervisn,\nföredr i byggn :frågor f folkhögsk :or m m\nperiodv sed 61. - Ordf Västerb distr av\nSv:es blåbandsförb 51-64, led dess\ncentralstyr 54-67, stud:rekt Blåbandsrör:s\nstudieförb 55-66, v ordf Västerb l\nsångar-förb 52-60, ordf sed 60, led diakonistyr\nSkolutskott sed 63. - Landst:man sed 63,\nled landst :komm f utredn om\nlantbr:un-dervisn i Västerb l 63-64, led landst\nkul-turnd sed 66. - Medl TempelrO\n(stormast sed 65). - Skr: författa :handbok f\nfolkhögskolor (SO 62-66). - Utm: RNO,\nSv sångarfbftjt, Västerb l sångarfbftjt.\n-Hobby: musik.\n\nGift 39 m Greta Bergström f 16, dtr t\nj v :tjm J L B o Maria ögren. - Barn:\nGunilla f 40, Bertil f 41, Karin f 45,\nIngrid f 46, Gunnar f 51.\n\n",
    "structured": {
        "0": {
            "full_name": "Sven H Hoff",
            "location": "Östersund",
            "occupation": "Mejeriingenjör",
            "birth_details": {
                "date": "28/11/1916",
                "place": "Tönsberg, Norge",
                "parents": "red Jörgen H and Oline Madsen"
            },
            "education": [
                {
                    "degree": "Stud:ex",
                    "year": "1938",
                    "institution": "Tönsberg"
                },
                {
                    "degree": "Mejerisk",
                    "year": "1941",
                    "institution": "Trondheim"
                },
                {
                    "degree": "Katrineholms tekn sk",
                    "year": "1942",
                    "institution": "Katrineholms"
                },
                {
                    "degree": "mejerikurs Alnarp",
                    "year": "1946",
                    "institution": "Alnarp"
                }
            ],
            "career": [
                {
                    "position": "anst Sv mejeriernas riksfören",
                    "years": {
                        "start_year": 1946,
                        "end_year": 1947
                    },
                    "organization": "Sv mejeriernas riksfören"
                },
                {
                    "position": "Vetlanda mejerifören",
                    "years": {
                        "start_year": 1947,
                        "end_year": 1948
                    },
                    "organization": "Vetlanda mejerifören"
                },
                {
                    "position": "Riksost",
                    "years": {
                        "start_year": 1952,
                        "end_year": 1953
                    },
                    "organization": "Riksost"
                },
                {
                    "position": "prod:-ch Jämtl L mejerifören Östersund",
                    "years": {
                        "start_year": 1953,
                        "end_year": null
                    },
                    "organization": "Jämtl L mejerifören Östersund"
                }
            ],
            "family": {
                "spouse": "Anne-Marie Gustafsson",
                "marriage_year": "1954",
                "children": [
                    {
                        "name": "Lennart",
                        "birth_year": null
                    }
                ]
            }
        },
        "1": {
            "full_name": "Witold E Hoffman",
            "location": "Ramvik",
            "occupation": "Provinsialläkare",
            "birth_details": {
                "date": "21/03/1920",
                "place": "Zakopane, Polen",
                "parents": "Dr jur Mikael H and Matilda Siess"
            },
            "education": [
                {
                    "degree": "Stud:ex",
                    "year": "1937",
                    "institution": "Krakow"
                },
                {
                    "degree": "med kand",
                    "year": "1939",
                    "institution": "Warszawa"
                },
                {
                    "degree": "lädex",
                    "year": "1948",
                    "institution": "Innsbruck"
                }
            ],
            "career": [
                {
                    "position": "tjg med avd Allgemeines Krankenhaus Stadt Linz a d Donau",
                    "years": {
                        "start_year": 1948,
                        "end_year": 1952
                    },
                    "organization": "Allgemeines Krankenhaus Stadt Linz a d Donau"
                },
                {
                    "position": "underläk kir o med avd Umeå las",
                    "years": {
                        "start_year": 1952,
                        "end_year": 1958
                    },
                    "organization": "Umeå las"
                },
                {
                    "position": "prov:läk Högsjö distr Ramvik",
                    "years": {
                        "start_year": 1958,
                        "end_year": null
                    },
                    "organization": "Högsjö distr Ramvik"
                }
            ],
            "family": {
                "spouse": "Ulla Pettersson",
                "marriage_year": "1956",
                "children": [
                    {
                        "name": "Kristina",
                        "birth_year": "1957"
                    },
                    {
                        "name": "Jan",
                        "birth_year": "1960"
                    },
                    {
                        "name": "Anna Maria",
                        "birth_year": "1963"
                    }
                ]
            },
            "hobbies": [
                "jakt",
                "fiske",
                "skidsport"
            ]
        },
        "2": {
            "full_name": "Simon Hofverberg",
            "location": "Burträsk",
            "occupation": "Rektor",
            "birth_details": {
                "date": "16/12/1915",
                "place": "Furunäs, Västerb l",
                "parents": "köpm Wlnof H and Fanny Sjölund"
            },
            "education": [
                {
                    "degree": "Stud:ex",
                    "year": "1936",
                    "institution": "Mellansel folkhögsk"
                },
                {
                    "degree": "teol kand",
                    "year": "1941",
                    "institution": "Upps"
                }
            ],
            "career": [
                {
                    "position": "rekt Edel-viks folkhögsk Burträsk",
                    "years": {
                        "start_year": 1941,
                        "end_year": 1952
                    },
                    "organization": "Edel-viks folkhögsk Burträsk"
                },
                {
                    "position": "rekt Hellidens folkhögsk Tidaholm",
                    "years": {
                        "start_year": 1952,
                        "end_year": 1953
                    },
                    "organization": "Hellidens folkhögsk Tidaholm"
                },
                {
                    "position": "Tf undervisn:råd",
                    "years": {
                        "start_year": 1961,
                        "end_year": null
                    }
                }
            ],
            "family": {
                "spouse": "Greta Bergström",
                "marriage_year": "1939",
                "children": [
                    {
                        "name": "Gunilla",
                        "birth_year": "1940"
                    },
                    {
                        "name": "Bertil",
                        "birth_year": "1941"
                    },
                    {
                        "name": "Karin",
                        "birth_year": "1945"
                    },
                    {
                        "name": "Ingrid",
                        "birth_year": "1946"
                    },
                    {
                        "name": "Gunnar",
                        "birth_year": "1951"
                    }
                ]
            },
            "community_involvement": [
                {
                    "role": "Ordf Västerb distr av Sv:es blåbandsförb",
                    "organization": "Sv:es blåbandsförb",
                    "years": "1951-1964"
                }
            ],
            "board_memberships": [
                {
                    "position": "Led landst kul-turnd",
                    "organization": "landst :komm f utredn om lantbr:un-dervisn i Västerb l",
                    "years": "1963-1964"
                }
            ],
            "honorary_titles": [
                {
                    "title": "RNO",
                    "institution": null,
                    "year": null
                },
                {
                    "title": "Sv sångarfbftjt",
                    "institution": null,
                    "year": null
                },
                {
                    "title": "Västerb l sångarfbftjt",
                    "institution": null,
                    "year": null
                }
            ],
            "hobbies": [
                "musik"
            ]
        }
    }
}