{
    "original": "HARTMAN,   ULLA   G,   tandläkare,\n\nGävle, f i Emmaboda, Kalmar l, 30/9/23\nav folkskollär Hjalmar H o Elin\nJonsson.\n\nStud:ex Skara 44, tandl:ex Sthlm 51,\ndistr:tandl Gävle 51-58, l:e distr:tandl\ndär sed 58.\n\nHASLUM,   J   BERTIL   O,   direktör,\n\nHolmsund, f i Gudmundrå, Vnorrl l,\n23/9/17 av dir Jörgen H o Aina\nMalmström.\n\nStud:ex Sigtuna 36, jur kand Sthlm 43,\ntingstjg N Möre o Stranda doms 43-46,\nbitr jur Alrutz’ adv:byrå Sthlm 46-47,\nomb :man Holmsunds ab Holmsund\n(dtr-bol t SCA) 47-54, ch pers:adm avd SCA\n54-62, dir 59, ch SCA\nHolmsundsgrup-pen sed 63 samt verkst dir ab Bröd\nEriksons mek snickerifabr Örebro sed\n65. - Led komm:fullm Holmsunds kpg\n51-54, Vnorrl l landst 59-62, styr:led\nVnorrl l föret:fören 57-62, nederländsk\nvicekonsul Umeå sed 63, ordf Sv\nhdls-bkns distr:styr Umeå sed 63, styr:led\nSocHS Umeå sed 62, led utbildn:rådet f\nekon:utbildn v Umeå univ sed 65,\npla-ner:rådet i Västerb l sed 65. - Utm:\nRVO, FHMM.\n\nGift 45 m gymn :dir Brita Assarsson\nf 22, dtr t labor, fil dr Gunnar A o\nlärov :adj Alice Appelqvist. - Barn:\nJörgen f 47, Beate f 49, Marie f 58.\n\nHASSELBERG, K GÖRAN, rådman,\n\nSundsvall,  f  i   Grundsunda,  Vnorrl  l,\n\n14/8/24 av lekt Gudmar H o Rut Luter-\n\nkort.\n\nStud:ex Gävle 43, jur kand Sthlm 49,\n\ntingstjg Jämtl n doms 49-51, fiskal hovr\nf N Norrl 52, tingssekr Jämtl n doms\n54, Bollnäs doms 55-56, assess rådhusr\nSundsvall 57, adj led hovr N Norrl\n61-62, rådm rådhusr Sundsvall sed 64,\n-Sekr utskrivn:nd Vnorrl l sed 58, suppl\nf ordf där sed 65.\n\nGift 56 m Inga Oddmar f 31, dtr t\nkyr-koh Emanuel O o Rut Selin. - Barn:\nLena f 57, Henrik f 59.\n\n",
    "structured": {
        "0": {
            "full_name": "ULLA G HARTMAN",
            "location": "Gävle",
            "occupation": "tandläkare",
            "birth_details": {
                "date": "30/09/1923",
                "place": "Emmaboda, Kalmar l",
                "parents": "folkskollär Hjalmar H o Elin Jonsson"
            },
            "education": [
                {
                    "degree": "Stud:ex",
                    "year": "1944",
                    "institution": "Skara"
                },
                {
                    "degree": "tandl:ex",
                    "year": "1951",
                    "institution": "Sthlm"
                }
            ],
            "career": [
                {
                    "position": "distr:tandl",
                    "years": {
                        "start_year": 1951,
                        "end_year": 1958
                    },
                    "organization": "Gävle"
                },
                {
                    "position": "l:e distr:tandl",
                    "years": {
                        "start_year": 1958
                    },
                    "organization": "Gävle"
                }
            ],
            "family": {
                "spouse": "NULL",
                "marriage_year": "NULL",
                "children": []
            }
        },
        "1": {
            "full_name": "J BERTIL O HASLUM",
            "location": "Holmsund",
            "occupation": "direktör",
            "birth_details": {
                "date": "23/09/1917",
                "place": "Gudmundrå, Vnorrl l",
                "parents": "dir Jörgen H o Aina Malmström"
            },
            "education": [
                {
                    "degree": "Stud:ex",
                    "year": "1936",
                    "institution": "Sigtuna"
                },
                {
                    "degree": "jur kand",
                    "year": "1943",
                    "institution": "Sthlm"
                }
            ],
            "career": [
                {
                    "position": "tingstjg",
                    "years": {
                        "start_year": 1943,
                        "end_year": 1946
                    },
                    "organization": "N Möre o Stranda doms"
                },
                {
                    "position": "bitr jur",
                    "years": {
                        "start_year": 1946,
                        "end_year": 1947
                    },
                    "organization": "Alrutz’ adv:byrå Sthlm"
                },
                {
                    "position": "omb :man",
                    "years": {
                        "start_year": 1947
                    },
                    "organization": "Holmsunds ab Holmsund (dtr-bol t SCA)"
                },
                {
                    "position": "ch pers:adm avd",
                    "years": {
                        "start_year": 1954,
                        "end_year": 1962
                    },
                    "organization": "SCA"
                },
                {
                    "position": "dir",
                    "years": {
                        "start_year": 1959
                    },
                    "organization": "SCA Holmsundsgruppen"
                },
                {
                    "position": "verkst dir",
                    "years": {
                        "start_year": 1965
                    },
                    "organization": "ab Bröd Eriksons mek snickerifabr Örebro"
                }
            ],
            "family": {
                "spouse": "gymn :dir Brita Assarsson f 22",
                "marriage_year": "1945",
                "children": [
                    {
                        "name": "Jörgen",
                        "birth_year": "1947"
                    },
                    {
                        "name": "Beate",
                        "birth_year": "1949"
                    },
                    {
                        "name": "Marie",
                        "birth_year": "1958"
                    }
                ]
            }
        },
        "2": {
            "full_name": "K GÖRAN HASSELBERG",
            "location": "Sundsvall",
            "occupation": "rådman",
            "birth_details": {
                "date": "14/08/1924",
                "place": "Grundsunda, Vnorrl l",
                "parents": "lekt Gudmar H o Rut Luterkort"
            },
            "education": [
                {
                    "degree": "Stud:ex",
                    "year": "1943",
                    "institution": "Gävle"
                },
                {
                    "degree": "jur kand",
                    "year": "1949",
                    "institution": "Sthlm"
                }
            ],
            "career": [
                {
                    "position": "tingstjg",
                    "years": {
                        "start_year": 1949,
                        "end_year": 1951
                    },
                    "organization": "Jämtl n doms"
                },
                {
                    "position": "fiskal hovr",
                    "years": {
                        "start_year": 1952
                    },
                    "organization": "N Norrl"
                },
                {
                    "position": "tingssekr",
                    "years": {
                        "start_year": 1954,
                        "end_year": 1956
                    },
                    "organization": "Jämtl n doms, Bollnäs doms"
                },
                {
                    "position": "assess rådhusr",
                    "years": {
                        "start_year": 1957
                    },
                    "organization": "Sundsvall"
                },
                {
                    "position": "adj led hovr",
                    "years": {
                        "start_year": 1961,
                        "end_year": 1962
                    },
                    "organization": "N Norrl"
                },
                {
                    "position": "rådm rådhusr",
                    "years": {
                        "start_year": 1964
                    },
                    "organization": "Sundsvall"
                }
            ],
            "family": {
                "spouse": "Inga Oddmar f 31",
                "marriage_year": "1956",
                "children": [
                    {
                        "name": "Lena",
                        "birth_year": "1957"
                    },
                    {
                        "name": "Henrik",
                        "birth_year": "1959"
                    }
                ]
            }
        }
    }
}