{
    "original": "HESSNER,   OLOF   E   J,   jägmästare,\n\nHudiksvall, f i Skogaholm, Örebro l,\n18/3/11 av bergsing Justinus H o\nHelena Norström.\n\nRes:off:ex 34, civ:jägm:ex SkHS 38,\njägm Munksunds ab Luleå 38, skogsförv\nJokkmokk 47, Strömbacka förvaltn\nIggesunds bruks ab 56, skyddsch ab\nIggesunds bruks ind:er o skogar sed 64. - Ch\nBergsjö hv :krets sed 62. - Kapt I 3 res\n47. - Hobbies: jakt, fiske, Skytte.\nGift 43 m textilkonstn Else Asker f 15,\ndtr t ing Erik A o Elisabet Friedrichsen.\n- Barn: Lisen f 45, Lärs-Olof f 55.\n\nHETTINGER, GUNNAR, fil dr,\nlaborator,   Umeå,   f   i   Malmö   8/10/30   av\nkont:ch Max H o Anna Seemüller.\nFil kand Lund 55, fil lic 59 o fil dr där\n\n60; aman o ass fys o radiofys inst Lunds\nuniv 55-59, doc i radiofysik 60-61, labor\ni radiofysik Umeå univ o förest radiofys\nlab Umeå las sed 62. - Verkst \"task\nleader\" Internat Commission ön\nRadia-tion Units and Measurements (ICRU)\n61-62, konsult där sed 65. - Skr i\nradiofysik.\n\nGift 55 m Ingrid Araskog f 29, dtr t\nkamr Axel A o Gertrud Creutzfeldt.\n-Barn: Anders f 56, Håkan f 59, Karin\nf 62.\n\nHEYMAN, TURE, rektor, Härnösand,\nf i Sthlm 26/12/17 av dir Bengt H o\nSiri Dahl.\n\nStud:ex 38, KTH 49; ing ab Atlas Diesel\n45, lär Karlskoga stads maskintekn\nfack-sk 49, adj Sjöbef :sk Härnösand 54, rekt\ndär sed 58. - Led hamnstyr Härnösand\n58-63. - Medl Rotary, S:t PetriO.\nGift 44 m Tora Heijl f 22, dtr t dr Carl\nH o Greta Röding. - Barn: Bengt f 45,\nBarbro f 47, Ulf f 49, Lena f 53.\n\nHIETALA,   HUGO  E,  rektor,   över-\n\ntorneå, f i övertorneå, Norrb l, 16/10/11\nav stat :karl Frans H o Hanna\nMoska-järvi.\n\nFolkskollär:ex Luleå 38, stud statskunsk\nUpps univ 65; folkskollär övertorneå\n38-58, rekt obl skolväs där sed 58,\növertorneå kns yrkessk sed 60. - Hv :ch sed\n44. - Styr:led Norrb idr:förb sed 44,\nNorrb skidförb sed 46 (ordf sed 57), Sv\nskidförb sed 57. - Led komm:fullm\nÖvertorneå sed 46, ordf skolstyr o byggn :ndn\nsed 53, Stift Matarengihem sed 58, sekr\nTornedalskommun:s förb sed 58. - Medl\nLions club. - Utm: HvGM, SvrifbGM,\nNorrb idr:fbGM, Norrb skidfbGM.\n-Hobby: sport.\n\nGift 40 m Eva Johansson f 08, dtr t fabr\nEdvin J o Elin Vennman. - Barn:\nPer-Olof, Gunder, Kjell-Änders, Lasse.\n\n",
    "structured": {
        "1": {
            "full_name": "Olof E J Hessner",
            "location": "Hudiksvall",
            "occupation": "jägmästare",
            "birth_details": {
                "date": "18/03/1911",
                "place": "Skogaholm, Örebro l",
                "parents": "bergssing Justinus H o Helena Norström"
            },
            "education": [
                {
                    "degree": "Res:off:ex",
                    "year": "1934",
                    "institution": "NULL"
                },
                {
                    "degree": "civ:jägm:ex",
                    "year": "1938",
                    "institution": "SkHS"
                }
            ],
            "career": [
                {
                    "position": "jägm",
                    "years": {
                        "start_year": 1938,
                        "end_year": 1938
                    },
                    "organization": "Munksunds ab Luleå"
                },
                {
                    "position": "jägm",
                    "years": {
                        "start_year": 1947,
                        "end_year": 1947
                    },
                    "organization": "skogsförv Jokkmokk"
                },
                {
                    "position": "förvaltn",
                    "years": {
                        "start_year": 1956,
                        "end_year": 1956
                    },
                    "organization": "Strömbacka förvaltn Iggesunds bruks ab"
                },
                {
                    "position": "skyddsch ab",
                    "years": {
                        "start_year": 1964,
                        "end_year": 1964
                    },
                    "organization": "Iggesunds bruks ind:er o skogar"
                }
            ],
            "family": {
                "spouse": "textilkonstn Else Asker",
                "marriage_year": "1943",
                "children": [
                    {
                        "name": "Lisen",
                        "birth_year": "1945"
                    },
                    {
                        "name": "Lärs-Olof",
                        "birth_year": "1955"
                    }
                ]
            }
        },
        "2": {
            "full_name": "Gunnar Hettinger",
            "location": "Umeå",
            "occupation": "fil dr, laborator",
            "birth_details": {
                "date": "08/10/1930",
                "place": "Malmö",
                "parents": "kont:ch Max H o Anna Seemüller"
            },
            "education": [
                {
                    "degree": "Fil kand",
                    "year": "1955",
                    "institution": "Lund"
                },
                {
                    "degree": "fil lic",
                    "year": "1959",
                    "institution": "Lund"
                },
                {
                    "degree": "fil dr",
                    "year": "1960",
                    "institution": "där 60"
                }
            ],
            "career": [
                {
                    "position": "aman o ass fys o radiofys inst Lunds univ",
                    "years": {
                        "start_year": 1955,
                        "end_year": 1959
                    },
                    "organization": "Lunds univ"
                },
                {
                    "position": "doc i radiofysik",
                    "years": {
                        "start_year": 1960,
                        "end_year": 1961
                    },
                    "organization": "Lunds univ"
                },
                {
                    "position": "förest radiofys lab Umeå las",
                    "years": {
                        "start_year": 1962,
                        "end_year": 1962
                    },
                    "organization": "Umeå las"
                },
                {
                    "position": "verkst task leader Internat Commission ön Radiation Units and Measurements (ICRU)",
                    "years": {
                        "start_year": 1961,
                        "end_year": 1962
                    },
                    "organization": "ICRU"
                },
                {
                    "position": "konsult där",
                    "years": {
                        "start_year": 1965,
                        "end_year": 1965
                    },
                    "organization": "NULL"
                }
            ],
            "family": {
                "spouse": "Ingrid Araskog",
                "marriage_year": "1955",
                "children": [
                    {
                        "name": "Anders",
                        "birth_year": "1956"
                    },
                    {
                        "name": "Håkan",
                        "birth_year": "1959"
                    },
                    {
                        "name": "Karin",
                        "birth_year": "1962"
                    }
                ]
            }
        },
        "3": {
            "full_name": "Ture Heyman",
            "location": "Härnösand",
            "occupation": "rektor",
            "birth_details": {
                "date": "26/12/1917",
                "place": "Sthlm",
                "parents": "dir Bengt H o Siri Dahl"
            },
            "education": [
                {
                    "degree": "Stud",
                    "year": "1938",
                    "institution": "NULL"
                },
                {
                    "degree": "KTH",
                    "year": "1949",
                    "institution": "NULL"
                }
            ],
            "career": [
                {
                    "position": "ing ab Atlas Diesel",
                    "years": {
                        "start_year": 1945,
                        "end_year": 1945
                    },
                    "organization": "NULL"
                },
                {
                    "position": "lär Karlskoga stads maskintekn fack-sk",
                    "years": {
                        "start_year": 1949,
                        "end_year": 1949
                    },
                    "organization": "NULL"
                },
                {
                    "position": "adj Sjöbef :sk Härnösand",
                    "years": {
                        "start_year": 1954,
                        "end_year": 1954
                    },
                    "organization": "NULL"
                },
                {
                    "position": "rekt där",
                    "years": {
                        "start_year": 1958,
                        "end_year": 1958
                    },
                    "organization": "NULL"
                }
            ],
            "family": {
                "spouse": "Tora Heijl",
                "marriage_year": "1944",
                "children": [
                    {
                        "name": "Bengt",
                        "birth_year": "1945"
                    },
                    {
                        "name": "Barbro",
                        "birth_year": "1947"
                    },
                    {
                        "name": "Ulf",
                        "birth_year": "1949"
                    },
                    {
                        "name": "Lena",
                        "birth_year": "1953"
                    }
                ]
            }
        },
        "4": {
            "full_name": "Hugo E Hietala",
            "location": "övertorneå",
            "occupation": "rektor",
            "birth_details": {
                "date": "16/10/1911",
                "place": "övertorneå, Norrb l",
                "parents": "stat :karl Frans H o Hanna Moskajärvi"
            },
            "education": [
                {
                    "degree": "Folkskollär:ex",
                    "year": "1938",
                    "institution": "Luleå"
                },
                {
                    "degree": "statskunsk Upps univ",
                    "year": "1965",
                    "institution": "Upps univ"
                }
            ],
            "career": [
                {
                    "position": "folkskollär",
                    "years": {
                        "start_year": 1938,
                        "end_year": 1958
                    },
                    "organization": "övertorneå"
                },
                {
                    "position": "rekt",
                    "years": {
                        "start_year": 1958,
                        "end_year": 1958
                    },
                    "organization": "obl skolväs"
                },
                {
                    "position": "övertorneå kns yrkessk",
                    "years": {
                        "start_year": 1960,
                        "end_year": 1960
                    },
                    "organization": "NULL"
                }
            ],
            "family": {
                "spouse": "Eva Johansson",
                "marriage_year": "1940",
                "children": [
                    {
                        "name": "Per-Olof",
                        "birth_year": "NULL"
                    },
                    {
                        "name": "Gunder",
                        "birth_year": "NULL"
                    },
                    {
                        "name": "Kjell-Änders",
                        "birth_year": "NULL"
                    },
                    {
                        "name": "Lasse",
                        "birth_year": "NULL"
                    }
                ]
            },
            "hobbies": [
                "sport"
            ]
        }
    }
}