{
    "original": "HJORTH, T A HERMAN, bitr\növerläkare, Luleå, f i Solna 5/4/28 av ing\nHarald H o Karin Sehman.\nStud:ex 46, med kand 49 o med lic\nSthlm 55, öl läk:förordn 53-56, tf\nunderläk röntgenavd Västerås las 56-57, allm\navd Radiumhemmet 57-59, röntgenavd\nKarol sjh 59-63, bitr överläk röntgenavd\nLuleå las sed 63.\n\nGift 56 m Sif Jacobsson f 22, dtr t\nArvid J o Sonja Krantz. - Barn: Margareta\nf 57, Torgny f 59.\n\nHJUKSTRÖM, EDOR A, major, Umeå,\nf i Sorsele, Västerb l, 8/5/16.\nStud:ex AUS 39, Off:ex KS 42, major\nI 20 62, utb:off där sed 65. - Ordf\nSkid-o friluftsfrämj Umeå sed 65. - Utm:\nRSO.\n\nHJUKSTRÖM, G J PATRIK, major,\n\nÖstersund, f i Arvidsjaur, Norrb l, 20/4/\n13 av krono j ag Gustav H o Ida\nAbrahamsson.\n\nStud:ex AUS Upps 37, off:ex 39, KHS\n46-48; kapt I 3 47, major I 5 sed 60.\n-Teamch neutr övervakn:kommiss Korea\n54. - Delt i mil :patrull v VM på skidor\nCortina d’Ampezzo 41. - Utm: RSO.\nArméns skytteGM, ST:s\nriksskyttetävl-Gplak (lagseger). - Hobbies: jakt, fiske,\nschack.\n\nGift 56 m Hedvig Laven, dtr t köpm\nKarl L o Cecilia Holmén. - Barn:\nAnders f 56, Gustav f 58.\n\nHJÄLSTEN, J ANDERS, överingenjör,\n\nSandviken, f i Mpholm, Skarab l, 12/1/\n21 av snick David Johansson o Märta\nAndréasson.\n\nCTH 47, anst Saab Trollhättan 48, ab\nBofors 49-54, övering o konstr:ch f\nbergborrar Sandvikens jernv ab sed 55.\nGift m Barbro Feuk, dtr t tullmäst\nAnders F o Edith Rönqvist. - Barn:\nKristina f 48, Bengt f 51, Helena f 56.\n\n",
    "structured": {
        "0": {
            "full_name": "Herman Hjorth",
            "location": "Luleå",
            "occupation": "Bitr överläkare",
            "birth_details": {
                "date": "05/04/1928",
                "place": "Solna",
                "parents": "Harald Hjorth och Karin Sehman"
            },
            "education": [
                {
                    "degree": "Stud:ex",
                    "year": "1946",
                    "institution": "NULL"
                },
                {
                    "degree": "Med kand",
                    "year": "1949",
                    "institution": "NULL"
                },
                {
                    "degree": "Med lic",
                    "year": "1955",
                    "institution": "Sthlm"
                }
            ],
            "career": [
                {
                    "position": "Öl läk:förordn",
                    "years": {
                        "start_year": 1953,
                        "end_year": 1956
                    },
                    "organization": "NULL"
                },
                {
                    "position": "Tf underläk röntgenavd",
                    "years": {
                        "start_year": 1956,
                        "end_year": 1957
                    },
                    "organization": "Västerås las"
                },
                {
                    "position": "Allm avd Radiumhemmet",
                    "years": {
                        "start_year": 1957,
                        "end_year": 1959
                    },
                    "organization": "NULL"
                },
                {
                    "position": "Röntgenavd Karol sjh",
                    "years": {
                        "start_year": 1959,
                        "end_year": 1963
                    },
                    "organization": "NULL"
                },
                {
                    "position": "Bitr överläk röntgenavd",
                    "years": {
                        "start_year": 1963,
                        "end_year": "NULL"
                    },
                    "organization": "Luleå las"
                }
            ],
            "family": {
                "spouse": "Sif Jacobsson",
                "marriage_year": "1956",
                "children": [
                    {
                        "name": "Margareta",
                        "birth_year": "1957"
                    },
                    {
                        "name": "Torgny",
                        "birth_year": "1959"
                    }
                ]
            }
        },
        "1": {
            "full_name": "Edor A Hjukström",
            "location": "Umeå",
            "occupation": "Major",
            "birth_details": {
                "date": "08/05/1916",
                "place": "Sorsele, Västerb l",
                "parents": "NULL"
            },
            "education": [
                {
                    "degree": "Stud:ex AUS",
                    "year": "1939",
                    "institution": "NULL"
                },
                {
                    "degree": "Off:ex KS",
                    "year": "1942",
                    "institution": "NULL"
                }
            ],
            "career": [
                {
                    "position": "Major I 20",
                    "years": {
                        "start_year": 1962,
                        "end_year": "NULL"
                    },
                    "organization": "NULL"
                }
            ],
            "family": {
                "spouse": "NULL",
                "marriage_year": "NULL",
                "children": []
            }
        },
        "2": {
            "full_name": "G J Patrik Hjukström",
            "location": "Östersund",
            "occupation": "Major",
            "birth_details": {
                "date": "20/04/1913",
                "place": "Arvidsjaur, Norrb l",
                "parents": "Krono j ag Gustav Hjukström och Ida Abrahamsson"
            },
            "education": [
                {
                    "degree": "Stud:ex AUS Upps",
                    "year": "1937",
                    "institution": "NULL"
                },
                {
                    "degree": "Off:ex",
                    "year": "1939",
                    "institution": "NULL"
                },
                {
                    "degree": "KHS",
                    "year": "1946-1948",
                    "institution": "NULL"
                }
            ],
            "career": [
                {
                    "position": "Kapt I 3",
                    "years": {
                        "start_year": 1947,
                        "end_year": "NULL"
                    },
                    "organization": "NULL"
                },
                {
                    "position": "Major I 5",
                    "years": {
                        "start_year": 1960,
                        "end_year": "NULL"
                    },
                    "organization": "NULL"
                }
            ],
            "family": {
                "spouse": "Hedvig Laven",
                "marriage_year": "1956",
                "children": [
                    {
                        "name": "Anders",
                        "birth_year": "1956"
                    },
                    {
                        "name": "Gustav",
                        "birth_year": "1958"
                    }
                ]
            },
            "hobbies": [
                "Jakt",
                "Fiske",
                "Schack"
            ]
        },
        "3": {
            "full_name": "Anders Hjälsten",
            "location": "Sandviken",
            "occupation": "Överingenjör",
            "birth_details": {
                "date": "12/01/1921",
                "place": "Mpholm, Skarab l",
                "parents": "Snick David Johansson och Märta Andréasson"
            },
            "education": [
                {
                    "degree": "CTH",
                    "year": "1947",
                    "institution": "NULL"
                }
            ],
            "career": [
                {
                    "position": "Anst Saab Trollhättan",
                    "years": {
                        "start_year": 1948,
                        "end_year": 1954
                    },
                    "organization": "NULL"
                },
                {
                    "position": "Övering o konstr:ch f bergborrar",
                    "years": {
                        "start_year": 1955,
                        "end_year": "NULL"
                    },
                    "organization": "Sandvikens jernv ab"
                }
            ],
            "family": {
                "spouse": "Barbro Feuk",
                "marriage_year": "NULL",
                "children": [
                    {
                        "name": "Kristina",
                        "birth_year": "1948"
                    },
                    {
                        "name": "Bengt",
                        "birth_year": "1951"
                    },
                    {
                        "name": "Helena",
                        "birth_year": "1956"
                    }
                ]
            }
        }
    }
}