{
    "original": "HEDMAN, PER, civil jägmästare,\nKramfors, f i Söderhamn 19/1/22 av\nfolkskollär A H o Rut Wahlström.\nCiv:jägm:ex SkHS 48, jägm\nMarma-Långrörs ab 48, SCA sed 53. - Styr:led\nVnorrl skytteförb sed 56, led Sv:es\nskyt-teförb överstyr sed 59. - Medl FrimO.\n-Utm: Gävleb sfbSM, Vnorrl sfbGM,\nSv-sfbftjplakS. - Hobby: Skytte.\nGift 48 m Hermine Jansson f 22, dtr t\nJ E J o Viktoria Ljung. - Barn: Per Erik\nf 49.\n\nHEEDMAN, PER-AXEL S, överläkare,\nÖstersund, f i Kalix 9/10/28 av\nfolkskollär Sanfrid H o folkskollär Adéle\nHeed-man.\n\nStud:ex Luleå 48, med kand 51 o med\nlic Sthlm 58; aman o ass Karol inst kem\ninst 53-58, öl läk:förordn 54-58,\nunderläk med klin Karol sjh 58, klin kem lab\n\nS:t Görans sjh 58-64, överläk klin kem\nlab Östersund sed 64. - Skr i klinisk o\nfysikalisk kemi samt mikrobiologi.\nGift 53 m adj, fil mag Marie-Louise\nLind f 29, dtr t adv Anders L o Ellen\nNeergaard. - Barn: Maria f 55, Birgitta\nf 58, Cecilia f 63.\n\nHEDMAN,   SVEN   H,   överingenjör,\n\nObbola, f i Gävle 8/4/26 av byggn:ing\nHelmer H o Gertrud H.\nStud:ex Gävle 45, KTH 51, anst\nSör-åkers sulfitfabr SCA 51, driftsing\nMackmyra sulfit ab 54, ab Iggesunds bruk 59,\növering tekn avd SCA:s huvudkont\nSundsvall 61, Obbola sulfatfabr SCA sed\n65.\n\nGift 52 m Margareta Sjöholm f 30, dtr t\nkamr Erik S o Greta Svensson. - Barn:\nLars f 55, Britta f 57, Jan f 65.\n\nHEDQUIST, G EINAR, förste rektor,\n\nNordmaling, f i Norrfjärden, Norrb l,\n\n18/4/31 av kontr:prost Johan H o Greta\n\nSjöblom.\n\nStud:ex Skellefteå 49, fil mag Upps 57,\n\nadj grundsk högstad Sthlm 60, vik lekt\n\nBandhagens komm gymn 63, tf rekt sam-\n\nrealsk Nordmaling sed 64, l :e rekt Nord-\n\nmalings kn sed 64. -  Medl Rotary.  -\n\nHobby: skidsport.\n\nGift 64 m Margareta Carlson f 29, dtr t\n\ning Alvar C o Greta Almstrand.\n\n",
    "structured": {
        "1": {
            "full_name": "HEDMAN, PER",
            "location": "Kramfors",
            "occupation": "civil jägmästare",
            "birth_details": {
                "date": "19/01/1922",
                "place": "Söderhamn",
                "parents": "A H o Rut Wahlström"
            },
            "education": [
                {
                    "degree": "civ:jägm:ex",
                    "year": "1948",
                    "institution": "SkHS"
                }
            ],
            "career": [
                {
                    "position": "jägm",
                    "years": {
                        "start_year": 1948,
                        "end_year": 1953
                    },
                    "organization": "Marma-Långrörs ab"
                },
                {
                    "position": "jägm",
                    "years": {
                        "start_year": 1953,
                        "end_year": null
                    },
                    "organization": "SCA"
                }
            ],
            "family": {
                "spouse": "Hermine Jansson",
                "marriage_year": "1948",
                "children": [
                    {
                        "name": "Per Erik",
                        "birth_year": "1949"
                    }
                ]
            },
            "hobbies": [
                "Skytte"
            ]
        },
        "2": {
            "full_name": "HEEDMAN, PER-AXEL S",
            "location": "Östersund",
            "occupation": "överläkare",
            "birth_details": {
                "date": "09/10/1928",
                "place": "Kalix",
                "parents": "Sanfrid H o Adéle Heedman"
            },
            "education": [
                {
                    "degree": "Stud:ex",
                    "year": "1948",
                    "institution": "Luleå"
                },
                {
                    "degree": "med kand",
                    "year": "1951",
                    "institution": null
                },
                {
                    "degree": "med lic",
                    "year": "1958",
                    "institution": "Sthlm"
                }
            ],
            "career": [
                {
                    "position": "överläk",
                    "years": {
                        "start_year": 1964,
                        "end_year": null
                    },
                    "organization": "klin kem lab Östersund"
                }
            ],
            "family": {
                "spouse": "Marie-Louise Lind",
                "marriage_year": "1953",
                "children": [
                    {
                        "name": "Maria",
                        "birth_year": "1955"
                    },
                    {
                        "name": "Birgitta",
                        "birth_year": "1958"
                    },
                    {
                        "name": "Cecilia",
                        "birth_year": "1963"
                    }
                ]
            }
        },
        "3": {
            "full_name": "HEDMAN, SVEN H",
            "location": "Obbola",
            "occupation": "överingenjör",
            "birth_details": {
                "date": "08/04/1926",
                "place": "Gävle",
                "parents": "Helmer H o Gertrud H"
            },
            "education": [
                {
                    "degree": "Stud:ex",
                    "year": "1945",
                    "institution": "Gävle"
                },
                {
                    "degree": null,
                    "year": "1951",
                    "institution": "KTH"
                }
            ],
            "career": [
                {
                    "position": null,
                    "years": {
                        "start_year": 1951,
                        "end_year": 1954
                    },
                    "organization": "Söråkers sulfitfabr SCA"
                },
                {
                    "position": "driftsing",
                    "years": {
                        "start_year": 1954,
                        "end_year": 1959
                    },
                    "organization": "Mackmyra sulfit ab"
                },
                {
                    "position": null,
                    "years": {
                        "start_year": 1959,
                        "end_year": 1961
                    },
                    "organization": "ab Iggesunds bruk"
                },
                {
                    "position": "övering tekn avd",
                    "years": {
                        "start_year": 1961,
                        "end_year": null
                    },
                    "organization": "SCA:s huvudkont Sundsvall"
                },
                {
                    "position": null,
                    "years": {
                        "start_year": 1965,
                        "end_year": null
                    },
                    "organization": "Obbola sulfatfabr SCA"
                }
            ],
            "family": {
                "spouse": "Margareta Sjöholm",
                "marriage_year": "1952",
                "children": [
                    {
                        "name": "Lars",
                        "birth_year": "1955"
                    },
                    {
                        "name": "Britta",
                        "birth_year": "1957"
                    },
                    {
                        "name": "Jan",
                        "birth_year": "1965"
                    }
                ]
            }
        },
        "4": {
            "full_name": "HEDQUIST, G EINAR",
            "location": "Nordmaling",
            "occupation": "förste rektor",
            "birth_details": {
                "date": "18/04/1931",
                "place": "Norrfjärden, Norrb l",
                "parents": "Johan H o Greta Sjöblom"
            },
            "education": [
                {
                    "degree": "Stud:ex",
                    "year": "1949",
                    "institution": "Skellefteå"
                },
                {
                    "degree": "fil mag",
                    "year": "1957",
                    "institution": "Upps"
                }
            ],
            "career": [
                {
                    "position": "vik lekt",
                    "years": {
                        "start_year": 1963,
                        "end_year": null
                    },
                    "organization": "Bandhagens komm gymn"
                },
                {
                    "position": "tf rekt",
                    "years": {
                        "start_year": 1964,
                        "end_year": null
                    },
                    "organization": "Nordmalings kn"
                }
            ],
            "family": {
                "spouse": "Margareta Carlson",
                "marriage_year": "1964",
                "children": null
            },
            "hobbies": [
                "skidsport"
            ]
        }
    }
}