{
    "original": "HEDENFALK, OLLE S,\nbyggnadsingenjör SBR, Östersund, f i Växjö 23/51\n18 av byggm Johan Jansson o Anny\nKarlsson.\n\nIng :ex tekn lärov Malmö 42, ing Sv\nriks-byggen Sthlm 43, G Birch-Lindgrens\narkit :kont 45, Jämtl l landst Östersund\n56, eg konsult verksamh 57-64, verkst\ndir Byggkonsult O Hedenfalk ab sed 64.\n\n-   Medl  Jämtl  gille.  -  Hobbies:  fiske,\ncurling.\n\nGift 43 m Inga Tidström f 16, dtr t\nköpm Ivar T o Elin T. - Barn: Eva f 44,\nKarin f 47, Per f 49.\n\nHEDENIUS, OLOF J A,\ndistriktsåklagare, Kvissleby, f i Sthlm 23/12/06 av\nkamr Emil H o Maria Jacobsson.\nStud:ex 26 o kansliex Sthlm 28,\nres:off:ex KA 30, anst landsstaten 30,\nlandsfiskal Njurunda distr 52-64, distr:åkl\nSundsvall sed 65.\n\nHEDENMARK, HANS R H, advokat,\n\nÖstersund, f i Östersund 8/4/17 av\nhä-radsskriv Per H o Gerda Nordeman.\nStud:ex 39, jur kand Upps 46, tingstjg\nVästerb s doms o Nora doms 46-47,\ninneh adv :byrå Östersund sed 55. - LSA\n51. - Led Stadsfullm sed 60, landst :man\nsed 67. - Hobbies: sport, friluftsliv.\nGift 47 m sjuksköt Kerstin Jehander\nf 24, dtr t ing Slven J o Astrid Ekerot.\n-Barn: Per f 48, Cecilia f 49, Magnus\nf 57.\n\nHEDENSJÖ,    ALVAR    F,    direktör,\n\nSkelleftehamn, f i Skellefteå 18/1/04 av\nfabr O M Andersson o Anna Löfling.\n\nStud:ex Luleå 24, KSS 26, sjökapt:ex\n28, styrm Rederi ab Transatlantic 29,\nRederi ab E Brolin 30, hamnkapt\nSkellefteå 33, stuverich o verkst dir N\nVästerb stuveri ab sed 56 (styr:suppl).\n- Besiktn :man o sjösakk rådhusr sed 33,\nv ordf Skellefteå stads hamnstyr 56-66.\n-Hed:ordf SXK:s Skelleftekrets sed 45.\n-Utg: Skellefteå hamns historia (45).\n-Utm: SXKftjtS. - Hobby: sjösport.\nGift 34 m Alice Olsson f 04, dtr t\nbank-dir Emil O o Nelly Wennberg. - Barn:\nGudrun f 37, Roland f 42.\n\nHEDHMAN se HEDMAN\n\n",
    "structured": {
        "1": {
            "full_name": "HEDENFALK, OLLE S",
            "location": "Östersund",
            "occupation": "byggnadsingenjör SBR",
            "birth_details": {
                "date": "23/05/1918",
                "place": "Växjö",
                "parents": "Johan Jansson o Anny Karlsson"
            },
            "education": [
                {
                    "degree": "ingenjör",
                    "year": "1942",
                    "institution": "tekniska läroverket i Malmö"
                }
            ],
            "career": [
                {
                    "position": "ing Sv riks-byggen",
                    "years": {
                        "start_year": 1943,
                        "end_year": 1943
                    },
                    "organization": "Sthlm"
                },
                {
                    "position": "konsult",
                    "years": {
                        "start_year": 1957,
                        "end_year": 1964
                    },
                    "organization": "egen verksamhet"
                },
                {
                    "position": "verkst dir",
                    "years": {
                        "start_year": 1964,
                        "end_year": null
                    },
                    "organization": "Byggkonsult O Hedenfalk ab"
                }
            ],
            "family": {
                "spouse": "Inga Tidström",
                "marriage_year": "1943",
                "children": [
                    {
                        "name": "Eva",
                        "birth_year": "1944"
                    },
                    {
                        "name": "Karin",
                        "birth_year": "1947"
                    },
                    {
                        "name": "Per",
                        "birth_year": "1949"
                    }
                ]
            },
            "hobbies": [
                "fiske",
                "curling"
            ]
        },
        "2": {
            "full_name": "HEDENIUS, OLOF J A",
            "location": "Kvissleby",
            "occupation": "distriktsåklagare",
            "birth_details": {
                "date": "23/12/1906",
                "place": "Sthlm",
                "parents": "Emil H o Maria Jacobsson"
            },
            "education": [
                {
                    "degree": "stud:ex",
                    "year": "1926",
                    "institution": "Sthlm"
                },
                {
                    "degree": "kansliex",
                    "year": "1928",
                    "institution": "Sthlm"
                }
            ],
            "career": [
                {
                    "position": "anst landsstaten",
                    "years": {
                        "start_year": 1930,
                        "end_year": null
                    },
                    "organization": "landsstaten"
                },
                {
                    "position": "landsfiskal",
                    "years": {
                        "start_year": 1952,
                        "end_year": 1964
                    },
                    "organization": "Njurunda distr"
                },
                {
                    "position": "distr:åkl",
                    "years": {
                        "start_year": 1965,
                        "end_year": null
                    },
                    "organization": "Sundsvall"
                }
            ],
            "family": {
                "spouse": null,
                "marriage_year": null,
                "children": []
            }
        },
        "3": {
            "full_name": "HEDENMARK, HANS R H",
            "location": "Östersund",
            "occupation": "advokat",
            "birth_details": {
                "date": "08/04/1917",
                "place": "Östersund",
                "parents": "Per H o Gerda Nordeman"
            },
            "education": [
                {
                    "degree": "stud:ex",
                    "year": "1939",
                    "institution": "Östersund"
                },
                {
                    "degree": "jur kand",
                    "year": "1946",
                    "institution": "Upps"
                }
            ],
            "career": [
                {
                    "position": "tin o norr doms",
                    "years": {
                        "start_year": 1946,
                        "end_year": 1947
                    },
                    "organization": "Västerb s doms o Nora doms"
                },
                {
                    "position": "inneh adv :byrå",
                    "years": {
                        "start_year": 1955,
                        "end_year": null
                    },
                    "organization": "Östersund"
                }
            ],
            "family": {
                "spouse": "Kerstin Jehander",
                "marriage_year": "1947",
                "children": [
                    {
                        "name": "Per",
                        "birth_year": "1948"
                    },
                    {
                        "name": "Cecilia",
                        "birth_year": "1949"
                    },
                    {
                        "name": "Magnus",
                        "birth_year": "1957"
                    }
                ]
            },
            "hobbies": [
                "sport",
                "friluftsliv"
            ]
        },
        "4": {
            "full_name": "HEDENSJÖ, ALVAR F",
            "location": "Skelleftehamn",
            "occupation": "direktör",
            "birth_details": {
                "date": "18/01/1904",
                "place": "Skellefteå",
                "parents": "O M Andersson o Anna Löfling"
            },
            "education": [
                {
                    "degree": "stud:ex",
                    "year": "1924",
                    "institution": "Luleå"
                },
                {
                    "degree": "sjökapt:ex",
                    "year": "1928",
                    "institution": "Luleå"
                }
            ],
            "career": [
                {
                    "position": "stuverich o verkst dir",
                    "years": {
                        "start_year": 1956,
                        "end_year": null
                    },
                    "organization": "N Västerb stuveri ab"
                }
            ],
            "family": {
                "spouse": "Alice Olsson",
                "marriage_year": "1934",
                "children": [
                    {
                        "name": "Gudrun",
                        "birth_year": "1937"
                    },
                    {
                        "name": "Roland",
                        "birth_year": "1942"
                    }
                ]
            },
            "publications": [
                {
                    "title": "Skellefteå hamns historia",
                    "year": "1945",
                    "type": null
                }
            ],
            "hobbies": [
                "sjösport"
            ]
        }
    }
}