{
    "original": "CARMELID, JAN ERIK S,\ncivilingenjör, Örebro, f i Ljungby 11/2/29 av\nlantbr Johan Karlsson o Sigrid\nMagnusson.\n\nStud:ex Halmstad 49, CTH 53, resestip\nTyskl o Frankr 54, anst Linkpgs stads\nbyggn :kont 55-57, arb :ch Sv väg ab\n58-59, Örebro stads byggn :kont sed 60.\n-Skr: upps i facktidskr. - Hobby:\nfriluftsliv.\n\nGift 55 m Ingrid Möller f 32, dtr t\növering Olof M o Emmy Muller. - Barn:\nLennart f 58.\n\nCARNMALM, BERNT S E, tekn lic,\nSödertälje, f i Västerås 10/6/24 av\nmaskinist Robert Carlsson o Signe\nGranström.\n\nCiviling:ex KTH 50, tekn lic 57, ass inst\nf org kemi KTH 49, lab:ledare forskn:-\n\nlab ab Astra, Södertälje sed 59. - Ordf\nSthlms akvarie- o terrariefören sed 61,\nv ordf Roslagens dykarklubb. - Skr:\nett 10-tal art i vetensk tidskr, brevkurs\ni org kemi f NKI-skolans ing :kurser.\n-Hobbies: sportdykning, akvaristik.\nGift 53 m Ingrid Viktorsson, dtr t dir\nJohan V o h h.\n\nCARPEL, CARL-GUSTAF, verkst\ndirektör, Pershagen, f i Södertälje 15/4/22\nav grossh Gustaf Andersson-Karpel o\nAstrid Wahlstedt.\n\nSTI 43, DHI 48, Management course\nKingston 59. - Forskn:ing ab Astra\nSödertälje 43-47, försäljn:ing ab Surna\nSthlm 49, försäljn :ch ab Pfizer 54-58,\nverkst dir Winthrop ab sed 60, skand:ch\nsed 61, ansv utg tidn Puls sed 61. - Utg:\nGolfhandboken (63). - Hobby: golf.\nGift 51 m Gunilla Hagman f 30, dtr t\nagr Birger Hagman o Britta Ellerdahl.\n- Barn: Peter f 52, Thomas f 55, Åke\nf 59, Louise f 60.\n\n",
    "structured": {
        "0": {
            "full_name": "Jan Erik S Carmelid",
            "location": "Örebro",
            "occupation": "Civilingenjör",
            "birth_details": {
                "date": "11/02/1929",
                "place": "Ljungby",
                "parents": "Johan Karlsson och Sigrid Magnusson"
            },
            "education": [
                {
                    "degree": "Stud:ex",
                    "year": "1949",
                    "institution": "Halmstad"
                },
                {
                    "degree": "CTH",
                    "year": "1953",
                    "institution": "Chalmers Tekniska Högskola"
                }
            ],
            "career": [
                {
                    "position": "Arb :ch",
                    "years": {
                        "start_year": 1958,
                        "end_year": 1959
                    },
                    "organization": "Sv väg ab"
                },
                {
                    "position": "Örebro stads byggn :kont",
                    "years": {
                        "start_year": 1960
                    }
                }
            ],
            "family": {
                "spouse": "Ingrid Möller",
                "marriage_year": "1955",
                "children": [
                    {
                        "name": "Lennart",
                        "birth_year": "1958"
                    }
                ]
            },
            "hobbies": [
                "Friluftsliv"
            ]
        },
        "1": {
            "full_name": "Bernt S E Carnmalm",
            "location": "Södertälje",
            "occupation": "Tekn lic",
            "birth_details": {
                "date": "10/06/1924",
                "place": "Västerås",
                "parents": "Robert Carlsson och Signe Granström"
            },
            "education": [
                {
                    "degree": "Civiling:ex",
                    "year": "1950",
                    "institution": "KTH"
                },
                {
                    "degree": "Tekn lic",
                    "year": "1957",
                    "institution": "KTH"
                }
            ],
            "career": [
                {
                    "position": "Lab:ledare forskn:lab ab Astra",
                    "years": {
                        "start_year": 1959
                    }
                }
            ],
            "family": {
                "spouse": "Ingrid Viktorsson",
                "marriage_year": "1953"
            },
            "publications": [],
            "community_involvement": [
                {
                    "role": "Ordf",
                    "organization": "Sthlms akvarie- o terrariefören",
                    "years": "1961"
                },
                {
                    "role": "V ordf",
                    "organization": "Roslagens dykarklubb"
                }
            ],
            "hobbies": [
                "Sportdykning",
                "Akvaristik"
            ]
        },
        "2": {
            "full_name": "Carl-Gustaf Carpel",
            "location": "Pershagen",
            "occupation": "Verkst direktör",
            "birth_details": {
                "date": "15/04/1922",
                "place": "Södertälje",
                "parents": "Gustaf Andersson-Karpel och Astrid Wahlstedt"
            },
            "education": [
                {
                    "degree": "STI",
                    "year": "1943",
                    "institution": "NULL"
                },
                {
                    "degree": "DHI",
                    "year": "1948",
                    "institution": "NULL"
                },
                {
                    "degree": "Management course",
                    "year": "1959",
                    "institution": "Kingston"
                }
            ],
            "career": [
                {
                    "position": "Forskn:ing ab Astra",
                    "years": {
                        "start_year": 1943,
                        "end_year": 1947
                    }
                },
                {
                    "position": "Försäljn:ing ab Surna",
                    "years": {
                        "start_year": 1949,
                        "end_year": 1959
                    }
                },
                {
                    "position": "Verkst dir Winthrop ab",
                    "years": {
                        "start_year": 1960
                    }
                },
                {
                    "position": "Skand:ch",
                    "years": {
                        "start_year": 1961
                    }
                }
            ],
            "family": {
                "spouse": "Gunilla Hagman",
                "marriage_year": "1951",
                "children": [
                    {
                        "name": "Peter",
                        "birth_year": "1952"
                    },
                    {
                        "name": "Thomas",
                        "birth_year": "1955"
                    },
                    {
                        "name": "Åke",
                        "birth_year": "1959"
                    },
                    {
                        "name": "Louise",
                        "birth_year": "1960"
                    }
                ]
            },
            "publications": [
                {
                    "title": "Golfhandboken",
                    "year": "1963",
                    "type": "NULL"
                }
            ],
            "hobbies": [
                "Golf"
            ]
        }
    }
}