{
    "original": "CEDERBERG, T CHRISTER,\ndistriktsläkare, Västerås, f i Hjo 31/8/25 av l:e\nprov:läk Thorsten C o Ellen Werner.\nStud:ex Skara 44, med kand Upps 47,\nmed lic 53, ol läk:förordn 46-52,\nunderläk barnavd Västerås las 53, 2:e\nunderläk med avd Ludvika las 56, Västerås\nlas 58, 2:e stadsläk Skara 59,\nstadsdistr:-läk Västerås sed 62.\n\nGift 54 m fil mag Lenah Brundin f 29,\ndtr t banktjm Hädar B o Karin\nLanden. - Barn: Björn f 55, Carl f 61.\n\nCEDERBLAD, SVEN A, fil dr, lektor,\n\nArvika, f i Vena, Kalmar l, 1/6/14 av\nlandsfiskal C A C o Gerda Roth.\nStud:ex Eksjö 32, fil mag Lund 39, fil\nlic 42, fil dr 46. - Komm lektor Arvika\n46-53, lektor hal Arvika sed 53. - Medl\nOdd Fellow.  - Skr: Studies  of bright\ndiffuse galactic nebulae (drsavh 46).\nGift 39 m Anna-Lisa Lindqvist f 12.\n-Barn: Carl-Göran f 42, Ingegerd f 46.\n\nCEDERBLOM, BO S, tandläkare,\nNorrtälje, f i Sthlm 3/7/34 av tandläk Sten\nC o Agneta Wennerstrand.\nStud:ex Sigtuna 54, THS 60, priv :prakt\nsed 61. - Sekr Roslagens tandl:fören sed\n60, Roslagens flygklubb sed 63, medl\nKAK, KSAK, STF. - Hobbies: foto,\nflygning.\n\nGift 61 m Rosalie Mattsson f 38, dtr t\nGösta M o Helga Hållen.\n\nCEDERBOM, A INGEMAR,\nläroverksadjunkt, Nyköping, f i Lidköping\n15/4/13 av lärov:adj Seth C o Eva\nLindblom.\n\nTeol kand Lund 42, adj hal Nyköping\nsed 59.\n\nGift 44 m Marianne Schlyter, dtr t\nkyrkoh Johan S o Maria Nilsson.\n-Barn: Sten f 46, Carl f 50.\n\n",
    "structured": {
        "1": {
            "full_name": "T Christer Cederberg",
            "location": "Västerås",
            "occupation": "Distriktsläkare",
            "birth_details": {
                "date": "31/08/1925",
                "place": "Hjo"
            },
            "education": [
                {
                    "degree": "Stud:ex",
                    "year": "1944",
                    "institution": "Skara"
                },
                {
                    "degree": "Med kand",
                    "year": "1947",
                    "institution": "Upps"
                },
                {
                    "degree": "Med lic",
                    "year": "1953",
                    "institution": "NULL"
                }
            ],
            "career": [
                {
                    "position": "Ol läk:förordn",
                    "years": {
                        "start_year": 1946,
                        "end_year": 1952
                    },
                    "organization": "NULL"
                },
                {
                    "position": "Underläk barnavd",
                    "years": {
                        "start_year": 1953,
                        "end_year": 1953
                    },
                    "organization": "Västerås las"
                },
                {
                    "position": "2:e underläk med avd",
                    "years": {
                        "start_year": 1956,
                        "end_year": 1958
                    },
                    "organization": "Ludvika las"
                },
                {
                    "position": "2:e stadsläk",
                    "years": {
                        "start_year": 1959,
                        "end_year": 1959
                    },
                    "organization": "Skara"
                },
                {
                    "position": "Stadsdistr:-läk",
                    "years": {
                        "start_year": 1962,
                        "end_year": 1962
                    },
                    "organization": "Västerås"
                }
            ],
            "family": {
                "spouse": "Lenah Brundin",
                "marriage_year": "1954",
                "children": [
                    {
                        "name": "Björn",
                        "birth_year": "1955"
                    },
                    {
                        "name": "Carl",
                        "birth_year": "1961"
                    }
                ]
            }
        },
        "2": {
            "full_name": "Sven A Cederblad",
            "location": "Arvika",
            "occupation": "Lektor",
            "birth_details": {
                "date": "01/06/1914",
                "place": "Vena, Kalmar l"
            },
            "education": [
                {
                    "degree": "Stud:ex",
                    "year": "1932",
                    "institution": "Eksjö"
                },
                {
                    "degree": "Fil mag",
                    "year": "1939",
                    "institution": "Lund"
                },
                {
                    "degree": "Fil lic",
                    "year": "1942",
                    "institution": "NULL"
                },
                {
                    "degree": "Fil dr",
                    "year": "1946",
                    "institution": "NULL"
                }
            ],
            "career": [
                {
                    "position": "Komm lektor",
                    "years": {
                        "start_year": 1946,
                        "end_year": 1953
                    },
                    "organization": "Arvika"
                },
                {
                    "position": "Lektor hal",
                    "years": {
                        "start_year": 1953,
                        "end_year": 1953
                    },
                    "organization": "Arvika"
                }
            ],
            "family": {
                "spouse": "Anna-Lisa Lindqvist",
                "marriage_year": "1939",
                "children": [
                    {
                        "name": "Carl-Göran",
                        "birth_year": "1942"
                    },
                    {
                        "name": "Ingegerd",
                        "birth_year": "1946"
                    }
                ]
            }
        },
        "3": {
            "full_name": "Bo S Cederblom",
            "location": "Norrtälje",
            "occupation": "Tandläkare",
            "birth_details": {
                "date": "03/07/1934",
                "place": "Sthlm"
            },
            "education": [
                {
                    "degree": "Stud:ex",
                    "year": "1954",
                    "institution": "Sigtuna"
                },
                {
                    "degree": "THS",
                    "year": "1960",
                    "institution": "NULL"
                }
            ],
            "career": [
                {
                    "position": "Priv :prakt",
                    "years": {
                        "start_year": 1961,
                        "end_year": 1961
                    },
                    "organization": "NULL"
                }
            ],
            "family": {
                "spouse": "Rosalie Mattsson",
                "marriage_year": "1961",
                "children": []
            },
            "hobbies": [
                "foto",
                "flygning"
            ]
        },
        "4": {
            "full_name": "A Ingemar Cederbom",
            "location": "Nyköping",
            "occupation": "Läroverksadjunkt",
            "birth_details": {
                "date": "15/04/1913",
                "place": "Lidköping"
            },
            "education": [
                {
                    "degree": "Teol kand",
                    "year": "1942",
                    "institution": "Lund"
                }
            ],
            "career": [
                {
                    "position": "Adj hal",
                    "years": {
                        "start_year": 1959,
                        "end_year": 1959
                    },
                    "organization": "Nyköping"
                }
            ],
            "family": {
                "spouse": "Marianne Schlyter",
                "marriage_year": "1944",
                "children": [
                    {
                        "name": "Sten",
                        "birth_year": "1946"
                    },
                    {
                        "name": "Carl",
                        "birth_year": "1950"
                    }
                ]
            }
        }
    }
}