{
    "original": "CRONER, ERIC R, konsulent,\nVästerås, f i Falun 19/12/11 av bryggeriförm\nRickard C o Brita Andersson.\nDiakonex 37, anst pens :ndn Västerås\n39-46, byräförest där 49, nykterh :v\n:konsulent Västmanl l sed 54, pens :styr omb\ndär 43-49, länsnykterh:ndns omb :man\n42-54, styr:led Nykterh :v :f örb Västmanl\nl sed 42. - Medl Odd Fellow.\nGift 41 m Majsti Heijkorn f 17, dtr t\nbergsing Gösta H o Astri Almström.\n-Barn: Urban f 43, Ingela f 48.\n\nCRONHOLM, LÄRS-ERIK G,\ntingsdomare, Eskilstuna, f i Sthlm 15/2/17 av\ndisp Erik C o Lydia Hansson-Levin.\nStud:ex 37, jur kand StHS 47, tingstjg\nNjudungs doms 47-50, asp Göta hovr 50,\nhovr :fiskal 51, assess där 59, tjg nedre\njust :rev 61-62, tingsdom Livgedingets\ndoms sed 63.\n\nGift 44 m Iris Lindeborg f 20, dtr t\ning Rubin L o Svea Sohlberg. - Barn:\nHelena f 53.\n\nCRONHOLM, SVEN A, bankdirektör,\nKatrineholm, f i Ängelholm 13/7/13 av\nAlgot C o Ebba-Linda Eriksson.\n\nStud:ex Halmstad 33, anst Skand bkn\nsed 38, kamr Norrkpg 53, bankdir\nKatrineholm sed 58. - Medl FrimO, Odd\nFellow, SHT, Rotary.\nGift 49 m Brita Nilsson f 24, dtr t\nkantor Nils N o Helga Svensson. - Barn:\nChrister f 50, Agneta f 54, Anders f 55,\nMattias f 62.\n\nCRONHOLM-TWETMAN,    GISELA,\n\ntandläkare, Västerås, f i Båstad, Kris-\n\ntianst l, 17/8/10 av l:e stat:skriv Hilmer\n\nCronholm  o Emy Johansson.\n\nStud:ex Hbg 30, odont kand 30, tandl:ex\n\n33, prakt Västerås sed 34, Skultuna 37-\n\n50. - Ordf FUB Västmanl l sed 59, medl\n\nZenta, lottakår. - Utm: Västmanl lotta-\n\nförbSM.\n\nGift 41 m maskining Bo Agardh-Twet-\n\nman f  12. - Barn: Anders f 44, Peter\n\nf 45, Wända f 47, Svante f  50.\n\n",
    "structured": {
        "1": {
            "full_name": "CRONER, ERIC R",
            "location": "Västerås",
            "occupation": "konsulent",
            "birth_details": {
                "date": "19/12/1911",
                "place": "Falun",
                "parents": "bryggeriförm Rickard C o Brita Andersson"
            },
            "education": [
                {
                    "degree": "Diakonex",
                    "year": "1937",
                    "institution": "anst pens :ndn Västerås"
                }
            ],
            "career": [
                {
                    "position": "byräförest",
                    "years": {
                        "start_year": 1949,
                        "end_year": 1949
                    },
                    "organization": "Västerås"
                },
                {
                    "position": "nykterh :v :konsulent",
                    "years": {
                        "start_year": 1954,
                        "end_year": 1954
                    },
                    "organization": "Västmanland"
                }
            ],
            "family": {
                "spouse": "Majsti Heijkorn",
                "marriage_year": "1941",
                "children": [
                    {
                        "name": "Urban",
                        "birth_year": "1943"
                    },
                    {
                        "name": "Ingela",
                        "birth_year": "1948"
                    }
                ]
            }
        },
        "2": {
            "full_name": "CRONHOLM, LÄRS-ERIK G",
            "location": "Eskilstuna",
            "occupation": "tingsdomare",
            "birth_details": {
                "date": "15/02/1917",
                "place": "Sthlm",
                "parents": "disp Erik C o Lydia Hansson-Levin"
            },
            "education": [
                {
                    "degree": "Stud:ex",
                    "year": "1937",
                    "institution": ""
                },
                {
                    "degree": "jur kand",
                    "year": "1947",
                    "institution": "StHS"
                }
            ],
            "career": [
                {
                    "position": "tingstjg",
                    "years": {
                        "start_year": 1947,
                        "end_year": 1950
                    },
                    "organization": "Njudungs doms"
                },
                {
                    "position": "asp",
                    "years": {
                        "start_year": 1950,
                        "end_year": 1951
                    },
                    "organization": "Göta hovr"
                },
                {
                    "position": "hovr :fiskal",
                    "years": {
                        "start_year": 1951,
                        "end_year": 1959
                    },
                    "organization": ""
                },
                {
                    "position": "assess",
                    "years": {
                        "start_year": 1959,
                        "end_year": 1961
                    },
                    "organization": ""
                }
            ],
            "family": {
                "spouse": "Iris Lindeborg",
                "marriage_year": "1944",
                "children": [
                    {
                        "name": "Helena",
                        "birth_year": "1953"
                    }
                ]
            }
        },
        "3": {
            "full_name": "CRONHOLM, SVEN A",
            "location": "Katrineholm",
            "occupation": "bankdirektör",
            "birth_details": {
                "date": "13/07/1913",
                "place": "Ängelholm",
                "parents": "Algot C o Ebba-Linda Eriksson"
            },
            "education": [
                {
                    "degree": "Stud:ex",
                    "year": "1933",
                    "institution": "Halmstad"
                }
            ],
            "career": [
                {
                    "position": "anst Skand bkn",
                    "years": {
                        "start_year": 1938,
                        "end_year": 1953
                    },
                    "organization": ""
                },
                {
                    "position": "kamr",
                    "years": {
                        "start_year": 1953,
                        "end_year": ""
                    },
                    "organization": "Norrkpg"
                },
                {
                    "position": "bankdir",
                    "years": {
                        "start_year": 1958,
                        "end_year": ""
                    },
                    "organization": "Katrineholm"
                }
            ],
            "family": {
                "spouse": "Brita Nilsson",
                "marriage_year": "1949",
                "children": [
                    {
                        "name": "Christer",
                        "birth_year": "1950"
                    },
                    {
                        "name": "Agneta",
                        "birth_year": "1954"
                    },
                    {
                        "name": "Anders",
                        "birth_year": "1955"
                    },
                    {
                        "name": "Mattias",
                        "birth_year": "1962"
                    }
                ]
            }
        },
        "4": {
            "full_name": "CRONHOLM-TWETMAN, GISELA",
            "location": "Västerås",
            "occupation": "tandläkare",
            "birth_details": {
                "date": "17/08/1910",
                "place": "Båstad, Kristianst l",
                "parents": "l:e stat:skriv Hilmer Cronholm o Emy Johansson"
            },
            "education": [
                {
                    "degree": "Stud:ex",
                    "year": "1930",
                    "institution": "Hbg"
                },
                {
                    "degree": "odont kand",
                    "year": "1930",
                    "institution": ""
                },
                {
                    "degree": "tandl:ex",
                    "year": "1933",
                    "institution": ""
                }
            ],
            "career": [
                {
                    "position": "prakt",
                    "years": {
                        "start_year": 1934,
                        "end_year": ""
                    },
                    "organization": "Västerås"
                },
                {
                    "position": "Skultuna",
                    "years": {
                        "start_year": 1937,
                        "end_year": 1950
                    },
                    "organization": ""
                }
            ],
            "family": {
                "spouse": "maskining Bo Agardh-Twetman",
                "marriage_year": "1941",
                "children": [
                    {
                        "name": "Anders",
                        "birth_year": "1944"
                    },
                    {
                        "name": "Peter",
                        "birth_year": "1945"
                    },
                    {
                        "name": "Wända",
                        "birth_year": "1947"
                    },
                    {
                        "name": "Svante",
                        "birth_year": "1950"
                    }
                ]
            }
        }
    }
}