{
    "original": "CLASON, L G WILHELM,\navdelningschef, Fagersta, f i Lund 7/4/05 av\nriksarkivarie Sam C o Elin Sebardt.\nStud:ex Sthlm 23, kansliex StHS 27,\nSchartaus hdlI 27, korresp Sandvikens\njernv 27, stud o prakt Frankr, Tyskl,\nUSA 28-31, korresp Fagersta bruk 31,\navd :ch där sed 45. - Medl Lions Club.\n- Hobbies: trädgårdsarbete,\nskogspromenader, skidåkning.\nGift 34 m Vanja Lundberg, dtr t\nbyggn:ing Ernst L o Astrid Svensson. - Barn:\nElin f 37, Anders f 39, Johan f 42.\n\nCLASON se CLAESSON\n\nCLAUSSEN,   ARNE   W,   överläkare,\n\nKatrineholm, f i Sthlm 25/8/03 av ing\nAgne C o Tora Sätter.\nStud:ex Kristianstad 22, med kand Sthlm\n25, med lic 31. - Aman ol inst 24-27, e\nläk Västerviks hosp 30, prakt läk\nVästervik 31, ass :läk o tf underläk\nrönt-genavd Sabbatsbergs sjh 33, ass :läk kir\navd 34, l:e underläk röntgenavd 35, tf\nläk röntgenavd Eksjö garn :sjh 39, l:e\nunderläk röntgenavd Västerås las 40,\nbitr överläk 43, l:e underläk\nRadiumhemmet 47, förest röntgenavd\nCarlan-derska sjukhemmet 49, överläk\nröntgenavd Kullbergska sjh Katrineholm 52.\n-Bat:läk flk 38-44, flk res 45-57. - Medl\nSv läk:sällsk, SLF. - Utg: ett 20-tal\nmindre skr i histol, radiodiagn o\nradioterapi. - Hobby: litteratur.\nGift 1) 31 m Maria Hagman f 06, dtr t\nköpm Vilhelm H o Augusta Lindström,\n2) 50 m Brita Molin f 21, dtr t\nciviling Anders M o Gunhild Ekesiöö.\n\nCLAVELL, S HARRY J, fd\nbankdirektör, Falun, f i Fölene, Älvsb l,\n24/6/98 av dir Herman Carlson o\nJosefina Larsson.\n\nStud:ex Vänersborg 17, anst Ensk bkn\nVänersborg 19, kamr Dalsl bk 29, Falu\nsparbk sed 35, verkst dir där 52-63.\n-Led Stadsfullm o DK Åmål 29-35, ab\nP J Svangren &amp; Co Gbg, kassaförv o\nled Dalarnas bf b sed 46, omb :man stift\nTallbacken Falun. - Kapt Iv res. - Utm:\nProPatrstGM, CFBGM, Dalarnas\nbfb-GM. - Hobbies: sport, trädgårdsskötsel,\nfriluftsliv, resor, litteratur.\nGift 25 m Margit Renström f Ol, dtr t\ntandläk Viktor R o Elvira Svangren.\n-Barn: Ulla o Birgit ff 27.\n\nCLÉMENTZ, K G ROBERT A,\nlands-fogde, Uppsala, f i Malmö 7/6/09 av\nkrim:kommiss Carl C o Hilma\nFagerberg.\n\nStud:ex Hbg 28, jur kand Lund 37, stat\npolissk 45, FHS 62, tingstjg Kinds o\nRedvägs doms 37-40, e stadsfiskal Sthlm\n42, särsk åklag i spionmål Sthlms\nråd-husr 44, krim:polisintend o bitr\nstads-fiskal Norrkpg 46, stadsfiskal Borås 50,\nlandsfogde Upps l sed 59. - Led 51 års\nrättegångskomm 51-61, styr :led Sv:es\njur:förb. - Medl Par Bricole. - Utm:\nRNO.\n\nGift 47 m Ulla Bergenstedt f 16, dtr t\ning Hjalmar Dahl o Gurli D. - Barn:\nMats f 50, Göran f 52.\n\nCLEVE von EULER, ASTRID M,\nprofessor, Uppsala, f i Upps 22/1/75\nav prof Per Cleve o Alma Öhbom.\nFil lic o fil dr Upps 98, ass StHS 98-02,\nbiol ass hydrogr-biolog kommiss 13-17,\nlär A Sandströms sem 11-17, Nya\nelem:-sk f fi 12, anst Uddeholms ab 17-23.\n-L Soc pro Fauna et Flora fennica 15.\n-Prof namn 55. - Skr: Stud över några\nsv växters groningstid o\nförstärkningsstadium (drsavh 98), Undersökn över\nlignin (20-23), Försök t analys av\nNordens senkvartära nivåförändr (23), Stud\növer Ancylustidens Mellansverige (30),\nKomsakulturens ålder (36), Natur und\nAlter der Strandflächen Finnlands (42),\nOm den sista landisens bortsmältn (46),\nDie Diatomeen von Schweden und\nFinnland (51-55), Was war der Svea älv?\n(57), Deglaciationen i Götaland o \"den\nbaltiska issjön\" (60), Istiden o\nmänniskor i norden (60), Sista biten i\npuzzlet (61), Detta är Eden. Två bilder (62)\nm m.\n\nGift 02-12 m prof em Hans von\nEuler-Chelpin f 73. - Barn: Sten f 03, Ulf f\n\n05, Karin f 07, Georg f 08, Birgit f 10.\n\n",
    "structured": {
        "1": {
            "full_name": "L G WILHELM CLASON",
            "location": "Fagersta",
            "occupation": "avdelningschef",
            "birth_details": {
                "date": "07/04/1905",
                "place": "Lund",
                "parents": "riksarkivarie Sam C o Elin Sebardt"
            },
            "education": [
                {
                    "degree": "Stud:ex",
                    "year": "1923",
                    "institution": "Sthlm"
                },
                {
                    "degree": "kansliex",
                    "year": "1927",
                    "institution": "StHS"
                },
                {
                    "degree": "Schartaus hdlI",
                    "year": "1927",
                    "institution": "Schartaus HdlI"
                }
            ],
            "career": [
                {
                    "position": "korresp",
                    "years": {
                        "start_year": 1927,
                        "end_year": 1931
                    },
                    "organization": "Sandvikens jernv"
                },
                {
                    "position": "korresp",
                    "years": {
                        "start_year": 1931,
                        "end_year": 1945
                    },
                    "organization": "Fagersta bruk"
                }
            ],
            "family": {
                "spouse": "Vanja Lundberg",
                "marriage_year": "1934",
                "children": [
                    {
                        "name": "Elin",
                        "birth_year": "1937"
                    },
                    {
                        "name": "Anders",
                        "birth_year": "1939"
                    },
                    {
                        "name": "Johan",
                        "birth_year": "1942"
                    }
                ]
            },
            "hobbies": [
                "trädgårdsarbete",
                "skogspromenader",
                "skidåkning"
            ]
        },
        "2": {
            "full_name": "ARNE W CLAUSSEN",
            "location": "Katrineholm",
            "occupation": "överläkare",
            "birth_details": {
                "date": "25/08/1903",
                "place": "Sthlm",
                "parents": "ing Agne C o Tora Sätter"
            },
            "education": [
                {
                    "degree": "Stud:ex",
                    "year": "1922",
                    "institution": "Kristianstad"
                },
                {
                    "degree": "med kand",
                    "year": "1925",
                    "institution": "Sthlm"
                },
                {
                    "degree": "med lic",
                    "year": "1931",
                    "institution": "NULL"
                }
            ],
            "career": [
                {
                    "position": "Aman ol inst",
                    "years": {
                        "start_year": 1924,
                        "end_year": 1927
                    },
                    "organization": "NULL"
                },
                {
                    "position": "e läk",
                    "years": {
                        "start_year": 1930,
                        "end_year": 1930
                    },
                    "organization": "Västerviks hosp"
                },
                {
                    "position": "ass :läk",
                    "years": {
                        "start_year": 1935,
                        "end_year": 1935
                    },
                    "organization": "Sabbatsbergs sjh"
                }
            ],
            "family": {
                "spouse": "Maria Hagman",
                "marriage_year": "1931",
                "children": [
                    {
                        "name": "NULL",
                        "birth_year": "NULL"
                    }
                ]
            },
            "hobbies": [
                "litteratur"
            ]
        },
        "3": {
            "full_name": "HARRY J CLAVELL",
            "location": "Falun",
            "occupation": "fd bankdirektör",
            "birth_details": {
                "date": "24/06/1898",
                "place": "Fölene, Älvsb l",
                "parents": "dir Herman Carlson o Josefina Larsson"
            },
            "hobbies": [
                "sport",
                "trädgårdsskötsel",
                "friluftsliv",
                "resor",
                "litteratur"
            ]
        },
        "4": {
            "full_name": "K G ROBERT A CLÉMENTZ",
            "location": "Uppsala",
            "occupation": "landsfogde",
            "birth_details": {
                "date": "07/06/1909",
                "place": "Malmö",
                "parents": "krim:kommiss Carl C o Hilma Fagerberg"
            },
            "education": [
                {
                    "degree": "Stud:ex",
                    "year": "1928",
                    "institution": "Hbg"
                },
                {
                    "degree": "jur kand",
                    "year": "1937",
                    "institution": "Lund"
                },
                {
                    "degree": "stat polissk",
                    "year": "1945",
                    "institution": "FHS"
                }
            ],
            "career": [
                {
                    "position": "tingstjg",
                    "years": {
                        "start_year": 1937,
                        "end_year": 1940
                    },
                    "organization": "Kinds o Redvägs doms"
                },
                {
                    "position": "e stadsfiskal",
                    "years": {
                        "start_year": 1942,
                        "end_year": 1946
                    },
                    "organization": "NULL"
                }
            ],
            "family": {
                "spouse": "Ulla Bergenstedt",
                "marriage_year": "1947",
                "children": [
                    {
                        "name": "Mats",
                        "birth_year": "1950"
                    },
                    {
                        "name": "Göran",
                        "birth_year": "1952"
                    }
                ]
            }
        },
        "5": {
            "full_name": "ASTRID M CLEVE von EULER",
            "location": "Uppsala",
            "occupation": "professor",
            "birth_details": {
                "date": "22/01/1875",
                "place": "Upps",
                "parents": "prof Per Cleve o Alma Öhbom"
            },
            "education": [
                {
                    "degree": "Fil lic",
                    "year": "1898",
                    "institution": "Upps"
                }
            ],
            "career": [],
            "family": {
                "spouse": "prof em Hans von Euler-Chelpin",
                "marriage_year": "1902",
                "children": [
                    {
                        "name": "Sten",
                        "birth_year": "1903"
                    },
                    {
                        "name": "Ulf",
                        "birth_year": "1905"
                    },
                    {
                        "name": "Karin",
                        "birth_year": "1907"
                    },
                    {
                        "name": "Georg",
                        "birth_year": "1908"
                    },
                    {
                        "name": "Birgit",
                        "birth_year": "1910"
                    }
                ]
            },
            "publications": [
                {
                    "title": "Komsakulturens ålder",
                    "year": "1936",
                    "type": "NULL"
                },
                {
                    "title": "Natur und Alter der Strandflächen Finnlands",
                    "year": "1942",
                    "type": "NULL"
                },
                {
                    "title": "Om den sista landisens bortsmältn",
                    "year": "1946",
                    "type": "NULL"
                }
            ]
        }
    }
}