{
    "original": "Ohm, Sven Thure Lennart, leg.\ntandläkare, Malmö, f. 17/7/20 i Malmö av\nbyråassist. Thure O. o. Ruth\nSörensson. G. 44 m. Marianne Göhrn.\nBarn: Vibeke f. 46. — Stud:ex. v.\nLunds priv. elem:sk. 40, odont. kand.\n4)5, tandläk :ex. 47. Aman. v.\ntand-läk :inst. i Sthlm avd. f. barntandv.\n46-47, v. tandläk :inst. i Malmö avd. f.\ncarieslära 48, assist, v. dess avd. f.\nbarntandv. fr. 48. Ordf. i Odontol.\nför en. i Sthlm 46-47.\n\nOhm, Oscar Ludvig Herman,\nkyrkoherde, Svenstorp, f. 22/10/92 i Malmö\nav fotograf Otto Louis Johannes\nHerman O. o. Anna Amelie Bengtsson.\nG. 28 m. Edith Carolina Nelander.\nBarn:  Bengt f. 29, Karin 31, Lars 34.\n\n—  Stud:ex. i Malmö 12, aman. v. zool.\ninst. i Lund 16-17 o. 19-21, fil. kand.\n21, teol. kand. 27, prakt, teol. prov\no. prästv. f. Lunds stift s. å. V.\npastor i Sturkö 27, kammin. i Flymen 30,\ntf. kyrkoh. i Bosarp o. V. Strö 39,\nkyrkoh. i Övraby, Benestad, Högestad o.\nBaldringe sed. 47. I Bosarp o. V.\nStrö ordf. o. kassör i barnav :nd, ordf.\ni kyrko- o. past:stämmor, i Övraby\nm. fl., ordf. i kyrjko- o. past :stämmor,\nkyrko- o. pastoratskassör. Skr.: art.\ni Fauna o. Flora, Verdandi o. Vår\nKrets.     Hobby:   biologi.\n\nÖländer, Carl Wilhelm, direktör,\nKristianstad,   f.  2/7/81   i   Kristianstad.\n\n—   Anst. v. Mårten Pehrsons\nVals-qvarn sed. 95, v. verkst. dir. där sed.\n25. Led. av stadsfullm. i flera per.\n12-41.   RVO 41.\n\nOlavi, Gustaf Edvard, lektor,\nKristianstad, f. 15/10/84 i Berg, Skarab. 1.\nG. 1. rS m. Hildur Olofsson, d. 21; 2.\n22 m. Eva Nordström. Barn: Sven f.\n19, civ:ing., Söderhamn, Göran 21, ing.,\nÖrebro, Bengt 23, jur. stud., Lund. —\nStud:ex. i Skara 06, fil. mag. i Lund\n11, fil. lic. 14’. Provar i Lund 13.\nVik. lektor i Hälsingb. 10, vik. lär. v.\nÖnnestads folkhö^gsk. 12, e. lär. i Lund\n14, e. o. lektor i Eslöv 14-17, adj. i\nLund 16, lektor v. Skara folksk :sem.\n19, lektor i modersm. v. h. a. 1. i\nKri-stianst. fr. 34. Bibi. där fr. 35. Kur.\nv. västg. nat. i Lund 10-14, i Kristianst.\nled. av kyrkofullm. o. fattigv :styr.\nIn-neh. ett ant. förtr :uppdr. äv. på andra\nplats. und. årens lopp. Skr.: div.\nfackupps.  o,   tidn:art.  RNO  38.\n\n",
    "structured": {
        "1": {
            "full_name": "Ohm, Sven Thure Lennart",
            "location": "Malmö",
            "occupation": "leg. tandläkare",
            "birth_details": {
                "date": "17/07/1920",
                "place": "Malmö",
                "parents": "Thure O. och Ruth Sörensson"
            },
            "education": [
                {
                    "degree": "Stud:ex.",
                    "year": "1940",
                    "institution": "Lunds priv. elem:sk."
                },
                {
                    "degree": "odont. kand.",
                    "year": "1945",
                    "institution": "odont. inst."
                },
                {
                    "degree": "tandläk :ex.",
                    "year": "1947",
                    "institution": "tandläk. inst."
                }
            ],
            "career": [
                {
                    "position": "Aman. v. tand-läk :inst. i Sthlm avd. f. barntandv.",
                    "years": {
                        "start_year": 1946,
                        "end_year": 1947
                    },
                    "organization": "tand-läk :inst. i Sthlm"
                },
                {
                    "position": "v. tandläk :inst. i Malmö avd. f. carieslära",
                    "years": {
                        "start_year": 1948,
                        "end_year": null
                    },
                    "organization": "tandläk :inst. i Malmö"
                }
            ],
            "family": {
                "spouse": "Marianne Göhrn",
                "marriage_year": "1944",
                "children": [
                    {
                        "name": "Vibeke",
                        "birth_year": "1946"
                    }
                ]
            }
        },
        "2": {
            "full_name": "Ohm, Oscar Ludvig Herman",
            "location": "Svenstorp",
            "occupation": "kyrkoherde",
            "birth_details": {
                "date": "22/10/1892",
                "place": "Malmö",
                "parents": "fotograf Otto Louis Johannes Herman O. och Anna Amelie Bengtsson"
            },
            "education": [
                {
                    "degree": "Stud:ex.",
                    "year": "1912",
                    "institution": "Malmö"
                },
                {
                    "degree": "aman. v. zool.",
                    "year": "1917",
                    "institution": "zool. inst. i Lund"
                },
                {
                    "degree": "fil. kand.",
                    "year": "1921",
                    "institution": "Lund"
                },
                {
                    "degree": "teol. kand.",
                    "year": "1927",
                    "institution": "Lunds stift"
                }
            ],
            "career": [
                {
                    "position": "V. pastor i Sturkö",
                    "years": {
                        "start_year": 1927,
                        "end_year": null
                    },
                    "organization": "Sturkö"
                },
                {
                    "position": "kammin. i Flymen",
                    "years": {
                        "start_year": 1930,
                        "end_year": null
                    },
                    "organization": "Flymen"
                },
                {
                    "position": "tf. kyrkoh. i Bosarp o. V. Strö",
                    "years": {
                        "start_year": 1939,
                        "end_year": null
                    },
                    "organization": "Bosarp o. V. Strö"
                },
                {
                    "position": "kyrkoh. i Övraby, Benestad, Högestad o. Baldringe",
                    "years": {
                        "start_year": 1947,
                        "end_year": null
                    },
                    "organization": "Övraby, Benestad, Högestad, Baldringe"
                }
            ],
            "family": {
                "spouse": "Edith Carolina Nelander",
                "marriage_year": "1928",
                "children": [
                    {
                        "name": "Bengt",
                        "birth_year": "1929"
                    },
                    {
                        "name": "Karin",
                        "birth_year": "1931"
                    },
                    {
                        "name": "Lars",
                        "birth_year": "1934"
                    }
                ]
            }
        },
        "3": {
            "full_name": "Öländer, Carl Wilhelm",
            "location": "Kristianstad",
            "occupation": "direktör",
            "birth_details": {
                "date": "02/07/1881",
                "place": "Kristianstad",
                "parents": null
            },
            "career": [
                {
                    "position": "Anst. v. Mårten Pehrsons Vals-qvarn",
                    "years": {
                        "start_year": 1895,
                        "end_year": null
                    },
                    "organization": "Mårten Pehrsons Vals-qvarn"
                },
                {
                    "position": "v. verkst. dir. där",
                    "years": {
                        "start_year": 1925,
                        "end_year": null
                    },
                    "organization": "Mårten Pehrsons Vals-qvarn"
                }
            ],
            "family": {
                "spouse": null,
                "marriage_year": null,
                "children": null
            }
        },
        "4": {
            "full_name": "Olavi, Gustaf Edvard",
            "location": "Kristianstad",
            "occupation": "lektor",
            "birth_details": {
                "date": "15/10/1884",
                "place": "Berg, Skarab. 1",
                "parents": null
            },
            "education": [
                {
                    "degree": "Stud:ex.",
                    "year": "1906",
                    "institution": "Skara"
                },
                {
                    "degree": "fil. mag.",
                    "year": "1911",
                    "institution": "Lund"
                },
                {
                    "degree": "fil. lic.",
                    "year": "1914",
                    "institution": "Lund"
                }
            ],
            "career": [
                {
                    "position": "Vik. lektor i Hälsingb.",
                    "years": {
                        "start_year": 1910,
                        "end_year": null
                    },
                    "organization": "Hälsingb."
                },
                {
                    "position": "lektor v. Skara folksk :sem.",
                    "years": {
                        "start_year": 1919,
                        "end_year": null
                    },
                    "organization": "Skara folksk :sem."
                },
                {
                    "position": "lektor i modersm. v. h. a. 1. i Kristianst.",
                    "years": {
                        "start_year": 1934,
                        "end_year": null
                    },
                    "organization": "Kristianst."
                }
            ],
            "family": {
                "spouse": "Hildur Olofsson",
                "marriage_year": "null",
                "children": [
                    {
                        "name": "Sven",
                        "birth_year": "1919"
                    },
                    {
                        "name": "Göran",
                        "birth_year": "1921"
                    },
                    {
                        "name": "Bengt",
                        "birth_year": "1923"
                    }
                ]
            }
        }
    }
}