{
    "original": "Olivius, Samuel Olof, kyrkoherde,\nHjärnarp, f. 29/10/02 i V. Klagstorp,\nMälmöh. 1. G. 28 m. Eva Martina\nMöller.     Barn:   Anders   f.  32,   Cecilia\n\n34, Eskil 39. — Stud :ex. i Lund 22,\nteol. fil. ex. 23;, teol. kand., prakt. teol.\nex. o. prästv. f. Lunds stift 26. V.\npastor i Osby 26, v. kommin. i Vittsjö\n28, kommin. i N. Åkarp 30-40, kyrkoh.\ni Hjärnarp o. Tos†arp sed. (38) 40.\n\nOlof son, Bror W., direktör, Malmö,\nf. 25/2/77 i Farstorp, Krist. 1., av Olof\nJonsson o. Hanna Waldemarsdotter.\nG. 1. 06 m. Vivica Strandberg; 2. 24\nm. Lia Trägårdh. Barn: Erik f. 07,\ntaxrinsp., Malmö, Valter 09’, disp. i\nfad. firma. Verks t. dir. i A-B\nBröderna Olof son i Malmö 09-43. Led. av\nstyr. f. fören. Södra Sv:es\ntextilgros-’sister m. fl. RNO, RVO.\nHed:-led. av Kulturhist. fören. f. Södra Sv:e\ni Lund.\n\nOlofson, Erik Lennart,\ntaxeringsinspektör, Malmö, f. 8/9/07 i Barkåkra,,\nKrist. 1., av dir. Bror O. o. Vivica\nStrandberg. G. 28 m. Sylvia Stenberg.\nBarn: Gun f. 29. — Stud:ex. v.\nLundsbergs sk. 27, fil. kand. i Lund 34, jur.\nkand. 41. Res. t. Tyskl. 28. Tingstjg.\ni Frosta o. Eslövs doms. 41, bitr. jur.\nv. länsstyr. i Malmöh. 1. 41-45,\ntax:-inis-p. där sed. 45. Ordf. i tax:nd i\nolika distr. 42-48, sekr. h. länsprövn\n:-nd 42-43.\n\nOlofsson, Ossian Herman, fil. dr,\nfiskeriintendent, Lund, f. 12/7/86 i\nAs-kersunds landsförs. av Gust. O. o.\nWalborg Nilsson. G. 21 m. Sigrid\nLagergren. Barn: Lars Barringer f. 23,\nBjörn Barringer 27, Hans 44. —\nStud:-ex. 04, fil. mag. i Upps. 09, fil. lic. 14,\nfil. dr 18. Stud. v. biol. stat.\nKristi-neberg 09, Aneboda 10, Hilleröd 11,\ndelt. i sv. exp. t. Spetsbergen 09’ o.\n10, stud:res. t. Murmankusten m. m.\n13, deleg. i svenskfinska\ngränsfiske-komm. 211-24. Aman. v. zool. inst. i\nUpps. 13-14, fiskeris†ip. 14-19, .tf.\nfis&gt;-keriint. i södra distr. 17-18, ord. i\növre norra distr. 19-39, i södra distr.\nfr. 39. Sekr. i Norrb. 1. fiskerind\n19-39, i Södra Sv:es fiskerifören. o. i\nfis-keristyr. i Malmöh. 1. 39, v. ordf. i\nSv. fiskev:förb. 41, sekr. i jaktv:fören.\n26-31, led. av Sv. jäg:’förb. styr.\n29-39, korrespL av Fiskerifören. i Finl*\nSkr.: Avh. oim entomostraka o. rotat,\nfr. Murmankust. o. norra Norge (17),\nOrn arkt. harpacticider (17), Stud. Üb.\ndie Siisswasserfauna Spitzbergens (18),\nupps. om ifiske, jakt, faunist. o.\netnologi i fackpress. RVO 32,\nRFinlVRO-lkl.\n\n",
    "structured": {
        "1": {
            "full_name": "Olivius, Samuel Olof",
            "location": "Hjärnarp",
            "occupation": "kyrkoherde",
            "birth_details": {
                "date": "29/10/1902",
                "place": "V. Klagstorp",
                "parents": null
            },
            "education": [
                {
                    "degree": "Stud",
                    "year": "1922",
                    "institution": "Lund"
                },
                {
                    "degree": "teol. fil. ex.",
                    "year": "1923",
                    "institution": null
                },
                {
                    "degree": "teol. kand.",
                    "year": "1926",
                    "institution": "Lunds stift"
                }
            ],
            "career": [
                {
                    "position": "v. pastor",
                    "years": {
                        "start_year": 1926,
                        "end_year": 1926
                    },
                    "organization": "Osby"
                },
                {
                    "position": "v. kommin.",
                    "years": {
                        "start_year": 1928,
                        "end_year": 1930
                    },
                    "organization": "Vittsjö"
                },
                {
                    "position": "kommin.",
                    "years": {
                        "start_year": 1930,
                        "end_year": 1940
                    },
                    "organization": "N. Åkarp"
                },
                {
                    "position": "kyrkoh.",
                    "years": {
                        "start_year": 1940,
                        "end_year": null
                    },
                    "organization": "Hjärnarp o. Tos†arp"
                }
            ],
            "family": {
                "spouse": "Eva Martina Möller",
                "marriage_year": "1928",
                "children": [
                    {
                        "name": "Anders",
                        "birth_year": "1932"
                    },
                    {
                        "name": "Cecilia",
                        "birth_year": "1934"
                    },
                    {
                        "name": "Eskil",
                        "birth_year": "1939"
                    }
                ]
            }
        },
        "2": {
            "full_name": "Olofson, Erik Lennart",
            "location": "Malmö",
            "occupation": "taxeringsinspektör",
            "birth_details": {
                "date": "8/9/1907",
                "place": "Barkåkra",
                "parents": "dir. Bror O. o. Vivica Strandberg"
            },
            "education": [
                {
                    "degree": "Stud:ex.",
                    "year": "1927",
                    "institution": "Lundsbergs sk."
                },
                {
                    "degree": "fil. kand.",
                    "year": "1934",
                    "institution": "Lund"
                },
                {
                    "degree": "jur. kand.",
                    "year": "1941",
                    "institution": null
                }
            ],
            "career": [
                {
                    "position": "Tingstjg.",
                    "years": {
                        "start_year": 1941,
                        "end_year": 1945
                    },
                    "organization": "Frosta o. Eslövs doms."
                },
                {
                    "position": "bitr. jur. v. länsstyr.",
                    "years": {
                        "start_year": 1941,
                        "end_year": 1945
                    },
                    "organization": "Malmöh. 1."
                },
                {
                    "position": "tax:inis-p.",
                    "years": {
                        "start_year": 1945,
                        "end_year": null
                    },
                    "organization": "Malmö"
                }
            ],
            "family": {
                "spouse": "Sylvia Stenberg",
                "marriage_year": "1928",
                "children": [
                    {
                        "name": "Gun",
                        "birth_year": "1929"
                    }
                ]
            }
        },
        "3": {
            "full_name": "Olofsson, Ossian Herman",
            "location": "Lund",
            "occupation": "fil. dr, fiskeriintendent",
            "birth_details": {
                "date": "12/7/1886",
                "place": "Askersunds landsförs.",
                "parents": "Gust. O. o. Walborg Nilsson"
            },
            "education": [
                {
                    "degree": "Stud:-ex.",
                    "year": "1904",
                    "institution": null
                },
                {
                    "degree": "fil. mag.",
                    "year": "1909",
                    "institution": "Upps."
                },
                {
                    "degree": "fil. lic.",
                    "year": "1914",
                    "institution": null
                },
                {
                    "degree": "fil. dr",
                    "year": "1918",
                    "institution": null
                }
            ],
            "career": [
                {
                    "position": "Aman. v. zool. inst.",
                    "years": {
                        "start_year": 1913,
                        "end_year": 1914
                    },
                    "organization": "Upps."
                },
                {
                    "position": "fiskeris†ip.",
                    "years": {
                        "start_year": 1914,
                        "end_year": 1919
                    },
                    "organization": "södra distr."
                },
                {
                    "position": "ord. i övre norra distr.",
                    "years": {
                        "start_year": 1919,
                        "end_year": 1939
                    },
                    "organization": null
                },
                {
                    "position": "ord. i södra distr.",
                    "years": {
                        "start_year": 1939,
                        "end_year": null
                    },
                    "organization": "Malmöh. 1."
                }
            ],
            "family": {
                "spouse": "Sigrid Lagergren",
                "marriage_year": "1921",
                "children": [
                    {
                        "name": "Lars Barringer",
                        "birth_year": "1923"
                    },
                    {
                        "name": "Björn Barringer",
                        "birth_year": "1927"
                    },
                    {
                        "name": "Hans",
                        "birth_year": "1944"
                    }
                ]
            }
        }
    }
}