{
    "original": "Ohlsson, Emil Theodor, kamrer,\nMalmö, f. 3/5/86 i Gödelöv, Malmöh. 1.,\nav mej :förest. A. O. o. Johanna\nKnutsson. G. 18 m. Anna Ekeblad. Barn:\nGunvor f. 23. — Stud:ex. i Malmö 06.\nTj :man i Brand- o. Lifförsäkr. A-B\nSkåne 06, chef f. korresp :avd. 11,\nkamrer o. kont :chef sed. 29. Fd. styr :led. i\nFörsäkr :sällsk. i Malmö, styr’:suppl. i\nBrand- o. Lifförsäkr. A-B Skåne.\nBrand- o. Lifskånes GM.\n\nOhlsson, Nils Erik Magnus,\nkomminister, Ödåkra, f. 18/5/10 i Örkened,\nKrist. 1., av Gustaf O. o. Signe\nJohnsson. G. 37 m. fil. kand. Birgit Gjöthlén.\nBarn: Stig f. 39, Staffan 41, Karin 44.\n— Stud:ex. i Lund 28, teol. fil. ex. 30,\nteol. kand. 34, prästv. f. Lunds stift\n34. Past :adj. i Allerum 34, v. past. i\nVadensjö o. Örja 37, kyrkoadj. i\nHärslöv, Säby, Vadensjö o. Örja 42,\nkorn-min. i Allerurn o. Fleninge sed. 48.\nFd. fäng:pred.\n\nOhlsson Olof Erik Vilhelm,\ncivilingenjör, Malmö, f. 5/2/18 i Tvååker,\nHall. 1., av Olof O. o. Amy Larsson.\nG. 47 m. Maja Bengtsson. Barn: Hans\nPetter f. 48. — Stud:ex. i Gbg 38,\nciv:-ing. 44. Anst. v. A-B Skånska\nCe-mentgjuteriet 44.\n\nOlsson, Erik Waldemar,\nfolkskollärare, kantor, Djurslöv, f. 8/3/02 i\nSvenstorp, Malmö-h. 1. G. 30 m.\nAnna-Gunhild Svemsson. Barn: Ingrid f. 31,\nLars-Erik 34. — Folikskoll :ex. i Lund\n25, org:- o. kyrkos:ex. i Visfcy 26.\nOrd. folkskoll. i Frillesås 26-27, i\nTott-arp sed. 28, kantor där, undervis, i\nslöjd, tillsynslär. Led. av komm :fullm.,\nv. ordf. i barnavrnd, bibliotekarie.\n\nOlsson, Ernst August, teol. o. fil.\nkand., kyrkoherde, Fjälkestad, f. 2/8/96\ni Lyngby, Malmöh. .1., av hemm :äg.\nPer o. Matilda Olivia O. G. 35 m.\nMajken Ahlquist. Barn: Lillemor f. 36,\nIngemar 40. — Stud:ex. v. Lunds priv.\nelem:sk. 20, stud. v. Göttingens univ.\n22, fil. kand. i Lund 24, teol. kand. 26,\nprästv. f. Lunds stift s. å. Vik.\nfolkskoll, i Alle rum 21, tf. kyrikoh. i St.\nHarrie 27, kyrkoadj. i Finja 27-32, lär.\nv. Hässleholms samrealsk. o. tekn. sk.\n29-32, kommin. i Allerum o. Fleninge\n(30) 312, kyrkoh. i Fjälkestad 47. I\nAllerum-Fleninge ordf. i kyrkostämma\no. kyrkofurlm., i styr. f. folksk.,\nfort-s:sk., h. folksk. o. hush :&lt;sk., ordf. o.\nkassör i barnavrnd o. .fam :bidr :nd,\nhuv:man i Fleninge Sparb. I\nFjälkestad   ordf.   i   kyrkostämman.\n\n",
    "structured": {
        "0": {
            "full_name": "Emil Theodor Ohlsson",
            "location": "Malmö",
            "occupation": "kamrer",
            "birth_details": {
                "date": "03/05/1886",
                "place": "Gödelöv, Malmöh"
            },
            "education": [
                {
                    "degree": "Stud:ex.",
                    "year": "1906",
                    "institution": "Malmö"
                }
            ],
            "career": [
                {
                    "position": "Tj :man",
                    "years": {
                        "start_year": 1906,
                        "end_year": 1929
                    },
                    "organization": "Brand- o. Lifförsäkr. A-B Skåne"
                },
                {
                    "position": "chef f. korresp",
                    "years": {
                        "start_year": 1929,
                        "end_year": null
                    },
                    "organization": "Brand- o. Lifförsäkr. A-B Skåne"
                },
                {
                    "position": "kamrer o. kont :chef",
                    "years": {
                        "start_year": 1929,
                        "end_year": null
                    },
                    "organization": null
                }
            ],
            "family": {
                "spouse": "Anna Ekeblad",
                "marriage_year": "1918",
                "children": [
                    {
                        "name": "Gunvor",
                        "birth_year": "1923"
                    }
                ]
            }
        },
        "1": {
            "full_name": "Nils Erik Magnus Ohlsson",
            "location": "Ödåkra",
            "occupation": "komminister",
            "birth_details": {
                "date": "18/05/1910",
                "place": "Örkened, Krist. 1."
            },
            "education": [
                {
                    "degree": "Stud:ex.",
                    "year": "1928",
                    "institution": "Lund"
                },
                {
                    "degree": "teol. fil. ex.",
                    "year": "1930",
                    "institution": null
                },
                {
                    "degree": "teol. kand.",
                    "year": "1934",
                    "institution": "Lunds stift"
                }
            ],
            "career": [
                {
                    "position": "Past :adj.",
                    "years": {
                        "start_year": 1934,
                        "end_year": null
                    },
                    "organization": "Allerum"
                },
                {
                    "position": "korn-min.",
                    "years": {
                        "start_year": 1948,
                        "end_year": null
                    },
                    "organization": "Allerurn o. Fleninge"
                }
            ],
            "family": {
                "spouse": "fil. kand. Birgit Gjöthlén",
                "marriage_year": "1937",
                "children": [
                    {
                        "name": "Stig",
                        "birth_year": "1939"
                    },
                    {
                        "name": "Staffan",
                        "birth_year": "1941"
                    },
                    {
                        "name": "Karin",
                        "birth_year": "1944"
                    }
                ]
            }
        },
        "2": {
            "full_name": "Olof Erik Vilhelm Ohlsson",
            "location": "Malmö",
            "occupation": "civilingenjör",
            "birth_details": {
                "date": "05/02/1918",
                "place": "Tvååker, Hall. 1."
            },
            "education": [
                {
                    "degree": "Stud:ex.",
                    "year": "1938",
                    "institution": "Gbg"
                },
                {
                    "degree": "civ:-ing.",
                    "year": "1944",
                    "institution": null
                }
            ],
            "career": [
                {
                    "position": null,
                    "years": {
                        "start_year": 1944,
                        "end_year": null
                    },
                    "organization": "A-B Skånska Cementgjuteriet"
                }
            ],
            "family": {
                "spouse": "Maja Bengtsson",
                "marriage_year": "1947",
                "children": [
                    {
                        "name": "Hans Petter",
                        "birth_year": "1948"
                    }
                ]
            }
        },
        "3": {
            "full_name": "Erik Waldemar Olsson",
            "location": "Djurslöv",
            "occupation": "folkskollärare, kantor",
            "birth_details": {
                "date": "08/03/1902",
                "place": "Svenstorp, Malmö-h. 1."
            },
            "education": [
                {
                    "degree": "Folikskoll :ex.",
                    "year": "1925",
                    "institution": "Lund"
                },
                {
                    "degree": "org:- o. kyrkos:ex.",
                    "year": "1926",
                    "institution": "Visfcy"
                }
            ],
            "career": [
                {
                    "position": "Ord. folkskoll.",
                    "years": {
                        "start_year": 1926,
                        "end_year": 1927
                    },
                    "organization": "Frillesås"
                },
                {
                    "position": "ord. folkskoll.",
                    "years": {
                        "start_year": 1928,
                        "end_year": null
                    },
                    "organization": "Tott-arp"
                },
                {
                    "position": "kantor",
                    "years": {
                        "start_year": null,
                        "end_year": null
                    },
                    "organization": "Frillesås"
                }
            ],
            "family": {
                "spouse": "Anna-Gunhild Svemsson",
                "marriage_year": "1930",
                "children": [
                    {
                        "name": "Ingrid",
                        "birth_year": "1931"
                    },
                    {
                        "name": "Lars-Erik",
                        "birth_year": "1934"
                    }
                ]
            }
        },
        "4": {
            "full_name": "Ernst August Olsson",
            "location": "Fjälkestad",
            "occupation": "teol. o. fil. kand., kyrkoherde",
            "birth_details": {
                "date": "02/08/1896",
                "place": "Lyngby, Malmöh. .1."
            },
            "education": [
                {
                    "degree": "Stud:ex.",
                    "year": "1920",
                    "institution": "Lunds priv. elem:sk."
                },
                {
                    "degree": null,
                    "year": "1922",
                    "institution": "Göttingens univ."
                },
                {
                    "degree": "fil. kand.",
                    "year": "1924",
                    "institution": "Lund"
                },
                {
                    "degree": "teol. kand.",
                    "year": "1926",
                    "institution": "Lunds stift"
                }
            ],
            "career": [
                {
                    "position": "Vik. folkskoll.",
                    "years": {
                        "start_year": 1921,
                        "end_year": 1921
                    },
                    "organization": "Alle rum"
                },
                {
                    "position": "korn-min.",
                    "years": {
                        "start_year": null,
                        "end_year": 1927
                    },
                    "organization": "Finja"
                },
                {
                    "position": "lär.",
                    "years": {
                        "start_year": 1929,
                        "end_year": 1932
                    },
                    "organization": "Hässleholms samrealsk. o. tekn. sk."
                },
                {
                    "position": "kommin.",
                    "years": {
                        "start_year": 1931,
                        "end_year": null
                    },
                    "organization": "Allerum o. Fleninge"
                },
                {
                    "position": "kyrkoh.",
                    "years": {
                        "start_year": 1947,
                        "end_year": null
                    },
                    "organization": "Fjälkestad"
                }
            ],
            "family": {
                "spouse": "Majken Ahlquist",
                "marriage_year": "1935",
                "children": [
                    {
                        "name": "Lillemor",
                        "birth_year": "1936"
                    },
                    {
                        "name": "Ingemar",
                        "birth_year": "1940"
                    }
                ]
            }
        }
    }
}