{
    "original": "EFVERLUND, STIG G, ingenjör,\nHuskvarna, f i Eskilstuna 13/7/21 av konstn\nGerhard Larsson o Ebba Efverlund.\n\nMaskinfacksk Eskilstuna 41, ing\nSkogstorps valsverk 42, verkst :ing Carlfors\nbruk sed 45. - Ag Ing :firman Sewin\n(kem-tekn apparatur) sed 48, verkst dir\nab Huluharnmars bruk Taberg sed 55.\n-Hobbies: pistolskytte, musik.\nGift 48 m Britt Bertilson f 23, dtr t\nmur armast Bertil Johansson o Nia\nAxelsdotter. - Barn: Git f 49, Ann f 50,\nPer f 55.\n\nEGELIUS, NILS G, överläkare,\nFinspång, f i Gbg 27/1/19 av disp E G\nErikson o Karin Rosenlöf.\nStud:ex Sigtuna 37, med kand 41 o med\nlic Sthlm 46, öl läk:förordn 46-47,\nunderläk med avd Södersjh 47-56, bitr läk\npensionsstyr 50-56, l:e underläk o bitr\növerläk med avd Linkpgs las 56-59,\növerläk med avd Finspångs las sed 59;\nförest reumat:dispens centrallås Linkpg\n57-63. - Styr :led Östergötl l avd av\nRiks-fören mot reumatism, led Östergötl l\npens :deleg. - Medl Rotary (presid\n62-63). - Skr i reumatol.\nGift 1) 43 m Aina Sjöberg f 19 d 46,\ndtr t disp Filip S o Mandi Andersson,\n2) 48 m Anna-Martha Malmar f 22, dtr\nt envoyén Folke M o adv Lily\nLindroth. - Barn: Mats f 49, Johan f 52.\n\nEGERDAL, G SIXTEN, direktör,\nGbg, f i Sthlm 29/2/04 av fabr Fritz\nKarlsson o Erika Lindberg.\nStud:ex 23, anst Swedish Trading Co\nab Sthlm 26-36, verkst dir ab Hedström\n&amp; Cp Gbg 36-64, dir o styr:led Frick\n&amp; Nilsson ab sed 65.\n\nGift 32 m Friedel Berns f 07, dtr t ing\nH B o Berta Harting. - Barn: Bo f 38,\nPer f 43.\n\nEGERDAL, G SIXTEN, direktör,\nkonsul, Uddevalla, f i Malmö 2/9/13.\nStud:ex 33, jur kand Lund 38, DHS 42,\nsekr IK 42, dir :assist Junex konfektions\nab 44, dir Bröderna Edstrand ab 47,\nverkst dir Granit ab C A Kullgrens Enka\nsed 53. - Styr :led ovanst bol, Stenind\narb :giv :f örb, Sv:es granitind:förb, Sv:es\ngranitind exportfören, Stenind\nforskn:-inst, Försäljn ab gat- o kantsten, Gbgs\nbk Uddevalla, Företagarefören,\nhdlskamm m fi. - Utm: ItSolSO.\nGift 44 m Ulla Ahlholm f 20. - Barn:\nInger f 45, Björn f 47, Tove f 50.\n\n",
    "structured": {
        "1": {
            "full_name": "EFVERLUND, STIG G",
            "location": "Huskvarna",
            "occupation": "ingenjör",
            "birth_details": {
                "date": "13/07/1921",
                "place": "Eskilstuna",
                "parents": "konstn Gerhard Larsson o Ebba Efverlund."
            },
            "education": [
                {
                    "degree": "Maskinfacksk",
                    "year": "1941",
                    "institution": "Eskilstuna"
                }
            ],
            "career": [
                {
                    "position": "ing Skogstorps valsverk",
                    "years": {
                        "start_year": 1942,
                        "end_year": 1942
                    },
                    "organization": "Carlfors bruk"
                },
                {
                    "position": "Ag Ing :firman Sewin",
                    "years": {
                        "start_year": 1948,
                        "end_year": null
                    },
                    "organization": "kem-tekn apparatur"
                },
                {
                    "position": "verkst dir ab Huluharnmars bruk Taberg",
                    "years": {
                        "start_year": 1955,
                        "end_year": null
                    }
                }
            ],
            "family": {
                "spouse": "Britt Bertilson",
                "marriage_year": "1948",
                "children": [
                    {
                        "name": "Git",
                        "birth_year": "1949"
                    },
                    {
                        "name": "Ann",
                        "birth_year": "1950"
                    },
                    {
                        "name": "Per",
                        "birth_year": "1955"
                    }
                ]
            },
            "hobbies": [
                "pistolskytte",
                "musik"
            ]
        },
        "2": {
            "full_name": "EGELIUS, NILS G",
            "location": "Finspång",
            "occupation": "överläkare",
            "birth_details": {
                "date": "27/01/1919",
                "place": "Göteborg",
                "parents": "disp E G Erikson o Karin Rosenlöf."
            },
            "education": [
                {
                    "degree": "Stud:ex",
                    "year": "1937",
                    "institution": "Sigtuna"
                },
                {
                    "degree": "med kand",
                    "year": "1941",
                    "institution": "Sthlm"
                },
                {
                    "degree": "med lic",
                    "year": "1946",
                    "institution": "Sthlm"
                }
            ],
            "career": [
                {
                    "position": "öl läk:förordn",
                    "years": {
                        "start_year": 1946,
                        "end_year": 1947
                    }
                },
                {
                    "position": "underläk med avd Södersjh",
                    "years": {
                        "start_year": 1947,
                        "end_year": 1956
                    }
                },
                {
                    "position": "bitr läk pensionsstyr",
                    "years": {
                        "start_year": 1950,
                        "end_year": 1956
                    }
                },
                {
                    "position": "l:e underläk o bitr överläk med avd Linkpgs las",
                    "years": {
                        "start_year": 1956,
                        "end_year": 1959
                    }
                }
            ],
            "family": {
                "spouse": "Aina Sjöberg",
                "marriage_year": "1943",
                "children": [
                    {
                        "name": "Mats",
                        "birth_year": "1949"
                    },
                    {
                        "name": "Johan",
                        "birth_year": "1952"
                    }
                ]
            },
            "publications": [],
            "community_involvement": [
                {
                    "role": "presid",
                    "organization": "Rotary",
                    "years": "1962-1963"
                }
            ]
        },
        "3": {
            "full_name": "EGERDAL, G SIXTEN",
            "location": "Göteborg",
            "occupation": "direktör",
            "birth_details": {
                "date": "29/02/1904",
                "place": "Sthlm",
                "parents": "fabr Fritz Karlsson o Erika Lindberg."
            },
            "education": [],
            "career": [
                {
                    "position": "anst Swedish Trading Co ab Sthlm",
                    "years": {
                        "start_year": 1926,
                        "end_year": 1936
                    }
                },
                {
                    "position": "verkst dir ab Hedström & Cp Gbg",
                    "years": {
                        "start_year": 1936,
                        "end_year": 1964
                    }
                }
            ],
            "family": {
                "spouse": "Friedel Berns",
                "marriage_year": "1932",
                "children": [
                    {
                        "name": "Bo",
                        "birth_year": "1938"
                    },
                    {
                        "name": "Per",
                        "birth_year": "1943"
                    }
                ]
            }
        },
        "4": {
            "full_name": "EGERDAL, G SIXTEN",
            "location": "Uddevalla",
            "occupation": "direktör, konsul",
            "birth_details": {
                "date": "02/09/1913",
                "place": "Malmö"
            },
            "education": [
                {
                    "degree": "Stud:ex",
                    "year": "1933",
                    "institution": "Lund"
                },
                {
                    "degree": "jur kand",
                    "year": "1938",
                    "institution": "Lund"
                },
                {
                    "degree": "DHS",
                    "year": "1942"
                }
            ],
            "career": [
                {
                    "position": "sekr IK",
                    "years": {
                        "start_year": 1942,
                        "end_year": null
                    },
                    "organization": "K"
                },
                {
                    "position": "dir assist Junex konfektions ab",
                    "years": {
                        "start_year": 1944,
                        "end_year": null
                    }
                },
                {
                    "position": "dir Bröderna Edstrand ab",
                    "years": {
                        "start_year": 1947,
                        "end_year": null
                    }
                },
                {
                    "position": "verkst dir Granit ab C A Kullgrens Enka",
                    "years": {
                        "start_year": 1953,
                        "end_year": null
                    }
                }
            ],
            "family": {
                "spouse": "Ulla Ahlholm",
                "marriage_year": "1944",
                "children": [
                    {
                        "name": "Inger",
                        "birth_year": "1945"
                    },
                    {
                        "name": "Björn",
                        "birth_year": "1947"
                    },
                    {
                        "name": "Tove",
                        "birth_year": "1950"
                    }
                ]
            },
            "honorary_titles": [
                {
                    "title": "ItSolSO",
                    "institution": null,
                    "year": null
                }
            ]
        }
    }
}