{
    "original": "EKLUND, P G RAGNAR,\nläroverksadjunkt, Gbg, f i Sthlm 18/2/06.\nAdj Vasa hal Gbg sed 37. - V ordf\nModersmålslär fören ortsfören 55.  -  Utg:\nSvensk språklära (3 :e uppl 59).\n\nEKLUND,   STIG   R   G,    tandläkare,\n\nGbg, f i Sthlm 21/5/14 av reg:läk\nGustaf E o Elsa Andersson.\nStud:ex Halmstad 32, tandl:ex Sthlm 35,\nass:tandl    Sundsvall    36-37,    priv:prakt\nLjusdal 38, Sundsvall 39-48, priv:prakt\nGbg sed 48. - Medl Odd Fellow.\nGift 2) 50 m Tora Maria Wennerblom\nf 14, dtr t Gustav W o Maria Lexén. -\n\nBarn: i l:a akt Madeleine f 46, i 2:a akt\nMats f 53.\nEKLUND,   UNO   R   E,   kyrkoherde,\n\nGbg, f i Eksjö 4/12/06 av metodistpast\nC J E o Emilia Persson.\nStud:ex Kalmar 26, teol kand Lund 32,\npast:adj Linkpg 33, bitr stiftsadj där 33,\nstiftsadj 34, kommin Hässleby 37,\nsjöm:-past S:t Johanneskyrkan Gbg 38,\nkom-min Johanneberg Gbg 44, kyrkoh där\nsed 55, mil:past Västkust marindistr\n42-47. - Ordf Joh förs kyrkoråd sed 55,\nutsedd av domkap att repr stadens\nkyrkoh :ar v kyrkofullm 56-66, led\nJohan-neskyrkans kyrkoråd, styr Gbgs kyrkl\nsjömansv, suppl Gbgs barnav:nd 49-53,\nstyr :ordf Sällsk Gbgs jultomtar, v ordf\nVasa Joh barnhem, De fattiges vänner,\nBrodhénska stift m m. - Skr: Soli Deo\nGloria (41), På heligt rum (43), medv\nEpistelpostilla (42), Aftonsångspostilla\n(46), medarb Stiftskrönikan m m. - Medl\nRotary. - Utm: LNO. - Hobby: musik.\nGift 37 m Inger Svenaeus f 18, dtr t\ndomprost SVen S o Ingeborg Anderberg.\n- Barn: Monika f 38.\n\nEKLUNDH se EKLUND\n\nEKLÖF, J F LENNART, direktör,\nJönköping, f i Örebro 8/2/15 av dir\nJosef E o h h.\n\nRealex 30, Norrkpgs hdlsgymn 32,\nLei-cester Coll of Techn 34; anst a’b Löf sko\n32, verkst dir o styr :led där sed 46,\nverkst dir o styr :led Lagerssons\nskosalonger Sthlm o Gbg samt ab Skodon.\n-Styr :led Sv:es skofabrikantfören, v ordf\nSv:es skofabrikanters intressentfören.\n-Utm: RVO. - Hobby: golf.\nGift 39 m Magda Gavelli f 18, dtr t\nkörsnär Henrik G o h h. - Barn:\nChrister f 41, Marianne f 45.\n\n",
    "structured": {
        "1": {
            "full_name": "EKLUND, P G RAGNAR",
            "location": "Göteborg",
            "occupation": "läroverksadjunkt",
            "birth_details": {
                "date": "18/02/1906",
                "place": "Stockholm"
            },
            "education": [
                {
                    "degree": "filosofie kandidat",
                    "year": "1955",
                    "institution": "ortsfören"
                }
            ]
        },
        "2": {
            "full_name": "EKLUND, STIG R G",
            "location": "Göteborg",
            "occupation": "tandläkare",
            "birth_details": {
                "date": "21/05/1914",
                "place": "Stockholm",
                "parents": "av reg:läk Gustaf E o Elsa Andersson"
            },
            "education": [
                {
                    "degree": "Stud:ex",
                    "year": "1932",
                    "institution": "Halmstad"
                },
                {
                    "degree": "tandl:ex",
                    "year": "1935",
                    "institution": "Stockholm"
                }
            ],
            "family": {
                "spouse": "Tora Maria Wennerblom",
                "marriage_year": "1950",
                "children": [
                    {
                        "name": "Madeleine",
                        "birth_year": "1946"
                    },
                    {
                        "name": "Mats",
                        "birth_year": "1953"
                    }
                ]
            }
        },
        "3": {
            "full_name": "EKLUND, UNO R E",
            "location": "Göteborg",
            "occupation": "kyrkoherde",
            "birth_details": {
                "date": "04/12/1906",
                "place": "Eksjö",
                "parents": "av metodistpast C J E o Emilia Persson"
            },
            "education": [
                {
                    "degree": "Stud:ex",
                    "year": "1926",
                    "institution": "Kalmar"
                },
                {
                    "degree": "teol kand",
                    "year": "1932",
                    "institution": "Lund"
                }
            ],
            "career": [
                {
                    "position": "sjöm:-past",
                    "years": {
                        "start_year": 1942,
                        "end_year": 1947
                    },
                    "organization": "S:t Johanneskyrkan Gbg"
                },
                {
                    "position": "kyrkoh",
                    "years": {
                        "start_year": 1955
                    },
                    "organization": "Johanneberg Gbg"
                }
            ],
            "family": {
                "spouse": "Inger Svenaeus",
                "marriage_year": "1937",
                "children": [
                    {
                        "name": "Monika",
                        "birth_year": "1938"
                    }
                ]
            },
            "publications": [
                {
                    "title": "Soli Deo Gloria",
                    "year": "1941",
                    "type": "bok"
                },
                {
                    "title": "På heligt rum",
                    "year": "1943",
                    "type": "bok"
                }
            ],
            "community_involvement": [
                {
                    "role": "Ordf",
                    "organization": "Joh förs kyrkoråd",
                    "years": "1955"
                }
            ],
            "honorary_titles": [
                {
                    "title": "LNO",
                    "institution": "NULL",
                    "year": "NULL"
                }
            ],
            "hobbies": [
                "musik"
            ]
        },
        "4": {
            "full_name": "EKLÖF, J F LENNART",
            "location": "Jönköping",
            "occupation": "direktör",
            "birth_details": {
                "date": "08/02/1915",
                "place": "Örebro",
                "parents": "av dir Josef E o h h"
            },
            "education": [
                {
                    "degree": "Realex",
                    "year": "1930",
                    "institution": "NULL"
                },
                {
                    "degree": "Norrkpgs hdlsgymn",
                    "year": "1932",
                    "institution": "NULL"
                },
                {
                    "degree": "Leicester Coll of Techn",
                    "year": "1934",
                    "institution": "NULL"
                }
            ],
            "family": {
                "spouse": "Magda Gavelli",
                "marriage_year": "1939",
                "children": [
                    {
                        "name": "Christer",
                        "birth_year": "1941"
                    },
                    {
                        "name": "Marianne",
                        "birth_year": "1945"
                    }
                ]
            },
            "hobbies": [
                "golf"
            ]
        }
    }
}