{
    "original": "EMILSSON,  EBBE  J  B,  lantmätare,\n\nVäxjö, f i S Vi, Kalmar l, 12/12/22 av\nhemm:äg Emil Petersson o Olga\nSvensson.\n\nStud:ex Linkpg 42, KTH 47, lantmät\nKalmar, Blek o Västerb l 47-55, Kronob\nl sed 55. - Hobbies: filateli, folkdans.\nGift 49 m Birgitta Brusewitz f 26, dtr t\nlärov :adj Nore B o Viva Grenholm.\n-Barn: Bengt o Göran ff 50, Viva f 54,\nPeter f 58.\n\nEMITSLÖF-DEJMO, A\nULLA-BRITTA, konstnärinna, Uddevalla, f i\nÄlmhult, Kronob l, 15/2/24 av kamr John\nE o Agnes Göthberg.\nSlöjdfören:s sk Gbg 44-46, Otte Skölds\nmålarsk Sthlm 46-48. - Bl arb:\nmonu-mentalarb i Älmhults gymn,\nkyrkotextilier. - Utst: Sthlm 52 o 55, mus i Växjö,\nEskil’stuna o Uddevalla, saml:utst bl a\npå Nät :mus o Liljevalens. - Repr:\nNät:-mus, H M Konungens saml, mus i\nVäxjö, Eskilstuna o Uddevalla.\nGift 48 m Kurt Dejmo f 19. - Barn:\nJan f 50.\n\nEMRICH, NILS-GUNNAR O,\nläroverksadjunkt, Uddevalla, f i Dalskog,\nÄlvsb l, 24/1/30 av kommin Oscar E o\nHildur Lindell.\n\nStud:ex Vänersborg 49, fil mag Gbg 54,\neo adj, sekr, vik rekt hal Uddevalla,\nadj där sed 60, fortbildn:led\nlänsskol:-ndn Älvsb l Vänersborg sed 63. - Medl\nRound Table.\n\nGift 57 m Margit Johansson f 29, dtr t\nbyggm J A J o Anna Eliasson. - Barn:\nChristina f 59, Anders f 62.\n\nENANDER, J ARTHUR,\nkontraktsprost, Gbg, f i Rydboholm, Älvsb l,\n15/8/06 av textilarb Johannes Larsson o\nAnna Enander.\n\nStud:ex Gbg 26, teol kand Lund 30,\nkyrkoadj Gamlestads förs Gbg 33,\nkommin där 35, kyrkoh Härianda förs 51,\nkontr :prost Gbgs ö :a kontr sed 62.\n-Ordf kyrkoråd o kyrkostämma, led\nkyr-kofullm, kyrkond, kyrkog :styr. - Utm:\nLNO.\n\nGift 36 m Kamma Knudsen, dtr t\növerlär Jens K o Margrethe Larsen. - Barn:\nInger f 38, Anne-Marie f 41, Barbro\nf 44.\n\n",
    "structured": {
        "1": {
            "full_name": "Emilsson, Ebbe J B",
            "location": "Växjö, Kalmar l",
            "occupation": "Lantmätare",
            "birth_details": {
                "date": "12/12/1922",
                "place": "S Vi, Kalmar l",
                "parents": "Emil Petersson and Olga Svensson"
            },
            "education": [
                {
                    "degree": "Stud:ex",
                    "year": "1942",
                    "institution": "Linkpg"
                },
                {
                    "degree": "KTH",
                    "year": "1947",
                    "institution": "KTH"
                }
            ],
            "career": [
                {
                    "position": "Lantmätare",
                    "years": {
                        "start_year": 1947,
                        "end_year": 1955
                    },
                    "organization": "Kalmar, Blek o Västerb l"
                },
                {
                    "position": "Kronob",
                    "years": {
                        "start_year": 1955,
                        "end_year": null
                    },
                    "organization": null
                }
            ],
            "family": {
                "spouse": "Birgitta Brusewitz",
                "marriage_year": "1949",
                "children": [
                    {
                        "name": "Bengt",
                        "birth_year": "1950"
                    },
                    {
                        "name": "Göran",
                        "birth_year": "1950"
                    },
                    {
                        "name": "Viva",
                        "birth_year": "1954"
                    },
                    {
                        "name": "Peter",
                        "birth_year": "1958"
                    }
                ]
            },
            "hobbies": [
                "filateli",
                "folkdans"
            ]
        },
        "2": {
            "full_name": "Emitslöf-Dejmo, A Ulla-Britta",
            "location": "Uddevalla",
            "occupation": "Konstnärinna",
            "birth_details": {
                "date": "15/2/1924",
                "place": "Älmhult, Kronob l",
                "parents": "John E and Agnes Göthberg"
            },
            "education": [
                {
                    "degree": "Slöjdfören:s sk",
                    "year": "1944-1946",
                    "institution": "Gbg"
                },
                {
                    "degree": "Otte Skölds målarsk",
                    "year": "1946-1948",
                    "institution": "Sthlm"
                }
            ],
            "career": [
                {
                    "position": "monumentalarb",
                    "years": {
                        "start_year": null,
                        "end_year": null
                    },
                    "organization": "Älmhults gymn, kyrkotextilier"
                }
            ],
            "family": {
                "spouse": "Kurt Dejmo",
                "marriage_year": "1948",
                "children": [
                    {
                        "name": "Jan",
                        "birth_year": "1950"
                    }
                ]
            }
        },
        "3": {
            "full_name": "Emrich, Nils-Gunnar O",
            "location": "Uddevalla",
            "occupation": "Läroverksadjunkt",
            "birth_details": {
                "date": "24/1/1930",
                "place": "Dalskog, Älvsb l",
                "parents": "Oscar E and Hildur Lindell"
            },
            "education": [
                {
                    "degree": "Stud:ex",
                    "year": "1949",
                    "institution": "Vänersborg"
                },
                {
                    "degree": "Fil mag",
                    "year": "1954",
                    "institution": "Gbg"
                }
            ],
            "career": [
                {
                    "position": "sekr, vik rekt",
                    "years": {
                        "start_year": 1960,
                        "end_year": null
                    },
                    "organization": "Uddevalla"
                }
            ],
            "family": {
                "spouse": "Margit Johansson",
                "marriage_year": "1957",
                "children": [
                    {
                        "name": "Christina",
                        "birth_year": "1959"
                    },
                    {
                        "name": "Anders",
                        "birth_year": "1962"
                    }
                ]
            }
        },
        "4": {
            "full_name": "Enander, J Arthur",
            "location": "Gbg",
            "occupation": "Kontraktsprost",
            "birth_details": {
                "date": "15/8/1906",
                "place": "Rydboholm, Älvsb l",
                "parents": "Johannes Larsson and Anna Enander"
            },
            "education": [
                {
                    "degree": "Stud:ex",
                    "year": "1926",
                    "institution": "Gbg"
                },
                {
                    "degree": "Teol kand",
                    "year": "1930",
                    "institution": "Lund"
                }
            ],
            "career": [
                {
                    "position": "kyrkoadj",
                    "years": {
                        "start_year": 1933,
                        "end_year": null
                    },
                    "organization": "Gamlestads förs Gbg"
                },
                {
                    "position": "kommin",
                    "years": {
                        "start_year": 1951,
                        "end_year": null
                    },
                    "organization": "Härianda förs"
                },
                {
                    "position": "kontr :prost",
                    "years": {
                        "start_year": 1962,
                        "end_year": null
                    },
                    "organization": "Gbgs ö :a kontr"
                }
            ],
            "family": {
                "spouse": "Kamma Knudsen",
                "marriage_year": "1936",
                "children": [
                    {
                        "name": "Inger",
                        "birth_year": "1938"
                    },
                    {
                        "name": "Anne-Marie",
                        "birth_year": "1941"
                    },
                    {
                        "name": "Barbro",
                        "birth_year": "1944"
                    }
                ]
            },
            "honorary_titles": [
                {
                    "title": "LNO",
                    "institution": null,
                    "year": null
                }
            ]
        }
    }
}