{
    "original": "ELG, J GÖSTA, överläkare, Kalmar,\nf i Borg, Östergötl l, 15/1/20 av ing\nJohn E o Karin Ellström.\nStud:ex Eskilstuna 39, med kand 42 o\nmed lic Sthlm 47; underläk Nässjö las\no RK :s sjukhem 46-48, ögonklin Karol\nsjh 48-53, bitr överläk ögonavd\nKarlskrona las 55, ögonavd Borås las 59,\n\nögonklin Sahlgr sjh 61, överläk ögonklin\nKalmar las sed 62. - Bat:läk flk res sed\n31.\n\nGift 52 m Gunnel Lindblom f 29, dtr t\nyrkeslär Lars L o Vendia L. - Barn:\nKarin f 53, Johan f 55, Sofi f 62.\nELGH, LARS B, kanslichef,\nNorrköping, f i Skövde 12/12/17 av boktr\nBertil E o Hildur Nyström.\nStud:ex 35, res:off:ex 37, jur kand Upps\n42, tingstjg Skövde doms 42-45,\nstadsnot Norrkpg 45, stadssekr 55, l:e\nstads-sekr där 60, kanslich sed 65. - Styr :led\nStrokirks bokind ab 48-58, Sv:es\njurist-förb sed 57, ,styr :suppl Norrkpgs sparbk\nsed 60, sekr div utredn o komm sed 47.\n- Medl SHT. - Hobby: foto.\nGift 46 m Siri Lindhe, dtr t Wilhelm L\no Lisa Thorsell.\n\nELGESKOG,   ERIK   G   A,   tekn   lic,\n\nLinköping, f i Karlskoga 24/10/25 av\nrekt Justus E o Ninnie Wahlborg.\nStud:ex Gbg 44, CTH 50, tekn lic 54;\nass CTH 50-55, tf bitr lär i mekanik II\ndär 51-52 o 53-55, tf labor i mekanik\n52-53, labor FOA 55-57, lär i\nelektro-tekn KHS 57, systeming Saab sed 57.\n-Skr: Kampekvationer o CTH :s elektr\ndifferentialanalysator (tills m H\nWall-man o B Stjernberg, 53), Photoformer\nanalysis and design (lic:avh 56). - Utm:\nJohn EricssonM. - Hobby: musik.\nGift 48 m Ulla Sjövall f 25, dtr t polism\nNils S o Ruth Björk. - Barn: Christina\nf 51, Agneta f 55.\n\nELGESKOG, JUSTUS F, fd rektor,\nLjungby, f i Vittaryd, Kronob l, 21/3/84\nav lantbr P J Magnusson o Emma\nPettersdotter.\n\nFolkskollär:ex 05, fil kand Upps 11, lär\nWendelsbergs folkhögsk 11-16, rekt där\n28-47, Karlskoga folkhögsk 16-28.\n-Styr :led Riksteat 33-54, riksstudieledare\nNTO 14-27, 32-35. - Skr bl a: Trädet\n(40), Folkrörelsernas studiehandbok (44),\nVårt språk i tanke, tal o skrift (54),\nGift 13 m Ninnie Wahlborg f 86, dtr t\npred Gustaf W o Augusta Karlen.\n-Barn: Inga Lisa f 14, Anna Lena f 15,\nGunnar f 18, Ninnie f 23, Erik f 25.\n\n",
    "structured": {
        "1": {
            "full_name": "ELG, J GÖSTA",
            "location": "Kalmar",
            "occupation": "överläkare",
            "birth_details": {
                "date": "15/01/1920",
                "place": "Borg, Östergötlands län"
            },
            "education": [
                {
                    "degree": "Stud:ex",
                    "year": "1939",
                    "institution": "Eskilstuna"
                },
                {
                    "degree": "med kand",
                    "year": "1942",
                    "institution": "NULL"
                },
                {
                    "degree": "med lic",
                    "year": "1947",
                    "institution": "Stockholm"
                }
            ],
            "career": [
                {
                    "position": "bat:läk flk",
                    "years": {
                        "start_year": 1931,
                        "end_year": "NULL"
                    },
                    "organization": "NULL"
                },
                {
                    "position": "underläk",
                    "years": {
                        "start_year": 1946,
                        "end_year": 1948
                    },
                    "organization": "Nässjö las o RK :s sjukhem"
                },
                {
                    "position": "bitr överläk ögonavd",
                    "years": {
                        "start_year": 1955,
                        "end_year": "NULL"
                    },
                    "organization": "Karlskrona las"
                },
                {
                    "position": "ögonavd Borås las",
                    "years": {
                        "start_year": 1959,
                        "end_year": "NULL"
                    },
                    "organization": "NULL"
                },
                {
                    "position": "ögonklin Sahlgr sjh",
                    "years": {
                        "start_year": 1961,
                        "end_year": "NULL"
                    },
                    "organization": "NULL"
                },
                {
                    "position": "överläk ögonklin Kalmar las",
                    "years": {
                        "start_year": 1962,
                        "end_year": "NULL"
                    },
                    "organization": "NULL"
                }
            ],
            "family": {
                "spouse": "Gunnel Lindblom",
                "marriage_year": "1952",
                "children": [
                    {
                        "name": "Karin",
                        "birth_year": "1953"
                    },
                    {
                        "name": "Johan",
                        "birth_year": "1955"
                    },
                    {
                        "name": "Sofi",
                        "birth_year": "1962"
                    }
                ]
            }
        },
        "2": {
            "full_name": "ELGH, LARS B",
            "location": "Norrköping",
            "occupation": "kanslichef",
            "birth_details": {
                "date": "12/12/1917",
                "place": "Skövde"
            },
            "education": [
                {
                    "degree": "Stud:ex",
                    "year": "1935",
                    "institution": "NULL"
                },
                {
                    "degree": "res:off:ex",
                    "year": "1937",
                    "institution": "NULL"
                },
                {
                    "degree": "jur kand",
                    "year": "1942",
                    "institution": "Uppsala"
                }
            ],
            "career": [
                {
                    "position": "tingstjg",
                    "years": {
                        "start_year": 1942,
                        "end_year": 1945
                    },
                    "organization": "Skövde doms"
                },
                {
                    "position": "stadsnot",
                    "years": {
                        "start_year": 1945,
                        "end_year": "NULL"
                    },
                    "organization": "Norrkpg"
                },
                {
                    "position": "stadssekr",
                    "years": {
                        "start_year": 1955,
                        "end_year": "NULL"
                    },
                    "organization": "NULL"
                },
                {
                    "position": "l:e stads-sekr",
                    "years": {
                        "start_year": 1960,
                        "end_year": "NULL"
                    },
                    "organization": "NULL"
                },
                {
                    "position": "kanslich",
                    "years": {
                        "start_year": 1965,
                        "end_year": "NULL"
                    },
                    "organization": "Norrköping"
                }
            ],
            "family": {
                "spouse": "Siri Lindhe",
                "marriage_year": "1946",
                "children": []
            },
            "hobbies": [
                "foto"
            ]
        },
        "3": {
            "full_name": "ELGESKOG, ERIK G A",
            "location": "Linköping",
            "occupation": "tekn lic",
            "birth_details": {
                "date": "24/10/1925",
                "place": "Karlskoga"
            },
            "education": [
                {
                    "degree": "Stud:ex",
                    "year": "1944",
                    "institution": "Göteborg"
                },
                {
                    "degree": "CTH",
                    "year": "1950",
                    "institution": "NULL"
                },
                {
                    "degree": "tekn lic",
                    "year": "1954",
                    "institution": "NULL"
                }
            ],
            "career": [
                {
                    "position": "ass",
                    "years": {
                        "start_year": 1950,
                        "end_year": 1955
                    },
                    "organization": "CTH"
                },
                {
                    "position": "lär i elektro-tekn",
                    "years": {
                        "start_year": 1957,
                        "end_year": "NULL"
                    },
                    "organization": "KHS"
                },
                {
                    "position": "systeming",
                    "years": {
                        "start_year": 1957,
                        "end_year": "NULL"
                    },
                    "organization": "Saab"
                }
            ],
            "family": {
                "spouse": "Ulla Sjövall",
                "marriage_year": "1948",
                "children": [
                    {
                        "name": "Christina",
                        "birth_year": "1951"
                    },
                    {
                        "name": "Agneta",
                        "birth_year": "1955"
                    }
                ]
            },
            "hobbies": [
                "musik"
            ]
        },
        "4": {
            "full_name": "ELGESKOG, JUSTUS F",
            "location": "Ljungby",
            "occupation": "fd rektor",
            "birth_details": {
                "date": "21/03/1884",
                "place": "Vittaryd, Kronobergs län"
            },
            "education": [
                {
                    "degree": "Folkskollär:ex",
                    "year": "1905",
                    "institution": "NULL"
                },
                {
                    "degree": "fil kand",
                    "year": "1911",
                    "institution": "Uppsala"
                }
            ],
            "career": [
                {
                    "position": "lär",
                    "years": {
                        "start_year": 1911,
                        "end_year": 1916
                    },
                    "organization": "Wendelsbergs folkhögsk"
                },
                {
                    "position": "rekt",
                    "years": {
                        "start_year": 1928,
                        "end_year": 1947
                    },
                    "organization": "Wendelsbergs folkhögsk"
                },
                {
                    "position": "rekt",
                    "years": {
                        "start_year": 1916,
                        "end_year": 1928
                    },
                    "organization": "Karlskoga folkhögsk"
                }
            ],
            "family": {
                "spouse": "Ninnie Wahlborg",
                "marriage_year": "1913",
                "children": [
                    {
                        "name": "Inga Lisa",
                        "birth_year": "1914"
                    },
                    {
                        "name": "Anna Lena",
                        "birth_year": "1915"
                    },
                    {
                        "name": "Gunnar",
                        "birth_year": "1918"
                    },
                    {
                        "name": "Ninnie",
                        "birth_year": "1923"
                    },
                    {
                        "name": "Erik",
                        "birth_year": "1925"
                    }
                ]
            }
        }
    }
}