{
    "original": "EHRNST, OLLE, tandläkare,\nTöreboda, f i Räpplinge, Kalmar l, 9/1/06\nav dir John E o Anna von Mentzer.\nStud:ex Kristianstad 24, med kand 27 o\ntandl:ex 32 Sthlm, förest RK:s\nambulerande tandklin i Jämtl l 33-42,\npriv:-prakt Töreboda sed 42, skoltandl\nTöreboda 42-43, Undenäs 42-56. - Styr:led\nVästerg tandl:fören 46-47, Skarab\ntandl:-fören 48-64, ordf där 56-62. - Led\nkomm:fuMm, komm:nd, lönend.\nGift 34 m Anna-Lisa Beskow f 10.\n-Barn: Ann-Sofie f 36, Olle f 38 d 58,\nGunnar f 40.\n\nEHRNSTRÖM, ANITA H E,\nläroverksadjunkt, Nässjö, f i Vallsjö,\nJön-kpgs l, 16/10/29 av prosten Einar E o\nEdith Carlsson.\n\nStud:ex Eksjö 49, fil måg Lund 55,\nprovar hal Linkpg 59, adj hal Nässjö\nsed 61 (e 55, eo 57). - Hobbies:\nträdgårdsskötsel, konsthantverk,\nfotografering.\n\nEIDESTEDT, C O BERTIL,\nkyrkoadjunkt, Norrköping, f i V Ryd, Östergötl\nl, 3/7/15 av hemm:äg Oskar Karlsson o\nDorothea Jonsson.\n\nStud:ex Upps 37, res:off:ex 40, teol kand\n46, past:adj S:t Olai förs Norrkpg 47,\nDomkyrkoförs Linkpg 50, kyrkoadj Borg\nNorrkpg sed 58. - Kapt I 4 res sed 54.\n-Medl Odd Fellow. - Hobby: jakt.\nGift 47 m Inga Ekdahl f 19, dtr t godsäg\nAlbin E o Linnea Nilsson. - Barn: Nils\nf 49, Birgitta f 51, Eva o Ulla ff 55.\n\nEIDLITZ, WALTHER, författare,\nOskarshamn, f i Wien 28/8/92 av Sigmund\nE o Friederike Weiss.\nStud:ex 10, stud tekn högsk Wien 16,\nstudier i indisk kultur Indien 38-46,\n50-51, anst religionshist inst StU. - Sv\nmedb 52, led Sv:es förf:fören sed 53.\n-Skr bl a: Der Berg in der Wüste (23),\nDie Gewaltigen (noveller 26), Zodiak\n(roman 30), Vindrosen runt (reseskildr\n\n35), Den glömda världen, en bok om\ndet okända Indien (48), Indisk mystik\n(52), Krishnas leende (55), Der Glaube\nund die heiligen Schriften der Inder\n(57), Der Guru — der geistige Meister\nin Indien (gram:skiva 64). - Utm:\nLite-raturpreis der Stadt Wien 24.\nGift 23 m Helena Spira f 98. - Barn:\nGünther f 33.\n\n",
    "structured": {
        "0": {
            "full_name": "OLLE EHRNST",
            "location": "Töreboda",
            "occupation": "tandläkare",
            "birth_details": {
                "date": "09/01/1906",
                "place": "Räpplinge, Kalmar l"
            },
            "parents": "dir John E o Anna von Mentzer",
            "education": [
                {
                    "degree": "Stud:ex",
                    "year": "1924",
                    "institution": "Kristianstad"
                },
                {
                    "degree": "med kand",
                    "year": "1927",
                    "institution": "unknown"
                },
                {
                    "degree": "tandl:ex",
                    "year": "1932",
                    "institution": "Sthlm"
                }
            ],
            "career": [
                {
                    "position": "förest RK:s ambulerande tandklin i Jämtl l",
                    "years": {
                        "start_year": 1933,
                        "end_year": 1942
                    },
                    "organization": "RK"
                },
                {
                    "position": "priv:-prakt Töreboda",
                    "years": {
                        "start_year": 1942,
                        "end_year": null
                    },
                    "organization": "unknown"
                },
                {
                    "position": "skoltandl Töreboda",
                    "years": {
                        "start_year": 1942,
                        "end_year": 1943
                    },
                    "organization": "unknown"
                },
                {
                    "position": "skoltandl Undenäs",
                    "years": {
                        "start_year": 1942,
                        "end_year": 1956
                    },
                    "organization": "unknown"
                }
            ],
            "family": {
                "spouse": "Anna-Lisa Beskow",
                "marriage_year": "1934",
                "children": [
                    {
                        "name": "Ann-Sofie",
                        "birth_year": "1936"
                    },
                    {
                        "name": "Olle",
                        "birth_year": "1938"
                    },
                    {
                        "name": "Gunnar",
                        "birth_year": "1940"
                    }
                ]
            }
        },
        "1": {
            "full_name": "ANITA H E EHRNSTRÖM",
            "location": "Nässjö",
            "occupation": "läroverksadjunkt",
            "birth_details": {
                "date": "16/10/1929",
                "place": "Vallsjö, Jön-kpgs l"
            },
            "parents": "prosten Einar E o Edith Carlsson",
            "education": [
                {
                    "degree": "Stud:ex",
                    "year": "1949",
                    "institution": "Eksjö"
                },
                {
                    "degree": "fil måg",
                    "year": "1955",
                    "institution": "Lund"
                }
            ],
            "career": [
                {
                    "position": "prov",
                    "years": {
                        "start_year": 1955,
                        "end_year": null
                    },
                    "organization": "Linkpg"
                },
                {
                    "position": "adj hal Nässjö",
                    "years": {
                        "start_year": 1961,
                        "end_year": null
                    },
                    "organization": "Nässjö"
                }
            ],
            "family": {},
            "hobbies": [
                "trädgårdsskötsel",
                "konsthantverk",
                "fotografering"
            ]
        },
        "2": {
            "full_name": "BERTIL EIDESTEDT",
            "location": "Norrköping",
            "occupation": "kyrkoadjunkt",
            "birth_details": {
                "date": "03/07/1915",
                "place": "V Ryd, Östergötl l"
            },
            "parents": "hemm:äg Oskar Karlsson o Dorothea Jonsson",
            "education": [
                {
                    "degree": "Stud:ex",
                    "year": "1937",
                    "institution": "Upps"
                },
                {
                    "degree": "res:off:ex",
                    "year": "1940",
                    "institution": "unknown"
                },
                {
                    "degree": "teol kand",
                    "year": "1946",
                    "institution": "unknown"
                }
            ],
            "career": [
                {
                    "position": "past:adj S:t Olai förs Norrkpg",
                    "years": {
                        "start_year": 1947,
                        "end_year": 1950
                    },
                    "organization": "S:t Olai förs Norrkpg"
                },
                {
                    "position": "Domkyrkoförs Linkpg",
                    "years": {
                        "start_year": 1950,
                        "end_year": null
                    },
                    "organization": "Domkyrkoförs Linkpg"
                },
                {
                    "position": "kyrkoadj Borg Norrkpg",
                    "years": {
                        "start_year": 1958,
                        "end_year": null
                    },
                    "organization": "Borg Norrkpg"
                }
            ],
            "family": {
                "spouse": "Inga Ekdahl",
                "marriage_year": "1947",
                "children": [
                    {
                        "name": "Nils",
                        "birth_year": "1949"
                    },
                    {
                        "name": "Birgitta",
                        "birth_year": "1951"
                    },
                    {
                        "name": "Eva",
                        "birth_year": "1955"
                    },
                    {
                        "name": "Ulla",
                        "birth_year": "1955"
                    }
                ]
            },
            "hobbies": "jakt"
        },
        "3": {
            "full_name": "WALTHER EIDLITZ",
            "location": "Oskarshamn",
            "occupation": "författare",
            "birth_details": {
                "date": "28/08/1892",
                "place": "Wien"
            },
            "parents": "Sigmund E o Friederike Weiss",
            "education": [
                {
                    "degree": "Stud:ex",
                    "year": "1910",
                    "institution": "unknown"
                },
                {
                    "degree": "stud tekn högsk",
                    "year": "1916",
                    "institution": "Wien"
                }
            ],
            "career": [
                {
                    "position": "led Sv:es förf:fören",
                    "years": {
                        "start_year": 1953,
                        "end_year": null
                    },
                    "organization": "Sv:es förf:fören"
                }
            ],
            "family": {
                "spouse": "Helena Spira",
                "marriage_year": "1923",
                "children": [
                    {
                        "name": "Günther",
                        "birth_year": "1933"
                    }
                ]
            },
            "publications": [
                {
                    "title": "Der Berg in der Wüste",
                    "year": "1923",
                    "type": "unknown"
                },
                {
                    "title": "Die Gewaltigen",
                    "year": "1926",
                    "type": "noveller"
                },
                {
                    "title": "Zodiak",
                    "year": "1930",
                    "type": "roman"
                },
                {
                    "title": "Vindrosen runt",
                    "year": "1935",
                    "type": "reseskildr 35"
                },
                {
                    "title": "Den glömda världen, en bok om det okända Indien",
                    "year": "1948",
                    "type": "unknown"
                },
                {
                    "title": "Indisk mystik",
                    "year": "1952",
                    "type": "unknown"
                },
                {
                    "title": "Krishnas leende",
                    "year": "1955",
                    "type": "unknown"
                },
                {
                    "title": "Der Glaube und die heiligen Schriften der Inder",
                    "year": "1957",
                    "type": "unknown"
                },
                {
                    "title": "Der Guru — der geistige Meister in Indien",
                    "year": "unknown",
                    "type": "gram:skiva 64"
                }
            ],
            "hobbies": "unknown"
        }
    }
}