{
    "original": "EDWARD, NILS J I, stadsdistriktsläkare, \nNorrköping, f i Kristinehamn 14/8/24 \nav byråass John E o Thelma Andrén.\n\nStud:ex Norrkpg 43, med kand 47 o\nmed lic Sthlm 53, l:e underläk pens:styr\nsjh Åre 53, infekt:- o epid:sjh Norrkpg\n54, med avd Kullbergska sjh\nKatrineholm 58, med klin Norrkpgs las 62,\nstadsdistr:läk Norrkpg sed 62. -\nHobbies: idrott, fiske, smalfilmning.\nGift 50 m Gun Andersson f 25, dtr t\nköpm John A o Ester Åkervall. - Barn:\nMats f 52, Hans f 54, Anders f 56.\n\n<b>EDWARDS, FOLKE E, redaktör,</b> Gbg,\nf i Shanghai 9/3/30 av köpm Einar E o\nBrita Jönsson.\n\nFil kand Upps 51, red Paletten sed 57,\nkonstkritiker ST sed 61.\n\nGift 61m skådesp Inga Botorp f 37, dtr\nt Anders B o Elna Enberg.\n\n<b>EDWARDSON, J JULIUS, lantbrukskonsulent,</b>\nVänersborg, f i Färgelanda,\nÄlvsb l, 15/1/08 av lantbr Edvard\nPettersson o Selma Jonasdotter.\n\nStud:ex Hermods 36, agr:ex KLH 41,\nagr Sörml l hush :sällsk 42, ass\negnahemsndn Sörml 44, lantbr:konsulent\nÄlvsb l n omr sed 48.\n\nGift 42 m Ulla Nilsson f 08, dtr t lantbr\nMattis N o h h.\n\nEDWARDSON, LARS E, tandläkare,\nTrollhättan, f i Ljung, Gbgs o Bohus l,\n8/5/22 av lantbr Anders E o Karin Maria Normell.\n\nStud:ex Uddevalla 44, tandl:ex Malmö\n53, distr:tandl Hörby 53, distr:tandl o\nförest distr:tandpoliklin Tyringe 55-59,\n1:e distr:tandl Trollhättan 59-64, bitr\ntandv:insp Älvsb l sed 65.\n\nGift m Etel Ingeiärd Alsen f 24, dtr t\nJohn A o Berta Persson. - Barn: Anders\nf 48, Ann-Charlotte f 50.\n\n<b>EDVARDSSON, SVEN M, disponent,</b>\nOrrefors, f i Hällefors, Örebro l, 21/11/13 av \nskogv Edvard Eriksson o Anna Andersson.\n\nRealex 30, forstm:ex SkHS 38, ass ab\nIggesunds bruk 39, skogsförv där 43,\nverkst dir ab Orrefors skogar sed 53.\n- Styr:led S Sv:es trävaruexp:fören m fl\n58-60, v ordf skogssekt f\nSmåland-Blekinge inom Sv lantarb :giv :f ören sed 63;\nkomm:fullm Hälleberg sed 57, vägkomm\nsed 57, högerfören sed 55. - Medl\nRotary. - Hobby: fiske.\n\nGift 43 m Siri Stigberg f 12, dtr t fabr\nArvid S o Anna Wilson.\n\n",
    "structured": {
        "0": {
            "full_name": "NILS J I EDWARD",
            "location": "Norrköping",
            "occupation": "Stadsdistriktsläkare",
            "birth_details": {
                "date": "14/08/1924",
                "place": "Kristinehamn",
                "parents": "Byråass John E. och Thelma Andrén"
            },
            "education": [
                {
                    "degree": "Stud:ex",
                    "year": "1943",
                    "institution": "Norrkpg"
                },
                {
                    "degree": "Med kand",
                    "year": "1947",
                    "institution": "N/A"
                },
                {
                    "degree": "Med lic",
                    "year": "1953",
                    "institution": "Sthlm"
                }
            ],
            "career": [
                {
                    "position": "L:e underläk",
                    "years": {
                        "start_year": 1953,
                        "end_year": 1962
                    },
                    "organization": "Pens:styr sjh Åre"
                },
                {
                    "position": "Infekt:- o epid:sjh",
                    "years": {
                        "start_year": 1954,
                        "end_year": null
                    },
                    "organization": "Norrkpg"
                },
                {
                    "position": "Med avd",
                    "years": {
                        "start_year": 1958,
                        "end_year": 1962
                    },
                    "organization": "Kullbergska sjh Katrineholm"
                },
                {
                    "position": "Med klin",
                    "years": {
                        "start_year": 1962,
                        "end_year": null
                    },
                    "organization": "Norrkpgs las"
                },
                {
                    "position": "Stadsdistr:läk",
                    "years": {
                        "start_year": 1962,
                        "end_year": null
                    },
                    "organization": "Norrkpg"
                }
            ],
            "family": {
                "spouse": "Gun Andersson",
                "marriage_year": "1950",
                "children": [
                    {
                        "name": "Mats",
                        "birth_year": "1952"
                    },
                    {
                        "name": "Hans",
                        "birth_year": "1954"
                    },
                    {
                        "name": "Anders",
                        "birth_year": "1956"
                    }
                ]
            },
            "hobbies": [
                "Idrott",
                "Fiske",
                "Smalfilmning"
            ]
        },
        "1": {
            "full_name": "FOLKE E EDWARDS",
            "location": "Gbg",
            "occupation": "Redaktör",
            "birth_details": {
                "date": "09/03/1930",
                "place": "Shanghai",
                "parents": "Köpm Einar E. och Brita Jönsson"
            },
            "education": [
                {
                    "degree": "Filosofie kandidat",
                    "year": "1951",
                    "institution": "Upps"
                }
            ],
            "career": [
                {
                    "position": "Red Paletten",
                    "years": {
                        "start_year": 1957,
                        "end_year": null
                    },
                    "organization": "N/A"
                },
                {
                    "position": "Konstkritiker ST",
                    "years": {
                        "start_year": 1961,
                        "end_year": null
                    },
                    "organization": "N/A"
                }
            ],
            "family": {
                "spouse": "Inga Botorp",
                "marriage_year": "1961"
            }
        },
        "2": {
            "full_name": "JULIUS EDWARDSON",
            "location": "Vänersborg",
            "occupation": "Lantbrukskonsulent",
            "birth_details": {
                "date": "15/01/1908",
                "place": "Färgelanda, Älvsb l",
                "parents": "Lantbr Edvard Pettersson och Selma Jonasdotter"
            },
            "education": [
                {
                    "degree": "Stud:ex",
                    "year": "1936",
                    "institution": "Hermods"
                },
                {
                    "degree": "Agr:ex",
                    "year": "1941",
                    "institution": "KLH"
                },
                {
                    "degree": "Agr",
                    "year": "1942",
                    "institution": "Sörml l hush :sällsk"
                }
            ],
            "career": [
                {
                    "position": "Ass egnahemsndn",
                    "years": {
                        "start_year": 1944,
                        "end_year": null
                    },
                    "organization": "Sörml"
                },
                {
                    "position": "Lantbr:konsulent Älvsb l n omr",
                    "years": {
                        "start_year": 1948,
                        "end_year": null
                    },
                    "organization": "N/A"
                }
            ],
            "family": {
                "spouse": "Ulla Nilsson",
                "marriage_year": "1942"
            }
        },
        "3": {
            "full_name": "LARS E EDWARDSON",
            "location": "Trollhättan",
            "occupation": "Tandläkare",
            "birth_details": {
                "date": "08/05/1922",
                "place": "Ljung, Gbgs o Bohus l",
                "parents": "Lantbr Anders E. och Karin Maria Normell"
            },
            "education": [
                {
                    "degree": "Stud:ex",
                    "year": "1944",
                    "institution": "Uddevalla"
                },
                {
                    "degree": "Tandl:ex",
                    "year": "1953",
                    "institution": "Malmö"
                }
            ],
            "career": [
                {
                    "position": "Distr:tandl",
                    "years": {
                        "start_year": 1953,
                        "end_year": 1964
                    },
                    "organization": "Hörby"
                },
                {
                    "position": "Bitr tandv:insp",
                    "years": {
                        "start_year": 1965,
                        "end_year": null
                    },
                    "organization": "Älvsb l"
                }
            ],
            "family": {
                "spouse": "Etel Ingeiärd Alsen",
                "marriage_year": "N/A",
                "children": [
                    {
                        "name": "Anders",
                        "birth_year": "1948"
                    },
                    {
                        "name": "Ann-Charlotte",
                        "birth_year": "1950"
                    }
                ]
            }
        },
        "4": {
            "full_name": "SVEN M EDVARDSSON",
            "location": "Orrefors",
            "occupation": "Disponent",
            "birth_details": {
                "date": "21/11/1913",
                "place": "Hällefors, Örebro l",
                "parents": "Skogv Edvard Eriksson och Anna Andersson"
            },
            "education": [
                {
                    "degree": "Realex",
                    "year": "1930",
                    "institution": "N/A"
                },
                {
                    "degree": "Forstm:ex",
                    "year": "1938",
                    "institution": "SkHS"
                }
            ],
            "career": [
                {
                    "position": "Ass ab",
                    "years": {
                        "start_year": 1939,
                        "end_year": 1953
                    },
                    "organization": "Iggesunds bruk"
                },
                {
                    "position": "Skogsförv",
                    "years": {
                        "start_year": 1943,
                        "end_year": null
                    },
                    "organization": "N/A"
                },
                {
                    "position": "Verkst dir",
                    "years": {
                        "start_year": 1953,
                        "end_year": null
                    },
                    "organization": "Orrefors skogar"
                }
            ],
            "family": {
                "spouse": "Siri Stigberg",
                "marriage_year": "1943"
            },
            "community_involvement": [
                {
                    "role": "Styr:led",
                    "organization": "S Sv:es trävaruexp:fören m fl",
                    "years": "58-60"
                }
            ],
            "hobbies": [
                "Fiske"
            ]
        }
    }
}