{
    "original": "ERICSON, E HUGO, direktör, Aspen,\nf i Hemsjö, Älvsb l, 10/5/14 av lantbr\nAnders E o Maria Andersson.\nHdlssk, verkst dir o inneh Hugo Ericson\nab Gbg sed 32, ag Kolboryds egend\nLerum. - V ordf kyrkofullm, led\nkyrkoråd, kyrkvärd Lerum. - Medl FrimO.\n-Skr: art i dagspr.\n\nGift 38 m Irma Svensson f 19, dtr t\nhandl Fritz S o Anna Henning. - Barn:\nMargaretha f 40, Rigmor f 43, Barbro\nf 46, Gunilla f 50, Annika f 54.\n\nERIKSSON, JAN-OLOF, civilingenjör,\n\nLinköping,  f  i  Trollhättan  7/12/29  av\n\nJohn E o Rakel Törnqvist.\n\nCTH 54, ing ab Bofors Sthlm 54, Saab\n\nLinkpg sed 58.\n\nGift 61 m Gunvor Ekman f 33, dtr t\n\nfabr Georg E o Sigrid Carlsson. - Barn:\n\nAnn f 62.\n\nERIKSSON, JOHANNES,\nbyggmästare, Gbg, f i Sätila, Älvsb l, 18/10/86\nav slaktare Johan E o Anna Olofsson\nLärk.\n\nSlöjdfören:s sk 14-18, verkm byggn\n:firman Bröd Persson 18-24, inneh eg\nbyggn :firma 24, Byggn ab Eriksson &amp;\nRann sed 56. - Styr:led Gbgs\nfastigh:äg:-fören 34-42, Gbgs byggm :f ören 44-52,\nled Gbgs hyresnd 44 o 45. - Medl PB,\nW-sex, Timglaset, sällsk Örgryte\nodalmän. - Hobby: blommor.\nG ift 16 m Julia Rundström, dtr t\nskeppare Leopold R o Amanda Olausdotter.\n- Barn: Inga-Lill f 17, Ann-Kerstin f 21.\n\nERIKSSON, K JONAS V,\nkomminister, N Kedum, f i Björsäter, Skarab l,\n28/4/29.\n\nStud:ex Upps 50, teol kand Lund 57,\nkyrkoadj Lyrestad 58, tf kommin\nHusaby 59, kyrkoadj Töreboda 62, kommin\nÖrslösa sed 63. - Ordf kyrkoråd o\nkyrkostämma. - Hobby: musik.\nGift 56 m org Britta Ragnarsdtr f 28,\ndtr t kyrkvärd Ragnar Andersson o\nAlbertina Andréasson. - Barn: Anna f 58,\nKarin f 61.\n\n",
    "structured": {
        "1": {
            "full_name": "ERICSON, E HUGO",
            "location": "Aspen",
            "occupation": "direktör",
            "birth_details": {
                "date": "10/05/1914",
                "place": "Hemsjö, Älvsborgs län",
                "parents": "lantbr Anders E o Maria Andersson"
            },
            "education": [
                {
                    "degree": "hdlssk",
                    "year": "NULL",
                    "institution": "NULL"
                }
            ],
            "career": [
                {
                    "position": "verkst dir",
                    "years": {
                        "start_year": 1932,
                        "end_year": 1965
                    },
                    "organization": "Hugo Ericson ab Gbg"
                }
            ],
            "family": {
                "spouse": "Irma Svensson",
                "marriage_year": "1938",
                "children": [
                    {
                        "name": "Margaretha",
                        "birth_year": "1940"
                    },
                    {
                        "name": "Rigmor",
                        "birth_year": "1943"
                    },
                    {
                        "name": "Barbro",
                        "birth_year": "1946"
                    },
                    {
                        "name": "Gunilla",
                        "birth_year": "1950"
                    },
                    {
                        "name": "Annika",
                        "birth_year": "1954"
                    }
                ]
            }
        },
        "2": {
            "full_name": "ERIKSSON, JAN-OLOF",
            "location": "Linköping",
            "occupation": "civilingenjör",
            "birth_details": {
                "date": "07/12/1929",
                "place": "Trollhättan",
                "parents": "John E o Rakel Törnqvist"
            },
            "education": [
                {
                    "degree": "CTH",
                    "year": "1954",
                    "institution": "NULL"
                }
            ],
            "career": [
                {
                    "position": "ing",
                    "years": {
                        "start_year": 1954,
                        "end_year": 1956
                    },
                    "organization": "ab Bofors Sthlm"
                },
                {
                    "position": "NULL",
                    "years": {
                        "start_year": 1958,
                        "end_year": "NULL"
                    },
                    "organization": "Saab Linköping"
                }
            ],
            "family": {
                "spouse": "Gunvor Ekman",
                "marriage_year": "1961",
                "children": [
                    {
                        "name": "Ann",
                        "birth_year": "1962"
                    }
                ]
            }
        },
        "3": {
            "full_name": "ERIKSSON, JOHANNES",
            "location": "Göteborg",
            "occupation": "byggmästare",
            "birth_details": {
                "date": "18/10/1886",
                "place": "Sätila, Älvsborgs län",
                "parents": "slaktare Johan E o Anna Olofsson Lärk"
            },
            "education": [
                {
                    "degree": "NULL",
                    "year": "1914-1918",
                    "institution": "Slöjdfören:s sk"
                }
            ],
            "career": [
                {
                    "position": "verkm byggn :firman",
                    "years": {
                        "start_year": 1918,
                        "end_year": 1924
                    },
                    "organization": "Bröd Persson"
                },
                {
                    "position": "inneh eg byggn :firma",
                    "years": {
                        "start_year": 1924,
                        "end_year": "NULL"
                    },
                    "organization": "NULL"
                }
            ],
            "family": {
                "spouse": "Julia Rundström",
                "marriage_year": "1916",
                "children": [
                    {
                        "name": "Inga-Lill",
                        "birth_year": "1917"
                    },
                    {
                        "name": "Ann-Kerstin",
                        "birth_year": "1921"
                    }
                ]
            },
            "hobbies": [
                "blommor"
            ]
        },
        "4": {
            "full_name": "ERIKSSON, K JONAS V",
            "location": "N Kedum",
            "occupation": "komminister",
            "birth_details": {
                "date": "28/04/1929",
                "place": "Björsäter, Skaraborgs län",
                "parents": "NULL"
            },
            "education": [
                {
                    "degree": "Stud:ex",
                    "year": "1950",
                    "institution": "Upps"
                },
                {
                    "degree": "teol kand",
                    "year": "1957",
                    "institution": "Lund"
                }
            ],
            "career": [
                {
                    "position": "kyrkoadj",
                    "years": {
                        "start_year": 1958,
                        "end_year": 1959
                    },
                    "organization": "Lyrestad"
                },
                {
                    "position": "tf kommin",
                    "years": {
                        "start_year": 1959,
                        "end_year": 1962
                    },
                    "organization": "Husaby"
                },
                {
                    "position": "kyrkoadj",
                    "years": {
                        "start_year": 1962,
                        "end_year": "NULL"
                    },
                    "organization": "Töreboda"
                },
                {
                    "position": "kommin",
                    "years": {
                        "start_year": 1963,
                        "end_year": "NULL"
                    },
                    "organization": "Örslösa"
                }
            ],
            "family": {
                "spouse": "org Britta Ragnarsdtr",
                "marriage_year": "1956",
                "children": [
                    {
                        "name": "Anna",
                        "birth_year": "1958"
                    },
                    {
                        "name": "Karin",
                        "birth_year": "1961"
                    }
                ]
            },
            "hobbies": [
                "musik"
            ]
        }
    }
}