{
    "original": "ENGEL, ERIK, tandläkare, Borås, f i\nEskilstuna 22/4/24 av diploming Erwin\nE o lär Magda Lundholm.\nStud:ex Sthlm 43, stud StHS 43-44,\ntandl:ex Sthlm 49, distr:tandl\nSmålands-stenar 49, priv :prakt Rävlanda 50, vik\nBorås 55, priv :prakt Borås sed 59.\n-Hobbies: arkeologi, golf.\nGift 48 m Gun Hultén f 26, dtr t köpm\nJ A H o Agnes Andersson. - Barn:\nThomas f 48, Gunilla f 50.\n\nENGEL, E GÖSTA G, direktör,\nMotala, f i Sthlm 2/7/03 av disp Georg E o\nAnna Westerlund.\n\nStud:ex 22, Schartaus hdlI 24,\nförsäljn:-ch Falu yllefabr ab 26, verkst dir\nSmålands yllefabr ab 28, verkst dir\nEngel-fabrikerna ab sed 39. - Styr:ordf Sv\nyllefabr :f ören 55-60, led centralstyr\nÖstergötl ensk bk 53-60. - Utm: RVO,\nKFinlLO, RFinlVROlkl.\n\nGift 26 m Inez Tidstrand f 04, dtr t\nfabr Axel T o Ellen Berg.\n\nENGELBRECHT, K HARRY,\ndirektör, Tidan, f i Skövde W/9/91 av ing\nAlbin E o Gunilla Yourstone.\nStat el :tekn facksk 22, ing Asea 23,\nSouthern Sierras Power Co Riverside Calif\nUSA 26, driftsing Kraft ab\nNykvarn-Tidan 31, verkst dir där. - Styr:led Kraft\nab Nykvarn-Tidan, Skarab l elektr fören,\nTidans regleringsfören. - Utm: ProPGM.\nGift 28 m Monna Söderberg f 98, dtr t\nHerman S o Lisa Andersson.\n\nENGELBREKTSON, HJÖRDIS I, by-\n\nrådirektör, Gbg, f i Gbg 14/10/20 av dir\nGustaf E o Alma Ericson.\nStud:ex Lund 48, jur kand Lund 55, anst\nlandsfogden i Gbgs o Boh l 56, länsstyr\n56-57, tf byrådir länsskolndn Gbgs o\nBoh l 62-64, Gbgs univ 57-62, eo\nbyrådir där sed 64.\n\nENGELLAU,  GUNNAR L, direktör,\n\nGbg, f i Sthlm U/ll/07 av adv Ivar E\no Hulda Lindequist.\n\nStud:ex 26, KTH 31, anst SJ 32-34, ch\nplanerings- o tidsstudieavd ab Motala\nverkstad 35, inköps- o försäljn :ch där\n37-39, tekn försäljn :ch ab Electrolux\nSthlm o Motala 39-43, verkst dir Sv\nflygmotor ab 43-56, ab Volvo sed 56.\n-Styr:ordf ab Bolinder-Munktell,\nKöpings mek verkstads ab, Volvo\nKöpingverken ab, ab Volvo Penta, Försäkr ab\nVolvia, Sv flygmotor ab, Automobiles\nVolvo SA Lausanne, Volvo (Canada)\nLtd Montreal, OY Volvo Auto ab\nH-fors, Volvo Inc Rockleigh USA, Volvo\nGmbH Frankfurt, styr :led ab Volvo,\nSkand bkn, Park Avenue Hotel ab,\nPripp-Bryggerierna ab, ab Electrolux,\nab Bahco, SAE o Sv:e-Amerika-stift.\n-Utm: KVOlkl.\n\nGift 33 m Margit Höckert f 11, dtr t\nreg:läk Fritz H o Ingrid Hallberg.\n-Barn: John-Jakob f 34, Christina f 36,\nBirgitta f 39, Margita f 41, Caroline\nf 43.\n\n",
    "structured": {
        "0": {
            "full_name": "ENGEL, ERIK",
            "location": "Borås",
            "occupation": "tandläkare",
            "birth_details": {
                "date": "22/4/1924",
                "place": "Eskilstuna",
                "parents": "diplomingenjör Erwin E och lärare Magda Lundholm"
            },
            "education": [
                {
                    "degree": "Stud:ex",
                    "year": "1943",
                    "institution": "Stockholm"
                },
                {
                    "degree": "StHS",
                    "year": "1943-1944",
                    "institution": "Sveriges Tandläkarhögskola"
                },
                {
                    "degree": "tandläk:ex",
                    "year": "1949",
                    "institution": "Stockholm"
                }
            ],
            "career": [
                {
                    "position": "distr:tandl",
                    "years": {
                        "start_year": 1949,
                        "end_year": 1949
                    },
                    "organization": "Smålands-stenar"
                },
                {
                    "position": "priv :prakt",
                    "years": {
                        "start_year": 1950,
                        "end_year": 1955
                    },
                    "organization": "Rävlanda"
                },
                {
                    "position": "vik",
                    "years": {
                        "start_year": 1955,
                        "end_year": 1959
                    },
                    "organization": "Borås"
                },
                {
                    "position": "priv :prakt",
                    "years": {
                        "start_year": 1959
                    },
                    "organization": "Borås"
                }
            ],
            "family": {
                "spouse": "Gun Hultén",
                "marriage_year": "1948",
                "children": [
                    {
                        "name": "Thomas",
                        "birth_year": "1948"
                    },
                    {
                        "name": "Gunilla",
                        "birth_year": "1950"
                    }
                ]
            },
            "hobbies": [
                "arkeologi",
                "golf"
            ]
        },
        "1": {
            "full_name": "ENGEL, E GÖSTA G",
            "location": "Motala",
            "occupation": "direktör",
            "birth_details": {
                "date": "2/7/1903",
                "place": "Stockholm",
                "parents": "disp Georg E och Anna Westerlund"
            },
            "education": [
                {
                    "degree": "Stud:ex",
                    "year": "1922",
                    "institution": "Stockholm"
                },
                {
                    "degree": "Schartaus hdlI",
                    "year": "1924",
                    "institution": "Schartaus Handelsinstitut"
                }
            ],
            "career": [
                {
                    "position": "försäljn:-ch",
                    "years": {
                        "start_year": 1926
                    },
                    "organization": "Falu yllefabr ab"
                },
                {
                    "position": "verkst dir",
                    "years": {
                        "start_year": 1928
                    },
                    "organization": "Smålands yllefabr ab"
                },
                {
                    "position": "verkst dir",
                    "years": {
                        "start_year": 1939
                    },
                    "organization": "Engel-fabrikerna ab"
                }
            ],
            "honorary_titles": [
                {
                    "title": "RVO",
                    "institution": null,
                    "year": null
                },
                {
                    "title": "KFinlLO",
                    "institution": null,
                    "year": null
                },
                {
                    "title": "RFinlVROlkl",
                    "institution": null,
                    "year": null
                }
            ]
        },
        "2": {
            "full_name": "ENGELBRECHT, K HARRY",
            "location": "Tidan",
            "occupation": "direktör",
            "birth_details": {
                "date": "W/9/1891",
                "place": "Skövde",
                "parents": "ing Albin E och Gunilla Yourstone"
            },
            "education": [
                {
                    "degree": "Stat el :tekn facksk",
                    "year": "1922",
                    "institution": null
                },
                {
                    "degree": "ing",
                    "year": "1923",
                    "institution": "Asea"
                }
            ],
            "career": [
                {
                    "position": "driftsing",
                    "years": {
                        "start_year": 1931
                    },
                    "organization": "Kraft ab Nykvarn-Tidan"
                },
                {
                    "position": "verkst dir",
                    "years": {
                        "start_year": 1931
                    },
                    "organization": "Kraft ab Nykvarn-Tidan"
                }
            ],
            "honorary_titles": [
                {
                    "title": "ProPGM",
                    "institution": null,
                    "year": null
                }
            ]
        },
        "3": {
            "full_name": "ENGELBREKTSON, HJÖRDIS I",
            "location": "Gbg",
            "occupation": "byrådirektör",
            "birth_details": {
                "date": "14/10/1920",
                "place": "Göteborg",
                "parents": "dir Gustaf E och Alma Ericson"
            },
            "education": [
                {
                    "degree": "Stud:ex",
                    "year": "1948",
                    "institution": "Lund"
                },
                {
                    "degree": "jur kand",
                    "year": "1955",
                    "institution": "Lund"
                }
            ],
            "career": [
                {
                    "position": "anst",
                    "years": {
                        "start_year": 1956
                    },
                    "organization": "landsfogden i Gbgs o Boh l"
                },
                {
                    "position": "länsstyr",
                    "years": {
                        "start_year": 1956,
                        "end_year": 1957
                    },
                    "organization": null
                },
                {
                    "position": "tf byrådir",
                    "years": {
                        "start_year": 1962,
                        "end_year": 1964
                    },
                    "organization": "länsskolndn Gbgs o Boh l"
                },
                {
                    "position": "eo byrådir",
                    "years": {
                        "start_year": 1964
                    },
                    "organization": "Gbgs univ"
                }
            ]
        },
        "4": {
            "full_name": "ENGELLAU, GUNNAR L",
            "location": "Gbg",
            "occupation": "direktör",
            "birth_details": {
                "date": "U/11/1907",
                "place": "Stockholm",
                "parents": "adv Ivar E och Hulda Lindequist"
            },
            "education": [
                {
                    "degree": "Stud:ex",
                    "year": "1926",
                    "institution": null
                },
                {
                    "degree": null,
                    "year": "1931",
                    "institution": "Kungliga Tekniska Högskolan"
                }
            ],
            "career": [
                {
                    "position": "anst",
                    "years": {
                        "start_year": 1932,
                        "end_year": 1934
                    },
                    "organization": "SJ"
                },
                {
                    "position": "ch planerings- o tidsstudieavd",
                    "years": {
                        "start_year": 1935
                    },
                    "organization": "Motala verkstad"
                },
                {
                    "position": "inköps- o försäljn :ch",
                    "years": {
                        "start_year": 1937,
                        "end_year": 1939
                    },
                    "organization": "Electrolux Sthlm o Motala"
                },
                {
                    "position": "tekn försäljn :ch",
                    "years": {
                        "start_year": 1939,
                        "end_year": 1943
                    },
                    "organization": "ab Electrolux"
                },
                {
                    "position": "verkst dir",
                    "years": {
                        "start_year": 1943,
                        "end_year": 1956
                    },
                    "organization": "Sv flygmotor ab"
                },
                {
                    "position": null,
                    "years": {
                        "start_year": 1956
                    },
                    "organization": "ab Volvo"
                }
            ],
            "family": {
                "spouse": "Margit Höckert",
                "marriage_year": "1933",
                "children": [
                    {
                        "name": "John-Jakob",
                        "birth_year": "1934"
                    },
                    {
                        "name": "Christina",
                        "birth_year": "1936"
                    },
                    {
                        "name": "Birgitta",
                        "birth_year": "1939"
                    },
                    {
                        "name": "Margita",
                        "birth_year": "1941"
                    },
                    {
                        "name": "Caroline",
                        "birth_year": "1943"
                    }
                ]
            }
        }
    }
}