{
    "original": "ULVENHEIM, INGVAR,\nfastighetsdirektör, Askersund, f i Kalmar 29/1/24\nav disp Fredrik Nilsson o Alma\nJohansson.\n\nDriftsled Askersunds bryggeri ab 50, eg\nbyggn :verksamh sed 58, inneh av Hus\nBygge Askersund. - Styr :led Askersunds\nhotell ab sed 58, Skand bkns avd :kont\nAskersund sed 60, led Stadsfullm, DK,\nbyggn:nd, tax:nd, pensionärshemstyr.\n-Medl Rotary. - Hobby: sport.\n\nUNDEN, NILS G, fd överjägmästare,\nVallentuna, f i Sthlm 7/4/96 av kassör\nGustaf U o Alma Bryzelli.\nStud:ex 14, res:off:ex 16, underlöjtn A 8\n19, avsk 24; SkHS 20, jägm\nKorpilombolo revir 34, överjägm Ö Norrb distr\n40-61. - Ordf Kalix m fi älvars\nflottn:-fören:ar, styr:led Norrb\nvirkesmätn:-fören, v ordf stiftsndn t 61. - Utm:\nKNO, KFinlLO, SvJägFGM.\nGift 22 m Ingegerd Paulsson f 98, dtr t\nkamr Nils P o Anna Andersson. - Barn:\nInger f 25.\n\nUNDHAGEN, CARL-GUSTAF, fil dr,\ndocent, Uppsala, f i Ånge, Västernorrl l,\n6/1/26 av köpm Petrus U o Linnea\nCarlberg.\n\nStud:ex Skara 46, fil kand o fil mag\nUpps 50, fil lic 57, fil dr o doc i\nlatinska språket o litteraturen Upps univ 60,\ndoc Lunds univ sed 64. - Förest Upps\nstud :kårs feriesk Västerås 53-63, tid\nlo-kalred SFS avhandl :reg samt led Upps\nstud :kårs undervisn :utsk o Upps univ:s\nundervisn:nd. - Skr: Birger Gregersons\n\nBirgiüta-officium (drsavh 60), ett flert\nvetensk art rör medeltidslatin o tidn:art\nom Birgitta o Linné.\nGift 1) 47-58 m småskollär Margareta\nOlsson f 25, dtr t sånglär Folke O o Elsa\nThyresson, 2) 61 m fil mag Lydia\nNeos-tus f 34, diflr t Richard N o Elisabeth\nTiido. - Barn: i l:a akt Mikael f 47,\nBirgit|ta f 55, i 2:a akt Thomas f 63.\n\n",
    "structured": {
        "0": {
            "full_name": "ULVENHEIM, INGVAR",
            "location": "Askersund",
            "occupation": "fastighetsdirektör",
            "birth_details": {
                "date": "29/01/1924",
                "place": "Kalmar",
                "parents": "disp Fredrik Nilsson o Alma Johansson"
            },
            "education": [
                {
                    "degree": "Driftsled",
                    "year": "1950",
                    "institution": "Askersunds bryggeri ab"
                },
                {
                    "degree": "Byggn:verksam",
                    "year": "1958",
                    "institution": "eg byggn :verksam"
                }
            ],
            "career": [
                {
                    "position": "Styr :led",
                    "years": {
                        "start_year": 1958,
                        "end_year": 2021
                    },
                    "organization": "Askersunds hotell ab"
                },
                {
                    "position": "Styr :led",
                    "years": {
                        "start_year": 1960,
                        "end_year": 2021
                    },
                    "organization": "Skand bkns avd :kont Askersund"
                }
            ],
            "family": {
                "spouse": "NULL",
                "marriage_year": "NULL",
                "children": []
            },
            "publications": [],
            "community_involvement": [],
            "board_memberships": [],
            "honorary_titles": [],
            "hobbies": [
                "sport"
            ]
        },
        "1": {
            "full_name": "UNDEN, NILS G",
            "location": "Vallentuna",
            "occupation": "fd överjägmästare",
            "birth_details": {
                "date": "7/4/1896",
                "place": "Sthlm",
                "parents": "kassör Gustaf U o Alma Bryzelli"
            },
            "education": [
                {
                    "degree": "Stud:ex",
                    "year": "1914",
                    "institution": "NULL"
                },
                {
                    "degree": "res:off:ex",
                    "year": "1916",
                    "institution": "NULL"
                },
                {
                    "degree": "underlöjtn A",
                    "year": "1919",
                    "institution": "NULL"
                },
                {
                    "degree": "SkHS",
                    "year": "1920",
                    "institution": "NULL"
                },
                {
                    "degree": "jägm",
                    "year": "1920",
                    "institution": "Korpilombolo revir"
                }
            ],
            "career": [
                {
                    "position": "överjägm",
                    "years": {
                        "start_year": 1940,
                        "end_year": 1961
                    },
                    "organization": "Ö Norrb distr"
                }
            ],
            "family": {
                "spouse": "Ingegerd Paulsson",
                "marriage_year": "1922",
                "children": [
                    {
                        "name": "Inger",
                        "birth_year": "1925"
                    }
                ]
            },
            "publications": [],
            "community_involvement": [],
            "board_memberships": [],
            "honorary_titles": [
                "KNO",
                "KFinlLO",
                "SvJägFGM"
            ],
            "hobbies": []
        },
        "2": {
            "full_name": "UNDHAGEN, CARL-GUSTAF",
            "location": "Uppsala",
            "occupation": "fil dr, docent",
            "birth_details": {
                "date": "6/1/1926",
                "place": "Ånge, Västernorrl l",
                "parents": "köpm Petrus U o Linnea Carlberg"
            },
            "education": [
                {
                    "degree": "Stud:ex",
                    "year": "1946",
                    "institution": "Skara"
                },
                {
                    "degree": "fil kand",
                    "year": "1950",
                    "institution": "Upps"
                },
                {
                    "degree": "fil mag",
                    "year": "1950",
                    "institution": "Upps"
                },
                {
                    "degree": "fil lic",
                    "year": "1957",
                    "institution": "Upps univ"
                },
                {
                    "degree": "fil dr",
                    "year": "1960",
                    "institution": "Upps univ"
                }
            ],
            "career": [
                {
                    "position": "doc",
                    "years": {
                        "start_year": 1964,
                        "end_year": 2021
                    },
                    "organization": "Lunds univ"
                }
            ],
            "family": {
                "spouse": "Lydia Neostus",
                "marriage_year": "1961",
                "children": [
                    {
                        "name": "Mikael",
                        "birth_year": "1947"
                    },
                    {
                        "name": "Birgitta",
                        "birth_year": "1955"
                    },
                    {
                        "name": "Thomas",
                        "birth_year": "1963"
                    }
                ]
            },
            "publications": [
                {
                    "title": "Birger Gregersons Birgiüta-officium",
                    "year": "1960",
                    "type": "drsavh"
                }
            ],
            "community_involvement": [
                {
                    "role": "tid lokalred SFS avhandl",
                    "organization": "NULL",
                    "years": "NULL"
                },
                {
                    "role": "led Upps stud :kårs undervisn :utsk",
                    "organization": "NULL",
                    "years": "NULL"
                },
                {
                    "role": "Upps univ:s undervisn:nd",
                    "organization": "NULL",
                    "years": "NULL"
                }
            ],
            "board_memberships": [],
            "honorary_titles": [],
            "hobbies": []
        }
    }
}