{
    "original": "HESSELBOM, KNUT E, elverkschef,\n\nÅmål, f i Åmål 14/9/05 av\nlokputs:för-man C H H o Karin Grund.\nIng:ex stat el:tekn facksk 41, driftsing\nÅmåls elverk 42, ch där sed 53. -\nStadsfullm 35-42 o sed 59 m fi kommun\nupp-dr, FK 46-58 (s), landst:man sed 63, led\nlantbr:nd sed 64, styr:ordf Forsane\nyr-kessk 53-63, ordf skolstyr sed 58.\nGift 34 m Astrid Lund f 07, dtr t\nstenhuggare K S L o Viktoria Matsson.\n-Barn: Kerstin f 42.\n\nHESSELGREN, OVE J, länspolischef,\n\nVäxjö, f i Malmö 7/3/22 av häradsh Ove\nH o Malin Lundblad.\nStud:ex Sthlm 42, jur kand 49,\npolisen:-kurs 56; tingstjg S Rosl o Solna doms\n50-52, tjg Svea hovr 52, landsfogdeass\n53-64, länspolisch Kronob l sed 65.\n-Hobby: golf.\n\nGift 55 m Inga Andersson f 35, dtr t\ndir Gösta A o Inez Neuman. - Barn:\nLärs-Ove f 55, Jan f 58.\nHESSELMARK, BENGT, godsägare,\nSt Levene, f i Levene, Skarab l, 21/4/12\nav godsäg Johan Johansson o Maria\nFornander.\n\nAxevalla folkhögsk 30-31, Hvilans\nlant-m:sk 34, ag Levene egend St Levene sed\n41. - Hobbies: jakt, jaktvård.\nGift 42 m Elsa Ekberg f 21, dtr t\nryttm Bertil E o Elsa Hård af\nSegerstad. - Barn: Lärs-Johan f 44, Stig f 45.\n\nHESSELROTH, A ROLF,\nförsäljningschef, Gbg, f i Malmö 23/12/17.\nHermods hdlI 35, befrakt\nskeppsmäkl:-f:orna Ludvig Svensson &amp; Co samt H\nSandström Malmö 35-37, Baltic\nShip-ping Co Köpenh 37, fartygskontr\nVV:-styr 40, insp Försäkr ab Haand i Haand\no National Malmö 41-42, Hansa Malmö\no Landskrona 42-44, ch Fenix-Heimdall\nMalmö 44, distr:ch Thulebol 50,\nsjökontaktman Thule Sthlm 55, distr :ch\nThules avd:kont Nordstaden Gbg 58,\nförsäljn:ch Skandiakonc centrumkont\nGbg sed 65. - Utm: ThuleSM. - Hobby:\nsegling.\n\nGift 2) 58 m Lilian Passberg f 32, dtr t\ndistr:ch Gunnar P o Ruth Nilsson.\n-Barn: i l:a akt Christi f 43, Charlotte\nf 52, i 2:a akt Rolf f 59.\n\n",
    "structured": {
        "0": {
            "full_name": "Knut E Hesselbom",
            "location": "Åmål",
            "occupation": "elverkschef",
            "birth_details": {
                "date": "14/09/1905",
                "place": "Åmål",
                "parents": "lokputs:för-man C H H o Karin Grund"
            },
            "education": [
                {
                    "degree": "stat el:tekn facksk",
                    "year": "1941",
                    "institution": "NULL"
                }
            ],
            "career": [
                {
                    "position": "driftsing Åmåls elverk",
                    "years": {
                        "start_year": 1942,
                        "end_year": 1953
                    },
                    "organization": "NULL"
                }
            ],
            "family": {
                "spouse": "Astrid Lund",
                "marriage_year": "1934",
                "children": [
                    {
                        "name": "Kerstin",
                        "birth_year": "1942"
                    }
                ]
            }
        },
        "1": {
            "full_name": "Ove J Hesselgren",
            "location": "Växjö",
            "occupation": "länspolischef",
            "birth_details": {
                "date": "07/03/1922",
                "place": "Malmö",
                "parents": "häradsh Ove H o Malin Lundblad"
            },
            "education": [
                {
                    "degree": "Stud",
                    "year": "1942",
                    "institution": "NULL"
                },
                {
                    "degree": "jur kand",
                    "year": "1949",
                    "institution": "NULL"
                },
                {
                    "degree": "polisen:-kurs",
                    "year": "1956",
                    "institution": "NULL"
                }
            ],
            "career": [
                {
                    "position": "tingstjg S Rosl o Solna doms",
                    "years": {
                        "start_year": 1950,
                        "end_year": 1952
                    },
                    "organization": "NULL"
                },
                {
                    "position": "tjg Svea hovr",
                    "years": {
                        "start_year": 1952,
                        "end_year": 1953
                    },
                    "organization": "NULL"
                },
                {
                    "position": "landsfogdeass",
                    "years": {
                        "start_year": 1953,
                        "end_year": 1964
                    },
                    "organization": "NULL"
                },
                {
                    "position": "länspolisch Kronob l",
                    "years": {
                        "start_year": 1965,
                        "end_year": null
                    },
                    "organization": "NULL"
                }
            ],
            "family": {
                "spouse": "Inga Andersson",
                "marriage_year": "1955",
                "children": [
                    {
                        "name": "Lärs-Ove",
                        "birth_year": "1955"
                    },
                    {
                        "name": "Jan",
                        "birth_year": "1958"
                    }
                ]
            },
            "hobbies": [
                "golf"
            ]
        },
        "2": {
            "full_name": "Bengt Hesslemark",
            "location": "St Levene",
            "occupation": "godsägare",
            "birth_details": {
                "date": "21/04/1912",
                "place": "Levene, Skarab l",
                "parents": "godsäg Johan Johansson o Maria Fornander"
            },
            "education": [
                {
                    "degree": "Axevalla folkhögsk",
                    "year": "1930-1931",
                    "institution": "NULL"
                },
                {
                    "degree": "Hvilans lant-m:sk",
                    "year": "1934",
                    "institution": "NULL"
                }
            ],
            "career": [
                {
                    "position": "ag Levene egend St Levene",
                    "years": {
                        "start_year": 1941,
                        "end_year": null
                    },
                    "organization": "NULL"
                }
            ],
            "family": {
                "spouse": "Elsa Ekberg",
                "marriage_year": "1942",
                "children": [
                    {
                        "name": "Lärs-Johan",
                        "birth_year": "1944"
                    },
                    {
                        "name": "Stig",
                        "birth_year": "1945"
                    }
                ]
            },
            "hobbies": [
                "jakt",
                "jaktvård"
            ]
        },
        "3": {
            "full_name": "A Rolf Hesslebroth",
            "location": "Gbg",
            "occupation": "försäljningschef",
            "birth_details": {
                "date": "23/12/1917",
                "place": "Malmö",
                "parents": "NULL"
            },
            "education": [
                {
                    "degree": "Hermods hdlI",
                    "year": "1935",
                    "institution": "NULL"
                }
            ],
            "career": [
                {
                    "position": "bfrakt skeppsmäkl:-f:orna Ludvig Svensson & Co samt H Sandström",
                    "years": {
                        "start_year": 1935,
                        "end_year": 1937
                    },
                    "organization": "NULL"
                },
                {
                    "position": "Baltic Shipping Co Köpenh",
                    "years": {
                        "start_year": 1937,
                        "end_year": null
                    },
                    "organization": "NULL"
                },
                {
                    "position": "fartygskontr VV:-styr",
                    "years": {
                        "start_year": 1940,
                        "end_year": null
                    },
                    "organization": "NULL"
                },
                {
                    "position": "insp Försäkr ab Haand i Haand o National Malmö",
                    "years": {
                        "start_year": 1941,
                        "end_year": 1942
                    },
                    "organization": "NULL"
                },
                {
                    "position": "Hansa Malmö o Landskrona",
                    "years": {
                        "start_year": 1942,
                        "end_year": 1944
                    },
                    "organization": "NULL"
                },
                {
                    "position": "ch Fenix-Heimdall Malmö",
                    "years": {
                        "start_year": 1944,
                        "end_year": null
                    },
                    "organization": "NULL"
                },
                {
                    "position": "distr:ch Thulebol",
                    "years": {
                        "start_year": 1950,
                        "end_year": null
                    },
                    "organization": "NULL"
                },
                {
                    "position": "sjökontaktman Thule Sthlm",
                    "years": {
                        "start_year": 1955,
                        "end_year": null
                    },
                    "organization": "NULL"
                },
                {
                    "position": "distr :ch Thules avd:kont Nordstaden Gbg",
                    "years": {
                        "start_year": 1958,
                        "end_year": null
                    },
                    "organization": "NULL"
                },
                {
                    "position": "försäljn:ch Skandiakonc centrumkont Gbg",
                    "years": {
                        "start_year": 1965,
                        "end_year": null
                    },
                    "organization": "NULL"
                }
            ],
            "family": {
                "spouse": null,
                "marriage_year": null,
                "children": [
                    {
                        "name": "Christi",
                        "birth_year": "1943"
                    },
                    {
                        "name": "Charlotte",
                        "birth_year": "1952"
                    },
                    {
                        "name": "Rolf",
                        "birth_year": "1959"
                    }
                ]
            },
            "hobbies": [
                "segling"
            ]
        }
    }
}