{
    "original": "HESSLANDER, INGRID A,\nförfattarinna, Jönköping, f i Gbg 13/5/07 av\nsjökapt Johan Hallberg o Adéle\nBerglund.\n\nStud:ex 27, ex h lär:nesem Gbg 31,\nkortare vik:förordn 31-44, ämneslär\nsam-realsk Gislaved 44-53, Jönkpgs prakt\nrealsk sed 53. - Medl Sv:es förf :f ören\nsed 52, sekr Smal förf :sällsk sed 61.\n-Skr: romanerna Grönt gräs på rot (45),\nGiftomans samtycke (52), Den heta\nsommaren (57), Jordiska fångsel (60) m fi.\nGift 37 m fil mag John Hesslander\nf 02.\n\nHESSLE, CHRISTIAN W, fil dr, fd\nbyråchef, Gbg, f å Hjelmared, Älvsb l,\n17/3/90 av godsäg Waldemar H o Gerda\nHolmgren.\n\nFil dr Upps 17, forskn :resa\nSöderhavsöarna 17-18, doc i zoologi Upps 18-21,\nfiskeristip 19, fiskeriintend 30, e föredr\nlantbr :styr 38, byrådir där 41, byråch\nfiskeristyr 48-57. - Sakk utredn inom\njust :dep 31, led strömmingshdlsutredn\n33-34, fiskehamnsutredn 44,\nfiskhdlsut-redn 51, ordf stat fiskend 37-42,\nfiskeri-utredn 45. - Skr i zoologi, fiske o\nfis-keribiologi. - Utm: RNO, RVO, RDDO.\nGift 21 m Sonja Larsson f 99, dtr t\nbankdir Pontus L o Anna Ericsson.\n-Barn: Valdemar f 23.\n\nHESSLEFORS, J ARTHUR E,\nkyrkoherde, Nossebro, f i Ryda, Skarab l,\n4/12/08 av hemm:äg Karl Persson o\nMatilda Andersdotter.\nTeol kand Lund 38, vik kommin Saleby\n39, past:adj Vänersborg 39-45, kommin\nGärdhem 45-63, pred Restads sjh 42-62,\nkyrkoh Främmestad o Bäreberg sed 63.\nGift 38 m fil kand Margareta Nelson\nf 14, dtr t postmast James N o Elsa\nJuhlin. - Barn: Gertrud f 39, Ingmar f\n41, Elisabeth f 44, Helge f 47.\n\nHESSLER, ÅKE O, major, Jönköping,\nf i Lund 23/2/18 av insp Per H o\nKerstin Johansson.\n\nStud:ex Eslöv 37, Off:ex 40, KHS 53-55.\n- Kapt A 3 48, ast 57, major A l 58, ch\nart kadett- o asp :sk 60, major A 6 sed\n\n64.   -  Utm: RSO, N Skånska bfubSM,\nart skytteM. - Hobbies: jakt, fiske, sport.\nGift 44 m Ingegerd Nilsson f 18. - Barn:\nAgneta f 45, Christina f 48.\n\n",
    "structured": {
        "0": {
            "full_name": "HESSLANDER, INGRID A",
            "location": "Jönköping",
            "occupation": "författarinna",
            "birth_details": {
                "date": "13/05/1907",
                "place": "Göteborg",
                "parents": "sjökapt Johan Hallberg o Adéle Berglund"
            },
            "education": [
                {
                    "degree": "Stud:ex",
                    "year": "1927",
                    "institution": "NULL"
                },
                {
                    "degree": "ex h lär:nesem",
                    "year": "1931",
                    "institution": "Göteborg"
                }
            ],
            "career": [
                {
                    "position": "kortare vik:förordn",
                    "years": {
                        "start_year": 1931,
                        "end_year": 1944
                    },
                    "organization": "NULL"
                },
                {
                    "position": "ämneslär sam-realsk",
                    "years": {
                        "start_year": 1944,
                        "end_year": 1953
                    },
                    "organization": "Gislaved"
                },
                {
                    "position": "Jönkpgs prakt realsk",
                    "years": {
                        "start_year": 1953,
                        "end_year": "NULL"
                    },
                    "organization": "NULL"
                }
            ],
            "family": {
                "spouse": "fil mag John Hesslander",
                "marriage_year": "1937",
                "children": [],
                "NULL": "NULL"
            }
        },
        "1": {
            "full_name": "HESSLE, CHRISTIAN W",
            "location": "Göteborg",
            "occupation": "fil dr, fd byråchef",
            "birth_details": {
                "date": "17/03/1890",
                "place": "Hjelmared, Älvsborgs län",
                "parents": "godsäg Waldemar H o Gerda Holmgren"
            },
            "education": [],
            "career": [
                {
                    "position": "forskning Söderhavsöarna",
                    "years": {
                        "start_year": 1917,
                        "end_year": 1918
                    },
                    "organization": "NULL"
                },
                {
                    "position": "doc i zoologi",
                    "years": {
                        "start_year": 1918,
                        "end_year": 1921
                    },
                    "organization": "Upps"
                },
                {
                    "position": "fiskeristip",
                    "years": {
                        "start_year": 1919,
                        "end_year": "NULL"
                    },
                    "organization": "NULL"
                },
                {
                    "position": "fiskeriintend",
                    "years": {
                        "start_year": 1930,
                        "end_year": "NULL"
                    },
                    "organization": "NULL"
                },
                {
                    "position": "föredr lantbr :styr",
                    "years": {
                        "start_year": 1938,
                        "end_year": "NULL"
                    },
                    "organization": "NULL"
                },
                {
                    "position": "byrådir",
                    "years": {
                        "start_year": 1941,
                        "end_year": "NULL"
                    },
                    "organization": "NULL"
                },
                {
                    "position": "byråch fiskeristyr",
                    "years": {
                        "start_year": 1948,
                        "end_year": 1957
                    },
                    "organization": "NULL"
                }
            ],
            "family": {
                "spouse": "Sonja Larsson",
                "marriage_year": "1921",
                "children": [
                    {
                        "name": "Valdemar",
                        "birth_year": "1923"
                    }
                ]
            }
        },
        "2": {
            "full_name": "HESSLEFORS, J ARTHUR E",
            "location": "Nossebro",
            "occupation": "kyrkoherde",
            "birth_details": {
                "date": "04/12/1908",
                "place": "Ryda, Skaraborgs län",
                "parents": "hemm:äg Karl Persson o Matilda Andersdotter"
            },
            "education": [
                {
                    "degree": "Teol kand",
                    "year": "1938",
                    "institution": "Lund"
                }
            ],
            "career": [
                {
                    "position": "vik kommin",
                    "years": {
                        "start_year": 1939,
                        "end_year": "NULL"
                    },
                    "organization": "Saleby"
                },
                {
                    "position": "past:adj",
                    "years": {
                        "start_year": 1939,
                        "end_year": 1945
                    },
                    "organization": "Vänersborg"
                },
                {
                    "position": "kommin",
                    "years": {
                        "start_year": 1945,
                        "end_year": 1963
                    },
                    "organization": "Gärdhem"
                }
            ],
            "family": {
                "spouse": "fil kand Margareta Nelson",
                "marriage_year": "1938",
                "children": [
                    {
                        "name": "Gertrud",
                        "birth_year": "1939"
                    },
                    {
                        "name": "Ingmar",
                        "birth_year": "1941"
                    },
                    {
                        "name": "Elisabeth",
                        "birth_year": "1944"
                    },
                    {
                        "name": "Helge",
                        "birth_year": "1947"
                    }
                ]
            }
        },
        "3": {
            "full_name": "HESSLER, ÅKE O",
            "location": "Jönköping",
            "occupation": "major",
            "birth_details": {
                "date": "23/02/1918",
                "place": "Lund",
                "parents": "insp Per H o Kerstin Johansson"
            },
            "education": [],
            "career": [
                {
                    "position": "Kapt A 3",
                    "years": {
                        "start_year": 1948,
                        "end_year": "NULL"
                    },
                    "organization": "NULL"
                },
                {
                    "position": "ast",
                    "years": {
                        "start_year": 1957,
                        "end_year": "NULL"
                    },
                    "organization": "NULL"
                },
                {
                    "position": "major A l",
                    "years": {
                        "start_year": 1958,
                        "end_year": "NULL"
                    },
                    "organization": "NULL"
                },
                {
                    "position": "ch art kadett- o asp :sk",
                    "years": {
                        "start_year": 1960,
                        "end_year": "NULL"
                    },
                    "organization": "NULL"
                },
                {
                    "position": "major A 6",
                    "years": {
                        "start_year": 1964,
                        "end_year": "NULL"
                    },
                    "organization": "NULL"
                }
            ],
            "family": {
                "spouse": "Ingegerd Nilsson",
                "marriage_year": "1944",
                "children": [
                    {
                        "name": "Agneta",
                        "birth_year": "1945"
                    },
                    {
                        "name": "Christina",
                        "birth_year": "1948"
                    }
                ]
            }
        }
    }
}