{
    "original": "HERMANSSON, SVEN P O,\növerläkare, Jönköping, f i Ratan, Jämtl l,\n27/1/01 av folkskollär Thure H o Emma\nMagnusson.\n\nStud:ex Upps 20, med lic Upps 29, olika\nläk:förordn 25-39, las:läk barnavd Umeå\nlas 40-44, överläk pediatr klin Jönkpgs\nlas sed 44. - Skr: upps i pediatrik.\nGift 36 m Ingegerd Pihl, dtr t kontr\n:-prost Torsten P o Elisabet Hultcrantz.\n-Barn: Bo f 37, Eva f 40.\n\nHERMELIN, CHRISTER S, friherre,\nlantmästare, Gripenberg, f i Ulfåsa,\nÖstergötl l, 5/9/19 av frih Gösta H o\nfrih:an Elin von Stapelmohr.\nUltuna lantbr:sk 40, Alnarps lantbr:inst\n45, anst Gripenbergs fideikommiss 53,\ndess inneh sed 57.\n\nGift 55 m Birgitta Jonas f 32, dtr t dir\nArvid J o h h. - Barn: Charlotte f 56,\nFredrik f 58.\n\nHERMELIN, S DAVID O, friherre, fd\n\növerste, Björsäter, f i Sthlm 22/7/97 av\növersten, frih Sven H o Anna Ohlsson.\nFänr livreg dragoner 17, bitr mil :attaché\nBryssel 22 o Paris 33, KHS 28-30, major\nK 4 40, öv :löjtn pansartr 42, överste kav\no ch K 4 47, sekundch K 3 51, fobef\nMalmö fö 54-57. - Utm: KSOlkl,\nRB-KrO, OffTunNI, DFrM, HvGM,\nCFB-SM, SLSM, SvBSSM, SCFftjtG, 4GM.\nGift 30 m Märtha Schenström f 09, dtr t\nmajor Eric S o Kjerstin Schnell. - Barn:\nDavid f 32, Johan f 37.\n\nHERMELIN, NILS G, friherre,\ngodsägare, Söderköping, f i Nykil,\nÖstergötl l, 8/9/11 av frih Robert H o Gunni\nPauli.\n\nRealsk, lantmannask, befalln:man Torsvi\ngård Enkpg 34-38, arrend Tomtaholm\n53-58, ag Bleckstad Söderkpg sed 38.\n-Ordf Hammarkinds häradsallm 57\n(styr:-led 48), v ordf Sv:es häradsallm förb 64,\nordf lokalavd av RLF 46-56 (styr:led\n39), led skogsv:styr Östergötl l 61.\n-Landst:man sed 56, ordf Stadsfullm\n59-64 (led sed 52), DK 64, led komm:fullm\n38-51. - Utm: HvGM, CFBSM,\nCen-tralförb Finl-Sv:e GM, FMMmsvosp,\nFMpbh, 2 FMK.\n\nGift 40 m Brita Östman f 19, dtr t\nciv:ing Artur Ö o Märta André. - Barn:\nAino f 41, Ulla f 43, Johan f 47,\nGunnar f 57.\n\n",
    "structured": {
        "0": {
            "full_name": "HERMANSSON, SVEN P O",
            "location": "Jönköping",
            "occupation": "överläkare",
            "birth_details": {
                "date": "27/01/1901",
                "place": "Ratan, Jämtlands län",
                "parents": "folkskollär Thure H o Emma Magnusson"
            },
            "education": [
                {
                    "degree": "Stud:ex",
                    "year": "1920",
                    "institution": "Upps"
                },
                {
                    "degree": "med lic",
                    "year": "1929",
                    "institution": "Upps"
                }
            ],
            "career": [
                {
                    "position": "las:läk barnavd",
                    "years": {
                        "start_year": 1940,
                        "end_year": 1944
                    },
                    "organization": "Umeå las"
                },
                {
                    "position": "överläk pediatr klin",
                    "years": {
                        "start_year": 1944
                    },
                    "organization": "Jönkpgs las"
                }
            ],
            "family": {
                "spouse": "Ingegerd Pihl",
                "marriage_year": "1936",
                "children": [
                    {
                        "name": "Bo",
                        "birth_year": "1937"
                    },
                    {
                        "name": "Eva",
                        "birth_year": "1940"
                    }
                ]
            }
        },
        "1": {
            "full_name": "HERMELIN, CHRISTER S",
            "location": "Gripenberg",
            "occupation": "lantmästare",
            "birth_details": {
                "date": "05/09/1919",
                "place": "Ulfåsa, Östergötlands län",
                "parents": "frih Gösta H o frih:an Elin von Stapelmohr"
            },
            "education": [
                {
                    "degree": "Ultuna lantbr:sk",
                    "year": "1940"
                },
                {
                    "degree": "Alnarps lantbr:inst",
                    "year": "1945"
                }
            ],
            "career": [
                {
                    "position": "anst Gripenbergs fideikommiss",
                    "years": {
                        "start_year": 1953
                    }
                }
            ],
            "family": {
                "spouse": "Birgitta Jonas",
                "marriage_year": "1955",
                "children": [
                    {
                        "name": "Charlotte",
                        "birth_year": "1956"
                    },
                    {
                        "name": "Fredrik",
                        "birth_year": "1958"
                    }
                ]
            }
        },
        "2": {
            "full_name": "HERMELIN, S DAVID O",
            "location": "Björsäter",
            "occupation": "fd överste",
            "birth_details": {
                "date": "22/07/1897",
                "place": "Sthlm",
                "parents": "översten, frih Sven H o Anna Ohlsson"
            },
            "education": [],
            "career": [
                {
                    "position": "fänr livreg dragoner",
                    "years": {
                        "start_year": 1917
                    }
                },
                {
                    "position": "bitr mil :attaché",
                    "years": {
                        "start_year": 1922
                    }
                },
                {
                    "position": "major K 4",
                    "years": {
                        "start_year": 1940
                    }
                },
                {
                    "position": "öv :löjtn pansartr",
                    "years": {
                        "start_year": 1942
                    }
                },
                {
                    "position": "överste kav o ch K 4",
                    "years": {
                        "start_year": 1947
                    }
                },
                {
                    "position": "sekundch K 3",
                    "years": {
                        "start_year": 1951
                    }
                },
                {
                    "position": "fobef Malmö fö",
                    "years": {
                        "start_year": 1954,
                        "end_year": 1957
                    }
                }
            ],
            "family": {
                "spouse": "Märtha Schenström",
                "marriage_year": "1930",
                "children": [
                    {
                        "name": "David",
                        "birth_year": "1932"
                    },
                    {
                        "name": "Johan",
                        "birth_year": "1937"
                    }
                ]
            }
        },
        "3": {
            "full_name": "HERMELIN, NILS G",
            "location": "Söderköping",
            "occupation": "godsägare",
            "birth_details": {
                "date": "08/09/1911",
                "place": "Nykil, Östergötlands län",
                "parents": "frih Robert H o Gunni Pauli"
            },
            "education": [],
            "career": [
                {
                    "position": "befalln:man Torsvi gård Enkpg",
                    "years": {
                        "start_year": 1934,
                        "end_year": 1938
                    }
                },
                {
                    "position": "arrend Tomtaholm",
                    "years": {
                        "start_year": 1953,
                        "end_year": 1958
                    }
                },
                {
                    "position": "ag Bleckstad Söderkpg",
                    "years": {
                        "start_year": 1938
                    }
                }
            ],
            "family": {
                "spouse": "Brita Östman",
                "marriage_year": "1940",
                "children": [
                    {
                        "name": "Aino",
                        "birth_year": "1941"
                    },
                    {
                        "name": "Ulla",
                        "birth_year": "1943"
                    },
                    {
                        "name": "Johan",
                        "birth_year": "1947"
                    },
                    {
                        "name": "Gunnar",
                        "birth_year": "1957"
                    }
                ]
            }
        }
    }
}