{
    "original": "AMINOFF, HANS-STEPHAN R, leg\nläkare, Gbg, f i Skövde 29/8/15 av\növ:-löjtn Iwan A o Olga Wallerstedt.\nStud:ex Sthlm 33, med kand 36 o med\nlic Sthlm 42, underläk KK Karol sjh\n41-44, med avd S:t Eriks sjh 44,\nRenströmska sjh Gbg 44-46, Vasa sjh 46-49, läk\nProtection o Indemnitys läk:mottagn\nGbg 50-55, pol :läk hälsocentr f sjöfolk\ni Gbg sed 55. - Styr:led Naut fören sed\n55. - Skr: art i sjömed.- Hobbies:\nsjösport, fiske.\n\nGift 42 m Ragnhild Stang f 22, dtr t\nkonsul Thomas S o Agnes\nSchwei-gaard (Oslo). - Barn: Stefan f 46, Georg\nf 49, Magnus f 56.\n\nAMUNDSSON, JOHN A,\nläroverksadjunkt, Gbg, f i Ödsmål, Gbgs o Boh\nl, 12/5/12 av hemm:äg Amund\nJohansson o Olga Berntsson.\nStud:ex Gbg 31, fil mag Lund 36,\nextra-lär o e adj Ängelholm 37, e adj\nKarlskrona 39, Vasa hal Gbg 43, eo adj Östra\nrealsk Gbg 46, adj hal Majorna 49,\nVasa hal sed 50; timlär Gbgs gymn f fi\n44-45, 49-51, Gbgs h samsk 46-53,\ntim-ass i fysik CTH 46-51. - Skr: läroböcker\ni matem f gymnasiet (tills m Bertil\nNyman o Arne Broman).\nGift 56 m Gun Erling f 23, dtr t kyrkoh\nAlbin E o Signhild Ocklind. - Barn:\nBirgitta f 58, Krister o Karin ff 60.\n\nAMVALL, H BERTIL, ingenjör,\nAs-kim, f i Mölnlycke 4/6/19 av köpm Eric\nAndersson o Maria Börjesson.\nGTI 44, ing Byggn :f örb Gbg 45, ch o\nans v byggm där 50, konsult byggn:ing\nsed 62. - Medl FrimO.\nGift 46 m Christina Claeson, dtr t fabr\nClaes Andersson o Judit Andersson.\n-Barn: Gertie f 49, Klas f 52.\n\nANDALEN, SVEN-ÅKE S,\nläroverksadjunkt, Åmål, f i Gbg 16/6/29 av ing\nEvald Andersson o Daga Rasmusson.\nStud:ex Vänersborg 50, fil mag Gbg 57,\ne adj hal Åmål 57, adj där sed 61.\n-Medl   Åmål-Dals   filatelistfören,\nDalslands konstfören. - Hobby: filateli.\nGift 53 m Inga Johansson f 29, dtr t\nAxel J o Anna J. - Barn: Anders f 55,\nPer f 57.\n\n",
    "structured": {
        "0": {
            "full_name": "AMINOFF, HANS-STEPHAN R",
            "location": "Göteborg",
            "occupation": "Leg läkare",
            "birth_details": {
                "date": "29/08/1915",
                "place": "Skövde",
                "parents": "Iwan A Aminoff, Olga Wallerstedt"
            },
            "education": [
                {
                    "degree": "Stud:ex",
                    "year": "1933",
                    "institution": "Stockholm"
                },
                {
                    "degree": "Med kand",
                    "year": "1936",
                    "institution": "Stockholm"
                },
                {
                    "degree": "Med lic",
                    "year": "1942",
                    "institution": "Stockholm"
                }
            ],
            "career": [
                {
                    "position": "Underläk",
                    "years": {
                        "start_year": 1941,
                        "end_year": 1944
                    },
                    "organization": "KK Karol sjh"
                },
                {
                    "position": "Med avd",
                    "years": {
                        "start_year": 1944,
                        "end_year": 1944
                    },
                    "organization": "S:t Eriks sjh"
                },
                {
                    "position": "Läk Protection o Indemnitys läk:mottagn",
                    "years": {
                        "start_year": 1950,
                        "end_year": 1955
                    },
                    "organization": "Göteborg"
                },
                {
                    "position": "Pol :läk hälsocentr f sjöfolk",
                    "years": {
                        "start_year": 1955,
                        "end_year": null
                    },
                    "organization": "Göteborg"
                }
            ],
            "family": {
                "spouse": "Ragnhild Stang",
                "marriage_year": "1942",
                "children": [
                    {
                        "name": "Stefan",
                        "birth_year": "1946"
                    },
                    {
                        "name": "Georg",
                        "birth_year": "1949"
                    },
                    {
                        "name": "Magnus",
                        "birth_year": "1956"
                    }
                ]
            },
            "hobbies": [
                "Sjösport",
                "Fiske"
            ],
            "publications": [],
            "community_involvement": [],
            "board_memberships": [],
            "honorary_titles": []
        },
        "1": {
            "full_name": "AMUNDSSON, JOHN A",
            "location": "Göteborg",
            "occupation": "Läroverksadjunkt",
            "birth_details": {
                "date": "12/05/1912",
                "place": "Ödsmål, Gbg o Boh"
            },
            "education": [
                {
                    "degree": "Stud:ex",
                    "year": "1931",
                    "institution": "Göteborg"
                },
                {
                    "degree": "Fil mag",
                    "year": "1936",
                    "institution": "Lund"
                }
            ],
            "career": [
                {
                    "position": "Extra-lär o e adj",
                    "years": {
                        "start_year": 1937,
                        "end_year": 1939
                    },
                    "organization": "Ängelholm"
                },
                {
                    "position": "Eo adj",
                    "years": {
                        "start_year": 1946,
                        "end_year": null
                    },
                    "organization": "Östra realsk Gbg"
                },
                {
                    "position": "Timlär Gbgs gymn f fi",
                    "years": {
                        "start_year": 1944,
                        "end_year": 1945
                    },
                    "organization": "Göteborg"
                },
                {
                    "position": "Tim-ass i fysik CTH",
                    "years": {
                        "start_year": 1946,
                        "end_year": 1951
                    }
                }
            ],
            "family": {
                "spouse": "Gun Erling",
                "marriage_year": "1956",
                "children": [
                    {
                        "name": "Birgitta",
                        "birth_year": "1958"
                    },
                    {
                        "name": "Krister",
                        "birth_year": "1960"
                    },
                    {
                        "name": "Karin",
                        "birth_year": "1960"
                    }
                ]
            },
            "hobbies": [],
            "publications": [],
            "community_involvement": [],
            "board_memberships": [],
            "honorary_titles": []
        },
        "2": {
            "full_name": "AMVALL, H BERTIL",
            "location": "Askim",
            "occupation": "Ingenjör",
            "birth_details": {
                "date": "04/06/1919",
                "place": "Mölnlycke"
            },
            "education": [],
            "career": [],
            "family": {
                "spouse": "Christina Claeson",
                "marriage_year": "1946",
                "children": [
                    {
                        "name": "Gertie",
                        "birth_year": "1949"
                    },
                    {
                        "name": "Klas",
                        "birth_year": "1952"
                    }
                ]
            },
            "hobbies": [],
            "publications": [],
            "community_involvement": [],
            "board_memberships": [],
            "honorary_titles": []
        },
        "3": {
            "full_name": "ANDALEN, SVEN-ÅKE S",
            "location": "Åmål",
            "occupation": "Läroverksadjunkt",
            "birth_details": {
                "date": "16/06/1929",
                "place": "Göteborg"
            },
            "education": [
                {
                    "degree": "Stud:ex",
                    "year": "1950",
                    "institution": "Vänersborg"
                },
                {
                    "degree": "Fil mag",
                    "year": "1957",
                    "institution": "Göteborg"
                }
            ],
            "career": [
                {
                    "position": "E adj hal",
                    "years": {
                        "start_year": 1957,
                        "end_year": null
                    },
                    "organization": "Åmål"
                }
            ],
            "family": {
                "spouse": "Inga Johansson",
                "marriage_year": "1953",
                "children": [
                    {
                        "name": "Anders",
                        "birth_year": "1955"
                    },
                    {
                        "name": "Per",
                        "birth_year": "1957"
                    }
                ]
            },
            "hobbies": [
                "Filateli"
            ],
            "publications": [],
            "community_involvement": [],
            "board_memberships": [],
            "honorary_titles": []
        }
    }
}