{
    "original": "AGGEBRINK, A GUNNAR, direktör,\nAnderstorp, f i Öxnevalla, Älvsb l, 5/1/\n17 av Anders Andersson o Augusta\nCarlsson.\n\nHdlsutbildn, inneh färghandel\nAnderstorp 38-46, verkst dir o inneh\nHagaplast ab Anderstorp sed 41. - Led\nkomm:nd, komrn:fullm m m. - Medl\nRotary, FrimO.\n\nGift 44 m Margit Kessel f 19, dtr t\nEmanuel H o Alma Höglund. - Barn:\nGun f 46, Lena f 48, Marita f 51.\n\nAGGING, G WILLIAM, tandläkare,\nTranås, f i Boxholm, Österg l, 15/11/04\nav bryggmäst A G Andersson o Maria\nJ :son Fålen.\n\nStud:ex Linkpg 26, tysk tandl:ex Bonn\n31, tandl:ex Sthlm 32, privatpraktik\nNy-kpg 32-36, Boxholm 36-38, Eksjö 38-47,\nförest mil :tandpol Eksjö 43-47,\nprivatpraktik Tranås sed 47.\nGift 36 m Ingeborg Boqvist f 08.\n-Barn: Birgitta f 40, Gunilla f 44.\n\nAGMAN, E MARGOT,\nläroverksadjunkt, Västervik, f i Sthlm 16/1/32 av\navd :ch Martin A o Elsa Nilsson.\nStud:ex Jönkpg 51, fil mag Upps 56, e\no eo adj komm fi:sk Östersund 56, eo\nadj hal Västervik 58, adj 61, vik lekt\ndär sed 61.\n\nAGORELIUS, GÖRAN P,\növeringenjör, Mariestad, f i Grythyttan, Örebro l,\n11/9/04 av bergsman Per-Johan Jansson\no Emilia Pettersson.\n\nCTH 29, anst Sv fören f ljuskultur Sthlm\n30, Malmö stads elverk 37, distrib:ing\nGullspångs kraft ab Mariestad 37,\növering o platsch där sed 58. - Led DK sed\n46, des AU sed 55, cfndn 45-59 (ordf\n50-59), byggn :ndn 50-59, hyresndn sed\n52, led o v ordf Mariestads\nmedb:hus-fören sed 56.Gift 34 m Sigrid Bergström f 10. - Barn:\nBjörn f 38, Lena f 42, Claes-Göran f 44.\n\n",
    "structured": {
        "0": {
            "full_name": "AGGEBRINK, A GUNNAR",
            "location": "Anderstorp",
            "occupation": "direktör",
            "birth_details": {
                "date": "05/01/1917",
                "place": "Öxnevalla, Älvsborgs län",
                "parents": "Anders Andersson o Augusta Carlsson"
            },
            "education": [
                {
                    "degree": "Hdlsutbildn",
                    "year": "1938",
                    "institution": "inneh färghandel Anderstorp"
                },
                {
                    "degree": "verkst dir",
                    "year": "1941",
                    "institution": "Hagaplast ab Anderstorp"
                }
            ],
            "career": [
                {
                    "position": "Led komm:nd",
                    "years": {
                        "start_year": null,
                        "end_year": null
                    },
                    "organization": null
                },
                {
                    "position": "komrn:fullm",
                    "years": {
                        "start_year": null,
                        "end_year": null
                    },
                    "organization": "m m"
                }
            ],
            "family": {
                "spouse": "Margit Kessel",
                "marriage_year": "1944",
                "children": [
                    {
                        "name": "Gun",
                        "birth_year": "1946"
                    },
                    {
                        "name": "Lena",
                        "birth_year": "1948"
                    },
                    {
                        "name": "Marita",
                        "birth_year": "1951"
                    }
                ]
            }
        },
        "1": {
            "full_name": "AGGING, G WILLIAM",
            "location": "Tranås",
            "occupation": "tandläkare",
            "birth_details": {
                "date": "15/11/1904",
                "place": "Boxholm, Östergötlands län",
                "parents": "bryggmäst A G Andersson o Maria J :son Fålen"
            },
            "education": [
                {
                    "degree": "Stud:ex",
                    "year": "1926",
                    "institution": "Linkpg"
                },
                {
                    "degree": "tysk tandl:ex",
                    "year": "1931",
                    "institution": "Bonn"
                },
                {
                    "degree": "tandl:ex",
                    "year": "1932",
                    "institution": "Sthlm"
                }
            ],
            "career": [
                {
                    "position": "förest mil :tandpol",
                    "years": {
                        "start_year": 1943,
                        "end_year": 1947
                    },
                    "organization": "Eksjö"
                }
            ],
            "family": {
                "spouse": "Ingeborg Boqvist",
                "marriage_year": "1936",
                "children": [
                    {
                        "name": "Birgitta",
                        "birth_year": "1940"
                    },
                    {
                        "name": "Gunilla",
                        "birth_year": "1944"
                    }
                ]
            }
        },
        "2": {
            "full_name": "AGMAN, E MARGOT",
            "location": "Västervik",
            "occupation": "läroverksadjunkt",
            "birth_details": {
                "date": "16/01/1932",
                "place": "Sthlm",
                "parents": "avd :ch Martin A o Elsa Nilsson"
            },
            "education": [
                {
                    "degree": "Stud:ex",
                    "year": "1951",
                    "institution": "Jönkpg"
                },
                {
                    "degree": "fil mag",
                    "year": "1956",
                    "institution": "Upps"
                }
            ],
            "career": [
                {
                    "position": "eo adj komm fi:sk",
                    "years": {
                        "start_year": 1956,
                        "end_year": 1958
                    },
                    "organization": "Östersund"
                },
                {
                    "position": "viko lekt",
                    "years": {
                        "start_year": 1961,
                        "end_year": null
                    },
                    "organization": "Västervik"
                }
            ],
            "family": null
        },
        "3": {
            "full_name": "AGORELIUS, GÖRAN P",
            "location": "Mariestad",
            "occupation": "överingenjör",
            "birth_details": {
                "date": "11/09/1904",
                "place": "Grythyttan, Örebro län",
                "parents": "bergsman Per-Johan Jansson o Emilia Pettersson"
            },
            "education": [
                {
                    "degree": "CTH",
                    "year": "1929",
                    "institution": null
                }
            ],
            "career": [
                {
                    "position": null,
                    "years": {
                        "start_year": 1930,
                        "end_year": null
                    },
                    "organization": "Sv fören f ljuskultur Sthlm"
                },
                {
                    "position": null,
                    "years": {
                        "start_year": 1937,
                        "end_year": null
                    },
                    "organization": "Malmö stads elverk"
                },
                {
                    "position": "övering",
                    "years": {
                        "start_year": 1958,
                        "end_year": null
                    },
                    "organization": "Gullspångs kraft ab Mariestad"
                }
            ],
            "family": {
                "spouse": "Sigrid Bergström",
                "marriage_year": "1934",
                "children": [
                    {
                        "name": "Björn",
                        "birth_year": "1938"
                    },
                    {
                        "name": "Lena",
                        "birth_year": "1942"
                    },
                    {
                        "name": "Claes-Göran",
                        "birth_year": "1944"
                    }
                ]
            }
        }
    }
}