{
    "original": "ARIN, A K ARNE, tandläkare,\nNässjö, f i Nässjö 17/2/15 av stat:förm\nGustaf A o Emma Pettersson.\nStud:ex Eksjö 35, tandl:ex Sthlm 39, vik\nSkänninge 39, Mjölby o Linkpg 40,\nass:-tandl Mjölby 39-40, priv:prakt Nässjö\nsed 40. - Medl TempelrO. - Hobby:\nmusik.\n\nGift 1) 45 m skolkökslär Febe Borell\nf 18 d 48, dtr t disp Axel Johansson o\nSanna Borell, 2) 50 m sjuksköt Ingrid\nHenricsson f 21, dtr t hemm:äg Nils H\no Anna Nilsson. - Barn: i l:a akt\nIng-Marie f 46, i 2:a akt Christina f 54,\nHåkan f 57.\n\nARIN, O G LENNART, överläkare,\nNässjö, f i Nässjö 20/6/11 av stat:förm\nGustaf A o Emma Pettersson.\nStud:ex Eksjö 31, med kand Upps 34,\nmed lic Sthlm 41, tf underläk Sävsjö\nsanat o Målilla sanat 41-42, underläk\nSävsjö sanat 42-44, Pensionsstyr sjh Ny-\n\nnäshamn 44-45, 2:e underläk med avd\nNykpgs las 45-46, l:e underläk där\n46-51, med avd Östersunds las 51-55, bitr\nlas:läk där 52-55, e läk m las:läk ställn\nmed avd Nässjö las 55-57, överläk där\nsed 57. - Skr i inv med. - Hobbies:\nteckning, målning, fotografering.\nGift 39 m Stina Lundberg f 14, dtr t\ngrossh Gustav L o Anny Andersson.\n-Barn: Anders f 44, Margareta f 48.\n\nARKHAMMAR, H O EVERT,\ncivilingenjör, Gbg, f i Främmestad, Skarab\nl, 25/9/27 av charkuterist Gunnar\nAndersson o Brita Eriksson.\nStud:ex Gbg 46, CTH 50, ing Sv ab\nPhilips 51, Philips teleind ab 53, Philips\nind :elektronik ab 60, försäljn:ing\nind:-avd Sv ab Philips Gbg sed 63. - Skr: art\ni fackpressen.\n\nGift 55 m Britt-Marie Pettersson f 32,\ndtr t skomakarm Allan P o Anna\nKarlsson. - Barn: Per f 59, Catrin f 62,\nNiklas f 64.\n\n",
    "structured": {
        "1": {
            "full_name": "Arin, A K Arne",
            "location": "Nässjö",
            "occupation": "Tandläkare",
            "birth_details": {
                "date": "17/02/1915",
                "place": "Nässjö",
                "parents": "Gustaf A och Emma Pettersson"
            },
            "education": [
                {
                    "degree": "Stud:ex",
                    "year": "1935",
                    "institution": "Eksjö"
                },
                {
                    "degree": "tandl:ex",
                    "year": "1939",
                    "institution": "Sthlm"
                }
            ],
            "career": [
                {
                    "position": "vik",
                    "years": {
                        "start_year": 1939,
                        "end_year": 1940
                    },
                    "organization": "Skänninge"
                },
                {
                    "position": "Mjölby o Linkpg",
                    "years": {
                        "start_year": 1940,
                        "end_year": 1940
                    }
                },
                {
                    "position": "ass:-tandl",
                    "years": {
                        "start_year": 1939,
                        "end_year": 1940
                    },
                    "organization": "Mjölby"
                },
                {
                    "position": "priv:prakt",
                    "years": {
                        "start_year": 1940
                    },
                    "organization": "Nässjö"
                }
            ],
            "family": {
                "spouse": "Febe Borell",
                "marriage_year": "1945",
                "children": [
                    {
                        "name": "Ing-Marie",
                        "birth_year": "1946"
                    },
                    {
                        "name": "Christina",
                        "birth_year": "1954"
                    },
                    {
                        "name": "Håkan",
                        "birth_year": "1957"
                    }
                ]
            }
        },
        "2": {
            "full_name": "Arin, O G Lennart",
            "location": "Nässjö",
            "occupation": "Överläkare",
            "birth_details": {
                "date": "20/06/1911",
                "place": "Nässjö",
                "parents": "Gustaf A och Emma Pettersson"
            },
            "education": [
                {
                    "degree": "Stud:ex",
                    "year": "1931",
                    "institution": "Eksjö"
                },
                {
                    "degree": "med kand",
                    "year": "1934",
                    "institution": "Upps"
                },
                {
                    "degree": "med lic",
                    "year": "1941",
                    "institution": "Sthlm"
                }
            ],
            "career": [
                {
                    "position": "tf underläk",
                    "years": {
                        "start_year": 1941,
                        "end_year": 1942
                    },
                    "organization": "Sävsjö sanat och Målilla sanat"
                },
                {
                    "position": "underläk",
                    "years": {
                        "start_year": 1942,
                        "end_year": 1944
                    },
                    "organization": "Sävsjö sanat"
                },
                {
                    "position": "Pensionsstyr sjh",
                    "years": {
                        "start_year": 1944,
                        "end_year": 1945
                    },
                    "organization": "Nynäshamn"
                },
                {
                    "position": "2:e underläk med avd",
                    "years": {
                        "start_year": 1945,
                        "end_year": 1946
                    },
                    "organization": "Nykpgs las"
                },
                {
                    "position": "l:e underläk där",
                    "years": {
                        "start_year": 1946,
                        "end_year": 1951
                    },
                    "organization": "Nykpgs las"
                },
                {
                    "position": "med avd",
                    "years": {
                        "start_year": 1951,
                        "end_year": 1955
                    },
                    "organization": "Östersunds las"
                },
                {
                    "position": "bitr las:läk där",
                    "years": {
                        "start_year": 1952,
                        "end_year": 1955
                    },
                    "organization": "Östersunds las"
                },
                {
                    "position": "e läk m las:läk ställn med avd",
                    "years": {
                        "start_year": 1955,
                        "end_year": 1957
                    },
                    "organization": "Nässjö las"
                },
                {
                    "position": "överläk där",
                    "years": {
                        "start_year": 1957
                    },
                    "organization": "Nässjö las"
                }
            ],
            "family": {
                "spouse": "Stina Lundberg",
                "marriage_year": "1939",
                "children": [
                    {
                        "name": "Anders",
                        "birth_year": "1944"
                    },
                    {
                        "name": "Margareta",
                        "birth_year": "1948"
                    }
                ]
            },
            "hobbies": [
                "teckning",
                "målning",
                "fotografering"
            ]
        },
        "3": {
            "full_name": "Arkhammar, H O Evert",
            "location": "Gbg",
            "occupation": "Civilingenjör",
            "birth_details": {
                "date": "25/09/1927",
                "place": "Främmestad, Skarab l",
                "parents": "Gunnar Andersson och Brita Eriksson"
            },
            "education": [
                {
                    "degree": "Stud:ex",
                    "year": "1946",
                    "institution": "Gbg"
                },
                {
                    "degree": "CTH",
                    "year": "1950"
                }
            ],
            "career": [
                {
                    "position": "ing Sv ab",
                    "years": {
                        "start_year": 1951
                    },
                    "organization": "Philips"
                },
                {
                    "position": "Philips teleind ab",
                    "years": {
                        "start_year": 1953
                    },
                    "organization": "Philips"
                },
                {
                    "position": "Philips ind :elektronik ab",
                    "years": {
                        "start_year": 1960
                    },
                    "organization": "Philips"
                },
                {
                    "position": "försäljn:ing ind:-avd Sv ab Philips",
                    "years": {
                        "start_year": 1963
                    },
                    "organization": "Philips Gbg"
                }
            ],
            "family": {
                "spouse": "Britt-Marie Pettersson",
                "marriage_year": "1955",
                "children": [
                    {
                        "name": "Per",
                        "birth_year": "1959"
                    },
                    {
                        "name": "Catrin",
                        "birth_year": "1962"
                    },
                    {
                        "name": "Niklas",
                        "birth_year": "1964"
                    }
                ]
            }
        }
    }
}