{
    "original": "ADOLFSSON, DAVID V E,\ntandläkare, Skänninge, f i Mortorp, Kalmar l,\n17/8/99 av godsäg August A o Hilda\nSvensson.\n\nStud:ex Linkpg 20, tandl:ex Sthlm 24,\nprivatpraktik Skänninge sed 24,\nskol-tandl 24-56. - Led kyrkorådet Skänninge\nsed 50, kyrkofullm sed 59. - Utm:\nÖstgöta sångarförb ftjGM o vet:tG, Sv\nsångarförb ftjtG, SRKSM.\nGift 26 m Edith Svensson f 00, dtr t\nT A S o Ottilia Andersson. - Barn:\nGöran f 30, Sören f 33, Håkan f 35.\n\nADOLFSSON, A EVERT E,\nläroverksadjunkt, Oskarshamn, f i Oskarshamn\n14/10/27 av typogr Emanuel A o\nMargot Svensson.\n\nStud:ex Kalmar 46, folkskollär :ex Hbg\n55, fil mag Upps 60. - Öl anst s\nhamn-arb, kont, tekniker, journ o lär 47-53,\nämneslär i matem o fys hal Västervik\n55, adj hal Oskarshamn sed 60. - Skr:\nHyttebud (novellsaml 59).\nGift 55 m Barbro Gustafsson f 34, dtr t\nfrisörmäst Ivar G o Elsa Andersson.\n-Barn: Anna Maria f 56, Kerstin f 59,\nAnders Johan f 61.\n\nADOLFSSON, GUNNAR,\nchefredaktör, riksdagsman, Gbg, f i Ryd, Kronob\nl, 21/8/06 av byggn:snick Gustaf A o\nIda Nilsson.\n\nRed :sekr Sydsv Kuriren Malmö 35, red\nFolkviljan Malmö 42, Arbetar-Tidn Gbg\nsed 50. - AK 45-48, FK sed 63 (k). - Led\nAlmundsryds komm:fullm 34-36, Malmö\nStadsfullm 47-50, Gbgs Stadsfullm sed59, stadskoll 59-62, fastigh:nd 59, div\nutredn :komm. - Medl Sv:es förf :f or en,\nGbgs förf:sällsk. - Skr: Arbetets barn\n(28), Nu vill vi leva (39), Väntande land\n(49), Trappan (55), Träskoland (64).\n-Hobby: skönlitteratur.\nGift 36 m Ester Eriksen, dtr t lantbr\nOle E o Marie E (Norge). - Barn: Eva\nf 42, Björn f 47.\n\n",
    "structured": {
        "1": {
            "full_name": "ADOLFSSON, DAVID V E",
            "location": "Skänninge",
            "occupation": "tandläkare",
            "birth_details": {
                "date": "17/08/1899",
                "place": "Mortorp, Kalmar l"
            },
            "education": [
                {
                    "degree": "Stud:ex",
                    "year": "1920",
                    "institution": "Linkpg"
                },
                {
                    "degree": "tandl:ex",
                    "year": "1924",
                    "institution": "Sthlm"
                }
            ],
            "career": [
                {
                    "position": "privatpraktik",
                    "years": {
                        "start_year": 1924,
                        "end_year": 1956
                    },
                    "organization": "Skänninge"
                },
                {
                    "position": "skol-tandl",
                    "years": {
                        "start_year": 1924,
                        "end_year": 1956
                    }
                }
            ],
            "family": {
                "spouse": "Edith Svensson",
                "marriage_year": "1926",
                "children": [
                    {
                        "name": "Göran",
                        "birth_year": "1930"
                    },
                    {
                        "name": "Sören",
                        "birth_year": "1933"
                    },
                    {
                        "name": "Håkan",
                        "birth_year": "1935"
                    }
                ]
            }
        },
        "2": {
            "full_name": "ADOLFSSON, A EVERT E",
            "location": "Oskarshamn",
            "occupation": "läroverksadjunkt",
            "birth_details": {
                "date": "14/10/1927",
                "place": "Oskarshamn"
            },
            "education": [
                {
                    "degree": "Stud:ex",
                    "year": "1946",
                    "institution": "Kalmar"
                },
                {
                    "degree": "folkskollär :ex",
                    "year": "1955",
                    "institution": "Hbg"
                },
                {
                    "degree": "fil mag",
                    "year": "1960",
                    "institution": "Upps"
                }
            ],
            "career": [
                {
                    "position": "tech. arb, kont, tekniker, journ",
                    "years": {
                        "start_year": 1947,
                        "end_year": 1953
                    },
                    "organization": "Oskarshamn"
                },
                {
                    "position": "ämneslär",
                    "years": {
                        "start_year": 1955
                    },
                    "organization": "Västervik"
                },
                {
                    "position": "adj",
                    "years": {
                        "start_year": 1960
                    },
                    "organization": "Oskarshamn"
                }
            ],
            "family": {
                "spouse": "Barbro Gustafsson",
                "marriage_year": "1955",
                "children": [
                    {
                        "name": "Anna Maria",
                        "birth_year": "1956"
                    },
                    {
                        "name": "Kerstin",
                        "birth_year": "1959"
                    },
                    {
                        "name": "Anders Johan",
                        "birth_year": "1961"
                    }
                ]
            }
        },
        "3": {
            "full_name": "ADOLFSSON, GUNNAR",
            "location": "Gbg",
            "occupation": "chefredaktör, riksdagsman",
            "birth_details": {
                "date": "21/08/1906",
                "place": "Ryd, Kronob l"
            },
            "career": [
                {
                    "position": "red :sekr",
                    "years": {
                        "start_year": 1935,
                        "end_year": 1942
                    },
                    "organization": "Sydsv Kuriren Malmö"
                },
                {
                    "position": "red",
                    "years": {
                        "start_year": 1942
                    },
                    "organization": "Folkviljan Malmö"
                },
                {
                    "position": "red",
                    "years": {
                        "start_year": 1950
                    },
                    "organization": "Arbetar-Tidn Gbg"
                }
            ],
            "family": {
                "spouse": "Ester Eriksen",
                "marriage_year": "1936",
                "children": [
                    {
                        "name": "Eva",
                        "birth_year": "1942"
                    },
                    {
                        "name": "Björn",
                        "birth_year": "1947"
                    }
                ]
            },
            "publications": [
                {
                    "title": "Arbetets barn",
                    "year": "1928",
                    "type": "book"
                },
                {
                    "title": "Nu vill vi leva",
                    "year": "1939",
                    "type": "book"
                },
                {
                    "title": "Väntande land",
                    "year": "1949",
                    "type": "book"
                },
                {
                    "title": "Trappan",
                    "year": "1955",
                    "type": "book"
                },
                {
                    "title": "Träskoland",
                    "year": "1964",
                    "type": "book"
                }
            ],
            "hobbies": [
                "skönlitteratur"
            ]
        }
    }
}