{
    "original": "AHLBECK, ELVY, författarinna, fru,\nBorgholm, f i Skallmeja, Skarab l, 24/4/\n31 av folkskollär Ernst Sätherdal o\nMaja Andersson.\n\nStud:ex Skara 51, univ:stud Lund,\nlär:vik sed 54. - Skr: Vargen (62), Mord\nutan förbindelse (64), På den säkra\nsi|dan (65), ett flert noveller i dagspressen.\n! Gift 54 m rekt Jan Olof Ahlbeck f 32.\n-Barn: Tomas f 57, Mattias f 60.\n\nAHLBÄCK, J INGWAR E,\ncivilingenjör, Mölndal, f i Hallsberg 21/12/25 av\nred Algot A o Signe Håkansson.\nStud:ex Örebro 44, CTH 50, bitr byråing\nÖrebro stads byggn :kont 50, ing Hbgs\nstads gatukont 53, byråing Mölndals\nstads byggn:kont 55, Gbgs stads\ngatukont 57, ch väg- o trafikavd Ing :firman\nOrrje &amp; Co ab Gbg sed 63.\nGift 52 m Lilian Danielsson f 30, dtr t\nköpm Georg D o Nanny Kjellström.\n-Barn: Mats f 54, Anna f 57.\n\nAHLBECK, JAN OLOF, rektor,\nBorgholm, f i Sthlm 30/6/32 av köpm Joel\nA o Emilia Lindquist.\nStud:ex Malmö 51, fil måg Lund 58; e\nadj Hbg, Växjö o Skara 57-59, eo adj\nNätra 59, adj o studierekt där 61-63,\nrekt samrealsk Borgholm sed 63. - Medl\nRotary.\n\nGift 54 m förf:an Elvy Sätherdal f 31,\ndtr t folkskollär Ernst S o Maja\nAndersson. - Barn: Tomas f 57, Mattias\nf 60.\n\nAHLBERG,   AXEL   R,\nläroverksadjunkt, Kalmar, f i Örebro 29/12/25 av\nlekt Reinhold A o Ingrid Wiegert.\nStud:ex Hbg 44, fil mag Lund 54. - Anst\nlänsstyr Kronob l 46-48, timlär o eo adj\nhal Kalmar 54-57, adj där sed 58.\nGift 54 m Majbritt Nordling f 28, dtr t\nfolkskollär John N o Målla Uppström.\n-Barn: Anders f 60.\n\nAHLBERG, K BERTIL, överpostiljon,\nstadsfullmäktigeordförande, Eksjö, f i\nEksjö 1/11/12 av Gustaf A o Anna\nJohansson.\n\nRealex 28, anst postv 30, överpostiljon\ndär. - Landst:man sed 54 (s), ordf stads-\n\nfullm Eksjö sed 63 (led 43-45 o sed 47,\n\nv ordf 54-62), v ordf DK, byggn :nd,\n\nordf brandstyr, polisnd t 64. - Hobby:\n\nfiske.\n\nGift 42 m Hilja Gillberg f 12, dtr t Karl\n\nG o Hilda G. - Barn: Anita f 44, Jan\n\nf 47.\n\n",
    "structured": {
        "1": {
            "full_name": "ELVY AHLBECK",
            "location": "Borgholm, Skaraborgs Län",
            "occupation": "författarinna",
            "birth_details": {
                "date": "24/04/1931",
                "place": "Skallmeja, Skaraborgs Län",
                "parents": "folkskollär Ernst Sätherdal och Maja Andersson"
            },
            "education": [
                {
                    "degree": "Stud:ex",
                    "year": "1951",
                    "institution": "Skara"
                },
                {
                    "degree": "univ:stud",
                    "year": "Lund",
                    "institution": "Lund"
                }
            ],
            "career": [
                {
                    "position": "lär:vik",
                    "years": {
                        "start_year": 1954
                    }
                }
            ],
            "family": {
                "spouse": "rekt Jan Olof Ahlbeck",
                "marriage_year": "1954",
                "children": [
                    {
                        "name": "Tomas",
                        "birth_year": "1957"
                    },
                    {
                        "name": "Mattias",
                        "birth_year": "1960"
                    }
                ]
            }
        },
        "2": {
            "full_name": "J. INGWAR E. AHLBÄCK",
            "location": "Mölndal",
            "occupation": "civilingenjör",
            "birth_details": {
                "date": "21/12/1925",
                "place": "Hallsberg",
                "parents": "red Algot A o Signe Håkansson"
            },
            "education": [
                {
                    "degree": "Stud:ex",
                    "year": "1944",
                    "institution": "Örebro"
                },
                {
                    "degree": "CTH",
                    "year": "1950",
                    "institution": "CTH"
                }
            ],
            "career": [
                {
                    "position": "bitr byråing",
                    "years": {
                        "start_year": 1950
                    },
                    "organization": "Örebro stads byggn :kont"
                },
                {
                    "position": "ing",
                    "years": {
                        "start_year": 1963
                    },
                    "organization": "Ing :firman Orrje & Co ab Gbg"
                }
            ],
            "family": {
                "spouse": "m Lilian Danielsson",
                "marriage_year": "1952",
                "children": [
                    {
                        "name": "Mats",
                        "birth_year": "1954"
                    },
                    {
                        "name": "Anna",
                        "birth_year": "1957"
                    }
                ]
            }
        },
        "3": {
            "full_name": "JAN OLOF AHLBECK",
            "location": "Borgholm",
            "occupation": "rektor",
            "birth_details": {
                "date": "30/06/1932",
                "place": "Sthlm",
                "parents": "köpm Joel A o Emilia Lindquist"
            },
            "education": [
                {
                    "degree": "Stud:ex",
                    "year": "1951",
                    "institution": "Malmö"
                },
                {
                    "degree": "fil måg",
                    "year": "1958",
                    "institution": "Lund"
                }
            ],
            "career": [
                {
                    "position": "eo adj",
                    "years": {
                        "start_year": 1957,
                        "end_year": 1959
                    },
                    "organization": "Hbg, Växjö o Skara"
                },
                {
                    "position": "rekt samrealsk",
                    "years": {
                        "start_year": 1963
                    },
                    "organization": "Borgholm"
                }
            ],
            "family": {
                "spouse": "rektor Jan Olof Ahlbeck",
                "marriage_year": "1954",
                "children": [
                    {
                        "name": "Tomas",
                        "birth_year": "1957"
                    },
                    {
                        "name": "Mattias",
                        "birth_year": "1960"
                    }
                ]
            }
        },
        "4": {
            "full_name": "AXEL R. AHLBERG",
            "location": "Kalmar",
            "occupation": "läroverksadjunkt",
            "birth_details": {
                "date": "29/12/1925",
                "place": "Örebro",
                "parents": "lekt Reinhold A o Ingrid Wiegert"
            },
            "education": [
                {
                    "degree": "Stud:ex",
                    "year": "1944",
                    "institution": "Hbg"
                },
                {
                    "degree": "fil mag",
                    "year": "1954",
                    "institution": "Lund"
                }
            ],
            "career": [
                {
                    "position": "eo adj",
                    "years": {
                        "start_year": 1954,
                        "end_year": 1957
                    },
                    "organization": "hal Kalmar"
                },
                {
                    "position": "adj",
                    "years": {
                        "start_year": 1958
                    },
                    "organization": "Kalmar"
                }
            ],
            "family": {
                "spouse": "m Majbritt Nordling",
                "marriage_year": "1954",
                "children": [
                    {
                        "name": "Anders",
                        "birth_year": "1960"
                    }
                ]
            }
        },
        "5": {
            "full_name": "K. BERTIL AHLBERG",
            "location": "Eksjö",
            "occupation": "överpostiljon, stadsfullmäktigeordförande",
            "birth_details": {
                "date": "01/11/1912",
                "place": "Eksjö",
                "parents": "Gustaf A o Anna Johansson"
            },
            "education": [
                {
                    "degree": "Realex",
                    "year": "1928",
                    "institution": "Eksjö"
                }
            ],
            "career": [
                {
                    "position": "anst postv",
                    "years": {
                        "start_year": 1930
                    }
                }
            ],
            "family": {
                "spouse": "m Hilja Gillberg",
                "marriage_year": "1942",
                "children": [
                    {
                        "name": "Anita",
                        "birth_year": "1944"
                    },
                    {
                        "name": "Jan",
                        "birth_year": "1947"
                    }
                ]
            },
            "hobbies": [
                "fiske"
            ]
        }
    }
}