{
    "original": "Tell, Yngve Samuel, kyrkoadjunkt,\nKattarp, f. 2/7/09 i Barkåkra, Krist.\n1., av järnv:tj :man Tellander T. o.\nIng-I rid Maria Emerentia Samuelsson. G.\nm. Judit Svensson. — Stud:ex. i Lund\n30, teol. fil. ex. 31, teol. kand.fc prakt,\nteol. prov o. prästv. f. Lunds stift 36.\nPastorsadj. i Barkåkra, kyrkoadj. i\nVälinge o. Kattarp  sed. 43.\n\nTellgren, Ragnhild Maria,\nläroverksadjunkt, Hälsingborg, f. 28/11/97\ni Marstrand av rektor L. E. T. o.\nHelfrid Lagergren. — Stud:ex. v. Gbgs h.\nsamsk. 16, fil. mag. v. Gbgs högsk. 26,\nnord. feriekurs^i Jena 30, res. f. pedag.\nstud. s. stip. t.\" skol. i hl. a. Danm. o.\nNorge 313. Provar v. Gbgs folksk :secm.\n29-30. Lär. i Östersund 26-29, v.\nMa-jornas elem:lärov. i. fl. i Gbg 30-31, v.\nGävle borg:sk. o. hand :inst. 31-35, vik.\nämneslär. i Motala 35-36, adj. i\nmodersm. o. hist. v. h. a. 1. f. fl. i\nHäl-singb.  fr. 36.\n\nTellving, Karl-Anders, civilingenjör,\nEslöv, f. 16/8/17 i Lund. G. 45 m.\nSonja Engström. Barn: Jan f. 47. —\nStud:ex. i Ystad 37, civ:ing:ex. v. CTH\n43. Anst. i Sydsv. Kraft A-B 43-47,\nund :ing. v. Eslövs stads tekn. verk fr.\n48.\n\nTengelin, Tor Björn Eskil, kapten,\n|   Kristianstad,   f.   22/6/86   i   Sthlm   av\n\nSèfciv :ing. Ernst T. o. Marie Louise\nOhlsson. G. 18 m. Cläre Vissing.\nBarn: Ulf 1 19, löjtn. v. A.9, Eskil 2:1,\nlöjtn. v. A.2, Gunvor 25, g. m. löjtn.\nJoel Svegel, Sthlm. — Stud:ex. i\nMalmö 04, off :ex. 07. Und:löjtn. v. Södra\nskånska infrreg. 07, löjtn. 11, kapten i\nreg. 22, v. reg. 26, på överg:stat 28.\nStatens justerare i Nynäshamn 30-32,\ni Upps. 32-39, i Örebro 39-42 o. i\nKristianstad fr. 43.  RSO.\n\nTengstam, Axel Ivar, komminister,\nMalmö, f. 14/3/04 i Munkaljungby,\nKrist. 1. G. 37 rn. Anna-Lisa\nKnutson.    Barn : Sven f. 38, d. s. å., Karin\n\n38, Lars 40, Anders 431, Mats 48. —\nStud :ex. i Hälsingb. 23, teol. fil. ex. 26,\nteol. kand. o. prästv. i. Lunds stift 29.\nV. pastor i Sankt Olof, v. kommin. i\nHörby, kyrkoadj. i Malmö 32,, kommin.\ndär sed. 39.\n\n",
    "structured": {
        "1": {
            "full_name": "Tell, Yngve Samuel",
            "location": "Kattarp",
            "occupation": "Kyrkoadjunkt",
            "birth_details": {
                "date": "02/07/1909",
                "place": "Barkåkra, Kristianstad"
            },
            "education": [
                {
                    "degree": "Stud:ex.",
                    "year": "1930",
                    "institution": "Lund"
                },
                {
                    "degree": "Teol. fil. ex.",
                    "year": "1931",
                    "institution": "NULL"
                },
                {
                    "degree": "Teol. kand.",
                    "year": "1936",
                    "institution": "NULL"
                }
            ],
            "career": [
                {
                    "position": "Pastorsadj. i Barkåkra",
                    "years": {
                        "start_year": 1936,
                        "end_year": 1939
                    },
                    "organization": "NULL"
                },
                {
                    "position": "Kyrkoadj. i Välinge o. Kattarp",
                    "years": {
                        "start_year": 1943,
                        "end_year": "NULL"
                    },
                    "organization": "NULL"
                }
            ],
            "family": {
                "spouse": "Judit Svensson",
                "marriage_year": "NULL",
                "children": "NULL"
            }
        },
        "2": {
            "full_name": "Tellgren, Ragnhild Maria",
            "location": "Hälsingborg",
            "occupation": "Läroverksadjunkt",
            "birth_details": {
                "date": "28/11/1897",
                "place": "Marstrand"
            },
            "education": [
                {
                    "degree": "Stud:ex.",
                    "year": "1916",
                    "institution": "Gbgs h. samsk."
                },
                {
                    "degree": "Fil. mag.",
                    "year": "1926",
                    "institution": "Gbgs högsk."
                }
            ],
            "career": [
                {
                    "position": "Provar v. Gbgs folksk :secm.",
                    "years": {
                        "start_year": 1929,
                        "end_year": 1930
                    },
                    "organization": "NULL"
                },
                {
                    "position": "Lär. i Östersund",
                    "years": {
                        "start_year": 1926,
                        "end_year": 1929
                    },
                    "organization": "NULL"
                },
                {
                    "position": "Lär. i Östersund",
                    "years": {
                        "start_year": 1926,
                        "end_year": 1929
                    },
                    "organization": "NULL"
                }
            ],
            "family": {
                "spouse": "NULL",
                "marriage_year": "NULL",
                "children": "NULL"
            }
        },
        "3": {
            "full_name": "Tellving, Karl-Anders",
            "location": "Eslöv",
            "occupation": "Civilingenjör",
            "birth_details": {
                "date": "16/08/1917",
                "place": "Lund"
            },
            "education": [
                {
                    "degree": "Stud:ex.",
                    "year": "1937",
                    "institution": "Ystad"
                },
                {
                    "degree": "Civ:ing:ex.",
                    "year": "1943",
                    "institution": "CTH"
                }
            ],
            "career": [
                {
                    "position": "Anst. i Sydsv. Kraft A-B",
                    "years": {
                        "start_year": 1943,
                        "end_year": 1947
                    },
                    "organization": "NULL"
                },
                {
                    "position": "Und :ing. v. Eslövs stads tekn. verk",
                    "years": {
                        "start_year": 1948,
                        "end_year": "NULL"
                    },
                    "organization": "NULL"
                }
            ],
            "family": {
                "spouse": "Sonja Engström",
                "marriage_year": "1945",
                "children": {
                    "name": "Jan",
                    "birth_year": "1947"
                }
            }
        },
        "4": {
            "full_name": "Tengelin, Tor Björn Eskil",
            "location": "Kristianstad",
            "occupation": "Kapten",
            "birth_details": {
                "date": "22/06/1886",
                "place": "Sthlm"
            },
            "education": [
                {
                    "degree": "Stud:ex.",
                    "year": "1904",
                    "institution": "Malmö"
                },
                {
                    "degree": "Off:ex.",
                    "year": "1907",
                    "institution": "NULL"
                }
            ],
            "career": [
                {
                    "position": "Löjtn.",
                    "years": {
                        "start_year": 1911,
                        "end_year": "NULL"
                    },
                    "organization": "A.9"
                },
                {
                    "position": "Kapten i reg.",
                    "years": {
                        "start_year": 1922,
                        "end_year": "NULL"
                    },
                    "organization": "NULL"
                }
            ],
            "family": {
                "spouse": "Cläre Vissing",
                "marriage_year": "1918",
                "children": [
                    {
                        "name": "Ulf",
                        "birth_year": "1919"
                    },
                    {
                        "name": "Eskil",
                        "birth_year": "1921"
                    },
                    {
                        "name": "Gunvor",
                        "birth_year": "1925"
                    }
                ]
            }
        },
        "5": {
            "full_name": "Tengstam, Axel Ivar",
            "location": "Malmö",
            "occupation": "Komminister",
            "birth_details": {
                "date": "14/03/1904",
                "place": "Munkaljungby, Kristianstad"
            },
            "education": [
                {
                    "degree": "Stud:ex.",
                    "year": "1923",
                    "institution": "Hälsingborg"
                },
                {
                    "degree": "Teol. fil. ex.",
                    "year": "1926",
                    "institution": "NULL"
                },
                {
                    "degree": "Teol. kand.",
                    "year": "1929",
                    "institution": "NULL"
                }
            ],
            "career": [
                {
                    "position": "V. pastor i Sankt Olof",
                    "years": {
                        "start_year": "NULL",
                        "end_year": "NULL"
                    },
                    "organization": "NULL"
                },
                {
                    "position": "V. kommin. i Hörby",
                    "years": {
                        "start_year": "NULL",
                        "end_year": "NULL"
                    },
                    "organization": "NULL"
                },
                {
                    "position": "Kyrkoadj. i Malmö",
                    "years": {
                        "start_year": 1939,
                        "end_year": "NULL"
                    },
                    "organization": "NULL"
                }
            ],
            "family": {
                "spouse": "Anna-Lisa Knutson",
                "marriage_year": "1937",
                "children": [
                    {
                        "name": "Sven",
                        "birth_year": "1938"
                    },
                    {
                        "name": "Karin",
                        "birth_year": "1938"
                    },
                    {
                        "name": "Lars",
                        "birth_year": "1940"
                    },
                    {
                        "name": "Anders",
                        "birth_year": "1943"
                    },
                    {
                        "name": "Mats",
                        "birth_year": "1948"
                    }
                ]
            }
        }
    }
}