{
    "original": "Trulson, Johan Edvard Theodor,\nskulptör, Malmö, f. 9/5/81 i Malmö av\nmassör Nils T. o. Ingrid Jönsson. G.\n31 m. Ingeborg Lenander. Barn: Ingel\no. Ellen ff. 31, Nils 33. — Stud. v. tekn.\nsk. o. v. Akad. f. de skjonne Kunster i\nKöpenhamn. Stud:resa t. Tyskl. 20. Bl.\nutf. arb.: modeller, av staty av Frans\nSuell i Malmö, fontän i Trelleb., byst\nav Bruzelius där, Flickan m. snäckan\ni stadsparken i Eslöv, staty av R. F.\nBerg i Limhamn, kolossalbyst av F. H.\nKockum i Malmö samt fontänerna\nFiskarpojken o. Najaden där m. fl.\nMedl. av Frimurarorden o. W-sex.\n\nTrulsson, Lars Otto, fil. dr, Lund, f.\n12/2/16 i Maglarp, Malmöh. 1., av Ture\nT. o. Blenda Larsson. G. 46 m. Kerstin\nHallbeck. Barn: Karin f. 47. —\nStud:-ex. 35, fil. mag. 39, fil. lic. 45, fil. dr 47.\nStud:res. i Tyskl. 38, Frankr. 46, Danm.\n46-47. E. adj. v. realsk. i Malmö 48,\nv. komm. gymn. i Trelleb. 48-49. Skr.:\nUlrik Scheffer som hattpolitiker\n(grad:avh. 47).\n\nTrägårdh, Sven Gustaf,\ncivilingenjör, Malmö, f. 17/1/14 i Landskrona.\nG. 40 m. Inga Stendahl. Barn:\nGunilla f. 42, Carl Gustaf 46. — Civ :ing\n:-ex. v. CTH (VoV) 37. Anst. i A-B\nArmerad Betong i Malmö sed. 37.\n\nTrönnberg, Nils Per Göran, med. lic,\nregementsläkare, Kristianstad, f. 25/7/\n11 i Sthlm av överlär. Per T. o.\nIngeborg Kinnwall. G. 39 m. Ruth Sjöfors.\nBarn: Gunnel f. 40, Kerstin 42, Anders\n\n45,  Eva 47. — Stud :ex. i Sthlm 30, med.\nkand. 32 o. med. lic. 37 v. Karol. inst.\nTf. andre und :läk. v. Kolmårdssan.\n37-38, tf. förste und :läk. 38, assist :läk. v.\nS :t Eriks sjukh. med. avd. 38-39, tf.\nförste und :läk. v. S :t Eriks prov. avd.\nå Karol. sjukh. 39. E. bat :läk. v.\nGar-n:sjukh. i Boden 40-43, tf. und :läk. v.\nSöderby sjukh. 43, reg:läk. v. Norra\nskånska inf:reg. sed. 44. Skr.: ett\ntiotal vetensk. arb. inom hæmatol. o.\ncar-diologi.\n\n",
    "structured": {
        "1": {
            "full_name": "Trulson, Johan Edvard Theodor",
            "location": "Malmö",
            "occupation": "skulptör",
            "birth_details": {
                "date": "09/05/1881",
                "place": "Malmö",
                "parents": "massör Nils T. o. Ingrid Jönsson"
            },
            "education": [
                {
                    "degree": "Stud. v. tekn. sk. o. v. Akad. f. de skjonne Kunster",
                    "year": "Tyskl. 1920",
                    "institution": "Köpenhamn"
                }
            ],
            "career": [
                {
                    "position": "skulptör",
                    "years": {
                        "start_year": 1920,
                        "end_year": null
                    },
                    "organization": null
                }
            ],
            "family": {
                "spouse": "Ingeborg Lenander",
                "marriage_year": "1931",
                "children": [
                    {
                        "name": "Ingel",
                        "birth_year": "1931"
                    },
                    {
                        "name": "Ellen",
                        "birth_year": "1931"
                    },
                    {
                        "name": "Nils",
                        "birth_year": "1933"
                    }
                ]
            }
        },
        "2": {
            "full_name": "Trulsson, Lars Otto",
            "location": "Lund",
            "occupation": "fil. dr",
            "birth_details": {
                "date": "12/02/1916",
                "place": "Maglarp, Malmöh. 1.",
                "parents": "Ture T. o. Blenda Larsson"
            },
            "education": [
                {
                    "degree": "Stud:-ex",
                    "year": "1935",
                    "institution": null
                },
                {
                    "degree": "fil. mag.",
                    "year": "1939",
                    "institution": null
                },
                {
                    "degree": "fil. lic.",
                    "year": "1945",
                    "institution": null
                },
                {
                    "degree": "fil. dr",
                    "year": "1947",
                    "institution": null
                }
            ],
            "career": [
                {
                    "position": "adj",
                    "years": {
                        "start_year": 1948,
                        "end_year": null
                    },
                    "organization": "realsk. i Malmö"
                },
                {
                    "position": "komm. gymn",
                    "years": {
                        "start_year": 1948,
                        "end_year": 1949
                    },
                    "organization": "Trelleb."
                }
            ],
            "family": {
                "spouse": "Kerstin Hallbeck",
                "marriage_year": "1946",
                "children": [
                    {
                        "name": "Karin",
                        "birth_year": "1947"
                    }
                ]
            }
        },
        "3": {
            "full_name": "Trägårdh, Sven Gustaf",
            "location": "Malmö",
            "occupation": "civilingenjör",
            "birth_details": {
                "date": "17/01/1914",
                "place": "Landskrona",
                "parents": null
            },
            "education": null,
            "career": [
                {
                    "position": "Civ :ing",
                    "years": {
                        "start_year": 1937,
                        "end_year": null
                    },
                    "organization": "A-B Armerad Betong i Malmö"
                }
            ],
            "family": {
                "spouse": "Inga Stendahl",
                "marriage_year": "1940",
                "children": [
                    {
                        "name": "Gunilla",
                        "birth_year": "1942"
                    },
                    {
                        "name": "Carl Gustaf",
                        "birth_year": "1946"
                    }
                ]
            }
        },
        "4": {
            "full_name": "Trönnberg, Nils Per Göran",
            "location": "Kristianstad",
            "occupation": "med. lic",
            "birth_details": {
                "date": "25/07/1911",
                "place": "Sthlm",
                "parents": "överlär. Per T. o. Ingeborg Kinnwall"
            },
            "education": [
                {
                    "degree": "Stud :ex",
                    "year": "1930",
                    "institution": "Sthlm"
                },
                {
                    "degree": "med. kand.",
                    "year": "1932",
                    "institution": "Karol. inst"
                },
                {
                    "degree": "med. lic",
                    "year": "1937",
                    "institution": "Karol. inst"
                }
            ],
            "career": [
                {
                    "position": "bat :läk",
                    "years": {
                        "start_year": 1940,
                        "end_year": 1943
                    },
                    "organization": "Gar-n:sjukh. i Boden"
                },
                {
                    "position": "reg:läk",
                    "years": {
                        "start_year": 1944,
                        "end_year": null
                    },
                    "organization": "Norra skånska inf:reg"
                }
            ],
            "family": {
                "spouse": "Ruth Sjöfors",
                "marriage_year": "1939",
                "children": [
                    {
                        "name": "Gunnel",
                        "birth_year": "1940"
                    },
                    {
                        "name": "Kerstin",
                        "birth_year": "1942"
                    },
                    {
                        "name": "Anders",
                        "birth_year": "1945"
                    },
                    {
                        "name": "Eva",
                        "birth_year": "1947"
                    }
                ]
            }
        }
    }
}