{
    "original": "OLSSON, G UNO, tekn dr, Hallsberg,\nf i Hallsberg, Örebro l, 8/6/95 av\nhernm:-äg Gustav O o Lovisa Eriksson.\nStud:ex Lund 18, KTH 23, tekn dr 57,\ning o konstr:ch Asea Ludvikav 24-60.\n-Led SvTF, SER. - Skr: Non-circular\nCylindrical Gears (drsavh 53),\nNon-circular Bevel Gears (59), upps i Tekn\ntidskr o Aseas tidn. - Utm: PatrSGM.\n-Hobby: vård av släktgård.\n\nOLSSON, K K VALDEMAR, leg\nläkare, Hedemora, f i Skärhamn, Gbgs o\nBohus l, 9/3/95 av handl Axel O o Klara\nRuckman.\n\nStud:ex Gbg 14, med kand Sthlm 18,\nmed lic Upps 26. - Tf prov :läk Tjörns\ndistr 22-23, l:e underläk Ronneby brunn\n25-27, prakt läk Hedemora 28, läk\nEpidemisjukstugan Hedemora 28-49, skolläk\nHedemora 29-61, läk Södra Dalarnes\nsjukhem 30-52, tf stadsläk Hedemora\n35-55, stadsläk 55-63, privatprakt där sed\n63. - Verksläk ab Hedemora verkstäder\nsed 29. - Stadsfullm Hedemora.\nGift 22 m Ingrid Carlsson f 96, dtr t\nstat:insp Joel C o Mathilda Jonsson.\n-Barn: Klas f 26, Kerstin f 29, Anders\nf 32.\n\nOLSSON, E ÅKE H, tandläkare,\nJakobsberg, f i Trollhättan 19/4/26 av tjm\nHugo O o Gertrud Andersson.\nStud:ex Vänersborg 46, tandläk:ex 53,\nanst distr:tandv Enkpg 53, prakt\nJakobsberg sed 57. - Medl Sthlms\ntand-läk:fören, Sv tandläk:sällsk. - Hobby:\nsport.\n\nOLSSON, J ÅKE, civilingenjör,\nVästerås, f i Nordingrå, Västernorrl l, 27/4/\n29 av köpm Karl O o Klara Rödén.\nStud:ex Härnösand 49,  KTH 54,  anst\nAsea Västerås 54, utveckl:ing där sed 60.\n- Hobbies: bridge, trädgårdsskötsel.\nGift 55 m Inga Sundström f 27, dtr t\nbyggm   Jonas   S   o   Greta   Näslund.\n-Barn: Ingrid f 58.\n\n",
    "structured": {
        "0": {
            "full_name": "G Uno Olsson",
            "location": "Hallsberg, Örebro l",
            "occupation": "tekn dr",
            "birth_details": {
                "date": "08/06/1895",
                "place": "Hallsberg, Örebro l",
                "parents": "hernm:-äg Gustav O o Lovisa Eriksson"
            },
            "education": [
                {
                    "degree": "Stud:ex",
                    "year": "1918",
                    "institution": "Lund"
                },
                {
                    "degree": "KTH",
                    "year": "1923",
                    "institution": "KTH"
                },
                {
                    "degree": "tekn dr",
                    "year": "1957",
                    "institution": "KTH"
                }
            ],
            "career": [
                {
                    "position": "ing o konstr:ch",
                    "years": {
                        "start_year": 1924,
                        "end_year": 1960
                    },
                    "organization": "Asea Ludvikav"
                }
            ],
            "family": {
                "spouse": "NULL",
                "marriage_year": "NULL",
                "children": [],
                "parents": "NULL"
            },
            "hobbies": [
                "vård av släktgård"
            ]
        },
        "1": {
            "full_name": "K K Valdemar Olsson",
            "location": "Hedemora",
            "occupation": "leg läkare",
            "birth_details": {
                "date": "09/03/1895",
                "place": "Skärhamn, Gbgs o Bohus l",
                "parents": "handl Axel O o Klara Ruckman"
            },
            "education": [
                {
                    "degree": "Stud:ex",
                    "year": "1914",
                    "institution": "Gbg"
                },
                {
                    "degree": "med kand",
                    "year": "1918",
                    "institution": "Sthlm"
                },
                {
                    "degree": "med lic",
                    "year": "1926",
                    "institution": "Upps"
                }
            ],
            "career": [
                {
                    "position": "tf stadsläk",
                    "years": {
                        "start_year": 1935,
                        "end_year": 1963
                    },
                    "organization": "Hedemora"
                }
            ],
            "family": {
                "spouse": "Ingrid Carlsson",
                "marriage_year": "1922",
                "children": [
                    {
                        "name": "Klas",
                        "birth_year": "1926"
                    },
                    {
                        "name": "Kerstin",
                        "birth_year": "1929"
                    },
                    {
                        "name": "Anders",
                        "birth_year": "1932"
                    }
                ],
                "parents": "NULL"
            },
            "hobbies": []
        },
        "2": {
            "full_name": "E Åke H Olsson",
            "location": "Jakobsberg",
            "occupation": "tandläkare",
            "birth_details": {
                "date": "19/04/1926",
                "place": "Trollhättan",
                "parents": "tjm Hugo O o Gertrud Andersson"
            },
            "education": [
                {
                    "degree": "Stud:ex",
                    "year": "1946",
                    "institution": "Vänersborg"
                },
                {
                    "degree": "tandläk:ex",
                    "year": "1953",
                    "institution": "NULL"
                }
            ],
            "career": [
                {
                    "position": "anst distr:tandv",
                    "years": {
                        "start_year": 1953,
                        "end_year": 1957
                    },
                    "organization": "Enkpg"
                },
                {
                    "position": "prakt",
                    "years": {
                        "start_year": 1957,
                        "end_year": "NULL"
                    },
                    "organization": "Jakobsberg"
                }
            ],
            "family": {
                "spouse": "NULL",
                "marriage_year": "NULL",
                "children": [],
                "parents": "NULL"
            },
            "hobbies": [
                "sport"
            ]
        },
        "3": {
            "full_name": "J Åke Olsson",
            "location": "Västerås",
            "occupation": "civilingenjör",
            "birth_details": {
                "date": "27/04/1929",
                "place": "Nordingrå, Västernorrl l",
                "parents": "köpm Karl O o Klara Rödén"
            },
            "education": [
                {
                    "degree": "Stud:ex",
                    "year": "1949",
                    "institution": "Härnösand"
                },
                {
                    "degree": "KTH",
                    "year": "1954",
                    "institution": "NULL"
                }
            ],
            "career": [
                {
                    "position": "anst",
                    "years": {
                        "start_year": 1954,
                        "end_year": "NULL"
                    },
                    "organization": "Asea Västerås"
                },
                {
                    "position": "utveckl:ing",
                    "years": {
                        "start_year": 1960,
                        "end_year": "NULL"
                    },
                    "organization": "ASEA"
                }
            ],
            "family": {
                "spouse": "Inga Sundström",
                "marriage_year": "1955",
                "children": [
                    {
                        "name": "Ingrid",
                        "birth_year": "1958"
                    }
                ],
                "parents": "NULL"
            },
            "hobbies": [
                "bridge",
                "trädgårdsskötsel"
            ]
        }
    }
}