{
    "original": "OMBERG, I TURE V, bruksdisponent,\n\nVikmanshyttan, f i Härnösand 6/9/13 av\ning Johan O o Arvida Nordenmark.\nKTH (bergs) 39, lab :ing Uddeholms ab\nHagfors järnverk 39, lab :ch St Kopparb\nbergsl ab Söderfors bruk 41, övering :ass\nFagersta bruks ab Fagerstaverken 48,\nchefsing där 51, verkst dir\nWikmans-hytte bruks ab sed 53. - Utm: RVO.\nGift 41 m fil lic Hildegard Blomqvist\nf 14, dtr t lektor Sven B o Alfhild\nWitte. - Barn: Margareta f 42.\n\nOÖM, BENGT O G, tekn lic, direktör,\n\nSödertälje, f i Snöstorp, Hall l, 27/12/18\nav civiling Gustaf O o Sigrid Bååth.\nStud:ex 37, KTH 43, tekn lic 55, stud\nUSA 47 o 53-54. - Lab :ch Sv\nkonserv-fabr Globus ab 43, sekt :ch materiallab\nAsea 45, serviceing Edström Trading Co\n47, ch materiallab LME 49, dir:ass ab\nAstra 53, bitr dir där 55, dir o ch Astra\nlab sed 59. - Sv led ISO Techn Comm\nnr 61 52-53. - Led SvTF (styr:led 59-61),\nmedl Sv kemiing riksfören (ordf 59-60),\nSv kemistsamf, Amer Chem Soc, New\nYork Acad of Se. - Medl Rotary,\nSö-dertelge skyttegille (ordf 58-64). - Skr:\nNKI-kursen Plastkemi (49), art Plaster\ni handb Råvaror o material (57) m fi\nart i facktidskr. - Utm: Södertelge\nskyt-teg ftjSM. - Hobbies: Skytte, konst,\nfotografering.\n\nGift 46 m Märta Landgren f 20, dtr t\npostmast Nils L o Anna Bergfors.\n-Barn: Björn f 48, Gunnar f 51.\n\nOPPERUD, ARVE, överingenjör,\nplatschef, Deje, fi Ullensaker, Norge, 3/3/11\nav hemm:äg Hans O o Marie Knai.\nStud:ex Oslo 30, NTH 35, ass h prof S\nSchmidt-Nielsen NTH Oslo 35-36,\nch:-kemist ab Mölnbacka-Trysil 53-62,\nlab:-förest Deje sulfatfabr o pappersbr 36-53,\nplatsch o övering där sed 62. - Medl\nFrimO, Rotary. - Hobbies: jakt,\nfriluftsliv.\n\nGift 37 m Ragna Kavli, dtr t agent\nWilhelm K o Marie Sevaldson. - Barn:\n\nInger-Marie   f   38,   Hans-Jörgen   f  42,\nArve f 49.\n",
    "structured": {
        "1": {
            "full_name": "Omberg, I Ture V",
            "location": "Vikmanshyttan",
            "occupation": "bruksdisponent",
            "birth_details": {
                "date": "06/09/1913",
                "place": "Härnösand",
                "parents": "Johan O and Arvida Nordenmark"
            },
            "education": [
                {
                    "degree": "KTH (bergs)",
                    "year": "1939",
                    "institution": "KTH"
                }
            ],
            "career": [
                {
                    "position": "lab :ing",
                    "years": {
                        "start_year": 1939,
                        "end_year": 1939
                    },
                    "organization": "Uddeholms ab Hagfors järnverk"
                },
                {
                    "position": "lab :ch",
                    "years": {
                        "start_year": 1941,
                        "end_year": 1941
                    },
                    "organization": "St Kopparbergs Län"
                },
                {
                    "position": "övering :ass",
                    "years": {
                        "start_year": 1948,
                        "end_year": 1948
                    },
                    "organization": "Fagersta bruks ab Fagerstaverken"
                },
                {
                    "position": "chefsing",
                    "years": {
                        "start_year": 1951,
                        "end_year": 1951
                    },
                    "organization": "Fagersta bruks ab Fagerstaverken"
                },
                {
                    "position": "verkst dir",
                    "years": {
                        "start_year": 1953,
                        "end_year": 1953
                    },
                    "organization": "Wikmanshytte bruks ab"
                }
            ],
            "family": {
                "spouse": "fil lic Hildegard Blomqvist",
                "marriage_year": "1941",
                "children": [
                    {
                        "name": "Margareta",
                        "birth_year": "1942"
                    }
                ]
            }
        },
        "2": {
            "full_name": "ÖÖM, Bengt O G",
            "location": "Södertälje",
            "occupation": "tekn lic, direktör",
            "birth_details": {
                "date": "27/12/1918",
                "place": "Snöstorp, Hall l",
                "parents": "civiling Gustaf O and Sigrid Bååth"
            },
            "education": [],
            "career": [
                {
                    "position": "lab :ch",
                    "years": {
                        "start_year": 1943,
                        "end_year": 1943
                    },
                    "organization": "Sv konservfabr Globus ab"
                },
                {
                    "position": "sekt :ch materiallab",
                    "years": {
                        "start_year": 1945,
                        "end_year": 1945
                    },
                    "organization": "Asea"
                },
                {
                    "position": "serviceing",
                    "years": {
                        "start_year": 1947,
                        "end_year": 1947
                    },
                    "organization": "Edström Trading Co"
                },
                {
                    "position": "ch materiallab",
                    "years": {
                        "start_year": 1949,
                        "end_year": 1949
                    },
                    "organization": "LME"
                },
                {
                    "position": "bitr dir",
                    "years": {
                        "start_year": 1955,
                        "end_year": 1955
                    },
                    "organization": "Astra lab"
                },
                {
                    "position": "dir o ch",
                    "years": {
                        "start_year": 1959,
                        "end_year": 1959
                    },
                    "organization": "Astra lab"
                }
            ],
            "family": {
                "spouse": "Märta Landgren",
                "marriage_year": "1946",
                "children": [
                    {
                        "name": "Björn",
                        "birth_year": "1948"
                    },
                    {
                        "name": "Gunnar",
                        "birth_year": "1951"
                    }
                ]
            },
            "hobbies": [
                "Skytte",
                "konst",
                "fotografering"
            ]
        },
        "3": {
            "full_name": "Opperud, Arve",
            "location": "Deje",
            "occupation": "överingenjör, platschef",
            "birth_details": {
                "date": "03/03/1911",
                "place": "Ullensaker, Norge",
                "parents": "Hans O and Marie Knai"
            },
            "education": [
                {
                    "degree": "NTH",
                    "year": "1935",
                    "institution": "NTH Oslo"
                }
            ],
            "career": [
                {
                    "position": "ass h prof",
                    "years": {
                        "start_year": 1935,
                        "end_year": 1936
                    },
                    "organization": "NTH Oslo"
                },
                {
                    "position": "ch:-kemist",
                    "years": {
                        "start_year": 1953,
                        "end_year": 1962
                    },
                    "organization": "ab Mölnbacka-Trysil"
                },
                {
                    "position": "lab:-förest",
                    "years": {
                        "start_year": 1936,
                        "end_year": 1953
                    },
                    "organization": "Deje sulfatfabr o pappersbr"
                },
                {
                    "position": "platsch o övering",
                    "years": {
                        "start_year": 1962,
                        "end_year": 1962
                    },
                    "organization": "Deje sulfatfabr o pappersbr"
                }
            ],
            "family": {
                "spouse": "Ragna Kavli",
                "marriage_year": "1937",
                "children": [
                    {
                        "name": "Inger-Marie",
                        "birth_year": "1938"
                    },
                    {
                        "name": "Hans-Jörgen",
                        "birth_year": "1942"
                    },
                    {
                        "name": "Arve",
                        "birth_year": "1949"
                    }
                ]
            },
            "hobbies": [
                "jakt",
                "friluftsliv"
            ]
        }
    }
}