{
    "original": "Nilsson, Carl-Axel Berthold,\ncivilingenjör, Malmö, f. 28/1/98 i Karlshamn\nav sjökapt. Bengt N. o. Ida Louisa\nJönsson. G. 26 m. Anna Diurson.\nBarn: Inga f. 27, Maud 31, Bengt\nArne 37. — Stud:ex. v. Gbgs h. re al 17,\nres :off. i kustart. 19, avg:ex. fr. CTI\n(kemi) 22. Ing:prakt. v. Wargöns\nPappersbr. 22-24, disp. v. Kem.-tekn.\nFabr. Carl i Malmö 25-35, försäljn\n:-chef v. A-B Malmö Strumpfabr. sed.\n36. Led. av Malmö stadsfullm. sed.\n30, ordf. i dess högergr. sed. 36, v. ordf.\ni beredn :utsk., drätselkamm.\nfinans-avd., Malmö’ stadsteat., konstnd, ordf.\ni samarb :nd f. konstfören. i Malmö\nm. fl. Styr:led. i Sydsv. Kraft A-B\nm. dotterbol., Hjälta A-B, Sv. A-B\nBromsregulator m. fl. RVO.\n\nNilsson, Daniel (Dan), arkitekt,.\nLimhamn, ’f. 16/2/911 i Limhamn av\n•byggm. Oscar N. o. Augusta Ekelund.\nG. 19 m. Ellen Karlsson.    Barn: Yrsa\n\nf.  24. — Ex. v. CTI (husbyggn :konst)\n17. Stud:res. t. Tyskl., Frankr. o.\nSchweiz. Arkit. i Allan Berglunds\nar-kit :byrå i Gbg 17-21, egen rör. i\nMalmö sed. 21. Varder :man f. Städ. Allm.\nBrandstodsbol., huv :man i Limihamns\nSparbank.\n\nNilsson, Nils Edvard, folkskollärare^\nBillinge, f. 3/12/96 i Bosarp, Malmöh.\n1, av Nils Andersson o. Emilia\nSvensson. — Folkskoll :ex. i Lund 18. Vik.\n.folkskoll. i Jonköp. 18, Svalöv 18-19,\nBrandsberga 19-24, ord. i Billinge sed.\n20, tillsynslär.    Kassör i Majbl :komm.\n\nNilsson, Edvin, rektor, Höganäs, L\nH/9/B5 i Ränneslöv, Hall. 1., av Nils\nPeter Olsson o. Anna Johansson. G.\n12 m. Emma Nilsson. Barn: Inga f.\n16, fil. mag., g. m. doc. Bertil Ej der,\nLund,   Kjell   Bockasten   17,   fil.   mag.,\n\ng.   m. Ingrid B rockman, Estrid 21, fil.\nmag. — Folkskoll :ex. 06, beh. t. ord.\nlär :befattn. v. h. folksk. 14. Res. t.\nTyskl. 09, 11 o. 13, Engl. 10 o. 38. E.\no. lär. v. Malmö folksk. 06, ord. 08,\nlär. v. Malmö borg:sk. fr. 10, ord.\nämneslär. i Väsby 19, rektor v. h. folksk.\ndär fr. 19. Skr.: Viktigare gagnväxter\n(3. uppl. 46).\n\n",
    "structured": {
        "0": {
            "full_name": "Carl-Axel Berthold Nilsson",
            "location": "Malmö",
            "occupation": "civilingenjör",
            "birth_details": {
                "date": "28/01/1898",
                "place": "Karlshamn",
                "parents": "sjökapt. Bengt N. o. Ida Louisa Jönsson"
            },
            "education": [
                {
                    "degree": "Stud:ex.",
                    "year": "1917",
                    "institution": "Gbgs h. real"
                },
                {
                    "degree": "res :off. i kustart.",
                    "year": "1919",
                    "institution": "CTI"
                }
            ],
            "career": [
                {
                    "position": "Ing:prakt.",
                    "years": {
                        "start_year": 1922,
                        "end_year": 1924
                    },
                    "organization": "Wargöns Pappersbr."
                },
                {
                    "position": "disp.",
                    "years": {
                        "start_year": 1925,
                        "end_year": 1935
                    },
                    "organization": "Kem.-tekn. Fabr. Carl i Malmö"
                },
                {
                    "position": "försäljn :chef",
                    "years": {
                        "start_year": 1936
                    },
                    "organization": "A-B Malmö Strumpfabr."
                }
            ],
            "family": {
                "spouse": "Anna Diurson",
                "marriage_year": "1926",
                "children": [
                    {
                        "name": "Inga",
                        "birth_year": "1927"
                    },
                    {
                        "name": "Maud",
                        "birth_year": "1931"
                    },
                    {
                        "name": "Bengt Arne",
                        "birth_year": "1937"
                    }
                ]
            }
        },
        "1": {
            "full_name": "Daniel (Dan) Nilsson",
            "location": "Limhamn",
            "occupation": "arkitekt",
            "birth_details": {
                "date": "16/02/1911",
                "place": "Limhamn",
                "parents": "byggm. Oscar N. o. Augusta Ekelund"
            },
            "education": [
                {
                    "degree": "Ex.",
                    "year": "1917",
                    "institution": "CTI"
                }
            ],
            "career": [
                {
                    "position": "Arkit.",
                    "years": {
                        "start_year": 1917,
                        "end_year": 1921
                    },
                    "organization": "Allan Berglunds ar-kit :byrå i Gbg"
                },
                {
                    "position": "egen rör.",
                    "years": {
                        "start_year": 1921
                    },
                    "organization": "Malmö"
                },
                {
                    "position": "Varder :man",
                    "years": {
                        "start_year": "Städ. Allm. Brandstodsbol.."
                    },
                    "organization": "Limihamns Sparbank"
                }
            ],
            "family": {
                "spouse": "Ellen Karlsson",
                "marriage_year": "1919",
                "children": [
                    {
                        "name": "Yrsa",
                        "birth_year": "1924"
                    }
                ]
            }
        },
        "2": {
            "full_name": "Nils Edvard Nilsson",
            "location": "Billinge",
            "occupation": "folkskollärare",
            "birth_details": {
                "date": "3/12/1896",
                "place": "Bosarp, Malmöh",
                "parents": "Nils Andersson o. Emilia Svensson"
            },
            "education": [
                {
                    "degree": "Folkskoll :ex.",
                    "year": "1918",
                    "institution": "Lund"
                }
            ],
            "career": [
                {
                    "position": "Vik. folkskoll.",
                    "years": {
                        "start_year": 1918,
                        "end_year": 1919
                    },
                    "organization": "Svalöv"
                },
                {
                    "position": "ord.",
                    "years": {
                        "start_year": "Billinge"
                    }
                },
                {
                    "position": "tillsynslär.",
                    "years": {
                        "start_year": "Majbl :komm."
                    }
                }
            ]
        },
        "3": {
            "full_name": "Edvin Nilsson",
            "location": "Höganäs",
            "occupation": "rektor",
            "birth_details": {
                "date": "9/7/1885",
                "place": "Ränneslöv, Hall. 1.",
                "parents": "Nils Peter Olsson o. Anna Johansson"
            },
            "education": [
                {
                    "degree": "Folkskoll :ex.",
                    "year": "1906",
                    "institution": "Lund"
                }
            ],
            "career": [
                {
                    "position": "E. o. lär.",
                    "years": {
                        "start_year": 1906,
                        "end_year": 1914
                    },
                    "organization": "Malmö"
                },
                {
                    "position": "ord. ämneslär.",
                    "years": {
                        "start_year": 1919
                    },
                    "organization": "Väsby"
                },
                {
                    "position": "rektor v.",
                    "years": {
                        "start_year": 1919
                    },
                    "organization": "h. folksk."
                }
            ],
            "family": {
                "spouse": "Emma Nilsson",
                "marriage_year": "1912",
                "children": [
                    {
                        "name": "Inga",
                        "birth_year": "1916"
                    },
                    {
                        "name": "Kjell Bockasten",
                        "birth_year": "1917"
                    },
                    {
                        "name": "Estrid",
                        "birth_year": "1921"
                    }
                ]
            }
        }
    }
}