{
    "original": "Norrseli, Karl Edvard, v.\nhäradshövding, fd. rådman, Hälsingborg, f. 27/\n9/66 i Hälsingb. G. 01 m. Marie-Louise\nLindahl. Barn: Sven f. 02, Bertil 03,\nGunnar 07. — Stud:ex. i Hälsingb. 84,\njur. fil. ex. 86, hovr :ex. 88. E. o. not.\ni Göta hovr. 89, v. här :hövd. 93,\nbrottmåls- o. polisnot. i Hälsingb. 99,\nrådman o. mag:sekr. där 11-31. Orrib\n:-man o. sekr. i drätselkamm. 95-99,\nsekr. h. stadsfullim. 00-11, fd. led. av\nstyr. f. Skånes stadsbyp:fören. o.\nSkånes bost :kreditfören. Hobby:\nväxter.   RNO,  RVO.\n\nNorrthon, Carl Peter, sjökapten,\nskeppsredare, Höganäs, f. 23/10/72 i\nHöganäs. G. 05 m. Nelly Hussénius.\n—. Sjökapt:ex. 94. Befälh. å\nsegelfart. 97, ångf. 00-16, skeppsred. sed.\n16, verkst. dir. i Red. A-B Höganäs,\nstyr :led. i Red. A-B Commercial,\nRed. A-B Walhall o. Wanadis. Ordf.\ni fattigvårdsstyreilsen 20-42, komm\n:-fullm. 27-35, ’stadsfullmäktige 36-42,\narb :lösh :kom’m. 35-42, Kullens\nhemb:-fören. styr. sed. 27. Kyrkovärd sed.\n23. V. ordf. i barnavmd 19-42, ordf.\ni byggn :nd sed. 35, nämndeman sed. 32,\nled. av styr. f. ett st. ant. föret. o.\nfören.  RNO,  RVO,  GMmf.\n\nNorström, Nils Gunnar Adolf,\nlandsfiskal, Landskrona, f. 10/4/02 i Saleby,\nSkaráb. 1., av Karl Axel N. o. Ellen\nEkelund. G. 29’ m. Dagny Petersson.\nBarn: Lennart f. 32, Bertil 3’6. —\nRealex. i Skara 18, stud. v. Gbgs\nhand :inst. 19-20, landsfiskalsex. 25. E.\nlandsfiskal i Charlottenberg 26,\nstän-digförordn. s. landsfiskal i Årjängs\ndi-str. 34, fullm. 41, landsfiskal i\nRönnebergs distr. fr. 47. I Årjäng ordf. i\ntax :nd  i  ol.   distr.,   ordf.   i  byggn :nd\n\n36-47, led. av hälsov :nd o. kyrkofullm.\nNFrK,\n\nNorström, Hugo Gotthild Fernando,\nläroverksadjunkt, Hälsingborg, f. 28/\n12/92 i Norra Mellby, Krist. 1., av\njärnhandl. August N. o. Mathilda\nSvensson. G. 26 m. Margareta\nDu-vander. Barn: Inger f. 27, Gunnel 29,\nRagnhild 36’. — Stud:ex. i Lund 09,\nfil. mag. 13. Provar v. norra real i\nSthlm 27. E. lär. i Lund 16, vik.\nlektor v. Malmö tekn. elem:sk. 17-18, e.\nlär. i Eslöv 18, ord. lär. o. timlär. i\nOsby 19-27, vik. adj. i Ängelholm\n28-29, vik. lekt., e. lär. v. b. a. 1. f. fl. i\nHälsingb. 29-33’, adj. i mat em. o. fys.\nsamt kemi där fr.  3’3.\n\n",
    "structured": {
        "1": {
            "full_name": "Norrseli, Karl Edvard",
            "location": "Hälsingborg",
            "occupation": "v. häradshövding, fd. rådman",
            "birth_details": {
                "date": "27/09/1866",
                "place": "Hälsingborg",
                "parents": null
            },
            "education": [
                {
                    "degree": "Stud:ex.",
                    "year": "1884",
                    "institution": "Hälsingborg"
                },
                {
                    "degree": "jur. fil. ex.",
                    "year": "1886",
                    "institution": "Hälsingborg"
                },
                {
                    "degree": "hovr :ex.",
                    "year": "1888",
                    "institution": null
                }
            ],
            "career": [
                {
                    "position": "E. o. not.",
                    "years": {
                        "start_year": 1889,
                        "end_year": 1889
                    },
                    "organization": "Göta hovr."
                },
                {
                    "position": "v. här :hövd.",
                    "years": {
                        "start_year": 1893,
                        "end_year": 1893
                    },
                    "organization": null
                },
                {
                    "position": "brottmåls- o. polisnot.",
                    "years": {
                        "start_year": 1899,
                        "end_year": 1899
                    },
                    "organization": "Hälsingborg"
                },
                {
                    "position": "rådman o. mag:sekr.",
                    "years": {
                        "start_year": 1911,
                        "end_year": 1931
                    },
                    "organization": "Hälsingborg"
                },
                {
                    "position": "Orrib :-man o. sekr. i drätselkamm.",
                    "years": {
                        "start_year": 1895,
                        "end_year": 1899
                    },
                    "organization": null
                },
                {
                    "position": "sekr. h. stadsfullim.",
                    "years": {
                        "start_year": 1900,
                        "end_year": 1911
                    },
                    "organization": null
                }
            ],
            "family": {
                "spouse": "Marie-Louise Lindahl",
                "marriage_year": "1901",
                "children": [
                    {
                        "name": "Sven",
                        "birth_year": "1902"
                    },
                    {
                        "name": "Bertil",
                        "birth_year": "1903"
                    },
                    {
                        "name": "Gunnar",
                        "birth_year": "1907"
                    }
                ]
            }
        },
        "2": {
            "full_name": "Norrthon, Carl Peter",
            "location": "Höganäs",
            "occupation": "sjökapten, skeppsredare",
            "birth_details": {
                "date": "23/10/1872",
                "place": "Höganäs",
                "parents": null
            },
            "education": [
                {
                    "degree": "Sjökapt:ex.",
                    "year": "1894",
                    "institution": null
                }
            ],
            "career": [
                {
                    "position": "Befälh. å segelfart.",
                    "years": {
                        "start_year": 1897,
                        "end_year": 1897
                    },
                    "organization": null
                },
                {
                    "position": "ångf.",
                    "years": {
                        "start_year": 1900,
                        "end_year": 1916
                    },
                    "organization": null
                },
                {
                    "position": "skeppsred.",
                    "years": {
                        "start_year": 1916,
                        "end_year": null
                    },
                    "organization": "Red. A-B Höganäs"
                }
            ],
            "family": {
                "spouse": "Nelly Hussénius",
                "marriage_year": "1905",
                "children": []
            }
        },
        "3": {
            "full_name": "Norström, Nils Gunnar Adolf",
            "location": "Landskrona",
            "occupation": "landsfiskal",
            "birth_details": {
                "date": "10/04/1902",
                "place": "Saleby, Skaráb. 1.",
                "parents": "Karl Axel N. and Ellen Ekelund"
            },
            "education": [
                {
                    "degree": "Realex.",
                    "year": "1918",
                    "institution": "Skara"
                },
                {
                    "degree": "stud. v. Gbgs hand :inst.",
                    "year": "1919-1920",
                    "institution": null
                },
                {
                    "degree": "landsfiskalsex.",
                    "year": "1925",
                    "institution": null
                }
            ],
            "career": [
                {
                    "position": "E. landsfiskal i Charlottenberg",
                    "years": {
                        "start_year": 1926,
                        "end_year": null
                    },
                    "organization": null
                },
                {
                    "position": "stän-digförordn. s. landsfiskal i Årjängs di-str.",
                    "years": {
                        "start_year": 1934,
                        "end_year": null
                    },
                    "organization": "Årjäng"
                },
                {
                    "position": "fullm.",
                    "years": {
                        "start_year": 1941,
                        "end_year": null
                    },
                    "organization": null
                },
                {
                    "position": "landsfiskal i Rönnebergs distr. fr. 47",
                    "years": {
                        "start_year": 1947,
                        "end_year": null
                    },
                    "organization": "Rönnebergs"
                }
            ],
            "family": {
                "spouse": "Dagny Petersson",
                "marriage_year": "1929",
                "children": [
                    {
                        "name": "Lennart",
                        "birth_year": "1932"
                    },
                    {
                        "name": "Bertil",
                        "birth_year": "1936"
                    }
                ]
            }
        },
        "4": {
            "full_name": "Norström, Hugo Gotthild Fernando",
            "location": "Hälsingborg",
            "occupation": "läroverksadjunkt",
            "birth_details": {
                "date": "28/12/1892",
                "place": "Norra Mellby, Krist. 1.",
                "parents": "August N. and Mathilda Svensson"
            },
            "education": [
                {
                    "degree": "Stud:ex.",
                    "year": "1909",
                    "institution": "Lund"
                },
                {
                    "degree": "fil. mag.",
                    "year": "1913",
                    "institution": null
                }
            ],
            "career": [
                {
                    "position": "Provar v. norra real i Sthlm",
                    "years": {
                        "start_year": 1927,
                        "end_year": null
                    },
                    "organization": "Sthlm"
                },
                {
                    "position": "lär. i Lund",
                    "years": {
                        "start_year": 1916,
                        "end_year": 1916
                    },
                    "organization": null
                },
                {
                    "position": "vik. lektor v. Malmö tekn. elem:sk.",
                    "years": {
                        "start_year": 1917,
                        "end_year": 1918
                    },
                    "organization": "Malmö"
                },
                {
                    "position": "e. lär. i Eslöv",
                    "years": {
                        "start_year": 1918,
                        "end_year": null
                    },
                    "organization": "Eslöv"
                },
                {
                    "position": "ord. lär. o. timlär. i Osby",
                    "years": {
                        "start_year": 1919,
                        "end_year": 1927
                    },
                    "organization": "Osby"
                },
                {
                    "position": "vik. adj. i Ängelholm",
                    "years": {
                        "start_year": 1928,
                        "end_year": 1929
                    },
                    "organization": "Ängelholm"
                },
                {
                    "position": "adj. i mat em. o. fys. samt kemi där fr. 3’3",
                    "years": {
                        "start_year": 1933,
                        "end_year": null
                    },
                    "organization": null
                }
            ],
            "family": {
                "spouse": "Margareta Du-vander",
                "marriage_year": "1926",
                "children": [
                    {
                        "name": "Inger",
                        "birth_year": "1927"
                    },
                    {
                        "name": "Gunnel",
                        "birth_year": "1929"
                    },
                    {
                        "name": "Ragnhild",
                        "birth_year": "1936"
                    }
                ]
            }
        }
    }
}