{
    "original": "GELLERSTEDT, B O (OLLE), civil-\n\ningenjör, Lycksele, f i Sthlm 31/8/20 av\nauktionsdir Harald G o Ellen\nAndersson.\n\nStud:ex 39, KTH 45, ing ab\nHammarby-verken 45, stat vattenf :verk 46, arb :ch\ndär sed 52. - Hobbies: sport, folkdans.\nGift 47 m Märta Larsson f 21, dtr t\nskogv Henrik L o Ellen Karlsson.\n-Barn: Dag f 51, Sten f 52.\n\nGERDIN, BENGT E GERLING-,\ntandläkare, Bjurholm, f i Milwaukee,\nUSA, 22/5/23 av ing Otto G o Ellen\nEriksson.\n\nStud:ex Vänersborg 43, tandl:ex Sthlm\n48, tandl folktandv Rimbo 49,\nass:-tandl Ronneby 49-50, Sthlm 50,\npriv:-prakt Bjurholm sed 50.\nGift 50 m Ulla Jonson f 27. - Barn:\nEllen Maria f 60.\n\nGERDIN, K GUNNAR, revisor,\nGävle, f i Sundsvall 14/12/13 av målarmäst\nGustaf G o Signe Nilsson.\nSundsvalls h hdlI 32, stud Tyskl 59 o 63,\nUSA 63; kamr 33-41, rev Sv:es\nlantbr:-förb 41, ekon :ch Gefleortens mejerifören\n\n52,   verkst   dir   Lärarnas   inköpscentral\nekon fören Gävle sed 57; eg rev:byrå\nsed 56. - Stadsrev Gävle. - Medl Odd\nFellow,    Rotary,    W-sex.    -    Hobbies:\nschack, bridge, filateli.\n\nGift 44 m Märta Olsson f 12, dtr t\nlantbr Måns O o h h. - Barn: Ulla f 45,\nBarbro f 47.\n\nGERHARDT, STEN O M, bitr förste\nprovinsialläkare, Östersund, f i Gbg l O/l/\n06 av järnv :kassör Gerhard G o Laura\nBock.\n\nStud:ex Gbg 24, med kand 27 o med lic\nSthlm 35, öl läk:förordn 35-38, underläk\nMariestads las 38-40, Kullbergska sjh\nKatrineholm 40-41, Mora las 41-44, tf\növerläk Mora o Strömstads las 44,\nprov:-läk Nossebro distr 45-50, Frösö distr\n51-58, bitr l:e prov:läk Jämtl l sed 55, l:e\nstadsdistr:läk Östersund 58-66, prakt läk\nsed 67. - Hobbies: musik, golf, bridge.\nGift 35 m Britta Fagrell f 09, dtr t\nbank-dir Viktor F o Beda Gabrielsson.\n-Barn: Magnus f 37, Folke f 42.\n\n",
    "structured": {
        "0": {
            "full_name": "GELLERSTEDT, B O (OLLE)",
            "location": "Lycksele",
            "occupation": "civilingenjör",
            "birth_details": {
                "date": "31/08/1920",
                "place": "Stockholm",
                "parents": "auktionsdir Harald G o Ellen Andersson"
            },
            "education": [
                {
                    "degree": "Stud:ex",
                    "year": "1939",
                    "institution": "KTH"
                },
                {
                    "degree": "ing ab",
                    "year": "1945",
                    "institution": "Hammarby-verken"
                }
            ],
            "career": [
                {
                    "position": "stat vattenf:verk",
                    "years": {
                        "start_year": 1946,
                        "end_year": 1952
                    },
                    "organization": "arb:ch"
                }
            ],
            "family": {
                "spouse": "Märta Larsson",
                "marriage_year": "1947",
                "children": [
                    {
                        "name": "Dag",
                        "birth_year": "1951"
                    },
                    {
                        "name": "Sten",
                        "birth_year": "1952"
                    }
                ]
            }
        },
        "1": {
            "full_name": "GERDIN, BENGT E GERLING-",
            "location": "Bjurholm",
            "occupation": "tandläkare",
            "birth_details": {
                "date": "22/05/1923",
                "place": "Milwaukee, USA",
                "parents": "ing Otto G o Ellen Eriksson"
            },
            "education": [
                {
                    "degree": "Stud:ex",
                    "year": "1943",
                    "institution": "Vänersborg"
                },
                {
                    "degree": "tandl:ex",
                    "year": "1948",
                    "institution": "Sthlm"
                }
            ],
            "career": [
                {
                    "position": "tandl folktandv",
                    "years": {
                        "start_year": 1949,
                        "end_year": 1950
                    },
                    "organization": "Rimbo"
                },
                {
                    "position": "ass:-tandl",
                    "years": {
                        "start_year": 1949,
                        "end_year": 1950
                    },
                    "organization": "Ronneby"
                },
                {
                    "position": "priv:-prakt",
                    "years": {
                        "start_year": 1950
                    },
                    "organization": "Bjurholm"
                }
            ],
            "family": {
                "spouse": "Ulla Jonson",
                "marriage_year": "1950",
                "children": [
                    {
                        "name": "Ellen Maria",
                        "birth_year": "1960"
                    }
                ]
            }
        },
        "2": {
            "full_name": "GERDIN, K GUNNAR",
            "location": "Gävle",
            "occupation": "revisor",
            "birth_details": {
                "date": "14/12/1913",
                "place": "Sundsvall",
                "parents": "målarmäst Gustaf G o Signe Nilsson"
            },
            "education": [
                {
                    "degree": "Sundsvalls h hdlI",
                    "year": "1932"
                },
                {
                    "degree": "stud Tyskl",
                    "year": "1959"
                }
            ],
            "career": [
                {
                    "position": "kamr",
                    "years": {
                        "start_year": 1933,
                        "end_year": 1941
                    },
                    "organization": "Gävleortens mejerifören"
                },
                {
                    "position": "verkst dir",
                    "years": {
                        "start_year": 1957
                    },
                    "organization": "Lärarnas inköpscentral ekon fören Gävle"
                }
            ],
            "family": {
                "spouse": "Märta Olsson",
                "marriage_year": "1944",
                "children": [
                    {
                        "name": "Ulla",
                        "birth_year": "1945"
                    },
                    {
                        "name": "Barbro",
                        "birth_year": "1947"
                    }
                ]
            },
            "hobbies": [
                "schack",
                "bridge",
                "filateli"
            ]
        },
        "3": {
            "full_name": "GERHARDT, STEN O M",
            "location": "Östersund",
            "occupation": "bitr förste provinsialläkare",
            "birth_details": {
                "date": "01/01/1906",
                "place": "Göteborg",
                "parents": "järnv:kassör Gerhard G o Laura Bock"
            },
            "education": [
                {
                    "degree": "Stud:ex",
                    "year": "1924",
                    "institution": "Gbg"
                },
                {
                    "degree": "med kand",
                    "year": "1927",
                    "institution": "Sthlm"
                }
            ],
            "career": [
                {
                    "position": "öl läk:förordn",
                    "years": {
                        "start_year": 1935,
                        "end_year": 1938
                    }
                },
                {
                    "position": "underläk",
                    "years": {
                        "start_year": 1938,
                        "end_year": 1940
                    },
                    "organization": "Mariestads las"
                },
                {
                    "position": "tf överläk",
                    "years": {
                        "start_year": 1944
                    },
                    "organization": "Mora o Strömstads las"
                }
            ],
            "family": {
                "spouse": "Britta Fagrell",
                "marriage_year": "1935",
                "children": [
                    {
                        "name": "Magnus",
                        "birth_year": "1937"
                    },
                    {
                        "name": "Folke",
                        "birth_year": "1942"
                    }
                ]
            },
            "hobbies": [
                "musik",
                "golf",
                "bridge"
            ]
        }
    }
}