{
    "original": "GEZELIUS,   L   GÖRAN,   överläkare,\n\nÖstersund, f i Norrkpg 25/7/02 av\napotekare Axel G o Signe Cleve.\nStud:ex Sthlm 21, med kand 25, med lic\n29, öl läk:förodn 30-34, underläk Gbgs\nbarnsjh 35-39, e läk med o pediatr avd\ncentrallås Gävle 40-43, överläk barnklin\nÖstersunds las sed 43. - Läk :ch f\nmottagande o vård av utl barn samt\nföredragande i med :styr 44, uppdr f WHO i\nGrekl 52, Iran 54-55. - Skr: upps i\npediatrik. - Utm: RNO, RFinlVRO.\n-Hobby: skytte.\n\nGift 48 m Birgit Liljedahl f 21, dtr t\nrådman Birger L o Gerda Håkansson.\n-Barn: Helena Maria f 51.\n\nGIDLÖF, NISSE, eo lektor, Lycksele,\nf i Hörnefors, Västerb l, 27/7/30 av Karl\nG o sömn :lär Agda Solin.\nFolkskollär:ex 51 o fil mag Upps 58;\nfolkskollär Lycksele landskn 51-55, adj\no eo lekt i matem o fysik hal Lycksele\nsed 58. - Medl Rotary. - Hobbies:\nskid-sport (tävl:ledare), folkdans.\nGift 55 m småskollär Vivi Israelsson\nf 31, dtr t faktor Sven I o Kerstin\nJakobsson. - Barn: Lena f 56, Mona f 59.\n\nGIDLÖF, P ÅKE H, tandläkare,\nSör-berge, f i Örnsköldsvik 12/6/29 av arb\nFingal G o Margit Höglund.\nStud:ex   49,   tandl:ex   Sthlm   54,   tandl\nfolktandv Skönsberg 54-56, ass:tandl\n56-57, priv:prakt Sörberge sed 57. - Medl\nFrimO. - Hobby: privatflyg.\nGift 52 m Else Wolff f 29, dtr t civ:ing\nNils W o Malle Graf. - Barn: Torbjörn\nf 53, Nina f 56, Anette f 62.\n\nGIFVARS,   K   HARRY,   tandläkare,\n\nStorvik, f i Sthlm 4/2/02 av byggm\nGifvas Olof Olsson o Frida Ekholm.\nStud:ex 22, med kand 27 o tandl:ex 30\nSthlm, vik Åmål o Sollentuna 30,\npriv:prakt Storvik sed 31, skoltandl sed 31.\n\n-  Medl Rotary. - Hobbies: fotografering,\nfiske.\n\nGift 31 m Astrid Domeij f 07, dtr t\nkassadir John D o Hulda Lundqvist.\n-Barn: Lars f 36, Anders f 40.\n\n",
    "structured": {
        "0": {
            "full_name": "Göran Gezelius",
            "location": "Östersund",
            "occupation": "överläkare",
            "birth_details": {
                "date": "25/07/1902",
                "place": "Norrköping"
            },
            "education": [
                {
                    "degree": "med kand",
                    "year": "1925",
                    "institution": "Sthlm"
                },
                {
                    "degree": "med lic",
                    "year": "1929",
                    "institution": "NULL"
                }
            ],
            "career": [
                {
                    "position": "öl läk:förodn",
                    "years": {
                        "start_year": 1930,
                        "end_year": 1934
                    },
                    "organization": "NULL"
                },
                {
                    "position": "underläk",
                    "years": {
                        "start_year": 1935,
                        "end_year": 1939
                    },
                    "organization": "Gbgs barnsjh"
                },
                {
                    "position": "e läk med o pediatr avd centrallås",
                    "years": {
                        "start_year": 1940,
                        "end_year": 1943
                    },
                    "organization": "Gävle"
                },
                {
                    "position": "överläk barnklin Östersunds las",
                    "years": {
                        "start_year": 1943,
                        "end_year": "NULL"
                    },
                    "organization": "NULL"
                }
            ],
            "family": {
                "spouse": "Birgit Liljedahl",
                "marriage_year": "1948",
                "children": [
                    {
                        "name": "Helena Maria",
                        "birth_year": "1951"
                    }
                ],
                "parents": "apotekare Axel G o Signe Cleve"
            },
            "hobbies": [
                "skytte"
            ]
        },
        "1": {
            "full_name": "Nisse Gidlöf",
            "location": "Lycksele",
            "occupation": "eo lektor",
            "birth_details": {
                "date": "27/07/1930",
                "place": "Hörnefors, Västerb l"
            },
            "education": [
                {
                    "degree": "fil mag",
                    "year": "1958",
                    "institution": "Upps"
                }
            ],
            "career": [
                {
                    "position": "folkskollär",
                    "years": {
                        "start_year": 1951,
                        "end_year": 1955
                    },
                    "organization": "Lycksele landskn"
                },
                {
                    "position": "adj o eo lekt i matem o fysik hal Lycksele",
                    "years": {
                        "start_year": 1958,
                        "end_year": "NULL"
                    },
                    "organization": "NULL"
                }
            ],
            "family": {
                "spouse": "Vivi Israelsson",
                "marriage_year": "1955",
                "children": [
                    {
                        "name": "Lena",
                        "birth_year": "1956"
                    },
                    {
                        "name": "Mona",
                        "birth_year": "1959"
                    }
                ],
                "parents": "Karl G o sömn :lär Agda Solin"
            },
            "hobbies": [
                "skid-sport (tävl:ledare)",
                "folkdans"
            ]
        },
        "2": {
            "full_name": "Åke H Gidlöf",
            "location": "Sörberge",
            "occupation": "tandläkare",
            "birth_details": {
                "date": "12/06/1929",
                "place": "Örnsköldsvik"
            },
            "education": [],
            "career": [
                {
                    "position": "tandl:ex",
                    "years": {
                        "start_year": 1954,
                        "end_year": "NULL"
                    },
                    "organization": "Sthlm"
                },
                {
                    "position": "tandl folktandv Skönsberg",
                    "years": {
                        "start_year": 1954,
                        "end_year": 1956
                    },
                    "organization": "NULL"
                },
                {
                    "position": "ass:tandl",
                    "years": {
                        "start_year": 1956,
                        "end_year": 1957
                    },
                    "organization": "NULL"
                },
                {
                    "position": "priv:prakt",
                    "years": {
                        "start_year": 1957,
                        "end_year": "NULL"
                    },
                    "organization": "Sörberge"
                }
            ],
            "family": {
                "spouse": "Else Wolff",
                "marriage_year": "1952",
                "children": [
                    {
                        "name": "Torbjörn",
                        "birth_year": "1953"
                    },
                    {
                        "name": "Nina",
                        "birth_year": "1956"
                    },
                    {
                        "name": "Anette",
                        "birth_year": "1962"
                    }
                ],
                "parents": "arb Fingal G o Margit Höglund"
            },
            "hobbies": [
                "privatflyg"
            ]
        },
        "3": {
            "full_name": "Harry Gifvars",
            "location": "Storvik",
            "occupation": "tandläkare",
            "birth_details": {
                "date": "04/02/1902",
                "place": "Sthlm"
            },
            "education": [
                {
                    "degree": "tandl:ex",
                    "year": "1930",
                    "institution": "Sthlm"
                }
            ],
            "career": [
                {
                    "position": "vik",
                    "years": {
                        "start_year": 1930,
                        "end_year": "NULL"
                    },
                    "organization": "Åmål o Sollentuna"
                },
                {
                    "position": "priv:prakt",
                    "years": {
                        "start_year": 1931,
                        "end_year": "NULL"
                    },
                    "organization": "Storvik"
                },
                {
                    "position": "skoltandl",
                    "years": {
                        "start_year": 1931,
                        "end_year": "NULL"
                    },
                    "organization": "NULL"
                }
            ],
            "family": {
                "spouse": "Astrid Domeij",
                "marriage_year": "1931",
                "children": [
                    {
                        "name": "Lars",
                        "birth_year": "1936"
                    },
                    {
                        "name": "Anders",
                        "birth_year": "1940"
                    }
                ],
                "parents": "byggm Gifvas Olof Olsson o Frida Ekholm"
            },
            "hobbies": [
                "fotografering",
                "fiske"
            ]
        }
    }
}