{
    "original": "GRANBERG, BROR A, polismästare,\n\nKalix, f i Haparanda 17/1/11 av\ngräns-överupps:man N P G o Elise Tano.\nLandsfiskalsex 35, bitr landsfiskal Norrb\n\n1   35, landsfiskal Karesuando 47, Töre\n52, Kalix 60, polismäst Kalix sed 65.\n-Civilförsv:ch Kalix, ordf\ntrafiksäkerh:-komm. - Medl Rotary. - Utm: FFrK4kl,\nRFinlVRO,   FMM.    -    Hobbies:   jakt,\nbridge.\n\nGift 40 m Edith Strömberg f 18, dtr t\növergruvfogde David S o Maria S.\n-Barn: Ulf f 41, Åke f 45, Ingegerd f 48,\nGunnar f 51.\n\nGRANBERG, J GEORG A,\nkyrkoherde, Funäsdalen, f i Stode, Vnorrl l,\n18/4/99 av folkskollär E A G o Kristina\nEngström.\n\nStud:ex Sundsvall 18, teol kand Upps\n27, prästv 28; ungd:ledare Upps\ndomk:-förs 20-26, past o l:e lär Åkerbr :kolonin\nHall 28, kommin Alnö 31, kyrkoh\nTän-näs past sed 34. - Landst:man sed 58.\n-Ordf Funäsdalens RK-krets sed 48 m m.\n- Skr ett flert skildr m motiv från\nHärjedalens fjällvärld. - Utm: LNO,\nRN-S:tOOlkl, SRKftjt, I I:s I 5:s, K I:s o\nI 14:s ftjt, Sv:es scoutfb förb:lilja.\n-Hobbies: fiske, litteratur.\n\n10 norr\n\nGift 1) 27 m Elsa Frykholm f 04, dtr t\nfolkskollär Lars F o Inga Wallin, 2) 59\nm Rut Mannerblad, dtr t jv:tjm A E M\no Hilma Åblad. - Barn: Christina f 32,\nStaffan f 35, Jörn f 38.\n\nGRANBERG, J HARRY,\ntegelbruks-ägare, Öjebyn, f i Öjebyn, Norrb l, 29/4/\n19 av hemm:äg Arvid G o Gerda\nHedkvist.\n\nAnst inom skogs- o jordbruk 41-46,\ninneh Framnäs tegelbruk ab 47-66 (ab sed\n60). - Hobby: fiske.\n\nGift 56 m Gunvor Fredriksson f 27, dtr\nt Johan F o Ida Isaksson. - Barn: Else\nf 56, Richard f 64.\n\n",
    "structured": {
        "1": {
            "full_name": "BROR A GRANBERG",
            "location": "Kalix",
            "occupation": "polismästare",
            "birth_details": {
                "date": "17/01/1911",
                "place": "Haparanda",
                "parents": "gräns-överupps. N P G o Elise Tano"
            },
            "education": [
                {
                    "degree": "landsfiskalsex",
                    "year": "1935",
                    "institution": "NULL"
                }
            ],
            "career": [
                {
                    "position": "bitr landsfiskal",
                    "years": {
                        "start_year": 1935,
                        "end_year": 1935
                    },
                    "organization": "Norrb"
                },
                {
                    "position": "landsfiskal",
                    "years": {
                        "start_year": 1935,
                        "end_year": 1935
                    },
                    "organization": "Karesuando"
                },
                {
                    "position": "polismäst",
                    "years": {
                        "start_year": 1965,
                        "end_year": "NULL"
                    },
                    "organization": "Kalix"
                }
            ],
            "family": {
                "spouse": "Edith Strömberg",
                "marriage_year": "1940",
                "children": [
                    {
                        "name": "Ulf",
                        "birth_year": "1941"
                    },
                    {
                        "name": "Åke",
                        "birth_year": "1945"
                    },
                    {
                        "name": "Ingegerd",
                        "birth_year": "1948"
                    },
                    {
                        "name": "Gunnar",
                        "birth_year": "1951"
                    }
                ]
            },
            "publications": "NULL",
            "community_involvement": "NULL",
            "board_memberships": "NULL",
            "honorary_titles": "NULL",
            "hobbies": [
                "jakt",
                "bridge"
            ]
        },
        "2": {
            "full_name": "J GEORG A GRANBERG",
            "location": "Funäsdalen",
            "occupation": "kyrkoherde",
            "birth_details": {
                "date": "18/04/1899",
                "place": "Stode, Vnorrl l",
                "parents": "folkskollär E A G o Kristina Engström"
            },
            "education": [
                {
                    "degree": "teol kand",
                    "year": "1927",
                    "institution": "Upps"
                }
            ],
            "career": [
                {
                    "position": "ungd:ledare",
                    "years": {
                        "start_year": 1920,
                        "end_year": 1926
                    },
                    "organization": "Upps domk:-förs"
                },
                {
                    "position": "past o l:e lär",
                    "years": {
                        "start_year": 1928,
                        "end_year": "NULL"
                    },
                    "organization": "Åkerbr :kolonin Hall"
                }
            ],
            "family": {
                "spouse": "Elsa Frykholm",
                "marriage_year": "1927",
                "children": [
                    {
                        "name": "Christina",
                        "birth_year": "1932"
                    },
                    {
                        "name": "Staffan",
                        "birth_year": "1935"
                    },
                    {
                        "name": "Jörn",
                        "birth_year": "1938"
                    }
                ]
            },
            "publications": "Skr ett flert skildr m motiv från Härjedalens fjällvärld",
            "community_involvement": "NULL",
            "board_memberships": "NULL",
            "honorary_titles": [
                "LNO",
                "RN-S:tOOlkl",
                "SRKftjt",
                "I I:s I 5:s",
                "K I:s o I 14:s ftjt",
                "Sv:es scoutfb förb:lilja"
            ],
            "hobbies": [
                "fiske",
                "litteratur"
            ]
        },
        "3": {
            "full_name": "J HARRY GRANBERG",
            "location": "Öjebyn, Norrb l",
            "occupation": "tegelbruks-ägare",
            "birth_details": {
                "date": "29/04/1919",
                "place": "Öjebyn",
                "parents": "hemm:äg Arvid G o Gerda Hedkvist"
            },
            "education": "NULL",
            "career": [
                {
                    "position": "inneh Framnäs tegelbruk ab",
                    "years": {
                        "start_year": 1947,
                        "end_year": 1966
                    },
                    "organization": "ab"
                }
            ],
            "family": {
                "spouse": "Gunvor Fredriksson",
                "marriage_year": "1956",
                "children": [
                    {
                        "name": "Else",
                        "birth_year": "1956"
                    },
                    {
                        "name": "Richard",
                        "birth_year": "1964"
                    }
                ]
            },
            "publications": "NULL",
            "community_involvement": "NULL",
            "board_memberships": "NULL",
            "honorary_titles": "NULL",
            "hobbies": [
                "fiske"
            ]
        }
    }
}