{
    "original": "GUSTAFSON, SETH, fil dr,\nseminarierektor, Härnösand, f i Alseda, Jönk\nl, 30/12/11 av lantbr Emil G o Alma\nJonsson.\n\nStud:ex Eksjö 31, fil mag 36, fil lic 44\no fil dr Lund 50, lekt i sv folksk:sem\nHärnösand sed 52, rekt där sed 56.\n-Medl FrimO, Rotary, SHT, S:t PetriO.\n-Skr: Hemming Gadhs språk (drsavh 50).\n- Utm: RNO.\n\nGift 40 m Tullie Boke f 12, dtr t disp\nOlof B o Agnes Olsson. - Barn: Göran\nf 42, Carl Johan f 46, Margareta f 48.\n\nGUSTAVSSON, V SIGVARD,\ncivilförsvarsdirektör, Gävle, f i Luleå 30/8/\n07 av tågmäst Viktor G o Anna\nHeden-grahn.\n\nStud:ex 27, Off:ex KS 31, fänr I 14 31,\nunderlöjtn 33, löjtn 35, kapt 41, major\n53. - KHS 42-44, FHS 54-55. - Bitr o tjf\nmil :attaché sv beskickn Hfors 44-46, tjg\nfst 46-47, mil:ass där 48-51, civilförsv:-\n\ndir länsstyr Gävleb l sed 51. - Medl\nSällsk NT Gävle, Lions club, InnocensO.\n- Utm: RSO, RNO, RFinlVROlkl,\nSCF-SM, Gävleb bfubSM, SRKSM, SCFftjtG,\nFBskftjMlklmsp. - Hobbies: jakt, fiske,\nbridge.\n\nGift 47 m Ruth Alfthan f 18, dtr t Karl\nJansson o Sigrid Andersson. - Barn:\nAgneta f 44, Christer f 48.\n\nGUSTAFSSON, STIG V, tandläkare,\n\nGävle, f i Söderhamn 18/1/25 av köpm\nEmil G o Annie Jansson.\nStud:ex Gävle 45, tandl:ex Sthlm 50,\ntandl folktandv Gävle 50-51, ass:tandl\nGävle 52-54, priv:prakt där sed 55.\n-Ordf Gävle tandl:fören 58-60, klubbm\nGävleb l tandl:fören sed 64; medl Lions\nclub, sällsk NT. - Hobby: golf.\nGift 53 m tandl Inga Forssell f 22, dtr t\nK G F o Gertrud Wedin. - Barn: Eva\nf 54, Lena f 58.\n\n",
    "structured": {
        "1": {
            "full_name": "Seth Gustafson",
            "location": "Härnösand",
            "occupation": "Seminarierektor",
            "birth_details": {
                "date": "30/12/1911",
                "place": "Alseda, Jönköping",
                "parents": "lantbr Emil G o Alma Jonsson"
            },
            "education": [
                {
                    "degree": "Stud:ex",
                    "year": "1931",
                    "institution": "Eksjö"
                },
                {
                    "degree": "Fil mag",
                    "year": "1936",
                    "institution": null
                },
                {
                    "degree": "Fil lic",
                    "year": "1944",
                    "institution": null
                },
                {
                    "degree": "Fil dr",
                    "year": "1950",
                    "institution": "Lund"
                }
            ],
            "career": [
                {
                    "position": "Lekt i sv folksk:sem",
                    "years": {
                        "start_year": 1952,
                        "end_year": 1956
                    },
                    "organization": "Härnösand"
                }
            ],
            "family": {
                "spouse": "Tullie Boke",
                "marriage_year": "1940",
                "children": [
                    {
                        "name": "Göran",
                        "birth_year": "1942"
                    },
                    {
                        "name": "Carl Johan",
                        "birth_year": "1946"
                    },
                    {
                        "name": "Margareta",
                        "birth_year": "1948"
                    }
                ]
            }
        },
        "2": {
            "full_name": "V Sigvard Gustavsson",
            "location": "Gävle",
            "occupation": "Civilförsvarsdirektör",
            "birth_details": {
                "date": "30/08/1907",
                "place": "Luleå",
                "parents": "tågmäst Viktor G o Anna Heden-grahn"
            },
            "education": [
                {
                    "degree": "Stud:ex",
                    "year": "1927",
                    "institution": null
                },
                {
                    "degree": "Off:ex",
                    "year": "1931",
                    "institution": "KS"
                }
            ],
            "career": [
                {
                    "position": "Bitr o tjf mil :attaché sv beskickn",
                    "years": {
                        "start_year": 1944,
                        "end_year": 1946
                    },
                    "organization": "Hfors"
                },
                {
                    "position": "Tjg fst",
                    "years": {
                        "start_year": 1946,
                        "end_year": 1947
                    },
                    "organization": null
                },
                {
                    "position": "Mil:ass",
                    "years": {
                        "start_year": 1948,
                        "end_year": 1951
                    },
                    "organization": "Hfors"
                },
                {
                    "position": "Civilförsv:dir länsstyr",
                    "years": {
                        "start_year": 1951,
                        "end_year": null
                    },
                    "organization": "Gävleb l"
                }
            ],
            "family": {
                "spouse": "Ruth Alfthan",
                "marriage_year": "1947",
                "children": [
                    {
                        "name": "Agneta",
                        "birth_year": "1944"
                    },
                    {
                        "name": "Christer",
                        "birth_year": "1948"
                    }
                ]
            },
            "hobbies": [
                "jakt",
                "fiske",
                "bridge"
            ]
        },
        "3": {
            "full_name": "Stig V Gustafsson",
            "location": "Gävle",
            "occupation": "Tandläkare",
            "birth_details": {
                "date": "18/01/1925",
                "place": "Söderhamn",
                "parents": "köpm Emil G o Annie Jansson"
            },
            "education": [
                {
                    "degree": "Stud:ex",
                    "year": "1945",
                    "institution": "Gävle"
                },
                {
                    "degree": "Tandl:ex",
                    "year": "1950",
                    "institution": "Sthlm"
                }
            ],
            "career": [
                {
                    "position": "Tandl folktandv",
                    "years": {
                        "start_year": 1950,
                        "end_year": 1951
                    },
                    "organization": "Gävle"
                },
                {
                    "position": "Ass:tandl",
                    "years": {
                        "start_year": 1952,
                        "end_year": 1954
                    },
                    "organization": "Gävle"
                },
                {
                    "position": "Priv:prakt",
                    "years": {
                        "start_year": 1955,
                        "end_year": null
                    },
                    "organization": "Gävle"
                }
            ],
            "family": {
                "spouse": "Inga Forssell",
                "marriage_year": "1953",
                "children": [
                    {
                        "name": "Eva",
                        "birth_year": "1954"
                    },
                    {
                        "name": "Lena",
                        "birth_year": "1958"
                    }
                ]
            },
            "hobbies": [
                "golf"
            ]
        }
    }
}