{
    "original": "Geyron, 3) 30 m skådesp:an Brita\nWerner (skilsm). - Barn: Per f 24.\n\nGERHARD, PER, regissör, Sthlm,\nf i Sthlm 23/6/24 av teaterdir Karl G\no Valborg Geyron.                                *\n\nDram teat elevsk 46-48, regissör o\nska-desp Norrkpgs stadsteat 48-50, Nya teat\nSthlm 50-52, ch Vasateat tills m Karl\nGerhard sed 52.\n\nGift 51 m skådesp:an Maj-Britt Nilsson\nf 24, dtr t Edmund N o Augusta Öberg.\n\nGERHARDSSON, GIDEON,\ncivil-ingenjör, Sthlm, f i Vännäs, Västerb\nl 4/8/20 av lantbruk Gerhard Abelsson\no Edith Sandström.\n\nSkellefteå tekn gymn 46, KTH 54,\nforskn:ing Bolidens gruv ab 46, stat\ninst f folkhälsan 49, l:e kemist där 56,\ntekn expert SAF sed 57. - Tekn ledare\narb:skyddsstyr koloxidutredn 57, ledare\nSAF:s högre dipl:kurs f skyddsing sed 59,\nv presid Comm VIII Internat Inst of\nWel-ding, sekr Fören f omgivn-.hygien, Sv\nläk:sällsk sektion f omgivn: hygien,\nFören Sv:es skyddstjm, led American\nIndustrial Hygiene Assoc, British Soc\nof Occupational Hygiene, American\nAir Poll Control Assoc, LSvTF.\n-Skr: i industri- o omgivn :hygieniska\nfrågor. - Hobby: topografi.\nGift 47 m Runa Rönnmark f 24, dtr t\nkamrer Alfred R o Linda Andersson.\n-Barn: Lars f 52, Maria f 56.\n\nGERRING, GUNNAR, ambassadråd,\nBonn, f i Sthlm 25/10/16 av lektor fil\ndr Hugo G p Hulan Åström.\nStud:ex 34, jur kand Upps 39, tingstjg\nSthlms rådhusr 40-42, attaché UD 42,\nMoskva 43, Budapest 46, 2:e sekr dep\n47, ambassadsekr Washington 49,\nAn-kara 51, l:e sekr dep 52, l:e\nambassadsekr Bern 57, ånyo l:e sekr dep 59,\nambassadråd Bonn sed 62. - Res:off:ex\n39, löjtn kav res 42-53. - Led sv-ung\nreg:-kommiss 48, omb v hdlsförhandl m\nBulgarien 47 o 49, Ungern 47, Jugoslavien\n48 o 49, sekr FN-deleg Paris 48 o New\nYork 50. - Bitr lär FHS 61-62.\n-Utm: RFMVRO, RTjslVLO.\nGift 51 m Ingrid Wikander f 19. - Barn:\nErik Gunnar f 52, Carl Gustaf f 54.\n\n",
    "structured": {
        "1": {
            "full_name": "GERHARD, PER",
            "location": "Sthlm",
            "occupation": "regissör",
            "birth_details": {
                "date": "23/06/1924",
                "place": "Sthlm"
            },
            "education": [
                {
                    "degree": "Dram teat elevsk",
                    "year": "1946-1948",
                    "institution": "N/A"
                },
                {
                    "degree": "N/A",
                    "year": "N/A",
                    "institution": "N/A"
                }
            ],
            "career": [
                {
                    "position": "regissör",
                    "years": {
                        "start_year": 1950,
                        "end_year": 1952
                    },
                    "organization": "Nya teat Sthlm"
                },
                {
                    "position": "ch Vasateat",
                    "years": {
                        "start_year": 1952,
                        "end_year": 1952
                    },
                    "organization": "N/A"
                }
            ],
            "family": {
                "spouse": "Maj-Britt Nilsson",
                "marriage_year": "1951",
                "children": [
                    {
                        "name": "Per",
                        "birth_year": "1950"
                    }
                ]
            }
        },
        "2": {
            "full_name": "GERHARDSSON, GIDEON",
            "location": "Sthlm",
            "occupation": "civil-ingenjör",
            "birth_details": {
                "date": "04/08/1920",
                "place": "Vännäs, Västerb"
            },
            "education": [
                {
                    "degree": "N/A",
                    "year": "N/A",
                    "institution": "N/A"
                }
            ],
            "career": {
                "position": "N/A",
                "years": {
                    "start_year": 1950,
                    "end_year": 1962
                },
                "organization": "N/A"
            },
            "family": {
                "spouse": "Runa Rönnmark",
                "marriage_year": "1947",
                "children": [
                    {
                        "name": "Lars",
                        "birth_year": "1952"
                    },
                    {
                        "name": "Maria",
                        "birth_year": "1956"
                    }
                ]
            },
            "hobbies": [
                "topografi"
            ]
        },
        "3": {
            "full_name": "GERRING, GUNNAR",
            "location": "Bonn",
            "occupation": "ambassadråd",
            "birth_details": {
                "date": "25/10/1916",
                "place": "Sthlm"
            },
            "education": [
                {
                    "degree": "N/A",
                    "year": "N/A",
                    "institution": "N/A"
                }
            ],
            "career": {
                "position": "N/A",
                "years": {
                    "start_year": 1950,
                    "end_year": 1962
                },
                "organization": "N/A"
            },
            "family": {
                "spouse": "Ingrid Wikander",
                "marriage_year": "1951",
                "children": [
                    {
                        "name": "Erik Gunnar",
                        "birth_year": "1952"
                    },
                    {
                        "name": "Carl Gustaf",
                        "birth_year": "1954"
                    }
                ]
            }
        }
    }
}