{
    "original": "GRABE, GERHARD,\nförsäkringsdirektör, Bromma, f i Sthlm 18/8/09 av\nmyntdir Alf G o Märta Notini.\nStudrex 28, kansliex 31, jur kand 35.\n-Stud MA 33; KS 40, fältpoliskurs 42.\n-Tjg Sthlms rådhusr o v assess där\n35-45, bitr sekr 45 års försäkriutredn\n45-49, omb:man Thule 49, bitr dir sed\n57. - Stynled Försäknjur fören, medl o\n\nsekr Sthlms kammärork, medl Mazerska\nkvartettsällsk 31, SHT 57.\nGift 39 m jur kand Birgit Erdmann\nf 13, dtr t v hovauditör Nils E o Elsa\nHerlin. - Barn: Inga f 41, Margareta\nf 43, Lennart f 46, Märta f 50.\n\nGRADIN,   ROLF   U,   civilingenjör,\n\nHuddinge, f i Sorsele, Västerb l, 23/5/30\nav hemmansäg Karl G o Sofia Linder.\nStudrex Uppsala 50, KTH 57, anst\nvattenfistyr 55, byrådir där. -\nKlubb-mast SER 59, fackred Tekn tidskr sed\n58. - Stud:res t Norge o Danm 42.\n-Hobbies: fiske, bridge.\nGift 54 m Marianne Körling f 30,\ndtr t fotograf Edvin H o Tekla\nSamuelsson. - Barn: Elisabeth f 55, Peter f 59.\n\nGRÄF, TIBOR, docent,\nSaltsjö-Duvnäs, f i Ersekujvår, Ungera, 2579/08.\nStudiex Budapest 26, elektroingrex\nÉcole Supérieure d’Électricité Paris 30,\nlicencié-és-sciences Sorbonne 32, fil lic\nSthlm 50, fil dr o doc StHS 51, käri&gt;\nfysik lab:stud Engl 51, anst h Marie\nCurie Curie-lab Paris 32,\nforskare Oslo univ 39, KTH 47, lektor i\nfysik Södra latinlärov Sthlm sed 54.\n-Medl Sv fysikersamf, Amer Phys Soc.\n-Skr: upps i kärnfysik.\nGift 46 m Barbro Moström, dtr t Frans\nM o Esther Malmerfelt. - Barn:\nMarie-Louise f 48, Elisabeth f 50.\n\nGRAF, J WILHELM, docent, Sthlm,\nf i Sthlm 7/2/20.\n\nStud:ex 38, med kand 41, med lic 46,\nmed dr 59, doc i invärtes medicin Karol\ninst sed 60. - Öl förordn Karol inst 40-52,\ncardiol avd Kronpr Lovisas barnsjh\n46-49, tf underläk med avd S:t Eriks sjh\n49, l:e underläk där sed 51. - Sekr Sv\nläkisällsk sekt f gastroenterologi. - Skr\ni histol, med o div populärmed.\n\n",
    "structured": {
        "0": {
            "full_name": "Gerhard Grabe",
            "location": "Bromma",
            "occupation": "försäkringsdirektör",
            "birth_details": {
                "date": "18/08/1909",
                "place": "Stockholm",
                "parents": "Alf G and Märta Notini"
            },
            "education": [
                {
                    "degree": "Studiex",
                    "year": "1928",
                    "institution": "NULL"
                },
                {
                    "degree": "kansliex",
                    "year": "1931",
                    "institution": "NULL"
                },
                {
                    "degree": "jur kand",
                    "year": "1935",
                    "institution": "NULL"
                },
                {
                    "degree": "Stud MA",
                    "year": "1933",
                    "institution": "NULL"
                },
                {
                    "degree": "KS",
                    "year": "1940",
                    "institution": "NULL"
                },
                {
                    "degree": "fältpoliskurs",
                    "year": "1942",
                    "institution": "NULL"
                }
            ],
            "career": [
                {
                    "position": "Tjg Sthlms rådhusr o v assess",
                    "years": {
                        "start_year": 1935,
                        "end_year": 1945
                    },
                    "organization": "NULL"
                },
                {
                    "position": "bitr sekr",
                    "years": {
                        "start_year": 1945,
                        "end_year": 1949
                    },
                    "organization": "års försäkriutredn"
                },
                {
                    "position": "omb:man",
                    "years": {
                        "start_year": 1949,
                        "end_year": 1949
                    },
                    "organization": "Thule"
                },
                {
                    "position": "bitr dir",
                    "years": {
                        "start_year": 1957,
                        "end_year": 1957
                    },
                    "organization": "NULL"
                }
            ],
            "family": {
                "spouse": "Birgit Erdmann",
                "marriage_year": "1939",
                "children": [
                    {
                        "name": "Inga",
                        "birth_year": "1941"
                    },
                    {
                        "name": "Margareta",
                        "birth_year": "1943"
                    },
                    {
                        "name": "Lennart",
                        "birth_year": "1946"
                    },
                    {
                        "name": "Märta",
                        "birth_year": "1950"
                    }
                ]
            }
        },
        "1": {
            "full_name": "Rolf U Gradin",
            "location": "Huddinge",
            "occupation": "civilingenjör",
            "birth_details": {
                "date": "23/05/1930",
                "place": "Sorsele, Västerbotten",
                "parents": "Karl G and Sofia Linder"
            },
            "education": [
                {
                    "degree": "Studrex",
                    "year": "1950",
                    "institution": "Uppsala"
                },
                {
                    "degree": "KTH",
                    "year": "1957",
                    "institution": "NULL"
                }
            ],
            "career": [
                {
                    "position": "anst vattenfistyr",
                    "years": {
                        "start_year": 1955,
                        "end_year": 1955
                    },
                    "organization": "NULL"
                },
                {
                    "position": "byrådir",
                    "years": {
                        "start_year": 1957,
                        "end_year": 1957
                    },
                    "organization": "KTH"
                }
            ],
            "family": {
                "spouse": "Marianne Körling",
                "marriage_year": "1954",
                "children": [
                    {
                        "name": "Elisabeth",
                        "birth_year": "1955"
                    },
                    {
                        "name": "Peter",
                        "birth_year": "1959"
                    }
                ]
            },
            "hobbies": [
                "fiske",
                "bridge"
            ]
        },
        "2": {
            "full_name": "Tibor Gräf",
            "location": "Saltsjö-Duvnäs",
            "occupation": "docent",
            "birth_details": {
                "date": "25/07/1908",
                "place": "Ersekujvár, Ungern",
                "parents": "NULL"
            },
            "education": [
                {
                    "degree": "Studiex",
                    "year": "1926",
                    "institution": "Budapest"
                },
                {
                    "degree": "elektroingrex",
                    "year": "1930",
                    "institution": "École Supérieure d’Électricité Paris"
                },
                {
                    "degree": "licencié-és-sciences",
                    "year": "1932",
                    "institution": "Sorbonne"
                },
                {
                    "degree": "fil lic",
                    "year": "1950",
                    "institution": "Stockholm"
                },
                {
                    "degree": "fil dr",
                    "year": "1951",
                    "institution": "StHS"
                }
            ],
            "career": [
                {
                    "position": "fysik lab:stud",
                    "years": {
                        "start_year": 1951,
                        "end_year": 1951
                    },
                    "organization": "Engl"
                },
                {
                    "position": "forskare",
                    "years": {
                        "start_year": 1939,
                        "end_year": 1939
                    },
                    "organization": "Oslo univ"
                },
                {
                    "position": "forskare",
                    "years": {
                        "start_year": 1947,
                        "end_year": 1947
                    },
                    "organization": "KTH"
                },
                {
                    "position": "lektor i fysik",
                    "years": {
                        "start_year": 1954,
                        "end_year": 1954
                    },
                    "organization": "Södra latinlärov Sthlm"
                }
            ],
            "family": {
                "spouse": "Barbro Moström",
                "marriage_year": "1946",
                "children": [
                    {
                        "name": "Marie-Louise",
                        "birth_year": "1948"
                    },
                    {
                        "name": "Elisabeth",
                        "birth_year": "1950"
                    }
                ]
            }
        },
        "3": {
            "full_name": "J Wilhelm Graf",
            "location": "Stockholm",
            "occupation": "docent",
            "birth_details": {
                "date": "07/02/1920",
                "place": "Stockholm",
                "parents": "NULL"
            },
            "education": [
                {
                    "degree": "Stud:ex",
                    "year": "1938",
                    "institution": "NULL"
                },
                {
                    "degree": "med kand",
                    "year": "1941",
                    "institution": "NULL"
                },
                {
                    "degree": "med lic",
                    "year": "1946",
                    "institution": "NULL"
                },
                {
                    "degree": "med dr",
                    "year": "1959",
                    "institution": "NULL"
                }
            ],
            "career": [
                {
                    "position": "Öl förordn",
                    "years": {
                        "start_year": 1940,
                        "end_year": 1952
                    },
                    "organization": "Karol inst"
                },
                {
                    "position": "cardiol avd",
                    "years": {
                        "start_year": 1946,
                        "end_year": 1949
                    },
                    "organization": "Kronpr Lovisas barnsjh"
                },
                {
                    "position": "tf underläk med avd",
                    "years": {
                        "start_year": 1949,
                        "end_year": 1951
                    },
                    "organization": "S:t Eriks sjh"
                },
                {
                    "position": "l:e underläk där",
                    "years": {
                        "start_year": 1951,
                        "end_year": 1951
                    },
                    "organization": "NULL"
                }
            ]
        }
    }
}