{
    "original": "GRANERUS, GÖSTA K R, direktör,\nBromma, f i Malmö 4/11/07 av\nsnickar-mäst C August G o Selma Roth.\nStudrex 28, DHS 31, dir rass Sv\ntelegr:-byrån Malmö 33, annonsdir AB Sthlm\n43, v verkst dir förlagshuset Norden\nMalmö 45, verkst dir Graf maskin ab\nTrollhättan 52, ab Dentatus o\nDiamantprodukter ab Sthlm sed 56 (styrrled).\nGift 38 m Ulla Olsson. - Barn: Gunilla\nf 38, Ulf f 42.\n\nGRANFELT, HANS O C, kapten,\nDjursholm, f i Sthlm 26/10/97 av\nun-derlöjtn Fredrik G o Maria Sundberg.\nStudrex 16, offrex 18, fänr I 2* 18,\növergrstat 25, kapt 33, gymnrdirrex 25.\n\n-   Försäljnrch   J   G   Swartz   ab   Sthlm\n28-57,   ab   Gust   Richter   26-61,   inneh\nexp rf ra Scandia Foreign Trade sed 36.\n\n-   Styrrordf  ab   Gust  Richter  60,  ordf\nFäktarbröderna 47-60. - 2:a pris lagtävl\nvärja OS Berlin 36, 10 individ SM värja\no sabel, olympiaman diskus Antwerpen\n20, 3 re pris diskus Sv spelen Gbg 23.\n-Utm:   RSO,   Sv   fäktförb   GM,\nSTidr-plak,  TyOlMM,  Frdel’EPhGM.\n\nGift 24 m Kate Richter f 03, dtr t\nkonsul Gustaf R o Gerda Nordwall.\n-Barn: Catharina f 26, Jan f 30, Lars\nf 35.\n\nGRANFELT,  HELGE  V,  fil  dr,  fd\nlektor,  Bromma,  f  i Uddevalla 4/3/91\nav verkmäst Josef Jakobsson o Maria\nAndersson.\nStudrex Gbg 11, fil kand  16, fil måg\n\n20,  fil lic 21, fil dr 24; vik adj Jönkpg\n\n21,  eo lär folksk f tekn utbildn Sthlm\n23, v adj hal f g å Södermalm 26,\nlektor hal Umeå 26, rektor 30-41, rektor\nhal Västerås 42,  lektor Kungsholmens\nhal 43-58. - Öl uppdrag Umeå, styr:led\nhist:lär   fören   m   m.   -   Skr:\nTrippelalliansen (bd I 24, bd II 61),\nNationernas förbund (25), Gustavsbergs barnhus\no badort (26), Samhället sådant det\nblivit (37,  2:a uppl 40), Sovjetunionen o\nminoriteternas  rätt  (45),  Striden  kring\nrebus sic stantibus etc (45), Om\nbegreppen anfall o anfallskrig (47), Politik o\nfolkrätt (48), Frågan om den\ninternationella rättens supremati (49),\nNeutralitet  o  försvarsallianser  (49),  Bilder  o\nberättelser ur Världshistorien I-V (tills\nm Hagnell-Olander 53-57), upps i\ntidskr.   -   Sign:   H.   G.   (Grt).   -    Utm:\nRNO.\n\nGift 1) 16 m Gertrud Häller f 94 d 16,\ndtr t Karl H, 2) 23 m Margarethe\nKohm f 98, dtr t prof Hans K (Wien)\no Maria Schubert. - Barn: Ingrid f 16,\nSonja f 25, Solveig f 28, Gunvor f 32.\n\n",
    "structured": {
        "0": {
            "full_name": "GÖSTA KRISTOFFER ROTH GRANERUS",
            "location": "Bromma",
            "occupation": "direktör",
            "birth_details": {
                "date": "04/11/1907",
                "place": "Malmö",
                "parents": "C August G o Selma Roth"
            },
            "education": [
                {
                    "degree": "Studrex",
                    "year": "1928",
                    "institution": ""
                },
                {
                    "degree": "DHS",
                    "year": "1931",
                    "institution": ""
                }
            ],
            "career": [
                {
                    "position": "dir rass Sv telegr:-byrån Malmö",
                    "years": {
                        "start_year": 1933,
                        "end_year": null
                    },
                    "organization": ""
                },
                {
                    "position": "annonsdir AB Sthlm",
                    "years": {
                        "start_year": 1943,
                        "end_year": null
                    },
                    "organization": ""
                },
                {
                    "position": "v verkst dir förlagshuset Norden Malmö",
                    "years": {
                        "start_year": 1945,
                        "end_year": null
                    },
                    "organization": ""
                },
                {
                    "position": "verkst dir Graf maskin ab Trollhättan",
                    "years": {
                        "start_year": 1952,
                        "end_year": null
                    },
                    "organization": ""
                },
                {
                    "position": "ab Dentatus o Diamantprodukter ab Sthlm",
                    "years": {
                        "start_year": 1956,
                        "end_year": null
                    },
                    "organization": "(styrrled)"
                }
            ],
            "family": {
                "spouse": "Ulla Olsson",
                "marriage_year": "1938",
                "children": [
                    {
                        "name": "Gunilla",
                        "birth_year": "1938"
                    },
                    {
                        "name": "Ulf",
                        "birth_year": "1942"
                    }
                ]
            }
        },
        "1": {
            "full_name": "HANS OLOF  CARL GRANFELT",
            "location": "Djursholm",
            "occupation": "kapten",
            "birth_details": {
                "date": "26/10/1897",
                "place": "Sthlm",
                "parents": "Fredrik G o Maria Sundberg"
            },
            "education": [
                {
                    "degree": "Studrex",
                    "year": "1916",
                    "institution": ""
                }
            ],
            "career": [
                {
                    "position": "Försäljnrch J G Swartz ab Sthlm",
                    "years": {
                        "start_year": 1928,
                        "end_year": 1957
                    },
                    "organization": ""
                },
                {
                    "position": "ab Gust Richter",
                    "years": {
                        "start_year": 1926,
                        "end_year": 1961
                    },
                    "organization": ""
                },
                {
                    "position": "inneh exp rf ra Scandia Foreign Trade",
                    "years": {
                        "start_year": 1936,
                        "end_year": null
                    },
                    "organization": "sed 36"
                },
                {
                    "position": "Styrrordf ab Gust Richter",
                    "years": {
                        "start_year": 1960,
                        "end_year": null
                    },
                    "organization": ""
                },
                {
                    "position": "ordf Fäktarbröderna",
                    "years": {
                        "start_year": 1947,
                        "end_year": 1960
                    },
                    "organization": ""
                }
            ],
            "family": {
                "spouse": "Kate Richter",
                "marriage_year": "1924",
                "children": [
                    {
                        "name": "Catharina",
                        "birth_year": "1926"
                    },
                    {
                        "name": "Jan",
                        "birth_year": "1930"
                    },
                    {
                        "name": "Lars",
                        "birth_year": "1935"
                    }
                ]
            }
        },
        "2": {
            "full_name": "HELGE VILHELM GRANFELT",
            "location": "Bromma",
            "occupation": "fil dr, fd lektor",
            "birth_details": {
                "date": "04/03/1891",
                "place": "Uddevalla",
                "parents": "Josef Jakobsson o Maria Andersson"
            },
            "education": [
                {
                    "degree": "Studrex Gbg",
                    "year": "1911",
                    "institution": ""
                },
                {
                    "degree": "fil kand",
                    "year": "1916",
                    "institution": ""
                },
                {
                    "degree": "fil måg",
                    "year": "1920",
                    "institution": ""
                },
                {
                    "degree": "fil lic",
                    "year": "1921",
                    "institution": ""
                },
                {
                    "degree": "fil dr",
                    "year": "1924",
                    "institution": ""
                }
            ],
            "career": [
                {
                    "position": "vik adj Jönkpg",
                    "years": {
                        "start_year": 1921,
                        "end_year": null
                    },
                    "organization": ""
                },
                {
                    "position": "eo lär folksk f tekn utbildn Sthlm",
                    "years": {
                        "start_year": 1923,
                        "end_year": null
                    },
                    "organization": ""
                },
                {
                    "position": "v adj hal f g å Södermalm",
                    "years": {
                        "start_year": 1926,
                        "end_year": null
                    },
                    "organization": ""
                },
                {
                    "position": "lektor hal Umeå",
                    "years": {
                        "start_year": 1926,
                        "end_year": null
                    },
                    "organization": ""
                },
                {
                    "position": "rektor",
                    "years": {
                        "start_year": 1930,
                        "end_year": 1941
                    },
                    "organization": ""
                },
                {
                    "position": "rektor hal Västerås",
                    "years": {
                        "start_year": 1942,
                        "end_year": null
                    },
                    "organization": ""
                },
                {
                    "position": "lektor Kungsholmens hal",
                    "years": {
                        "start_year": 1943,
                        "end_year": 1958
                    },
                    "organization": ""
                }
            ],
            "family": {
                "spouse": "Gertrud Häller",
                "marriage_year": "1916",
                "children": [
                    {
                        "name": "Ingrid",
                        "birth_year": "1916"
                    },
                    {
                        "name": "Sonja",
                        "birth_year": "1925"
                    },
                    {
                        "name": "Solveig",
                        "birth_year": "1928"
                    },
                    {
                        "name": "Gunvor",
                        "birth_year": "1932"
                    }
                ]
            },
            "publications": [
                {
                    "title": "Trippelalliansen (bd I 24, bd II 61)",
                    "year": "",
                    "type": ""
                },
                {
                    "title": "Nationernas förbund (25)",
                    "year": "",
                    "type": ""
                },
                {
                    "title": "Gustavsbergs barnhus o badort (26)",
                    "year": "",
                    "type": ""
                },
                {
                    "title": "Samhället sådant det blivit (37, 2:a uppl 40)",
                    "year": "",
                    "type": ""
                },
                {
                    "title": "Sovjetunionen o minoriteternas rätt (45)",
                    "year": "",
                    "type": ""
                },
                {
                    "title": "Striden kring rebus sic stantibus etc (45)",
                    "year": "",
                    "type": ""
                },
                {
                    "title": "Om begreppen anfall o anfallskrig (47)",
                    "year": "",
                    "type": ""
                },
                {
                    "title": "Politik o folkrätt (48)",
                    "year": "",
                    "type": ""
                },
                {
                    "title": "Frågan om den internationella rättens supremati (49)",
                    "year": "",
                    "type": ""
                },
                {
                    "title": "Neutralitet o försvarsallianser (49)",
                    "year": "",
                    "type": ""
                },
                {
                    "title": "Bilder o berättelser ur Världshistorien I-V (tills m Hagnell-Olander 53-57)",
                    "year": "",
                    "type": ""
                }
            ],
            "honorary_titles": [
                {
                    "title": "RNO",
                    "institution": "",
                    "year": ""
                }
            ]
        }
    }
}