{
    "original": "GEDAL, HARRY G L,\nredaktionschef, Enskede, f i Gällivare 28/6/19\nav gruvarb Gunnar G o Svea\nSandman.\n\nRealex 36, journ Norrl :folket Kiruna\n36, notisch Norrl Socialdem Boden 44,\nred:sekr Nya Norrl Sollefteå 51, MT\nSthlm 53, notisch AT 55, redrsekr ST\n56, red:ch där sed 61. - Led SJF:s VU\n56-62, medl Sthlms journ:fören (ordf\n57-61), TempelriddarO.\nGift 42 m Kerstin Degerman f 20, dtr\nt gruvbygg Olof D o Sara Kramer.\n-Barn: Mats f 46, Lars f 51.\n\nGEDDA,   H   G   NICOLAI,\noperasångare,  Vällingby,  f  i  Sthlm   11/7/25\nav  sångare   Michail  Ustinoff   o   Olga\nGedda.\n\nStudrex 44, MA 49-50, stip K teat\n51-52, debut 52 (tenor). - Konserter Rom\n52, Paris 53 o 55, Wien 55,\nAix-en-Provence 54-55, gästsp operan München,\nLuzern, Milano o Rom ffg 53, Paris,\nLondon o Wien ffg 54, festspelen\nSalzburg 57-59 o Edinburgh 58 o 59, eng\nMetropolitan New York 57. - Bl roller:\nDon Ottavio, Tamino, Hertigen, Faust,\nHüon i Oberon, Orphée, Alfred i\nTra-viata.\n\nGEDDA, PER O H, advokat,\nSaltsjö-Duvnäs, f i V Frölunda, Gbg o Boh l,\n28/8/14 av dir Harald G o Hilda\nWallerius.\n\nStudrex Gbg 34, jur kand Upps’ 38,\ntingstjg Askims, Hisings o Sävedals doms\n39-42, Gbgs hamnstyr 42-43, bitr jurist\nEmil Heijnes advibyrå Sthlm 43, deläg\nsed 49. - LSA 46. - Styrrordf Bolinders\nfabriks ab, stynled ab Metallimport.\n-Löjtn Sjövärnskåren, v ordf KSSS, Sv\nseglarförb. - Medl SHT. - Sv mast\nstar-båtssegl 32, 2:a pris OS 52, KSSS\nrorsGM, KSSS ftjSM. - Skr: Segling\n(60). - Hobby: segling.\nGift 43 m Barbro H:son-Ericson f 22,\ndtr t amiral Stig H-E o Barbro\nAhnström. - Barn: Catarina f 44, Viveca f\n47, Terese f 53.\n\n",
    "structured": {
        "0": {
            "full_name": "GEDAL, HARRY G L",
            "location": "Enskede",
            "occupation": "redaktionschef",
            "birth_details": {
                "date": "28/06/1919",
                "place": "Gällivare",
                "parents": "gruvarb Gunnar G o Svea Sandman"
            },
            "education": [
                {
                    "degree": "Realexamen",
                    "year": "1936",
                    "institution": "NULL"
                }
            ],
            "career": [
                {
                    "position": "journ",
                    "years": {
                        "start_year": 1936,
                        "end_year": 1936
                    },
                    "organization": "Norrl :folket Kiruna"
                },
                {
                    "position": "notisch",
                    "years": {
                        "start_year": 1936,
                        "end_year": 1936
                    },
                    "organization": "Norrl Socialdem Boden"
                },
                {
                    "position": "red:sekr",
                    "years": {
                        "start_year": 1951,
                        "end_year": 1951
                    },
                    "organization": "Nya Norrl Sollefteå"
                },
                {
                    "position": "MT",
                    "years": {
                        "start_year": 1953,
                        "end_year": 1953
                    },
                    "organization": "Sthlm"
                },
                {
                    "position": "notisch AT",
                    "years": {
                        "start_year": 1955,
                        "end_year": 1955
                    },
                    "organization": "NULL"
                },
                {
                    "position": "redrsekr ST",
                    "years": {
                        "start_year": 1956,
                        "end_year": 1956
                    },
                    "organization": "NULL"
                },
                {
                    "position": "red:ch",
                    "years": {
                        "start_year": "sed 1961",
                        "end_year": "NULL"
                    },
                    "organization": "där"
                }
            ],
            "family": {
                "spouse": "Kerstin Degerman",
                "marriage_year": "1942",
                "children": [
                    {
                        "name": "Mats",
                        "birth_year": "1946"
                    },
                    {
                        "name": "Lars",
                        "birth_year": "1951"
                    }
                ]
            }
        },
        "1": {
            "full_name": "GEDDA, H G NICOLAI",
            "location": "Vällingby",
            "occupation": "operasångare",
            "birth_details": {
                "date": "11/07/1925",
                "place": "Sthlm",
                "parents": "sångare Michail Ustinoff o Olga Gedda"
            },
            "education": [
                {
                    "degree": "Studrex",
                    "year": "1944",
                    "institution": "NULL"
                },
                {
                    "degree": "MA",
                    "year": "1949-1950",
                    "institution": "NULL"
                },
                {
                    "degree": "stip K teat",
                    "year": "1951-1952",
                    "institution": "NULL"
                }
            ],
            "career": [
                {
                    "position": "debut",
                    "years": {
                        "start_year": 1952,
                        "end_year": 1952
                    },
                    "organization": "NULL (tenor)"
                }
            ],
            "family": {
                "spouse": "NULL",
                "marriage_year": "NULL",
                "children": []
            }
        },
        "2": {
            "full_name": "GEDDA, PER O H",
            "location": "Saltsjö-Duvnäs",
            "occupation": "advokat",
            "birth_details": {
                "date": "28/08/1914",
                "place": "V Frölunda, Gbg o Boh",
                "parents": "dir Harald G o Hilda Wallerius"
            },
            "education": [
                {
                    "degree": "Studrex",
                    "year": "1934",
                    "institution": "Gbg"
                },
                {
                    "degree": "jur kand",
                    "year": "1938",
                    "institution": "Upps"
                }
            ],
            "career": [
                {
                    "position": "tingstjg",
                    "years": {
                        "start_year": 1939,
                        "end_year": 1942
                    },
                    "organization": "Askims, Hisings o Sävedals doms"
                },
                {
                    "position": "Gbgs hamnstyr",
                    "years": {
                        "start_year": 1942,
                        "end_year": 1943
                    },
                    "organization": "NULL"
                },
                {
                    "position": "bitr jurist",
                    "years": {
                        "start_year": 1943,
                        "end_year": "NULL"
                    },
                    "organization": "Emil Heijnes advibyrå Sthlm"
                }
            ],
            "family": {
                "spouse": "Barbro H:son-Ericson",
                "marriage_year": "1943",
                "children": [
                    {
                        "name": "Catarina",
                        "birth_year": "1944"
                    },
                    {
                        "name": "Viveca",
                        "birth_year": "1947"
                    },
                    {
                        "name": "Terese",
                        "birth_year": "1953"
                    }
                ]
            }
        }
    }
}