{
    "original": "GRUNDEN, LARS H, civilekonom,\nBromma, f i Eskilstuna 24/11/20 av\nförvalt Gustav G o Margareta G.\nStudrex 39, DHS 48, anst ab Gbgs bk\n46-49, ab National kassa register 49-55,\nPhilipson automobil ab 55-57,\nForss-hinds motor ab Gävle 58-60, verkst dir\nab Grafisk färg Sthlm sed 61. - Kapt\n110 res. - Hobbies: musik, tennis, fiske.\nGift 48 m May Nyquist f 21, dtr t\nIvar N o Gunhild N. - Barn: Mats f\n49, Hans f 54.\n\nGRUNDEN, PER, operasångare,\nWien o Sthlm, f i Eskilstuna 23/5/22\nav förvalt Gustaf G o Greta G.\nStud Musikhögsk f J Hislop, f Knut\nErman Gbg o Olavi Nyberg Hfors, eng\nSt teat Gbg 45-49, Oscarsteat Sthlm\n49-52, K teat 52-54, gästspel Malmö\nstads-teat 52-55, Volksoper Wien 53-60,\nÖsterr Kammersänger 58. Tenor.\nGift 48 m Susanne Gneiser, dtr t\nförsäkr: insp Eric G o Karin Zachrisson.\n\nGRUNDITZ, N R HAMPUS,\ndirektör, Danderyd, f i Ystad 2/8/21.\nStud:ex 40, DHS 45, HHS:s stip f\nspec:-stud Univ of Michigan USA 47-48.\n-Aman Affärsekon inst 44, anst NK 46,\ndir rass o ekonomich där 55, bitr dir 58,\nv verkst dir sed 61. - Res:off:ex\ning:-trupp 42.\n\nGift 50 m Inger Andersson f 23.\n-Barn: Maria f 51, Eva f 55.\n\nGRUNDSTRÖM, G BIRGER, lektor,\nDjursholm, f i Norrkpg 14/11/05 av\nverkmäst R G o Augusta Johansson.\nStud:ex 24, fil mag Sthlm 28, fil lic 32,\nfil dr 36, doc i fysik StHS 36-57,\nlaborator där 37-41, lektor i fysik o\nmatematik Djursholms samsk sed 41. - Förest\n\nSthl’ms arb:inst 51-53, kursledare o\nföreläsare i fysik vid ett flertal inst o\nyrkes-fören, censor vid stud:ex sed 56. - Skr:\nSpektroskopische Untersuchungen über\ndie Erdalkalihydride (drsavh 36), arb\nav fysikali vetensk innehåll. - Utm:\nRNO.\n\nGift 36 m Gurli Lindbom f 07, dtr t\ndir Gustav Jansson o Svea L.\n\n",
    "structured": {
        "0": {
            "full_name": "Lars H Grunden",
            "location": "Bromma",
            "occupation": "Civilekonom",
            "birth_details": {
                "date": "24/11/1920",
                "place": "Eskilstuna",
                "parents": "förvalt Gustav G o Margareta G"
            },
            "education": [
                {
                    "degree": "Studrex",
                    "year": "1939",
                    "institution": "NULL"
                },
                {
                    "degree": "DHS",
                    "year": "1948",
                    "institution": "NULL"
                }
            ],
            "career": [
                {
                    "position": "anst ab Gbgs bk",
                    "years": {
                        "start_year": 1946,
                        "end_year": 1949
                    },
                    "organization": "NULL"
                },
                {
                    "position": "ab National kassa register",
                    "years": {
                        "start_year": 1949,
                        "end_year": 1955
                    },
                    "organization": "NULL"
                },
                {
                    "position": "Philipson automobil ab",
                    "years": {
                        "start_year": 1955,
                        "end_year": 1957
                    },
                    "organization": "NULL"
                },
                {
                    "position": "Forss-hinds motor ab Gävle",
                    "years": {
                        "start_year": 1958,
                        "end_year": 1960
                    },
                    "organization": "NULL"
                },
                {
                    "position": "verkst dir ab Grafisk färg Sthlm",
                    "years": {
                        "start_year": 1961,
                        "end_year": "NULL"
                    },
                    "organization": "NULL"
                }
            ],
            "family": {
                "spouse": "May Nyquist",
                "marriage_year": "1948",
                "children": [
                    {
                        "name": "Mats",
                        "birth_year": "1949"
                    },
                    {
                        "name": "Hans",
                        "birth_year": "1954"
                    }
                ]
            },
            "hobbies": [
                "musik",
                "tennis",
                "fiske"
            ]
        },
        "1": {
            "full_name": "Per Grunden",
            "location": "Wien o Sthlm",
            "occupation": "Operasångare",
            "birth_details": {
                "date": "23/5/1922",
                "place": "Eskilstuna",
                "parents": "förvalt Gustaf G o Greta G"
            },
            "education": [
                {
                    "degree": "Stud Musikhögsk",
                    "year": "NULL",
                    "institution": "J Hislop"
                }
            ],
            "career": [
                {
                    "position": "Stud Musikhögsk",
                    "years": {
                        "start_year": 1945,
                        "end_year": 1949
                    },
                    "organization": "NULL"
                },
                {
                    "position": "Oscarsteat Sthlm",
                    "years": {
                        "start_year": 1949,
                        "end_year": 1952
                    },
                    "organization": "NULL"
                },
                {
                    "position": "K teat",
                    "years": {
                        "start_year": 1952,
                        "end_year": 1954
                    },
                    "organization": "NULL"
                },
                {
                    "position": "Volksoper Wien",
                    "years": {
                        "start_year": 1953,
                        "end_year": 1960
                    },
                    "organization": "NULL"
                }
            ],
            "family": {
                "spouse": "Susanne Gneiser",
                "marriage_year": "1948",
                "children": []
            }
        },
        "2": {
            "full_name": "N R Hampus Grunditz",
            "location": "Danderyd",
            "occupation": "Direktör",
            "birth_details": {
                "date": "2/8/1921",
                "place": "Ystad",
                "parents": "NULL"
            },
            "education": [
                {
                    "degree": "Stud:ex",
                    "year": "1940",
                    "institution": "NULL"
                },
                {
                    "degree": "DHS",
                    "year": "1945",
                    "institution": "NULL"
                },
                {
                    "degree": "HHS:s stip",
                    "year": "NULL",
                    "institution": "f spec:-stud Univ of Michigan USA"
                }
            ],
            "career": [
                {
                    "position": "anst NK",
                    "years": {
                        "start_year": 1946,
                        "end_year": "NULL"
                    },
                    "organization": "NULL"
                }
            ],
            "family": {
                "spouse": "Inger Andersson",
                "marriage_year": "1950",
                "children": [
                    {
                        "name": "Maria",
                        "birth_year": "1951"
                    },
                    {
                        "name": "Eva",
                        "birth_year": "1955"
                    }
                ]
            }
        },
        "3": {
            "full_name": "G Birger Grundström",
            "location": "Djursholm",
            "occupation": "Lektor",
            "birth_details": {
                "date": "14/11/1905",
                "place": "Norrköping",
                "parents": "verkmäst R G o Augusta Johansson"
            },
            "education": [
                {
                    "degree": "Stud:ex",
                    "year": "1924",
                    "institution": "NULL"
                },
                {
                    "degree": "fil mag",
                    "year": "1928",
                    "institution": "Sthlm"
                },
                {
                    "degree": "fil lic",
                    "year": "1932",
                    "institution": "NULL"
                },
                {
                    "degree": "fil dr",
                    "year": "1936",
                    "institution": "NULL"
                }
            ],
            "career": [
                {
                    "position": "doc i fysik",
                    "years": {
                        "start_year": 1936,
                        "end_year": 1957
                    },
                    "organization": "StHS"
                },
                {
                    "position": "lektor i fysik o matematik Djursholms samsk",
                    "years": {
                        "start_year": 1941,
                        "end_year": "NULL"
                    },
                    "organization": "NULL"
                }
            ],
            "family": {
                "spouse": "Gurli Lindbom",
                "marriage_year": "1936",
                "children": []
            }
        }
    }
}