{
    "original": "LEIFLAND, LEIF, förste\nambassadsekreterare, Washington, f i Sthlm 30/\n12/25 av aukt rev Sigfrid L o Elna\nJonasson.\n\nJur kand 50, anst UD 51, attaché Athen\n53-55, Bonn 55-58, 2:e sekr Sthlm 58,\nbitr sekr Nord rådet 58-60, l:e\nambr-sekr Washington sed 61. - Sekr utredn\nang sv rnedbrskap s villkor f statstjänst\n58-60. - Utm: RNSrtOO, RTyskRFO.\nGift m Karin Abard f 30, dtr t dir\nGustaf A o Ingrid Nordin. - Barn:\nKarl f 55, Christina f 57, Eva f 60.\n\nLEIJON,    ALEX,    organisationschef,\n\nSollentuna, f i Sthlm 8/7/15 av\nförsäkrr-kamrer Alex L o Gabriella Gumaelius.\nStudrex 34, affärsverksamh, anst Valand\n36, Heimdall 37, Hero 38, försäljnrch\ndär 45, bitr org:ch AVH-bol 47, org:ch\nValand 55, Valand-Pensionsbol sed 58.\n- Hobby: resor.\n\nGift 41 m Birgit Axelson f 17. - Barn:\nJohan f 43, Magnus f 45.\n\nLEIJON, ARNE B, direktör,\nHägersten, f i Sthlm 6/8/24 av lagerbitr Axel\nL o Signe Johansson.\nStud:ex 44, res:off:ex 47, stabsred fst\n58. - Speditör ab Olson &amp; Wright Sthlm\n47, reklamass ab S Gumxlius\nannonsbyrå 49, kontaktman där 50,\nprogramledare o verkst dir De blindas dag 52 års\nrikskampanj 52, anst DN annonsavd 53,\ndir rass 55, bitr annonsdir där 57-60,\nverkst dir aukt annonsbyrån Leijon &amp;\n\nLüning ab sed 61. - Lär Sthlms\nförsäljn:- o reklamfören 54-61. - Stynled\nSthlms blindfören 52-54, Sthlms\nförsäljn:- &amp; reklamfören 52-53, 55-56.\nGift m Pella Aulin. - Barn: Agneta\nf 51, Johan f 52, Katarina f 55.\n\nLEIJON, CURT, ambassadör, Bogotå,\nf i Sthlm 14/7/10 av kamrer Alex L o\nGabriella Gumaelius.\nStud:ex 29, jur kand Sthlm 35,\nres:off:-ex 32, löjtn KA:s res 36, attaché UD 36,\ntjg San Francisco, Washington, New\nYork 37, sekr UD 41, l:e leg:sekr\nLissabon 45, konsul Danzig 48, New\nYork 50, byråch UD 53, bitr ch UD:s\nrättsavd o utrikesråds namn 59,\nambassadör Bogotå samt minister Quito o\nPanama sed 61. - Ordf UD:s understödsnd\n53-59, expert 46 års sjömanskomm\n53-57. - Utm: RNO, KFintLO, KPKO,\nRDDO, KNS:tOO, KTadjNelAOlkl.\nGift 43 m Else Pettersen f 10. - Barn:\nErik f 44, Margaretha f 47.\n\n",
    "structured": {
        "0": {
            "full_name": "LEIFLAND, LEIF",
            "location": "Washington",
            "occupation": "förste ambassadsekreterare",
            "birth_details": {
                "date": "30/12/1925",
                "place": "Stockholm",
                "parents": "aukt rev Sigfrid L o Elna Jonasson"
            },
            "education": [
                {
                    "degree": "Jur kand",
                    "year": "1950",
                    "institution": "NULL"
                }
            ],
            "career": [
                {
                    "position": "attaché",
                    "years": {
                        "start_year": 1953,
                        "end_year": 1955
                    },
                    "organization": "Athen"
                },
                {
                    "position": "2:e sekr",
                    "years": {
                        "start_year": 1958,
                        "end_year": 1960
                    },
                    "organization": "Sthlm"
                },
                {
                    "position": "bitr sekr",
                    "years": {
                        "start_year": 1958,
                        "end_year": 1960
                    },
                    "organization": "Nord rådet"
                },
                {
                    "position": "l:e ambr-sekr",
                    "years": {
                        "start_year": 1961,
                        "end_year": "NULL"
                    },
                    "organization": "Washington"
                }
            ],
            "family": {
                "spouse": "Karin Abard",
                "marriage_year": "NULL",
                "children": [
                    {
                        "name": "Karl",
                        "birth_year": "1955"
                    },
                    {
                        "name": "Christina",
                        "birth_year": "1957"
                    },
                    {
                        "name": "Eva",
                        "birth_year": "1960"
                    }
                ]
            }
        },
        "1": {
            "full_name": "LEIJON, ALEX",
            "location": "Sollentuna",
            "occupation": "organisationschef",
            "birth_details": {
                "date": "8/7/1915",
                "place": "Stockholm",
                "parents": "försäkrr-kamrer Alex L o Gabriella Gumaelius"
            },
            "education": [],
            "career": [
                {
                    "position": "försäljnrch",
                    "years": {
                        "start_year": 1945,
                        "end_year": "NULL"
                    },
                    "organization": "Hero"
                },
                {
                    "position": "bitr org:ch",
                    "years": {
                        "start_year": 1947,
                        "end_year": "NULL"
                    },
                    "organization": "AVH-bol"
                },
                {
                    "position": "org:ch",
                    "years": {
                        "start_year": 1955,
                        "end_year": "NULL"
                    },
                    "organization": "Valand"
                },
                {
                    "position": "verkst dir",
                    "years": {
                        "start_year": 1961,
                        "end_year": "NULL"
                    },
                    "organization": "Valand-Pensionsbol"
                }
            ],
            "family": {
                "spouse": "Birgit Axelson",
                "marriage_year": "1941",
                "children": [
                    {
                        "name": "Johan",
                        "birth_year": "1943"
                    },
                    {
                        "name": "Magnus",
                        "birth_year": "1945"
                    }
                ]
            },
            "hobbies": [
                "resor"
            ]
        },
        "2": {
            "full_name": "LEIJON, ARNE B",
            "location": "Hägersten",
            "occupation": "direktör",
            "birth_details": {
                "date": "6/8/1924",
                "place": "Stockholm",
                "parents": "lagerbitr Axel L o Signe Johansson"
            },
            "education": [
                {
                    "degree": "Stud:ex",
                    "year": "1944",
                    "institution": "NULL"
                }
            ],
            "career": [
                {
                    "position": "speditör",
                    "years": {
                        "start_year": 1947,
                        "end_year": "NULL"
                    },
                    "organization": "Olson & Wright Sthlm"
                },
                {
                    "position": "reklamass",
                    "years": {
                        "start_year": 1949,
                        "end_year": "NULL"
                    },
                    "organization": "S Gumxlius annonsbyrå"
                },
                {
                    "position": "kontaktman",
                    "years": {
                        "start_year": 1950,
                        "end_year": "NULL"
                    },
                    "organization": "Där"
                },
                {
                    "position": "verkst dir",
                    "years": {
                        "start_year": 1961,
                        "end_year": "NULL"
                    },
                    "organization": "Leijon & Lüning ab"
                }
            ],
            "family": {
                "spouse": "Pella Aulin",
                "marriage_year": "NULL",
                "children": [
                    {
                        "name": "Agneta",
                        "birth_year": "1951"
                    },
                    {
                        "name": "Johan",
                        "birth_year": "1952"
                    },
                    {
                        "name": "Katarina",
                        "birth_year": "1955"
                    }
                ]
            }
        },
        "3": {
            "full_name": "LEIJON, CURT",
            "location": "Bogotå",
            "occupation": "ambassadör",
            "birth_details": {
                "date": "14/7/1910",
                "place": "Stockholm",
                "parents": "kamrer Alex L o Gabriella Gumaelius"
            },
            "education": [
                {
                    "degree": "Stud:ex",
                    "year": "1929",
                    "institution": "NULL"
                },
                {
                    "degree": "jur kand",
                    "year": "1935",
                    "institution": "Sthlm"
                }
            ],
            "career": [
                {
                    "position": "löjtn",
                    "years": {
                        "start_year": 1936,
                        "end_year": "NULL"
                    },
                    "organization": "KA:s res"
                },
                {
                    "position": "attaché",
                    "years": {
                        "start_year": 1936,
                        "end_year": "NULL"
                    },
                    "organization": "UD"
                },
                {
                    "position": "sekr",
                    "years": {
                        "start_year": 1941,
                        "end_year": "NULL"
                    },
                    "organization": "UD"
                },
                {
                    "position": "ambassadör",
                    "years": {
                        "start_year": 1961,
                        "end_year": "NULL"
                    },
                    "organization": "Bogotå"
                }
            ],
            "family": {
                "spouse": "Else Pettersen",
                "marriage_year": "1943",
                "children": [
                    {
                        "name": "Erik",
                        "birth_year": "1944"
                    },
                    {
                        "name": "Margaretha",
                        "birth_year": "1947"
                    }
                ]
            }
        }
    }
}