{
    "original": "LAGERCRANTZ,   RUTGER   H   C,\n\nmed dr, docent, Sthlm, f i Sthlm 14/\n11/7 av bankdir Carl L o Agnes\nHamilton.\n\nStud:ex 36, med kand Upps 38, med\nlic Sthlm 43, med dr 56, doc i pediatr\nKarol inst sed 57, tf underläk Norbergs\nlas 43, Kronpr:an Lovisas barnsjh 45,\nGbgs epidrsjh 47, tf ass Sthlms städs\nbakteriol lab 45-47, e läk Sthlms\nepidrsjh 47-49, tf laborator bakteriol lab\nKarol sjh 48, 2:e underläk med klin\n49, l:e underläk med avd barnklin\nKarol sjh 51-59, bitr överläk där sed 59.\n- Sekr Sv pediatr sällsk. - Skr i klin\nbakteriolog o pediatr.\nGift 43-52 m Marit Heyman f 18, dtr\nt dir Hugo H o Gunhild Roland.\n-Barn: Hugo f 45, Cecilia f 47.\n\nLAGERFELT, U R\nGUSTAV-ADOLF (GÖSTA), friherre,\nsektionschef, Lidingö, f i Linkpg 10/7/19 av\nfrih Gösta L o Carin Sparre.\nStud:ex 40, journ:stud 43,\nluftskydds-insp utbildn:- o övn:avd 44. -\nJourn:-praktik 43, anst press- o filmavd\ncivil-försv:styr 45, reklamch Nord\nResebureau Sthlm 47, rederiab Sv Lloyd Gbg\n51, reklam- o försäljnxh SvD 54,\nsek-tionsch Wahl Asmussen annonsbyrå sed\n59. - Res:off:ex 43.\n\nGift 49 m Stina Pihlgren f 24, dtr t\nGustaf P o Stina P.\n\nLAGERFELT, I KARL-GUSTAV\n(K-G) E, friherre, ambassadör, Bryssel,\nf i Jönkpg 21/11/09 av kapt, frih\nGustaf L o fr ih: an Gertrud von Essen.\nJur kand 32, fil kand 35, attaché UD\n35, Hfors 36, London 38, UD 38, 2:e\nsekr där 39, l :e sekr 43, London 43,\nParis 47, UD 48, byråch 50 (tf 48), dipl\nrepr Japan 51, envoyé Tokio 52, ständ\nomb Europarådet 57-60, kolL o stålun h\nmyndigh Luxemburg sed 56, Euratom\no europ ekon gemensk Bryssel sed 59.\n-Utm: fd Härold v KMO, RNO,\nRJoh-O, JHSOlkl, KFinlLOlkl, KUngRFO,\nRFinlVROlkl, RFrHL.\nGift 47 m Sara Champion de Crespigny\nf 14, dtr t britt majoren Vierville C de\nC o Nora McSftoy. - Barn: CaroMne f 47,\nJohan f 49.\n\nLAGERGRÉEN, BENGT J R, leg\nläkare, Sthlm, f i Kristianstad 31/1/16\nav kapten Ragnar L o Kerstin\nKindbom.\n\nStud:ex 35, med kand 38, med lic 44,\neo aman Karol inst anat inst 38, patol\ninst 42-44, ass:läk, aman o tf\nunderläk kir klin Sahlgr sjh 44-48, underläk\n48-53, aman o ass Karol inst anat inst\n\n52-56, vik poliklinikläk Sahlgr sjh\n49-53, bat:läk v flk 53-56, bat:läk I l\n56-59, tf bat:läk K l 59-60, tf reg:läk\nIng l 60-61, eg prakt sed 57. - Stud\nPas-teurinst Paris 38, stud:resa USA 47.\n-Skr i kirurgi o fysiol.\nGift 43 m Brita Lilliehöök f 20, dtr t\nkapten Anders L o Viveka\nBergenstråhle. - Barn: Magnus f 44,\nMarie-Louise f 45, Claes f 47.\n\n",
    "structured": {
        "0": {
            "full_name": "Rutger H C Lagercrantz",
            "location": "Sthlm",
            "occupation": "med dr, docent",
            "birth_details": {
                "date": "14/11/1907",
                "place": "Sthlm",
                "parents": "av bankdir Carl L o Agnes Hamilton"
            },
            "education": [
                {
                    "degree": "Stud:ex",
                    "year": "1936",
                    "institution": "Upps"
                },
                {
                    "degree": "med kand",
                    "year": "1938",
                    "institution": "Upps"
                },
                {
                    "degree": "med lic",
                    "year": "1943",
                    "institution": "Sthlm"
                },
                {
                    "degree": "med dr",
                    "year": "1956",
                    "institution": null
                }
            ],
            "career": [
                {
                    "position": "tf underläk",
                    "years": {
                        "start_year": 1943,
                        "end_year": null
                    },
                    "organization": "Norbergs las"
                },
                {
                    "position": "tf ass",
                    "years": {
                        "start_year": 1945,
                        "end_year": 1947
                    },
                    "organization": "Sthlms städs bakteriol lab"
                },
                {
                    "position": "e läk",
                    "years": {
                        "start_year": 1947,
                        "end_year": 1949
                    },
                    "organization": "Sthlms epidrsjh"
                },
                {
                    "position": "2:e underläk med klin",
                    "years": {
                        "start_year": 1949,
                        "end_year": null
                    },
                    "organization": null
                }
            ],
            "family": {
                "spouse": "Marit Heyman",
                "marriage_year": "1943",
                "children": [
                    {
                        "name": "Hugo",
                        "birth_year": "1945"
                    },
                    {
                        "name": "Cecilia",
                        "birth_year": "1947"
                    }
                ]
            }
        },
        "1": {
            "full_name": "Gustav-Adolf (Gösta) Lagerfelt",
            "location": "Lidingö",
            "occupation": "sektionschef",
            "birth_details": {
                "date": "10/07/1919",
                "place": "Linkpg",
                "parents": "av frih Gösta L o Carin Sparre"
            },
            "education": [
                {
                    "degree": "Stud:ex",
                    "year": "1940",
                    "institution": null
                }
            ],
            "career": [
                {
                    "position": "anst press- o filmavd civil-försv:styr",
                    "years": {
                        "start_year": 1945,
                        "end_year": null
                    },
                    "organization": null
                },
                {
                    "position": "reklamch",
                    "years": {
                        "start_year": 1954,
                        "end_year": null
                    },
                    "organization": "SvD"
                }
            ],
            "family": {
                "spouse": "Stina Pihlgren",
                "marriage_year": "1949",
                "children": []
            }
        },
        "2": {
            "full_name": "Karl-Gustav (K-G) E Lagerfelt",
            "location": "Bryssel",
            "occupation": "ambassadör",
            "birth_details": {
                "date": "21/11/1909",
                "place": "Jönkpg",
                "parents": "av kapt, frih Gustaf L o fr ih: an Gertrud von Essen"
            },
            "education": [
                {
                    "degree": "Jur kand",
                    "year": "1932",
                    "institution": null
                },
                {
                    "degree": "fil kand",
                    "year": "1935",
                    "institution": null
                }
            ],
            "career": [
                {
                    "position": "attaché",
                    "years": {
                        "start_year": 1935,
                        "end_year": null
                    },
                    "organization": "UD"
                },
                {
                    "position": "envoyé",
                    "years": {
                        "start_year": 1952,
                        "end_year": null
                    },
                    "organization": "Tokio"
                }
            ],
            "family": {
                "spouse": "Sara Champion de Crespigny",
                "marriage_year": "1947",
                "children": [
                    {
                        "name": "Caroline",
                        "birth_year": "1947"
                    },
                    {
                        "name": "Johan",
                        "birth_year": "1949"
                    }
                ]
            }
        },
        "3": {
            "full_name": "Bengt J R Lagergréen",
            "location": "Sthlm",
            "occupation": "leg läkare",
            "birth_details": {
                "date": "31/01/1916",
                "place": "Kristianstad",
                "parents": "av kapten Ragnar L o Kerstin Kindbom"
            },
            "education": [
                {
                    "degree": "Stud:ex",
                    "year": "1935",
                    "institution": null
                },
                {
                    "degree": "med kand",
                    "year": "1938",
                    "institution": null
                },
                {
                    "degree": "med lic",
                    "year": "1944",
                    "institution": null
                }
            ],
            "career": [
                {
                    "position": "ass:läk",
                    "years": {
                        "start_year": 1942,
                        "end_year": 1944
                    },
                    "organization": "patol inst"
                },
                {
                    "position": "underläk",
                    "years": {
                        "start_year": 1948,
                        "end_year": 1953
                    },
                    "organization": "Sahlgr sjh"
                }
            ],
            "family": {
                "spouse": "Brita Lilliehöök",
                "marriage_year": "1943",
                "children": [
                    {
                        "name": "Magnus",
                        "birth_year": "1944"
                    },
                    {
                        "name": "Marie-Louise",
                        "birth_year": "1945"
                    },
                    {
                        "name": "Claes",
                        "birth_year": "1947"
                    }
                ]
            }
        }
    }
}