{
    "original": "LINDBERG, BENGT F, tandläkare,\nBromma, f i Upps 11/10/04 av\nboktryckerifaktor Axel L o Emma Nyman.\nMed kand Upps, tandläkrex Sthlm 30,\nvik tandläk Karlshamn 30, praktik\nBromma sed 31. - Medl Sthlms\ntand^-läkrfören, Sv tandläk rsällsk. - Hobby:\nhortikultur.\n\nGift 57 m Carin Busck, dtr t arkit\nAugust B o Rose Eck.\n\nLINDBERG, BENGT G, professor,\nSthlm, f i Sthlm 17/7/19 av byråchef\nHenry L o Elsa Tengwall.\nFil måg 42, fil lic 44, fil dr 50, doc\ni organisk kemi KTH sed 50, spec:lär\ni träkemi där sed 55, laborator Sv\ntraf or skn: inst sed 55, förest träkem avd\ndär sed 56, prof namn 59. - Skr: i\nkolhydratkemi o träkemi.\nGift 47 m Ethel Jonson f 26.\n-Barn: Elsa f 48, Gustaf f 52.\n\nLINDBERG, BENGT T, direktör,\nSthlm, f i Upps 23/11/10 av dir T M L\no Tora Pettersson.\n\nStudrex   30,   HHS   33;   verkst   dir   ab\nBengt Lindberg Lidingö. - Styrrled ab\nIngvar Bergengren 41.\nGift 36 m Britta Jaeger. - Barn:\nKristina f 37, Gunilla f 39.\n\nLINDBERG,    K    BIRGER,    arkitekt\nSAR, Sthlm, f i Eksjö 18/3/02.\nStudrex 21, KTH 29, KKH 33, eg\narkitr-verksamh Sthlm sed 33.\n\nLINDBERG, BÖRJE, civilekonom,\nLidingö, f i Sthlm 12/4/12 av tandläk\nMartin L o Hilma L.\n\nStudrex 32, DHS 35, anst AEF 35,\nEr-vaco o Inst f marknrundersöknrar ab\nSthlm 37, eg firma Lindberg &amp;\nNeuman 47-54, ab Marknadsbyrån sed 47,\nverkst dlr ab Säljkonsult Börje\nLindberg sed 54. - Sakk komm f utredn av\nPsykolog försv, ordf forstorkomm Sv\nförsäljn:- o reklamförb sed 53, sv repr\nESpMAR. - Medl presidiet Nord\nförsäljn:- o reklamförb, Sv\norgrkonsul-ters fören (ordf sed 60), medl Sthlms\nförsäljn:- o reklamfören (ordf 49-52),\nv ordf direkt IHR, M-gr (ordf 55-60),\nS-gr. - Skr: Reklamprövning (40),\nHur läser folk annonser (tills m\nBertil Neuman 45), Sätt och vett i telefon\n(4:e uppl 61), art om\nmarknadsunder-sökn, reklamprövn, företrledn o org i\nin- o utl fackpress. - Hobby: segling.\nGift 55 m Camill’a Björnström, dtr t\nbyråing Axel B o Ebba Björkman.\n-Barn: Tomas f 55, Andreas f 58.\n\n",
    "structured": {
        "1": {
            "full_name": "Bengt F Lindberg",
            "location": "Bromma",
            "occupation": "Tandläkare",
            "birth_details": {
                "date": "11/10/1904",
                "place": "Uppsala",
                "parents": "Boktryckerifaktor Axel L o Emma Nyman"
            },
            "education": [
                {
                    "degree": "Med kand",
                    "year": "30",
                    "institution": "Upps"
                },
                {
                    "degree": "Tandläkrex",
                    "year": "30",
                    "institution": "Sthlm"
                }
            ],
            "career": [
                {
                    "position": "Vik tandläk",
                    "years": {
                        "start_year": 30,
                        "end_year": 30
                    },
                    "organization": "Karlshamn"
                },
                {
                    "position": "Praktik",
                    "years": {
                        "start_year": 31,
                        "end_year": null
                    },
                    "organization": "Bromma"
                }
            ],
            "family": {
                "spouse": "Carin Busck",
                "marriage_year": "57",
                "children": []
            },
            "hobbies": [
                "Hortikultur"
            ]
        },
        "2": {
            "full_name": "Bengt G Lindberg",
            "location": "Sthlm",
            "occupation": "Professor",
            "birth_details": {
                "date": "17/7/1919",
                "place": "Sthlm",
                "parents": "Byråchef Henry L o Elsa Tengwall"
            },
            "education": [
                {
                    "degree": "Fil måg",
                    "year": "42",
                    "institution": ""
                },
                {
                    "degree": "Fil lic",
                    "year": "44",
                    "institution": ""
                },
                {
                    "degree": "Fil dr",
                    "year": "50",
                    "institution": ""
                }
            ],
            "career": [
                {
                    "position": "Doc i organisk kemi",
                    "years": {
                        "start_year": 50,
                        "end_year": null
                    },
                    "organization": "KTH"
                },
                {
                    "position": "Spec:lär i träkemi",
                    "years": {
                        "start_year": 55,
                        "end_year": null
                    },
                    "organization": "KTH"
                }
            ],
            "family": {
                "spouse": "Ethel Jonson",
                "marriage_year": "47",
                "children": [
                    {
                        "name": "Elsa",
                        "birth_year": "48"
                    },
                    {
                        "name": "Gustaf",
                        "birth_year": "52"
                    }
                ]
            }
        },
        "3": {
            "full_name": "Bengt T Lindberg",
            "location": "Sthlm",
            "occupation": "Direktör",
            "birth_details": {
                "date": "23/11/1910",
                "place": "Upps",
                "parents": "Dir T M L o Tora Pettersson"
            },
            "education": [
                {
                    "degree": "Studrex",
                    "year": "30",
                    "institution": ""
                },
                {
                    "degree": "HHS",
                    "year": "33",
                    "institution": ""
                }
            ],
            "career": [
                {
                    "position": "Verkst dir",
                    "years": {
                        "start_year": null,
                        "end_year": null
                    },
                    "organization": "ab Bengt Lindberg Lidingö"
                },
                {
                    "position": "Styrrled",
                    "years": {
                        "start_year": 41,
                        "end_year": null
                    },
                    "organization": "ab Ingvar Bergengren"
                }
            ],
            "family": {
                "spouse": "Britta Jaeger",
                "marriage_year": "36",
                "children": [
                    {
                        "name": "Kristina",
                        "birth_year": "37"
                    },
                    {
                        "name": "Gunilla",
                        "birth_year": "39"
                    }
                ]
            }
        },
        "4": {
            "full_name": "K Birger Lindberg",
            "location": "Sthlm",
            "occupation": "Arkitekt SAR",
            "birth_details": {
                "date": null,
                "place": "Eksjö",
                "parents": null
            },
            "education": [
                {
                    "degree": "Studrex",
                    "year": "21",
                    "institution": ""
                },
                {
                    "degree": "",
                    "year": "29",
                    "institution": "KTH"
                },
                {
                    "degree": "",
                    "year": "33",
                    "institution": "KKH"
                }
            ],
            "career": [
                {
                    "position": "",
                    "years": {
                        "start_year": 33,
                        "end_year": null
                    },
                    "organization": "eg arkitr-verksamh Sthlm"
                }
            ],
            "family": {
                "spouse": "",
                "marriage_year": "",
                "children": []
            }
        },
        "5": {
            "full_name": "Börje Lindberg",
            "location": "Lidingö",
            "occupation": "Civilekonom",
            "birth_details": {
                "date": "12/4/1912",
                "place": "Sthlm",
                "parents": "Tandläk Martin L o Hilma L"
            },
            "education": [
                {
                    "degree": "Studrex",
                    "year": "32",
                    "institution": ""
                },
                {
                    "degree": "DHS",
                    "year": "35",
                    "institution": ""
                }
            ],
            "career": [
                {
                    "position": "Anst",
                    "years": {
                        "start_year": 35,
                        "end_year": null
                    },
                    "organization": "AEF"
                },
                {
                    "position": "Er-vaco o Inst f marknrundersöknrar ab",
                    "years": {
                        "start_year": 37,
                        "end_year": 37
                    },
                    "organization": "Sthlm"
                },
                {
                    "position": "Eg firma Lindberg & Neuman",
                    "years": {
                        "start_year": 47,
                        "end_year": 54
                    },
                    "organization": ""
                },
                {
                    "position": "",
                    "years": {
                        "start_year": 47,
                        "end_year": null
                    },
                    "organization": "ab Marknadsbyrån"
                },
                {
                    "position": "Verkst dlr",
                    "years": {
                        "start_year": 54,
                        "end_year": null
                    },
                    "organization": "ab Säljkonsult Börje Lindberg"
                }
            ],
            "family": {
                "spouse": "Camill’a Björnström",
                "marriage_year": "55",
                "children": [
                    {
                        "name": "Tomas",
                        "birth_year": "55"
                    },
                    {
                        "name": "Andreas",
                        "birth_year": "58"
                    }
                ]
            },
            "hobbies": [
                "Segling"
            ]
        }
    }
}