{
    "original": "LAURITZEN, FOLKE K,\ncivilingenjör, Stocksund, f i Vassända-Naglums\nförs, Älvsbgs l, 5/2/11.\nStudiex Strängnäs 29, KTH 34, ing\nSv väg ab Sthlm 37-42, konsult ing\nJacobson &amp; Widmark 42-48, byggniinsp\nmed:styr 48, byrådir där 60 byggnich\nsed 61.\n\nGift 38 m adv Elin Paues f 16, dtr t\nenvoyé Johan P o Kari Fateter. - Barn:\nEva f 40, Viveka f 44, Inger f 48.\n\nLAURITZSON, J INGE L,\nlänsveterinär, VälJingby, f i Kristianst 25/2/\n08 av eo hovrättsnot Lauritz Nilsson\no Elisabeth N.\n\nStudiex Lund 29, vet:ex Sthlm 36,\nbe-siktn:vet Enkpg 38,\ntuberkuloskonsulent med: styr 40, byrå vet där 42, vet:\nstyr 47, länsvet Sthlms l sed 48.\n-Speciallär i veterinär\nförfattningskunskap VHS 46-55. - Utredn:man rör\npersonalbehovet v avd f\nfödoämneshygien VHS 54, sakk förhandl i\nGeneve 57, styr:led stat vet:med anst sed\n56, ordf Sv:es yngre veterinärers fören\n41 o 42. - Skr: saml av författn,\ncirkulär m m rör vet:väs i Sv:e (44).\n-Utm: RNO.\n\nGift 42 m sophiasystern Ingegerd Broek\nf   12,   dtr  t   distr:vet  Sven  B   o  Elin\nStenström.   -   Barn:  Sven  f  43,\nElisabeth f 45. Nils f 52.\n\nLAVETT, E GUNNAR A, disponent,\n\nFarsta, f i Sthlm 10/11/09 av\nstyckjun-kare Edvin L o Anna Johansson.\nBokförl.-stud Tyskl 51, försäljaren\nAlmqvist &amp; Wiksell/Gebers förlag ab.\n-Ordf Oüto Halldéns fabr &amp; H ab,\nSthlms Frihamns ab, v ordf\nFarstarådet, Farsta kyrkoful’kn, led Sthlms\nStadsfullm, Farsta kyrkoråd, suppl\nInd:verksstyr Sthlm, Sthlms st arb:lösh:nd,\ndirekt f Sthlms st uppbördsv, preses sällsk\nBel’l’mans minne, medl Odd Fellow,\nSthlms bufb. - Utm: SihknsbufbftjSM,\nSällsk Bellmans minnes SPlak. -\nHobbies: Skytte, stockholmiana, bellmaniana.\nGift 40 m Karin Valldor, dtr t Carl\nAnderson o h h f Nordwall. - Barn:\nUlf-Magnus f 42, Björn-Edvin f 43.\n\n",
    "structured": {
        "0": {
            "full_name": "Folke K Lauritzen",
            "location": "Stocksund",
            "occupation": "Civilingenjör",
            "birth_details": {
                "date": "05/02/1911",
                "place": "Vassända-Naglums förs, Älvsbgs l"
            },
            "education": [
                {
                    "degree": "Studiex",
                    "year": "1929",
                    "institution": "Strängnäs"
                },
                {
                    "degree": "KTH",
                    "year": "1934",
                    "institution": "Stockholm"
                }
            ],
            "career": [
                {
                    "position": "Ing",
                    "years": {
                        "start_year": 1942,
                        "end_year": 1948
                    },
                    "organization": "Jacobson & Widmark"
                },
                {
                    "position": "Byggniinsp",
                    "years": {
                        "start_year": 1948,
                        "end_year": 1960
                    },
                    "organization": "Byggnich"
                }
            ],
            "family": {
                "spouse": "Elin Paues",
                "marriage_year": "1938",
                "children": [
                    {
                        "name": "Eva",
                        "birth_year": "1940"
                    },
                    {
                        "name": "Viveka",
                        "birth_year": "1944"
                    },
                    {
                        "name": "Inger",
                        "birth_year": "1948"
                    }
                ]
            }
        },
        "1": {
            "full_name": "J Inge L Lauritzson",
            "location": "VälJingby",
            "occupation": "Länsveterinär",
            "birth_details": {
                "date": "25/02/1908",
                "place": "Kristianst"
            },
            "education": [
                {
                    "degree": "Studiex",
                    "year": "1929",
                    "institution": "Lund"
                },
                {
                    "degree": "Vet:ex",
                    "year": "1936",
                    "institution": "Stockholm"
                }
            ],
            "career": [
                {
                    "position": "Tuberkuloskonsulent",
                    "years": {
                        "start_year": 1940,
                        "end_year": 1942
                    },
                    "organization": "Enkpg"
                },
                {
                    "position": "Länsvet",
                    "years": {
                        "start_year": 1948
                    },
                    "organization": "Sthlms l"
                }
            ],
            "family": {
                "spouse": "Ingegerd Broek",
                "marriage_year": "1942",
                "children": [
                    {
                        "name": "Sven",
                        "birth_year": "1943"
                    },
                    {
                        "name": "Elisabeth",
                        "birth_year": "1945"
                    },
                    {
                        "name": "Nils",
                        "birth_year": "1952"
                    }
                ]
            }
        },
        "2": {
            "full_name": "E Gunnar A Lavett",
            "location": "Farsta",
            "occupation": "Disponent",
            "birth_details": {
                "date": "10/11/1909",
                "place": "Stockholm"
            },
            "education": [
                {
                    "degree": "Bokförl.-stud",
                    "year": "1951",
                    "institution": "Tyskland"
                }
            ],
            "career": [
                {
                    "position": "Ordf",
                    "years": {
                        "start_year": null,
                        "end_year": null
                    },
                    "organization": "Oüto Halldéns fabr & H ab"
                },
                {
                    "position": "V Ordf",
                    "years": {
                        "start_year": null,
                        "end_year": null
                    },
                    "organization": "Farstarådet"
                }
            ],
            "family": {
                "spouse": "Karin Valldor",
                "marriage_year": "1940",
                "children": [
                    {
                        "name": "Ulf-Magnus",
                        "birth_year": "1942"
                    },
                    {
                        "name": "Björn-Edvin",
                        "birth_year": "1943"
                    }
                ]
            },
            "hobbies": [
                "Skytte",
                "Stockholmiana",
                "Bellmaniana"
            ]
        }
    }
}