{
    "original": "LINDBLAD, C IVAR EMIL,\ntandläkare, Sthlm, f i Lidingö 27/4/14 av\ntand-läk Emil L o Maja Rosenberg.\nStud:ex Sthlm 33, tandläkrex 38, eg prakt\nSthlm sed 39.\n\nGift 47 m Käthie Gentele f 20, dtr t\ndir H W G o h h. - Barn: Frank f 49.\n\nLINDBLAD, LARS A,\ncivilingenjör, Johanneshov, f i Ludvika 21/6/17\nav fil dr Axel L o Ester Bergman.\nStud:ex 37, civiling 45, anst\nforsknr-lab LKB 45, ab Wicanders korkfabr\n46, isoler ab WMB 48, försäkrrab\nSkandia 50, branding sed 51, reassurrch sed\n57. - Sekr Sv försäkrrbol\natomförsäkrr-komm 56, medl Sv\natomförsäkrrpoo-lens tekn utsk f sakförsäkr 58.\n\nLINDBLAD, PER   OLOF,   docent,\nSaltsjöbaden,   f   i   Uppsala   22/10/27\nav prof Bertil  L  o  Dagmar  Bolin.\nStudrex Saltsjöbaden 46, fil kand Sthlm\n51,  fil mag  52,  fü  lic  56, fil  dr 60,\naman    Sthlms    observatorium\nSaltsjöbaden 51, ass där sed 57, doc Sthlms univ\nsed 60. - Sekr Sv astronom sälsk  59.\n\n-  Löjtn A l res 57. - Skr i astronomi.\nGift 59 m fil mag Gunilla Alsen f 35,\ndtr t justitiekansler Olof A o Hervor\nLindström. - Barn: Hans f 60.\n\nLINDBLAD, STEN A S, major,\nNäsbypark, f i Frinnaryd, Jönkpgs l, 27/10/\n14 av godsäg Sixten L o Elisabeth Grek.\nStudrex Linkpg 34, offrex 37, kapt 45,\nmajor 52. - KSHS 47. - Tjg\nmarin-förvaltn 47-53, lär KSHS 51-54, sousch\nKSS 54, sektrch marinförvaltn sed 59.\n\n-  Utm: RSO, RyttOlftjM.\n\nGift m Helena Schullström f 17, dtr t\nköpman Harald S o h h. - Barn:\nSten-Olof f 47, Björn f 48, Bo f 53.\nLINDBLAD, SVEN J H,\nbankdirektör, Lidingö, f i Väddö, Sthlms l,\n6/11/09 av landsfiskal Ragnar L o Edith\nPira.\n\nStudiex Södertälje 29, jur kand 34,\ntingstjg 34-37, länsbokhåil Sthlms l\n37-44, eo tax .’insp där 45-46, länsassess\n47-50 (eo 46), akad:räntmäst Upps\n50-60, verkst dlr Sparbankernas bk ab sed\n60. - Ordf berednindr 37, 44 o 51,\ntaxrndr 39-51, sekr länsstyr antagn:nd\n44-50, kamrer o dir:sekr inst f blinda\nTomteboda 47-50, sakk fin:dep rör\nman-talsskrivn 48, expert 47 års pens:utredn\n48-50, led 49 års folkbokför:sakk, komm\nf utbyggn av Akad sjh 52-60, v ordf dir\nf Akad sjh 54-60, prefekt gymn:- o\nidr:-inst Upps univ 54-60, led sakk utredn\no förhand! rör StHS framtida stallo\n56-59, komm f utredn ang univ\negend:-förvaltn 58, stynled ab Pharmacia 59,\nordf 61 m fi, hedL Upps stud idr:fören,\nUppl nät, OD, medl S:ta Ragnhilds\ngille, SHT, Sthlms köpmansklubb,\nNat:-ekon fören. - LVS 56. - Utm: RNO.\nGift 38 m Ingrid Larsson f 14, dtr t\npostmast Oscar L o Anna Neuman.\n-Barn: Ragnar f 39, Ulf f 41, Kerstin\nf 49.\n\n",
    "structured": {
        "0": {
            "full_name": "C Ivar Emil Lindblad",
            "location": "Stockholm",
            "occupation": "Tandläkare",
            "birth_details": {
                "date": "27/04/1914",
                "place": "Lidingö",
                "parents": "Tandläk Emil L o Maja Rosenberg"
            },
            "education": [
                {
                    "degree": "Studentexamen",
                    "year": "1933",
                    "institution": "Stockholm"
                },
                {
                    "degree": "Tandläkarexamen",
                    "year": "1938",
                    "institution": "Egen praktik, Stockholm"
                }
            ],
            "career": [
                {
                    "position": "Egen praktik",
                    "years": {
                        "start_year": 1939,
                        "end_year": null
                    },
                    "organization": "Stockholm"
                }
            ],
            "family": {
                "spouse": "Käthie Gentele",
                "marriage_year": "1947",
                "children": [
                    {
                        "name": "Frank",
                        "birth_year": "1949"
                    }
                ]
            }
        },
        "1": {
            "full_name": "Lars A Lindblad",
            "location": "Johanneshov",
            "occupation": "Civilingenjör",
            "birth_details": {
                "date": "21/06/1917",
                "place": "Ludvika",
                "parents": "Fil dr Axel L o Ester Bergman"
            },
            "education": [
                {
                    "degree": "Studentexamen",
                    "year": "1937",
                    "institution": null
                },
                {
                    "degree": "Civilingenjörsexamen",
                    "year": "1945",
                    "institution": null
                }
            ],
            "career": [
                {
                    "position": "Anst Forsknr-lab",
                    "years": {
                        "start_year": 1945,
                        "end_year": null
                    },
                    "organization": "LKB"
                },
                {
                    "position": "Ab Wicanders korkfabr",
                    "years": {
                        "start_year": 1946,
                        "end_year": null
                    },
                    "organization": null
                },
                {
                    "position": "Isoler Ab WMB",
                    "years": {
                        "start_year": 1948,
                        "end_year": null
                    },
                    "organization": null
                },
                {
                    "position": "Försäkrrab Skandia",
                    "years": {
                        "start_year": 1950,
                        "end_year": null
                    },
                    "organization": null
                },
                {
                    "position": "Branding",
                    "years": {
                        "start_year": 1951,
                        "end_year": null
                    },
                    "organization": null
                },
                {
                    "position": "Reassurrch",
                    "years": {
                        "start_year": 1957,
                        "end_year": null
                    },
                    "organization": null
                }
            ],
            "family": null
        },
        "2": {
            "full_name": "Per Olof Lindblad",
            "location": "Saltsjöbaden",
            "occupation": "Docent",
            "birth_details": {
                "date": "22/10/1927",
                "place": "Uppsala",
                "parents": "Prof Bertil L o Dagmar Bolin"
            },
            "education": [
                {
                    "degree": "Studrex",
                    "year": "1946",
                    "institution": "Saltsjöbaden"
                },
                {
                    "degree": "Fil kand",
                    "year": "1951",
                    "institution": "Stockholm"
                },
                {
                    "degree": "Fil mag",
                    "year": "1952",
                    "institution": null
                },
                {
                    "degree": "Fü lic",
                    "year": "1956",
                    "institution": null
                },
                {
                    "degree": "Fil dr",
                    "year": "1960",
                    "institution": null
                }
            ],
            "career": [
                {
                    "position": "Aman Sthlms observatorium",
                    "years": {
                        "start_year": 1951,
                        "end_year": null
                    },
                    "organization": "Saltsjöbaden"
                },
                {
                    "position": "Ass",
                    "years": {
                        "start_year": 1957,
                        "end_year": null
                    },
                    "organization": "Sthlms univ"
                },
                {
                    "position": "Doc",
                    "years": {
                        "start_year": 1960,
                        "end_year": null
                    },
                    "organization": "Sthlms univ"
                }
            ],
            "family": {
                "spouse": "Gunilla Alsen",
                "marriage_year": "1959",
                "children": [
                    {
                        "name": "Hans",
                        "birth_year": "1960"
                    }
                ]
            }
        },
        "3": {
            "full_name": "Sten A S Lindblad",
            "location": "Näsbypark",
            "occupation": "Major",
            "birth_details": {
                "date": "27/10/1914",
                "place": "Frinnaryd, Jönkpgs l",
                "parents": "Godsäg Sixten L o Elisabeth Grek"
            },
            "education": [
                {
                    "degree": "Studrex",
                    "year": "1934",
                    "institution": "Linkpg"
                },
                {
                    "degree": "Offrex",
                    "year": "1937",
                    "institution": null
                }
            ],
            "career": [
                {
                    "position": "Tjg marin-förvaltn",
                    "years": {
                        "start_year": 1947,
                        "end_year": 1953
                    },
                    "organization": null
                },
                {
                    "position": "Lär",
                    "years": {
                        "start_year": 1951,
                        "end_year": 1954
                    },
                    "organization": "KSHS"
                },
                {
                    "position": "Sousch",
                    "years": {
                        "start_year": 1954,
                        "end_year": null
                    },
                    "organization": "KSS"
                },
                {
                    "position": "Sektrch marinförvaltn",
                    "years": {
                        "start_year": 1959,
                        "end_year": null
                    },
                    "organization": null
                }
            ],
            "family": {
                "spouse": "Helena Schullström",
                "marriage_year": null,
                "children": [
                    {
                        "name": "Sten-Olof",
                        "birth_year": "1947"
                    },
                    {
                        "name": "Björn",
                        "birth_year": "1948"
                    },
                    {
                        "name": "Bo",
                        "birth_year": "1953"
                    }
                ]
            }
        },
        "4": {
            "full_name": "Sven J H Lindblad",
            "location": "Lidingö",
            "occupation": "Bankdirektör",
            "birth_details": {
                "date": "06/11/1909",
                "place": "Väddö, Sthlms l",
                "parents": "Landsfiskal Ragnar L o Edith Pira"
            },
            "education": [
                {
                    "degree": "Studiex",
                    "year": "1929",
                    "institution": "Södertälje"
                },
                {
                    "degree": "Jur kand",
                    "year": "1934",
                    "institution": null
                }
            ],
            "career": [
                {
                    "position": "Tingstjg",
                    "years": {
                        "start_year": 1934,
                        "end_year": 1937
                    },
                    "organization": null
                },
                {
                    "position": "Länsbokhållare",
                    "years": {
                        "start_year": 1937,
                        "end_year": 1944
                    },
                    "organization": "Sthlms l"
                },
                {
                    "position": "Eo tax insp",
                    "years": {
                        "start_year": 1945,
                        "end_year": 1946
                    },
                    "organization": "Sthlms l"
                },
                {
                    "position": "Länsassess",
                    "years": {
                        "start_year": 1947,
                        "end_year": 1950
                    },
                    "organization": null
                },
                {
                    "position": "Akad:räntmäst",
                    "years": {
                        "start_year": 1950,
                        "end_year": 1960
                    },
                    "organization": "Upps"
                },
                {
                    "position": "Verkst dlr",
                    "years": {
                        "start_year": 1960,
                        "end_year": null
                    },
                    "organization": "Sparbankernas bk ab"
                }
            ],
            "family": {
                "spouse": "Ingrid Larsson",
                "marriage_year": "1938",
                "children": [
                    {
                        "name": "Ragnar",
                        "birth_year": "1939"
                    },
                    {
                        "name": "Ulf",
                        "birth_year": "1941"
                    },
                    {
                        "name": "Kerstin",
                        "birth_year": "1949"
                    }
                ]
            }
        }
    }
}