{
    "original": "LIDSTRÖM, FRITZ O, överläkare,\nSthlm, f i Piteå 23/10/00 av skogsinsp\nLudvig L o Augusta Larsson.\n\nStud:ex Umeå 20, med kand Sthlm 23,\nmed lic 27, med dr 54; öl läk:förordn\n27-37, l:e underläk o bitr överläk kir\navd Sabbatsb sjh 37, överläk där sed\n58. - Skr: i kirurgi.\n\nGift 36 m Ruth Belin f 07, dtr t fabr\nJohn B o Ebba Wiberg. - Barn: Olle\nf 37, Per f 39, Anders f 42.\n\nLIDSTRÖM, THORE E, tandläkare,\nSthlm, f i Malmbäck, Jönkpgs l, 30/10/04\nav folkskollär Claes L o Karin\nAndersson.\n\nStudiex Eksjö 24, odont kand 25,\ntand-läk:ex 27, prakt Nässjö 27-30, Upps sed\n30, prakt Sthlm. - Medl Tandläkrförb,\nTandläkisällsk, FrimO.\nGift 51 m Elsa Ennius.\n\nLIEDBERG, E GUNNAR, pöl mag,\nBandhagen, f i Sthlm 2/7/28 av tjm\nErik L o Birgitta Carlsson.\nStud:ex 47, pol mag, sekr orgravd\nSthlms städs kansli sed 60. - Sekr Sv\nsjhfören sed 62.\n\nGift m Lena Karlström. - Barn: Asa\nf 58, Anna f 62.\n\nLIEDBERGIUS, A CAMILLA K,\nmusikdirektör, Bromma, f i Kristianst\n1/6/14 av arkit Erik Rasmussen o\nHedvig Nilsson.\n\nGmg flicklärov, MA 34-40, högre\nmusiklär: ex 38, sångstud f Marianne\nMörner o Eva Pawlo, ex pianopedagog,\npianolär Sthlms kommun musiksk sed 61,\nsolist o ackompanjatris på konserter o i\nradio i Sv:e o utl, sångsollist i kyrkor,\nradio o m ork:fören. - Styr:led Sv\npia-öolänförb, Nya Idun sed 38. - Utg:\nvisor, romanser, kör- o\nviolinarrangemang.\n\nGift 40 m sångpedagog Sixten\nLied^-bergius f 04. - Barn: Håkan f 42,\nAnders f 45, Sixten f 47, Lars Johan f 51.\n\n",
    "structured": {
        "1": {
            "full_name": "LIDSTRÖM, FRITZ O",
            "location": "Sthlm",
            "occupation": "överläkare",
            "birth_details": {
                "date": "23/10/1900",
                "place": "Piteå",
                "parents": "skogsinsp Ludvig L o Augusta Larsson"
            },
            "education": [
                {
                    "degree": "Stud:ex",
                    "year": "1920",
                    "institution": "Umeå"
                },
                {
                    "degree": "med kand",
                    "year": "1923",
                    "institution": "Sthlm"
                },
                {
                    "degree": "med lic",
                    "year": "1927",
                    "institution": "Sthlm"
                },
                {
                    "degree": "med dr",
                    "year": "1954",
                    "institution": null
                }
            ],
            "career": [
                {
                    "position": "öl läk:förordn",
                    "years": {
                        "start_year": 1927,
                        "end_year": 1937
                    },
                    "organization": null
                },
                {
                    "position": "l:e underläk o bitr överläk kir avd Sabbatsb sjh",
                    "years": {
                        "start_year": 1937,
                        "end_year": 1958
                    },
                    "organization": null
                }
            ],
            "family": {
                "spouse": "Ruth Belin",
                "marriage_year": "1936",
                "children": [
                    {
                        "name": "Olle",
                        "birth_year": "1937"
                    },
                    {
                        "name": "Per",
                        "birth_year": "1939"
                    },
                    {
                        "name": "Anders",
                        "birth_year": "1942"
                    }
                ]
            }
        },
        "2": {
            "full_name": "LIDSTRÖM, THORE E",
            "location": "Sthlm",
            "occupation": "tandläkare",
            "birth_details": {
                "date": "30/10/1904",
                "place": "Malmbäck, Jönkpgs l",
                "parents": "folkskollär Claes L o Karin Andersson"
            },
            "education": [
                {
                    "degree": "Studiex",
                    "year": "1924",
                    "institution": "Eksjö"
                },
                {
                    "degree": "odont kand",
                    "year": "1925",
                    "institution": null
                },
                {
                    "degree": "tand-läk:ex",
                    "year": "1927",
                    "institution": null
                }
            ],
            "career": [
                {
                    "position": "prakt Nässjö",
                    "years": {
                        "start_year": 1927,
                        "end_year": 1930
                    },
                    "organization": null
                },
                {
                    "position": "prakt Sthlm",
                    "years": {
                        "start_year": 1930,
                        "end_year": null
                    },
                    "organization": null
                }
            ],
            "family": {
                "spouse": "Elsa Ennius",
                "marriage_year": "1951",
                "children": []
            }
        },
        "3": {
            "full_name": "LIEDBERG, E GUNNAR",
            "location": "Bandhagen",
            "occupation": "pöl mag",
            "birth_details": {
                "date": "2/7/1928",
                "place": "Sthlm",
                "parents": "tjm Erik L o Birgitta Carlsson"
            },
            "education": [
                {
                    "degree": "Stud:ex",
                    "year": "1947",
                    "institution": null
                },
                {
                    "degree": "pol mag",
                    "year": null,
                    "institution": null
                }
            ],
            "career": [
                {
                    "position": "sekr orgravd Sthlms städs kansli",
                    "years": {
                        "start_year": 1960,
                        "end_year": null
                    },
                    "organization": null
                }
            ],
            "family": {
                "spouse": "Lena Karlström",
                "marriage_year": null,
                "children": [
                    {
                        "name": "Asa",
                        "birth_year": "1958"
                    },
                    {
                        "name": "Anna",
                        "birth_year": "1962"
                    }
                ]
            }
        },
        "4": {
            "full_name": "LIEDBERGIUS, A CAMILLA K",
            "location": "Bromma",
            "occupation": "musikdirektör",
            "birth_details": {
                "date": "1/6/1914",
                "place": "Kristianst",
                "parents": "arkit Erik Rasmussen o Hedvig Nilsson"
            },
            "education": [
                {
                    "degree": "flicklärov, MA",
                    "year": "1934-1940",
                    "institution": null
                },
                {
                    "degree": "högre musiklär: ex",
                    "year": "1938",
                    "institution": null
                },
                {
                    "degree": "sångstud f Marianne Mörner o Eva Pawlo",
                    "year": null,
                    "institution": null
                },
                {
                    "degree": "ex pianopedagog",
                    "year": null,
                    "institution": null
                },
                {
                    "degree": "pianolär Sthlms kommun musiksk",
                    "year": "1961",
                    "institution": null
                }
            ],
            "career": [
                {
                    "position": "solist o ackompanjatris på konserter o i radio i Sv:e o utl",
                    "years": {
                        "start_year": null,
                        "end_year": null
                    },
                    "organization": null
                }
            ],
            "family": {
                "spouse": "sångpedagog Sixten Liedbergius",
                "marriage_year": "1940",
                "children": [
                    {
                        "name": "Håkan",
                        "birth_year": "1942"
                    },
                    {
                        "name": "Anders",
                        "birth_year": "1945"
                    },
                    {
                        "name": "Sixten",
                        "birth_year": "1947"
                    },
                    {
                        "name": "Lars Johan",
                        "birth_year": "1951"
                    }
                ]
            }
        }
    }
}