{
    "original": "PETERHOFF, ROME, bitr överläkare,\n\nNorrköping, f i Tartu, Estl, 16/11/20 av\ndorn Bruno P o Mary Amberg.\nStud:ex Tartu 38, med kand 46 o med\nlic Lund 50, underläk röntgenavd\nKarlskrona las 51-53, kir avd Eksjö las 53-55,\nröntgendiagn avd o radiol klin Lunds\nlas 55-61, bitr överläk röntgenavd\nNorr-kpgs las sed 61. - Konsult Söderkpgs las\n61-62. - Skr i röntgendiagn.\nGift 43 m Eha Lusikas f 21, dtr t rev\nAlfred L o Hilda Frisch. - Barn: Urmas\nf 48, Henrik f 52.\n\nPETERS, BENGT E, lektor, Gbg, f i\nGbg 26/2/17 av jv:kondukt Emil P o\nAgnes Olsson.\n\nStud:ex 35, fil kand Gbg 41, fil mag 43,\nfil lic 51; e lär GbgHdlI 43, eo ämneslär\ndär 51, adj Hvitfeldtska hal 56, vik lekt\nVasa hal sed 60, lekt Östra realsk komm\ngymn sed 62. - Tunlar GbgHdlI sed 58.\n\n-  Intend GbgHS stud :kår 45-47.\n\nGift 55 m sjuksköt Gerd Säf ström f 16.\n\n-  Barn: Michael f 55, Monica f 58.\n\nPETERSEN, S ERLAND J, disponent,\n\nGbg, f i Gbg 27/1/07 av prokurist Sven\nP o Gerda Persson.\n\nStud:ex 26, Slöjdfören sk 27-33,\nreklam-ch m m Gbgs litogr ab, förs :ch Wezäta\nab 43, disp 55, disp o ch Wezäta ab i\nWezäta-Melins ab sed 62. - Ordf Gbgs\nreklamfören 51-52, styr:led Sv\nförsäljn:-o reklamförb sed 54. - Skr: art i fackpr,\nföredr v utb:kurser i typografi, försäljn\no reklam. - Hobbies: foto, konst.\nGift 33 m Gertrud Hjalmarson f 11, dtr\nt grossh Hjalmar Andersson o Alli\nOlsson. - Barn: Birgitta f 35, Lars f 40.\n\nPETERSEN, K G INGEMAR, docent,\n\növerläkare, Gbg, f i Luleå 22/10/16 av\ntonsätt Gunnar P o Anna Hall.\nMed lic Upps 45, med dr Sthlm 52, doc\ni klinisk neurofysiologi Karol inst 53-56,\nGbgs univ sed 56; öl läk :förordn 45-55,\növerläk klin:-neurofysiolog lab Sahlgr\nsjh sed 56. - Gästforsk Bay lör Univ\nTexas USA 59-60 o 63. - Skr i\nneurologi, klinisk neurofysiologi o\nneurofysiologi.\n\nGift 39 m Edith Ekberg f 13, dtr t köpm\nAugust E o Alma Lundkvist. - Barn:\nIng-Marie f 40.\n\nPETERZÉN,  INGVAR  A  O,  fil  dr,\n\nlektor, Motala, f i Sthlm 14/11/04 av\nlitograf Axel P o Anna Widman.\nStud:ex 23, fil mag 27, fil lic 34, fil dr\n45. - Ämneslär komm mellansk\nStocksund 38, lekt i modersm o hist m\nsamh:-lära hal Motala sed 46. -\nTryckfrihets-omb sed 59. - Ordf distr E LR sed 62,\nöstgötakrets Historielär fören sed 57,\nÖstergötl distr :studieråd av studieförb\nMedborgarsk sed 59, Motala hum förb\nsed 47, Motalaavd fören Norden 48-58;\nled Stadsfullm sed 54 (2:e v ordf 59-62).\n- Skr: Studier rör Sthlms historia under\nGustav Vasa (drsavh 45), ett flert upps i\nHist tidskr, Samf S:t Eriks årsbok (43),\nFrån bergslag o bondebygd (55) m m,\nutg ett flert skoluppl av skönlitt verk\nsed 54. - Utm: RNO.\nGift 36 m Karin Englund f 12, dtr t\nkont :ch Fritiof E o Marie-Louise\nTuju-lin. - Barn: Elisabet f 38, Gustaf f 41,\nMargareta f 44.\n\nPETERZÉN,   C   JAN   O,   tandläkare,\n\nLinköping, f i Linkpg 1/10/32 av tandl\nCurt P o Ingeborg Hegerfors.\nStud:ex 51, stud v CTH Gbg 52-54,\ntandl :ex Sthlm 59, priv :prakt Linkpg sed\n59. - Red Odont fören tidskr 57-58, ordf\nOdont fören 58-59. - Medl DruidO.\n-Hobbies: sändareamatör (SM5BKN),\nfotografering.\n\nGift 62 m talpedagog Catrine Almroth\nf 30, dtr t lantbr Rudolf A o Hanna\nHansson. - Barn: Åsa f 62, Anna o Ulla\nff 63.\n\n",
    "structured": {
        "1": {
            "full_name": "PETERHOFF, ROME",
            "location": "Norrköping",
            "occupation": "bitr överläkare",
            "birth_details": {
                "date": "16/11/1920",
                "place": "Tartu, Estland",
                "parents": "Bruno P o Mary Amberg"
            },
            "education": [
                {
                    "degree": "Stud:ex",
                    "year": "1938",
                    "institution": "Tartu"
                },
                {
                    "degree": "med kand",
                    "year": "1946",
                    "institution": "Tartu"
                },
                {
                    "degree": "med lic",
                    "year": "1950",
                    "institution": "Lund"
                }
            ],
            "career": [
                {
                    "position": "underläk röntgenavd",
                    "years": {
                        "start_year": 1951,
                        "end_year": 1953
                    },
                    "organization": "Karlskrona las"
                },
                {
                    "position": "kir avd",
                    "years": {
                        "start_year": 1953,
                        "end_year": 1955
                    },
                    "organization": "Eksjö las"
                },
                {
                    "position": "röntgendiagn avd o radiol klin",
                    "years": {
                        "start_year": 1955,
                        "end_year": 1961
                    },
                    "organization": "Lunds las"
                },
                {
                    "position": "bitr överläk röntgenavd",
                    "years": {
                        "start_year": 1961,
                        "end_year": null
                    },
                    "organization": "Norr-kpgs las"
                }
            ],
            "family": {
                "spouse": "Eha Lusikas",
                "marriage_year": "1943",
                "children": [
                    {
                        "name": "Urmas",
                        "birth_year": "1948"
                    },
                    {
                        "name": "Henrik",
                        "birth_year": "1952"
                    }
                ]
            }
        },
        "2": {
            "full_name": "PETERS, BENGT E",
            "location": "Gbg",
            "occupation": "lektor",
            "birth_details": {
                "date": "26/02/1917",
                "place": "Gbg"
            },
            "education": [
                {
                    "degree": "Stud:ex",
                    "year": "1935",
                    "institution": null
                },
                {
                    "degree": "fil kand",
                    "year": "1941",
                    "institution": "Gbg"
                },
                {
                    "degree": "fil mag",
                    "year": "1943",
                    "institution": null
                },
                {
                    "degree": "fil lic",
                    "year": "1951",
                    "institution": null
                }
            ],
            "career": [
                {
                    "position": "e lär",
                    "years": {
                        "start_year": 1943,
                        "end_year": null
                    },
                    "organization": "GbgHdlI"
                },
                {
                    "position": "eo ämneslär",
                    "years": {
                        "start_year": 1951,
                        "end_year": null
                    },
                    "organization": "GbgHdlI"
                },
                {
                    "position": "adj",
                    "years": {
                        "start_year": 1956,
                        "end_year": null
                    },
                    "organization": "Hvitfeldtska hal"
                },
                {
                    "position": "vik lekt",
                    "years": {
                        "start_year": 1960,
                        "end_year": null
                    },
                    "organization": "Vasa hal"
                }
            ],
            "family": {
                "spouse": "Gerd Säf ström",
                "marriage_year": "1955",
                "children": [
                    {
                        "name": "Michael",
                        "birth_year": "1955"
                    },
                    {
                        "name": "Monica",
                        "birth_year": "1958"
                    }
                ]
            }
        },
        "3": {
            "full_name": "PETERSEN, S ERLAND J",
            "location": "Gbg",
            "occupation": "disponent",
            "birth_details": {
                "date": "27/01/1907",
                "place": "Gbg",
                "parents": "prokurist Sven P o Gerda Persson"
            },
            "education": [
                {
                    "degree": "Stud:ex",
                    "year": "1926",
                    "institution": null
                }
            ],
            "career": [
                {
                    "position": null,
                    "years": {
                        "start_year": 1955,
                        "end_year": null
                    },
                    "organization": "Wezäta ab"
                }
            ],
            "family": {
                "spouse": "Gertrud Hjalmarson",
                "marriage_year": "1933",
                "children": [
                    {
                        "name": "Birgitta",
                        "birth_year": "1935"
                    },
                    {
                        "name": "Lars",
                        "birth_year": "1940"
                    }
                ]
            },
            "hobbies": [
                "foto",
                "konst"
            ]
        },
        "4": {
            "full_name": "PETERSEN, K G INGEMAR",
            "location": "Gbg",
            "occupation": "docent, överläkare",
            "birth_details": {
                "date": "22/10/1916",
                "place": "Luleå",
                "parents": "tonsätt Gunnar P o Anna Hall"
            },
            "education": [
                {
                    "degree": "Med lic",
                    "year": "1945",
                    "institution": "Upps"
                },
                {
                    "degree": "Med dr",
                    "year": "1952",
                    "institution": "Sthlm"
                }
            ],
            "career": [
                {
                    "position": "överläk klin:-neurofysiolog lab",
                    "years": {
                        "start_year": 1956,
                        "end_year": null
                    },
                    "organization": "Sahlgr sjh"
                }
            ],
            "family": {
                "spouse": "Edith Ekberg",
                "marriage_year": "1939",
                "children": [
                    {
                        "name": "Ing-Marie",
                        "birth_year": "1940"
                    }
                ]
            }
        },
        "5": {
            "full_name": "PETERZÉN, INGVAR A O",
            "location": "Motala",
            "occupation": "fil dr, lektor",
            "birth_details": {
                "date": "14/11/1904",
                "place": "Sthlm",
                "parents": "litograf Axel P o Anna Widman"
            },
            "education": [
                {
                    "degree": "Stud:ex",
                    "year": "1923",
                    "institution": null
                },
                {
                    "degree": "fil mag",
                    "year": "1927",
                    "institution": null
                },
                {
                    "degree": "fil lic",
                    "year": "1934",
                    "institution": null
                },
                {
                    "degree": "fil dr",
                    "year": "1945",
                    "institution": null
                }
            ],
            "career": [
                {
                    "position": "Ämneslär",
                    "years": {
                        "start_year": 1946,
                        "end_year": null
                    },
                    "organization": "Motala"
                },
                {
                    "position": "lekt i modersm o hist",
                    "years": {
                        "start_year": null,
                        "end_year": null
                    },
                    "organization": "Motala"
                }
            ],
            "family": {
                "spouse": "Karin Englund",
                "marriage_year": "1936",
                "children": [
                    {
                        "name": "Elisabet",
                        "birth_year": "1938"
                    },
                    {
                        "name": "Gustaf",
                        "birth_year": "1941"
                    },
                    {
                        "name": "Margareta",
                        "birth_year": "1944"
                    }
                ]
            }
        },
        "6": {
            "full_name": "PETERZÉN, C JAN O",
            "location": "Linköping",
            "occupation": "tandläkare",
            "birth_details": {
                "date": "01/10/1932",
                "place": "Linkpg",
                "parents": "tandl Curt P o Ingeborg Hegerfors"
            },
            "education": [
                {
                    "degree": "Stud:ex",
                    "year": "1951",
                    "institution": null
                },
                {
                    "degree": "stud v",
                    "year": "1952-1954",
                    "institution": "CTH Gbg"
                },
                {
                    "degree": "tandl :ex",
                    "year": "1959",
                    "institution": "Sthlm"
                }
            ],
            "career": [
                {
                    "position": "priv :prakt",
                    "years": {
                        "start_year": 1959,
                        "end_year": null
                    },
                    "organization": "Linkpg"
                }
            ],
            "family": {
                "spouse": "Catrine Almroth",
                "marriage_year": "1962",
                "children": [
                    {
                        "name": "Åsa",
                        "birth_year": "1962"
                    },
                    {
                        "name": "Anna",
                        "birth_year": "1963"
                    },
                    {
                        "name": "Ulla",
                        "birth_year": "1963"
                    }
                ]
            },
            "hobbies": [
                "sändareamatör (SM5BKN)",
                "fotografering"
            ]
        }
    }
}