{
    "original": "PATRIKSON, HANS V P,\ndistriktsveterinär, Gamleby, f i Karlslunda,\nKalmar l, 1/9/21 av landsfiskal Patrik\nErlandson o Ebba Nilsson.\nVet:ex VHS 49, ch :vet Tjustbygdens\nse-minfören 50-65, tjg NIB i Kalibia\nTunisien 63-65, distr :vet Gamleby sed 65.\n-Medl Lions club.\n\nGift 46 m Ingrid Ström f 22, dtr t\nlandsfiskal Erland S o Helmi Zeidlitz. - Barn:\nAnna-Karin f 47, Patrik f 52.\n\nPAUES, ERIC, disponent, Västervik, f\ni Gävle 4/9/05 av l:e stat:skriv Gösta P\no Anna Borg.\n\nSchartaus hdlI 27, kont F:a H\nEysen-hardt Sthlm 27, ink:ch ab Sv\nStrebelver-ken Västervik 33, disp Grantorpets fabr\nab 37-64 (styr:led). - Medl Odd Fellow.\nGift 34 m Magda Sköldborg f 07.\n-Barn: Anna-Lena f 43.\n\nPAULSEN, P ERIK,\ndistriktslantmätare, Vimmerby, f i Malmö 6/8/11 av\njordbr:konsulent Hjalmar P o Anna\nBondesson.\n\nKTH 36, lantmät Kristianst l 36,\nläns-lantmät:kont Luleå 42, Kopparb l 45-53,\nlantmät :styr 46, distr :lantmät Vimmerby\ndistr sed 53. - Expr:tekn Kalm l 56, led\nvägsynendrna f N Kalm l 56. - Ordf\nStadsfullm 64 (led 58), suppl DK 59, led\nnykterh:nd 55-59, skolstyr 58-60 (suppl\n60-63), ordf centr byggn:komm 59. -\n\nKapt   A   6   res   53.   -   Utm:   SCFftjtS,\nSkytteSM. - Hobby: numismatik.\nGift 42 m Gunvor Johansson f 15, dtr\nt adv Gustaf J o Anna Sonesson. - Barn:\nBo f 52, Anker f 53, Elisabet f 59.\n\nPAULSON, G BIRGER, direktör,\nLinköping, f i Kallna, Kristianst l, 27/2/01\nav handl A P o A Ch Svensson.\nHdlssk 22, SBH Köpenh 26, bryggmäst\nMjölby o Vadstena brygg 27, disp ab\nWasabrygg Borlänge 30, verkst dir ab\nNya centralbrygg 34, konsult dir 64;\ninneh firma Globe sed 52. - Styr :led ab\nNya centralbrygg o dess dtrbol 34-64,\nSv ab Consul o Porla brunns ab 43-64,\nab Fructus fabr 56-64, styr :ordf Skand\nbkn Linkpg. - Styr :led Sv vattenfabr\nriksförb o ordf dess Östg:krets, styr:led\nSv bryggarefören o Sv:es bryggeriförb\n48-64, ordf Sv bryggarefören ö :a krets\n47-64, hedL där o Mell Sv:es\nbryggeri-fören. - Led Inst of Brewing sed 51.\n-Led DK Linkpg 38-48 m fi allm uppdr.\n- Medl Rotary, FrimO. - Utm: RVO,\n",
    "structured": {
        "1": {
            "full_name": "Hans V P Patrikson",
            "location": "Gamleby",
            "occupation": "distriktsveterinär",
            "birth_details": {
                "date": "01/09/1921",
                "place": "Karlslunda, Kalmar l",
                "parents": "landsfiskal Patrik Erlandson o Ebba Nilsson"
            },
            "education": [
                {
                    "degree": "Vet:ex VHS",
                    "year": "1949",
                    "institution": "VHS"
                }
            ],
            "career": [
                {
                    "position": "ch :vet Tjustbygdens se-minfören",
                    "years": {
                        "start_year": 1950,
                        "end_year": 1965
                    },
                    "organization": "Tjustbygdens se-minfören"
                },
                {
                    "position": "tjg NIB i Kalibia Tunisien",
                    "years": {
                        "start_year": 1963,
                        "end_year": 1965
                    },
                    "organization": "NIB"
                },
                {
                    "position": "distr :vet Gamleby",
                    "years": {
                        "start_year": 1965
                    },
                    "organization": "Gamleby"
                }
            ],
            "family": {
                "spouse": "Ingrid Ström",
                "marriage_year": "1946",
                "children": [
                    {
                        "name": "Anna-Karin",
                        "birth_year": "1947"
                    },
                    {
                        "name": "Patrik",
                        "birth_year": "1952"
                    }
                ]
            }
        },
        "2": {
            "full_name": "Eric Paues",
            "location": "Västervik",
            "occupation": "disponent",
            "birth_details": {
                "date": "04/09/1905",
                "place": "Gävle",
                "parents": "l:e stat:skriv Gösta P o Anna Borg"
            },
            "education": [
                {
                    "degree": "Schartaus hdlI",
                    "year": "1927",
                    "institution": "Schartaus hdlI"
                }
            ],
            "career": [
                {
                    "position": "kont F:a H Eysenhardt Sthlm",
                    "years": {
                        "start_year": 1927
                    },
                    "organization": "F:a H Eysenhardt Sthlm"
                },
                {
                    "position": "ink:ch ab Sv Strebelverken Västervik",
                    "years": {
                        "start_year": 1933
                    },
                    "organization": "Sv Strebelverken Västervik"
                },
                {
                    "position": "disp Grantorpets fabr ab",
                    "years": {
                        "start_year": 1937,
                        "end_year": 1964
                    },
                    "organization": "Grantorpets fabr ab"
                }
            ],
            "family": {
                "spouse": "Magda Sköldborg",
                "marriage_year": "1934",
                "children": [
                    {
                        "name": "Anna-Lena",
                        "birth_year": "1943"
                    }
                ]
            }
        },
        "3": {
            "full_name": "P Erik Paulsen",
            "location": "Vimmerby",
            "occupation": "distriktslantmätare",
            "birth_details": {
                "date": "06/08/1911",
                "place": "Malmö",
                "parents": "jordbr:konsulent Hjalmar P o Anna Bondesson"
            },
            "education": [
                {
                    "degree": "KTH",
                    "year": "1936",
                    "institution": "KTH"
                },
                {
                    "degree": "lantmät Kristianst l",
                    "year": "1936",
                    "institution": "Lantmät Kristianst l"
                }
            ],
            "career": [
                {
                    "position": "läns-lantmät:kont Luleå",
                    "years": {
                        "start_year": 1942
                    },
                    "organization": "Luleå"
                },
                {
                    "position": "Kopparb l",
                    "years": {
                        "start_year": 1945,
                        "end_year": 1953
                    },
                    "organization": "Kopparb l"
                },
                {
                    "position": "lantmät :styr",
                    "years": {
                        "start_year": 1946
                    }
                },
                {
                    "position": "distr :lantmät Vimmerby",
                    "years": {
                        "start_year": 1953
                    },
                    "organization": "Vimmerby"
                }
            ],
            "family": {
                "spouse": "Gunvor Johansson",
                "marriage_year": "1942",
                "children": [
                    {
                        "name": "Bo",
                        "birth_year": "1952"
                    },
                    {
                        "name": "Anker",
                        "birth_year": "1953"
                    },
                    {
                        "name": "Elisabet",
                        "birth_year": "1959"
                    }
                ]
            },
            "hobbies": [
                "numismatik"
            ]
        },
        "4": {
            "full_name": "G Birger Paulson",
            "location": "Linköping",
            "occupation": "direktör",
            "birth_details": {
                "date": "27/02/1901",
                "place": "Kallna, Kristianst l",
                "parents": "handl A P o A Ch Svensson"
            },
            "education": [
                {
                    "degree": "Hdlssk",
                    "year": "1922",
                    "institution": "Hdlssk"
                },
                {
                    "degree": "SBH Köpenh",
                    "year": "1926",
                    "institution": "SBH Köpenh"
                }
            ],
            "career": [
                {
                    "position": "bryggmäst Mjölby o Vadstena brygg",
                    "years": {
                        "start_year": 1927
                    },
                    "organization": "Mjölby o Vadstena brygg"
                },
                {
                    "position": "disp ab Wasabrygg Borlänge",
                    "years": {
                        "start_year": 1930
                    },
                    "organization": "ab Wasabrygg Borlänge"
                },
                {
                    "position": "verkst dir ab Nya centralbrygg",
                    "years": {
                        "start_year": 1934
                    },
                    "organization": "ab Nya centralbrygg"
                },
                {
                    "position": "konsult dir",
                    "years": {
                        "start_year": 1964
                    },
                    "organization": "firma Globe"
                }
            ],
            "family": {
                "spouse": "NULL",
                "marriage_year": "NULL",
                "children": []
            },
            "board_memberships": [
                {
                    "position": "styr :led ab Nya centralbrygg o dess dtrbol",
                    "organization": "ab Nya centralbrygg",
                    "years": "1934-1964"
                },
                {
                    "position": "styr :led Sv ab Consul o Porla brunns ab",
                    "organization": "Sv ab Consul o Porla brunns ab",
                    "years": "1943-1964"
                }
            ],
            "community_involvement": [
                {
                    "role": "Led DK Linkpg",
                    "organization": "DK Linkpg",
                    "years": "1938-1948"
                }
            ],
            "hobbies": [
                "numismatik"
            ],
            "honorary_titles": [
                {
                    "title": "RVO"
                }
            ]
        }
    }
}