{
    "original": "BONDE, CARL J C:SON, friherre,\nhofjägmästare, Katrineholm, f i St\nMalm, Södermani l, 13/12/14 av l:e\nhovjägm, frih Carl B o Ingeborg Thott.\nStud:ex 34, inneh Ericsbergs\nfideikommiss sed 37, hovjägm sed 53, verkst dir\nab Forssjö bruk. - Led Stora Malms\nkomm:fullm 43-50 o sed 55, ordf cf:nd.\n- Stormast Arla ColdinuO, LSkS 44.\n-Utm: RVO, SvJägFHmG. - Hobby:\njakt.\n\nGift 40 m grev:an Marianne Mörner\naf Morlanda f 18, dtr t major, greve\nGöran M o Dorothy Bolinder. - Barn:\nCarl Göran f 41, Christina f 43, Eva\nf 45, Johan o Nils ff 49, Louise f 61.\n\nBONDE, KNUT O C, friherre,\nryttmästare, Katrineholm, f 26/1/17 av l:e\nhovjägm, frih Carl B o frih:an\nIngeborg Thott.\n\nRyttm ka v res; deläg o förvalt\nGim-mersta (Nygård), Katrineholm.\nGift 1) 42-51 m grev:an Gunnila\nMörner af Morlanda f 19, 2) 51 m Inga\nSvärdström f 23. - Barn: i l:a akt\nCatharina f 44, Torgils f 47, i 2:a akt\nCecilia f 57.\n\nBONNEVIER, K GÖSTA W, ingenjör,\nBarkarby, f i Sthlm 19/12/21 av Hugo\nB o Maria Andersson.\nIng:ex STI 53, verkm ab Merton Sthlm\n45, verkst :ch ab Automatisk värme 51,\narb :stud :ing ab Nord armaturfabr\nKungsör 53, driftsing G Nyström ab Umeå\n56, verkst :ch ab Nord armaturfabr\nKungsör 57, fabr :ch\nKontroll-Automatik fabr ab Mjölby 60, l:e avd:ing\nSthlms stads arb :v: byrå sed 64. - Led\nkomm:nd Kungsör 58-60, fritidsnd\nMjölby 61-63. - Medl Odd Fellow, Lions\nclub. - Hobbies: bridge, curling.\nGift 44 m Daina Karlsson f 24, dtr t\nhemm:äg Erik K o Hilda Nilsson.\n-Barn: Anita f 45, Thomas f 52.\n\nBONNEVIER, JOHN OLOF, leg\nläkare, Uppsala, f i Karlstad 17/7/25 av\nlas :läk John Svensson o Anna Bergstedt.\nStud:ex Sigtuna 44, med kand Sthlm 47,\nmed lic 52, ol läk :förordn 52-53,\nunderläk med avd Härnösands las 54,\nbarn-avd Nykpgs las 56, Västerås las 57,\nAkad sjh sed 62.\n\nGift 52 m Barbro Ramqvist f 23, dtr t\nkonsul Nils R o Ingegerd Frender.\n-Barn: Mikael f 53, Charlotte f 56.\n\n",
    "structured": {
        "0": {
            "full_name": "CARL J C:SON BONDE",
            "location": "Katrineholm",
            "occupation": "Hofjägmästare",
            "birth_details": {
                "date": "13/12/1914",
                "place": "St Malm, Södermani l",
                "parents": "Frih Carl B o Ingeborg Thott"
            },
            "education": [
                {
                    "degree": "Stud:ex",
                    "year": "1934",
                    "institution": "NULL"
                }
            ],
            "career": [
                {
                    "position": "Verkst dir ab Forssjö bruk",
                    "years": {
                        "start_year": 1953,
                        "end_year": null
                    },
                    "organization": "NULL"
                }
            ],
            "family": {
                "spouse": "Marianne Mörner af Morlanda",
                "marriage_year": "1940",
                "children": [
                    {
                        "name": "Carl Göran",
                        "birth_year": "1941"
                    },
                    {
                        "name": "Christina",
                        "birth_year": "1943"
                    },
                    {
                        "name": "Eva",
                        "birth_year": "1945"
                    },
                    {
                        "name": "Johan",
                        "birth_year": "1949"
                    },
                    {
                        "name": "Nils",
                        "birth_year": "1949"
                    },
                    {
                        "name": "Louise",
                        "birth_year": "1961"
                    }
                ]
            }
        },
        "1": {
            "full_name": "KNUT O C BONDE",
            "location": "Katrineholm",
            "occupation": "Ryttmästare",
            "birth_details": {
                "date": "26/01/1917",
                "place": "Katrineholm",
                "parents": "Frih Carl B o Frih:an Ingeborg Thott"
            },
            "education": [],
            "career": [],
            "family": {
                "spouse": "Gunnila Mörner af Morlanda",
                "marriage_year": "1942",
                "children": [
                    {
                        "name": "Catharina",
                        "birth_year": "1944"
                    },
                    {
                        "name": "Torgils",
                        "birth_year": "1947"
                    },
                    {
                        "name": "Cecilia",
                        "birth_year": "1957"
                    }
                ]
            }
        },
        "2": {
            "full_name": "K GÖSTA W BONNEVIER",
            "location": "Barkarby",
            "occupation": "Ingenjör",
            "birth_details": {
                "date": "19/12/1921",
                "place": "Sthlm",
                "parents": "Hugo B o Maria Andersson"
            },
            "education": [
                {
                    "degree": "Ing:ex",
                    "year": "1953",
                    "institution": "STI"
                }
            ],
            "career": [
                {
                    "position": "L:e avd:ing Sthlms stads arb :v: byrå",
                    "years": {
                        "start_year": 1964,
                        "end_year": null
                    },
                    "organization": "NULL"
                }
            ],
            "family": {
                "spouse": "Daina Karlsson",
                "marriage_year": "1944",
                "children": [
                    {
                        "name": "Anita",
                        "birth_year": "1945"
                    },
                    {
                        "name": "Thomas",
                        "birth_year": "1952"
                    }
                ]
            },
            "publications": [],
            "community_involvement": [],
            "board_memberships": [],
            "honorary_titles": [],
            "hobbies": [
                "bridge",
                "curling"
            ]
        },
        "3": {
            "full_name": "JOHN OLOF BONNEVIER",
            "location": "Uppsala",
            "occupation": "Leg läkare",
            "birth_details": {
                "date": "17/7/1925",
                "place": "Karlstad",
                "parents": "Las :läk John Svensson o Anna Bergstedt"
            },
            "education": [
                {
                    "degree": "Stud:ex",
                    "year": "1944",
                    "institution": "Sigtuna"
                },
                {
                    "degree": "Med kand",
                    "year": "1947",
                    "institution": "Sthlm"
                },
                {
                    "degree": "Med lic",
                    "year": "1952",
                    "institution": "NULL"
                }
            ],
            "career": [
                {
                    "position": "Underläk med avd Härnösands las",
                    "years": {
                        "start_year": 1954,
                        "end_year": null
                    },
                    "organization": "NULL"
                },
                {
                    "position": "Barn-avd Nykpgs las",
                    "years": {
                        "start_year": 1956,
                        "end_year": null
                    },
                    "organization": "NULL"
                },
                {
                    "position": "Västerås las",
                    "years": {
                        "start_year": 1957,
                        "end_year": null
                    },
                    "organization": "NULL"
                },
                {
                    "position": "Akad sjh",
                    "years": {
                        "start_year": 1962,
                        "end_year": null
                    },
                    "organization": "NULL"
                }
            ],
            "family": {
                "spouse": "Barbro Ramqvist",
                "marriage_year": "1952",
                "children": [
                    {
                        "name": "Mikael",
                        "birth_year": "1953"
                    },
                    {
                        "name": "Charlotte",
                        "birth_year": "1956"
                    }
                ]
            }
        }
    }
}