{
    "original": "BERGGREN,    FRITZ,   bankdirektör,\n\nKarlskoga, f i Karlskoga 1/9/02 av\ngjutare Herman B o Amy Hellström.\nFolkhögsk, montör o arb :led ab Bofors\n16-48, verkst dir Karlskoga-Degerfors\nsparbk sed 48 (styr:led 43). - Styr:suppl\nSparbkrnas bk ab, styr :led Koop\nförh:-org, led Stadsfullm sed 30, ordf 40,\nkom-m:fullm sed 30, ordf länsnykt:ndn\nÖrebro l sed 49, kretsordf Örebro l fören\nNorden sed 56.\n\nGift 27 m Olga Lindström. - Barn:\nBirgitta f 27.\n\nBERGGREN, LENNART, med dr,\ndo-cent, Uppsala, f i Sthlm 30/1/27 av dir\nHilding B o h h.\n\nStud:ex 45, med kand 47, med lic Sthlm\n52, doc i farmakologi 59, med dr 60,\n\ndoc i oftalmiatrik Upps univ 61, bitr\növerläk ögonklin Akad sjh.\n\nBERGGREN,   B   PAUL   I,   ingenjör,\n\nSödertälje, f i Nykpg 3/6/26 av\nsadelmak William B o Olga Larsson.\nIng:ex Eskilstuna 54, arb:stud:ing ab\nScania-Vabis Södertälje 54, gruppch\narb:stud:avd där 58, ch dess utveckl:sekt\nsed 59. - Ämneslär Södertälje stads tekn\naftonsk sed 58, undervis div prod:tekn\nkurser Scania-Vabis o RATI. - Uppdr\ninom TBV Södertälje o Sthlm 56-59.\n-Hobbies: konst, ornitologi.\nGift 52 m Gunborg Eriksson f 28, dtr t\nmöbelsnick Hjalmar E o Anna Eriksson.\n- Barn: Mats f 57, Ulf f 61.\n\nBERGGREN,   SUNE,   kyrkoherde,\n\nRamsberg, f i Stora Tuna, Kopparb l,\n29/11/05 av hdlsförest Alfred B o\nJohanna Persson.\n\nStud:ex Sthlm 25, teol kand Upps 33’,\nprästtjg Västerås stift 33-37, kommin\nRamsberg 37, kyrkoh där 41, kyrkoh\nGrytnäs sed 63; kontr :prost Fellingsbro\n49-58. - Utm: LVO.\n\nGift 37 m Gunborg Görs f 05, dtr t\nhandl Gustaf Eriksson o Sofie Modin.\n-Barn: Gunilla f 40, Magdalena f 41’,\nMagnus f 46.\n\n",
    "structured": {
        "1": {
            "full_name": "FRITZ BERGGREN",
            "location": "Karlskoga",
            "occupation": "bankdirektör",
            "birth_details": {
                "date": "01/09/1902",
                "place": "Karlskoga",
                "parents": "gjutare Herman B o Amy Hellström"
            },
            "education": [
                {
                    "degree": "Folkhögsk",
                    "year": "16-48",
                    "institution": "montör o arb :led ab Bofors"
                }
            ],
            "career": [
                {
                    "position": "verkst dir",
                    "years": {
                        "start_year": 1948,
                        "end_year": 1953
                    },
                    "organization": "Karlskoga-Degerfors sparbk"
                }
            ],
            "family": {
                "spouse": "Olga Lindström",
                "marriage_year": "1927",
                "children": [
                    {
                        "name": "Birgitta",
                        "birth_year": "1927"
                    }
                ]
            }
        },
        "2": {
            "full_name": "LENNART BERGGREN",
            "location": "Uppsala",
            "occupation": "med dr, docent",
            "birth_details": {
                "date": "30/01/1927",
                "place": "Sthlm",
                "parents": "dir Hilding B o h h"
            },
            "education": [
                {
                    "degree": "Stud:ex",
                    "year": "45",
                    "institution": null
                },
                {
                    "degree": "med kand",
                    "year": "47",
                    "institution": null
                },
                {
                    "degree": "med lic",
                    "year": "52",
                    "institution": "Sthlm"
                },
                {
                    "degree": "med dr",
                    "year": "60",
                    "institution": null
                }
            ],
            "career": [
                {
                    "position": "doc i farmakologi",
                    "years": {
                        "start_year": 1959,
                        "end_year": 1960
                    },
                    "organization": "Sthlm"
                },
                {
                    "position": "doc i oftalmiatrik",
                    "years": {
                        "start_year": 1961,
                        "end_year": 1961
                    },
                    "organization": "Upps univ"
                }
            ],
            "family": {
                "spouse": null,
                "marriage_year": null,
                "children": []
            }
        },
        "3": {
            "full_name": "PAUL I. BERGGREN",
            "location": "Södertälje",
            "occupation": "ingenjör",
            "birth_details": {
                "date": "3/6/1926",
                "place": "Nykpg",
                "parents": "sadelmak William B o Olga Larsson"
            },
            "education": [],
            "career": [
                {
                    "position": "arb:stud:ing",
                    "years": {
                        "start_year": 1954,
                        "end_year": 1954
                    },
                    "organization": "ab Scania-Vabis Södertälje"
                },
                {
                    "position": "gruppch arb:stud",
                    "years": {
                        "start_year": 1958,
                        "end_year": 1959
                    },
                    "organization": "dess utveckl:sekt"
                }
            ],
            "family": {
                "spouse": "Gunborg Eriksson",
                "marriage_year": "1952",
                "children": [
                    {
                        "name": "Mats",
                        "birth_year": "1957"
                    },
                    {
                        "name": "Ulf",
                        "birth_year": "1961"
                    }
                ]
            }
        },
        "4": {
            "full_name": "SUNE BERGGREN",
            "location": "Ramsberg",
            "occupation": "kyrkoherde",
            "birth_details": {
                "date": "29/11/1905",
                "place": "Stora Tuna, Kopparb l",
                "parents": "hdlsförest Alfred B o Johanna Persson"
            },
            "education": [
                {
                    "degree": "Stud:ex",
                    "year": "25",
                    "institution": null
                },
                {
                    "degree": "teol kand",
                    "year": "33",
                    "institution": "Upps"
                }
            ],
            "career": [
                {
                    "position": "prästtjg",
                    "years": {
                        "start_year": 1933,
                        "end_year": 1937
                    },
                    "organization": "Västerås stift"
                },
                {
                    "position": "kommin",
                    "years": {
                        "start_year": 1937,
                        "end_year": 1941
                    },
                    "organization": "Ramsberg"
                },
                {
                    "position": "kyrkoh",
                    "years": {
                        "start_year": 1941,
                        "end_year": 1963
                    },
                    "organization": "Grytnäs"
                },
                {
                    "position": "kontr :prost",
                    "years": {
                        "start_year": 1949,
                        "end_year": 1958
                    },
                    "organization": "Fellingsbro"
                }
            ],
            "family": {
                "spouse": "Gunborg Görs",
                "marriage_year": "1937",
                "children": [
                    {
                        "name": "Gunilla",
                        "birth_year": "1940"
                    },
                    {
                        "name": "Magdalena",
                        "birth_year": "1941"
                    },
                    {
                        "name": "Magnus",
                        "birth_year": "1946"
                    }
                ]
            }
        }
    }
}