{
    "original": "BENGTSSON, P ANDERS J,\nstats-agronom, Uppsala, f i Väsby, Malmöh\nl, 19/2/26 av lantbr Josef B o Astrid B.\nStud:ex Hbg 46, agr KLH 52, agr lic\n56, agr dr o docent 61, försöksled inst\nf växtodl Upps 62, statsagr sed 63.\n-Skr: Droppstorlekens inflytande på\nogräsmedlens verkan (61) m fi.\nGift 53 m Brita Persson. - Barn: Karin\nf 53, Mina f 60, Per f 62.\n\nBENGTSSON, BENGT A, ingenjör,\nNyköping, f i Sthlm 25/8/16 av fabr Carl\nB o Julia Håkansson.\nWS Katrineholm 36, anst fortif :förv\n42, Hugo Teorells ing :byrå 44-46, verkst\ndir o inneh Bengtsson &amp; Gjerdman ab\nsed 53, inneh Nykpgs svetsn ab sed 61.\n\n-  Medl W-sex. - Hobbies: jakt, fiske.\nGift 44 m Margit Persson. - Barn:\nAnn-mari f 49, Margareta f 51.\n\nBENKTSON, BENNY A L, fd\nkontraktsprost, Örebro, f i Varberg 18/8/92\nav sjökapt Lars B o Anna Borgström.\nTeol kand Upps 15, kommin Viby 16,\nkyrkoh Husby-Rekarne 31, kontr :prost\n38, kyrkoh Örebro Nikolai 42-60, prost\növer egen förs 42, kontr:prost Örebro\nkontr 52-60. - Skr: Lagens ämbete (48),\npredikn o upps i ol saml. - Utm: LNO.\nGift 17 m Greta Forssman f 91, dtr t\ngodsförv Lärs-Fredrik F o Anna\nOllan-der. - Barn: Benkt-Erik f 18, Hans\nf 22, Sten f 24.\n\nBENGTSSON, T BERTIL, jur dr,\npre-ceptor, Uppsala, f i Gbg 1315126 av\n\nbankdir Thorsten B o Asta Lundgren.\nStud:ex 44, fil kand Upps 46, jur kand\n\n50,   jur lic 59, jur dr 60.  - Anst Dag\nMagnussons adv :byrå Gbg 50-51,\ntingstjg Aska, Dals o Bobergs doms 51-53,\nfiskalsasp, fiskal o adj led hovr f V Sv :e\n53-56 o tidv därefter, tf rådm Alingsås m\nfi doms tidv 54-60, doc Upps univ 60,\npreceptor i civilrätt där sed 62. - Expert\nutredn  om forskarrekryter v  de  jurid\nfakult 60-61. - Skr: Om tolkning av\nansvarsförsäkringsvillkor (60), Om\nansvarsförsäkring  i  kontraktsförhållanden  I-II\n(drsavh 60), Skadestånd vid sport, lek o\nsällskapsliv (62), Allemansrätt o\nmark-ägarskydd (63), upps i SvJT m fi.\nGift 50 m fil måg Solveig Lindgren f 24,\ndtr t målarmäst Arvid L o Annie\nAndersson. - Barn: Jan f 55, Klas f 59,\nBengt Olof f 62.\n\n",
    "structured": {
        "0": {
            "full_name": "P Anders J Bengtsson",
            "location": "Uppsala",
            "occupation": "stats-agronom",
            "birth_details": {
                "date": "19/02/1926",
                "place": "Väsby, Malmöh"
            },
            "education": [
                {
                    "degree": "Stud:ex",
                    "year": "1946",
                    "institution": "Hbg"
                },
                {
                    "degree": "agr KLH",
                    "year": "1952",
                    "institution": "NULL"
                },
                {
                    "degree": "agr lic",
                    "year": "1956",
                    "institution": "NULL"
                },
                {
                    "degree": "agr dr",
                    "year": "1961",
                    "institution": "NULL"
                },
                {
                    "degree": "docent",
                    "year": "1961",
                    "institution": "NULL"
                }
            ],
            "career": [
                {
                    "position": "försöksledare",
                    "years": {
                        "start_year": 1962,
                        "end_year": 1963
                    },
                    "organization": "inst f växtodl Upps"
                }
            ],
            "family": {
                "spouse": "Brita Persson",
                "marriage_year": "1953",
                "children": [
                    {
                        "name": "Karin",
                        "birth_year": "1953"
                    },
                    {
                        "name": "Mina",
                        "birth_year": "1960"
                    },
                    {
                        "name": "Per",
                        "birth_year": "1962"
                    }
                ]
            }
        },
        "1": {
            "full_name": "Bengt A Bengtsson",
            "location": "Nyköping",
            "occupation": "ingenjör",
            "birth_details": {
                "date": "25/08/1916",
                "place": "Sthlm"
            },
            "education": [
                {
                    "degree": "WS",
                    "year": "1936",
                    "institution": "Katrineholm",
                    "career": [
                        {
                            "position": "anst fortif :förv",
                            "years": {
                                "start_year": 1942,
                                "end_year": 1946
                            },
                            "organization": "NULL"
                        },
                        {
                            "position": "verkst dir",
                            "years": {
                                "start_year": 1953,
                                "end_year": null
                            },
                            "organization": "Bengtsson & Gjerdman ab"
                        }
                    ],
                    "family": {
                        "spouse": "Margit Persson",
                        "marriage_year": "1944",
                        "children": [
                            {
                                "name": "Ann-mari",
                                "birth_year": "1949"
                            },
                            {
                                "name": "Margareta",
                                "birth_year": "1951"
                            }
                        ]
                    },
                    "hobbies": [
                        "jakt",
                        "fiske"
                    ]
                }
            ],
            "2": {
                "full_name": "Benny A L Benktson",
                "location": "Örebro",
                "occupation": "fd kontraktsprost",
                "birth_details": {
                    "date": "18/08/1892",
                    "place": "Varberg"
                },
                "education": [
                    {
                        "degree": "Teol kand",
                        "year": "1915",
                        "institution": "Upps"
                    }
                ],
                "career": [
                    {
                        "position": "kommin",
                        "years": {
                            "start_year": 1916,
                            "end_year": 1931
                        },
                        "organization": "Viby"
                    },
                    {
                        "position": "kyrkoh",
                        "years": {
                            "start_year": 1931,
                            "end_year": 1942
                        },
                        "organization": "Husby-Rekarne"
                    },
                    {
                        "position": "prost",
                        "years": {
                            "start_year": 1942,
                            "end_year": 1960
                        },
                        "organization": "Örebro Nikolai"
                    }
                ],
                "family": {
                    "spouse": "Greta Forssman",
                    "marriage_year": "1917",
                    "children": [
                        {
                            "name": "Benkt-Erik",
                            "birth_year": "1918"
                        },
                        {
                            "name": "Hans",
                            "birth_year": "1922"
                        },
                        {
                            "name": "Sten",
                            "birth_year": "1924"
                        }
                    ]
                },
                "honorary_titles": [
                    {
                        "title": "LNO",
                        "institution": "NULL",
                        "year": "NULL"
                    }
                ]
            },
            "3": {
                "full_name": "T Bertil Bengtsson",
                "location": "Uppsala",
                "occupation": "jur dr, preceptor",
                "birth_details": {
                    "date": "13/12/1926",
                    "place": "Gbg"
                },
                "education": [
                    {
                        "degree": "Stud:ex",
                        "year": "1944",
                        "institution": "NULL"
                    },
                    {
                        "degree": "fil kand",
                        "year": "1946",
                        "institution": "Upps"
                    },
                    {
                        "degree": "jur kand",
                        "year": "1950",
                        "institution": "NULL"
                    },
                    {
                        "degree": "jur lic",
                        "year": "1959",
                        "institution": "NULL"
                    },
                    {
                        "degree": "jur dr",
                        "year": "1960",
                        "institution": "NULL"
                    }
                ],
                "career": [
                    {
                        "position": "an",
                        "years": {
                            "start_year": 1950,
                            "end_year": 1951
                        },
                        "organization": "Dag Magnussons adv :byrå Gbg"
                    },
                    {
                        "position": "tingstjg",
                        "years": {
                            "start_year": 1951,
                            "end_year": 1953
                        },
                        "organization": "Aska, Dals o Bobergs doms"
                    },
                    {
                        "position": "fiskal",
                        "years": {
                            "start_year": 1953,
                            "end_year": 1956
                        },
                        "organization": "hovr f V Sv :e"
                    },
                    {
                        "position": "tf rådm",
                        "years": {
                            "start_year": 1954,
                            "end_year": 1960
                        },
                        "organization": "Alingsås m fi doms"
                    },
                    {
                        "position": "doc",
                        "years": {
                            "start_year": 1960,
                            "end_year": 1962
                        },
                        "organization": "Upps univ"
                    },
                    {
                        "position": "preceptor i civilrätt",
                        "years": {
                            "start_year": 1962,
                            "end_year": null
                        },
                        "organization": "NULL"
                    }
                ],
                "family": {
                    "spouse": "Solveig Lindgren",
                    "marriage_year": "1950",
                    "children": [
                        {
                            "name": "Jan",
                            "birth_year": "1955"
                        },
                        {
                            "name": "Klas",
                            "birth_year": "1959"
                        },
                        {
                            "name": "Bengt Olof",
                            "birth_year": "1962"
                        }
                    ]
                }
            }
        }
    }
}