{
    "original": "BOHLIN, PER S, arkitekt SAR,\nVästerås, f i Borås 29/6/08 av lärov:adj H\nO B o Frida Engman.\nStud:ex Borås 27, KTH 32, KKH 46,\nstadsarkit Arboga 34, länsarkit:ass\nHärnösand 36, stadspl:arkit Upps 38,\nstadsarkit Lidkpg 45, Västerås 47-62, eg\nar-kit:verksamh sed 63. - Medl SAR,\nRo-tary.\n\nGift 35 m textillär Ingrid Dahlberg f 12,\ndtr t kamr Ernst D o Ester Boman.\n-Barn: Per-Hans f 37, Ann-Kristin f 39,\nHenrik f 48.\n\nBOHM,   EINAR,   med   dr,   professor,\n\nUppsala, f i Linkpg 1/2/17 av las:läk\nVerner B o Inga Leffler.\nMed lic Sthlm 43, med dr 53, doc i\nneu-rokirurgi Karol inst sed 54, eo aman\nanat inst Karol inst 39, patol inst 42, eo\nunderläk kir avd S:t Görans sjh 41 o 42,\neo aman Allm BB 44, tf underläk kir\nklin Seraf:las 44, 2:e underläk neurokir\nklin 44, 3 :e underläk kir klin 45, tf bitr\nläk neurokir klin 46-49, tf underläk kir\navd Södertälje las 48 o 50, bitr läk\nneurokir klin Seraf:las 49-55, tf överläk\nneu-rotraumatol klin 53-55, bitr överläk neu^\nrokir klin Seraf:las 55-62, prof i\nneurokirurg! Upps univ o överläk neurokir\n\nklin Akad sjh sed 62. - Skr i patol, kir\no neurokir.\n\nGift 49 m Birgit Westerlund f 22, dtr t\nhandl Hjalmar W o Terese Sundén.\n-Barn: Hans f 49, Bengt f 52, Karin f 53.\n\nBOHM, C G IVAR S, direktör,\nHofors, f i Sthlm 1/3/00 av kamr Sam B o\nElsa Friedemann.\n\nKTH 24, ass KTH 25-29, spec:lär i\nallmän metallurgi 27-31, tf prof i järnets\nmetallurgi 29-31, ing Hagfors\n(Uddeholms ab) 31-36, övering Nykroppa\n37-41, övering o platsch SKF Hofors 41-47,\ndir där sed 48. - Styr:led Järnbruksförb,\nNorbergs gruf ab m fi, fullm Jernkont\nsed 61. - Utm: KVO.\nGift 28 m Stina Wallin f 02 d 63, dtr t\ndir Gustav W o Ester Arnberg. - Barn:\nBastån f 29, Ulla f 30, Elsbeth f 32,\nAnna f 36.\n\n",
    "structured": {
        "0": {
            "full_name": "PER S BOHLIN",
            "location": "Västerås",
            "occupation": "arkitekt SAR",
            "birth_details": {
                "date": "29/06/1908",
                "place": "Borås",
                "parents": "lärov:adj H O B o Frida Engman"
            },
            "education": [
                {
                    "degree": "Stud:ex",
                    "year": "1927",
                    "institution": "Borås"
                },
                {
                    "degree": "KTH",
                    "year": "1932",
                    "institution": "KTH"
                },
                {
                    "degree": "KKH",
                    "year": "1946",
                    "institution": "KKH"
                }
            ],
            "career": [
                {
                    "position": "stadsarkit",
                    "years": {
                        "start_year": 1934,
                        "end_year": 34
                    },
                    "organization": "Arboga"
                },
                {
                    "position": "länsarkit:ass",
                    "years": {
                        "start_year": 1936,
                        "end_year": 36
                    },
                    "organization": "Härnösand"
                },
                {
                    "position": "stadspl:arkit",
                    "years": {
                        "start_year": 1938,
                        "end_year": 38
                    },
                    "organization": "Upps"
                },
                {
                    "position": "stadsarkit",
                    "years": {
                        "start_year": 1945,
                        "end_year": 45
                    },
                    "organization": "Lidkpg"
                },
                {
                    "position": "stadsarkit",
                    "years": {
                        "start_year": 1947,
                        "end_year": 1962
                    },
                    "organization": "Västerås"
                }
            ],
            "family": {
                "spouse": "textillär Ingrid Dahlberg",
                "marriage_year": "1935",
                "children": [
                    {
                        "name": "Per-Hans",
                        "birth_year": "1937"
                    },
                    {
                        "name": "Ann-Kristin",
                        "birth_year": "1939"
                    },
                    {
                        "name": "Henrik",
                        "birth_year": "1948"
                    }
                ]
            }
        },
        "1": {
            "full_name": "EINAR BOHM",
            "location": "Uppsala",
            "occupation": "med dr, professor",
            "birth_details": {
                "date": "01/02/1917",
                "place": "Linkpg",
                "parents": "las:läk Verner B o Inga Leffler"
            },
            "education": [
                {
                    "degree": "Med lic",
                    "year": "1943",
                    "institution": "Sthlm"
                },
                {
                    "degree": "med dr",
                    "year": "1953",
                    "institution": "Karol inst"
                }
            ],
            "career": [
                {
                    "position": "prof i neurokirurgi",
                    "years": {
                        "start_year": 1962
                    },
                    "organization": "Upps univ"
                },
                {
                    "position": "överläk neurokir",
                    "years": {
                        "start_year": 1962
                    },
                    "organization": "Akad sjh"
                }
            ],
            "family": {
                "spouse": "Birgit Westerlund",
                "marriage_year": "1949",
                "children": [
                    {
                        "name": "Hans",
                        "birth_year": "1949"
                    },
                    {
                        "name": "Bengt",
                        "birth_year": "1952"
                    },
                    {
                        "name": "Karin",
                        "birth_year": "1953"
                    }
                ]
            }
        },
        "2": {
            "full_name": "C G IVAR S BOHM",
            "location": "Hofors",
            "occupation": "direktör",
            "birth_details": {
                "date": "01/03/1900",
                "place": "Sthlm",
                "parents": "kamr Sam B o Elsa Friedemann"
            },
            "education": [
                {
                    "degree": "KTH",
                    "year": "1924",
                    "institution": "KTH"
                }
            ],
            "career": [
                {
                    "position": "ing",
                    "years": {
                        "start_year": 1931,
                        "end_year": 1936
                    },
                    "organization": "Hagfors (Uddeholms ab)"
                },
                {
                    "position": "övering",
                    "years": {
                        "start_year": 1941,
                        "end_year": 1947
                    },
                    "organization": "Nykroppa"
                },
                {
                    "position": "övering o platsch",
                    "years": {
                        "start_year": 1941,
                        "end_year": 1947
                    },
                    "organization": "SKF Hofors"
                }
            ],
            "family": {
                "spouse": "Stina Wallin",
                "marriage_year": "1928",
                "children": [
                    {
                        "name": "Bastån",
                        "birth_year": "1929"
                    },
                    {
                        "name": "Ulla",
                        "birth_year": "1930"
                    },
                    {
                        "name": "Elsbeth",
                        "birth_year": "1932"
                    },
                    {
                        "name": "Anna",
                        "birth_year": "1936"
                    }
                ]
            },
            "honorary_titles": [
                {
                    "title": "KVO"
                }
            ]
        }
    }
}