{
    "original": "BERNER, KARL-ERIK, civilingenjör,\n\nÖrebro, f 4/7/25.\n\nCTH 50, konsult verksamh, deläg\nBygg-konsult i Örebro ab.\nBERNESJÖ, LENNART I, lektor,\nArvika, f i  Sthlm 23/10/20  av hemm:äg\nIvar Karlsson o Ester Claesson.\nStud:ex 41, fü mag Sthlm 45, fil lic 49,\nlekt komm gymn Arvika 50, hal Arvika\n54, Karlstad 58, Arvika sed 60,\nstudie-rekt kvällsgymn f vuxna Arvika sed 61.\n\n-  Ordf Bibl vänner 60, led LR distr:styr\nVärml l 54 (ordf 58-60), suppl\ndeput:-förs 55, medl Sv litt :sällsk, Tegnérsamf,\nOdd  Fellow,  FrimO.  -  Skr:  Leopolds\ndikt \"Predikaren\" som tidsdikt o\npersonligt dokument (Samlaren 53), Ur Stig\nDagermans diktning (64), art i Sv män\no kvinnor 49, 50), Tidn f Sv:es lärov.\n-Hobbies: fiske, musik, friluftsliv.\n\nGift 48 m Inga-Britt Höök, dtr t köpm\nEric H o Clara Schärström. - Barn:\nStefan f 49, Ingemar f 53.\n\nBERNHAGEN, VIKTOR,\nkommunal-borgmästare, Askersund, f i\nVänersborg 2/9/14.\n\nStud:ex 32, jur kand Lund 39, bitr jur\nlänsstyr Älvsb l 39, tingstjg Fryksdals\ndoms 41-44, aman länsarb:ndn Älvsb l\n44, komm :borgmäst Askersund sed 48.\n-Verkst dir Askersund-Skyllbergs jv ab\nsed 48 (styr:led 52), v ordf Askersunds\nsparbk 60 (styr:led 49, omb:man), led\nÖrebro l sparbksfören 58’, suppl Fören\nSv:es komm :borgmäst 54. - Sekr\nStadsfullm, drätselkamm samt fi nämnder,\nordf valnd, byggn :nd, barnav:nd, v ordf\nhyresnd, överförmynd, kronoomb\ntax:-nd. - Medl Rotary (presid 52-53).\nGift 42 m Ingrid Nilsson f 15. - Barn:\nLars f 45.\n\nBERNHARDTZ, TORE E,\ndriftsingenjör, Örebro, f i Karlskrona 19/10/14\nav maskinist Josef B o Martina\nJohansson.\n\nStat el :tekn facksk Västerås 39, ing Asea\nVästerås 39, stat vattenf :verk Umeå 41,\nHammarforsens kraft ab Sundsvall 46,\nKraft ab Gullspång-Munkfors Gullspång\n48, driftsing Kraft ab\nGullspång-Munkfors Örebro sed 58. - Medl Odd Fellow.\n\n-  Hobbies: bridge, trädgårdsskötsel.\n\nGift 43 m Brita Falk f 20, dtr t köpman\nJohn F o Märta Ehn. - Barn:\nJan-Änders f 46, Lärs-Göran f 49, Lena f 55.\n\n",
    "structured": {
        "0": {
            "full_name": "Karl-Erik Berner",
            "location": "Örebro",
            "occupation": "Civilingenjör",
            "birth_details": {
                "date": "04/07/1925",
                "place": "Örebro"
            },
            "education": [
                {
                    "degree": "Stud:ex",
                    "year": "1950",
                    "institution": "CTH"
                }
            ],
            "career": [
                {
                    "position": "Konsult verksamh, deläg Bygg-konsult i Örebro ab",
                    "years": {
                        "start_year": 1950
                    }
                }
            ],
            "family": {
                "spouse": "Inga-Britt Höök",
                "marriage_year": "1948",
                "children": [
                    {
                        "name": "Stefan",
                        "birth_year": "1949"
                    },
                    {
                        "name": "Ingemar",
                        "birth_year": "1953"
                    }
                ]
            },
            "hobbies": [
                "Fiske",
                "Musik",
                "Friluftsliv"
            ]
        },
        "1": {
            "full_name": "Lennart I Bernesjö",
            "location": "Arvika",
            "occupation": "Lektor",
            "birth_details": {
                "date": "23/10/1920",
                "place": "Sthlm",
                "parents": "Ivar Karlsson o Ester Claesson"
            },
            "education": [
                {
                    "degree": "Stud:ex",
                    "year": "1941",
                    "institution": "NULL"
                },
                {
                    "degree": "Fil. mag",
                    "year": "1945",
                    "institution": "Sthlm"
                },
                {
                    "degree": "Fil. lic",
                    "year": "1949",
                    "institution": "NULL"
                }
            ],
            "career": [
                {
                    "position": "Lekt komm gymn",
                    "years": {
                        "start_year": 1950
                    },
                    "organization": "Arvika"
                },
                {
                    "position": "Hal",
                    "years": {
                        "start_year": 1954
                    },
                    "organization": "Arvika"
                },
                {
                    "position": "Studie-rekt kvällsgymn f vuxna",
                    "years": {
                        "start_year": 1961
                    },
                    "organization": "Arvika"
                }
            ],
            "family": {
                "spouse": "Inga-Britt Höök",
                "marriage_year": "1948",
                "children": [
                    {
                        "name": "Stefan",
                        "birth_year": "1949"
                    },
                    {
                        "name": "Ingemar",
                        "birth_year": "1953"
                    }
                ]
            },
            "publications": [
                "Leopolds dikt 'Predikaren' som tidsdikt o personligt dokument (Samlaren 53)",
                "Ur Stig Dagermans diktning (64)",
                "Art i Sv män o kvinnor 49, 50)",
                "Tidn f Sv:es lärov."
            ],
            "community_involvement": [
                {
                    "role": "Ordf Bibl vänner",
                    "organization": "NULL",
                    "years": "60"
                },
                {
                    "role": "Led LR distr:styr",
                    "organization": "Värml l",
                    "years": "54-60"
                }
            ],
            "board_memberships": [
                {
                    "position": "Suppl deput:-förs",
                    "organization": "NULL",
                    "years": "55"
                }
            ],
            "honorary_titles": [
                {
                    "title": "Skr",
                    "institution": "Leopolds dikt",
                    "year": "53"
                }
            ],
            "hobbies": [
                "Fiske",
                "Musik",
                "Friluftsliv"
            ]
        },
        "2": {
            "full_name": "Viktor Bernhagen",
            "location": "Askersund",
            "occupation": "Kommunalborgmästare",
            "birth_details": {
                "date": "02/09/1914",
                "place": "Vänersborg"
            },
            "education": [
                {
                    "degree": "Stud:ex",
                    "year": "1932",
                    "institution": "NULL"
                },
                {
                    "degree": "Jur kand",
                    "year": "1939",
                    "institution": "Lund"
                }
            ],
            "career": [
                {
                    "position": "Bitr jur länsstyr",
                    "years": {
                        "start_year": 1939,
                        "end_year": 1939
                    },
                    "organization": "Älvsb l"
                },
                {
                    "position": "Tingstjg",
                    "years": {
                        "start_year": 1941,
                        "end_year": 1944
                    },
                    "organization": "Fryksdals doms"
                },
                {
                    "position": "Aman länsarb:ndn",
                    "years": {
                        "start_year": 1944,
                        "end_year": 1948
                    },
                    "organization": "Älvsb l"
                },
                {
                    "position": "Komm:borgmäst",
                    "years": {
                        "start_year": 1948
                    },
                    "organization": "Askersund"
                }
            ],
            "family": {
                "spouse": "Ingrid Nilsson",
                "marriage_year": "1942",
                "children": [
                    {
                        "name": "Lars",
                        "birth_year": "1945"
                    }
                ]
            },
            "honorary_titles": [
                {
                    "title": "Suppl Fören Sv:es komm:borgmäst",
                    "institution": "NULL",
                    "year": "54"
                }
            ]
        },
        "3": {
            "full_name": "Tore E Bernhardtz",
            "location": "Örebro",
            "occupation": "Driftsingenjör",
            "birth_details": {
                "date": "19/10/1914",
                "place": "Karlskrona",
                "parents": "Maskinist Josef B o Martina Johansson"
            },
            "education": [
                {
                    "degree": "Stat el:tekn facksk",
                    "year": "1939",
                    "institution": "Västerås"
                }
            ],
            "career": [
                {
                    "position": "Ing Asea",
                    "years": {
                        "start_year": 1939,
                        "end_year": 1939
                    },
                    "organization": "Västerås"
                },
                {
                    "position": "Stat vattenf:verk",
                    "years": {
                        "start_year": 1941,
                        "end_year": 1946
                    },
                    "organization": "Umeå"
                },
                {
                    "position": "Driftsing Kraft ab Gullspång-Munkfors",
                    "years": {
                        "start_year": 1948
                    },
                    "organization": "Örebro"
                }
            ],
            "family": {
                "spouse": "Brita Falk",
                "marriage_year": "1943",
                "children": [
                    {
                        "name": "Jan-Änders",
                        "birth_year": "1946"
                    },
                    {
                        "name": "Lärs-Göran",
                        "birth_year": "1949"
                    },
                    {
                        "name": "Lena",
                        "birth_year": "1955"
                    }
                ]
            },
            "hobbies": [
                "Bridge",
                "Trädgårdsskötsel"
            ]
        }
    }
}