{
    "original": "BACKLUND, L RIKARD,\ncivilingenjör, Falun, f i Älvdalen, Kopparb l,\n\n27/1/31 av skogsarb Otto B o Svea\nOlsson.\n\nHTL Norrkpg 53, KTH 58, ing vattenf\n:-styr 59-60, St Kopparb bergsl ab\nkraftverken Falun. - Hobbies: jakt, Skytte.\nGift 58 m Ingegerd Eriksson f 28, dtr t\nDofs Alfred E o Ida Tiger. - Barn:\nMikael f 53 (fosterson), Mats f 61,\nMargareta f 63.\n\nBACKMAN, AXEL B, skeppsmäklare,\n\naukt skeppsklarerare, Södertälje, f i\nSödertälje 13/11/21 av tullöveruppsyn:man\nBirger Olsson o Harriet Lundberg.\nRealex 38, anst Larsen &amp; Stoss Lübeck\n39, ab Fören sped:- o red :agenturen\nSthlm 39, befrakt h skeppsred Hugo\nSil-vén Säffle 46, Emil R Boman ab Sthlm\n47, verkst dir o inneh firma Axel B\nOlsson Shipping ab sed 49, G Berggren i\nSödertälje ab sed 56. - Led Södertälje\nstads hdls- o sjöf:nd 63. - Medl\nNep-tuniO, Odd Fellow, S:ta Ragnhilds\ngille, ConvivierO!; Södertälje ork :f Ören.\n-Hobby: musik.\n\nGift 49 m Marianne Elert f 27, dtr t\nrekt Thorild E o Elisabeth Wennerlund.\nBarn: Marie f 49, Héléne f 50, Dan\nf 55.\n\nBACKMAN, AXEL T, grosshandlare\n\nEskilstuna, f i Nykpg 2/3/91 av jvtjm P\nB o Carolina Ersson.\nStud hdlssk, tekn sk, anst Eskilstuna\njernmanuf ab 05, ab Gustav Erikssons\nmetallfabr Eskilstuna 13, ab Josef Rängi\nKarlshamn 17, kolonialv:firma Ericsson\n&amp; Co Eskilstuna sed 18, inneh o ch där\nt 59. - Kronoomb, led Östergötl o\nSödermani hdlskamm, ordf Södermani gros^\nsistfören, Södermani grossist o köpm\nförtr:råd, styr:led Bergsl-Mälarbygd köp-)\nm :f ören, Södermani baptistmiss (led AU\no kassaförv). - Medl Rotary. - Hobbies:\njakt, hundsport, tennis.\nGift m Karin Ericsson. - Barn:\nMarianne f 21, Gunnar f 23.\n\n",
    "structured": {
        "1": {
            "full_name": "BACKLUND, L RIKARD",
            "location": "Falun",
            "occupation": "civilingenjör",
            "birth_details": {
                "date": "27/01/1931",
                "place": "Älvdalen, Kopparbergs län"
            },
            "education": [
                {
                    "degree": "HTL",
                    "year": "1953",
                    "institution": "Norrköping"
                },
                {
                    "degree": "KTH",
                    "year": "1958",
                    "institution": "Kungliga Tekniska högskolan"
                }
            ],
            "career": [
                {
                    "position": "ing vattenf :-styr",
                    "years": {
                        "start_year": 1959,
                        "end_year": 1960
                    },
                    "organization": "St Kopparbergs bergslag kraftverken Falun"
                }
            ],
            "family": {
                "spouse": "Ingegerd Eriksson",
                "marriage_year": "1958",
                "children": [
                    {
                        "name": "Mikael",
                        "birth_year": "1953"
                    },
                    {
                        "name": "Mats",
                        "birth_year": "1961"
                    },
                    {
                        "name": "Margareta",
                        "birth_year": "1963"
                    }
                ]
            },
            "hobbies": [
                "jakt",
                "Skytte"
            ]
        },
        "2": {
            "full_name": "BACKMAN, AXEL B",
            "location": "Södertälje",
            "occupation": "skeppsmäklare, aukt skeppsklarerare",
            "birth_details": {
                "date": "13/11/1921",
                "place": "Södertälje"
            },
            "education": [
                {
                    "degree": "Realex",
                    "year": "1938"
                }
            ],
            "career": [
                {
                    "position": "verkst dir o inneh firma",
                    "years": {
                        "start_year": 1949
                    },
                    "organization": "Axel B Olsson Shipping ab"
                },
                {
                    "position": "verkst dir o inneh firma",
                    "years": {
                        "start_year": 1956
                    },
                    "organization": "G Berggren i Södertälje ab"
                }
            ],
            "family": {
                "spouse": "Marianne Elert",
                "marriage_year": "1949",
                "children": [
                    {
                        "name": "Marie",
                        "birth_year": "1949"
                    },
                    {
                        "name": "Héléne",
                        "birth_year": "1950"
                    },
                    {
                        "name": "Dan",
                        "birth_year": "1955"
                    }
                ]
            },
            "hobbies": [
                "musik"
            ]
        },
        "3": {
            "full_name": "BACKMAN, AXEL T",
            "location": "Eskilstuna",
            "occupation": "grosshandlare",
            "birth_details": {
                "date": "2/3/1891",
                "place": "Nyköping"
            },
            "education": [
                {
                    "institution": "Stud hdlssk"
                },
                {
                    "institution": "tekn sk"
                }
            ],
            "career": [
                {
                    "position": "kolonialv:firma",
                    "years": {
                        "start_year": 1918
                    },
                    "organization": "Ericsson & Co Eskilstuna"
                },
                {
                    "position": "inneh o ch",
                    "years": {
                        "start_year": 1959
                    }
                }
            ],
            "family": {
                "spouse": "Karin Ericsson",
                "children": [
                    {
                        "name": "Marianne",
                        "birth_year": "1921"
                    },
                    {
                        "name": "Gunnar",
                        "birth_year": "1923"
                    }
                ]
            },
            "hobbies": [
                "jakt",
                "hundsport",
                "tennis"
            ]
        }
    }
}