{
    "original": "ZETTERBERG, K MANDER,\narkitekt, Sthlm, f i Sthlm 4/10/08 av\nbyggnads ing Carl Z o Maria Johansson.\nStud:ex 27, KTH 33, arkit\nbyggn:-finnan Zetterberg ab 33, verkst dir\nsed 48, inneh sed 51. - Ans v byggmäst\n\n1   Sthlm sed 46,  styr:led  Sthlms\nbygg-mästarefören sed 55, led direkt f\nDrottninghuset   Sthlm   59.   -   Medl\nBorgerskapet Sthlm 49, led Murmästare-Ämb\nSthlm 54.\n\nGift 45  m   Maj  Christensson  f   11.\n-Barn: Georg f 49, Sonja f 51.\nZETTERBERG, N (NISSE) H,\nkonstnär, Sthlm, f i Sthlm 21/11/10 av\nkonstnär Albert Z o Ruth Lagerström.\nKKH, stud Frankr, Holland, Belg, Ital\n\n0  Engl, huvudlär Konstfacksk sed 57.\n-Porträtt,   landskap,   stilleben   o\nnaken-måln,   dekorerat   fris   i   marmormosaik\nNya folksk Säffle 49, väggmåln i\nStucco lustro Skand bkn Köping 51, mosaik\nGävleb   l   landsstatshus   55,   väggmåln\nhdlstj:mannaförb   konf :rum   56,   Stucco\nlustro Malmö stadsbibl entréhall 56, vägg\n\n1  marmor o glasmosaik Högdalens\nfolksk Sthlm 58, illustrerat bl a Frödings\no Ferlins dikter o Heidenstams\nKarolinerna. - Sep:utst bl a Sthlm, Gbg o\nOslo.\n\nGift  1)  39 m konstnär Eva Lindquist\n\nf 11, 2) 55 m Gunvor Schumacher f 12,\ndtr t kansliråd Gunnar S o Nanna\nTorp. - Barn: i l:a akt Susanna f 41,\nAnna Miaria f 48.\n\nZETTERBERG, C SVEN, direktör,\nBromma, f i Sthlm 25/8/18 av\nbyggn:ing Carl Z o Margit Sjöberg.\nStud:ex 37, DHS 40, civilekonom Sv\nmjölkprodukter ab 42-51, v verkst dlr\ndär 49-51, verkst dir ab Carlton hotel\nsed 52, inneh sed 51. - Styr :led Sv\nmjölkprodukter ab, Lexa ab, led\növerstyr Sthlms stads brandkontor m fi.\nGift 47 m Dagmar Cederborg. - Barn:\nKerstin f 47, Boel f 50, Johan f 53,\nCarl f 59.\n\n",
    "structured": {
        "0": {
            "full_name": "Zetterberg, K Mander",
            "location": "Sthlm",
            "occupation": "arkitekt",
            "birth_details": {
                "date": "04/10/1908",
                "place": "Sthlm",
                "parents": "byggnads ing Carl Z o Maria Johansson"
            },
            "education": [
                {
                    "degree": "Stud:ex",
                    "year": "1927",
                    "institution": "NULL"
                },
                {
                    "degree": "KTH",
                    "year": "1933",
                    "institution": "NULL"
                }
            ],
            "career": [
                {
                    "position": "arkit byggn",
                    "years": {
                        "start_year": 1933,
                        "end_year": 1948
                    },
                    "organization": "Zetterberg ab"
                },
                {
                    "position": "verkst dir",
                    "years": {
                        "start_year": 1948,
                        "end_year": 1951
                    },
                    "organization": "NULL"
                }
            ],
            "family": {
                "spouse": "Maj Christensson",
                "marriage_year": "1945",
                "children": [
                    {
                        "name": "Georg",
                        "birth_year": "1949"
                    },
                    {
                        "name": "Sonja",
                        "birth_year": "1951"
                    }
                ]
            }
        },
        "1": {
            "full_name": "Zetterberg, N (Nisse) H",
            "location": "Sthlm",
            "occupation": "konstnär",
            "birth_details": {
                "date": "21/11/1910",
                "place": "Sthlm",
                "parents": "konstnär Albert Z o Ruth Lagerström"
            },
            "education": [
                {
                    "degree": "KKH",
                    "year": "NULL",
                    "institution": "NULL"
                }
            ],
            "career": [
                {
                    "position": "huvudlär Konstfacksk",
                    "years": {
                        "start_year": 1957,
                        "end_year": "NULL"
                    },
                    "organization": "NULL"
                }
            ],
            "family": {
                "spouse": "1) Eva Lindquist / 2) Gunvor Schumacher",
                "marriage_year": "1) 1939 / 2) 1955",
                "children": [
                    {
                        "name": "Susanna",
                        "birth_year": "1941"
                    },
                    {
                        "name": "Anna Miaria",
                        "birth_year": "1948"
                    }
                ]
            }
        },
        "2": {
            "full_name": "Zetterberg, C Sven",
            "location": "Bromma",
            "occupation": "direktör",
            "birth_details": {
                "date": "25/8/1918",
                "place": "Sthlm",
                "parents": "byggn:ing Carl Z o Margit Sjöberg"
            },
            "education": [
                {
                    "degree": "Stud:ex",
                    "year": "1937",
                    "institution": "NULL"
                },
                {
                    "degree": "DHS",
                    "year": "1940",
                    "institution": "NULL"
                }
            ],
            "career": [
                {
                    "position": "civilekonom",
                    "years": {
                        "start_year": 1942,
                        "end_year": 1951
                    },
                    "organization": "Sv mjölkprodukter ab"
                },
                {
                    "position": "verkst dlr",
                    "years": {
                        "start_year": 1949,
                        "end_year": 1951
                    },
                    "organization": "Sv mjölkprodukter ab"
                },
                {
                    "position": "verkst dir",
                    "years": {
                        "start_year": 1952,
                        "end_year": "NULL"
                    },
                    "organization": "ab Carlton hotel"
                }
            ],
            "family": {
                "spouse": "Dagmar Cederborg",
                "marriage_year": "1947",
                "children": [
                    {
                        "name": "Kerstin",
                        "birth_year": "1947"
                    },
                    {
                        "name": "Boel",
                        "birth_year": "1950"
                    },
                    {
                        "name": "Johan",
                        "birth_year": "1953"
                    },
                    {
                        "name": "Carl",
                        "birth_year": "1959"
                    }
                ]
            }
        }
    }
}