{
    "original": "marknadslära o ekon föreningsrör,\nmedarb Nord fam :bok o Sv uppsl:bok, art\ni fack- o  dagspress.  -  Utm: KNOlkl,\nRLettSO.\nGift 1) 30 m Vivan Wallström f 02 d 57,\n\ndtr t dekorationsmål Theodor W o Ester\nArvidson, 2) 58 m Else Brolid f 19,\ndtr t dir Robert o Manna Herdahl.\n-Barn: Lars f 31, Karl Herbert f 33,\nIngrid f 35.\n\nZACCO-WALDENSTRÖM, MÄRTA\n\nS U, leg läkare, Sthlm, f i Sthlm 1/7/26\nav rev Sven Zacco o Svea Tjernström.\nStud:ex 45, med kand 48, med lic Sthlm\n53, 2:e underläk hudklin Karol sjh 56,\nl:e underläk där 57, vik l:e underläk\nRadiumhemmet sed 60.\nGift 49 m civiling Tord Waldenström f\n21. - Barn: Sven f 53, Ulrika f 57.\n\nZACHARIAS, RICHARD M, advokat,\nSthlm, f i Sthlm 21/11/19 av dir Efraim\nZ o Hanna Kopowski.\nStud:ex 37, jur kand 43, not o tf assess\nSthlms rådhusr 43-45, aman nedre\njust:-rev 44, tf rådman rådhusr Eskilstuna\n45, kronoomb skatteverket Sthlm 46-47,\nbitr jurist h adv Axel\nHemming-Sjöberg 45-48, eg adv:verksamh sed 49.\n-LSA 48. - V ordf hdlskamm\nSv:e-Isra-el sed 61, ordf tennissekt Djurgårdens\nIF sed 59. - Hobbies: sport, jakt, bridge.\nGift 1) 43-55 m Brita Simann f 22,\ndtr t köpman Carl Matulsky o Rachel\nSimann, 2) 56 m Martine Delfosse f\n34, dtr t baron Jean D o Lucy D.\n-Barn: i l:a akt Ted f 44, Tom f 48, i\n2:a akt Claude f 61.\n\nZACHAU, INGVAR A, byrådirektör,\nSthlm, f i Uddevalla 10/5/06 av disp\nArthur Z o Gertrud Bergman.\nFil kand Upps 28, jur kand 32, tjg\nutr:-förvaltn o Sthlms rådhusr 33-36,\npat:-o reg :verket 37, byrådir där sed 47.\n-Ordf Sv-franska stift sed 53, styr:led\nBohusl gille sed 47, Dante Alighieri di\nStoccolma sed 51. - Utm: RItRFO.\n-Hobbies: kultur- o konstfrämjande,\nfolklivsforskning, fil’ateli, bridge, schack.\nGift m Birgit Kocken f 14. - Barn:\nInga f 51.\n\n",
    "structured": {
        "1": {
            "full_name": "Zacco-Waldenström, Märta",
            "location": "Stockholm",
            "occupation": "Leg läkare",
            "birth_details": {
                "date": "01/07/1926",
                "place": "Stockholm"
            },
            "education": [
                {
                    "degree": "Stud:ex",
                    "year": "1945",
                    "institution": "Sthlm"
                },
                {
                    "degree": "med kand",
                    "year": "1948",
                    "institution": "Sthlm"
                },
                {
                    "degree": "med lic",
                    "year": "1953",
                    "institution": "Sthlm"
                }
            ],
            "career": [
                {
                    "position": "2:e underläk hudklin Karol sjh",
                    "years": {
                        "start_year": 1956,
                        "end_year": 1957
                    },
                    "organization": "Karolinska Sjukhuset"
                },
                {
                    "position": "l:e underläk",
                    "years": {
                        "start_year": 1957,
                        "end_year": null
                    },
                    "organization": "Karolinska Sjukhuset"
                },
                {
                    "position": "vik l:e underläk Radiumhemmet",
                    "years": {
                        "start_year": 1960,
                        "end_year": null
                    },
                    "organization": "Radiumhemmet"
                }
            ],
            "family": {
                "spouse": "Tord Waldenström",
                "marriage_year": "1949",
                "children": [
                    {
                        "name": "Sven",
                        "birth_year": "1953"
                    },
                    {
                        "name": "Ulrika",
                        "birth_year": "1957"
                    }
                ]
            }
        },
        "2": {
            "full_name": "Zacharias, Richard M",
            "location": "Stockholm",
            "occupation": "Advokat",
            "birth_details": {
                "date": "21/11/1919",
                "place": "Stockholm"
            },
            "education": [
                {
                    "degree": "Stud:ex",
                    "year": "1937",
                    "institution": null
                },
                {
                    "degree": "jur kand",
                    "year": "1943",
                    "institution": null
                }
            ],
            "career": [
                {
                    "position": "not o tf assess Sthlms rådhusr",
                    "years": {
                        "start_year": 1943,
                        "end_year": 1945
                    },
                    "organization": "Sthlms Rådhus"
                },
                {
                    "position": "aman nedre just:-rev",
                    "years": {
                        "start_year": 1944,
                        "end_year": null
                    },
                    "organization": null
                },
                {
                    "position": "tf rådman rådhusr Eskilstuna",
                    "years": {
                        "start_year": 1945,
                        "end_year": null
                    },
                    "organization": "Eskilstuna Rådhus"
                },
                {
                    "position": "kronoomb skatteverket Sthlm",
                    "years": {
                        "start_year": 1946,
                        "end_year": 1947
                    },
                    "organization": "Skatteverket"
                },
                {
                    "position": "eg adv:verksamh",
                    "years": {
                        "start_year": 1949,
                        "end_year": null
                    },
                    "organization": null
                }
            ],
            "family": {
                "spouse": "Martine Delfosse",
                "marriage_year": "1956",
                "children": [
                    {
                        "name": "Ted",
                        "birth_year": "1944"
                    },
                    {
                        "name": "Tom",
                        "birth_year": "1948"
                    },
                    {
                        "name": "Claude",
                        "birth_year": "1961"
                    }
                ]
            },
            "hobbies": [
                "sport",
                "jakt",
                "bridge"
            ]
        },
        "3": {
            "full_name": "Zachau, Ingvar A",
            "location": "Stockholm",
            "occupation": "Byrådirektör",
            "birth_details": {
                "date": "10/5/1906",
                "place": "Uddevalla"
            },
            "education": [
                {
                    "degree": "Fil kand",
                    "year": "1928",
                    "institution": "Uppsala"
                },
                {
                    "degree": "jur kand",
                    "year": "1932",
                    "institution": null
                }
            ],
            "career": [
                {
                    "position": "tjg utr:-förvaltn o Sthlms rådhusr",
                    "years": {
                        "start_year": 1933,
                        "end_year": 1936
                    },
                    "organization": "Stockholm Rådhus"
                },
                {
                    "position": "pat:-o reg :verket",
                    "years": {
                        "start_year": 1937,
                        "end_year": null
                    },
                    "organization": "Patent- och registreringsverket"
                },
                {
                    "position": "byrådir",
                    "years": {
                        "start_year": 1947,
                        "end_year": null
                    },
                    "organization": "Stockholm Rådhus"
                }
            ],
            "family": {
                "spouse": "Birgit Kocken",
                "marriage_year": null,
                "children": [
                    {
                        "name": "Inga",
                        "birth_year": "1951"
                    }
                ]
            },
            "hobbies": [
                "kultur- o konstfrämjande",
                "folklivsforskning",
                "filateli",
                "bridge",
                "schack"
            ]
        }
    }
}