{
    "original": "Palmcrantz, Johan Magnus, gods- o.\nfastighetsägare, Sthlm, f. 27/5/68 i\nSkövde av Johan Mauritz P. o. Rakel\nAugusta Moberg. Gmg. lantmannask.\n86-87. Förvaltare v. ön o. Alebäcken i\nSkarab. 1. 87-00, ägde Alebäcken 00-08,\nSeglinge i Almunge skn, Sthlms L,\n09-11, Sofielund i Västerhaninge socken,\nSthlms L, 14 samt Högby i Nysätra skn.\n15-18, fastigh :äg. i Sthlm sed. 20. Medl.\nav prernieringsnd f. nötboskap,\nhus-halm :sällsk. i Skaraborgs o. Sthlms L\nSkänkt kyrkklocka t. Sundtorps kapell\nm. fi. donationer. Hobbies: Bil- o,\nmotorsport samt ridsport.\nPalme, Erik Rutger Christian,\nadvokat, Sthlm, f. 21/7/10 i Sthlm av fiU\nlic. O. P. o. Ola Tenow. G. 40 m. Lena\nCarlsson. Barn: Agneta f. 41, Sven f.\n43. Studrex. 29, jur. kand. 34.\nTingstjg, i Nyköpings doms. 34-38, anst. å\nKnut Littorins advokatbyrå i Sthlm\n38-40, v. Statens ammunitionsnd 41-43,,\nv. Kgl. ’Krigsmaterielverket 43,\nförste-byråsekr. 44. Led. av Sv :es Adv :samf.\n40. Ordf. i stud :fören. Heimdal 33-34,\nordf. i Södermani. Ungsv. distr. 35-38\no. h. Ungsvenskarna i Sthlm 41-42,.\nkyrkofullm. sed. 42.\nPalme, Nils, kapten, direktör, Sthlm,\nf. 26/2/95 i Djursholm av dir. Sven P.\no. frih :an Hanna v. Born. G. 20 m.\nMargareta Lindquist. Stud :ex. 12, und\n:-löjtn. v. Göta art:reg. 16, i res. 20, AIHS\n18-19, kapten i Svea art:reg:s res. 30.\nDelt. i Finl. frihetskrig ss. kapten o.\nmajor 18, praktik v. sågv. o. cell:fabr.\n20, i Paris 21, dir:ass. o. sekr. i\nSågv:-förb. 21-23, ass. v. försäljn :avd. i\nKramfors A-B 23-29, försäljn :ch. v.\nLjusne-Woxna A-B ,29-37, sekr. i Sv.\nWallboard-fabr :s för., omb :m. i\nWallboardgrup-pen o. Scanboard 37-39, verkst, dir. i\nScankraft fr. 39, i Scanpapp fr. 40.\nKFinlLOlkl, KFinlVRO, FFrK2, 3 o. 4\nkl m sv.\nPalmer, Ivar,, docent, överläkare,\nStocksund, f. 18/3/97 i Lena, Älvsb. 1.,\nav kyrkoh. John P. o. Karin Kling. G.\n23 m. Dagny Bohlin. Med. kand. Upps.\n49, med. lic. Karol. inst. 23, med. dr\n38, doc. i kir. v. Karol. inst. 39, tjg. v.\nlas. i Eksjö, Gällivare, Östersund,\nBoden, Karlsborg, v. Seraf:Ias. o.\nSab-batsb. sjukh., bitr. överläk. v. Karol.\nsjukh. 40, överläk. v. Sabbatsb. sjukh.\nkir. avd. II fr. 42. Stud :res. t. Österr.,\nEngl., U. S. A., t. krigsskådepl. i n :a\nFinl. vintern 40 o. somm. 41, Frankr,\no. Belg. 40. Skr.: ett 30-tal kir. arb.,\ndet största om knäledens\nligamentska-dor, volymen om skador genom\nolycksfall i serien Vår tids medicin samt ett\n10-tal mil :med. o. krigskir. arb. RVO,\nFFrKSkl.\n",
    "structured": {
        "1": {
            "full_name": "Palmcrantz, Johan Magnus",
            "location": "Stockholm",
            "occupation": "Gods- och fastighetsägare",
            "birth_details": {
                "date": "27/05/1868",
                "place": "Skövde"
            },
            "education": [
                {
                    "degree": "Lantmannask. ",
                    "year": "1886-1887",
                    "institution": "unspecified"
                }
            ],
            "career": [
                {
                    "position": "Förvaltare",
                    "years": {
                        "start_year": 1887,
                        "end_year": 1900
                    },
                    "organization": "ön o. Alebäcken i Skarab. 1."
                },
                {
                    "position": "Ägare",
                    "years": {
                        "start_year": 1900,
                        "end_year": 1908
                    },
                    "organization": "Alebäcken"
                },
                {
                    "position": "Ägare",
                    "years": {
                        "start_year": 1909,
                        "end_year": 1911
                    },
                    "organization": "Seglinge i Almunge skn, Sthlms L"
                },
                {
                    "position": "Ägare",
                    "years": {
                        "start_year": 1914,
                        "end_year": 1915
                    },
                    "organization": "Sofielund i Västerhaninge socken, Sthlms L"
                },
                {
                    "position": "Ägare",
                    "years": {
                        "start_year": 1915,
                        "end_year": 1918
                    },
                    "organization": "Högby i Nysätra skn."
                },
                {
                    "position": "Fastighetsäg. i Sthlm",
                    "years": {
                        "start_year": 1920,
                        "end_year": "present"
                    },
                    "organization": "unspecified"
                }
            ],
            "family": {
                "spouse": "unspecified",
                "marriage_year": "unspecified",
                "children": []
            },
            "publications": [],
            "community_involvement": [],
            "board_memberships": [],
            "honorary_titles": [],
            "hobbies": [
                "Bil- och motorsport",
                "Ridsport"
            ]
        },
        "2": {
            "full_name": "Palme, Erik Rutger Christian",
            "location": "Stockholm",
            "occupation": "Advokat",
            "birth_details": {
                "date": "21/07/1910",
                "place": "Stockholm"
            },
            "education": [],
            "career": [
                {
                    "position": "Tingstjg",
                    "years": {
                        "start_year": 1934,
                        "end_year": 1938
                    },
                    "organization": "Nyköpings doms."
                },
                {
                    "position": "Anst",
                    "years": {
                        "start_year": 1938,
                        "end_year": 1940
                    },
                    "organization": "Knut Littorins advokatbyrå i Sthlm"
                },
                {
                    "position": "V. Statens ammunitionsnd",
                    "years": {
                        "start_year": 1941,
                        "end_year": 1943
                    },
                    "organization": "unspecified"
                },
                {
                    "position": "V. Kgl. ’Krigsmaterielverket",
                    "years": {
                        "start_year": 1943,
                        "end_year": "unspecified"
                    },
                    "organization": "unspecified"
                }
            ],
            "family": {
                "spouse": "Lena Carlsson",
                "marriage_year": "1940",
                "children": [
                    {
                        "name": "Agneta",
                        "birth_year": "1941"
                    },
                    {
                        "name": "Sven",
                        "birth_year": "1943"
                    }
                ]
            },
            "publications": [],
            "community_involvement": [
                {
                    "role": "Ordf",
                    "organization": "Södermani",
                    "years": "35-38"
                },
                {
                    "role": "Ordf",
                    "organization": "Sthlm",
                    "years": "41-42"
                },
                {
                    "role": "Kyrkofullm.",
                    "organization": "unspecified",
                    "years": "42"
                }
            ],
            "board_memberships": [],
            "honorary_titles": [],
            "hobbies": []
        },
        "3": {
            "full_name": "Palme, Nils",
            "location": "Stockholm",
            "occupation": "Kapten, Direktör",
            "birth_details": {
                "date": "26/02/1895",
                "place": "Djursholm"
            },
            "education": [
                {
                    "degree": "Studex.",
                    "year": "1912",
                    "institution": "unspecified"
                },
                {
                    "degree": "Und: löjtn.",
                    "year": "1916",
                    "institution": "Göta art:reg."
                }
            ],
            "career": [
                {
                    "position": "Kapten",
                    "years": {
                        "start_year": 1930,
                        "end_year": "unspecified"
                    },
                    "organization": "Svea art:reg:s res."
                }
            ],
            "family": {
                "spouse": "Margareta Lindquist",
                "marriage_year": "1920",
                "children": []
            },
            "publications": [],
            "community_involvement": [],
            "board_memberships": [],
            "honorary_titles": [
                {
                    "title": "KFinlLOlkl",
                    "institution": "unspecified",
                    "year": "unspecified"
                },
                {
                    "title": "KFinlVRO",
                    "institution": "unspecified",
                    "year": "unspecified"
                },
                {
                    "title": "FFrK2, 3 o. 4",
                    "institution": "unspecified",
                    "year": "unspecified"
                }
            ],
            "hobbies": []
        },
        "4": {
            "full_name": "Palmer, Ivar",
            "location": "Stocksund",
            "occupation": "Docent, Överläkare",
            "birth_details": {
                "date": "18/03/1897",
                "place": "Lena, Älvsb. 1."
            },
            "education": [
                {
                    "degree": "Med. kand.",
                    "year": "unspecified",
                    "institution": "Upps."
                },
                {
                    "degree": "Med. lic.",
                    "year": "unspecified",
                    "institution": "Karol. inst."
                }
            ],
            "career": [
                {
                    "position": "Bitr. överläk.",
                    "years": {
                        "start_year": 1940,
                        "end_year": 1942
                    },
                    "organization": "Karol. sjukh."
                },
                {
                    "position": "Överläk.",
                    "years": {
                        "start_year": "1942",
                        "end_year": "unspecified"
                    },
                    "organization": "Sabbatsb. sjukh. kir. avd. II"
                }
            ],
            "family": {
                "spouse": "Dagny Bohlin",
                "marriage_year": "1923",
                "children": []
            },
            "publications": [],
            "community_involvement": [],
            "board_memberships": [],
            "honorary_titles": [
                {
                    "title": "RVO",
                    "institution": "unspecified",
                    "year": "unspecified"
                },
                {
                    "title": "FFrKSkl",
                    "institution": "unspecified",
                    "year": "unspecified"
                }
            ],
            "hobbies": []
        }
    }
}