{
    "original": "VALBERG, LARS A, tandläkare,\nUppsala, f i Upps 25/3/19 av dr Martin V o\nElsa Sjölander.\n\nStud:ex Upps 38, tandläk:ex 44, anst\nfolktandv Västerås 45, priv prakt Upps\nsed 46. - Medl SHT, Lions Club.\nGift 58 m Ulla Nordström f 34, dtr t\nkonsul Erik N o Ingrid Bergman.\n-Barn: Claes f 59, Lena f 61.\n\nVALBERG, G MARTIN, fd\nstadsdistriktsläkare, Uppsala, f i Västerås 7/9/89\nav lokf or A G V o Emilie Larsson.\nStud:ex 08, med kand Upps 12, med lic\n16, tjg Akad sjh Upps 15-20, tf l:e\nstads-läk Upps 24, stadsdistr:läk där 25-56,\nprakt läk Upps sed 20. - Tjänsteläk\nteleverket 20-56, Upps ålderdoms- o\nsjukhem 25-56. - Utm: RVO, Upps stads\nftJM.\n\nGift 16 m Elsa Sjölander f 92, dtr t\nkantor Anders S o Mathilda\nSamuelsson. - Barn: Ingegerd f 17, Lars f 19,\nJan f 21, Kerstin o Lisbet ff 25.\n\nWALDE, NILS, civilingenjör,\nNyköping, f i Hjortsberga, Kronob l, 8/3/29\nav trädg :mast Gunnar W o Ruth\nJohansson.\n\nStud:ex Karlskrona 49, KTH 59, lab :ing\nab Astra Södertälje 58, forskn:ing ab\nAtomenergi Studsvik sed 61. - Res:off:ex\n\n50.   - Hobbies: fiske,  sport,\nträdgårdsskötsel.\n\nGift 55 m Catharina Pontén f 33, dtr t\nlandsfogde Åke P o Anna Lisa\nLundberg. - Barn: Mats f 58, Sten f 63.\n\nWALDEGREN, GEORG V, direktör,\n\nFilipstad, f i Tutaryd, Kronob l, 9/11/04\nav folkskollär o kant J W o Hulda\nWal-degren.\n\nStud:ex 23, DHS 26, inköpsch Strömsnäs\nbruks ab 27, kont :ch där 36, exp:- o\ninköpsdir ab Wasa spisbrödsfabr\nFilipstad 42, v verkst dir o sekt :ch f pers:- o\ninköpsavd där sed 64. - Ordf Filipstads\nandelstvättfören, v ordf Filipstads\nsparbk. - Medl Rotary. - Hobbies: jakt,\nfiske, foto.\n\nGift 42 m Gunborg Andersson f 16, dtr\nt förvalt Sigfrid A o Agda Persson.\n-Barn: Jan f 44, Sten f 46, Ola f 51.\n\nWALDEKRANZ, RUNE, rektor,\nSödertälje, f i Turinge, Sthlms l, 14/9/11\nav dir Einar W o Olga Emthén.\nStud:ex Södertälje 31, fil kand Upps 35,\nfil mag 37, film- o litt:rec SvD 39,\nprod:ch Sandrew-film 42, rekt Sv\nfilminst filmskola sed 64. - Preses Sv\nfilm-samf 57-59, led dess presid sed 57, ordf\nFilmhist saml sed 62, medl juryn v\nFilmfestivalen Mexico City 58, föreläsn\ni filmens hist o formprobl StU 62 o 6.3.\n-Skr: Filmen växer upp (41), Modern film\n(51), Italiensk film (53), Amerikansk\nfilm (54), Film fr hela världen (55),\nLevande bilder (55), Knaurs Buch von\nFilm (tills m V Arpe 56), Filmen — det\nnya språket (tills m B Lauritzen 58)\nmm.- Sign: Roderick. - Utm: Fib :s\nfilmpr 56, Sv filmsamf plak 61, Anders\nSandrews Hplak 61. - Hobby: historia.\nGift 1) 43-47 m Ebon Ringblom f 24,\n2) 47 m Brita Klein f 20, dtr t adv\nWalter K o Elsa Grönberg. - Barn:\nCecilia f 48, Jan f 52.\n\nWALDEMARSSON, ERIK,\nlänsassessor, Nyköping, f i Kristianstad 20/2/07\nav musikstyckjunk Alfred W o Emilia\nAndersson.\n\nStud:ex 26, jur kand Lund 32, tingstjg\nAlvesta 33-35, länsnot Växjö 36, Nykpg\n\n51,  länsassess o sekt :ch planer :sekt sed\n53. - V ordf Riksbkns avd :kont Nykpg\nsed 61, ordf Södermani l\ntrafiksäkerh:-komm 53-62,  sekr Södermani  l\nnaturvårdsråd, dir f S:ta Annas sjh.\n\nGift 37 m Inez Ryd f 14, dtr t dir Oscar\nR o Hilma Johansson. - Barn: Ulla f 45,\nHåkan f 50.\n\nWALDENSTRÖM, CARL A H F D,\narkitekt SAR, stadsarkitekt, Säffle, f i\n\nKöpenh 23/6/20 av bankdir Erik W o\nMette Skow-Pedersen.\nStud:ex Sthlm 39, KTH 47, anst\nbyggn:-styr 47-49, stadsarkit Säf f le sed 51  (tf\n49), egen arkit :verksamh där sed 50.\nGift 44 m Märta Wiklund f 24, dtr t\nsjö-kapt Hugo W o Maria Sikström. - Barn:\nEva f 45, Hans f 47, Lars f 51.\nWALFRIDSSON, ERNST G,\nbankdirektör, Eskilstuna, f i L Isie sn, Malmöh\nl, 29/12/96 av lantbr Walfrid Persson o\nJohanna Nilsson.\n\nHbgs hdlsgymn 18, anst Sv hdlsbkn 18,\ndir avd :kont Eskilstuna 45-61. - Led Sv\nbkmförb centralstyr, AU m m. - Medl\nOdd Fellow, B 7. - Skr: kåserier, art,\nessäer o noveller i landsortspressen.\n-Hobbies: sång, litteratur, resor,\nträdgårdsskötsel.\n\nGift 1) 24 m Ebba Olsson f 98, dtr t\nfabr Anders O, 2) 31 m Irma Bergström\nf 06, dtr t stat:insp V B o h h. - Barn: i\nl:a akt Erik f 25, Stig o Gunnar ff 26,\ni 2:a akt Gunilla f 33, Rolf f 40.\nVALIN se WALLIN\n",
    "structured": {
        "0": {
            "full_name": "VALBERG, LARS A",
            "location": "Uppsala",
            "occupation": "tandläkare",
            "birth_details": {
                "date": "25/03/1919",
                "place": "Uppsala",
                "parents": "dr Martin V o Elsa Sjölander"
            },
            "education": [
                {
                    "degree": "Stud:ex",
                    "year": "1938",
                    "institution": "Uppsala"
                },
                {
                    "degree": "tandläk:ex",
                    "year": "1944",
                    "institution": "NULL"
                }
            ],
            "career": [
                {
                    "position": "anst folktandv Västerås",
                    "years": {
                        "start_year": 1945,
                        "end_year": 1945
                    },
                    "organization": "NULL"
                },
                {
                    "position": "priv prakt Upps",
                    "years": {
                        "start_year": 1946,
                        "end_year": null
                    },
                    "organization": "NULL"
                }
            ],
            "family": {
                "spouse": "Ulla Nordström",
                "marriage_year": "1958",
                "children": [
                    {
                        "name": "Claes",
                        "birth_year": "1959"
                    },
                    {
                        "name": "Lena",
                        "birth_year": "1961"
                    }
                ]
            }
        },
        "1": {
            "full_name": "VALBERG, G MARTIN",
            "location": "Uppsala",
            "occupation": "fd stadsdistriktsläkare",
            "birth_details": {
                "date": "07/09/1889",
                "place": "Västerås",
                "parents": "lokf or A G V o Emilie Larsson"
            },
            "education": [
                {
                    "degree": "Stud:ex",
                    "year": "1908",
                    "institution": "NULL"
                },
                {
                    "degree": "med kand",
                    "year": "1912",
                    "institution": "Uppsala"
                },
                {
                    "degree": "med lic",
                    "year": "1916",
                    "institution": "NULL"
                }
            ],
            "career": [
                {
                    "position": "tjg Akad sjh Upps",
                    "years": {
                        "start_year": 1915,
                        "end_year": 1920
                    },
                    "organization": "NULL"
                },
                {
                    "position": "tf l:e stads-läk Upps",
                    "years": {
                        "start_year": 1924,
                        "end_year": 1924
                    },
                    "organization": "Uppsala"
                },
                {
                    "position": "stadsdistr:läk där",
                    "years": {
                        "start_year": 1925,
                        "end_year": 1956
                    },
                    "organization": "Uppsala"
                },
                {
                    "position": "prakt läk Upps",
                    "years": {
                        "start_year": 1920,
                        "end_year": null
                    },
                    "organization": "Uppsala"
                },
                {
                    "position": "Tjänsteläk televerket",
                    "years": {
                        "start_year": 1920,
                        "end_year": 1956
                    },
                    "organization": "televerket"
                }
            ],
            "family": {
                "spouse": "Elsa Sjölander",
                "marriage_year": "1916",
                "children": [
                    {
                        "name": "Ingegerd",
                        "birth_year": "1917"
                    },
                    {
                        "name": "Lars",
                        "birth_year": "1919"
                    },
                    {
                        "name": "Jan",
                        "birth_year": "1921"
                    },
                    {
                        "name": "Kerstin",
                        "birth_year": "1925"
                    },
                    {
                        "name": "Lisbet",
                        "birth_year": "1925"
                    }
                ]
            }
        },
        "2": {
            "full_name": "WALDE, NILS",
            "location": "Nyköping",
            "occupation": "civilingenjör",
            "birth_details": {
                "date": "08/03/1929",
                "place": "Hjortsberga, Kronob l",
                "parents": "trädg :mast Gunnar W o Ruth Johansson"
            },
            "education": [
                {
                    "degree": "Stud:ex",
                    "year": "1949",
                    "institution": "Karlskrona"
                },
                {
                    "degree": "KTH",
                    "year": "1959",
                    "institution": "NULL"
                }
            ],
            "career": [
                {
                    "position": "lab :ing ab Astra Södertälje",
                    "years": {
                        "start_year": 1958,
                        "end_year": null
                    },
                    "organization": "ab Astra Södertälje"
                },
                {
                    "position": "forskn:ing ab Atomenergi Studsvik",
                    "years": {
                        "start_year": 1961,
                        "end_year": null
                    },
                    "organization": "ab Atomenergi Studsvik"
                }
            ],
            "family": {
                "spouse": "Catharina Pontén",
                "marriage_year": "1955",
                "children": [
                    {
                        "name": "Mats",
                        "birth_year": "1958"
                    },
                    {
                        "name": "Sten",
                        "birth_year": "1963"
                    }
                ]
            }
        },
        "3": {
            "full_name": "WALDEGREN, GEORG V",
            "location": "Filipstad",
            "occupation": "direktör",
            "birth_details": {
                "date": "09/11/1904",
                "place": "Tutaryd, Kronob l",
                "parents": "folkskollär o kant J W o Hulda Wal-degren"
            },
            "education": [
                {
                    "degree": "Stud:ex",
                    "year": "1923",
                    "institution": "NULL"
                },
                {
                    "degree": "DHS",
                    "year": "1926",
                    "institution": "NULL"
                }
            ],
            "career": [
                {
                    "position": "inköpsch Strömsnäs bruks ab",
                    "years": {
                        "start_year": 1927,
                        "end_year": 1927
                    },
                    "organization": "Strömsnäs bruks ab"
                },
                {
                    "position": "kont :ch där",
                    "years": {
                        "start_year": 1936,
                        "end_year": 1936
                    },
                    "organization": "Strömsnäs bruks ab"
                },
                {
                    "position": "exp:- o inköpsdir ab Wasa spisbrödsfabr",
                    "years": {
                        "start_year": 1942,
                        "end_year": 1942
                    },
                    "organization": "ab Wasa spisbrödsfabr"
                },
                {
                    "position": "v verkst dir o sekt :ch f pers:- o inköpsavd där",
                    "years": {
                        "start_year": 1964,
                        "end_year": null
                    },
                    "organization": "ab Wasa spisbrödsfabr"
                }
            ],
            "family": {
                "spouse": "Gunborg Andersson",
                "marriage_year": "1942",
                "children": [
                    {
                        "name": "Jan",
                        "birth_year": "1944"
                    },
                    {
                        "name": "Sten",
                        "birth_year": "1946"
                    },
                    {
                        "name": "Ola",
                        "birth_year": "1951"
                    }
                ]
            }
        },
        "4": {
            "full_name": "WALDEKRANZ, RUNE",
            "location": "Södertälje",
            "occupation": "rektor",
            "birth_details": {
                "date": "14/09/1911",
                "place": "Turinge, Sthlms l",
                "parents": "dir Einar W o Olga Emthén"
            },
            "education": [
                {
                    "degree": "Stud:ex",
                    "year": "1931",
                    "institution": "Södertälje"
                },
                {
                    "degree": "fil kand",
                    "year": "1935",
                    "institution": "Uppsala"
                },
                {
                    "degree": "fil mag",
                    "year": "1937",
                    "institution": "NULL"
                }
            ],
            "career": [
                {
                    "position": "prod:ch Sandrew-film",
                    "years": {
                        "start_year": 1942,
                        "end_year": null
                    },
                    "organization": "Sandrew-film"
                }
            ],
            "family": {
                "spouse": null,
                "marriage_year": "NULL",
                "children": [
                    {
                        "name": "Cecilia",
                        "birth_year": "1948"
                    },
                    {
                        "name": "Jan",
                        "birth_year": "1952"
                    }
                ]
            }
        },
        "5": {
            "full_name": "WALDEMARSSON, ERIK",
            "location": "Nyköping",
            "occupation": "länsassessor",
            "birth_details": {
                "date": "20/02/1907",
                "place": "Kristianstad",
                "parents": "musikstyckjunk Alfred W o Emilia Andersson"
            },
            "education": [
                {
                    "degree": "Stud:ex",
                    "year": "1926",
                    "institution": "NULL"
                },
                {
                    "degree": "jur kand",
                    "year": "1932",
                    "institution": "Lund"
                }
            ],
            "career": [
                {
                    "position": "tingstjg Alvesta",
                    "years": {
                        "start_year": 1933,
                        "end_year": 1935
                    },
                    "organization": "Alvesta"
                },
                {
                    "position": "länsnot Växjö",
                    "years": {
                        "start_year": 1936,
                        "end_year": 1951
                    },
                    "organization": "Växjö"
                },
                {
                    "position": "länsassess o sekt :ch planer :sekt",
                    "years": {
                        "start_year": 1953,
                        "end_year": null
                    },
                    "organization": "NULL"
                }
            ],
            "family": {
                "spouse": "Inez Ryd",
                "marriage_year": "1937",
                "children": [
                    {
                        "name": "Ulla",
                        "birth_year": "1945"
                    },
                    {
                        "name": "Håkan",
                        "birth_year": "1950"
                    }
                ]
            }
        },
        "6": {
            "full_name": "WALDENSTRÖM, CARL A H F D",
            "location": "Säffle",
            "occupation": "arkitekt SAR, stadsarkitekt",
            "birth_details": {
                "date": "23/06/1920",
                "place": "Köpenh",
                "parents": "bankdir Erik W o Mette Skow-Pedersen"
            },
            "education": [
                {
                    "degree": "Stud:ex",
                    "year": "1939",
                    "institution": "Sthlm"
                },
                {
                    "degree": "KTH",
                    "year": "1947",
                    "institution": "NULL"
                }
            ],
            "career": [
                {
                    "position": "anst byggn:-styr",
                    "years": {
                        "start_year": 1947,
                        "end_year": 1949
                    },
                    "organization": "NULL"
                },
                {
                    "position": "stadsarkit Säf f le",
                    "years": {
                        "start_year": 1951,
                        "end_year": null
                    },
                    "organization": "NULL"
                }
            ],
            "family": {
                "spouse": "Märta Wiklund",
                "marriage_year": "1944",
                "children": [
                    {
                        "name": "Eva",
                        "birth_year": "1945"
                    },
                    {
                        "name": "Hans",
                        "birth_year": "1947"
                    },
                    {
                        "name": "Lars",
                        "birth_year": "1951"
                    }
                ]
            }
        },
        "7": {
            "full_name": "WALFRIDSSON, ERNST G",
            "location": "Eskilstuna",
            "occupation": "bankdirektör",
            "birth_details": {
                "date": "29/12/1896",
                "place": "L Isie sn, Malmöh l",
                "parents": "lantbr Walfrid Persson o Johanna Nilsson"
            },
            "education": [
                {
                    "degree": "Hbgs hdlsgymn",
                    "year": "1918",
                    "institution": "Hbgs"
                },
                {
                    "degree": "NULL",
                    "year": "NULL",
                    "institution": "NULL"
                }
            ],
            "career": [
                {
                    "position": "anst Sv hdlsbkn",
                    "years": {
                        "start_year": 1918,
                        "end_year": null
                    },
                    "organization": "Sv hdlsbkn"
                }
            ],
            "family": {
                "spouse": "Ebba Olsson",
                "marriage_year": "1924",
                "children": [
                    {
                        "name": "Erik",
                        "birth_year": "1925"
                    },
                    {
                        "name": "Stig",
                        "birth_year": "1926"
                    },
                    {
                        "name": "Gunnar",
                        "birth_year": "1926"
                    },
                    {
                        "name": "Gunilla",
                        "birth_year": "1933"
                    },
                    {
                        "name": "Rolf",
                        "birth_year": "1940"
                    }
                ]
            }
        }
    }
}