{
    "original": "VILKE, A JOHAN S,\nkriminalkommissarie, ryttmästare, Västerås, f i Lund\n5/1/04 av lärov:adj August V o Elisa\nEllingsen.\n\nStud:ex 22, stud Lunds univ 23-24,\nres:off:ex 24, GCI 26, kansliex 32, hdlssk\n34, poliskommiss:kurs 50, cfch:ex 51,\nanst Sthlms polis 27, kriminalkommiss\no ch kriminalavd Västerås sed 51.\n-Krig- o marinpolisch Gotland 44-45,\nkontr :off (tf major) FN:s ö vervakn\n:kommiss Korea 54-55, lär flottiljpolissk FV:s\ncentr skola Västerås 52-61. - Tax:ordf\no led valnd Sthlm 47-51, led särsk tax:nd\nVästerås 52-61, fastigh :tax:nd 56,\nval-ndsordf Västerås sed 52. - Medl S:t\nKnutsgillet Lund, Hum förb Västerås.\n-Hobbies: bridge, resor.\nGift 28 m Karin Mandahl f 05, dtr t\nfabr Oskar M o Alma Lindström.\n-Barn: Margaretha f 41.\n\nWILKENSON, LARS W, fabrikör,\nÖrebro, f i Gbg 13/11/15 av ing Wilken W\no Anna-Greta Boijsen.\nRealex 32, gesäll 37, mästare 40, inneh\nab Wilkensons handskfabr Örebro sed\n40. - Ordf Sv handskfabr:fören, styr:led\nÖrebro l f öret :f ören 48. - Led Stadsfullm\n54, drätselkamm 56. - Medl Rotary,\nFrimO. - Hobbies: sjösport, golf, tennis.\nGift 44 m Margit Ginberg. - Barn: Åsa\nf 45, Charlotte f 47.\n\nWILLÉN, HANS W F, ingenjör,\nLudvika, f i Malmö 31/12/15 av köpman\nErnest W o Thea Hansson.\nIng:ex HTL Malmö 36, ing Asea\nLudvika 37, sekt :ch konstr :kont f mindre\ntransformatorer 45, f st transformatorer\nsed 63.\n\nGift 41 m Gertrud Ståhl, dtr t jv:tjm\nGustaf S o Alma Holm. - Barn:\nBirgitta f 42, Hans f 44, Mats f 50.\n\nWILLERMAN, SVEN E, direktör,\nKumla, f i Kumla 23/9/06 av dir J W\nJohansson o Ingegärd Karlsson.\nAnst Kumla foder o utsädes ab 24,\nverkst dir o styr :ordf där sed 43, verkst\ndir o styr:ordf Örebro bil o traktor ab\nsed 47 samt Carman ab Lindesberg sed\n60. - Styr:ordf Sv hdlsbkn Kumla.\nGift 33 m Inga Löfgren f 11, dtr t disp\nJonan L o Anna L. - Barn: Anders f 36,\nIngegärd f 41, Dag f 46.\n\nWILLIAM-OLSSON, J O ROBIN W,\nprovinsialläkare, Lövstabruk, f i Sthlm\n19/1/32 av med lic Leslie W-O o Birgit\nEkström.\n\nStud:ex 50, med kand Sthlm 53, med lic\n58, underläk las Falkpg 58, prov:läk\nLövsta distr sed 61.\n\nGift 54 m Marianne Avellan-Hultman\nf 29, dtr t pat:ing Bengt A-H o Helga\nEkström. - Barn: Mikael f 56, Charlotte\nf 58, Tomas f 63.\n\nWILLIAMSSON, TAGE W, ingenjör,\nSödertälje, f i Sthlm 5/2/24 av adv Johan\nW o Agnes Lunqvist.\nIng:ex STI 42, försäljn:ing ab Gustaf\nTerling Sthlm 7 år, avd :ch ab Pegasus\n10 år, inneh Ing:firma Tage Williamsson\nSödertälje. - Fd sekr o kassör\nOljeeldn:-tekn fören. - Medl Odd Fellow, WasaO.\n- Utm: VermeilM v 12:e internat\nuppf:-mässan B russel, B M v 20 :e internat\nuppf :mässan Nürnberg 63. - Hobbies:\ntennis, skidsports, trädgårdsskötsel.\nGift 50 m Gund Erikson f 23, dtr t\nlantbr Wilhelm E o Linnea E. - Barn:\nPer Åke f 51, Lena f 57.\n\nWILUND, HJALMAR J R, instruktör,\nUppsala, f i Upps 5/8/10 av murarmäst\nKarl Johansson o Hilda Karlsson.\nKondit Upps, Gbg o Eskilstuna 28-38,\nanst Güntherska hovkondit Upps 38,\nomb :man Folkrör sparkampanj 47, instr\nUpps ABF-avd sed 48. - Ordf Upps\nstads kulturndsutredn 63, styr :led ab S:t\nEriks lervarufabr 54-61, HSB Upps 54.\n-Led Stadsfullm 56, ungd :styr 52, bibl :styr\n53, v ordf skolstyr 56. - Sekr Fören\nNordens Upps :avd 53.\nGift 37 m Gulli Samuelsson. - Barn:\nChristina f 37, Ingemar f 40, Per f 42.\n\nWIMAN, ERIK, lektor, Kristinehamn,\nf i Upps 1/6/01 av prof Carl W o Agnes\nUggla.\n\nFil dr 30, adj Söderkpg 34, lektor hal\nKristinehamn sed 36. - Ordf Geogr :lär\nriksfören Vänerkrets 47, styr :led\nKristinehamns stadsbibl. - Skr: Archgean\nrocks near Upsala, Morpho-tectonics of\nMälar depression, Aspects of the\npre-cambrian geology of south-eastern\n",
    "structured": {
        "1": {
            "full_name": "Vilke, A Johan S",
            "location": "Västerås",
            "occupation": "Kriminalkommissarie, Ryttmästare",
            "birth_details": {
                "date": "05/01/1904",
                "place": "Lund"
            },
            "education": [
                {
                    "degree": "Stud:ex",
                    "year": "1922",
                    "institution": "Lunds universitet"
                },
                {
                    "degree": "Res:off:ex",
                    "year": "1924"
                },
                {
                    "degree": "GCI",
                    "year": "1926"
                },
                {
                    "degree": "Kansliex",
                    "year": "1932"
                },
                {
                    "degree": "Hdlssk",
                    "year": "1934"
                },
                {
                    "degree": "Poliskommiss:kurs",
                    "year": "1950"
                },
                {
                    "degree": "Cfch:ex",
                    "year": "1951"
                }
            ],
            "career": [
                {
                    "position": "Anst Sthlms polis",
                    "years": {
                        "start_year": 1927
                    }
                },
                {
                    "position": "Kriminalkommiss o ch kriminalavd Västerås",
                    "years": {
                        "start_year": 1951
                    }
                },
                {
                    "position": "Krig- o marinpolisch Gotland",
                    "years": {
                        "start_year": 1944,
                        "end_year": 1945
                    }
                },
                {
                    "position": "Kontr :off (tf major) FN:s ö vervakn",
                    "years": {
                        "start_year": 1954,
                        "end_year": 1955
                    }
                },
                {
                    "position": "Lär flottiljpolissk FV:s centr skola Västerås",
                    "years": {
                        "start_year": 1952,
                        "end_year": 1961
                    }
                }
            ],
            "family": {
                "spouse": "Karin Mandahl",
                "marriage_year": "1928",
                "children": [
                    {
                        "name": "Margaretha",
                        "birth_year": "1941"
                    }
                ]
            },
            "hobbies": [
                "Bridge",
                "Resor"
            ]
        },
        "2": {
            "full_name": "Wilkenson, Lars W",
            "location": "Örebro",
            "occupation": "Fabrikör",
            "birth_details": {
                "date": "13/11/1915",
                "place": "Göteborg"
            },
            "education": [
                {
                    "degree": "Realex",
                    "year": "1932"
                },
                {
                    "degree": "Gesäll",
                    "year": "1937"
                },
                {
                    "degree": "Mästare",
                    "year": "1940"
                }
            ],
            "career": [
                {
                    "position": "Inneh ab Wilkensons handskfabr Örebro",
                    "years": {
                        "start_year": 1940
                    }
                }
            ],
            "family": {
                "spouse": "Margit Ginberg",
                "marriage_year": "1944",
                "children": [
                    {
                        "name": "Åsa",
                        "birth_year": "1945"
                    },
                    {
                        "name": "Charlotte",
                        "birth_year": "1947"
                    }
                ]
            },
            "hobbies": [
                "Sjösport",
                "Golf",
                "Tennis"
            ]
        },
        "3": {
            "full_name": "Willén, Hans W F",
            "location": "Ludvika",
            "occupation": "Ingenjör",
            "birth_details": {
                "date": "31/12/1915",
                "place": "Malmö"
            },
            "education": [
                {
                    "degree": "Ing:ex HTL Malmö",
                    "year": "1936"
                }
            ],
            "career": [
                {
                    "position": "Ing Asea Ludvika",
                    "years": {
                        "start_year": 1937
                    }
                }
            ],
            "family": {
                "spouse": "Gertrud Ståhl",
                "marriage_year": "1941",
                "children": [
                    {
                        "name": "Birgitta",
                        "birth_year": "1942"
                    },
                    {
                        "name": "Hans",
                        "birth_year": "1944"
                    },
                    {
                        "name": "Mats",
                        "birth_year": "1950"
                    }
                ]
            }
        },
        "4": {
            "full_name": "Willerman, Sven E",
            "location": "Kumla",
            "occupation": "Direktör",
            "birth_details": {
                "date": "23/09/1906",
                "place": "Kumla"
            },
            "career": [
                {
                    "position": "Anst Kumla foder o utsädes ab",
                    "years": {
                        "start_year": 1924
                    }
                },
                {
                    "position": "Verkst dir o styr:ordf där",
                    "years": {
                        "start_year": 1943
                    }
                },
                {
                    "position": "Verkst dir o styr:ordf Örebro bil o traktor ab",
                    "years": {
                        "start_year": 1947
                    }
                },
                {
                    "position": "Verkst dir o styr:ordf Carman ab Lindesberg",
                    "years": {
                        "start_year": 1960
                    }
                }
            ],
            "family": {
                "spouse": "Inga Löfgren",
                "marriage_year": "1933",
                "children": [
                    {
                        "name": "Anders",
                        "birth_year": "1936"
                    },
                    {
                        "name": "Ingegärd",
                        "birth_year": "1941"
                    },
                    {
                        "name": "Dag",
                        "birth_year": "1946"
                    }
                ]
            }
        },
        "5": {
            "full_name": "William-Olsson, J O Robin W",
            "location": "Lövstabruk",
            "occupation": "Provinsialläkare",
            "birth_details": {
                "date": "19/01/1932",
                "place": "Stockholm"
            },
            "education": [
                {
                    "degree": "Stud:ex",
                    "year": "1950"
                },
                {
                    "degree": "Med kand",
                    "year": "1953",
                    "institution": "Karolinska Institutet Stockholm"
                },
                {
                    "degree": "Med lic",
                    "year": "1958"
                }
            ],
            "career": [
                {
                    "position": "Underläk las Falkpg",
                    "years": {
                        "start_year": 1958
                    }
                },
                {
                    "position": "Prov:läk Lövsta distr",
                    "years": {
                        "start_year": 1961
                    }
                }
            ],
            "family": {
                "spouse": "Marianne Avellan-Hultman",
                "marriage_year": "1954",
                "children": [
                    {
                        "name": "Mikael",
                        "birth_year": "1956"
                    },
                    {
                        "name": "Charlotte",
                        "birth_year": "1958"
                    },
                    {
                        "name": "Tomas",
                        "birth_year": "1963"
                    }
                ]
            }
        },
        "6": {
            "full_name": "Williamsson, Tage W",
            "location": "Södertälje",
            "occupation": "Ingenjör",
            "birth_details": {
                "date": "05/02/1924",
                "place": "Stockholm"
            },
            "education": [
                {
                    "degree": "Ing:ex STI",
                    "year": "1942"
                }
            ],
            "career": [
                {
                    "position": "Försäljn:ing ab Gustaf Terling Sthlm",
                    "years": {
                        "start_year": "1944",
                        "end_year": "1951"
                    }
                },
                {
                    "position": "Avd :ch ab Pegasus",
                    "years": {
                        "start_year": "1951",
                        "end_year": "1961"
                    }
                },
                {
                    "position": "Inneh Ing:firma Tage Williamsson Södertälje"
                }
            ],
            "family": {
                "spouse": "Gund Erikson",
                "marriage_year": "1950",
                "children": [
                    {
                        "name": "Per Åke",
                        "birth_year": "1951"
                    },
                    {
                        "name": "Lena",
                        "birth_year": "1957"
                    }
                ]
            },
            "honorary_titles": [
                {
                    "title": "VermeilM v 12:e internat uppf",
                    "institution": "Russel"
                },
                {
                    "title": "B M v 20 :e internat uppf",
                    "institution": "Nürnberg",
                    "year": "1963"
                }
            ],
            "hobbies": [
                "Tennis",
                "Skidsport",
                "Trädgårdsskötsel"
            ]
        },
        "7": {
            "full_name": "Wilund, Hjalmar J R",
            "location": "Uppsala",
            "occupation": "Instruktör",
            "birth_details": {
                "date": "5/8/1910",
                "place": "Uppsala"
            },
            "education": [
                {
                    "degree": "Kondit",
                    "year": "1928"
                }
            ],
            "career": [
                {
                    "position": "Omb :man Folkrör sparkampanj",
                    "years": {
                        "start_year": 1947
                    }
                },
                {
                    "position": "Instr Upps ABF-avd",
                    "years": {
                        "start_year": 1948
                    }
                }
            ],
            "family": {
                "spouse": "Gulli Samuelsson",
                "marriage_year": "1937",
                "children": [
                    {
                        "name": "Christina",
                        "birth_year": "1937"
                    },
                    {
                        "name": "Ingemar",
                        "birth_year": "1940"
                    },
                    {
                        "name": "Per",
                        "birth_year": "1942"
                    }
                ]
            }
        }
    }
}