{
    "original": "VARDHEIM, STEINAR V, fil dr,\nSthlm, f i Oslo 2/10/31 av avd:ch Erling\nAndersen o Signe Vike.\nStud:ex 50, Tekn högsk Edinburgh 55,\nM Se 57, fil dr univ i Birmingham 58.\n-Forskn:ing Papirind forskn:inst Oslo\n55-56, avd:ing där 58, forskn:ch A/S Freia\n\n60,  sekt :ch forskn:inst Billeruds ab Säf\nfilé 61, anst ab Defibrator Sthlm sed 64.\n\n-  Skr: art i facktidskr. - Hobbies: fiske,\nfilateli, sport.\n\nGift 54 m Marjory Maddaford f 33, dtr\nt övering William M o Marjory\nBrad-shaw. - Barn: Roy f 56, Kari f 60,\nElisabeth f 63.\n\nWARHOLM, CURT R, civilingenjör,\nKarlstad, f i Karlstad 13/3/25 av disp\nEngelbert W o Maria Simonsson.\nCTH 51, anst ab Värml trikåfabr\nKarlstad 51, adj komm realsk Skoghall 55,\nkomm flicksk Karlstad 57, ämneslär\nKarlstads yrkessk sed 58. - Styr :ordf ab\nVärml trikåfabr 61 (styr:led 51). -\nHobby: fiske.\n\nGift 51 m Sigbritt Hultbäck, dtr t\ntull-mast Olof H o Märta Björndal. - Barn:\nStellan f 52, Robert f 59.\n\nWARHOLM, STEN S, direktör,\nKarlstad, f i Vänersborg 7/4/19 av disp\nEngelbert W o Maria Simonsson.\nFilip Holmqvists HdlI, stud Pitman’s\nColl London, verkst dir ab Värml\ntrikåfabr Karlstad sed 42. - Styr :led ab Värml\ntrikåfabr, ab Tidafors ind, Sv:es\ntextil-ind:förb, Sv:es trikåfabr fören,\nTextilrådet, Werml ensk bk, Fastigh ab Idun,\nab Isbanan Karlstad. - Medl Lions Club.\nGift 42 m Ingrid Ajax, dtr t grossh\nJohn A o h h. - Barn: Sten-Olof f 43.\n\nWARMLAND, KNUT H, adjunkt,\nFilipstad, f i Fryksände, Värml l, 10/4/28\nav virkesmät Einar Johnson o Frida\nHenriksson.\n\nStud:ex Karlstad 48, fil mag Upps 54,\neo adj hal Borås 54, samrealsk Arboga\n55, hal Filipstad 56, adj o vik lekt där\nsed 59. - Styr:ordf Filipstads stadsbibl\n\n61,  v ordf Sv:es lärov:bibl riksförb 60.\n\n-  Utg: Eyvind Johnson: Noveller\n(skol-uppl 62), Näverbrev (dikter 63),\nGränsland (antologi tills m R Nordenberg 63),\nupps o rec i dagspr o facktidskr. - Medl\nRotary. - Hobby: böcker.\n\nGift 60 m textillär Bodil Lindskog f 37,\ndtr t kyrkoh Olle L o Elsa Axelson.\n-Barn: Jon f 61 Elsa f 63.\n\nWARNE,  K TOMAS,  arkitekt SAR,\n\nSträngnäs, f i Gbg 8/9/26 av civiling\nOscar W o Brita Stuart.\nCTH 56, anst Lettströms arkit :kont\nEskilstuna 54, arkit o deläg Klemmings\narkit :kont ab 55, arkit ab Hultsfredsind\n58, eg arkit :verksamh Hultsfred 62,\nSträngnäs sed 63. - Skr: art i fackpr rör\nprefabricerade småhus, kompend f CTH.\nGift 54 m arb :terapeut Ingalill Tingdal,\ndtr t förvalt Ernst T o Hildur Wallin.\n-Barn: Johan o Maria ff 57.\n",
    "structured": {
        "0": {
            "full_name": "STEINAR VARDHEIM",
            "location": "Sthlm",
            "occupation": "Filosofie doktor",
            "birth_details": {
                "date": "02/10/1931",
                "place": "Oslo"
            },
            "education": [
                {
                    "degree": "Stud:ex",
                    "year": "1950",
                    "institution": "Tekn högsk Edinburgh"
                },
                {
                    "degree": "M Se",
                    "year": "1957",
                    "institution": "Fil dr univ i Birmingham"
                }
            ],
            "career": [
                {
                    "position": "Forskn:ing Papirind forskn:inst Oslo",
                    "years": {
                        "start_year": 1955,
                        "end_year": 1956
                    },
                    "organization": "A/S Freia"
                },
                {
                    "position": "Sekt :ch forskn:inst Billeruds ab Säf filé",
                    "years": {
                        "start_year": 1960,
                        "end_year": 1961
                    },
                    "organization": "ab Defibrator Sthlm"
                }
            ],
            "family": {
                "spouse": "Marjory Maddaford",
                "marriage_year": "1954",
                "children": [
                    {
                        "name": "Roy",
                        "birth_year": "1956"
                    },
                    {
                        "name": "Kari",
                        "birth_year": "1960"
                    },
                    {
                        "name": "Elisabeth",
                        "birth_year": "1963"
                    }
                ]
            },
            "hobbies": [
                "fiske",
                "filateli",
                "sport"
            ]
        },
        "1": {
            "full_name": "CURT R WARHOLM",
            "location": "Karlstad",
            "occupation": "Civilingenjör",
            "birth_details": {
                "date": "13/03/1925",
                "place": "Karlstad"
            },
            "education": [
                {
                    "degree": "CTH",
                    "year": "1951",
                    "institution": "ab Värml trikåfabr Karlstad"
                }
            ],
            "career": [
                {
                    "position": "Anst ab Värml trikåfabr Karlstad",
                    "years": {
                        "start_year": 1951,
                        "end_year": 1951
                    },
                    "organization": "ab Värml trikåfabr"
                },
                {
                    "position": "Adj komm realsk Skoghall",
                    "years": {
                        "start_year": 1955,
                        "end_year": 1955
                    }
                },
                {
                    "position": "Komm flicksk Karlstad",
                    "years": {
                        "start_year": 1957,
                        "end_year": 1957
                    }
                },
                {
                    "position": "Ämneslär Karlstads yrkessk",
                    "years": {
                        "start_year": 1958
                    }
                }
            ],
            "family": {
                "spouse": "Sigbritt Hultbäck",
                "marriage_year": "1951",
                "children": [
                    {
                        "name": "Stellan",
                        "birth_year": "1952"
                    },
                    {
                        "name": "Robert",
                        "birth_year": "1959"
                    }
                ]
            },
            "hobbies": [
                "fiske"
            ]
        },
        "2": {
            "full_name": "STEN S WARHOLM",
            "location": "Karlstad",
            "occupation": "Direktör",
            "birth_details": {
                "date": "07/04/1919",
                "place": "Vänersborg"
            },
            "education": [
                {
                    "degree": "Filip Holmqvists HdlI"
                },
                {
                    "degree": "Stud Pitman’s Coll London"
                }
            ],
            "career": [
                {
                    "position": "Verkst dir ab Värml trikåfabr Karlstad",
                    "years": {
                        "start_year": 1942
                    }
                }
            ],
            "family": {
                "spouse": "Ingrid Ajax",
                "marriage_year": "1942",
                "children": [
                    {
                        "name": "Sten-Olof",
                        "birth_year": "1943"
                    }
                ]
            }
        },
        "3": {
            "full_name": "KNUT H WARMLAND",
            "location": "Filipstad",
            "occupation": "Adjunkt",
            "birth_details": {
                "date": "10/04/1928",
                "place": "Fryksände, Värml l"
            },
            "education": [
                {
                    "degree": "Stud:ex Karlstad",
                    "year": "1948"
                },
                {
                    "degree": "Fil mag Upps",
                    "year": "1954"
                }
            ],
            "career": [
                {
                    "position": "Adj hal Borås",
                    "years": {
                        "start_year": 1954,
                        "end_year": 1955
                    }
                },
                {
                    "position": "Samrealsk Arboga",
                    "years": {
                        "start_year": 1955
                    }
                },
                {
                    "position": "Hal Filipstad",
                    "years": {
                        "start_year": 1956
                    }
                },
                {
                    "position": "Adj o vik lekt där",
                    "years": {
                        "start_year": 1959
                    }
                }
            ],
            "family": {
                "spouse": "Bodil Lindskog",
                "marriage_year": "1960",
                "children": [
                    {
                        "name": "Jon",
                        "birth_year": "1961"
                    },
                    {
                        "name": "Elsa",
                        "birth_year": "1963"
                    }
                ]
            },
            "hobbies": [
                "böcker"
            ]
        },
        "4": {
            "full_name": "TOMAS K WARNE",
            "location": "Strängnäs",
            "occupation": "Arkitekt SAR",
            "birth_details": {
                "date": "08/09/1926",
                "place": "Gbg"
            },
            "education": [
                {
                    "degree": "CTH",
                    "year": "1956"
                }
            ],
            "career": [
                {
                    "position": "Anst Lettströms arkit :kont Eskilstuna",
                    "years": {
                        "start_year": 1954,
                        "end_year": 1954
                    }
                },
                {
                    "position": "Arkit o deläg Klemmings arkit :kont ab",
                    "years": {
                        "start_year": 1955,
                        "end_year": 1955
                    }
                },
                {
                    "position": "Arkit ab Hultsfredsind",
                    "years": {
                        "start_year": 1958,
                        "end_year": 1958
                    }
                },
                {
                    "position": "Eg arkit :verksamh Hultsfred",
                    "years": {
                        "start_year": 1962
                    }
                }
            ],
            "family": {
                "spouse": "Ingalill Tingdal",
                "marriage_year": "1954",
                "children": [
                    {
                        "name": "Johan",
                        "birth_year": "1957"
                    },
                    {
                        "name": "Maria ff",
                        "birth_year": "1957"
                    }
                ]
            }
        }
    }
}