{
    "original": "VARNAS, K ALLAN, direktör,\nVästerås, f i Krylbo, Kopparb l, 11/5/14 av\nbyggmäst Verner Andersson o h h.\nSTI 36, arb :ch byggn:f:an Verner\nAndersson ab Västerås 42, verkst dir, inneh\no styr :led där samt Varnäsf öretagen\n(Tierps järnbr, Kolbäcks metall). - Medl\nOdd Fellow.\n\nGift 38 m Margit Thalén f 10, dtr t\nköpm Emanuel T o Judit Stohrén.\n-Barn: Christer f 41, Carsten f 44,\nLise-Lotte f 51, Carolina f 57.\n\nWARROL,   HANS   I, bruksdisponent,\n\nMorgårdshammar, f i Falun 21/5/26 av\ning Helge W o Sally Carlsson.\nStud:ex Eskilstuna 45, KTH 50,\nforskn:ing KTH 50-51, valsv:ing Sandvikens\njernv ab 51, konstr :ch där 60, v verkst\ndir Morgårdshammar mek verkst ab o\nArboga mek verkst ab 62, verkst dir där\nsed 64. - Styr:led ab Åkers styckebruk.\nGift 52 m Ånn Hallen f 24, dtr t rekt\nHans H o Annie Renvall. - Barn: Johan\nf 55, Kristian f 58.\n\nWARSTRÖM, BERTIL A, direktör,\nKristinehamn, f i Kristinehamn 31/5/26.\nRealex, hdlsstud, inneh ab Kristinehamns\nbilsk, Warströms bil ab Kristinehamn\nsed 52. - Styr:led Scania-Vabis\nåterför-sälj:fören 60. - Medl Rotary. - Hobby:\nbilsport.\n\nGift 53 m Marianne Andersson f 27.\n-Barn: Lars f 55, Mikael f 60.\n\nWASASTIERNA, G (GÖSTA) A,\ncivilingenjör, tekn direktör, Eskilstuna,\nf i Känru, Finl, 15/5/15 av jägm Gustaf\nW o Hilma Kiukas.\n\nStud:ex 35, res:off:ex 38, KTH 41, anst\nab Atlas Diesel 42, ch maskinlab ab\nBolinder-Munktell 44, ritkont:ch där 49,\növering 55, tekn dir sed 60. - LSvTF.\n-Hobby: konst.\n\nGift 44 m Greta Sellman f 13, dtr t fabr\nKarl S o Signe S.\n\nWASE, GERT H E, disponent, Arboga,\nf i Hällefors, Örebro l, 27/8/24 av\nreparatör Ingvar W o Märta Andersson.\nPåhlmans hdlI 42, kont Hellefors bruks\n\nab 40, bokf o tjm skogsförvaltn ab\nIggesunds bruk 47, dir:ass Hjälmare\nkanal- &amp; slussv ab 52, disp o verkst dir\ndär sed 57. - Medl Odd Fellow. -\nHobbies: jakt, fiske, musik.\nGift 49 m Greta Höglund f 24, dtr t\nförman Gunnar H o Ester Vestermark.\n- Barn: Henrik f 50, Ingrid f 53,\nCatharina f 61.\n\nWASSBERG,  ERIK  H,  bankkamrer,\n\nAskersund,   f   i   Njutånger,   Gävleb   l,\n\n12/7/08  av  övermontör  Hennan  W  o\n\nMargareta Wengenroth.\n\nStud:ex Hudiksvall 28,  Schartaus  hdlI\n\n30,   stenograf   Iggesunds   bruk   29-30,\n\nkamr, kont :f or est o styr :led Skand bkns\n\navd :kont Askersund sed 44.\n\nGift 36 m Carin Nilson f 07, dtr t Karl\n\nN o Signe Andréasson. - Barn: Birgitta\n\nf 37, Kristina f 38, Barbro f 42.\n\nWAXBERG,    HENRY,    fältveterinär,\n\nStrömsholm, f i Trollhättan 26/4/91 av\npast Harald W o Anna Wåhlander.\nStud:ex Sthlm 09, vet:ex 13, vet\nStrömsholms hingstdepå 16, båt :vet RS 19,\nreg:vet 30, RS 37, fältvet 43, i res 51.\n-Ag o bebor St Åsby gård sed 48. - Ordf\nSv mil:-vet :sällsk 37-54, styr:led Sv:es\nvet:förb 39-51, komm:fullm 42-51, vet\nv sv olympiatruppen Amsterdam 28.\n-HedL Sv mil:-vet:sällsk 54. - Skr:\nHästen i hälsa o sjukdom (23), art i\nfack-tidskr. - Utm: RVO.\n\nGift 18 m Valborg Mallander f 93, dtr\nt grossh Gotthard M o Augusta\nCron-qvist. - Barn: Göran f 19, Lärs-Henrik\nf 22, Marie-Louise f 30.\n\nWEDBERG, MATS G W, tandläkare,\n\nKristinehamn, f i Ljungarum, Jönkpgs l,\n11/10/09 av pred Justus W o Emilia\nStröm.\n\nStud:ex Karlstad 30, tandläk:ex 33, prakt\nGullspång 33, Kristinehamn sed 46.\nGift 34 m Ingrid Larsson f 11, dtr t\nstatistiker Olof L o Sigrid Andersson.\n-Barn: Gunnar f 35, Kerstin f 37,\nGunilla f 38, Sten-Olof f 40, Lena f 42,\nAnders f 48, Annika f 51.\n\n",
    "structured": {
        "0": {
            "full_name": "VARNAS, K ALLAN",
            "location": "Västerås",
            "occupation": "direktör",
            "birth_details": {
                "date": "11/05/1914",
                "place": "Krylbo, Kopparbergs län",
                "parents": "byggmäst Verner Andersson o h h"
            },
            "education": [
                {
                    "degree": "STI",
                    "year": "1936",
                    "institution": "NULL"
                }
            ],
            "career": [
                {
                    "position": "arb :ch byggn:f:an",
                    "years": {
                        "start_year": 1942,
                        "end_year": 2020
                    },
                    "organization": "Verner Andersson ab Västerås"
                },
                {
                    "position": "verkst dir",
                    "years": {
                        "start_year": 2020,
                        "end_year": 2020
                    },
                    "organization": "NULL"
                }
            ],
            "family": {
                "spouse": "Margit Thalén",
                "marriage_year": "1938",
                "children": [
                    {
                        "name": "Christer",
                        "birth_year": "1941"
                    },
                    {
                        "name": "Carsten",
                        "birth_year": "1944"
                    },
                    {
                        "name": "Lise-Lotte",
                        "birth_year": "1951"
                    },
                    {
                        "name": "Carolina",
                        "birth_year": "1957"
                    }
                ]
            }
        },
        "1": {
            "full_name": "WARROL, HANS I",
            "location": "Morgårdshammar",
            "occupation": "bruksdisponent",
            "birth_details": {
                "date": "21/05/1926",
                "place": "Falun",
                "parents": "ing Helge W o Sally Carlsson"
            },
            "education": [
                {
                    "degree": "Stud:ex",
                    "year": "1945",
                    "institution": "Eskilstuna"
                },
                {
                    "degree": "KTH",
                    "year": "1950",
                    "institution": "NULL"
                }
            ],
            "career": [
                {
                    "position": "valsv:ing",
                    "years": {
                        "start_year": 1951,
                        "end_year": 1951
                    },
                    "organization": "Sandvikens jernv ab"
                },
                {
                    "position": "konstr :ch",
                    "years": {
                        "start_year": 1960,
                        "end_year": 1962
                    },
                    "organization": "Sandvikens jernv ab"
                },
                {
                    "position": "verkst dir",
                    "years": {
                        "start_year": 1962,
                        "end_year": 2020
                    },
                    "organization": "Morgårdshammar mek verkst ab o Arboga mek verkst ab"
                }
            ],
            "family": {
                "spouse": "Ånn Hallen",
                "marriage_year": "1952",
                "children": [
                    {
                        "name": "Johan",
                        "birth_year": "1955"
                    },
                    {
                        "name": "Kristian",
                        "birth_year": "1958"
                    }
                ]
            }
        },
        "2": {
            "full_name": "WARSTRÖM, BERTIL A",
            "location": "Kristinehamn",
            "occupation": "direktör",
            "birth_details": {
                "date": "31/05/1926",
                "place": "Kristinehamn",
                "parents": "NULL"
            },
            "education": [],
            "career": [],
            "family": {
                "spouse": "Marianne Andersson",
                "marriage_year": "1953",
                "children": [
                    {
                        "name": "Lars",
                        "birth_year": "1955"
                    },
                    {
                        "name": "Mikael",
                        "birth_year": "1960"
                    }
                ]
            }
        },
        "3": {
            "full_name": "WASASTIERNA, G (GÖSTA) A",
            "location": "Eskilstuna",
            "occupation": "civilingenjör, tekn direktör",
            "birth_details": {
                "date": "15/05/1915",
                "place": "Känru, Finland",
                "parents": "jägm Gustaf W o Hilma Kiukas"
            },
            "education": [
                {
                    "degree": "Stud:ex",
                    "year": "1935",
                    "institution": "NULL"
                },
                {
                    "degree": "res:off:ex",
                    "year": "1938",
                    "institution": "NULL"
                },
                {
                    "degree": "KTH",
                    "year": "1941",
                    "institution": "NULL"
                }
            ],
            "career": [
                {
                    "position": "anst ab Atlas Diesel",
                    "years": {
                        "start_year": 1942,
                        "end_year": 1944
                    },
                    "organization": "NULL"
                },
                {
                    "position": "ch maskinlab ab Bolinder-Munktell",
                    "years": {
                        "start_year": 1949,
                        "end_year": 1949
                    },
                    "organization": "NULL"
                },
                {
                    "position": "övering",
                    "years": {
                        "start_year": 1955,
                        "end_year": 1955
                    },
                    "organization": "Bolinder-Munktell"
                },
                {
                    "position": "tekn dir",
                    "years": {
                        "start_year": 1960,
                        "end_year": 2020
                    },
                    "organization": "Bolinder-Munktell"
                }
            ],
            "family": {
                "spouse": "Greta Sellman",
                "marriage_year": "1944",
                "children": []
            }
        },
        "4": {
            "full_name": "WASE, GERT H E",
            "location": "Arboga",
            "occupation": "disponent",
            "birth_details": {
                "date": "27/08/1924",
                "place": "Hällefors, Örebro län",
                "parents": "reparatör Ingvar W o Märta Andersson"
            },
            "education": [
                {
                    "degree": "NULL",
                    "year": "1942",
                    "institution": "Påhlmans hdlI"
                }
            ],
            "career": [
                {
                    "position": "bokf o tjm",
                    "years": {
                        "start_year": 1947,
                        "end_year": 1947
                    },
                    "organization": "skogsförvaltn ab Iggesunds bruk"
                },
                {
                    "position": "disp o verkst dir",
                    "years": {
                        "start_year": 1957,
                        "end_year": 2020
                    },
                    "organization": "Hjälmare kanal- & slussv ab"
                }
            ],
            "family": {
                "spouse": "Greta Höglund",
                "marriage_year": "1949",
                "children": [
                    {
                        "name": "Henrik",
                        "birth_year": "1950"
                    },
                    {
                        "name": "Ingrid",
                        "birth_year": "1953"
                    },
                    {
                        "name": "Catharina",
                        "birth_year": "1961"
                    }
                ]
            }
        },
        "5": {
            "full_name": "WASSBERG, ERIK H",
            "location": "Askersund",
            "occupation": "bankkamrer",
            "birth_details": {
                "date": "12/07/1908",
                "place": "Njutånger, Gävleborgs län",
                "parents": "övermontör Hennan W o Margareta Wengenroth"
            },
            "education": [
                {
                    "degree": "Stud:ex",
                    "year": "1928",
                    "institution": "Hudiksvall"
                },
                {
                    "degree": "Schartaus hdlI",
                    "year": "1930",
                    "institution": "NULL"
                },
                {
                    "degree": "kamr",
                    "year": "NULL",
                    "institution": "NULL"
                }
            ],
            "career": [
                {
                    "position": "kamr, kont",
                    "years": {
                        "start_year": 1944,
                        "end_year": 2020
                    },
                    "organization": "Skand bkns avd :kont Askersund"
                }
            ],
            "family": {
                "spouse": "Carin Nilson",
                "marriage_year": "1936",
                "children": [
                    {
                        "name": "Birgitta",
                        "birth_year": "1937"
                    },
                    {
                        "name": "Kristina",
                        "birth_year": "1938"
                    },
                    {
                        "name": "Barbro",
                        "birth_year": "1942"
                    }
                ]
            }
        },
        "6": {
            "full_name": "WAXBERG, HENRY",
            "location": "Strömsholm",
            "occupation": "fältveterinär",
            "birth_details": {
                "date": "26/04/1891",
                "place": "Trollhättan",
                "parents": "past Harald W o Anna Wåhlander"
            },
            "education": [
                {
                    "degree": "Stud:ex",
                    "year": "1909",
                    "institution": "Sthlm"
                },
                {
                    "degree": "vet:ex",
                    "year": "1913",
                    "institution": "NULL"
                }
            ],
            "career": [
                {
                    "position": "fältvet",
                    "years": {
                        "start_year": 1943,
                        "end_year": 2020
                    },
                    "organization": "i res"
                }
            ],
            "family": {
                "spouse": "Valborg Mallander",
                "marriage_year": "1918",
                "children": [
                    {
                        "name": "Göran",
                        "birth_year": "1919"
                    },
                    {
                        "name": "Lärs-Henrik",
                        "birth_year": "1922"
                    },
                    {
                        "name": "Marie-Louise",
                        "birth_year": "1930"
                    }
                ]
            }
        },
        "7": {
            "full_name": "WEDBERG, MATS G W",
            "location": "Kristinehamn",
            "occupation": "tandläkare",
            "birth_details": {
                "date": "11/10/1909",
                "place": "Ljungarum, Jönköpings län",
                "parents": "pred Justus W o Emilia Ström"
            },
            "education": [
                {
                    "degree": "Stud:ex",
                    "year": "1930",
                    "institution": "Karlstad"
                },
                {
                    "degree": "tandläk:ex",
                    "year": "1933",
                    "institution": "NULL"
                }
            ],
            "career": [
                {
                    "position": "prakt",
                    "years": {
                        "start_year": 1946,
                        "end_year": 2020
                    },
                    "organization": "Kristinehamn"
                }
            ],
            "family": {
                "spouse": "Ingrid Larsson",
                "marriage_year": "1934",
                "children": [
                    {
                        "name": "Gunnar",
                        "birth_year": "1935"
                    },
                    {
                        "name": "Kerstin",
                        "birth_year": "1937"
                    },
                    {
                        "name": "Gunilla",
                        "birth_year": "1938"
                    },
                    {
                        "name": "Sten-Olof",
                        "birth_year": "1940"
                    },
                    {
                        "name": "Lena",
                        "birth_year": "1942"
                    },
                    {
                        "name": "Anders",
                        "birth_year": "1948"
                    },
                    {
                        "name": "Annika",
                        "birth_year": "1951"
                    }
                ]
            }
        }
    }
}