{
    "original": "FISCHERSTRÖM, NILS A L,\nagronom, direktör, Gävle, f i Umeå 22/7/13\nav major Nils F o Verna Lindbäck.\nHvilans spec :gymn 37, agr:ex KLH 42, e\njordbr:konsulent Jämtl l hush:sällsk 42,\njordbr :konsulent Västerb l hush :sällsk\n\n47,  lantbr :konsulent lantbr:ndn Värml l\n\n48,  j ordbr :konsulent Södermani l\nhush:-sällsk 53, dir Gävleb l hush:sällsk sed\n58. - Styr:led Gävleb l föret:fören sed\n58, SALF 59-65. - Medl Sällsk NT,\nRo-tary. - Utm: RNO. - Hobby: fiske.\nGi/f 44 m Ylfva Birgitta Bark f 22, dtr\nt kapt Gunnar B o Margit Leier. - Barn:\nGöran f 45, Jan f 47, Övar f 53.\n\nFJAESTAD, J O SVERKER, ingenjör,\n\nGallejaurbygget, f i Lidingö 18/6/09.\nIng:ex Tekn sk Sthlm 30, res:off:ex 34,\nSchartaus hdlI 38, ing ab Betongind 39,\nverkst :ch tygdep 42, verkst:ing stat\nvat-tenf :verk sed 46. - Kapt I 5 res 44.\nGift 40 m Birgit Holmin f 11. - Barn:\nBjörn f 43.\n\nFLADVAD, O SIGURD, civilingenjör,\n\nSundsvall, f i Berg, Jämtl l, 26/8/11 av\nförvalt Johann F o Anna Pettersson.\nCTH 34, ing Asea 35, ab Liljeholmens\nkabelfabr 37, ch apparatbyrån Asea 45,\n\növering o platsch Cebe ab 48-53, verkst\ndir El ab Sivers &amp; Häger 54-56, filialen\nAsea Sundsvall sed 57. - Led\nmunicip:-fullm Svalöv 49-52. - Medl FrimO,\nRo-tary. - Hobby: bridge.\nGi’/f 41 m Gunborg Sjöberg, dtr t fanj\nGunnar S o Mary S. - Barn: Birgitta\nf 43, Johann Olov f 45, Gunnar f 46.\n\nFLEMMING, STEEN E O, konstnär,\n\nStensele, f i Köpenh 15/4/97 av A S F\n\n0  Hanna Ohlson.\n\nRealex Köpenh 13, tekn sk 14-18, priv\nmålarsk 16-17, Kunstakad 18-21. -\nSep:-utst Köpenh 23, Sthlm 31 o 37, Umeå\n32, 35, 37, 41 o 56, delt i saml:utst\nKöpenh, Sthlm, Gbg, Hbg, Umeå m m.\n-Repr nät :mus, prins Eugens\nWaldemarsudde o Stat mus for kunst Köpenh.\n-Hobby: foto.\n\nGi/f 27 m Carin Carlstedt f 00, dtr t red\nCarl C o Axelina Wallberg. - Barn:\nErland f 28, Stig f 34.\n\n",
    "structured": {
        "0": {
            "full_name": "NILS A L FISCHERSTRÖM",
            "location": "Gävle",
            "occupation": "agronom, direktör",
            "birth_details": {
                "date": "22/07/1913",
                "place": "Umeå",
                "parents": "major Nils F o Verna Lindbäck"
            },
            "education": [
                {
                    "degree": "gymn",
                    "year": "1937",
                    "institution": "Hvilans spec"
                },
                {
                    "degree": "agr:ex",
                    "year": "1942",
                    "institution": "KLH"
                }
            ],
            "career": [
                {
                    "position": "jordbr:konsulent",
                    "years": {
                        "start_year": 1942,
                        "end_year": 1947
                    },
                    "organization": "Jämtl l hush:sällsk"
                },
                {
                    "position": "jordbr:konsulent",
                    "years": {
                        "start_year": 1947,
                        "end_year": 1948
                    },
                    "organization": "Västerb l hush :sällsk"
                }
            ],
            "family": {
                "spouse": "Ylfva Birgitta Bark",
                "marriage_year": "1944",
                "children": [
                    {
                        "name": "Göran",
                        "birth_year": "1945"
                    },
                    {
                        "name": "Jan",
                        "birth_year": "1947"
                    },
                    {
                        "name": "Övar",
                        "birth_year": "1953"
                    }
                ]
            },
            "hobbies": [
                "fiske"
            ]
        },
        "1": {
            "full_name": "J O SVERKER FJAESTAD",
            "location": "Gallejaurbygget",
            "occupation": "ingenjör",
            "birth_details": {
                "date": "18/06/1909",
                "place": "Lidingö"
            },
            "education": [
                {
                    "degree": "Ing:ex",
                    "year": "1930",
                    "institution": "Tekn sk Sthlm"
                }
            ],
            "career": [
                {
                    "position": "kapt I 5 res",
                    "years": {
                        "start_year": 1944,
                        "end_year": null
                    },
                    "organization": null
                }
            ],
            "family": {
                "spouse": "Birgit Holmin",
                "marriage_year": "1940",
                "children": [
                    {
                        "name": "Björn",
                        "birth_year": "1943"
                    }
                ]
            }
        },
        "2": {
            "full_name": "O SIGURD FLADVAD",
            "location": "Sundsvall",
            "occupation": "civilingenjör",
            "birth_details": {
                "date": "26/08/1911",
                "place": "Berg, Jämtl l",
                "parents": "förvalt Johann F o Anna Pettersson"
            },
            "education": [
                {
                    "degree": null,
                    "year": "1934",
                    "institution": "CTH"
                },
                {
                    "degree": "ing",
                    "year": "1935",
                    "institution": "Asea"
                }
            ],
            "career": [
                {
                    "position": "övering o platsch",
                    "years": {
                        "start_year": 1948,
                        "end_year": 1953
                    },
                    "organization": "Cebe ab"
                }
            ],
            "family": {
                "spouse": "Gunborg Sjöberg",
                "marriage_year": "1941",
                "children": [
                    {
                        "name": "Birgitta",
                        "birth_year": "1943"
                    },
                    {
                        "name": "Johann Olov",
                        "birth_year": "1945"
                    },
                    {
                        "name": "Gunnar",
                        "birth_year": "1946"
                    }
                ]
            },
            "hobbies": [
                "bridge"
            ]
        },
        "3": {
            "full_name": "STEEN E O FLEMMING",
            "location": "Stensele",
            "occupation": "konstnör",
            "birth_details": {
                "date": "15/04/1897",
                "place": "Köpenh",
                "parents": "A S F o Hanna Ohlson"
            },
            "education": [
                {
                    "degree": "realex",
                    "year": "1913",
                    "institution": "Köpenh"
                },
                {
                    "degree": null,
                    "year": "1914-1918",
                    "institution": "tekn sk"
                }
            ],
            "career": [],
            "family": {
                "spouse": "Carin Carlstedt",
                "marriage_year": "1927",
                "children": [
                    {
                        "name": "Erland",
                        "birth_year": "1928"
                    },
                    {
                        "name": "Stig",
                        "birth_year": "1934"
                    }
                ]
            },
            "hobbies": [
                "foto"
            ]
        }
    }
}