{
    "original": "FORSMAN, P VIDAR,\nlänsarbetsdirektör, Gävle, f i Borås 7/3/16 av\nkonditor-mast Axel F o Emmy Johansson.\nStud:ex 34, fil mag Upps 39,\nyrkesväg-ledn :konsulent länsarb:ndn Borås 41,\narb :f örmedl:insp där 43, länsarb:dir\nGävleb l sed 59.\n\nGift 50 m Astrid Zettergrén f 20, dtr t\nlöjtn Wictor Z o Anna Svensson.\n-Barn: Karin f 51, Anders f 53.\n\nFORSMAN,   ÅKE   F,   bergsingenjör,\n\nSandviken,   f   i   Djursholm   16/3/24   av\növerdir Otto F o Siri Pettersson.\nStud:ex 43, KTH 50, ing Kockums jernv\nab   50,  Söderfors  bruk  53,  Sandvikens\njernv ab sed 59. - Hobby: sport.\nGift 51 m Agneta Nordqvist f 27, dtr t\n\ndir Helmer N o Magda Edlund. - Barn:\nEva f 52, Anne f 54, Helen f 59.\n\nFORSSBERG se FORSBERG\n\nFORSSBLAD, Å LARS HENRIK,\ncivilingenjör, Gävle, f i Paris 14/6/27 av\ntjm Åke F o Anna Bergström.\nStud:ex Söderhamn 46, KTH 51,\nforskn:ing Mo o Domsjö ab 51, övering\nMarma Långrör ab 57, utveckl:avd\nKorsnäs-Marma ab Gävle 61, forskn :ch där.\nGift 53 m Vera Grandien, dtr t chefred\nHans G o h h. - Barn: Lena f 53,\nMagnus f 57, Henrik f 60, Anders f 65.\n\nFORSSELL, GÖRAN, civiljägmästare,\n\nArjeplog, f i Dillnäs, Södermani l, I/H/\n23.\n\nSkHS 51, anst domänv 51, jägm\nArjeplogs revir sed 61.\n\nFORSSELL, NILS F, kanslichef,\nLjusdal, f i Upps 23/7/20 av jordbr:arb Karl\nF o Anna Sofia Hedman.\nDSI Sthlm 48, komm:kamr Torsåkers kn\n49, stadskamr Bollnäs 54, kanslich\nLjusdals kpg sed 67. - Rev HSB Bollnäs sed\n63, sekr Hälsingl tennisförb sed 60.\n-Medl Odd Fellow. - Skr i fackämn.\n-Hobby: tennis.\n\nGift 50 m Gunvor Löfgren f 17, dtr t\nEdvin L o Selma Backlund. - Barn:\nHåkan f 53.\n\nFORSSLUND se FORSLUND\nFORSSMAN se FORSMAN\n\n",
    "structured": {
        "0": {
            "full_name": "P VIDAR FORSMAN",
            "location": "Gävle",
            "occupation": "länsarbetsdirektör",
            "birth_details": {
                "date": "07/03/1916",
                "place": "Borås",
                "parents": "konditor-mast Axel F o Emmy Johansson"
            },
            "education": [
                {
                    "degree": "Stud:ex",
                    "year": "1934",
                    "institution": "NULL"
                },
                {
                    "degree": "filosofie magister",
                    "year": "1939",
                    "institution": "Upps"
                }
            ],
            "career": [
                {
                    "position": "konsulent",
                    "years": {
                        "start_year": 1941,
                        "end_year": 1943
                    },
                    "organization": "länsarb:ndn Borås"
                },
                {
                    "position": "länsarb:dir",
                    "years": {
                        "start_year": 1959,
                        "end_year": null
                    },
                    "organization": "Gävleb l"
                }
            ],
            "family": {
                "spouse": "Astrid Zettergrén",
                "marriage_year": "1950",
                "children": [
                    {
                        "name": "Karin",
                        "birth_year": "1951"
                    },
                    {
                        "name": "Anders",
                        "birth_year": "1953"
                    }
                ]
            }
        },
        "1": {
            "full_name": "ÅKE F FORSMAN",
            "location": "Sandviken",
            "occupation": "bergsingenjör",
            "birth_details": {
                "date": "16/03/1924",
                "place": "Djursholm",
                "parents": "överdir Otto F o Siri Pettersson"
            },
            "education": [
                {
                    "degree": "Stud:ex",
                    "year": "1943",
                    "institution": "NULL"
                },
                {
                    "degree": "KTH",
                    "year": "1950",
                    "institution": "NULL"
                }
            ],
            "career": [
                {
                    "position": "ing",
                    "years": {
                        "start_year": 1950,
                        "end_year": 1953
                    },
                    "organization": "Kockums jernv ab"
                },
                {
                    "position": "NULL",
                    "years": null,
                    "organization": "Söderfors bruk"
                },
                {
                    "position": "NULL",
                    "years": {
                        "start_year": 1959,
                        "end_year": null
                    },
                    "organization": "Sandvikens jernv ab"
                }
            ],
            "family": {
                "spouse": "Agneta Nordqvist",
                "marriage_year": "1951",
                "children": [
                    {
                        "name": "Eva",
                        "birth_year": "1952"
                    },
                    {
                        "name": "Anne",
                        "birth_year": "1954"
                    },
                    {
                        "name": "Helen",
                        "birth_year": "1959"
                    }
                ]
            },
            "hobbies": [
                "sport"
            ]
        },
        "2": {
            "full_name": "Å LARS HENRIK FORSSBLAD",
            "location": "Gävle",
            "occupation": "civilingenjör",
            "birth_details": {
                "date": "14/06/1927",
                "place": "Paris",
                "parents": "tjm Åke F o Anna Bergström"
            },
            "education": [
                {
                    "degree": "Stud:ex",
                    "year": "1946",
                    "institution": "Söderhamn"
                },
                {
                    "degree": "KTH",
                    "year": "1951",
                    "institution": "NULL"
                }
            ],
            "career": [
                {
                    "position": "forskn:ing",
                    "years": {
                        "start_year": 1951,
                        "end_year": 1957
                    },
                    "organization": "Mo o Domsjö ab"
                },
                {
                    "position": "övering",
                    "years": {
                        "start_year": 1957,
                        "end_year": 1961
                    },
                    "organization": "Marma Långrör ab"
                },
                {
                    "position": "forskn :ch",
                    "years": {
                        "start_year": 1961,
                        "end_year": null
                    },
                    "organization": "Korsnäs-Marma ab Gävle"
                }
            ],
            "family": {
                "spouse": "Vera Grandien",
                "marriage_year": "1953",
                "children": [
                    {
                        "name": "Lena",
                        "birth_year": "1953"
                    },
                    {
                        "name": "Magnus",
                        "birth_year": "1957"
                    },
                    {
                        "name": "Henrik",
                        "birth_year": "1960"
                    },
                    {
                        "name": "Anders",
                        "birth_year": "1965"
                    }
                ]
            }
        },
        "3": {
            "full_name": "GÖRAN FORSSELL",
            "location": "Arjeplog",
            "occupation": "civiljägmästare",
            "birth_details": {
                "date": "01/07/1923",
                "place": "Dillnäs, Södermani l",
                "parents": "NULL"
            },
            "education": [
                {
                    "degree": "SkHS",
                    "year": "1951",
                    "institution": "NULL"
                }
            ],
            "career": [
                {
                    "position": "anst domänv",
                    "years": {
                        "start_year": 1951,
                        "end_year": 1961
                    },
                    "organization": "NULL"
                }
            ],
            "family": "NULL"
        },
        "4": {
            "full_name": "NILS F FORSSELL",
            "location": "Ljusdal",
            "occupation": "kanslichef",
            "birth_details": {
                "date": "23/07/1920",
                "place": "Upps",
                "parents": "jordbr:arb Karl F o Anna Sofia Hedman"
            },
            "education": [
                {
                    "degree": "DSI",
                    "year": "1948",
                    "institution": "Sthlm"
                }
            ],
            "career": [
                {
                    "position": "komm:kamr",
                    "years": {
                        "start_year": 1949,
                        "end_year": 1954
                    },
                    "organization": "Torsåkers kn"
                },
                {
                    "position": "stadskamr",
                    "years": {
                        "start_year": 1954,
                        "end_year": 1967
                    },
                    "organization": "Bollnäs"
                },
                {
                    "position": "kanslich",
                    "years": {
                        "start_year": 1967,
                        "end_year": null
                    },
                    "organization": "Ljusdals kpg"
                }
            ],
            "family": {
                "spouse": "Gunvor Löfgren",
                "marriage_year": "1950",
                "children": [
                    {
                        "name": "Håkan",
                        "birth_year": "1953"
                    }
                ]
            },
            "community_involvement": [
                {
                    "role": "Rev HSB",
                    "organization": "Bollnäs",
                    "years": "1963"
                },
                {
                    "role": "sekr",
                    "organization": "Hälsingl tennisförb",
                    "years": "1960"
                }
            ],
            "board_memberships": [
                "NULL"
            ],
            "hobbies": [
                "tennis"
            ]
        }
    }
}