{
    "original": "OLLING, CARL-HENRIK S O,\nassuransdirektör, Sthlm, f i Sura,\nVästmanl l, 31/7/11 av bruksintend Sven\nOlsson o Terese Janson.\nStud:ex 30, jur kand 34, tingstjg\n35-36, stud Tyskl o Engl 36-37, DHS 39,\ndispaschörskomp 43. - Anst internat\nSiporex ab Sthlm, adv :firma\nReyn-holds, Sons &amp; Gorst o Sv hdlskamm\nLondon 36-37, bitr avd:ch stat\nkrigs-försäkr:nd 40, haverich Hansa 45, bitr\ndir där 57, bitr dir Sjöförsäkr ab\nHansa-Mälaren sed 60. - Styr:led\nJu-rid fören StHS 33-34, led\nNäringslivets trafikdeleg, Sv allm exportfören\ndokumentkomm.\n\nGift 51 m Eva Åsell f 25, dtr t\nköpman Helmer Å o Elsa Sartz.\n\nOLOFGÖRS, H GUNNAR H,\ncivilingenjör, Bromma, f i Kristineh 1/9/26\nav ing Henrik O o Agnes Olsson.\nKTH 49, fil kand 51, anst ^nterprise\nLeon BaHot Paris 50, ab\nVattenbyggn:-byrån Sthlm 51, Byggn\n:entreprenör-fören 52, Byggn :ind :f örb 55, verkst dir\ndär sed 58. - Suppl arb:markn:styr,\nar-b:markn yrkesråd.\n\nGift 52 m fil kand Barbro Ståhl f 28,\ndtr t kassör Alf S o Tora Björkman.\n-Barn: Mats f 54, Lena f 57.\n\nOLOFSSON, J EGON, ingenjör,\nBromma, f i Östersund 1/7/02 av\nkäl-larmäst John O o Anna Andersson.\nPrakt ol ind 19-21, ing CTI 24,\ning:-prakt 24-27, anst General Motors Nord\nab Sthlm 28, stat bilinsp Västerb 26,\nbiling Hansa sed 29. - Ordf\nFörsäkr :männens biltekn klubb, f v led Sv\nautomobiltariffören tekn komm. - Medl\nSF 29. - Styr:led Sv:es motortekn\nfören, föreläs stat hantv:inst.\nGift 31 m Esther Wahlqvist f 97.\n-Barn: Lena f 32, Kerstin f 37.\n\nOLOFSSON, GUNNAR E, tf\nbyråchef, Bandhagen, f i Sthlm 27/12/20 av\nköpman Edvin O o Sigrid Bergstedt.\nStud:ex 40, jur kand 45, tingstjg 45-48,\naman inr:dep 48, l:e kanslisekr 55 (tf\n53), budgetsekr 57, tf byråch sed 60.\n-Sekr 51 års strålskyddskomm 52,\nprofes-sorslöneutredn 51. - Hobby: bridge.\n\nGift 47 m  Britt Hedman f 23,  dtr t\nl:e kammarskr Ture H o Annie\nBergman. - Barn: Björn f 50, Annika f 54.\n",
    "structured": {
        "1": {
            "full_name": "OLLING, CARL-HENRIK S O",
            "location": "Sthlm",
            "occupation": "assuransdirektör",
            "birth_details": {
                "date": "31/07/1911",
                "place": "Sura, Västmanl"
            },
            "education": [
                {
                    "degree": "Stud:ex",
                    "year": "1930",
                    "institution": null
                },
                {
                    "degree": "jur kand",
                    "year": "1934",
                    "institution": null
                },
                {
                    "degree": "DHS",
                    "year": "1939",
                    "institution": null
                }
            ],
            "career": [
                {
                    "position": "dispaschörskomp",
                    "years": {
                        "start_year": 1943,
                        "end_year": null
                    },
                    "organization": "internat Siporex ab Sthlm"
                },
                {
                    "position": "adv :firma",
                    "years": {
                        "start_year": 1936,
                        "end_year": 1937
                    },
                    "organization": "Reyn-holds, Sons & Gorst o Sv hdlskamm London"
                },
                {
                    "position": "bitr avd:ch stat krigs-försäkr:nd",
                    "years": {
                        "start_year": 1940,
                        "end_year": null
                    },
                    "organization": "Hansa"
                },
                {
                    "position": "bitr dir",
                    "years": {
                        "start_year": 1957,
                        "end_year": null
                    },
                    "organization": "Hansa"
                }
            ],
            "family": {
                "spouse": "Eva Åsell",
                "marriage_year": "1951",
                "children": []
            }
        },
        "2": {
            "full_name": "OLOFGÖRS, H GUNNAR H",
            "location": "Bromma",
            "occupation": "civilingenjör",
            "birth_details": {
                "date": "01/09/1926",
                "place": "Kristineh"
            },
            "education": [
                {
                    "degree": "KTH",
                    "year": "1949",
                    "institution": null
                },
                {
                    "degree": "fil kand",
                    "year": "1951",
                    "institution": null
                }
            ],
            "career": [
                {
                    "position": "verkst dir",
                    "years": {
                        "start_year": 1958,
                        "end_year": null
                    },
                    "organization": "Byggn :ind :f örb"
                }
            ],
            "family": {
                "spouse": "Barbro Ståhl",
                "marriage_year": "1952",
                "children": [
                    {
                        "name": "Mats",
                        "birth_year": "1954"
                    },
                    {
                        "name": "Lena",
                        "birth_year": "1957"
                    }
                ]
            }
        },
        "3": {
            "full_name": "OLOFSSON, J EGON",
            "location": "Bromma",
            "occupation": "ingenjör",
            "birth_details": {
                "date": "01/07/1902",
                "place": "Östersund"
            },
            "education": [
                {
                    "degree": "CTI",
                    "year": "1924",
                    "institution": null
                }
            ],
            "career": [
                {
                    "position": "anst General Motors Nord ab Sthlm",
                    "years": {
                        "start_year": 1928,
                        "end_year": null
                    },
                    "organization": null
                }
            ],
            "family": {
                "spouse": "Esther Wahlqvist",
                "marriage_year": "1931",
                "children": [
                    {
                        "name": "Lena",
                        "birth_year": "1932"
                    },
                    {
                        "name": "Kerstin",
                        "birth_year": "1937"
                    }
                ]
            }
        },
        "4": {
            "full_name": "OLOFSSON, GUNNAR E",
            "location": "Bandhagen",
            "occupation": "tf byråchef",
            "birth_details": {
                "date": "27/12/1920",
                "place": "Sthlm"
            },
            "education": [
                {
                    "degree": "jur kand",
                    "year": "1945",
                    "institution": null
                }
            ],
            "career": [
                {
                    "position": "tf byråch",
                    "years": {
                        "start_year": 1960,
                        "end_year": null
                    },
                    "organization": null
                }
            ],
            "family": {
                "spouse": "Britt Hedman",
                "marriage_year": "1947",
                "children": [
                    {
                        "name": "Björn",
                        "birth_year": "1950"
                    },
                    {
                        "name": "Annika",
                        "birth_year": "1954"
                    }
                ]
            },
            "hobbies": [
                "bridge"
            ]
        }
    }
}