{
    "original": "ODMARK, P FOLKE S,\nförsäkrings-direktör, Sthlm, f i Lidingö 21/1/00\nav trädgårdsmäst Fredrik Andersson\no Alma Helander.\n\nStud:ex 18, anst Folksam 23, kontorsch\n47, dir sed 55. - Stadsfullm Lidingö\n39-50, ordf nykterh:ndn, led\ndrätsel-kamm 48-51, kyrkofullm o\nkyrkorådsled 34.\n\nGift 27 m Gerda Håkansson f 00, dtr\nt missionsskollär Josef H o Anna\nNilsson. - Barn: Per f 28, Brita f 31,\nTorsten f 34, Göran f 34.\n\nODQVIST, DAGMAR, förste\nbibliotekarie, Sthlm, f i Sthlm 23/12/01 av\nreg:läk Karl O o Inez Wåhlén.\nStud:ex 21, fil kand Upps 26, fil lic\nSthlm 39. - Elevtjg Vasa förs:bibi,\nKTH:s bibl o Konstakad:s bibl 26-28,\nass KTH:s bibl 28, aman 30, bibl 46,\nl:e bibl sed 47. - Sekr o kassaförvalt\nTekn litt:sällsk 37-45, styr:led Sv\nbibk-samf 52, medl Sällsk Nya Idun. - Skr:\nupps i bi bl :tekn ämnen i ol tidskr.\n-Hobby: musik.\n\nODQVIST, FOLKE K G, professor,\nDjursholm, f i Sthlm 29/7/99 av reg:läk\nKarl O o Inez Wåhlén.\n\nKTH 22, fil lic 25, fil dr 28,\nSv:e-Amer-stift stip 25-26, l:e ass KTH\n22-24, ing :verksamh Sthlm (Electrolux,\nNomy), 26-36, doc teknisk mekanik KTH\n31, prof hålilfasthetslära KTH 36,\nprorektor 43, stud :kårens insp 42-50,\nstyr:-led stat provn:anst 47, dess ordf sed\n55, presid Internat unionen f mekanik\n56-60, led Sv nät komm mek 50, ordf\nsed 58. - LIVA 41, LVA 57. - Skr:\ndiv upps o art IVA :s handl, i Tekn\ntidskr, VA :s Arkiv f matem astronomi\no fysik, utl facktidskr m m,\nPlasticitets-teori m tillämpn (34), Hållfasthetslära\n(48), Kriechfestigheit (tills m J Hult\n62). - Utm: KNO. - Hobby: segling.\nGift 26 m Vera Traugott f 04, dtr t\ndir Oscar T o Cecilie Salomon. - Barn:\nAnn-Marie f 28, Kerstin f 28, Eva\nf 31, Sven f 43.\n\n",
    "structured": {
        "1": {
            "full_name": "ODMARK, P FOLKE S",
            "location": "Sthlm",
            "occupation": "försäkrings-direktör",
            "birth_details": {
                "date": "21/01/1900",
                "place": "Lidingö",
                "parents": "trädgårdsmäst Fredrik Andersson o Alma Helander"
            },
            "education": [
                {
                    "degree": "Stud:ex",
                    "year": "1918",
                    "institution": "NULL"
                }
            ],
            "career": [
                {
                    "position": "anst Folksam",
                    "years": {
                        "start_year": 1923,
                        "end_year": 1947
                    },
                    "organization": "NULL"
                },
                {
                    "position": "kontorsch",
                    "years": {
                        "start_year": 1947,
                        "end_year": 1955
                    },
                    "organization": "NULL"
                }
            ],
            "family": {
                "spouse": "Gerda Håkansson",
                "marriage_year": "1927",
                "children": [
                    {
                        "name": "Per",
                        "birth_year": "1928"
                    },
                    {
                        "name": "Brita",
                        "birth_year": "1931"
                    },
                    {
                        "name": "Torsten",
                        "birth_year": "1934"
                    },
                    {
                        "name": "Göran",
                        "birth_year": "1934"
                    }
                ]
            }
        },
        "2": {
            "full_name": "ODQVIST, DAGMAR",
            "location": "Sthlm",
            "occupation": "förste bibliotekarie",
            "birth_details": {
                "date": "23/12/1901",
                "place": "Sthlm",
                "parents": "reg:läk Karl O o Inez Wåhlén"
            },
            "education": [
                {
                    "degree": "Stud:ex",
                    "year": "1921",
                    "institution": "NULL"
                },
                {
                    "degree": "fil kand",
                    "year": "1926",
                    "institution": "Upps"
                },
                {
                    "degree": "fil lic",
                    "year": "1939",
                    "institution": "Sthlm"
                }
            ],
            "career": [
                {
                    "position": "amam",
                    "years": {
                        "start_year": 1930,
                        "end_year": "NULL"
                    },
                    "organization": "NULL"
                },
                {
                    "position": "bibl",
                    "years": {
                        "start_year": "1946",
                        "end_year": "NULL"
                    },
                    "organization": "NULL"
                }
            ],
            "family": {
                "spouse": "NULL",
                "marriage_year": "NULL",
                "children": []
            },
            "hobbies": [
                "musik"
            ]
        },
        "3": {
            "full_name": "ODQVIST, FOLKE K G",
            "location": "Djursholm",
            "occupation": "professor",
            "birth_details": {
                "date": "29/07/1899",
                "place": "Sthlm",
                "parents": "reg:läk Karl O o Inez Wåhlén"
            },
            "education": [
                {
                    "degree": "KTH",
                    "year": "1922",
                    "institution": "NULL"
                },
                {
                    "degree": "fil lic",
                    "year": "1925",
                    "institution": "NULL"
                },
                {
                    "degree": "fil dr",
                    "year": "1928",
                    "institution": "NULL"
                }
            ],
            "career": [
                {
                    "position": "ing :verksamh",
                    "years": {
                        "start_year": 1926,
                        "end_year": 1936
                    },
                    "organization": "Sthlm (Electrolux, Nomy)"
                },
                {
                    "position": "doc teknisk mekanik",
                    "years": {
                        "start_year": 1931,
                        "end_year": "NULL"
                    },
                    "organization": "KTH"
                }
            ],
            "family": {
                "spouse": "Vera Traugott",
                "marriage_year": "1926",
                "children": [
                    {
                        "name": "Ann-Marie",
                        "birth_year": "1928"
                    },
                    {
                        "name": "Kerstin",
                        "birth_year": "1928"
                    },
                    {
                        "name": "Eva",
                        "birth_year": "1931"
                    },
                    {
                        "name": "Sven",
                        "birth_year": "1943"
                    }
                ]
            },
            "hobbies": [
                "segling"
            ]
        }
    }
}