{
    "original": "Lindell, Gilbert Oscar Wilhelm,\ntandläkare, Amål, f. 2/7/05 i\nMinneapolis, USA, av fabr. Johan L. o. Hanna\nRåhlin. G. 33 m. Brita Falk. Barn:\nPer-Oiof f. 35, Birgitta 38, Gunilla 39,\nEva 43, Karin 45. — Studrex. v.\nVänersborgs h. allm. lärov. 25, tandl\n:-kand. 30, tandl. 33. Frakt, i Amål sed.\n33, skoltandl. 36-45. Hobbies: segling\n. o. fotografering.\n\nLindell, Harald, landskamrerare,\nVisby, f. 1/2/93 i Norrköping av\ncivil-ing. August L. o. Alice Nordström. G.\n21 m. Ingrid Johnzon. Barn: Göran\nH:son f. 23, arkit. SAR. — Jur. kand.\ni Upps. 19. Andre länsbokh. i Värml.\nlän 22, förste dito 29, länsassessor i\nKopparb. län 36, landskamr. i Gotl.\nlän sed. 42. Innehade olika kommun,\nuppdrag i Karlstad, v. ordf. i direkt,\nf. S :t Olofs sjukh. o. Gotl. läns\nkristidsstyr. 43’, ordf. i styr. f.\nRiksbankens avd:kont. i Visby 47. RNO.\n\nLindell, Karl Fredrik, direktör,\nGöteborg, f. 8/8/91 i Gbg av organisten\nL P. L. o. Aurora Lindell. G. 31 m.\nKarin Bernt&amp;son. Barn:\nCarl-Magnus f. 32, Anita 34, Margareta 36. —\nAvg:ex. fr. Gbgs hand:inst. 10, stud.\nv. Gbgs hand :högsk :kurser 15-20.\nAn-st. i Älvsb. m. fl. läns hypoteksfören.\nsed. 10, bokhåll. 12, aman. 19, tf.\nom’b:-man 20, v. omb :man 24, förste\nomb:-man 26, kamr. 30, verkst. dir. o. förste\nomb :man sed. 33. Led. av styr. f.\nÄlvsb. m. fl. läns hypoteksfören. sed.\n37, rev. i De bHndas fören. Hoppet\n19-24, led. av ’Styr. f. samma fören.\n25-30, hed:led. där sed. 31, Sv.\nbo-stadskreditkassans omb. i styr. f. Gbgs\nbostadskreditfören. o. Gbgs o. Boh.\n\n1. bostadskreditfören. 47. RVO,\nPro-PatrstGM.\n\nLindell, Nils Gustaf Magnus,\nkyrkoherde, Rävemåla, f. 17/9/04 i Örsjö,\nKalmar 1., av kyrkoh. Axel L. o.\nHerta Engström. G. 32 m.\nskolköks-lär :an Carin Wångdahl. Barn:\nMonika f. 33, Kerstin 36, Ingegerd 40,\nBarbro 43. — Stud:ex. i Kalmar 23,\nfil. ämb :ex. i Lund 26, teol. kand.\nsamt prakt. teol. prov 28, prästv. f.\nVäxjö stift 29. Tjg. som v. pastor i\nVickleby, past :adj. o. v. pastor i\nVax-ho’lm, pred. v. Sthlms - läns sjukhem i\nVaxholm, kommin. i örsjö, kyrkoh.\ni Älmeboda sed. 39. Ombud f. Sv.\nkyrkans miss :styr. i Konga kontr. E.\no. ämneslär. v. Vaxholms komm.\nmel-lansk. o. samrealsk, 29-32, insp. f.\nEmmaboda samrealsk. sed. 46.\n\n",
    "structured": {
        "1": {
            "full_name": "Gilbert Oscar Wilhelm Lindell",
            "location": "Amål",
            "occupation": "tandläkare",
            "birth_details": {
                "date": "02/07/1905",
                "place": "Minneapolis, USA"
            },
            "education": [
                {
                    "degree": "Studrex.",
                    "year": "1925",
                    "institution": "Vänersborgs h. allm. lärov."
                },
                {
                    "degree": "tandl:-kand.",
                    "year": "1930",
                    "institution": "NULL"
                },
                {
                    "degree": "tandl.",
                    "year": "1933",
                    "institution": "NULL"
                }
            ],
            "career": [
                {
                    "position": "Frakt, i Amål",
                    "years": {
                        "start_year": 1933,
                        "end_year": 1933
                    },
                    "organization": "NULL"
                },
                {
                    "position": "skoltandl.",
                    "years": {
                        "start_year": 1936,
                        "end_year": 1945
                    },
                    "organization": "NULL"
                }
            ],
            "family": {
                "spouse": "Brita Falk",
                "marriage_year": "1933",
                "children": [
                    {
                        "name": "Per-Oiof",
                        "birth_year": "1935"
                    },
                    {
                        "name": "Birgitta",
                        "birth_year": "1938"
                    },
                    {
                        "name": "Gunilla",
                        "birth_year": "1939"
                    },
                    {
                        "name": "Eva",
                        "birth_year": "1943"
                    },
                    {
                        "name": "Karin",
                        "birth_year": "1945"
                    }
                ]
            },
            "hobbies": [
                "segling",
                "fotografering"
            ]
        },
        "2": {
            "full_name": "Harald Lindell",
            "location": "Visby",
            "occupation": "landskamrerare",
            "birth_details": {
                "date": "01/02/1893",
                "place": "Norrköping"
            },
            "education": [
                {
                    "degree": "Jur. kand.",
                    "year": "1919",
                    "institution": "Upps."
                }
            ],
            "career": [
                {
                    "position": "Andre länsbokh.",
                    "years": {
                        "start_year": 1922,
                        "end_year": 1929
                    },
                    "organization": "Värml. län"
                },
                {
                    "position": "förste dito",
                    "years": {
                        "start_year": 1929,
                        "end_year": 1936
                    },
                    "organization": "NULL"
                },
                {
                    "position": "länsassessor",
                    "years": {
                        "start_year": 1936,
                        "end_year": 1942
                    },
                    "organization": "Kopparb. län"
                },
                {
                    "position": "landskamr.",
                    "years": {
                        "start_year": 1942,
                        "end_year": 1947
                    },
                    "organization": "Gotl. län"
                }
            ],
            "family": {
                "spouse": "Ingrid Johnzon",
                "marriage_year": "1921",
                "children": [
                    {
                        "name": "Göran H:son",
                        "birth_year": "1923"
                    }
                ]
            },
            "honorary_titles": [
                {
                    "title": "RNO"
                }
            ]
        },
        "3": {
            "full_name": "Karl Fredrik Lindell",
            "location": "Göteborg",
            "occupation": "direktör",
            "birth_details": {
                "date": "08/08/1891",
                "place": "Gbg"
            },
            "education": [
                {
                    "degree": "Avg:ex. fr. Gbgs hand:inst.",
                    "year": "1910",
                    "institution": "NULL"
                },
                {
                    "degree": "stud. v. Gbgs hand :högsk :kurser",
                    "year": "1915-1920",
                    "institution": "NULL"
                }
            ],
            "career": [
                {
                    "position": "An-st. i Älvsb. m. fl. läns hypoteksfören.",
                    "years": {
                        "start_year": 1910,
                        "end_year": 1910
                    },
                    "organization": "NULL"
                },
                {
                    "position": "bokhåll.",
                    "years": {
                        "start_year": 1912,
                        "end_year": 1912
                    },
                    "organization": "NULL"
                },
                {
                    "position": "aman.",
                    "years": {
                        "start_year": 1919,
                        "end_year": 1919
                    },
                    "organization": "NULL"
                },
                {
                    "position": "tf. om’b:-man",
                    "years": {
                        "start_year": 1920,
                        "end_year": 1920
                    },
                    "organization": "NULL"
                },
                {
                    "position": "v. omb :man",
                    "years": {
                        "start_year": 1924,
                        "end_year": 1924
                    },
                    "organization": "NULL"
                },
                {
                    "position": "förste omb:-man",
                    "years": {
                        "start_year": 1926,
                        "end_year": 1926
                    },
                    "organization": "NULL"
                },
                {
                    "position": "kamr.",
                    "years": {
                        "start_year": 1930,
                        "end_year": 1930
                    },
                    "organization": "NULL"
                },
                {
                    "position": "verkst. dir. o. förste omb :man",
                    "years": {
                        "start_year": 1933,
                        "end_year": 1933
                    },
                    "organization": "NULL"
                }
            ],
            "family": {
                "spouse": "Karin Bernt&amp;son",
                "marriage_year": "1931",
                "children": [
                    {
                        "name": "Carl-Magnus",
                        "birth_year": "1932"
                    },
                    {
                        "name": "Anita",
                        "birth_year": "1934"
                    },
                    {
                        "name": "Margareta",
                        "birth_year": "1936"
                    }
                ]
            },
            "honorary_titles": [
                {
                    "title": "RVO"
                },
                {
                    "title": "Pro-PatrstGM"
                }
            ]
        },
        "4": {
            "full_name": "Nils Gustaf Magnus Lindell",
            "location": "Rävemåla",
            "occupation": "kyrkoherde",
            "birth_details": {
                "date": "17/09/1904",
                "place": "Örsjö, Kalmar 1."
            },
            "education": [
                {
                    "degree": "Stud:ex. i Kalmar",
                    "year": "1923",
                    "institution": "NULL"
                },
                {
                    "degree": "fil. ämb :ex. i Lund",
                    "year": "1926",
                    "institution": "NULL"
                },
                {
                    "degree": "teol. kand.",
                    "year": "1928",
                    "institution": "NULL"
                }
            ],
            "career": [
                {
                    "position": "Tjg. som v. pastor i Vickleby",
                    "years": {
                        "start_year": 1929,
                        "end_year": 1929
                    },
                    "organization": "NULL"
                },
                {
                    "position": "past :adj. o. v. pastor i Vax-ho’lm",
                    "years": {
                        "start_year": "NULL",
                        "end_year": "NULL"
                    },
                    "organization": "NULL"
                },
                {
                    "position": "pred. v. Sthlms - läns sjukhem i Vaxholm",
                    "years": {
                        "start_year": "NULL",
                        "end_year": "NULL"
                    },
                    "organization": "NULL"
                },
                {
                    "position": "kommin. i örsjö",
                    "years": {
                        "start_year": "NULL",
                        "end_year": "NULL"
                    },
                    "organization": "NULL"
                },
                {
                    "position": "kyrkoh.",
                    "years": {
                        "start_year": 1939,
                        "end_year": 1939
                    },
                    "organization": "Älmeboda"
                },
                {
                    "position": "Ombud f. Sv. kyrkans miss :styr. i Konga kontr.",
                    "years": {
                        "start_year": "NULL",
                        "end_year": "NULL"
                    },
                    "organization": "NULL"
                }
            ],
            "family": {
                "spouse": "Carin Wångdahl",
                "marriage_year": "1932",
                "children": [
                    {
                        "name": "Monika",
                        "birth_year": "1933"
                    },
                    {
                        "name": "Kerstin",
                        "birth_year": "1936"
                    },
                    {
                        "name": "Ingegerd",
                        "birth_year": "1940"
                    },
                    {
                        "name": "Barbro",
                        "birth_year": "1943"
                    }
                ]
            }
        }
    }
}