{
    "original": "Lindgren, Olof August,\ntelegraf-kommissarie, Växjö, f. 28/2/86 i\nNämdö, Sthlms 1., av kommin. Oskar\nL. o. Elisabet Hadders. G. 17 m.\nAnna Vidén. Barn: Greta f. 22, Caisa\n25. — Stud:ex. 06, telegr:kurs s. å.\nTelegr :komm. i Växjö fr. 42. Utg. av\nKronob. 1. tel :katalog.\n\nLindgren, Carl Olof, advokat,\nTen-hult, f. 22/2/08 å Visingsö, Jönköp. 1.,\nav kronojäg. Carl L. o. Emma\nStrö-berg. G. 37 m. Vera Adelsköld. Barn:\nMarianne f. 39. Göran 41, Håkan o.\nKarin 43. — Stud:ex. i Jönköp. 27,\njur. kand. i Upps. 33. Tingstjg. i\nVar-tofta o. Frökinds doms. 33-36, aman.\no. tf. vattenrättssekr. v. Västerbygd.\nvattendomst. 36-38, ans’t. å Axel FaM-\n\nströms adv:kont. i Jönköp. 38, deläg.\nsed. 42. Led. av Sv:es adv:samf. sed.\n40.\n\nLindgren, Oscar Emanuel,\nstadsveterinär, Karlshamn, f. 2/11/85 i\nJämshög, Blek. L, av grosshandl. Elof L.\no. Ulrika Hultstein. G. 27 m. Svea\nWallander. Barn: Ulrika f. 28,\nElisabeth 33. — Mog:ex. i Kristianstad 05,\nvet:ex. 11. Besiktn:vet. i Gbg 12-15,\ndito i Karlshamn sed. 15, stadsvet. där\nsed. 17, besiktn :vet. v. kontrollslakt,\nnr 104 i Mörruni sed. 27, besiktn :vet,\nv. Mörrums köttbesiktn :byrå sed. 31.\nLed. av Karlshamns hälsov:nd sed. 21.\n, ’’Lindgren, Bror Ossian Gaetano.\nriksbanksdirektör, Växjö, f. 31/7/83 i\nSkön, Västernorrl. 1, av insp. J. T. L.\n\n0.\tMarie Loui’se Flodberg. G. m.\nVi-van Hjelm. — Stud:ex. 03. Anst. i\nriksb. i Umeå 03, ord. bokh. i Luleå\n11, registr. i Växjö 14, förste bokh.\ni Kalm. 18, kassör i Umeå 21, kamr.\ni Växjö 27, i Norrköp. 36, dir. i Växjö\nsed. 40. Siffergransk. v. Småi. Ensk.\nBank i Kaim. 19-21, skattm. v. Umeå\nelem:lärov. f. fl. 23-27, sekr. i Västerb.\n\n1.\tsinnes-slöanst. 26-27, stat. rev. h.\nKronob. 1. hush :sällsk. egnah :nd\n31-36, 11. Kronob. 1. hush :’sällsk. 33-36,\nordf. i tax:ndn i ett par ilandskomm.\n33-34, led. av styr. f. Riksbankstj :m.\nfören. 30-42, v. ordf. 39-42. Hobby:\nornitologi. RVO.\n\n",
    "structured": {
        "0": {
            "full_name": "Lindgren, Olof August",
            "location": "Växjö",
            "occupation": "Telegraf-kommissarie",
            "birth_details": {
                "date": "28/02/1886",
                "place": "Nämdö, Sthlms 1",
                "parents": "kommin. Oskar L. o. Elisabet Hadders"
            },
            "education": [
                {
                    "degree": "Stud:ex.",
                    "year": "1906",
                    "institution": "NULL"
                },
                {
                    "degree": "Telegr:kurs",
                    "year": "s.å.",
                    "institution": "NULL"
                }
            ],
            "career": [
                {
                    "position": "Telegr :komm.",
                    "years": {
                        "start_year": 1942,
                        "end_year": "NULL"
                    },
                    "organization": "Växjö"
                }
            ],
            "family": {
                "spouse": "Anna Vidén",
                "marriage_year": "17 m.",
                "children": [
                    {
                        "name": "Greta",
                        "birth_year": "1922"
                    },
                    {
                        "name": "Caisa",
                        "birth_year": "1925"
                    }
                ]
            }
        },
        "1": {
            "full_name": "Lindgren, Carl Olof",
            "location": "Ten-hult",
            "occupation": "Advokat",
            "birth_details": {
                "date": "22/02/1908",
                "place": "Visingsö, Jönköp. 1",
                "parents": "kronojäg. Carl L. o. Emma Strömberg"
            },
            "education": [
                {
                    "degree": "Stud:ex.",
                    "year": "1927",
                    "institution": "Jönköp."
                },
                {
                    "degree": "Jur. kand.",
                    "year": "1933",
                    "institution": "Upps."
                }
            ],
            "career": [
                {
                    "position": "Tingstjg.",
                    "years": {
                        "start_year": 1933,
                        "end_year": 1936
                    },
                    "organization": "Vartofta o. Frökinds doms."
                },
                {
                    "position": "Aman. o. tf. vattenrättssekr.",
                    "years": {
                        "start_year": 1933,
                        "end_year": 1936
                    },
                    "organization": "Västerbygd. vattendomst."
                },
                {
                    "position": "Ans't. å Axel FaMströms adv:kont.",
                    "years": {
                        "start_year": 1938,
                        "end_year": "NULL"
                    },
                    "organization": "Jönköp."
                }
            ],
            "family": {
                "spouse": "Vera Adelsköld",
                "marriage_year": "37 m.",
                "children": [
                    {
                        "name": "Marianne",
                        "birth_year": "1939"
                    },
                    {
                        "name": "Göran",
                        "birth_year": "1941"
                    },
                    {
                        "name": "Håkan",
                        "birth_year": "1943"
                    },
                    {
                        "name": "Karin",
                        "birth_year": "1943"
                    }
                ]
            }
        },
        "2": {
            "full_name": "Lindgren, Oscar Emanuel",
            "location": "Karlshamn",
            "occupation": "Stadsveterinär",
            "birth_details": {
                "date": "2/11/1885",
                "place": "Jämshög, Blek. L",
                "parents": "grosshandl. Elof L. o. Ulrika Hultstein"
            },
            "education": [
                {
                    "degree": "Mog:ex.",
                    "year": "1905",
                    "institution": "Kristianstad"
                },
                {
                    "degree": "Vet:ex.",
                    "year": "1911",
                    "institution": "NULL"
                }
            ],
            "career": [
                {
                    "position": "Besiktn:vet.",
                    "years": {
                        "start_year": 1912,
                        "end_year": 1915
                    },
                    "organization": "Gbg"
                },
                {
                    "position": "Dito",
                    "years": {
                        "start_year": "NULL",
                        "end_year": "NULL"
                    },
                    "organization": "NULL"
                },
                {
                    "position": "Stadsvet.",
                    "years": {
                        "start_year": 1917,
                        "end_year": "NULL"
                    },
                    "organization": "Karlshamn"
                },
                {
                    "position": "Besiktn :vet.",
                    "years": {
                        "start_year": "NULL",
                        "end_year": "NULL"
                    },
                    "organization": "kontrollslakt, nr 104 i Mörruni"
                },
                {
                    "position": "Besiktn :vet.",
                    "years": {
                        "start_year": "NULL",
                        "end_year": "NULL"
                    },
                    "organization": "Mörrums köttbesiktn :byrå"
                }
            ],
            "family": {
                "spouse": "Svea Wallander",
                "marriage_year": "27 m.",
                "children": [
                    {
                        "name": "Ulrika",
                        "birth_year": "1928"
                    },
                    {
                        "name": "Elisabeth",
                        "birth_year": "1933"
                    }
                ]
            }
        },
        "3": {
            "full_name": "Lindgren, Bror Ossian Gaetano",
            "location": "Växjö",
            "occupation": "Riksbanksdirektör",
            "birth_details": {
                "date": "31/07/1883",
                "place": "Skön, Västernorrl. 1",
                "parents": "insp. J. T. L. 0. Marie Loui'se Flodberg"
            },
            "education": [
                {
                    "degree": "Stud:ex.",
                    "year": "1903",
                    "institution": "NULL"
                }
            ],
            "career": [
                {
                    "position": "Anst. i riksb.",
                    "years": {
                        "start_year": 1903,
                        "end_year": "NULL"
                    },
                    "organization": "Umeå"
                },
                {
                    "position": "Ord. bokh.",
                    "years": {
                        "start_year": 1911,
                        "end_year": "NULL"
                    },
                    "organization": "Luleå"
                },
                {
                    "position": "Registr.",
                    "years": {
                        "start_year": 1914,
                        "end_year": "NULL"
                    },
                    "organization": "Växjö"
                },
                {
                    "position": "Förste bokh.",
                    "years": {
                        "start_year": 1918,
                        "end_year": "NULL"
                    },
                    "organization": "Kalm."
                },
                {
                    "position": "Kassör",
                    "years": {
                        "start_year": 1927,
                        "end_year": "NULL"
                    },
                    "organization": "Umeå"
                },
                {
                    "position": "Kamr.",
                    "years": {
                        "start_year": 1936,
                        "end_year": "NULL"
                    },
                    "organization": "Norrköp."
                },
                {
                    "position": "Dir.",
                    "years": {
                        "start_year": "1940",
                        "end_year": "NULL"
                    },
                    "organization": "Växjö"
                }
            ],
            "family": {
                "spouse": "Vivan Hjelm",
                "marriage_year": "NULL",
                "children": "NULL"
            },
            "hobbies": [
                "ornitologi"
            ],
            "honorary_titles": [
                {
                    "title": "RVO",
                    "institution": "NULL",
                    "year": "NULL"
                }
            ]
        }
    }
}