{
    "original": "Ljungberg, Carl-Johan, prost,\nAlingsås, f. 28/1/91 i Visby av\nskolfö-rest. O. N. Ljungberg o. Emma\nSegerdahl. G. 21 m. Greta Söderström.\nBarn: Maj f. 27. ~ Stud:ex. i Visby\n10, teol. kand. i Upps., prakt. teol.\nprov samt prästv. i Skara 14.\nKommin. i Liared 17, kyrkoh. i Norra\nFå-gelås 23, i Hova 28, kontr :prost 31,\nprost o. kyrkoh. i Alingsås sed. 40.\nInsp. f. samreadsk. i Alingsås sed. 44.\nLNO.\n\nLjungberg, Gunnar Åke David,\ncivilingenjör, Alingsås, f. 13/2/09 i\nJönköp. av ing. David L. o. Hanna\nPettersson. G. 38 m. Margit Persson.\nBarn: Per f. 40. — Stud:ex. i\nJönköp. 28, utex. fr. CTI (E) 32.\nPraktik v. Jönk. mekaniska verkstad,\nElektr. A-B Sivers &amp; Häger i Jönköp.\nsamt Jönköp. gasverk, anst. v. Borås\nstads elverk 35-36, v. Yngeredsfors\nKraft A-B i Mölndal 36-37, chef v.\nAlingsås stads gas- o. elverk sed. 38.\n\nLjungberg, Gösta Olof, andre\nstadsläkare, Trollhättan, f. 13/2/04 i\nKristianstad av P. O. L. o. Emma Maria\nPersson. G. 34 m. Ingrid Knaust.\nBarn: Ulla f. 35, Jan 37, Per 40, Lars\n42. — Stud:ex. i Kristianstad 23, med.\nkand. i Lund 27, med. lic. i Sthlm 33.\nE. o. aman. v. Seraf :las. med. poliklin.\n29, v. nervklin. där 32 samt v.\nnerv-poiiklin. å., assis,t:läk. v. Kronpr.\nLovisas vårdanst. 33, vik. andre\nund:-läk. v. Seraf :las. med. klin. 34, andre\nund:iläk. o. Regneils aman, där 35-37,\nförordn. som prov :’läk. samt kort.\ntjg. v. Söderby sjukh., Sthlms\nepid:-sjukh. o. Seraf :las. öronpoliklin.\n37-38, assist :läk. v. Gbgs barnsjukh. 38,\nandre und :iäk. v. Svenshögens sanat.\n38-39, därefter prakt. läk. i\nTrollhättan, andre stadsläk. samt läk. v.\nbar-nav:centr. där.\n\n^Ljungberg, Johan Leonard,\ndirektör, Ulricehamn, f. 20/1/81 i Falsterbo\nav Johan L. o. Kristina Jeppsson. G. 05\nm. Hedvig Nord. Barn: Ingrid f. 12. —\nKöpm. i Blidsberg 05-19, disp. v.\nUlricehamns Yllefabr. A-B o. nu dir. f.\nföret. Led. av stadsfullm., fattigv :styr.\no. skolråd fr. 22, landstingsman fr. 27,\n\nled. av förviutsk. fr. 31, ordf. i\nlo-kal-styr. f. Borås Bank. Tildh. Sv. miss\nförb. fr. 98, styr :led. i Blidsbergs\nmiss :förs., ordf. i ungdifören. 05-19,\nordf. i Ätradalens ungd:förb. 07-24, i\nUlricehamns miss :förs. fr. 24,\nstyr:-led. i Sv. miss :förb. fr. 36, i Västergötl.\nmiss :fören. o. dess ungd:förb. RVO.\n\n",
    "structured": {
        "1": {
            "full_name": "Ljungberg, Carl-Johan",
            "location": "Alingsås",
            "occupation": "prost",
            "birth_details": {
                "date": "28/01/1891",
                "place": "Visby",
                "parents": "O. N. Ljungberg and Emma Segerdahl"
            },
            "education": [
                {
                    "degree": "Stud:ex.",
                    "year": "1910",
                    "institution": "Visby"
                },
                {
                    "degree": "teol. kand.",
                    "year": "Upps.",
                    "institution": "prakt. teol. prov samt prästv."
                }
            ],
            "career": [
                {
                    "position": "Kommin.",
                    "years": {
                        "start_year": 1917,
                        "end_year": 1917
                    },
                    "organization": "Liared"
                },
                {
                    "position": "kyrkoh.",
                    "years": {
                        "start_year": 1923,
                        "end_year": 1923
                    },
                    "organization": "Norra Få-gelås"
                },
                {
                    "position": "kyrkoh.",
                    "years": {
                        "start_year": 1928,
                        "end_year": 1928
                    },
                    "organization": "Hova"
                },
                {
                    "position": "kontr :prost",
                    "years": {
                        "start_year": 1931,
                        "end_year": 1931
                    },
                    "organization": "Alingsås"
                },
                {
                    "position": "prost",
                    "years": {
                        "start_year": 1940,
                        "end_year": null
                    },
                    "organization": "Alingsås"
                }
            ],
            "family": {
                "spouse": "Greta Söderström",
                "marriage_year": "1921",
                "children": [
                    {
                        "name": "Maj",
                        "birth_year": "1927"
                    }
                ]
            }
        },
        "2": {
            "full_name": "Ljungberg, Gunnar Åke David",
            "location": "Alingsås",
            "occupation": "civilingenjör",
            "birth_details": {
                "date": "13/02/1909",
                "place": "Jönköp"
            },
            "education": [
                {
                    "degree": "Stud:ex.",
                    "year": "1928",
                    "institution": "Jönköp."
                },
                {
                    "degree": "utex. fr. CTI (E)",
                    "year": "1932",
                    "institution": null
                }
            ],
            "career": [
                {
                    "position": null,
                    "years": {
                        "start_year": 1935,
                        "end_year": 1936
                    },
                    "organization": "Borås stads elverk"
                },
                {
                    "position": "chef",
                    "years": {
                        "start_year": 1938,
                        "end_year": null
                    },
                    "organization": "Alingsås stads gas- o. elverk"
                }
            ],
            "family": {
                "spouse": "Margit Persson",
                "marriage_year": "1938",
                "children": [
                    {
                        "name": "Per",
                        "birth_year": "1940"
                    }
                ]
            }
        },
        "3": {
            "full_name": "Ljungberg, Gösta Olof",
            "location": "Trollhättan",
            "occupation": "andre stadsläkare",
            "birth_details": {
                "date": "13/02/1904",
                "place": "Kristianstad",
                "parents": "P. O. L. and Emma Maria Persson"
            },
            "education": [
                {
                    "degree": "Stud:ex.",
                    "year": "1923",
                    "institution": "Kristianstad"
                },
                {
                    "degree": "med. kand.",
                    "year": "Lund",
                    "institution": "Seraf :las."
                },
                {
                    "degree": "med. lic.",
                    "year": "Sthlm",
                    "institution": null
                }
            ],
            "career": [
                {
                    "position": null,
                    "years": {
                        "start_year": 1938,
                        "end_year": 1939
                    },
                    "organization": "Svenshögens sanat."
                }
            ],
            "family": {
                "spouse": "Ingrid Knaust",
                "marriage_year": "1934",
                "children": [
                    {
                        "name": "Ulla",
                        "birth_year": "1935"
                    },
                    {
                        "name": "Jan",
                        "birth_year": "1937"
                    },
                    {
                        "name": "Per",
                        "birth_year": "1940"
                    },
                    {
                        "name": "Lars",
                        "birth_year": "1942"
                    }
                ]
            }
        },
        "4": {
            "full_name": "Ljungberg, Johan Leonard",
            "location": "Ulricehamn",
            "occupation": "direktör",
            "birth_details": {
                "date": "20/01/1881",
                "place": "Falsterbo",
                "parents": "Johan L. and Kristina Jeppsson"
            },
            "education": null,
            "career": [
                {
                    "position": "Köpm.",
                    "years": {
                        "start_year": 1905,
                        "end_year": 1919
                    },
                    "organization": "Blidsberg"
                },
                {
                    "position": "disp. v.",
                    "years": {
                        "start_year": null,
                        "end_year": null
                    },
                    "organization": "Ulricehamns Yllefabr. A-B o. nu dir. f. föret."
                }
            ],
            "family": {
                "spouse": "Hedvig Nord",
                "marriage_year": "1905",
                "children": [
                    {
                        "name": "Ingrid",
                        "birth_year": "1912"
                    }
                ]
            }
        }
    }
}