{
    "original": "Liljeros, Bror Gustaf Adolf,\ndirektör, Borås, f. 6/11/98 i Visby av K. A.\nL. o. Olga Ahlstedt. G. 28 m. Signe\nLückUg. Barn: Karl-Ivar f. 30, Jan\n35. — Anst. i Västg. Väfn. A-B i\nÄlfsered 12-23, Bröd. Wennerlund i\nBorås 23-25, deläg., styr:led. o. dir. i\nA-B Bröd. Liljeros sed. 25. Res. t.\nEngl. 33, 47, Tyskl. 40. Hobbies: tennis,\nblomsterodl.\n\nLiljestrand, Holger, civilingenjör,\nvägdirektör, Jönköping, f. 28/4/97 i\nGbg av försäkr:dir. Peter Erik L. o.\nTekla Carlberg. — Stud :ex. v. Sofi\nAlmquists samsk. i Sthlm 15, avg:ex.\nfr. KTH 22, res:off:ex. 17. Fänr. i\nfortif. res. 17, und :löjtn. 20, löjtn. 25,\ni VVK 26, kapt. i VVK 33. Konstr.\nv. Bergsunds Mek. Verkst. A-B i\nSthlm 23, arb:led. h. J. M. Hutchison\nEntrepr. i Pennsylvania, USA,\narb:-led. o. bitr. arb :chef v. A-B\nVägför-bättringar i Sthlm 25-32, tf. byråing.\nv. väg- o. vattenbyggn :styr. 32-35,\nbyråing. å vägtrafikbyrån där 36, vägdir.\ni Jönköp. 1. sed. 43. Medl. av Sv.\ntek-n :för. 23-35.\n\nLiljhagen, Sven Håkan,\növerstelöjtnant, Göteborg, f. 14/4/99 i Sthlm av\nstatskonsul. Gustaf L. o. GötaTundahl.\nG. 37 m. jur. kand. Beatrice Bartram.\nBarn: Else Marie f. 38, Gustav 39,\nBirgitta 42. — Stud :ex. i Strängnäs\n18, off:ex. å Karlberg 21, AIHSak 24,\narméns flygsk. å Malmslätt 25, jag:sk.\n27, fotogr :of f :kurs 28, arméspan :kurs\n32, spec :kurs i fotogr. v. KTH 37,\nflyg-krigshögsk. stabskurs 40. Fänr. v. Uppl.\nart:reg. 22, und:löjtn. 24, löjtn. 26,\nv. Norrl. art:reg. 28 v. flygv. kapt.\nv. flygv. 36, major v. flygv. 41, öv:löjtn.\ni flygv. 47. Tjg. v. Uppl. art:reg. 22-24,\nflygkomp. o. 3. flygkàren à\nMalmslätt 25-26, flygkåren å Frösön\n27-31, flygstyr., flygförvaltn. samt\ngeneralstabens fotograf, lab. 32-37, Östg.\nflygflottilj 38-41, Södermani. dito\n41-42, .stabschef v. Västra flygbasomr. i\nGbg sed. 43. Org. flygv. fotografitj.\nsamt kartläggn :flygn. f. Rikets allm.\nkartv. 32-34, org. första tillverkn. av\nflygkameror o. flygfotogr. mäter, i\nSv:e samt var chef o. lär. f. olika kur-\n\nkurser i flygfotogr. o. flygbildläsn. 33-37,\ndiverse militära komm: upp drag 32-37.\nMedl. av Fotogrametr. sällsk. i Sthlm\nsed. 33, styr:led. i Mil:sällsk. där\n34-37. Stud:res. o. kommend. i Tyskl.\n33 o. 34, Tjeckoslov. 34, Engl. 35, Itai.\n40. Skr.: div. art. betr. flygfotogr.\nRSO, FlygSm.\n\n<b>Liljorstrand, Per</b> Theofrid,\nkontraktsprost, Dädesjö, f. 24/2/87 i\nVäckelsång, Kronob. 1. G. 22 m.\nRK-systern Maria Transtedt. — Studiex.\ni Lund 16, teol. fil. ex. där 17, teol.\nkand., prakt. teol. prov samt\nprästvigd f. Växjö stift 20. Tjg. som v.\npastor i Linneryd o. Berga samt som\nv. kommin. i Torpa o. Nöttja, v. pastor\ni Älghult 22-27, tillika i Kråksmåla\n24-25, kommin. i Älghult 22, kyrkoh. i\nDädesjö 27, kontrrprost i Uppvidinge\nkontr. 40, kyrkobokföringsinsp. sed.\n46. Led. av boställsndn f. IV. distr.\n36, fullm. f. Växjö stift i Prästersk.\nänke- o. pup :kassa, ombud f. Sv.\nkyrkans miss:styr. o. stiftsrådet, ordf. i\nkyrko- o. past:stämma o. i skolstyr.\nStud rresor t. Engl. 35, Tyskl. 36. Skr.:\nett flertal predikn. i tidn. o. tidskr.\nLVO 46.\n\n<b>Lilliecreutz</b>, Jacob <b>Henrik</b> Eugén\nFredriksson, major, friherre, Bor, f.\n10/6/73 i Herrestad, Kärda s:n,\nJönköp. l., av godsäg., frih. Fredrik L.\no. Maria Rydström. G. 02 m. Julia\nMaria Sofia Tham. — Stud:ex. i Sthlm\n95, off:ex. 97. Und :löjtn. v. Kronob.\nreg. 97, löjtn. 01, kapt. 12, major på\nres:stat 21, avsk. 28. Inneh.\nLundboholms fideikommisskapital,\nLundboholm. Bor. RSO, RJohO, Hall.\nskytteförb. GM.\n\n<b>Lilliecreutz, Jacob</b> Magnus,\nfriherre, godsägare, Kärda, f. 11/9/87 i\nKärda, Jönköp. l., av bruksäg., frih. Adolf\nL. o. h. h., f. Ljunglöf. G. 1. 19 m.\nHanna de Laval, d. 28; 2. 29 m. Hild\nBerg. Barn: Anna f. 19, Christina 21,\nMagnus 26, Christoffer 31. — Mog:ex. i \nVäxjö 08, jur. stud. i Lund 08-13.\nDisp. v. A-B Åminne Bruk 16-21,\ndeläg., styr:led. samt verkst. dir. i\nÅminne Gård A-B i Kärda sed. 45. Ordf.\ni Kärda-Hångers tax:nd sed. 19,\nKärda-Hångers kristidsnd, Kärda\nkomm:fullm. o. valdistr.\n\n<b>Lilliedahl, Sven</b> Rudolf Wilhelm,\nlektor, Linköping, f. 29/1/98 i Ahus,\nKrist. l., av provrläk. Ernst Wilhelm\nL. o. Anna Magdalena Österberg. G.\n27 m. Dagmar Eneström. Barn: Märta f. 30. \n— Stud:ex. v. norra latin i\nSthlm 16, fil. kand. i Lund 20, fil. mag.\n21, fil. lic. 26, fil. dr 28, provår i\nLund 27. Timlär. v. Osby samsk.\n19-20, e. o. lär. v. Hälsingborgs gosslärov.\n21-22, timlär. v. Lunds priv. lärov.\n23-24, Lunds fullst. lärov. f. fl. 24-26, e. o.\nlektor v. Eksjö h. a. 1. 27-28, lektor i\nlat. o. grek. v. Linköp. h. a. 1. sed.\n28. Res. t. Tyskl. 20 o. 38, Ital.\n22-23 o. 40. Skr.: Florusstudien\n(grad:avh. 28), Zur Frage vom »inneren»\nWert der Klauseln (32), Katedern, en\nroman om skolpreusseriet (32), Svårigheter \nv. latinöversättningarna (34), Lundanätter \n(roman 34), Fr. antikens Rom (37). RNO.\n\n<b>Lilliehöök</b>, Malcolm Wilhelmsson (<b>Mac</b>), \nstiftsjägmästare, Skara, f. 6/10/89 i \nBro, Värml. l., av majoren C. J. W.\nL. o. frih:an Elin Uggla. G. 18 m.\nSigne Östman. Barn: Bertil f. 19, Claes 21,\nKerstin 23. — Stud:ex. 09,\nciviljägmäst. 17. E. jägmäst. i domänverket\n17, skogsindeln :assist., skogsing. o.\nrevirassist. 17-33, stiftsjägmäst. i Skara\nstift fr. 33, utn. 39. Styr:led. i\nSkarab. l. jaktv:fören. RVO, RSpCFO,\nSv. jäg:förb. guldjetong, Skarab. l.\njaktv:fören. ftjGM, Skytte-m.\n\n<b>Lillieroth, Hilding</b> Georg Waldemar,\nkyrkoherde, Tun, f. 3/6/03 i Frillesås,\nHall. l., av kyrkoh. Fredrik L. o.\nAnna Ekedahl. G. 27 m. Ruth\nStrömqvist. Barn: Birgit f. 28, Karin 29,\nHjördis 32, Ulia 35, Inger 42. —\nStud:ex. i Gbg 21, teol. kand. o. prakt. teol.\nex. 25, prästv. 26. Kommin. i\nYllestad 26, kyrkoh. i Tun fr. 40. Ordf.\ni Vartofta-Äsaka kyrkostämma o.\nskolråd t. 40, ordf. i Tuns past.\nkyrkost. o. skolråd sed. 41, ordf. i Tuns\npast. kyrkofullm. sed. 43, ordf. i Tuns\nkyrkofullm. sed. 44.\n\n<b>Lilliestierna</b>, Anders <b>Hjalmar</b> Edward, \nbitr. lasarettsläkare o. prakt,\nläkare, Norrköping, f. 22/4/97 i Sthlm\nav öv:löjtn. Anders Henrik Hjalmar\nRichard L. o. Ingeborg Kristina\nWallenius. G. 27 m. Gunnel Engström, d.\n42. Barn: Ingeborg f. 30, Christina\n32, Margareta 34, Elisabeth 38. —\nStud:ex. i Skövde 15, med. kand. i\nUpps. 20 o. med. lic. där 26. Utr.\nstud:res. 30, 32 o. 34. Assist:läk. v.\nÖrebro las. med. avd. 26, andre und:läk. \nv. Kolmårdssanat. 27-28, assist:läk. \nv. Norrköp. las. med. avd. 28-29,\nandre und:läk. där 29-32 o. förste dito\n32-34, e. läk. v. Sthlms epidisjukh. 34,\nandre und:läk. o. tf. aman. v. Seraf\n:-las. nervklin. 35-36, tf. und :läk. v.\nLångbro sjukh. 36, aman. o. tf. förste\nläk. v. Psykiatr. sjukh. 36-37, läk. v.\nNorrköp. las. tub :avd. 38, v.\nungd:-anst. å Skenäs s. å., prakt. läk. i\nNorrköp. Skr.: upps. i neurologi m.\nm. RJohO.\n\n",
    "structured": {
        "1": {
            "full_name": "Liljeros, Bror Gustaf Adolf",
            "location": "Borås",
            "occupation": "direktör",
            "birth_details": {
                "date": "6/11/1898",
                "place": "Visby",
                "parents": "K. A. L. o. Olga Ahlstedt"
            },
            "education": [
                {
                    "degree": "NULL",
                    "year": "NULL",
                    "institution": "NULL"
                }
            ],
            "career": [
                {
                    "position": "Anst. i Västg. Väfn. A-B",
                    "years": {
                        "start_year": 1912,
                        "end_year": 1923
                    },
                    "organization": "Älfsered"
                },
                {
                    "position": "Bröd. Wennerlund i Borås",
                    "years": {
                        "start_year": 1923,
                        "end_year": 1925
                    },
                    "organization": "NULL"
                },
                {
                    "position": "deläg., styr:led. o. dir. i A-B Bröd. Liljeros",
                    "years": {
                        "start_year": 1925,
                        "end_year": "NULL"
                    },
                    "organization": "NULL"
                }
            ],
            "family": {
                "spouse": "Signe LückUg",
                "marriage_year": "28",
                "children": [
                    {
                        "name": "Karl-Ivar",
                        "birth_year": "30"
                    },
                    {
                        "name": "Jan",
                        "birth_year": "35"
                    }
                ]
            }
        },
        "2": {
            "full_name": "Liljestrand, Holger",
            "location": "Jönköping",
            "occupation": "civilingenjör, vägdirektör",
            "birth_details": {
                "date": "28/4/1897",
                "place": "Gbg",
                "parents": "försäkr:dir. Peter Erik L. o. Tekla Carlberg"
            },
            "education": [
                {
                    "degree": "NULL",
                    "year": 1915,
                    "institution": "Sofi Almquists samsk. i Sthlm"
                },
                {
                    "degree": "NULL",
                    "year": 1922,
                    "institution": "KTH"
                }
            ],
            "career": [
                {
                    "position": "Konstr. v. Bergsunds Mek. Verkst. A-B in Sthlm",
                    "years": {
                        "start_year": 1923
                    },
                    "organization": "NULL"
                },
                {
                    "position": "arb:led. h. J. M. Hutchison Entrepr. in Pennsylvania, USA",
                    "years": {
                        "start_year": "NULL"
                    },
                    "organization": "NULL"
                },
                {
                    "position": "tf. byråing. v. väg- o. vattenbyggn :styr.",
                    "years": {
                        "start_year": 1932,
                        "end_year": 1935
                    },
                    "organization": "NULL"
                },
                {
                    "position": "vägdir. i Jönköp. 1.",
                    "years": {
                        "start_year": 1943,
                        "end_year": "NULL"
                    },
                    "organization": "NULL"
                }
            ],
            "family": {
                "spouse": "NULL",
                "marriage_year": "NULL",
                "children": []
            }
        },
        "3": {
            "full_name": "Liljhagen, Sven Håkan",
            "location": "Göteborg",
            "occupation": "överstelöjtnant",
            "birth_details": {
                "date": "14/4/1899",
                "place": "Sthlm",
                "parents": "statskonsul. Gustaf L. o. GötaTundahl"
            },
            "education": [
                {
                    "degree": "NULL",
                    "year": 1918,
                    "institution": "Strängnäs"
                },
                {
                    "degree": "NULL",
                    "year": 1921,
                    "institution": "Karlberg"
                }
            ],
            "career": [
                {
                    "position": "major v. flygv.",
                    "years": {
                        "start_year": 1947
                    },
                    "organization": "flygv"
                }
            ],
            "family": {
                "spouse": "jur. kand. Beatrice Bartram",
                "marriage_year": "37",
                "children": [
                    {
                        "name": "Else Marie",
                        "birth_year": "38"
                    },
                    {
                        "name": "Gustav",
                        "birth_year": "39"
                    },
                    {
                        "name": "Birgitta",
                        "birth_year": "42"
                    }
                ]
            }
        },
        "4": {
            "full_name": "Liljorstrand, Per Theofrid",
            "location": "Dädesjö",
            "occupation": "kontraktsprost",
            "birth_details": {
                "date": "24/2/1887",
                "place": "Väckelsång, Kronob. 1.",
                "parents": "RK-systern Maria Transtedt"
            },
            "education": [
                {
                    "degree": "NULL",
                    "year": 1916,
                    "institution": "Lund"
                },
                {
                    "degree": "teol. kand.",
                    "year": 1920,
                    "institution": "Växjö stift"
                }
            ],
            "career": [
                {
                    "position": "kontrrprost i Uppvidinge kontr.",
                    "years": {
                        "start_year": 1940
                    },
                    "organization": "NULL"
                }
            ],
            "family": {
                "spouse": "NULL",
                "marriage_year": "22",
                "children": []
            }
        },
        "5": {
            "full_name": "Lilliecreutz, Jacob Henrik Eugén Fredriksson",
            "location": "Bor",
            "occupation": "major, friherre",
            "birth_details": {
                "date": "10/6/1873",
                "place": "Herrestad, Kärda s:n, Jönköp. l.",
                "parents": "godsäg., frih. Fredrik L. o. Maria Rydström"
            },
            "education": [
                {
                    "degree": "NULL",
                    "year": 1895,
                    "institution": "Sthlm"
                },
                {
                    "degree": "NULL",
                    "year": 1897,
                    "institution": "NULL"
                }
            ],
            "career": [
                {
                    "position": "avsk.",
                    "years": {
                        "start_year": 1928
                    },
                    "organization": "NULL"
                }
            ],
            "family": {
                "spouse": "Julia Maria Sofia Tham",
                "marriage_year": "02",
                "children": []
            }
        },
        "6": {
            "full_name": "Lilliecreutz, Jacob Magnus",
            "location": "Kärda",
            "occupation": "friherre, godsägare",
            "birth_details": {
                "date": "11/9/1887",
                "place": "Kärda, Jönköp. l.",
                "parents": "bruksäg., frih. Adolf L. o. h. h., f. Ljunglöf"
            },
            "education": [
                {
                    "degree": "NULL",
                    "year": 1908,
                    "institution": "Växjö"
                },
                {
                    "degree": "NULL",
                    "year": "08-13",
                    "institution": "Lund"
                }
            ],
            "career": [
                {
                    "position": "Ordf. i Kärda-Hångers tax:nd",
                    "years": {
                        "start_year": 1919
                    },
                    "organization": "NULL"
                },
                {
                    "position": "ordf. i Kärda-Hångers kristidsnd",
                    "years": {
                        "start_year": "NULL"
                    },
                    "organization": "NULL"
                }
            ],
            "family": {
                "spouse": "NULL",
                "marriage_year": "NULL",
                "children": [
                    {
                        "name": "Anna",
                        "birth_year": "19"
                    },
                    {
                        "name": "Christina",
                        "birth_year": "21"
                    },
                    {
                        "name": "Magnus",
                        "birth_year": "26"
                    },
                    {
                        "name": "Christoffer",
                        "birth_year": "31"
                    }
                ]
            }
        },
        "7": {
            "full_name": "Lilliedahl, Sven Rudolf Wilhelm",
            "location": "Linköping",
            "occupation": "lektor",
            "birth_details": {
                "date": "29/1/1898",
                "place": "Ahus, Krist. l.",
                "parents": "provrläk. Ernst Wilhelm L. o. Anna Magdalena Österberg"
            },
            "education": [
                {
                    "degree": "NULL",
                    "year": 1916,
                    "institution": "Sthlm"
                },
                {
                    "degree": "fil. kand.",
                    "year": "20-21",
                    "institution": "Lund"
                },
                {
                    "degree": "fil. mag.",
                    "year": "21",
                    "institution": "NULL"
                },
                {
                    "degree": "fil. lic.",
                    "year": "26",
                    "institution": "NULL"
                }
            ],
            "career": [
                {
                    "position": "e. o. lektor v. Eksjö h. a.",
                    "years": {
                        "start_year": 1927,
                        "end_year": 1928
                    },
                    "organization": "NULL"
                },
                {
                    "position": "lektor i lat. o. grek. v. Linköp. h. a.",
                    "years": {
                        "start_year": 1928,
                        "end_year": "NULL"
                    },
                    "organization": "NULL"
                }
            ],
            "family": {
                "spouse": "NULL",
                "marriage_year": "NULL",
                "children": [
                    {
                        "name": "Märta",
                        "birth_year": "30"
                    }
                ]
            }
        },
        "8": {
            "full_name": "Lilliehöök, Malcolm Wilhelmsson (Mac)",
            "location": "Skara",
            "occupation": "stiftsjägmästare",
            "birth_details": {
                "date": "6/10/1889",
                "place": "Bro, Värml. l.",
                "parents": "majoren C. J. W. L. o. frih:an Elin Uggla"
            },
            "education": [
                {
                    "degree": "NULL",
                    "year": 1909,
                    "institution": "NULL"
                },
                {
                    "degree": "civiljägmäst.",
                    "year": 1917,
                    "institution": "NULL"
                }
            ],
            "career": [
                {
                    "position": "stiftsjägmäst. i Skara stift fr. 33",
                    "years": {
                        "start_year": 1933
                    },
                    "organization": "NULL"
                }
            ],
            "family": {
                "spouse": "Signe Östman",
                "marriage_year": "18",
                "children": [
                    {
                        "name": "Bertil",
                        "birth_year": "19"
                    },
                    {
                        "name": "Claes",
                        "birth_year": "21"
                    },
                    {
                        "name": "Kerstin",
                        "birth_year": "23"
                    }
                ]
            }
        },
        "9": {
            "full_name": "Lillieroth, Hilding Georg Waldemar",
            "location": "Tun",
            "occupation": "kyrkoherde",
            "birth_details": {
                "date": "3/6/1903",
                "place": "Frillesås, Hall. l.",
                "parents": "kyrkoh. Fredrik L. o. Anna Ekedahl"
            },
            "education": [
                {
                    "degree": "NULL",
                    "year": 1921,
                    "institution": "Gbg"
                },
                {
                    "degree": "teol. kand.",
                    "year": 1925,
                    "institution": "NULL"
                }
            ],
            "career": [
                {
                    "position": "kyrkoh. i Tun fr. 40",
                    "years": {
                        "start_year": 1940
                    },
                    "organization": "NULL"
                }
            ],
            "family": {
                "spouse": "Ruth Strömqvist",
                "marriage_year": "27",
                "children": [
                    {
                        "name": "Birgit",
                        "birth_year": "28"
                    },
                    {
                        "name": "Karin",
                        "birth_year": "29"
                    },
                    {
                        "name": "Hjördis",
                        "birth_year": "32"
                    },
                    {
                        "name": "Ulia",
                        "birth_year": "35"
                    },
                    {
                        "name": "Inger",
                        "birth_year": "42"
                    }
                ]
            }
        },
        "10": {
            "full_name": "Lilliestierna, Anders Hjalmar Edward",
            "location": "Norrköping",
            "occupation": "bitr. lasarettsläkare o. praktläkare",
            "birth_details": {
                "date": "22/4/1897",
                "place": "Sthlm",
                "parents": "öv:löjtn. Anders Henrik Hjalmar Richard L. o. Ingeborg Kristina Wallenius"
            },
            "education": [
                {
                    "degree": "NULL",
                    "year": 1915,
                    "institution": "Skövde"
                },
                {
                    "degree": "med. kand.",
                    "year": "20",
                    "institution": "Upps."
                },
                {
                    "degree": "med. lic.",
                    "year": "26",
                    "institution": "NULL"
                }
            ],
            "career": [
                {
                    "position": "NULL",
                    "years": {
                        "start_year": 1927,
                        "end_year": 1928
                    },
                    "organization": "e. läk. v. Seraf :-las. nervklin."
                },
                {
                    "position": "NULL",
                    "years": {
                        "start_year": 1935,
                        "end_year": 1936
                    },
                    "organization": "stabschef v. Västra flygbasomr. i Gbg"
                }
            ],
            "family": {
                "spouse": "Gunnel Engström",
                "marriage_year": "27",
                "children": [
                    {
                        "name": "Ingeborg",
                        "birth_year": "30"
                    },
                    {
                        "name": "Christina",
                        "birth_year": "32"
                    },
                    {
                        "name": "Margareta",
                        "birth_year": "34"
                    },
                    {
                        "name": "Elisabeth",
                        "birth_year": "38"
                    }
                ]
            }
        }
    }
}