{
    "original": "Josefson, Harry Fritiof August,\nkomminister, Hyssna, f. 22/5/09 i\nTa-num, Gbgs o. Boh. 1., av järnv:tj:-\n\nman Axel J. o. Ida Johansson. G. 37\nm. Märtha Bergström. Barn: Margit\nf. 38, Brita 40, Inge 43. — Stud:ex. i\nUddevalla 28, teol. fi-l. ex. 30, teol.\nkand. samt prakt. teol. prov 34, prästv.\nf. Gbgs stift 35. Varit past:adj. i\nöckerö, Skepplanda o. Tanum, v.\nkommin. i Grebbestad samt stiftsadj.\ni Gbgs stift (m. plac. i Sikagen, Danm.,\n\n0.\ttjg. bl. sv. fiskare i Danm., Norge,\nEngl. o. Skottl.), kyrkoadj. i Lysekil\n42, kommin. i Hyssna sed. 42. Ordf.\ni HyS’Sna kyrkostämma, suppl. i Gbgs\nstifts diakoniråd.\n\nJosefson, Sten, disponent,\nUlricehamn, f. 11/3/14 i Ulricehamn av\ngrosshandl. Erik J. o. Ingeborg\nAndersson. — Stud:ex. i Borås 33, Gbgs\nhand :inst. fackkurs f. stud. 34, Höhere\nFachschule f. Wirkerei- und\nStricke-reiindustrie i Chemnitz 37, prakt,\ninom textilind. i Tyskl. o. Schv^eiz.\nStud :res. t. Tyskl., Schv^eiz, Frankr.,\nBelg. o. Tjeckoslov. Disp. o. led. av\nstyr. f. A-B Erik Josefson &amp; Co. i\nUlricehamn sed. 38. Suppl. i styr. f.\nUlricehamns Tidn. A-B, verkst. dir.\ndär 43-46, Led. av stadsfullm. (h) sed.\n43 siamt av des’s beredn :utsk., led. av\ndrätselkamm. fr. 47, suppl. i lokalstyr.\n\n1.\tUlricehamns samrealsk., av Älvsb. 1.\nlandsting utsedd t. siuppl i direkt, f.\nSjö-Gunnarsbo san. o. sjukst. i\nUlricehamn, led. av styr. f. Ulricehamns\nhö-gerfören. o. södra Älvsb. högerförb.\n\nJuhlin, Axel Matteus Emanuel,\nkomminister, Håbol, f. 21/9/88 i\nWisconsin, USA, av pastor C. A. J. o.\nHelena Rydin. — Mog:ex. i Karlstad 08,\nfarm. kand. 11, teol. fil. ex. 16, teol.\nkand. 22, prakt. teol. prov samt prästv.\nf. Karlstads stift 25. Tf. kommin. i\nNyskoga 26, kommin. i Håbol sed. 28.\nOrdf. i kyrkostämma, ’skolstyr. o.\nkomm :fullm.\n\n",
    "structured": {
        "0": {
            "full_name": "Josefson, Harry Fritiof August",
            "location": "Hyssna, Gbgs o. Boh. l.",
            "occupation": "komminister",
            "birth_details": {
                "date": "22/05/1909",
                "place": "Tanum"
            },
            "education": [
                {
                    "degree": "Stud:ex.",
                    "year": "1928",
                    "institution": "Uddevalla"
                },
                {
                    "degree": "teol. fil. ex.",
                    "year": "1930",
                    "institution": null
                },
                {
                    "degree": "teol. kand.",
                    "year": "1934",
                    "institution": null
                }
            ],
            "career": [
                {
                    "position": "past:adj.",
                    "years": {
                        "start_year": 0,
                        "end_year": 0
                    },
                    "organization": "öckerö, Skepplanda o. Tanum"
                },
                {
                    "position": "kommin.",
                    "years": {
                        "start_year": 0,
                        "end_year": 0
                    },
                    "organization": "Grebbestad"
                },
                {
                    "position": "stiftsadj.",
                    "years": {
                        "start_year": 0,
                        "end_year": 0
                    },
                    "organization": "Gbgs stift"
                },
                {
                    "position": "kyrkoadj.",
                    "years": {
                        "start_year": 1942,
                        "end_year": 1942
                    },
                    "organization": "Lysekil"
                },
                {
                    "position": "kommin.",
                    "years": {
                        "start_year": 1942,
                        "end_year": 0
                    },
                    "organization": "Hyssna"
                }
            ],
            "family": {
                "spouse": "Märtha Bergström",
                "marriage_year": "1937",
                "children": [
                    {
                        "name": "Margit",
                        "birth_year": "1938"
                    },
                    {
                        "name": "Brita",
                        "birth_year": "1940"
                    },
                    {
                        "name": "Inge",
                        "birth_year": "1943"
                    }
                ]
            }
        },
        "1": {
            "full_name": "Josefson, Sten",
            "location": "Ulricehamn",
            "occupation": "disponent",
            "birth_details": {
                "date": "11/03/1914",
                "place": "Ulricehamn"
            },
            "education": [
                {
                    "degree": "Stud:ex.",
                    "year": "1933",
                    "institution": "Borås"
                },
                {
                    "degree": "Gbgs hand :inst. fackkurs",
                    "year": "1934",
                    "institution": null
                },
                {
                    "degree": "Höhere Fachschule f. Wirkerei- und Strickereiindustrie",
                    "year": "1937",
                    "institution": "Chemnitz"
                }
            ],
            "career": [
                {
                    "position": "disp.",
                    "years": {
                        "start_year": 1938,
                        "end_year": 0
                    },
                    "organization": "A-B Erik Josefson & Co."
                },
                {
                    "position": "verkst. dir.",
                    "years": {
                        "start_year": 1943,
                        "end_year": 1946
                    },
                    "organization": "Ulricehamn"
                }
            ],
            "family": {
                "spouse": null,
                "marriage_year": "NULL",
                "children": []
            }
        },
        "2": {
            "full_name": "Juhlin, Axel Matteus Emanuel",
            "location": "Håbol",
            "occupation": "komminister",
            "birth_details": {
                "date": "21/09/1888",
                "place": "Wisconsin, USA"
            },
            "education": [
                {
                    "degree": "Mog:ex.",
                    "year": "1908",
                    "institution": "Karlstad"
                },
                {
                    "degree": "farm. kand.",
                    "year": "1911",
                    "institution": null
                },
                {
                    "degree": "teol. fil. ex.",
                    "year": "1916",
                    "institution": null
                }
            ],
            "career": [
                {
                    "position": "Tf. kommin.",
                    "years": {
                        "start_year": 1926,
                        "end_year": 0
                    },
                    "organization": "Nyskoga"
                },
                {
                    "position": "kommin.",
                    "years": {
                        "start_year": 1928,
                        "end_year": 0
                    },
                    "organization": "Håbol"
                }
            ],
            "family": {
                "spouse": "NULL",
                "marriage_year": "NULL",
                "children": []
            }
        }
    }
}