{
    "original": "Jyllman, Axel Vilhelm,\nläroverksadjunkt, Jönköping, f. 3/8/92 i\nJön-köp. — Stud:ex. i Jönköp. 11, fil. mag.\ni Upps. 18, provår i Lund 28. Vik. adj.,\ne. o. ämneslär. v. Landskr. fo’lksk:sem.\n19, i Trollhättan 19-20 o. 21-24, Tryde\n20-21, Klippan 24, Ludvika 25-28, v.\nJönköp. h. a. 1. 29-32, adj. i kemi o.\nbiol. m. hälsolära där sed. 33. Skr.:\nDvalin under 50 år (42).\n\nJäderberg, Dagmar Helena Elisabet,\ntandläkare, Alingsås, f. 30/9/96 i Gbg\nav sjökapt. o. skeppsred. August\nUppvall o. \"Signe Burman. G, 22 m.\nprov:läk. Elis Jäderberg. Barn:\nBengt-Elis f. 25. — Stud:ex. v.\nLy-ceum f. fl. i Sthlm 16, tandhkand. 20,\ntandl. 22. Prakt, i Hunnebostrand 22,\ni Dorotea 23, vik. i Karlshamn «omm.\n23, prakt, i Ryd 23-42, skoltandl. där\n35-41, distr:tandl. där 41, dito i\nLerum sed. 43.\n\nJäderberg, Karl Elis,\nprovinsialläkare, Alingsås, f. 6/8/91 i\nGuldsmedshyttan, Örebro 1., av bruksförvalt. Erik J.\no. Anna Rosell. G. 22 m. tandl.\nDagmar Uppvall. Barn: Bengt-Elis f. 25.\n— Stud:ex. i Örebro 10, med. kand.\ni Upps. 17, med. lic. i Sthlm 22. Tf.\naman. v. Allm. BB i Sthlm 19-20, tf.\nandre stadsläk. i Söderhamn 20, tf.\nund:’läk. resp. assist :läk. v.\nKarlshamns las. sju mån. 21-23, tf. stadsläk.\ni Skellefteå o. tf. prov:läk. i Sotenäs\ndistr. 22, tf. prov:läk. i Dorotea distr.\n23, e. prov:läk. i Ryds distr. 23-24,\ntf. prov:läk. där 24-25 o. prov:läk.\n25-42, prov:läk. i Alingsås distr. sed. 42,\n\nläk. v. Ryds brunns- o. badanst.\n24-29, järnv:läk. v.\nKarlshamn-Vislanda-Bolmens Järnv. 23-42 o, v.\nHönshylte-Kvarnamåla Järnv. 25-42. Var i Ryd\nv. ordf. i hälsov:nd, led. av\nmunic:-’fullm. o. ordf. i nykiterh :nd. RNO.\n\nJäremo, Uno Gösta, .stadskamrer,\nEksjö, f. 11/12/96 i Ljungarum,\nJön-köp. 1. G. 26 m. Sigrid Gullers. Barn:\nInga-Stina f. 27, Ann-Mari 29, Johan\n34, Gunnar 35, Annika 41. — Studiex.\ni Jönköp. 15, civ:ing:ex. v. CTI 19,\nDSI (komm. linjen) 31. Studiresa t.\nDanm. 26. Anst. v. Sv. Skifferverken\n19-21, lär. v. oiika folkhögsk. 21-30,\nkomm:kamr. i Hässelby villastad\n31-37, stadskamr. i Eksjö sed. 37.\nKro-noomb. i Eksjö .stads ö. tax:distr. sed.\n39, kassaförvalt. f. Röda korsets\nsemesterhem Hamnaryd sed. 44, komm.\nled. av styr. f. HSB i Eksjö sed. 45.\n\n",
    "structured": {
        "0": {
            "full_name": "Jyllman, Axel Vilhelm",
            "location": "Jönköping",
            "occupation": "läroverksadjunkt",
            "birth_details": {
                "date": "03/08/1892",
                "place": "Jönköping",
                "parents": null
            },
            "education": [
                {
                    "degree": "Stud:ex.",
                    "year": "1911",
                    "institution": "Jönköp."
                },
                {
                    "degree": "fil. mag.",
                    "year": "1918",
                    "institution": "Upps."
                },
                {
                    "degree": "provår",
                    "year": "1928",
                    "institution": "Lund"
                }
            ],
            "career": [
                {
                    "position": "Vik. adj.",
                    "years": {
                        "start_year": 1919,
                        "end_year": 1920
                    },
                    "organization": "Landskr. fo' lksk: sem."
                },
                {
                    "position": "e. o. ämneslär.",
                    "years": {
                        "start_year": 1921,
                        "end_year": 1924
                    },
                    "organization": "Trollhättan"
                },
                {
                    "position": "adj.",
                    "years": {
                        "start_year": 1928,
                        "end_year": 1932
                    },
                    "organization": "Jönköp. h. a. 1."
                },
                {
                    "position": "adj. i kemi o. biol. m. hälsolära",
                    "years": {
                        "start_year": 1933,
                        "end_year": null
                    },
                    "organization": "Jönköp."
                }
            ],
            "family": null
        },
        "1": {
            "full_name": "Jäderberg, Dagmar Helena Elisabet",
            "location": "Alingsås",
            "occupation": "tandläkare",
            "birth_details": {
                "date": "30/09/1896",
                "place": "Gbg",
                "parents": "sjökapt. o. skeppsred. August Uppvall o. Signe Burman"
            },
            "education": [
                {
                    "degree": "Stud:ex.",
                    "year": "1916",
                    "institution": "Lyceum"
                },
                {
                    "degree": "tandhkand.",
                    "year": "1920",
                    "institution": null
                },
                {
                    "degree": "tandl.",
                    "year": "1922",
                    "institution": null
                }
            ],
            "career": [
                {
                    "position": "Prakt.",
                    "years": {
                        "start_year": 1922,
                        "end_year": null
                    },
                    "organization": "Hunnebostrand"
                },
                {
                    "position": "vik.",
                    "years": {
                        "start_year": 1923,
                        "end_year": 1923
                    },
                    "organization": "Karlshamn komm."
                },
                {
                    "position": "prakt.",
                    "years": {
                        "start_year": 1923,
                        "end_year": 1942
                    },
                    "organization": "Ryd"
                },
                {
                    "position": "skoltandl.",
                    "years": {
                        "start_year": 1935,
                        "end_year": 1941
                    },
                    "organization": "Ryd"
                },
                {
                    "position": "distr:tandl.",
                    "years": {
                        "start_year": 1941,
                        "end_year": null
                    },
                    "organization": "Lerum"
                }
            ],
            "family": {
                "spouse": "Elis Jäderberg",
                "marriage_year": "1922",
                "children": [
                    {
                        "name": "Bengt-Elis",
                        "birth_year": "1925"
                    }
                ]
            }
        },
        "2": {
            "full_name": "Jäderberg, Karl Elis",
            "location": "Alingsås",
            "occupation": "provinsialläkare",
            "birth_details": {
                "date": "06/08/1891",
                "place": "Guldsmedshyttan, Örebro 1.",
                "parents": "bruksförvalt. Erik J. o. Anna Rosell"
            },
            "education": [
                {
                    "degree": "Stud:ex.",
                    "year": "1910",
                    "institution": "Örebro"
                },
                {
                    "degree": "med. kand.",
                    "year": "1917",
                    "institution": "Upps."
                },
                {
                    "degree": "med. lic.",
                    "year": "1922",
                    "institution": "Sthlm"
                }
            ],
            "career": [
                {
                    "position": "Tf. aman. v. Allm. BB",
                    "years": {
                        "start_year": 1919,
                        "end_year": 1920
                    },
                    "organization": "Sthlm"
                },
                {
                    "position": "tf. andre stadsläk.",
                    "years": {
                        "start_year": 1920,
                        "end_year": null
                    },
                    "organization": "Söderhamn"
                },
                {
                    "position": "tf. und:'läk. resp. assist :läk. v.",
                    "years": {
                        "start_year": 1921,
                        "end_year": 1923
                    },
                    "organization": "Karlshamns las. sju mån."
                },
                {
                    "position": "prov:läk.",
                    "years": {
                        "start_year": 1925,
                        "end_year": 1942
                    },
                    "organization": "Ryds distr."
                },
                {
                    "position": "prov:läk.",
                    "years": {
                        "start_year": 1942,
                        "end_year": null
                    },
                    "organization": "Alingsås distr."
                }
            ],
            "family": {
                "spouse": "Dagmar Uppvall",
                "marriage_year": "1922",
                "children": [
                    {
                        "name": "Bengt-Elis",
                        "birth_year": "1925"
                    }
                ]
            }
        },
        "3": {
            "full_name": "Järemo, Uno Gösta",
            "location": "Eksjö",
            "occupation": "stadskamrer",
            "birth_details": {
                "date": "11/12/1896",
                "place": "Ljungarum, Jönköp. 1."
            },
            "education": [
                {
                    "degree": "Studiex.",
                    "year": "1915",
                    "institution": "Jönköp."
                },
                {
                    "degree": "civ:ing:ex.",
                    "year": "1919",
                    "institution": "CTI"
                },
                {
                    "degree": "DSI (komm. linjen)",
                    "year": "1931",
                    "institution": null
                }
            ],
            "career": [
                {
                    "position": "Anst. v. Sv. Skifferverken",
                    "years": {
                        "start_year": 1919,
                        "end_year": 1921
                    },
                    "organization": null
                },
                {
                    "position": "lär. v. olika folkhögsk.",
                    "years": {
                        "start_year": 1921,
                        "end_year": 1930
                    },
                    "organization": null
                },
                {
                    "position": "komm:kamr.",
                    "years": {
                        "start_year": 1931,
                        "end_year": 1937
                    },
                    "organization": "Hässelby villastad"
                },
                {
                    "position": "stadskamr.",
                    "years": {
                        "start_year": 1937,
                        "end_year": null
                    },
                    "organization": "Eksjö"
                },
                {
                    "position": "Kronoomb.",
                    "years": {
                        "start_year": 1945,
                        "end_year": null
                    },
                    "organization": "Röda korsets semesterhem Hamnaryd"
                }
            ],
            "family": {
                "spouse": "Sigrid Gullers",
                "marriage_year": "1926",
                "children": [
                    {
                        "name": "Inga-Stina",
                        "birth_year": "1927"
                    },
                    {
                        "name": "Ann-Mari",
                        "birth_year": "1929"
                    },
                    {
                        "name": "Johan",
                        "birth_year": "1934"
                    },
                    {
                        "name": "Gunnar",
                        "birth_year": "1935"
                    },
                    {
                        "name": "Annika",
                        "birth_year": "1941"
                    }
                ]
            }
        }
    }
}