{
    "original": "Johansson, Reimer Napoleon,\nlandshövding, Halmstad, f. 17/11/93 i\nNorrby, Västmanl. 1., av K. A. J. o. Ellen\nEriksson. G. 1. 16 m. Elsa Maria\nEriksson, d. 44; 2. 46 m. fil. dr Karin\nBreimer. Barn: Gerd f. 17, Stig 21,\nBengt 26. — Folkhögsk., lantm:sk.\nLantbr. i Norrby, äg. t. Norrbäck\nv. Sala, släktgård under mer än\n300 år i rakt nedstigande led,\nlands-hövd. i Hall. 1. sed. 43. Ordf. i 43 års\n\nmejeriutredn., tidigare ordf. i Sv:es\nlantbr :f’örb., Mejeriernas riksfören. o.\nLantmännens Mjölikförsäljn :fören. i\nSthlm, v. ordf. i livsmed :komm. 40-43’,\nled. aiv ’stait. priskontr :nd, ordf. i\nkom-mind i Norrby o. i polis- o.\nsjukv:-distr., led. av benisin- o. oljend 40 o. 42\nårs statl. jordibr ikomm., led. av styr.\nf. stat. lantfbr :k:em. ansit. o. Riksförb.\nf. Sv:es försv. KNO’, RVO.\n\nJohansson, Carl Robert, direktör,\nGöteborg, f. 30i/10/82 i Gbg. G. 10 m.\nKarin Köhlberg. Barn: Bertil f. 11,\nTycho 20, Birgit 25. — Majornas\nele-m:lärov. 98, ensk. hand:- o.\nspråk-und:visn. Anst. h. firma Victor\nJanson i Gbg 98-15, h. Färg A-B\nInternational i Gbg :s. kont :chef o. kamr.\n14-34, verkst. dir. där samt i\nMarie-bolms Nya Industri A-B sed. 34.\nSuppl. i styr. f. de två sistnämnda\nföret., led. av ’Styr. f. Såpförädlings A-B\ni Gbg, Färg- &amp; Fernissfabr. fören. i\nSthlm o. Färg- &amp; Fernissfabr.\nråva-rufören. där, ordf. i\nIsoleringsfirmornas fören. i Gbg. PatrstGM.\n\nJohansson, Johan Rudolf,\nkyrkoherde, Torp, f. 25/2/06 i Horn, Skarab.\n1., av Nils Anders J. o. Hilma Alfrida\nJohansson. G. 32 m. Ingrid\nJohansson. Barn: Lasse f. 33, Per 36, Britta\n39, Inga 41, Margareta 45.\nStud:-ex. i Skövde 25, teol. fil. ex. 26, teol.\nkand. o. prakt. teol. prov 29, prästv.\nf. Skara stift 30. Past:adj. i\nLånga-red 30, v. pastor i N. Asarp 31,\nkom-min. i Lagman ser ed 32, kyrkoh. i Hol\nsed. 39.\n\n",
    "structured": {
        "0": {
            "full_name": "Reimer Napoleon Johansson",
            "location": "Halmstad",
            "occupation": "Landshövding",
            "birth_details": {
                "date": "17/11/1893",
                "place": "Norrby, Västmanlands län",
                "parents": "K. A. J. o. Ellen Eriksson"
            },
            "education": [
                {
                    "degree": "Folkhögsk.",
                    "year": "NULL",
                    "institution": "NULL"
                },
                {
                    "degree": "lantm:sk.",
                    "year": "NULL",
                    "institution": "NULL"
                }
            ],
            "career": [
                {
                    "position": "Lantbr.",
                    "years": {
                        "start_year": 0,
                        "end_year": 0
                    },
                    "organization": "Norrby"
                },
                {
                    "position": "äg. t. Norrbäck v. Sala",
                    "years": {
                        "start_year": 0,
                        "end_year": 0
                    },
                    "organization": "NULL"
                },
                {
                    "position": "lands-hövd. i Hall. l.",
                    "years": {
                        "start_year": 43,
                        "end_year": 0
                    },
                    "organization": "NULL"
                },
                {
                    "position": "Ordf. i 43 års mejeriutredn.",
                    "years": {
                        "start_year": 0,
                        "end_year": 0
                    },
                    "organization": "NULL"
                },
                {
                    "position": "tidigare ordf. i Sv:es lantbr :f’örb.",
                    "years": {
                        "start_year": 0,
                        "end_year": 0
                    },
                    "organization": "NULL"
                },
                {
                    "position": "Ordf. i livsmed :komm.",
                    "years": {
                        "start_year": 40,
                        "end_year": 43
                    },
                    "organization": "NULL"
                },
                {
                    "position": "v. ordf. i livsmed :komm.",
                    "years": {
                        "start_year": 0,
                        "end_year": 0
                    },
                    "organization": "NULL"
                },
                {
                    "position": "led. aiv ’stait. priskontr :nd",
                    "years": {
                        "start_year": 0,
                        "end_year": 0
                    },
                    "organization": "NULL"
                },
                {
                    "position": "ordf. i kom-mind i Norrby o. i polis- o. sjukv:-distr.",
                    "years": {
                        "start_year": 0,
                        "end_year": 0
                    },
                    "organization": "NULL"
                },
                {
                    "position": "led. av benisin- o. oljend",
                    "years": {
                        "start_year": 40,
                        "end_year": 42
                    },
                    "organization": "NULL"
                }
            ],
            "family": {
                "spouse": "Elsa Maria Eriksson, fil. dr Karin Breimer",
                "marriage_year": "16/11/1916, 1946",
                "children": [
                    {
                        "name": "Gerd",
                        "birth_year": "17"
                    },
                    {
                        "name": "Stig",
                        "birth_year": "21"
                    },
                    {
                        "name": "Bengt",
                        "birth_year": "26"
                    }
                ]
            }
        },
        "1": {
            "full_name": "Carl Robert Johansson",
            "location": "Göteborg",
            "occupation": "Direktör",
            "birth_details": {
                "date": "30/10/1882",
                "place": "Göteborg",
                "parents": "NULL"
            },
            "education": [
                {
                    "degree": "Majornas elem:lärov.",
                    "year": "98",
                    "institution": "NULL"
                }
            ],
            "career": [
                {
                    "position": "NULL",
                    "years": {
                        "start_year": 0,
                        "end_year": 0
                    },
                    "organization": "NULL"
                }
            ],
            "family": {
                "spouse": "Karin Köhlberg",
                "marriage_year": "10/1910",
                "children": [
                    {
                        "name": "Bertil",
                        "birth_year": "11"
                    },
                    {
                        "name": "Tycho",
                        "birth_year": "20"
                    },
                    {
                        "name": "Birgit",
                        "birth_year": "25"
                    }
                ]
            }
        },
        "2": {
            "full_name": "Johan Rudolf Johansson",
            "location": "Torp",
            "occupation": "Kyrkoherde",
            "birth_details": {
                "date": "25/02/1906",
                "place": "Horn, Skarab. l.",
                "parents": "Nils Anders J. o. Hilma Alfrida Johansson"
            },
            "education": [
                {
                    "degree": "Stud:-ex. i Skövde",
                    "year": "25",
                    "institution": "NULL"
                },
                {
                    "degree": "teol. fil. ex.",
                    "year": "26",
                    "institution": "NULL"
                },
                {
                    "degree": "teol. kand.",
                    "year": "29",
                    "institution": "NULL"
                },
                {
                    "degree": "prakt. teol. prov",
                    "year": "29",
                    "institution": "NULL"
                }
            ],
            "career": [
                {
                    "position": "Past:adj. i Långa-red",
                    "years": {
                        "start_year": 30,
                        "end_year": 0
                    },
                    "organization": "NULL"
                },
                {
                    "position": "v. pastor i N. Asarp",
                    "years": {
                        "start_year": 31,
                        "end_year": 0
                    },
                    "organization": "NULL"
                },
                {
                    "position": "kom-min. i Lagman ser ed",
                    "years": {
                        "start_year": 32,
                        "end_year": 0
                    },
                    "organization": "NULL"
                },
                {
                    "position": "kyrkoh. i Hol",
                    "years": {
                        "start_year": 39,
                        "end_year": 0
                    },
                    "organization": "NULL"
                }
            ],
            "family": {
                "spouse": "Ingrid Johansson",
                "marriage_year": "32",
                "children": [
                    {
                        "name": "Lasse",
                        "birth_year": "33"
                    },
                    {
                        "name": "Per",
                        "birth_year": "36"
                    },
                    {
                        "name": "Britta",
                        "birth_year": "39"
                    },
                    {
                        "name": "Inga",
                        "birth_year": "41"
                    },
                    {
                        "name": "Margareta",
                        "birth_year": "45"
                    }
                ]
            }
        }
    }
}