{
    "original": "Jonsson, Karl Erik Gunnar,\n’läroverksadjunkt, Linköping, f. 13/6/89 i\nLofta, Kalmar 1., av godsäg. C. F. J.\no. Alma Andersson. G. 24 m.\nMargareta Gustafsson. Barn: Bo f. 26,\nBarbro 30. — Stud:ex. i Linköp. 10,\nfil. mag. i Upps. 16, fil. lic. 20, provår\ni Sthlm 22. Vik. adj. i Falun 16-17,\ne. lär. i Södertälje 20-22, v. Linköp.\n\nh. a. 1. 23-26, adj. i kemi, matem. o.\nfysik där sed. 26. Skr.: Uber\nAlkali-siiberthiosulfate (21). RVOlkl.\n\nJohnsson, Otto Eric, direktör,\ntrafikchef, Norrköping, f. 17/10/91 i Öved,\nMalmöh. 1., av fisk :tillsyningsman\nNils J. o. Johanna Olsson. — Elev v.\nNorra Ö’stergötl. Järnv. 06, kont:bitr.\ndär 08, stat:skriv. 15, kont:skriv. v.\nMell. Östergötl. Järnv. 20, förste dito\n21, byråas’sist. 22, hnjeinsp. v.\nVar-berg-Borås-Herrljunga Järnv. 29,\ntra-fikinsp. 34, verkst. dir. o. trafikchef\nf. Trafikförv. östergötl. Smalspår.\nJärnv. 36, verkst. dir. f. Norra\nöstergötl. Järnv. A-B, Mell. Östergötl.\nJärnv. A-B,\nNorrköp.-Söderköp.-Vik-bolandets Järnv. A-B o. Norra Tjusts\nTrafik A-B. V. ordf. i Mell.\nöstergötl. Trafik A-B, Hästholmens\nHamn-Si Mag. A-B, styr:led. i Trafik A-B\nJönköp.-Gränna-Ödeshög. o.\nArkö-sunds Hotell o. Restaurang A-B.\nMedl. av Sv. tekn:fören.. Norrköp.\nRotarykl., Frimurarorden o. Odd\nFel-low. RVO.\n\nJohnsson, Erik Wilhelm Gunnar,\ntandläkare, Eksjö, f. 17/6/96 i Åseda,\nKronob. 1. — Stud:ex. i Växjö 17,\ntandl. 23. Prakt, i Storvik 23-29,\ndärefter i Emmabo.da o. num. i Eksjö.\n\nJonson, Eskil Magnus Lorentz,\nkyrkoherde, Vislanda, f. 21/12/95 i\nBreda-ryd, Jönköp. 1., av folkskoll. o. org.\nCarl J. o. Amanda Lorentzson. G. 22\nm. Hanna Paulsson. Barn: Per f. 23,\nCarl 26. — Stud:ex. i Jönköp. 15, teol.\nfil. ex. i Lund 16, teol. kand. samt\npraikt. teol. prov 21, prästv. f. Växjö\nstift 22. Varit v. kommin. i Hänger o.\nVåxtorp samt bitr. åt v. pasit. i\nVärnamo, kommin. i Hånger 23, i Sankt\nSigfrid 24, kyrkoh. i Södra Hestra o.\nGryteryds past. 32, i Vislanda o.\nBlä-dinge sed. 46. Ordf. i kyrkostämma o.\nskolråd.\n\n",
    "structured": {
        "0": {
            "full_name": "Johnsson Karl Erik Gunnar",
            "location": "Linköping",
            "occupation": "läroverksadjunkt",
            "birth_details": {
                "date": "13/06/1889",
                "place": "Lofta, Kalmar",
                "parents": "C. F. J. o. Alma Andersson"
            },
            "education": [
                {
                    "degree": "Stud:ex.",
                    "year": "1910",
                    "institution": "Linköp."
                },
                {
                    "degree": "fil. mag.",
                    "year": "1916",
                    "institution": "Upps."
                },
                {
                    "degree": "fil. lic.",
                    "year": "1920",
                    "institution": "provår i Sthlm"
                }
            ],
            "career": [
                {
                    "position": "Vik. adj.",
                    "years": {
                        "start_year": 1923,
                        "end_year": 1926
                    },
                    "organization": "Linköp."
                },
                {
                    "position": "adj.",
                    "years": {
                        "start_year": 1926,
                        "end_year": null
                    },
                    "organization": "Södertälje"
                }
            ],
            "family": {
                "spouse": "Margareta Gustafsson",
                "marriage_year": "1924",
                "children": [
                    {
                        "name": "Bo",
                        "birth_year": "1926"
                    },
                    {
                        "name": "Barbro",
                        "birth_year": "1930"
                    }
                ]
            }
        },
        "1": {
            "full_name": "Johnsson Otto Eric",
            "location": "Norrköping",
            "occupation": "direktör, trafikchef",
            "birth_details": {
                "date": "17/10/1891",
                "place": "Öved, Malmöh"
            },
            "education": [
                {
                    "degree": "Elev v.",
                    "year": "1906",
                    "institution": "Norra Ö’stergötl. Järnv."
                }
            ],
            "career": [
                {
                    "position": "verkst. dir. o. trafikchef",
                    "years": {
                        "start_year": 1936,
                        "end_year": null
                    },
                    "organization": "Norrköping"
                }
            ],
            "family": {
                "spouse": "",
                "marriage_year": null,
                "children": []
            }
        },
        "2": {
            "full_name": "Johnsson Erik Wilhelm Gunnar",
            "location": "Eksjö",
            "occupation": "tandläkare",
            "birth_details": {
                "date": "17/06/1896",
                "place": "Åseda, Kronob."
            },
            "education": [
                {
                    "degree": "Stud:ex.",
                    "year": "1917",
                    "institution": "Växjö"
                },
                {
                    "degree": "tandl.",
                    "year": "1923",
                    "institution": "NULL"
                }
            ],
            "career": [],
            "family": {
                "spouse": "",
                "marriage_year": null,
                "children": []
            }
        },
        "3": {
            "full_name": "Jonson Eskil Magnus Lorentz",
            "location": "Vislanda",
            "occupation": "kyrkoherde",
            "birth_details": {
                "date": "21/12/1895",
                "place": "Bredar-ryd, Jönköp."
            },
            "education": [
                {
                    "degree": "Stud:ex.",
                    "year": "1915",
                    "institution": "Jönköp."
                },
                {
                    "degree": "teol. fil. ex.",
                    "year": "1916",
                    "institution": "Lund"
                },
                {
                    "degree": "teol. kand.",
                    "year": "NULL",
                    "institution": "NULL"
                }
            ],
            "career": [
                {
                    "position": "kommin.",
                    "years": {
                        "start_year": 1922,
                        "end_year": 1923
                    },
                    "organization": "Hånger"
                },
                {
                    "position": "kyrkoh.",
                    "years": {
                        "start_year": 1946,
                        "end_year": null
                    },
                    "organization": "Vislanda o. Blä-dinge"
                }
            ],
            "family": {
                "spouse": "Hanna Paulsson",
                "marriage_year": "1922",
                "children": [
                    {
                        "name": "Per",
                        "birth_year": "1923"
                    },
                    {
                        "name": "Carl",
                        "birth_year": "1926"
                    }
                ]
            }
        }
    }
}