{
    "original": "Gunne, Carl Mikael, konstnär, Sthlm,\nf. 29/9/93 i Sundsvall av byggm. C. A.\nOlsson o. Clara Jonsson. G. 21 m.\nAsta Brattström. Fil. kand. 15, jur.\nkand. 20, fil. lic. 31, att. i utrrdep. 20,\naman. v. Natimus. 21, förest, f.\nNat:-mus. saml. av modernt måleri o.\nskulpt. 32-37. Sekr. i nden f. stödj. av\nden konstn. verksamh, i Sv :e 23-24,\nsekr. f. sv. konstutst. i London 24, sv.\nkonstindustriutst. i U. S.A. 27, kommiss,\nf. utst. Ung Pariserkonst 27, f. sv.\nkonstutst. i Paris 29, fackkommiss. f.\navd. glas o. keramik inom Sthlmsutst.\n30, kommiss, f. ital. konstutst. i Sv:e,\nFinl. o. Norge 31, sekr. f. sv. konstutst.\ni Oslo 32, kommiss, f. belg. konstutst.\ni Sv:e 34, f. sv. konstutst. i Belg.,\nHoll. o. Finl. 34, i Budapest 38. Repr.\ni Natrmus., Ateneum, Hfors, Musée\ndes Beaux-Arts, Antwerpen, Magyar\nNemzeti Mus., Budapest. RVO,\nOfflt-KrO, OffLettTSO, OffüngFO,\nRB-LeopO, RFinlVROlkl, RFrHL,\nOfC-Frdel’Ip.\nGünther, Johan Georg Allan, med.\nlic., prakt, läkare, Sthlm, f. 12/7/96 i\nNya Varvet, Gtbgs o. Bohus L, av\nfolkskollär. Johannes Theodor G. o.\nHanna Bergenlund. Stud:ex. i Gtbg\n16, med. kand. i Upps. 21, med. lic. i\nUpps. 26. Assist :läk. v. Akad. sjukh. i\nUpps. kir. avd. 24, t f. und:läk. v.\nlas :s i Karlstad med. avd. somm. 26,\nassist :läk. v. Akad. sjukh. i Upps. kir.\navd. 27-28, und rläk. St. Ekebergs\nsanat. 28, und :läk. o. aman. v.\nKron-pr:an Lovisas vårdanstrs med. avd.\n29-32, däreft. läk. v. poliklin. v. sa.\nsjukh., prakt. läk. i Sthlm sed. 32.\nStud:res. t. Bryssel 26-27 o. gmgått\nkurs v. École de medicine tropicale.\nGünther, Johannes Ludvig Sigurd,\nkomminister, Stuvsta, f. 26/5/00 i Nya\nVarvets fs., Gtbgs o. Boh. L, av lär.\nJohannes Theodor G. o. Hanna\nBergenlund. G. 32 m. Svea Hjalmy\nTeodora Svensson. Barn: Birgitta f. 33,\nSigfrid f. 35, d. 42, Hannes f, 37,\nAnna Theodora f. 43. Stud :ex. i Gtbg\n20, teol. fil. ex. 24, teol. kand. 27,\nprakt. teol. prov 27, pv. f. Strängnäs\nstift 28, t. f. komm. i Stora Malm 30,\nkyrkoadj. i Längbro 41, komm. i\nHuddinge 42.\n",
    "structured": {
        "0": {
            "full_name": "Gunne, Carl Mikael",
            "location": "Stockholm",
            "occupation": "Konstnär",
            "birth_details": {
                "date": "29/09/1893",
                "place": "Sundsvall",
                "parents": "Byggm. C. A. Olsson o. Clara Jonsson"
            },
            "education": [
                {
                    "degree": "Filosofie kandidat",
                    "year": "1915",
                    "institution": "Unknown"
                },
                {
                    "degree": "Juris kandidat",
                    "year": "1920",
                    "institution": "Unknown"
                },
                {
                    "degree": "Filosofie licentiat",
                    "year": "1931",
                    "institution": "Unknown"
                }
            ],
            "career": [
                {
                    "position": "Att. i utrrdep",
                    "years": {
                        "start_year": 1920,
                        "end_year": null
                    },
                    "organization": "Unknown"
                },
                {
                    "position": "Aman. v. Natimus",
                    "years": {
                        "start_year": 1921,
                        "end_year": null
                    },
                    "organization": "Unknown"
                },
                {
                    "position": "Förest, f. Nat:-mus. saml. av modernt måleri o. skulpt.",
                    "years": {
                        "start_year": 1932,
                        "end_year": 1937
                    },
                    "organization": "Unknown"
                },
                {
                    "position": "Sekr. i nden f. stödj. av den konstn. verksamh, i Sv :e",
                    "years": {
                        "start_year": 1923,
                        "end_year": 1924
                    },
                    "organization": "Unknown"
                },
                {
                    "position": "Sekr. f. sv. konstutst. i London",
                    "years": {
                        "start_year": 1924,
                        "end_year": null
                    },
                    "organization": "Unknown"
                },
                {
                    "position": "Sv. konstindustriutst. i U. S.A.",
                    "years": {
                        "start_year": 1927,
                        "end_year": null
                    },
                    "organization": "Unknown"
                },
                {
                    "position": "Kommiss, f. utst. Ung Pariserkonst",
                    "years": {
                        "start_year": 1927,
                        "end_year": null
                    },
                    "organization": "Unknown"
                },
                {
                    "position": "Fackkommiss. f. avd. glas o. keramik inom Sthlmsutst.",
                    "years": {
                        "start_year": 1930,
                        "end_year": null
                    },
                    "organization": "Unknown"
                },
                {
                    "position": "Kommiss, f. ital. konstutst. i Sv:e, Finl. o. Norge",
                    "years": {
                        "start_year": 1931,
                        "end_year": null
                    },
                    "organization": "Unknown"
                },
                {
                    "position": "Sekr. f. sv. konstutst. i Oslo",
                    "years": {
                        "start_year": 1932,
                        "end_year": null
                    },
                    "organization": "Unknown"
                },
                {
                    "position": "Kommiss, f. belg. konstutst. i Sv:e",
                    "years": {
                        "start_year": 1934,
                        "end_year": null
                    },
                    "organization": "Unknown"
                },
                {
                    "position": "F. sv. konstutst. i Belg., Holl. o. Finl.",
                    "years": {
                        "start_year": 1934,
                        "end_year": null
                    },
                    "organization": "Unknown"
                },
                {
                    "position": "I Budapest",
                    "years": {
                        "start_year": 1938,
                        "end_year": null
                    },
                    "organization": "Unknown"
                }
            ],
            "family": {
                "spouse": "Asta Brattström",
                "marriage_year": "Unknown",
                "children": []
            }
        },
        "1": {
            "full_name": "Günther, Johan Georg Allan",
            "location": "Stockholm",
            "occupation": "Prakt, läkare",
            "birth_details": {
                "date": "12/07/1896",
                "place": "Nya Varvet, Gtbgs o. Bohus L",
                "parents": "Folkskollär. Johannes Theodor G. o. Hanna Bergenlund"
            },
            "education": [
                {
                    "degree": "Stud:ex. i Gtbg",
                    "year": "1916",
                    "institution": "Unknown"
                },
                {
                    "degree": "Med. kand. i Upps.",
                    "year": "1921",
                    "institution": "Unknown"
                },
                {
                    "degree": "Med. lic. i Upps.",
                    "year": "1926",
                    "institution": "Unknown"
                }
            ],
            "career": [
                {
                    "position": "Assist :läk. v. Akad. sjukh. i Upps. kir. avd.",
                    "years": {
                        "start_year": 1924,
                        "end_year": null
                    },
                    "organization": "Unknown"
                }
            ],
            "family": {
                "spouse": "Unknown",
                "marriage_year": "Unknown",
                "children": []
            }
        },
        "2": {
            "full_name": "Günther, Johannes Ludvig Sigurd",
            "location": "Stuvsta",
            "occupation": "Komminister",
            "birth_details": {
                "date": "26/05/1900",
                "place": "Nya Varvets fs., Gtbgs o. Boh. L",
                "parents": "Lär. Johannes Theodor G. o. Hanna Bergenlund"
            },
            "education": [
                {
                    "degree": "Stud :ex. i Gtbg",
                    "year": "1920",
                    "institution": "Unknown"
                },
                {
                    "degree": "Teol. fil. ex.",
                    "year": "1924",
                    "institution": "Unknown"
                },
                {
                    "degree": "Teol. kand.",
                    "year": "1927",
                    "institution": "Unknown"
                }
            ],
            "career": [
                {
                    "position": "Prakt. teol. prov",
                    "years": {
                        "start_year": 1927,
                        "end_year": null
                    },
                    "organization": "Unknown"
                },
                {
                    "position": "Pv. f. Strängnäs stift",
                    "years": {
                        "start_year": 1928,
                        "end_year": null
                    },
                    "organization": "Unknown"
                },
                {
                    "position": "T. f. komm. i Stora Malm",
                    "years": {
                        "start_year": 1930,
                        "end_year": null
                    },
                    "organization": "Unknown"
                },
                {
                    "position": "Kyrkoadj. i Längbro",
                    "years": {
                        "start_year": 1941,
                        "end_year": null
                    },
                    "organization": "Unknown"
                },
                {
                    "position": "Komm. i Huddinge",
                    "years": {
                        "start_year": 1942,
                        "end_year": null
                    },
                    "organization": "Unknown"
                }
            ],
            "family": {
                "spouse": "Svea Hjalmy Teodora Svensson",
                "marriage_year": "Unknown",
                "children": [
                    {
                        "name": "Birgitta",
                        "birth_year": "1933"
                    },
                    {
                        "name": "Sigfrid",
                        "birth_year": "1935"
                    },
                    {
                        "name": "Hannes",
                        "birth_year": "1937"
                    },
                    {
                        "name": "Anna Theodora",
                        "birth_year": "1943"
                    }
                ]
            }
        }
    }
}