{
    "original": "CARLSSON, L H ROLAND,\ntandläkare, Östersund, f i Umeå 24/12/30 av\nbilrep Helge C o Thea Strahlström.\nStud:ex Umeå 52, tandl:ex Malmö 58,\naman avd f barntandv TI Umeå 58-60,\nass 60, aman avd f odontologisk\nortopedi TI Umeå 61-62, ass:tandl 62-66,\nprakt tandl Östersund sed 66.\nGift 55 m Elisabeth Brodin f 32, dtr t\nhemm:äg V B o Lilly Edholm. - Barn:\nInger f 59, Nils f 62, Erik f 65.\n\nCARLSSON, Å SIMON, överingenjör,\n\nBureå, f i Högsjö, Vnorrl l, 27/9/04 av\nförrn Augustin Karlsson o Elida\nGranlund.\n\nIng :ex Tekn facksk Härnösand 24, ing\nUtansjö cellulosa ab 24, driftsing\nÖhr-vikens ab Örviken 35, övering ab\nScha-rins söner Clemensnäs 42, Karlholms ab\n56, Bure ab sed 58.\n\nGift 30 m Hilda Carlsson f 06, dtr t\nkantor Petrus C o Hilda Swanström.\n-Barn: Britt-Inger f 35, Torbjörn f 42.\n\nCARLSON, C G YNGVE,\ntingsdomare, Söderhamn, f i Örebro 17/10/04\nav köpm Carl Oscar C o Antonia\nJohansson.\n\nStud:ex Gbg 24, jur kand Sthlm 32,\ntingstjg S Rosl doms 32-35, tjg Svea\nhovr 35-36, rådm rådhusr Söderhamn\n40-43 (tf 36) o 47-64, tf borgm 64,\ntingsdom Sydöstra Hälsingl doms sed 65.\n-Sekr o föredr Stat hyresråd 44-47. - Sekr\nhvnd Söderhamn 37-44 o 47-63,\nbyggn:-nd 34-44 o 47-63, DK 40-44 o 47-55, öl\nkomm utredn :uppdr, rev Söderhamns\nsparbk 54-63. - Utm: RNO.\nGift 41 m Alva Wallbom f 18, dtr t\nFredrik W o Elin Johansson. - Barn:\nLennart f 44, Ylva f 49.\n\nCARLSTEN, STEN G E, entreprenör,\n\nÄlvsbyn, f i Älvsbyn, Norrb l, 4/3/37 av\nköpm Enar C o Agda Forsgrén.\nHdlssk   56,  brevbär   56,  bensinstat :bitr\n57-59, traktorförare 59-61, inneh Firma\nSten Carlsten (schaktn:arb) Älvsbyn sed\n61. - Hobby: fiske.\nGift 61 m l:e postexp Siv Hedlund, dtr\n\nt l:e banbitr Verner H o Hillevi H.\n-Barn: Maud f 62, Charlotte f 65.\n\n",
    "structured": {
        "0": {
            "full_name": "L H ROLAND CARLSSON",
            "location": "Östersund",
            "occupation": "Tandläkare",
            "birth_details": {
                "date": "24/12/1930",
                "place": "Umeå",
                "parents": "Helge C o Thea Strahlström"
            },
            "education": [
                {
                    "degree": "Stud",
                    "year": "1952",
                    "institution": "Umeå"
                },
                {
                    "degree": "Tandl",
                    "year": "1958",
                    "institution": "Malmö"
                }
            ],
            "career": [
                {
                    "position": "Aman avd f barntandv TI Umeå",
                    "years": {
                        "start_year": 1958,
                        "end_year": 1960
                    },
                    "organization": "TI Umeå"
                },
                {
                    "position": "Aman avd f odontologisk ortopedi TI Umeå",
                    "years": {
                        "start_year": 1961,
                        "end_year": 1962
                    },
                    "organization": "TI Umeå"
                },
                {
                    "position": "Prakt tandl Östersund",
                    "years": {
                        "start_year": 1966
                    },
                    "organization": "Östersund"
                }
            ],
            "family": {
                "spouse": "Elisabeth Brodin",
                "marriage_year": "1955",
                "children": [
                    {
                        "name": "Inger",
                        "birth_year": "1959"
                    },
                    {
                        "name": "Nils",
                        "birth_year": "1962"
                    },
                    {
                        "name": "Erik",
                        "birth_year": "1965"
                    }
                ]
            }
        },
        "1": {
            "full_name": "Å SIMON CARLSSON",
            "location": "Bureå",
            "occupation": "Överingenjör",
            "birth_details": {
                "date": "27/09/1904",
                "place": "Högsjö, Vnorrl l",
                "parents": "Augustin Karlsson o Elida Granlund"
            },
            "education": [
                {
                    "degree": "Ing :ex Tekn facksk",
                    "year": "1924",
                    "institution": "Härnösand"
                }
            ],
            "career": [
                {
                    "position": "Ing Utansjö cellulosa ab",
                    "years": {
                        "start_year": 1924
                    },
                    "organization": "Utansjö cellulosa ab"
                },
                {
                    "position": "Driftingenjör Öhrvikens ab Örviken",
                    "years": {
                        "start_year": 1935
                    },
                    "organization": "Öhrvikens ab Örviken"
                },
                {
                    "position": "Överinge ab Scharins söner Clemensnäs",
                    "years": {
                        "start_year": 1942
                    },
                    "organization": "Scharins söner Clemensnäs"
                },
                {
                    "position": "Karlholms ab",
                    "years": {
                        "start_year": 1956
                    },
                    "organization": "Karlholms ab"
                },
                {
                    "position": "Bure ab",
                    "years": {
                        "start_year": 1958
                    },
                    "organization": "Bure ab"
                }
            ],
            "family": {
                "spouse": "Hilda Carlsson",
                "marriage_year": "1930",
                "children": [
                    {
                        "name": "Britt-Inger",
                        "birth_year": "1935"
                    },
                    {
                        "name": "Torbjörn",
                        "birth_year": "1942"
                    }
                ]
            }
        },
        "2": {
            "full_name": "C G YNGVE CARLSON",
            "location": "Söderhamn",
            "occupation": "Tingsdomare",
            "birth_details": {
                "date": "17/10/1904",
                "place": "Örebro",
                "parents": "Carl Oscar C o Antonia Johansson"
            },
            "education": [
                {
                    "degree": "Stud",
                    "year": "1924",
                    "institution": "Gbg"
                },
                {
                    "degree": "Jur kand",
                    "year": "1932",
                    "institution": "Sthlm"
                }
            ],
            "career": [
                {
                    "position": "Tingstjg S Rosl doms",
                    "years": {
                        "start_year": 1932,
                        "end_year": 1935
                    },
                    "organization": "S Rosl doms"
                },
                {
                    "position": "Tjg Svea hovr",
                    "years": {
                        "start_year": 1935,
                        "end_year": 1936
                    },
                    "organization": "Svea hovr"
                },
                {
                    "position": "Rådm rådhusr Söderhamn",
                    "years": {
                        "start_year": 1940,
                        "end_year": 1964
                    },
                    "organization": "rådhusr Söderhamn"
                },
                {
                    "position": "Tf borgm",
                    "years": {
                        "start_year": 1964
                    }
                },
                {
                    "position": "Tingsdom Sydöstra Hälsingl doms",
                    "years": {
                        "start_year": 1965
                    },
                    "organization": "Sydöstra Hälsingl doms"
                },
                {
                    "position": "Sekr o föredr Stat hyresråd",
                    "years": "44-47"
                },
                {
                    "position": "Sekr hvnd Söderhamn",
                    "years": "37-44 o 47-63"
                },
                {
                    "position": "Byggn:-nd",
                    "years": "34-44 o 47-63"
                },
                {
                    "position": "DK",
                    "years": "40-44 o 47-55"
                },
                {
                    "position": "Öl komm utredn :uppdr",
                    "years": null
                }
            ],
            "family": {
                "spouse": "Alva Wallbom",
                "marriage_year": "1941",
                "children": [
                    {
                        "name": "Lennart",
                        "birth_year": "1944"
                    },
                    {
                        "name": "Ylva",
                        "birth_year": "1949"
                    }
                ]
            },
            "honorary_titles": [
                {
                    "title": "RNO",
                    "institution": null,
                    "year": null
                }
            ]
        },
        "3": {
            "full_name": "STEN G E CARLSTEN",
            "location": "Älvsbyn",
            "occupation": "Entreprenör",
            "birth_details": {
                "date": "4/3/1937",
                "place": "Älvsbyn, Norrb l",
                "parents": "Enar C o Agda Forsgrén"
            },
            "education": [
                {
                    "degree": "Hdlssk",
                    "year": "1956",
                    "institution": null
                }
            ],
            "career": [
                {
                    "position": "Brevbär",
                    "years": "56"
                },
                {
                    "position": "Bensinstat :bitr",
                    "years": "57-59"
                },
                {
                    "position": "Traktorförare",
                    "years": "59-61"
                },
                {
                    "position": "Inneh Firma Sten Carlsten (schaktn:arb) Älvsbyn",
                    "years": "61"
                }
            ],
            "family": {
                "spouse": "Siv Hedlund",
                "marriage_year": "1961",
                "children": [
                    {
                        "name": "Maud",
                        "birth_year": "1962"
                    },
                    {
                        "name": "Charlotte",
                        "birth_year": "1965"
                    }
                ]
            },
            "hobbies": [
                "fiske"
            ]
        }
    }
}