{
    "original": "CARLBOM, GÖSTA, ingenjör,\nSundsvall,   f   i   Tierp,   Upps  l,   27/11/07   av\nbruksinsp Alfred C o Ingrid Grandin.\nStud:ex Falun 28, ing:ex NKI 44; ass\nFalu   priv   rundradiostation   29-39,   ing\ntelev radiostation Borlänge 40, telestyr\nradiobyrå Sthlm 46, förest telev\nradiostation Sundsvall 51, telev radiosekt där\nsed 53. - Hobbies: sport, filateli.\nGift 39 m Elsa Lindwall, dtr t fyrvakt\n\nGottfrid L o Anna Blombäck. - Barn:\nKerstin f 40, Ingrid f 44.\n\nCARLBORG, G MAURITZ,\nstadsbibliotekarie, Skellefteå, f i Sthlm 26/11/10\nav v häradsh Axel C o Adéle\nLindquis-ter.\n\nStud:ex 32, fil kand Sthlm, SÖ:s bibl:sk\n48-49, nord bibi:kurs Oslo 55; elev o ass\nSthlms stadsbibl 46-48, bibl:ie Malungs\nförs:bibi 49, stadsbibl:ie Boden 52,\nSkellefteå sed 56. - Medl W-sex.\nGift 50 m Margareta Norman f 10, dtr t\njv:tjm Otto N o Anna Eklund.\n\nCARLBORG,  L  OLOF,  ombudsman,\n\nSundsvall, f i Lungsund, Värml l, 21/8/\n20.\n\nStud:ex Karlstad 39, jur kand Upps 46,\ntingstjg Nordmarks doms 46-48, bitr jur\nAlrutz’ adv:byrå Sthlm 49-51, bitr\nomb: man Dynas ab o Svanö ab Väja\n52-55, omb :man Hammarforsens kraft ab\nSundsvall 56-63, Bålforsens kraft ab sed\n63.\n\nGift 45 m Blanche\nWormsdorff-Törn-quist f 22, dtr t agr Oscar T o Eje W.\n-Barn: Blanche f 47, Christel f 51,\nFlemming f 56.\n\nCARLÉN, CARL E, kommunalkamrer,\n\nVindeln, f i Dorotea, Västerb l, 6/7/16\nav Axel C o Ida Persson.\nHdlsutb Katrineholm, kommunaltjm\nDorotea 42, Vilhelmina 43, Norsjö 45,\nkommunalkamr Lövånger 47, Vindeln\nsed 51.\n\nGift 43 m Dora Lindström f 25, dtr t\nAxel L o Mary L. - Barn: Anita f 43,\nAston f 45, Lärs-Åke f 49.\n\nCARLÉN,    JAN-CHRISTER    H    O,\n\nbergsingenjör, Sandviken, f i Stora\nTuna, Kopparb l, 6/4/34 av kontr :prost\nOve C o Gudrun Ullholm.\nStud:ex Västerås 52, KTH 57,\nforskn:ing Jernkont Sthlm 57, Sandvikens jernv\nab 58, avd :ch 65, övering o ch rör- o\nstångstålslab där sed 67. - Ordf\nSandvikens högerfören 63-65. - Medl FrimO.\n- Skr art i JKA, Welding Journal,\nSchweissen und Schneiden m fi. -\nHobbies: bridge, litteratur.\nGift 58 m Birgitta Olsson f 36, dtr t\nkorresp Albin O o Nea Eriksson. - Barn:\nJonas f 59, Susanna f 61, Christer f 63.\n\n",
    "structured": {
        "1": {
            "full_name": "GÖSTA CARLBOM",
            "location": "Sundsvall",
            "occupation": "ingenjör",
            "birth_details": {
                "date": "27/11/1907",
                "place": "Tierp, Uppsala län"
            },
            "education": [
                {
                    "degree": "Stud:ex",
                    "year": "1928",
                    "institution": "Falun"
                },
                {
                    "degree": "ing:ex",
                    "year": "1944",
                    "institution": "NKI"
                }
            ],
            "career": [
                {
                    "position": "ass Falu priv rundradiostation",
                    "years": {
                        "start_year": 1929,
                        "end_year": 1939
                    },
                    "organization": "Falu priv rundradiostation"
                },
                {
                    "position": "ing telev radiostation",
                    "years": {
                        "start_year": 1940,
                        "end_year": 1940
                    },
                    "organization": "Borlänge"
                },
                {
                    "position": "telestyr radiobyrå",
                    "years": {
                        "start_year": 1946,
                        "end_year": 1946
                    },
                    "organization": "Sthlm"
                },
                {
                    "position": "förest telev radiostation",
                    "years": {
                        "start_year": 1951,
                        "end_year": 1951
                    },
                    "organization": "Sundsvall"
                },
                {
                    "position": "telev radiosekt",
                    "years": {
                        "start_year": 1953,
                        "end_year": null
                    },
                    "organization": "Sundsvall"
                }
            ],
            "family": {
                "spouse": "Elsa Lindwall",
                "marriage_year": "1939",
                "children": [
                    {
                        "name": "Kerstin",
                        "birth_year": "1940"
                    },
                    {
                        "name": "Ingrid",
                        "birth_year": "1944"
                    }
                ]
            }
        },
        "2": {
            "full_name": "MAURITZ CARLBORG",
            "location": "Skellefteå",
            "occupation": "stadsbibliotekarie",
            "birth_details": {
                "date": "26/11/1910",
                "place": "Stockholm"
            },
            "education": [
                {
                    "degree": "Stud:ex",
                    "year": "1932",
                    "institution": "Sthlm"
                },
                {
                    "degree": "fil kand",
                    "year": null,
                    "institution": null
                },
                {
                    "degree": "SÖ:s bibl:sk",
                    "year": "1948-1949",
                    "institution": null
                },
                {
                    "degree": "nord bibi:kurs",
                    "year": "1955",
                    "institution": "Oslo"
                }
            ],
            "career": [
                {
                    "position": "elev o ass Sthlms stadsbibl",
                    "years": {
                        "start_year": 1946,
                        "end_year": 1948
                    },
                    "organization": "Sthlm"
                },
                {
                    "position": "bibl:ie",
                    "years": {
                        "start_year": 1949,
                        "end_year": 1949
                    },
                    "organization": "Malungs förs:bibi"
                },
                {
                    "position": "stadsbibl:ie",
                    "years": {
                        "start_year": 1952,
                        "end_year": 1952
                    },
                    "organization": "Boden"
                },
                {
                    "position": "stadsbibl:ie",
                    "years": {
                        "start_year": 1956,
                        "end_year": null
                    },
                    "organization": "Skellefteå"
                }
            ],
            "family": {
                "spouse": "Margareta Norman",
                "marriage_year": "1950",
                "children": []
            }
        },
        "3": {
            "full_name": "OLOF CARLBORG",
            "location": "Sundsvall",
            "occupation": "ombudsman",
            "birth_details": {
                "date": "21/08/1920",
                "place": "Lungsund, Värmland län"
            },
            "education": [
                {
                    "degree": "Stud:ex",
                    "year": "1939",
                    "institution": "Karlstad"
                },
                {
                    "degree": "jur kand",
                    "year": "1946",
                    "institution": "Uppsala"
                }
            ],
            "career": [
                {
                    "position": "tingstjg",
                    "years": {
                        "start_year": 1946,
                        "end_year": 1948
                    },
                    "organization": "Nordmarks doms"
                },
                {
                    "position": "bitr jur",
                    "years": {
                        "start_year": 1949,
                        "end_year": 1951
                    },
                    "organization": "Alrutz’ adv:byrå Sthlm"
                },
                {
                    "position": "bitr omb",
                    "years": {
                        "start_year": 1952,
                        "end_year": 1955
                    },
                    "organization": "Dynas ab o Svanö ab Väja"
                },
                {
                    "position": "omb :man",
                    "years": {
                        "start_year": 1956,
                        "end_year": 1963
                    },
                    "organization": "Hammarforsens kraft ab Sundsvall"
                },
                {
                    "position": "omb :man",
                    "years": {
                        "start_year": 1963,
                        "end_year": null
                    },
                    "organization": "Bålforsens kraft ab"
                }
            ],
            "family": {
                "spouse": "Blanche Wormsdorff-Törnquist",
                "marriage_year": "1945",
                "children": [
                    {
                        "name": "Blanche",
                        "birth_year": "1947"
                    },
                    {
                        "name": "Christel",
                        "birth_year": "1951"
                    },
                    {
                        "name": "Flemming",
                        "birth_year": "1956"
                    }
                ]
            }
        },
        "4": {
            "full_name": "CARL E CARLÉN",
            "location": "Vindeln",
            "occupation": "kommunalkamrer",
            "birth_details": {
                "date": "06/07/1916",
                "place": "Dorotea, Västerbotten län"
            },
            "education": [
                {
                    "degree": "Hdlsutb",
                    "year": null,
                    "institution": "Katrineholm"
                }
            ],
            "career": [
                {
                    "position": "kommunaltjm",
                    "years": {
                        "start_year": 1942,
                        "end_year": 1942
                    },
                    "organization": "Dorotea"
                },
                {
                    "position": "kommunalkamr",
                    "years": {
                        "start_year": 1951,
                        "end_year": null
                    },
                    "organization": "Vindeln"
                }
            ],
            "family": {
                "spouse": "Dora Lindström",
                "marriage_year": "1943",
                "children": [
                    {
                        "name": "Anita",
                        "birth_year": "1943"
                    },
                    {
                        "name": "Aston",
                        "birth_year": "1945"
                    },
                    {
                        "name": "Lärs-Åke",
                        "birth_year": "1949"
                    }
                ]
            }
        },
        "5": {
            "full_name": "JAN-CHRISTER H CARLÉN",
            "location": "Sandviken",
            "occupation": "bergsingenjör",
            "birth_details": {
                "date": "06/04/1934",
                "place": "Stora Tuna, Kopparbergs län"
            },
            "education": [
                {
                    "degree": "Stud:ex",
                    "year": "1952",
                    "institution": "Västerås"
                },
                {
                    "degree": null,
                    "year": null,
                    "institution": "KTH"
                }
            ],
            "career": [
                {
                    "position": "forskn:ing",
                    "years": {
                        "start_year": 1957,
                        "end_year": 1957
                    },
                    "organization": "Jernkont Sthlm"
                },
                {
                    "position": "övering o ch rör- o stångstålslab",
                    "years": {
                        "start_year": 1967,
                        "end_year": null
                    },
                    "organization": "Sandvikens jernv ab"
                }
            ],
            "family": {
                "spouse": "Birgitta Olsson",
                "marriage_year": "1958",
                "children": [
                    {
                        "name": "Jonas",
                        "birth_year": "1959"
                    },
                    {
                        "name": "Susanna",
                        "birth_year": "1961"
                    },
                    {
                        "name": "Christer",
                        "birth_year": "1963"
                    }
                ]
            }
        }
    }
}