{
    "original": "CARLSTRÖM, KARL A R L, proto-\n\nkoilssekreterare, Umeå, f i Nora förs,\nVnorrl l, 20/3/03 av sjökapt August C o\nKristina Westman.\n\nStud:ex Härnösand 21, jur kand Upps\n29, tingstjg Ångermani s doms 30-34,\nupplägg av fastböcker i doms o stad\n35-39, dir :ass länsarb:ndn Umeå 40-42,\nvattenr:aman Nedre Norrbygd vattendomst\n\n43,  protokollssekr sed 52. - Hobby:\nfilateli.\n\nGift 48 m banktjm Lisa Lindgren f 04,\ndtr t förv Otto L o Gerda Hedman.\n\nCARNERUP, CARL-ERIC, tandläkare,\n\nBoden, f i Boden 28/11/13 av köpm\nOscar Carlson o Augusta Bergqvist.\nStud:ex Luleå 34, med kand Upps 39,\ntandl:ex Sthlm 43, priv:prakt Boden sed\n\n44.  - Medl FrimO, TR. - Hobbies: jakt,\nfiske, golf.\n\nGift 42 m Britta Aurell f 14, dtr t jvtjm\nOskar A o Signe Johansson. - Barn:\nEva f 50, Mats f 51.\n\nCARS, G B KARL-GERHARD, vat-\n\ntenrättsdomare, Östersund, f i Linkpg\n18/4/21 av leg läk Gunnar C o Elsa\nCarlsson.\n\nStud:ex Linkpg 39, res:off:ex 43, jur\nkand Upps 45, tingstjg Västernärkes\ndoms 45-48, fiskal Svea hovr 49,\nvatten-r:sekr Söderbygd vattendomst 49-54, adj\nled Svea hovr 55-56, assess 56,\nvattenr:-dom Mellanbygd vattendomst sed 66 (eo\n57). - Kapt I 4 res 59. - Expert\nvatten-vårdskomm 53-57, suppl stat hyresråd\n56-65, ordf Östersunds nykterh:nd sed\n62, styr:led SAFR sed 64 o RC sed 66.\n- Utm: RNO.\n\nGift 45 m Karin Hesselvik f 20, dtr t\nbankkamr August H o Ingrid\nAndersson. - Barn: Otto f 46, Eva f 48,\nKristina f 51.\n\n",
    "structured": {
        "0": {
            "full_name": "CARLSTRÖM, KARL A R L",
            "location": "Umeå",
            "occupation": "protokollssekreterare",
            "birth_details": {
                "date": "20/03/1903",
                "place": "Nora förs",
                "parents": "sjökapt August C o Kristina Westman"
            },
            "education": [
                {
                    "degree": "Stud",
                    "year": "1921",
                    "institution": "Härnösand"
                },
                {
                    "degree": "jur kand",
                    "year": "1929",
                    "institution": "Upps"
                }
            ],
            "career": [
                {
                    "position": "tingstjg",
                    "years": {
                        "start_year": 1930,
                        "end_year": 1934
                    },
                    "organization": "Ångermani s doms"
                },
                {
                    "position": "upplägg av fastböcker i doms o stad",
                    "years": {
                        "start_year": 1935,
                        "end_year": 1939
                    }
                },
                {
                    "position": "dir :ass länsarb:ndn",
                    "years": {
                        "start_year": 1940,
                        "end_year": 1942
                    },
                    "organization": "Umeå"
                },
                {
                    "position": "vattenr:aman",
                    "years": {
                        "start_year": 1943
                    },
                    "organization": "Nedre Norrbygd vattendomst"
                },
                {
                    "position": "protokollssekr",
                    "years": {
                        "start_year": 1952
                    }
                }
            ],
            "family": {
                "spouse": "Lisa Lindgren",
                "marriage_year": "1948",
                "children": [
                    {
                        "name": "NULL",
                        "birth_year": "NULL"
                    }
                ]
            }
        },
        "1": {
            "full_name": "CARNERUP, CARL-ERIC",
            "location": "Boden",
            "occupation": "tandläkare",
            "birth_details": {
                "date": "28/11/1913",
                "place": "Boden",
                "parents": "köpm Oscar Carlson o Augusta Bergqvist"
            },
            "education": [
                {
                    "degree": "Stud",
                    "year": "1934",
                    "institution": "Luleå"
                },
                {
                    "degree": "med kand",
                    "year": "1939",
                    "institution": "Upps"
                },
                {
                    "degree": "tandl:ex",
                    "year": "1943",
                    "institution": "Sthlm"
                }
            ],
            "career": [
                {
                    "position": "priv:prakt",
                    "years": {
                        "start_year": 1944
                    },
                    "organization": "Boden"
                }
            ],
            "family": {
                "spouse": "Britta Aurell",
                "marriage_year": "1942",
                "children": [
                    {
                        "name": "Eva",
                        "birth_year": "1950"
                    },
                    {
                        "name": "Mats",
                        "birth_year": "1951"
                    }
                ]
            }
        },
        "2": {
            "full_name": "CARS, G B KARL-GERHARD",
            "location": "Östersund",
            "occupation": "vattenrättsdomare",
            "birth_details": {
                "date": "18/04/1921",
                "place": "Linkpg",
                "parents": "leg läk Gunnar C o Elsa Carlsson"
            },
            "education": [
                {
                    "degree": "Stud",
                    "year": "1939",
                    "institution": "Linkpg"
                },
                {
                    "degree": "res:off:ex",
                    "year": "1943"
                },
                {
                    "degree": "jur kand",
                    "year": "1945",
                    "institution": "Upps"
                }
            ],
            "career": [
                {
                    "position": "tingstjg",
                    "years": {
                        "start_year": 1945,
                        "end_year": 1948
                    },
                    "organization": "Västernärkes doms"
                },
                {
                    "position": "fiskal",
                    "years": {
                        "start_year": 1949
                    },
                    "organization": "Svea hovr"
                },
                {
                    "position": "vatten-r:sekr",
                    "years": {
                        "start_year": 1949,
                        "end_year": 1954
                    },
                    "organization": "Söderbygd vattendomst"
                },
                {
                    "position": "adj led",
                    "years": {
                        "start_year": 1955,
                        "end_year": 1956
                    },
                    "organization": "Svea hovr"
                },
                {
                    "position": "assess",
                    "years": {
                        "start_year": 1956
                    }
                },
                {
                    "position": "vattenr:-dom",
                    "years": {
                        "start_year": 1966
                    },
                    "organization": "Mellanbygd vattendomst"
                }
            ],
            "family": {
                "spouse": "Karin Hesselvik",
                "marriage_year": "1945",
                "children": [
                    {
                        "name": "Otto",
                        "birth_year": "1946"
                    },
                    {
                        "name": "Eva",
                        "birth_year": "1948"
                    },
                    {
                        "name": "Kristina",
                        "birth_year": "1951"
                    }
                ]
            }
        }
    }
}