{
    "original": "Berninger, Anders, hovpredikant, kyrkoherde, Räpplinge, f. 16/2/92 i Södervidinge, Malmöh. L G. 18 m. Lilly Svensson. Barn: Nik-Gustaf f. 19, fänrik, Sven-Erik 21, lantbruks-stud., Ingemo 35. — Stud:ex. i Lund 14, teol. fil. ex. där 25, teol. kand. 26, prakt. teol. prov samt prästv. i. Växjö stift 27. Banktj :man 15-18, fondchef 19-21, vik. folkskoll. 22-24, v. pastor i Rogberga 27-28, i Repplinge 28, kj^rkoh. där sed. 28, tjg. e. o. hov-pred. sed. 44. Ordf. i kyrkostämma sed. 27, skolråd 27-40, led. av barnav:-nd sed. 28, led. av dir. f. Drottn. Victorias vilo-hem 30-37, komm:fuMm. 39- 42, v. ordf. i pens :nd sed. 40. LVO, H. M. Konungens GM åttonde storl m. Serafimerordens band, FMM.",
    "translated": "Berninger, Anders, court preacher, parish priest of Räpplinge. Born on February 16th, 1892 in Södervidinge, Malmöhus. Married to Lilly Svensson in 1918. Children: Nik-Gustaf, born in 1919 and became a lieutenant, Sven-Erik, born in 1921 and studied agriculture, and Ingemo, born in 1904. \n\nHe passed his final exams in Lund in 1914, received his theology degree in 1925, and became a candidate in theology in 1926. He passed his practical theology examination and was ordained as a priest in the diocese of Växjö in 1927. \n\nFrom 1915 to 1918, he worked in a bank and from 1919 to 1921, he was a fund manager. He worked as a substitute primary school teacher from 1922 to 1924 and then became an assistant pastor in Rogberga from 1927 to 1928. He then became the pastor of Räpplinge in 1928 and served there until 1944, also serving as the court preacher. \n\nHe was the chairman of the church meeting from 1927 and served on the school board from 1927 to 1940. He was a member of the child welfare committee from 1928 and a member of the board of directors for Queen Victoria's Rest Home from 1930 to 1937. He was a member of the municipality committee from 1939 to 1942 and the vice chairman of the pension committee from 1940. \n\nHe received the Litteris et Artibus medal and was awarded the 8th grade of the Order of the Sword by King Gustaf VI Adolf. He was also a member of the Order of Vasa.",
    "structured_raw": "{\n  \"@context\": \"https://schema.org\",\n  \"@type\": \"Person\",\n  \"name\": \"Anders Berninger\",\n  \"jobTitle\": \"Court Preacher, Parish Priest\",\n  \"birthDate\": \"1892-02-16\",\n  \"birthPlace\": {\n    \"@type\": \"City\",\n    \"name\": \"Södervidinge\",\n    \"address\": {\n      \"@type\": \"PostalAddress\",\n      \"addressLocality\": \"Malmöhus\"\n    }\n  },\n  \"spouse\": {\n    \"@type\": \"Person\",\n    \"name\": \"Lilly Svensson\",\n    \"marriageDate\": \"1918\"\n  },\n  \"children\": [\n    {\n      \"@type\": \"Person\",\n      \"name\": \"Nik-Gustaf\",\n      \"birthDate\": \"1919\",\n      \"jobTitle\": \"Lieutenant\"\n    },\n    {\n      \"@type\": \"Person\",\n      \"name\": \"Sven-Erik\",\n      \"birthDate\": \"1921\",\n      \"jobTitle\": \"Agriculture Student\"\n    },\n    {\n      \"@type\": \"Person\",\n      \"name\": \"Ingemo\",\n      \"birthDate\": \"1904\"\n    }\n  ],\n  \"alumniOf\": [\n    {\n      \"@type\": \"CollegeOrUniversity\",\n      \"name\": \"Lund University\",\n      \"endDate\": \"1914\",\n      \"degreeName\": \"Stud:ex.\"\n    },\n    {\n      \"@type\": \"CollegeOrUniversity\",\n      \"name\": \"Lund University\",\n      \"endDate\": \"1925\",\n      \"degreeName\": \"Teol. Fil. ex.\"\n    }\n  ],\n  \"worksFor\": [\n    {\n      \"@type\": \"Organization\",\n      \"name\": \"Växjö Diocese\",\n      \"jobTitle\": \"Priest\",\n      \"startDate\": \"1927\",\n      \"endDate\": \"1944\"\n    }\n  ],\n  \"memberOf\": [\n    {\n      \"@type\": \"Organization\",\n      \"name\": \"Church Meeting\",\n      \"roleName\": \"Chairman\",\n      \"startDate\": \"1927\"\n    },\n    {\n      \"@type\": \"Organization\",\n      \"name\": \"School Board\",\n      \"startDate\": \"1927\",\n      \"endDate\": \"1940\"\n    },\n    {\n      \"@type\": \"Organization\",\n      \"name\": \"Child Welfare Committee\",\n      \"startDate\": \"1928\"\n    },\n    {\n      \"@type\": \"Organization\",\n      \"name\": \"Queen Victoria's Rest Home Board of Directors\",\n      \"startDate\": \"1930\",\n      \"endDate\": \"1937\"\n    },\n    {\n      \"@type\": \"Organization\",\n      \"name\": \"Municipality Committee\",\n      \"startDate\": \"1939\",\n      \"endDate\": \"1942\"\n    },\n    {\n      \"@type\": \"Organization\",\n      \"name\": \"Pension Committee\",\n      \"roleName\": \"Vice Chairman\",\n      \"startDate\": \"1940\"\n    }\n  ],\n  \"awards\": [\n    {\n      \"@type\": \"Medal\",\n      \"name\": \"Litteris et Artibus\"\n    },\n    {\n      \"@type\": \"Order\",\n      \"name\": \"Order of the Sword\",\n      \"awardGrade\": \"8th\",\n      \"issuer\": {\n        \"@type\": \"Organization\",\n        \"name\": \"King Gustaf VI Adolf\"\n      }\n    },\n    {\n      \"@type\": \"Order\",\n      \"name\": \"Order of Vasa\"\n    }\n  ]\n}",
    "structured": {
        "@context": "https://schema.org",
        "@type": "Person",
        "name": "Anders Berninger",
        "jobTitle": "Court Preacher, Parish Priest",
        "birthDate": "1892-02-16",
        "birthPlace": {
            "@type": "City",
            "name": "Södervidinge",
            "address": {
                "@type": "PostalAddress",
                "addressLocality": "Malmöhus"
            }
        },
        "spouse": {
            "@type": "Person",
            "name": "Lilly Svensson",
            "marriageDate": "1918"
        },
        "children": [
            {
                "@type": "Person",
                "name": "Nik-Gustaf",
                "birthDate": "1919",
                "jobTitle": "Lieutenant"
            },
            {
                "@type": "Person",
                "name": "Sven-Erik",
                "birthDate": "1921",
                "jobTitle": "Agriculture Student"
            },
            {
                "@type": "Person",
                "name": "Ingemo",
                "birthDate": "1904"
            }
        ],
        "alumniOf": [
            {
                "@type": "CollegeOrUniversity",
                "name": "Lund University",
                "endDate": "1914",
                "degreeName": "Stud:ex."
            },
            {
                "@type": "CollegeOrUniversity",
                "name": "Lund University",
                "endDate": "1925",
                "degreeName": "Teol. Fil. ex."
            }
        ],
        "worksFor": [
            {
                "@type": "Organization",
                "name": "Växjö Diocese",
                "jobTitle": "Priest",
                "startDate": "1927",
                "endDate": "1944"
            }
        ],
        "memberOf": [
            {
                "@type": "Organization",
                "name": "Church Meeting",
                "roleName": "Chairman",
                "startDate": "1927"
            },
            {
                "@type": "Organization",
                "name": "School Board",
                "startDate": "1927",
                "endDate": "1940"
            },
            {
                "@type": "Organization",
                "name": "Child Welfare Committee",
                "startDate": "1928"
            },
            {
                "@type": "Organization",
                "name": "Queen Victoria's Rest Home Board of Directors",
                "startDate": "1930",
                "endDate": "1937"
            },
            {
                "@type": "Organization",
                "name": "Municipality Committee",
                "startDate": "1939",
                "endDate": "1942"
            },
            {
                "@type": "Organization",
                "name": "Pension Committee",
                "roleName": "Vice Chairman",
                "startDate": "1940"
            }
        ],
        "awards": [
            {
                "@type": "Medal",
                "name": "Litteris et Artibus"
            },
            {
                "@type": "Order",
                "name": "Order of the Sword",
                "awardGrade": "8th",
                "issuer": {
                    "@type": "Organization",
                    "name": "King Gustaf VI Adolf"
                }
            },
            {
                "@type": "Order",
                "name": "Order of Vasa"
            }
        ]
    }
}