{
    "original": "Amylon, Nils, tandläkare, Göleborg, f. 28/2/05 i HälsingboTg av J. A. Amy-loin o. Anna Boman. G. 1. 33 m. Anna-Liisa PauLison; 2. 45 m. Brita S vensison. Barn: Margot f. 35, Rodif 37, Nils O^l-oif 39. — Stud:ex. i Häiisimgborg 24, tand-il: kand. 27, tandl’. 30. Vik. i Eskü-stuna 30, där ef t. praikt. o. konsuik. tandl. v. (länslas. i Ängeilhoilm samt «iko’ltandL i Barkåkra ’S :n, i Gbgs stads tjänst sed. 41. Schultzbergslka fondens stip. v. Charité i Berliin, Westdeutsche Kiefer-kiliiniik i Diis^se^Morf samt Kruppsk’a ^tandlkilin. i Esisen 36. Sekr. i Nordv. Skånes tandil :fören. 35, klubbmäist. där 38, ordf. 39, -led. av Ängelhoilm^s bygg-n:nd 40, ordf. i tjämstesekt. linom Gbgs tandl :sä!ilsk. förb :avd. 42-47, ’sckr. i Gbgs tandl: ställs k. förb :’avd. 43’-47.",
    "translated": "Amylon, Nils, dentist, Gothenburg, born February 28, 1905 in HälsingboTg to J.A. Amyloin and Anna Boman. Married 1st to Anna-Liisa Paulison for 33 years, and 2nd to Brita Svensison for 45 years. Children: Margot born in 1935, Rodif born in 1937, Nils Ol-oif born in 1939. He passed his student exams in Hälsingborg in 1924, became a dental student in 1927 and a dental practitioner in 1930. Worked in Eskilstuna in 1930, then worked as a practice owner and consultant dentist in Ängelholm and also as a coal mine dentist in Barkåkra 'S:t. He has been in the service of Gothenburg since 1941. He was a scholarship recipient of the Schultzberg Foundation at the Charité in Berlin, the West German Jaw Clinic in Düsseldorf-Morf, and the Krupp Dental Clinic in Essen in 1936. He was the secretary of the North V. Skåne Dental Association in 1935, the club master there in 1938, and the chairman in 1939. He was a member of Ängelholm's construction committee in 1940, and the chairman of the official section of the Gothenburg Dental Association division from 1942-47. He was the secretary of the Gothenburg Dental Association from 1943-47.",
    "structured": {
        "@context": "https://schema.org",
        "@type": "Person",
        "name": "Nils Amylon",
        "jobTitle": "Dentist",
        "birthPlace": "HälsingboTg",
        "birthDate": "1905-02-28",
        "parents": [
            {
                "@type": "Person",
                "name": "J.A. Amyloin"
            },
            {
                "@type": "Person",
                "name": "Anna Boman"
            }
        ],
        "spouse": [
            {
                "@type": "Person",
                "name": "Anna-Liisa Paulison"
            },
            {
                "@type": "Person",
                "name": "Brita Svensison"
            }
        ],
        "children": [
            {
                "@type": "Person",
                "name": "Margot",
                "birthDate": "1935"
            },
            {
                "@type": "Person",
                "name": "Rodif",
                "birthDate": "1937"
            },
            {
                "@type": "Person",
                "name": "Nils O^l-oif",
                "birthDate": "1939"
            }
        ],
        "memberOf": [
            {
                "@type": "Organization",
                "name": "North V. Skåne Dental Association"
            },
            {
                "@type": "Organization",
                "name": "Ängelholm's construction committee"
            },
            {
                "@type": "Organization",
                "name": "Gothenburg Dental Association"
            }
        ],
        "education": [
            {
                "@type": "EducationalOccupationalCredential",
                "credentialCategory": "student exams",
                "recognizedBy": {
                    "@type": "Organization",
                    "name": "Hälsingborg"
                },
                "value": "1924"
            },
            {
                "@type": "EducationalOccupationalCredential",
                "credentialCategory": "dental student",
                "recognizedBy": {
                    "@type": "Organization",
                    "name": "Hälsingborg"
                },
                "value": "1927"
            },
            {
                "@type": "EducationalOccupationalCredential",
                "credentialCategory": "dental practitioner",
                "recognizedBy": {
                    "@type": "Organization",
                    "name": "Hälsingborg"
                },
                "value": "1930"
            }
        ],
        "hasOccupation": [
            {
                "@type": "MedicalBusiness",
                "name": "Eskilstuna",
                "startDate": "1930",
                "endDate": "1930",
                "jobTitle": "Dental Practitioner",
                "description": "Worked in Eskilstuna in 1930"
            },
            {
                "@type": "MedicalBusiness",
                "name": "Ängelholm",
                "jobTitle": "Practice Owner, Consultant Dentist",
                "description": "Worked as a practice owner and consultant dentist in Ängelholm"
            },
            {
                "@type": "MedicalBusiness",
                "name": "Barkåkra 'S:t",
                "jobTitle": "Coal Mine Dentist",
                "description": "Worked as a coal mine dentist in Barkåkra 'S:t"
            },
            {
                "@type": "GovernmentOrganization",
                "name": "Gothenburg",
                "jobTitle": "Dental Practitioner",
                "description": "Has been in the service of Gothenburg since 1941"
            }
        ],
        "awards": [
            {
                "@type": "Scholarship",
                "name": "Schultzberg Foundation",
                "description": "Scholarship recipient of the Schultzberg Foundation at the Charité in Berlin"
            },
            {
                "@type": "Scholarship",
                "name": "West German Jaw Clinic",
                "description": "Scholarship recipient of the West German Jaw Clinic in Düsseldorf-Morf"
            },
            {
                "@type": "Scholarship",
                "name": "Krupp Dental Clinic",
                "description": "Scholarship recipient of the Krupp Dental Clinic in Essen in 1936"
            }
        ]
    }
}