{
    "original": "Engdahl, Gustaf Reinhold, major, Göteborg, f. 4/12/03 i Väckelsång, Kronob. 1., av löjtn. Sven Gustaf E. o. HiMa Maria Sandberg. G. 28 m. Maud Ernestine Elliot. Barn: Yvonne Marie-Louise f. 31. — Stud :ex. i Eksiö 23, kustart :off :ex. v. sjökrigssk. 25, kustart. skjutsk. ak 28, KSHS ak 29-30 m. bef :övn. 31, arméns gasoff :k. 31 o. 34, SS 32, kiurs’ i art. f. öub :o’ff. v. KA 32, f. p-ersioimadlv :oiff. v. fisit. 42, i soc :-psyk. v. KA-imsp. 44, i ikriigsigravtj. v. flsit. 44. Priv. utir :reis. ’Siamitkomm. m. flygpil:-kry&amp;s. Gotland t. TyskL, Holl., Span. o. Engl. 35-36. KA-kadett 23, fänr. v. KA 25, und:löjtn. 27, löjtn. 29, kapt. 36, major 45. P’lac. v. Vaxholms’ KA-reg. 25, v. Älvsb. KA-reg. fr. 42. Ka-dettoff. å flygpl :kryss. Gotland v. långresa 35-36, komp :off. v. arméns uoffsk. 36-38, chef f. KA ’Stud:komp. 35-38, skjutkurs f. res :kadetter 39-40, f. stamkad. 40, förber. art:kurs f. res:-off. 39-40, ^sign:sk. 44. Tjg. v. tygförv. VF 40, adj. v. sjöfrontsart :sk. 41. Avd:chef v. reg:’Stab. fr. 45. Led. av komm. f. utarb. av instr. i hydrofontj. 41, ’suppil. f. ordf. i MDV bàlMin :råd 42- 46, personalv :off. fr. 42, ordf. i civ:-anst:nd fr. 46. Styr:led. i Gbgs ma-rinlottakårs marinhem fr. 42, i fören. Sv. flaggans dag i Gbg arb :utsk. fr. 43, i stift. KA 4 s-oldathem fr. 44, kas-saförv. i div. ideelda fören. Skr.: div. kompend. i mil. ämnen 31-35. RSO.",
    "translated": "Engdahl, Gustaf Reinhold, Major, Gothenburg, born December 4th, 1903 in Väckelsång, Kronoberg County, firstborn of Lieutenant Sven Gustaf E. and HiMa Maria Sandberg. Married to Maud Ernestine Elliot in 1928. They have one child: Yvonne Marie-Louise, born in 1931. Completed his studentexamen in Eksjö in 1923, coast artillery officer exam at the Naval Academy in 1925, coast artillery shooting school at the Artillery Shooting School in 1928, Royal Swedish Army Staff College course in 1929-1930 with subsequent exercise in 1931, army gas-officer course in 1931 and 1934, air defense officer course at the State Defense Staff in 1932, field officer course in artillery from the Artillery and Engineering School in 1942, social and psychological course at the State Defense Staff in 1944, and war graves course at the State Defense Staff in 1944. Privately travelled to Siam as part of a delegation with a flying boat squadron to Germany, Holland, Spain, and England in 1935-1936. Enrolled at the Military Academy in 1923, promoted to second lieutenant in 1927, to lieutenant in 1929, to captain in 1936, and to major in 1945. Stationed at Vaxholm Coastal Artillery Regiment in 1925, then at Älvsborg Coastal Artillery Regiment from 1942. Cadet officer for a flying boat squadron at Gotland for a long trip in 1935-1936, company officer at the Army Noncommissioned Officers School from 1936-1938, head of the Military Academy's student company from 1935-1938, shooting course for reservist cadets in 1939-1940, standing cadet in 1940, preparatory course for artillery officers from the reserve in 1939-1940, and signed up for the army's intelligence service in 1944. Currently serving at the ammunition depot of the Swedish Armed Forces in 1940 and as an adjutant for the naval frontline artillery school in 1941. Department Chief of the regimental headquarters since 1945. Led committee for the development of a manual in hydrophonics in 1941, supplementary member for the chairman in the Director-General of Military Affairs Council in 1942-1946, a personal officer since 1942, and chairman in the civilian employee commission since 1946. Steering committee member of the Gothenburg Marine Volunteer Corps marine home since 1942, in the Swedish Flag Association's working committee for Gothenburg since 1943, in the bishopric's KA 4 soldier home since 1944, and treasurer for various non-profit associations. Authored several compendiums on military topics from 1931-1935. Recipient of the Royal Order of the Sword.",
    "structured_raw": "{\n  \"@context\": \"https://schema.org\",\n  \"@type\": \"Person\",\n  \"name\": \"Gustaf Reinhold Engdahl\",\n  \"birthDate\": \"1903-12-04\",\n  \"birthPlace\": {\n      \"@type\": \"PostalAddress\",\n      \"addressLocality\": \"Väckelsång\",\n      \"addressRegion\": \"Kronoberg County\",\n      \"addressCountry\": \"Sweden\"\n  },\n  \"nationality\": \"Swedish\",\n  \"alumniOf\": [\n      {\n          \"@type\": \"EducationalOrganization\",\n          \"name\": \"Eksjö\"\n      },\n      {\n          \"@type\": \"EducationalOrganization\",\n          \"name\": \"Royal Swedish Army Staff College\"\n      },\n      {\n          \"@type\": \"EducationalOrganization\",\n          \"name\": \"Naval Academy\"\n      },\n      {\n          \"@type\": \"EducationalOrganization\",\n          \"name\": \"Artillery Shooting School\"\n      },\n      {\n          \"@type\": \"EducationalOrganization\",\n          \"name\": \"State Defense Staff\"\n      },\n      {\n          \"@type\": \"EducationalOrganization\",\n          \"name\": \"Artillery and Engineering School\"\n      }\n  ],\n  \"parent\": [\n      {\n          \"@type\": \"Person\",\n          \"name\": \"Sven Gustaf Engdahl\",\n          \"jobTitle\": \"Lieutenant\"\n      },\n      {\n          \"@type\": \"Person\",\n          \"name\": \"HiMa Maria Sandberg\"\n      }\n  ],\n  \"spouse\": {\n      \"@type\": \"Person\",\n      \"name\": \"Maud Ernestine Elliot\",\n      \"marriageDate\": \"1928\"\n  },\n  \"children\": {\n      \"@type\": \"Person\",\n      \"name\": \"Yvonne Marie-Louise\",\n      \"birthDate\": \"1931\"\n  },\n  \"jobTitle\": \"Major\",\n  \"worksFor\": [\n      {\n          \"@type\": \"Organization\",\n          \"name\": \"Vaxholm Coastal Artillery Regiment\"\n      },\n      {\n          \"@type\": \"Organization\",\n          \"name\": \"Älvsborg Coastal Artillery Regiment\"\n      },\n      {\n          \"@type\": \"Organization\",\n          \"name\": \"Swedish Armed Forces Ammunition Depot\"\n      },\n      {\n          \"@type\": \"Organization\",\n          \"name\": \"Naval Frontline Artillery School\"\n      }\n  ],\n  \"memberOf\": [\n      {\n          \"@type\": \"Organization\",\n          \"name\": \"Swedish Flag Association\"\n      },\n      {\n          \"@type\": \"Organization\",\n          \"name\": \"KA 4 Soldier Home\"\n      },\n      {\n          \"@type\": \"Organization\",\n          \"name\": \"Gothenburg Marine Volunteer Corps Marine Home\"\n      },\n      {\n          \"@type\": \"Organization\",\n          \"name\": \"Director-General of Military Affairs Council\"\n      },\n      {\n          \"@type\": \"Organization\",\n          \"name\": \"Civilian Employee Commission\"\n      }\n  ],\n  \"event\": [\n      {\n          \"@type\": \"EducationalEvent\",\n          \"name\": \"Coast Artillery Officer Exam\",\n          \"startDate\": \"1925\"\n      },\n      {\n          \"@type\": \"EducationalEvent\",\n          \"name\": \"Coast Artillery Shooting School\",\n          \"startDate\": \"1928\"\n      },\n      {\n          \"@type\": \"EducationalEvent\",\n          \"name\": \"Army Gas-Officer Course\",\n          \"startDate\": \"1931\",\n          \"endDate\": \"1934\"\n      },\n      {\n          \"@type\": \"EducationalEvent\",\n          \"name\": \"Air Defense Officer Course\",\n          \"startDate\": \"1932\"\n      },\n      {\n          \"@type\": \"EducationalEvent\",\n          \"name\": \"Field Officer Course\",\n          \"startDate\": \"1942\"\n      },\n      {\n          \"@type\": \"EducationalEvent\",\n          \"name\": \"Social and Psychological Course\",\n          \"startDate\": \"1944\"\n      },\n      {\n          \"@type\": \"EducationalEvent\",\n          \"name\": \"War Graves Course\",\n          \"startDate\": \"1944\"\n      }\n  ],\n  \"knowsAbout\": [\n      \"Military Affairs\"\n  ],\n  \"description\": \"Gustaf Reinhold Engdahl was a Swedish Major born on December 4th, 1903 in Väckelsång, Kronoberg County. He completed his studentexamen in Eksjö in 1923 and had extensive military education. Engdahl was stationed in various organizations including Vaxholm Coastal Artillery Regiment, Älvsborg Coastal Artillery Regiment, Swedish Armed Forces Ammunition Depot, and Naval Frontline Artillery School. He was also a member of several associations such as Swedish Flag Association, KA 4 Soldier Home, Gothenburg Marine Volunteer Corps Marine Home, Director-General of Military Affairs Council, and Civilian Employee Commission.\"\n}",
    "structured": {
        "@context": "https://schema.org",
        "@type": "Person",
        "name": "Gustaf Reinhold Engdahl",
        "birthDate": "1903-12-04",
        "birthPlace": {
            "@type": "PostalAddress",
            "addressLocality": "Väckelsång",
            "addressRegion": "Kronoberg County",
            "addressCountry": "Sweden"
        },
        "nationality": "Swedish",
        "alumniOf": [
            {
                "@type": "EducationalOrganization",
                "name": "Eksjö"
            },
            {
                "@type": "EducationalOrganization",
                "name": "Royal Swedish Army Staff College"
            },
            {
                "@type": "EducationalOrganization",
                "name": "Naval Academy"
            },
            {
                "@type": "EducationalOrganization",
                "name": "Artillery Shooting School"
            },
            {
                "@type": "EducationalOrganization",
                "name": "State Defense Staff"
            },
            {
                "@type": "EducationalOrganization",
                "name": "Artillery and Engineering School"
            }
        ],
        "parent": [
            {
                "@type": "Person",
                "name": "Sven Gustaf Engdahl",
                "jobTitle": "Lieutenant"
            },
            {
                "@type": "Person",
                "name": "HiMa Maria Sandberg"
            }
        ],
        "spouse": {
            "@type": "Person",
            "name": "Maud Ernestine Elliot",
            "marriageDate": "1928"
        },
        "children": {
            "@type": "Person",
            "name": "Yvonne Marie-Louise",
            "birthDate": "1931"
        },
        "jobTitle": "Major",
        "worksFor": [
            {
                "@type": "Organization",
                "name": "Vaxholm Coastal Artillery Regiment"
            },
            {
                "@type": "Organization",
                "name": "Älvsborg Coastal Artillery Regiment"
            },
            {
                "@type": "Organization",
                "name": "Swedish Armed Forces Ammunition Depot"
            },
            {
                "@type": "Organization",
                "name": "Naval Frontline Artillery School"
            }
        ],
        "memberOf": [
            {
                "@type": "Organization",
                "name": "Swedish Flag Association"
            },
            {
                "@type": "Organization",
                "name": "KA 4 Soldier Home"
            },
            {
                "@type": "Organization",
                "name": "Gothenburg Marine Volunteer Corps Marine Home"
            },
            {
                "@type": "Organization",
                "name": "Director-General of Military Affairs Council"
            },
            {
                "@type": "Organization",
                "name": "Civilian Employee Commission"
            }
        ],
        "event": [
            {
                "@type": "EducationalEvent",
                "name": "Coast Artillery Officer Exam",
                "startDate": "1925"
            },
            {
                "@type": "EducationalEvent",
                "name": "Coast Artillery Shooting School",
                "startDate": "1928"
            },
            {
                "@type": "EducationalEvent",
                "name": "Army Gas-Officer Course",
                "startDate": "1931",
                "endDate": "1934"
            },
            {
                "@type": "EducationalEvent",
                "name": "Air Defense Officer Course",
                "startDate": "1932"
            },
            {
                "@type": "EducationalEvent",
                "name": "Field Officer Course",
                "startDate": "1942"
            },
            {
                "@type": "EducationalEvent",
                "name": "Social and Psychological Course",
                "startDate": "1944"
            },
            {
                "@type": "EducationalEvent",
                "name": "War Graves Course",
                "startDate": "1944"
            }
        ],
        "knowsAbout": [
            "Military Affairs"
        ],
        "description": "Gustaf Reinhold Engdahl was a Swedish Major born on December 4th, 1903 in Väckelsång, Kronoberg County. He completed his studentexamen in Eksjö in 1923 and had extensive military education. Engdahl was stationed in various organizations including Vaxholm Coastal Artillery Regiment, Älvsborg Coastal Artillery Regiment, Swedish Armed Forces Ammunition Depot, and Naval Frontline Artillery School. He was also a member of several associations such as Swedish Flag Association, KA 4 Soldier Home, Gothenburg Marine Volunteer Corps Marine Home, Director-General of Military Affairs Council, and Civilian Employee Commission."
    }
}