{
    "original": "Bliding, Carl Vilhelm, lektor, Borås, f. 6/4/91 i Almundsryd, Kronob. 1. G. 32 m. Ruth Bohlin. Barn: Carl-Ragnar f. 33, Lars Äke 36. — Stud:ex. i Växjö 10, fil. mag. 15, fil. Hc. 26, fil. dr 28, provår 23. Res. t. VA havsbiolog. station Kristineberg 24 o. 31-43. E. o. aman. v. botan. inst. 16, lär. i Falkenberg 17-19, ord. ämneslär. där 19, adj. där 28, lektor i biol. o. kemi v. Borås h. a. 1. sed. 28. Led. av Falkenbergs folksk:styr. 21-26. Skr.: ett 10-tal avh. om algernas utv. o. systematik. RNO 44.",
    "translated": "Bliding, Carl Vilhelm, lecturer, Borås, b. 6/4/91 in Almundsryd, Kronob. Married in 1932 to Ruth Bohlin. Children: Carl-Ragnar b. 1933, Lars Äke b. 1936. Educational background: High school diploma in Växjö 1910, Bachelor of Arts 1915, Filosofie Hc. 1926, Doctor of Philosophy 1928, probationary year 1923. Residency at the Kristineberg Oceanographic Research Station in 1924 and 1931-1943. Assistant curator at the Botanical Institute 1916, teacher in Falkenberg 1917-1919, regular subject teacher there in 1919, associate professor there in 1928, lecturer in biology and chemistry at Borås high school from 1928. Member of the Falkenberg Board of Education 1921-1926. Author of about ten works on the evolution and systematics of algae. Awarded the Royal Order of the North Star in 1944.",
    "structured_raw": "{\n    \"@context\": \"http://schema.org\",\n    \"@type\": \"Person\",\n    \"name\": \"Carl Vilhelm Bliding\",\n    \"jobTitle\": \"lecturer\",\n    \"birthDate\": \"1891-06-04\",\n    \"birthPlace\": \"Almundsryd, Kronob\",\n    \"spouse\": {\n        \"@type\": \"Person\",\n        \"name\": \"Ruth Bohlin\",\n        \"marriageDate\": \"1932\"\n    },\n    \"children\": [\n        {\n            \"@type\": \"Person\",\n            \"name\": \"Carl-Ragnar Bliding\",\n            \"birthDate\": \"1933\"\n        },\n        {\n            \"@type\": \"Person\",\n            \"name\": \"Lars Äke Bliding\",\n            \"birthDate\": \"1936\"\n        }\n    ],\n    \"alumniOf\": [\n        {\n            \"@type\": \"EducationalOrganization\",\n            \"name\": \"Växjö High School\",\n            \"endDate\": \"1910\"\n        },\n        {\n            \"@type\": \"EducationalOrganization\",\n            \"name\": \"Unknown University\",\n            \"degreeName\": \"Bachelor of Arts\",\n            \"endDate\": \"1915\"\n        },\n        {\n            \"@type\": \"EducationalOrganization\",\n            \"name\": \"Unknown University\",\n            \"degreeName\": \"Filosofie Hc.\",\n            \"endDate\": \"1926\"\n        },\n        {\n            \"@type\": \"EducationalOrganization\",\n            \"name\": \"Unknown University\",\n            \"degreeName\": \"Doctor of Philosophy\",\n            \"endDate\": \"1928\"\n        }\n    ],\n    \"worksFor\": {\n        \"@type\": \"Organization\",\n        \"name\": \"Borås High School\",\n        \"startDate\": \"1928\"\n    },\n    \"memberOf\": [\n        {\n            \"@type\": \"Organization\",\n            \"name\": \"Falkenberg Board of Education\",\n            \"startDate\": \"1921\",\n            \"endDate\": \"1926\"\n        }\n    ],\n    \"sameAs\": [] \n}",
    "structured": {
        "@context": "http://schema.org",
        "@type": "Person",
        "name": "Carl Vilhelm Bliding",
        "jobTitle": "lecturer",
        "birthDate": "1891-06-04",
        "birthPlace": "Almundsryd, Kronob",
        "spouse": {
            "@type": "Person",
            "name": "Ruth Bohlin",
            "marriageDate": "1932"
        },
        "children": [
            {
                "@type": "Person",
                "name": "Carl-Ragnar Bliding",
                "birthDate": "1933"
            },
            {
                "@type": "Person",
                "name": "Lars Äke Bliding",
                "birthDate": "1936"
            }
        ],
        "alumniOf": [
            {
                "@type": "EducationalOrganization",
                "name": "Växjö High School",
                "endDate": "1910"
            },
            {
                "@type": "EducationalOrganization",
                "name": "Unknown University",
                "degreeName": "Bachelor of Arts",
                "endDate": "1915"
            },
            {
                "@type": "EducationalOrganization",
                "name": "Unknown University",
                "degreeName": "Filosofie Hc.",
                "endDate": "1926"
            },
            {
                "@type": "EducationalOrganization",
                "name": "Unknown University",
                "degreeName": "Doctor of Philosophy",
                "endDate": "1928"
            }
        ],
        "worksFor": {
            "@type": "Organization",
            "name": "Borås High School",
            "startDate": "1928"
        },
        "memberOf": [
            {
                "@type": "Organization",
                "name": "Falkenberg Board of Education",
                "startDate": "1921",
                "endDate": "1926"
            }
        ],
        "sameAs": []
    }
}