{
    "original": "Bergquist, Harry JuHus Albin, lektor, Göteborg, f. 15/4/00 i Härad, Södermani. 1., av folksk :lär. o. musikdir. Janne B. o. Julia Peterson. G. 32 m. fil. mag. Ester Nordin. Barn: Birgit- ta f. 37, Ragnihild 42. ~ Stud:ex. 18, fil. kand. 22, fil. mag. 24, fil. lic. 32, fil. dr 33 samt provår 32-33, allt i Sthlm, stud. v. Kristinebergs zool. stat. somr. 19, 24 o. 25. Stud:res. t. TyskL, Schweiz, Frankr., Ital., Tyro-len, Norge, Finl., Danm. m. fl. Lär. f. H. K. H. Hertigen av Småland 24- 27, f. H. K. H. Hertigen av Dalarna 27-28, doc. i zoologi v. Sthlms högsk. 32-36, periodv. vik. adj. samt e. lär. v. olika lärov. i Sthlm 27-36, lektor i biol. m. hälsolära o. kemi v. Vänersborgs h. a. 1. 36-42, dito v. h. a. 1. i Majorna i Gbg sed. 42. Tjänstegrens-chef f. gasskyddet i Vänersborg 38-42, under samma tid bitr. länsstyr. m. ett filert. kurser i gas skyddstjänst i olika delar av länet. Ordf. i Sthlms kristl. situd:fören. 26-28, led. av styr. f. Sv:es kriistl. studentrörelse, stift. Studihemmet i Sthlm 27-36, ordf. i Sthlms högsk. zoologkl. 31-32, idépo-litiskt arb. i den nysv. rör., sekr. i v. krets, av Biologilär. fören. m. m. Skr.: Jämf.-anat. studie över hjärnkärnor-nas utveckl. i mellanhjärnan h. lägre ryggradsdjur (grad:avh.), skilda upps. i tidn. o. tidskr.",
    "translated": "Bergquist, Harry JuHus Albin, lecturer, Gothenburg, born April 15th, 1900 in Härad, Södermani. First-born child of elementary school teacher and music director Janne B. and Julia Peterson. Married in 1932 to Ester Nordin, who holds a degree in philology. They have two children: Birgit-ta (born in 1937) and Ragnihild (born in 1942). Harry passed his matriculation exam in 1918 and obtained his Bachelor of Arts degree in 1922, his Master of Arts degree in 1924, his Licentiate of Philosophy degree in 1932, and his Doctorate of Philosophy degree in 1933 - all in Stockholm. He studied at Kristinebergs Zoological Station during the summers of 1919, 1924, and 1925, and conducted study trips to Germany, Switzerland, France, Italy, Tyrol, Norway, Finland, Denmark, and other countries. He was a lecturer for the Duke of Smaland from 1924 to 1927 and for the Duke of Dalarna from 1927 to 1928. From 1932 to 1936, he was a docent in zoology at Stockholm University, and from 1927 to 1936, he served as a temporary adjunct and regular teacher at various high schools in Stockholm. From 1936 to 1942, he was a lecturer in biology, health science, and chemistry at the high school in Vänersborg, and then transferred to the same position at the high school in Majorna, Gothenburg, where he has been since 1942. From 1938 to 1942, he served as the head of the gas protection department in Vänersborg, while also assisting the county government with a series of courses on gas protection services held throughout the county. He was the chairman of the Stockholm Christian Situd Society from 1926 to 1928, a member of the board of the Swedish Christian Student Movement, and a founder of the student home in Stockholm from 1927 to 1936. He was also the chairman of the Zoological Club of Stockholm University from 1931 to 1932, and was involved in ideological work in the emerging Swedish movement, serving as the secretary in various circles of the Biology Teachers Association, among other things. Harry's academic work includes a comparative anatomical study of the development of brain nuclei in midbrain and lower vertebrates (degree thesis), as well as various publications in newspapers and journals.",
    "structured_raw": "{\n\t\"@context\": \"https://schema.org\",\n\t\"@type\": \"Person\",\n\t\"name\": \"Harry JuHus Albin Bergquist\",\n\t\"birthDate\": \"1900-04-15\",\n\t\"birthPlace\": \"Härad, Södermani\",\n\t\"nationality\": \"Swedish\",\n\t\"occupation\": \"Lecturer\",\n\t\"description\": \"Swedish lecturer and expert in zoology\",\n\t\"spouse\": {\n\t\t\"@type\": \"Person\",\n\t\t\"name\": \"Ester Nordin\",\n\t\t\"education\": \"Philology\"\n\t},\n\t\"children\": [\n\t\t{\n\t\t\t\"@type\": \"Person\",\n\t\t\t\"name\": \"Birgitta Bergquist\",\n\t\t\t\"birthDate\": \"1937\"\n\t\t},\n\t\t{\n\t\t\t\"@type\": \"Person\",\n\t\t\t\"name\": \"Ragnihild Bergquist\",\n\t\t\t\"birthDate\": \"1942\"\n\t\t}\n\t],\n\t\"parent\": [\n\t\t{\n\t\t\t\"@type\": \"Person\",\n\t\t\t\"name\": \"Janne B.\",\n\t\t\t\"jobTitle\": \"Elementary School Teacher and Music Director\"\n\t\t},\n\t\t{\n\t\t\t\"@type\": \"Person\",\n\t\t\t\"name\": \"Julia Peterson\"\n\t\t}\n\t],\n\t\"education\": [\n\t\t{\n\t\t\t\"endDate\": \"1918\",\n\t\t\t\"institution\": \"Stud\",\n\t\t\t\"description\": \"Studied at Kristinebergs Zoological Station during the summers of 1919, 1924, and 1925\"\n\t\t},\n\t\t{\n\t\t\t\"startDate\": \"1918\",\n\t\t\t\"endDate\": \"1922\",\n\t\t\t\"institution\": \"Sthlm\",\n\t\t\t\"degree\": \"Bachelor of Arts\"\n\t\t},\n\t\t{\n\t\t\t\"startDate\": \"1922\",\n\t\t\t\"endDate\": \"1924\",\n\t\t\t\"institution\": \"Sthlm\",\n\t\t\t\"degree\": \"Master of Arts\"\n\t\t},\n\t\t{\n\t\t\t\"startDate\": \"1924\",\n\t\t\t\"endDate\": \"1932\",\n\t\t\t\"institution\": \"Sthlm\",\n\t\t\t\"degree\": \"Licentiate of Philosophy\"\n\t\t},\n\t\t{\n\t\t\t\"startDate\": \"1932\",\n\t\t\t\"endDate\": \"1933\",\n\t\t\t\"institution\": \"Sthlm\",\n\t\t\t\"degree\": \"Doctorate of Philosophy\"\n\t\t}\n\t],\n\t\"workExperience\": [\n\t\t{\n\t\t\t\"startDate\": \"1924\", \n\t\t\t\"endDate\": \"1927\",\n\t\t\t\"position\": \"Lecturer\",\n\t\t\t\"description\": \"Lecturer for the Duke of Smaland\"\n\t\t},\n\t\t{\n\t\t\t\"startDate\": \"1927\", \n\t\t\t\"endDate\": \"1928\",\n\t\t\t\"position\": \"Lecturer\",\n\t\t\t\"description\": \"Lecturer for the Duke of Dalarna\"\n\t\t},\n\t\t{\n\t\t\t\"startDate\": \"1932\",\n\t\t\t\"endDate\": \"1936\",\n\t\t\t\"position\": \"Docent in Zoology\",\n\t\t\t\"employer\": \"Stockholm University\"\n\t\t},\n\t\t{\n\t\t\t\"startDate\": \"1927\",\n\t\t\t\"endDate\": \"1936\",\n\t\t\t\"position\": \"Temporary Adjunct and Regular Teacher\",\n\t\t\t\"employer\": \"Various high schools in Stockholm\"\n\t\t},\n\t\t{\n\t\t\t\"startDate\": \"1936\",\n\t\t\t\"endDate\": \"1942\",\n\t\t\t\"position\": \"Lecturer in Biology, Health Science, and Chemistry\",\n\t\t\t\"employer\": \"High school in Vänersborg\"\n\t\t},\n\t\t{\n\t\t\t\"startDate\": \"1942\",\n\t\t\t\"position\": \"Lecturer in Biology, Health Science, and Chemistry\",\n\t\t\t\"employer\": \"High school in Majorna, Gothenburg\"\n\t\t},\n\t\t{\n\t\t\t\"startDate\": \"1938\",\n\t\t\t\"endDate\": \"1942\",\n\t\t\t\"position\": \"Head of the Gas Protection Department\",\n\t\t\t\"employer\": \"Vänersborg\"\n\t\t}\n\t],\n\t\"society\": [\n\t\t{\n\t\t\t\"startDate\": \"1926\",\n\t\t\t\"endDate\": \"1928\",\n\t\t\t\"position\": \"Chairman\",\n\t\t\t\"name\": \"Stockholm Christian Situd Society\"\n\t\t},\n\t\t{\n\t\t\t\"position\": \"Member of the Board\",\n\t\t\t\"name\": \"Swedish Christian Student Movement\"\n\t\t}\n\t],\n\t\"memberOf\": [\n\t\t{\n\t\t\t\"startDate\": \"1927\",\n\t\t\t\"endDate\": \"1936\",\n\t\t\t\"position\": \"Founder\",\n\t\t\t\"name\": \"Student Home in Stockholm\"\n\t\t},\n\t\t{\n\t\t\t\"startDate\": \"1931\",\n\t\t\t\"endDate\": \"1932\",\n\t\t\t\"position\": \"Chairman\",\n\t\t\t\"name\": \"Zoological Club of Stockholm University\"\n\t\t},\n\t\t{\n\t\t\t\"position\": \"Secretary\",\n\t\t\t\"name\": \"Biology Teachers Association\"\n\t\t}\n\t],\n\t\"publication\": [\n\t\t{\n\t\t\t\"name\": \"Comparative Anatomical Study of the Development of Brain Nuclei in Midbrain and Lower Vertebrates\",\n\t\t\t\"description\": \"Degree Thesis\"\n\t\t}\n\t]\n}",
    "structured": {
        "@context": "https://schema.org",
        "@type": "Person",
        "name": "Harry JuHus Albin Bergquist",
        "birthDate": "1900-04-15",
        "birthPlace": "Härad, Södermani",
        "nationality": "Swedish",
        "occupation": "Lecturer",
        "description": "Swedish lecturer and expert in zoology",
        "spouse": {
            "@type": "Person",
            "name": "Ester Nordin",
            "education": "Philology"
        },
        "children": [
            {
                "@type": "Person",
                "name": "Birgitta Bergquist",
                "birthDate": "1937"
            },
            {
                "@type": "Person",
                "name": "Ragnihild Bergquist",
                "birthDate": "1942"
            }
        ],
        "parent": [
            {
                "@type": "Person",
                "name": "Janne B.",
                "jobTitle": "Elementary School Teacher and Music Director"
            },
            {
                "@type": "Person",
                "name": "Julia Peterson"
            }
        ],
        "education": [
            {
                "endDate": "1918",
                "institution": "Stud",
                "description": "Studied at Kristinebergs Zoological Station during the summers of 1919, 1924, and 1925"
            },
            {
                "startDate": "1918",
                "endDate": "1922",
                "institution": "Sthlm",
                "degree": "Bachelor of Arts"
            },
            {
                "startDate": "1922",
                "endDate": "1924",
                "institution": "Sthlm",
                "degree": "Master of Arts"
            },
            {
                "startDate": "1924",
                "endDate": "1932",
                "institution": "Sthlm",
                "degree": "Licentiate of Philosophy"
            },
            {
                "startDate": "1932",
                "endDate": "1933",
                "institution": "Sthlm",
                "degree": "Doctorate of Philosophy"
            }
        ],
        "workExperience": [
            {
                "startDate": "1924",
                "endDate": "1927",
                "position": "Lecturer",
                "description": "Lecturer for the Duke of Smaland"
            },
            {
                "startDate": "1927",
                "endDate": "1928",
                "position": "Lecturer",
                "description": "Lecturer for the Duke of Dalarna"
            },
            {
                "startDate": "1932",
                "endDate": "1936",
                "position": "Docent in Zoology",
                "employer": "Stockholm University"
            },
            {
                "startDate": "1927",
                "endDate": "1936",
                "position": "Temporary Adjunct and Regular Teacher",
                "employer": "Various high schools in Stockholm"
            },
            {
                "startDate": "1936",
                "endDate": "1942",
                "position": "Lecturer in Biology, Health Science, and Chemistry",
                "employer": "High school in Vänersborg"
            },
            {
                "startDate": "1942",
                "position": "Lecturer in Biology, Health Science, and Chemistry",
                "employer": "High school in Majorna, Gothenburg"
            },
            {
                "startDate": "1938",
                "endDate": "1942",
                "position": "Head of the Gas Protection Department",
                "employer": "Vänersborg"
            }
        ],
        "society": [
            {
                "startDate": "1926",
                "endDate": "1928",
                "position": "Chairman",
                "name": "Stockholm Christian Situd Society"
            },
            {
                "position": "Member of the Board",
                "name": "Swedish Christian Student Movement"
            }
        ],
        "memberOf": [
            {
                "startDate": "1927",
                "endDate": "1936",
                "position": "Founder",
                "name": "Student Home in Stockholm"
            },
            {
                "startDate": "1931",
                "endDate": "1932",
                "position": "Chairman",
                "name": "Zoological Club of Stockholm University"
            },
            {
                "position": "Secretary",
                "name": "Biology Teachers Association"
            }
        ],
        "publication": [
            {
                "name": "Comparative Anatomical Study of the Development of Brain Nuclei in Midbrain and Lower Vertebrates",
                "description": "Degree Thesis"
            }
        ]
    }
}