{
    "original": "Lindström, Alf Bertil Erik, disponent, Norrköping, f. 3/2/12 i Oravais, Finl., av fabr. Abel L. o. Mary La-gergrén. G. 38 m. Brita Petersson, — Realsk. t. 27, handelssk. 28, dipl. tex-tiling. i Stuttgart-Reutlingen 31, tekn. praktik i Tyskl., Schweiz o. Engl. t. o. m. 33. Disp., verkst. dir. samt styr:-led. i A-B Abel Lindströms Tricot-fabr. i Norrköp. sed. 38, därjämte konsult, verksamh. f. trikåind. samt föreläs, i trikåtekn. kursen v. o. led. av styr. f. Lennings textiltekn. insi. i Norrköp. Medl. av Sv. textiltekn. riksförb., Norrköp. polytekn. fören.. Norrköp. fältrittklubb, Sthlms fältritt-kiubb, Civi’la ryttarförb. o. Norrköp. segelsällsk. Arl. branschstudie- o. inköpsresor t. flert. europ. länder t. o. m. 39. Skr.: Trikàvarans teknologi (succ. 40-46). Hobbies: ridning, segling, skidåkning. RyttarGm.",
    "translated": "Lindström, Alf Bertil Erik, manager, Norrköping, b. 3/2/12 in Oravais, Finland, son of factory owner Abel L. and Mary Lagergrén. Married in 1938 to Brita Petersson. Attended a secondary school until 1927, then a commercial school until 1928, and obtained a diploma in textile engineering in Stuttgart-Reutlingen in 1931. Completed technical internships in Germany, Switzerland, and England until 1933. Became a manager, executive director, and board member of A-B Abel Lindströms Tricot-factory in Norrköping starting from 1938. Also served as a consultant and engaged in activities related to the knitwear industry, including giving lectures in the knitwear technology course established by the board of Lennings Textile Technology Institute in Norrköping. Member of the Swedish textile engineering national association, Norrköping Polytechnic Association, Norrköping Equestrian Club, Stockholm Equestrian Club, Civil Equestrian Association, and Norrköping Sailing Club. Took industry-related study and procurement trips to several European countries until 1939. Author of \"Technology of Knitted Fabrics\" (successful from 1940-1946). Hobbies include horseback riding, sailing, and skiing. Married to an equestrian partner.",
    "structured_raw": "{\n  \"@context\": \"https://schema.org\",\n  \"@type\": \"Person\",\n  \"name\": \"Alf Bertil Erik Lindström\",\n  \"jobTitle\": \"Manager\",\n  \"birthDate\": \"1912-02-03\",\n  \"birthPlace\": \"Oravais, Finland\",\n  \"parents\": [\n    {\n      \"@type\": \"Person\",\n      \"name\": \"Abel Lindström\",\n      \"jobTitle\": \"Factory Owner\"\n    },\n    {\n      \"@type\": \"Person\",\n      \"name\": \"Mary Lagergrén\"\n    }\n  ],\n  \"spouse\": {\n    \"@type\": \"Person\",\n    \"name\": \"Brita Petersson\",\n    \"marriageDate\": \"1938\"\n  },\n  \"education\": [\n    {\n      \"@type\": \"EducationalOrganization\",\n      \"name\": \"Secondary School\"\n    },\n    {\n      \"@type\": \"EducationalOrganization\",\n      \"name\": \"Commercial School\",\n      \"endDate\": \"1928\"\n    },\n    {\n      \"@type\": \"EducationalOrganization\",\n      \"name\": \"Stuttgart-Reutlingen\",\n      \"specialty\": \"Textile Engineering\",\n      \"diplomaDate\": \"1931\"\n    }\n  ],\n  \"workHistory\": [\n    {\n      \"@type\": \"Organization\",\n      \"name\": \"A-B Abel Lindströms Tricot-fabr.\",\n      \"jobTitle\": \"Manager, Executive Director, Board Member\",\n      \"startDate\": \"1938\",\n      \"description\": \"Knitwear factory in Norrköping\"\n    }\n  ],\n  \"memberOf\": [\n    {\n      \"@type\": \"Organization\",\n      \"name\": \"Swedish Textile Engineering National Association\"\n    },\n    {\n      \"@type\": \"Organization\",\n      \"name\": \"Norrköping Polytechnic Association\"\n    },\n    {\n      \"@type\": \"Organization\",\n      \"name\": \"Norrköping Equestrian Club\"\n    },\n    {\n      \"@type\": \"Organization\",\n      \"name\": \"Stockholm Equestrian Club\"\n    },\n    {\n      \"@type\": \"Organization\",\n      \"name\": \"Civil Equestrian Association\"\n    },\n    {\n      \"@type\": \"Organization\",\n      \"name\": \"Norrköping Sailing Club\"\n    }\n  ],\n  \"hobbies\": [\n    \"Horseback Riding\",\n    \"Sailing\",\n    \"Skiing\"\n  ],\n  \"publications\": [\n    {\n      \"@type\": \"CreativeWork\",\n      \"name\": \"Technology of Knitted Fabrics\",\n      \"startDate\": \"1940\",\n      \"endDate\": \"1946\"\n    }\n  ]\n}",
    "structured": {
        "@context": "https://schema.org",
        "@type": "Person",
        "name": "Alf Bertil Erik Lindström",
        "jobTitle": "Manager",
        "birthDate": "1912-02-03",
        "birthPlace": "Oravais, Finland",
        "parents": [
            {
                "@type": "Person",
                "name": "Abel Lindström",
                "jobTitle": "Factory Owner"
            },
            {
                "@type": "Person",
                "name": "Mary Lagergrén"
            }
        ],
        "spouse": {
            "@type": "Person",
            "name": "Brita Petersson",
            "marriageDate": "1938"
        },
        "education": [
            {
                "@type": "EducationalOrganization",
                "name": "Secondary School"
            },
            {
                "@type": "EducationalOrganization",
                "name": "Commercial School",
                "endDate": "1928"
            },
            {
                "@type": "EducationalOrganization",
                "name": "Stuttgart-Reutlingen",
                "specialty": "Textile Engineering",
                "diplomaDate": "1931"
            }
        ],
        "workHistory": [
            {
                "@type": "Organization",
                "name": "A-B Abel Lindströms Tricot-fabr.",
                "jobTitle": "Manager, Executive Director, Board Member",
                "startDate": "1938",
                "description": "Knitwear factory in Norrköping"
            }
        ],
        "memberOf": [
            {
                "@type": "Organization",
                "name": "Swedish Textile Engineering National Association"
            },
            {
                "@type": "Organization",
                "name": "Norrköping Polytechnic Association"
            },
            {
                "@type": "Organization",
                "name": "Norrköping Equestrian Club"
            },
            {
                "@type": "Organization",
                "name": "Stockholm Equestrian Club"
            },
            {
                "@type": "Organization",
                "name": "Civil Equestrian Association"
            },
            {
                "@type": "Organization",
                "name": "Norrköping Sailing Club"
            }
        ],
        "hobbies": [
            "Horseback Riding",
            "Sailing",
            "Skiing"
        ],
        "publications": [
            {
                "@type": "CreativeWork",
                "name": "Technology of Knitted Fabrics",
                "startDate": "1940",
                "endDate": "1946"
            }
        ]
    }
}