{
    "original": "Bokelund, Nils Albert Julius, fd. läroverksadjunkt, Göteborg, f. 20/3/67 i Hälsingborg av bagarm. Aug. B. o. Amalia Nilsson. G. 92 m. A’lma Olsson. — Studiex. 85, fil. kand. i Lund ’89, pro vår i Lund 91. E. lär. i Hälsingborg 92-01, lärov:adj. i Skara 00-08, därefter v. Gbgs’ latin, lär. v. Gbgs gymn. f. fl. fr. 11. Led. av stads-fullm. i Skara 07-08, sekr. i Gbgs lär:sällsk. 13-16, v. ordf. 20-22, ordf. i Gbgs adj :-fören. 19-21, led. av styr. f. Lärovilär. riksförb. 21-26. Skr.: åtsk. läroböcker i tyska o. latin, upps. o. rec. i pedag. tidskr. o. dagl. tidn. RVO 23.",
    "translated": "Bokelund, Nils Albert Julius, former high school teacher, Gothenburg, born on March 20, 1867 in Helsingborg to baker August B. and Amalia Nilsson. Married to Alma Olsson in 1892. - Graduated from high school 1885, earned a Bachelor's degree in Lund in 1889, and became a teaching assistant in Lund in 1891. He was a teacher in Helsingborg from 1892 to 1901, a high school teacher in Skara from 1900 to 1908, and later a Latin teacher at Gothenburg's grammar school from 1911. He was a member of the city council in Skara from 1907 to 1908, secretary of the Gothenburg Teacher's Society from 1913 to 1916, vice president from 1920 to 1922, chairman of the Gothenburg Teacher's Association from 1919 to 1921, and a member of the board of the National Association of Teachers from 1921 to 1926. He wrote several textbooks in German and Latin, as well as articles and reviews in educational journals and newspapers. He was awarded the Royal Order of Vasa in 1923.",
    "structured_raw": "{\n  \"@context\": \"https://schema.org\",\n  \"@type\": \"Person\",\n  \"name\": \"Nils Albert Julius Bokelund\",\n  \"givenName\": \"Nils\",\n  \"familyName\": \"Bokelund\",\n  \"gender\": \"Male\",\n  \"birthDate\": \"1867-03-20\",\n  \"birthPlace\": \"Helsingborg, Sweden\",\n  \"deathDate\": null,\n  \"nationality\": \"Swedish\",\n  \"education\": [\n    {\n      \"@type\": \"EducationEvent\",\n      \"institution\": \"Lund University\",\n      \"studyType\": \"Bachelor's degree\",\n      \"startDate\": \"1885\",\n      \"endDate\": \"1889\"\n    }\n  ],\n  \"jobTitle\": \"Former high school teacher\",\n  \"worksFor\": {\n    \"@type\": \"Organization\",\n    \"name\": \"Gothenburg\"\n  },\n  \"spouse\": {\n    \"@type\": \"Person\",\n    \"name\": \"Alma Olsson\",\n    \"gender\": \"Female\",\n    \"marriageDate\": \"1892\"\n  },\n  \"memberOf\": [\n    {\n      \"@type\": \"Organization\",\n      \"name\": \"City Council of Skara\",\n      \"startDate\": \"1907\",\n      \"endDate\": \"1908\"\n    },\n    {\n      \"@type\": \"Organization\",\n      \"name\": \"Gothenburg Teacher's Society\",\n      \"roleName\": \"Secretary\",\n      \"startDate\": \"1913\",\n      \"endDate\": \"1916\"\n    },\n    {\n      \"@type\": \"Organization\",\n      \"name\": \"Gothenburg Teacher's Association\",\n      \"roleName\": \"Chairman\",\n      \"startDate\": \"1919\",\n      \"endDate\": \"1921\"\n    },\n    {\n      \"@type\": \"Organization\",\n      \"name\": \"National Association of Teachers\",\n      \"startDate\": \"1921\",\n      \"endDate\": \"1926\",\n      \"roleName\": \"Member of the Board\"\n    }\n  ],\n  \"description\": \"Swedish author of textbooks in German and Latin, as well as articles and reviews in educational journals and newspapers. He was also awarded the Royal Order of Vasa in 1923.\",\n  \"sameAs\": null\n}",
    "structured": {
        "@context": "https://schema.org",
        "@type": "Person",
        "name": "Nils Albert Julius Bokelund",
        "givenName": "Nils",
        "familyName": "Bokelund",
        "gender": "Male",
        "birthDate": "1867-03-20",
        "birthPlace": "Helsingborg, Sweden",
        "deathDate": null,
        "nationality": "Swedish",
        "education": [
            {
                "@type": "EducationEvent",
                "institution": "Lund University",
                "studyType": "Bachelor's degree",
                "startDate": "1885",
                "endDate": "1889"
            }
        ],
        "jobTitle": "Former high school teacher",
        "worksFor": {
            "@type": "Organization",
            "name": "Gothenburg"
        },
        "spouse": {
            "@type": "Person",
            "name": "Alma Olsson",
            "gender": "Female",
            "marriageDate": "1892"
        },
        "memberOf": [
            {
                "@type": "Organization",
                "name": "City Council of Skara",
                "startDate": "1907",
                "endDate": "1908"
            },
            {
                "@type": "Organization",
                "name": "Gothenburg Teacher's Society",
                "roleName": "Secretary",
                "startDate": "1913",
                "endDate": "1916"
            },
            {
                "@type": "Organization",
                "name": "Gothenburg Teacher's Association",
                "roleName": "Chairman",
                "startDate": "1919",
                "endDate": "1921"
            },
            {
                "@type": "Organization",
                "name": "National Association of Teachers",
                "startDate": "1921",
                "endDate": "1926",
                "roleName": "Member of the Board"
            }
        ],
        "description": "Swedish author of textbooks in German and Latin, as well as articles and reviews in educational journals and newspapers. He was also awarded the Royal Order of Vasa in 1923.",
        "sameAs": null
    }
}