{
    "original": "Lundvik, Vilhelm Göran, landshövding, förutv. statsråd, Vänersborg, f. 28/8/83 å Næs järnverk, Norge, av övering. Carl-Johan L. o. Ebba Simp-ler. G. 1. 15 m. Karin Alfthan, d. 19; 2. 22 m. Dagmar Lamm. Barn: Ulf f. 16. — Mog:ex. i Gävle 02, fil. kand. i Upps. 06, jur. kand. där 12. Attaché i UD 12, sekr. h. riksd. konstit :utsk. 13 o. 14, h. dess lagutsk. 15 samt h. kommunalskattekomm. 15-16, omb :-man h. Järnbruksförb. 16-19, handelsattaché o. -råd v. sv. beskickn. i Paris 19-25, tillika v. sv. beskickn. i Bryssel 21-25, handelsråds namn 26, tf. statssekr. i handelsdep. 25-26, statsråd o. ch. f. handdsdep. 2/10 28-7/6 30, verkst. dir. i Sv res indrförb. 26-41, landshövd. i Älvsb. län sed. 41. Sekr. v. sv. repr. i internat. komm. f. för-valtn. av Slesvig under folkomröstn. o. ch. f. komm. folkomröstn :byrå 20, led. - av NF ekon. komm. 30-33, kor-resp. led. 33, v. ordf. i 32 års han-delskomm., led. av järnvrrådet 32-43, av traktatberedn. sed. 32, v. ordf. där sed. 36, led. av kulturrådet sed. 35, av stat. handelskomm. sed. 39, ordf. där sed. 45, ordf. i Älvsb. läns södra hush rsällsk. sed. 43 o. i Älvsb. läns norra hush rsällsk. sed. 45. Led. av Sv. teknrfören. fr. 27. KNOlkl, RVO, FFrKl o. 3kl StkPolRest, StkÖHT, StOffBKrO, KDDOlgr, KFinliVROlkl, KNSrtOO m kr, KFrHL. *Luthman, Gustaf Arne, flygläkare, Såtenäs, f. 16/7/05 i Södertälje av gros’sh. Per Gustaf L. o. Ester Sigrid Augusta Jan&amp;son. G. 36 m. Signe Lind. — Studrex. i Södertälje 24, med. kand. v. Karol. inst. 28, med. lic. där 33. Förordn. .s. provrläk. i Västanhede o. Söderköp. distr. samt s. assiistrläk v. Linköp. las. med. avd., s. e. o. aman. v. S rt Görans sjukh. dermato-venereo-log. avd. o. s. und rläk. v. Hässleby san. 33, e. läk. v. Mariebergs sjukhus 34, assist rläk. o. tf. andre undr-läk. v. Karlstads las. med. avd. 34-35, und rläk. v. Garphyttans san. 35-37, tf. s’anrläk. där fyra mån., tredje undr-läk. o. tf. förste und rläk. v. Karlstads las. med. avd. 37, ord. förste und rläk. där 37, även tf. las rläk. där, flygläk. av första gr. 40.",
    "translated": "Lundvik, Vilhelm Göran, county governor, former minister, Vänersborg, born on August 28, 1883 at Næs Ironworks, Norway, son of Carl-Johan L. and Ebba Simp-ler. Married 1st in 1915 to Karin Alfthan, died in 1919; 2nd in 1922 to Dagmar Lamm. Children: Ulf born in 1916. Divorced in Gävle in 1902, graduated with a Bachelor of Arts in Uppsala in 1906, graduated with a Bachelor of Laws there in 1912. Attaché in the Ministry of Foreign Affairs in 1912, secretary of the Parliamentary Constitutional Committee in 1913 and 1914, of the Legal Committee from 1915, and of the Municipal Tax Committee from 1915 to 1916; representative of the Ironworks Association from 1916 to 1919, commercial attaché and counselor at the Swedish Embassy in Paris from 1919 to 1925, also at the Swedish Embassy in Brussels from 1921 to 1925; given the title of commercial counselor in 1926, acting undersecretary of state in the Ministry of Trade from 1925 to 1926, minister and head of the Ministry of Trade from October 2, 1928 to June 7, 1930, executive director in the Swedish Travel Industry Association from 1926 to 1941, county governor of Älvsborg County since 1941. Secretary of the Swedish representation in the international committee for the administration of Schleswig during the referendum and chairman of the referendum bureau in 1920, member and correspondent member of the Economic Commission of the League of Nations from 1930 to 1933, vice chairman of the 1932 Trade Commission; member of the Railway Council from 1932 to 1943, of the Treaty Committee since 1932, vice chairman since 1936, member of the Cultural Council since 1935, of the State Trade Committee since 1939, chairman since 1945, chairman of the Southern Household Association of Älvsborg County since 1943 and of the Northern Household Association since 1945. Member of the Swedish Technical Association since 1927. Grand Cross of the Order of the North Star, Commander of the Order of Vasa, Knight of the Order of St. John, Grand Officer of the Order of the Crown of Belgium, Commander with Star of the Order of the Finnish White Rose, Knight of the Order of the Polar Star, Member of the Order of the Sword with Olgr leaf cluster, Knight First Class of the Order of the Dannebrog. \n\n*Luthman, Gustaf Arne, flight doctor, Såtenäs, born on July 16, 1905 in Södertälje, son of Per Gustaf L. and Ester Sigrid Augusta Jan&amp;son. Married in 1936 to Signe Lind. Studied in Södertälje until 1924, received his Bachelor of Medicine degree from Karolinska Institute in 1928 and his medical license in 1933. Appointed as probationary doctor in Västanhede and Söderköping districts, as assistant doctor in Linköping hospital's medical department, as temporary assistant doctor at Söder Görans Hospital's dermatovenereology department, and as junior physician at Hässleby sanatorium in 1933. Became a general practitioner at Marieberg Hospital in 1934, assistant doctor and temporary senior doctor for four months at Garphyttan sanatorium in 1935, temporary junior physician and temporary senior doctor at Karlstad hospital's medical department from 1937 to 1939, permanent senior doctor at Karlstad hospital from 1939; also acted as temporary chief medical officer there. Flight doctor of the first group since 1940.",
    "structured_raw": "{\n  \"@context\": \"https://schema.org\",\n  \"@type\": \"Person\",\n  \"name\": \"Vilhelm Göran Lundvik\",\n  \"description\": \"County governor and former minister\",\n  \"birthDate\": \"1883-08-28\",\n  \"birthPlace\": {\n    \"@type\": \"Country\",\n    \"name\": \"Norway\"\n  },\n  \"parent\": [\n    {\n      \"@type\": \"Person\",\n      \"name\": \"Carl-Johan Lundvik\",\n      \"gender\": \"male\"\n    },\n    {\n      \"@type\": \"Person\",\n      \"name\": \"Ebba Simp-ler\",\n      \"gender\": \"female\"\n    }\n  ],\n  \"spouse\": [\n    {\n      \"@type\": \"Person\",\n      \"name\": \"Karin Alfthan\",\n      \"deathDate\": \"1919\"\n    },\n    {\n      \"@type\": \"Person\",\n      \"name\": \"Dagmar Lamm\"\n    }\n  ],\n  \"children\": [\n    {\n      \"@type\": \"Person\",\n      \"name\": \"Ulf Lundvik\",\n      \"birthDate\": \"1916\"\n    }\n  ],\n  \"education\": [\n    {\n      \"@type\": \"EducationalOrganization\",\n      \"name\": \"Gävle\",\n      \"endDate\": \"1902\"\n    },\n    {\n      \"@type\": \"EducationalOrganization\",\n      \"name\": \"Uppsala\",\n      \"endDate\": \"1906\",\n      \"degree\": {\n        \"@type\": \"EducationalDegree\",\n        \"name\": \"Bachelor of Arts\"\n      }\n    },\n    {\n      \"@type\": \"EducationalOrganization\",\n      \"name\": \"Uppsala\",\n      \"endDate\": \"1912\",\n      \"degree\": {\n        \"@type\": \"EducationalDegree\",\n        \"name\": \"Bachelor of Laws\"\n      }\n    }\n  ],\n  \"work\": [\n    {\n      \"@type\": \"OrganizationRole\",\n      \"title\": \"Attaché\",\n      \"startDate\": \"1912\",\n      \"endDate\": \"1912\",\n      \"organization\": {\n        \"@type\": \"Organization\",\n        \"name\": \"Ministry of Foreign Affairs\"\n      }\n    },\n    {\n      \"@type\": \"OrganizationRole\",\n      \"title\": \"Secretary\",\n      \"startDate\": \"1913\",\n      \"endDate\": \"1914\",\n      \"organization\": {\n        \"@type\": \"Organization\",\n        \"name\": \"Parliamentary Constitutional Committee\"\n      }\n    },\n    {\n      \"@type\": \"OrganizationRole\",\n      \"title\": \"Secretary\",\n      \"startDate\": \"1915\",\n      \"endDate\": \"present\",\n      \"organization\": {\n        \"@type\": \"Organization\",\n        \"name\": \"Legal Committee\"\n      }\n    },\n    {\n      \"@type\": \"OrganizationRole\",\n      \"title\": \"Secretary\",\n      \"startDate\": \"1915\",\n      \"endDate\": \"1916\",\n      \"organization\": {\n        \"@type\": \"Organization\",\n        \"name\": \"Municipal Tax Committee\"\n      }\n    },\n    {\n      \"@type\": \"OrganizationRole\",\n      \"title\": \"Representative\",\n      \"startDate\": \"1916\",\n      \"endDate\": \"1919\",\n      \"organization\": {\n        \"@type\": \"Organization\",\n        \"name\": \"Ironworks Association\"\n      }\n    },\n    {\n      \"@type\": \"OrganizationRole\",\n      \"title\": \"Commercial Attaché\",\n      \"startDate\": \"1919\",\n      \"endDate\": \"1925\",\n      \"organization\": {\n        \"@type\": \"Organization\",\n        \"name\": \"Swedish Embassy in Paris\"\n      }\n    },\n    {\n      \"@type\": \"OrganizationRole\",\n      \"title\": \"Commercial Counselor\",\n      \"startDate\": \"1926\",\n      \"endDate\": \"present\"\n    },\n    {\n      \"@type\": \"OrganizationRole\",\n      \"title\": \"Acting Undersecretary of State\",\n      \"startDate\": \"1925\",\n      \"endDate\": \"1926\",\n      \"organization\": {\n        \"@type\": \"Organization\",\n        \"name\": \"Ministry of Trade\"\n      }\n    },\n    {\n      \"@type\": \"OrganizationRole\",\n      \"title\": \"Minister\",\n      \"startDate\": \"1928-10-02\",\n      \"endDate\": \"1930-06-07\",\n      \"organization\": {\n        \"@type\": \"Organization\",\n        \"name\": \"Ministry of Trade\"\n      }\n    },\n    {\n      \"@type\": \"OrganizationRole\",\n      \"title\": \"Executive Director\",\n      \"startDate\": \"1926\",\n      \"endDate\": \"1941\",\n      \"organization\": {\n        \"@type\": \"Organization\",\n        \"name\": \"Swedish Travel Industry Association\"\n      }\n    },\n    {\n      \"@type\": \"OrganizationRole\",\n      \"title\": \"County Governor\",\n      \"startDate\": \"1941\",\n      \"endDate\": \"present\",\n      \"organization\": {\n        \"@type\": \"Organization\",\n        \"name\": \"Älvsborg County\"\n      }\n    },\n    {\n      \"@type\": \"OrganizationRole\",\n      \"title\": \"Secretary\",\n      \"startDate\": \"1920\",\n      \"endDate\": \"present\",\n      \"organization\": {\n        \"@type\": \"Organization\",\n        \"name\": \"Swedish Representation in International Committee for Administration of Schleswig\"\n      }\n    },\n    {\n      \"@type\": \"OrganizationRole\",\n      \"title\": \"Chairman\",\n      \"startDate\": \"1945\",\n      \"endDate\": \"present\",\n      \"organization\": {\n        \"@type\": \"Organization\",\n        \"name\": \"Älvsborg County Southern Household Association\"\n      }\n    },\n    {\n      \"@type\": \"OrganizationRole\",\n      \"title\": \"Chairman\",\n      \"startDate\": \"1943\",\n      \"endDate\": \"present\",\n      \"organization\": {\n        \"@type\": \"Organization\",\n        \"name\": \"Älvsborg County Northern Household Association\"\n      }\n    }\n  ],\n  \"memberOf\": [\n    {\n      \"@type\": \"Organization\",\n      \"name\": \"Swedish Technical Association\",\n      \"startDate\": \"1927\",\n      \"endDate\": \"present\"\n    }\n  ]\n}",
    "structured": {
        "@context": "https://schema.org",
        "@type": "Person",
        "name": "Vilhelm Göran Lundvik",
        "description": "County governor and former minister",
        "birthDate": "1883-08-28",
        "birthPlace": {
            "@type": "Country",
            "name": "Norway"
        },
        "parent": [
            {
                "@type": "Person",
                "name": "Carl-Johan Lundvik",
                "gender": "male"
            },
            {
                "@type": "Person",
                "name": "Ebba Simp-ler",
                "gender": "female"
            }
        ],
        "spouse": [
            {
                "@type": "Person",
                "name": "Karin Alfthan",
                "deathDate": "1919"
            },
            {
                "@type": "Person",
                "name": "Dagmar Lamm"
            }
        ],
        "children": [
            {
                "@type": "Person",
                "name": "Ulf Lundvik",
                "birthDate": "1916"
            }
        ],
        "education": [
            {
                "@type": "EducationalOrganization",
                "name": "Gävle",
                "endDate": "1902"
            },
            {
                "@type": "EducationalOrganization",
                "name": "Uppsala",
                "endDate": "1906",
                "degree": {
                    "@type": "EducationalDegree",
                    "name": "Bachelor of Arts"
                }
            },
            {
                "@type": "EducationalOrganization",
                "name": "Uppsala",
                "endDate": "1912",
                "degree": {
                    "@type": "EducationalDegree",
                    "name": "Bachelor of Laws"
                }
            }
        ],
        "work": [
            {
                "@type": "OrganizationRole",
                "title": "Attaché",
                "startDate": "1912",
                "endDate": "1912",
                "organization": {
                    "@type": "Organization",
                    "name": "Ministry of Foreign Affairs"
                }
            },
            {
                "@type": "OrganizationRole",
                "title": "Secretary",
                "startDate": "1913",
                "endDate": "1914",
                "organization": {
                    "@type": "Organization",
                    "name": "Parliamentary Constitutional Committee"
                }
            },
            {
                "@type": "OrganizationRole",
                "title": "Secretary",
                "startDate": "1915",
                "endDate": "present",
                "organization": {
                    "@type": "Organization",
                    "name": "Legal Committee"
                }
            },
            {
                "@type": "OrganizationRole",
                "title": "Secretary",
                "startDate": "1915",
                "endDate": "1916",
                "organization": {
                    "@type": "Organization",
                    "name": "Municipal Tax Committee"
                }
            },
            {
                "@type": "OrganizationRole",
                "title": "Representative",
                "startDate": "1916",
                "endDate": "1919",
                "organization": {
                    "@type": "Organization",
                    "name": "Ironworks Association"
                }
            },
            {
                "@type": "OrganizationRole",
                "title": "Commercial Attaché",
                "startDate": "1919",
                "endDate": "1925",
                "organization": {
                    "@type": "Organization",
                    "name": "Swedish Embassy in Paris"
                }
            },
            {
                "@type": "OrganizationRole",
                "title": "Commercial Counselor",
                "startDate": "1926",
                "endDate": "present"
            },
            {
                "@type": "OrganizationRole",
                "title": "Acting Undersecretary of State",
                "startDate": "1925",
                "endDate": "1926",
                "organization": {
                    "@type": "Organization",
                    "name": "Ministry of Trade"
                }
            },
            {
                "@type": "OrganizationRole",
                "title": "Minister",
                "startDate": "1928-10-02",
                "endDate": "1930-06-07",
                "organization": {
                    "@type": "Organization",
                    "name": "Ministry of Trade"
                }
            },
            {
                "@type": "OrganizationRole",
                "title": "Executive Director",
                "startDate": "1926",
                "endDate": "1941",
                "organization": {
                    "@type": "Organization",
                    "name": "Swedish Travel Industry Association"
                }
            },
            {
                "@type": "OrganizationRole",
                "title": "County Governor",
                "startDate": "1941",
                "endDate": "present",
                "organization": {
                    "@type": "Organization",
                    "name": "Älvsborg County"
                }
            },
            {
                "@type": "OrganizationRole",
                "title": "Secretary",
                "startDate": "1920",
                "endDate": "present",
                "organization": {
                    "@type": "Organization",
                    "name": "Swedish Representation in International Committee for Administration of Schleswig"
                }
            },
            {
                "@type": "OrganizationRole",
                "title": "Chairman",
                "startDate": "1945",
                "endDate": "present",
                "organization": {
                    "@type": "Organization",
                    "name": "Älvsborg County Southern Household Association"
                }
            },
            {
                "@type": "OrganizationRole",
                "title": "Chairman",
                "startDate": "1943",
                "endDate": "present",
                "organization": {
                    "@type": "Organization",
                    "name": "Älvsborg County Northern Household Association"
                }
            }
        ],
        "memberOf": [
            {
                "@type": "Organization",
                "name": "Swedish Technical Association",
                "startDate": "1927",
                "endDate": "present"
            }
        ]
    }
}