{
    "original": "Aschan, Carl Henning Wilhelm, överstelöjtnant, Gemla, f. 28/11/79 i Öja, Kronob. 1., av jägm. o. bruksäg. Janne A. o. Ottilia Daniels’son-Aschan. G. 12 m. Asta Beijer. Barn: Gottfried Beijer f. 13, g. 44 m. Karin Svärdell, Henning 16, Malmö, löjtn. i Kronob. reg. res., Lisbeth 18, g. 44 m. förvalt. Fredrik Ekströmer. — Stud:ex. i Lund 99, off:ex. 02. Und:löjtn. v. Södra skånska inf :reg. 02, löjtn. 07, kapt. v. reg. 22, major v. Kronob. reg. 28, öv:-löjtn. i armén 33. Äg. o. bebor Grans-hotos herrgård, Gemfe, Öja s :n. RSO, RNO.",
    "translated": "Aschan, Carl Henning Wilhelm, Lieutenant Colonel, Gemla, born November 28th, 1879 in Öja, Kronoberg County, first son of forest owner and industrialist Janne A. and Ottilia Daniels'son-Aschan. Married to Asta Beijer in 1912. Children: Gottfried Beijer born 1913, married Karin Svärdell in 1944; Henning born 1916, Lieutenant in the Kronoberg Regiment Reserve; Lisbeth born 1918, married Fredrik Ekströmer in 1944. Aschan attended Lund University and passed his officer's exam in 1902. He was a Second Lieutenant in the South Scanian Infantry Regiment in 1902, became a Lieutenant in 1907, Captain in 1922, Major in the Kronoberg Regiment in 1928, and Lieutenant Colonel in the Army in 1933. He owns and resides in Grans-hotos Manor in Gemla, Öja parish. Has received the Royal Order of the Seraphim and the Royal Norwegian Order of Merit.",
    "structured": {
        "@context": "https://schema.org",
        "@type": "Person",
        "name": "Carl Henning Wilhelm Aschan",
        "givenName": "Carl",
        "additionalName": "Henning Wilhelm",
        "familyName": "Aschan",
        "gender": "Male",
        "birthDate": "1879-11-28",
        "birthPlace": {
            "@type": "Place",
            "name": "Öja, Kronoberg County"
        },
        "nationality": {
            "@type": "Country",
            "name": "Sweden"
        },
        "parents": [
            {
                "@type": "Person",
                "name": "Janne A. Aschan",
                "jobTitle": "Forest Owner and Industrialist"
            },
            {
                "@type": "Person",
                "name": "Ottilia Daniels'son-Aschan"
            }
        ],
        "spouse": {
            "@type": "Person",
            "name": "Asta Beijer",
            "marriageDate": "1912"
        },
        "children": [
            {
                "@type": "Person",
                "name": "Gottfried Beijer",
                "birthDate": "1913",
                "spouse": {
                    "@type": "Person",
                    "name": "Karin Svärdell",
                    "marriageDate": "1944"
                }
            },
            {
                "@type": "Person",
                "name": "Henning Aschan",
                "birthDate": "1916",
                "jobTitle": "Lieutenant",
                "memberOf": {
                    "@type": "Organization",
                    "name": "Kronoberg Regiment Reserve"
                }
            },
            {
                "@type": "Person",
                "name": "Lisbeth Aschan",
                "birthDate": "1918",
                "spouse": {
                    "@type": "Person",
                    "name": "Fredrik Ekströmer",
                    "marriageDate": "1944"
                },
                "jobTitle": "Forvaltare"
            }
        ],
        "education": {
            "@type": "EducationalOccupationalCredential",
            "credentialCategory": "academic degree",
            "credentialAwarded": "Stud:ex.",
            "educationLevel": "University",
            "educationalProgramMode": "full-time",
            "educationalSpecialization": "Lund University",
            "endDate": "1899"
        },
        "worksFor": {
            "@type": "Organization",
            "name": "South Scanian Infantry Regiment",
            "jobTitle": "Second Lieutenant",
            "startDate": "1902",
            "endDate": "1907"
        },
        "memberOf": [
            {
                "@type": "Organization",
                "name": "Kronoberg Regiment",
                "jobTitle": "Captain",
                "startDate": "1922"
            },
            {
                "@type": "Organization",
                "name": "Kronoberg Regiment",
                "jobTitle": "Major",
                "startDate": "1928"
            }
        ],
        "jobTitle": "Lieutenant Colonel",
        "owns": {
            "@type": "Place",
            "name": "Grans-hotos Manor, Gemla, Öja Parish"
        },
        "award": [
            {
                "@type": "Order",
                "name": "Royal Order of the Seraphim"
            },
            {
                "@type": "Order",
                "name": "Royal Norwegian Order of Merit"
            }
        ]
    }
}