{
    "original": "Carl Salomon, prakt. Häkare, Växjö, f. 28/1/97 i Haltostad av förste postexp. Emil W. o. Mathil-da Benigtsson. G. 21 m. förf. Ingrid Katarina Holmqvist. Barn i Bengt-Göran f. 22, Alf Emil 28, Ulla Lena 29. — Studiex. i Halmstad 15, med. kand. i Lund 19, med. lic. i Sthlm 24. Tf. provilàk. i Älvsby, Äknihults o. Malungs distr. 22-24, aman. v. Ka-rol. inst. dermiato-syfilidoiloig-. klin. 215, tf. undiläk. där 25-26, tf. proviläk. i Sunne, Lycksele o. Strängnäs distr. tMils:. c:a ett år 25-29, t’f. umdiläk. v. V;ästerviiks o. Halimisitads las., Seraf las. kir. avd. o. Gbgs BB c:a ’femjton mån. 26-28, andre und ’Mk. v. Växjö las. 20’-3ll, f(örs’te undiiläk. där 311-34, tf. las :l(äk. dlär tre mån., prakt läk. i Växjö sed. 3’4. Stud:resa t. Wien 21, uthres. årl. 28-39. Skr.: Syfilis (priis-bel. tävhskr. i ser. Vad vi veta), upps. i facktidskr. Föreliäs, i med. ämn:. i Föreläsn o-. ABF. , Ingrid Katarina, författarinna, Växjö, f. i Karlskrona av Blekingeskildr. J. O. Holmqvist o. h. h. G. 21 m. prakt. läk. Carl W. — Små-skoll:ex. 11, språkstud. v. borg:sk. i Stlilm. Res. i Europa årl. 28-39. Anst. v. små- o. folksk. i Skatelöv, Torhamn, Älmhult 11-25. Styr:led. i stat. forts :-sk. f. talundervisn. i Växjö fr. 38, i Kvinn. beredsk :kamm., medl. av Växjö ungd:råd. Skr.: Lillköpingsbarnen, läseb. f. småsk. (I o. II, 27), Gullstu-gan, bredvidläseb. f. småsk. (33), Handledn. i Fröbelarb., Pinnslöjd (24), Barnvissaml.: Knäckkalaset (24), Sockerlandet (27), Lillebrors visor (32), Läseb. i hyg. o. hälsovård. Hälsans ABC-bok (33, övers t. norska), Barnens första julbok, julläsn. f. nyb. (32), Tomtenisse, julläsn. f. nyb. (årl. fr. 33’), Bevingat folk (i ser. Vår underbara värld, 33), Ett strå t. stacken (i samma ser. 46), Vi vill vara .friska (samma ser. 48), I Hoppareland, nytto- o. nö-jesiläsn. f. nyb. (44), Kungens lille doktor (44), Vi o. vår hälsa (48). Med avsnitt av dessa o. icke publ. arb. medarb. i radiotj. barnprogr. fr. 25. Medarb. i Folksk. läseb. samt »Min s ka 11 k amma re».",
    "translated": "Carl Salomon, practical physician, Växjö, born on January 28, 1897 in Haltostad to chief postal employee Emil W. and Mathilda Benigtsson. Married on June 21, to author Ingrid Katarina Holmqvist. Children: Bengt-Göran (born in 1922), Alf Emil (born in 1928), Ulla Lena (born in 1929). - Graduated from high school in Halmstad in 1915, received a Bachelor of Medicine degree in Lund in 1919, received a medical license in Stockholm in 1924. Substitute district medical officer in Älvsbyn, Äknihult, and Malung districts from 1922 to 1924; assistant at Karlolinska Institute Dermato-Syphilidology Clinic from 1921-1925; substitute clinical assistant there from 1925-1926; substitute district medical officer in Sunne, Lycksele, and Strängnäs districts for about a year from 1925-1929; substitute clinical assistant at Västervik and Halmstad hospitals, Seraf Hospital Surgical Ward, and Gothenburg's BB for approximately fifteen months from 1926-1928; second clinical assistant at Växjö hospital from 1920-1931; first substitute district medical officer there from 1931-1934; substitute hospital physician for three months; practicing physician in Växjö since 1934. Studied in Vienna in 1921, annual travel from 1928-1939. Writings: Syphilis (prize-winning contest paper in the series \"What We Know\"), essays in professional journals, lectures on medical subjects in Lecture Hall and ABF. \n\nIngrid Katarina, author, Växjö, born in Karlskrona to Blekinge descriptive writer J.O. Holmqvist and his wife. Married on June 21 to practical physician Carl W. - Graduated from elementary school in 1911, language studies at a high school in Stockholm. Traveled in Europe annually from 1928-1939. Employed in small and primary schools in Skatelöv, Torhamn, and Älmhult from 1911-1925. Board member of the State Continuing School for Speech Education in Växjö from 1938, member of the Women's Preparedness Chamber, member of the Växjö Youth Council. Writings: Lillköpingsbarnen, reading book for elementary school (I and II, 1927), Gullstugan, supplementary reading book for elementary school (1933), Manual for Fröbelwork, Stick Craft (1924), Children's Song Collection: Knäckkalaset (1924), Sockerlandet (1927), Lillebrors visor (1932), Reading book on hygiene and health. Health ABC book (1933, also translated into Norwegian), Children's First Christmas Book, Christmas reading for beginners (1932), Tomtenisse, Christmas reading for beginners (annual since 1933), Bevingat folk (in the series \"Our Wonderful World\", 1933), A straw for the bee (in the same series, 1946), We want to be healthy (same series, 1948), In Hoppareland, informative and entertaining reading for beginners (1944), The King's Little Doctor (1944), Us and Our Health (1948). Contributed to and collaborated on unpublished works and radio programs for children from 1925. Collaborated on reading books for elementary school and \"My Schoolmate.\"",
    "structured_raw": "{\n  \"@context\": \"https://schema.org\",\n  \"@type\": \"Person\",\n  \"name\": \"Carl Salomon\",\n  \"birthDate\": \"1897-01-28\",\n  \"birthPlace\": \"Haltostad\",\n  \"deathDate\": \"\",\n  \"nationality\": \"Swedish\",\n  \"description\": \"Practical physician\",\n  \"memberOf\": [\n    {\n      \"@type\": \"Organization\",\n      \"name\": \"Växjö\"\n    }\n  ],\n  \"parents\": [\n    {\n      \"@type\": \"Person\",\n      \"name\": \"Emil W.\"\n    },\n    {\n      \"@type\": \"Person\",\n      \"name\": \"Mathilda Benigtsson\"\n    }\n  ],\n  \"spouse\": {\n    \"@type\": \"Person\",\n    \"name\": \"Ingrid Katarina Holmqvist\",\n    \"birthPlace\": \"Karlskrona\",\n    \"parents\": [\n      {\n        \"@type\": \"Person\",\n        \"name\": \"J.O. Holmqvist\"\n      },\n      {\n        \"@type\": \"Person\",\n        \"name\": \"h. h.\"\n      }\n    ],\n    \"memberOf\": [\n      {\n        \"@type\": \"Organization\",\n        \"name\": \"Växjö\"\n      }\n    ],\n    \"occupation\": {\n      \"@type\": \"Role\",\n      \"name\": \"Author\"\n    }\n  },\n  \"children\": [\n    {\n      \"@type\": \"Person\",\n      \"name\": \"Bengt-Göran\",\n      \"birthDate\": \"1922\"\n    },\n    {\n      \"@type\": \"Person\",\n      \"name\": \"Alf Emil\",\n      \"birthDate\": \"1928\"\n    },\n    {\n      \"@type\": \"Person\",\n      \"name\": \"Ulla Lena\",\n      \"birthDate\": \"1929\"\n    }\n  ],\n  \"education\": [\n    {\n      \"@type\": \"EducationalOccupationalCredential\",\n      \"credentialCategory\": \"Studiexamen\",\n      \"credentialSubject\": \"Halmstad\",\n      \"completionDate\": \"1915\"\n    },\n    {\n      \"@type\": \"EducationalOccupationalCredential\",\n      \"credentialCategory\": \"Med. kand.\",\n      \"credentialSubject\": \"Lund\",\n      \"completionDate\": \"1919\"\n    },\n    {\n      \"@type\": \"EducationalOccupationalCredential\",\n      \"credentialCategory\": \"Med. lic.\",\n      \"credentialSubject\": \"Stockholm\",\n      \"completionDate\": \"1924\"\n    }\n  ],\n  \"work\": [\n    {\n      \"@type\": \"MedicalOrganization\",\n      \"name\": \"Älvsbyn\",\n      \"startDate\": \"1922\",\n      \"endDate\": \"1924\",\n      \"jobTitle\": \"Substitute District Medical Officer\"\n    },\n    {\n      \"@type\": \"MedicalOrganization\",\n      \"name\": \"Karlolinska Institute Dermato-Syphilidology Clinic\",\n      \"startDate\": \"1921\",\n      \"endDate\": \"1925\",\n      \"jobTitle\": \"Assistant\"\n    },\n    {\n      \"@type\": \"MedicalOrganization\",\n      \"name\": \"Sunne, Lycksele, and Strängnäs\",\n      \"startDate\": \"1925\",\n      \"endDate\": \"1929\",\n      \"jobTitle\": \"Substitute District Medical Officer\"\n    },\n    {\n      \"@type\": \"MedicalOrganization\",\n      \"name\": \"Växjö\",\n      \"startDate\": \"1920\",\n      \"endDate\": \"1931\",\n      \"jobTitle\": \"Second Clinical Assistant\"\n    },\n    {\n      \"@type\": \"MedicalOrganization\",\n      \"name\": \"Växjö\",\n      \"startDate\": \"1931\",\n      \"endDate\": \"1934\",\n      \"jobTitle\": \"First Substitute District Medical Officer\"\n    },\n    {\n      \"@type\": \"MedicalOrganization\",\n      \"name\": \"Växjö\",\n      \"startDate\": \"1934\",\n      \"endDate\": \"\",\n      \"jobTitle\": \"Practicing Physician\"\n    }\n  ],\n  \"additionalName\": \"prakt. Häkare\",\n  \"worksFor\": \"Växjö\",\n  \"givenName\": \"Carl\",\n  \"familyName\": \"Salomon\",\n  \"contactPoint\": {\n    \"@type\": \"ContactPoint\",\n    \"telephone\": \"\",\n    \"email\": \"\",\n    \"address\": \"\"\n  },\n  \"sameAs\": \"\"\n}",
    "structured": {
        "@context": "https://schema.org",
        "@type": "Person",
        "name": "Carl Salomon",
        "birthDate": "1897-01-28",
        "birthPlace": "Haltostad",
        "deathDate": "",
        "nationality": "Swedish",
        "description": "Practical physician",
        "memberOf": [
            {
                "@type": "Organization",
                "name": "Växjö"
            }
        ],
        "parents": [
            {
                "@type": "Person",
                "name": "Emil W."
            },
            {
                "@type": "Person",
                "name": "Mathilda Benigtsson"
            }
        ],
        "spouse": {
            "@type": "Person",
            "name": "Ingrid Katarina Holmqvist",
            "birthPlace": "Karlskrona",
            "parents": [
                {
                    "@type": "Person",
                    "name": "J.O. Holmqvist"
                },
                {
                    "@type": "Person",
                    "name": "h. h."
                }
            ],
            "memberOf": [
                {
                    "@type": "Organization",
                    "name": "Växjö"
                }
            ],
            "occupation": {
                "@type": "Role",
                "name": "Author"
            }
        },
        "children": [
            {
                "@type": "Person",
                "name": "Bengt-Göran",
                "birthDate": "1922"
            },
            {
                "@type": "Person",
                "name": "Alf Emil",
                "birthDate": "1928"
            },
            {
                "@type": "Person",
                "name": "Ulla Lena",
                "birthDate": "1929"
            }
        ],
        "education": [
            {
                "@type": "EducationalOccupationalCredential",
                "credentialCategory": "Studiexamen",
                "credentialSubject": "Halmstad",
                "completionDate": "1915"
            },
            {
                "@type": "EducationalOccupationalCredential",
                "credentialCategory": "Med. kand.",
                "credentialSubject": "Lund",
                "completionDate": "1919"
            },
            {
                "@type": "EducationalOccupationalCredential",
                "credentialCategory": "Med. lic.",
                "credentialSubject": "Stockholm",
                "completionDate": "1924"
            }
        ],
        "work": [
            {
                "@type": "MedicalOrganization",
                "name": "Älvsbyn",
                "startDate": "1922",
                "endDate": "1924",
                "jobTitle": "Substitute District Medical Officer"
            },
            {
                "@type": "MedicalOrganization",
                "name": "Karlolinska Institute Dermato-Syphilidology Clinic",
                "startDate": "1921",
                "endDate": "1925",
                "jobTitle": "Assistant"
            },
            {
                "@type": "MedicalOrganization",
                "name": "Sunne, Lycksele, and Strängnäs",
                "startDate": "1925",
                "endDate": "1929",
                "jobTitle": "Substitute District Medical Officer"
            },
            {
                "@type": "MedicalOrganization",
                "name": "Växjö",
                "startDate": "1920",
                "endDate": "1931",
                "jobTitle": "Second Clinical Assistant"
            },
            {
                "@type": "MedicalOrganization",
                "name": "Växjö",
                "startDate": "1931",
                "endDate": "1934",
                "jobTitle": "First Substitute District Medical Officer"
            },
            {
                "@type": "MedicalOrganization",
                "name": "Växjö",
                "startDate": "1934",
                "endDate": "",
                "jobTitle": "Practicing Physician"
            }
        ],
        "additionalName": "prakt. Häkare",
        "worksFor": "Växjö",
        "givenName": "Carl",
        "familyName": "Salomon",
        "contactPoint": {
            "@type": "ContactPoint",
            "telephone": "",
            "email": "",
            "address": ""
        },
        "sameAs": ""
    }
}