{
    "original": "Builders, San Francisco, 23-25, ing. h. stat. arb :lösh :komm. 26, Södertälje stads byiggnichef 27-31, chef f. konstr:kont. v. Sthlms stads om-byggn:arb. v. Slussen 31-35, tf. byggnxhef f. arb. v. Slussen 36, sär-sk. uppdr. f. Sthlms stads fastigh:nd 37, arb rchef f. stat. hamn- o. farleds-byggn. i v. distr. sed. 38. Led. av styr. f. Ö. Södermanl. kulturhist. mus. i Södertälje 29-31, riksantikv. omb. f. Södertälje m. omn. 29-31. Skr.: Arb :-metoder f. betonggjutn. v. en amerikansk dammbyggn. (23), De verkeers-regeling bij Slussen in Stockholm (34), Slussen, the New Traffic Centre of Sthlm (35), Grundläggn. v. Slussen i Sthlm m. påln. enl. system Franki (36), Industri o. hantverk i Sthlm, deras lokalisering samt de allm. ekonom, förutsättn. f. deras utveckl. (delv. 38), Industri o. hantverk i Sthlm (38). RVO. ’^Bjurby, Axel Hilde, komminister, Målsryd, f. 17/11/00 i Torsby, Värml. 1. — Studiex. i Lund 20, teol. fil. ex. 23, teol. kand. samt prästv. f. Skara stift 28. V. pastor i Fägre, kommin. i Toarp 33. Led. av kyrkofullm. o. barnav :nd.",
    "translated": "Builders, San Francisco, 23-25, engineering high state worker, unemployed, commune member 26, Södertälje city building chief 27-31, head of construction office for Stockholm city's rebuilding work at Slussen 31-35, acting building chief for work at Slussen 36, special assignments for Stockholm city's real estate 37, chief engineer for state harbor and fairway construction in western district since 38. Member of the board for East Södermanland Cultural History Museum in Södertälje 29-31, national antiquarian deputy for Södertälje with mention 29-31. Writings: Work methods for concrete casting for an American dam construction (23), Traffic regulation for Slussen in Stockholm (34), Slussen, the New Traffic Center of Stockholm (35), Foundation of Slussen in Stockholm with Franki piling system (36), Industry and handicrafts in Stockholm, their localization and the general economic conditions for their development (partly 38), Industry and handicrafts in Stockholm (38). RVO. Bjurby, Axel Hilde, clergyman, Målsryd, born on 17/11/00 in Torsby, Värmland. Completed undergraduate studies in Lund in 20, obtained a degree in theology and philosophy in 23, theology candidate, and ordained as a priest in Skara diocese in 28. Assisted pastor in Fägre, became a clergyman in Toarp in 33. Member of church council and child welfare. Note that '\\d\\d m. partners name' means that the person married in the year 19xx.",
    "structured_raw": "{\n   \"@context\": \"https://schema.org/\",\n   \"@type\": \"Person\",\n   \"name\": \"Builders\",\n   \"birthPlace\": \"Torsby, Värmland\",\n   \"birthDate\": \"1900-11-17\",\n   \"deathDate\": null,\n   \"jobTitle\": [\n      \"Engineering High State Worker\",\n      \"Södertälje City Building Chief\",\n      \"Head of Construction Office for Stockholm City's Rebuilding Work at Slussen\",\n      \"Acting Building Chief for Work at Slussen\",\n      \"Chief Engineer for State Harbor and Fairway Construction in Western District\"\n   ],\n   \"memberOf\": [\n      {\n         \"@type\": \"Organization\",\n         \"name\": \"East Södermanland Cultural History Museum\",\n         \"startDate\": \"1929-01-01\",\n         \"endDate\": \"1931-12-31\",\n         \"description\": \"Member of the Board\"\n      },\n      {\n         \"@type\": \"Organization\",\n         \"name\": \"National Antiquarian Deputy for Södertälje\",\n         \"startDate\": \"1929-01-01\",\n         \"endDate\": \"1931-12-31\",\n         \"description\": \"Deputy\"\n      }\n   ],\n   \"worksFor\": {\n      \"@type\": \"Organization\",\n      \"name\": \"Stockholm City\"\n   },\n   \"spouse\": null,\n   \"children\": [],\n   \"description\": \"Axel Hilde Bjurby was an expert in concrete casting and traffic regulation. He worked for the Stockholm City and was a member of the board for East Södermanland Cultural History Museum in Södertälje from 1929 to 1931. Axel Hilde Bjurby was also a national antiquarian deputy for Södertälje during the same period.\",\n   \"sameAs\": null,\n   \"url\": null,\n   \"gender\": null,\n   \"height\": null,\n   \"weight\": null,\n   \"nationality\": \"Swedish\",\n   \"education\": [\n      {\n         \"institution\": \"Lund University\",\n         \"startDate\": \"1920-01-01\",\n         \"endDate\": null,\n         \"field\": \"Undergraduate Studies\"\n      },\n      {\n         \"institution\": null,\n         \"startDate\": \"1923-01-01\",\n         \"endDate\": null,\n         \"degree\": [\n            \"Degree in Theology\",\n            \"Degree in Philosophy\"\n         ]\n      }\n   ],\n   \"alumniOf\": [],\n   \"knows\": null,\n   \"relatedTo\": null,\n   \"deathPlace\": null,\n   \"causeOfDeath\": null,\n   \"birthPlace\": \"Torsby, Värmland\"\n}",
    "structured": {
        "@context": "https://schema.org/",
        "@type": "Person",
        "name": "Builders",
        "birthPlace": "Torsby, Värmland",
        "birthDate": "1900-11-17",
        "deathDate": null,
        "jobTitle": [
            "Engineering High State Worker",
            "Södertälje City Building Chief",
            "Head of Construction Office for Stockholm City's Rebuilding Work at Slussen",
            "Acting Building Chief for Work at Slussen",
            "Chief Engineer for State Harbor and Fairway Construction in Western District"
        ],
        "memberOf": [
            {
                "@type": "Organization",
                "name": "East Södermanland Cultural History Museum",
                "startDate": "1929-01-01",
                "endDate": "1931-12-31",
                "description": "Member of the Board"
            },
            {
                "@type": "Organization",
                "name": "National Antiquarian Deputy for Södertälje",
                "startDate": "1929-01-01",
                "endDate": "1931-12-31",
                "description": "Deputy"
            }
        ],
        "worksFor": {
            "@type": "Organization",
            "name": "Stockholm City"
        },
        "spouse": null,
        "children": [],
        "description": "Axel Hilde Bjurby was an expert in concrete casting and traffic regulation. He worked for the Stockholm City and was a member of the board for East Södermanland Cultural History Museum in Södertälje from 1929 to 1931. Axel Hilde Bjurby was also a national antiquarian deputy for Södertälje during the same period.",
        "sameAs": null,
        "url": null,
        "gender": null,
        "height": null,
        "weight": null,
        "nationality": "Swedish",
        "education": [
            {
                "institution": "Lund University",
                "startDate": "1920-01-01",
                "endDate": null,
                "field": "Undergraduate Studies"
            },
            {
                "institution": null,
                "startDate": "1923-01-01",
                "endDate": null,
                "degree": [
                    "Degree in Theology",
                    "Degree in Philosophy"
                ]
            }
        ],
        "alumniOf": [],
        "knows": null,
        "relatedTo": null,
        "deathPlace": null,
        "causeOfDeath": null
    }
}