{
    "original": "Carl Wallis, kyrkoherde, Gränna, f. 12/4/04 i Jönköp. av grossih. Carl W. o. Emilia Dahlström. G. 32 m. Carola Allgulin. Barn: Elisabeth f. 3i6. — Stud:ex. i Jönköp. 23, fil. kand. 24, teol. kand. o. prakt. teol. prov 28, prästv. f. Växjö stift 29. Tjg. s. v. kommin. i Långaryd, pastorsadj. i Skirö o. v. kommin. i Vallsjö. Kommin. i Bredaryd 30, kyrkoh. i Gränna sed. 42. Ordf. i kyrkofullm., v. ordf. i h. .’folksk. styr. o. barnav:nd, ordf. o. förest, f. föreläsn :fören., kårchef i Gränna scoutkår, distr:kaplan i norra Smål. scoutdistr. Skr.: Det stora valet (inst:pred. 42), tidn:art. , John Wilhelm Victor Car-lén-, kapten, gymnastikdirektör, Göteborg, f. 16/7/83 i Hjo av kapt. Gustaf W. o. Maria Carlén. G. 13-21 o. 25-28 m. Eira Hörnfeldt; 2. 37 m. gymn :dir. Marianne Carlberg. Barn: Gull Brita ;f. 14, g. m. Gunnar Bäcker-Backlund, Ulla Marianne 18, g. m. red. Bengt Grafström. — Stud:ex. i Skara 02, gymn:dir:ex. v. GCI 09. Und :löjtn. i Västg. reg. res. 04, löjtn. 10, kapt. 17. Sjukgymn. i London 09-10, gymn :lär. i Enköp. o. sjukgymn. h. dr Wester-lund lO-lil, gymn:lär. v. Malmö h. a. 1. 12-47, tillika gymn :insp. v. Malmö folksk. 15-43. Hed:ordf. i Malmö gymn:- o. fäktkl., Malmö gymn:förb.. Sv. gymn :lär:sällsk. södra krets samt i Skaradjäkn. södra distr., hed:led. i Dansk gymn :forb. o. i Skånes gymn:-förb., led. av Sv. gymn :lär:sällsk. cen-tr:styr., dess v. ordf. sed. 28, led. av styr. i. Sv. gymn :förb. sed. 16. Led. f. ett flert. utl:färd. m. gymn :trupp. m. uppdr. att repr. Sv:e, led. f. sv. mani. masstruppen v. Lingiaden i Sthlm 39, ordf. i spec :komm. f. Lingiad. 49. Skr.: Dagövningar ;f. folkskolor (34), Utvalda lekar (36), Hemgymn. gör underverk (tills. m. Alvar Medin 41), Det mesta är sant (45), Mera nästan sant (46), därjämte ett stort ant. tidn:-o. tidskr:art. Föreläsare. RNO, RVO, ProPatrstGM, LingJubM, RiksidrlM, LingM, Nord. gymn :förb. förtjO, Fe-der. dnt. de Gymn. Lings komm :t., samt ytterlig, en mlångifald sv. o. uti. utm:t.",
    "translated": "Carl Wallis, clergyman, Gränna, born on April 12, 1904 in Jönköping, son of wholesaler Carl W. and Emilia Dahlström. Married in 1932 to Carola Allgulin. Children: Elisabeth, born on March 16. Completed his studies at Jönköping in 1923, graduated with a Bachelor of Arts in 1924, Bachelor of Theology and practical theological examination in 1928, ordained as a priest in the Växjö diocese in 1929. Served as curate in Långaryd, assistant pastor in Skirö and curate in Vallsjö. Became curate in Bredaryd in 1930 and pastor in Gränna since 1942. Chairman of the church council, vice chairman of the National Elementary School Board, chairman and director of the lecture association, leader of the Gränna Scout Corps, district chaplain in the northern Småland scout district. Published works include \"Det stora valet\" (installation sermon in 1942) and newspaper articles. \nJohn Wilhelm Victor Car-lén-, captain, gymnastics director, Gothenburg, born on July 16, 1883 in Hjo, son of Captain Gustaf W. and Maria Carlén. Married from 1913 to 1921 and from 1925 to 1928 to Eira Hörnfeldt; married for the second time in 1937 to gymnastics director Marianne Carlberg. Children: Gull Brita, born in 1914, married to Gunnar Bäcker-Backlund, Ulla Marianne, born in 1918, married to editor Bengt Grafström. Completed his studies in Skara in 1902, graduated as a gymnastics director from GCI in 1909. Lieutenant in the Västgöta Regiment from 1904, promoted to lieutenant in 1910, captain in 1917. Worked as a physiotherapist in London from 1909 to 1910, gymnastics teacher in Enköping and physiotherapist under Dr. Westerlund from 1910 to 1911. Gymnastics teacher at Malmö Högskola from 1912 to 1947, also served as inspector of physical education in Malmö elementary schools from 1915 to 1943. Honorary chairman of Malmö gymnastics and fencing club, Malmö gymnastics association, Swedish gymnastics teachers' society southern district, and Skaradjäknarna southern district. Honorary member of the Danish gymnastics association and Skåne gymnastics association. Member of the central board of the Swedish gymnastics teachers' society, vice chairman since 1928, member of the board of the Swedish gymnastics association since 1916. Led several international gymnastics trips as a representative of Sweden, member of the Swedish gymnastics mass troop at the Lingiad in Stockholm in 1939, chairman of the special committee for Lingiad in 1949. Published works include \"Dagövningar för folkskolor\" (1934), \"Utvalda lekar\" (1936), \"Hemgymn. gör underverk\" (co-authored with Alvar Medin in 1941), \"Det mesta är sant\" (1945), and \"Mera nästan sant\" (1946), in addition to numerous articles in newspapers and magazines. Speaker. Awarded with the Order of the North Star, Order of Vasa, ProPatria Gold Medal, Ling Anniversary Medal, Riksidrottsmärket (the Swedish National Sports Badge), Ling Medal, Honorary Medal of the Nordic Gymnastics Association, and various Swedish and international awards.",
    "structured_raw": "{\n  \"@context\": \"http://schema.org\",\n  \"@type\": \"Person\",\n  \"name\": \"Carl Wallis\",\n  \"birthDate\": \"1904-04-12\",\n  \"birthPlace\": \"Jönköping\",\n  \"deathDate\": \"unknown\",\n  \"description\": \"Clergyman\",\n  \"children\": [\n    {\n      \"@type\": \"Person\",\n      \"name\": \"Elisabeth\",\n      \"birthDate\": \"unknown\"\n    }\n  ],\n  \"spouse\": {\n    \"@type\": \"Person\",\n    \"name\": \"Carola Allgulin\"\n  },\n  \"parent\": [\n    {\n      \"@type\": \"Person\",\n      \"name\": \"Carl W.\"\n    },\n    {\n      \"@type\": \"Person\",\n      \"name\": \"Emilia Dahlström\"\n    }\n  ],\n  \"education\": [\n    {\n      \"@type\": \"EducationEvent\",\n      \"institution\": {\n        \"@type\": \"Organization\",\n        \"name\": \"Jönköping\"\n      },\n      \"endDate\": \"1923\"\n    },\n    {\n      \"@type\": \"EducationEvent\",\n      \"degree\": {\n        \"@type\": \"EducationalOccupationalCredential\",\n        \"name\": \"Bachelor of Arts\"\n      },\n      \"endDate\": \"1924\"\n    },\n    {\n      \"@type\": \"EducationEvent\",\n      \"degree\": {\n        \"@type\": \"EducationalOccupationalCredential\",\n        \"name\": \"Bachelor of Theology\"\n      },\n      \"endDate\": \"1928\"\n    }\n  ],\n  \"employment\": [\n    {\n      \"@type\": \"JobPosting\",\n      \"title\": \"Curate\",\n      \"startDate\": \"unknown\",\n      \"endDate\": \"unknown\",\n      \"location\": {\n        \"@type\": \"Place\",\n        \"name\": \"Långaryd\"\n      }\n    },\n    {\n      \"@type\": \"JobPosting\",\n      \"title\": \"Assistant Pastor\",\n      \"startDate\": \"unknown\",\n      \"endDate\": \"unknown\",\n      \"location\": {\n        \"@type\": \"Place\",\n        \"name\": \"Skirö\"\n      }\n    },\n    {\n      \"@type\": \"JobPosting\",\n      \"title\": \"Curate\",\n      \"startDate\": \"unknown\",\n      \"endDate\": \"unknown\",\n      \"location\": {\n        \"@type\": \"Place\",\n        \"name\": \"Vallsjö\"\n      }\n    },\n    {\n      \"@type\": \"JobPosting\",\n      \"title\": \"Curate\",\n      \"startDate\": \"1930\",\n      \"endDate\": \"unknown\",\n      \"location\": {\n        \"@type\": \"Place\",\n        \"name\": \"Bredaryd\"\n      }\n    },\n    {\n      \"@type\": \"JobPosting\",\n      \"title\": \"Pastor\",\n      \"startDate\": \"1942\",\n      \"endDate\": \"unknown\",\n      \"location\": {\n        \"@type\": \"Place\",\n        \"name\": \"Gränna\"\n      }\n    }\n  ],\n  \"memberOf\": [\n    {\n      \"@type\": \"Organization\",\n      \"name\": \"Church Council\"\n    },\n    {\n      \"@type\": \"Organization\",\n      \"name\": \"National Elementary School Board\"\n    },\n    {\n      \"@type\": \"Organization\",\n      \"name\": \"Lecture Association\"\n    },\n    {\n      \"@type\": \"Organization\",\n      \"name\": \"Gränna Scout Corps\"\n    },\n    {\n      \"@type\": \"Organization\",\n      \"name\": \"Northern Småland Scout District\"\n    }\n  ]\n}",
    "structured": {
        "@context": "http://schema.org",
        "@type": "Person",
        "name": "Carl Wallis",
        "birthDate": "1904-04-12",
        "birthPlace": "Jönköping",
        "deathDate": "unknown",
        "description": "Clergyman",
        "children": [
            {
                "@type": "Person",
                "name": "Elisabeth",
                "birthDate": "unknown"
            }
        ],
        "spouse": {
            "@type": "Person",
            "name": "Carola Allgulin"
        },
        "parent": [
            {
                "@type": "Person",
                "name": "Carl W."
            },
            {
                "@type": "Person",
                "name": "Emilia Dahlström"
            }
        ],
        "education": [
            {
                "@type": "EducationEvent",
                "institution": {
                    "@type": "Organization",
                    "name": "Jönköping"
                },
                "endDate": "1923"
            },
            {
                "@type": "EducationEvent",
                "degree": {
                    "@type": "EducationalOccupationalCredential",
                    "name": "Bachelor of Arts"
                },
                "endDate": "1924"
            },
            {
                "@type": "EducationEvent",
                "degree": {
                    "@type": "EducationalOccupationalCredential",
                    "name": "Bachelor of Theology"
                },
                "endDate": "1928"
            }
        ],
        "employment": [
            {
                "@type": "JobPosting",
                "title": "Curate",
                "startDate": "unknown",
                "endDate": "unknown",
                "location": {
                    "@type": "Place",
                    "name": "Långaryd"
                }
            },
            {
                "@type": "JobPosting",
                "title": "Assistant Pastor",
                "startDate": "unknown",
                "endDate": "unknown",
                "location": {
                    "@type": "Place",
                    "name": "Skirö"
                }
            },
            {
                "@type": "JobPosting",
                "title": "Curate",
                "startDate": "unknown",
                "endDate": "unknown",
                "location": {
                    "@type": "Place",
                    "name": "Vallsjö"
                }
            },
            {
                "@type": "JobPosting",
                "title": "Curate",
                "startDate": "1930",
                "endDate": "unknown",
                "location": {
                    "@type": "Place",
                    "name": "Bredaryd"
                }
            },
            {
                "@type": "JobPosting",
                "title": "Pastor",
                "startDate": "1942",
                "endDate": "unknown",
                "location": {
                    "@type": "Place",
                    "name": "Gränna"
                }
            }
        ],
        "memberOf": [
            {
                "@type": "Organization",
                "name": "Church Council"
            },
            {
                "@type": "Organization",
                "name": "National Elementary School Board"
            },
            {
                "@type": "Organization",
                "name": "Lecture Association"
            },
            {
                "@type": "Organization",
                "name": "Gränna Scout Corps"
            },
            {
                "@type": "Organization",
                "name": "Northern Småland Scout District"
            }
        ]
    }
}