{
    "original": "Bäckman, Elon Conrad, köpman, Göteborg, f. 2/6/00 av Erik Conrad B. o. Emilia Pettersson. G. 45 m. Margit Östergren. — Stud. v. Eskilstuna tekn. sk. 15-16, merkant. utb. v. Hermods korresp :inst. Kont. v. Munktelis Mek. Verkst. A-B i Eskilstuna 15-21, avd:-chef f. planeringen v. Nydqvist &amp; Holm A-B, Eskilstuna-Verken, 21-23, ink:chef där 23-25, kamr. o. försäljn:-chief i jiärnigrossh : firman Knut W. Are-skogh i Eskilstuna (repr. f. Avesta Jernverk, A-B Bofors o. A-B Axel Christiernsson) 25-45, egen firma i Gbg sed. 45. Sekr. i sekt. f. fri idr., fiolb., biandy o. skidor i GUIF i Eskils-tunia 17-24i, s€kt. f. fri idr. o. bandy 28-32, sekr. i Södermani. idr:förb. 25-27, v. sekr. 28 o. 39-45, styr :led. i Sv:es GUIF sekt. f. gymn. o. idr. 24-30, stift, av Södermani. bandyförb. 29, dess sekr. o. kassör 29-33, rev. i Eskilstuna tenniskl. 30-32, sekr. 33-36, ordf. i arb:-utsk. 35, sekr. 39-41, ordf. 42-45, init:-tag. t. Södermani. idr :förb. tennissekt. i Eskilstuna 38, ordf. 38-45, sekr. i fören. Eskilstuna idr :hall u. p. a. 38-45, omb :man f. riksskidmarschen i Södermani. 42-45, instruktör i civ:försv. 40-45. Bandy- o. fotb:domare 19-25, domare i fri idr. 19-44, dito i tennis 32-45. Har hemf. flera segrar i fotb., bandy, löpn., cykel o. tennis. Med-arb. i Sörmiandsposten und. sign. Con Brio, i GUIF medl :blad Lysmasken 20-29, red. 29-32. Riksidr :förb. för-tj :t. i guld.",
    "translated": "Bäckman, Elon Conrad, merchant, Gothenburg, b. June 2nd, 1900 to Erik Conrad B. and Emilia Pettersson. Married in 1945 to Margit Östergren. Studied at Eskilstuna Technical School from 1915 to 1916, and received commercial education from Hermods Correspondence Institute. Worked at Munktelis Mechanical Works AB in Eskilstuna from 1915 to 1921, became department manager for planning at Nydqvist & Holm AB, Eskilstuna-Verken from 1921 to 1923, then head of purchase from 1923 to 1925. Became a trade and sales manager for iron wholesale firm Knut W. Areskogh in Eskilstuna, representing Avesta Jernverk AB, AB Bofors, and AB Axel Christiernsson from 1925 to 1945. Started his own company in Gothenburg in 1945. Served as secretary for the section for free sports, ice hockey, bandy and skiing at GUIF in Eskilstuna from 1917 to 1924. Served as secretary for the section for free sports and bandy from 1928 to 1932, and as secretary and vice-secretary for Södermani. Idrarförbund from 1925 to 1927, and from 1928 to 1945 respectivelty. Also served as a board member for the Swedish GUIF section for gymnastics and sports from 1924 to 1930, and for the Södermani. Bandy Association in 1929, as well as its secretary and treasurer from 1929 to 1933. Served as auditor for the Eskilstuna Tennis Club from 1930 to 1932, before becoming its secretary from 1933 to 1936, and then chairman from 1938 to 1945. Initiated the Södermani. Idrarforbund tennis section in Eskilstuna in 1938, and served as chairman from 1938 to 1945. Also served as secretary for Eskilstuna Sports Hall Association from 1938 to 1945, and as an official for the national ski march in Södermani. from 1942 to 1945. Instructed in civil defense from 1940 to 1945. Was a bandy and football referee from 1919 to 1925, a referee in free sports from 1919 to 1944, and a tennis referee from 1932 to 1945. Won several victories in football, bandy, running, cycling, and tennis. Was a collaborator for Sörmiandsposten under the pseudonym Con Brio, and was a member and editor of Lysmasken from 1920 to 1929. Received gold from the National Sports Federation.",
    "structured_raw": "{\n  \"@context\": \"https://schema.org/\",\n  \"@type\": \"Person\",\n  \"name\": \"Elon Conrad Bäckman\",\n  \"birthDate\": \"1900-06-02\",\n  \"birthPlace\": \"Gothenburg\",\n  \"parents\": [\n    {\n      \"@type\": \"Person\",\n      \"name\": \"Erik Conrad Bäckman\",\n      \"sameAs\": \"\"\n    },\n    {\n      \"@type\": \"Person\",\n      \"name\": \"Emilia Pettersson\",\n      \"sameAs\": \"\"\n    }\n  ],\n  \"spouse\": {\n    \"@type\": \"Person\",\n    \"name\": \"Margit Östergren\",\n    \"sameAs\": \"\"\n  },\n  \"education\": [\n    {\n      \"@type\": \"EducationalOrganization\",\n      \"name\": \"Eskilstuna Technical School\",\n      \"startDate\": \"1915\",\n      \"endDate\": \"1916\"\n    },\n    {\n      \"@type\": \"EducationalOrganization\",\n      \"name\": \"Hermods Correspondence Institute\"\n    }\n  ],\n  \"employmentHistory\":[\n    {\n      \"@type\": \"Organization\",\n      \"name\": \"Munktelis Mechanical Works AB\",\n      \"startDate\": \"1915\",\n      \"endDate\": \"1921\",\n      \"position\": \"Employee\"\n    },\n    {\n      \"@type\": \"Organization\",\n      \"name\": \"Nydqvist & Holm AB, Eskilstuna-Verken\",\n      \"startDate\": \"1921\",\n      \"endDate\": \"1923\",\n      \"position\": \"Department Manager for Planning\"\n    },\n    {\n      \"@type\": \"Organization\",\n      \"name\": \"Nydqvist & Holm AB, Eskilstuna-Verken\",\n      \"startDate\": \"1923\",\n      \"endDate\": \"1925\",\n      \"position\": \"Head of Purchase\"\n    },\n    {\n      \"@type\": \"Organization\",\n      \"name\": \"Knut W. Areskogh\",\n      \"startDate\": \"1925\",\n      \"endDate\": \"1945\",\n      \"position\": \"Trade and Sales Manager\"\n    },\n    {\n      \"@type\": \"Organization\",\n      \"name\": \"Own Company\",\n      \"startDate\": \"1945\",\n      \"position\": \"Founder\"\n    }\n  ],\n  \"memberOf\":[\n    {\n      \"@type\": \"Organization\",\n      \"name\": \"GUIF\",\n      \"position\": \"Secretary\",\n      \"startDate\": \"1917\",\n      \"endDate\": \"1924\"\n    },\n    {\n      \"@type\": \"Organization\",\n      \"name\": \"Södermani Idrarförbund\",\n      \"position\": \"Secretary and Vice-Secretary\",\n      \"startDate\": \"1925\",\n      \"endDate\": \"1945\"\n    },\n    {\n      \"@type\": \"Organization\",\n      \"name\": \"Swedish GUIF\",\n      \"position\": \"Board Member\",\n      \"startDate\": \"1924\",\n      \"endDate\": \"1930\"\n    },\n    {\n      \"@type\": \"Organization\",\n      \"name\": \"Södermani Bandy Association\",\n      \"position\": \"Board Member, Secretary and Treasurer\",\n      \"startDate\": \"1929\",\n      \"endDate\": \"1933\"\n    },\n    {\n      \"@type\": \"Organization\",\n      \"name\": \"Eskilstuna Tennis Club\",\n      \"position\": \"Auditor, Secretary, Chairman\",\n      \"startDate\": \"1930\",\n      \"endDate\": \"1945\"\n    },\n    {\n      \"@type\": \"Organization\",\n      \"name\": \"Eskilstuna Sports Hall Association\",\n      \"position\": \"Secretary\",\n      \"startDate\": \"1938\",\n      \"endDate\": \"1945\"\n    }\n  ],\n  \"refereeOf\": [\n    {\n      \"@type\": \"SportsTeam\",\n      \"name\": \"Football\",\n      \"startDate\": \"1919\",\n      \"endDate\": \"1925\"\n    },\n    {\n      \"@type\": \"SportsTeam\",\n      \"name\": \"Free Sports\",\n      \"startDate\": \"1919\",\n      \"endDate\": \"1944\"\n    },\n    {\n      \"@type\": \"SportsTeam\",\n      \"name\": \"Tennis\",\n      \"startDate\": \"1932\",\n      \"endDate\": \"1945\"\n    }\n  ],\n  \"awards\": {\n    \"@type\": \"Award\",\n    \"name\": \"Gold from the National Sports Federation\"\n  }\n}",
    "structured": {
        "@context": "https://schema.org/",
        "@type": "Person",
        "name": "Elon Conrad Bäckman",
        "birthDate": "1900-06-02",
        "birthPlace": "Gothenburg",
        "parents": [
            {
                "@type": "Person",
                "name": "Erik Conrad Bäckman",
                "sameAs": ""
            },
            {
                "@type": "Person",
                "name": "Emilia Pettersson",
                "sameAs": ""
            }
        ],
        "spouse": {
            "@type": "Person",
            "name": "Margit Östergren",
            "sameAs": ""
        },
        "education": [
            {
                "@type": "EducationalOrganization",
                "name": "Eskilstuna Technical School",
                "startDate": "1915",
                "endDate": "1916"
            },
            {
                "@type": "EducationalOrganization",
                "name": "Hermods Correspondence Institute"
            }
        ],
        "employmentHistory": [
            {
                "@type": "Organization",
                "name": "Munktelis Mechanical Works AB",
                "startDate": "1915",
                "endDate": "1921",
                "position": "Employee"
            },
            {
                "@type": "Organization",
                "name": "Nydqvist & Holm AB, Eskilstuna-Verken",
                "startDate": "1921",
                "endDate": "1923",
                "position": "Department Manager for Planning"
            },
            {
                "@type": "Organization",
                "name": "Nydqvist & Holm AB, Eskilstuna-Verken",
                "startDate": "1923",
                "endDate": "1925",
                "position": "Head of Purchase"
            },
            {
                "@type": "Organization",
                "name": "Knut W. Areskogh",
                "startDate": "1925",
                "endDate": "1945",
                "position": "Trade and Sales Manager"
            },
            {
                "@type": "Organization",
                "name": "Own Company",
                "startDate": "1945",
                "position": "Founder"
            }
        ],
        "memberOf": [
            {
                "@type": "Organization",
                "name": "GUIF",
                "position": "Secretary",
                "startDate": "1917",
                "endDate": "1924"
            },
            {
                "@type": "Organization",
                "name": "Södermani Idrarförbund",
                "position": "Secretary and Vice-Secretary",
                "startDate": "1925",
                "endDate": "1945"
            },
            {
                "@type": "Organization",
                "name": "Swedish GUIF",
                "position": "Board Member",
                "startDate": "1924",
                "endDate": "1930"
            },
            {
                "@type": "Organization",
                "name": "Södermani Bandy Association",
                "position": "Board Member, Secretary and Treasurer",
                "startDate": "1929",
                "endDate": "1933"
            },
            {
                "@type": "Organization",
                "name": "Eskilstuna Tennis Club",
                "position": "Auditor, Secretary, Chairman",
                "startDate": "1930",
                "endDate": "1945"
            },
            {
                "@type": "Organization",
                "name": "Eskilstuna Sports Hall Association",
                "position": "Secretary",
                "startDate": "1938",
                "endDate": "1945"
            }
        ],
        "refereeOf": [
            {
                "@type": "SportsTeam",
                "name": "Football",
                "startDate": "1919",
                "endDate": "1925"
            },
            {
                "@type": "SportsTeam",
                "name": "Free Sports",
                "startDate": "1919",
                "endDate": "1944"
            },
            {
                "@type": "SportsTeam",
                "name": "Tennis",
                "startDate": "1932",
                "endDate": "1945"
            }
        ],
        "awards": {
            "@type": "Award",
            "name": "Gold from the National Sports Federation"
        }
    }
}