{
    "original": "Zåk, Frans Carl, musikdirektör, Göteborg, f. 24/1/97 i Bohumin, Tjecko-slov., av musikdir. Frans o. Dolfi Zàk. G. 23 m. Lisa Peterson. Barn: Majken f. 24. — Musikdir :ex. 20. Res. t. Tyskl. 26, USA 30, 39, Paris 37. Tid. kapellm. v. teat. i Brünn, v. St. Teat. i Gbg, or g. o. kördirig. v. katolska förs. i Gbg fr. 32, kapellm. v. Gbgs stadsteat. fr. 36. Medl. av TSO o. TG. Sv. medb. fr. 27. Komp. kyrkl. hymner. Hobby: filateh.",
    "translated": "Zåk, Frans Carl, music director, Gothenburg, born on January 24, 1897 in Bohumin, Czechoslovakia, son of music director Frans and Dolfi Zàk. Married in 1923 to Lisa Peterson. Children: Majken, born in 1924. Became a music director in 1920. Resided in Germany in 1926, the United States in 1930 and 1939, and Paris in 1937. Served as a conductor for the theater in Brno, the State Theater in Gothenburg, and as a church choir conductor for the Catholic parish in Gothenburg from 1932. Became a conductor for Gothenburg City Theatre in 1936. Was a member of the Gothenburg Symphony Orchestra (TSO) and the Gothenburg Theater Association (TG). Became a Swedish citizen in 1927. Composed church hymns. Hobby: philately.",
    "structured_raw": "{\n  \"@context\": \"https://schema.org\",\n  \"@type\": \"Person\",\n  \"name\": \"Frans Carl Zåk\",\n  \"jobTitle\": \"Music Director\",\n  \"address\": {\n    \"@type\": \"PostalAddress\",\n    \"addressLocality\": \"Gothenburg\"\n  },\n  \"birthDate\": \"1897-01-24\",\n  \"birthPlace\": {\n    \"@type\": \"Place\",\n    \"name\": \"Bohumin, Czechoslovakia\"\n  },\n  \"parents\": [\n    {\n      \"@type\": \"Person\",\n      \"name\": \"Frans Zàk\",\n      \"jobTitle\": \"Music Director\"\n    },\n    {\n      \"@type\": \"Person\",\n      \"name\": \"Dolfi Zàk\"\n    }\n  ],\n  \"spouse\": {\n    \"@type\": \"Person\",\n    \"name\": \"Lisa Peterson\"\n  },\n  \"children\": [\n    {\n      \"@type\": \"Person\",\n      \"name\": \"Majken\",\n      \"birthDate\": \"1924\"\n    }\n  ],\n  \"worksFor\": {\n    \"@type\": \"Organization\",\n    \"name\": \"Gothenburg City Theatre\"\n  },\n  \"memberOf\": [\n    {\n      \"@type\": \"Organization\",\n      \"name\": \"Gothenburg Symphony Orchestra\"\n    },\n    {\n      \"@type\": \"Organization\",\n      \"name\": \"Gothenburg Theater Association\"\n    }\n  ],\n  \"nationality\": \"Swedish\",\n  \"hobbies\": \"Philately\"\n}",
    "structured": {
        "@context": "https://schema.org",
        "@type": "Person",
        "name": "Frans Carl Zåk",
        "jobTitle": "Music Director",
        "address": {
            "@type": "PostalAddress",
            "addressLocality": "Gothenburg"
        },
        "birthDate": "1897-01-24",
        "birthPlace": {
            "@type": "Place",
            "name": "Bohumin, Czechoslovakia"
        },
        "parents": [
            {
                "@type": "Person",
                "name": "Frans Zàk",
                "jobTitle": "Music Director"
            },
            {
                "@type": "Person",
                "name": "Dolfi Zàk"
            }
        ],
        "spouse": {
            "@type": "Person",
            "name": "Lisa Peterson"
        },
        "children": [
            {
                "@type": "Person",
                "name": "Majken",
                "birthDate": "1924"
            }
        ],
        "worksFor": {
            "@type": "Organization",
            "name": "Gothenburg City Theatre"
        },
        "memberOf": [
            {
                "@type": "Organization",
                "name": "Gothenburg Symphony Orchestra"
            },
            {
                "@type": "Organization",
                "name": "Gothenburg Theater Association"
            }
        ],
        "nationality": "Swedish",
        "hobbies": "Philately"
    }
}