{
    "original": "Ewards, Elisabeth Anna Maria, läroverksadjunkt, Karlskrona, f. 18/3/88 i Karlskrona. •— Stud:ex. v. Åhlinska sk. i Sthlm 09, fil. mag. i Lund 13, provår 30. Lär. v. Kävlinge priv. samsk. 17-21, Nyströmska h. flicklä-rov. i Malmö 21-22, e. o. ämneslär. i Huskvarna 22-32, e. lär. där 32-36, adj. i tyska o. franska v. Karlskrona h. a. 1. sed. 36. *Ewe-Ericsson, Runo, rektor, Göteborg, f. 5/12/92 i Malmö. — Stud. v. h. a. 1. i Malmö, tekn. facksk. där o. CTH, intern. flyg:certif. 17, spec:-stud. i motor- o. flygtekn. i uti. Prakt, v. Malmö stads elverks lab., v. SJis verkstäd., v. Götaverken, v. Thulinverken, h. Burmeister &amp; Wain i Köpenhamn m. fl. Tekn. chef f. A-B Togas au to- o. motor tekn. avd. i Malmö 21-27, spec :ilär. i förbränn :mot., för- bränn :kenii o. fiygtekn. v. Gbgs tekn. inst. ’sed. 27, bitr. rektor 38, rektor sed. 41. Skr.: fl. kompend. om förbränn :-mot., i biitekn. o. tekn. gasanalyser, fl. pat. på bl. a. autom. varuhisskonstr.",
    "translated": "Ewards, Elisabeth Anna Maria, school assistant, Karlskrona, b. 18/3/88 in Karlskrona. - Graduated from Åhlinska School in Stockholm with a studentexamen in 1909, graduated with a degree of filosofie magister from Lund University in 1913, with a one-year supplementary education in 1930. Taught at Kävlinge private school from 1917-1921, Nyström's girls' high school in Malmö from 1921-1922, acting subject teacher in Huskvarna from 1922-1932, permanent teacher there from 1932-1936, and assistant teacher in German and French at Karlskrona high school since 1936. \n\n*Ewe-Ericsson, Runo, principal, Gothenburg, b. 5/12/92 in Malmö. - Studied at Malmö high school, technical vocational school there, Chalmers University of Technology, and earned international flight certification in 1917. Specialized in motor and aviation technology through international studies. Worked in practical settings such as Malmö city power plant laboratory, SJIs workshops, Götaverken, Thulinverken, Burmeister &amp; Wain in Copenhagen, and others. Technical manager for A-B Togas motor and automotive technical department in Malmö from 1921-1927, specialized teacher in combustion engines, combustion chemistry, and aviation technology at the Gothenburg Technical Institute since 1927, vice principal in 1938, principal since 1941. Wrote several compendiums on combustion engines, biotechnology, and technical gas analysis, as well as several patents on automatic elevator design, among others.",
    "structured_raw": "{\n  \"@context\": \"https://schema.org/\",\n  \"@type\": \"Person\",\n  \"name\": \"Elisabeth Anna Maria Ewards\",\n  \"jobTitle\": \"School Assistant\",\n  \"birthPlace\": \"Karlskrona\",\n  \"birthDate\": \"1888-03-18\",\n  \"deathDate\": \"\",\n  \"alumniOf\": [\n    {\n      \"@type\": \"EducationalOrganization\",\n      \"name\": \"Åhlinska School\"\n    },\n    {\n      \"@type\": \"CollegeOrUniversity\",\n      \"name\": \"Lund University\",\n      \"degree\": \"filosofie magister\",\n      \"classYear\": \"1913\"\n    }\n  ],\n  \"additionalProperty\": [\n    {\n      \"@type\": \"PropertyValue\",\n      \"name\": \"Stud:ex\",\n      \"value\": \"1909\"\n    },\n    {\n      \"@type\": \"PropertyValue\",\n      \"name\": \"provår\",\n      \"value\": \"1930\"\n    }\n  ],\n  \"memberOf\": [\n    {\n      \"@type\": \"Organization\",\n      \"name\": \"Kävlinge Private School\",\n      \"startDate\": \"1917\",\n      \"endDate\": \"1921\"\n    },\n    {\n      \"@type\": \"Organization\",\n      \"name\": \"Nyström's Girls' High School\",\n      \"startDate\": \"1921\",\n      \"endDate\": \"1922\"\n    },\n    {\n      \"@type\": \"Organization\",\n      \"name\": \"Huskvarna\",\n      \"roleName\": \"acting subject teacher\",\n      \"startDate\": \"1922\",\n      \"endDate\": \"1932\"\n    },\n    {\n      \"@type\": \"Organization\",\n      \"name\": \"Huskvarna\",\n      \"roleName\": \"permanent teacher\",\n      \"startDate\": \"1932\",\n      \"endDate\": \"1936\"\n    },\n    {\n      \"@type\": \"Organization\",\n      \"name\": \"Karlskrona High School\",\n      \"roleName\": \"Assistant Teacher\",\n      \"startDate\": \"1936\"\n    }\n  ],\n  \"spouse\": {\n    \"@type\": \"Person\",\n    \"name\": \"Runo Ewe-Ericsson\",\n    \"jobTitle\": \"Principal\",\n    \"birthPlace\": \"Malmö\",\n    \"birthDate\": \"1892-12-05\",\n    \"alumniOf\": [\n      {\n        \"@type\": \"EducationalOrganization\",\n        \"name\": \"Malmö High School\"\n      },\n      {\n        \"@type\": \"EducationalOrganization\",\n        \"name\": \"Chalmers University of Technology\"\n      }\n    ],\n    \"additionalProperty\": [\n      {\n        \"@type\": \"PropertyValue\",\n        \"name\": \"international flight certification\",\n        \"value\": \"1917\"\n      }\n    ],\n    \"memberOf\": [\n      {\n        \"@type\": \"Organization\",\n        \"name\": \"Göteborg Technical Institute\",\n        \"roleName\": \"specialized teacher\",\n        \"startDate\": \"1927\"\n      }\n    ],\n    \"worksFor\": {\n      \"@type\": \"Organization\",\n      \"name\": \"A-B Togas\",\n      \"roleName\": \"Technical Manager\",\n      \"startDate\": \"1921\",\n      \"endDate\": \"1927\"\n    },\n    \"description\": \"Specialized in motor and aviation technology through international studies. Wrote several compendiums on combustion engines, biotechnology, and technical gas analysis, as well as several patents on automatic elevator design, among others.\"\n  }\n}",
    "structured": {
        "@context": "https://schema.org/",
        "@type": "Person",
        "name": "Elisabeth Anna Maria Ewards",
        "jobTitle": "School Assistant",
        "birthPlace": "Karlskrona",
        "birthDate": "1888-03-18",
        "deathDate": "",
        "alumniOf": [
            {
                "@type": "EducationalOrganization",
                "name": "Åhlinska School"
            },
            {
                "@type": "CollegeOrUniversity",
                "name": "Lund University",
                "degree": "filosofie magister",
                "classYear": "1913"
            }
        ],
        "additionalProperty": [
            {
                "@type": "PropertyValue",
                "name": "Stud:ex",
                "value": "1909"
            },
            {
                "@type": "PropertyValue",
                "name": "provår",
                "value": "1930"
            }
        ],
        "memberOf": [
            {
                "@type": "Organization",
                "name": "Kävlinge Private School",
                "startDate": "1917",
                "endDate": "1921"
            },
            {
                "@type": "Organization",
                "name": "Nyström's Girls' High School",
                "startDate": "1921",
                "endDate": "1922"
            },
            {
                "@type": "Organization",
                "name": "Huskvarna",
                "roleName": "acting subject teacher",
                "startDate": "1922",
                "endDate": "1932"
            },
            {
                "@type": "Organization",
                "name": "Huskvarna",
                "roleName": "permanent teacher",
                "startDate": "1932",
                "endDate": "1936"
            },
            {
                "@type": "Organization",
                "name": "Karlskrona High School",
                "roleName": "Assistant Teacher",
                "startDate": "1936"
            }
        ],
        "spouse": {
            "@type": "Person",
            "name": "Runo Ewe-Ericsson",
            "jobTitle": "Principal",
            "birthPlace": "Malmö",
            "birthDate": "1892-12-05",
            "alumniOf": [
                {
                    "@type": "EducationalOrganization",
                    "name": "Malmö High School"
                },
                {
                    "@type": "EducationalOrganization",
                    "name": "Chalmers University of Technology"
                }
            ],
            "additionalProperty": [
                {
                    "@type": "PropertyValue",
                    "name": "international flight certification",
                    "value": "1917"
                }
            ],
            "memberOf": [
                {
                    "@type": "Organization",
                    "name": "Göteborg Technical Institute",
                    "roleName": "specialized teacher",
                    "startDate": "1927"
                }
            ],
            "worksFor": {
                "@type": "Organization",
                "name": "A-B Togas",
                "roleName": "Technical Manager",
                "startDate": "1921",
                "endDate": "1927"
            },
            "description": "Specialized in motor and aviation technology through international studies. Wrote several compendiums on combustion engines, biotechnology, and technical gas analysis, as well as several patents on automatic elevator design, among others."
        }
    }
}