{
    "original": "Kaiser, Erik, prakt, läkare, Göteborg, f. 20/8/92 i Sthlm av grosshandl. Eduard K. o. Thérèse Bensow^. G. 19 m. Karin Charlotta Eisner. Barn: Ragnar f. 21, jur. kand., Marianne 25, ex. vävlär. — Stud:ex. i Sthlm 10, med. kand. v. Karol. inst. 15 o. med. lic. där 19. Aman. i anat. v. Karol. inst. 15, tf. und :läk. v. Eskilstuna las. 17, andre aman. v. Seraf :las. kir. klin. 18, tf. und:läk. v. Sthlms epid:sjukh. 19, v. Skellefteå las. 19, und:läk. v. Ängelholms las. 19-20, bitr. läk. v. Holtermanska sjukh. 20-23, tf. över-läk. där tre mån., assist :läk. v. Gbgs stads poliklin. f. hud- o. könssjukd. 33-34, läk. där 34, läk. å Sv. Amerika Liniens fartyg kort. tider 21, 24 o. 26, prakt. läk. i Gbg ^sed. 23. Kalén, Helge Olov Efraim, tandläkare, Norrköping, f. 13/5/07 i Tingstad, östergötl. 1., av folksk :lär. o. kantorn Albert K. o. Emma Andersson. G. m. Dagmar Walman. Barn: Ulla Britt f. 29, Ragnar 36, Lena-Kari 38. — Stud:ex. i Norrköp. 25, tandl:-kand. 26, tandl. 29. Prakt, i Hallstavik 29-30, i Hudiksvall 30-32 o. i Norrköp. sed. 33. Kalén, Herbert Johannes, rektor, Göteborg, f. 21/6/93 i Gbg av rektor Frithiof K. o. Lizzie Frost. G. 23 m. Vera Pattison. Barn: Roger f. 27. — Stud:ex. v. Gbgs h. latin 11, fil. kand. i Gbg 14, fil. mag. 17, fil. lic. 21, fil. dr 23, stud. v. univ. i Jena 13, Oxford 19, Dijon o. Paris 28-29, provår v. Gbgs h. real 22-23. Res. t. Tyskl., Engl. o. Frankr. uppr. ggr 12-39 o. 45-46 samt t. Norge, Danm., HolL, Belg., Österr. o. Ital. Lär. v. Rodhes sk. i Gbg 11-22, e. lär. v. Gbgs hand:-inst. 17-20 o. 21-22, e. o. lektor v. Uddevalla komm. gymn. 23-27, adj. v. Linköp. h. a. 1. 27-29, v. Gbgs h. real 29^31, lektor i eng. o. franska v. Gbgs hand :inst. sed. 31, reaktor där sed. 41. Timlär. v. Gbgs flickgymn. 30-32, an-ordn. o. lett sommarkurs, f, sv. skol-ungd. i Oxford o. Bournemouth 23-29 samt lett eng. sommarkurs f. folk-sk :lär. 45. Rev. v. Gbgs högsk., led. av styr. f. Gbgs hand:högsk., Gbgs prakt, mellansk., Anglo-Sv^ed. Soc. i Gbg. Skr.: A Middle-Engl. Metrical Paraphrase of the Old Testament (grad:avh. 23), Grammat. övn :bok i eng. affärsspråk (37), An Engl. com-merc. Reader (m. ordlista o. kom-ment. 35), Avgångsprov i eng. v. Iiand:g3^mn. (45), språkvet :skapl. o. pedagog, art. o. rec. i tidn. o. tidskr. Hobbies: litt., filateli, resor, skidåkn. RVOlikl. Kalén, Eva Agda Ingeborg, tandläkare, Motala, f. 20/8/02 i Tingstad, Östergötl. L, av folksk :lär. o. kantorn Albert K. o. Emma Andersson. — Stud:ex. i Eslöv 22, tandl:kand. 25, tandl. 27. Vik. i Sollefteå 27-28, prakt, i Motala :sed. 28. Kalén, Ingemar Eskil Johan, fil. kand., stadsbibliotekarie, Tranås, f. 28/10/17 i Varberg av folkskollär. Johan K. o. Theres Boman. G. 44 m. Inger Cars. Barn: Kerstin f. 45, Johan\" 46. — Stud:ex. 37, fil. kand. 43, utex. fr. sikolö ver styr. bibi isköla 45. Stads-bibi. i Tranås sed. 45. Styr :l’ed. i Sv. folkbiblioteikariefören. ’sed. 45.",
    "translated": "Kaiser, Erik, M.D., Gothenburg, born on August 20, 1892 in Stockholm, son of merchant Eduard K. and Thérèse Bensow^. Married to Karin Charlotta Eisner. Children: Ragnar, born in 1921, law graduate, Marianne, born in 1925, textile consultant. Completed high school in Stockholm in 1910, earned a Bachelor of Medicine degree from the Caroline Institute in 1915, and a medical license in 1919. Assistant in Anatomy at the Caroline Institute in 1915, temporary assistant physician at Eskilstuna Hospital in 1917, assistant physician at Seraf Central Hospital Surgical Clinic in 1918, temporary assistant physician at Stockholm Epidemic Hospital in 1919, at Skellefteå Hospital in 1919, at Ängelholm Hospital from 1919 to 1920, assistant physician at Holtermanska Hospital from 1920 to 1923, temporary chief physician there for three months, assisting physician at Gothenburg City Polyclinic for Dermatology and Venereology from 1933 to 1934, physician there in 1934, physician on Swedish America Line ships for short periods in 1921, 1924, and 1926, practicing physician in Gothenburg since 1923.\n\nKalén, Helge Olov Efraim, dentist, Norrköping, born on May 13, 1907 in Tingstad, Östergötland County, son of primary school teacher Albert K. and Emma Andersson. Married to Dagmar Walman. Children: Ulla Britt, born in 1929, Ragnar, born in 1936, Lena-Kari, born in 1938. Completed high school in Norrköping in 1925, earned a dental degree in 1926, and became a dentist in 1929. Practiced in Hallstavik from 1929 to 1930, in Hudiksvall from 1930 to 1932, and in Norrköping since 1933.\n\nKalén, Herbert Johannes, rector, Gothenburg, born on June 21, 1893 in Gothenburg, son of rector Frithiof K. and Lizzie Frost. Married in 1923 to Vera Pattison. Son: Roger, born in 1927. Completed high school at Gothenburg Latin School in 1911, earned a Bachelor of Arts degree in Gothenburg in 1914, a Master of Arts in 1917, a Licentiate of Philosophy in 1921, and a Doctorate of Philosophy in 1923. Studied at the University of Jena in 1913, Oxford University in 1919, and in Dijon and Paris from 1928 to 1929. Foundation year at Gothenburg Real School in 1922-1923. Traveled to Germany, England, France, Norway, Denmark, the Netherlands, Belgium, Austria, and Italy multiple times between 1912 and 1939, and again in 1945 and 1946. Taught at Rodhe's School in Gothenburg from 1911 to 1922, substitute teacher at Gothenburg School of Commerce from 1917 to 1920 and from 1921 to 1922, extra lecturer at Uddevalla Municipality Gymnasium from 1923 to 1927, adjunct at Linköping Higher Primary School from 1927 to 1929, at Gothenburg Real School from 1929 to 1931, lecturer in English and French at Gothenburg School of Commerce since 1931, rector there since 1941. Hourly teacher at Gothenburg Girls' Gymnasium from 1930 to 1932, organizer and instructor of summer courses for Swedish school youths in Oxford and Bournemouth from 1923 to 1929, and instructor of summer courses in English for primary school teachers in 1945. Revised Gothenburg University, member of the Gothenburg School of Commerce board, Gothenburg Practical Mid-level College, and the Anglo-Swedish Society in Gothenburg. Writings: A Middle-English Metrical Paraphrase of the Old Testament (doctoral dissertation, 1923), Grammar exercises book in English for business language (1937), An English commercial reader (with glossary and commentary, 1935), Graduation exam in English for commercial school (1945), articles and reviews in journals and magazines. Hobbies: literature, philately, travel, skiing. Received the Order of the Polar Star.\n\nKalén, Eva Agda Ingeborg, dentist, Motala, born on August 20, 1902 in Tingstad, Östergötland County, daughter of primary school teacher Albert K. and Emma Andersson. Completed high school in Eslöv in 1922, earned a dental degree in 1925, and became a dentist in 1927. Worked temporarily in Sollefteå from 1927 to 1928, and has been practicing in Motala since 1928.\n\nKalén, Ingemar Eskil Johan, Bachelor of Arts, city librarian, Tranås, born on October 28, 1917 in Varberg, son of primary school teacher Johan K. and Theres Boman. Married in 1944 to Inger Cars. Children: Kerstin, born in 1945, Johan, born in 1946. Completed high school in 1937, earned a Bachelor of Arts degree in 1943, passed the examination in library studies in 1945. City librarian in Tranås since 1945. Board member of the Swedish Folk Librarians Association since 1945.",
    "structured_raw": "{\n  \"@context\": \"https://schema.org\",\n  \"@type\": \"Person\",\n  \"name\": \"Erik Kaiser\",\n  \"birthDate\": \"1892-08-20\",\n  \"birthPlace\": \"Stockholm\",\n  \"jobTitle\": \"Doctor\",\n  \"address\": {\n    \"@type\": \"PostalAddress\",\n    \"addressLocality\": \"Gothenburg\",\n    \"addressCountry\": \"Sweden\"\n  },\n  \"parent\": [\n    {\n      \"@type\": \"Person\",\n      \"name\": \"Eduard Kaiser\",\n      \"jobTitle\": \"Merchant\"\n    },\n    {\n      \"@type\": \"Person\",\n      \"name\": \"Thérèse Bensow^\"\n    }\n  ],\n  \"spouse\": {\n    \"@type\": \"Person\",\n    \"name\": \"Karin Charlotta Eisner\"\n  },\n  \"children\": [\n    {\n      \"@type\": \"Person\",\n      \"name\": \"Ragnar Kaiser\",\n      \"birthDate\": \"1921\"\n    },\n    {\n      \"@type\": \"Person\",\n      \"name\": \"Marianne Kaiser\",\n      \"birthDate\": \"1925\"\n    }\n  ],\n  \"education\": [\n    {\n      \"@type\": \"EducationalOccupationalCredential\",\n      \"credentialCategory\": \"HighSchoolDiploma\",\n      \"educationalLevel\": \"High school\",\n      \"startDate\": \"1910\",\n      \"endDate\": \"1910\",\n      \"awardingInstitution\": {\n        \"@type\": \"Organization\",\n        \"name\": \"Stockholm High School\"\n      }\n    },\n    {\n      \"@type\": \"EducationalOccupationalCredential\",\n      \"credentialCategory\": \"BachelorDegree\",\n      \"educationalLevel\": \"Bachelor's\",\n      \"fieldOfStudy\": \"Medicine\",\n      \"startDate\": \"1915\",\n      \"endDate\": \"1915\",\n      \"awardingInstitution\": {\n        \"@type\": \"Organization\",\n        \"name\": \"Caroline Institute\"\n      }\n    },\n    {\n      \"@type\": \"EducationalOccupationalCredential\",\n      \"credentialCategory\": \"MedicalLicense\",\n      \"startDate\": \"1919\",\n      \"endDate\": \"1919\",\n      \"awardingInstitution\": {\n        \"@type\": \"Organization\",\n        \"name\": \"Caroline Institute\"\n      }\n    }\n  ],\n  \"employmentHistory\": [\n    {\n      \"@type\": \"OrganizationRole\",\n      \"startDate\": \"1915\",\n      \"endDate\": \"1915\",\n      \"roleName\": \"Assistant in Anatomy\",\n      \"organization\": {\n        \"@type\": \"Organization\",\n        \"name\": \"Caroline Institute\"\n      }\n    },\n    {\n      \"@type\": \"OrganizationRole\",\n      \"startDate\": \"1917\",\n      \"endDate\": \"1917\",\n      \"roleName\": \"Temporary Assistant Physician\",\n      \"organization\": {\n        \"@type\": \"Organization\",\n        \"name\": \"Eskilstuna Hospital\"\n      }\n    },\n    {\n      \"@type\": \"OrganizationRole\",\n      \"startDate\": \"1918\",\n      \"endDate\": \"1918\",\n      \"roleName\": \"Assistant Physician\",\n      \"organization\": {\n        \"@type\": \"Organization\",\n        \"name\": \"Seraf Central Hospital Surgical Clinic\"\n      }\n    },\n    {\n      \"@type\": \"OrganizationRole\",\n      \"startDate\": \"1919\",\n      \"endDate\": \"1919\",\n      \"roleName\": \"Temporary Assistant Physician\",\n      \"organization\": {\n        \"@type\": \"Organization\",\n        \"name\": \"Stockholm Epidemic Hospital\"\n      }\n    },\n    {\n      \"@type\": \"OrganizationRole\",\n      \"startDate\": \"1919\",\n      \"endDate\": \"1919\",\n      \"roleName\": \"Temporary Assistant Physician\",\n      \"organization\": {\n        \"@type\": \"Organization\",\n        \"name\": \"Skellefteå Hospital\"\n      }\n    },\n    {\n      \"@type\": \"OrganizationRole\",\n      \"startDate\": \"1919\",\n      \"endDate\": \"1920\",\n      \"roleName\": \"Assistant Physician\",\n      \"organization\": {\n        \"@type\": \"Organization\",\n        \"name\": \"Ängelholm Hospital\"\n      }\n    },\n    {\n      \"@type\": \"OrganizationRole\",\n      \"startDate\": \"1920\",\n      \"endDate\": \"1923\",\n      \"roleName\": \"Assistant Physician\",\n      \"organization\": {\n        \"@type\": \"Organization\",\n        \"name\": \"Holtermanska Hospital\"\n      }\n    },\n    {\n      \"@type\": \"OrganizationRole\",\n      \"startDate\": \"1933\",\n      \"endDate\": \"1934\",\n      \"roleName\": \"Assisting Physician\",\n      \"organization\": {\n        \"@type\": \"Organization\",\n        \"name\": \"Gothenburg City Polyclinic for Dermatology and Venereology\"\n      }\n    },\n    {\n      \"@type\": \"OrganizationRole\",\n      \"startDate\": \"1934\",\n      \"endDate\": \"1934\",\n      \"roleName\": \"Physician\",\n      \"organization\": {\n        \"@type\": \"Organization\",\n        \"name\": \"Gothenburg City Polyclinic for Dermatology and Venereology\"\n      }\n    }\n  ],\n  \"honorificSuffix\": \"M.D.\",\n  \"additionalName\": \"Prakt\",\n  \"spouse\": {\n    \"@type\": \"Person\",\n    \"name\": \"Karin Charlotta Eisner\"\n  }\n}",
    "structured": {
        "@context": "https://schema.org",
        "@type": "Person",
        "name": "Erik Kaiser",
        "birthDate": "1892-08-20",
        "birthPlace": "Stockholm",
        "jobTitle": "Doctor",
        "address": {
            "@type": "PostalAddress",
            "addressLocality": "Gothenburg",
            "addressCountry": "Sweden"
        },
        "parent": [
            {
                "@type": "Person",
                "name": "Eduard Kaiser",
                "jobTitle": "Merchant"
            },
            {
                "@type": "Person",
                "name": "Thérèse Bensow^"
            }
        ],
        "spouse": {
            "@type": "Person",
            "name": "Karin Charlotta Eisner"
        },
        "children": [
            {
                "@type": "Person",
                "name": "Ragnar Kaiser",
                "birthDate": "1921"
            },
            {
                "@type": "Person",
                "name": "Marianne Kaiser",
                "birthDate": "1925"
            }
        ],
        "education": [
            {
                "@type": "EducationalOccupationalCredential",
                "credentialCategory": "HighSchoolDiploma",
                "educationalLevel": "High school",
                "startDate": "1910",
                "endDate": "1910",
                "awardingInstitution": {
                    "@type": "Organization",
                    "name": "Stockholm High School"
                }
            },
            {
                "@type": "EducationalOccupationalCredential",
                "credentialCategory": "BachelorDegree",
                "educationalLevel": "Bachelor's",
                "fieldOfStudy": "Medicine",
                "startDate": "1915",
                "endDate": "1915",
                "awardingInstitution": {
                    "@type": "Organization",
                    "name": "Caroline Institute"
                }
            },
            {
                "@type": "EducationalOccupationalCredential",
                "credentialCategory": "MedicalLicense",
                "startDate": "1919",
                "endDate": "1919",
                "awardingInstitution": {
                    "@type": "Organization",
                    "name": "Caroline Institute"
                }
            }
        ],
        "employmentHistory": [
            {
                "@type": "OrganizationRole",
                "startDate": "1915",
                "endDate": "1915",
                "roleName": "Assistant in Anatomy",
                "organization": {
                    "@type": "Organization",
                    "name": "Caroline Institute"
                }
            },
            {
                "@type": "OrganizationRole",
                "startDate": "1917",
                "endDate": "1917",
                "roleName": "Temporary Assistant Physician",
                "organization": {
                    "@type": "Organization",
                    "name": "Eskilstuna Hospital"
                }
            },
            {
                "@type": "OrganizationRole",
                "startDate": "1918",
                "endDate": "1918",
                "roleName": "Assistant Physician",
                "organization": {
                    "@type": "Organization",
                    "name": "Seraf Central Hospital Surgical Clinic"
                }
            },
            {
                "@type": "OrganizationRole",
                "startDate": "1919",
                "endDate": "1919",
                "roleName": "Temporary Assistant Physician",
                "organization": {
                    "@type": "Organization",
                    "name": "Stockholm Epidemic Hospital"
                }
            },
            {
                "@type": "OrganizationRole",
                "startDate": "1919",
                "endDate": "1919",
                "roleName": "Temporary Assistant Physician",
                "organization": {
                    "@type": "Organization",
                    "name": "Skellefteå Hospital"
                }
            },
            {
                "@type": "OrganizationRole",
                "startDate": "1919",
                "endDate": "1920",
                "roleName": "Assistant Physician",
                "organization": {
                    "@type": "Organization",
                    "name": "Ängelholm Hospital"
                }
            },
            {
                "@type": "OrganizationRole",
                "startDate": "1920",
                "endDate": "1923",
                "roleName": "Assistant Physician",
                "organization": {
                    "@type": "Organization",
                    "name": "Holtermanska Hospital"
                }
            },
            {
                "@type": "OrganizationRole",
                "startDate": "1933",
                "endDate": "1934",
                "roleName": "Assisting Physician",
                "organization": {
                    "@type": "Organization",
                    "name": "Gothenburg City Polyclinic for Dermatology and Venereology"
                }
            },
            {
                "@type": "OrganizationRole",
                "startDate": "1934",
                "endDate": "1934",
                "roleName": "Physician",
                "organization": {
                    "@type": "Organization",
                    "name": "Gothenburg City Polyclinic for Dermatology and Venereology"
                }
            }
        ],
        "honorificSuffix": "M.D.",
        "additionalName": "Prakt"
    }
}