{
    "original": "Karl Albert, fd. överläkare, Göteborg, f. 1/6/72 i Gbg av stadsdi-str :liäk. Lars August Theoidor W. o. Anna Emfrida Mathàlda Almiberg. G. 10 m. Lida Böving. — Mog:ex. i Gbg 90, med. kand. 96 o. med. lic. 03’ i Upps. E. o. aman. v. a-nat. inst. i Upps. 94-95, v. kir. klin. där 98-99, aman. v. kir. poliklin. 99-00, e. o. assist, o. ob-ducent v. patolog, inst. 00, aman. v. kir. klin. 03’, underkir. där 04, aman. v. Sahligr. sjukh. kir. o. med. avd. 05, tf. andre Häk. v. kir. avd. där 05-06, andre läk. där 06-10, därunder tf. över-läk. tre mån., överläk. v. Ekmanska sjukh. 10-37, prakt. läk. Hobby: filateli. RNO, Hed:L av Gbgs nat. i Upps., Uppl. skytteförb. GM, Skytte-Gm. , Arvid Edvard; kyrkoiherde, Åled,, f. 3ll’/8/89 i Gbg av Edvard W. 0. Alma Holmstedt. G. 27 m. Märtha Olsso^n. Ad ibarn: Gunnel o. Ulla ff. 34. Mog:ex. i Gbg 09, fylln :pr. i latin 14, teol. fil. ex. 14, teol. kand. o. prakt, teol. prov 19, prästv. f. Gbgs stift 20. Tjg. s. pastorsadj. i Morlanda, Örby, Harplinge, v. pastor i Harplinge, Hjär-tum, B olleby gd, Getinge, År stad, Sätila, Eldsberga m. fl samt kyrkoadj. i Forsbälila o. Hjärtum, kyrkob. i Enslöv sed. 41.",
    "translated": "Karl Albert, former senior physician, Gothenburg, born on 1/6/72 in Gothenburg to city district physician Lars August Theoidor W. and Anna Emfrida Mathilda Almiberg. Married 10 times to Lida Böving. - Completed secondary education in Gothenburg in 1990, received a Bachelor's degree in Medicine in 1996 and a medical license in 2003 from Uppsala University. Assistant and trainee at the national institute in Uppsala 94-95, at the surgical clinic there 98-99, trainee at the surgical outpatient clinic 99-00, assistant and examiner at the pathology institute from 2000, assistant at the surgical clinic from 2003, sub-surgeon there from 2004, trainee at Sahligr. hospital surgical and medical department from 2005, acting deputy surgeon at the surgical department there 05-06, deputy physician there 06-10, including three months as acting senior physician. Senior physician at Ekmanska hospital 10-37, general practitioner. Hobby: philately. Recipient of Royal Order of the North Star, Helsingborg Medal of Honor in Uppsala, and Uppland Shooting Association Gold medal, Shooting Gold Medal. \n\nArvid Edvard; clergyman, Åled, born on 31/08/89 in Gothenburg to Edvard W. and Alma Holmstedt. Married 27 times to Märtha Olsson. Two children: Gunnel and Ulla born in 1934. Completed secondary education in Gothenburg in 1909, passed a Latin exam in 1914, received a degree in Philosophy in Theology in 1914, passed a theology exam and practical theology test in 1919, ordained as a priest for the Gothenburg diocese in 1920. Served as pastoral assistant in Morlanda, Örby, Harplinge, and as a pastor in Harplinge, Hjärtum, Bollebygd, Getinge, Årstads, Sätila, Eldsberga, among others, and as a church assistant in Forsbälila and Hjärtum, church official in Enslöv since 1941.",
    "structured_raw": "{\n  \"@context\": \"https://schema.org\",\n  \"@type\": \"Person\",\n  \"name\": \"Karl Albert\",\n  \"birthDate\": \"1872-06-01\",\n  \"birthPlace\": \"Gothenburg\",\n  \"education\": [\n    {\n      \"@type\": \"EducationalOccupationalCredential\",\n      \"credentialCategory\": \"secondaryEducation\",\n      \"educationalLevel\": \"Secondary education\",\n      \"institution\": \"Gothenburg\",\n      \"completionDate\": \"1990\"\n    },\n    {\n      \"@type\": \"EducationalOccupationalCredential\",\n      \"credentialCategory\": \"bachelor\",\n      \"educationalLevel\": \"Bachelor's degree in Medicine\",\n      \"institution\": \"Uppsala University\",\n      \"completionDate\": \"1996\"\n    },\n    {\n      \"@type\": \"EducationalOccupationalCredential\",\n      \"credentialCategory\": \"medical_license\",\n      \"educationalLevel\": \"Medical license\",\n      \"institution\": \"Uppsala University\",\n      \"completionDate\": \"2003\"\n    }\n  ],\n  \"jobTitle\": \"Former senior physician\",\n  \"worksFor\": \"Gothenburg\",\n  \"parents\": [\n    {\n      \"@type\": \"Person\",\n      \"name\": \"Lars August Theoidor W.\"\n    },\n    {\n      \"@type\": \"Person\",\n      \"name\": \"Anna Emfrida Mathilda Almiberg\"\n    }\n  ],\n  \"spouse\": [\n    {\n      \"@type\": \"Person\",\n      \"name\": \"Lida Böving\",\n      \"marriageDate\": \"1900-10\"\n    }\n  ],\n  \"hobby\": \"Philately\",\n  \"awards\": [\n    {\n      \"@type\": \"Order\",\n      \"name\": \"Royal Order of the North Star\"\n    },\n    {\n      \"@type\": \"Medal\",\n      \"name\": \"Helsingborg Medal of Honor in Uppsala\"\n    },\n    {\n      \"@type\": \"Medal\",\n      \"name\": \"Uppland Shooting Association Gold Medal\"\n    },\n    {\n      \"@type\": \"Medal\",\n      \"name\": \"Shooting Gold Medal\"\n    }\n  ]\n}",
    "structured": {
        "@context": "https://schema.org",
        "@type": "Person",
        "name": "Karl Albert",
        "birthDate": "1872-06-01",
        "birthPlace": "Gothenburg",
        "education": [
            {
                "@type": "EducationalOccupationalCredential",
                "credentialCategory": "secondaryEducation",
                "educationalLevel": "Secondary education",
                "institution": "Gothenburg",
                "completionDate": "1990"
            },
            {
                "@type": "EducationalOccupationalCredential",
                "credentialCategory": "bachelor",
                "educationalLevel": "Bachelor's degree in Medicine",
                "institution": "Uppsala University",
                "completionDate": "1996"
            },
            {
                "@type": "EducationalOccupationalCredential",
                "credentialCategory": "medical_license",
                "educationalLevel": "Medical license",
                "institution": "Uppsala University",
                "completionDate": "2003"
            }
        ],
        "jobTitle": "Former senior physician",
        "worksFor": "Gothenburg",
        "parents": [
            {
                "@type": "Person",
                "name": "Lars August Theoidor W."
            },
            {
                "@type": "Person",
                "name": "Anna Emfrida Mathilda Almiberg"
            }
        ],
        "spouse": [
            {
                "@type": "Person",
                "name": "Lida Böving",
                "marriageDate": "1900-10"
            }
        ],
        "hobby": "Philately",
        "awards": [
            {
                "@type": "Order",
                "name": "Royal Order of the North Star"
            },
            {
                "@type": "Medal",
                "name": "Helsingborg Medal of Honor in Uppsala"
            },
            {
                "@type": "Medal",
                "name": "Uppland Shooting Association Gold Medal"
            },
            {
                "@type": "Medal",
                "name": "Shooting Gold Medal"
            }
        ]
    }
}