{
    "original": "Bergmann, Olga Lovisa, fil. lic., läroverksadjunkt, studierektor, Göteborg, f. 29/12/85 i V. Frölunda, Gbgs o. Boh. 1., av Alex. Bernh. Lorentzon o. Olivia Olsson. G. 16 m. banktj :m. Friedrich Bergmann. Barn: Fritz f. 16, banktj :m., g. m. Ebba Klint-Högström, Ellen 20, g. m. Henrik Gold-kuhl, Inga-Lisa 22, anst. v. sv. leg. i Washington, Sven-Arne 27, fil. stud. i Gbg. — Stud:ex. v. Gbgs samsk. 09, fil. mag. i Gbg 11, fil. lic. 27, provår v. Gbgs real 12. Stud:res. t. Tyskl. 09, 13, 13-14, 15, 16, 19-20, 25, 26, 29, 36, Engl. 33, 34, 35 o. 38. Lär. v. S. Rudebecks sk. i Gbg 11-12, Vasa flicksk. i Gbg 13-14, ämneslär. i Malmköp. 14-15, timlär. i Math. Halls sk. f. fl. i Gbg 18-19, v. Fruntimmersfören. flicksk. i Gbg 18-20, v. Kjellbergska sem. 19-20, part. vik. lektor v. Gbgs real 28, ämneslär. v. S. Rudebecks sk. o. Gbgs gymn. f. fl. 22-30, adj. v. Gbgs latin 30, ämneslär. v. Gbgs h. a. 1. f. fl. 30, adj. där sed. 37, studierektor v. Gbgs gymn. f. fl. sed. 35. Medl. av lärov:sakk. 31-32, led. av priva-^istndn i Gbg 43 o. 44, led. av LMS centr:styr. o. arb:utsk. sed. 38, v. ordf. i Gbgs lokalfören. av LMS 42, led. av styr. f. Sigrid Rudebecks sk. sed. 35. Skr.: övers. Rud. Goldscheid : Fredsrörelse o. människoekonomi (16), K. Gibran: Profeten (33), R. Fülop-Miller: Helgonen som fört världen framåt (47).",
    "translated": "Bergmann, Olga Lovisa, Fil. Lic. (Doctor of Philosophy), Senior Secondary School Teacher, Study Director, Gothenburg, born on December 29th, 1885 in Västra Frölunda, Gothenburg and Bohus County, the first child of Alexander Bernhard Lorentzon and Olivia Olsson. She married bank clerk Friedrich Bergmann in 1916. They had four children: Fritz, born in 1916, who became a bank clerk and married Ebba Klint-Högström; Ellen, born in 1920, who married Henrik Gold-kuhl; Inga-Lisa, born in 1922, who worked for the Swedish embassy in Washington; and Sven-Arne, born in 1927, who studied Philosophy in Gothenburg. \n\nOlga Lovisa graduated from the Gothenburg Grammar School in 1909 and received her Doctor of Philosophy degree from the University of Gothenburg in 1911. She completed a postgraduate year at the Gothenburg Real School in 1912 and continued her studies in Germany in 1909, 1913, 1914, 1915, 1916, 1919, 1920, 1925, 1926, 1929, and 1936. She also visited England in 1933, 1934, 1935, and 1938. \n\nShe worked at various educational institutions including S. Rudebeck's School in Gothenburg from 1911-1912, Vasa Girls School in Gothenburg from 1913-1914, Malmköping as a subject teacher from 1914-1915, Math. Hall's School in Gothenburg as a temporary teacher in 1918-1919, Fruntimmersföreningens Flickskola in Gothenburg from 1918-1920, Kjellberg's Seminary as a part-time substitute teacher in 1919-1920, Gothenburg's Real School as a part-time substitute teacher in 1928, S. Rudebeck's School and Gothenburg's Gymnasium from 1922-1930, and Gothenburg's Latin School as an adjunct from 1930. She also worked as a subject teacher at Gothenburg's High School from 1930 and as an adjunct there since 1937. She was appointed as a Study Director at Gothenburg's Gymnasium in 1935. \n\nShe served as a member of the school committee from 1931-1932, a member of the Private Schools Committee in Gothenburg in 1943-1944, a member of the Central Committee and Working Committee of LMS (Svenska Missionsförbundet) since 1938, Vice-Chair of LMS's Gothenburg Local Association in 1942, and a member of the Board of Sigrid Rudebeck's School since 1935. \n\nShe wrote the translations of Rudolf Goldscheid's \"Peace Movement and Human Economics\" in 1916, Kahlil Gibran's \"The Prophet\" in 1933, and R. Fülöp-Miller's \"The Saints Who Moved the World Forward\" in 1947.",
    "structured_raw": "{\n    \"@context\": \"https://schema.org\",\n    \"@type\": \"Person\",\n    \"name\": \"Olga Lovisa Bergmann\",\n    \"givenName\": \"Olga Lovisa\",\n    \"familyName\": \"Bergmann\",\n    \"gender\": \"female\",\n    \"birthDate\": \"1885-12-29\",\n    \"birthPlace\": {\n        \"@type\": \"Place\",\n        \"address\": {\n            \"@type\": \"PostalAddress\",\n            \"addressLocality\": \"Västra Frölunda\",\n            \"addressRegion\": \"Gothenburg and Bohus County\",\n            \"addressCountry\": \"Sweden\"\n        }\n    },\n    \"parents\": [\n        {\n            \"@type\": \"Person\",\n            \"givenName\": \"Alexander Bernhard\",\n            \"familyName\": \"Lorentzon\"\n        },\n        {\n            \"@type\": \"Person\",\n            \"givenName\": \"Olivia\",\n            \"familyName\": \"Olsson\"\n        }\n    ],\n    \"spouse\": {\n        \"@type\": \"Person\",\n        \"givenName\": \"Friedrich\",\n        \"familyName\": \"Bergmann\",\n        \"occupation\": \"bank clerk\"\n    },\n    \"children\": [\n        {\n            \"@type\": \"Person\",\n            \"givenName\": \"Fritz\",\n            \"birthDate\": \"1916\"\n        },\n        {\n            \"@type\": \"Person\",\n            \"givenName\": \"Ellen\",\n            \"birthDate\": \"1920\"\n        },\n        {\n            \"@type\": \"Person\",\n            \"givenName\": \"Inga-Lisa\",\n            \"birthDate\": \"1922\",\n            \"memberOf\": {\n                \"@type\": \"Organization\",\n                \"name\": \"Swedish embassy in Washington\"\n            }\n        },\n        {\n            \"@type\": \"Person\",\n            \"givenName\": \"Sven-Arne\",\n            \"birthDate\": \"1927\",\n            \"memberOf\": {\n                \"@type\": \"EducationalOrganization\",\n                \"name\": \"University of Gothenburg\",\n                \"department\": \"Philosophy\"\n            }\n        }\n    ],\n    \"alumniOf\": {\n        \"@type\": \"EducationalOrganization\",\n        \"name\": \"University of Gothenburg\",\n        \"hasCredential\": {\n            \"@type\": \"EducationalOccupationalCredential\",\n            \"name\": \"Doctor of Philosophy\"\n        },\n        \"alumniOf\": [\n            {\n                \"@type\": \"EducationalOrganization\",\n                \"name\": \"Gothenburg Grammar School\",\n                \"endDate\": \"1909\"\n            },\n            {\n                \"@type\": \"EducationalOrganization\",\n                \"name\": \"Gothenburg Real School\",\n                \"startDate\": \"1912\",\n                \"endDate\": \"1913\"\n            }\n        ]\n    },\n    \"memberOf\": [\n        {\n            \"@type\": \"EducationalOrganization\",\n            \"name\": \"S. Rudebeck's School\",\n            \"startDate\": \"1911\",\n            \"endDate\": \"1912\"\n        },\n        {\n            \"@type\": \"EducationalOrganization\",\n            \"name\": \"Vasa Girls School\",\n            \"startDate\": \"1913\",\n            \"endDate\": \"1914\"\n        },\n        {\n            \"@type\": \"EducationalOrganization\",\n            \"name\": \"Malmköping\",\n            \"jobTitle\": \"Subject Teacher\",\n            \"startDate\": \"1914\",\n            \"endDate\": \"1915\"\n        },\n        {\n            \"@type\": \"EducationalOrganization\",\n            \"name\": \"Math. Hall's School\",\n            \"jobTitle\": \"Temporary Teacher\",\n            \"startDate\": \"1918\",\n            \"endDate\": \"1919\"\n        },\n        {\n            \"@type\": \"EducationalOrganization\",\n            \"name\": \"Fruntimmersföreningens Flickskola\",\n            \"startDate\": \"1918\",\n            \"endDate\": \"1920\"\n        },\n        {\n            \"@type\": \"EducationalOrganization\",\n            \"name\": \"Kjellberg's Seminary\",\n            \"jobTitle\": \"Part-time Substitute Teacher\",\n            \"startDate\": \"1919\",\n            \"endDate\": \"1920\"\n        },\n        {\n            \"@type\": \"EducationalOrganization\",\n            \"name\": \"Gothenburg's Real School\",\n            \"jobTitle\": \"Part-time Substitute Teacher\",\n            \"startDate\": \"1928\"\n        },\n        {\n            \"@type\": \"EducationalOrganization\",\n            \"name\": \"Gothenburg's Gymnasium\",\n            \"jobTitle\": [\n                \"Subject Teacher\",\n                \"Study Director\",\n                \"Adjunct\"\n            ],\n            \"startDate\": \"1922\",\n            \"endDate\": \"1930\"\n        },\n        {\n            \"@type\": \"EducationalOrganization\",\n            \"name\": \"Gothenburg's Latin School\",\n            \"jobTitle\": \"Adjunct\",\n            \"startDate\": \"1930\",\n            \"endDate\": \"1937\"\n        },\n        {\n            \"@type\": \"EducationalOrganization\",\n            \"name\": \"Gothenburg's Gymnasium\",\n            \"jobTitle\": \"Study Director\",\n            \"startDate\": \"1935\"\n        }\n    ],\n    \"memberOf\": [\n        {\n            \"@type\": \"Organization\",\n            \"name\": \"School Committee\",\n            \"startDate\": \"1931\",\n            \"endDate\": \"1932\"\n        },\n        {\n            \"@type\": \"Organization\",\n            \"name\": \"Private Schools Committee\",\n            \"startDate\": \"1943\",\n            \"endDate\": \"1944\"\n        },\n        {\n            \"@type\": \"Organization\",\n            \"name\": \"LMS (Svenska Missionsförbundet) Central Committee and Working Committee\",\n            \"startDate\": \"1938\"\n        },\n        {\n            \"@type\": \"Organization\",\n            \"name\": \"LMS Gothenburg Local Association\",\n            \"jobTitle\": \"Vice-Chair\",\n            \"startDate\": \"1942\"\n        },\n        {\n            \"@type\": \"Organization\",\n            \"name\": \"Board of Sigrid Rudebeck's School\",\n            \"startDate\": \"1935\"\n        }\n    ],\n    \"worksFor\": [\n        {\n            \"@type\": \"Organization\",\n            \"name\": \"University of Gothenburg\",\n            \"department\": \"Philosophy\"\n        },\n        {\n            \"@type\": \"Organization\",\n            \"name\": \"Swedish embassy in Washington\"\n        }\n    ],\n    \"translator\": [\n        {\n            \"@type\": \"CreativeWork\",\n            \"name\": \"Peace Movement and Human Economics\",\n            \"author\": \"Rudolf Goldscheid\",\n            \"datePublished\": \"1916\"\n        },\n        {\n            \"@type\": \"CreativeWork\",\n            \"name\": \"The Prophet\",\n            \"author\": \"Kahlil Gibran\",\n            \"datePublished\": \"1933\"\n        },\n        {\n            \"@type\": \"CreativeWork\",\n            \"name\": \"The Saints Who Moved the World Forward\",\n            \"author\": \"R. Fülöp-Miller\",\n            \"datePublished\": \"1947\"\n        }\n    ]\n}",
    "structured": {
        "@context": "https://schema.org",
        "@type": "Person",
        "name": "Olga Lovisa Bergmann",
        "givenName": "Olga Lovisa",
        "familyName": "Bergmann",
        "gender": "female",
        "birthDate": "1885-12-29",
        "birthPlace": {
            "@type": "Place",
            "address": {
                "@type": "PostalAddress",
                "addressLocality": "Västra Frölunda",
                "addressRegion": "Gothenburg and Bohus County",
                "addressCountry": "Sweden"
            }
        },
        "parents": [
            {
                "@type": "Person",
                "givenName": "Alexander Bernhard",
                "familyName": "Lorentzon"
            },
            {
                "@type": "Person",
                "givenName": "Olivia",
                "familyName": "Olsson"
            }
        ],
        "spouse": {
            "@type": "Person",
            "givenName": "Friedrich",
            "familyName": "Bergmann",
            "occupation": "bank clerk"
        },
        "children": [
            {
                "@type": "Person",
                "givenName": "Fritz",
                "birthDate": "1916"
            },
            {
                "@type": "Person",
                "givenName": "Ellen",
                "birthDate": "1920"
            },
            {
                "@type": "Person",
                "givenName": "Inga-Lisa",
                "birthDate": "1922",
                "memberOf": {
                    "@type": "Organization",
                    "name": "Swedish embassy in Washington"
                }
            },
            {
                "@type": "Person",
                "givenName": "Sven-Arne",
                "birthDate": "1927",
                "memberOf": {
                    "@type": "EducationalOrganization",
                    "name": "University of Gothenburg",
                    "department": "Philosophy"
                }
            }
        ],
        "alumniOf": {
            "@type": "EducationalOrganization",
            "name": "University of Gothenburg",
            "hasCredential": {
                "@type": "EducationalOccupationalCredential",
                "name": "Doctor of Philosophy"
            },
            "alumniOf": [
                {
                    "@type": "EducationalOrganization",
                    "name": "Gothenburg Grammar School",
                    "endDate": "1909"
                },
                {
                    "@type": "EducationalOrganization",
                    "name": "Gothenburg Real School",
                    "startDate": "1912",
                    "endDate": "1913"
                }
            ]
        },
        "memberOf": [
            {
                "@type": "Organization",
                "name": "School Committee",
                "startDate": "1931",
                "endDate": "1932"
            },
            {
                "@type": "Organization",
                "name": "Private Schools Committee",
                "startDate": "1943",
                "endDate": "1944"
            },
            {
                "@type": "Organization",
                "name": "LMS (Svenska Missionsförbundet) Central Committee and Working Committee",
                "startDate": "1938"
            },
            {
                "@type": "Organization",
                "name": "LMS Gothenburg Local Association",
                "jobTitle": "Vice-Chair",
                "startDate": "1942"
            },
            {
                "@type": "Organization",
                "name": "Board of Sigrid Rudebeck's School",
                "startDate": "1935"
            }
        ],
        "worksFor": [
            {
                "@type": "Organization",
                "name": "University of Gothenburg",
                "department": "Philosophy"
            },
            {
                "@type": "Organization",
                "name": "Swedish embassy in Washington"
            }
        ],
        "translator": [
            {
                "@type": "CreativeWork",
                "name": "Peace Movement and Human Economics",
                "author": "Rudolf Goldscheid",
                "datePublished": "1916"
            },
            {
                "@type": "CreativeWork",
                "name": "The Prophet",
                "author": "Kahlil Gibran",
                "datePublished": "1933"
            },
            {
                "@type": "CreativeWork",
                "name": "The Saints Who Moved the World Forward",
                "author": "R. Fülöp-Miller",
                "datePublished": "1947"
            }
        ]
    }
}