{
    "original": "Löfstedt, Frithiof, leg. veterinär, klinikchef, bataljonsveterinär v. Fvk, Skara, f. 8/10/06 i Lund av kantor Jonas o. Elna L. G. 38 m. Harriet Al-lerfeldt. — Stud:ex. v. Lunds kate-dralsk. 26, veter:ex. 41. Vik:förordn. som tf. distr :veter. 35-38, assist, h. distr:veter. G. Danelius i Linköp. 37- 39, militärtj. 40, assist, v. veter rhögsk. medic. o. kir. klin. 41-46, klinikchef v. veter linrättn. i Skara S’ed. 46. Batal-jonsveter. v. Fvk sed. 43. Medl. av Sällsk. f. veter :medic. forskn. sed. 43. Skr.: Behandl. av inälvsparasiter h. häst (38), Enchondrcsis interverte-bralis (41), Valpsjuka h. hund (41), Otitis externa h. hund (41), Om K-vitamin o. protrombin (42), Banga-bortmetastas-er i bursor, senskidor o. leder h. häst o. nötkreatur (45), Sänkningsreaktionen, leukocyträkning o. formoi-gelreaktionen v. kir. lidanden h. häst o. hund (45), Allergi o. allerg. senskide-, ’sen- o. ledlidanden h. häst o. hund (45), Vätskebalansen v. kir. lidanden m. spec. hänsyn t. serumpro-teinhalten (45). Hobbies: musik, målning, fiske o. jakt.",
    "translated": "Löfstedt, Frithiof, Licensed Veterinarian, Clinic Manager, Battalion Veterinarian at the Military Air Base in Skara, born on October 8, 1906 in Lund, son of Cantor Jonas and Elna L. G. Married to Harriet Allerfeldt in 1938. \n\nEducation: Graduated from Lunds katedralskola in 1926, obtained veterinary degree in 1941. Temporary District Veterinarian from 1935-1938, assistant to District Veterinarian G. Danelius in Linköping from 1937-1939, military service in 1940. Worked as assistant at Veterinary University Hospital's Medical and Surgical Clinic from 1941-1946, became clinic manager at the Veterinary Training Center in Skara in 1946. Battalion Veterinarian at the Military Air Base since 1943. Member of the Society for Veterinary Medical Research since 1943.\n\nPublications: Treatment of internal parasites in horses (1938), Intervertebral enchondrosis (1941), Distemper in dogs (1941), External otitis in dogs (1941), K-vitamin and prothrombin (1942), Removal of metastases in bursas, tendons, and joints in horses and cattle (1945), Erythrocyte sedimentation rate, leukocyte count and phagocytosis reaction in surgical diseases of horses and dogs (1945), Allergy and allergic diseases in tendons, ligaments, and joints of horses and dogs (1945), Fluid balance in surgical diseases with special consideration for serum protein content (1945).\n\nHobbies: Music, painting, fishing, and hunting.",
    "structured_raw": "{\n  \"@context\": \"https://schema.org\",\n  \"@type\": \"Person\",\n  \"name\": \"Frithiof Löfstedt\",\n  \"birthDate\": \"1906-10-08\",\n  \"birthPlace\": \"Lund\",\n  \"parents\": [\n    {\n      \"@type\": \"Person\",\n      \"name\": \"Jonas Löfstedt\",\n      \"jobTitle\": \"Cantor\"\n    },\n    {\n      \"@type\": \"Person\",\n      \"name\": \"Elna Löfstedt\"\n    }\n  ],\n  \"spouse\": {\n    \"@type\": \"Person\",\n    \"name\": \"Harriet Allerfeldt\",\n    \"marriageDate\": \"1938\"\n  },\n  \"education\": [\n    {\n      \"@type\": \"EducationalOccupationalCredential\",\n      \"alumniOf\": {\n        \"@type\": \"EducationalOrganization\",\n        \"name\": \"Lunds katedralskola\"\n      },\n      \"startDate\": \"1926\",\n      \"endDate\": \"1941\"\n    }\n  ],\n  \"worksFor\": [\n    {\n      \"@type\": \"Organization\",\n      \"name\": \"Military Air Base in Skara\",\n      \"jobTitle\": \"Battalion Veterinarian\",\n      \"startDate\": \"1943\"\n    },\n    {\n      \"@type\": \"Organization\",\n      \"name\": \"Veterinary Training Center in Skara\",\n      \"jobTitle\": \"Clinic Manager\",\n      \"startDate\": \"1946\"\n    },\n    {\n      \"@type\": \"Organization\",\n      \"name\": \"Veterinary University Hospital\",\n      \"jobTitle\": \"Assistant\",\n      \"startDate\": \"1941\",\n      \"endDate\": \"1946\"\n    }\n  ],\n  \"memberOf\": {\n    \"@type\": \"Organization\",\n    \"name\": \"Society for Veterinary Medical Research\",\n    \"membershipStartDate\": \"1943\"\n  },\n  \"publications\": [\n    {\n      \"@type\": \"Article\",\n      \"name\": \"Treatment of internal parasites in horses\",\n      \"datePublished\": \"1938\"\n    },\n    {\n      \"@type\": \"Article\",\n      \"name\": \"Intervertebral enchondrosis\",\n      \"datePublished\": \"1941\"\n    },\n    {\n      \"@type\": \"Article\",\n      \"name\": \"Distemper in dogs\",\n      \"datePublished\": \"1941\"\n    },\n    {\n      \"@type\": \"Article\",\n      \"name\": \"External otitis in dogs\",\n      \"datePublished\": \"1941\"\n    },\n    {\n      \"@type\": \"Article\",\n      \"name\": \"K-vitamin and prothrombin\",\n      \"datePublished\": \"1942\"\n    },\n    {\n      \"@type\": \"Article\",\n      \"name\": \"Removal of metastases in bursas, tendons, and joints in horses and cattle\",\n      \"datePublished\": \"1945\"\n    },\n    {\n      \"@type\": \"Article\",\n      \"name\": \"Erythrocyte sedimentation rate, leukocyte count and phagocytosis reaction in surgical diseases of horses and dogs\",\n      \"datePublished\": \"1945\"\n    },\n    {\n      \"@type\": \"Article\",\n      \"name\": \"Allergy and allergic diseases in tendons, ligaments, and joints of horses and dogs\",\n      \"datePublished\": \"1945\"\n    },\n    {\n      \"@type\": \"Article\",\n      \"name\": \"Fluid balance in surgical diseases with special consideration for serum protein content\",\n      \"datePublished\": \"1945\"\n    }\n  ],\n  \"hobbies\": [\n    \"Music\",\n    \"Painting\",\n    \"Fishing\",\n    \"Hunting\"\n  ]\n}",
    "structured": {
        "@context": "https://schema.org",
        "@type": "Person",
        "name": "Frithiof Löfstedt",
        "birthDate": "1906-10-08",
        "birthPlace": "Lund",
        "parents": [
            {
                "@type": "Person",
                "name": "Jonas Löfstedt",
                "jobTitle": "Cantor"
            },
            {
                "@type": "Person",
                "name": "Elna Löfstedt"
            }
        ],
        "spouse": {
            "@type": "Person",
            "name": "Harriet Allerfeldt",
            "marriageDate": "1938"
        },
        "education": [
            {
                "@type": "EducationalOccupationalCredential",
                "alumniOf": {
                    "@type": "EducationalOrganization",
                    "name": "Lunds katedralskola"
                },
                "startDate": "1926",
                "endDate": "1941"
            }
        ],
        "worksFor": [
            {
                "@type": "Organization",
                "name": "Military Air Base in Skara",
                "jobTitle": "Battalion Veterinarian",
                "startDate": "1943"
            },
            {
                "@type": "Organization",
                "name": "Veterinary Training Center in Skara",
                "jobTitle": "Clinic Manager",
                "startDate": "1946"
            },
            {
                "@type": "Organization",
                "name": "Veterinary University Hospital",
                "jobTitle": "Assistant",
                "startDate": "1941",
                "endDate": "1946"
            }
        ],
        "memberOf": {
            "@type": "Organization",
            "name": "Society for Veterinary Medical Research",
            "membershipStartDate": "1943"
        },
        "publications": [
            {
                "@type": "Article",
                "name": "Treatment of internal parasites in horses",
                "datePublished": "1938"
            },
            {
                "@type": "Article",
                "name": "Intervertebral enchondrosis",
                "datePublished": "1941"
            },
            {
                "@type": "Article",
                "name": "Distemper in dogs",
                "datePublished": "1941"
            },
            {
                "@type": "Article",
                "name": "External otitis in dogs",
                "datePublished": "1941"
            },
            {
                "@type": "Article",
                "name": "K-vitamin and prothrombin",
                "datePublished": "1942"
            },
            {
                "@type": "Article",
                "name": "Removal of metastases in bursas, tendons, and joints in horses and cattle",
                "datePublished": "1945"
            },
            {
                "@type": "Article",
                "name": "Erythrocyte sedimentation rate, leukocyte count and phagocytosis reaction in surgical diseases of horses and dogs",
                "datePublished": "1945"
            },
            {
                "@type": "Article",
                "name": "Allergy and allergic diseases in tendons, ligaments, and joints of horses and dogs",
                "datePublished": "1945"
            },
            {
                "@type": "Article",
                "name": "Fluid balance in surgical diseases with special consideration for serum protein content",
                "datePublished": "1945"
            }
        ],
        "hobbies": [
            "Music",
            "Painting",
            "Fishing",
            "Hunting"
        ]
    }
}