{
    "original": "Lundmark, Frey, med. dr, lasarettsläkare, Vadstena, f. 23/3/04 i Karlskrona av las :läk. Rudolf L. o. Esther Andersson. G. 31 m. Asta Nordbeck. Barn: Anders f. 32, Dag 37. — Studiex. i Karlskrona 23, med. kand. i Upps. 27, med. lic. där 32 samt med. dr 45. E. o. aman. v. patolog, inst. i Upps. 28-29, assist :läk. v. Akad. sjukh. med. avd. 31, bitr. sjuk-h :läk. v. flottans sjukh. i Karlskrona 32-33, tf. andre und :läk. v. Lidköp. las. med. avd. 33 o. 34, ord. und :läk. s’amt vik. lasrläk. där 34-38, assist :-läk. o. tf. aman. v. Akad. sjukh. med. avd. i Linköp. 42-46, las:läk. v. klin. samt tf. und :läk. o. överläk. där 38-42, bitr. samt vik. las :läk. v. med. avd. i Linköp. 42-46, tf. las :läk. v. med. avd. å Vadstena las. sed. 46. Ma-rinläk:stip. över stat 32, marinläk :stip. v. Mlk 33, marinläk. av andra gr. i res. 34, av första gr. i res. 42. Skr.: Fem fall av trichinos (37), Fall av egendoml. granulomatös hudaffektion m. organamyloidos (38), Några reflex. m. anledn. av en andra tularemiepid. i Söderfors hösten 38 (39), Trigeminus-reflex v. decerebrate rigidity o. v. kontrakt» facialispares (41), Klin. un-dersökn. över pupillotoni o. dess relät, t. reflektorisk pupillstelhet (grad:-avh. 45).",
    "translated": "Lundmark, Frey, MD, hospital doctor, Vadstena, b. 23/3/04 in Karlskrona to Dr. Rudolf L. and Esther Andersson. Married on 31 with Asta Nordbeck. Children: Anders b. 32, Dag 37. — Completed studies in Karlskrona in 1923, obtained a Bachelor of Medicine degree in Uppsala in 1927, a medical license there in 1932, and a doctorate in medicine in 1945. Acting assistant at the Institute of Pathology in Uppsala from 1928-1929, medical assistant at the Academic Hospital Medical Department in 1931, assistant medical officer at the Navy Hospital in Karlskrona from 1932-1933, acting second assistant medical officer at Lidköping Hospital Medical Department in 1933 and 1934, and regular assistant medical officer and substitute hospital doctor there from 1934-1938. Assistant medical officer and acting assistant at the Academic Hospital Medical Department in Linköping from 1942-1946, hospital doctor and acting second assistant and senior physician there from 1938-1942, and deputy and substitute hospital doctor at the Medical Department in Linköping from 1942-1946. Temporary hospital doctor at Vadstena Hospital since 1946. Received a scholarship from the Naval Medical Corps in 1932, a scholarship from the Military Medical Corps in 1933, promoted to second grade naval physician in 1934, and promoted to first grade naval physician in 1942. Published works: Five cases of trichinosis (1937), Case of peculiar granulomatous skin affection with organ amyloidosis (1938), Several reflexes due to a second tularemia epidemic in Söderfors in the autumn of 1938 (1939), Trigeminal reflex in decerebrate rigidity and facial paralysis contracture (1941), Clinical examination of pupillotonia and its relationship to reflex pupillary rigidity (degree-dependent) (1945).",
    "structured_raw": "{\n  \"@context\": \"https://schema.org\",\n  \"@type\": \"Person\",\n  \"name\": \"Frey Lundmark\",\n  \"birthDate\": \"1904-03-23\",\n  \"birthPlace\": \"Karlskrona, Sweden\",\n  \"deathDate\": null,\n  \"nationality\": \"Swedish\",\n  \"alumniOf\": [\n    {\n      \"@type\": \"EducationalOrganization\",\n      \"name\": \"Karlskrona\",\n      \"startDate\": \"1923\",\n      \"endDate\": \"1923\"\n    },\n    {\n      \"@type\": \"EducationalOrganization\",\n      \"name\": \"Uppsala\",\n      \"startDate\": \"1927\",\n      \"endDate\": \"1927\"\n    },\n    {\n      \"@type\": \"EducationalOrganization\",\n      \"name\": \"Uppsala\",\n      \"startDate\": \"1932\",\n      \"endDate\": \"1932\"\n    }\n  ],\n  \"worksFor\": {\n    \"@type\": \"MedicalOrganization\",\n    \"name\": \"Vadstena Hospital\"\n  },\n  \"jobTitle\": \"MD, Hospital Doctor\",\n  \"spouse\": {\n    \"@type\": \"Person\",\n    \"name\": \"Asta Nordbeck\",\n    \"marriageDate\": \"1931-01-31\"\n  },\n  \"children\": [\n    {\n      \"@type\": \"Person\",\n      \"name\": \"Anders Lundmark\",\n      \"birthDate\": \"1932-01-01\"\n    },\n    {\n      \"@type\": \"Person\",\n      \"name\": \"Dag Lundmark\",\n      \"birthDate\": \"1937-01-01\"\n    }\n  ],\n  \"employeeOf\": [\n    {\n      \"@type\": \"MedicalOrganization\",\n      \"name\": \"Institute of Pathology\"\n    },\n    {\n      \"@type\": \"MedicalOrganization\",\n      \"name\": \"Academic Hospital Medical Department\",\n      \"startDate\": \"1931\",\n      \"endDate\": \"1931\"\n    },\n    {\n      \"@type\": \"MedicalOrganization\",\n      \"name\": \"Navy Hospital Karlskrona\",\n      \"startDate\": \"1932\",\n      \"endDate\": \"1933\"\n    },\n    {\n      \"@type\": \"MedicalOrganization\",\n      \"name\": \"Lidköping Hospital Medical Department\",\n      \"startDate\": \"1933\",\n      \"endDate\": \"1938\"\n    },\n    {\n      \"@type\": \"MedicalOrganization\",\n      \"name\": \"Academic Hospital Medical Department\",\n      \"startDate\": \"1942\",\n      \"endDate\": \"1946\"\n    },\n    {\n      \"@type\": \"MedicalOrganization\",\n      \"name\": \"Linköping Hospital Medical Department\",\n      \"startDate\": \"1938\",\n      \"endDate\": \"1942\"\n    },\n    {\n      \"@type\": \"MedicalOrganization\",\n      \"name\": \"Medical Department Linköping\",\n      \"startDate\": \"1942\",\n      \"endDate\": \"1946\"\n    },\n    {\n      \"@type\": \"MedicalOrganization\",\n      \"name\": \"Vadstena Hospital\",\n      \"startDate\": \"1946\"\n    }\n  ],\n  \"scholarships\": [\n    {\n      \"@type\": \"OrganizationRole\",\n      \"roleName\": \"Naval Medical Corps\",\n      \"startDate\": \"1932\"\n    },\n    {\n      \"@type\": \"OrganizationRole\",\n      \"roleName\": \"Military Medical Corps\",\n      \"startDate\": \"1933\"\n    }\n  ],\n  \"publications\": [\n    {\n      \"@type\": \"ScholarlyArticle\",\n      \"headline\": \"Five cases of trichinosis\",\n      \"datePublished\": \"1937\"\n    },\n    {\n      \"@type\": \"ScholarlyArticle\",\n      \"headline\": \"Case of peculiar granulomatous skin affection with organ amyloidosis\",\n      \"datePublished\": \"1938\"\n    },\n    {\n      \"@type\": \"ScholarlyArticle\",\n      \"headline\": \"Several reflexes due to a second tularemia epidemic in Söderfors in the autumn of 1938\",\n      \"datePublished\": \"1939\"\n    },\n    {\n      \"@type\": \"ScholarlyArticle\",\n      \"headline\": \"Trigeminal reflex in decerebrate rigidity and facial paralysis contracture\",\n      \"datePublished\": \"1941\"\n    },\n    {\n      \"@type\": \"ScholarlyArticle\",\n      \"headline\": \"Clinical examination of pupillotonia and its relationship to reflex pupillary rigidity (degree-dependent)\",\n      \"datePublished\": \"1945\"\n    }\n  ]\n}",
    "structured": {
        "@context": "https://schema.org",
        "@type": "Person",
        "name": "Frey Lundmark",
        "birthDate": "1904-03-23",
        "birthPlace": "Karlskrona, Sweden",
        "deathDate": null,
        "nationality": "Swedish",
        "alumniOf": [
            {
                "@type": "EducationalOrganization",
                "name": "Karlskrona",
                "startDate": "1923",
                "endDate": "1923"
            },
            {
                "@type": "EducationalOrganization",
                "name": "Uppsala",
                "startDate": "1927",
                "endDate": "1927"
            },
            {
                "@type": "EducationalOrganization",
                "name": "Uppsala",
                "startDate": "1932",
                "endDate": "1932"
            }
        ],
        "worksFor": {
            "@type": "MedicalOrganization",
            "name": "Vadstena Hospital"
        },
        "jobTitle": "MD, Hospital Doctor",
        "spouse": {
            "@type": "Person",
            "name": "Asta Nordbeck",
            "marriageDate": "1931-01-31"
        },
        "children": [
            {
                "@type": "Person",
                "name": "Anders Lundmark",
                "birthDate": "1932-01-01"
            },
            {
                "@type": "Person",
                "name": "Dag Lundmark",
                "birthDate": "1937-01-01"
            }
        ],
        "employeeOf": [
            {
                "@type": "MedicalOrganization",
                "name": "Institute of Pathology"
            },
            {
                "@type": "MedicalOrganization",
                "name": "Academic Hospital Medical Department",
                "startDate": "1931",
                "endDate": "1931"
            },
            {
                "@type": "MedicalOrganization",
                "name": "Navy Hospital Karlskrona",
                "startDate": "1932",
                "endDate": "1933"
            },
            {
                "@type": "MedicalOrganization",
                "name": "Lidköping Hospital Medical Department",
                "startDate": "1933",
                "endDate": "1938"
            },
            {
                "@type": "MedicalOrganization",
                "name": "Academic Hospital Medical Department",
                "startDate": "1942",
                "endDate": "1946"
            },
            {
                "@type": "MedicalOrganization",
                "name": "Linköping Hospital Medical Department",
                "startDate": "1938",
                "endDate": "1942"
            },
            {
                "@type": "MedicalOrganization",
                "name": "Medical Department Linköping",
                "startDate": "1942",
                "endDate": "1946"
            },
            {
                "@type": "MedicalOrganization",
                "name": "Vadstena Hospital",
                "startDate": "1946"
            }
        ],
        "scholarships": [
            {
                "@type": "OrganizationRole",
                "roleName": "Naval Medical Corps",
                "startDate": "1932"
            },
            {
                "@type": "OrganizationRole",
                "roleName": "Military Medical Corps",
                "startDate": "1933"
            }
        ],
        "publications": [
            {
                "@type": "ScholarlyArticle",
                "headline": "Five cases of trichinosis",
                "datePublished": "1937"
            },
            {
                "@type": "ScholarlyArticle",
                "headline": "Case of peculiar granulomatous skin affection with organ amyloidosis",
                "datePublished": "1938"
            },
            {
                "@type": "ScholarlyArticle",
                "headline": "Several reflexes due to a second tularemia epidemic in Söderfors in the autumn of 1938",
                "datePublished": "1939"
            },
            {
                "@type": "ScholarlyArticle",
                "headline": "Trigeminal reflex in decerebrate rigidity and facial paralysis contracture",
                "datePublished": "1941"
            },
            {
                "@type": "ScholarlyArticle",
                "headline": "Clinical examination of pupillotonia and its relationship to reflex pupillary rigidity (degree-dependent)",
                "datePublished": "1945"
            }
        ]
    }
}