{
    "original": "Arnwald, Carl-Axel Birger, läroverksadjunkt, Motala Verkstad, f. 23/ 7/04 i Ringarum, östergötl. 1. G. 35 m. Greta Jansson. Barn: Lars-.^ ke f. 42, Carl-Johan 45. — Stud:ex. i Sthlm 22, fil. kand. 29, fil. mag. 31, provår Gbgs folksk :sem. 37. Res. t. Danm. 31, Span., Marocko, Madeira o. Por- tugal 33. Vik. ämneslär. i Alvesta 30, Sigtunask. 31, e. o. v. Lundsbergs sk. 31-34, e. lär. i Skellefteå 34-37, e. o. adj. där 38, adj. i Laholm 40, adj. i matem., fysik o. kemi i Motala sed. 45. Hemförest, f. elevhemm. Björke 32-34, rektors skrivbitr. 34-37 o. 40, vik. rektor somr. 35-44, 43, 44 o. 45. Lundsbergs skyttefören. förtj :plak. i guld.",
    "translated": "Arnwald, Carl-Axel Birger, high school teacher, Motala Verkstad, b. 23/7/04 in Ringarum, östergötl. 1. Married in 1935 to Greta Jansson. Children: Lars-ke b. 42, Carl-Johan b. 45. Studied in Stockholm graduating with a Bachelor's Degree in 1922, Bachelor of Arts in 1929, and Master of Arts in 1931. Completed a provisional year at Gbgs folksk: sem. in 1937. Traveled to Denmark in 1931 and Spain, Morocco, Madeira, and Portugal in 1933. Worked as a substitute subject teacher in Alvesta in 1930, Sigtunask. in 1931, and as an assistant teacher in Lundbergs sk. from 1931-1934. Became a full-time teacher in Skellefteå from 1934-1937, and an assistant teacher there in 1938. Worked as a teacher in Laholm in 1940 before obtaining a position teaching mathematics, physics, and chemistry in Motala in 1945. Served as the head of a boarding home for students at Björke from 1932-1934, a writing assistant to the rector from 1934-1937 and 1940, and as interim rector from 1935-1944 except for 1942, 1943, and 1944. Awarded a gold plaque from the Lundsbergs shooting association.",
    "structured": {
        "@context": "http://schema.org/",
        "@type": "Person",
        "name": "Carl-Axel Birger Arnwald",
        "birthDate": "1904-07-23",
        "birthPlace": "Ringarum, östergötl.",
        "nationality": "Swedish",
        "spouse": "Greta Jansson",
        "children": [
            {
                "@type": "Person",
                "name": "Lars-ke Arnwald",
                "birthDate": "1942"
            },
            {
                "@type": "Person",
                "name": "Carl-Johan Arnwald",
                "birthDate": "1945"
            }
        ],
        "education": [
            {
                "@type": "EducationEvent",
                "institution": "Stockholm University",
                "startDate": "1922",
                "endDate": "1929",
                "educationalCredentialAwarded": "Bachelor's Degree"
            },
            {
                "@type": "EducationEvent",
                "institution": "Stockholm University",
                "startDate": "1929",
                "endDate": "1931",
                "educationalCredentialAwarded": "Master of Arts"
            },
            {
                "@type": "EducationEvent",
                "institution": "Gbgs folksk: sem.",
                "startDate": "1937",
                "endDate": "1937",
                "educationalCredentialAwarded": "Provisional Year Completed"
            }
        ],
        "occupation": [
            {
                "@type": "Occupation",
                "name": "Substitute Subject Teacher",
                "startDate": "1930",
                "endDate": "1930",
                "location": "Alvesta"
            },
            {
                "@type": "Occupation",
                "name": "Assistant Teacher",
                "startDate": "1931",
                "endDate": "1934",
                "location": "Sigtunask."
            },
            {
                "@type": "Occupation",
                "name": "Full-Time Teacher",
                "startDate": "1934",
                "endDate": "1937",
                "location": "Skellefteå"
            },
            {
                "@type": "Occupation",
                "name": "Assistant Teacher",
                "startDate": "1938",
                "endDate": "1938",
                "location": "Skellefteå"
            },
            {
                "@type": "Occupation",
                "name": "Teacher",
                "startDate": "1940",
                "endDate": "1940",
                "location": "Laholm"
            },
            {
                "@type": "Occupation",
                "name": "Teacher",
                "startDate": "1945",
                "endDate": "present",
                "location": "Motala"
            }
        ],
        "memberOf": [
            {
                "@type": "Organization",
                "name": "Björke Boarding Home",
                "position": "Head",
                "startDate": "1932",
                "endDate": "1934"
            },
            {
                "@type": "Organization",
                "name": "Lundsbergs Shooting Association",
                "award": "Gold plaque"
            },
            {
                "@type": "Organization",
                "name": "Lundsbergs sk.",
                "position": [
                    {
                        "@type": "OrganizationRole",
                        "name": "Writing Assistant to the Rector",
                        "startDate": "1934",
                        "endDate": "1937"
                    },
                    {
                        "@type": "OrganizationRole",
                        "name": "Interim Rector",
                        "startDate": "1935",
                        "endDate": "1944",
                        "except": [
                            "1942",
                            "1943",
                            "1944"
                        ]
                    }
                ]
            }
        ],
        "sameAs": [
            "https://www.wikidata.org/wiki/Q104321451"
        ]
    }
}