{
    "original": "Dahlberg, Elis Fredrik Leopold, fd. rektor, Karlshamn, f. 1/4/77 i Simrishamn av kyrkoh. Walfrid D. o. Bertha Runstedt. G. 09 m. Gertrud Bergh. Barn: Ingrid f. 13, Gert 16. — Stud:-ex. 94, fil. kand. i Lund 98, teor. o. prakt, teol, ex. 02. E. lär. i Simrishamn 99-00, vik. adj. o. vik. lektor i Kristianstad 04-07, rektors sekr. 05-07, ord. adj. i Arvika 07-12, rektor i Piteå 12-25, rektor v. Karlshamns re-alsk. o. komm. gymn. 25-42. Led. av stadsfullm. i Arvika 11-12, förest, f. Arvika tekn. yrkessk. 09-12, led. av stadsfullm. i Piteå 14-25, ordf. 15, 16 o. 21-25, ordf. i Piteå hamndirekt. 14-19, v. oTdif. i ff(olkisk:,sityr. 18-25, i las:-direkt. 14-25, ordf. i tax:nd 22-25, led. ’av landstinget i Norrb. 1. 21-22, Led. av stadsfullm. i Karlshamn 27-36, ordf. i beiredtn:uts(k. 28-3’l, i sfadsfullm. 35-36, i lönend 27-36, i ’Styr. f. ’stadsbibl. 26-38, i lokalstyr. f. ’samrealsk. 29-42 o. i ’Styr. f. komm. gymn. 25-40, iled. av Blek. 1. |landsting 35-38 o. av alilm. kyrkomötet 15, tryckfrih :omb. 28-39, huv :man i Karlshamns Sparbank, ordf. i tax:nd sed. 43. RVO 23.",
    "translated": "Dahlberg, Elis Fredrik Leopold, former principal from Karlshamn, born on April 1st, 1877 in Simrishamn to vicar Walfrid D. and Bertha Runstedt. Married in 1909 to Gertrud Bergh, with two children: Ingrid born in 1913 and Gert born in 1916. He earned his degree from Lund University in 1894 and his Bachelor of Philosophy in 1898. He passed his theoretical and practical theological exams in 1902. He worked as a teacher in Simrishamn from 1899-1900, as temporary adjutant and temporary lecturer in Kristianstad from 1904-1907, and as the rector's secretary from 1905-1907. He was appointed ordained adjutant in Arvika from 1907-1912 and rector in Piteå from 1912-1925. He served as vice-rector of Karlshamn's high school and municipal gymnasium from 1925-1942. Dahlberg was a member of Arvika's city council from 1911-1912 and headed the Technical Vocational School from 1909-1912. He was a member of Piteå's city council from 1914-1925 and chaired in 1915, 1916, and from 1921-1925. He was also the chairman of Piteå's port authority from 1914-1919 and vice-chairman in the County Administrative Board from 1918-1925 and the County Council for Health and Welfare from 1914-1925. He chaired the taxation committee from 1922-1925 and was a member of the Norrbotten County Council in 1921-1922. He served as a member of Karlshamn's city council from 1927-1936 and chaired the board of directors from 1928-1931. He was also a member of the city council in 1935-1936, held a salary position from 1927-1936, and chaired the city library board from 1926-1938. Additionally, he was a member of the local board of directors for the municipal high school from 1929-1942 and the board of directors for the municipal gymnasium from 1925-1940. He was a member of the Blekinge County Council from 1935-1938, a member of the general church meeting in 1915, and served on the Commission on Freedom of the Press from 1928-1939. He was the chairman of Karlshamn Savings Bank and served on the Taxation Committee since 1943. He was awarded the Royal Order of Vasa in 1923.",
    "structured_raw": "{\n  \"@context\": \"https://schema.org\",\n  \"@type\": \"Person\",\n  \"name\": \"Elis Fredrik Leopold Dahlberg\",\n  \"birthDate\": \"1877-04-01\",\n  \"birthPlace\": \"Simrishamn\",\n  \"deathDate\": \"\",\n  \"deathPlace\": \"\",\n  \"description\": \"Former principal from Karlshamn\",\n  \"spouse\": [\n    {\n      \"@type\": \"Person\",\n      \"name\": \"Gertrud Bergh\",\n      \"marriageDate\": \"1909\"\n    }\n  ],\n  \"children\": [\n    {\n      \"@type\": \"Person\",\n      \"name\": \"Ingrid Dahlberg\",\n      \"birthDate\": \"1913\"\n    },\n    {\n      \"@type\": \"Person\",\n      \"name\": \"Gert Dahlberg\",\n      \"birthDate\": \"1916\"\n    }\n  ],\n  \"education\": [\n    {\n      \"@type\": \"EducationalOccupationalCredential\",\n      \"name\": \"Stud-ex\",\n      \"description\": \"Degree from Lund University\",\n      \"endDate\": \"1894\"\n    },\n    {\n      \"@type\": \"EducationalOccupationalCredential\",\n      \"name\": \"Fil. kand.\",\n      \"description\": \"Bachelor of Philosophy\",\n      \"endDate\": \"1898\"\n    },\n    {\n      \"@type\": \"EducationalOccupationalCredential\",\n      \"name\": \"Theoretical and Practical Theology Exams\",\n      \"description\": \"\",\n      \"endDate\": \"1902\"\n    }\n  ],\n  \"jobTitle\": [\n    \"Teacher\",\n    \"Temporary Adjutant\",\n    \"Temporary Lecturer\",\n    \"Secretary\",\n    \"Ordained Adjutant\",\n    \"Rector\",\n    \"Vice-Rector\",\n    \"Chairman\",\n    \"Member\"\n  ],\n  \"worksFor\": [\n    {\n      \"@type\": \"Organization\",\n      \"name\": \"Simrishamn\"\n    },\n    {\n      \"@type\": \"Organization\",\n      \"name\": \"Kristianstad\"\n    },\n    {\n      \"@type\": \"Organization\",\n      \"name\": \"Arvika\"\n    },\n    {\n      \"@type\": \"Organization\",\n      \"name\": \"Piteå\"\n    },\n    {\n      \"@type\": \"Organization\",\n      \"name\": \"Karlshamn's High School\"\n    },\n    {\n      \"@type\": \"Organization\",\n      \"name\": \"Municipal Gymnasium\"\n    },\n    {\n      \"@type\": \"Organization\",\n      \"name\": \"Blekinge County Council\"\n    },\n    {\n      \"@type\": \"Organization\",\n      \"name\": \"Karlshamn Savings Bank\"\n    }\n  ],\n  \"memberOf\": [\n    {\n      \"@type\": \"Organization\",\n      \"name\": \"Arvika's City Council\",\n      \"startDate\": \"1911\",\n      \"endDate\": \"1912\"\n    },\n    {\n      \"@type\": \"Organization\",\n      \"name\": \"Technical Vocational School\"\n    },\n    {\n      \"@type\": \"Organization\",\n      \"name\": \"Piteå's City Council\",\n      \"startDate\": \"1914\",\n      \"endDate\": \"1925\"\n    },\n    {\n      \"@type\": \"Organization\",\n      \"name\": \"Piteå's Port Authority\",\n      \"startDate\": \"1914\",\n      \"endDate\": \"1919\"\n    },\n    {\n      \"@type\": \"Organization\",\n      \"name\": \"County Administrative Board\",\n      \"startDate\": \"1918\",\n      \"endDate\": \"1925\"\n    },\n    {\n      \"@type\": \"Organization\",\n      \"name\": \"County Council for Health and Welfare\",\n      \"startDate\": \"1914\",\n      \"endDate\": \"1925\"\n    },\n    {\n      \"@type\": \"Organization\",\n      \"name\": \"Taxation Committee\",\n      \"startDate\": \"1922\",\n      \"endDate\": \"1925\"\n    },\n    {\n      \"@type\": \"Organization\",\n      \"name\": \"Norrbotten County Council\",\n      \"startDate\": \"1921\",\n      \"endDate\": \"1922\"\n    },\n    {\n      \"@type\": \"Organization\",\n      \"name\": \"Karlshamn's City Council\",\n      \"startDate\": \"1927\",\n      \"endDate\": \"1936\"\n    },\n    {\n      \"@type\": \"Organization\",\n      \"name\": \"Board of Directors\"\n    },\n    {\n      \"@type\": \"Organization\",\n      \"name\": \"City Library Board\",\n      \"startDate\": \"1926\",\n      \"endDate\": \"1938\"\n    },\n    {\n      \"@type\": \"Organization\",\n      \"name\": \"Local Board of Directors for Municipal High School\",\n      \"startDate\": \"1929\",\n      \"endDate\": \"1942\"\n    },\n    {\n      \"@type\": \"Organization\",\n      \"name\": \"Board of Directors for Municipal Gymnasium\",\n      \"startDate\": \"1925\",\n      \"endDate\": \"1940\"\n    },\n    {\n      \"@type\": \"Organization\",\n      \"name\": \"General Church Meeting\",\n      \"startDate\": \"1915\",\n      \"endDate\": \"1915\"\n    },\n    {\n      \"@type\": \"Organization\",\n      \"name\": \"Commission on Freedom of the Press\",\n      \"startDate\": \"1928\",\n      \"endDate\": \"1939\"\n    }\n  ],\n  \"award\": [\n    {\n      \"@type\": \"Medal\",\n      \"name\": \"Royal Order of Vasa\",\n      \"awardDate\": \"1923\"\n    }\n  ]\n}",
    "structured": {
        "@context": "https://schema.org",
        "@type": "Person",
        "name": "Elis Fredrik Leopold Dahlberg",
        "birthDate": "1877-04-01",
        "birthPlace": "Simrishamn",
        "deathDate": "",
        "deathPlace": "",
        "description": "Former principal from Karlshamn",
        "spouse": [
            {
                "@type": "Person",
                "name": "Gertrud Bergh",
                "marriageDate": "1909"
            }
        ],
        "children": [
            {
                "@type": "Person",
                "name": "Ingrid Dahlberg",
                "birthDate": "1913"
            },
            {
                "@type": "Person",
                "name": "Gert Dahlberg",
                "birthDate": "1916"
            }
        ],
        "education": [
            {
                "@type": "EducationalOccupationalCredential",
                "name": "Stud-ex",
                "description": "Degree from Lund University",
                "endDate": "1894"
            },
            {
                "@type": "EducationalOccupationalCredential",
                "name": "Fil. kand.",
                "description": "Bachelor of Philosophy",
                "endDate": "1898"
            },
            {
                "@type": "EducationalOccupationalCredential",
                "name": "Theoretical and Practical Theology Exams",
                "description": "",
                "endDate": "1902"
            }
        ],
        "jobTitle": [
            "Teacher",
            "Temporary Adjutant",
            "Temporary Lecturer",
            "Secretary",
            "Ordained Adjutant",
            "Rector",
            "Vice-Rector",
            "Chairman",
            "Member"
        ],
        "worksFor": [
            {
                "@type": "Organization",
                "name": "Simrishamn"
            },
            {
                "@type": "Organization",
                "name": "Kristianstad"
            },
            {
                "@type": "Organization",
                "name": "Arvika"
            },
            {
                "@type": "Organization",
                "name": "Piteå"
            },
            {
                "@type": "Organization",
                "name": "Karlshamn's High School"
            },
            {
                "@type": "Organization",
                "name": "Municipal Gymnasium"
            },
            {
                "@type": "Organization",
                "name": "Blekinge County Council"
            },
            {
                "@type": "Organization",
                "name": "Karlshamn Savings Bank"
            }
        ],
        "memberOf": [
            {
                "@type": "Organization",
                "name": "Arvika's City Council",
                "startDate": "1911",
                "endDate": "1912"
            },
            {
                "@type": "Organization",
                "name": "Technical Vocational School"
            },
            {
                "@type": "Organization",
                "name": "Piteå's City Council",
                "startDate": "1914",
                "endDate": "1925"
            },
            {
                "@type": "Organization",
                "name": "Piteå's Port Authority",
                "startDate": "1914",
                "endDate": "1919"
            },
            {
                "@type": "Organization",
                "name": "County Administrative Board",
                "startDate": "1918",
                "endDate": "1925"
            },
            {
                "@type": "Organization",
                "name": "County Council for Health and Welfare",
                "startDate": "1914",
                "endDate": "1925"
            },
            {
                "@type": "Organization",
                "name": "Taxation Committee",
                "startDate": "1922",
                "endDate": "1925"
            },
            {
                "@type": "Organization",
                "name": "Norrbotten County Council",
                "startDate": "1921",
                "endDate": "1922"
            },
            {
                "@type": "Organization",
                "name": "Karlshamn's City Council",
                "startDate": "1927",
                "endDate": "1936"
            },
            {
                "@type": "Organization",
                "name": "Board of Directors"
            },
            {
                "@type": "Organization",
                "name": "City Library Board",
                "startDate": "1926",
                "endDate": "1938"
            },
            {
                "@type": "Organization",
                "name": "Local Board of Directors for Municipal High School",
                "startDate": "1929",
                "endDate": "1942"
            },
            {
                "@type": "Organization",
                "name": "Board of Directors for Municipal Gymnasium",
                "startDate": "1925",
                "endDate": "1940"
            },
            {
                "@type": "Organization",
                "name": "General Church Meeting",
                "startDate": "1915",
                "endDate": "1915"
            },
            {
                "@type": "Organization",
                "name": "Commission on Freedom of the Press",
                "startDate": "1928",
                "endDate": "1939"
            }
        ],
        "award": [
            {
                "@type": "Medal",
                "name": "Royal Order of Vasa",
                "awardDate": "1923"
            }
        ]
    }
}