{
    "original": "Bergwik, Ernst Wilhelm, direktör, Lidköping, f. 29/7/80 i Skara av förv. Johan Jonsson o. Klara Wollstedt. G. 06 m. Elin Boije. Barn: Gunvor f. 08, Gösta 10, civ :ing., Malmö. — Egen aff:rör. sed. 04, ombild. t. A-B Berg-v^iks Herrekiper. 36. Ordf. i Sv. be-klädn:- o. manufakturhandl ifören. 38-43, v. ordf. i Sv. köpmiförb. t. 43, hed:led. i Västergötl. köpmiförb., hed:ordf. i Lidköp. köpm:fören., led. av styr. f. Kraft A-B Gullspång-Munkfors, las :dir. i Lidköp., ordf. där sed. 43, stadsfullm. ised. 19, v. ordf. sed. 39, landstingsman sed. 32, ordf. i styr. f. Sparbanken i Lidköp. Led. av Spa|rbankernas Bank A-B,s styr. i Sthlm sed. 46, oTdf. i fören. f. Pauvres Ho’n-teux i Lidköp. ’sed. 44, i fören. Lidköp. Frimurarebröder sed. 32. ’RVO, Sv. köpmiförb. ftjGM.",
    "translated": "Bergwik, Ernst Wilhelm, director, Lidköping, born July 29, 1880 in Skara to foster father Johan Jonsson and Klara Wollstedt. Married in 1906 to Elin Boije. Children: Gunvor born in 1908, Gösta born in 1910, civil engineer, Malmö. Own business since 1904, transformed into A-B Bergwiks Herrekiper in 1936. Chairman of the Swedish Clothing and Fashion Merchants' Association from 1938-1943, Vice Chairman of the Swedish Merchants' Association until 1943, Honorary Member of the Västergötl. Merchants' Association, Honorary Chairman of the Lidköping Merchants' Association, member of the board of directors of Kraft A-B Gullspång-Munkfors, district director in Lidköping, chairman since 1943, city council member since 1919, vice chairman since 1939, county council member since 1932, chairman of the board of directors of the Savings Bank in Lidköping. Member of the board of directors of Spa|rbanken's Bank A-B in Stockholm since 1946, chairman of the association for Pauvres Honteux in Lidköping since 1944, member of the Lidköping Freemasons' Association since 1932. RVO, Swedish Merchants' Association ftjGM.",
    "structured_raw": "{\n  \"@context\": \"https://schema.org\",\n  \"@type\": \"Person\",\n  \"name\": \"Ernst Wilhelm Bergwik\",\n  \"jobTitle\": \"Director\",\n  \"birthDate\": \"1880-07-29\",\n  \"birthPlace\": \"Skara\",\n  \"nationality\": \"Swedish\",\n  \"parent\": [\n    {\n      \"@type\": \"Person\",\n      \"name\": \"Johan Jonsson\",\n      \"relationship\": \"foster father\"\n    },\n    {\n      \"@type\": \"Person\",\n      \"name\": \"Klara Wollstedt\",\n      \"relationship\": \"foster\"\n    }\n  ],\n  \"spouse\": {\n    \"@type\": \"Person\",\n    \"name\": \"Elin Boije\",\n    \"marriageDate\": \"1906\"\n  },\n  \"children\": [\n    {\n      \"@type\": \"Person\",\n      \"name\": \"Gunvor Bergwik\",\n      \"birthDate\": \"1908\"\n    },\n    {\n      \"@type\": \"Person\",\n      \"name\": \"Gösta Bergwik\",\n      \"jobTitle\": \"Civil Engineer\",\n      \"birthDate\": \"1910\",\n      \"birthPlace\": \"Malmö\"\n    }\n  ],\n  \"memberOf\": [\n    {\n      \"@type\": \"Organization\",\n      \"name\": \"Swedish Clothing and Fashion Merchants' Association\",\n      \"startDate\": \"1938\",\n      \"endDate\": \"1943\",\n      \"jobTitle\": \"Chairman\"\n    },\n    {\n      \"@type\": \"Organization\",\n      \"name\": \"Swedish Merchants' Association\",\n      \"startDate\": \"\",\n      \"endDate\": \"1943\",\n      \"jobTitle\": \"Vice Chairman\"\n    },\n    {\n      \"@type\": \"Organization\",\n      \"name\": \"Västergötl. Merchants' Association\",\n      \"honorificSuffix\": \"Honorary Member\"\n    },\n    {\n      \"@type\": \"Organization\",\n      \"name\": \"Lidköping Merchants' Association\",\n      \"honorificSuffix\": \"Honorary Chairman\"\n    },\n    {\n      \"@type\": \"Organization\",\n      \"name\": \"Kraft A-B Gullspång-Munkfors\",\n      \"jobTitle\": \"Board Member\"\n    },\n    {\n      \"@type\": \"Organization\",\n      \"name\": \"Savings Bank in Lidköping\",\n      \"jobTitle\": \"Chairman of the Board of Directors\"\n    },\n    {\n      \"@type\": \"Organization\",\n      \"name\": \"Spa|rbanken's Bank A-B\",\n      \"jobTitle\": \"Board Member\"\n    },\n    {\n      \"@type\": \"Organization\",\n      \"name\": \"Association for Pauvres Honteux in Lidköping\",\n      \"startDate\": \"1944\",\n      \"jobTitle\": \"Chairman\"\n    },\n    {\n      \"@type\": \"Organization\",\n      \"name\": \"Lidköping Freemasons' Association\",\n      \"startDate\": \"1932\"\n    }\n  ],\n  \"memberOf\": {\n    \"@type\": \"Organization\",\n    \"name\": \"Swedish Merchants' Association\",\n    \"honorificSuffix\": \"RVO ftjGM\"\n  },\n  \"owns\": {\n    \"@type\": \"Organization\",\n    \"name\": \"A-B Bergwiks Herrekiper\",\n    \"startDate\": \"1904\",\n    \"endDate\": \"1936\"\n  },\n  \"worksFor\": {\n    \"@type\": \"Organization\",\n    \"name\": \"Lidköping Municipality\",\n    \"jobTitle\": \"District Director\",\n    \"startDate\": \"1943\"\n  },\n  \"hasOccupation\": {\n    \"@type\": \"Organization\",\n    \"name\": \"City Council of Lidköping\",\n    \"jobTitle\": \"City Councilor\",\n    \"startDate\": \"1919\",\n    \"endDate\": \"1939\",\n    \"honorificSuffix\": \"Vice Chairman\"\n  },\n  \"hasOccupation\": {\n    \"@type\": \"Organization\",\n    \"name\": \"County Council of Lidköping\",\n    \"jobTitle\": \"County Councilor\",\n    \"startDate\": \"1932\"\n  }\n}",
    "structured": {
        "@context": "https://schema.org",
        "@type": "Person",
        "name": "Ernst Wilhelm Bergwik",
        "jobTitle": "Director",
        "birthDate": "1880-07-29",
        "birthPlace": "Skara",
        "nationality": "Swedish",
        "parent": [
            {
                "@type": "Person",
                "name": "Johan Jonsson",
                "relationship": "foster father"
            },
            {
                "@type": "Person",
                "name": "Klara Wollstedt",
                "relationship": "foster"
            }
        ],
        "spouse": {
            "@type": "Person",
            "name": "Elin Boije",
            "marriageDate": "1906"
        },
        "children": [
            {
                "@type": "Person",
                "name": "Gunvor Bergwik",
                "birthDate": "1908"
            },
            {
                "@type": "Person",
                "name": "Gösta Bergwik",
                "jobTitle": "Civil Engineer",
                "birthDate": "1910",
                "birthPlace": "Malmö"
            }
        ],
        "memberOf": {
            "@type": "Organization",
            "name": "Swedish Merchants' Association",
            "honorificSuffix": "RVO ftjGM"
        },
        "owns": {
            "@type": "Organization",
            "name": "A-B Bergwiks Herrekiper",
            "startDate": "1904",
            "endDate": "1936"
        },
        "worksFor": {
            "@type": "Organization",
            "name": "Lidköping Municipality",
            "jobTitle": "District Director",
            "startDate": "1943"
        },
        "hasOccupation": {
            "@type": "Organization",
            "name": "County Council of Lidköping",
            "jobTitle": "County Councilor",
            "startDate": "1932"
        }
    }
}