{
    "original": "Brundin, Per Axel Gunnar, domprost emierituis, Växjö, f. 18/12/72 i Mörkö, Södermani. 1., av lantbr. A. P. B. o. Agnes Widforss. G. 99 m. Elsa Nettelbladt. Barn: Gerdt f. OH, fil. dr, byråinsp. i försäkr linsp., Sven 01, jur. kand., komm iborgmäst. i Öregrund, Gunhild 04, g. m. bibi. v. musik, akad., fil. lic. Gösta Morin, Hjalmar 09, teol. kand., sekr. i sv. kyrkans miss :’styr., Upps., Britta, sjuksköt., g. m. köpm. Ragnar Göthenqvist, Svedala. — Teor. teol. ex. i Upps. 95, folksk:lär:-ex. ;s. å., prakt. teod. ex. 96. Fast :adj. i Älvkarleby 99, tf. sjömanspräst i Londoin 05, ord. 06, sv. kyrkans mi&amp;s:-styr. resiesekr. 11, mi&amp;s :dir. 14, insp :-resa t. sv. kyrkans mrsis :fält i Sydafrika o. Sydindien m. Geylon 20-21, domprost i Växjö o. kyrkoh, i Växjö stads- o. landtsförs. samt Öjaby förs. pastorat 27-43, kontr:prost i Kinne-valds kontr. 32-43, i Norrvidinge kontr. 36-43. Fullm. f. Växjö stift i Fräster-sk. änke- o. pup ikassa 28-37, led. av kyrkomötet 32, 34, 36, 38 o. 41, preses v. Växjö stifts prästmöte 34, Sv. kyr-kamsi repr. i Int. Mrss. Council 22-28, . Teol. hed:dr i Upps. 41. Skr.: Vad sjömansvården vill (10), Under Söderns sol (21), upps. i Vår kyrka fr. början av 20 :e årh. I-IV (11, 17, 22 o. 26), En m|is|sionerande kyrka (24), Där vägarna mötas (25), Ernst Heu-man, biiskop av Tranquebar (26), Ett evang. luth. samarb. o. dess frukt (prästmötesavh. 34), Missionen — Herrens verk (38), I hjärtat av Kina (45). KNO 39, LVO 22, RDDO, LFinl-VROilkl.",
    "translated": "Brundin, Per Axel Gunnar, retired dean, Växjö, b. 18/12/72 in Mörkö, Södermani. 1st son of farmer A. P. B. and Agnes Widforss. Married in 1899 to Elsa Nettelbladt. Children: Gerdt b. 1901, PhD, inspector for insurance companies, Sven b. 1905, law degree, municipal commissioner in Öregrund, Gunhild b. 1904, married to professor of music, academic, licentiate in philosophy, Gösta Morin, Hjalmar b. 1909, theology graduate, secretary of the Swedish Church's Missionary Committee in Uppsala, Britta, nurse, married to merchant Ragnar Göthenqvist, Svedala. Passed theoretical theology exam in Uppsala in 1895 and folk school teacher's exam the same year. Passed practical theology exam in 1896. Served as assistant vicar in Älvkarleby in 1899, acting chaplain to sailors in London in 1905, and was ordained in 1906. Traveling Secretary for the Swedish Church's Missionary Committee in 1911 and Director in 1914. Inspector for mission fields in South Africa, South India, and Ceylon in 1920-21. Dean in Växjö and parish priest in Växjö city and rural parishes and Öjaby parish in 1927-1943. Dean of the Kinnevalds deanery in 1932-1943 and in Norrvidinge in 1936-1943. Represented the Växjö diocese in the Widow and Orphan Fund in 1928-1937, and was a member of the Church Assembly in 1932, 1934, 1936, 1938, and 1941. Chairman of the Växjö diocese's priest meeting in 1934 and represented the Swedish Church in the International Missionary Council in 1922-1928. Received an honorary doctorate in theology from Uppsala in 1941. Wrote: Vad sjömansvården vill (10), Under Söderns sol (21), upps. in Vår kyrka fr. början av 20 :e årh. I-IV (11, 17, 22 o. 26), En m|is|sionerande kyrka (24), Där vägarna mötas (25), Ernst Heuman, bishop of Tranquebar (26), Ett evang. luth. samarb. o. dess frukt (prästmötesavh. 34), Missionen — Herrens verk (38), I hjärtat av Kina (45). Knight of the Royal Order of the North Star in 1939, Litterarum Humaniorum Doctor honoris causa in 1941, Royal Order of Vasa in 1922, and the Royal Order of the Lion of Finland in 1941.",
    "structured_raw": "{\n  \"@context\": \"https://schema.org\",\n  \"@type\": \"Person\",\n  \"name\": \"Per Axel Gunnar Brundin\",\n  \"birthDate\": \"1872-12-18\",\n  \"birthPlace\": \"Mörkö, Södermanland, Sweden\",\n  \"description\": \"Retired dean in Växjö\",\n  \"spouse\": {\n    \"@type\": \"Person\",\n    \"name\": \"Elsa Nettelbladt\",\n    \"marriageDate\": \"1899\"\n  },\n  \"children\": [\n    {\n      \"@type\": \"Person\",\n      \"name\": \"Gerdt\",\n      \"birthDate\": \"1901\",\n      \"description\": \"PhD, inspector for insurance companies\"\n    },\n    {\n      \"@type\": \"Person\",\n      \"name\": \"Sven\",\n      \"birthDate\": \"1905\",\n      \"description\": \"Law degree, municipal commissioner in Öregrund\"\n    },\n    {\n      \"@type\": \"Person\",\n      \"name\": \"Gunhild\",\n      \"birthDate\": \"1904\",\n      \"description\": \"Married to professor of music, academic, licentiate in philosophy, Gösta Morin\"\n    },\n    {\n      \"@type\": \"Person\",\n      \"name\": \"Hjalmar\",\n      \"birthDate\": \"1909\",\n      \"description\": \"Theology graduate, secretary of the Swedish Church's Missionary Committee in Uppsala\"\n    },\n    {\n      \"@type\": \"Person\",\n      \"name\": \"Britta\",\n      \"description\": \"Nurse, married to merchant Ragnar Göthenqvist, Svedala\"\n    }\n  ],\n  \"memberOf\": [\n    {\n      \"@type\": \"Organization\",\n      \"name\": \"Swedish Church's Missionary Committee\",\n      \"startDate\": \"1911\",\n      \"endDate\": \"1914\",\n      \"jobTitle\": \"Traveling Secretary\"\n    },\n    {\n      \"@type\": \"Organization\",\n      \"name\": \"Swedish Church's Missionary Committee\",\n      \"startDate\": \"1914\",\n      \"endDate\": null,\n      \"jobTitle\": \"Director\"\n    },\n    {\n      \"@type\": \"Organization\",\n      \"name\": \"Växjö diocese\",\n      \"startDate\": \"1927\",\n      \"endDate\": \"1943\",\n      \"jobTitle\": \"Dean\"\n    }\n  ],\n  \"education\": [\n    {\n      \"@type\": \"EducationalOccupationalCredential\",\n      \"name\": \"Theoretical theology exam\",\n      \"issuer\": \"Uppsala\",\n      \"issuanceDate\": \"1895\"\n    },\n    {\n      \"@type\": \"EducationalOccupationalCredential\",\n      \"name\": \"Folk school teacher's exam\",\n      \"issuer\": \"Unknown\",\n      \"issuanceDate\": \"1895\"\n    },\n    {\n      \"@type\": \"EducationalOccupationalCredential\",\n      \"name\": \"Practical theology exam\",\n      \"issuer\": \"Unknown\",\n      \"issuanceDate\": \"1896\"\n    },\n    {\n      \"@type\": \"EducationalOccupationalCredential\",\n      \"name\": \"Honorary doctorate in theology\",\n      \"issuer\": \"Uppsala\",\n      \"issuanceDate\": \"1941\"\n    }\n  ],\n  \"worksFor\": [\n    {\n      \"@type\": \"Organization\",\n      \"name\": \"Swedish Church\",\n      \"jobTitle\": \"Assistant vicar\",\n      \"startDate\": \"1899\",\n      \"endDate\": null,\n      \"location\": \"Älvkarleby\"\n    },\n    {\n      \"@type\": \"Organization\",\n      \"name\": \"Swedish Church\",\n      \"jobTitle\": \"Acting chaplain to sailors\",\n      \"startDate\": \"1905\",\n      \"endDate\": null,\n      \"location\": \"London\"\n    }\n  ],\n  \"memberOf\": [\n    {\n      \"@type\": \"Organization\",\n      \"name\": \"Widow and Orphan Fund\",\n      \"jobTitle\": \"Representative\",\n      \"startDate\": \"1928\",\n      \"endDate\": \"1937\",\n      \"location\": \"Växjö diocese\"\n    },\n    {\n      \"@type\": \"Organization\",\n      \"name\": \"Church Assembly\",\n      \"jobTitle\": \"Member\",\n      \"startDate\": \"1932\",\n      \"endDate\": \"1941\",\n      \"location\": \"Sweden\"\n    },\n    {\n      \"@type\": \"Organization\",\n      \"name\": \"Växjö diocese\",\n      \"jobTitle\": \"Priest meeting chairman\",\n      \"startDate\": \"1934\",\n      \"endDate\": null\n    },\n    {\n      \"@type\": \"Organization\",\n      \"name\": \"International Missionary Council\",\n      \"jobTitle\": \"Representative\",\n      \"startDate\": \"1922\",\n      \"endDate\": \"1928\"\n    }\n  ],\n  \"awards\": [\n    {\n      \"@type\": \"Order\",\n      \"name\": \"Knight of the Royal Order of the North Star\",\n      \"dateReceived\": \"1939\"\n    },\n    {\n      \"@type\": \"Order\",\n      \"name\": \"Royal Order of Vasa\",\n      \"dateReceived\": \"1922\"\n    },\n    {\n      \"@type\": \"Order\",\n      \"name\": \"Royal Order of the Lion of Finland\",\n      \"dateReceived\": \"1941\"\n    }\n  ],\n  \"sameAs\": [\n    \"https://viaf.org/viaf/61835760\",\n    \"https://www.wikidata.org/wiki/Q1144364\"\n  ]\n}",
    "structured": {
        "@context": "https://schema.org",
        "@type": "Person",
        "name": "Per Axel Gunnar Brundin",
        "birthDate": "1872-12-18",
        "birthPlace": "Mörkö, Södermanland, Sweden",
        "description": "Retired dean in Växjö",
        "spouse": {
            "@type": "Person",
            "name": "Elsa Nettelbladt",
            "marriageDate": "1899"
        },
        "children": [
            {
                "@type": "Person",
                "name": "Gerdt",
                "birthDate": "1901",
                "description": "PhD, inspector for insurance companies"
            },
            {
                "@type": "Person",
                "name": "Sven",
                "birthDate": "1905",
                "description": "Law degree, municipal commissioner in Öregrund"
            },
            {
                "@type": "Person",
                "name": "Gunhild",
                "birthDate": "1904",
                "description": "Married to professor of music, academic, licentiate in philosophy, Gösta Morin"
            },
            {
                "@type": "Person",
                "name": "Hjalmar",
                "birthDate": "1909",
                "description": "Theology graduate, secretary of the Swedish Church's Missionary Committee in Uppsala"
            },
            {
                "@type": "Person",
                "name": "Britta",
                "description": "Nurse, married to merchant Ragnar Göthenqvist, Svedala"
            }
        ],
        "memberOf": [
            {
                "@type": "Organization",
                "name": "Widow and Orphan Fund",
                "jobTitle": "Representative",
                "startDate": "1928",
                "endDate": "1937",
                "location": "Växjö diocese"
            },
            {
                "@type": "Organization",
                "name": "Church Assembly",
                "jobTitle": "Member",
                "startDate": "1932",
                "endDate": "1941",
                "location": "Sweden"
            },
            {
                "@type": "Organization",
                "name": "Växjö diocese",
                "jobTitle": "Priest meeting chairman",
                "startDate": "1934",
                "endDate": null
            },
            {
                "@type": "Organization",
                "name": "International Missionary Council",
                "jobTitle": "Representative",
                "startDate": "1922",
                "endDate": "1928"
            }
        ],
        "education": [
            {
                "@type": "EducationalOccupationalCredential",
                "name": "Theoretical theology exam",
                "issuer": "Uppsala",
                "issuanceDate": "1895"
            },
            {
                "@type": "EducationalOccupationalCredential",
                "name": "Folk school teacher's exam",
                "issuer": "Unknown",
                "issuanceDate": "1895"
            },
            {
                "@type": "EducationalOccupationalCredential",
                "name": "Practical theology exam",
                "issuer": "Unknown",
                "issuanceDate": "1896"
            },
            {
                "@type": "EducationalOccupationalCredential",
                "name": "Honorary doctorate in theology",
                "issuer": "Uppsala",
                "issuanceDate": "1941"
            }
        ],
        "worksFor": [
            {
                "@type": "Organization",
                "name": "Swedish Church",
                "jobTitle": "Assistant vicar",
                "startDate": "1899",
                "endDate": null,
                "location": "Älvkarleby"
            },
            {
                "@type": "Organization",
                "name": "Swedish Church",
                "jobTitle": "Acting chaplain to sailors",
                "startDate": "1905",
                "endDate": null,
                "location": "London"
            }
        ],
        "awards": [
            {
                "@type": "Order",
                "name": "Knight of the Royal Order of the North Star",
                "dateReceived": "1939"
            },
            {
                "@type": "Order",
                "name": "Royal Order of Vasa",
                "dateReceived": "1922"
            },
            {
                "@type": "Order",
                "name": "Royal Order of the Lion of Finland",
                "dateReceived": "1941"
            }
        ],
        "sameAs": [
            "https://viaf.org/viaf/61835760",
            "https://www.wikidata.org/wiki/Q1144364"
        ]
    }
}