{
    "original": "Liljestrand, Holger, civilingenjör, vägdirektör, Jönköping, f. 28/4/97 i Gbg av försäkr:dir. Peter Erik L. o. Tekla Carlberg. — Stud :ex. v. Sofi Almquists samsk. i Sthlm 15, avg:ex. fr. KTH 22, res:off:ex. 17. Fänr. i fortif. res. 17, und :löjtn. 20, löjtn. 25, i VVK 26, kapt. i VVK 33. Konstr. v. Bergsunds Mek. Verkst. A-B i Sthlm 23, arb:led. h. J. M. Hutchison Entrepr. i Pennsylvania, USA, arb:-led. o. bitr. arb :chef v. A-B Vägför-bättringar i Sthlm 25-32, tf. byråing. v. väg- o. vattenbyggn :styr. 32-35, byråing. å vägtrafikbyrån där 36, vägdir. i Jönköp. 1. sed. 43. Medl. av Sv. tek-n :för. 23-35.",
    "translated": "Liljestrand, Holger, civil engineer, road director, Jönköping, born April 28, 1897 in Gothenburg, son of insurance director Peter Erik L. and Tekla Carlberg. Completed studies at Sofi Almquist's coeducational school in Stockholm in 1915, graduated from KTH (Royal Institute of Technology) in 1922, completed reserve officer training in 1917. Became a second lieutenant in the fortification reserve in 1920, lieutenant in 1925, and joined the Road and Water Construction Corps in 1926. Promoted to captain in 1933. Engineering work at Bergsunds Mekaniska Verkstads AB in Stockholm in 1923, worked as a supervisor at J.M. Hutchison Entreprises in Pennsylvania, USA, and as assistant works manager at AB Vägförbättringar in Stockholm from 1925 to 1932. Temporary bureau engineer at the Road and Water Construction Board from 1932 to 1935, bureau engineer at the road traffic bureau in 1936, and road director in Jönköping since 1943. Member of the Swedish Technical Association from 1923 to 1935.",
    "structured_raw": "{\n  \"@context\": \"http://schema.org\",\n  \"@type\": \"Person\",\n  \"name\": \"Holger Liljestrand\",\n  \"birthDate\": \"1897-04-28\",\n  \"birthPlace\": \"Gothenburg, Sweden\",\n  \"nationality\": \"Swedish\",\n  \"description\": \"Civil engineer, road director in Jönköping\",\n  \"parents\": [\n    {\n      \"@type\": \"Person\",\n      \"name\": \"Peter Erik Liljestrand\",\n      \"jobTitle\": \"Insurance Director\"\n    },\n    {\n      \"@type\": \"Person\",\n      \"name\": \"Tekla Carlberg\"\n    }\n  ],\n  \"education\": [\n    {\n      \"@type\": \"EducationalOrganization\",\n      \"name\": \"Sofi Almquists Samskola\",\n      \"location\": \"Stockholm, Sweden\"\n    },\n    {\n      \"@type\": \"EducationalOrganization\",\n      \"name\": \"Royal Institute of Technology\",\n      \"location\": \"Stockholm, Sweden\",\n      \"startDate\": \"1915\",\n      \"endDate\": \"1922\"\n    }\n  ],\n  \"work\": [\n    {\n      \"@type\": \"Organization\",\n      \"name\": \"Bergsunds Mekaniska Verkstads AB\",\n      \"location\": \"Stockholm, Sweden\",\n      \"startDate\": \"1923\"\n    },\n    {\n      \"@type\": \"Organization\",\n      \"name\": \"J.M. Hutchison Entreprises\",\n      \"location\": \"Pennsylvania, USA\"\n    },\n    {\n      \"@type\": \"Organization\",\n      \"name\": \"AB Vägförbättringar\",\n      \"location\": \"Stockholm, Sweden\",\n      \"startDate\": \"1925\",\n      \"endDate\": \"1932\",\n      \"jobTitle\": \"Assistant Works Manager\"\n    },\n    {\n      \"@type\": \"Organization\",\n      \"name\": \"Road and Water Construction Board\",\n      \"jobTitle\": \"Temporary Bureau Engineer\",\n      \"startDate\": \"1932\",\n      \"endDate\": \"1935\"\n    },\n    {\n      \"@type\": \"Organization\",\n      \"name\": \"Road Traffic Bureau\",\n      \"jobTitle\": \"Bureau Engineer\",\n      \"startDate\": \"1936\"\n    },\n    {\n      \"@type\": \"Organization\",\n      \"name\": \"Road Director in Jönköping\",\n      \"startDate\": \"1943\"\n    }\n  ],\n  \"memberOf\": [\n    {\n      \"@type\": \"Organization\",\n      \"name\": \"Swedish Technical Association\",\n      \"startDate\": \"1923\",\n      \"endDate\": \"1935\"\n    }\n  ],\n  \"gender\": \"Male\"\n}",
    "structured": {
        "@context": "http://schema.org",
        "@type": "Person",
        "name": "Holger Liljestrand",
        "birthDate": "1897-04-28",
        "birthPlace": "Gothenburg, Sweden",
        "nationality": "Swedish",
        "description": "Civil engineer, road director in Jönköping",
        "parents": [
            {
                "@type": "Person",
                "name": "Peter Erik Liljestrand",
                "jobTitle": "Insurance Director"
            },
            {
                "@type": "Person",
                "name": "Tekla Carlberg"
            }
        ],
        "education": [
            {
                "@type": "EducationalOrganization",
                "name": "Sofi Almquists Samskola",
                "location": "Stockholm, Sweden"
            },
            {
                "@type": "EducationalOrganization",
                "name": "Royal Institute of Technology",
                "location": "Stockholm, Sweden",
                "startDate": "1915",
                "endDate": "1922"
            }
        ],
        "work": [
            {
                "@type": "Organization",
                "name": "Bergsunds Mekaniska Verkstads AB",
                "location": "Stockholm, Sweden",
                "startDate": "1923"
            },
            {
                "@type": "Organization",
                "name": "J.M. Hutchison Entreprises",
                "location": "Pennsylvania, USA"
            },
            {
                "@type": "Organization",
                "name": "AB Vägförbättringar",
                "location": "Stockholm, Sweden",
                "startDate": "1925",
                "endDate": "1932",
                "jobTitle": "Assistant Works Manager"
            },
            {
                "@type": "Organization",
                "name": "Road and Water Construction Board",
                "jobTitle": "Temporary Bureau Engineer",
                "startDate": "1932",
                "endDate": "1935"
            },
            {
                "@type": "Organization",
                "name": "Road Traffic Bureau",
                "jobTitle": "Bureau Engineer",
                "startDate": "1936"
            },
            {
                "@type": "Organization",
                "name": "Road Director in Jönköping",
                "startDate": "1943"
            }
        ],
        "memberOf": [
            {
                "@type": "Organization",
                "name": "Swedish Technical Association",
                "startDate": "1923",
                "endDate": "1935"
            }
        ],
        "gender": "Male"
    }
}