{
    "original": "Höglund, Hjallmar Hugo, sjukhusdirektör, Göteborg, f. 4/11/89 i’Gbg av Sven Johan H. o. Hulda Carlsson. G. 1. 13 m. Agnes Bengtsson, d. 44; 2. 46 m. Birgit Persson. Barn: Ingela f. 19, g. m. civ :ing. Sven Kristensson, Gbg. — Förest, f. Gbgs offentl. arb:-förmedk 27-33, socialstyr. omb. 30-33, sjukhusdir. i Gbg sed. 33. Inneh. ett stort ant. komm. o. a. förtr :uppdr., bl. a. ordf. i Gbgs-Postens persikl 15-19, i maskinsätt :sekt. 18-20, i Gbgs typogr. fören. 20-27, i typogr:förb. v. distr. 21-27, led. av styr. f. typogr förb. samma tid, ordf. i Gbgs-Postens driftsråd 26-27, distr :ordf. i Gbgs arb:-kommun 20-28, ordf. i Gbgs fackfören. centr iförs. 21-27, led. av stadsfullm. (s) sed. 21, ordf. i dess diskuss :kl. samt v. ordf. i dess socrdem. grupp, led. av stadskoll., drätselkamm., po-lisndn, arb :lös’h :komm., styr. f. arb:-förmedl, styr. f. Renströmska bad-anst., flicklärov., stadsteatern o. div. byggn:komm., ordf. i hälsovindn, sjukhusdirekt., valkomm., gatunamns-beredn., fam :bidr :ndn, sjuksköt :sk. o. semesterhemmet f. husmödrar, led. av länsarb :ndn, stadsförb. styr. o. dess sjukvårdsdeilegation, led. av div. kungl. komm., tillh. lOGT. Föret. uti. stud:-res.",
    "translated": "Höglund, Hjallmar Hugo, hospital director, Gothenburg, b. 4/11/89 in Gothenburg to Sven Johan H. and Hulda Carlsson. Married 1st in 1913 to Agnes Bengtsson, d. 1944; 2nd in 1946 to Birgit Persson. Children: Ingela b. 1919, married to civil engineer Sven Kristensson, Gothenburg. Previously held various municipal and other positions, including chairman of the Gothenburg Post's editorial board from 1915-1919, in the typesetting section from 1918-1920, in the Gothenburg typographers' association from 1920-1927, on the executive board of the Typographers' Union from 1921-1927, chairman of the Gothenburg Post's operations board from 1926-1927, district chairman of the Gothenburg Labour Committee from 1920-1928, chairman of the Gothenburg Trade Union Center for Commerce and Industry from 1921-1927, member of the city council (Social Democrats) since 1921, chairman of its discussion committee, and vice chairman of its social democratic group, member of the city inspection, finance committee, police commission, unemployment committee, Board of Labor, Board of the Renström Bath House, girls' schools committee, city theater committee, and various building committees. Also chairman of the Health Wind, Hospital Director, Election Committee, Street Name Committee, Family Allowance Board, Nursing School and Holiday Home for Housewives, member of the County Labour Board, City Federation Board and its Health care delegation, as well as various royal commissions, and a member of the IOGT (the International Organisation of Good Templars). Undertook study trips abroad.",
    "structured_raw": "{\n   \"@context\": \"https://schema.org\",\n   \"@type\": \"Person\",\n   \"name\": \"Hjallmar Hugo Höglund\",\n   \"givenName\": \"Hjallmar Hugo\",\n   \"familyName\": \"Höglund\",\n   \"birthPlace\": \"Gothenburg\",\n   \"birthDate\": \"1889-11-04\",\n   \"father\": {\n      \"@type\": \"Person\",\n      \"name\": \"Sven Johan H. Höglund\"\n   },\n   \"mother\": {\n      \"@type\": \"Person\",\n      \"name\": \"Hulda Carlsson\"\n   },\n   \"spouse\": [\n      {\n         \"@type\": \"Person\",\n         \"name\": \"Agnes Bengtsson\",\n         \"marriageDate\": \"1913\",\n         \"deathDate\": \"1944\"\n      },\n      {\n         \"@type\": \"Person\",\n         \"name\": \"Birgit Persson\",\n         \"marriageDate\": \"1946\"\n      }\n   ],\n   \"children\": [\n      {\n         \"@type\": \"Person\",\n         \"name\": \"Ingela\",\n         \"birthDate\": \"1919\",\n         \"spouse\": {\n            \"@type\": \"Person\",\n            \"name\": \"Sven Kristensson\",\n            \"jobTitle\": \"Civil Engineer\",\n            \"worksFor\": \"Gothenburg\"\n         }\n      }\n   ],\n   \"jobTitle\": \"Hospital Director\",\n   \"worksFor\": \"Gothenburg\",\n   \"memberOf\": [\n      {\n         \"@type\": \"Organization\",\n         \"name\": \"Gothenburg Post\",\n         \"jobTitle\": \"Chairman of Editorial Board\",\n         \"startDate\": \"1915\",\n         \"endDate\": \"1919\"\n      },\n      {\n         \"@type\": \"Organization\",\n         \"name\": \"Gothenburg Typographers' Association\",\n         \"jobTitle\": \"Chairman\",\n         \"startDate\": \"1920\",\n         \"endDate\": \"1927\"\n      },\n      {\n         \"@type\": \"Organization\",\n         \"name\": \"Typographers' Union\",\n         \"jobTitle\": \"Executive Board Member\",\n         \"startDate\": \"1921\",\n         \"endDate\": \"1927\"\n      },\n      {\n         \"@type\": \"Organization\",\n         \"name\": \"Gothenburg Labour Committee\",\n         \"jobTitle\": \"District Chairman\",\n         \"startDate\": \"1920\",\n         \"endDate\": \"1928\"\n      },\n      {\n         \"@type\": \"Organization\",\n         \"name\": \"City Council\",\n         \"jobTitle\": \"Member\",\n         \"startDate\": \"1921\"\n      },\n      {\n         \"@type\": \"Organization\",\n         \"name\": \"Health Wind\",\n         \"jobTitle\": \"Chairman\",\n         \"startDate\": \"unknown\"\n      },\n      {\n         \"@type\": \"Organization\",\n         \"name\": \"Renström Bath House\",\n         \"jobTitle\": \"Board Member\",\n         \"startDate\": \"unknown\"\n      },\n      {\n         \"@type\": \"Organization\",\n         \"name\": \"IOGT\",\n         \"jobTitle\": \"Member\",\n         \"startDate\": \"unknown\"\n      }\n   ],\n   \"education\": [\n      {\n         \"@type\": \"EducationalOrganization\",\n         \"name\": \"unknown\"\n      }\n   ]\n}",
    "structured": {
        "@context": "https://schema.org",
        "@type": "Person",
        "name": "Hjallmar Hugo Höglund",
        "givenName": "Hjallmar Hugo",
        "familyName": "Höglund",
        "birthPlace": "Gothenburg",
        "birthDate": "1889-11-04",
        "father": {
            "@type": "Person",
            "name": "Sven Johan H. Höglund"
        },
        "mother": {
            "@type": "Person",
            "name": "Hulda Carlsson"
        },
        "spouse": [
            {
                "@type": "Person",
                "name": "Agnes Bengtsson",
                "marriageDate": "1913",
                "deathDate": "1944"
            },
            {
                "@type": "Person",
                "name": "Birgit Persson",
                "marriageDate": "1946"
            }
        ],
        "children": [
            {
                "@type": "Person",
                "name": "Ingela",
                "birthDate": "1919",
                "spouse": {
                    "@type": "Person",
                    "name": "Sven Kristensson",
                    "jobTitle": "Civil Engineer",
                    "worksFor": "Gothenburg"
                }
            }
        ],
        "jobTitle": "Hospital Director",
        "worksFor": "Gothenburg",
        "memberOf": [
            {
                "@type": "Organization",
                "name": "Gothenburg Post",
                "jobTitle": "Chairman of Editorial Board",
                "startDate": "1915",
                "endDate": "1919"
            },
            {
                "@type": "Organization",
                "name": "Gothenburg Typographers' Association",
                "jobTitle": "Chairman",
                "startDate": "1920",
                "endDate": "1927"
            },
            {
                "@type": "Organization",
                "name": "Typographers' Union",
                "jobTitle": "Executive Board Member",
                "startDate": "1921",
                "endDate": "1927"
            },
            {
                "@type": "Organization",
                "name": "Gothenburg Labour Committee",
                "jobTitle": "District Chairman",
                "startDate": "1920",
                "endDate": "1928"
            },
            {
                "@type": "Organization",
                "name": "City Council",
                "jobTitle": "Member",
                "startDate": "1921"
            },
            {
                "@type": "Organization",
                "name": "Health Wind",
                "jobTitle": "Chairman",
                "startDate": "unknown"
            },
            {
                "@type": "Organization",
                "name": "Renström Bath House",
                "jobTitle": "Board Member",
                "startDate": "unknown"
            },
            {
                "@type": "Organization",
                "name": "IOGT",
                "jobTitle": "Member",
                "startDate": "unknown"
            }
        ],
        "education": [
            {
                "@type": "EducationalOrganization",
                "name": "unknown"
            }
        ]
    }
}