{
    "original": "Aspelin, Per Algot, fd. apotekare, Tidaholm, f. 31/12/75 i Hållnäs, Upps. L, av Anders A. o. Charlotta Bohlin. G. m. Sigrid Rönström. Barn: Karin f. 14, g. m. apot. Bertil Berg, Lidköp. — Mog:ex. i Gävle 97, farm. kand. 02, apot:ex. 07. Anst. v. apot. Kronan i Linköp. 02-03, v. apot. i Örnsköldsvik 03-05, v. Svanen i Sthlm 07-08, apot. i Fränsta 08, i Dannemora 08-09, i Askersund 09-11, i Kungälv 11-14, i Mariestad 14-31, i Vara 31-32, i Liden 32-34, priv. å apot. i Tidahoim. 35-45.",
    "translated": "Aspelin, Per Algot, former pharmacist, born December 31, 1875 in Hållnäs, Uppsala County, son of Anders A. and Charlotta Bohlin. Married to Sigrid Rönström. Children: Karin, born in 1914, married to pharmacist Bertil Berg in Lidköping. Completed studies in Pharmacy in Gävle in 1897, obtained a Bachelor of Science degree in Pharmacy in 1902, and obtained a pharmacy license in 1907. Employed at Kronan Pharmacy in Linköping from 1902-1903, deputy pharmacist in Örnsköldsvik from 1903-1905, deputy at Svanen Pharmacy in Stockholm from 1907-1908, pharmacist at Fränsta Pharmacy in 1908, Danemora Pharmacy in 1908-1909, Askersund Pharmacy from 1909-1911, Kungälv Pharmacy from 1911-1914, Mariestad Pharmacy from 1914-1931, Vara Pharmacy from 1931-1932, Liden Pharmacy from 1932-1934, and privately at Tidaholm Pharmacy from 1935-1945.",
    "structured": {
        "@context": "https://schema.org",
        "@type": "Person",
        "name": "Per Algot Aspelin",
        "jobTitle": "Former pharmacist",
        "birthDate": "1875-12-31",
        "birthPlace": {
            "@type": "City",
            "name": "Hållnäs"
        },
        "nationality": {
            "@type": "Country",
            "name": "Sweden"
        },
        "parent": {
            "@type": "Person",
            "name": "Anders A. Aspelin and Charlotta Bohlin"
        },
        "spouse": {
            "@type": "Person",
            "name": "Sigrid Rönström"
        },
        "children": {
            "@type": "Person",
            "name": "Karin Aspelin",
            "birthDate": "1914",
            "spouse": {
                "@type": "Person",
                "name": "Bertil Berg",
                "jobTitle": "Pharmacist",
                "memberOf": {
                    "@type": "LocalBusiness",
                    "name": "Lidköping Pharmacy"
                }
            }
        },
        "education": {
            "@type": "EducationalOccupationalCredential",
            "name": "Pharmacy Studies",
            "credentialCategory": "degree",
            "educationalLevel": "Bachelor's degree",
            "provider": {
                "@type": "Organization",
                "name": "University of Gävle"
            },
            "startDate": "1897",
            "endDate": "1902"
        },
        "worksFor": [
            {
                "@type": "Organization",
                "name": "Kronan Pharmacy",
                "startDate": "1902",
                "endDate": "1903",
                "jobTitle": "Pharmacist"
            },
            {
                "@type": "Organization",
                "name": "Örnsköldsvik Pharmacy",
                "startDate": "1903",
                "endDate": "1905",
                "jobTitle": "Deputy Pharmacist"
            },
            {
                "@type": "Organization",
                "name": "Svanen Pharmacy",
                "startDate": "1907",
                "endDate": "1908",
                "jobTitle": "Deputy Pharmacist"
            },
            {
                "@type": "Organization",
                "name": "Fränsta Pharmacy",
                "startDate": "1908",
                "endDate": "1909",
                "jobTitle": "Pharmacist"
            },
            {
                "@type": "Organization",
                "name": "Danemora Pharmacy",
                "startDate": "1908",
                "endDate": "1909",
                "jobTitle": "Pharmacist"
            },
            {
                "@type": "Organization",
                "name": "Askersund Pharmacy",
                "startDate": "1909",
                "endDate": "1911",
                "jobTitle": "Pharmacist"
            },
            {
                "@type": "Organization",
                "name": "Kungälv Pharmacy",
                "startDate": "1911",
                "endDate": "1914",
                "jobTitle": "Pharmacist"
            },
            {
                "@type": "Organization",
                "name": "Mariestad Pharmacy",
                "startDate": "1914",
                "endDate": "1931",
                "jobTitle": "Pharmacist"
            },
            {
                "@type": "Organization",
                "name": "Vara Pharmacy",
                "startDate": "1931",
                "endDate": "1932",
                "jobTitle": "Pharmacist"
            },
            {
                "@type": "Organization",
                "name": "Liden Pharmacy",
                "startDate": "1932",
                "endDate": "1934",
                "jobTitle": "Pharmacist"
            },
            {
                "@type": "Organization",
                "name": "Tidaholm Pharmacy",
                "startDate": "1935",
                "endDate": "1945",
                "jobTitle": "Pharmacist",
                "hasOfferCatalog": {
                    "@type": "OfferCatalog",
                    "name": "Private pharmacy services"
                }
            }
        ]
    }
}