{
    "original": "Josefson, Sten, disponent, Ulricehamn, f. 11/3/14 i Ulricehamn av grosshandl. Erik J. o. Ingeborg Andersson. — Stud:ex. i Borås 33, Gbgs hand :inst. fackkurs f. stud. 34, Höhere Fachschule f. Wirkerei- und Stricke-reiindustrie i Chemnitz 37, prakt, inom textilind. i Tyskl. o. Schv^eiz. Stud :res. t. Tyskl., Schv^eiz, Frankr., Belg. o. Tjeckoslov. Disp. o. led. av styr. f. A-B Erik Josefson &amp; Co. i Ulricehamn sed. 38. Suppl. i styr. f. Ulricehamns Tidn. A-B, verkst. dir. där 43-46, Led. av stadsfullm. (h) sed. 43 siamt av des’s beredn :utsk., led. av drätselkamm. fr. 47, suppl. i lokalstyr. 1. Ulricehamns samrealsk., av Älvsb. 1. landsting utsedd t. siuppl i direkt, f. Sjö-Gunnarsbo san. o. sjukst. i Ulricehamn, led. av styr. f. Ulricehamns hö-gerfören. o. södra Älvsb. högerförb.",
    "translated": "Josefson, Sten, manager, Ulricehamn, b. March 11, 1914 in Ulricehamn to wholesale merchant Erik J. and Ingeborg Andersson. — Graduated from high school in Borås in 1933, specialized course for students at the Gothenburg School of Business in 1934, Higher Technical School for Weaving and Knitting Industry in Chemnitz in 1937, practical experience in textile industry in Germany and Switzerland. Studied abroad in Germany, Switzerland, France, Belgium, and Czechoslovakia. Manager and board member of Erik Josefson & Co. AB in Ulricehamn since 1938. Board member of Ulricehamns Tidnings AB, where he served as managing director from 1943 to 1946. Member of the city council (conservative party) since 1943, as well as member of its preparatory committee. Also a member of the municipal board in Ulricehamns samrealskola, appointed by the Älvsborg county council as deputy member of the board for Sjö-Gunnarsbo sanatorium and hospital in Ulricehamn, and board member of Ulricehamns conservative association and the Southern Älvsborg Conservative Federation.",
    "structured_raw": "{\n  \"@context\": \"https://schema.org\",\n  \"@type\": \"Person\",\n  \"givenName\": \"Sten\",\n  \"familyName\": \"Josefson\",\n  \"jobTitle\": \"Manager\",\n  \"birthDate\": \"1914-03-11\",\n  \"birthPlace\": \"Ulricehamn\",\n  \"nationality\": \"Swedish\",\n  \"alumniOf\": [\n    {\n      \"@type\": \"EducationalOrganization\",\n      \"name\": \"Borås High School\",\n      \"location\": \"Borås\",\n      \"startDate\": \"1933\"\n    },\n    {\n      \"@type\": \"EducationalOrganization\",\n      \"name\": \"Gothenburg School of Business\",\n      \"location\": \"Gothenburg\",\n      \"specialization\": \"Student specialized course\",\n      \"startDate\": \"1934\"\n    },\n    {\n      \"@type\": \"EducationalOrganization\",\n      \"name\": \"Higher Technical School for Weaving and Knitting Industry\",\n      \"location\": \"Chemnitz\",\n      \"startDate\": \"1937\"\n    }\n  ],\n  \"memberOf\": [\n    {\n      \"@type\": \"Organization\",\n      \"name\": \"Erik Josefson & Co. AB\",\n      \"position\": \"Manager and board member\",\n      \"startDate\": \"1938\"\n    },\n    {\n      \"@type\": \"Organization\",\n      \"name\": \"Ulricehamns Tidnings AB\",\n      \"position\": \"Board member\",\n      \"startDate\": \"1943\",\n      \"endDate\": \"1946\"\n    },\n    {\n      \"@type\": \"Organization\",\n      \"name\": \"City council\",\n      \"position\": \"Member\",\n      \"startDate\": \"1943\",\n      \"memberOf\": [\n        {\n          \"@type\": \"Organization\",\n          \"name\": \"Preparatory committee\"\n        }\n      ]\n    },\n    {\n      \"@type\": \"Organization\",\n      \"name\": \"Ulricehamns samrealskola\",\n      \"position\": \"Municipal board member\"\n    },\n    {\n      \"@type\": \"Organization\",\n      \"name\": \"Älvsborg county council\",\n      \"position\": \"Deputy member of board for Sjö-Gunnarsbo sanatorium and hospital in Ulricehamn\"\n    },\n    {\n      \"@type\": \"Organization\",\n      \"name\": \"Ulricehamns conservative association\",\n      \"position\": \"Board member\"\n    },\n    {\n      \"@type\": \"Organization\",\n      \"name\": \"Southern Älvsborg Conservative Federation\",\n      \"position\": \"Board member\"\n    }\n  ]\n}",
    "structured": {
        "@context": "https://schema.org",
        "@type": "Person",
        "givenName": "Sten",
        "familyName": "Josefson",
        "jobTitle": "Manager",
        "birthDate": "1914-03-11",
        "birthPlace": "Ulricehamn",
        "nationality": "Swedish",
        "alumniOf": [
            {
                "@type": "EducationalOrganization",
                "name": "Borås High School",
                "location": "Borås",
                "startDate": "1933"
            },
            {
                "@type": "EducationalOrganization",
                "name": "Gothenburg School of Business",
                "location": "Gothenburg",
                "specialization": "Student specialized course",
                "startDate": "1934"
            },
            {
                "@type": "EducationalOrganization",
                "name": "Higher Technical School for Weaving and Knitting Industry",
                "location": "Chemnitz",
                "startDate": "1937"
            }
        ],
        "memberOf": [
            {
                "@type": "Organization",
                "name": "Erik Josefson & Co. AB",
                "position": "Manager and board member",
                "startDate": "1938"
            },
            {
                "@type": "Organization",
                "name": "Ulricehamns Tidnings AB",
                "position": "Board member",
                "startDate": "1943",
                "endDate": "1946"
            },
            {
                "@type": "Organization",
                "name": "City council",
                "position": "Member",
                "startDate": "1943",
                "memberOf": [
                    {
                        "@type": "Organization",
                        "name": "Preparatory committee"
                    }
                ]
            },
            {
                "@type": "Organization",
                "name": "Ulricehamns samrealskola",
                "position": "Municipal board member"
            },
            {
                "@type": "Organization",
                "name": "Älvsborg county council",
                "position": "Deputy member of board for Sjö-Gunnarsbo sanatorium and hospital in Ulricehamn"
            },
            {
                "@type": "Organization",
                "name": "Ulricehamns conservative association",
                "position": "Board member"
            },
            {
                "@type": "Organization",
                "name": "Southern Älvsborg Conservative Federation",
                "position": "Board member"
            }
        ]
    }
}