{
    "original": "Danielsson, Daniel Ragnar, |landsfiskal, Kungsbacka, f. 20/6/88 i Ullasjö, Älvsb. 1., av lantbr. Josef D. o. Nelly Peterson. G. 19 m. Hanna Persson. Barn: Åke f. 20. — Landsfiskalsex. Landsfiskal i Kungsbacka distr. sed. 41. Led. av stadsfullm. (h) sed. 22, ordf. i drätselkamm. sed. 37, i nykter-h :ndn, i styr. f. A-B Gbgs Banks avd :kont. i Kungsbacka, i länsavd. f. fören. Sv:es landsfiskaler o. i taxmd, led. av länsprövn :ndn 28-42 o. av Fjä-rebygdens vägnd m. m.",
    "translated": "Danielsson, Daniel Ragnar, landsfiskal (a type of senior police officer with specific legal duties), Kungsbacka, born on June 20th, 1888 in Ullasjö, Älvsborgs län, son of farmer Josef D. and Nelly Peterson. Married in 1919 to Hanna Persson and they had a son named Åke, born in 1920. Danielsson has held the position of Landsfiskal in Kungsbacka district since 1941. He has been a member of the city council (h) since 1922, chairman of the finance committee since 1937, in the sobriety commission, in the board of directors for A-B Gbgs Banks branch office in Kungsbacka, in the county branch of the Association of Swedish landsfiskaler, and in the tax commission. He has also been a member of the county appeals court from 1928 to 1942 and of the Fjärebygdens road committee among others.",
    "structured_raw": "{\n  \"@context\": \"https://schema.org\",\n  \"@type\": \"Person\",\n  \"name\": \"Daniel Ragnar Danielsson\",\n  \"birthDate\": \"1888-06-20\",\n  \"birthPlace\": {\n    \"@type\": \"Place\",\n    \"name\": \"Ullasjö, Älvsborgs län\"\n  },\n  \"parents\": [\n    {\n      \"@type\": \"Person\",\n      \"name\": \"Josef D.\"\n    },\n    {\n      \"@type\": \"Person\",\n      \"name\": \"Nelly Peterson\"\n    }\n  ],\n  \"spouse\": {\n    \"@type\": \"Person\",\n    \"name\": \"Hanna Persson\",\n    \"dateOfMarriage\": \"1919\"\n  },\n  \"children\": {\n    \"@type\": \"Person\",\n    \"name\": \"Åke\",\n    \"birthDate\": \"1920\"\n  },\n  \"jobTitle\": \"Landsfiskal\",\n  \"workLocation\": {\n    \"@type\": \"Place\",\n    \"name\": \"Kungsbacka\"\n  },\n  \"startDate\": \"1941\",\n  \"memberOf\": [\n    {\n      \"@type\": \"Organization\",\n      \"name\": \"City Council\",\n      \"startDate\": \"1922\"\n    },\n    {\n      \"@type\": \"Organization\",\n      \"name\": \"Finance Committee\",\n      \"startDate\": \"1937\"\n    },\n    {\n      \"@type\": \"Organization\",\n      \"name\": \"Sobriety Commission\"\n    },\n    {\n      \"@type\": \"Organization\",\n      \"name\": \"Board of Directors for A-B Gbgs Banks branch office in Kungsbacka\"\n    },\n    {\n      \"@type\": \"Organization\",\n      \"name\": \"County branch of the Association of Swedish landsfiskaler\"\n    },\n    {\n      \"@type\": \"Organization\",\n      \"name\": \"Tax Commission\"\n    },\n    {\n      \"@type\": \"Organization\",\n      \"name\": \"County Appeals Court\",\n      \"startDate\": \"1928\",\n      \"endDate\": \"1942\"\n    },\n    {\n      \"@type\": \"Organization\",\n      \"name\": \"Fjärebygdens Road Committee\"\n    }\n  ]\n}",
    "structured": {
        "@context": "https://schema.org",
        "@type": "Person",
        "name": "Daniel Ragnar Danielsson",
        "birthDate": "1888-06-20",
        "birthPlace": {
            "@type": "Place",
            "name": "Ullasjö, Älvsborgs län"
        },
        "parents": [
            {
                "@type": "Person",
                "name": "Josef D."
            },
            {
                "@type": "Person",
                "name": "Nelly Peterson"
            }
        ],
        "spouse": {
            "@type": "Person",
            "name": "Hanna Persson",
            "dateOfMarriage": "1919"
        },
        "children": {
            "@type": "Person",
            "name": "Åke",
            "birthDate": "1920"
        },
        "jobTitle": "Landsfiskal",
        "workLocation": {
            "@type": "Place",
            "name": "Kungsbacka"
        },
        "startDate": "1941",
        "memberOf": [
            {
                "@type": "Organization",
                "name": "City Council",
                "startDate": "1922"
            },
            {
                "@type": "Organization",
                "name": "Finance Committee",
                "startDate": "1937"
            },
            {
                "@type": "Organization",
                "name": "Sobriety Commission"
            },
            {
                "@type": "Organization",
                "name": "Board of Directors for A-B Gbgs Banks branch office in Kungsbacka"
            },
            {
                "@type": "Organization",
                "name": "County branch of the Association of Swedish landsfiskaler"
            },
            {
                "@type": "Organization",
                "name": "Tax Commission"
            },
            {
                "@type": "Organization",
                "name": "County Appeals Court",
                "startDate": "1928",
                "endDate": "1942"
            },
            {
                "@type": "Organization",
                "name": "Fjärebygdens Road Committee"
            }
        ]
    }
}