{
    "original": "Björkman, Astrid Carola, överläkare, Vänersborg, f. 9/1/86 av apot. Karl B. o. Matty Egerström. — Stud:ex. i Sthlm 04, med. fil. ex. i Upps. 06, med. kand. där 10, med. lic. i Sthlm 17. Läk:förordn. v. Upps. epid:sjukh. 12, v. Säters hosp. o. Uddevalla las. samt förordn. s. prov:läk. i Borgholm 17-19, tf. e. o. hosp :läk. v. Lunds hosp. 19-25, hosp :läk. av 2. kl. där 25-27, hosp :läk. av 1 kl. v. Hälsingborgs hosp. 27-30, tf. överläk. v. Källs-hagens sjukh. i Vänersborg 30, över-läk. av 1. kl. o. sjukh :chef där 31-36, dito v. Restads sjukh. i Vänersborg sed. 36. GMiqml 8 st. 45.",
    "translated": "Björkman, Astrid Carola, senior physician, Vänersborg, born January 9th, 1886 to pharmacist Karl B. and Matty Egerström. She completed her studentexamen in Stockholm in 1904, followed by her medical and philosophy degree in Uppsala in 1906, and her medical degree in 1910. She received her medical license in Stockholm in 1917. She served as a medical intern at Uppsala epidemic hospital in 1912, Säters hospital and Uddevalla county hospital, and was appointed as a prosectorial physician in Borgholm from 1917 to 1919. From 1919 to 1925, she was a resident physician at Lund's hospital, after which she was promoted to second-class resident physician from 1925 to 1927. She was then promoted to first-class resident physician at Helsingborg's hospital from 1927 to 1930, and acting senior physician at Källshagens hospital in Vänersborg in 1930. From 1931 to 1936, she served as a senior physician of first class and hospital director at Källshagens hospital, and continued on in this position at Restads hospital in Vänersborg from 1936 onward. She married but the name of her partner and the date of marriage is unknown.",
    "structured_raw": "{\n  \"@context\": \"https://schema.org\",\n  \"@type\": \"Person\",\n  \"name\": \"Astrid Carola Björkman\",\n  \"birthDate\": \"1886-01-09\",\n  \"birthPlace\": \"Vänersborg\",\n  \"spouse\": [\n    {\n      \"@type\": \"Person\",\n      \"name\": \"<UNKNOWN>\"\n    }\n  ],\n  \"jobTitle\": \"Senior Physician\",\n  \"memberOf\": [\n    {\n      \"@type\": \"Organization\",\n      \"name\": \"Uppsala Epidemic Hospital\",\n      \"startDate\": \"1912\",\n      \"endDate\": \"1912\"\n    },\n    {\n      \"@type\": \"Organization\",\n      \"name\": \"Säters Hospital\"\n    },\n    {\n      \"@type\": \"Organization\",\n      \"name\": \"Uddevalla County Hospital\"\n    },\n    {\n      \"@type\": \"Organization\",\n      \"name\": \"Borgholm Hospital\",\n      \"startDate\": \"1917\",\n      \"endDate\": \"1919\"\n    },\n    {\n      \"@type\": \"Organization\",\n      \"name\": \"Lund's Hospital\",\n      \"startDate\": \"1919\",\n      \"endDate\": \"1927\"\n    },\n    {\n      \"@type\": \"Organization\",\n      \"name\": \"Helsingborg's Hospital\",\n      \"startDate\": \"1927\",\n      \"endDate\": \"1930\"\n    },\n    {\n      \"@type\": \"Organization\",\n      \"name\": \"Källshagens Hospital\",\n      \"startDate\": \"1930\",\n      \"endDate\": \"1936\"\n    },\n    {\n      \"@type\": \"Organization\",\n      \"name\": \"Restads Hospital\",\n      \"startDate\": \"1936\"\n    }\n  ],\n  \"education\": [\n    {\n      \"@type\": \"EducationalOccupationalCredential\",\n      \"name\": \"Studentexamen\",\n      \"educationalLevel\": \"Upper Secondary School\",\n      \"awardingInstitution\": \"Stockholm\",\n      \"awardDate\": \"1904\"\n    },\n    {\n      \"@type\": \"EducationalOccupationalCredential\",\n      \"name\": \"Medical and Philosophy Degree\",\n      \"educationalLevel\": \"Higher Education\",\n      \"awardingInstitution\": \"Uppsala\",\n      \"awardDate\": \"1906\"\n    },\n    {\n      \"@type\": \"EducationalOccupationalCredential\",\n      \"name\": \"Medical Degree\",\n      \"educationalLevel\": \"Higher Education\",\n      \"awardingInstitution\": \"Uppsala\",\n      \"awardDate\": \"1910\"\n    },\n    {\n      \"@type\": \"EducationalOccupationalCredential\",\n      \"name\": \"Medical License\",\n      \"educationalLevel\": \"Professional Certification\",\n      \"awardingInstitution\": \"Stockholm\",\n      \"awardDate\": \"1917\"\n    }\n  ]\n}",
    "structured": {
        "@context": "https://schema.org",
        "@type": "Person",
        "name": "Astrid Carola Björkman",
        "birthDate": "1886-01-09",
        "birthPlace": "Vänersborg",
        "spouse": [
            {
                "@type": "Person",
                "name": "<UNKNOWN>"
            }
        ],
        "jobTitle": "Senior Physician",
        "memberOf": [
            {
                "@type": "Organization",
                "name": "Uppsala Epidemic Hospital",
                "startDate": "1912",
                "endDate": "1912"
            },
            {
                "@type": "Organization",
                "name": "Säters Hospital"
            },
            {
                "@type": "Organization",
                "name": "Uddevalla County Hospital"
            },
            {
                "@type": "Organization",
                "name": "Borgholm Hospital",
                "startDate": "1917",
                "endDate": "1919"
            },
            {
                "@type": "Organization",
                "name": "Lund's Hospital",
                "startDate": "1919",
                "endDate": "1927"
            },
            {
                "@type": "Organization",
                "name": "Helsingborg's Hospital",
                "startDate": "1927",
                "endDate": "1930"
            },
            {
                "@type": "Organization",
                "name": "Källshagens Hospital",
                "startDate": "1930",
                "endDate": "1936"
            },
            {
                "@type": "Organization",
                "name": "Restads Hospital",
                "startDate": "1936"
            }
        ],
        "education": [
            {
                "@type": "EducationalOccupationalCredential",
                "name": "Studentexamen",
                "educationalLevel": "Upper Secondary School",
                "awardingInstitution": "Stockholm",
                "awardDate": "1904"
            },
            {
                "@type": "EducationalOccupationalCredential",
                "name": "Medical and Philosophy Degree",
                "educationalLevel": "Higher Education",
                "awardingInstitution": "Uppsala",
                "awardDate": "1906"
            },
            {
                "@type": "EducationalOccupationalCredential",
                "name": "Medical Degree",
                "educationalLevel": "Higher Education",
                "awardingInstitution": "Uppsala",
                "awardDate": "1910"
            },
            {
                "@type": "EducationalOccupationalCredential",
                "name": "Medical License",
                "educationalLevel": "Professional Certification",
                "awardingInstitution": "Stockholm",
                "awardDate": "1917"
            }
        ]
    }
}