{
    "original": "Cederbaum, Per Fredrik Israel, major, Linköping, f. 7/9/82 i Järstad, Östergötl. 1., av godsäg. Conrad C. o. grev:an Ellen Sinclair. G. 1. 15 m. Ellen Wennberg, d. 38; 2. 39 m. Sonja Elfverson. Barn: Pehr-Fredrik f. 19, löjtn. v. Livgren :reg. ■— Mog:ex. i Nyköp. 03, off:ex. 05, AIHS (ak) 13-14, vapenoff :kurs 17. Und:löjtn. v. Södermani. reg. 05, löjtn. 07, kapt. 18, v. Andra divgren :reg. 21, major i armén 33, i res. s. å. Tjg. v. Göta livg. 06 o. 08, reg:adjut. 08-11, andre lär. v. SS 18-19, fransk krigstjg. 19-20, lär. y. kspkurs 20-23 o. ställf. chef 24-26, tjg. i norska armén 27. Ordf. i komm:stämma, v. ordf. i styr. f. östergötl. L. Brandst:bol. m. m. Äger o. bebor Lambohofs säteri. RSO, RVO, RJohO, RNS:t001kl, Södermani. 1. skytteförb. GM, SkytteRM o. M.",
    "translated": "Cederbaum, Per Fredrik Israel was a major from Linköping, born on 7th September 1882 in Järstad, Östergötland, firstborn son of the landowner Conrad C. and the Countess Ellen Sinclair. He married twice, first to Ellen Wennberg in 1915 until her death in 1938, and then to Sonja Elfverson in 1939. He had a son named Pehr-Fredrik who was born in 1919, and who became a lieutenant in the Life Grenadiers Regiment and attended the Military Academy. He also served as a second lieutenant in the Södermanland Regiment in 1905, and later became a captain in 1918 and served in the Second Division Regiment in 1921. He was promoted to major in the army in 1933 and retired in the same year. He served in the Gothenburg Life Guards in 1906 and 1908, was a regimental adjutant from 1908 to 1911, held a position as a lecturer from 1918 to 1919, was part of the French military mission from 1919 to 1920, and served as a lecturer in the Artillery and Engineering School from 1920 to 1923, and as deputy head from 1924 to 1926. He also served in the Norwegian army in 1927. He was the chairman of the municipal council and vice-chairman of the board for the Östergötland Fire Insurance Company, among other positions. He owned and lived on the Lambohof estate and was awarded several honors and medals including the Order of the Sword, the Order of the Polar Star, the Order of John of Jerusalem, the Order of Vasa, and the Medal of the Swedish National Sports Association.",
    "structured_raw": "{\n  \"@context\": \"https://schema.org/\",\n  \"@type\": \"Person\",\n  \"name\": \"Per Fredrik Israel Cederbaum\",\n  \"jobTitle\": \"Major\",\n  \"birthPlace\": \"Järstad, Östergötland, Sweden\",\n  \"birthDate\": \"1882-09-07\",\n  \"deathDate\": \"N/A\",\n  \"parent\": [\n    {\n      \"@type\": \"Person\",\n      \"name\": \"Conrad Cederbaum\",\n      \"jobTitle\": \"Landowner\"\n    },\n    {\n      \"@type\": \"Person\",\n      \"name\": \"Countess Ellen Sinclair\"\n    }\n  ],\n  \"spouse\": [\n    {\n      \"@type\": \"Person\",\n      \"name\": \"Ellen Wennberg\",\n      \"marriageDate\": \"1915\",\n      \"deathDate\": \"1938\"\n    },\n    {\n      \"@type\": \"Person\",\n      \"name\": \"Sonja Elfverson\",\n      \"marriageDate\": \"1939\",\n      \"deathDate\": \"N/A\"\n    }\n  ],\n  \"children\": [\n    {\n      \"@type\": \"Person\",\n      \"name\": \"Pehr-Fredrik Cederbaum\",\n      \"birthDate\": \"1919\",\n      \"jobTitle\": \"Lieutenant\",\n      \"affiliation\": {\n        \"@type\": \"Organization\",\n        \"name\": \"Life Grenadiers Regiment\"\n      },\n      \"education\": {\n        \"@type\": \"EducationalOrganization\",\n        \"name\": \"Military Academy\"\n      }\n    }\n  ],\n  \"affiliation\": [\n    {\n      \"@type\": \"Organization\",\n      \"name\": \"Södermanland Regiment\",\n      \"jobTitle\": \"Second Lieutenant\",\n      \"startDate\": \"1905\",\n      \"endDate\": \"N/A\"\n    },\n    {\n      \"@type\": \"Organization\",\n      \"name\": \"Gothenburg Life Guards\",\n      \"jobTitle\": \"Tjänstgöring\",\n      \"startDate\": \"1906\",\n      \"endDate\": \"1908\"\n    },\n    {\n      \"@type\": \"Organization\",\n      \"name\": \"Life Grenadiers Regiment\",\n      \"jobTitle\": \"Lieutenant\",\n      \"startDate\": \"N/A\",\n      \"endDate\": \"N/A\"\n    },\n    {\n      \"@type\": \"Organization\",\n      \"name\": \"Artillery and Engineering School\",\n      \"jobTitle\": \"Lecturer\",\n      \"startDate\": \"1920\",\n      \"endDate\": \"1923\"\n    }\n  ],\n  \"deathPlace\": null,\n  \"award\": [\n    {\n      \"@type\": \"Order\",\n      \"name\": \"Order of the Sword\"\n    },\n    {\n      \"@type\": \"Order\",\n      \"name\": \"Order of the Polar Star\"\n    },\n    {\n      \"@type\": \"Order\",\n      \"name\": \"Order of John of Jerusalem\"\n    },\n    {\n      \"@type\": \"Order\",\n      \"name\": \"Order of Vasa\"\n    },\n    {\n      \"@type\": \"Medal\",\n      \"name\": \"Medal of the Swedish National Sports Association\"\n    }\n  ],\n  \"memberOf\": [\n    {\n      \"@type\": \"Organization\",\n      \"name\": \"Östergötland Fire Insurance Company\",\n      \"jobTitle\": \"Vice-Chairman\"\n    }\n  ],\n  \"address\": {\n    \"@type\": \"PostalAddress\",\n    \"addressLocality\": \"Lambohof estate\",\n    \"addressCountry\": \"Sweden\"\n  }\n}",
    "structured": {
        "@context": "https://schema.org/",
        "@type": "Person",
        "name": "Per Fredrik Israel Cederbaum",
        "jobTitle": "Major",
        "birthPlace": "Järstad, Östergötland, Sweden",
        "birthDate": "1882-09-07",
        "deathDate": "N/A",
        "parent": [
            {
                "@type": "Person",
                "name": "Conrad Cederbaum",
                "jobTitle": "Landowner"
            },
            {
                "@type": "Person",
                "name": "Countess Ellen Sinclair"
            }
        ],
        "spouse": [
            {
                "@type": "Person",
                "name": "Ellen Wennberg",
                "marriageDate": "1915",
                "deathDate": "1938"
            },
            {
                "@type": "Person",
                "name": "Sonja Elfverson",
                "marriageDate": "1939",
                "deathDate": "N/A"
            }
        ],
        "children": [
            {
                "@type": "Person",
                "name": "Pehr-Fredrik Cederbaum",
                "birthDate": "1919",
                "jobTitle": "Lieutenant",
                "affiliation": {
                    "@type": "Organization",
                    "name": "Life Grenadiers Regiment"
                },
                "education": {
                    "@type": "EducationalOrganization",
                    "name": "Military Academy"
                }
            }
        ],
        "affiliation": [
            {
                "@type": "Organization",
                "name": "Södermanland Regiment",
                "jobTitle": "Second Lieutenant",
                "startDate": "1905",
                "endDate": "N/A"
            },
            {
                "@type": "Organization",
                "name": "Gothenburg Life Guards",
                "jobTitle": "Tjänstgöring",
                "startDate": "1906",
                "endDate": "1908"
            },
            {
                "@type": "Organization",
                "name": "Life Grenadiers Regiment",
                "jobTitle": "Lieutenant",
                "startDate": "N/A",
                "endDate": "N/A"
            },
            {
                "@type": "Organization",
                "name": "Artillery and Engineering School",
                "jobTitle": "Lecturer",
                "startDate": "1920",
                "endDate": "1923"
            }
        ],
        "deathPlace": null,
        "award": [
            {
                "@type": "Order",
                "name": "Order of the Sword"
            },
            {
                "@type": "Order",
                "name": "Order of the Polar Star"
            },
            {
                "@type": "Order",
                "name": "Order of John of Jerusalem"
            },
            {
                "@type": "Order",
                "name": "Order of Vasa"
            },
            {
                "@type": "Medal",
                "name": "Medal of the Swedish National Sports Association"
            }
        ],
        "memberOf": [
            {
                "@type": "Organization",
                "name": "Östergötland Fire Insurance Company",
                "jobTitle": "Vice-Chairman"
            }
        ],
        "address": {
            "@type": "PostalAddress",
            "addressLocality": "Lambohof estate",
            "addressCountry": "Sweden"
        }
    }
}