{
    "original": "Matthias Natanael (Natan), lektor, Växjö, f. 30/5/98 i Asarum, Blek. il. G. 1. 27-33 m. Sys Poulsen; 2. 36 m. Lita Walilin. Barn: Jan f. 29, Lena 36, Klas 37, Stefan 44. — Fil. kand. i Lund 21, fil. mag. 22, fil. lic. 28, fil. dr 30, promov. 31. Assist, v. Asinegrävn. 24-26, uti. medl. av École frang. d’Athènes 25-27, sekr. v. sv. in st. i Rom 27, stud. v. Köpeng-hamns univ. 29-30, lett egna utgrävn. i Messenien i GreM. 26-37, stud :res. i Grdkl., Ital.,, Jugoslav., Alban., Egypt., Palest., Syrien, Tyskl., Österr., Ung., Frankr., Holll. 24-47. Doc. v. Lunds univ. 30-40, tf. prof. där 30, 3(2, 36-40, v. Gbgs högsk. 32, 36, 34, ileiktor i Hudiksvall 40-45, i andra för si :rumm. t. prof. i Lund 39, lektor v. h. a. 1. i Växjö ’fr. 45. Byggt o. ordn. museet i Vasiliko i Grekl. 33-35. Ordf. i klass, fil. fören. i Lund 30-36, init :taig. t. hemvärnen i Slkåne 40, ordf. i Hudiksvalls hemv:,fören. 40-45, start, human, fören. dlär 43, sekr. 43-45, medl. av vetensk :so€. i Lund 36^ korr. miedl. av Deutsch. arch. Inst. 37, medl. av ’koimm. f. siv. inst. i Aten 46. Skr.: Karlshamn-Asarum (23), Études topoigrapb. sur la Messenie anc. (30), Aten gen. tiderna (311),, A la grecque (32), Dagl. liv i det gamla Aten (34, dansk uppl. 35), Arb. o. slaveri i antiken (37), Det mod. Grekl. (317), Demokr. i d. gamla Aten (39), The Sw^ed. Messenie Exp. (38), Fouillies de Ddphes III :VI (teat:inskr. 39’), d. adriat. Geb. etc. (39), Hellensk horisont (41), Alex. d. store (42, dansk uppl. 43), Hannibal (44, dansk uppl. 46), Vid vinrött hav (44), Det dor. probil. (45), Demos-thenes (46), ett 20-tal vetensk. art., ett 40-tal pop :vetensk. tidskr :upps., med-arb. i Sv. uppsl:boik o. i in- o. uti. dagspress. Hobbies: landsikapsmåln., frimärkssaml. O^ffGrGO 36, KGrFenO 47, hed:borgare i Vasiliko i Grekl. 33, Hemv. ftj :plak. i guld 42. , Axel Ruben Natanael, tand|läkare, Sölvesiborg, f. 8/1/87 i Hässlehol|m av falbr. Axel Israeil W. 0. Maria Andersson. G. 13 m. Jenny Wessiberg. Barn: Aino f. M, d. K, Margaretha 15, Carl-Gustav 17„ Carl-Axel 18, Börje 20, Birgitta 22, d. 29, Gudrun 24. — Mogiex. i Krisitianst. 06, tandlikand. 09, tandliäk. 11. Ban’k-t j: man 06-08., tandil: p rakt. i Sö 1 ve sib. sed. Ifl, skoiltandl. där 29’-44. Styr:-led. i Bilek. tandl :fören. 28-311, v. ordf. 3!l-3i6 o. ordf. 36-46. Led. av ifoltksk:-styr. samt styr. f. Sölvesb, Spritför-säljn. A-B fr. 28. Stud:resa t. Tyskl.. 15.",
    "translated": "Matthias Natanael (Natan), lecturer, Växjö, b. 30/5/98 in Asarum, Blekinge county. Married 1. in 1927 to Sys Poulsen; 2. in 1936 to Lita Walilin. Children: Jan b. 1929, Lena b. 1936, Klas b. 1937, Stefan b. 1944. - Bachelor of Arts in Lund in 1921, Master of Arts in 1922, Licentiate of Philosophy in 1928, Doctor of Philosophy in 1930, promoted in 1931. Assistant at Asine excavation in 1924-1926, external member at École française d'Athènes in 1925-1927, secretary at the Swedish Institute in Rome in 1927, student at the University of Copenhagen in 1929-1930, led own excavations in Messenia in Greece in 1926-1937, studied in Greece, Italy, Yugoslavia, Albania, Egypt, Palestine, Syria, Germany, Austria, Hungary, France, and the Netherlands in 1924-1947. Lecturer at Lund University in 1930-1940, acting professor there in 1930-1932, 1936-1940, at Gothenburg University in 1932, 1936, 1934, lecturer in Hudiksvall in 1940-1945, professor in Lund from 1939, lecturer at the Teacher's Training College in Växjö from 1945. Built and organized the museum in Vasiliko in Greece from 1933-1935. Chairman of the Faculty of Philosophy society in Lund from 1930-1936, initiated the home guard in Skåne in 1940, chairman of the Hudiksvalls home guard association from 1940-1945, started the humanistic society's library in 1943, secretary from 1943-1945, member of the Royal Society of Sciences in Lund from 1936, corresponding member of the German Archaeological Institute in 1937, member of the Commission for Civil Institutions in Athens in 1946. Works: Karlshamn-Asarum (1923), Topographical Studies on Ancient Messenia (1930), Athens in ancient times (1931), A la grecque (1932), Daily life in ancient Athens (1934, Danish edition in 1935), Work and Slavery in Antiquity (1937), Modern Greece (1937), Democracy in ancient Athens (1939), The Swedish Messenia Expedition (1938), Excavations at Delphi III:VI (inscriptions in theaters, 1939), The Adriatic Area etc. (1939), Hellenistic horizon (1941), Alexander the Great (1942, Danish edition in 1943), Hannibal (1944, Danish edition in 1946), By the wine-red sea (1944), The Doric problem (1945), Demosthenes (1946), around 20 scientific articles, around 40 popular scientific journal articles, co-author of the Swedish Encyclopedia and in national and international daily press. Hobbies: landscape painting, stamp collecting. Knight of the Order of Vasa in 1936, Commander of the Order of the North Star in 1947, honorary citizen of Vasiliko in Greece in 1933, Home Guard's gold plaque in 1942. Axel Ruben Natanael, dentist, Sölvesborg, b. 8/1/87 in Hässleholm, son of falbr. Axel Israel W. 0. Maria Andersson. Married in 1913 to Jenny Wessiberg. Children: Aino b. 1914, died in 1918. Margaretha b. 1915, Carl-Gustav b. 1917, Carl-Axel b. 1918, Börje b. 1920, Birgitta b. 1922, died in 1929, Gudrun b. 1924. - Graduated from Christianstad in 1906, dentistry degree in 1909, dentist in 1911. Bank clerk in 1906-1908, dental practitioner in Sölvesborg since 1911, school dentist there in 1929-1944. Board member of the Swedish Dental Association in 1928-1931, vice chairman in 1931-1936 and chairman in 1936-1946. Member of the county board of health and the board of Sölvesborg Spirits Limited since 1928. Studied in Germany in 1915.",
    "structured_raw": "{\n  \"@context\": \"https://schema.org\",\n  \"@type\": \"Person\",\n  \"name\": \"Matthias Natanael\",\n  \"givenName\": \"Matthias\",\n  \"additionalName\": \"Natan\",\n  \"familyName\": \"Natanael\",\n  \"birthDate\": \"1898-05-30\",\n  \"birthPlace\": {\n    \"@type\": \"Place\",\n    \"name\": \"Asarum, Blekinge county\"\n  },\n  \"jobTitle\": \"Lecturer\",\n  \"worksFor\": {\n    \"@type\": \"Organization\",\n    \"name\": \"Växjö\"\n  },\n  \"spouse\": [\n    {\n      \"@type\": \"Person\",\n      \"name\": \"Sys Poulsen\",\n      \"startDate\": \"1927\",\n      \"endDate\": \"1933\"\n    },\n    {\n      \"@type\": \"Person\",\n      \"name\": \"Lita Walilin\",\n      \"startDate\": \"1936\"\n    }\n  ],\n  \"children\": [\n    {\n      \"@type\": \"Person\",\n      \"name\": \"Jan\",\n      \"birthDate\": \"1929\"\n    },\n    {\n      \"@type\": \"Person\",\n      \"name\": \"Lena\",\n      \"birthDate\": \"1936\"\n    },\n    {\n      \"@type\": \"Person\",\n      \"name\": \"Klas\",\n      \"birthDate\": \"1937\"\n    },\n    {\n      \"@type\": \"Person\",\n      \"name\": \"Stefan\",\n      \"birthDate\": \"1944\"\n    }\n  ],\n  \"education\": [\n    {\n      \"@type\": \"EducationalOccupationalCredential\",\n      \"educationalLevel\": \"Bachelor\",\n      \"educationalDegree\": \"Fil. kand.\",\n      \"educationalInstitution\": \"Lund University\",\n      \"awardDate\": \"1921\"\n    },\n    {\n      \"@type\": \"EducationalOccupationalCredential\",\n      \"educationalLevel\": \"Master\",\n      \"educationalDegree\": \"Fil. mag.\",\n      \"educationalInstitution\": \"Lund University\",\n      \"awardDate\": \"1922\"\n    },\n    {\n      \"@type\": \"EducationalOccupationalCredential\",\n      \"educationalLevel\": \"Licentiate\",\n      \"educationalDegree\": \"Fil. lic.\",\n      \"educationalInstitution\": \"Lund University\",\n      \"awardDate\": \"1928\"\n    },\n    {\n      \"@type\": \"EducationalOccupationalCredential\",\n      \"educationalLevel\": \"Doctorate\",\n      \"educationalDegree\": \"Fil. dr\",\n      \"educationalInstitution\": \"Lund University\",\n      \"awardDate\": \"1930\"\n    },\n    {\n      \"@type\": \"EducationalOccupationalCredential\",\n      \"educationalDegree\": \"Promotion\",\n      \"educationalInstitution\": \"Lund University\",\n      \"awardDate\": \"1931\"\n    }\n  ],\n  \"employmentHistory\": [\n    {\n      \"@type\": \"OrganizationRole\",\n      \"startDate\": \"1924\",\n      \"endDate\": \"1926\",\n      \"roleName\": \"Assistant\",\n      \"organization\": {\n        \"@type\": \"Organization\",\n        \"name\": \"Asinegravn.\"\n      }\n    },\n    {\n      \"@type\": \"OrganizationRole\",\n      \"startDate\": \"1925\",\n      \"endDate\": \"1927\",\n      \"roleName\": \"External Member\",\n      \"organization\": {\n        \"@type\": \"Organization\",\n        \"name\": \"École française d'Athènes\"\n      }\n    },\n    {\n      \"@type\": \"OrganizationRole\",\n      \"startDate\": \"1927\",\n      \"endDate\": \"1927\",\n      \"roleName\": \"Secretary\",\n      \"organization\": {\n        \"@type\": \"Organization\",\n        \"name\": \"Swedish Institute in Rome\"\n      }\n    },\n    {\n      \"@type\": \"OrganizationRole\",\n      \"startDate\": \"1929\",\n      \"endDate\": \"1930\",\n      \"roleName\": \"Student\",\n      \"organization\": {\n        \"@type\": \"Organization\",\n        \"name\": \"University of Copenhagen\"\n      }\n    },\n    {\n      \"@type\": \"OrganizationRole\",\n      \"startDate\": \"1940\",\n      \"endDate\": \"1945\",\n      \"roleName\": \"Lecturer\",\n      \"organization\": {\n        \"@type\": \"Organization\",\n        \"name\": \"Hudiksvall\"\n      }\n    },\n    {\n      \"@type\": \"OrganizationRole\",\n      \"startDate\": \"1945\",\n      \"roleName\": \"Lecturer\",\n      \"organization\": {\n        \"@type\": \"Organization\",\n        \"name\": \"Teacher's Training College in Växjö\"\n      }\n    }\n  ],\n  \"memberOf\": [\n    {\n      \"@type\": \"Organization\",\n      \"name\": \"Lund University\",\n      \"membershipStartDate\": \"1930\",\n      \"membershipEndDate\": \"1940\"\n    },\n    {\n      \"@type\": \"Organization\",\n      \"name\": \"Gothenburg University\",\n      \"membershipStartDate\": \"1932\",\n      \"membershipEndDate\": \"1932\"\n    }\n  ],\n  \"creativeWorks\": [\n    {\n      \"@type\": \"Book\",\n      \"name\": \"Karlshamn-Asarum\",\n      \"datePublished\": \"1923\"\n    },\n    {\n      \"@type\": \"Book\",\n      \"name\": \"Topographical Studies on Ancient Messenia\",\n      \"datePublished\": \"1930\"\n    },\n    {\n      \"@type\": \"Book\",\n      \"name\": \"Athens in ancient times\",\n      \"datePublished\": \"1931\"\n    },\n    {\n      \"@type\": \"Book\",\n      \"name\": \"A la grecque\",\n      \"datePublished\": \"1932\"\n    },\n    {\n      \"@type\": \"Book\",\n      \"name\": \"Daily life in ancient Athens\",\n      \"datePublished\": \"1934\",\n      \"edition\": \"Danish\",\n      \"editionDate\": \"1935\"\n    },\n    {\n      \"@type\": \"Book\",\n      \"name\": \"Work and Slavery in Antiquity\",\n      \"datePublished\": \"1937\"\n    },\n    {\n      \"@type\": \"Book\",\n      \"name\": \"Modern Greece\",\n      \"datePublished\": \"1937\"\n    },\n    {\n      \"@type\": \"Book\",\n      \"name\": \"Democracy in ancient Athens\",\n      \"datePublished\": \"1939\"\n    },\n    {\n      \"@type\": \"Book\",\n      \"name\": \"The Swedish Messenia Expedition\",\n      \"datePublished\": \"1938\"\n    },\n    {\n      \"@type\": \"Book\",\n      \"name\": \"Excavations at Delphi III:VI\",\n      \"subTitle\": \"Inscriptions in theaters\",\n      \"datePublished\": \"1939\"\n    },\n    {\n      \"@type\": \"Book\",\n      \"name\": \"The Adriatic Area etc.\",\n      \"datePublished\": \"1939\"\n    },\n    {\n      \"@type\": \"Book\",\n      \"name\": \"Hellenistic horizon\",\n      \"datePublished\": \"1941\"\n    },\n    {\n      \"@type\": \"Book\",\n      \"name\": \"Alexander the Great\",\n      \"datePublished\": \"1942\",\n      \"edition\": \"Danish\",\n      \"editionDate\": \"1943\"\n    },\n    {\n      \"@type\": \"Book\",\n      \"name\": \"Hannibal\",\n      \"datePublished\": \"1944\",\n      \"edition\": \"Danish\",\n      \"editionDate\": \"1946\"\n    },\n    {\n      \"@type\": \"Book\",\n      \"name\": \"By the wine-red sea\",\n      \"datePublished\": \"1944\"\n    },\n    {\n      \"@type\": \"Book\",\n      \"name\": \"The Doric problem\",\n      \"datePublished\": \"1945\"\n    },\n    {\n      \"@type\": \"Book\",\n      \"name\": \"Demosthenes\",\n      \"datePublished\": \"1946\"\n    }\n  ],\n  \"hobbies\": [\n    \"Landscape painting\",\n    \"Stamp collecting\"\n  ],\n  \"awards\": [\n    {\n      \"@type\": \"Order\",\n      \"name\": \"Order of Vasa\",\n      \"awardDate\": \"1936\",\n      \"description\": \"Knight\"\n    },\n    {\n      \"@type\": \"Order\",\n      \"name\": \"Order of the North Star\",\n      \"awardDate\": \"1947\",\n      \"description\": \"Commander\"\n    }\n  ]\n}\n",
    "structured": {
        "@context": "https://schema.org",
        "@type": "Person",
        "name": "Matthias Natanael",
        "givenName": "Matthias",
        "additionalName": "Natan",
        "familyName": "Natanael",
        "birthDate": "1898-05-30",
        "birthPlace": {
            "@type": "Place",
            "name": "Asarum, Blekinge county"
        },
        "jobTitle": "Lecturer",
        "worksFor": {
            "@type": "Organization",
            "name": "Växjö"
        },
        "spouse": [
            {
                "@type": "Person",
                "name": "Sys Poulsen",
                "startDate": "1927",
                "endDate": "1933"
            },
            {
                "@type": "Person",
                "name": "Lita Walilin",
                "startDate": "1936"
            }
        ],
        "children": [
            {
                "@type": "Person",
                "name": "Jan",
                "birthDate": "1929"
            },
            {
                "@type": "Person",
                "name": "Lena",
                "birthDate": "1936"
            },
            {
                "@type": "Person",
                "name": "Klas",
                "birthDate": "1937"
            },
            {
                "@type": "Person",
                "name": "Stefan",
                "birthDate": "1944"
            }
        ],
        "education": [
            {
                "@type": "EducationalOccupationalCredential",
                "educationalLevel": "Bachelor",
                "educationalDegree": "Fil. kand.",
                "educationalInstitution": "Lund University",
                "awardDate": "1921"
            },
            {
                "@type": "EducationalOccupationalCredential",
                "educationalLevel": "Master",
                "educationalDegree": "Fil. mag.",
                "educationalInstitution": "Lund University",
                "awardDate": "1922"
            },
            {
                "@type": "EducationalOccupationalCredential",
                "educationalLevel": "Licentiate",
                "educationalDegree": "Fil. lic.",
                "educationalInstitution": "Lund University",
                "awardDate": "1928"
            },
            {
                "@type": "EducationalOccupationalCredential",
                "educationalLevel": "Doctorate",
                "educationalDegree": "Fil. dr",
                "educationalInstitution": "Lund University",
                "awardDate": "1930"
            },
            {
                "@type": "EducationalOccupationalCredential",
                "educationalDegree": "Promotion",
                "educationalInstitution": "Lund University",
                "awardDate": "1931"
            }
        ],
        "employmentHistory": [
            {
                "@type": "OrganizationRole",
                "startDate": "1924",
                "endDate": "1926",
                "roleName": "Assistant",
                "organization": {
                    "@type": "Organization",
                    "name": "Asinegravn."
                }
            },
            {
                "@type": "OrganizationRole",
                "startDate": "1925",
                "endDate": "1927",
                "roleName": "External Member",
                "organization": {
                    "@type": "Organization",
                    "name": "École française d'Athènes"
                }
            },
            {
                "@type": "OrganizationRole",
                "startDate": "1927",
                "endDate": "1927",
                "roleName": "Secretary",
                "organization": {
                    "@type": "Organization",
                    "name": "Swedish Institute in Rome"
                }
            },
            {
                "@type": "OrganizationRole",
                "startDate": "1929",
                "endDate": "1930",
                "roleName": "Student",
                "organization": {
                    "@type": "Organization",
                    "name": "University of Copenhagen"
                }
            },
            {
                "@type": "OrganizationRole",
                "startDate": "1940",
                "endDate": "1945",
                "roleName": "Lecturer",
                "organization": {
                    "@type": "Organization",
                    "name": "Hudiksvall"
                }
            },
            {
                "@type": "OrganizationRole",
                "startDate": "1945",
                "roleName": "Lecturer",
                "organization": {
                    "@type": "Organization",
                    "name": "Teacher's Training College in Växjö"
                }
            }
        ],
        "memberOf": [
            {
                "@type": "Organization",
                "name": "Lund University",
                "membershipStartDate": "1930",
                "membershipEndDate": "1940"
            },
            {
                "@type": "Organization",
                "name": "Gothenburg University",
                "membershipStartDate": "1932",
                "membershipEndDate": "1932"
            }
        ],
        "creativeWorks": [
            {
                "@type": "Book",
                "name": "Karlshamn-Asarum",
                "datePublished": "1923"
            },
            {
                "@type": "Book",
                "name": "Topographical Studies on Ancient Messenia",
                "datePublished": "1930"
            },
            {
                "@type": "Book",
                "name": "Athens in ancient times",
                "datePublished": "1931"
            },
            {
                "@type": "Book",
                "name": "A la grecque",
                "datePublished": "1932"
            },
            {
                "@type": "Book",
                "name": "Daily life in ancient Athens",
                "datePublished": "1934",
                "edition": "Danish",
                "editionDate": "1935"
            },
            {
                "@type": "Book",
                "name": "Work and Slavery in Antiquity",
                "datePublished": "1937"
            },
            {
                "@type": "Book",
                "name": "Modern Greece",
                "datePublished": "1937"
            },
            {
                "@type": "Book",
                "name": "Democracy in ancient Athens",
                "datePublished": "1939"
            },
            {
                "@type": "Book",
                "name": "The Swedish Messenia Expedition",
                "datePublished": "1938"
            },
            {
                "@type": "Book",
                "name": "Excavations at Delphi III:VI",
                "subTitle": "Inscriptions in theaters",
                "datePublished": "1939"
            },
            {
                "@type": "Book",
                "name": "The Adriatic Area etc.",
                "datePublished": "1939"
            },
            {
                "@type": "Book",
                "name": "Hellenistic horizon",
                "datePublished": "1941"
            },
            {
                "@type": "Book",
                "name": "Alexander the Great",
                "datePublished": "1942",
                "edition": "Danish",
                "editionDate": "1943"
            },
            {
                "@type": "Book",
                "name": "Hannibal",
                "datePublished": "1944",
                "edition": "Danish",
                "editionDate": "1946"
            },
            {
                "@type": "Book",
                "name": "By the wine-red sea",
                "datePublished": "1944"
            },
            {
                "@type": "Book",
                "name": "The Doric problem",
                "datePublished": "1945"
            },
            {
                "@type": "Book",
                "name": "Demosthenes",
                "datePublished": "1946"
            }
        ],
        "hobbies": [
            "Landscape painting",
            "Stamp collecting"
        ],
        "awards": [
            {
                "@type": "Order",
                "name": "Order of Vasa",
                "awardDate": "1936",
                "description": "Knight"
            },
            {
                "@type": "Order",
                "name": "Order of the North Star",
                "awardDate": "1947",
                "description": "Commander"
            }
        ]
    }
}