{
    "original": "Johansson, Johan Viktor, fil. dr, förste bibliotekarie, sekreterare, Göteborg, f. 22/12/88 i Hammar, Örebro 1., av insp. Gustaf J. o. Hilma Carlström. G. 1. 15-22 m. Signe Bruno; 2. 23 m. Märta Wåhlin. Barn: Klas f. 16, jur. kand. Mats 25, fri. stud., Siv 28. — Mogrex. 08, fil. kand. i Gbg 13, fil. lic. 19, fil. dr 27. E. o. aman. v. Gbgs stadsbibi. 15, aman. där 16, andre bibi. 19, förste dito sed. 30. Aman. v. Gbgs högsk. exped. 17, högsk. sekr. 22, tf. sekr. v. Gbgs handrhögsk. 23-28, sekr. i VVS 38, led. av o. sekr. i styr. f. Oceanograf. inst. i Gbg 38 o. komm. f. den med. und :visn. v. Gbgs högsk. 40. Skr.: Den förromant. balladen i Sv:e (12), Gbgs högsk. matrikel 91-16 (tills. m. L. Wåhlin 16), Études sur Denis Diderot (27), Extra Posten 1792-95 1-2 (36), Vem var sign. von K? (36), Gbgs högsk. fonder (39), Va-riantex. av Stiernhielms Ulfilas-ed. (39), Gbgs stadsbibi. handskr :saml. (41), Minnestal hållna i Gbgs vet skåps- o. vitterhetssamh. 38-42 (42), Verner von Heidenstam (43), Försvar f. boksamlaren (43), Snoilsky som bib-liofil (45), Katalog över Gbgs stadsbibi. Viktor Rydbergs-utställn. (45), Torgny Segerstedt (46), Variantex. o. tryckteknik (47), art. o. rec., bidr. t. Sv. biogr. lex. m. m., redig. o. utg. bl. a. Bokvandningar (45), Svenska bibiioteik (46), J. A. Wadman, Valda dikter (46). Hobby: boksamlande. RNO, RVO, LVVS.",
    "translated": "Johansson, Johan Viktor, PhD, First Librarian, Secretary, Gothenburg, born December 22, 1888, in Hammar, Örebro county, son of inspector Gustaf J. and Hilma Carlström. Married 1st to Signe Bruno (1915-1922); 2nd to Märta Wåhlin in 1923. Children: Klas (born 1916), Mats (born 1925), and Siv (born 1928). Completed his Bachelor of Arts degree in 1908, Bachelor of Philosophy at University of Gothenburg in 1913, Licentiate of Philosophy in 1919, and Doctorate of Philosophy in 1927. Assisted librarian at Gothenburg city library in 1915 and became a librarian in 1916. In 1919 became the second librarian and in 1930 became the first librarian. Also served as assistant secretary at the University of Gothenburg in 1917 and was appointed secretary in 1922, temporarily serving as secretary of the Gothenburg School of Business from 1923 to 1928. Secretary of The learned Society of Gothenburg in 1938, and member and secretary of the Board of the Oceanographic Institute in Gothenburg in 1938 and the medical under: orship committee of the University of Gothenburg in 1940. Author of \"The Pre-Romantic Ballad in Sweden\" (1912), \"University of Gothenburg Register 1891-1916\" (1916) with L. Wåhlin, \"Studies on Denis Diderot\" (1927), \"Extra Posten 1792-95 1-2\" (1936), \"Who was Sign. von K?\" (1936), \"University of Gothenburg Funds\" (1939), \"Variantex. of Stiernhielm's Ulfilas Edition\" (1939), \"Gothenburg City Library Manuscript Collection\" (1941), \"Memorial Speeches Held in the Learned Society of Gothenburg and the Society of Literature and Knowledge in 1938-1942\" (1942), \"Verner von Heidenstam\" (1943), \"Defense for the Book Collector\" (1943), \"Snoilsky as a Book Collector\" (1945), \"Catalog of Gothenburg City Library Viktor Rydberg Exhibition\" (1945), \"Torgny Segerstedt\" (1946), \"Variantex and Printing Techniques\" (1947), articles, reviews, contributions to the Swedish Biographical Dictionary, etc., edited and published, among others, \"Bokvandningar\" (1945) and \"Svenska Bibliotek\" (1946), J.A. Wadman, Selected Poems (1946). Hobby: book collecting. Awards: Royal Order of the North Star, Royal Order of Vasa, and member of the learned Society of Gothenburg.",
    "structured_raw": "{\n    \"@context\": \"http://schema.org\",\n    \"@type\": \"Person\",\n    \"name\": \"Johan Viktor Johansson\",\n    \"birthDate\": \"1888-12-22\",\n    \"birthPlace\": {\n        \"@type\": \"Place\",\n        \"name\": \"Hammar, Örebro county\"\n    },\n    \"parents\": [\n        {\n            \"@type\": \"Person\",\n            \"name\": \"Gustaf J. Johansson\"\n        },\n        {\n            \"@type\": \"Person\",\n            \"name\": \"Hilma Carlström\"\n        }\n    ],\n    \"spouse\": [\n        {\n            \"@type\": \"Person\",\n            \"name\": \"Signe Bruno\",\n            \"marriageDate\": \"1915\"\n        },\n        {\n            \"@type\": \"Person\",\n            \"name\": \"Märta Wåhlin\",\n            \"marriageDate\": \"1923\"\n        }\n    ],\n    \"children\": [\n        {\n            \"@type\": \"Person\",\n            \"name\": \"Klas Johansson\",\n            \"birthDate\": \"1916\"\n        },\n        {\n            \"@type\": \"Person\",\n            \"name\": \"Mats Johansson\",\n            \"birthDate\": \"1925\"\n        },\n        {\n            \"@type\": \"Person\",\n            \"name\": \"Siv Johansson\",\n            \"birthDate\": \"1928\"\n        }\n    ],\n    \"jobTitle\": [\n        \"PhD\",\n        \"First Librarian\",\n        \"Secretary\"\n    ],\n    \"workLocation\": \"Gothenburg\",\n    \"alumniOf\": [\n        {\n            \"@type\": \"CollegeOrUniversity\",\n            \"name\": \"University of Gothenburg\",\n            \"degree\": {\n                \"@type\": \"BachelorsDegree\",\n                \"name\": \"Bachelor of Arts\",\n                \"dateReceived\": \"1908\"\n            }\n        },\n        {\n            \"@type\": \"CollegeOrUniversity\",\n            \"name\": \"University of Gothenburg\",\n            \"degree\": {\n                \"@type\": \"BachelorDegree\",\n                \"name\": \"Bachelor of Philosophy\",\n                \"dateReceived\": \"1913\"\n            }\n        },\n        {\n            \"@type\": \"CollegeOrUniversity\",\n            \"name\": \"University of Gothenburg\",\n            \"degree\": {\n                \"@type\": \"LicentiateDegree\",\n                \"name\": \"Licentiate of Philosophy\",\n                \"dateReceived\": \"1919\"\n            }\n        },\n        {\n            \"@type\": \"CollegeOrUniversity\",\n            \"name\": \"University of Gothenburg\",\n            \"degree\": {\n                \"@type\": \"DoctoralDegree\",\n                \"name\": \"Doctorate of Philosophy\",\n                \"dateReceived\": \"1927\"\n            }\n        }\n    ],\n    \"memberOf\": [\n        {\n            \"@type\": \"Organization\",\n            \"name\": \"Gothenburg City Library\",\n            \"jobTitle\": \"Assistant Librarian\",\n            \"startDate\": \"1915\"\n        },\n        {\n            \"@type\": \"Organization\",\n            \"name\": \"University of Gothenburg\",\n            \"jobTitle\": \"Assistant Secretary\",\n            \"startDate\": \"1917\"\n        },\n        {\n            \"@type\": \"Organization\",\n            \"name\": \"Gothenburg School of Business\",\n            \"jobTitle\": \"Temporary Secretary\",\n            \"startDate\": \"1923\",\n            \"endDate\": \"1928\"\n        },\n        {\n            \"@type\": \"Organization\",\n            \"name\": \"The Learned Society of Gothenburg\",\n            \"jobTitle\": \"Secretary\",\n            \"startDate\": \"1938\"\n        },\n        {\n            \"@type\": \"Organization\",\n            \"name\": \"Board of the Oceanographic Institute in Gothenburg\",\n            \"jobTitle\": \"Secretary\",\n            \"startDate\": \"1938\"\n        },\n        {\n            \"@type\": \"Organization\",\n            \"name\": \"Medical Under: orship Committee of the University of Gothenburg\",\n            \"jobTitle\": \"Member and Secretary\",\n            \"startDate\": \"1940\"\n        }\n    ],\n    \"deathDate\": null,\n    \"sameAs\": [\n        {\n            \"@type\": \"URL\",\n            \"url\": \"https://www.wikidata.org/wiki/Q3280596\"\n        }\n    ],\n    \"description\": \"Johan Viktor Johansson (1888–) was a Swedish author and librarian.\"\n}",
    "structured": {
        "@context": "http://schema.org",
        "@type": "Person",
        "name": "Johan Viktor Johansson",
        "birthDate": "1888-12-22",
        "birthPlace": {
            "@type": "Place",
            "name": "Hammar, Örebro county"
        },
        "parents": [
            {
                "@type": "Person",
                "name": "Gustaf J. Johansson"
            },
            {
                "@type": "Person",
                "name": "Hilma Carlström"
            }
        ],
        "spouse": [
            {
                "@type": "Person",
                "name": "Signe Bruno",
                "marriageDate": "1915"
            },
            {
                "@type": "Person",
                "name": "Märta Wåhlin",
                "marriageDate": "1923"
            }
        ],
        "children": [
            {
                "@type": "Person",
                "name": "Klas Johansson",
                "birthDate": "1916"
            },
            {
                "@type": "Person",
                "name": "Mats Johansson",
                "birthDate": "1925"
            },
            {
                "@type": "Person",
                "name": "Siv Johansson",
                "birthDate": "1928"
            }
        ],
        "jobTitle": [
            "PhD",
            "First Librarian",
            "Secretary"
        ],
        "workLocation": "Gothenburg",
        "alumniOf": [
            {
                "@type": "CollegeOrUniversity",
                "name": "University of Gothenburg",
                "degree": {
                    "@type": "BachelorsDegree",
                    "name": "Bachelor of Arts",
                    "dateReceived": "1908"
                }
            },
            {
                "@type": "CollegeOrUniversity",
                "name": "University of Gothenburg",
                "degree": {
                    "@type": "BachelorDegree",
                    "name": "Bachelor of Philosophy",
                    "dateReceived": "1913"
                }
            },
            {
                "@type": "CollegeOrUniversity",
                "name": "University of Gothenburg",
                "degree": {
                    "@type": "LicentiateDegree",
                    "name": "Licentiate of Philosophy",
                    "dateReceived": "1919"
                }
            },
            {
                "@type": "CollegeOrUniversity",
                "name": "University of Gothenburg",
                "degree": {
                    "@type": "DoctoralDegree",
                    "name": "Doctorate of Philosophy",
                    "dateReceived": "1927"
                }
            }
        ],
        "memberOf": [
            {
                "@type": "Organization",
                "name": "Gothenburg City Library",
                "jobTitle": "Assistant Librarian",
                "startDate": "1915"
            },
            {
                "@type": "Organization",
                "name": "University of Gothenburg",
                "jobTitle": "Assistant Secretary",
                "startDate": "1917"
            },
            {
                "@type": "Organization",
                "name": "Gothenburg School of Business",
                "jobTitle": "Temporary Secretary",
                "startDate": "1923",
                "endDate": "1928"
            },
            {
                "@type": "Organization",
                "name": "The Learned Society of Gothenburg",
                "jobTitle": "Secretary",
                "startDate": "1938"
            },
            {
                "@type": "Organization",
                "name": "Board of the Oceanographic Institute in Gothenburg",
                "jobTitle": "Secretary",
                "startDate": "1938"
            },
            {
                "@type": "Organization",
                "name": "Medical Under: orship Committee of the University of Gothenburg",
                "jobTitle": "Member and Secretary",
                "startDate": "1940"
            }
        ],
        "deathDate": null,
        "sameAs": [
            {
                "@type": "URL",
                "url": "https://www.wikidata.org/wiki/Q3280596"
            }
        ],
        "description": "Johan Viktor Johansson (1888–) was a Swedish author and librarian."
    }
}