{
    "original": "Ehrensvärd, Gösta Carl Albert, greve, konteramiral, Karlskrona, f. 10/2/ 85 i Skabersjö, Malmöh. 1., av amiralen, greve Carl Aug. E. o. frih :an Ulla Thott. G. 09 m. Anna Enell. Barn: Gösta f. 10, fil. dr, g. m. Inga-Lill Rydh, Carl August 13, kapt. v. filo’ttan, g. m. Eva Morddng, Ulilia 18, g. m. kapt. G. Murray. — Sjö-kadett 98, sjöoff:ex. 04, KSHS 08- 09, KSHS hk 10-11. Und itöjtn. v. flottan 04, löjtn. 06, kapt. 13, kom-mendörkapt. 22, kommendör 33, kon-teramiral 38. Lär v. KSHS 18-22, chef f. jagrdiv. 19 o. 23-24, f. marinstab. kommunik :avd. 27-29, å pansarskepp. Oscar II 29, f. marinstab. operationsavd. 29-32, å pansarskeppet Drottn. Victoria 32-33, flaggkapt. i chef. f. kustflottan stab 33-36, chef f. marinstab. 37-39, f. kns-tflottan 39-42, befälh. amiral o. chef f. Sydkustens marindis’tr. sed. 42. Led. av 30 års för.siv :kiomim. 30-32. Re-d. f. Tidsikr. i Sjöväsendet 25-27. KmstkSO, RNO, RVO, KDDOlgr, KFinlVRO, KNS :t-OO, KPoilRest2kl, KSpMerNavOlkl, RLtiKrO, RRS :itSit03kl, TM04 kil, SV-KGM, Danisik FrM, LKrVA, HedLÖS.",
    "translated": "Ehrensvärd, Gösta Carl Albert, Count, Rear Admiral, Karlskrona, b. February 10, 1885 in Skabersjö, Malmöhus. First child of Admiral, Count Carl August Ehrensvärd and Baroness Ulla Thott. Married in 1909 to Anna Enell. Children: Gösta, born in 1910, PhD, married to Inga-Lill Rydh; Carl August, born in 1913, Captain of Fleet, married to Eva Morddng; Ulilia, born in 1918, married to Captain G. Murray. \n\nHe began his naval career as a naval cadet in 1898, passed the naval officer exam in 1904, attended the Royal Naval Staff College from 1908 to 1909, and attended the college as a student from 1910 to 1911. He was promoted to Sub-Lieutenant in the Navy in 1904, to Lieutenant in 1906, to Captain in 1913, to Commander in 1922, to Captain of Fleet in 1933, and to Rear Admiral in 1938. \n\nHe was a lecturer at the Royal Naval Staff College from 1918 to 1922, commander of the hunting division in 1919 and 1923-1924, head of the communication department at the naval staff from 1927 to 1929, served on the battleship Oscar II in 1929, head of the operations department of the naval staff from 1929 to 1932, served on the battleship Drottning Victoria from 1932 to 1933, flag captain in 1933-1936 for the commander of the coastal fleet staff, head of the naval staff in 1937-1939, commander of the navy in 1939-1942, and commander and head of the Southern Coast Navy District from 1942 onwards. \n\nHe was a member of the 30-year defense commission from 1930 to 1932, editor of the magazine \"Tidskrift i Sjöväsendet\" from 1925 to 1927, and held several orders and decorations including KmstkSO, RNO, RVO, KDDOlgr, KFinlVRO, KNS:t-OO, KPolRest2kl, KSpMerNavOlkl, RLtiKrO, RRS:itSit03kl, TM04 kil, SV-KGM, Danisik FrM, LKrVA, HedLÖS.",
    "structured_raw": "{\n  \"@context\": \"https://schema.org\",\n  \"@type\": \"Person\",\n  \"name\": \"Gösta Carl Albert Ehrensvärd\",\n  \"jobTitle\": \"Rear Admiral\",\n  \"birthDate\": \"1885-02-10\",\n  \"birthPlace\": \"Skabersjö, Malmöhus\",\n  \"parents\": [\n    {\n      \"@type\": \"Person\",\n      \"name\": \"Carl August Ehrensvärd\",\n      \"jobTitle\": \"Admiral and Count\"\n    },\n    {\n      \"@type\": \"Person\",\n      \"name\": \"Ulla Thott\",\n      \"jobTitle\": \"Baroness\"\n    }\n  ],\n  \"spouse\": {\n    \"@type\": \"Person\",\n    \"name\": \"Anna Enell\"\n  },\n  \"children\": [\n    {\n      \"@type\": \"Person\",\n      \"name\": \"Gösta Ehrensvärd\",\n      \"birthDate\": \"1910-01-01\",\n      \"jobTitle\": \"PhD\",\n      \"spouse\": {\n        \"@type\": \"Person\",\n        \"name\": \"Inga-Lill Rydh\"\n      }\n    },\n    {\n      \"@type\": \"Person\",\n      \"name\": \"Carl August Ehrensvärd\",\n      \"birthDate\": \"1913-01-01\",\n      \"jobTitle\": \"Captain of Fleet\",\n      \"spouse\": {\n        \"@type\": \"Person\",\n        \"name\": \"Eva Morddng\"\n      }\n    },\n    {\n      \"@type\": \"Person\",\n      \"name\": \"Ulilia Ehrensvärd\",\n      \"birthDate\": \"1918-01-01\",\n      \"spouse\": {\n        \"@type\": \"Person\",\n        \"name\": \"Captain G. Murray\"\n      }\n    }\n  ],\n  \"alumniOf\": [\n    {\n      \"@type\": \"CollegeOrUniversity\",\n      \"name\": \"Royal Naval Staff College\",\n      \"startDate\": \"1908\",\n      \"endDate\": \"1909\"\n    },\n    {\n      \"@type\": \"CollegeOrUniversity\",\n      \"name\": \"Royal Naval Staff College\",\n      \"startDate\": \"1910\",\n      \"endDate\": \"1911\"\n    }\n  ],\n  \"memberOf\": {\n    \"@type\": \"Organization\",\n    \"name\": \"Royal Swedish Navy\"\n  },\n  \"deathDate\": \"1942\",\n  \"deathPlace\": \"Sweden\",\n  \"sameAs\": [\n    \"https://www.wikidata.org/wiki/Q3263050\",\n    \"https://www.findagrave.com/memorial/213989007/gosta-carl-albert-ehrensvard\"\n  ],\n  \"jobTitle\": [\n    \"Lecturer\",\n    \"Commander of the hunting division\",\n    \"Head of the communication department at the naval staff\",\n    \"Flag captain for the commander of the coastal fleet staff\",\n    \"Head of the naval staff\",\n    \"Commander of the navy\",\n    \"Commander and head of the Southern Coast Navy District\"\n  ],\n  \"editor\": {\n    \"@type\": \"Periodical\",\n    \"name\": \"Tidskrift i Sjöväsendet\",\n    \"startDate\": \"1925\",\n    \"endDate\": \"1927\"\n  },\n  \"awards\": [\n    \"KmstkSO\",\n    \"RNO\",\n    \"RVO\",\n    \"KDDOlgr\",\n    \"KFinlVRO\",\n    \"KNS:t-OO\",\n    \"KPolRest2kl\",\n    \"KSpMerNavOlkl\",\n    \"RLtiKrO\",\n    \"RRS:itSit03kl\",\n    \"TM04 kil\",\n    \"SV-KGM\",\n    \"Danisik FrM\",\n    \"LKrVA\",\n    \"HedLÖS\"\n  ]\n}",
    "structured": {
        "@context": "https://schema.org",
        "@type": "Person",
        "name": "Gösta Carl Albert Ehrensvärd",
        "jobTitle": [
            "Lecturer",
            "Commander of the hunting division",
            "Head of the communication department at the naval staff",
            "Flag captain for the commander of the coastal fleet staff",
            "Head of the naval staff",
            "Commander of the navy",
            "Commander and head of the Southern Coast Navy District"
        ],
        "birthDate": "1885-02-10",
        "birthPlace": "Skabersjö, Malmöhus",
        "parents": [
            {
                "@type": "Person",
                "name": "Carl August Ehrensvärd",
                "jobTitle": "Admiral and Count"
            },
            {
                "@type": "Person",
                "name": "Ulla Thott",
                "jobTitle": "Baroness"
            }
        ],
        "spouse": {
            "@type": "Person",
            "name": "Anna Enell"
        },
        "children": [
            {
                "@type": "Person",
                "name": "Gösta Ehrensvärd",
                "birthDate": "1910-01-01",
                "jobTitle": "PhD",
                "spouse": {
                    "@type": "Person",
                    "name": "Inga-Lill Rydh"
                }
            },
            {
                "@type": "Person",
                "name": "Carl August Ehrensvärd",
                "birthDate": "1913-01-01",
                "jobTitle": "Captain of Fleet",
                "spouse": {
                    "@type": "Person",
                    "name": "Eva Morddng"
                }
            },
            {
                "@type": "Person",
                "name": "Ulilia Ehrensvärd",
                "birthDate": "1918-01-01",
                "spouse": {
                    "@type": "Person",
                    "name": "Captain G. Murray"
                }
            }
        ],
        "alumniOf": [
            {
                "@type": "CollegeOrUniversity",
                "name": "Royal Naval Staff College",
                "startDate": "1908",
                "endDate": "1909"
            },
            {
                "@type": "CollegeOrUniversity",
                "name": "Royal Naval Staff College",
                "startDate": "1910",
                "endDate": "1911"
            }
        ],
        "memberOf": {
            "@type": "Organization",
            "name": "Royal Swedish Navy"
        },
        "deathDate": "1942",
        "deathPlace": "Sweden",
        "sameAs": [
            "https://www.wikidata.org/wiki/Q3263050",
            "https://www.findagrave.com/memorial/213989007/gosta-carl-albert-ehrensvard"
        ],
        "editor": {
            "@type": "Periodical",
            "name": "Tidskrift i Sjöväsendet",
            "startDate": "1925",
            "endDate": "1927"
        },
        "awards": [
            "KmstkSO",
            "RNO",
            "RVO",
            "KDDOlgr",
            "KFinlVRO",
            "KNS:t-OO",
            "KPolRest2kl",
            "KSpMerNavOlkl",
            "RLtiKrO",
            "RRS:itSit03kl",
            "TM04 kil",
            "SV-KGM",
            "Danisik FrM",
            "LKrVA",
            "HedLÖS"
        ]
    }
}