{
    "original": "Lindström, Karl Arne, chefredaktör, Västervik, f. 31/10/01 i Sthlm. G. 29 m. Thyra Boklund. Barn: Blanche f. 32. — Stud:ex. i Örebro 20. Chefred. f. Lysekrlsposten 34-35, Umebla-det 35-38, Härnösands-Posten o. Sollefteå-Bladet 38-43, Örebro Dagbl. 43- 44 samt Västerviks-Tidn. o. Vimmer-by Dagbl. ’sed. 44. Led. av stadsfullm. i Lysekil 35, Umeå (tilltr. ej) 39 samt Härnösand 43, ett fdertal uppdrag av olika sdag på olika platser, bl. a. led. av stadsbibi :styr. i Umeå, Härnösand och Västervik, v. ordf. i System A-B i Härnösand 41-43, led. av nykterh:-ndn i Örebro, ’sekr. i Lysekils idr:-platskomm., ordf. i Lysekils simsällsk. o. scoutkår m. m., presid. i Västerviks rotaryklubb 46-47, led. av styr. f. Sv. högerpressens förenings ekon. sekt., ett flertal fören :uppdrag etc. Skr.: Romantiskt landskap (31), Besvärjelse (47), flera särtr3xk av art. i Ord o. Bild, Sv. Tidskr. m. fd. Redig. Härnömässan 41 o. 42. Hobbies : mod. måleri, nutida litteratur.",
    "translated": "Lindström, Karl Arne, editor-in-chief, Västervik, b. 31/10/01 in Stockholm. Married in 1929 to Thyra Boklund. Children: Blanche b. 1932. Graduated from high school in Örebro in 1920. Editor-in-chief for Lysekilsposten 1934-1935, Umebla-det 1935-1938, Härnösands-Posten and Sollefteå-Bladet 1938-1943, Örebro Dagblad 1943-1944, and Västerviks-Tidningen and Vimmerby Dagblad since 1944. Member of the city council in Lysekil in 1935, Umeå (did not assume office) in 1939, and Härnösand in 1943. Various assignments for different newspapers in different places, including being a member of the city library board in Umeå, Härnösand, and Västervik, vice-president of System A-B in Härnösand 1941-1943, member of the temperance society in Örebro, secretary of the Lysekil sports area committee, chairman of the Lysekil swimming club and scout troop, president of the Västervik Rotary Club 1946-1947, member of the Swedish Right Press Association's economic sector board, and various other association assignments, etc. Publications: Romantiskt landskap (1931), Besvärjelse (1947), several separate works of articles in Ord och Bild, and Svenska Tidskrift with former editorship. Organized the Härnömässan trade fair in 1941 and 1942. Hobbies: modern painting, contemporary literature.",
    "structured_raw": "{\n  \"@context\": \"https://schema.org\",\n  \"@type\": \"Person\",\n  \"name\": \"Karl Arne Lindström\",\n  \"jobTitle\": \"Editor-in-chief\",\n  \"birthDate\": \"1901-10-31\",\n  \"birthPlace\": \"Stockholm, Sweden\",\n  \"address\": {\n    \"@type\": \"PostalAddress\",\n    \"addressLocality\": \"Västervik\",\n    \"addressCountry\": \"Sweden\"\n  },\n  \"spouse\": {\n    \"@type\": \"Person\",\n    \"name\": \"Thyra Boklund\",\n    \"marriageDate\": \"1929\"\n  },\n  \"children\": [{\n    \"@type\": \"Person\",\n    \"name\": \"Blanche\",\n    \"birthDate\": \"1932\"\n  }],\n  \"education\": [\n    {\n      \"@type\": \"EducationalOccupationalCredential\",\n      \"startDate\": \"1920\",\n      \"alumniOf\": {\n        \"@type\": \"EducationalOrganization\",\n        \"name\": \"Örebro\"\n      }\n    }\n  ],\n  \"worksFor\": [\n    {\n      \"@type\": \"Organization\",\n      \"name\": \"Lysekilsposten\",\n      \"startDate\": \"1934\",\n      \"endDate\": \"1935\"\n    },\n    {\n      \"@type\": \"Organization\",\n      \"name\": \"Umebla-det\",\n      \"startDate\": \"1935\",\n      \"endDate\": \"1938\"\n    },\n    {\n      \"@type\": \"Organization\",\n      \"name\": \"Härnösands-Posten\"\n    },\n    {\n      \"@type\": \"Organization\",\n      \"name\": \"Sollefteå-Bladet\",\n      \"startDate\": \"1938\",\n      \"endDate\": \"1943\"\n    },\n    {\n      \"@type\": \"Organization\",\n      \"name\": \"Örebro Dagblad\",\n      \"startDate\": \"1943\",\n      \"endDate\": \"1944\"\n    },\n    {\n      \"@type\": \"Organization\",\n      \"name\": \"Västerviks-Tidningen\"\n    },\n    {\n      \"@type\": \"Organization\",\n      \"name\": \"Vimmerby Dagblad\",\n      \"startDate\": \"1944\"\n    }\n  ],\n  \"memberOf\": [\n    {\n      \"@type\": \"Organization\",\n      \"name\": \"City Council of Lysekil\",\n      \"startDate\": \"1935\"\n    },\n    {\n      \"@type\": \"Organization\",\n      \"name\": \"City Council of Härnösand\",\n      \"startDate\": \"1943\"\n    }\n  ],\n  \"affiliation\": [\n    {\n      \"@type\": \"Organization\",\n      \"name\": \"Swedish Right Press Association\",\n      \"department\": \"Economic sector board\"\n    }\n  ],\n  \"publication\": [\n    {\n      \"@type\": \"Book\",\n      \"name\": \"Romantiskt landskap\",\n      \"datePublished\": \"1931\"\n    },\n    {\n      \"@type\": \"Book\",\n      \"name\": \"Besvärjelse\",\n      \"datePublished\": \"1947\"\n    }\n  ],\n  \"hobbies\": [\n    \"modern painting\",\n    \"contemporary literature\"\n  ]\n}",
    "structured": {
        "@context": "https://schema.org",
        "@type": "Person",
        "name": "Karl Arne Lindström",
        "jobTitle": "Editor-in-chief",
        "birthDate": "1901-10-31",
        "birthPlace": "Stockholm, Sweden",
        "address": {
            "@type": "PostalAddress",
            "addressLocality": "Västervik",
            "addressCountry": "Sweden"
        },
        "spouse": {
            "@type": "Person",
            "name": "Thyra Boklund",
            "marriageDate": "1929"
        },
        "children": [
            {
                "@type": "Person",
                "name": "Blanche",
                "birthDate": "1932"
            }
        ],
        "education": [
            {
                "@type": "EducationalOccupationalCredential",
                "startDate": "1920",
                "alumniOf": {
                    "@type": "EducationalOrganization",
                    "name": "Örebro"
                }
            }
        ],
        "worksFor": [
            {
                "@type": "Organization",
                "name": "Lysekilsposten",
                "startDate": "1934",
                "endDate": "1935"
            },
            {
                "@type": "Organization",
                "name": "Umebla-det",
                "startDate": "1935",
                "endDate": "1938"
            },
            {
                "@type": "Organization",
                "name": "Härnösands-Posten"
            },
            {
                "@type": "Organization",
                "name": "Sollefteå-Bladet",
                "startDate": "1938",
                "endDate": "1943"
            },
            {
                "@type": "Organization",
                "name": "Örebro Dagblad",
                "startDate": "1943",
                "endDate": "1944"
            },
            {
                "@type": "Organization",
                "name": "Västerviks-Tidningen"
            },
            {
                "@type": "Organization",
                "name": "Vimmerby Dagblad",
                "startDate": "1944"
            }
        ],
        "memberOf": [
            {
                "@type": "Organization",
                "name": "City Council of Lysekil",
                "startDate": "1935"
            },
            {
                "@type": "Organization",
                "name": "City Council of Härnösand",
                "startDate": "1943"
            }
        ],
        "affiliation": [
            {
                "@type": "Organization",
                "name": "Swedish Right Press Association",
                "department": "Economic sector board"
            }
        ],
        "publication": [
            {
                "@type": "Book",
                "name": "Romantiskt landskap",
                "datePublished": "1931"
            },
            {
                "@type": "Book",
                "name": "Besvärjelse",
                "datePublished": "1947"
            }
        ],
        "hobbies": [
            "modern painting",
            "contemporary literature"
        ]
    }
}