{
    "original": "Andersson, Torsten, redaktör. Bräm-hult, f. 9/12/09 i Borås av Hjalmar A. o. Hilda Peterson. G. 39 m. Anna-Lisa Danielson. Barn: Eva-Lisa f. 45. — Stud :ex. i Borås 30. Anst. i Sju-häradsbygdens Tidn. 31, dess red. o. ansv. utg. sed. 33. Ordf. i S. Älvsb. distr. av SLU 44, i Borås-ortens SLU- avd. 36, i Vedens-krets, av SLU 43, i Brämhults bondeförb.-avd. 40, i Bräm-hults komm:fullm. 45, v. ordf. i arb:-löshind 43, i skolbyggn :komm. 44, kommunal rev. 41, led. av bostadsnd 45, hyresnd 46, barnav :man 41 o. 45, ordf. i Brämhults idr :platsfören. 46, led. av bildnirådet v. I 15 40, ordf. i Gingri m. fl. socknars rusthåll 44, sekr. i S. Älvsb. distr. av SLS 34-45, distr :-tävl .-ledare i SLU 36-41, ordf. i distr :-tävl:ndn 36-45, landstingsman 46. Sign.: T. A-n, Pepe. Civ. o. mil. ’skyt-tem. i silver, mil. idr :m. i silver.",
    "translated": "Andersson, Torsten, editor. Bräm-hult, born December 9, 1909 in Borås to Hjalmar A. and Hilda Peterson. Married in 1939 to Anna-Lisa Danielson. Children: Eva-Lisa, born in 1945. Graduated from Borås College in 1930. Employed at Sju-häradsbygdens Tidn. in 1931, where he became editor and responsible publisher since 1933. Chairman of SLU (Swedish Farmers' Association) in the S. Älvsb. district from 1944, in the Borås-ortens SLU division from 1936, in the Vedens-krets of SLU in 1943, in the farm association division of Brämhults in 1940, in the municipal council of Bräm-hult in 1945, deputy chairman of the unemployment commission in 1943, in the school building committee in 1944, municipal auditor in 1941, member of the housing committee in 1945, member of the Child Welfare Council in 1941 and 1945, chairman of Brämhults idr: platsfören. in 1946, member of the art council at I 15 in 1940, chairman of Gingri and other parishes' rusthåll in 1944, secretary of SLS (Swedish Local Authority Association) in the S. Älvsb. district from 1934 to 1945, district competition leader in SLU from 1936 to 1941, chairman of the district competition committee from 1936 to 1945, county councilor in 1946. Signature: T. A-n, Pepe. Civil and military distinction in silver, military sports medal in silver.",
    "structured": {
        "@context": "https://schema.org",
        "@type": "Person",
        "name": "Torsten Andersson",
        "birthDate": "1909-12-09",
        "birthPlace": "Borås, Sweden",
        "spouse": {
            "@type": "Person",
            "name": "Anna-Lisa Danielson",
            "marriageDate": "1939"
        },
        "children": [
            {
                "@type": "Person",
                "name": "Eva-Lisa Andersson",
                "birthDate": "1945"
            }
        ],
        "jobTitle": "Editor",
        "worksFor": {
            "@type": "Organization",
            "name": "Sju-häradsbygdens Tidn"
        },
        "education": {
            "@type": "EducationalOccupationalCredential",
            "credentialCategory": "diploma",
            "name": "Stud:ex.",
            "educationalLevel": "High School",
            "issuer": {
                "@type": "Organization",
                "name": "Borås College"
            },
            "yearAwarded": "1930"
        },
        "memberOf": [
            {
                "@type": "Organization",
                "name": "Swedish Farmers' Association",
                "position": {
                    "@type": "Role",
                    "startDate": "1944",
                    "endDate": null,
                    "roleName": "Chairman",
                    "namedPosition": "S. Älvsb. district"
                }
            },
            {
                "@type": "Organization",
                "name": "Swedish Farmers' Association",
                "position": {
                    "@type": "Role",
                    "startDate": "1936",
                    "endDate": null,
                    "roleName": "Chairman",
                    "namedPosition": "Borås-ortens SLU division"
                }
            },
            {
                "@type": "Organization",
                "name": "Swedish Farmers' Association",
                "position": {
                    "@type": "Role",
                    "startDate": "1943",
                    "endDate": null,
                    "roleName": "Chairman",
                    "namedPosition": "Vedens-krets of SLU"
                }
            },
            {
                "@type": "Organization",
                "name": "Brämhults bondeförb",
                "position": {
                    "@type": "Role",
                    "startDate": "1940",
                    "endDate": null,
                    "roleName": "Chairman",
                    "namedPosition": "Farm association division"
                }
            },
            {
                "@type": "Organization",
                "name": "Brämhults komm",
                "position": {
                    "@type": "Role",
                    "startDate": "1945",
                    "endDate": null,
                    "roleName": "Member",
                    "namedPosition": "Municipal Council"
                }
            },
            {
                "@type": "Organization",
                "name": "Unemployment Commission",
                "position": {
                    "@type": "Role",
                    "startDate": "1943",
                    "endDate": null,
                    "roleName": "Deputy Chairman"
                }
            },
            {
                "@type": "Organization",
                "name": "School Building Committee",
                "position": {
                    "@type": "Role",
                    "startDate": "1944",
                    "endDate": null,
                    "roleName": "Member"
                }
            },
            {
                "@type": "Organization",
                "name": "Municipal Auditor",
                "position": {
                    "@type": "Role",
                    "startDate": "1941",
                    "endDate": null,
                    "roleName": "Member"
                }
            },
            {
                "@type": "Organization",
                "name": "Housing Committee",
                "position": {
                    "@type": "Role",
                    "startDate": "1945",
                    "endDate": null,
                    "roleName": "Member"
                }
            },
            {
                "@type": "Organization",
                "name": "Child Welfare Council",
                "position": [
                    {
                        "@type": "Role",
                        "startDate": "1941",
                        "endDate": null,
                        "roleName": "Member"
                    },
                    {
                        "@type": "Role",
                        "startDate": "1945",
                        "endDate": null,
                        "roleName": "Member"
                    }
                ]
            },
            {
                "@type": "Organization",
                "name": "Brämhults idr: platsfören",
                "position": {
                    "@type": "Role",
                    "startDate": "1946",
                    "endDate": null,
                    "roleName": "Chairman"
                }
            },
            {
                "@type": "Organization",
                "name": "Art Council at I 15",
                "position": {
                    "@type": "Role",
                    "startDate": "1940",
                    "endDate": null,
                    "roleName": "Member"
                }
            },
            {
                "@type": "Organization",
                "name": "Gingri and other parishes' rusthåll",
                "position": {
                    "@type": "Role",
                    "startDate": "1944",
                    "endDate": null,
                    "roleName": "Chairman"
                }
            }
        ],
        "award": [
            {
                "@type": "Award",
                "name": "Silver Military Sports Medal",
                "description": "Awarded for military athletic achievement"
            },
            {
                "@type": "Award",
                "name": "Silver Skytte-tem.",
                "description": "Awarded for marksmanship in both civilian and military contexts"
            }
        ],
        "givenName": "Torsten",
        "familyName": "Andersson",
        "additionalName": null,
        "gender": "Male",
        "nationality": "Swedish"
    }
}