{
    "original": "Lindahl, Karl Johan Elias, fd. folkskolinspektör, Norrköping, f. 17/4/81 i Växjö av Samuel L. o. Maria Ahlberg. G. 1. 08 m. Hanna Jönsson, d. 41; 2. 43 ^ m. Ruth Wittmark. Barn: Birgit f. 09, skolköks- o. handarb :lär., g. 33 m. rektor Thor sten Åberg, Karl-Erik 12, ing., Britt-Stina 17, fil. mag., Karl-Love 21, civ:ing., lantmät. — Mog:ex. i Växjö 00, folkskoll :ex. där 01, kyr-kosångarex. 02, fil. kand. i Lund 08. E. o. lär. v. Växjö folksk. 01-02, ord. dito 03-09, lär. v. Växjö tekn. yrkes-sk. 04-09, förest, o. förste lär. v. An-derslövs h. folksk. 09-11, rektor o-, ämneslär. v. Nybro komm. mellansk. 11-16, folksk :insp. i östergötl. östra insp :omr. 16-46, vik. o. e. undervisn :-råd samt led. av skolöverstyr. v. skilda tillf, sammani. över tre år sed. 19, sakk. i ecklidep. f. utredn. av viss skolfråga 21-22. Ordf. i Nybro före-;läsn:fören. o. bibl:styr. 12-16, i styr. :f. komm. mellansk. där 15-16, i kyr-I kobyggn :komm. o. pens:nd, dir. o. |ordf, i styr. f. Nybro brunn o. bad-anst. 16, ombud f. tryckta skr. i Nybro fyra år, led. av Norrköp. stads-fullm. (fp.) 35-42, insp. f. komm. mellansk., prakt, mellansk. samt h. folksk. i Norrköp. sed. 36. Skr.: Nybro brunn o. badanst. (33), årsberätt. f. sk. i Anderslöv o. Nybro, upps. o. föredrag i skolfrågor i mötesberätt., tidn., saml :verk m. m. Utg. tills. m. Britta Wittmark o. Ruth Wittmark-Lindah’1: Min skrivbok, övn :bok i rationell välskrivn. RVO.",
    "translated": "Lindahl, Karl Johan Elias, former school inspector, Norrköping, b. 17/4/81 in Växjö to Samuel L. and Maria Ahlberg. Married 1st in 1908 to Hanna Jönsson, d. 1941; 2nd in 1943 to Ruth Wittmark. Children: Birgit b. 1909, cooking and handicraft teacher, married in 1933 to principal Thorsten Åberg, Karl-Erik b. 1912, engineer, Britt-Stina b. 1917, Master of Arts, Karl-Love b. 1921, civil engineer, surveyor. Completed exams in Växjö in 1900, primary school exam in 1901, choir singer exam in 1902, Bachelor of Arts in Lund in 1908. Temporary and regular teacher at Växjö primary school from 1901-1909, teacher at Växjö technical vocational school from 1904-1909, principal and subject teacher at Anderslöv primary school from 1909-1911, principal and subject teacher at Nybro municipal middle school from 1911-1916, school inspector in the eastern part of Östergötland from 1916-1946, acting and permanent education council member, and member of the school management board at various times over three years since 1919, expert in the Department of Ecclesiastical Affairs for a certain school question investigation from 1921-1922. Chairman of Nybro lecture association and library board from 1912-1916, member of the board of Nybro municipal middle school from 1915-1916, in the church construction committee and pension board, director and chairman of the board of Nybro spa and bathing establishment in 1916, representative for printed writings in Nybro for four years, member of Norrköping city council (progressive party) from 1935-1942, inspector for municipal middle school, practical middle school, and higher primary school in Norrköping since 1936. Writings: \"Nybro spa and bathing establishment\" (1933), annual report for schools in Anderslöv and Nybro, essays and lectures on educational issues in meeting reports, newspapers, anthologies, etc. Co-authored with Britta Wittmark and Ruth Wittmark-Lindahl: \"My Writing Book,\" exercise book in efficient penmanship, RVO.",
    "structured_raw": "{\n  \"@context\": \"https://schema.org\",\n  \"@type\": \"Person\",\n  \"name\": \"Karl Johan Elias Lindahl\",\n  \"jobTitle\": \"former school inspector\",\n  \"birthPlace\": \"Växjö\",\n  \"birthDate\": \"1881-04-17\",\n  \"parents\": [\n    {\n      \"@type\": \"Person\",\n      \"name\": \"Samuel L. Lindahl\"\n    },\n    {\n      \"@type\": \"Person\",\n      \"name\": \"Maria Ahlberg\"\n    }\n  ],\n  \"spouse\": [\n    {\n      \"@type\": \"Person\",\n      \"name\": \"Hanna Jönsson\",\n      \"deathDate\": \"1941\"\n    },\n    {\n      \"@type\": \"Person\",\n      \"name\": \"Ruth Wittmark\",\n      \"marriageDate\": \"1943\"\n    }\n  ],\n  \"children\": [\n    {\n      \"@type\": \"Person\",\n      \"name\": \"Birgit\",\n      \"birthDate\": \"1909\",\n      \"occupation\": \"cooking and handicraft teacher\"\n    },\n    {\n      \"@type\": \"Person\",\n      \"name\": \"Karl-Erik\",\n      \"birthDate\": \"1912\",\n      \"occupation\": \"engineer\"\n    },\n    {\n      \"@type\": \"Person\",\n      \"name\": \"Britt-Stina\",\n      \"birthDate\": \"1917\",\n      \"occupation\": \"Master of Arts\"\n    },\n    {\n      \"@type\": \"Person\",\n      \"name\": \"Karl-Love\",\n      \"birthDate\": \"1921\",\n      \"occupation\": \"civil engineer, surveyor\"\n    }\n  ],\n  \"education\": [\n    {\n      \"@type\": \"EducationalOccupationalCredential\",\n      \"credentialCategory\": \"Mog:ex.\",\n      \"educationalLevel\": \"examination\",\n      \"educationalRole\": \"Växjö 1900\"\n    },\n    {\n      \"@type\": \"EducationalOccupationalCredential\",\n      \"credentialCategory\": \"folkskoll :ex.\",\n      \"educationalLevel\": \"examination\",\n      \"educationalRole\": \"Växjö 1901\"\n    },\n    {\n      \"@type\": \"EducationalOccupationalCredential\",\n      \"credentialCategory\": \"kyr-kosångarex.\",\n      \"educationalLevel\": \"examination\",\n      \"educationalRole\": \"Växjö 1902\"\n    },\n    {\n      \"@type\": \"EducationalOccupationalCredential\",\n      \"credentialCategory\": \"fil. kand.\",\n      \"educationalLevel\": \"Bachelor of Arts\",\n      \"educationalRole\": \"Lund 1908\"\n    }\n  ],\n  \"workExperience\": [\n    {\n      \"@type\": \"JobPosting\",\n      \"title\": \"Temporary and regular teacher\",\n      \"startDate\": \"1901\",\n      \"endDate\": \"1909\",\n      \"employer\": \"Växjö primary school\"\n    },\n    {\n      \"@type\": \"JobPosting\",\n      \"title\": \"Teacher\",\n      \"startDate\": \"1904\",\n      \"endDate\": \"1909\",\n      \"employer\": \"Växjö technical vocational school\"\n    },\n    {\n      \"@type\": \"JobPosting\",\n      \"title\": \"Principal and subject teacher\",\n      \"startDate\": \"1909\",\n      \"endDate\": \"1911\",\n      \"employer\": \"Anderslöv primary school\"\n    },\n    {\n      \"@type\": \"JobPosting\",\n      \"title\": \"Principal and subject teacher\",\n      \"startDate\": \"1911\",\n      \"endDate\": \"1916\",\n      \"employer\": \"Nybro municipal middle school\"\n    },\n    {\n      \"@type\": \"JobPosting\",\n      \"title\": \"School inspector\",\n      \"startDate\": \"1916\",\n      \"endDate\": \"1946\",\n      \"employer\": \"Eastern part of Östergötland\"\n    }\n  ],\n  \"memberOf\": [\n    {\n      \"@type\": \"Organization\",\n      \"name\": \"Nybro lecture association\"\n    },\n    {\n      \"@type\": \"Organization\",\n      \"name\": \"Nybro library board\"\n    },\n    {\n      \"@type\": \"Organization\",\n      \"name\": \"Nybro municipal middle school board\"\n    },\n    {\n      \"@type\": \"Organization\",\n      \"name\": \"Church construction committee\"\n    },\n    {\n      \"@type\": \"Organization\",\n      \"name\": \"Pension board\"\n    },\n    {\n      \"@type\": \"Organization\",\n      \"name\": \"Nybro spa and bathing establishment\",\n      \"roleName\": \"chairman\"\n    },\n    {\n      \"@type\": \"Organization\",\n      \"name\": \"Norrköping city council\",\n      \"roleName\": \"member\",\n      \"startDate\": \"1935\",\n      \"endDate\": \"1942\",\n      \"affiliation\": \"progressive party\"\n    }\n  ],\n  \"publication\": [\n    {\n      \"@type\": \"PublicationEvent\",\n      \"name\": \"Nybro spa and bathing establishment\",\n      \"location\": \"Nybro\",\n      \"startDate\": \"1933\"\n    }\n  ]\n}",
    "structured": {
        "@context": "https://schema.org",
        "@type": "Person",
        "name": "Karl Johan Elias Lindahl",
        "jobTitle": "former school inspector",
        "birthPlace": "Växjö",
        "birthDate": "1881-04-17",
        "parents": [
            {
                "@type": "Person",
                "name": "Samuel L. Lindahl"
            },
            {
                "@type": "Person",
                "name": "Maria Ahlberg"
            }
        ],
        "spouse": [
            {
                "@type": "Person",
                "name": "Hanna Jönsson",
                "deathDate": "1941"
            },
            {
                "@type": "Person",
                "name": "Ruth Wittmark",
                "marriageDate": "1943"
            }
        ],
        "children": [
            {
                "@type": "Person",
                "name": "Birgit",
                "birthDate": "1909",
                "occupation": "cooking and handicraft teacher"
            },
            {
                "@type": "Person",
                "name": "Karl-Erik",
                "birthDate": "1912",
                "occupation": "engineer"
            },
            {
                "@type": "Person",
                "name": "Britt-Stina",
                "birthDate": "1917",
                "occupation": "Master of Arts"
            },
            {
                "@type": "Person",
                "name": "Karl-Love",
                "birthDate": "1921",
                "occupation": "civil engineer, surveyor"
            }
        ],
        "education": [
            {
                "@type": "EducationalOccupationalCredential",
                "credentialCategory": "Mog:ex.",
                "educationalLevel": "examination",
                "educationalRole": "Växjö 1900"
            },
            {
                "@type": "EducationalOccupationalCredential",
                "credentialCategory": "folkskoll :ex.",
                "educationalLevel": "examination",
                "educationalRole": "Växjö 1901"
            },
            {
                "@type": "EducationalOccupationalCredential",
                "credentialCategory": "kyr-kosångarex.",
                "educationalLevel": "examination",
                "educationalRole": "Växjö 1902"
            },
            {
                "@type": "EducationalOccupationalCredential",
                "credentialCategory": "fil. kand.",
                "educationalLevel": "Bachelor of Arts",
                "educationalRole": "Lund 1908"
            }
        ],
        "workExperience": [
            {
                "@type": "JobPosting",
                "title": "Temporary and regular teacher",
                "startDate": "1901",
                "endDate": "1909",
                "employer": "Växjö primary school"
            },
            {
                "@type": "JobPosting",
                "title": "Teacher",
                "startDate": "1904",
                "endDate": "1909",
                "employer": "Växjö technical vocational school"
            },
            {
                "@type": "JobPosting",
                "title": "Principal and subject teacher",
                "startDate": "1909",
                "endDate": "1911",
                "employer": "Anderslöv primary school"
            },
            {
                "@type": "JobPosting",
                "title": "Principal and subject teacher",
                "startDate": "1911",
                "endDate": "1916",
                "employer": "Nybro municipal middle school"
            },
            {
                "@type": "JobPosting",
                "title": "School inspector",
                "startDate": "1916",
                "endDate": "1946",
                "employer": "Eastern part of Östergötland"
            }
        ],
        "memberOf": [
            {
                "@type": "Organization",
                "name": "Nybro lecture association"
            },
            {
                "@type": "Organization",
                "name": "Nybro library board"
            },
            {
                "@type": "Organization",
                "name": "Nybro municipal middle school board"
            },
            {
                "@type": "Organization",
                "name": "Church construction committee"
            },
            {
                "@type": "Organization",
                "name": "Pension board"
            },
            {
                "@type": "Organization",
                "name": "Nybro spa and bathing establishment",
                "roleName": "chairman"
            },
            {
                "@type": "Organization",
                "name": "Norrköping city council",
                "roleName": "member",
                "startDate": "1935",
                "endDate": "1942",
                "affiliation": "progressive party"
            }
        ],
        "publication": [
            {
                "@type": "PublicationEvent",
                "name": "Nybro spa and bathing establishment",
                "location": "Nybro",
                "startDate": "1933"
            }
        ]
    }
}