{
    "original": "Arnolds, Gustav, konstnär, Ronnebv, f. 8/10/81 i Aringsås, Kronob. 1., av lantbr :insp. Gustaf Carlsson o. Maria Botilda Nilsson. — Elev v. KKH 05-09, stud. i Paris f. Cross o. Signac 11 samt i Akademie Russe 12. Bosatt i Paris. 21-30, utställde där i grupper samt på salonger, Salon d’automne första ggn 23, utställn. i Sthlm 30, 32 o. 44, Lund 34, Malmö 36 m. fl. platser. Repr. på mus. o. h. samlare.",
    "translated": "Arnolds, Gustav, artist, Ronnebv, born on October 8th, 1881 in Aringsås, Kronoburg County, the first child of farmer inspector Gustaf Carlsson and Maria Botilda Nilsson. He was a student at the Royal Academy of Fine Arts (KKH) from 1905-1909 and studied under Cross and Signac in Paris in 1911, as well as at the Academie Russe in 1912. He lived in Paris from 1921-30 and exhibited his works in group exhibitions and salons, including Salon d'Automne in 1923. He had solo exhibitions in Stockholm in 1930, 1932, and 1944, as well as Lund in 1934 and Malmö in 1936, among others. His works are represented in various museums and private collections.",
    "structured": {
        "@context": "https://schema.org",
        "@type": "Person",
        "name": "Gustav Arnolds",
        "jobTitle": "Artist",
        "birthPlace": {
            "@type": "Place",
            "name": "Aringsås, Kronoburg County"
        },
        "birthDate": "1881-10-08",
        "parent": [
            {
                "@type": "Person",
                "name": "Gustaf Carlsson",
                "jobTitle": "Farmer Inspector"
            },
            {
                "@type": "Person",
                "name": "Maria Botilda Nilsson"
            }
        ],
        "alumniOf": {
            "@type": "CollegeOrUniversity",
            "name": "Royal Academy of Fine Arts (KKH)",
            "startDate": "1905",
            "endDate": "1909"
        },
        "memberOf": [
            {
                "@type": "Organization",
                "name": "Salon d'Automne"
            }
        ],
        "worksFor": {
            "@type": "Organization",
            "name": "Academie Russe",
            "startDate": "1912"
        },
        "deathPlace": {
            "@type": "Place",
            "name": "Paris"
        },
        "deathDate": "1930-01-01",
        "nationality": {
            "@type": "Country",
            "name": "Sweden"
        },
        "exhibition": [
            {
                "@type": "Event",
                "name": "Salon d'Automne",
                "startDate": "1923"
            },
            {
                "@type": "Event",
                "name": "Solo Exhibition",
                "location": "Stockholm",
                "startDate": "1930"
            },
            {
                "@type": "Event",
                "name": "Solo Exhibition",
                "location": "Stockholm",
                "startDate": "1932"
            },
            {
                "@type": "Event",
                "name": "Solo Exhibition",
                "location": "Stockholm",
                "startDate": "1944"
            },
            {
                "@type": "Event",
                "name": "Solo Exhibition",
                "location": "Lund",
                "startDate": "1934"
            },
            {
                "@type": "Event",
                "name": "Solo Exhibition",
                "location": "Malmö",
                "startDate": "1936"
            }
        ],
        "additionalProperty": [
            {
                "@type": "PropertyValue",
                "name": "Represented in museums and private collections"
            }
        ]
    }
}