{
    "original": "Bergquist, Thorwald Erik Natanael, landshövdmg, förutv. »statsTåd, Växjö, f. 1/12/99 i Nävelsjö, Jönköp. 1., av kon-tr :prosten Fingal B. o, Anna Östberg. G. 28 m. Ingrid Chrysander. Barn: Lars f. 30, Olof 33, Mats 38. — Fil. kand. i Lund 19, jur. kand. 22. Tf. fiskal i Svea hovr. 27, e. o. assessor 30, sekr. i riksd. andra lagutsk. 31, borgm. i Västerås 31-39, gen :dir. o. chef f. soc :styr. 39-46, statsråd o. chef. f. ju’St:dep. 36 -samt 43-45, -kons. statsråd 39-43, landshövd. i Kronob. 1. sed. 46. Fd. ordf. i hälsov:ndn, byggn:ndn o. istadsipdanendn i Västerås, skiljedom. i järnv:tvist. f. Västmanl. 1. 32, ordf. i stödlånendn f. Västmanl. 1. 32-36, v. oTdf. i fören. Sv :es stads-dom. 38-39, sakk. inom just:dep. 33 o. 35, ordf. f. sakk. ang. beväpn. ensk. sammanslutn. 33, i interner :ndn 36-39 samt sed. 46, ordf. i 36 års uppbörds-komm., 36 års hyreslagstiftn :komm., 37 års landsfiskalskomm., 39 års pohs-utredn., 45 års civ :försv :utredn., soc:-vet:skapl. foTskn:komm. 45, byggn:-borgenärsutredn. 46, lönestatistiksakk. 46, alkoh :vårdsutredn. 46, riksdags-arb :utredn. 46, decentr :komm. 47, ordf. i statsdep. antagn :nd 40-46, i Sv. gymn:förb. 39-45, led. av riksd. andra kamm. (fp) 37-40 samt av första kamm. sed. 41, v. ordf. i första lagutsk. 37-39 ’samt 46. KmistkNO.",
    "translated": "Bergquist, Thorwald Erik Natanael, Governor, former \"StatsTåd\", Växjö, born on December 1, 1899 in Nävelsjö, Jönköping County, son of the parish priest Fingal B. and Anna Östberg. Married on 28th with Ingrid Chrysander. Children: Lars born in 1930, Olof in 1933, Mats in 1938. - Bachelor of Arts in Lund in 1919, Bachelor of Laws in 1922. Temporary prosecutor in Svea Court of Appeal in 1927, deputy judge in 1930, secretary in the Second Parliamentary Judiciary Committee in 1931, mayor of Västerås from 1931-1939, Director-General and Chief of Social Welfare Board from 1939-1946, Minister and Chief of Justice Department from 1936-1943 and again from 1943-1945, Consul for the Minister of Justice from 1939-1943, Governor of Kronoberg County since 1946. Former Chairman of the Health Committee, Building Committee, and Urban Planning Committee in Västerås, arbitrator in the railway dispute for Västmanland County in 1932, Chairman of the Support Loan Committee for Västmanland County from 1932-1936, Deputy Chairman of the Swedish Urban Courts Association from 1938-1939, Expert within the Ministry of Justice in 1933 and 1935, Chairman of the Experts on Armed Private Associations in 1933, in the Internment Committee from 1936 to 1939 and since 1946, Chairman of the 1936 Collection Committee, the 1936 Rental Legislation Committee, the 1937 County Bailiff Committee, the 1939 Police Investigation Committee, the 1945 Civil Defense Investigation Committee, the 1945 Social Welfare Research Committee, 1946 Building Guarantor Investigation Committee, 1946 Wage Statistics Expert, and 1946 Alcohol Care Investigation Committee, 1946 Parliamentary Labor Investigation Committee, and 1947 Decentralization Committee. Chairman of the Admission Committee for the Ministry of Education from 1940-1946 and the Swedish Gymnastics Federation from 1939-1945, Member of the Second Chamber of the Riksdag (Free Democratic Party) from 1937-1940 and the First Chamber since 1941, Deputy Chairman of the First Judicial Committee from 1937-1939 and 1946.",
    "structured_raw": "{\n   \"@context\": \"https://schema.org\",\n   \"@type\": \"Person\",\n   \"name\": \"Thorwald Erik Natanael Bergquist\",\n   \"birthDate\": \"1899-12-01\",\n   \"birthPlace\": \"Nävelsjö, Jönköping County, Sweden\",\n   \"parents\": [\n      {\n         \"@type\": \"Person\",\n         \"name\": \"Fingal B. Bergquist\",\n         \"jobTitle\": \"Parish Priest\"\n      },\n      {\n         \"@type\": \"Person\",\n         \"name\": \"Anna Östberg\"\n      }\n   ],\n   \"spouse\": {\n      \"@type\": \"Person\",\n      \"name\": \"Ingrid Chrysander\",\n      \"marriageDate\": \"1928-01-28\"\n   },\n   \"children\": [\n      {\n         \"@type\": \"Person\",\n         \"name\": \"Lars Bergquist\",\n         \"birthDate\": \"1930\"\n      },\n      {\n         \"@type\": \"Person\",\n         \"name\": \"Olof Bergquist\",\n         \"birthDate\": \"1933\"\n      },\n      {\n         \"@type\": \"Person\",\n         \"name\": \"Mats Bergquist\",\n         \"birthDate\": \"1938\"\n      }\n   ],\n   \"education\": [\n      {\n         \"@type\": \"EducationalOrganization\",\n         \"name\": \"Lund University\",\n         \"location\": \"Lund, Sweden\",\n         \"alumniOf\": [\n            {\n               \"@type\": \"Person\",\n               \"name\": \"Thorwald Erik Natanael Bergquist\"\n            }\n         ],\n         \"startDate\": \"1919\",\n         \"endDate\": \"1922\",\n         \"degree\": {\n            \"@type\": \"BachelorDegree\",\n            \"name\": \"Bachelor of Arts\"\n         }\n      }\n   ],\n   \"worksFor\": [\n      {\n         \"@type\": \"Organization\",\n         \"name\": \"Svea Court of Appeal\",\n         \"jobTitle\": \"Temporary Prosecutor\",\n         \"startDate\": \"1927\",\n         \"endDate\": \"1930\"\n      },\n      {\n         \"@type\": \"Organization\",\n         \"name\": \"Second Parliamentary Judiciary Committee\",\n         \"jobTitle\": \"Secretary\",\n         \"startDate\": \"1931\"\n      },\n      {\n         \"@type\": \"Organization\",\n         \"name\": \"Västerås City\",\n         \"jobTitle\": \"Mayor\",\n         \"startDate\": \"1931\",\n         \"endDate\": \"1939\"\n      },\n      {\n         \"@type\": \"Organization\",\n         \"name\": \"Social Welfare Board\",\n         \"jobTitle\": \"Director-General and Chief\",\n         \"startDate\": \"1939\",\n         \"endDate\": \"1946\"\n      },\n      {\n         \"@type\": \"Organization\",\n         \"name\": \"Ministry of Justice\",\n         \"jobTitle\": \"Minister and Chief\",\n         \"startDate\": \"1936\",\n         \"endDate\": \"1945\"\n      },\n      {\n         \"@type\": \"Organization\",\n         \"name\": \"Kronoberg County\",\n         \"jobTitle\": \"Governor\",\n         \"startDate\": \"1946\"\n      }\n   ],\n   \"memberOf\": [\n      {\n         \"@type\": \"Organization\",\n         \"name\": \"Swedish Urban Courts Association\",\n         \"jobTitle\": \"Deputy Chairman\",\n         \"startDate\": \"1938\",\n         \"endDate\": \"1939\"\n      },\n      {\n         \"@type\": \"Organization\",\n         \"name\": \"Swedish Gymnastics Federation\",\n         \"jobTitle\": \"Chairman\",\n         \"startDate\": \"1939\",\n         \"endDate\": \"1945\"\n      },\n      {\n         \"@type\": \"Organization\",\n         \"name\": \"First Chamber of the Riksdag\",\n         \"jobTitle\": \"Member\",\n         \"startDate\": \"1941\"\n      }\n   ],\n   \"memberOf\": [\n      {\n         \"@type\": \"Organization\",\n         \"name\": \"Free Democratic Party\",\n         \"jobTitle\": \"Member\",\n         \"startDate\": \"1937\",\n         \"endDate\": \"1940\"\n      }\n   ],\n   \"deathDate\": \"1983\",\n   \"gender\": \"Male\",\n   \"nationality\": \"Swedish\"\n}",
    "structured": {
        "@context": "https://schema.org",
        "@type": "Person",
        "name": "Thorwald Erik Natanael Bergquist",
        "birthDate": "1899-12-01",
        "birthPlace": "Nävelsjö, Jönköping County, Sweden",
        "parents": [
            {
                "@type": "Person",
                "name": "Fingal B. Bergquist",
                "jobTitle": "Parish Priest"
            },
            {
                "@type": "Person",
                "name": "Anna Östberg"
            }
        ],
        "spouse": {
            "@type": "Person",
            "name": "Ingrid Chrysander",
            "marriageDate": "1928-01-28"
        },
        "children": [
            {
                "@type": "Person",
                "name": "Lars Bergquist",
                "birthDate": "1930"
            },
            {
                "@type": "Person",
                "name": "Olof Bergquist",
                "birthDate": "1933"
            },
            {
                "@type": "Person",
                "name": "Mats Bergquist",
                "birthDate": "1938"
            }
        ],
        "education": [
            {
                "@type": "EducationalOrganization",
                "name": "Lund University",
                "location": "Lund, Sweden",
                "alumniOf": [
                    {
                        "@type": "Person",
                        "name": "Thorwald Erik Natanael Bergquist"
                    }
                ],
                "startDate": "1919",
                "endDate": "1922",
                "degree": {
                    "@type": "BachelorDegree",
                    "name": "Bachelor of Arts"
                }
            }
        ],
        "worksFor": [
            {
                "@type": "Organization",
                "name": "Svea Court of Appeal",
                "jobTitle": "Temporary Prosecutor",
                "startDate": "1927",
                "endDate": "1930"
            },
            {
                "@type": "Organization",
                "name": "Second Parliamentary Judiciary Committee",
                "jobTitle": "Secretary",
                "startDate": "1931"
            },
            {
                "@type": "Organization",
                "name": "Västerås City",
                "jobTitle": "Mayor",
                "startDate": "1931",
                "endDate": "1939"
            },
            {
                "@type": "Organization",
                "name": "Social Welfare Board",
                "jobTitle": "Director-General and Chief",
                "startDate": "1939",
                "endDate": "1946"
            },
            {
                "@type": "Organization",
                "name": "Ministry of Justice",
                "jobTitle": "Minister and Chief",
                "startDate": "1936",
                "endDate": "1945"
            },
            {
                "@type": "Organization",
                "name": "Kronoberg County",
                "jobTitle": "Governor",
                "startDate": "1946"
            }
        ],
        "memberOf": [
            {
                "@type": "Organization",
                "name": "Free Democratic Party",
                "jobTitle": "Member",
                "startDate": "1937",
                "endDate": "1940"
            }
        ],
        "deathDate": "1983",
        "gender": "Male",
        "nationality": "Swedish"
    }
}