{
    "original": "Christoffersson, Carl Emanuel, distriktslantmätare, Norrköping, f. 25/1/ 84 i Landskrona av köpm. Nils C. o. Mathilda Svensson. G. 10 m. Linnéa Sandberg. Barn: Lennart f. 14, Bertil 18. — Mog:ex. 02, lantmät lauskult. 06. Distr :lantmät. i Norrköp. n. distr. sed. 20. Bitr. sekr. i 17 års lantmät:-komm. 18, sekr. där 19-20, v. ordf. i Sv:es ilantmät rfören. 34-45, ordf. i Sv:es d|str :lantmät ifören. 39-46, led. av styr. f. o. skattmäst. i Norrköp. konstgilk sed. 34. RVO.",
    "translated": "Christoffersson, Carl Emanuel, district surveyor, Norrköping, born January 25, 1884 in Landskrona, son of merchant Nils C. and Mathilda Svensson. Married to Linnéa Sandberg in 19xx. Children: Lennart born in 1914 and Bertil born in 1918. Graduated from college in 1902 and from the Surveying and Mapping School in 1906. District surveyor in Norrköping since 1920. Assistant secretary in the Surveying Committee for 17 years starting in 1918, secretary from 1919-1920, vice president of the Swedish Surveyor Association from 1934-1945, chairman of the Swedish District Surveyor Association from 1939-1946, and member of the board of the Art Guild and Taxmaster in Norrköping since 1934. Received the honor of the Royal Victorian Order.",
    "structured_raw": "{\n  \"@context\": \"https://schema.org\",\n  \"@type\": \"Person\",\n  \"name\": \"Carl Emanuel Christoffersson\",\n  \"birthDate\": \"1884-01-25\",\n  \"birthPlace\": \"Landskrona, Sweden\",\n  \"nationality\": \"Swedish\",\n  \"occupation\": \"District Surveyor\",\n  \"memberOf\": [\n    {\n      \"@type\": \"Organization\",\n      \"name\": \"Swedish Surveyor Association\",\n      \"startDate\": \"1934\",\n      \"endDate\": \"1945\",\n      \"roleName\": \"Vice President\"\n    },\n    {\n      \"@type\": \"Organization\",\n      \"name\": \"Swedish District Surveyor Association\",\n      \"startDate\": \"1939\",\n      \"endDate\": \"1946\",\n      \"roleName\": \"Chairman\"\n    }\n  ],\n  \"education\": [\n    {\n      \"@type\": \"EducationalOrganization\",\n      \"name\": \"Surveying and Mapping School\",\n      \"endDate\": \"1906\"\n    }\n  ],\n  \"spouse\": {\n    \"@type\": \"Person\",\n    \"name\": \"Linnéa Sandberg\",\n    \"marriageDate\": \"19xx\"\n  },\n  \"children\": [\n    {\n      \"@type\": \"Person\",\n      \"name\": \"Lennart Christoffersson\",\n      \"birthDate\": \"1914\"\n    },\n    {\n      \"@type\": \"Person\",\n      \"name\": \"Bertil Christoffersson\",\n      \"birthDate\": \"1918\"\n    }\n  ],\n  \"parent\": [\n    {\n      \"@type\": \"Person\",\n      \"name\": \"Nils C. Christoffersson\",\n      \"jobTitle\": \"Merchant\"\n    },\n    {\n      \"@type\": \"Person\",\n      \"name\": \"Mathilda Svensson\"\n    }\n  ],\n  \"deathDate\": \"unknown\",\n  \"sameAs\": \"unknown\",\n  \"honorificPrefix\": \"RVO\"\n}",
    "structured": {
        "@context": "https://schema.org",
        "@type": "Person",
        "name": "Carl Emanuel Christoffersson",
        "birthDate": "1884-01-25",
        "birthPlace": "Landskrona, Sweden",
        "nationality": "Swedish",
        "occupation": "District Surveyor",
        "memberOf": [
            {
                "@type": "Organization",
                "name": "Swedish Surveyor Association",
                "startDate": "1934",
                "endDate": "1945",
                "roleName": "Vice President"
            },
            {
                "@type": "Organization",
                "name": "Swedish District Surveyor Association",
                "startDate": "1939",
                "endDate": "1946",
                "roleName": "Chairman"
            }
        ],
        "education": [
            {
                "@type": "EducationalOrganization",
                "name": "Surveying and Mapping School",
                "endDate": "1906"
            }
        ],
        "spouse": {
            "@type": "Person",
            "name": "Linnéa Sandberg",
            "marriageDate": "19xx"
        },
        "children": [
            {
                "@type": "Person",
                "name": "Lennart Christoffersson",
                "birthDate": "1914"
            },
            {
                "@type": "Person",
                "name": "Bertil Christoffersson",
                "birthDate": "1918"
            }
        ],
        "parent": [
            {
                "@type": "Person",
                "name": "Nils C. Christoffersson",
                "jobTitle": "Merchant"
            },
            {
                "@type": "Person",
                "name": "Mathilda Svensson"
            }
        ],
        "deathDate": "unknown",
        "sameAs": "unknown",
        "honorificPrefix": "RVO"
    }
}