{
    "original": "Ekeroth, Gunnar, överste, Göteborg, f. 16/9/86 i Sthlm av dir.* Gösta E. o. Anna Wahlstedt. G. 14 m. Ebba Stj^ernswärd. Barn: Marianne f. 15, försäkr :tj :man, Sthlm, Carl Gustaf 17, kapten i Wendes art:reg., tj :m’an v. SKF, Gbg, g. m. Magdalena Thott, Gunniar 18, ing., Sth’I(m, g. m. Vera Wästifelit. — AieS(hk) 12-14. Und:-(llöjtn. v. We-ndeiS’ ,art:reg. 09, ilöjtn. 13, k’apt:. 24, miajör v. Bodiensi art :-reg. 33, v. Svea ar;t:reg. 36, öv:-ilöjtn. 36, över:ste i armén 40, på resi:)sttat 41, tff. chef. f. Svea art:reg. 41, överste o. chef f. Göta art:reg. 43-46. Tjg. v. art:staben 17-19, art:-stabsoff. 19-26, adjut. h. ^ H. K. H. Kronprinsen sed. 27, åtföljt denne bl. a. på res. t. Egypt. o. Cypern 30, t. Delawarejub. i USA 38. GVisJmt, KSOlkl, RVO, KDD0i2gr, KStbVO-2kl, NyaSvM, H. M. Konungens skjutpris f. battxhefer 29.",
    "translated": "Ekeroth, Gunnar, colonel, Gothenburg, born on September 16, 1886 in Stockholm to director Gösta E. and Anna Wahlstedt. Married for 14 years to Ebba Stjärnswärd. Children: Marianne born in 1915, insurance company employee in Stockholm, Carl Gustaf born in 1917, captain in Wendes artillery regiment, married to Magdalena Thott and works for SKF in Gothenburg, Gunnar born in 1918, engineer in Stockholm, married to Vera Wästifelit. Ekeroth served as a second lieutenant in Wendes artillery regiment from 1909 to 1913, as a lieutenant in 1913, as a captain in 1924, as a major in Bodiens artillery regiment in 1933, as a major in Svea artillery regiment in 1936, as a lieutenant colonel in 1936, as a colonel in the army in 1940, and was on reserve in 1941 before becoming the chief of Svea artillery regiment in 1941 and then the colonel and chief of Göta artillery regiment from 1943 to 1946. He served as a member of the artillery staff from 1917 to 1919, as an artillery staff officer from 1919 to 1926, as an adjutant to H. R. H. the Crown Prince from 1927 and accompanied him on a trip to Egypt and Cyprus in 1930 and to the Delaware jubilee in the USA in 1938. Ekeroth received the Order of the Sword, Litteris et Artibus, Royal Victorian Order, Knight of the First Class of the Order of the Seraphim, and the King's Shooting Prize for Battalion Commanders in 1929.",
    "structured_raw": "{\n  \"@context\": \"https://schema.org\",\n  \"@type\": \"Person\",\n  \"name\": \"Gunnar Ekeroth\",\n  \"birthDate\": \"1886-09-16\",\n  \"birthPlace\": \"Stockholm, Sweden\",\n  \"deathDate\": \"\",\n  \"deathPlace\": \"\",\n  \"spouse\": {\n    \"@type\": \"Person\",\n    \"name\": \"Ebba Stjärnswärd\",\n    \"marriageDate\": \"XXXX-XX-XX\"\n  },\n  \"children\": [\n    {\n      \"@type\": \"Person\",\n      \"name\": \"Marianne Ekeroth\",\n      \"birthDate\": \"1915\",\n      \"occupation\": \"Insurance company employee\",\n      \"birthPlace\": \"Stockholm, Sweden\"\n    },\n    {\n      \"@type\": \"Person\",\n      \"name\": \"Carl Gustaf Ekeroth\",\n      \"birthDate\": \"1917\",\n      \"occupation\": \"Captain in Wendes artillery regiment\",\n      \"birthPlace\": \"\",\n      \"spouse\": {\n        \"@type\": \"Person\",\n        \"name\": \"Magdalena Thott\"\n      },\n      \"worksFor\": \"SKF\",\n      \"worksIn\": \"Gothenburg, Sweden\"\n    },\n    {\n      \"@type\": \"Person\",\n      \"name\": \"Gunnar Ekeroth\",\n      \"birthDate\": \"1918\",\n      \"occupation\": \"Engineer\",\n      \"birthPlace\": \"Stockholm, Sweden\",\n      \"spouse\": {\n        \"@type\": \"Person\",\n        \"name\": \"Vera Wästifelit\"\n      }\n    }\n  ],\n  \"jobTitle\": \"Colonel\",\n  \"worksFor\": \"Swedish Army\",\n  \"memberOf\": [\n    {\n      \"@type\": \"Organization\",\n      \"name\": \"Wendes Artillery Regiment\"\n    },\n    {\n      \"@type\": \"Organization\",\n      \"name\": \"Bodiens Artillery Regiment\"\n    },\n    {\n      \"@type\": \"Organization\",\n      \"name\": \"Svea Artillery Regiment\"\n    },\n    {\n      \"@type\": \"Organization\",\n      \"name\": \"Artillery Staff\"\n    },\n    {\n      \"@type\": \"Organization\",\n      \"name\": \"H.R.H. the Crown Prince\"\n    },\n    {\n      \"@type\": \"Organization\",\n      \"name\": \"Göta Artillery Regiment\"\n    }\n  ],\n  \"knowsLanguage\": \"Swedish\",\n  \"nationality\": \"Swedish\",\n  \"education\": \"\",\n  \"award\": [\n    {\n      \"@type\": \"Order\",\n      \"name\": \"Order of the Sword\"\n    },\n    {\n      \"@type\": \"Order\",\n      \"name\": \"Litteris et Artibus\"\n    },\n    {\n      \"@type\": \"Order\",\n      \"name\": \"Royal Victorian Order\"\n    },\n    {\n      \"@type\": \"Order\",\n      \"name\": \"Knight of the First Class of the Order of the Seraphim\"\n    },\n    {\n      \"@type\": \"Award\",\n      \"name\": \"King's Shooting Prize for Battalion Commanders\",\n      \"awardDate\": \"1929\"\n    }\n  ],\n  \"event\": [\n    {\n      \"@type\": \"Event\",\n      \"name\": \"Trip to Egypt and Cyprus\",\n      \"startDate\": \"1930\",\n      \"location\": \"Egypt, Cyprus\"\n    },\n    {\n      \"@type\": \"Event\",\n      \"name\": \"Delaware Jubilee\",\n      \"startDate\": \"1938\",\n      \"location\": \"Delaware, USA\"\n    }\n  ],\n  \"gender\": \"Male\"\n}",
    "structured": {
        "@context": "https://schema.org",
        "@type": "Person",
        "name": "Gunnar Ekeroth",
        "birthDate": "1886-09-16",
        "birthPlace": "Stockholm, Sweden",
        "deathDate": "",
        "deathPlace": "",
        "spouse": {
            "@type": "Person",
            "name": "Ebba Stjärnswärd",
            "marriageDate": "XXXX-XX-XX"
        },
        "children": [
            {
                "@type": "Person",
                "name": "Marianne Ekeroth",
                "birthDate": "1915",
                "occupation": "Insurance company employee",
                "birthPlace": "Stockholm, Sweden"
            },
            {
                "@type": "Person",
                "name": "Carl Gustaf Ekeroth",
                "birthDate": "1917",
                "occupation": "Captain in Wendes artillery regiment",
                "birthPlace": "",
                "spouse": {
                    "@type": "Person",
                    "name": "Magdalena Thott"
                },
                "worksFor": "SKF",
                "worksIn": "Gothenburg, Sweden"
            },
            {
                "@type": "Person",
                "name": "Gunnar Ekeroth",
                "birthDate": "1918",
                "occupation": "Engineer",
                "birthPlace": "Stockholm, Sweden",
                "spouse": {
                    "@type": "Person",
                    "name": "Vera Wästifelit"
                }
            }
        ],
        "jobTitle": "Colonel",
        "worksFor": "Swedish Army",
        "memberOf": [
            {
                "@type": "Organization",
                "name": "Wendes Artillery Regiment"
            },
            {
                "@type": "Organization",
                "name": "Bodiens Artillery Regiment"
            },
            {
                "@type": "Organization",
                "name": "Svea Artillery Regiment"
            },
            {
                "@type": "Organization",
                "name": "Artillery Staff"
            },
            {
                "@type": "Organization",
                "name": "H.R.H. the Crown Prince"
            },
            {
                "@type": "Organization",
                "name": "Göta Artillery Regiment"
            }
        ],
        "knowsLanguage": "Swedish",
        "nationality": "Swedish",
        "education": "",
        "award": [
            {
                "@type": "Order",
                "name": "Order of the Sword"
            },
            {
                "@type": "Order",
                "name": "Litteris et Artibus"
            },
            {
                "@type": "Order",
                "name": "Royal Victorian Order"
            },
            {
                "@type": "Order",
                "name": "Knight of the First Class of the Order of the Seraphim"
            },
            {
                "@type": "Award",
                "name": "King's Shooting Prize for Battalion Commanders",
                "awardDate": "1929"
            }
        ],
        "event": [
            {
                "@type": "Event",
                "name": "Trip to Egypt and Cyprus",
                "startDate": "1930",
                "location": "Egypt, Cyprus"
            },
            {
                "@type": "Event",
                "name": "Delaware Jubilee",
                "startDate": "1938",
                "location": "Delaware, USA"
            }
        ],
        "gender": "Male"
    }
}