{
    "original": "Blomqvist, Nils Sigfrid, bankdirektör, Ämål, f. 6/5/95 i Brålanda, Älvsb. 1., av folksk:lär. J. S. B. o. Anna Janson. G. 23 m. Greta Abenius. Barn: Nils-Erik f. 24, Wilhelm 25, Anna-Greta 28, Sven 29. — Vänersborgs h. a. 1. Bokhåll. i Ensk. Banken i Vänersb. 11, kassör 15, kamr, i A-B Dalslands Bank 18, verkst. dir. i Åmåls Sparbank sed. 29. Huvudman o. v. styr:ordf. där., ordf. i Åmåls civ :-försv:nd o i Åmåls luftsk :fören., ordf. i Dalslands Sångarförb., skattm,. i Scoutfrämj. på Dal, sekr. i Åmåls fas-tigh :’äg:fören., styr :led. i Skarab. o. Älvsb. 1. sparbanksfören., styr :led. i o. kassiaförvaCt. f. Hedbergslka stift. f. värnlösa. Dalslands sångarförb. GM, Försäkr. A-B Nornans GM, Sv. sång:-förb. förtj :t i guld, FMM.",
    "translated": "Blomqvist, Nils Sigfrid, bank director, Ämål, b. May 6, 1895 in Brålanda, Älvsborg County, son of primary school teacher J. S. B. and Anna Janson. Married in 1923 to Greta Abenius. Children: Nils-Erik b. 1924, Wilhelm b. 1925, Anna-Greta b. 1928, Sven b. 1929. Worked as a bookkeeper at Enskilda Banken in Vänersborg in 1911, cashier in 1915, chamberlain in A-B Dalslands Bank in 1918, and executive director in Åmåls Sparbank since 1929. Chairman and board member in Åmåls Sparbank, chairman in Åmåls civilian defense committee and Åmåls air defense association, chairman in Dalslands Sångarförbund (song association), treasurer in Scoutfrämjande på Dal (scout promotion), board member in Skaraborg and Älvsborg County savings bank association, board member and treasurer for the Hedberg Foundation for orphans. Received medals from Dalslands Sångarförbund, Försäkrings A-B Nornan, and Swedish Singers Association. Awarded the Swedish Singers Association's gold medal of merit (Sv. sångförb. förtj.t i guld) and the Order of the Seraphim (FMM).",
    "structured_raw": "{\n  \"@context\": \"https://schema.org\",\n  \"@type\": \"Person\",\n  \"name\": \"Nils Sigfrid Blomqvist\",\n  \"birthDate\": \"1895-05-06\",\n  \"birthPlace\": {\n    \"@type\": \"City\",\n    \"name\": \"Brålanda\"\n  },\n  \"nationality\": \"Swedish\",\n  \"jobTitle\": \"Bank Director\",\n  \"worksFor\": {\n    \"@type\": \"Organization\",\n    \"name\": \"Åmåls Sparbank\"\n  },\n  \"familyName\": \"Blomqvist\",\n  \"givenName\": \"Nils Sigfrid\",\n  \"parent\": [\n    {\n      \"@type\": \"Person\",\n      \"name\": \"J. S. B.\"\n    },\n    {\n      \"@type\": \"Person\",\n      \"name\": \"Anna Janson\"\n    }\n  ],\n  \"spouse\": {\n    \"@type\": \"Person\",\n    \"name\": \"Greta Abenius\",\n    \"marriageDate\": \"1923\"\n  },\n  \"children\": [\n    {\n      \"@type\": \"Person\",\n      \"name\": \"Nils-Erik\",\n      \"birthDate\": \"1924\"\n    },\n    {\n      \"@type\": \"Person\",\n      \"name\": \"Wilhelm\",\n      \"birthDate\": \"1925\"\n    },\n    {\n      \"@type\": \"Person\",\n      \"name\": \"Anna-Greta\",\n      \"birthDate\": \"1928\"\n    },\n    {\n      \"@type\": \"Person\",\n      \"name\": \"Sven\",\n      \"birthDate\": \"1929\"\n    }\n  ],\n  \"memberOf\": [\n    {\n      \"@type\": \"Organization\",\n      \"name\": \"Åmåls civilian defense committee\",\n      \"position\": \"Chairman\"\n    },\n    {\n      \"@type\": \"Organization\",\n      \"name\": \"Åmåls air defense association\",\n      \"position\": \"Chairman\"\n    },\n    {\n      \"@type\": \"Organization\",\n      \"name\": \"Dalslands Sångarförbund\",\n      \"position\": \"Chairman\"\n    },\n    {\n      \"@type\": \"Organization\",\n      \"name\": \"Scoutfrämjande på Dal\",\n      \"position\": \"Treasurer\"\n    },\n    {\n      \"@type\": \"Organization\",\n      \"name\": \"Skaraborg and Älvsborg County savings bank association\",\n      \"position\": \"Board Member\"\n    },\n    {\n      \"@type\": \"Organization\",\n      \"name\": \"Hedberg Foundation for orphans\",\n      \"position\": \"Board Member and Treasurer\"\n    }\n  ],\n  \"honorificSuffix\": [\n    \"GM\",\n    \"Försäkr. A-B Nornans GM\",\n    \"Sv. sångförb. förtj.t i guld\",\n    \"FMM\"\n  ]\n}",
    "structured": {
        "@context": "https://schema.org",
        "@type": "Person",
        "name": "Nils Sigfrid Blomqvist",
        "birthDate": "1895-05-06",
        "birthPlace": {
            "@type": "City",
            "name": "Brålanda"
        },
        "nationality": "Swedish",
        "jobTitle": "Bank Director",
        "worksFor": {
            "@type": "Organization",
            "name": "Åmåls Sparbank"
        },
        "familyName": "Blomqvist",
        "givenName": "Nils Sigfrid",
        "parent": [
            {
                "@type": "Person",
                "name": "J. S. B."
            },
            {
                "@type": "Person",
                "name": "Anna Janson"
            }
        ],
        "spouse": {
            "@type": "Person",
            "name": "Greta Abenius",
            "marriageDate": "1923"
        },
        "children": [
            {
                "@type": "Person",
                "name": "Nils-Erik",
                "birthDate": "1924"
            },
            {
                "@type": "Person",
                "name": "Wilhelm",
                "birthDate": "1925"
            },
            {
                "@type": "Person",
                "name": "Anna-Greta",
                "birthDate": "1928"
            },
            {
                "@type": "Person",
                "name": "Sven",
                "birthDate": "1929"
            }
        ],
        "memberOf": [
            {
                "@type": "Organization",
                "name": "Åmåls civilian defense committee",
                "position": "Chairman"
            },
            {
                "@type": "Organization",
                "name": "Åmåls air defense association",
                "position": "Chairman"
            },
            {
                "@type": "Organization",
                "name": "Dalslands Sångarförbund",
                "position": "Chairman"
            },
            {
                "@type": "Organization",
                "name": "Scoutfrämjande på Dal",
                "position": "Treasurer"
            },
            {
                "@type": "Organization",
                "name": "Skaraborg and Älvsborg County savings bank association",
                "position": "Board Member"
            },
            {
                "@type": "Organization",
                "name": "Hedberg Foundation for orphans",
                "position": "Board Member and Treasurer"
            }
        ],
        "honorificSuffix": [
            "GM",
            "Försäkr. A-B Nornans GM",
            "Sv. sångförb. förtj.t i guld",
            "FMM"
        ]
    }
}