{
    "original": "Forssell, Carl Fredrik Jakob, fil. dr, civilingenjÖT, GöfeboTg, f. 6/4/77 i Asp e bo da, Kopparb. 1., av in t. Abraham F. o. Maria Trahn. G. 04 m. Augusta Gottlieb. Barn: Harry f. 08, Sigvard 10, Nina 14, Ruth 19. — Mo^g:-ex. v. Norra real i Sthlm 95, stud. v. KTH (E) 96-99, v. Sthlm&gt;s högsk. o. univ. i Giessen 99-02, fil. dr i Giessen 02. Assist v. Mass. Inst. of Techn. i Boston 02-03, ing. v. Nat. Carbon Co. i Cleveland 03-08, bruksing. v. Höga-näs-Billesho’lmiS A-B 08-10, verkst. dir. f. A-B Kolm 10-15, konsult, ing. 15-17, grund, av samt verksl. dir. f. Skand. Grafitind. A-B 17-47. Styr :ordf. där samt i TrO’Hh. elektro’kem. arbetsgiv :-förb. 20-47, hed:ordf. i Tro’1’l’h. skarp-skyttefören., led. av skytteförb. överstyr., ord’f. i styr. f. Västg.-Dals ’skytteförb., stadsfullm. 20-26, ordf. i brandstyr. 20-28, suppl. i stadstyr. 3il-38. Föret, ett flertal ’Studie- o. aff :-resor o. som konsult, ing. t. kontin., Engl. o. USA. Skr.: art. i värm’etekn., kem. o. eiektrokem. frågor i in- o. uti. fackpubk RNO, RVO, PatrstGM, fkra skytteutmärk., HedLIVA.",
    "translated": "Forssell, Carl Fredrik Jakob, PhD, MSc in Engineering, from Göteborg, born on April 6th, 1877, in Asp e bo da, Kopparberg County, son of Abraham F. and Maria Trahn. Married in 1904 to Augusta Gottlieb, with children Harry (born 1908), Sigvard (born 1910), Nina (born 1914), and Ruth (born 1919). He attended Norra real in Stockholm in 1895 and studied at KTH (E) from 1896 to 1899, and at Stockholm University and the University of Giessen from 1899 to 1902, where he earned a PhD. He worked as an assistant at the Massachusetts Institute of Technology in Boston from 1902 to 1903, an engineer at National Carbon Co. in Cleveland from 1903 to 1908, a works engineer at Höganäs-Billesholmia A-B from 1908 to 1910, and as managing director for A-B Kolm from 1910 to 1915. He worked as a consultant engineer from 1915 to 1917, and founded and served as managing director for Skand. Grafitind. A-B from 1917 to 1947. He served as chairman of the board at Skand. Grafitind. A-B, as well as the electrochemical employers' association Tro’Hh from 1920 to 1947. He also served as honorary chairman for the Tro’1’l’h sharpshooting association, and was a member of the national shooting association's steering committee. He was the chairman of the board for Västg.-Dals' shooting association, a city council member from 1920 to 1926, chairman of the fire brigade from 1920 to 1928, and a substitute member of the city council from 1931 to 1938. He undertook multiple study and business trips as a consultant engineer, both domestically and abroad, including to the UK and USA. He has publications on heat technology, chemistry, and electrochemistry in various industry publications, both in Sweden and internationally, and has received several awards and honors, including a Royal Medal of the 8th size, Knight of the Order of Vasa, Patent Examiner, Shooting Awards, and the Honorary Livelihood Award.",
    "structured_raw": "{\n  \"@context\": \"https://schema.org\",\n  \"@type\": \"Person\",\n  \"name\": \"Carl Fredrik Jakob Forssell\",\n  \"birthDate\": \"1877-04-06\",\n  \"birthPlace\": {\n    \"@type\": \"Place\",\n    \"name\": \"Asp e bo da, Kopparberg County, Sweden\"\n  },\n  \"deathDate\": \"1947\",\n  \"spouse\": {\n    \"@type\": \"Person\",\n    \"name\": \"Augusta Gottlieb\",\n    \"marriageDate\": \"1904\"\n  },\n  \"children\": [\n    {\n      \"@type\": \"Person\",\n      \"name\": \"Harry Forssell\",\n      \"birthDate\": \"1908\"\n    },\n    {\n      \"@type\": \"Person\",\n      \"name\": \"Sigvard Forssell\",\n      \"birthDate\": \"1910\"\n    },\n    {\n      \"@type\": \"Person\",\n      \"name\": \"Nina Forssell\",\n      \"birthDate\": \"1914\"\n    },\n    {\n      \"@type\": \"Person\",\n      \"name\": \"Ruth Forssell\",\n      \"birthDate\": \"1919\"\n    }\n  ],\n  \"education\": [\n    {\n      \"@type\": \"EducationalOrganization\",\n      \"name\": \"Norra real\",\n      \"startDate\": \"1895\",\n      \"endDate\": \"1895\"\n    },\n    {\n      \"@type\": \"EducationalOrganization\",\n      \"name\": \"KTH\",\n      \"areaOfStudy\": \"Engineering\",\n      \"startDate\": \"1896\",\n      \"endDate\": \"1899\"\n    },\n    {\n      \"@type\": \"EducationalOrganization\",\n      \"name\": \"Stockholm University\"\n    },\n    {\n      \"@type\": \"EducationalOrganization\",\n      \"name\": \"University of Giessen\",\n      \"startDate\": \"1899\",\n      \"endDate\": \"1902\",\n      \"degree\": {\n        \"@type\": \"EducationalDegree\",\n        \"name\": \"PhD\"\n      }\n    }\n  ],\n  \"memberOf\": [\n    {\n      \"@type\": \"Organization\",\n      \"name\": \"Massachusetts Institute of Technology\",\n      \"roleName\": \"Assistant\",\n      \"startDate\": \"1902\",\n      \"endDate\": \"1903\"\n    },\n    {\n      \"@type\": \"Organization\",\n      \"name\": \"National Carbon Co.\",\n      \"roleName\": \"Engineer\",\n      \"startDate\": \"1903\",\n      \"endDate\": \"1908\"\n    },\n    {\n      \"@type\": \"Organization\",\n      \"name\": \"Höganäs-Billesholmia A-B\",\n      \"roleName\": \"Works Engineer\",\n      \"startDate\": \"1908\",\n      \"endDate\": \"1910\"\n    },\n    {\n      \"@type\": \"Organization\",\n      \"name\": \"A-B Kolm\",\n      \"roleName\": \"Managing Director\",\n      \"startDate\": \"1910\",\n      \"endDate\": \"1915\"\n    },\n    {\n      \"@type\": \"Organization\",\n      \"name\": \"Skand. Grafitind. A-B\",\n      \"roleName\": \"Founder and Managing Director\",\n      \"startDate\": \"1917\",\n      \"endDate\": \"1947\"\n    },\n    {\n      \"@type\": \"Organization\",\n      \"name\": \"Tro’Hh Electrochemical Employers' Association\",\n      \"roleName\": \"Chairman of the Board\",\n      \"startDate\": \"1920\",\n      \"endDate\": \"1947\"\n    }\n  ],\n  \"awards\": [\n    {\n      \"@type\": \"Medal\",\n      \"name\": \"Royal Medal of the 8th size\"\n    },\n    {\n      \"@type\": \"Order\",\n      \"name\": \"Knight of the Order of Vasa\"\n    },\n    {\n      \"@type\": \"Patent\",\n      \"name\": \"Patent Examiner\"\n    },\n    {\n      \"@type\": \"Medal\",\n      \"name\": \"Shooting Awards\"\n    },\n    {\n      \"@type\": \"Medal\",\n      \"name\": \"Honorary Livelihood Award\"\n    }\n  ],\n  \"description\": \"Swedish scholar and engineer known for his work in heat technology, chemistry, and electrochemistry.\"\n}",
    "structured": {
        "@context": "https://schema.org",
        "@type": "Person",
        "name": "Carl Fredrik Jakob Forssell",
        "birthDate": "1877-04-06",
        "birthPlace": {
            "@type": "Place",
            "name": "Asp e bo da, Kopparberg County, Sweden"
        },
        "deathDate": "1947",
        "spouse": {
            "@type": "Person",
            "name": "Augusta Gottlieb",
            "marriageDate": "1904"
        },
        "children": [
            {
                "@type": "Person",
                "name": "Harry Forssell",
                "birthDate": "1908"
            },
            {
                "@type": "Person",
                "name": "Sigvard Forssell",
                "birthDate": "1910"
            },
            {
                "@type": "Person",
                "name": "Nina Forssell",
                "birthDate": "1914"
            },
            {
                "@type": "Person",
                "name": "Ruth Forssell",
                "birthDate": "1919"
            }
        ],
        "education": [
            {
                "@type": "EducationalOrganization",
                "name": "Norra real",
                "startDate": "1895",
                "endDate": "1895"
            },
            {
                "@type": "EducationalOrganization",
                "name": "KTH",
                "areaOfStudy": "Engineering",
                "startDate": "1896",
                "endDate": "1899"
            },
            {
                "@type": "EducationalOrganization",
                "name": "Stockholm University"
            },
            {
                "@type": "EducationalOrganization",
                "name": "University of Giessen",
                "startDate": "1899",
                "endDate": "1902",
                "degree": {
                    "@type": "EducationalDegree",
                    "name": "PhD"
                }
            }
        ],
        "memberOf": [
            {
                "@type": "Organization",
                "name": "Massachusetts Institute of Technology",
                "roleName": "Assistant",
                "startDate": "1902",
                "endDate": "1903"
            },
            {
                "@type": "Organization",
                "name": "National Carbon Co.",
                "roleName": "Engineer",
                "startDate": "1903",
                "endDate": "1908"
            },
            {
                "@type": "Organization",
                "name": "Höganäs-Billesholmia A-B",
                "roleName": "Works Engineer",
                "startDate": "1908",
                "endDate": "1910"
            },
            {
                "@type": "Organization",
                "name": "A-B Kolm",
                "roleName": "Managing Director",
                "startDate": "1910",
                "endDate": "1915"
            },
            {
                "@type": "Organization",
                "name": "Skand. Grafitind. A-B",
                "roleName": "Founder and Managing Director",
                "startDate": "1917",
                "endDate": "1947"
            },
            {
                "@type": "Organization",
                "name": "Tro’Hh Electrochemical Employers' Association",
                "roleName": "Chairman of the Board",
                "startDate": "1920",
                "endDate": "1947"
            }
        ],
        "awards": [
            {
                "@type": "Medal",
                "name": "Royal Medal of the 8th size"
            },
            {
                "@type": "Order",
                "name": "Knight of the Order of Vasa"
            },
            {
                "@type": "Patent",
                "name": "Patent Examiner"
            },
            {
                "@type": "Medal",
                "name": "Shooting Awards"
            },
            {
                "@type": "Medal",
                "name": "Honorary Livelihood Award"
            }
        ],
        "description": "Swedish scholar and engineer known for his work in heat technology, chemistry, and electrochemistry."
    }
}