{
    "original": "Alen, Alvin Agaton, tandläkare, Göteborg, f. 10/12/88 i Gbg av stadskem., fil. dr J. E. A. o. Anna Lundmark. G. 17 m. Anna Hinke. Barn: Bertil f. 18, Bengt 20. — Stud:ex. v. Gbgs h. latin 09, tandl :kand. 11, tandl. 14. Stud:resa t. Berhn 14. Prakt, i Gbg sed. 15. Sekr. i Gbgs tandl :,sällsk. 23-25 o. 29-30, bibi. o. konservator 17-36, konservator 37-46, ordf. 35-36 o. samtid. ordf. i ’sällsk. förb:avd., ordf. i GbgS’ skyttekrets 22-24, v. ordf. i Gbgs o. Boh. skytt ef örb. o. dess repr. i Svsfb, ordf. i Göta Par Bricoles sångkör. Svsfb O’. Sv. ’SpoTtskytteförb. m. fl. förtj :M.",
    "translated": "Alen, Alvin Agaton, dentist, Gothenburg, b. December 10, 1888 in Gothenburg to city chemist, PhD J. E. A. and Anna Lundmark. Married to Anna Hinke in 1917. Children: Bertil, b. 1918, Bengt, b. 1920. Completed high school at Gothenburg Latin School in 1909, graduated from dental school in 1911, became a licensed dentist in 1914. Went on a study trip to Berlin in 1914. Has been practicing dentistry in Gothenburg since 1915. Secretary of the Gothenburg Dental Society from 1923-1925 and 1929-1930, librarian and conservator from 1917-1936, conservator from 1937-1946, chairman in 1935-1936, and concurrent chairman of the Swedish Dental Society's local chapter. Chairman of the Gothenburg Shooting District from 1922-1924, deputy chairman of the Gothenburg and Bohus Shooting Association and its representative in the Swedish Shooting Federation, chairman of the Göta Par Bricoles singing choir, and member of the Swedish Sports Shooting Association and other organizations. Has received several honorary awards.",
    "structured_raw": "{\n  \"@context\": \"https://schema.org\",\n  \"@type\": \"Person\",\n  \"name\": \"Alvin Agaton Alen\",\n  \"jobTitle\": \"Dentist\",\n  \"birthDate\": \"1888-12-10\",\n  \"birthPlace\": \"Gothenburg, Sweden\",\n  \"nationality\": \"Swedish\",\n  \"alumniOf\": [\n    {\n      \"@type\": \"CollegeOrUniversity\",\n      \"name\": \"Gothenburg Latin School\",\n      \"endDate\": \"1909\"\n    },\n    {\n      \"@type\": \"CollegeOrUniversity\",\n      \"name\": \"Dental School\",\n      \"endDate\": \"1911\"\n    }\n  ],\n  \"parent\": [\n    {\n      \"@type\": \"Person\",\n      \"name\": \"J. E. A.\",\n      \"jobTitle\": \"PhD City Chemist\"\n    },\n    {\n      \"@type\": \"Person\",\n      \"name\": \"Anna Lundmark\"\n    }\n  ],\n  \"spouse\": {\n    \"@type\": \"Person\",\n    \"name\": \"Anna Hinke\",\n    \"marriageDate\": \"1917\"\n  },\n  \"children\": [\n    {\n      \"@type\": \"Person\",\n      \"name\": \"Bertil\",\n      \"birthDate\": \"1918\"\n    },\n    {\n      \"@type\": \"Person\",\n      \"name\": \"Bengt\",\n      \"birthDate\": \"1920\"\n    }\n  ],\n  \"description\": \"Alvin Agaton Alen was a Swedish dentist born in Gothenburg on December 10, 1888. He studied at the Gothenburg Latin School and graduated from dental school in 1911. Alen went on a study trip to Berlin in 1914 and has been practicing dentistry in Gothenburg since 1915. He was secretary of the Gothenburg Dental Society, librarian, conservator, and chairman of the Swedish Dental Society's local chapter. Alen was also involved in several shooting organizations and received several honorary awards.\"\n}",
    "structured": {
        "@context": "https://schema.org",
        "@type": "Person",
        "name": "Alvin Agaton Alen",
        "jobTitle": "Dentist",
        "birthDate": "1888-12-10",
        "birthPlace": "Gothenburg, Sweden",
        "nationality": "Swedish",
        "alumniOf": [
            {
                "@type": "CollegeOrUniversity",
                "name": "Gothenburg Latin School",
                "endDate": "1909"
            },
            {
                "@type": "CollegeOrUniversity",
                "name": "Dental School",
                "endDate": "1911"
            }
        ],
        "parent": [
            {
                "@type": "Person",
                "name": "J. E. A.",
                "jobTitle": "PhD City Chemist"
            },
            {
                "@type": "Person",
                "name": "Anna Lundmark"
            }
        ],
        "spouse": {
            "@type": "Person",
            "name": "Anna Hinke",
            "marriageDate": "1917"
        },
        "children": [
            {
                "@type": "Person",
                "name": "Bertil",
                "birthDate": "1918"
            },
            {
                "@type": "Person",
                "name": "Bengt",
                "birthDate": "1920"
            }
        ],
        "description": "Alvin Agaton Alen was a Swedish dentist born in Gothenburg on December 10, 1888. He studied at the Gothenburg Latin School and graduated from dental school in 1911. Alen went on a study trip to Berlin in 1914 and has been practicing dentistry in Gothenburg since 1915. He was secretary of the Gothenburg Dental Society, librarian, conservator, and chairman of the Swedish Dental Society's local chapter. Alen was also involved in several shooting organizations and received several honorary awards."
    }
}