{
    "original": "Öhman, Karl Johan Robert, prakt, läkare, Norrköping, f. 13/7/98 i Sthlm av kyrkoh. Karl Ö. o. Davida Sylvan. G. m. Gerd Engström. Barn: Rolf f. 45. — Stud:ex. i Sthlm 16, tysk läk:-ex. i Marburg an der Lalin 26, med. kand. 28 o. med. lic. 30 i Sthlm. E. läk. i Töreboda distr. 30, tf. andre und:läk. v. Hällnäs san. fem mån. 30-31, förordn. s. prov:läk. i ol. distr. somm. 31, assist :läk. v. Lidköp. las. kir. avd. åtta mån. 31-32, tf. und :läk. v. Filipstads las. 32, e. läk. v. Mariebergs sjukh. fyra mån. 32-33, prakt, läk. i Norrköp. sed. 33, tf. prov:läk. i Norrköp. distr. kort. tider 33-41, tf. andre stadsläk. i Norrköp. okt. 40-febr. 43. *Öhman, Sofia Lovisa, fil. mag., läroverksadjunkt, Norrköping, f. 21/7/92. — Stud:ex. H, fil. kand. 15, fil. mag. 16. Lär. v. Umeå folksk :sem. 15, i Lindesberg 16, i Malmberget 17, 18-20, i Tierp 20, ord. ämneslär. där 21, tf. bitr. förest. 3i2, bitr. förest. 33’, adj. i mo-dersm. o. eng. v. h. a. 1. i Norrköp. fr.",
    "translated": "Öhman, Karl Johan Robert, prakt. (praktiserande) läkare (medical doctor), Norrköping, born 13/7/98 in Stockholm, son of reverend Karl Ö. and Davida Sylvan. Married to Gerd Engström. Children: Rolf, born in 1945. Completed high school in Stockholm in 1916, medical degree in Germany in Marburg an der Lahn in 1926, Bachelor of Medicine in Stockholm in 1928, and medical license in 1930 in Stockholm. Worked as a doctor in the Töreboda district in 1930, temporary senior physician at the Hällnäs sanatorium for five months in 1930-1931, appointed as a provisional doctor in various districts in the summer of 1931, assistant doctor at the surgical department of Lidköping hospital for eight months in 1931-1932, temporary junior doctor at Filipstad hospital in 1932, employed doctor at Marieberg hospital for four months in 1932-1933, and practicing doctor in Norrköping since 1933. Served as temporary provisional doctor in the Norrköping district for short periods between 1933 and 1941, and as temporary deputy city physician in Norrköping from October 1940 to February 1943. \n\nÖhman, Sofia Lovisa, fil. (filosofie) mag. (Master of Arts), high school teacher, Norrköping, born 21/7/92. Completed high school in H, Bachelor of Arts in 1915, and Master of Arts in 1916. Taught at Umeå public school seminar in 1915, in Lindesberg in 1916, in Malmberget in 1917 and 1920, and in Tierp in 1920. Became a regular subject teacher in Tierp in 1921, acting assistant supervisor in 1932, and deputy supervisor in 1933. Adjunct in mother tongue and English at H a. l. in Norrköping from [year missing].\n\nNote: The abbreviation '\\d\\d m. partners name' means that the person married in the year 19xx.",
    "structured_raw": "{\n  \"@context\": \"https://schema.org\",\n  \"@type\": \"Person\",\n  \"name\": \"Karl Johan Robert Öhman\",\n  \"givenName\": \"Karl\",\n  \"familyName\": \"Öhman\",\n  \"birthDate\": \"1898-07-13\",\n  \"birthPlace\": \"Stockholm\",\n  \"jobTitle\": \"Medical Doctor\",\n  \"description\": \"Practicing doctor in Norrköping.\",\n  \"spouse\": {\n    \"@type\": \"Person\",\n    \"name\": \"Gerd Engström\"\n  },\n  \"children\": {\n    \"@type\": \"Person\",\n    \"name\": \"Rolf Öhman\",\n    \"birthDate\": \"1945\"\n  },\n  \"education\": [\n    {\n      \"@type\": \"EducationalOccupationalCredential\",\n      \"credentialCategory\": \"SecondaryEducationCredential\",\n      \"educationalLevel\": \"High School\",\n      \"startDate\": \"1916\",\n      \"endDate\": \"1916\"\n    },\n    {\n      \"@type\": \"EducationalOccupationalCredential\",\n      \"credentialCategory\": \"MedicalDegreeCredential\",\n      \"educationalLevel\": \"Bachelor's Degree\",\n      \"startDate\": \"1928\",\n      \"endDate\": \"1928\"\n    },\n    {\n      \"@type\": \"EducationalOccupationalCredential\",\n      \"credentialCategory\": \"MedicalLicenseCredential\",\n      \"educationalLevel\": \"Medical License\",\n      \"startDate\": \"1930\",\n      \"endDate\": \"1930\"\n    }\n  ],\n  \"work\": [\n    {\n      \"@type\": \"MedicalOrganization\",\n      \"name\": \"Töreboda District\",\n      \"jobTitle\": \"Doctor\",\n      \"startDate\": \"1930\",\n      \"endDate\": \"1930\"\n    },\n    {\n      \"@type\": \"MedicalOrganization\",\n      \"name\": \"Hällnäs Sanatorium\",\n      \"jobTitle\": \"Temporary Senior Physician\",\n      \"startDate\": \"1930\",\n      \"endDate\": \"1931\"\n    },\n    {\n      \"@type\": \"MedicalOrganization\",\n      \"name\": \"Lidköping Hospital\",\n      \"jobTitle\": \"Assistant Doctor\",\n      \"startDate\": \"1931\",\n      \"endDate\": \"1932\"\n    },\n    {\n      \"@type\": \"MedicalOrganization\",\n      \"name\": \"Filipstad Hospital\",\n      \"jobTitle\": \"Temporary Junior Doctor\",\n      \"startDate\": \"1932\",\n      \"endDate\": \"1932\"\n    },\n    {\n      \"@type\": \"MedicalOrganization\",\n      \"name\": \"Marieberg Hospital\",\n      \"jobTitle\": \"Employed Doctor\",\n      \"startDate\": \"1932\",\n      \"endDate\": \"1933\"\n    },\n    {\n      \"@type\": \"MedicalOrganization\",\n      \"name\": \"Norrköping\",\n      \"jobTitle\": \"Practicing Doctor\",\n      \"startDate\": \"1933\"\n    }\n  ]\n}",
    "structured": {
        "@context": "https://schema.org",
        "@type": "Person",
        "name": "Karl Johan Robert Öhman",
        "givenName": "Karl",
        "familyName": "Öhman",
        "birthDate": "1898-07-13",
        "birthPlace": "Stockholm",
        "jobTitle": "Medical Doctor",
        "description": "Practicing doctor in Norrköping.",
        "spouse": {
            "@type": "Person",
            "name": "Gerd Engström"
        },
        "children": {
            "@type": "Person",
            "name": "Rolf Öhman",
            "birthDate": "1945"
        },
        "education": [
            {
                "@type": "EducationalOccupationalCredential",
                "credentialCategory": "SecondaryEducationCredential",
                "educationalLevel": "High School",
                "startDate": "1916",
                "endDate": "1916"
            },
            {
                "@type": "EducationalOccupationalCredential",
                "credentialCategory": "MedicalDegreeCredential",
                "educationalLevel": "Bachelor's Degree",
                "startDate": "1928",
                "endDate": "1928"
            },
            {
                "@type": "EducationalOccupationalCredential",
                "credentialCategory": "MedicalLicenseCredential",
                "educationalLevel": "Medical License",
                "startDate": "1930",
                "endDate": "1930"
            }
        ],
        "work": [
            {
                "@type": "MedicalOrganization",
                "name": "Töreboda District",
                "jobTitle": "Doctor",
                "startDate": "1930",
                "endDate": "1930"
            },
            {
                "@type": "MedicalOrganization",
                "name": "Hällnäs Sanatorium",
                "jobTitle": "Temporary Senior Physician",
                "startDate": "1930",
                "endDate": "1931"
            },
            {
                "@type": "MedicalOrganization",
                "name": "Lidköping Hospital",
                "jobTitle": "Assistant Doctor",
                "startDate": "1931",
                "endDate": "1932"
            },
            {
                "@type": "MedicalOrganization",
                "name": "Filipstad Hospital",
                "jobTitle": "Temporary Junior Doctor",
                "startDate": "1932",
                "endDate": "1932"
            },
            {
                "@type": "MedicalOrganization",
                "name": "Marieberg Hospital",
                "jobTitle": "Employed Doctor",
                "startDate": "1932",
                "endDate": "1933"
            },
            {
                "@type": "MedicalOrganization",
                "name": "Norrköping",
                "jobTitle": "Practicing Doctor",
                "startDate": "1933"
            }
        ]
    }
}