{
    "original": "Dahl, Torsten Salomon, direktörs-asiSLStent, Linköping, f. 30/12/97 i Växjö av förest. Salomon D. o. Emma Kristina Dahil. G. 27 m. Anna-Greta Bäcklund. Barn: Gunnar f. 32. — Stud iex. v. Växjö h. a. 1. 17. Värnpl. fänrik 40. Banktj :man i Sydsv. Kredit A-B o. A-B Sydsv. Banken 18-24, förvalt. v. Seffle Bryggeri i Säffle (tillh. A-B Svea Brygg, i Filipstad) 25-29, disp. v. Filipstads Bageri A-B i Filipstad 30-32, kont :chef, sederm. disp. v. A-B Arvid Petterssons Bröd-fa’br. i Eskilstuna 33-36, kamr. v. A-B Nya Centr |bryggeriet i Linköp. 37-40, dirrassist. där sed. 40. Led. av styr. f. Filipstads Bageri A-B 30-32, A-B Arvid Petterssons Brödfabr. 35-36 o. A-B Druvans Mineralvattenfabr. i Linköp. sed. 45, -led. av 45 års fastig-h:tax:nd i Linköp., suppl. i rör:tax:-ndn där sed. 44. Medl. av Frimurarorden. Hobbies: filateli, sport.",
    "translated": "Dahl, Torsten Salomon, director-ASIStent, Linköping, born on 30/12/97 in Växjö to parents Salomon D. and Emma Kristina Dahil. Married in 1927 to Anna-Greta Bäcklund. They had one child, Gunnar, born in 1932. Torsten completed his studies at Växjö high school in 1917 and was a sergeant in the military in 1940. He worked as a bank clerk for Sydsv. Kredit A-B and A-B Sydsv. Banken from 1918 to 1924. Then he managed the Seffle Bryggeri in Säffle (belonging to A-B Svea Brygg, in Filipstad) from 1925 to 1929. From 1930 to 1932, he was the director of Filipstads Bageri A-B in Filipstad, then became the head of the department and later a director at the A-B Arvid Petterssons Bröd-fa’br. in Eskilstuna from 1933 to 1936. In 1937, he became a chamberlaine at A-B Nya Centrbryggeriet in Linköping, and later an assistant director in 1940. He served on the board of directors for Filipstads Bageri A-B from 1930 to 1932, A-B Arvid Petterssons Brödfabr from 1935 to 1936 and A-B Druvans Mineralvattenfabr. in Linköp. since 1945. He was a member of the 45-year real estate commission in Linköping and has been a member of the pipe commission since 1944. He was a member of the Freemason Order and had hobbies of philately and sports.",
    "structured_raw": "{\n  \"@context\": \"https://schema.org\",\n  \"@type\": \"Person\",\n  \"name\": \"Torsten Salomon Dahl\",\n  \"birthDate\": \"1897-12-30\",\n  \"birthPlace\": \"Växjö, Sweden\",\n  \"parents\": [\n    {\n      \"@type\": \"Person\",\n      \"name\": \"Salomon Dahl\"\n    },\n    {\n      \"@type\": \"Person\",\n      \"name\": \"Emma Kristina Dahil\"\n    }\n  ],\n  \"spouse\": {\n    \"@type\": \"Person\",\n    \"name\": \"Anna-Greta Bäcklund\",\n    \"marriageDate\": \"1927\"\n  },\n  \"children\": [\n    {\n      \"@type\": \"Person\",\n      \"name\": \"Gunnar Dahl\",\n      \"birthDate\": \"1932\"\n    }\n  ],\n  \"education\": {\n    \"@type\": \"EducationalOrganization\",\n    \"name\": \"Växjö High School\",\n    \"endDate\": \"1917\"\n  },\n  \"militaryService\": {\n    \"@type\": \"MilitaryService\",\n    \"serviceType\": \"Sergeant\",\n    \"startDate\": \"1940\"\n  },\n  \"jobTitle\": \"Director-ASIStent\",\n  \"memberOf\": [\n    {\n      \"@type\": \"Organization\",\n      \"name\": \"Frimurarorden\"\n    }\n  ],\n  \"hobbies\": \"Philately, Sport\",\n  \"worksFor\": [\n    {\n      \"@type\": \"Organization\",\n      \"name\": \"Sydsv. Kredit A-B\"\n    },\n    {\n      \"@type\": \"Organization\",\n      \"name\": \"A-B Sydsv. Banken\",\n      \"startDate\": \"1918\",\n      \"endDate\": \"1924\"\n    },\n    {\n      \"@type\": \"Organization\",\n      \"name\": \"Seffle Bryggeri\"\n    },\n    {\n      \"@type\": \"Organization\",\n      \"name\": \"A-B Svea Brygg\"\n    },\n    {\n      \"@type\": \"Organization\",\n      \"name\": \"Filipstads Bageri A-B\",\n      \"startDate\": \"1930\",\n      \"endDate\": \"1932\"\n    },\n    {\n      \"@type\": \"Organization\",\n      \"name\": \"A-B Arvid Petterssons Bröd-fa’br.\",\n      \"startDate\": \"1933\",\n      \"endDate\": \"1936\"\n    },\n    {\n      \"@type\": \"Organization\",\n      \"name\": \"A-B Nya Centrbryggeriet\",\n      \"startDate\": \"1937\",\n      \"endDate\": \"1940\"\n    },\n    {\n      \"@type\": \"Organization\",\n      \"name\": \"A-B Druvans Mineralvattenfabr.\",\n      \"startDate\": \"1945\"\n    }\n  ],\n  \"hasOccupation\": [\n    {\n      \"@type\": \"Occupation\",\n      \"name\": \"Bank Clerk\"\n    },\n    {\n      \"@type\": \"Occupation\",\n      \"name\": \"Manager\"\n    },\n    {\n      \"@type\": \"Occupation\",\n      \"name\": \"Department Head\"\n    },\n    {\n      \"@type\": \"Occupation\",\n      \"name\": \"Director\"\n    },\n    {\n      \"@type\": \"Occupation\",\n      \"name\": \"Chamberlaine\"\n    },\n    {\n      \"@type\": \"Occupation\",\n      \"name\": \"Assistant Director\"\n    }\n  ]\n}",
    "structured": {
        "@context": "https://schema.org",
        "@type": "Person",
        "name": "Torsten Salomon Dahl",
        "birthDate": "1897-12-30",
        "birthPlace": "Växjö, Sweden",
        "parents": [
            {
                "@type": "Person",
                "name": "Salomon Dahl"
            },
            {
                "@type": "Person",
                "name": "Emma Kristina Dahil"
            }
        ],
        "spouse": {
            "@type": "Person",
            "name": "Anna-Greta Bäcklund",
            "marriageDate": "1927"
        },
        "children": [
            {
                "@type": "Person",
                "name": "Gunnar Dahl",
                "birthDate": "1932"
            }
        ],
        "education": {
            "@type": "EducationalOrganization",
            "name": "Växjö High School",
            "endDate": "1917"
        },
        "militaryService": {
            "@type": "MilitaryService",
            "serviceType": "Sergeant",
            "startDate": "1940"
        },
        "jobTitle": "Director-ASIStent",
        "memberOf": [
            {
                "@type": "Organization",
                "name": "Frimurarorden"
            }
        ],
        "hobbies": "Philately, Sport",
        "worksFor": [
            {
                "@type": "Organization",
                "name": "Sydsv. Kredit A-B"
            },
            {
                "@type": "Organization",
                "name": "A-B Sydsv. Banken",
                "startDate": "1918",
                "endDate": "1924"
            },
            {
                "@type": "Organization",
                "name": "Seffle Bryggeri"
            },
            {
                "@type": "Organization",
                "name": "A-B Svea Brygg"
            },
            {
                "@type": "Organization",
                "name": "Filipstads Bageri A-B",
                "startDate": "1930",
                "endDate": "1932"
            },
            {
                "@type": "Organization",
                "name": "A-B Arvid Petterssons Bröd-fa’br.",
                "startDate": "1933",
                "endDate": "1936"
            },
            {
                "@type": "Organization",
                "name": "A-B Nya Centrbryggeriet",
                "startDate": "1937",
                "endDate": "1940"
            },
            {
                "@type": "Organization",
                "name": "A-B Druvans Mineralvattenfabr.",
                "startDate": "1945"
            }
        ],
        "hasOccupation": [
            {
                "@type": "Occupation",
                "name": "Bank Clerk"
            },
            {
                "@type": "Occupation",
                "name": "Manager"
            },
            {
                "@type": "Occupation",
                "name": "Department Head"
            },
            {
                "@type": "Occupation",
                "name": "Director"
            },
            {
                "@type": "Occupation",
                "name": "Chamberlaine"
            },
            {
                "@type": "Occupation",
                "name": "Assistant Director"
            }
        ]
    }
}