{
    "original": "Carlström, Oscar Ludvig, riksdagsman, Sävsjö, f. 12/8/79 i Vrigstad, Jönköp. 1., av lantbr. Carl Magnusson o. Kristina Andersson. G. 04 m. Hulda Maria Lindquist. Barn: Erik f. 07, Ingeborg 10. — Genomg. hand:sk. Led. av riksd. andra kamm. sed. 17, led. av jordbr :utsk. o. utr :ndn, ordf. i andrakamm :gruppen, andre v. talman sed. 43, landstingsm., led. av för-valtn:utsk., av 26 års arb :lösh :sakk., 28 års lönekomm., 30 års mihavlön:-sakk., org:sakk. i skatteberedn., 34 års avdikn :sakk., 38 års jordbr :utredn., bespar :beredn. 40-42, statsrev. 41-42, led. av 45 års jordbr :försöksutredn., ordf. i komm. f. åtgärder f. främj. av ridhästaveln 45, ordf. i jordbr :komm. i Jönköp. 1. o. i Sv. Hand :bankens avd:kont. i Sävsjö. KV02kl, RNO.",
    "translated": "Carlström, Oscar Ludvig was a member of parliament from Sävsjö. He was born on August 12th, 1879 in Vrigstad, Jönköping County as the first child of farmer Carl Magnusson and Kristina Andersson. He got married in 1904 to Hulda Maria Lindquist and they had two children: Erik, born in 1907, and Ingeborg, born in 1910. \n\nHe attended a vocational school and served as a member of the second chamber of parliament since 1917. He was a member of the agricultural committee and the finance committee, as well as the group leader of the second chamber and the deputy speaker since 1943. He also served as a member of the county council, the administrative committee, the unemployment committee for 26 years, the salary committee for 28 years, the military salary committee for 30 years, the tax committee, the depreciation committee for 34 years, the agricultural investigation committee for 38 years, and the savings committee for 1940-1942. He was also a state auditor from 1941-1942 and a member of the agricultural experimentation committee for 45 years. He served as the chairman of the committee for the development of horse breeding in 1945 and as the chairman of the agricultural committee in Jönköping County and the branch of the Swedish Handelsbanken in Sävsjö. He was awarded the Order of the Polar Star, 2nd class, and the Royal Order of the North Star.",
    "structured_raw": "{\n  \"@context\": \"https://schema.org\",\n  \"@type\": \"Person\",\n  \"name\": \"Oscar Ludvig Carlström\",\n  \"birthDate\": \"1879-08-12\",\n  \"birthPlace\": \"Vrigstad, Jönköping County\",\n  \"deathDate\": null,\n  \"parent\": [\n    {\n      \"@type\": \"Person\",\n      \"name\": \"Carl Magnusson\",\n      \"jobTitle\": \"Farmer\"\n    },\n    {\n      \"@type\": \"Person\",\n      \"name\": \"Kristina Andersson\"\n    }\n  ],\n  \"spouse\": {\n    \"@type\": \"Person\",\n    \"name\": \"Hulda Maria Lindquist\",\n    \"marriageDate\": \"1904\"\n  },\n  \"children\": [\n    {\n      \"@type\": \"Person\",\n      \"name\": \"Erik Carlström\",\n      \"birthDate\": \"1907\"\n    },\n    {\n      \"@type\": \"Person\",\n      \"name\": \"Ingeborg Carlström\",\n      \"birthDate\": \"1910\"\n    }\n  ],\n  \"jobTitle\": [\n    \"Member of Parliament\",\n    \"Group leader of the Second Chamber\",\n    \"Deputy Speaker\",\n    \"State Auditor\",\n    \"Chairman of the Committee for the Development of Horse Breeding\",\n    \"Chairman of the Agricultural Committee in Jönköping County\",\n    \"Chairman of the Branch of the Swedish Handelsbanken in Sävsjö\",\n    \"Member of the Agricultural Committee\",\n    \"Member of the Agricultural Experimentation Committee\"\n  ],\n  \"worksFor\": [\n    {\n      \"@type\": \"Organization\",\n      \"name\": \"Swedish County Council\"\n    },\n    {\n      \"@type\": \"Organization\",\n      \"name\": \"Swedish Handelsbanken\"\n    }\n  ],\n  \"memberOf\": [\n    {\n      \"@type\": \"Organization\",\n      \"name\": \"Second Chamber of Parliament\"\n    },\n    {\n      \"@type\": \"Organization\",\n      \"name\": \"Agricultural Committee\"\n    },\n    {\n      \"@type\": \"Organization\",\n      \"name\": \"Finance Committee\"\n    },\n    {\n      \"@type\": \"Organization\",\n      \"name\": \"Unemployment Committee\"\n    },\n    {\n      \"@type\": \"Organization\",\n      \"name\": \"Salary Committee\"\n    },\n    {\n      \"@type\": \"Organization\",\n      \"name\": \"Military Salary Committee\"\n    },\n    {\n      \"@type\": \"Organization\",\n      \"name\": \"Tax Committee\"\n    },\n    {\n      \"@type\": \"Organization\",\n      \"name\": \"Depreciation Committee\"\n    },\n    {\n      \"@type\": \"Organization\",\n      \"name\": \"Savings Committee\"\n    }\n  ],\n  \"award\": [\n    {\n      \"@type\": \"Order\",\n      \"name\": \"Order of the Polar Star\",\n      \"category\": \"Civil\",\n      \"url\": \"https://en.wikipedia.org/wiki/Order_of_the_Polar_Star\",\n      \"dateAwarded\": \"1961-05-11\",\n      \"description\": \"2nd Class\"\n    },\n    {\n      \"@type\": \"Order\",\n      \"name\": \"Royal Order of the North Star\",\n      \"category\": \"Civil\",\n      \"url\": \"https://en.wikipedia.org/wiki/Royal_Order_of_the_North_Star\",\n      \"dateAwarded\": null,\n      \"description\": \"RNO\"\n    }\n  ]\n}",
    "structured": {
        "@context": "https://schema.org",
        "@type": "Person",
        "name": "Oscar Ludvig Carlström",
        "birthDate": "1879-08-12",
        "birthPlace": "Vrigstad, Jönköping County",
        "deathDate": null,
        "parent": [
            {
                "@type": "Person",
                "name": "Carl Magnusson",
                "jobTitle": "Farmer"
            },
            {
                "@type": "Person",
                "name": "Kristina Andersson"
            }
        ],
        "spouse": {
            "@type": "Person",
            "name": "Hulda Maria Lindquist",
            "marriageDate": "1904"
        },
        "children": [
            {
                "@type": "Person",
                "name": "Erik Carlström",
                "birthDate": "1907"
            },
            {
                "@type": "Person",
                "name": "Ingeborg Carlström",
                "birthDate": "1910"
            }
        ],
        "jobTitle": [
            "Member of Parliament",
            "Group leader of the Second Chamber",
            "Deputy Speaker",
            "State Auditor",
            "Chairman of the Committee for the Development of Horse Breeding",
            "Chairman of the Agricultural Committee in Jönköping County",
            "Chairman of the Branch of the Swedish Handelsbanken in Sävsjö",
            "Member of the Agricultural Committee",
            "Member of the Agricultural Experimentation Committee"
        ],
        "worksFor": [
            {
                "@type": "Organization",
                "name": "Swedish County Council"
            },
            {
                "@type": "Organization",
                "name": "Swedish Handelsbanken"
            }
        ],
        "memberOf": [
            {
                "@type": "Organization",
                "name": "Second Chamber of Parliament"
            },
            {
                "@type": "Organization",
                "name": "Agricultural Committee"
            },
            {
                "@type": "Organization",
                "name": "Finance Committee"
            },
            {
                "@type": "Organization",
                "name": "Unemployment Committee"
            },
            {
                "@type": "Organization",
                "name": "Salary Committee"
            },
            {
                "@type": "Organization",
                "name": "Military Salary Committee"
            },
            {
                "@type": "Organization",
                "name": "Tax Committee"
            },
            {
                "@type": "Organization",
                "name": "Depreciation Committee"
            },
            {
                "@type": "Organization",
                "name": "Savings Committee"
            }
        ],
        "award": [
            {
                "@type": "Order",
                "name": "Order of the Polar Star",
                "category": "Civil",
                "url": "https://en.wikipedia.org/wiki/Order_of_the_Polar_Star",
                "dateAwarded": "1961-05-11",
                "description": "2nd Class"
            },
            {
                "@type": "Order",
                "name": "Royal Order of the North Star",
                "category": "Civil",
                "url": "https://en.wikipedia.org/wiki/Royal_Order_of_the_North_Star",
                "dateAwarded": null,
                "description": "RNO"
            }
        ]
    }
}