{
    "original": "Jernström, Åke Jakob, överlantmätare, Vänersborg, f. 26/7/98 i Lidköp. av tandl. Isac J. o. August Fröberg. G. 28 m. Gerda Isaksson. Barn: Uil-la-Brita f. 31, Gunnar -38. — Stud:ex. i Skara 16, KTH (V) 16-20, lant-mätiex. 22, kulturtekn. ex. 26. E. lantmät. i Skarab. 1. 22-28, assist, i Västerb. 1. 28-30, tf. distr :lantmät. i Väddö distr. 30, e. lantmät. i Örebro 1. 31-33, tf. distr rlantmät. i Ronneby distr. 33-35, utn. byråing. i lantmät :-styr. 33, tjg. i styr. 3’5-36, utn. distr :-lantmät. i Lindes distr. 35, överlant-mät. i Älvsb. 1. ;sed. 36. Ordf. i ex-propr :ndr 41 o. i styr. f. Älvsb. 1. stadshypoteksfören. o. Västg.-Dals bo-stadskreditfören. 42, led. av kristidsstyr. f. Älvsb. 1. n. omr. 44 o. av styr. f. System A-B i Vänersborg 45. RNO.",
    "translated": "Jernström, Åke Jakob, Chief Surveyor, Vänersborg, b. 26/7/98 in Lidköping, the son of the dentist Isac J. and August Fröberg. Married to Gerda Isaksson in 1928. Children: Uil-la-Brita (born in 1931), Gunnar (born in 1938). \n\nEducation: Graduated from Skara High School in 1916. Studies at KTH (V) from 1916 to 1920. Surveyor examination in 1922. Cultural engineering examination in 1926. \n\nCareer: Assistant Surveyor in Skaraborg County from 1922 to 1928. Assistant in Västerbotten County from 1928 to 1930. Temporary District Surveyor in Väddö District in 1930. Permanent Surveyor in Örebro County from 1931 to 1933. Temporary District Surveyor in Ronneby District from 1933 to 1935. Appointed as a bureau engineer in the Surveyor Authority in 1933. Served in the authority from 1935 to 1936. Appointed as District Surveyor in Lindes District in 1935. Chief Surveyor in Älvsborg County since 1936. Chairman of the expropriation board in 1941 and the board of Älvsborg City Mortgage Association and Västergötland-Dals Housing Credit Association in 1942. Member of the crisis management board for Älvsborg County northern area in 1944 and the board of System A-B in Vänersborg in 1945. \n\nRecipient of the Royal Order of the North Star (RNO.)",
    "structured_raw": "{\n  \"@context\": \"https://schema.org\",\n  \"@type\": \"Person\",\n  \"name\": \"Åke Jakob Jernström\",\n  \"birthDate\": \"1898-07-26\",\n  \"birthPlace\": \"Lidköping, Sweden\",\n  \"parents\": [\n    {\n      \"@type\": \"Person\",\n      \"name\": \"Isac Jernström\",\n      \"jobTitle\": \"Dentist\"\n    },\n    {\n      \"@type\": \"Person\",\n      \"name\": \"August Fröberg\"\n    }\n  ],\n  \"spouse\": {\n    \"@type\": \"Person\",\n    \"name\": \"Gerda Isaksson\"\n  },\n  \"children\": [\n    {\n      \"@type\": \"Person\",\n      \"name\": \"Uil-la-Brita Jernström\"\n    },\n    {\n      \"@type\": \"Person\",\n      \"name\": \"Gunnar Jernström\",\n      \"birthDate\": \"1938\"\n    }\n  ],\n  \"education\": [\n    {\n      \"@type\": \"EducationalOccupationalCredential\",\n      \"description\": \"High School Diploma\",\n      \"startDate\": \"1916\",\n      \"endDate\": \"1916\",\n      \"educationalLevel\": \"SecondaryEducation\",\n      \"issuer\": {\n        \"@type\": \"Organization\",\n        \"name\": \"Skara High School\"\n      }\n    },\n    {\n      \"@type\": \"EducationalOccupationalCredential\",\n      \"description\": \"Studies at KTH\",\n      \"startDate\": \"1916\",\n      \"endDate\": \"1920\",\n      \"educationalLevel\": \"Undergraduate\"\n    },\n    {\n      \"@type\": \"EducationalOccupationalCredential\",\n      \"description\": \"Surveyor Examination\",\n      \"startDate\": \"1922\",\n      \"endDate\": \"1922\",\n      \"educationalLevel\": \"Professional\"\n    },\n    {\n      \"@type\": \"EducationalOccupationalCredential\",\n      \"description\": \"Cultural Engineering Examination\",\n      \"startDate\": \"1926\",\n      \"endDate\": \"1926\",\n      \"educationalLevel\": \"Professional\"\n    }\n  ],\n  \"jobTitle\": [\n    \"Chief Surveyor\",\n    \"Assistant Surveyor\",\n    \"Temporary District Surveyor\",\n    \"Permanent Surveyor\",\n    \"Bureau Engineer\",\n    \"Chairman\"\n  ],\n  \"memberOf\": [\n    {\n      \"@type\": \"Organization\",\n      \"name\": \"Expropriation Board\"\n    },\n    {\n      \"@type\": \"Organization\",\n      \"name\": \"Älvsborg City Mortgage Association\"\n    },\n    {\n      \"@type\": \"Organization\",\n      \"name\": \"Västergötland-Dals Housing Credit Association\"\n    },\n    {\n      \"@type\": \"Organization\",\n      \"name\": \"Crisis Management Board for Älvsborg County Northern Area\"\n    },\n    {\n      \"@type\": \"Organization\",\n      \"name\": \"System A-B\"\n    }\n  ],\n  \"awards\": {\n    \"@type\": \"Order\",\n    \"name\": \"Royal Order of the North Star\"\n  }\n}",
    "structured": {
        "@context": "https://schema.org",
        "@type": "Person",
        "name": "Åke Jakob Jernström",
        "birthDate": "1898-07-26",
        "birthPlace": "Lidköping, Sweden",
        "parents": [
            {
                "@type": "Person",
                "name": "Isac Jernström",
                "jobTitle": "Dentist"
            },
            {
                "@type": "Person",
                "name": "August Fröberg"
            }
        ],
        "spouse": {
            "@type": "Person",
            "name": "Gerda Isaksson"
        },
        "children": [
            {
                "@type": "Person",
                "name": "Uil-la-Brita Jernström"
            },
            {
                "@type": "Person",
                "name": "Gunnar Jernström",
                "birthDate": "1938"
            }
        ],
        "education": [
            {
                "@type": "EducationalOccupationalCredential",
                "description": "High School Diploma",
                "startDate": "1916",
                "endDate": "1916",
                "educationalLevel": "SecondaryEducation",
                "issuer": {
                    "@type": "Organization",
                    "name": "Skara High School"
                }
            },
            {
                "@type": "EducationalOccupationalCredential",
                "description": "Studies at KTH",
                "startDate": "1916",
                "endDate": "1920",
                "educationalLevel": "Undergraduate"
            },
            {
                "@type": "EducationalOccupationalCredential",
                "description": "Surveyor Examination",
                "startDate": "1922",
                "endDate": "1922",
                "educationalLevel": "Professional"
            },
            {
                "@type": "EducationalOccupationalCredential",
                "description": "Cultural Engineering Examination",
                "startDate": "1926",
                "endDate": "1926",
                "educationalLevel": "Professional"
            }
        ],
        "jobTitle": [
            "Chief Surveyor",
            "Assistant Surveyor",
            "Temporary District Surveyor",
            "Permanent Surveyor",
            "Bureau Engineer",
            "Chairman"
        ],
        "memberOf": [
            {
                "@type": "Organization",
                "name": "Expropriation Board"
            },
            {
                "@type": "Organization",
                "name": "Älvsborg City Mortgage Association"
            },
            {
                "@type": "Organization",
                "name": "Västergötland-Dals Housing Credit Association"
            },
            {
                "@type": "Organization",
                "name": "Crisis Management Board for Älvsborg County Northern Area"
            },
            {
                "@type": "Organization",
                "name": "System A-B"
            }
        ],
        "awards": {
            "@type": "Order",
            "name": "Royal Order of the North Star"
        }
    }
}