{
    "original": "Bergendal, Tomas Arvid Tomasson, assuransdirektör, kapten, Göteborg, f. 22n/%S i Söderfors, Upps. 1., av bruksdisp. Tom E. G. B. o. Maria Strömbom. G. 13 m. Sigrun Edling. — Stud:ex. i Upps. 04, stud. v. tekn. högsk. o. v. hand:sk. Und:löjtn. i Svea art:reg. res. 08, löjtn. 14, kapt. 23. Ing. v. Sv. Diamantbergborrn. A-B, kont :chef v. Sv-Ryska StåHinefabr :a i Sthlm 15, rev:- o. insp :uppdr. av försäkr :insp. 21-26, verkst. dir. i Sjö-försäkr. A-B Gauthiod i Gbg sed. 26. RVO.",
    "translated": "Bergendal, Tomas Arvid Tomasson, insurance director, captain, Gothenburg, born on 22nd of %S in Söderfors, Uppsala County, son of Tom E. G. B. and Maria Strömbom who worked as an industrial superintendent. Married to Sigrun Edling in 1913. He graduated from Uppsala Secondary School in 1904 and studied at the Technical University and the School of Commerce. He served as a second lieutenant in the Svea Artillery Regiment Reserve in 1908, became lieutenant in 1914 and captain in 1923. He worked as an engineer for the Swedish Diamond Drilling Co. Ltd, was the head of the Stockholm Russo-Swedish Steel Factory from 1915, and had reviewing and inspection duties for the insurance inspectorate from 1921 to 1926. He was the managing director of the Marine Insurance Company Gauthiod AB in Gothenburg from 1926. He was awarded the Royal Order of Vasa.",
    "structured_raw": "{\n \"name\": \"Tomas Arvid Tomasson Bergendal\",\n \"jobTitle\": \"Insurance Director, Captain\",\n \"birthDate\": \"1879-09-22\",\n \"birthPlace\": \"Söderfors, Uppsala, Sweden\",\n \"nationality\": \"Swedish\",\n \"parents\": [\n   {\n     \"name\": \"Tom E. G. B.\",\n     \"jobTitle\": \"Industrial Superintendent\"\n   },\n   {\n     \"name\": \"Maria Strömbom\",\n     \"jobTitle\": \"Industrial Superintendent\"\n   }\n ],\n \"spouse\": {\n   \"name\": \"Sigrun Edling\",\n   \"marriageDate\": \"1913-01-01\"\n },\n \"education\": [\n   {\n     \"institution\": \"Uppsala Secondary School\",\n     \"startDate\": \"1904\",\n     \"endDate\": \"Year of graduation\"\n   },\n   {\n     \"institution\": \"Technical University\",\n     \"startDate\": \"Year of admission\"\n   },\n   {\n     \"institution\": \"School of Commerce\",\n     \"startDate\": \"Year of admission\"\n   }\n ],\n \"worksFor\": [\n   {\n     \"name\": \"Swedish Diamond Drilling Co., Ltd.\",\n     \"jobTitle\": \"Engineer\",\n     \"startDate\": \"Year of employment\"\n   },\n   {\n     \"name\": \"Stockholm Russo-Swedish Steel Factory\",\n     \"jobTitle\": \"Head\",\n     \"startDate\": \"1915\"\n   },\n   {\n     \"name\": \"Marine Insurance Company Gauthiod AB\",\n     \"jobTitle\": \"Managing Director\",\n     \"startDate\": \"1926\"\n   }\n ],\n \"militaryService\": [\n   {\n     \"branch\": \"Svea Artillery Regiment Reserve\",\n     \"rank\": \"Second Lieutenant\",\n     \"startDate\": \"1908\"\n   },\n   {\n     \"branch\": \"Svea Artillery Regiment Reserve\",\n     \"rank\": \"Lieutenant\",\n     \"startDate\": \"1914\"\n   },\n   {\n     \"branch\": \"Svea Artillery Regiment Reserve\",\n     \"rank\": \"Captain\",\n     \"startDate\": \"1923\"\n   }\n ],\n \"awards\": [\n   {\n     \"name\": \"Royal Order of Vasa\",\n     \"date\": \"Year of award\"\n   }\n ]\n}",
    "structured": {
        "name": "Tomas Arvid Tomasson Bergendal",
        "jobTitle": "Insurance Director, Captain",
        "birthDate": "1879-09-22",
        "birthPlace": "Söderfors, Uppsala, Sweden",
        "nationality": "Swedish",
        "parents": [
            {
                "name": "Tom E. G. B.",
                "jobTitle": "Industrial Superintendent"
            },
            {
                "name": "Maria Strömbom",
                "jobTitle": "Industrial Superintendent"
            }
        ],
        "spouse": {
            "name": "Sigrun Edling",
            "marriageDate": "1913-01-01"
        },
        "education": [
            {
                "institution": "Uppsala Secondary School",
                "startDate": "1904",
                "endDate": "Year of graduation"
            },
            {
                "institution": "Technical University",
                "startDate": "Year of admission"
            },
            {
                "institution": "School of Commerce",
                "startDate": "Year of admission"
            }
        ],
        "worksFor": [
            {
                "name": "Swedish Diamond Drilling Co., Ltd.",
                "jobTitle": "Engineer",
                "startDate": "Year of employment"
            },
            {
                "name": "Stockholm Russo-Swedish Steel Factory",
                "jobTitle": "Head",
                "startDate": "1915"
            },
            {
                "name": "Marine Insurance Company Gauthiod AB",
                "jobTitle": "Managing Director",
                "startDate": "1926"
            }
        ],
        "militaryService": [
            {
                "branch": "Svea Artillery Regiment Reserve",
                "rank": "Second Lieutenant",
                "startDate": "1908"
            },
            {
                "branch": "Svea Artillery Regiment Reserve",
                "rank": "Lieutenant",
                "startDate": "1914"
            },
            {
                "branch": "Svea Artillery Regiment Reserve",
                "rank": "Captain",
                "startDate": "1923"
            }
        ],
        "awards": [
            {
                "name": "Royal Order of Vasa",
                "date": "Year of award"
            }
        ]
    }
}