{
    "original": "Sigrfrid, direktör, Göteborg, f. Vmm i Vicklelby, Kalm. 1. G. 20 m. Harriet Price. — Stud :ex. 11, Schartaus liandelsinst. 12. Anst. v. Margarin A-B Svea i Kalmar 13-22, avd :ohef v. A-B Pellerins Margarin-faibr. i Gbg 22-26, verkst. dir. där sed. 27, tillika f. Margarin A-B Zenith i Malmö sed. 317. Led. av styr. ’f. Marga-rinfabrinas Försäljn. A-B, Gbgs Kex-fabr. A-B, A-B Kvarnintressenter m. fl. , Hilly, rektor, Jönköping, f, 30/10/00 i Jönköp. av verkmäst. S. R. W. o. h. ih. f. Johansson. — 8-klass. fUcklärov. m. norm :sk rkomp. 18, Fack-sk. f. husl. ekon. 24. Stud. i Engl. 20-21, i Tyskl. 21-22, 34, 35, 39, i Frankr. 47. Anst. s. skolkökslär. v. Jönköp. västra flicksk. o. Jönköp. östra flicksk., rektor v. Jönköp. stads yrkessk. fr. 33. Led. av Sv. skolkökslär mefören. cen-tristyr., av pens :nd, av hemhj :nd, ordf. i Yrkeskvinn. kl. Led. av stads-fullm. 42-46.",
    "translated": "Sigrfrid, director, Gothenburg, b. Vmm in Vicklelby, Kalm. 1st marriage 20 with Harriet Price. - Graduation from Schartau's Trade Institute in 1911. Employment at Margarin A-B Svea in Kalmar from 1913-1922, department head at A-B Pellerins Margarine Factory in Gothenburg from 1922-1926, executive director there since 1927, and also for Margarin A-B Zenith in Malmö since 1931. Member of the board for Margarine Factory Sales A-B, Gothenburg Biscuit Factory A-B, A-B Mill Interests, and others. \n\nHilly, principal, Jönköping, b. 30/10/1900 in Jönköping, son of master mechanic S. R. W. and his wife Johansson. - Completed 8th grade at a public school with normal school curriculum in 1918, completed household economics vocational school in 1924. Studied in England from 1920-1921, in Germany from 1921-1922, 1934, 1935, and 1939, and in France in 1947. Employed as a school kitchen teacher at Jönköping Western Girls' School and Jönköping Eastern Girls' School, principal at Jönköping City Vocational School from 1933. Member of the central board for the Swedish School Kitchen Teachers Association, the pension committee, the home help committee, chairperson of the Professional Women's Club. Member of the city council from 1942-1946.",
    "structured_raw": "{\n  \"name\": \"Sigrfrid\",\n  \"jobTitle\": \"Director\",\n  \"address\": {\n    \"addressLocality\": \"Gothenburg\"\n  },\n  \"birthPlace\": \"Vicklelby, Kalm\",\n  \"birthDate\": \"Unknown\",\n  \"spouse\": [\n    {\n      \"name\": \"Harriet Price\"\n    }\n  ],\n  \"education\": [\n    {\n      \"startDate\": \"1911\",\n      \"endDate\": \"Unknown\",\n      \"institution\": \"Schartau's Trade Institute\"\n    },\n    {\n      \"startDate\": \"1920\",\n      \"endDate\": \"1921\",\n      \"institution\": \"England\"\n    },\n    {\n      \"startDate\": \"1921\",\n      \"endDate\": \"1922\",\n      \"institution\": \"Germany\"\n    },\n    {\n      \"startDate\": \"1934\",\n      \"endDate\": \"1935\",\n      \"institution\": \"Germany\"\n    },\n    {\n      \"startDate\": \"1939\",\n      \"endDate\": \"1939\",\n      \"institution\": \"Germany\"\n    },\n    {\n      \"startDate\": \"1947\",\n      \"endDate\": \"1947\",\n      \"institution\": \"France\"\n    }\n  ],\n  \"employmentHistory\": [\n    {\n      \"startDate\": \"1913\",\n      \"endDate\": \"1922\",\n      \"employer\": \"Margarin A-B Svea\",\n      \"location\": \"Kalmar\"\n    },\n    {\n      \"startDate\": \"1922\",\n      \"endDate\": \"1926\",\n      \"employer\": \"A-B Pellerins Margarine Factory\",\n      \"location\": \"Gothenburg\"\n    },\n    {\n      \"startDate\": \"1927\",\n      \"endDate\": \"Unknown\",\n      \"employer\": \"A-B Pellerins Margarine Factory\",\n      \"location\": \"Gothenburg\"\n    },\n    {\n      \"startDate\": \"1931\",\n      \"endDate\": \"Unknown\",\n      \"employer\": \"Margarin A-B Zenith\",\n      \"location\": \"Malmö\"\n    }\n  ],\n  \"boardMemberships\": [\n    {\n      \"name\": \"Margarine Factory Sales A-B\"\n    },\n    {\n      \"name\": \"Gothenburg Biscuit Factory A-B\"\n    },\n    {\n      \"name\": \"A-B Mill Interests\"\n    }\n  ]\n}",
    "structured": {
        "name": "Sigrfrid",
        "jobTitle": "Director",
        "address": {
            "addressLocality": "Gothenburg"
        },
        "birthPlace": "Vicklelby, Kalm",
        "birthDate": "Unknown",
        "spouse": [
            {
                "name": "Harriet Price"
            }
        ],
        "education": [
            {
                "startDate": "1911",
                "endDate": "Unknown",
                "institution": "Schartau's Trade Institute"
            },
            {
                "startDate": "1920",
                "endDate": "1921",
                "institution": "England"
            },
            {
                "startDate": "1921",
                "endDate": "1922",
                "institution": "Germany"
            },
            {
                "startDate": "1934",
                "endDate": "1935",
                "institution": "Germany"
            },
            {
                "startDate": "1939",
                "endDate": "1939",
                "institution": "Germany"
            },
            {
                "startDate": "1947",
                "endDate": "1947",
                "institution": "France"
            }
        ],
        "employmentHistory": [
            {
                "startDate": "1913",
                "endDate": "1922",
                "employer": "Margarin A-B Svea",
                "location": "Kalmar"
            },
            {
                "startDate": "1922",
                "endDate": "1926",
                "employer": "A-B Pellerins Margarine Factory",
                "location": "Gothenburg"
            },
            {
                "startDate": "1927",
                "endDate": "Unknown",
                "employer": "A-B Pellerins Margarine Factory",
                "location": "Gothenburg"
            },
            {
                "startDate": "1931",
                "endDate": "Unknown",
                "employer": "Margarin A-B Zenith",
                "location": "Malmö"
            }
        ],
        "boardMemberships": [
            {
                "name": "Margarine Factory Sales A-B"
            },
            {
                "name": "Gothenburg Biscuit Factory A-B"
            },
            {
                "name": "A-B Mill Interests"
            }
        ]
    }
}