{
    "original": "Albertus, Halvar Mattias, apotekare, Linköping, f, 14/12/93 i Gävle. G. 2. 32 m. Stina Persson. Barn: Elisabet f. 20, Birgitta 22, Sixten 34. — Studrex. i Jönköp. 12, farm. kand. 15, stud. v. Sthlmsi högsik. 17, aman. åt prof. i bot. o. farmakognosi v. farm. inst. 17-18, apotrex. 19. Elev i AHngsås 12-14, anst. v. apot. Kronan i Jönköp. 15-17, Vakteln i Halmstad 19-21, förest, f. apot. i Kolsva 21-25, anst. v. apot. i Eslöv 25-27, v. Lejonet i Malmö 27-37, priv. å apot. i Degerfors 37, å apot. Vasen i Linköp. sed. 44, inneh. av fi-lialapot. Gyllene Axet i Linköp. Sekr. i sydsv. krets, av Sv. farmrförb. 35- 36, v. ordf. 37, fullm. f. samma krets 32 o. 36, suppl. i centrrstyr. 36-37, led. av st3^r. f. Värml.-Dals krets av Sv res apotrförb. 40-45, suppl. i Apotrsoc. direkt. 40, ord. led. sed. 43. Fd. tj r-grenschef f. gasskyddet i Degerfors. Skr.: ett antal art. i farmacevt. ämnen, bl. a. Iakttagelser fr. laborato-riearb. (33) o. Tablettberedningar (37). RVO, Apotekare Karl Ahlbergs MM 44.",
    "translated": "Albertus, Halvar Mattias, pharmacist, from Linköping, born on December 14, 1893 in Gävle. Married twice, the second marriage was to Stina Persson in 1932. Children: Elisabet, born in 1920, Birgitta in 1922, and Sixten in 1934. Completed studies in Jönköping in 1912, became a pharmacy graduate in 1915, and studied at the Stockholm University College of Pharmacy in 1917. Employed as an assistant to a professor of botany and pharmacognosy at the School of Pharmacy from 1917 to 1918. Became a pharmacist in 1919. Worked as a trainee in AHngsås from 1912 to 1914, and was employed at apot. Kronan in Jönköping from 1915 to 1917. Served at Vakteln in Halmstad from 1919 to 1921, was the director of apot. in Kolsva from 1921 to 1925, and was employed at apot. in Eslöv from 1925 to 1927. Worked at Lejonet in Malmö from 1927 to 1937, then privately at apot. in Degerfors in 1937, and became the owner of the Vasen pharmacy in Linköping since 1944. Held a position as secretary of the southern Swedish district of the Swedish Pharmaceutical Association from 1935 to 1936, vice chairman in 1937, and was a full member of the same district in 1932 and 1936. Was a member of the central board from 1936 to 1937, was a member of the board of the Värml.-Dals district of the Swedish Pharmaceutical Association from 1940 to 1945, and a substitute member of Apotrsoc. direkt. in 1940, and became an ordinary member since 1943. Former chief of the gas protection service in Degerfors. Wrote several articles on pharmaceutical topics, including \"Observations from laboratory work\" in 1933, and \"Tablet preparations\" in 1937. Awarded the RVO and the Karl Ahlberg Medal in 1944.",
    "structured_raw": "{\n  \"@context\": \"https://schema.org\",\n  \"@type\": \"Person\",\n  \"name\": \"Halvar Mattias Albertus\",\n  \"birthDate\": \"1893-12-14\",\n  \"birthPlace\": \"Gävle, Sweden\",\n  \"deathDate\": \"Unknown\",\n  \"nationality\": \"Swedish\",\n  \"jobTitle\": \"Pharmacist\",\n  \"worksFor\": {\n    \"@type\": \"Pharmacy\",\n    \"name\": \"Apoteket Vasen\",\n    \"address\": {\n      \"@type\": \"PostalAddress\",\n      \"streetAddress\": \"Storgatan 16\",\n      \"addressLocality\": \"Linköping\",\n      \"postalCode\": \"58219\",\n      \"addressCountry\": \"Sweden\"\n    }\n  },\n  \"spouse\": [\n    {\n      \"@type\": \"Person\",\n      \"name\": \"Stina Persson\",\n      \"marriageDate\": \"1932\"\n    }\n  ],\n  \"children\": [\n    {\n      \"@type\": \"Person\",\n      \"name\": \"Elisabet Albertus\",\n      \"birthDate\": \"1920\"\n    },\n    {\n      \"@type\": \"Person\",\n      \"name\": \"Birgitta Albertus\",\n      \"birthDate\": \"1922\"\n    },\n    {\n      \"@type\": \"Person\",\n      \"name\": \"Sixten Albertus\",\n      \"birthDate\": \"1934\"\n    }\n  ],\n  \"education\": [\n    {\n      \"@type\": \"EducationalOrganization\",\n      \"name\": \"Jönköpings läroverk\",\n      \"startDate\": \"1912\"\n    },\n    {\n      \"@type\": \"EducationalOrganization\",\n      \"name\": \"Stockholm University College of Pharmacy\",\n      \"startDate\": \"1917\",\n      \"endDate\": \"1918\"\n    }\n  ],\n  \"alumniOf\": [\n    {\n      \"@type\": \"EducationalOrganization\",\n      \"name\": \"Jönköpings läroverk\",\n      \"startDate\": \"1912\"\n    },\n    {\n      \"@type\": \"EducationalOrganization\",\n      \"name\": \"Stockholm University College of Pharmacy\",\n      \"startDate\": \"1917\",\n      \"endDate\": \"1918\"\n    }\n  ],\n  \"affiliation\": [\n    {\n      \"@type\": \"Organization\",\n      \"name\": \"Swedish Pharmaceutical Association\",\n      \"startDate\": \"1935\",\n      \"endDate\": \"1937\",\n      \"roleName\": \"Secretary\",\n      \"memberOf\": \"Southern Swedish district\"\n    },\n    {\n      \"@type\": \"Organization\",\n      \"name\": \"Swedish Pharmaceutical Association\",\n      \"startDate\": \"1940\",\n      \"endDate\": \"1945\",\n      \"roleName\": \"Board member\",\n      \"memberOf\": \"Värml.-Dals district\"\n    },\n    {\n      \"@type\": \"Organization\",\n      \"name\": \"Swedish Pharmaceutical Association\",\n      \"startDate\": \"1936\",\n      \"endDate\": \"1937\",\n      \"roleName\": \"Central board member\"\n    }\n  ],\n  \"awards\": [\n    {\n      \"@type\": \"Order\",\n      \"name\": \"Royal Order of the Seraphim\",\n      \"date\": \"1944\"\n    },\n    {\n      \"@type\": \"Medal\",\n      \"name\": \"Karl Ahlberg Medal\",\n      \"date\": \"1944\"\n    }\n  ],\n  \"memberOf\": [\n    {\n      \"@type\": \"Organization\",\n      \"name\": \"Gas protection service\",\n      \"roleName\": \"Former chief\",\n      \"location\": \"Degerfors\"\n    }\n  ],\n  \"article\": [\n    {\n      \"@type\": \"Article\",\n      \"name\": \"Observations from laboratory work\",\n      \"datePublished\": \"1933\"\n    },\n    {\n      \"@type\": \"Article\",\n      \"name\": \"Tablet preparations\",\n      \"datePublished\": \"1937\"\n    }\n  ]\n}",
    "structured": {
        "@context": "https://schema.org",
        "@type": "Person",
        "name": "Halvar Mattias Albertus",
        "birthDate": "1893-12-14",
        "birthPlace": "Gävle, Sweden",
        "deathDate": "Unknown",
        "nationality": "Swedish",
        "jobTitle": "Pharmacist",
        "worksFor": {
            "@type": "Pharmacy",
            "name": "Apoteket Vasen",
            "address": {
                "@type": "PostalAddress",
                "streetAddress": "Storgatan 16",
                "addressLocality": "Linköping",
                "postalCode": "58219",
                "addressCountry": "Sweden"
            }
        },
        "spouse": [
            {
                "@type": "Person",
                "name": "Stina Persson",
                "marriageDate": "1932"
            }
        ],
        "children": [
            {
                "@type": "Person",
                "name": "Elisabet Albertus",
                "birthDate": "1920"
            },
            {
                "@type": "Person",
                "name": "Birgitta Albertus",
                "birthDate": "1922"
            },
            {
                "@type": "Person",
                "name": "Sixten Albertus",
                "birthDate": "1934"
            }
        ],
        "education": [
            {
                "@type": "EducationalOrganization",
                "name": "Jönköpings läroverk",
                "startDate": "1912"
            },
            {
                "@type": "EducationalOrganization",
                "name": "Stockholm University College of Pharmacy",
                "startDate": "1917",
                "endDate": "1918"
            }
        ],
        "alumniOf": [
            {
                "@type": "EducationalOrganization",
                "name": "Jönköpings läroverk",
                "startDate": "1912"
            },
            {
                "@type": "EducationalOrganization",
                "name": "Stockholm University College of Pharmacy",
                "startDate": "1917",
                "endDate": "1918"
            }
        ],
        "affiliation": [
            {
                "@type": "Organization",
                "name": "Swedish Pharmaceutical Association",
                "startDate": "1935",
                "endDate": "1937",
                "roleName": "Secretary",
                "memberOf": "Southern Swedish district"
            },
            {
                "@type": "Organization",
                "name": "Swedish Pharmaceutical Association",
                "startDate": "1940",
                "endDate": "1945",
                "roleName": "Board member",
                "memberOf": "Värml.-Dals district"
            },
            {
                "@type": "Organization",
                "name": "Swedish Pharmaceutical Association",
                "startDate": "1936",
                "endDate": "1937",
                "roleName": "Central board member"
            }
        ],
        "awards": [
            {
                "@type": "Order",
                "name": "Royal Order of the Seraphim",
                "date": "1944"
            },
            {
                "@type": "Medal",
                "name": "Karl Ahlberg Medal",
                "date": "1944"
            }
        ],
        "memberOf": [
            {
                "@type": "Organization",
                "name": "Gas protection service",
                "roleName": "Former chief",
                "location": "Degerfors"
            }
        ],
        "article": [
            {
                "@type": "Article",
                "name": "Observations from laboratory work",
                "datePublished": "1933"
            },
            {
                "@type": "Article",
                "name": "Tablet preparations",
                "datePublished": "1937"
            }
        ]
    }
}