{
    "original": "Brändström, Hilding Konstantin, borgmästare, Västervik, f. 9/8/96 i Luleå av överlantmät. Hugo Konstantin B. o. Emma Bäckström. G. 24 m. Ingeborg Hagberg. Barn: Inger f. 25, Hugo 26, Hilding 28, Torbjörn 31, Ingeborg Gunilla 38. — Stud:ex. i Sthlm 11, DHS 13, res:off:ex. 16, und:löjtn. v. Norrb. reg. 17, jur. kand. i Sthlm 19. E. o. not. i Svea hovr. 20, tings tjg. 21-22, auditör o. krigsdom. tidv. 22 o. 23, tf. borgmäst. i Örnsköldsvik tidv. 23-28, egen adv:verks. där samma tid, borgmäst. i Västervik sed. 28. Sekr. h. stadsfullm. o. drät-selkamm. i Örnsköldsvik 24-28, fastig-h:reg:för. 26-28, ordf. i styr. f. Sv. Hand :bankens avd :kont. i Västervik sed. 29, ordf. i länsnykterh :ndn f. Kalmar 1., ordf. i Kalm. 1. gymn:förb. RNO 33.",
    "translated": "Brändström, Hilding Konstantin, mayor of Västervik, born on August 9, 1896 in Luleå to surveyor Hugo Konstantin B. and Emma Bäckström. Married on June 24 to Ingeborg Hagberg. Children: Inger (born in 1925), Hugo (1926), Hilding (1928), Torbjörn (1931), Ingeborg Gunilla (1938). He graduated from the Stockholm Gymnasium in 1911, DHS in 1913, was a reserve officer in 1916, a second lieutenant in the Norrbotten regiment in 1917, and earned a degree in law from Stockholm University in 1919. He was appointed a notary public in the Svea Court of Appeal in 1920, served as a court clerk from 1921-1922, was an auditor and military judge temporarily in 1922 and 1923, was acting mayor of Örnsköldsvik from time to time between 1923 and 1928 and operated his own law firm during the same period, and has been the mayor of Västervik since 1928. He was also the secretary of the city council and finance committee in Örnsköldsvik from 1924-1928, a member of the real estate registration board from 1926-1928, chairman of the Swedish Handelsbanken branch in Västervik since 1929, chairman of the county temperance board for Kalmar, and chairman of the Kalmar 1. gymnastics association. He was awarded the Royal Nordic Philanthropic Order in 1933.",
    "structured_raw": "{\n  \"@context\": \"https://schema.org/\",\n  \"@type\": \"Person\",\n  \"name\": \"Hilding Konstantin Brändström\",\n  \"birthDate\": \"1896-08-09\",\n  \"birthPlace\": \"Luleå\",\n  \"nationality\": \"Swedish\",\n  \"jobTitle\": \"Mayor\",\n  \"workLocation\": \"Västervik\",\n  \"parent\": [\n    {\n      \"@type\": \"Person\",\n      \"name\": \"Hugo Konstantin B. Brändström\",\n      \"jobTitle\": \"Surveyor\"\n    },\n    {\n      \"@type\": \"Person\",\n      \"name\": \"Emma Bäckström\"\n    }\n  ],\n  \"spouse\": {\n    \"@type\": \"Person\",\n    \"name\": \"Ingeborg Hagberg\",\n    \"marriageDate\": \"1924-06-24\"\n  },\n  \"children\": [\n    {\n      \"@type\": \"Person\",\n      \"name\": \"Inger\",\n      \"birthDate\": \"1925\"\n    },\n    {\n      \"@type\": \"Person\",\n      \"name\": \"Hugo\",\n      \"birthDate\": \"1926\"\n    },\n    {\n      \"@type\": \"Person\",\n      \"name\": \"Hilding\",\n      \"birthDate\": \"1928\"\n    },\n    {\n      \"@type\": \"Person\",\n      \"name\": \"Torbjörn\",\n      \"birthDate\": \"1931\"\n    },\n    {\n      \"@type\": \"Person\",\n      \"name\": \"Ingeborg Gunilla\",\n      \"birthDate\": \"1938\"\n    }\n  ],\n  \"education\": [\n    {\n      \"@type\": \"EducationalOrganization\",\n      \"name\": \"Stockholm Gymnasium\",\n      \"endDate\": \"1911\"\n    },\n    {\n      \"@type\": \"EducationalOrganization\",\n      \"name\": \"DHS\",\n      \"endDate\": \"1913\"\n    },\n    {\n      \"@type\": \"Organization\",\n      \"name\": \"Stockholm University\",\n      \"endDate\": \"1919\",\n      \"jobTitle\": \"Juris Doctor\"\n    }\n  ],\n  \"workExperience\": [\n    {\n      \"@type\": \"GovernmentOrganization\",\n      \"name\": \"Svea Court of Appeal\",\n      \"startDate\": \"1920\",\n      \"jobTitle\": \"Notary Public\"\n    },\n    {\n      \"@type\": \"GovernmentOrganization\",\n      \"name\": \"Örnsköldsvik Municipality\",\n      \"startDate\": \"1921\",\n      \"endDate\": \"1922\",\n      \"jobTitle\": \"Court Clerk\"\n    },\n    {\n      \"@type\": \"Organization\",\n      \"name\": \"Swedish Handelsbanken\",\n      \"startDate\": \"1929\",\n      \"jobTitle\": \"Chairman, Västervik branch\"\n    }\n  ],\n  \"event\": [\n    {\n      \"@type\": \"Event\",\n      \"name\": \"Royal Nordic Philanthropic order\",\n      \"startDate\": \"1933\",\n      \"description\": \"Awarded RNO in 1933\"\n    }\n  ],\n  \"memberOf\": [\n    {\n      \"@type\": \"Organization\",\n      \"name\": \"Kalmar County Temperance Board\",\n      \"jobTitle\": \"Chairman\"\n    },\n    {\n      \"@type\": \"Organization\",\n      \"name\": \"Kalmar 1. gymnastics association\",\n      \"jobTitle\": \"Chairman\"\n    }\n  ]\n}",
    "structured": {
        "@context": "https://schema.org/",
        "@type": "Person",
        "name": "Hilding Konstantin Brändström",
        "birthDate": "1896-08-09",
        "birthPlace": "Luleå",
        "nationality": "Swedish",
        "jobTitle": "Mayor",
        "workLocation": "Västervik",
        "parent": [
            {
                "@type": "Person",
                "name": "Hugo Konstantin B. Brändström",
                "jobTitle": "Surveyor"
            },
            {
                "@type": "Person",
                "name": "Emma Bäckström"
            }
        ],
        "spouse": {
            "@type": "Person",
            "name": "Ingeborg Hagberg",
            "marriageDate": "1924-06-24"
        },
        "children": [
            {
                "@type": "Person",
                "name": "Inger",
                "birthDate": "1925"
            },
            {
                "@type": "Person",
                "name": "Hugo",
                "birthDate": "1926"
            },
            {
                "@type": "Person",
                "name": "Hilding",
                "birthDate": "1928"
            },
            {
                "@type": "Person",
                "name": "Torbjörn",
                "birthDate": "1931"
            },
            {
                "@type": "Person",
                "name": "Ingeborg Gunilla",
                "birthDate": "1938"
            }
        ],
        "education": [
            {
                "@type": "EducationalOrganization",
                "name": "Stockholm Gymnasium",
                "endDate": "1911"
            },
            {
                "@type": "EducationalOrganization",
                "name": "DHS",
                "endDate": "1913"
            },
            {
                "@type": "Organization",
                "name": "Stockholm University",
                "endDate": "1919",
                "jobTitle": "Juris Doctor"
            }
        ],
        "workExperience": [
            {
                "@type": "GovernmentOrganization",
                "name": "Svea Court of Appeal",
                "startDate": "1920",
                "jobTitle": "Notary Public"
            },
            {
                "@type": "GovernmentOrganization",
                "name": "Örnsköldsvik Municipality",
                "startDate": "1921",
                "endDate": "1922",
                "jobTitle": "Court Clerk"
            },
            {
                "@type": "Organization",
                "name": "Swedish Handelsbanken",
                "startDate": "1929",
                "jobTitle": "Chairman, Västervik branch"
            }
        ],
        "event": [
            {
                "@type": "Event",
                "name": "Royal Nordic Philanthropic order",
                "startDate": "1933",
                "description": "Awarded RNO in 1933"
            }
        ],
        "memberOf": [
            {
                "@type": "Organization",
                "name": "Kalmar County Temperance Board",
                "jobTitle": "Chairman"
            },
            {
                "@type": "Organization",
                "name": "Kalmar 1. gymnastics association",
                "jobTitle": "Chairman"
            }
        ]
    }
}