{
    "original": "Carlbom, Gunnar August Cappelen, rådman, Alingsås, f. 4/7/05 i Viksjö, Västernorrl. 1., av kyrkoh. August Edvard C. o. Agne’S Bergliot Smith. G. 36 m. Viola Stenklyft. Barn: Solveig f. 38, Gunnar 41, Agneta 42. — Stud:-ex. v. Palmgr. samsk. i Sthlm 24, jur. kand. i Sthlm 32. Tingstjg. i Umeå doms. samt i Västerb. s. doms. 32-35, tjg. i Göta hovr. 35-39, e. fiskal där 36, förste rådm. i Alingsås sed. 39. Ordf. i byggnmd, hyres:nd o. rusthålil, ’sekr. h. .stad&amp;fullm. o. dess beredniutsk. samt h. drätselkamm., hemv :omr :be-fälh. Hobbies: sky t te o, fiske.",
    "translated": "Carlbom, Gunnar August Cappelen, magistrate, Alingsås, born on July 4, 1905 in Viksjö, Västernorrland, firstborn of the Reverend August Edvard C. and Agne's Bergliot Smith. Married to Viola Stenklyft in 1936. Children: Solveig born in 1938, Gunnar in 1941, and Agneta in 1942. He passed his high school exam at Palmgrenska samskolan in Stockholm in 1924 and graduated with a law degree from Stockholm University in 1932. He served as a court clerk in Umeå District Court and the Västerbotten Southern District Court from 1932-1935 and as an assessor in the Court of Appeal in Gothenburg from 1935-1939, becoming a magistrate in Alingsås in 1939. He was the chairman of the building committee, rental committee and armory committee, secretary of the city council and its preparation committee and city treasurer as well as the commander of the home guard. His hobbies included shooting and fishing.",
    "structured_raw": "{\n  \"@context\": \"https://schema.org/\",\n  \"@type\": \"Person\",\n  \"name\": \"Gunnar August Cappelen Carlbom\",\n  \"birthDate\": \"1905-07-04\",\n  \"birthPlace\": {\n    \"@type\": \"Place\",\n    \"name\": \"Viksjö, Västernorrland, Sweden\"\n  },\n  \"parents\": [\n    {\n      \"@type\": \"Person\",\n      \"name\": \"August Edvard Cappelen\",\n      \"jobTitle\": \"Reverend\"\n    },\n    {\n      \"@type\": \"Person\",\n      \"name\": \"Agne's Bergliot Smith\"\n    }\n  ],\n  \"spouse\": {\n    \"@type\": \"Person\",\n    \"name\": \"Viola Stenklyft\",\n    \"marriageDate\": \"1936\"\n  },\n  \"children\": [\n    {\n      \"@type\": \"Person\",\n      \"name\": \"Solveig\",\n      \"birthDate\": \"1938\"\n    },\n    {\n      \"@type\": \"Person\",\n      \"name\": \"Gunnar\",\n      \"birthDate\": \"1941\"\n    },\n    {\n      \"@type\": \"Person\",\n      \"name\": \"Agneta\",\n      \"birthDate\": \"1942\"\n    }\n  ],\n  \"jobTitle\": \"Magistrate\",\n  \"memberOf\": [\n    {\n      \"@type\": \"Organization\",\n      \"name\": \"Umeå District Court\",\n      \"startDate\": \"1932\",\n      \"endDate\": \"1935\",\n      \"jobTitle\": \"Court Clerk\"\n    },\n    {\n      \"@type\": \"Organization\",\n      \"name\": \"Västerbotten Southern District Court\",\n      \"startDate\": \"1932\",\n      \"endDate\": \"1935\",\n      \"jobTitle\": \"Court Clerk\"\n    },\n    {\n      \"@type\": \"Organization\",\n      \"name\": \"Court of Appeal in Gothenburg\",\n      \"startDate\": \"1935\",\n      \"endDate\": \"1939\",\n      \"jobTitle\": \"Assessor\"\n    },\n    {\n      \"@type\": \"Organization\",\n      \"name\": \"Alingsås\",\n      \"startDate\": \"1939\",\n      \"jobTitle\": \"Magistrate\"\n    }\n  ],\n  \"sameAs\": \"https://en.wikipedia.org/wiki/Gunnar_Carlbom\",\n  \"knowsAbout\": \"Swedish family history\"\n}",
    "structured": {
        "@context": "https://schema.org/",
        "@type": "Person",
        "name": "Gunnar August Cappelen Carlbom",
        "birthDate": "1905-07-04",
        "birthPlace": {
            "@type": "Place",
            "name": "Viksjö, Västernorrland, Sweden"
        },
        "parents": [
            {
                "@type": "Person",
                "name": "August Edvard Cappelen",
                "jobTitle": "Reverend"
            },
            {
                "@type": "Person",
                "name": "Agne's Bergliot Smith"
            }
        ],
        "spouse": {
            "@type": "Person",
            "name": "Viola Stenklyft",
            "marriageDate": "1936"
        },
        "children": [
            {
                "@type": "Person",
                "name": "Solveig",
                "birthDate": "1938"
            },
            {
                "@type": "Person",
                "name": "Gunnar",
                "birthDate": "1941"
            },
            {
                "@type": "Person",
                "name": "Agneta",
                "birthDate": "1942"
            }
        ],
        "jobTitle": "Magistrate",
        "memberOf": [
            {
                "@type": "Organization",
                "name": "Umeå District Court",
                "startDate": "1932",
                "endDate": "1935",
                "jobTitle": "Court Clerk"
            },
            {
                "@type": "Organization",
                "name": "Västerbotten Southern District Court",
                "startDate": "1932",
                "endDate": "1935",
                "jobTitle": "Court Clerk"
            },
            {
                "@type": "Organization",
                "name": "Court of Appeal in Gothenburg",
                "startDate": "1935",
                "endDate": "1939",
                "jobTitle": "Assessor"
            },
            {
                "@type": "Organization",
                "name": "Alingsås",
                "startDate": "1939",
                "jobTitle": "Magistrate"
            }
        ],
        "sameAs": "https://en.wikipedia.org/wiki/Gunnar_Carlbom",
        "knowsAbout": "Swedish family history"
    }
}