{
    "original": "Berg, Bengt Magnus Kristoffer, dr h. c., författare, Halltorp, f. 9/1/85 i Kalmar av lärov :adj. Fabian B. o. Oda Angeldorff. G. 30 m. Inger II-lum. Barn: Bolette f. 32, Jens 35. — Assist, v. Zool. Riksinstit Museum Koenig i Bonn 10-14, dr h. c. v. univ. i Bonn. Hedrades 45 m. statsbidrag på 200.000 kr. t. utbyggn. av Maravi-kens biol. försöksomr. Föret, ett flertal zool. forsknings- o. filmexp. i Afrika o. Asien 20-37. Framställt ett stort antal djurfilmer, hl. a. Storkarna, Som flyttfågel i Afrika, Abu Mar-küb o. De sista örnarna. Skr.: Sjöfallsboken (10), Heiden (drama på tyska 11), Genezaret (12), Måseskär (12),’ Tåkern (13), Där kriget rasar (15), Stora Karlsö (15), En german (16), Sällsynta fåglar I-II (16 o. 19), Min vän fjällpiparen (17), De rikas hunger (18), Hägrar o. storkar (20), Med tranorna t. Afrika (22), De sista örnarna (23), Aby Markub (24), Tavlor av sv. fåglar (25), Arizona Char-leys p-ojke (27), Den flygande draken (31), På jakt efter Enhörningen (32), Tigrar (34), Mina försök med vildgäss (37). Skr. utkomna på 14 språk i 1.3’00.000 ex. Banbrytande arbete i uppt. av bilder av fritt levande djur. Hobbies: sportfiske, jakt, målning.",
    "translated": "Berg, Bengt Magnus Kristoffer, honorary doctor, author, Halltorp, b. 9/1/85 in Kalmar to teacher Fabian B. and Oda Angeldorff. Married to Inger II-lum since 1930. Children: Bolette b. 1932, Jens b. 1935. - Assistant in Zoology at the Riksinstitut Museum Koenig in Bonn from 1910-1914, honorary doctor at the university in Bonn. Awarded 45 times with government grants of 200,000 SEK for the development of Maravi-ken's biological research area. Conducted several zoological research and film expeditions in Africa and Asia from 1920-1937. Produced numerous animal films, including Storks, Flying birds in Africa, Abu Mar-kub and The Last Eagles. Wrote: The Waterfall Book (1910), Heiden (German drama, 1911), Genezaret (1912), Måseskär (1912), Tåkern (1913), Where War Rages (1915), Stora Karlsö (1915), A German (1916), Rare Birds I-II (1916 and 1919), My Friend the Whimbrel (1917), The Hunger of the Rich (1918), Herons and Storks (1920), With Cranes to Africa (1922), The Last Eagles (1923), Aby Markub (1924), Paintings of Swedish Birds (1925), Arizona Charley’s Boy (1927), The Flying Dragon (1931), In Search of the Unicorn (1932), Tigers (1934), My Experiments with Wild Geese (1937). His works were published in 14 languages in 1.3 million copies. Pioneering work in capturing images of free-living animals. Hobbies: sport fishing, hunting, painting.",
    "structured_raw": "{\n  \"@context\": \"https://schema.org\",\n  \"@type\": \"Person\",\n  \"name\": \"Bengt Magnus Kristoffer Berg\",\n  \"birthDate\": \"1885-01-09\",\n  \"birthPlace\": {\n    \"@type\": \"Place\",\n    \"name\": \"Kalmar\"\n  },\n  \"parent\": [\n    {\n      \"@type\": \"Person\",\n      \"name\": \"Fabian B. Berg\"\n    },\n    {\n      \"@type\": \"Person\",\n      \"name\": \"Oda Angeldorff\"\n    }\n  ],\n  \"spouse\": {\n    \"@type\": \"Person\",\n    \"name\": \"Inger II-lum\",\n    \"marriageDate\": \"1930\"\n  },\n  \"children\": [\n    {\n      \"@type\": \"Person\",\n      \"name\": \"Bolette\",\n      \"birthDate\": \"1932\"\n    },\n    {\n      \"@type\": \"Person\",\n      \"name\": \"Jens\",\n      \"birthDate\": \"1935\"\n    }\n  ],\n  \"jobTitle\": [\n    \"Honorary Doctor\",\n    \"Author\"\n  ],\n  \"memberOf\": [\n    {\n      \"@type\": \"Organization\",\n      \"name\": \"Riksinstitut Museum Koenig\"\n    },\n    {\n      \"@type\": \"Organization\",\n      \"name\": \"University of Bonn\"\n    }\n  ],\n  \"award\": {\n    \"@type\": \"MonetaryGrant\",\n    \"name\": \"Government grants of 200,000 SEK for the development of Maravi-ken's biological research area\",\n    \"startDate\": \"1910\",\n    \"endDate\": \"1937\",\n    \"numberOfAwards\": 45\n  },\n  \"workLocation\": {\n    \"@type\": \"Place\",\n    \"name\": \"Bonn\"\n  },\n  \"hasOccupation\": [\n    {\n      \"@type\": \"Occupation\",\n      \"name\": \"Assistant in Zoology\"\n    },\n    {\n      \"@type\": \"Occupation\",\n      \"name\": \"Zoological Researcher\"\n    },\n    {\n      \"@type\": \"Occupation\",\n      \"name\": \"Filmmaker\"\n    }\n  ],\n  \"filmography\": [\n    \"Storks\",\n    \"Flying Birds in Africa\",\n    \"Abu Mar-kub\",\n    \"The Last Eagles\"\n  ],\n  \"book\": [\n    \"The Waterfall Book\",\n    \"Heiden\",\n    \"Genezaret\",\n    \"Måseskär\",\n    \"Tåkern\",\n    \"Where War Rages\",\n    \"Stora Karlsö\",\n    \"A German\",\n    \"Rare Birds I-II\",\n    \"My Friend the Whimbrel\",\n    \"The Hunger of the Rich\",\n    \"Herons and Storks\",\n    \"With Cranes to Africa\",\n    \"The Last Eagles\",\n    \"Aby Markub\",\n    \"Paintings of Swedish Birds\",\n    \"Arizona Charley’s Boy\",\n    \"The Flying Dragon\",\n    \"In Search of the Unicorn\",\n    \"Tigers\",\n    \"My Experiments with Wild Geese\"\n  ],\n  \"languagePublished\": [\n    \"Swedish\",\n    \"German\",\n    \"and 12 other languages\"\n  ],\n  \"pioneeringWork\": [\n    \"Capturing images of free-living animals\"\n  ],\n  \"hasInterest\": [\n    {\n      \"@type\": \"Thing\",\n      \"name\": \"Sport Fishing\"\n    },\n    {\n      \"@type\": \"Thing\",\n      \"name\": \"Hunting\"\n    },\n    {\n      \"@type\": \"Thing\",\n      \"name\": \"Painting\"\n    }\n  ]\n}",
    "structured": {
        "@context": "https://schema.org",
        "@type": "Person",
        "name": "Bengt Magnus Kristoffer Berg",
        "birthDate": "1885-01-09",
        "birthPlace": {
            "@type": "Place",
            "name": "Kalmar"
        },
        "parent": [
            {
                "@type": "Person",
                "name": "Fabian B. Berg"
            },
            {
                "@type": "Person",
                "name": "Oda Angeldorff"
            }
        ],
        "spouse": {
            "@type": "Person",
            "name": "Inger II-lum",
            "marriageDate": "1930"
        },
        "children": [
            {
                "@type": "Person",
                "name": "Bolette",
                "birthDate": "1932"
            },
            {
                "@type": "Person",
                "name": "Jens",
                "birthDate": "1935"
            }
        ],
        "jobTitle": [
            "Honorary Doctor",
            "Author"
        ],
        "memberOf": [
            {
                "@type": "Organization",
                "name": "Riksinstitut Museum Koenig"
            },
            {
                "@type": "Organization",
                "name": "University of Bonn"
            }
        ],
        "award": {
            "@type": "MonetaryGrant",
            "name": "Government grants of 200,000 SEK for the development of Maravi-ken's biological research area",
            "startDate": "1910",
            "endDate": "1937",
            "numberOfAwards": 45
        },
        "workLocation": {
            "@type": "Place",
            "name": "Bonn"
        },
        "hasOccupation": [
            {
                "@type": "Occupation",
                "name": "Assistant in Zoology"
            },
            {
                "@type": "Occupation",
                "name": "Zoological Researcher"
            },
            {
                "@type": "Occupation",
                "name": "Filmmaker"
            }
        ],
        "filmography": [
            "Storks",
            "Flying Birds in Africa",
            "Abu Mar-kub",
            "The Last Eagles"
        ],
        "book": [
            "The Waterfall Book",
            "Heiden",
            "Genezaret",
            "Måseskär",
            "Tåkern",
            "Where War Rages",
            "Stora Karlsö",
            "A German",
            "Rare Birds I-II",
            "My Friend the Whimbrel",
            "The Hunger of the Rich",
            "Herons and Storks",
            "With Cranes to Africa",
            "The Last Eagles",
            "Aby Markub",
            "Paintings of Swedish Birds",
            "Arizona Charley’s Boy",
            "The Flying Dragon",
            "In Search of the Unicorn",
            "Tigers",
            "My Experiments with Wild Geese"
        ],
        "languagePublished": [
            "Swedish",
            "German",
            "and 12 other languages"
        ],
        "pioneeringWork": [
            "Capturing images of free-living animals"
        ],
        "hasInterest": [
            {
                "@type": "Thing",
                "name": "Sport Fishing"
            },
            {
                "@type": "Thing",
                "name": "Hunting"
            },
            {
                "@type": "Thing",
                "name": "Painting"
            }
        ]
    }
}