{
    "original": "Malmöh. 1., av landshövd. greve Gotth. W. o. frih :an Elisabeth von Essen. G. 00 m. Greta Lindström. Barn: Eva f. 00, d. 47, Carl Johan 03, Hans 12. — Studiex. i Sthim 90, und:-löjtn. v. Göta art:reg. 93, löjtn. 98, kapten 04, major v. Smål. art :reg. 16, överstelöjtn. v. Göta art:reg. 22. RSO, RNO, RVO, KFinlVRO. , Hans Wilhehn, Axelsson, civil jägmästare, greve, Karlskrona, f. 25/12/13 i Lidingö av ryttmäst. greve .Ajcel W. o. Caroda von Eckermann. G. 38 m. Ingrid Tobieson. Barn: Hans f. 40, Wilhelm 42, Gabriel 43, Agneta 46. — Stud:ex. i Karlskr. 3il, utex. fr. skoigsliögsk. 38, fänr. i Livreg. gren. res. 35, kapten 45. Bitr. mil:-attaché v. leg. i Paris 38, bränsle-chef i Blek. 1. 45-46, jordbr :förv. v. Jo-hannishus fideikommiss fr. 46. Off-TunNI, Karlskr. svfl GM, 2 SkytteM, SkytiteRM.",
    "translated": "Malmöh. 1., son of provincial governor Count Gotth. W. and Baroness Elisabeth von Essen. Married to Greta Lindström in the year 1900. Children: Eva born in 1900, died in 1947, Carl Johan born in 1903, Hans born in 1912. Graduated from the University of Stockholm in 1890, second lieutenant in the Gotha Artillery Regiment in 1893, lieutenant in 1898, captain in 1904, major in the Småland Artillery Regiment in 1916, lieutenant colonel in the Gotha Artillery Regiment in 1922. Decorated with the Royal Order of the Seraphim (RSO), the Royal Order of the North Star (RNO), the Royal Order of Vasa (RVO), and the Knight of the Finnish White Rose Order (KFinlVRO).\n\nHans Wilhelm Axelsson, civil forester, count, born on December 25, 1913, in Lidingö, son of cavalry captain Count Axel W. and Caroda von Eckermann. Married to Ingrid Tobieson in 1938. Children: Hans born in 1940, Wilhelm born in 1942, Gabriel born in 1943, Agneta born in 1946. Graduated from the Royal Naval Academy in Karlskrona in 1933, graduated from the Forestry School in 1938, ensign in the Life Grenadier Regiment Reserve in 1935, captain in 1945. Assistant military attaché at the Swedish Legation in Paris in 1938, fuel chief in Blekinge County from 1945-1946, agricultural supervisor of the Johannishus Estate from 1946. Officer of the Order of the Sword (Off-TunNI), Karlskrona Naval Society Gold Medal (Karlskr. svfl GM), recipient of the 2nd Class Skytte Medal (2 SkytteM), recipient of the Skytte Medal in Gold (SkytiteRM).",
    "structured_raw": "{\n  \"@context\": \"https://schema.org\",\n  \"@type\": \"Person\",\n  \"name\": \"Malmöh\",\n  \"givenName\": \"Hans Wilhelm Axelsson\",\n  \"familyName\": \"Malmöh\",\n  \"birthDate\": \"1913-12-25\",\n  \"birthPlace\": \"Lidingö\",\n  \"gender\": \"Male\",\n  \"nationality\": \"Swedish\",\n  \"father\": {\n    \"@type\": \"Person\",\n    \"name\": \"Gotth. W.\",\n    \"givenName\": \"Gotth\",\n    \"familyName\": \"W.\"\n  },\n  \"mother\": {\n    \"@type\": \"Person\",\n    \"name\": \"Elisabeth von Essen\",\n    \"givenName\": \"Elisabeth\",\n    \"familyName\": \"von Essen\"\n  },\n  \"spouse\": {\n    \"@type\": \"Person\",\n    \"name\": \"Greta Lindström\",\n    \"givenName\": \"Greta\",\n    \"familyName\": \"Lindström\"\n  },\n  \"children\": [\n    {\n      \"@type\": \"Person\",\n      \"name\": \"Hans\",\n      \"givenName\": \"Hans\",\n      \"birthDate\": \"1940\"\n    },\n    {\n      \"@type\": \"Person\",\n      \"name\": \"Wilhelm\",\n      \"givenName\": \"Wilhelm\",\n      \"birthDate\": \"1942\"\n    },\n    {\n      \"@type\": \"Person\",\n      \"name\": \"Gabriel\",\n      \"givenName\": \"Gabriel\",\n      \"birthDate\": \"1943\"\n    },\n    {\n      \"@type\": \"Person\",\n      \"name\": \"Agneta\",\n      \"givenName\": \"Agneta\",\n      \"birthDate\": \"1946\"\n    }\n  ],\n  \"description\": \"Civil Forester, Count\",\n  \"alumniOf\": [\n    {\n      \"@type\": \"EducationalOrganization\",\n      \"name\": \"Royal Naval Academy Karlskrona\",\n      \"location\": \"Karlskrona\"\n    },\n    {\n      \"@type\": \"EducationalOrganization\",\n      \"name\": \"Forestry School\"\n    }\n  ],\n  \"workExperience\": [\n    {\n      \"@type\": \"OrganizationRole\",\n      \"startDate\": \"1935\",\n      \"endDate\": \"1946\",\n      \"roleName\": \"Ensign\",\n      \"organization\": {\n        \"@type\": \"Organization\",\n        \"name\": \"Life Grenadier Regiment Reserve\"\n      }\n    },\n    {\n      \"@type\": \"OrganizationRole\",\n      \"startDate\": \"1945\",\n      \"endDate\": \"1946\",\n      \"roleName\": \"Fuel Chief\",\n      \"organization\": {\n        \"@type\": \"Organization\",\n        \"name\": \"Blekinge County\"\n      }\n    },\n    {\n      \"@type\": \"OrganizationRole\",\n      \"startDate\": \"1946\",\n      \"roleName\": \"Agricultural Supervisor\",\n      \"organization\": {\n        \"@type\": \"Organization\",\n        \"name\": \"Johannishus Estate\"\n      }\n    }\n  ],\n  \"membershipIn\": [\n    {\n      \"@type\": \"Organization\",\n      \"name\": \"Order of the Sword\",\n      \"memberOf\": \"Officer\"\n    },\n    {\n      \"@type\": \"Organization\",\n      \"name\": \"Karlskrona Naval Society Gold Medal\",\n      \"memberOf\": \"Recipient\"\n    },\n    {\n      \"@type\": \"Organization\",\n      \"name\": \"2nd Class Skytte Medal\",\n      \"memberOf\": \"Recipient\"\n    },\n    {\n      \"@type\": \"Organization\",\n      \"name\": \"Skytte Medal in Gold\",\n      \"memberOf\": \"Recipient\"\n    }\n  ]\n}",
    "structured": {
        "@context": "https://schema.org",
        "@type": "Person",
        "name": "Malmöh",
        "givenName": "Hans Wilhelm Axelsson",
        "familyName": "Malmöh",
        "birthDate": "1913-12-25",
        "birthPlace": "Lidingö",
        "gender": "Male",
        "nationality": "Swedish",
        "father": {
            "@type": "Person",
            "name": "Gotth. W.",
            "givenName": "Gotth",
            "familyName": "W."
        },
        "mother": {
            "@type": "Person",
            "name": "Elisabeth von Essen",
            "givenName": "Elisabeth",
            "familyName": "von Essen"
        },
        "spouse": {
            "@type": "Person",
            "name": "Greta Lindström",
            "givenName": "Greta",
            "familyName": "Lindström"
        },
        "children": [
            {
                "@type": "Person",
                "name": "Hans",
                "givenName": "Hans",
                "birthDate": "1940"
            },
            {
                "@type": "Person",
                "name": "Wilhelm",
                "givenName": "Wilhelm",
                "birthDate": "1942"
            },
            {
                "@type": "Person",
                "name": "Gabriel",
                "givenName": "Gabriel",
                "birthDate": "1943"
            },
            {
                "@type": "Person",
                "name": "Agneta",
                "givenName": "Agneta",
                "birthDate": "1946"
            }
        ],
        "description": "Civil Forester, Count",
        "alumniOf": [
            {
                "@type": "EducationalOrganization",
                "name": "Royal Naval Academy Karlskrona",
                "location": "Karlskrona"
            },
            {
                "@type": "EducationalOrganization",
                "name": "Forestry School"
            }
        ],
        "workExperience": [
            {
                "@type": "OrganizationRole",
                "startDate": "1935",
                "endDate": "1946",
                "roleName": "Ensign",
                "organization": {
                    "@type": "Organization",
                    "name": "Life Grenadier Regiment Reserve"
                }
            },
            {
                "@type": "OrganizationRole",
                "startDate": "1945",
                "endDate": "1946",
                "roleName": "Fuel Chief",
                "organization": {
                    "@type": "Organization",
                    "name": "Blekinge County"
                }
            },
            {
                "@type": "OrganizationRole",
                "startDate": "1946",
                "roleName": "Agricultural Supervisor",
                "organization": {
                    "@type": "Organization",
                    "name": "Johannishus Estate"
                }
            }
        ],
        "membershipIn": [
            {
                "@type": "Organization",
                "name": "Order of the Sword",
                "memberOf": "Officer"
            },
            {
                "@type": "Organization",
                "name": "Karlskrona Naval Society Gold Medal",
                "memberOf": "Recipient"
            },
            {
                "@type": "Organization",
                "name": "2nd Class Skytte Medal",
                "memberOf": "Recipient"
            },
            {
                "@type": "Organization",
                "name": "Skytte Medal in Gold",
                "memberOf": "Recipient"
            }
        ]
    }
}