{
    "original": "Axelson, Carl Ove Alphons, redaktör, Jönköping, f. 23/1/95 i Jönköp. av Axel Gustafsson o. Ada Josefina Bengtsson. G. 35 m. Siri Peterson. Barn: Rolf f. 37. — Realex. Anst. v. Bergmans Bokh. i Jönköp. 13-15, Jönköp. stadsing :kont. 15-18, medarb. i Smål. Alleh. sed. 18, red :’sekr. där sed. 20, nattred. sed. 44. Sekr. i Jönköp. radioklubb o. led. av dess säri-darnd sed. 27, programchef v. Jönköp. rundradiostat. 33-34, inom Jönköp. ra- diokl. sed. 33, hed :led. i Jönköp. scoutkår, fd. led. av Jönköp. höger-fören. styr., SMK styr., Jönköp. södra fastigh :äg :fören. styr., Motorkl. i Jönköp. trafiknd, styr :led. i Fören. gamla fattigas vänner, styr :led. i Fören. t. understödj. av Jönköp. scoutkår, medl. av Sv. Journ:fören. Sign.: -c, Nic, O. A. Hobbres: filateli, fisk-e, motorsport. Sv:es scoutförb. vita hed:tecken, PatrGM.",
    "translated": "Axelson, Carl Ove Alphons, editor, Jönköping, born January 23rd, 1895 in Jönköping to parents Axel Gustafsson and Ada Josefina Bengtsson. Married to Siri Peterson in 1935. They had a son named Rolf, born in 1937. He attended a commercial college. He was employed at Bergmans Bookstore in Jönköping from 1913 to 1915, worked at the Jönköping city accountant's office from 1915 to 1918, and was a collaborator at Småland's Allehanda from 1918. He was the secretary there from 1920 to 1944. He was the secretary of the Jönköping radio club and a member of its board since 1927, program director for Jönköping radio station from 1933 to 1934, and involved with the Jönköping radio club since 1933. He was an honorary member of the Jönköping scout troop, a former member of the Jönköping right-wing association board, the Swedish Motorist Club board, the Jönköping southern property owners' association board, the Jönköping traffic association, on the board of directors of the Friends of the Old Poor association, board of the Jönköping Scout Group Benevolent Association, and a member of the Swedish Journalist Association. He used the signatures -c, Nic, O.A. Hobbres, and was interested in philately, fishing, and motorsport. He was awarded the Swedish Scout Association White Hedging Badge and PatrGM.",
    "structured": {
        "@context": "https://schema.org/",
        "@type": "Person",
        "name": "Carl Ove Alphons Axelson",
        "givenName": "Carl Ove Alphons",
        "familyName": "Axelson",
        "jobTitle": "Editor",
        "birthDate": "1895-01-23",
        "birthPlace": {
            "@type": "Place",
            "name": "Jönköping"
        },
        "parent": [
            {
                "@type": "Person",
                "name": "Axel Gustafsson",
                "gender": "male"
            },
            {
                "@type": "Person",
                "name": "Ada Josefina Bengtsson",
                "gender": "female"
            }
        ],
        "spouse": {
            "@type": "Person",
            "name": "Siri Peterson"
        },
        "children": [
            {
                "@type": "Person",
                "name": "Rolf Axelson",
                "birthDate": "1937"
            }
        ],
        "alumniOf": {
            "@type": "CollegeOrUniversity",
            "name": "Commercial College"
        },
        "workExperience": [
            {
                "@type": "Organization",
                "name": "Bergmans Bookstore",
                "startDate": "1913",
                "endDate": "1915"
            },
            {
                "@type": "Organization",
                "name": "Jönköping city accountant's office",
                "startDate": "1915",
                "endDate": "1918"
            },
            {
                "@type": "Organization",
                "name": "Småland's Allehanda",
                "startDate": "1918",
                "endDate": "1944"
            }
        ],
        "memberOf": [
            {
                "@type": "Organization",
                "name": "Jönköping radio club",
                "foundingLocation": {
                    "@type": "Place",
                    "name": "Jönköping"
                },
                "foundingDate": "1927",
                "hasBoardMember": true
            },
            {
                "@type": "Organization",
                "name": "Jönköping scout troop",
                "isHonoraryMember": true
            },
            {
                "@type": "Organization",
                "name": "Jönköping right-wing association",
                "formerMember": true,
                "hasBoardMember": true
            },
            {
                "@type": "Organization",
                "name": "Swedish Motorist Club",
                "hasBoardMember": true
            },
            {
                "@type": "Organization",
                "name": "Jönköping southern property owners' association",
                "hasBoardMember": true
            },
            {
                "@type": "Organization",
                "name": "Jönköping traffic association",
                "hasBoardMember": true
            },
            {
                "@type": "Organization",
                "name": "Friends of the Old Poor association",
                "hasBoardMember": true
            },
            {
                "@type": "Organization",
                "name": "Jönköping Scout Group Benevolent Association",
                "hasBoardMember": true
            },
            {
                "@type": "Organization",
                "name": "Swedish Journalist Association",
                "isMember": true
            }
        ],
        "signature": [
            "-c",
            "Nic",
            "O.A. Hobbres"
        ],
        "interest": [
            {
                "@type": "Thing",
                "name": "Philately"
            },
            {
                "@type": "Thing",
                "name": "Fishing"
            },
            {
                "@type": "Thing",
                "name": "Motorsport"
            }
        ],
        "award": [
            {
                "@type": "Thing",
                "name": "Swedish Scout Association White Hedging Badge"
            },
            {
                "@type": "Thing",
                "name": "PatrGM"
            }
        ]
    }
}