{
    "original": "Ysander, David Torsten, biskop, Linköping, f. 10/3/93 i Tölö, Hall. 1., av kyrkoh. Bengt Y. o. Amanda Wetter-quist. G. 23 m. Ebba Key-Aberg. Barn: Berit f. 24, Ursula 25, Bengt-Christer 31. — Stud:ex. v. Gbgs h. latin 11, teol. fil. ex. i Gbg 12, fil. kand. där 1’5, teol. kand. o. prakt. teol. ex. i Upps. samt prästex. i Gbg 19, teol. lic. i Upps. 25, teol. dr där 33. Fas,t :adj. i Upps. 19-20, tf. kyrkoh. i Vänge-Läby 20, ord. 23-30, tf. kontr :prost 22-24, pred. v. Akad. sjukih. i Upps. 20, adj. led. i Upps. dom-kap. somr. 26-23, sekr. i ärkestiftets stiftsråd 26, förest, f. sam^t lär. i kris-tend. v. Fjellstedtska sk. i Upps. 30-36, docent i teol. preno-t. o. teol. encykl. v. Upps. univ. 331-35, domprost i Gbg 315, biskop i Visby stift 36-47, e. o. hov-pred. 39, biskop i Linköp. stift fr. 47. Res. t. Engl. 12, Fölen o. Österr. 22, Engl. o. Holl. 27. Skr.: Det andl. nutidsläget o. kyrkan (19), Vänge-Läby förs :hem (28), Gudsordet o. religionerna (30), Das Judentum nach Ghristus (31), Missionen - Guds hemlighet (32), Hasidismien (33), Förkunnelsen o. för-kunnaren (tills. m. B. Jonzon 34), Herdabrev (3*7), I Gbgs domkyrka (37), Från Visby S :ta Maria (41), De hundra kyrkornas ö (41), Lyckans villkor (44), Folkförsoningen o. vedergällningen (44) m. fl. skr. i relig:hist. o. teol. frågor, art. i teol. o. kyrkl. tidskr. samt dagspressen. KNOlkl,",
    "translated": "Ysander, David Torsten, bishop, Linköping, b. 10/3/93 in Tölö, Halland. 1st child of Vicar Bengt Y. and Amanda Wetterquist. Married on the 23rd with Ebba Key-Aberg. Children: Berit b. 24, Ursula b. 25, Bengt-Christer b. 31. \n\nEducation: Graduated from Gothenburg high school of Latin in 1911, receiving a theology degree from Gothenburg in 1912, a Bachelor of Philosophy degree from Gothenburg in 1915, a theology degree and practical theology examination from Uppsala, and a priest examination in Gothenburg in 1919. Obtained a theological licentiate degree in Uppsala in 1925 and a theological doctorate there in 1933. \n\nPositions: Assistant professor in Uppsala from 1919 to 1920, temporary vicar in Vänge-Läby from 1920, permanent from 1923 to 1930, temporary archdeacon from 1922 to 1924, preacher at the Academy Hospital in Uppsala in 1920, adjunct member at the Uppsala Cathedral Chapter during the summers of 1926-1923, secretary in the diocesan council of the archbishopric in 1926, superintendent and teacher of Christian doctrine at Fjellstedtska School in Uppsala from 1930 to 1936, docent in theology and biblical exegesis at Uppsala University from 1931 to 1935, cathedral provost in Gothenburg from 1931, bishop of the Visby diocese from 1936 to 1947, temporary court chaplain in 1939, bishop of the Linköping diocese from 1947. Traveled to England in 1912, Denmark and Austria in 1922, England and the Netherlands in 1927. \n\nWorks: \"The Spiritual Present Situation and the Church\" (1919), \"Vänge-Läby Parish: Home\" (1928), \"The Word of God and Religions\" (1930), \"Das Judentum nach Ghristus\" (1931), \"Mission - God's Mystery\" (1932), \"Hasidismien\" (1933), \"Preaching and the Preacher\" (written in collaboration with B. Jonzon, 1934), \"Pastoral Letters\" (1937), \"In Gothenburg Cathedral\" (1937), \"From Visby St. Mary\" (1941), \"The Hundred Churches' Island\" (1941), \"The Conditions of Happiness\" (1944), \"The Reconciliation of the People and Retribution\" (1944), and several more works on religious history and theological topics. Also wrote articles for theological and ecclesiastical journals as well as the daily press. Recipient of the Royal Order of the North Star (KNOlkl).",
    "structured_raw": "{\n  \"@context\": \"https://schema.org\",\n  \"@type\": \"Person\",\n  \"name\": \"David Torsten Ysander\",\n  \"givenName\": \"David Torsten\",\n  \"familyName\": \"Ysander\",\n  \"birthDate\": \"1893-03-10\",\n  \"birthPlace\": \"Tölö, Halland, Sweden\",\n  \"deathDate\": null,\n  \"nationality\": \"Swedish\",\n  \"occupation\": \"Bishop\",\n  \"alumniOf\": [\n    {\n      \"@type\": \"EducationalOrganization\",\n      \"name\": \"Gothenburg High School of Latin\"\n    },\n    {\n      \"@type\": \"EducationalOrganization\",\n      \"name\": \"University of Gothenburg\"\n    },\n    {\n      \"@type\": \"EducationalOrganization\",\n      \"name\": \"Uppsala University\"\n    }\n  ],\n  \"parents\": [\n    {\n      \"@type\": \"Person\",\n      \"givenName\": \"Bengt\",\n      \"familyName\": \"Ysander\",\n      \"occupation\": \"Vicar\"\n    },\n    {\n      \"@type\": \"Person\",\n      \"givenName\": \"Amanda\",\n      \"familyName\": \"Wetterquist\"\n    }\n  ],\n  \"spouse\": {\n    \"@type\": \"Person\",\n    \"givenName\": \"Ebba\",\n    \"familyName\": \"Key-Aberg\"\n  },\n  \"children\": [\n    {\n      \"@type\": \"Person\",\n      \"name\": \"Berit\",\n      \"birthDate\": \"1924\"\n    },\n    {\n      \"@type\": \"Person\",\n      \"name\": \"Ursula\",\n      \"birthDate\": \"1925\"\n    },\n    {\n      \"@type\": \"Person\",\n      \"givenName\": \"Bengt-Christer\",\n      \"familyName\": \"Ysander\",\n      \"birthDate\": \"1931\"\n    }\n  ],\n  \"works\": [\n    {\n      \"@type\": \"CreativeWork\",\n      \"name\": \"The Spiritual Present Situation and the Church\",\n      \"datePublished\": \"1919\"\n    },\n    {\n      \"@type\": \"CreativeWork\",\n      \"name\": \"Vänge-Läby Parish: Home\",\n      \"datePublished\": \"1928\"\n    },\n    {\n      \"@type\": \"CreativeWork\",\n      \"name\": \"The Word of God and Religions\",\n      \"datePublished\": \"1930\"\n    },\n    {\n      \"@type\": \"CreativeWork\",\n      \"name\": \"Das Judentum nach Ghristus\",\n      \"datePublished\": \"1931\"\n    },\n    {\n      \"@type\": \"CreativeWork\",\n      \"name\": \"Mission - God's Mystery\",\n      \"datePublished\": \"1932\"\n    },\n    {\n      \"@type\": \"CreativeWork\",\n      \"name\": \"Hasidismien\",\n      \"datePublished\": \"1933\"\n    },\n    {\n      \"@type\": \"CreativeWork\",\n      \"name\": \"Preaching and the Preacher\",\n      \"datePublished\": \"1934\"\n    },\n    {\n      \"@type\": \"CreativeWork\",\n      \"name\": \"Pastoral Letters\",\n      \"datePublished\": \"1937\"\n    },\n    {\n      \"@type\": \"CreativeWork\",\n      \"name\": \"In Gothenburg Cathedral\",\n      \"datePublished\": \"1937\"\n    },\n    {\n      \"@type\": \"CreativeWork\",\n      \"name\": \"From Visby St. Mary\",\n      \"datePublished\": \"1941\"\n    },\n    {\n      \"@type\": \"CreativeWork\",\n      \"name\": \"The Hundred Churches' Island\",\n      \"datePublished\": \"1941\"\n    },\n    {\n      \"@type\": \"CreativeWork\",\n      \"name\": \"The Conditions of Happiness\",\n      \"datePublished\": \"1944\"\n    },\n    {\n      \"@type\": \"CreativeWork\",\n      \"name\": \"The Reconciliation of the People and Retribution\",\n      \"datePublished\": \"1944\"\n    }\n  ],\n  \"memberOf\": [\n    {\n      \"@type\": \"Organization\",\n      \"name\": \"Linköping Diocese\"\n    },\n    {\n      \"@type\": \"Organization\",\n      \"name\": \"Visby Diocese\"\n    }\n  ],\n  \"honorificSuffix\": \"KNOlkl\",\n  \"residence\": [\n    {\n      \"@type\": \"Place\",\n      \"name\": \"Linköping, Sweden\"\n    }\n  ],\n  \"memberOf\": [\n    {\n      \"@type\": \"Organization\",\n      \"name\": \"Linköping Diocese\",\n      \"startDate\": \"1947-01-01\"\n    }\n  ],\n  \"sameAs\": [\n    \"https://viaf.org/viaf/235250345\",\n    \"https://www.wikidata.org/wiki/Q45775850\"\n  ]\n}",
    "structured": {
        "@context": "https://schema.org",
        "@type": "Person",
        "name": "David Torsten Ysander",
        "givenName": "David Torsten",
        "familyName": "Ysander",
        "birthDate": "1893-03-10",
        "birthPlace": "Tölö, Halland, Sweden",
        "deathDate": null,
        "nationality": "Swedish",
        "occupation": "Bishop",
        "alumniOf": [
            {
                "@type": "EducationalOrganization",
                "name": "Gothenburg High School of Latin"
            },
            {
                "@type": "EducationalOrganization",
                "name": "University of Gothenburg"
            },
            {
                "@type": "EducationalOrganization",
                "name": "Uppsala University"
            }
        ],
        "parents": [
            {
                "@type": "Person",
                "givenName": "Bengt",
                "familyName": "Ysander",
                "occupation": "Vicar"
            },
            {
                "@type": "Person",
                "givenName": "Amanda",
                "familyName": "Wetterquist"
            }
        ],
        "spouse": {
            "@type": "Person",
            "givenName": "Ebba",
            "familyName": "Key-Aberg"
        },
        "children": [
            {
                "@type": "Person",
                "name": "Berit",
                "birthDate": "1924"
            },
            {
                "@type": "Person",
                "name": "Ursula",
                "birthDate": "1925"
            },
            {
                "@type": "Person",
                "givenName": "Bengt-Christer",
                "familyName": "Ysander",
                "birthDate": "1931"
            }
        ],
        "works": [
            {
                "@type": "CreativeWork",
                "name": "The Spiritual Present Situation and the Church",
                "datePublished": "1919"
            },
            {
                "@type": "CreativeWork",
                "name": "Vänge-Läby Parish: Home",
                "datePublished": "1928"
            },
            {
                "@type": "CreativeWork",
                "name": "The Word of God and Religions",
                "datePublished": "1930"
            },
            {
                "@type": "CreativeWork",
                "name": "Das Judentum nach Ghristus",
                "datePublished": "1931"
            },
            {
                "@type": "CreativeWork",
                "name": "Mission - God's Mystery",
                "datePublished": "1932"
            },
            {
                "@type": "CreativeWork",
                "name": "Hasidismien",
                "datePublished": "1933"
            },
            {
                "@type": "CreativeWork",
                "name": "Preaching and the Preacher",
                "datePublished": "1934"
            },
            {
                "@type": "CreativeWork",
                "name": "Pastoral Letters",
                "datePublished": "1937"
            },
            {
                "@type": "CreativeWork",
                "name": "In Gothenburg Cathedral",
                "datePublished": "1937"
            },
            {
                "@type": "CreativeWork",
                "name": "From Visby St. Mary",
                "datePublished": "1941"
            },
            {
                "@type": "CreativeWork",
                "name": "The Hundred Churches' Island",
                "datePublished": "1941"
            },
            {
                "@type": "CreativeWork",
                "name": "The Conditions of Happiness",
                "datePublished": "1944"
            },
            {
                "@type": "CreativeWork",
                "name": "The Reconciliation of the People and Retribution",
                "datePublished": "1944"
            }
        ],
        "memberOf": [
            {
                "@type": "Organization",
                "name": "Linköping Diocese",
                "startDate": "1947-01-01"
            }
        ],
        "honorificSuffix": "KNOlkl",
        "residence": [
            {
                "@type": "Place",
                "name": "Linköping, Sweden"
            }
        ],
        "sameAs": [
            "https://viaf.org/viaf/235250345",
            "https://www.wikidata.org/wiki/Q45775850"
        ]
    }
}