{
    "original": "Karlsson, Karil Gustaf Yngve, kyrkoherde, KäUby, f. 19/7/01 i ^ Habo, Skarab. 1. G. 35 m. Emma Gurli Eleonora Rang. Barn: Sigfrid f. 36, Ragnar 37, Birgitta 39, Harald 41, Yngve Efraimj 43. — Stud:ex. i Upps. 26, teol. fil. ex, 27, teo’L kiand. 30, pratkt. teOil. prov O’, prästv. s. å. V. paistor i KäLlby 30-33, i Habo 33-34, stiftsadj. 34-38, kyrtoadj. i Skövde 38-41, kyrikoh. i Källby fr. 41. Ordf. i kyrkoråden o. sikoltstyr., d-ed. av barnavmd. Carlsson-Betts, Inez, prakt, läkare, Ronneby, f. 3/5/91 i Karlshamn av Carl Fredrik Carlsson o. Ingrid Nilsson. G. 42 m. fd. maskining. William Betts. — Studiex. 11, med. kand. 14 o. med. lic. 20, allt i Sthlm. Föret, studires. t. ett flert. europ. länder. Kort. förordn. som e. läk. v. oiika las., sanat. o. hosp. 16-19, klin. aman. v. Sthlms hosp. 17 o. 20, e. läk. v. Växjö hosp. 20, andre und :&lt;läk. v. Högbo tub :isjukh. 21, tf. förste und :läk. där 21-22, läk. v. Älvgårdens sjukh. i Dalarna samt v. Västmanl. 1. tub :sjukh. 22, assist :läk. o. tf. andre und:läk. v. Vänersborgs las. 22-23, und:läk. v. Pens:styr. isjukh. i Åre 23-25, därunder tf. överläk. tre mån., tf. prov:-l!äk. i Ronneby m. fil. distr. kort. tider 25-47, pr^kt lak. i Ronneby sed. 25, lläk. v. Bleking|e komm. vårdhem sed. 29. Led. av ’stadsfullm. 30-42. Carlsson Ring, Carl Johan, direktör, nämndeman, Ringås, f. 26/8/99 i Ör-tomta, östergötl. 1., av nämndeman C. J. Carlsson o. Maria Larsdotter. G. 27 m. Aina Görarns son. Barn: Björn f. 28, Birgitta 31. — Studrex. i Linköp. 19. Anst. v. Sthlms Skofabr. A-B 19-24, intr. i faderns firma Carlsson Ring i Örtomta 24, dir. f. Aukt .’firman C. J. Carlsson Ring i Linköp. sed. 28. Nämndeman i Linköp. doms. sed. 34, inneh. ett flertal rev :uppdr. i ekon. isammanslutn. samt kommunala uppdr. Medl. av Odd Felilow o. KAK. *Karlsteen, Karl Oskar Arvid Henrik, ingenjör, stadsbyggmästare, Göteborg, f. 27/8/90 i Sthlm. G. m. Lisa Carlsson. Barn: Britta f. 23. — Lä-rovistud. i Sthlm, ex. v. STI 14. Konstr. o. ing. v. Bergsmek. byrån i Ludvika 15-17, chef f. Domnarvets Jernverks arkit:byrå 17-24, byggn:-ing. h. folksk:styr. i Gbg 24-31, stads-byggmäst. i Gbg sed. 31. Medi. av Sthlms gymnrförb. 10-15. Svgifrfb plakett, Sthlms gymn:förb. MM.",
    "translated": "Karlsson, Karil Gustaf Yngve, parish pastor, KäUby, born on July 19, 1901, in Habo, Skaraborg. First marriage in 1935 with Emma Gurli Eleonora Rang. Children: Sigfrid, born in 1936; Ragnar, born in 1937; Birgitta, born in 1939; Harald, born in 1941; Yngve Efraimj, born in 1943. Education: graduated in Uppsala in 1926, theological studies in 1927, practical theology examination in the same year, ordained as a pastor in 1930. Pastoral appointments in KäUby from 1930-1933, in Habo from 1933-1934, diocesan adjutant from 1934-1938, church adjutant in Skövde from 1938-1941, parish pastor in Källby from 1941. Chairman of church councils and school boards, member of the board of children's welfare. \n\nCarlsson-Betts, Inez, practicing physician in Ronneby, born on May 3, 1891, in Karlshamn, to Carl Fredrik Carlsson and Ingrid Nilsson. Second marriage in 1942 with former engineer William Betts. Education: graduated in 1911, medical candidate in 1914, medical licentiate in 1920, all in Stockholm. Further studies in several European countries. Worked as a medical intern at various hospitals and clinics from 1916-1919, clinical assistant at Stockholm Hospital in 1917 and 1920, resident physician at Växjö Hospital in 1920, second assistant physician at Högbo Tuberculosis Hospital in 1921, acting chief physician there in 1921-1922, physician at Älvgården Hospital in Dalarna and Västmanland Tuberculosis Hospital in 1922, assistant physician and acting second assistant physician at Vänersborg Hospital in 1922-1923, physician at Pensionatstyrelsen's Hospital in Åre from 1923-1925, temporary chief physician for three months, temporary district medical officer in Ronneby with a district of fil. studies during short periods from 1925-1947, practicing physician in Ronneby since 1925, physician at the Blekinge Municipal Care Home since 1929. Member of the City Council from 1930-1942. \n\nCarlsson Ring, Carl Johan, director, lay judge, Ringås, born on August 26, 1899, in Örtomta, Östergötland county, son of lay judge C. J. Carlsson and Maria Larsdotter. Married in 1927 to Aina Görarns son. Children: Björn, born in 1928; Birgitta, born in 1931. Education: graduated in Linköping in 1919. Employed at Stockholm Footwear Factory A-B from 1919-1924, entered his father's firm Carlsson Ring in Örtomta in 1924, director of Aukt. firm C. J. Carlsson Ring in Linköping since 1928. Lay judge in Linköping Court since 1934, held several positions in economic associations and municipal tasks. Member of the Odd Fellow and KAK (Swedish Automobile Club). \n\nKarlsteen, Karl Oskar Arvid Henrik, engineer, city architect, Gothenburg, born on August 27, 1890, in Stockholm. Married to Lisa Carlsson. Child: Britta, born in 1923. Education: studied at a high school in Stockholm, graduated from STI in 1914. Construction and engineering work at Bergsmek. Agency in Ludvika from 1915-1917, head of Domnarvet Ironworks' architectural bureau from 1917-1924, building engineer for the public elementary school board in Gothenburg from 1924-1931, city architect in Gothenburg since 1931. Member of Stockholm Gymnastics Association from 1910-1915. Recipient of the Sthlms Gymnastic Association plaque.",
    "structured_raw": "{\n  \"@context\": \"https://schema.org\",\n  \"@type\": \"Person\",\n  \"givenName\": \"Karil Gustaf Yngve\",\n  \"familyName\": \"Karlsson\",\n  \"gender\": \"Male\",\n  \"birthDate\": \"1901-07-19\",\n  \"birthPlace\": {\n    \"@type\": \"Place\",\n    \"address\": {\n      \"@type\": \"PostalAddress\",\n      \"addressLocality\": \"Habo, Skaraborg\"\n    }\n  },\n  \"parents\": [\n    {\n      \"@type\": \"Person\",\n      \"givenName\": \"Carl Fredrik\",\n      \"familyName\": \"Carlsson\",\n      \"gender\": \"Male\"\n    },\n    {\n      \"@type\": \"Person\",\n      \"givenName\": \"Ingrid\",\n      \"familyName\": \"Nilsson\",\n      \"gender\": \"Female\"\n    }\n  ],\n  \"spouse\": {\n    \"@type\": \"Person\",\n    \"givenName\": \"Emma Gurli Eleonora\",\n    \"familyName\": \"Rang\",\n    \"gender\": \"Female\"\n  },\n  \"children\": [\n    {\n      \"@type\": \"Person\",\n      \"givenName\": \"Sigfrid\",\n      \"birthDate\": \"1936\"\n    },\n    {\n      \"@type\": \"Person\",\n      \"givenName\": \"Ragnar\",\n      \"birthDate\": \"1937\"\n    },\n    {\n      \"@type\": \"Person\",\n      \"givenName\": \"Birgitta\",\n      \"birthDate\": \"1939\"\n    },\n    {\n      \"@type\": \"Person\",\n      \"givenName\": \"Harald\",\n      \"birthDate\": \"1941\"\n    },\n    {\n      \"@type\": \"Person\",\n      \"givenName\": \"Yngve Efraimj\",\n      \"birthDate\": \"1943\"\n    }\n  ],\n  \"education\": [\n    {\n      \"@type\": \"EducationalOccupationalCredential\",\n      \"credentialCategory\": \"Academic\",\n      \"educationalLevel\": \"Bachelor's Degree\",\n      \"educationalProgram\": \"Studiex.\",\n      \"educationalSpecialty\": \"Uppsala\",\n      \"startDate\": \"1926\",\n      \"endDate\": \"1927\"\n    },\n    {\n      \"@type\": \"EducationalOccupationalCredential\",\n      \"credentialCategory\": \"Academic\",\n      \"educationalLevel\": \"Bachelor's Degree\",\n      \"educationalProgram\": \"Teology\",\n      \"startDate\": \"1927\",\n      \"endDate\": \"1930\"\n    }\n  ],\n  \"occupation\": [\n    {\n      \"@type\": \"OrganizationRole\",\n      \"startDate\": \"1930\",\n      \"endDate\": \"1933\",\n      \"roleName\": \"Pastor\",\n      \"namedPosition\": \"KäUby\"\n    },\n    {\n      \"@type\": \"OrganizationRole\",\n      \"startDate\": \"1933\",\n      \"endDate\": \"1934\",\n      \"roleName\": \"Pastor\",\n      \"namedPosition\": \"Habo\"\n    },\n    {\n      \"@type\": \"OrganizationRole\",\n      \"startDate\": \"1934\",\n      \"endDate\": \"1938\",\n      \"roleName\": \"Diocesan Adjutant\"\n    },\n    {\n      \"@type\": \"OrganizationRole\",\n      \"startDate\": \"1938\",\n      \"endDate\": \"1941\",\n      \"roleName\": \"Church Adjutant\",\n      \"namedPosition\": \"Skövde\"\n    },\n    {\n      \"@type\": \"OrganizationRole\",\n      \"startDate\": \"1941\",\n      \"roleName\": \"Parish Pastor\",\n      \"namedPosition\": \"Källby\"\n    }\n  ]\n}",
    "structured": {
        "@context": "https://schema.org",
        "@type": "Person",
        "givenName": "Karil Gustaf Yngve",
        "familyName": "Karlsson",
        "gender": "Male",
        "birthDate": "1901-07-19",
        "birthPlace": {
            "@type": "Place",
            "address": {
                "@type": "PostalAddress",
                "addressLocality": "Habo, Skaraborg"
            }
        },
        "parents": [
            {
                "@type": "Person",
                "givenName": "Carl Fredrik",
                "familyName": "Carlsson",
                "gender": "Male"
            },
            {
                "@type": "Person",
                "givenName": "Ingrid",
                "familyName": "Nilsson",
                "gender": "Female"
            }
        ],
        "spouse": {
            "@type": "Person",
            "givenName": "Emma Gurli Eleonora",
            "familyName": "Rang",
            "gender": "Female"
        },
        "children": [
            {
                "@type": "Person",
                "givenName": "Sigfrid",
                "birthDate": "1936"
            },
            {
                "@type": "Person",
                "givenName": "Ragnar",
                "birthDate": "1937"
            },
            {
                "@type": "Person",
                "givenName": "Birgitta",
                "birthDate": "1939"
            },
            {
                "@type": "Person",
                "givenName": "Harald",
                "birthDate": "1941"
            },
            {
                "@type": "Person",
                "givenName": "Yngve Efraimj",
                "birthDate": "1943"
            }
        ],
        "education": [
            {
                "@type": "EducationalOccupationalCredential",
                "credentialCategory": "Academic",
                "educationalLevel": "Bachelor's Degree",
                "educationalProgram": "Studiex.",
                "educationalSpecialty": "Uppsala",
                "startDate": "1926",
                "endDate": "1927"
            },
            {
                "@type": "EducationalOccupationalCredential",
                "credentialCategory": "Academic",
                "educationalLevel": "Bachelor's Degree",
                "educationalProgram": "Teology",
                "startDate": "1927",
                "endDate": "1930"
            }
        ],
        "occupation": [
            {
                "@type": "OrganizationRole",
                "startDate": "1930",
                "endDate": "1933",
                "roleName": "Pastor",
                "namedPosition": "KäUby"
            },
            {
                "@type": "OrganizationRole",
                "startDate": "1933",
                "endDate": "1934",
                "roleName": "Pastor",
                "namedPosition": "Habo"
            },
            {
                "@type": "OrganizationRole",
                "startDate": "1934",
                "endDate": "1938",
                "roleName": "Diocesan Adjutant"
            },
            {
                "@type": "OrganizationRole",
                "startDate": "1938",
                "endDate": "1941",
                "roleName": "Church Adjutant",
                "namedPosition": "Skövde"
            },
            {
                "@type": "OrganizationRole",
                "startDate": "1941",
                "roleName": "Parish Pastor",
                "namedPosition": "Källby"
            }
        ]
    }
}