{
    "original": "Bolin, Olof Daniel, folkskollärare. Stenkyrka, f. 10/3/78 i Sproge s :n, Gotl. 1. G. 05 m. Elise Engström. Barn: Elsa, g. Calamnius. — Folksk:-lär:ex. 99. Lär. v. Stenkyrka sk. sed. 00, tillsyn :lär. där sed. 20. Tf. folk-sk :insp. i Gotl. insp :omr. somr. 26 o. 27. Ordf. i barnavind sed. 24, i komm:stämma sed. 38 o. i komm:-fullm. sed. 39, v. ordf. i pensrnd o. valnd, led. av kyrkoråd sed. 45, kro-noomb. v. tax., kyrko-, prästlöne-, skol- o. pastoratskassör sed. 25, lär kårens repr. i skolrådet sed. 06, ordf. i Sv:es allm. folksk :lär :fören. länsnd på Gotl. sed. 25, i Stenkyrka hem-bygdsfören. sed. 31, led. av styr. f. Gotl.-krets. av Sv:es allm. folksk :-lär:fören. sed. 23, riksantikv. omb. inom Stenkyrka-Tingstäde-Martebo-Lummelunda socknar sed. 28, led. av styr. f. Visby barn- o. upptagn :hem. GMmf 5 st. 45.",
    "translated": "Bolin, Olof Daniel, primary school teacher. Stenkyrka, born on March 10, 1878 in Sproge parish, Gotland. Married in 1905 to Elise Engström. Children: Elsa, married to Calamnius. Primary school teaching degree received in 1899. Started teaching at Stenkyrka school in 1900, promoted to supervising teacher in 1920. Acting inspector for Gotland's inspectoral district for two summers in 1926 and 1927. Chairman of the board for Barnavind since 1924, in the municipality assembly since 1938, in the municipal council since 1939, vice chairman of the pension and choice committee, member of the church council since 1945, tax official for the crown, treasurer for the church, clergy, school, and parish since 1925, representative for the teaching corps in the school council since 1906, chairman of the Swedish primary school teacher association's county committee on Gotland since 1925, chairman of the Stenkyrka local history association since 1931, member of the board for the Gotland district of the Swedish primary school teacher association since 1923, national antiquarian delegate within the Stenkyrka-Tingstäde-Martebo-Lummelunda parishes since 1928, member of the board for Visby children's home and intake center. Married to five children since 1945.",
    "structured_raw": "{\n  \"@context\": \"https://schema.org\",\n  \"@type\": \"Person\",\n  \"name\": \"Olof Daniel Bolin\",\n  \"birthDate\": \"1878-03-10\",\n  \"birthPlace\": \"Sproge parish, Gotland\",\n  \"spouse\": {\n    \"@type\": \"Person\",\n    \"name\": \"Elise Engström\",\n    \"marriageDate\": \"1905\"\n  },\n  \"children\": [\n    {\n      \"@type\": \"Person\",\n      \"name\": \"Elsa Calamnius\"\n    }\n  ],\n  \"education\": {\n    \"@type\": \"EducationEvent\",\n    \"eventDate\": \"1899\",\n    \"description\": \"Primary school teaching degree\"\n  },\n  \"jobTitle\": \"Primary School Teacher\",\n  \"affiliation\": [\n    {\n      \"@type\": \"Organization\",\n      \"name\": \"Stenkyrka School\",\n      \"startDate\": \"1900\",\n      \"endDate\": \"1920\"\n    },\n    {\n      \"@type\": \"Organization\",\n      \"name\": \"Gotland Inspectoral District\",\n      \"startDate\": \"1926\",\n      \"endDate\": \"1927\"\n    },\n    {\n      \"@type\": \"Organization\",\n      \"name\": \"Barnavind\",\n      \"startDate\": \"1924\"\n    },\n    {\n      \"@type\": \"Organization\",\n      \"name\": \"Municipality Assembly\",\n      \"startDate\": \"1938\"\n    },\n    {\n      \"@type\": \"Organization\",\n      \"name\": \"Municipal Council\",\n      \"startDate\": \"1939\"\n    },\n    {\n      \"@type\": \"Organization\",\n      \"name\": \"Pension and Choice Committee\",\n      \"description\": \"Vice Chairman\"\n    },\n    {\n      \"@type\": \"Organization\",\n      \"name\": \"Church Council\",\n      \"startDate\": \"1945\"\n    },\n    {\n      \"@type\": \"Organization\",\n      \"name\": \"Swedish Primary School Teacher Association\",\n      \"description\": \"Representative for the teaching corps in the school council since 1906\",\n      \"affiliationLocation\": [\n        {\n          \"@type\": \"Country\",\n          \"name\": \"Sweden\"\n        },\n        {\n          \"@type\": \"AdministrativeArea\",\n          \"name\": \"Gotland County\"\n        }\n      ]\n    },\n    {\n      \"@type\": \"Organization\",\n      \"name\": \"Stenkyrka Local History Association\",\n      \"startDate\": \"1931\"\n    },\n    {\n      \"@type\": \"Organization\",\n      \"name\": \"Visby Children's Home and Intake Center\",\n      \"affiliationRole\": \"Member of Board\"\n    },\n    {\n      \"@type\": \"Organization\",\n      \"name\": \"Gotland District of the Swedish Primary School Teacher Association\",\n      \"startDate\": \"1923\"\n    }\n  ]\n}",
    "structured": {
        "@context": "https://schema.org",
        "@type": "Person",
        "name": "Olof Daniel Bolin",
        "birthDate": "1878-03-10",
        "birthPlace": "Sproge parish, Gotland",
        "spouse": {
            "@type": "Person",
            "name": "Elise Engström",
            "marriageDate": "1905"
        },
        "children": [
            {
                "@type": "Person",
                "name": "Elsa Calamnius"
            }
        ],
        "education": {
            "@type": "EducationEvent",
            "eventDate": "1899",
            "description": "Primary school teaching degree"
        },
        "jobTitle": "Primary School Teacher",
        "affiliation": [
            {
                "@type": "Organization",
                "name": "Stenkyrka School",
                "startDate": "1900",
                "endDate": "1920"
            },
            {
                "@type": "Organization",
                "name": "Gotland Inspectoral District",
                "startDate": "1926",
                "endDate": "1927"
            },
            {
                "@type": "Organization",
                "name": "Barnavind",
                "startDate": "1924"
            },
            {
                "@type": "Organization",
                "name": "Municipality Assembly",
                "startDate": "1938"
            },
            {
                "@type": "Organization",
                "name": "Municipal Council",
                "startDate": "1939"
            },
            {
                "@type": "Organization",
                "name": "Pension and Choice Committee",
                "description": "Vice Chairman"
            },
            {
                "@type": "Organization",
                "name": "Church Council",
                "startDate": "1945"
            },
            {
                "@type": "Organization",
                "name": "Swedish Primary School Teacher Association",
                "description": "Representative for the teaching corps in the school council since 1906",
                "affiliationLocation": [
                    {
                        "@type": "Country",
                        "name": "Sweden"
                    },
                    {
                        "@type": "AdministrativeArea",
                        "name": "Gotland County"
                    }
                ]
            },
            {
                "@type": "Organization",
                "name": "Stenkyrka Local History Association",
                "startDate": "1931"
            },
            {
                "@type": "Organization",
                "name": "Visby Children's Home and Intake Center",
                "affiliationRole": "Member of Board"
            },
            {
                "@type": "Organization",
                "name": "Gotland District of the Swedish Primary School Teacher Association",
                "startDate": "1923"
            }
        ]
    }
}