{
    "original": "Börjesson, Artur, disponent, Halmstad, f. 27/2/92 i Frillesås, Hall. 1., av lantbr. A. P. B. o. Lena Andersson. G. 25 m. Ingeborg Andrup. Barn: Börje f. 28, Per-Henrik 30. — Genomg. folkhögsk., lantmisk. o. agronomkurser, hand-.stud. Förv. v. slakt, i Halmstad 20, anst. i London 22-23, affiled. i Plalmstads slakt :fören. sed. 24, tillika disp. v. Hall. slaktbosk :fören. sed. 37. Red. f. Hall. Lantmannatidn. sed. 26. V. ordf. i styr. f. Sv. exp rslakt rfören. sed. 35, led. av statens jordbr :nd 35-39, av statens livsmrkomm. råd sed. 39 o. chef f. dess slakt :sekt. 40-43, led. av stadsfullm. sed. 28, led. av stads-fullm. beredn:utsk. sed. 43, av hamnstyr. 30-40, suppl. i styr. f. Sydsv. Kraft A-B sed. 44, ordf. i Halmstads stads trafiknd sed. 46, statsrev. Hobby: golf. RVO, Hall. hush:sällsk. stGM, LLA.",
    "translated": "Börjesson, Artur, manager, Halmstad, born February 27, 1892 in Frillesås, Halland County, son of farmer A. P. B. and Lena Andersson. Married to Ingeborg Andrup in 1925. Children: Börje born in 1928 and Per-Henrik born in 1930. He attended folk high school, took courses in agriculture and agronomy, and studied business. He trained in slaughterhouses in Halmstad in 1920 and was employed in London from 1922-23. He joined the Halmstad Slaughter Association in 1924 and became its manager in 1937. He was also a member of the board of directors for the Halland Cattle Slaughtering Association. He became the editor of the Halland Farmer newspaper in 1926. He was the vice chairman of the board for the Swedish export slaughter industry association in 1935, a member of the National Board of Agriculture from 1935-39, a member of the National Food Committee from 1939 and chief of its slaughter department from 1940-43. He was a member of the city council from 1928 and a member of the city council planning committee from 1943, a member of the port authority from 1930-40 and a substitute member of the board of directors for Sydsvenska Kraft AB from 1944. He was the chairman of the Halmstad city traffic board from 1946. His hobbies included golf. He received the Order of Vasa, a Commander of the Royal Swedish Patriotic Society, and was a member of the Royal Agricultural Society.",
    "structured_raw": "{\n  \"@context\": \"https://schema.org\",\n  \"@type\": \"Person\",\n  \"name\": \"Artur Börjesson\",\n  \"birthDate\": \"1892-02-27\",\n  \"birthPlace\": {\n    \"@type\": \"Place\",\n    \"address\": {\n      \"@type\": \"PostalAddress\",\n      \"addressLocality\": \"Frillesås\",\n      \"addressRegion\": \"Halland County\"\n    }\n  },\n  \"deathDate\": null,\n  \"spouse\": {\n    \"@type\": \"Person\",\n    \"name\": \"Ingeborg Andrup\",\n    \"marriageDate\": \"1925\"\n  },\n  \"children\": [\n    {\n      \"@type\": \"Person\",\n      \"name\": \"Börje\",\n      \"birthDate\": \"1928\"\n    },\n    {\n      \"@type\": \"Person\",\n      \"name\": \"Per-Henrik\",\n      \"birthDate\": \"1930\"\n    }\n  ],\n  \"education\": [\n    {\n      \"@type\": \"EducationalOccupationalCredential\",\n      \"credentialCategory\": \"Folk High School\"\n    },\n    {\n      \"@type\": \"EducationalOccupationalCredential\",\n      \"credentialCategory\": \"Agriculture\"\n    },\n    {\n      \"@type\": \"EducationalOccupationalCredential\",\n      \"credentialCategory\": \"Agronomy\"\n    },\n    {\n      \"@type\": \"EducationalOccupationalCredential\",\n      \"credentialCategory\": \"Business\"\n    }\n  ],\n  \"jobTitle\": \"Manager\",\n  \"worksFor\": {\n    \"@type\": \"Organization\",\n    \"name\": \"Halmstad Slaughter Association\"\n  },\n  \"memberOf\": [\n    {\n      \"@type\": \"Organization\",\n      \"name\": \"Halland Cattle Slaughtering Association\",\n      \"roleName\": \"Board of Directors\"\n    },\n    {\n      \"@type\": \"Organization\",\n      \"name\": \"Swedish Export Slaughter Industry Association\",\n      \"roleName\": \"Vice Chairman of the Board\"\n    },\n    {\n      \"@type\": \"Organization\",\n      \"name\": \"National Board of Agriculture\",\n      \"roleName\": \"Member\"\n    },\n    {\n      \"@type\": \"Organization\",\n      \"name\": \"National Food Committee\",\n      \"roleName\": \"Member\"\n    },\n    {\n      \"@type\": \"Organization\",\n      \"name\": \"City Council of Halmstad\",\n      \"roleName\": \"Member\"\n    },\n    {\n      \"@type\": \"Organization\",\n      \"name\": \"Port Authority\",\n      \"roleName\": \"Member\"\n    },\n    {\n      \"@type\": \"Organization\",\n      \"name\": \"Sydsvenska Kraft AB\",\n      \"roleName\": \"Substitute Member of the Board of Directors\"\n    },\n    {\n      \"@type\": \"Organization\",\n      \"name\": \"Halmstad City Traffic Board\",\n      \"roleName\": \"Chairman\"\n    }\n  ],\n  \"nationality\": \"Swedish\",\n  \"honorificPrefix\": null,\n  \"honorificSuffix\": \"RVO, Hall. hush:sällsk. stGM, LLA\",\n  \"description\": \"Editor of the Halland Farmer newspaper, and a golfer.\"\n}",
    "structured": {
        "@context": "https://schema.org",
        "@type": "Person",
        "name": "Artur Börjesson",
        "birthDate": "1892-02-27",
        "birthPlace": {
            "@type": "Place",
            "address": {
                "@type": "PostalAddress",
                "addressLocality": "Frillesås",
                "addressRegion": "Halland County"
            }
        },
        "deathDate": null,
        "spouse": {
            "@type": "Person",
            "name": "Ingeborg Andrup",
            "marriageDate": "1925"
        },
        "children": [
            {
                "@type": "Person",
                "name": "Börje",
                "birthDate": "1928"
            },
            {
                "@type": "Person",
                "name": "Per-Henrik",
                "birthDate": "1930"
            }
        ],
        "education": [
            {
                "@type": "EducationalOccupationalCredential",
                "credentialCategory": "Folk High School"
            },
            {
                "@type": "EducationalOccupationalCredential",
                "credentialCategory": "Agriculture"
            },
            {
                "@type": "EducationalOccupationalCredential",
                "credentialCategory": "Agronomy"
            },
            {
                "@type": "EducationalOccupationalCredential",
                "credentialCategory": "Business"
            }
        ],
        "jobTitle": "Manager",
        "worksFor": {
            "@type": "Organization",
            "name": "Halmstad Slaughter Association"
        },
        "memberOf": [
            {
                "@type": "Organization",
                "name": "Halland Cattle Slaughtering Association",
                "roleName": "Board of Directors"
            },
            {
                "@type": "Organization",
                "name": "Swedish Export Slaughter Industry Association",
                "roleName": "Vice Chairman of the Board"
            },
            {
                "@type": "Organization",
                "name": "National Board of Agriculture",
                "roleName": "Member"
            },
            {
                "@type": "Organization",
                "name": "National Food Committee",
                "roleName": "Member"
            },
            {
                "@type": "Organization",
                "name": "City Council of Halmstad",
                "roleName": "Member"
            },
            {
                "@type": "Organization",
                "name": "Port Authority",
                "roleName": "Member"
            },
            {
                "@type": "Organization",
                "name": "Sydsvenska Kraft AB",
                "roleName": "Substitute Member of the Board of Directors"
            },
            {
                "@type": "Organization",
                "name": "Halmstad City Traffic Board",
                "roleName": "Chairman"
            }
        ],
        "nationality": "Swedish",
        "honorificPrefix": null,
        "honorificSuffix": "RVO, Hall. hush:sällsk. stGM, LLA",
        "description": "Editor of the Halland Farmer newspaper, and a golfer."
    }
}