{
    "original": "Borgstedt, Bror Torsten, major, Eksjö, f. 17/5/90 i Ljungby av bankdir. Richard Gabriel B. o. Ina Ahlberg. G. 19 m. Ebba Jeanna Francke. Barn: Margareta f. 19, Curt 21, anst. v. Norska Amerika-Linjen, Märta 23. — Undilöjtn. v. Kalmar reg. 12, löjtn. 16, kapt. i armén 27, major i Jönköping-Kalmar reg. res. 39. Befälh. f. ro 19 i Värnamo 39-42, exp :off. i io 12 sed. 42. RSO, SkytteM.",
    "translated": "Borgstedt, Bror Torsten, Major, Eksjö, b. May 17th, 1890 in Ljungby, son of Bank Director Richard Gabriel B. and Ina Ahlberg. Married in 1919 to Ebba Jeanna Francke. Children: Margareta b. 1919, Curt b. 1921 employed by Norwegian America Line, Märta b. 1923. Formerly Second Lieutenant in the Kalmar Regiment, promoted to Lieutenant in 1916, Captain in the army in 1927, and Major in the Jönköping-Kalmar Regiment in the reserve in 1939. Commanding Officer of the Värnamo Rifle Battalion from 1939-1942 and retired as an Expeditionary Officer in 1942. Awarded the Order of the Sword and the Shooters' Medal.",
    "structured_raw": "{\n   \"@context\": \"https://schema.org\",\n   \"@type\": \"Person\",\n   \"name\": \"Bror Torsten Borgstedt\",\n   \"birthDate\": \"1890-05-17\",\n   \"birthPlace\": \"Ljungby\",\n   \"nationality\": \"Swedish\",\n   \"jobTitle\": \"Major\",\n   \"alumniOf\": [\n      {\n         \"@type\": \"Organization\",\n         \"name\": \"Kalmar Regiment\"\n      }\n   ],\n   \"spouse\": {\n      \"@type\": \"Person\",\n      \"name\": \"Ebba Jeanna Francke\",\n      \"marriageDate\": \"1919\"\n   },\n   \"children\": [\n      {\n         \"@type\": \"Person\",\n         \"name\": \"Margareta\",\n         \"birthDate\": \"1919\"\n      }, \n      {\n         \"@type\": \"Person\",\n         \"name\": \"Curt\",\n         \"birthDate\": \"1921\",\n         \"occupation\": \"Employed by Norwegian America Line\"\n      },\n      {\n         \"@type\": \"Person\",\n         \"name\": \"Märta\",\n         \"birthDate\": \"1923\"\n      }\n   ],\n   \"worksFor\": {\n      \"@type\": \"Organization\",\n      \"name\": \"Jönköping-Kalmar Regiment\"\n   },\n   \"memberOf\": {\n      \"@type\": \"Organization\",\n      \"name\": \"Swedish Army\"\n   },\n   \"award\": [\n      {\n         \"@type\": \"Order\",\n         \"name\": \"Order of the Sword\"\n      },\n      {\n         \"@type\": \"Medal\",\n         \"name\": \"Shooters' Medal\"\n      }\n   ],\n   \"deathDate\": \"1968\"\n}",
    "structured": {
        "@context": "https://schema.org",
        "@type": "Person",
        "name": "Bror Torsten Borgstedt",
        "birthDate": "1890-05-17",
        "birthPlace": "Ljungby",
        "nationality": "Swedish",
        "jobTitle": "Major",
        "alumniOf": [
            {
                "@type": "Organization",
                "name": "Kalmar Regiment"
            }
        ],
        "spouse": {
            "@type": "Person",
            "name": "Ebba Jeanna Francke",
            "marriageDate": "1919"
        },
        "children": [
            {
                "@type": "Person",
                "name": "Margareta",
                "birthDate": "1919"
            },
            {
                "@type": "Person",
                "name": "Curt",
                "birthDate": "1921",
                "occupation": "Employed by Norwegian America Line"
            },
            {
                "@type": "Person",
                "name": "Märta",
                "birthDate": "1923"
            }
        ],
        "worksFor": {
            "@type": "Organization",
            "name": "Jönköping-Kalmar Regiment"
        },
        "memberOf": {
            "@type": "Organization",
            "name": "Swedish Army"
        },
        "award": [
            {
                "@type": "Order",
                "name": "Order of the Sword"
            },
            {
                "@type": "Medal",
                "name": "Shooters' Medal"
            }
        ],
        "deathDate": "1968"
    }
}