{
    "original": "Brändstedt, Carl Gustav (Gösta), lasarettsläkare, regementsläkare, Uddevalla, f. 5/11/99 i Sthlm av fabr. C. W. Svensson o. Emma Brändstedt. G. 34 m. tandläk. Hed Paulsson. Barn: Stephan f. 43, Eva 45. — Stud:ex. 17, med. kand. 21 o. med. lic. 26 i Sthlm, med. dr i Lund 35. Div. förordn. s. assist:- o. und :läk. 24-26, und :läk. v. Gällivare las. 27-2S, v. Linköp. las. kir. avd. 28-29, e. läk., aman. samt tf. und:läk. v. ögonklin. i Lund 29-30, 31-32 o. 33-34, e. läk. f. ögonsjukv. v. Uddevalla las. 35-38, las:läk. där sed. 38. Bat:läk. i Fik res. 26, v. Fik 31, bat:-läk. v. Bohusl. reg. 33, reg:läk. där sed. 38. Stud. v. ögonklin. i Köpenhamn fem mån. 33. Ordf. i Bohusl. läk:fören., fullm. i läk:förb. Skr.: Studien über minimum perceptibile und distinktionsvermögen besonders bei myopi (35). • RVO.",
    "translated": "Brändstedt, Carl Gustav (Gösta), a doctor at a hospital and regimental doctor in Uddevalla, was born on November 5th, 1899 in Stockholm to C.W. Svensson, a factory worker, and Emma Brändstedt. He married Hed Paulsson, a dentist, in 1934, and they had two children: Stephan, born in 1943, and Eva, born in 1945. Brändstedt graduated from high school in 1917, earned his Bachelor of Medicine degree in 1921 and his medical license in 1926 in Stockholm. He received his doctorate in medicine in Lund in 1935. He held various positions as assistant and deputy doctor from 1924 to 1934, including deputy doctor in Gällivare Hospital from 1927 to 1928, and surgical department of Linköping Hospital from 1928 to 1929. He was a medical assistant, assistant and temporary deputy doctor at the ophthalmology clinic in Lund from 1929 to 1930, 1931 to 1932 and 1933 to 1934. He was appointed medical doctor for eye care at Uddevalla hospital from 1935 to 1938, and became a hospital doctor there in 1938. He served as a battalion doctor in Fik in 1926 and 1931 and later as a battalion doctor for the Bohuslän regiment in 1933, finally becoming their regimental doctor in 1938. He studied at the ophthalmology clinic in Copenhagen for five months in 1933. He was the chairman of the Bohuslän Medical Association and a delegate to the Swedish Medical Association. He authored the publication entitled \"Studies on minimum perceptibility and distinctiveness, particularly in myopia\" in 1935 and was awarded the Illis Quorum medal.",
    "structured_raw": "{\n   \"@context\":\"https://schema.org\",\n   \"@type\":\"Person\",\n   \"name\":\"Carl Gustav Brändstedt (Gösta)\",\n   \"birthDate\":\"1899-11-05\",\n   \"birthPlace\":{\n      \"@type\":\"Place\",\n      \"name\":\"Stockholm\"\n   },\n   \"nationality\":\"Swedish\",\n   \"father\":{\n      \"@type\":\"Person\",\n      \"name\":\"C. W. Svensson\",\n      \"jobTitle\":\"Factory Worker\"\n   },\n   \"mother\":{\n      \"@type\":\"Person\",\n      \"name\":\"Emma Brändstedt\"\n   },\n   \"spouse\":{\n      \"@type\":\"Person\",\n      \"name\":\"Hed Paulsson\",\n      \"jobTitle\":\"Dentist\"\n   },\n   \"children\":[\n      {\n         \"@type\":\"Person\",\n         \"name\":\"Stephan\",\n         \"birthDate\":\"1943\"\n      },\n      {\n         \"@type\":\"Person\",\n         \"name\":\"Eva\",\n         \"birthDate\":\"1945\"\n      }\n   ],\n   \"alumniOf\":[\n      {\n         \"@type\":\"EducationalOrganization\",\n         \"name\":\"Stockholm High School\",\n         \"startDate\":\"1917\"\n      },\n      {\n         \"@type\":\"CollegeOrUniversity\",\n         \"name\":\"Karolinska Institute\",\n         \"courseMode\":\"Bachelor\",\n         \"startDate\":\"1917\",\n         \"endDate\":\"1921\"\n      },\n      {\n         \"@type\":\"CollegeOrUniversity\",\n         \"name\":\"Karolinska Institute\",\n         \"courseMode\":\"Medical\",\n         \"startDate\":\"1921\",\n         \"endDate\":\"1926\"\n      },\n      {\n         \"@type\":\"CollegeOrUniversity\",\n         \"name\":\"Lund University\",\n         \"courseMode\":\"Doctorate\",\n         \"startDate\":\"1935\",\n         \"endDate\":\"1935\"\n      }\n   ],\n   \"jobTitle\":[\n      \"Hospital Doctor\",\n      \"Regimental Doctor\"\n   ],\n   \"worksFor\":[\n      {\n         \"@type\":\"Organization\",\n         \"name\":\"Uddevalla Hospital\",\n         \"startDate\":\"1935\",\n         \"endDate\":\"1938\"\n      }\n   ],\n   \"memberOf\":[\n      {\n         \"@type\":\"Organization\",\n         \"name\":\"Bohuslän Medical Association\"\n      },\n      {\n         \"@type\":\"Organization\",\n         \"name\":\"Swedish Medical Association\"\n      }\n   ],\n   \"deathDate\":null,\n   \"author\":{\n      \"@type\":\"CreativeWork\",\n      \"name\":\"Studies on minimum perceptibility and distinctiveness, particularly in myopia\",\n      \"datePublished\":\"1935\"\n   },\n   \"award\":{\n      \"@type\":\"Order\",\n      \"name\":\"Illis Quorum\"\n   }\n}",
    "structured": {
        "@context": "https://schema.org",
        "@type": "Person",
        "name": "Carl Gustav Brändstedt (Gösta)",
        "birthDate": "1899-11-05",
        "birthPlace": {
            "@type": "Place",
            "name": "Stockholm"
        },
        "nationality": "Swedish",
        "father": {
            "@type": "Person",
            "name": "C. W. Svensson",
            "jobTitle": "Factory Worker"
        },
        "mother": {
            "@type": "Person",
            "name": "Emma Brändstedt"
        },
        "spouse": {
            "@type": "Person",
            "name": "Hed Paulsson",
            "jobTitle": "Dentist"
        },
        "children": [
            {
                "@type": "Person",
                "name": "Stephan",
                "birthDate": "1943"
            },
            {
                "@type": "Person",
                "name": "Eva",
                "birthDate": "1945"
            }
        ],
        "alumniOf": [
            {
                "@type": "EducationalOrganization",
                "name": "Stockholm High School",
                "startDate": "1917"
            },
            {
                "@type": "CollegeOrUniversity",
                "name": "Karolinska Institute",
                "courseMode": "Bachelor",
                "startDate": "1917",
                "endDate": "1921"
            },
            {
                "@type": "CollegeOrUniversity",
                "name": "Karolinska Institute",
                "courseMode": "Medical",
                "startDate": "1921",
                "endDate": "1926"
            },
            {
                "@type": "CollegeOrUniversity",
                "name": "Lund University",
                "courseMode": "Doctorate",
                "startDate": "1935",
                "endDate": "1935"
            }
        ],
        "jobTitle": [
            "Hospital Doctor",
            "Regimental Doctor"
        ],
        "worksFor": [
            {
                "@type": "Organization",
                "name": "Uddevalla Hospital",
                "startDate": "1935",
                "endDate": "1938"
            }
        ],
        "memberOf": [
            {
                "@type": "Organization",
                "name": "Bohuslän Medical Association"
            },
            {
                "@type": "Organization",
                "name": "Swedish Medical Association"
            }
        ],
        "deathDate": null,
        "author": {
            "@type": "CreativeWork",
            "name": "Studies on minimum perceptibility and distinctiveness, particularly in myopia",
            "datePublished": "1935"
        },
        "award": {
            "@type": "Order",
            "name": "Illis Quorum"
        }
    }
}