{
    "original": "Lundqvist, Bo Gustav Verner V:son, rektor, fil. dr, Vänersborg, f. 20/2/01 i Skara av lärov:adj. Verner L. o. gymn:dir. Karin Plate. G. 35 m. skolkökslär. Inga Heüman. Barn: Katarina Bosdotter f. 37, Dag Boson 40. — Stud:ex. i Skara 19, stud. i Upps. 19, fil. kand. 23, fil. mag. 25, fil. lic. 34, fil. dr 35, allt i Upps. Arkiv-forskn. i Köpenhamn, Kiel o. Berlin 30, 31, 34, res. t. Danm., Finl., Norge o. Tyskl. ett flert. gånger, t. Belg. o. Frankr. 20, t. Ital., Jugoslov., Österr. o. Tjeckoislov. 22. Vik. adj. i Skara 22, lär. v. Fjellstedtska sk. i Upps. 30-34, e. o. lekt. i Lidingö 36-38, lär. v. Sthlms borgarsk. 36-38, lekt. v. h. a. 1. i Umeå 37, lär. v. Umeå hand :gymn. 40-45, rekt. v. h. a. 1. i Vänersb. sed. 47. Andre kur. v. Västgöta nat. i Upps. 2&amp;-29, bibi. där 27, v. Upps. stud :kårs bibi. 32-34, v. Lidingö lärov. 36-38, v. Umeå lärov. 43-47, huv:red. f. Vestro-gothica 28-40, led. av Sv. Rotaryråd. ised. 45, led. av Stadshist. ins;t. nd sed. 43, led. av stadsfullm. i Umeå samt av div. utsk. o. komm. und. olika per., led. av styr. f. Vänersb. mus. sed. 47, ordf. i Sv.-Finl. stud:förb. 31-32, ordf. i Umeå tjänstem :sällsk. 42-47, styr:-medl. fr. 38, ordf. i Umeå hum. förb. 42-47, sekr. 40-41, ordf. i styr. f. Umeå komm. flicksk. 44-47, presid. i Umeå Rotarykl. 44-46, sekr. o, v. pres. 40-44, ordf. i Västerb ikrets. av fören. Norden 46-47, v. ordf. o. ordf. i Umeåavd:s arb :utsk. 43-45, 46-47, omb. f. Radiotjänst o. programchef v. Umeå rundradio’Stat. 43-47. Skr.: Sverige o. den slesvig-holsteinska frågan (ak. avh. 34), Falköp. hist. I-III (40 -46), Västgöta nat. i Upps. fr. år 1595, Biiogr. anteckn., bd I 1595-1720 (28-46), Den yngre grenen av släkt. Heü-man (48), upps. i Hist. tidskr. m. fl, art. i Nord. Famibok, kult. medarb. i Umeblad. 41-47, rec. i Gbgs-Posten, föredr., kås. o. report, i radio. Hobby: Sveriges kommunikationer.",
    "translated": "Lundqvist, Bo Gustav Verner V:son, principal, Ph.D., Vänersborg, b. 20/2/01 in Skara to high school teacher Verner L. and gymnasium director Karin Plate. Married in 1935 to home economics teacher Inga Heüman. Children: Katarina Bosdotter b. 1937, Dag Boson b. 1940. Education: High school diploma in Skara in 1919, student in Uppsala in 1919, Bachelor of Arts in 1923, Master of Arts in 1925, Bachelor of Arts (honorary degree) in 1934, Ph.D. in 1935, all degrees obtained in Uppsala. Archive research in Copenhagen, Kiel, and Berlin in 1930, 1931, and 1934, respectively. Multiple trips to Denmark, Finland, Norway, and Germany, and visits to Belgium and France in 1920, Italy, Yugoslavia, Austria, and Czechoslovakia in 1922. Temporary high school teacher in Skara in 1922, teacher at Fjellstedt School in Uppsala from 1930-1934, temporary lecturer in Lidingö from 1936-1938, teacher at Stockholm High School from 1936-1938, lecturer at the Higher Commercial School in Umeå in 1937, teacher at Umeå Handheld Gymnasium from 1940-1945, principal at the Higher Agricultural School in Vänersborg since 1947. Second curator at Västgöta National Museum in Uppsala from 1922-1929, librarian there in 1927, librarian at Uppsala Student Union Library from 1932-1934, librarian at Lidingö High School from 1936-1938, librarian at Umeå High School from 1943-1947. Editor-in-chief of Vestro-gothica from 1928-1940, member of the Swedish Rotary Council since 1945, member of the City Historical Institute since 1943, member of the City Council in Umeå and various committees and commissions during different periods, member of the Board of Directors for Vänersborg Museum since 1947, chairman of the Swedish-Finnish Study Association from 1931-1932, chairman of the Umeå Civil Servants Society from 1942-1947, board member since 1938, chairman of the Umeå Humanities Association from 1942-1947, secretary from 1940-1941, chairman of the Board of Directors for Umeå Community Girls' School from 1944-1947, president of the Umeå Rotary Club from 1944-1946, secretary and vice president from 1940-1944, chairman of the Västerbotten district of the Association of Norden from 1946-1947, vice chairman and chairman of the Umeå branch's work committee from 1943-1945, 1946-1947, representative for Radiotjänst and program director at Umeå Public Radio Station from 1943-1947. Publications: Sweden and the Schleswig-Holstein question (doctoral thesis, 1934), Falköping history I-III (1940-1946), Västgöta National Museum in Uppsala from 1595, Biographical notes, vol. I 1595-1720 (1928-1946), The younger branch of the Heüman family (1948), essays in the Historical Journal and others, articles in the Nordic Family Book, cultural contributor to Umeblad from 1941-1947, book reviews in Gbgs-Posten, lectures, essays, and reports on radio. Hobby: Sweden’s communications.",
    "structured_raw": "{\n  \"@context\": \"https://schema.org/\",\n  \"@type\": \"Person\",\n  \"name\": \"Bo Gustav Verner Lundqvist\",\n  \"givenName\": \"Bo Gustav Verner\",\n  \"additionalName\": \"V:son\",\n  \"familyName\": \"Lundqvist\",\n  \"jobTitle\": \"Principal\",\n  \"degree\": [\n    {\n      \"@type\": \"EducationalOccupationalCredential\",\n      \"name\": \"Doctor of Philosophy\",\n      \"description\": \"Ph.D.\"\n    }\n  ],\n  \"birthPlace\": \"Skara, Sweden\",\n  \"birthDate\": \"1901-02-20\",\n  \"parents\": [\n    {\n      \"@type\": \"Person\",\n      \"name\": \"Verner L.\",\n      \"jobTitle\": \"High School Teacher\"\n    },\n    {\n      \"@type\": \"Person\",\n      \"name\": \"Karin Plate\",\n      \"jobTitle\": \"Gymnasium Director\"\n    }\n  ],\n  \"spouse\": {\n    \"@type\": \"Person\",\n    \"name\": \"Inga Heüman\",\n    \"jobTitle\": \"Home Economics Teacher\"\n  },\n  \"children\": [\n    {\n      \"@type\": \"Person\",\n      \"name\": \"Katarina Bosdotter\",\n      \"birthDate\": \"1937\"\n    },\n    {\n      \"@type\": \"Person\",\n      \"name\": \"Dag Boson\",\n      \"birthDate\": \"1940\"\n    }\n  ],\n  \"education\": [\n    {\n      \"@type\": \"EducationalOccupationalCredential\",\n      \"name\": \"High School Diploma\",\n      \"description\": \"Skara, 1919\"\n    },\n    {\n      \"@type\": \"EducationalOccupationalCredential\",\n      \"name\": \"Bachelor of Arts\",\n      \"description\": \"Uppsala, 1923\"\n    },\n    {\n      \"@type\": \"EducationalOccupationalCredential\",\n      \"name\": \"Master of Arts\",\n      \"description\": \"Uppsala, 1925\"\n    },\n    {\n      \"@type\": \"EducationalOccupationalCredential\",\n      \"name\": \"Bachelor of Arts (Honorary)\",\n      \"description\": \"Uppsala, 1934\"\n    },\n    {\n      \"@type\": \"EducationalOccupationalCredential\",\n      \"name\": \"Doctor of Philosophy\",\n      \"description\": \"Uppsala, 1935\"\n    }\n  ],\n  \"workLocation\": \"Vänersborg\",\n  \"workStartDate\": \"1947\",\n  \"worksFor\": \"Higher Agricultural School\",\n  \"workExperience\": [\n    {\n      \"@type\": \"Occupation\",\n      \"name\": \"Temporary High School Teacher\",\n      \"startDate\": \"1922\",\n      \"endDate\": \"1922\",\n      \"location\": \"Skara\"\n    },\n    {\n      \"@type\": \"Occupation\",\n      \"name\": \"Teacher\",\n      \"startDate\": \"1930\",\n      \"endDate\": \"1934\",\n      \"location\": \"Fjellstedtska School, Uppsala\"\n    },\n    {\n      \"@type\": \"Occupation\",\n      \"name\": \"Temporary Lecturer\",\n      \"startDate\": \"1936\",\n      \"endDate\": \"1938\",\n      \"location\": \"Lidingö\"\n    },\n    {\n      \"@type\": \"Occupation\",\n      \"name\": \"Teacher\",\n      \"startDate\": \"1936\",\n      \"endDate\": \"1938\",\n      \"location\": \"Stockholm High School\"\n    },\n    {\n      \"@type\": \"Occupation\",\n      \"name\": \"Lecturer\",\n      \"startDate\": \"1937\",\n      \"endDate\": \"1937\",\n      \"location\": \"Higher Commercial School, Umeå\"\n    },\n    {\n      \"@type\": \"Occupation\",\n      \"name\": \"Teacher\",\n      \"startDate\": \"1940\",\n      \"endDate\": \"1945\",\n      \"location\": \"Umeå Handheld Gymnasium\"\n    },\n    {\n      \"@type\": \"Occupation\",\n      \"name\": \"Principal\",\n      \"startDate\": \"1947\",\n      \"location\": \"Higher Agricultural School, Vänersborg\"\n    }\n  ],\n  \"memberOf\": [\n    {\n      \"@type\": \"Organization\",\n      \"name\": \"Swedish Rotary Council\",\n      \"startDate\": \"1945\"\n    },\n    {\n      \"@type\": \"Organization\",\n      \"name\": \"City Historical Institute\",\n      \"startDate\": \"1943\"\n    },\n    {\n      \"@type\": \"Organization\",\n      \"name\": \"Vänersborg Museum\",\n      \"startDate\": \"1947\"\n    },\n    {\n      \"@type\": \"Organization\",\n      \"name\": \"Swedish-Finnish Study Association\",\n      \"startDate\": \"1931\",\n      \"endDate\": \"1932\"\n    },\n    {\n      \"@type\": \"Organization\",\n      \"name\": \"Umeå Civil Servants Society\",\n      \"startDate\": \"1942\",\n      \"endDate\": \"1947\"\n    },\n    {\n      \"@type\": \"Organization\",\n      \"name\": \"Umeå Humanities Association\",\n      \"startDate\": \"1942\",\n      \"endDate\": \"1947\"\n    },\n    {\n      \"@type\": \"Organization\",\n      \"name\": \"Umeå Community Girls' School\",\n      \"startDate\": \"1944\",\n      \"endDate\": \"1947\"\n    },\n    {\n      \"@type\": \"Organization\",\n      \"name\": \"Umeå Rotary Club\",\n      \"startDate\": \"1944\",\n      \"endDate\": \"1946\"\n    },\n    {\n      \"@type\": \"Organization\",\n      \"name\": \"Association of Norden\",\n      \"startDate\": \"1946\",\n      \"endDate\": \"1947\"\n    }\n  ],\n  \"isPartOf\": [\n    {\n      \"@type\": \"Organization\",\n      \"name\": \"Umeåavn; TetfSÄlaue. &amp; tj- . erS/' School Work Committee\",\n      \"startDate\": \"1943\",\n      \"endDate\": \"1945\"\n    },\n    {\n      \"@type\": \"Organization\",\n      \"name\": \"Radiotjänst\",\n      \"startDate\": \"1943\",\n      \"endDate\": \"1947\"\n    }\n  ],\n  \"publications\": [\n    {\n      \"@type\": \"CreativeWork\",\n      \"name\": \"Sverige o. den slesvig-holsteinska frågan\",\n      \"description\": \"Doctoral thesis, 1934\"\n    },\n    {\n      \"@type\": \"CreativeWork\",\n      \"name\": \"Falköping history I-III\",\n      \"description\": \"1940-1946\"\n    },\n    {\n      \"@type\": \"CreativeWork\",\n      \"name\": \"Västgöta National Museum in Uppsala from 1595\",\n      \"description\": \"1928-1946\"\n    },\n    {\n      \"@type\": \"CreativeWork\",\n      \"name\": \"Biographical notes, vol. I 1595-1720\",\n      \"description\": \"1928-1946\"\n    },\n    {\n      \"@type\": \"CreativeWork\",\n      \"name\": \"The younger branch of the Heüman family\",\n      \"description\": \"1948\"\n    }\n  ],\n  \"hobbies\": \"Sweden’s communications\"\n}",
    "structured": {
        "@context": "https://schema.org/",
        "@type": "Person",
        "name": "Bo Gustav Verner Lundqvist",
        "givenName": "Bo Gustav Verner",
        "additionalName": "V:son",
        "familyName": "Lundqvist",
        "jobTitle": "Principal",
        "degree": [
            {
                "@type": "EducationalOccupationalCredential",
                "name": "Doctor of Philosophy",
                "description": "Ph.D."
            }
        ],
        "birthPlace": "Skara, Sweden",
        "birthDate": "1901-02-20",
        "parents": [
            {
                "@type": "Person",
                "name": "Verner L.",
                "jobTitle": "High School Teacher"
            },
            {
                "@type": "Person",
                "name": "Karin Plate",
                "jobTitle": "Gymnasium Director"
            }
        ],
        "spouse": {
            "@type": "Person",
            "name": "Inga Heüman",
            "jobTitle": "Home Economics Teacher"
        },
        "children": [
            {
                "@type": "Person",
                "name": "Katarina Bosdotter",
                "birthDate": "1937"
            },
            {
                "@type": "Person",
                "name": "Dag Boson",
                "birthDate": "1940"
            }
        ],
        "education": [
            {
                "@type": "EducationalOccupationalCredential",
                "name": "High School Diploma",
                "description": "Skara, 1919"
            },
            {
                "@type": "EducationalOccupationalCredential",
                "name": "Bachelor of Arts",
                "description": "Uppsala, 1923"
            },
            {
                "@type": "EducationalOccupationalCredential",
                "name": "Master of Arts",
                "description": "Uppsala, 1925"
            },
            {
                "@type": "EducationalOccupationalCredential",
                "name": "Bachelor of Arts (Honorary)",
                "description": "Uppsala, 1934"
            },
            {
                "@type": "EducationalOccupationalCredential",
                "name": "Doctor of Philosophy",
                "description": "Uppsala, 1935"
            }
        ],
        "workLocation": "Vänersborg",
        "workStartDate": "1947",
        "worksFor": "Higher Agricultural School",
        "workExperience": [
            {
                "@type": "Occupation",
                "name": "Temporary High School Teacher",
                "startDate": "1922",
                "endDate": "1922",
                "location": "Skara"
            },
            {
                "@type": "Occupation",
                "name": "Teacher",
                "startDate": "1930",
                "endDate": "1934",
                "location": "Fjellstedtska School, Uppsala"
            },
            {
                "@type": "Occupation",
                "name": "Temporary Lecturer",
                "startDate": "1936",
                "endDate": "1938",
                "location": "Lidingö"
            },
            {
                "@type": "Occupation",
                "name": "Teacher",
                "startDate": "1936",
                "endDate": "1938",
                "location": "Stockholm High School"
            },
            {
                "@type": "Occupation",
                "name": "Lecturer",
                "startDate": "1937",
                "endDate": "1937",
                "location": "Higher Commercial School, Umeå"
            },
            {
                "@type": "Occupation",
                "name": "Teacher",
                "startDate": "1940",
                "endDate": "1945",
                "location": "Umeå Handheld Gymnasium"
            },
            {
                "@type": "Occupation",
                "name": "Principal",
                "startDate": "1947",
                "location": "Higher Agricultural School, Vänersborg"
            }
        ],
        "memberOf": [
            {
                "@type": "Organization",
                "name": "Swedish Rotary Council",
                "startDate": "1945"
            },
            {
                "@type": "Organization",
                "name": "City Historical Institute",
                "startDate": "1943"
            },
            {
                "@type": "Organization",
                "name": "Vänersborg Museum",
                "startDate": "1947"
            },
            {
                "@type": "Organization",
                "name": "Swedish-Finnish Study Association",
                "startDate": "1931",
                "endDate": "1932"
            },
            {
                "@type": "Organization",
                "name": "Umeå Civil Servants Society",
                "startDate": "1942",
                "endDate": "1947"
            },
            {
                "@type": "Organization",
                "name": "Umeå Humanities Association",
                "startDate": "1942",
                "endDate": "1947"
            },
            {
                "@type": "Organization",
                "name": "Umeå Community Girls' School",
                "startDate": "1944",
                "endDate": "1947"
            },
            {
                "@type": "Organization",
                "name": "Umeå Rotary Club",
                "startDate": "1944",
                "endDate": "1946"
            },
            {
                "@type": "Organization",
                "name": "Association of Norden",
                "startDate": "1946",
                "endDate": "1947"
            }
        ],
        "isPartOf": [
            {
                "@type": "Organization",
                "name": "Umeåavn; TetfSÄlaue. &amp; tj- . erS/' School Work Committee",
                "startDate": "1943",
                "endDate": "1945"
            },
            {
                "@type": "Organization",
                "name": "Radiotjänst",
                "startDate": "1943",
                "endDate": "1947"
            }
        ],
        "publications": [
            {
                "@type": "CreativeWork",
                "name": "Sverige o. den slesvig-holsteinska frågan",
                "description": "Doctoral thesis, 1934"
            },
            {
                "@type": "CreativeWork",
                "name": "Falköping history I-III",
                "description": "1940-1946"
            },
            {
                "@type": "CreativeWork",
                "name": "Västgöta National Museum in Uppsala from 1595",
                "description": "1928-1946"
            },
            {
                "@type": "CreativeWork",
                "name": "Biographical notes, vol. I 1595-1720",
                "description": "1928-1946"
            },
            {
                "@type": "CreativeWork",
                "name": "The younger branch of the Heüman family",
                "description": "1948"
            }
        ],
        "hobbies": "Sweden’s communications"
    }
}