{
    "original": "Ideforss, Hjalmar Emanuel, rektor, Göteborg, f. 30/1/91 i V. Sallerup, Malmöh. k G. 19 ni. Margareta HaM-fberg. Biarn: Kerstin f. 21. — Stud:-ex. 10, fil. kand. 11, fil. mag. 14, fil. lic. 24, fik dr 28, provår 18, allt i Lund. Doc. i sv. språket v. Lunds univ. 28, vik. prof. v. Gbgs liögsk. 31. Stud:-res. t. Norge, Danm., Tyskl. o. Ös-terr. Vik. adj. i Strömstad 15, e. lär. i Halmstad 15, vik. ämneslär. i Höör 16, åter i Halmstad 16-17, ord. lär. i Falkenberg 17, e. o. lektor v. Lunds folkskrsem. 19-20, adj. v. Malmö goss-lärov. 20, lektor i modersm. o. tyska v. Hvitfeldtska h. a. 1. i Gbg sed. 28, rektor v. Borås h. a. 1. 31, v. Major-nas h. a. 1. i Gbg sed. 39. Tf. und:-visn:råd 317-38, 39 samt somr. 39-47. Led. av stadsfullm. i Borås 36-38. Skr.: De primära interjektionerna i nysvenskan I (28), Vårt modersmåls liv o. utveckl. (28), I språkets utmärker (30), Rättstavn ifrågan som prakt. o. teor. problem (31), De primära lockorden i nysvenskan (31), art. o. rec. i tidn. o. tidskr. RNO.",
    "translated": "Ideforss, Hjalmar Emanuel, principal, Gothenburg, born on January 30, 1891, in V. Sallerup, Malmöhus County. Married to Margareta Hambraeus in 1919. Children: Kerstin, born in 1921. He obtained his high school diploma in 1910, B.A. in 1911, M.A. in 1914, Ph.Lic. in 1924, Doctorate in Philosophy in 1928, and practical year in 1918, all from Lund University. He became a docent in Swedish language at Lund University in 1928 and acting professor at the University of Gothenburg in 1931. He studied in Norway, Denmark, Germany, and Austria. He worked as an assistant teacher in Strömstad in 1915, a teacher in Halmstad in 1915, a substitute subject teacher in Höör in 1916, returned to Halmstad in 1916-1917, an ordinary teacher in Falkenberg in 1917, an extra professor at Lund's folk school from 1919-1920, an assistant teacher at Malmö Boys' School in 1920, a teacher of mother tongue and German at Hvitfeldtska High School in Gothenburg from 1928, a principal at Borås High School from 1931, and a principal at Majornas High School in Gothenburg since 1939. He served as a temporary education counselor in 1937-1938 and 1939 and during the summer of 1939-1947. He was also a member of the city council in Borås from 1936-1938. He published numerous articles and reviews in newspapers and magazines, including De primära interjektionerna i nysvenskan I (28), Vårt modersmåls liv o. utveckl. (28), I språkets utmärker (30), Rättstavn ifrågan som prakt. o. teor. problem (31), De primära lockorden i nysvenskan (31).",
    "structured_raw": "{\n  \"@context\": \"https://schema.org\",\n  \"@type\": \"Person\",\n  \"name\": \"Hjalmar Emanuel Ideforss\",\n  \"birthDate\": \"1891-01-30\",\n  \"birthPlace\": \"V. Sallerup, Malmöhus County\",\n  \"nationality\": \"Swedish\",\n  \"spouse\": {\n    \"@type\": \"Person\",\n    \"name\": \"Margareta Hambraeus\",\n    \"dateOfMarriage\": \"1919\"\n  },\n  \"children\": {\n    \"@type\": \"Person\",\n    \"name\": \"Kerstin Ideforss\",\n    \"birthDate\": \"1921\"\n  },\n  \"alumniOf\": \"Lund University\",\n  \"educationCredential\": [\n    {\n      \"@type\": \"EducationalOccupationalCredential\",\n      \"name\": \"High School Diploma\",\n      \"educationalLevel\": \"HighSchool\",\n      \"dateIssued\": \"1910\"\n    },\n    {\n      \"@type\": \"EducationalOccupationalCredential\",\n      \"name\": \"Bachelor of Arts\",\n      \"educationalLevel\": \"Bachelor\",\n      \"dateIssued\": \"1911\"\n    },\n    {\n      \"@type\": \"EducationalOccupationalCredential\",\n      \"name\": \"Master of Arts\",\n      \"educationalLevel\": \"Master\",\n      \"dateIssued\": \"1914\"\n    },\n    {\n      \"@type\": \"EducationalOccupationalCredential\",\n      \"name\": \"Ph.Lic.\",\n      \"dateIssued\": \"1924\"\n    },\n    {\n      \"@type\": \"EducationalOccupationalCredential\",\n      \"name\": \"Doctorate in Philosophy\",\n      \"dateIssued\": \"1928\"\n    },\n    {\n      \"@type\": \"EducationalOccupationalCredential\",\n      \"name\": \"Practical Year\",\n      \"dateIssued\": \"1918\"\n    }\n  ],\n  \"jobTitle\": [\n    \"Docent in Swedish Language at Lund University\",\n    \"Acting Professor at the University of Gothenburg\",\n    \"Assistant Teacher in Strömstad\",\n    \"Teacher in Halmstad\",\n    \"Substitute Subject Teacher in Höör\",\n    \"Ordinary Teacher in Falkenberg\",\n    \"Extra Professor at Lund's Folk School\",\n    \"Assistant Teacher at Malmö Boys' School\",\n    \"Teacher of Mother Tongue and German at Hvitfeldtska High School\",\n    \"Principal at Borås High School\",\n    \"Principal at Majornas High School in Gothenburg\",\n    \"Temporary Education Counselor\"\n  ],\n  \"worksFor\": [\n    \"Lund University\",\n    \"University of Gothenburg\",\n    \"Borås High School\",\n    \"Majornas High School\"\n  ],\n  \"memberOf\": [\n    {\n      \"@type\": \"Organization\",\n      \"name\": \"City Council of Borås\",\n      \"startDate\": \"1936\",\n      \"endDate\": \"1938\"\n    }\n  ],\n  \"citation\": [\n    {\n      \"@type\": \"Article\",\n      \"name\": \"De primära interjektionerna i nysvenskan I\",\n      \"datePublished\": \"1928\"\n    },\n    {\n      \"@type\": \"Article\",\n      \"name\": \"Vårt modersmåls liv o. utveckl.\",\n      \"datePublished\": \"1928\"\n    },\n    {\n      \"@type\": \"Article\",\n      \"name\": \"I språkets utmärker\",\n      \"datePublished\": \"1930\"\n    },\n    {\n      \"@type\": \"Article\",\n      \"name\": \"Rättstavn ifrågan som prakt. o. teor. problem\",\n      \"datePublished\": \"1931\"\n    },\n    {\n      \"@type\": \"Article\",\n      \"name\": \"De primära lockorden i nysvenskan\",\n      \"datePublished\": \"1931\"\n    }\n  ]\n}",
    "structured": {
        "@context": "https://schema.org",
        "@type": "Person",
        "name": "Hjalmar Emanuel Ideforss",
        "birthDate": "1891-01-30",
        "birthPlace": "V. Sallerup, Malmöhus County",
        "nationality": "Swedish",
        "spouse": {
            "@type": "Person",
            "name": "Margareta Hambraeus",
            "dateOfMarriage": "1919"
        },
        "children": {
            "@type": "Person",
            "name": "Kerstin Ideforss",
            "birthDate": "1921"
        },
        "alumniOf": "Lund University",
        "educationCredential": [
            {
                "@type": "EducationalOccupationalCredential",
                "name": "High School Diploma",
                "educationalLevel": "HighSchool",
                "dateIssued": "1910"
            },
            {
                "@type": "EducationalOccupationalCredential",
                "name": "Bachelor of Arts",
                "educationalLevel": "Bachelor",
                "dateIssued": "1911"
            },
            {
                "@type": "EducationalOccupationalCredential",
                "name": "Master of Arts",
                "educationalLevel": "Master",
                "dateIssued": "1914"
            },
            {
                "@type": "EducationalOccupationalCredential",
                "name": "Ph.Lic.",
                "dateIssued": "1924"
            },
            {
                "@type": "EducationalOccupationalCredential",
                "name": "Doctorate in Philosophy",
                "dateIssued": "1928"
            },
            {
                "@type": "EducationalOccupationalCredential",
                "name": "Practical Year",
                "dateIssued": "1918"
            }
        ],
        "jobTitle": [
            "Docent in Swedish Language at Lund University",
            "Acting Professor at the University of Gothenburg",
            "Assistant Teacher in Strömstad",
            "Teacher in Halmstad",
            "Substitute Subject Teacher in Höör",
            "Ordinary Teacher in Falkenberg",
            "Extra Professor at Lund's Folk School",
            "Assistant Teacher at Malmö Boys' School",
            "Teacher of Mother Tongue and German at Hvitfeldtska High School",
            "Principal at Borås High School",
            "Principal at Majornas High School in Gothenburg",
            "Temporary Education Counselor"
        ],
        "worksFor": [
            "Lund University",
            "University of Gothenburg",
            "Borås High School",
            "Majornas High School"
        ],
        "memberOf": [
            {
                "@type": "Organization",
                "name": "City Council of Borås",
                "startDate": "1936",
                "endDate": "1938"
            }
        ],
        "citation": [
            {
                "@type": "Article",
                "name": "De primära interjektionerna i nysvenskan I",
                "datePublished": "1928"
            },
            {
                "@type": "Article",
                "name": "Vårt modersmåls liv o. utveckl.",
                "datePublished": "1928"
            },
            {
                "@type": "Article",
                "name": "I språkets utmärker",
                "datePublished": "1930"
            },
            {
                "@type": "Article",
                "name": "Rättstavn ifrågan som prakt. o. teor. problem",
                "datePublished": "1931"
            },
            {
                "@type": "Article",
                "name": "De primära lockorden i nysvenskan",
                "datePublished": "1931"
            }
        ]
    }
}