{
    "original": "Andersson, Anders, direktör, Linköping, f. 27/5/94 i Rättvik, Kopparb. 1., av hemm:äg. Pellas Anders Jonsson o. Kerstin Hansson. G. 26 m. Gunni Svensson. Barn: Kerstin Maria f. 27, John Anders Gunnar 30. — CTI (E) 16-19. . Offert- o. montageing. v. Elektr. A-B Christian Bergh i Malmö 19-20, bitr. ing. v. Trollhätte kraftv. distr :kont. 20-21, distrib :ing. v. Linköp. elverk 22-25, driftsing. där 25 o. verkst. dir. f. Linköp. Elektr. Kraft-&amp; Belysn. A-B sed. 44. Led. av styr. f. A-B Nya Centr:brygg. sed. 33, v. ordf. sed. 44, huv:man i Linköp. Sparbank sed. 42, led. av styr. f. Linköp. Omnibusbol. Led. av Sv. tekn:fören.",
    "translated": "Andersson, Anders, director, Linköping, b. May 27, 1894 in Rättvik, Kopparberg County, son of home owner Pellas Anders Jonsson and Kerstin Hansson. Married Gunni Svensson on May 26. Children: Kerstin Maria born in 1927, John Anders Gunnar born in 1930. CTI (E) 16-19. Offer and installation engineer at Elektr. A-B Christian Bergh in Malmö from 1919-1920, assistant engineer at Trollhätte power district office from 1920-1921, distribution engineer at Linköping power station from 1922-1925, operations engineer there from 1925 and managing director of Linköping Elektr. Kraft- &amp; Belysn. A-B since 1944. Member of the board of A-B Nya Centr:brygg. since 1933, vice chairman since 1944, main officer of Linköping Sparbank since 1942, member of the board of Linköping Omnibusbol. Member of the Swedish technical association.",
    "structured": {
        "@context": "http://schema.org",
        "@type": "Person",
        "name": "Anders Andersson",
        "jobTitle": "Director",
        "address": {
            "@type": "PostalAddress",
            "addressLocality": "Linköping"
        },
        "birthDate": "1894-05-27",
        "birthPlace": {
            "@type": "Place",
            "name": "Rättvik, Kopparberg County"
        },
        "parent": [
            {
                "@type": "Person",
                "name": "Pellas Anders Jonsson",
                "jobTitle": "Home Owner"
            },
            {
                "@type": "Person",
                "name": "Kerstin Hansson"
            }
        ],
        "spouse": {
            "@type": "Person",
            "name": "Gunni Svensson"
        },
        "children": [
            {
                "@type": "Person",
                "name": "Kerstin Maria",
                "birthDate": "1927"
            },
            {
                "@type": "Person",
                "name": "John Anders Gunnar",
                "birthDate": "1930"
            }
        ],
        "memberOf": [
            {
                "@type": "Organization",
                "name": "A-B Nya Centr:brygg.",
                "memberOf": "board",
                "startDate": "1933",
                "endDate": "present",
                "occupation": "vice-chairman"
            },
            {
                "@type": "Organization",
                "name": "Linköping Sparbank",
                "memberOf": "main officer",
                "startDate": "1942",
                "endDate": "present"
            },
            {
                "@type": "Organization",
                "name": "Linköping Omnibusbol.",
                "memberOf": "board"
            },
            {
                "@type": "Organization",
                "name": "Sv. tekn:fören.",
                "memberOf": "member"
            }
        ],
        "jobHistory": [
            {
                "@type": "Organization",
                "name": "Elektr. A-B Christian Bergh",
                "startDate": "1919-01-01",
                "endDate": "1920-12-31",
                "occupation": "Offer and installation engineer"
            },
            {
                "@type": "Organization",
                "name": "Trollhätte power district office",
                "startDate": "1920-01-01",
                "endDate": "1921-12-31",
                "occupation": "Assistant engineer"
            },
            {
                "@type": "Organization",
                "name": "Linköping power station",
                "startDate": "1922-01-01",
                "endDate": "1925-12-31",
                "occupation": "Distribution engineer"
            },
            {
                "@type": "Organization",
                "name": "Linköping Elektr. Kraft- &amp; Belysn. A-B",
                "startDate": "1944-01-01",
                "endDate": "present",
                "occupation": "Managing director"
            }
        ]
    }
}