{
    "original": "Arild, Uno A:son, civilingenjör, Göteborg, f. 21/8/94 i Sthlm av köpm. Ern&amp;t Gustaf A. o. Ida Larsson. G. 24 m. Kaj Andersson. Barn: Folke f. 28. — Stud:ex. v. Norrm. lärov. i Sthlm 14, civ:ing:ex. v. KTH 19. Stud:resa i Mellan-Europa m. komm:- koU. stip. 21, stud:- o. affärsres. t.. Tyskl. o. Baltikum 29, Mellan-Europa 35 o. 38, Engl. 39, Tyskl. 43, Engl. 46. Bitr. verkst:ing. v. A-B Sv. Maskin-verken i Södertälje 18-19, offerting. v. Luth o. Roséns El. A-B i Sthlm 19-24, avdxhef v. Luth o. Roséns El. A-B i Gbg 24-26, offerting. v. A-B Hen-råks-sons Brandredskap 26-28, venkst. dir. där 28-35, avd :chef v. A-B Pump-induiSitrii, Ibrandavd., Ghg, 35-44, föirs’äilj-nrchef där s-ed. 45. Lär. v. utbildn:-kurser f. ibrandoff. 33. Medl. av Sv. •tekn:fören. sed. 20. Skr.: ett lOO-tal tetkn. art. rör. brandskydd.",
    "translated": "Arild Uno A:son was a civil engineer born on August 21, 1894 in Stockholm to merchant parents Ernst Gustaf A. and Ida Larsson. He married Kaj Andersson on January 24th and had a son named Folke, born in 1928. Arild attended Norrmalm High School in Stockholm and graduated in 1914, then went on to obtain his degree in civil engineering from the Royal Institute of Technology in 1919. He also undertook study trips throughout Europe with scholarships and for business purposes between 1921 and 1946. Arild worked as a junior engineer at AB Swedish Machinery Works in Södertälje from 1918-1919, and later worked in sales and management positions at various engineering companies including Luth & Rosén’s Electrics AB, AB Henriksson’s Fire Fighting Equipment, and AB Pumpindustrii’s Fire Department in Gothenburg. He taught firefighting courses for officers in 1933 and was a member of the Swedish Society of Technical Engineers since 1920. Arild wrote over 100 technical articles on fire safety.",
    "structured": {
        "@context": "https://schema.org/",
        "@type": "Person",
        "name": "Arild Uno A:son",
        "birthDate": "1894-08-21",
        "birthPlace": "Stockholm, Sweden",
        "deathDate": null,
        "spouse": {
            "@type": "Person",
            "name": "Kaj Andersson",
            "marriageDate": "Unknown"
        },
        "children": {
            "@type": "Person",
            "name": "Folke",
            "birthDate": "1928"
        },
        "nationality": "Swedish",
        "jobTitle": "Civil Engineer",
        "memberOf": [
            {
                "@type": "Organization",
                "name": "Swedish Society of Technical Engineers",
                "startDate": "1920"
            }
        ],
        "education": [
            {
                "@type": "EducationalInstitution",
                "name": "Norrmalm High School",
                "endDate": "1914"
            },
            {
                "@type": "EducationalInstitution",
                "name": "Royal Institute of Technology",
                "endDate": "1919"
            }
        ],
        "articleBody": "Arild Uno A:son was a civil engineer born on August 21, 1894 in Stockholm to merchant parents Ernst Gustaf A. and Ida Larsson. He married Kaj Andersson on January 24th and had a son named Folke, born in 1928. Arild attended Norrmalm High School in Stockholm and graduated in 1914, then went on to obtain his degree in civil engineering from the Royal Institute of Technology in 1919. He also undertook study trips throughout Europe with scholarships and for business purposes between 1921 and 1946. Arild worked as a junior engineer at AB Swedish Machinery Works in Södertälje from 1918-1919, and later worked in sales and management positions at various engineering companies including Luth & Rosén’s Electrics AB, AB Henriksson’s Fire Fighting Equipment, and AB Pumpindustrii’s Fire Department in Gothenburg. He taught firefighting courses for officers in 1933 and wrote over 100 technical articles on fire safety."
    }
}