{
    "original": "Engdahl, Elsa Olena Mathilda, fd. rektor, Gösisäter, f. 20/6/81 i Kalmar av las:läk. Edvard E. o. Bertha An- dersson. — Ex. v. h. lär:nesem. i Sthlm 02, fjärde avd. 06. Timlär, v. Kalmar elem:sk. f. fl. 02-03, ord. ämneslär. där 03-36, förest. 25-36, rektor v. Kalmar komm. flicksk. 36-46. Led. av stadsWlm. 23-25, led. av styr. f. Kalmar RK-krets sed. 20, ordf. sed. 46, led. av styr. f. Riksfören. f. svenskh. bev. i uti. o. Moderata kvin-nokl. GMmf, SMsjv.",
    "translated": "Engdahl, Elsa Olena Mathilda, former principal, Gösisäter, born on June 20th, 1881 in Kalmar to physician Edvard E. and Bertha Andersson. She graduated from the teacher training program in Stockholm in 1902, specializing in the fourth department in 1906. She worked as a substitute teacher at Kalmar elementary school and others from 1902 to 1903, and as a subject teacher in the same school from 1903 to 1936, serving as its chairman from 1925 to 1936. She was the principal of the Kalmar municipal girls' school from 1936 to 1946. She was a member of the Stockholm city council from 1923 to 1925, and a member of the board for the Kalmar Red Cross district since 1920. She was elected as a chairman in 1946. She was a member of the board for the Swedish Society for Race Hygiene Abroad and the Moderate Women's Club. She married but her partner's name is not provided.",
    "structured_raw": "{\n  \"@context\": \"https://schema.org\",\n  \"@type\": \"Person\",\n  \"name\": \"Elsa Olena Mathilda Engdahl\",\n  \"givenName\": \"Elsa\",\n  \"middleName\": \"Olena Mathilda\",\n  \"familyName\": \"Engdahl\",\n  \"birthDate\": \"1881-06-20\",\n  \"birthPlace\": \"Kalmar\",\n  \"deathDate\": null,\n  \"gender\": \"Female\",\n  \"jobTitle\": \"Former Principal\",\n  \"nationality\": \"Swedish\",\n  \"education\": [\n    {\n      \"@type\": \"EducationalOccupationalCredential\",\n      \"educationalLevel\": \"High school graduate\",\n      \"educationCredentialAwarded\": \"Ex. v. h. lär:nesem.\",\n      \"educationalSpecialty\": \"Teacher Training\"\n    }\n  ],\n  \"worksFor\": [\n    {\n      \"@type\": \"Organization\",\n      \"name\": \"Kalmar Municipal Girls' School\",\n      \"jobTitle\": \"Principal\",\n      \"startDate\": \"1936\",\n      \"endDate\": \"1946\"\n    }\n  ],\n  \"memberOf\": [\n    {\n      \"@type\": \"Organization\",\n      \"name\": \"Stockholm City Council\",\n      \"startDate\": \"1923\",\n      \"endDate\": \"1925\"\n    },\n    {\n      \"@type\": \"Organization\",\n      \"name\": \"Kalmar Red Cross District\",\n      \"startDate\": \"1920\"\n    },\n    {\n      \"@type\": \"Organization\",\n      \"name\": \"Swedish Society for Race Hygiene Abroad\"\n    },\n    {\n      \"@type\": \"Organization\",\n      \"name\": \"Moderate Women's Club\"\n    }\n  ],\n  \"spouse\": null,\n  \"parents\": [\n    {\n      \"@type\": \"Person\",\n      \"name\": \"Edvard E.\",\n      \"jobTitle\": \"Physician\"\n    },\n    {\n      \"@type\": \"Person\",\n      \"name\": \"Bertha Andersson\"\n    }\n  ],\n  \"sameAs\": []\n}",
    "structured": {
        "@context": "https://schema.org",
        "@type": "Person",
        "name": "Elsa Olena Mathilda Engdahl",
        "givenName": "Elsa",
        "middleName": "Olena Mathilda",
        "familyName": "Engdahl",
        "birthDate": "1881-06-20",
        "birthPlace": "Kalmar",
        "deathDate": null,
        "gender": "Female",
        "jobTitle": "Former Principal",
        "nationality": "Swedish",
        "education": [
            {
                "@type": "EducationalOccupationalCredential",
                "educationalLevel": "High school graduate",
                "educationCredentialAwarded": "Ex. v. h. lär:nesem.",
                "educationalSpecialty": "Teacher Training"
            }
        ],
        "worksFor": [
            {
                "@type": "Organization",
                "name": "Kalmar Municipal Girls' School",
                "jobTitle": "Principal",
                "startDate": "1936",
                "endDate": "1946"
            }
        ],
        "memberOf": [
            {
                "@type": "Organization",
                "name": "Stockholm City Council",
                "startDate": "1923",
                "endDate": "1925"
            },
            {
                "@type": "Organization",
                "name": "Kalmar Red Cross District",
                "startDate": "1920"
            },
            {
                "@type": "Organization",
                "name": "Swedish Society for Race Hygiene Abroad"
            },
            {
                "@type": "Organization",
                "name": "Moderate Women's Club"
            }
        ],
        "spouse": null,
        "parents": [
            {
                "@type": "Person",
                "name": "Edvard E.",
                "jobTitle": "Physician"
            },
            {
                "@type": "Person",
                "name": "Bertha Andersson"
            }
        ],
        "sameAs": []
    }
}