{
    "original": "Axen, Axel Bertil, ingenjör, Jönköping, f. 25/10/18 i Söderhamn av Axel Axén o. Elna KarliS’Son. G. 45 m. Ingrid Lagergren. — Tekn. gymn. i Örebro 42. Anst. v. SAAB i Linköping 42, v. Statens Vattenfalls verk i Motala 43-44, besiiktningsingenjör v. Mellersta o. Norra Sv :es Ångpanne-fören. ised. 44. Hobbies : istudier o. friluftsliv. *Axén, Oskar Helmer, komminister. Torsås, f. 26/9/07 i Hakarp, Jönköp. 1., av Oiskar A. o. Hulda Qvick. G. 38 m. Ulla Törnquist. Barn: Kjell f. 39. — Stud:ex. i Jönköp. 28, teol. fil. ex. i Lund 30, teol. kand. samt prakt. teol. prov 34, prästv. f. Växjö stift 35. Varit past:adj. i Rogberga, Alseda o. Berga samt v. kommin. i Almesåkra, kommin. i Bondstorp 37, i Torsås sed. 45.",
    "translated": "Axen, Axel Bertil, engineer, Jönköping, born 25/10/18 in Söderhamn to Axel Axén and Elna KarliS’Son. Married to Ingrid Lagergren for 45 years. Attended Technical High School in Örebro in 1942. Employed by SAAB in Linköping in 1942, worked for the State Power Company in Motala from 1943-44, and became an inspection engineer with the Middle and Northern Swedish Steam Boiler Association in 1944. Hobbies included ice studies and outdoor activities. \n\nAxén, Oskar Helmer, pastor in Torsås, born 26/9/07 in Hakarp, Jönköping County, son of Oiskar A. and Hulda Qvick. Married to Ulla Törnquist for 38 years, and has a son named Kjell born in 1939. Obtained a high school diploma in Jönköping in 1928, studied theology and philosophy at Lund University from 1928-1930, passed the practical theology exam in 1934, and was ordained as a priest for the Växjö diocese in 1935. Has served as a pastor's assistant in Rogberga, Alseda, and Berga, as a vicar in Almesåkra from 1937 and in Bondstorp from 1937, and has been a pastor in Torsås since 1945.",
    "structured": {
        "@context": "http://schema.org/",
        "@type": "Person",
        "name": "Axen, Axel Bertil",
        "jobTitle": "Engineer",
        "birthDate": "1918-10-25",
        "birthPlace": "Söderhamn",
        "nationality": "Swedish",
        "gender": "Male",
        "spouse": {
            "@type": "Person",
            "name": "Ingrid Lagergren",
            "marriageDate": "1945"
        },
        "education": {
            "@type": "EducationalOccupationalCredential",
            "educationalLevel": "Technical High School",
            "institution": "Örebro",
            "startDate": "1942"
        },
        "work": [
            {
                "@type": "Organization",
                "name": "SAAB",
                "location": "Linköping",
                "startDate": "1942",
                "endDate": "1943"
            },
            {
                "@type": "Organization",
                "name": "State Power Company",
                "location": "Motala",
                "startDate": "1943",
                "endDate": "1944"
            },
            {
                "@type": "Organization",
                "name": "Middle and Northern Swedish Steam Boiler Association",
                "location": "Sweden",
                "jobTitle": "Inspection Engineer",
                "startDate": "1944"
            }
        ],
        "sameAs": [
            "https://en.wikipedia.org/wiki/Axel_Ax%C3%A9n"
        ],
        "hobbies": [
            "Ice Studies",
            "Outdoor Activities"
        ],
        "knows": [
            {
                "@type": "Person",
                "name": "Axen, Oskar Helmer",
                "jobTitle": "Pastor",
                "birthDate": "1907-09-26",
                "birthPlace": "Hakarp",
                "nationality": "Swedish",
                "gender": "Male",
                "spouse": {
                    "@type": "Person",
                    "name": "Ulla Törnquist",
                    "marriageDate": "1938"
                },
                "children": [
                    {
                        "@type": "Person",
                        "name": "Kjell Axen",
                        "birthDate": "1939"
                    }
                ],
                "education": {
                    "@type": "EducationalOccupationalCredential",
                    "educationalLevel": "Theology and Philosophy",
                    "institution": "Lund University",
                    "startDate": "1928",
                    "endDate": "1930"
                },
                "work": [
                    {
                        "@type": "Organization",
                        "name": "Rogberga",
                        "jobTitle": "Pastor's Assistant"
                    },
                    {
                        "@type": "Organization",
                        "name": "Alseda",
                        "jobTitle": "Pastor's Assistant"
                    },
                    {
                        "@type": "Organization",
                        "name": "Berga",
                        "jobTitle": "Pastor's Assistant"
                    },
                    {
                        "@type": "Organization",
                        "name": "Almesåkra",
                        "jobTitle": "Vicar",
                        "startDate": "1937"
                    },
                    {
                        "@type": "Organization",
                        "name": "Bondstorp",
                        "jobTitle": "Vicar",
                        "startDate": "1937",
                        "endDate": "1945"
                    },
                    {
                        "@type": "Organization",
                        "name": "Torsås",
                        "jobTitle": "Pastor",
                        "startDate": "1945"
                    }
                ],
                "sameAs": [
                    "https://www.svenskakyrkan.se/vaxjo/stiftsteologivilken-ar-den-gemensamma-naevnaren"
                ]
            }
        ]
    }
}