{
    "original": "Lars Georg, provinsialläkare, Jörlanda, f. 2/8/98’ i Kärrbo, Väst-mani. 1., av landshövd. Claes W. o. Charlotte Lev^enhaupt. G. 26 mi. fri-h :an Ulla Cederström. Barn : Birgitta f. 27, Sten 20-, Anne-Marie 3a, Ulrika 313, Margareta 34, Cecilia 40, Elisabeth 42, Claes-Johan 44. — Sttid:ex. i Västerås 16, med. kand. i Upps. 22, med. lic. v. Karol. inst. 27. Assist :läk. v. Nyköp. las. 24, tf. prov :läk. i Bjur-holms distr. kortare tider 26 o. 26, assist :läk. o. tf. andre und :läk. v. Karlshamns las. tills, tretton mån. 26-27, tf. prov :läk. i Frän st a o. Svenljunga distr. kortare tider 27 o. 28, kommunalt anst. i Tranemo 27-28, tf. e. prov :-läk. i Tranemo distr. 29-30’, ord. dito 30, prov:läk. i Jörlanda distr. sed. 42, järnv:läk. v. Falkenbergs järnv. 28-34. Ordf. i Tranemo hälsovmd 30-34, i Jörilandakrets. av SvRK sed. 43. We&amp;sberg, Claes Evald, rektor, Trollhättan, f. 30/5/91 i Torslanda, Gbgs o. Boh. 1., av Edvard W. o. Charlotta Tönnesdotter. G. 1. 21 m. Gertrud Lindqvist, d. 27; 2. 31 m. Ruth Lindqvist. Barn: Claès-Henrik f. 22, Gertrud 26. — Stud:ex. v. Gbgs h. la-ti-nlärov. lil, fil. kand. i Gbig 15, fil. mag. 16, pr o vår v. Norra latin i Sthlm ht. 28. Vik. ämneslär. v. Vara komm. mellan sk. 16 o. 17, e. o. ämne slär. v. Nässjö dito 17-18, lär. v. Trollhättans samsk. 18-19, ämneslär. v. Trollhättans koimm. miellansk. 19-27, adj. i moders-m., tyska o. hist. mi. samh :lära v. Trollhättans samrealsk. sed. 28, vik. rektor 20i-2ll, rektor v. komm.’ mellan-sk. 21-30, v. samrealsk. sed. 30. Rev. av kyrkans räkensk. o. förvaltn. 29-312, tryckfrih lombud sed. 31, o^mbud f. til’’syn av viss fond f. skoländamål, insp. f. yrkessk., led. av kyrkofullm. Resor t. Tyskl. 12, 21’ o. 37, delt. i SvRiK invalidtransp. IS o. 17. RVO, RLSF utmärkit. i silver. , Thérèse, tandläkare, Göteborg, f. i Maltnö av järnv:ing. o. skeppsbygg. A. P. Wessberg o. Kerstin Andreasson. Mogiex. v. ÄMinska sk. i Sthlmi 011, tandl:kand. 02, tandläkare 04. Assist, i Hässleholm 04, praktik i Västervik 05-12, assist, i Falkenberg 12-15, skoltandl. i Gbg 16-42, egen prakt, i Gbg ’sed. 24. Wessén, Claes Hugo, major, Halmstad, f. 26/1(1/96 i Veinge, Hall. 1., av red. Viktor Larsson o. Sigrid Wessén. G. 213’ m. Margit Drakenberg. Barn: Barbro f. 23, Birgitta 29, Gunvor 34. — Stud: ex. i Halmstad ll5, off :ex. 17, sign :oif:kurs 24, 29. Fänr. v. fd. Västg. reg. 17, löjtn. 19, v. Hall. reg. 28, kapten 3f2, major i armén 45. Mo-(biliser:o.ff. fr. 40. Sekr. i Hall. 1st-förb. 313-37, chefinstr. där 38-40, led. av dess verkst. utsk. 35-45. RSO, CFBGM, Hall. IfbGM. Wessén, Daniel Gotthold Johannes, advokat. Mjölby, f. 27/10/96 i Högby, östergötl. 1., av kyrkoh. C. G. W. o. Lydia Sehman. — Stud;:ex. i Linköp. 14, jur. kand. i Upps. 19, tingstjg. i Lysings o. Göstrings samt Mjölby doms. 21-24. Eg. adv :verksamh. i Mjölby fr. 24. Led. av Sv:es adv:-samf. fr. 36. Disp. f. A-B Mjölby ka-nikegård fr. 411. Led. av stadsfullm. Skr.: div. upps. i jur. ämnen.",
    "translated": "Lars Georg, provincial physician, Jörlanda, b. 2/8/98 in Kärrbo, Västmanland. Son of Governor Claes W. and Charlotte Levénhaupt. Married on 26th May to Ulla Cederström. Children: Birgitta born in 1927, Sten born in 1920, Anne-Marie born in 1930, Ulrika born in 1931, Margareta born in 1934, Cecilia born in 1940, Elisabeth born in 1942, Claes-Johan born in 1944. Education: Västerås matriculation exam in 1916, medical candidate at Uppsala University in 1922, medical license from Karolinska Institute in 1927. Assistant doctor at Nyköping hospital in 1924, acting provincial physician in Bjurholm district for short periods in 1926 and 1927, assistant doctor and acting deputy head physician at Karlshamn hospital for thirteen months in 1926-1927, acting provincial physician in Fräntorps and Svenljunga districts for short periods in 1927 and 1928, employed by Tranemo municipality in 1927-1928, acting deputy provincial physician in Tranemo district in 1929-1930, appointed as regular deputy provincial physician in 1930, provincial physician in Jörlanda district since 1942, railway physician for Falkenberg railways in 1928-1934. Chairman of the Tranemo health council from 1930 to 1934, chairman of the Jörlanda district of the Swedish Red Cross since 1943.\n\nClaes Evald Wesberg, rector, Trollhättan, b. 30/5/91 in Torslanda, Gothenburg and Bohuslän. Son of Edvard W. and Charlotta Tönnesdotter. First married in 1921 to Gertrud Lindqvist, deceased in 1927; second married in 1931 to Ruth Lindqvist. Children: Claès-Henrik born in 1922, Gertrud born in 1926. Education: Graduated from Gothenburg higher Latin school in 1911, Bachelor of Arts from Gothenburg University in 1915, Master of Arts in 1916, teacher at Norra latin school in Stockholm in the spring term of 1928. Temporary subject teacher in Vara municipality between school years 1916 and 1917, substitute subject teacher in Nässjö during 1917-1918, teacher at Trollhättan private school in 1918-1919, subject teacher at Trollhättan municipal middle school in 1919-1927, adjunct in mother tongue, German and history with social studies at Trollhättan secondary school since 1928, acting rector from 1920-1921, rector of the municipal middle school from 1921-1930, rector of the secondary school since 1930. Auditor for church accounts and administration from 1929-1931, advocate for freedom of the press from 1931, representative for oversight of a certain school fund, inspector for vocational schools, member of the church council. Traveled to Germany in 1912, 1921, and 1937, participated in Swedish Red Cross invalid transport in 1915 and 1917. Awarded with RVO (Order of Vasa), RLSF (Royal Swedish Academy of Sciences), and silver medal.\n\nThérèse, dentist, Gothenburg, born in Malmtö, daughter of railway engineer and shipbuilder A. P. Wessberg and Kerstin Andreasson. Graduated from Amelie Flygt School in Stockholm in 1911, dentist candidate in 1902, became a dentist in 1904. Assistant dentist in Hässleholm in 1904, practice in Västervik from 1905-1912, assistant dentist in Falkenberg from 1912-1915, school dentist in Gothenburg from 1916-1942, started her own practice in Gothenburg in 1924.\n\nClaes Hugo Wessén, major, Halmstad, b. 26/11/96 in Veinge, Halland. Son of editor Viktor Larsson and Sigrid Wessén. Married in 1921 to Margit Drakenberg. Children: Barbro born in 1923, Birgitta born in 1929, Gunvor born in 1934. Education: Halmstad matriculation exam in 1915, officer exam in 1917, signal course in 1924 and 1929. Ensign in Västgöta Regiment in 1917, lieutenant in 1919, in Halland Regiment in 1928, captain in 1932, major in the army since 1945. Mobilization officer from 1940. Secretary in Halland First Cavalry Association from 1933-1937, chief instructor from 1938-1940, member of the executive committee from 1935-1945. Awarded with RSO (Sword of Honor), CFBGM (Royal Halland Infantry Regiment's Gold Medal), Halland County Association's Gold Medal.\n\nDaniel Gotthold Johannes Wessén, lawyer, Mjölby, b. 27/10/96 in Högby, Östergötland. Son of Pastor C. G. Wessén and Lydia Sehman. Education: Linköping matriculation exam in 1914, law degree from Uppsala University in 1919, court clerk in Lysings, Göstrings, and Mjölby districts from 1921-1924. Established own law practice in Mjölby in 1924. Member of the Swedish Bar Association since 1936. Authorized to manage the Mjölby Canonry Estate from 1941. Member of the city council. Has written several papers on legal subjects.",
    "structured_raw": "{\n  \"@context\": \"https://schema.org\",\n  \"@type\": \"Person\",\n  \"name\": \"Lars Georg\",\n  \"birthDate\": \"1898-08-02\",\n  \"birthPlace\": \"Kärrbo, Västmanland\",\n  \"memberOf\": [\n    {\n      \"@type\": \"Organization\",\n      \"name\": \"Swedish Red Cross\"\n    }\n  ],\n  \"children\": [\n    {\n      \"@type\": \"Person\",\n      \"name\": \"Birgitta\",\n      \"birthDate\": \"1927\"\n    },\n    {\n      \"@type\": \"Person\",\n      \"name\": \"Sten\",\n      \"birthDate\": \"1920\"\n    },\n    {\n      \"@type\": \"Person\",\n      \"name\": \"Anne-Marie\",\n      \"birthDate\": \"1930\"\n    },\n    {\n      \"@type\": \"Person\",\n      \"name\": \"Ulrika\",\n      \"birthDate\": \"1931\"\n    },\n    {\n      \"@type\": \"Person\",\n      \"name\": \"Margareta\",\n      \"birthDate\": \"1934\"\n    },\n    {\n      \"@type\": \"Person\",\n      \"name\": \"Cecilia\",\n      \"birthDate\": \"1940\"\n    },\n    {\n      \"@type\": \"Person\",\n      \"name\": \"Elisabeth\",\n      \"birthDate\": \"1942\"\n    },\n    {\n      \"@type\": \"Person\",\n      \"name\": \"Claes-Johan\",\n      \"birthDate\": \"1944\"\n    }\n  ],\n  \"education\": [\n    {\n      \"@type\": \"EducationalOccupationalCredential\",\n      \"credentialCategory\": \"Matriculation Exam\",\n      \"educationalLevel\": \"High School\",\n      \"educationalCredentialAwarded\": \"Västerås matriculation exam\",\n      \"awardDate\": \"1916\"\n    },\n    {\n      \"@type\": \"EducationalOccupationalCredential\",\n      \"credentialCategory\": \"Degree\",\n      \"educationalLevel\": \"Undergraduate\",\n      \"educationalCredentialAwarded\": \"Medical Candidate\",\n      \"awardDate\": \"1922\",\n      \"educationalInstitution\": {\n        \"@type\": \"CollegeOrUniversity\",\n        \"name\": \"Uppsala University\"\n      }\n    },\n    {\n      \"@type\": \"EducationalOccupationalCredential\",\n      \"credentialCategory\": \"Degree\",\n      \"educationalLevel\": \"Postgraduate\",\n      \"educationalCredentialAwarded\": \"Medical License\",\n      \"awardDate\": \"1927\",\n      \"educationalInstitution\": {\n        \"@type\": \"CollegeOrUniversity\",\n        \"name\": \"Karolinska Institute\"\n      }\n    }\n  ],\n  \"affiliation\": [\n    {\n      \"@type\": \"OrganizationRole\",\n      \"roleName\": \"Provincial Physician\",\n      \"affiliationStartDate\": \"1942\",\n      \"affiliationLocation\": {\n        \"@type\": \"City\",\n        \"name\": \"Jörlanda\"\n      }\n    }\n  ],\n  \"spouse\": {\n    \"@type\": \"Person\",\n    \"name\": \"Ulla Cederström\",\n    \"marriageDate\": \"1926-05-26\"\n  },\n  \"parent\": [\n    {\n      \"@type\": \"Person\",\n      \"name\": \"Claes W.\"\n    },\n    {\n      \"@type\": \"Person\",\n      \"name\": \"Charlotte Levénhaupt\"\n    }\n  ],\n  \"jobTitle\": \"Provincial Physician\"\n}",
    "structured": {
        "@context": "https://schema.org",
        "@type": "Person",
        "name": "Lars Georg",
        "birthDate": "1898-08-02",
        "birthPlace": "Kärrbo, Västmanland",
        "memberOf": [
            {
                "@type": "Organization",
                "name": "Swedish Red Cross"
            }
        ],
        "children": [
            {
                "@type": "Person",
                "name": "Birgitta",
                "birthDate": "1927"
            },
            {
                "@type": "Person",
                "name": "Sten",
                "birthDate": "1920"
            },
            {
                "@type": "Person",
                "name": "Anne-Marie",
                "birthDate": "1930"
            },
            {
                "@type": "Person",
                "name": "Ulrika",
                "birthDate": "1931"
            },
            {
                "@type": "Person",
                "name": "Margareta",
                "birthDate": "1934"
            },
            {
                "@type": "Person",
                "name": "Cecilia",
                "birthDate": "1940"
            },
            {
                "@type": "Person",
                "name": "Elisabeth",
                "birthDate": "1942"
            },
            {
                "@type": "Person",
                "name": "Claes-Johan",
                "birthDate": "1944"
            }
        ],
        "education": [
            {
                "@type": "EducationalOccupationalCredential",
                "credentialCategory": "Matriculation Exam",
                "educationalLevel": "High School",
                "educationalCredentialAwarded": "Västerås matriculation exam",
                "awardDate": "1916"
            },
            {
                "@type": "EducationalOccupationalCredential",
                "credentialCategory": "Degree",
                "educationalLevel": "Undergraduate",
                "educationalCredentialAwarded": "Medical Candidate",
                "awardDate": "1922",
                "educationalInstitution": {
                    "@type": "CollegeOrUniversity",
                    "name": "Uppsala University"
                }
            },
            {
                "@type": "EducationalOccupationalCredential",
                "credentialCategory": "Degree",
                "educationalLevel": "Postgraduate",
                "educationalCredentialAwarded": "Medical License",
                "awardDate": "1927",
                "educationalInstitution": {
                    "@type": "CollegeOrUniversity",
                    "name": "Karolinska Institute"
                }
            }
        ],
        "affiliation": [
            {
                "@type": "OrganizationRole",
                "roleName": "Provincial Physician",
                "affiliationStartDate": "1942",
                "affiliationLocation": {
                    "@type": "City",
                    "name": "Jörlanda"
                }
            }
        ],
        "spouse": {
            "@type": "Person",
            "name": "Ulla Cederström",
            "marriageDate": "1926-05-26"
        },
        "parent": [
            {
                "@type": "Person",
                "name": "Claes W."
            },
            {
                "@type": "Person",
                "name": "Charlotte Levénhaupt"
            }
        ],
        "jobTitle": "Provincial Physician"
    }
}