{
    "original": "Jacobowsky, Carl Ulf Vilhelm, fil. dr, landsbibliotekarie, Skara, f. 23/4/96 i Uddevalla av dir. Efraim J. o. Rosa Simkov^sky. G. 39 m. fil. mag. Agda Sandberg. Barn: Carl Olof Ludvig f. 42. — Studiex. i Gbg 15, fil. kand. i Upps. 20, fil. lic. 25, fil. dr 32. Anst. v. red. av Sv. uppsl :bok. 28-30, tf. läns-hibl. i Östersund 30-38, därunder organ. vandr :bibl :verksamh. i Jämtl. 1., bibi. v. stifts- o. landsbibi. i Skara samt ordf. i styr. f. detsamma sed. 38. Skr.: Uddevalla m. omnejd i sv. litt. (17), Böcker om Bohuslän (22), Sy studenter i Oxford c:a 1620-1740 (28). Svenskar i främm. land under gångna tider (30), Andrée (30), J. G. Spar-wenfeld (akad. avh. 32), Litt. om Nya Sv:e (37) m. fl. bibliograf. skr., person- O’, kulturhist. art. i Sv. uppsl bok, tidn. o. tidskr., redig. Jämtil. bibi. årsskr. 32-38.",
    "translated": "Jacobowsky, Carl Ulf Vilhelm, PhD, county librarian, Skara, born on April 23rd, 1896 in Uddevalla to director Efraim J. and Rosa Simkovsky. Married in 1939 to Agda Sandberg, who has a degree in philosophy. They have a son named Carl Olof Ludvig, born in 1942. He took his high school degree in Gothenburg in 1915, received a Bachelor of Arts in Uppsala in 1920, a licentiate in philosophy in 1925, and a PhD in philosophy in 1932. He was employed as a managing editor of the Swedish National Encyclopedia from 1928 to 1930, acting county librarian in Östersund from 1930 to 1938, during which he organized the mobile library activities in Jämtland County. Afterwards, he served as a librarian at the Skara diocese and county library and chairman of its board since 1938. He authored several bibliographical and cultural history works on Uddevalla and its surroundings (1917), books on Bohuslän (1922), Oxford students from Sweden around 1620-1740 (1928), Swedes abroad in past times (1930), Andrée (1930), J.G. Sparwenfeld (PhD thesis in 1932), Literature on New Sweden (1937), among others. Additionally, he has written personal, cultural, and historical articles for the Swedish National Encyclopedia, newspapers, journals, and edited the Jämtland County Library's annual journal from 1932 to 1938.",
    "structured_raw": "{\n    \"@context\": \"https://schema.org\",\n    \"@type\": \"Person\",\n    \"name\": \"Carl Ulf Vilhelm Jacobowsky\",\n    \"givenName\": \"Carl Ulf Vilhelm\",\n    \"familyName\": \"Jacobowsky\",\n    \"birthDate\": \"1896-04-23\",\n    \"birthPlace\": \"Uddevalla\",\n    \"deathDate\": null,\n    \"nationality\": \"Swedish\",\n    \"parent\": [\n        {\n            \"@type\": \"Person\",\n            \"name\":\"Efraim J. Jacobowsky\",\n            \"jobTitle\": \"Director\"\n        },\n        {\n            \"@type\": \"Person\",\n            \"name\": \"Rosa Simkovsky\"\n        }\n    ],\n    \"spouse\": {\n        \"@type\": \"Person\",\n        \"name\":\"Agda Sandberg\",\n        \"jobTitle\": \"Philosopher\",\n        \"educationalCredentialAwarded\": \"Master's degree\",\n        \"datePublished\": \"1939\",\n        \"dateModified\": \"1939\"\n    },\n    \"children\": {\n        \"@type\": \"Person\",\n        \"name\": \"Carl Olof Ludvig\",\n        \"birthDate\": \"1942\"\n    },\n    \"alumniOf\": [\n        {\n            \"@type\": \"EducationalOrganization\",\n            \"name\": \"University of Gothenburg\",\n            \"location\": \"Gothenburg\",\n            \"educationalCredentialAwarded\": \"High school degree\",\n            \"endDate\": \"1915\"\n        },\n        {\n            \"@type\": \"EducationalOrganization\",\n            \"name\": \"Uppsala University\",\n            \"location\": \"Uppsala\",\n            \"educationalCredentialAwarded\": \"Bachelor of Arts\",\n            \"startDate\": \"1915\",\n            \"endDate\": \"1920\"\n        },\n        {\n            \"@type\": \"EducationalOrganization\",\n            \"name\": \"Uppsala University\",\n            \"location\": \"Uppsala\",\n            \"educationalCredentialAwarded\": \"Licentiate in Philosophy\",\n            \"startDate\": \"1920\",\n            \"endDate\": \"1925\"\n        },\n        {\n            \"@type\": \"EducationalOrganization\",\n            \"name\": \"Uppsala University\",\n            \"location\": \"Uppsala\",\n            \"educationalCredentialAwarded\": \"PhD in Philosophy\",\n            \"startDate\": \"1925\",\n            \"endDate\": \"1932\"\n        }\n    ],\n    \"jobTitle\": \"County Librarian\",\n    \"worksFor\": {\n        \"@type\": \"Organization\",\n        \"name\": \"Skara Diocese and County Library\"\n    },\n    \"affiliation\": {\n        \"@type\": \"Organization\",\n        \"name\": \"Swedish National Encyclopedia\",\n        \"jobTitle\": \"Managing Editor\",\n        \"startDate\": \"1928\",\n        \"endDate\": \"1930\"\n    },\n    \"alternateName\": \"Dr. Carl Ulf Vilhelm Jacobowsky\",\n    \"description\": \"Swedish family historian and author of bibliographical and cultural history works\"\n}",
    "structured": {
        "@context": "https://schema.org",
        "@type": "Person",
        "name": "Carl Ulf Vilhelm Jacobowsky",
        "givenName": "Carl Ulf Vilhelm",
        "familyName": "Jacobowsky",
        "birthDate": "1896-04-23",
        "birthPlace": "Uddevalla",
        "deathDate": null,
        "nationality": "Swedish",
        "parent": [
            {
                "@type": "Person",
                "name": "Efraim J. Jacobowsky",
                "jobTitle": "Director"
            },
            {
                "@type": "Person",
                "name": "Rosa Simkovsky"
            }
        ],
        "spouse": {
            "@type": "Person",
            "name": "Agda Sandberg",
            "jobTitle": "Philosopher",
            "educationalCredentialAwarded": "Master's degree",
            "datePublished": "1939",
            "dateModified": "1939"
        },
        "children": {
            "@type": "Person",
            "name": "Carl Olof Ludvig",
            "birthDate": "1942"
        },
        "alumniOf": [
            {
                "@type": "EducationalOrganization",
                "name": "University of Gothenburg",
                "location": "Gothenburg",
                "educationalCredentialAwarded": "High school degree",
                "endDate": "1915"
            },
            {
                "@type": "EducationalOrganization",
                "name": "Uppsala University",
                "location": "Uppsala",
                "educationalCredentialAwarded": "Bachelor of Arts",
                "startDate": "1915",
                "endDate": "1920"
            },
            {
                "@type": "EducationalOrganization",
                "name": "Uppsala University",
                "location": "Uppsala",
                "educationalCredentialAwarded": "Licentiate in Philosophy",
                "startDate": "1920",
                "endDate": "1925"
            },
            {
                "@type": "EducationalOrganization",
                "name": "Uppsala University",
                "location": "Uppsala",
                "educationalCredentialAwarded": "PhD in Philosophy",
                "startDate": "1925",
                "endDate": "1932"
            }
        ],
        "jobTitle": "County Librarian",
        "worksFor": {
            "@type": "Organization",
            "name": "Skara Diocese and County Library"
        },
        "affiliation": {
            "@type": "Organization",
            "name": "Swedish National Encyclopedia",
            "jobTitle": "Managing Editor",
            "startDate": "1928",
            "endDate": "1930"
        },
        "alternateName": "Dr. Carl Ulf Vilhelm Jacobowsky",
        "description": "Swedish family historian and author of bibliographical and cultural history works"
    }
}