{
    "original": "Dymling, Ebbe Samuel, jur. o. fil. kand., borgmästare, krigsdomare, Karlskrona, f. 29/8/94 i Gbg av kontr:-prosten Karl Andersson o. Anna Dymling. G. 1. 30 m. Mary Strömberg, d. 33; 2. 41 m. Selma Särner, f. Hellquist. — Stud:ex. i Halmstad 13, fil. kand. i Lund 18, jur. kand. 22. Tingstjg. 24-26, tf. fiskal i hovr. över Skåne o. Blek. 26, assessor 30, borg-mäst. i Karlskrona sed. 33. Krigs-dorh. v. Karlskrona örlogsstat. o. Karlskrona kustart :reg. sed. 37. V. ordf. i länsarb :nd f. Blek. sed. 45, ordf. i länsnykterh :ndn i Blek. 1. sed. 39. RNO.",
    "translated": "Dymling, Ebbe Samuel, MA in Law and Philosophy, Mayor, War judge, Karlskrona, born on August 29, 1894 in Gothenburg, son of district-provost Karl Andersson and Anna Dymling. He was married twice, first in 1930 to Mary Strömberg who died in 1933, and then in 1941 to Selma Särner, born Hellquist. — He completed his high school studies in Halmstad in 1913, and obtained a BA in Philosophy from Lund University in 1918, and an MA in Law in 1922. He served in the court in Tingstjg. from 1924 to 1926, was acting clerk in the Court of Appeal for Skåne and Blekinge in 1926, became an assessor in 1930, and has been a mayor of Karlskrona since 1933. He has also been the military judge for the Karlskrona naval base and the Karlskrona coastal artillery regiment since 1937. He was the deputy chairman of the county labor board for Blekinge from 1945, and the chairman of the county temperance commission in Blekinge since 1939. He has been awarded the Order of the North Star (RNO).",
    "structured_raw": "{\n   \"@context\": \"https://schema.org\",\n   \"@type\": \"Person\",\n   \"name\": \"Ebbe Samuel Dymling\",\n   \"birthDate\": \"1894-08-29\",\n   \"birthPlace\": \"Gothenburg\",\n   \"deathDate\": null,\n   \"parent\": [\n      {\n         \"@type\": \"Person\",\n         \"name\": \"Karl Andersson\"\n      },\n      {\n         \"@type\": \"Person\",\n         \"name\": \"Anna Dymling\"\n      }\n   ],\n   \"spouse\": [\n      {\n         \"@type\": \"Person\",\n         \"name\": \"Mary Strömberg\",\n         \"marriageDate\": \"1930\",\n         \"divorceDate\": \"1933\",\n         \"deathDate\": \"1933\"\n      },\n      {\n         \"@type\": \"Person\",\n         \"name\": \"Selma Särner\",\n         \"marriageDate\": \"1941\"\n      }\n   ],\n   \"education\": [\n      {\n         \"@type\": \"EducationalOccupationalCredential\",\n         \"name\": \"MA in Law\",\n         \"educationalLevel\": \"Master'sDegree\",\n         \"dateReceived\": \"1922\"\n      },\n      {\n         \"@type\": \"EducationalOccupationalCredential\",\n         \"name\": \"BA in Philosophy\",\n         \"educationalLevel\": \"Bachelor'sDegree\",\n         \"dateReceived\": \"1918\"\n      }\n   ],\n   \"jobTitle\": [\n      \"Mayor\",\n      \"War judge\"\n   ],\n   \"memberOf\": [\n      {\n         \"@type\": \"Organization\",\n         \"name\": \"Karlskrona municipal\"\n      },\n      {\n         \"@type\": \"Organization\",\n         \"name\": \"Court of Appeal for Skåne and Blekinge\"\n      }\n   ],\n   \"affiliation\": [\n      {\n         \"@type\": \"Organization\",\n         \"name\": \"Karlskrona naval base\"\n      },\n      {\n         \"@type\": \"Organization\",\n         \"name\": \"Karlskrona coastal artillery regiment\"\n      }\n   ],\n   \"honors\": [\n      {\n         \"@type\": \"Order\",\n         \"name\": \"Order of the North Star\",\n         \"dateReceived\": null,\n         \"description\": \"RNO\"\n      }\n   ],\n   \"deathPlace\": null\n}",
    "structured": {
        "@context": "https://schema.org",
        "@type": "Person",
        "name": "Ebbe Samuel Dymling",
        "birthDate": "1894-08-29",
        "birthPlace": "Gothenburg",
        "deathDate": null,
        "parent": [
            {
                "@type": "Person",
                "name": "Karl Andersson"
            },
            {
                "@type": "Person",
                "name": "Anna Dymling"
            }
        ],
        "spouse": [
            {
                "@type": "Person",
                "name": "Mary Strömberg",
                "marriageDate": "1930",
                "divorceDate": "1933",
                "deathDate": "1933"
            },
            {
                "@type": "Person",
                "name": "Selma Särner",
                "marriageDate": "1941"
            }
        ],
        "education": [
            {
                "@type": "EducationalOccupationalCredential",
                "name": "MA in Law",
                "educationalLevel": "Master'sDegree",
                "dateReceived": "1922"
            },
            {
                "@type": "EducationalOccupationalCredential",
                "name": "BA in Philosophy",
                "educationalLevel": "Bachelor'sDegree",
                "dateReceived": "1918"
            }
        ],
        "jobTitle": [
            "Mayor",
            "War judge"
        ],
        "memberOf": [
            {
                "@type": "Organization",
                "name": "Karlskrona municipal"
            },
            {
                "@type": "Organization",
                "name": "Court of Appeal for Skåne and Blekinge"
            }
        ],
        "affiliation": [
            {
                "@type": "Organization",
                "name": "Karlskrona naval base"
            },
            {
                "@type": "Organization",
                "name": "Karlskrona coastal artillery regiment"
            }
        ],
        "honors": [
            {
                "@type": "Order",
                "name": "Order of the North Star",
                "dateReceived": null,
                "description": "RNO"
            }
        ],
        "deathPlace": null
    }
}