{
    "original": "Ernfrid Hilding Valdemar, läroverksadjunkt, rektor, Ronneby, f. 20/1791 i No^rdmark, Värml. 1., av A. W. Westberg o. Augusta Bengtsson. G. 18 m. Gunda Winberg. Barn: Björn Hilding Sture f. 20. — Stud:ex. i Karlstad 11, fil. mag. i Upps. 17, lic:kurs v. Sthlms högsk. 21-22, pro vår i Sthlm 19-20. E. o. lär. i Gävle 17, Strö|mstad 18-19, Katarina realsk. i Sthlmi 1!9, Karlstads folksk:-semin. 20, Norra latin i Sthlm 20-22, Nya elem;lärov. i Sthlto 22,-23, Karol. lärov. i Örebro i23’-3il, timlär. i biol. v. Betelsemin. i Sthlmi 21»-2!3’, adj. i biol. m. hälsolära o. kemi v. Ronneb^^ samrealsk. sed. 3il, rektor f. Ro-nneby stads yrkessk. sed. 45. Kyrkoftillm. 39, v. ordf. i BU 39-46, stadsfullm. 43, led. av fam:bidragsndn 44, civil-försv:chef i Ronneby civilförsv :omr. 44-46, dep. o. styr :medl. i Lärov :lär. riksförb. sed. 42. Utställn :komm. v. hemslöjdsutstäliln. i Strömstad 19. Skr.: Dy rörts systemets överdrifter (44), tid-n :art. i löne- o. skattefrågoT. , Sven Ivan Kristoffer, bruksdisponent, Ekenässjön, f. 17/1/83 i Kläckeberga,, Kalmar 1., av godsförv. J. P. Westberg o. Sofie Högländer. G. 2. 32 m. Edith Zyrner. Barn: Anne-Sofie f. 12, Maj 13, Britta 18, Elsbeth 36. — Ans t. v. Lindefoirs glasibruk 02-07, Bergdala 07-li3&gt;, Pukeberg 14-18, Airboga 19-22, Ekenäs sed. 26’. Ordf. i Sv. glasexportfÖTen. o. Flaskfabrikan-ternas fören., styrrled. i Sv:es små-gliasbruksförb. o. Hushånsglasfabr :-fören. Led. av komim rfullm., kyrko-fiillm., kyrkoråd, vägstyr., tax:nd, kassör i skolstyr. RNO, RVO. Westborg, E&amp;aias, bankdirektör, Växjö, f. 2/6/88 i Södra Hestra, Jön-köp. L, av John Nilsson o. Emma Westborg. G. 24 m. Karin Swenson. Barn: Jodin-Erik f. 28, Sven-Magnus 32, Bengt-Jo’han 36. — Stud:ex. 08. Anst. v. Sydsvenska kredit A-B i Lund 10, v. huv :kont. 15, kassör i Linköp. 17, kamr. i Mariestad 18, i Växjö s. år, kamr. i Kronob. 1. sparb. verkst. dir. ,fr. 26, styr:led. fr. 33. Kamr. i Växjö ränte- o. kap :förs :anst. sed. 25. Äg. fastigh. i Växjö. Ordf. i länets sparb :fören., v. ordf. i Sparb. gar :kasisa, styr:led. i Sparb, förhandl:-org., styrrsuppl. i Sparbankernas bank A-B o. i Sparfrämjandets förlags A-B, rev. i Sv. sparb :fören., skattm. i fören. f. Smål. fornminnen o. kulturhist., om’b. f. Städernas förs :bol’. Resor t. Tyskl., Hoil’1., Belg., Frankr., Ital. o. Schv^eiz 23. Skr.: Kronob. 1. sparb. 1828-1928. Medl. av Rotarykl. Hob-bies: segl., sportfiske. RVO.",
    "translated": "Ernfrid Hilding Valdemar, high school teacher, principal, Ronneby, born on February 20, 1791 in Nordmark, Värmland County, son of A. W. Westberg and Augusta Bengtsson. Married to Gunda Winberg in 1818. Children: Björn Hilding Sture, born on February 20. Education: Completed secondary school in Karlstad in 1811, received a bachelor's degree in Uppsala in 1817, attended a licentiate course at Stockholm University in 1821-1822, and served as a temporary teacher in Gävle in 1817, Strömstad in 1818-1819, Katarina High School in Stockholm in 1819, Karlstad People's School-Seminary in 1820, Norra Latin High School in Stockholm in 1820-1822, Nya Elementarläroverket in Stockholm in 1822-1823, Karolinska High School in Örebro in 1823-1831, and biology teacher at Betelseminarium in Stockholm from 1821-1823. Became an adjunct biology teacher with health science and chemistry at Ronneby Real School in 1831, and later became the principal of Ronneby City Vocational School in 1845. Member of the church council since 1839, vice chairman of the school board from 1839 to 1846, member of the city council since 1843, member of the family welfare committee since 1844, civil defense chief in the Ronneby civil defense district from 1944 to 1946, and department and board member of the National Teachers Association since 1942. Also served on the exhibition committee for the home crafts exhibition in Strömstad in 1919. Author of the book \"Dy rörts systemets överdrifter\" (The Exaggerations of the Movement System) in 1944, and wrote articles on salary and taxation issues. \n\nSven Ivan Kristoffer, industrial manager, Ekenässjön, born on January 17, 1883 in Kläckeberga, Kalmar County, son of estate manager J. P. Westberg and Sofie Högländer. Married to Edith Zyrner in 1932. Children: Anne-Sofie, born in 1912, Maj in 1913, Britta in 1918, Elsbeth in 1936. Worked at Lindefors Glassworks from 1902 to 1907, Bergdala from 1907 to 1913, Pukeberg from 1914 to 1918, Airboga from 1919 to 1922, and has been working at Ekenäs since 1926. Served as chairman of the Swedish Glass Export Association and the Bottle Manufacturers' Association, and board member of the Swedish Small Glassworks Association and the Household Glass Factory Association. Also served as a member of the municipal council, church council, road board, tax committee and treasurer of the school board. Received the Royal Order of the North Star (RNO) and the Royal Order of Vasa (RVO). \n\nWestborg, Eaias, bank director, Växjö, born on June 2, 1888 in Södra Hestra, Jönköping County, son of John Nilsson and Emma Westborg. Married to Karin Swenson in 1924. Children: Jodin-Erik, born in 1928, Sven-Magnus in 1932, Bengt-Johan in 1936. Completed secondary school in 1908. Worked at Sydsvenska Kredit AB in Lund from 1910, becoming the head cashier in 1915. Later worked as a cashier in Linköping in 1917, and then in Mariestad in 1918. Joined Växjö Savings Bank in the same year and became a chamberlain in 1926, and then the managing director of the bank in 1933. Also served as a board member of various organizations and was a member of the Växjö Interest and Capital Insurance Institution since 1925. Owns properties in Växjö. Served as chairman of the county savings bank association, vice chairman of the Savings Bank Guarantee Association, board substitute of the Savings Banks Bank AB and the Savings Promotion Publishing AB, auditor of the Swedish Savings Association, treasurer of the Association for Småland's Antiquities and Cultural History, and commissioner for the cities' defense agency. Traveled to Germany, Holland, Belgium, France, Italy, and Switzerland in 1923. Author of the book \"Kronob. 1. sparb. 1828-1928\" (Kronoberg County Savings Bank 1828-1928). Member of the Rotary Club. Hobbies include sailing and sport fishing. Received the Royal Order of Vasa (RVO).",
    "structured_raw": "{\n  \"@context\": \"https://schema.org\",\n  \"@type\": \"Person\",\n  \"name\": \"Ernfrid Hilding Valdemar\",\n  \"birthDate\": \"1791-02-20\",\n  \"birthPlace\": {\n    \"@type\": \"City\",\n    \"name\": \"Nordmark\",\n    \"address\": {\n      \"@type\": \"PostalAddress\",\n      \"addressLocality\": \"Värmland County\"\n    }\n  },\n  \"parent\": [\n    {\n      \"@type\": \"Person\",\n      \"name\": \"A. W. Westberg\",\n      \"gender\": \"male\"\n    },\n    {\n      \"@type\": \"Person\",\n      \"name\": \"Augusta Bengtsson\",\n      \"gender\": \"female\"\n    }\n  ],\n  \"spouse\": {\n    \"@type\": \"Person\",\n    \"name\": \"Gunda Winberg\"\n  },\n  \"children\": [\n    {\n      \"@type\": \"Person\",\n      \"name\": \"Björn Hilding Sture\",\n      \"birthDate\": \"1820-02-20\"\n    }\n  ],\n  \"education\": [\n    {\n      \"@type\": \"EducationalOccupationalCredential\",\n      \"educationalLevel\": \"SecondarySchool\",\n      \"educationalRole\": \"Graduate\",\n      \"startDate\": \"1811\",\n      \"endDate\": \"1811\",\n      \"educationalInstitution\": {\n        \"@type\": \"Organization\",\n        \"name\": \"Karlstad\"\n      }\n    },\n    {\n      \"@type\": \"EducationalOccupationalCredential\",\n      \"educationalLevel\": \"BachelorDegree\",\n      \"educationalRole\": \"Magister\",\n      \"startDate\": \"1817\",\n      \"endDate\": \"1817\",\n      \"educationalInstitution\": {\n        \"@type\": \"Organization\",\n        \"name\": \"Uppsala\"\n      }\n    },\n    {\n      \"@type\": \"EducationalOccupationalCredential\",\n      \"educationalLevel\": \"LicentiateCourse\",\n      \"educationalRole\": \"Student\",\n      \"startDate\": \"1821\",\n      \"endDate\": \"1822\",\n      \"educationalInstitution\": {\n        \"@type\": \"Organization\",\n        \"name\": \"Stockholm University\"\n      }\n    }\n  ],\n  \"occupationHistory\": [\n    {\n      \"@type\": \"Occupation\",\n      \"name\": \"Teacher\",\n      \"startDate\": \"1817\",\n      \"endDate\": \"1817\",\n      \"employer\": {\n        \"@type\": \"Organization\",\n        \"name\": \"Gävle\"\n      }\n    },\n    {\n      \"@type\": \"Occupation\",\n      \"name\": \"Teacher\",\n      \"startDate\": \"1818\",\n      \"endDate\": \"1819\",\n      \"employer\": {\n        \"@type\": \"Organization\",\n        \"name\": \"Strömstad\"\n      }\n    },\n    {\n      \"@type\": \"Occupation\",\n      \"name\": \"Teacher\",\n      \"startDate\": \"1819\",\n      \"endDate\": \"1819\",\n      \"employer\": {\n        \"@type\": \"Organization\",\n        \"name\": \"Katarina High School\"\n      }\n    },\n    {\n      \"@type\": \"Occupation\",\n      \"name\": \"Teacher\",\n      \"startDate\": \"1820\",\n      \"endDate\": \"1820\",\n      \"employer\": {\n        \"@type\": \"Organization\",\n        \"name\": \"Karlstad People's School-Seminary\"\n      }\n    },\n    {\n      \"@type\": \"Occupation\",\n      \"name\": \"Teacher\",\n      \"startDate\": \"1820\",\n      \"endDate\": \"1822\",\n      \"employer\": {\n        \"@type\": \"Organization\",\n        \"name\": \"Norra Latin High School\"\n      }\n    },\n    {\n      \"@type\": \"Occupation\",\n      \"name\": \"Teacher\",\n      \"startDate\": \"1822\",\n      \"endDate\": \"1823\",\n      \"employer\": {\n        \"@type\": \"Organization\",\n        \"name\": \"Nya Elementarläroverket\"\n      }\n    },\n    {\n      \"@type\": \"Occupation\",\n      \"name\": \"Teacher\",\n      \"startDate\": \"1823\",\n      \"endDate\": \"1831\",\n      \"employer\": {\n        \"@type\": \"Organization\",\n        \"name\": \"Karolinska High School in Örebro\"\n      }\n    },\n    {\n      \"@type\": \"Occupation\",\n      \"name\": \"Teacher\",\n      \"startDate\": \"1821\",\n      \"endDate\": \"1823\",\n      \"employer\": {\n        \"@type\": \"Organization\",\n        \"name\": \"Betelseminarium\"\n      }\n    },\n    {\n      \"@type\": \"Occupation\",\n      \"name\": \"Adjunct Biology Teacher\",\n      \"specialty\": \"Health Science, Chemistry\",\n      \"startDate\": \"1831\",\n      \"endDate\": null,\n      \"employer\": {\n        \"@type\": \"Organization\",\n        \"name\": \"Ronneby Real School\"\n      }\n    },\n    {\n      \"@type\": \"Occupation\",\n      \"name\": \"Principal\",\n      \"startDate\": \"1845\",\n      \"endDate\": null,\n      \"employer\": {\n        \"@type\": \"Organization\",\n        \"name\": \"Ronneby City Vocational School\"\n      }\n    }\n  ],\n  \"memberOf\": [\n    {\n      \"@type\": \"Organization\",\n      \"name\": \"Church Council\"\n    },\n    {\n      \"@type\": \"Organization\",\n      \"name\": \"School Board\",\n      \"roleName\": \"Vice Chairman\",\n      \"startDate\": \"1839\",\n      \"endDate\": \"1846\"\n    },\n    {\n      \"@type\": \"Organization\",\n      \"name\": \"City Council\",\n      \"startDate\": \"1843\"\n    },\n    {\n      \"@type\": \"Organization\",\n      \"name\": \"Family Welfare Committee\",\n      \"startDate\": \"1844\"\n    },\n    {\n      \"@type\": \"Organization\",\n      \"name\": \"National Teachers Association\",\n      \"roleName\": \"Department and Board Member\",\n      \"startDate\": \"1942\"\n    }\n  ],\n  \"worksPublished\": [\n    {\n      \"@type\": \"CreativeWork\",\n      \"name\": \"Dy rörts systemets överdrifter\",\n      \"datePublished\": \"1944\"\n    }\n  ]\n}",
    "structured": {
        "@context": "https://schema.org",
        "@type": "Person",
        "name": "Ernfrid Hilding Valdemar",
        "birthDate": "1791-02-20",
        "birthPlace": {
            "@type": "City",
            "name": "Nordmark",
            "address": {
                "@type": "PostalAddress",
                "addressLocality": "Värmland County"
            }
        },
        "parent": [
            {
                "@type": "Person",
                "name": "A. W. Westberg",
                "gender": "male"
            },
            {
                "@type": "Person",
                "name": "Augusta Bengtsson",
                "gender": "female"
            }
        ],
        "spouse": {
            "@type": "Person",
            "name": "Gunda Winberg"
        },
        "children": [
            {
                "@type": "Person",
                "name": "Björn Hilding Sture",
                "birthDate": "1820-02-20"
            }
        ],
        "education": [
            {
                "@type": "EducationalOccupationalCredential",
                "educationalLevel": "SecondarySchool",
                "educationalRole": "Graduate",
                "startDate": "1811",
                "endDate": "1811",
                "educationalInstitution": {
                    "@type": "Organization",
                    "name": "Karlstad"
                }
            },
            {
                "@type": "EducationalOccupationalCredential",
                "educationalLevel": "BachelorDegree",
                "educationalRole": "Magister",
                "startDate": "1817",
                "endDate": "1817",
                "educationalInstitution": {
                    "@type": "Organization",
                    "name": "Uppsala"
                }
            },
            {
                "@type": "EducationalOccupationalCredential",
                "educationalLevel": "LicentiateCourse",
                "educationalRole": "Student",
                "startDate": "1821",
                "endDate": "1822",
                "educationalInstitution": {
                    "@type": "Organization",
                    "name": "Stockholm University"
                }
            }
        ],
        "occupationHistory": [
            {
                "@type": "Occupation",
                "name": "Teacher",
                "startDate": "1817",
                "endDate": "1817",
                "employer": {
                    "@type": "Organization",
                    "name": "Gävle"
                }
            },
            {
                "@type": "Occupation",
                "name": "Teacher",
                "startDate": "1818",
                "endDate": "1819",
                "employer": {
                    "@type": "Organization",
                    "name": "Strömstad"
                }
            },
            {
                "@type": "Occupation",
                "name": "Teacher",
                "startDate": "1819",
                "endDate": "1819",
                "employer": {
                    "@type": "Organization",
                    "name": "Katarina High School"
                }
            },
            {
                "@type": "Occupation",
                "name": "Teacher",
                "startDate": "1820",
                "endDate": "1820",
                "employer": {
                    "@type": "Organization",
                    "name": "Karlstad People's School-Seminary"
                }
            },
            {
                "@type": "Occupation",
                "name": "Teacher",
                "startDate": "1820",
                "endDate": "1822",
                "employer": {
                    "@type": "Organization",
                    "name": "Norra Latin High School"
                }
            },
            {
                "@type": "Occupation",
                "name": "Teacher",
                "startDate": "1822",
                "endDate": "1823",
                "employer": {
                    "@type": "Organization",
                    "name": "Nya Elementarläroverket"
                }
            },
            {
                "@type": "Occupation",
                "name": "Teacher",
                "startDate": "1823",
                "endDate": "1831",
                "employer": {
                    "@type": "Organization",
                    "name": "Karolinska High School in Örebro"
                }
            },
            {
                "@type": "Occupation",
                "name": "Teacher",
                "startDate": "1821",
                "endDate": "1823",
                "employer": {
                    "@type": "Organization",
                    "name": "Betelseminarium"
                }
            },
            {
                "@type": "Occupation",
                "name": "Adjunct Biology Teacher",
                "specialty": "Health Science, Chemistry",
                "startDate": "1831",
                "endDate": null,
                "employer": {
                    "@type": "Organization",
                    "name": "Ronneby Real School"
                }
            },
            {
                "@type": "Occupation",
                "name": "Principal",
                "startDate": "1845",
                "endDate": null,
                "employer": {
                    "@type": "Organization",
                    "name": "Ronneby City Vocational School"
                }
            }
        ],
        "memberOf": [
            {
                "@type": "Organization",
                "name": "Church Council"
            },
            {
                "@type": "Organization",
                "name": "School Board",
                "roleName": "Vice Chairman",
                "startDate": "1839",
                "endDate": "1846"
            },
            {
                "@type": "Organization",
                "name": "City Council",
                "startDate": "1843"
            },
            {
                "@type": "Organization",
                "name": "Family Welfare Committee",
                "startDate": "1844"
            },
            {
                "@type": "Organization",
                "name": "National Teachers Association",
                "roleName": "Department and Board Member",
                "startDate": "1942"
            }
        ],
        "worksPublished": [
            {
                "@type": "CreativeWork",
                "name": "Dy rörts systemets överdrifter",
                "datePublished": "1944"
            }
        ]
    }
}