{
    "original": "Karlholm, Bertil Karl Otto, provinsialläkare, Ullared, f. 28/5/02 i Valdemarsvik, östergötl. 1., av krono-länsm. Karl K. o. Teresia Janse. G. 34 m. Aksa Hedvall. Barn: Kerstin f. 36, Karl 39, Eva 42, Britta 44. — Stud:ex. i Skara 21, med. kand. i Sthlm 26, med. Hc. där 31. Assist :läk. v. Finspångs las. 31-32, kort. förordn. s. prov:iläk. i Valdemarsviks distr. samt s. järnv:läk. i Kungsbacka o. stadsläk. i Söderköp. 32, prov:läk. i Finspångs distr. 32 o. 33, i Offerdals distr. 33, und:läk. v. Styrsö kustsan. 33, tf. andre und:läk. v. Västerviks las. 32 o. 33, v. Uddevalla las. 33, andre und:läk. v. Västerviks las. 34-36, förste und :läk. v. Oskarshamns las. 36-39, andre und :läk. v. Eksjö san. 39-40, ett flert. förordn. s. prov :däk. o. stadsläk. 40-42, e. prov:läk. i Krist-dala 42-45, prov:läk. i Ullareds distr. sed. 45. Led. av komm:ful’lm. o. nyk-terh :ndn sed. 47.",
    "translated": "Karlholm, Bertil Karl Otto, District Medical Officer, Ullared, b. 28/5/02 in Valdemarsvik, Östergötland, son of Karl K. and Teresia Janse. Married in 1934 to Aksa Hedvall. Children: Kerstin b. 1936, Karl b. 1939, Eva b. 1942, Britta b. 1944. \n\nEducation: Student examination in Skara in 1921, Bachelor of Medicine in Stockholm in 1926, Doctor of Medicine in 1931. \n\nProfessional experience: Assistant doctor at Finspång Hospital 1931-1932, temporary district medical officer in Valdemarsvik district and railway doctor in Kungsbacka and city doctor in Söderköping in 1932, district medical officer in Finspång district in 1932-1933, in Offerdal district in 1933, deputy doctor at Styrsö Coastal Sanatorium in 1933, temporary deputy doctor at Västervik Hospital in 1932-1933, assistant doctor at Uddevalla Hospital in 1933, deputy doctor at Västervik Hospital in 1934-1936, first assistant doctor at Oskarshamn Hospital in 1936-1939, deputy doctor at Eksjö Sanatorium in 1939-1940, multiple temporary appointments as district doctor and city doctor in 1940-1942, assistant doctor in Kristdala in 1942-1945, district medical officer in Ullared district since 1945. \n\nMember of the Municipal Health Committee and the Temperance Association since 1947.",
    "structured_raw": "{\n  \"@context\": \"https://schema.org\",\n  \"@type\": \"Person\",\n  \"name\": \"Bertil Karl Otto Karlholm\",\n  \"birthDate\": \"1902-05-28\",\n  \"birthPlace\": \"Valdemarsvik, Östergötland\",\n  \"nationality\": \"Swedish\",\n  \"parent\": [\n    {\n      \"@type\": \"Person\",\n      \"name\": \"Karl K.\"\n    },\n    {\n      \"@type\": \"Person\",\n      \"name\": \"Teresia Janse\"\n    }\n  ],\n  \"spouse\": {\n    \"@type\": \"Person\",\n    \"name\": \"Aksa Hedvall\",\n    \"marriageDate\": \"1934\"\n  },\n  \"children\": [\n    {\n      \"@type\": \"Person\",\n      \"name\": \"Kerstin\",\n      \"birthDate\": \"1936\"\n    },\n    {\n      \"@type\": \"Person\",\n      \"name\": \"Karl\",\n      \"birthDate\": \"1939\"\n    },\n    {\n      \"@type\": \"Person\",\n      \"name\": \"Eva\",\n      \"birthDate\": \"1942\"\n    },\n    {\n      \"@type\": \"Person\",\n      \"name\": \"Britta\",\n      \"birthDate\": \"1944\"\n    }\n  ],\n  \"alumniOf\": [\n    {\n      \"@type\": \"EducationalOrganization\",\n      \"name\": \"Skara\",\n      \"startDate\": \"1921\",\n      \"endDate\": \"1921\",\n      \"alumniOf\": {\n        \"@type\": \"EducationalOrganization\",\n        \"name\": \"Student examination\"\n      }\n    },\n    {\n      \"@type\": \"EducationalOrganization\",\n      \"name\": \"Stockholm\",\n      \"startDate\": \"1926\",\n      \"endDate\": \"1931\",\n      \"alumniOf\": {\n        \"@type\": \"EducationalOrganization\",\n        \"name\": \"Bachelor of Medicine\"\n      }\n    }\n  ],\n  \"hasOccupation\": [\n    {\n      \"@type\": \"MedicalOccupation\",\n      \"name\": \"District Medical Officer\",\n      \"startDate\": \"1945\"\n    }\n  ],\n  \"affiliation\": [\n    {\n      \"@type\": \"Organization\",\n      \"name\": \"Municipal Health Committee\",\n      \"startDate\": \"1947\"\n    },\n    {\n      \"@type\": \"Organization\",\n      \"name\": \"Temperance Association\",\n      \"startDate\": \"1947\"\n    }\n  ],\n  \"worksFor\": {\n    \"@type\": \"Organization\",\n    \"name\": \"Ullared\"\n  }\n}",
    "structured": {
        "@context": "https://schema.org",
        "@type": "Person",
        "name": "Bertil Karl Otto Karlholm",
        "birthDate": "1902-05-28",
        "birthPlace": "Valdemarsvik, Östergötland",
        "nationality": "Swedish",
        "parent": [
            {
                "@type": "Person",
                "name": "Karl K."
            },
            {
                "@type": "Person",
                "name": "Teresia Janse"
            }
        ],
        "spouse": {
            "@type": "Person",
            "name": "Aksa Hedvall",
            "marriageDate": "1934"
        },
        "children": [
            {
                "@type": "Person",
                "name": "Kerstin",
                "birthDate": "1936"
            },
            {
                "@type": "Person",
                "name": "Karl",
                "birthDate": "1939"
            },
            {
                "@type": "Person",
                "name": "Eva",
                "birthDate": "1942"
            },
            {
                "@type": "Person",
                "name": "Britta",
                "birthDate": "1944"
            }
        ],
        "alumniOf": [
            {
                "@type": "EducationalOrganization",
                "name": "Skara",
                "startDate": "1921",
                "endDate": "1921",
                "alumniOf": {
                    "@type": "EducationalOrganization",
                    "name": "Student examination"
                }
            },
            {
                "@type": "EducationalOrganization",
                "name": "Stockholm",
                "startDate": "1926",
                "endDate": "1931",
                "alumniOf": {
                    "@type": "EducationalOrganization",
                    "name": "Bachelor of Medicine"
                }
            }
        ],
        "hasOccupation": [
            {
                "@type": "MedicalOccupation",
                "name": "District Medical Officer",
                "startDate": "1945"
            }
        ],
        "affiliation": [
            {
                "@type": "Organization",
                "name": "Municipal Health Committee",
                "startDate": "1947"
            },
            {
                "@type": "Organization",
                "name": "Temperance Association",
                "startDate": "1947"
            }
        ],
        "worksFor": {
            "@type": "Organization",
            "name": "Ullared"
        }
    }
}