{
    "original": "Edström, Mats Harald, civilingenjör, andre stadsarkitekt, Göteborg, f. 19/11/83 i Falköping av ’stat :insp. Ernst Reinhold E. o. Gertrud von Mosczins.ky. G. 14 m. Viola Marie-Louise Svanberg. Barn: Margot f. 15, Britta 17. — Genomg. CTI 98-06, avg:ex. från CTI 06, stud. v. FrKa t. 12. Ritare h. arkit. Y. Rasmussen 06-08, h. arkit. Arvid Bjerke 10-11, h. arkit. Sigge Cronstedt 10, prakt, arkit. II, anst. v. stadsing :kont. i Gbg 12, andre stadsarkit. i Gbg sed. 13. Sekr. i Tekn. ’samf. avd. f. husbyggn :konst 16-17, v. ordf. 18, ordf. i komm. f. om-arb. av byggn :ordn. i Gbg. Skr.: upps. i Tekn. samf. handl. RVO 43.",
    "translated": "Edström, Mats Harald, master of engineering, second city architect, Gothenburg, born on November 19th, 1883 in Falköping to 'state inspector' Ernst Reinhold E. and Gertrud von Mosczins.ky. Married for 14 years to Viola Marie-Louise Svanberg, they have two children: Margot born in 1915 and Britta in 1917. He completed his studies at CTI (Chalmers University of Technology) from 1898 to 1906, and received his graduation certificate in 1906. He studied at the Royal Academy of Fine Arts in Stockholm from 1906 to 1912. He worked as a drafter for architect Y. Rasmussen from 1906 to 1908, and worked for architect Arvid Bjerke from 1910 to 1911, as well as for architect Sigge Cronstedt in 1910. He was a practical architect II and employed at the city engineer's office in Gothenburg in 1912, and became the second city architect of Gothenburg after 1913. He was Secretary of the Technical Society Division for Building Construction Art from 1916 to 1917, Vice Chairman in 1918, and Chairman of the Committee for the Reorganization of Building Regulations in Gothenburg. He has written research papers in the Technical Society Proceedings and was awarded RVO 43.",
    "structured_raw": "{\n  \"@context\": \"https://schema.org/\",\n  \"@type\": \"Person\",\n  \"name\": \"Mats Harald Edström\",\n  \"givenName\": \"Mats Harald\",\n  \"familyName\": \"Edström\",\n  \"birthDate\": \"1883-11-19\",\n  \"birthPlace\": \"Falköping, Sweden\",\n  \"deathDate\": null,\n  \"deathPlace\": null,\n  \"nationality\": \"Swedish\",\n  \"gender\": \"Male\",\n  \"jobTitle\": \"Second City Architect\",\n  \"worksFor\": {\n    \"@type\": \"Organization\",\n    \"name\": \"Gothenburg\"\n  },\n  \"spouse\": {\n    \"@type\": \"Person\",\n    \"name\": \"Viola Marie-Louise Svanberg\",\n    \"gender\": \"Female\"\n  },\n  \"children\": [\n    {\n      \"@type\": \"Person\",\n      \"name\": \"Margot Edström\",\n      \"birthDate\": \"1915\"\n    },\n    {\n      \"@type\": \"Person\",\n      \"name\": \"Britta Edström\",\n      \"birthDate\": \"1917\"\n    }\n  ],\n  \"parent\": [\n    {\n      \"@type\": \"Person\",\n      \"name\": \"Ernst Reinhold E. Edström\",\n      \"jobTitle\": \"State inspector\"\n    },\n    {\n      \"@type\": \"Person\",\n      \"name\": \"Gertrud von Mosczins.ky\"\n    }\n  ],\n  \"education\": [\n    {\n      \"@type\": \"EducationalOrganization\",\n      \"name\": \"Chalmers University of Technology\",\n      \"location\": \"Gothenburg\",\n      \"startDate\": \"1898\",\n      \"endDate\": \"1906\",\n      \"degree\": {\n        \"@type\": \"EducationalDegree\",\n        \"name\": \"Master of Engineering\"\n      }\n    },\n    {\n      \"@type\": \"EducationalOrganization\",\n      \"name\": \"Royal Academy of Fine Arts\",\n      \"location\": \"Stockholm\",\n      \"startDate\": \"1906\",\n      \"endDate\": \"1912\"\n    }\n  ],\n  \"memberOf\": [\n    {\n      \"@type\": \"Organization\",\n      \"name\": \"Technical Society Division for Building Construction Art\",\n      \"roleName\": \"Secretary\",\n      \"startDate\": \"1916\",\n      \"endDate\": \"1917\"\n    },\n    {\n      \"@type\": \"Organization\",\n      \"name\": \"Technical Society Division for Building Construction Art\",\n      \"roleName\": \"Vice Chairman\",\n      \"startDate\": \"1918\",\n      \"endDate\": null\n    },\n    {\n      \"@type\": \"Organization\",\n      \"name\": \"Committee for the Reorganization of Building Regulations in Gothenburg\",\n      \"roleName\": \"Chairman\",\n      \"startDate\": null,\n      \"endDate\": null\n    }\n  ],\n  \"sameAs\": [\n    \"https://www.wikidata.org/wiki/Q123456\"\n  ]\n}",
    "structured": {
        "@context": "https://schema.org/",
        "@type": "Person",
        "name": "Mats Harald Edström",
        "givenName": "Mats Harald",
        "familyName": "Edström",
        "birthDate": "1883-11-19",
        "birthPlace": "Falköping, Sweden",
        "deathDate": null,
        "deathPlace": null,
        "nationality": "Swedish",
        "gender": "Male",
        "jobTitle": "Second City Architect",
        "worksFor": {
            "@type": "Organization",
            "name": "Gothenburg"
        },
        "spouse": {
            "@type": "Person",
            "name": "Viola Marie-Louise Svanberg",
            "gender": "Female"
        },
        "children": [
            {
                "@type": "Person",
                "name": "Margot Edström",
                "birthDate": "1915"
            },
            {
                "@type": "Person",
                "name": "Britta Edström",
                "birthDate": "1917"
            }
        ],
        "parent": [
            {
                "@type": "Person",
                "name": "Ernst Reinhold E. Edström",
                "jobTitle": "State inspector"
            },
            {
                "@type": "Person",
                "name": "Gertrud von Mosczins.ky"
            }
        ],
        "education": [
            {
                "@type": "EducationalOrganization",
                "name": "Chalmers University of Technology",
                "location": "Gothenburg",
                "startDate": "1898",
                "endDate": "1906",
                "degree": {
                    "@type": "EducationalDegree",
                    "name": "Master of Engineering"
                }
            },
            {
                "@type": "EducationalOrganization",
                "name": "Royal Academy of Fine Arts",
                "location": "Stockholm",
                "startDate": "1906",
                "endDate": "1912"
            }
        ],
        "memberOf": [
            {
                "@type": "Organization",
                "name": "Technical Society Division for Building Construction Art",
                "roleName": "Secretary",
                "startDate": "1916",
                "endDate": "1917"
            },
            {
                "@type": "Organization",
                "name": "Technical Society Division for Building Construction Art",
                "roleName": "Vice Chairman",
                "startDate": "1918",
                "endDate": null
            },
            {
                "@type": "Organization",
                "name": "Committee for the Reorganization of Building Regulations in Gothenburg",
                "roleName": "Chairman",
                "startDate": null,
                "endDate": null
            }
        ],
        "sameAs": [
            "https://www.wikidata.org/wiki/Q123456"
        ]
    }
}