{
    "original": "Ekman, Carl-Axel, förste flygläkare, flottiljläkare v. Östgöta flygflottilj, Lin|köping, f. 14/1/01 i Liund’ av toMi-uppsyniman Axel E. o. Bothilda Al-fons. G. 34 m. Karin Nyländer. Barn: Bengt f. 42. — Studiex. i Malmö 20, med. kand. i Lund 26 o. med. lic. där 32. E. läk. v. kir. klin. i Lund 28, assist :läk. v. Landskrona las. 32, dito o. tredje und :läk. v. Malmö allm. sjukh. kir. avd. 33, tf. andre und:läk. där 33-34, und :läk. v. Kullbergska las. 34-37, därund. uppr. förordn. s. över-läk., tf. stads- o. sjukhusläk. i Arboga 37, uppr. förordn. s. stadsläk. i Linköp. 38-46, järnv:läk. å linjen Linköp.-Bjärka Säby-Åtvidaberg sed. 44. Marinläk :stip. över stat 29, dito i res. 31-35, v. Mlk 35, marinläk. av 2 gr. 36, flygläk. av 1. gr. 37, förste flygläk. sed. 42, kommend. s. fartygs- o. fäst-n:läk. 30-37. RVO.",
    "translated": "Ekman, Carl-Axel, first flight surgeon, squadron physician at the Östgöta Air Force Wing in Linköping, born January 14, 1901 in Liund, son of inspector Axel E. and Bothilda Al-fons. Married to Karin Nyländer in 1934, with a son named Bengt, born in 1942. He completed his baccalaureate in Malmö in 1920, became a medical candidate at Lund University in 1926, and received his medical license there in 1932. Ekman worked as a medical intern at the surgical clinic in Lund in 1928, assisted as a medical intern at Landskrona Hospital in 1932, worked as a third and acting second medical intern at the surgical department of Malmö's general hospital in 1933, and served as a medical intern at Kullberg Hospital from 1934 to 1937. He was temporarily appointed as chief physician and acting municipal doctor in Arboga in 1937, temporarily appointed as municipal doctor in Linköping from 1938 to 1946, and has served as a railway doctor on the Linköping-Bjärka Säby-Åtvidaberg line since 1944. Ekman was awarded with the Royal Order of the Vasa. He was also a naval medical stipendiate from the state in 1929, served in reserves from 1931 to 1935, became a military physician in 1935, became a flight surgeon in 1937, then became a first flight surgeon in 1942. He served as commander for ship and fortress physicians from 1930 to 1937.",
    "structured_raw": "{\n   \"@context\":\"http://schema.org/\",\n   \"@type\":\"Person\",\n   \"name\":\"Carl-Axel Ekman\",\n   \"birthDate\":\"1901-01-14\",\n   \"birthPlace\":\"Liund\",\n   \"nationality\":\"Swedish\",\n   \"occupation\":[\n      {\n         \"@type\":\"MedicalSpecialty\",\n         \"name\":\"First Flight Surgeon\"\n      },\n      {\n         \"@type\":\"MedicalSpecialty\",\n         \"name\":\"Squadron Physician\"\n      }\n   ],\n   \"spouse\":{\n      \"@type\":\"Person\",\n      \"name\":\"Karin Nyländer\",\n      \"marriageDate\":\"1934\"\n   },\n   \"children\":{\n      \"@type\":\"Person\",\n      \"name\":\"Bengt\",\n      \"birthDate\":\"1942\"\n   },\n   \"education\":[\n      {\n         \"@type\":\"CollegeOrUniversity\",\n         \"name\":\"Malmö\",\n         \"startDate\":\"1920\",\n         \"endDate\":\"N/A\"\n      },\n      {\n         \"@type\":\"CollegeOrUniversity\",\n         \"name\":\"Lund University\",\n         \"startDate\":\"1926\",\n         \"endDate\":\"1932\"\n      }\n   ],\n   \"worksFor\":[\n      {\n         \"@type\":\"Organization\",\n         \"name\":\"Östgöta Air Force Wing\"\n      },\n      {\n         \"@type\":\"Organization\",\n         \"name\":\"Lund University\"\n      },\n      {\n         \"@type\":\"Organization\",\n         \"name\":\"Landskrona Hospital\"\n      },\n      {\n         \"@type\":\"Organization\",\n         \"name\":\"Malmö's General Hospital\"\n      },\n      {\n         \"@type\":\"Organization\",\n         \"name\":\"Kullberg Hospital\"\n      },\n      {\n         \"@type\":\"Organization\",\n         \"name\":\"Arboga Municipality\",\n         \"startDate\":\"1937\",\n         \"endDate\":\"N/A\"\n      },\n      {\n         \"@type\":\"Organization\",\n         \"name\":\"Linköping Municipality\",\n         \"startDate\":\"1938\",\n         \"endDate\":\"1946\"\n      },\n      {\n         \"@type\":\"Organization\",\n         \"name\":\"Linköping-Bjärka Säby-Åtvidaberg Railway\",\n         \"startDate\":\"1944\",\n         \"endDate\":\"N/A\"\n      }\n   ],\n   \"award\":{\n      \"@type\":\"Order\",\n      \"name\":\"Royal Order of the Vasa\"\n   },\n   \"affiliation\":[\n      {\n         \"@type\":\"Organization\",\n         \"name\":\"Swedish Navy\",\n         \"affiliationStartDate\":\"1929\",\n         \"affiliationEndDate\":\"N/A\",\n         \"memberOf\":[\n            {\n               \"@type\":\"Organization\",\n               \"name\":\"Reserves\"\n            }\n         ]\n      },\n      {\n         \"@type\":\"Organization\",\n         \"name\":\"Swedish Military\",\n         \"affiliationStartDate\":\"1935\",\n         \"affiliationEndDate\":\"N/A\"\n      }\n   ]\n}",
    "structured": {
        "@context": "http://schema.org/",
        "@type": "Person",
        "name": "Carl-Axel Ekman",
        "birthDate": "1901-01-14",
        "birthPlace": "Liund",
        "nationality": "Swedish",
        "occupation": [
            {
                "@type": "MedicalSpecialty",
                "name": "First Flight Surgeon"
            },
            {
                "@type": "MedicalSpecialty",
                "name": "Squadron Physician"
            }
        ],
        "spouse": {
            "@type": "Person",
            "name": "Karin Nyländer",
            "marriageDate": "1934"
        },
        "children": {
            "@type": "Person",
            "name": "Bengt",
            "birthDate": "1942"
        },
        "education": [
            {
                "@type": "CollegeOrUniversity",
                "name": "Malmö",
                "startDate": "1920",
                "endDate": "N/A"
            },
            {
                "@type": "CollegeOrUniversity",
                "name": "Lund University",
                "startDate": "1926",
                "endDate": "1932"
            }
        ],
        "worksFor": [
            {
                "@type": "Organization",
                "name": "Östgöta Air Force Wing"
            },
            {
                "@type": "Organization",
                "name": "Lund University"
            },
            {
                "@type": "Organization",
                "name": "Landskrona Hospital"
            },
            {
                "@type": "Organization",
                "name": "Malmö's General Hospital"
            },
            {
                "@type": "Organization",
                "name": "Kullberg Hospital"
            },
            {
                "@type": "Organization",
                "name": "Arboga Municipality",
                "startDate": "1937",
                "endDate": "N/A"
            },
            {
                "@type": "Organization",
                "name": "Linköping Municipality",
                "startDate": "1938",
                "endDate": "1946"
            },
            {
                "@type": "Organization",
                "name": "Linköping-Bjärka Säby-Åtvidaberg Railway",
                "startDate": "1944",
                "endDate": "N/A"
            }
        ],
        "award": {
            "@type": "Order",
            "name": "Royal Order of the Vasa"
        },
        "affiliation": [
            {
                "@type": "Organization",
                "name": "Swedish Navy",
                "affiliationStartDate": "1929",
                "affiliationEndDate": "N/A",
                "memberOf": [
                    {
                        "@type": "Organization",
                        "name": "Reserves"
                    }
                ]
            },
            {
                "@type": "Organization",
                "name": "Swedish Military",
                "affiliationStartDate": "1935",
                "affiliationEndDate": "N/A"
            }
        ]
    }
}