{
    "original": "Leissner, Sven Herman, överläkare, Göteborg, f. 27/12/04 i Djursholm av v. här :hövd. Engelbrekt L. o. Anna Andersson. G. 31 m. Malin Güettler. Barn: Per f. 33, Karl-Henrik 36, Anita 38, Inga 39, Sven 41, d. 44, Tom 43, Marianne 44, Herman 46. — Stud:ex. i Djursholm 22, med. kand. v. Karol. inst. 25 o. med. lic. där 30. E. aman. v. Allm. BB i Sthlm 29, und:läk. v. Seraf :las. med. polikHn. 30-31, v. Sab-batsb. sjukh. obstetr. avd. 31-32, e. und:läk. v. Radiumhemm. 32-33, kort. överläk :förordn. v. gynekol., obstetr. o. radiolog. sjukhusavd. 33^ o. 34, assist, v. Östersunds las. kir. avd. samt tf. und :läk. där o. v. Halmstads las. 34, andre und:läk. v. Mariestads las. 35, förste dito 36-37, aman. v. Lunds las. obstetr. o. gynekol. klin. 38, e. läk. där 39, und :läk. 40, bitr. överläk. 40-42, tillika bitr. lär. i ob’stetr. o. gyne-kologi v. Lunds univ., kort. prof :för-ordn. s. å., und :läk. v. Radiumhemm. gynekol. avd. 42, tf. överläk. v. Sahlgr. sjukh. jub:klin. gynekol. avd. 43, ord. överläk. sed. 44. Skr.: ett antal smärre arb. inom gynekologi, obstetrik o. radiologi.",
    "translated": "Leissner, Sven Herman, senior physician, Gothenburg, b. 27/12/04 in Djursholm, son of cavalry commander Engelbrekt L. and Anna Andersson. Married in 1931 to Malin Güettler. Children: Per b. 1933, Karl-Henrik b. 1936, Anita b. 1938, Inga b. 1939, Sven b. 1941, d. 1944, Tom b. 1943, Marianne b. 1944, Herman b. 1946. Educational background: Graduated from Djursholm High School in 1922, received Bachelor of Medicine degree from Karolinska Institute in 1925, and obtained medical license in 1930. Work experience: Intern at Allmänna barnbördshuset in Stockholm in 1929, assistant physician at Serafimerlasarettet's medical polyclinic from 1930 to 1931, at Sabbatsbergs sjukhus obstetrics department from 1931 to 1932, at Radiumhemmet from 1932 to 1933, short-term senior physician and consultant at gynecology, obstetrics, and radiology hospital department in 1933 and 1934, assistant at Östersunds lasarett surgical department, temporary assistant physician there and at Halmstads lasarett in 1934, second assistant physician at Mariestads lasarett in 1935, first assistant physician from 1936 to 1937, intern at Lund lasarett obstetrics and gynecology clinic in 1938, employed doctor there in 1939, assistant physician in 1940, deputy senior physician from 1940 to 1942, also assistant professor in obstetrics and gynecology at Lund University, appointed temporary professor in the same year, assistant physician at Radiumhemmet gynecology department in 1942, temporary senior physician at Sahlgr. sjukhem's maternity clinic gynecology department in 1943, regular senior physician since 1944. Publications: Several minor works in the field of gynecology, obstetrics, and radiology.",
    "structured_raw": "{\n  \"@context\": \"https://schema.org\",\n  \"@type\": \"Person\",\n  \"name\": \"Sven Herman Leissner\",\n  \"birthDate\": \"1904-12-27\",\n  \"birthPlace\": \"Djursholm\",\n  \"nationality\": \"Swedish\",\n  \"description\": \"Senior physician in Gothenburg\",\n  \"parents\": [\n    {\n      \"@type\": \"Person\",\n      \"name\": \"Engelbrekt L.\"\n    },\n    {\n      \"@type\": \"Person\",\n      \"name\": \"Anna Andersson\"\n    }\n  ],\n  \"spouse\": {\n    \"@type\": \"Person\",\n    \"name\": \"Malin Güettler\",\n    \"marriageDate\": \"1931\"\n  },\n  \"children\": [\n    {\n      \"@type\": \"Person\",\n      \"name\": \"Per\",\n      \"birthDate\": \"1933\"\n    },\n    {\n      \"@type\": \"Person\",\n      \"name\": \"Karl-Henrik\",\n      \"birthDate\": \"1936\"\n    },\n    {\n      \"@type\": \"Person\",\n      \"name\": \"Anita\",\n      \"birthDate\": \"1938\"\n    },\n    {\n      \"@type\": \"Person\",\n      \"name\": \"Inga\",\n      \"birthDate\": \"1939\"\n    },\n    {\n      \"@type\": \"Person\",\n      \"name\": \"Sven\",\n      \"birthDate\": \"1941\",\n      \"deathDate\": \"1944\"\n    },\n    {\n      \"@type\": \"Person\",\n      \"name\": \"Tom\",\n      \"birthDate\": \"1943\"\n    },\n    {\n      \"@type\": \"Person\",\n      \"name\": \"Marianne\",\n      \"birthDate\": \"1944\"\n    },\n    {\n      \"@type\": \"Person\",\n      \"name\": \"Herman\",\n      \"birthDate\": \"1946\"\n    }\n  ],\n  \"alumniOf\": [\n    {\n      \"@type\": \"EducationalOrganization\",\n      \"name\": \"Djursholm High School\",\n      \"endDate\": \"1922\"\n    },\n    {\n      \"@type\": \"EducationalOrganization\",\n      \"name\": \"Karolinska Institute\",\n      \"startDate\": \"1922\",\n      \"endDate\": \"1925\"\n    }\n  ],\n  \"worksFor\": {\n    \"@type\": \"Organization\",\n    \"name\": \"Gothenburg\",\n    \"jobTitle\": \"Senior Physician\"\n  },\n  \"memberOf\": [\n    {\n      \"@type\": \"Organization\",\n      \"name\": \"Allmänna barnbördshuset\"\n    },\n    {\n      \"@type\": \"Organization\",\n      \"name\": \"Serafimerlasarettet\"\n    },\n    {\n      \"@type\": \"Organization\",\n      \"name\": \"Sabbatsbergs sjukhus\"\n    },\n    {\n      \"@type\": \"Organization\",\n      \"name\": \"Radiumhemmet\"\n    },\n    {\n      \"@type\": \"Organization\",\n      \"name\": \"Östersunds lasarett\"\n    },\n    {\n      \"@type\": \"Organization\",\n      \"name\": \"Halmstads lasarett\"\n    },\n    {\n      \"@type\": \"Organization\",\n      \"name\": \"Mariestads lasarett\"\n    },\n    {\n      \"@type\": \"Organization\",\n      \"name\": \"Lund lasarett\"\n    },\n    {\n      \"@type\": \"Organization\",\n      \"name\": \"Lund University\"\n    },\n    {\n      \"@type\": \"Organization\",\n      \"name\": \"Sahlgr. sjukhem\"\n    }\n  ],\n  \"knowsAbout\": [\n    \"Gynecology\",\n    \"Obstetrics\",\n    \"Radiology\"\n  ]\n}",
    "structured": {
        "@context": "https://schema.org",
        "@type": "Person",
        "name": "Sven Herman Leissner",
        "birthDate": "1904-12-27",
        "birthPlace": "Djursholm",
        "nationality": "Swedish",
        "description": "Senior physician in Gothenburg",
        "parents": [
            {
                "@type": "Person",
                "name": "Engelbrekt L."
            },
            {
                "@type": "Person",
                "name": "Anna Andersson"
            }
        ],
        "spouse": {
            "@type": "Person",
            "name": "Malin Güettler",
            "marriageDate": "1931"
        },
        "children": [
            {
                "@type": "Person",
                "name": "Per",
                "birthDate": "1933"
            },
            {
                "@type": "Person",
                "name": "Karl-Henrik",
                "birthDate": "1936"
            },
            {
                "@type": "Person",
                "name": "Anita",
                "birthDate": "1938"
            },
            {
                "@type": "Person",
                "name": "Inga",
                "birthDate": "1939"
            },
            {
                "@type": "Person",
                "name": "Sven",
                "birthDate": "1941",
                "deathDate": "1944"
            },
            {
                "@type": "Person",
                "name": "Tom",
                "birthDate": "1943"
            },
            {
                "@type": "Person",
                "name": "Marianne",
                "birthDate": "1944"
            },
            {
                "@type": "Person",
                "name": "Herman",
                "birthDate": "1946"
            }
        ],
        "alumniOf": [
            {
                "@type": "EducationalOrganization",
                "name": "Djursholm High School",
                "endDate": "1922"
            },
            {
                "@type": "EducationalOrganization",
                "name": "Karolinska Institute",
                "startDate": "1922",
                "endDate": "1925"
            }
        ],
        "worksFor": {
            "@type": "Organization",
            "name": "Gothenburg",
            "jobTitle": "Senior Physician"
        },
        "memberOf": [
            {
                "@type": "Organization",
                "name": "Allmänna barnbördshuset"
            },
            {
                "@type": "Organization",
                "name": "Serafimerlasarettet"
            },
            {
                "@type": "Organization",
                "name": "Sabbatsbergs sjukhus"
            },
            {
                "@type": "Organization",
                "name": "Radiumhemmet"
            },
            {
                "@type": "Organization",
                "name": "Östersunds lasarett"
            },
            {
                "@type": "Organization",
                "name": "Halmstads lasarett"
            },
            {
                "@type": "Organization",
                "name": "Mariestads lasarett"
            },
            {
                "@type": "Organization",
                "name": "Lund lasarett"
            },
            {
                "@type": "Organization",
                "name": "Lund University"
            },
            {
                "@type": "Organization",
                "name": "Sahlgr. sjukhem"
            }
        ],
        "knowsAbout": [
            "Gynecology",
            "Obstetrics",
            "Radiology"
        ]
    }
}