{
    "original": "Ågren, Per Gustaf, direktör, kapten, Göteborg, f. 20/6/98 i Gbg av grossh. Axel Hugo Å. o. Louise Schmidt. G. 28 m. Märtha Winqwist. Barn: Louise f. 31, Birgitta 33, Kristina 35, Ann-Charlotte 39, Axel Hugo 42. — Stud:-ex. v. Gbgs h. real 18, of;f :ex. 20, AIHIS allm. art:kurs 23, DHG 31. Fänrik v. Göta art:reg. 20, löjtn. 24, kapten i res. 35. Anst. v. Axel H. Ågren A-B i Gbg s’ed. 31, dir. där sed. 34. Styr:led. i Gbgs Sand A-B, i Sodafabr. Försäljn. A-B, i Gbgs spar^b., i Ränte- o. Kap :-försäkr :anst. i Gbg, ordf. i Gbgs o. Boh. 1. skytteför&lt;b. fr. 38, Skytteföi^b. ord. repr. i Bef :ut!b :förb. fr. 38, led. av en mängd komm. o. ndr inom skytterör., ledare f. SM på armégev. i Gbg 38, f. Gbgs o. Boh. 1. skytteförib. jub:tävl. i Gbg 43, v. ordf. i Res:off :sällsk. i Gbg 37-45, ordlf. sed. 46, styr:led. i Sv. arméns o. flygv. res :off :förb. sed. 46. Holbbies: skytte, ridsp. RVO, Skytteförb. öv:-styr. ftjSM, Gbgs o. Boh. 1. skytteförb. ftjGM, RFinlLolkl 47, FMM f. hum. verks., Finl. res :off :förb. Hed-Gt, De Vernepl. off. foren. i Oslo Hed-Gt.",
    "translated": "Ågren, Per Gustaf, director, captain, Gothenburg, b. 20/6/98 in Gothenburg to wholesale merchant Axel Hugo Å. and Louise Schmidt. Married on the 28th to Märtha Winqwist. Children: Louise b. 31, Birgitta b. 33, Kristina b. 35, Ann-Charlotte b. 39, Axel Hugo b. 42. - Studied at Gothenburg Higher Real School, graduated in 1918; Officer's Exam in 1920; General Art Course at AIHIS in 1923; DHG (Society for the Dissemination of General and Practical Knowledge) in 1931. Ensign in the Gotha Artillery Regiment in 1920, lieutenant in 1924, captain in the reserves in 1935. Employed by Axel H. Ågren A-B in Gothenburg since 1931, director since 1934. Board member of Gothenburg Sand A-B, of Soda Factory Sales A-B, of Gothenburg Savings Bank, of Interest and Capital Insurance Institution in Gothenburg. Chairman of Gothenburg and Bohus County 1st Shooting Association since 1938; Ordinary representative in the National Shooting Association since 1938. Member of various committees and associations within the shooting field. Leader of the Swedish Championship on army rifle in Gothenburg in 1938, organizer of the Gothenburg and Bohus County 1st Shooting Association Jubilee Competition in Gothenburg in 1943. Vice chairman of the Reserve Officers' Society in Gothenburg from 1937-1945, chairman since 1946. Board member of the Swedish Army and Air Force Reserve Officers' Association since 1946. Hobbies: shooting, equestrian sports. Holder of the Royal Order of Vasa, Chief of the Shooting Association Honorary Staff, First-Class Medal of Merit in Gold of Gothenburg and Bohus County 1st Shooting Association, Commander 4th Class of the Order of the White Rose of Finland, Member of the Society for the Promotion of Humane Actions, Honorary Member of the Finnish Reserve Officers' Association.",
    "structured_raw": "{\n  \"@context\": \"https://schema.org\",\n  \"@type\": \"Person\",\n  \"name\": \"Per Gustaf Ågren\",\n  \"birthDate\": \"1898-06-20\",\n  \"birthPlace\": \"Gothenburg, Sweden\",\n  \"nationality\": \"Swedish\",\n  \"occupation\": [\n    \"Director\",\n    \"Captain\"\n  ],\n  \"address\": \"Gothenburg\",\n  \"parents\": [\n    {\n      \"name\": \"Axel Hugo Ågren\",\n      \"relationship\": \"father\"\n    },\n    {\n      \"name\": \"Louise Schmidt\",\n      \"relationship\": \"mother\"\n    }\n  ],\n  \"spouse\": {\n    \"name\": \"Märtha Winqwist\",\n    \"marriageDate\": \"1928-04-28\"\n  },\n  \"children\": [\n    {\n      \"name\": \"Louise\",\n      \"birthDate\": \"1931\"\n    },\n    {\n      \"name\": \"Birgitta\",\n      \"birthDate\": \"1933\"\n    },\n    {\n      \"name\": \"Kristina\",\n      \"birthDate\": \"1935\"\n    },\n    {\n      \"name\": \"Ann-Charlotte\",\n      \"birthDate\": \"1939\"\n    },\n    {\n      \"name\": \"Axel Hugo\",\n      \"birthDate\": \"1942\"\n    }\n  ],\n  \"education\": [\n    {\n      \"name\": \"Gothenburg Higher Real School\",\n      \"typeOfEducation\": \"Secondary Education\",\n      \"yearGraduated\": 1918\n    },\n    {\n      \"name\": \"Officer's Exam\",\n      \"typeOfEducation\": \"Military Education\",\n      \"yearGraduated\": 1920\n    },\n    {\n      \"name\": \"General Art Course at AIHIS\",\n      \"typeOfEducation\": \"Art Education\",\n      \"yearGraduated\": 1923\n    },\n    {\n      \"name\": \"DHG (Society for the Dissemination of General and Practical Knowledge)\",\n      \"typeOfEducation\": \"General Education\",\n      \"yearGraduated\": 1931\n    }\n  ],\n  \"militaryService\": [\n    {\n      \"name\": \"Gotha Artillery Regiment\",\n      \"rank\": \"Ensign\",\n      \"startDate\": \"1920\",\n      \"endDate\": \"1924\"\n    },\n    {\n      \"rank\": \"Lieutenant\",\n      \"startDate\": \"1924\",\n      \"endDate\": \"1935\"\n    }\n  ],\n  \"employment\": [\n    {\n      \"name\": \"Axel H. Ågren A-B\",\n      \"position\": \"Employee\",\n      \"startDate\": \"1931\",\n      \"endDate\": \"1934\"\n    },\n    {\n      \"name\": \"Axel H. Ågren A-B\",\n      \"position\": \"Director\",\n      \"startDate\": \"1934\"\n    }\n  ],\n  \"boardMember\": [\n    {\n      \"name\": \"Gothenburg Sand A-B\"\n    },\n    {\n      \"name\": \"Soda Factory Sales A-B\"\n    },\n    {\n      \"name\": \"Gothenburg Savings Bank\"\n    },\n    {\n      \"name\": \"Interest and Capital Insurance Institution in Gothenburg\"\n    }\n  ],\n  \"chairman\": [\n    {\n      \"name\": \"Gothenburg and Bohus County 1st Shooting Association\",\n      \"startDate\": \"1938\"\n    }\n  ],\n  \"associationMembership\": [\n    {\n      \"name\": \"National Shooting Association\",\n      \"startDate\": \"1938\"\n    },\n    {\n      \"name\": \"Reserve Officers' Society in Gothenburg\",\n      \"position\": \"Vice Chairman\",\n      \"startDate\": \"1937\",\n      \"endDate\": \"1945\"\n    },\n    {\n      \"name\": \"Reserve Officers' Society in Gothenburg\",\n      \"position\": \"Chairman\",\n      \"startDate\": \"1946\"\n    },\n    {\n      \"name\": \"Swedish Army and Air Force Reserve Officers' Association\",\n      \"startDate\": \"1946\"\n    }\n  ],\n  \"hobbies\": [\n    \"Shooting\",\n    \"Equestrian sports\"\n  ],\n  \"honors\": [\n    {\n      \"name\": \"Royal Order of Vasa\"\n    },\n    {\n      \"name\": \"Chief of the Shooting Association Honorary Staff\",\n      \"honoraryClass\": \"First-Class\"\n    },\n    {\n      \"name\": \"Medal of Merit in Gold of Gothenburg and Bohus County 1st Shooting Association\",\n      \"honoraryClass\": \"First-Class\"\n    },\n    {\n      \"name\": \"Order of the White Rose of Finland\",\n      \"rank\": \"Commander 4th Class\"\n    },\n    {\n      \"name\": \"Society for the Promotion of Humane Actions\",\n      \"honoraryMember\": true\n    },\n    {\n      \"name\": \"Finnish Reserve Officers' Association\",\n      \"honoraryMember\": true\n    }\n  ]\n}",
    "structured": {
        "@context": "https://schema.org",
        "@type": "Person",
        "name": "Per Gustaf Ågren",
        "birthDate": "1898-06-20",
        "birthPlace": "Gothenburg, Sweden",
        "nationality": "Swedish",
        "occupation": [
            "Director",
            "Captain"
        ],
        "address": "Gothenburg",
        "parents": [
            {
                "name": "Axel Hugo Ågren",
                "relationship": "father"
            },
            {
                "name": "Louise Schmidt",
                "relationship": "mother"
            }
        ],
        "spouse": {
            "name": "Märtha Winqwist",
            "marriageDate": "1928-04-28"
        },
        "children": [
            {
                "name": "Louise",
                "birthDate": "1931"
            },
            {
                "name": "Birgitta",
                "birthDate": "1933"
            },
            {
                "name": "Kristina",
                "birthDate": "1935"
            },
            {
                "name": "Ann-Charlotte",
                "birthDate": "1939"
            },
            {
                "name": "Axel Hugo",
                "birthDate": "1942"
            }
        ],
        "education": [
            {
                "name": "Gothenburg Higher Real School",
                "typeOfEducation": "Secondary Education",
                "yearGraduated": 1918
            },
            {
                "name": "Officer's Exam",
                "typeOfEducation": "Military Education",
                "yearGraduated": 1920
            },
            {
                "name": "General Art Course at AIHIS",
                "typeOfEducation": "Art Education",
                "yearGraduated": 1923
            },
            {
                "name": "DHG (Society for the Dissemination of General and Practical Knowledge)",
                "typeOfEducation": "General Education",
                "yearGraduated": 1931
            }
        ],
        "militaryService": [
            {
                "name": "Gotha Artillery Regiment",
                "rank": "Ensign",
                "startDate": "1920",
                "endDate": "1924"
            },
            {
                "rank": "Lieutenant",
                "startDate": "1924",
                "endDate": "1935"
            }
        ],
        "employment": [
            {
                "name": "Axel H. Ågren A-B",
                "position": "Employee",
                "startDate": "1931",
                "endDate": "1934"
            },
            {
                "name": "Axel H. Ågren A-B",
                "position": "Director",
                "startDate": "1934"
            }
        ],
        "boardMember": [
            {
                "name": "Gothenburg Sand A-B"
            },
            {
                "name": "Soda Factory Sales A-B"
            },
            {
                "name": "Gothenburg Savings Bank"
            },
            {
                "name": "Interest and Capital Insurance Institution in Gothenburg"
            }
        ],
        "chairman": [
            {
                "name": "Gothenburg and Bohus County 1st Shooting Association",
                "startDate": "1938"
            }
        ],
        "associationMembership": [
            {
                "name": "National Shooting Association",
                "startDate": "1938"
            },
            {
                "name": "Reserve Officers' Society in Gothenburg",
                "position": "Vice Chairman",
                "startDate": "1937",
                "endDate": "1945"
            },
            {
                "name": "Reserve Officers' Society in Gothenburg",
                "position": "Chairman",
                "startDate": "1946"
            },
            {
                "name": "Swedish Army and Air Force Reserve Officers' Association",
                "startDate": "1946"
            }
        ],
        "hobbies": [
            "Shooting",
            "Equestrian sports"
        ],
        "honors": [
            {
                "name": "Royal Order of Vasa"
            },
            {
                "name": "Chief of the Shooting Association Honorary Staff",
                "honoraryClass": "First-Class"
            },
            {
                "name": "Medal of Merit in Gold of Gothenburg and Bohus County 1st Shooting Association",
                "honoraryClass": "First-Class"
            },
            {
                "name": "Order of the White Rose of Finland",
                "rank": "Commander 4th Class"
            },
            {
                "name": "Society for the Promotion of Humane Actions",
                "honoraryMember": true
            },
            {
                "name": "Finnish Reserve Officers' Association",
                "honoraryMember": true
            }
        ]
    }
}