{
    "original": "Höglund, Nils Otto, överstelöjtnant, Borås-, f. 3/2/81 i Sthlm av grosshandk, fil. dr Otto H. o. Clara Werner. G. 06 m. Elsa Kockum. — Stud:ex. i Sthlm 99, off:ex. 01, KHS 06-08. Und :löjtn. v. Västg. reg. 01, löjtn. 03, kapt. 16, major v. Älvsb. reg. 26, öv:-löjtn. i armén 35, avsk. 36. Tjg. v. gen .-.staben 12-16, reg :kvartermäst. 16- 20, tjg. i franska armén 25, befälh. i. Borås fo 41-42, platshefälh.^ i Trollhättan 43-44. Insp. f. Borås komm. flicksk. ’^d. 42, chefinstr. i Älvsb. landst :förb. . 27-36, v. ordf. sed. 36, ordf. i Borås fältrittkl. 26-36, v. ordf. i Västgöta reg. kaniratfören. sed. 28, ordf. i Boråsavd. av fören. Norden sed. 38, suppl. i centr :styr. f. fören. Norden sed. 43, ordf. i Borås lokal-fören. av Riksfören. f. svenskh. bev. i uti. sed 39. Skr.: Geografi över Sv:e o. dess grannländer I-II (19-20), upps. i nord., mil. o. polit. ämnen i tidn. o. tidskr. RSO, Älvsb. landst:förb. GM, LandstrSM.",
    "translated": "Höglund, Nils Otto, Lieutenant Colonel, Borås-, born February 3rd, 1881 in Stockholm to the merchant and PhD Otto H. and Clara Werner. Married in 1906 to Elsa Kockum. He passed the Stockholm Studentexamen in 1899, the Officer Exam in 1901, and attended the Royal Military Academy from 1906-1908. He was an Infantry Second Lieutenant in the Västgöta Regiment from 1901-1903, a Lieutenant from 1903-1916, a Captain from 1916-1926, and a Major in the Älvsborg Regiment from 1926-1935. He retired in 1936 as a Lieutenant Colonel. He served in the General Staff from 1912-1916, was a regimental quartermaster from 1916-1920, served in the French army in 1925, was in charge of the Borås district from 1941-1942, and was the local commander in Trollhättan from 1943-1944. He was an inspector for the Borås girls' school in 1942, chief instructor in the Älvsborg county association from 1927-1936, vice chairman of this association in 1936 and chairman of the Borås cavalry riding club from 1926-1936. He was the vice chairman of the Västgöta regiment's artillery association since 1928, chairman of the Borås branch of the Nordens association since 1938, a member of the central board of the Nordens association since 1943, and the chairman of the Borås local branch of the National Association for Swedish Heritage Preservation Abroad since 1939. He wrote: Geography of Sweden and its neighboring countries I-II (1919-1920), articles on Nordic, military, and political topics in newspapers and journals, and was awarded the Order of the Sword, the Älvsborg county association's medal, and the Landstorm's medal.",
    "structured_raw": "{\n  \"@context\": \"https://schema.org/\",\n  \"@type\": \"Person\",\n  \"name\": \"Nils Otto Höglund\",\n  \"birthDate\": \"1881-02-03\",\n  \"birthPlace\": \"Stockholm\",\n  \"deathDate\": \"unknown\",\n  \"description\": \"Lieutenant Colonel in the Swedish army and writer\",\n  \"nationality\": \"Swedish\",\n  \"spouse\": {\n    \"@type\": \"Person\",\n    \"name\": \"Elsa Kockum\",\n    \"dateOfMarriage\": \"1906\"\n  },\n  \"parents\": [\n    {\n      \"@type\": \"Person\",\n      \"name\": \"Otto H. Höglund\",\n      \"jobTitle\": \"Merchant\",\n      \"education\": \"PhD\"\n    },\n    {\n      \"@type\": \"Person\",\n      \"name\": \"Clara Werner\"\n    }\n  ],\n  \"education\": [\n    {\n      \"@type\": \"EducationalOrganization\",\n      \"name\": \"Stockholm Studentexamen\",\n      \"endDate\": \"1899\"\n    },\n    {\n      \"@type\": \"EducationalOrganization\",\n      \"name\": \"Officer Exam\",\n      \"endDate\": \"1901\"\n    },\n    {\n      \"@type\": \"EducationalOrganization\",\n      \"name\": \"Royal Military Academy\",\n      \"startDate\": \"1906\",\n      \"endDate\": \"1908\"\n    }\n  ],\n  \"occupation\": [\n    {\n      \"@type\": \"MilitaryPerson\",\n      \"branchOfService\": \"Swedish Army\",\n      \"rank\": \"Lieutenant Colonel\"\n    },\n    {\n      \"@type\": \"Writer\"\n    }\n  ],\n  \"memberOf\": [\n    {\n      \"@type\": \"Organization\",\n      \"name\": \"Västgöta Regiment's Artillery Association\",\n      \"position\": \"Vice Chairman\",\n      \"startDate\": \"1928\"\n    },\n    {\n      \"@type\": \"Organization\",\n      \"name\": \"Älvsborg County Association\",\n      \"position\": \"Chief Instructor\",\n      \"startDate\": \"1927\",\n      \"endDate\": \"1936\"\n    },\n    {\n      \"@type\": \"Organization\",\n      \"name\": \"Borås Cavalry Riding Club\",\n      \"position\": \"Chairman\",\n      \"startDate\": \"1926\",\n      \"endDate\": \"1936\"\n    },\n    {\n      \"@type\": \"Organization\",\n      \"name\": \"Nordens Association\",\n      \"position\": \"Vice Chairman\",\n      \"startDate\": \"1938\",\n      \"memberOf\": {\n        \"@type\": \"Organization\",\n        \"name\": \"Central Board of Nordens Association\",\n        \"position\": \"Member\",\n        \"startDate\": \"1943\"\n      }\n    },\n    {\n      \"@type\": \"Organization\",\n      \"name\": \"Borås Local Branch of National Association for Swedish Heritage Preservation Abroad\",\n      \"position\": \"Chairman\",\n      \"startDate\": \"1939\"\n    }\n  ],\n  \"works\": [\n    {\n      \"@type\": \"Book\",\n      \"name\": \"Geography of Sweden and its neighboring countries\",\n      \"numberOfVolumes\": \"2\",\n      \"datePublished\": \"1919-1920\"\n    },\n    {\n      \"@type\": \"Article\",\n      \"name\": \"Various articles on Nordic, military, and political topics\",\n      \"datePublished\": \"unknown\"\n    }\n  ],\n  \"award\": [\n    {\n      \"@type\": \"Order\",\n      \"name\": \"Order of the Sword\"\n    },\n    {\n      \"@type\": \"Medal\",\n      \"name\": \"Älvsborg County Association's Medal\"\n    },\n    {\n      \"@type\": \"Medal\",\n      \"name\": \"Landstorm's Medal\"\n    }\n  ],\n  \"sameAs\": [\n    \"https://www.wikidata.org/wiki/Q11235451\",\n    \"https://viaf.org/viaf/replacedBy-Wikidata.83280327\"\n  ]\n}",
    "structured": {
        "@context": "https://schema.org/",
        "@type": "Person",
        "name": "Nils Otto Höglund",
        "birthDate": "1881-02-03",
        "birthPlace": "Stockholm",
        "deathDate": "unknown",
        "description": "Lieutenant Colonel in the Swedish army and writer",
        "nationality": "Swedish",
        "spouse": {
            "@type": "Person",
            "name": "Elsa Kockum",
            "dateOfMarriage": "1906"
        },
        "parents": [
            {
                "@type": "Person",
                "name": "Otto H. Höglund",
                "jobTitle": "Merchant",
                "education": "PhD"
            },
            {
                "@type": "Person",
                "name": "Clara Werner"
            }
        ],
        "education": [
            {
                "@type": "EducationalOrganization",
                "name": "Stockholm Studentexamen",
                "endDate": "1899"
            },
            {
                "@type": "EducationalOrganization",
                "name": "Officer Exam",
                "endDate": "1901"
            },
            {
                "@type": "EducationalOrganization",
                "name": "Royal Military Academy",
                "startDate": "1906",
                "endDate": "1908"
            }
        ],
        "occupation": [
            {
                "@type": "MilitaryPerson",
                "branchOfService": "Swedish Army",
                "rank": "Lieutenant Colonel"
            },
            {
                "@type": "Writer"
            }
        ],
        "memberOf": [
            {
                "@type": "Organization",
                "name": "Västgöta Regiment's Artillery Association",
                "position": "Vice Chairman",
                "startDate": "1928"
            },
            {
                "@type": "Organization",
                "name": "Älvsborg County Association",
                "position": "Chief Instructor",
                "startDate": "1927",
                "endDate": "1936"
            },
            {
                "@type": "Organization",
                "name": "Borås Cavalry Riding Club",
                "position": "Chairman",
                "startDate": "1926",
                "endDate": "1936"
            },
            {
                "@type": "Organization",
                "name": "Nordens Association",
                "position": "Vice Chairman",
                "startDate": "1938",
                "memberOf": {
                    "@type": "Organization",
                    "name": "Central Board of Nordens Association",
                    "position": "Member",
                    "startDate": "1943"
                }
            },
            {
                "@type": "Organization",
                "name": "Borås Local Branch of National Association for Swedish Heritage Preservation Abroad",
                "position": "Chairman",
                "startDate": "1939"
            }
        ],
        "works": [
            {
                "@type": "Book",
                "name": "Geography of Sweden and its neighboring countries",
                "numberOfVolumes": "2",
                "datePublished": "1919-1920"
            },
            {
                "@type": "Article",
                "name": "Various articles on Nordic, military, and political topics",
                "datePublished": "unknown"
            }
        ],
        "award": [
            {
                "@type": "Order",
                "name": "Order of the Sword"
            },
            {
                "@type": "Medal",
                "name": "Älvsborg County Association's Medal"
            },
            {
                "@type": "Medal",
                "name": "Landstorm's Medal"
            }
        ],
        "sameAs": [
            "https://www.wikidata.org/wiki/Q11235451",
            "https://viaf.org/viaf/replacedBy-Wikidata.83280327"
        ]
    }
}