{
    "original": "Johansson, Folke Ludvig \" Hemming, civiljägmästare, direktör, Göteborg, f. 5/2/99 i Sthlm av dir. H. J. J. o. Olga Sellman. — Studiex. i Sthlm 18, ex. v. skogshögsk. jägmäst:kurs 24. Red:-■sekr. i Sv. -skogsv rfören. 26-40, sekr. h. centr:rådet f. ’sikogsv :.s’tyr. förbi 38-41, h. Sv. skogsv.-fören. 40-47, byråchef i skogsstyr. 41-47, verkst. dir. i S’kogS’sälls’k. i Gbg sed. 47. Sekr. h. 31 års iSkogs’sakk. 31, h. skogsbrand- komm. 35, h. 36 års skogsutredn. 36 samt h. skogsveckan sed. 40, ’särsk. .sakk. h. skogslagutredn. 42, led. av 44 års skogsv istyr :utredn. 44, ordf. i jordbr :komm. f. Sthlm’s län o. stad 46, • led. av styr. f. stat. skogsmäst :sk. 44, ordf. i 46 års sakk. f. utb. av lantmiät. o. lantbriing., rapportör o. deleg. v. ett flert. int. konf. Red. o. ansv. utg. av Tidskr. Skogen 41-47 o. Sv. Skogs-v:fören. Tidskr. 43-47. RNO.",
    "translated": "Johansson, Folke Ludvig \"Hemming\", civil forest officer, director, from Gothenburg, born on February 5th, 1899 in Stockholm to director H.J.J. and Olga Sellman. He passed his exams in Stockholm in 1918 and completed the forestry course in the School of Agriculture in 1924. He served as secretary in the Swedish Forestry Association from 1926 to 1940, secretary in the central council for forestry management from 1938 to 1941, was involved with the Swedish Forestry Association from 1940 to 1947, and was the chief of the forestry control bureau from 1941 to 1947. He became the managing director of the Skogsällskapet (Swedish Forest Society) in Gothenburg in 1947. He was the secretary of the 31-year-old Skogsägarkår (Forest Owners Association) in 1931, the forest fire commission in 1935, the 36-year-old forest investigation in 1936, and the Skogsveckan (Forest Week) from 1940 to 1947. In 1942, he was a special adviser for the forestry law investigation, and was a member of the forestry board investigation of 1944. In 1946, he was the chairman of the agricultural committee for Stockholm's county and city, and a member of the board for the State Forestry Masters School in 1944. He was the chairman of the 1946 committee for education of land surveying and agriculture, member of the report and delegate at several international conferences. He was the editor and responsible publisher for the forestry magazines Tidskriften Skogen from 1941 to 1947 and Svenska Skogsvårdsföreningens (Swedish Forestry Association) Tidskrift from 1943 to 1947. He was awarded the RNO award.",
    "structured_raw": "{\n   \"@context\": \"https://schema.org/\",\n   \"@type\": \"Person\",\n   \"name\": \"Folke Ludvig Johansson\",\n   \"givenName\": \"Folke Ludvig\",\n   \"familyName\": \"Johansson\",\n   \"additionalName\": \"Hemming\",\n   \"birthDate\": \"1899-02-05\",\n   \"birthPlace\": \"Stockholm, Sweden\",\n   \"deathDate\": \"\",\n   \"deathPlace\": \"\",\n   \"jobTitle\": [\n      \"Civil Forest Officer\",\n      \"Director\"\n   ],\n   \"nationality\": \"Swedish\",\n   \"memberOf\": [\n      {\n         \"@type\": \"Organization\",\n         \"name\": \"Swedish Forestry Association\",\n         \"startDate\": \"1940\",\n         \"endDate\": \"1947\"\n      },\n      {\n         \"@type\": \"Organization\",\n         \"name\": \"Skogsällskapet\",\n         \"startDate\": \"1947\"\n      }\n   ],\n   \"education\": [\n      {\n         \"@type\": \"EducationalOccupationalCredential\",\n         \"name\": \"Studiex\",\n         \"description\": \"Passed exams in Stockholm\",\n         \"year\": \"1918\"\n      },\n      {\n         \"@type\": \"EducationalOccupationalCredential\",\n         \"name\": \"Ex. v. skogshögsk\",\n         \"description\": \"Completed forestry course in School of Agriculture\",\n         \"year\": \"1924\"\n      }\n   ],\n   \"workLocation\": [\n      {\n         \"@type\": \"Place\",\n         \"name\": \"Gothenburg, Sweden\"\n      }\n   ],\n   \"worksFor\": [\n      {\n         \"@type\": \"Organization\",\n         \"name\": \"Swedish Forestry Association\",\n         \"startDate\": \"1926\",\n         \"endDate\": \"1940\"\n      },\n      {\n         \"@type\": \"Organization\",\n         \"name\": \"Central Council for Forestry Management\",\n         \"startDate\": \"1938\",\n         \"endDate\": \"1941\"\n      },\n      {\n         \"@type\": \"Organization\",\n         \"name\": \"Forestry Control Bureau\",\n         \"startDate\": \"1941\",\n         \"endDate\": \"1947\",\n         \"jobTitle\": \"Chief\"\n      }\n   ],\n   \"memberOf\": [\n      {\n         \"@type\": \"Organization\",\n         \"name\": \"Skogsägarkår (Forest Owners Association)\",\n         \"startDate\": \"1931\"\n      },\n      {\n         \"@type\": \"Organization\",\n         \"name\": \"Forest Fire Commission\",\n         \"startDate\": \"1935\"\n      },\n      {\n         \"@type\": \"Organization\",\n         \"name\": \"36-year-old Forest Investigation\",\n         \"startDate\": \"1936\"\n      },\n      {\n         \"@type\": \"Organization\",\n         \"name\": \"Skogsveckan (Forest Week)\",\n         \"startDate\": \"1940\",\n         \"endDate\": \"1947\"\n      },\n      {\n         \"@type\": \"Organization\",\n         \"name\": \"Forestry Law Investigation\",\n         \"startDate\": \"1942\"\n      },\n      {\n         \"@type\": \"Organization\",\n         \"name\": \"Forestry Board Investigation\",\n         \"startDate\": \"1944\"\n      },\n      {\n         \"@type\": \"Organization\",\n         \"name\": \"Agricultural Committee for Stockholm's County and City\",\n         \"startDate\": \"1946\"\n      },\n      {\n         \"@type\": \"Organization\",\n         \"name\": \"Board for the State Forestry Masters School\",\n         \"startDate\": \"1944\"\n      },\n      {\n         \"@type\": \"Organization\",\n         \"name\": \"1946 Committee for Education of Land Surveying and Agriculture\"\n      },\n      {\n         \"@type\": \"Organization\",\n         \"name\": \"International Conferences\"\n      }\n   ],\n   \"sameAs\": \"\",\n   \"awards\": [\n      {\n         \"@type\": \"Order\",\n         \"name\": \"RNO\"\n      }\n   ]\n}",
    "structured": {
        "@context": "https://schema.org/",
        "@type": "Person",
        "name": "Folke Ludvig Johansson",
        "givenName": "Folke Ludvig",
        "familyName": "Johansson",
        "additionalName": "Hemming",
        "birthDate": "1899-02-05",
        "birthPlace": "Stockholm, Sweden",
        "deathDate": "",
        "deathPlace": "",
        "jobTitle": [
            "Civil Forest Officer",
            "Director"
        ],
        "nationality": "Swedish",
        "memberOf": [
            {
                "@type": "Organization",
                "name": "Skogsägarkår (Forest Owners Association)",
                "startDate": "1931"
            },
            {
                "@type": "Organization",
                "name": "Forest Fire Commission",
                "startDate": "1935"
            },
            {
                "@type": "Organization",
                "name": "36-year-old Forest Investigation",
                "startDate": "1936"
            },
            {
                "@type": "Organization",
                "name": "Skogsveckan (Forest Week)",
                "startDate": "1940",
                "endDate": "1947"
            },
            {
                "@type": "Organization",
                "name": "Forestry Law Investigation",
                "startDate": "1942"
            },
            {
                "@type": "Organization",
                "name": "Forestry Board Investigation",
                "startDate": "1944"
            },
            {
                "@type": "Organization",
                "name": "Agricultural Committee for Stockholm's County and City",
                "startDate": "1946"
            },
            {
                "@type": "Organization",
                "name": "Board for the State Forestry Masters School",
                "startDate": "1944"
            },
            {
                "@type": "Organization",
                "name": "1946 Committee for Education of Land Surveying and Agriculture"
            },
            {
                "@type": "Organization",
                "name": "International Conferences"
            }
        ],
        "education": [
            {
                "@type": "EducationalOccupationalCredential",
                "name": "Studiex",
                "description": "Passed exams in Stockholm",
                "year": "1918"
            },
            {
                "@type": "EducationalOccupationalCredential",
                "name": "Ex. v. skogshögsk",
                "description": "Completed forestry course in School of Agriculture",
                "year": "1924"
            }
        ],
        "workLocation": [
            {
                "@type": "Place",
                "name": "Gothenburg, Sweden"
            }
        ],
        "worksFor": [
            {
                "@type": "Organization",
                "name": "Swedish Forestry Association",
                "startDate": "1926",
                "endDate": "1940"
            },
            {
                "@type": "Organization",
                "name": "Central Council for Forestry Management",
                "startDate": "1938",
                "endDate": "1941"
            },
            {
                "@type": "Organization",
                "name": "Forestry Control Bureau",
                "startDate": "1941",
                "endDate": "1947",
                "jobTitle": "Chief"
            }
        ],
        "sameAs": "",
        "awards": [
            {
                "@type": "Order",
                "name": "RNO"
            }
        ]
    }
}