{
    "original": "Kina, Jap., Sydafr. o. USA. Skr.: Jorden runt (23). Hobbies: segling, golf. KVOlkl, RNO, KDDOlkl, KFinlVRO, KNS:t002kl, Gbgs kgl. segelsällsk. förtjGM. Carlsson, Gustaf Adolf, komminister, Mariestad, f. 6/11/90 i Alingsås av godsäg. Olaus C. o. Augusta Carlsson. G. 26 m. Ingeborg Andersson. Barn: Britta f. 29. — Stud:ex. i Skara 11, fil. kand. 21, teol. kand. samt prästv. f. Skara stift 23. V. pastor i Fägre 23, kommin. i Korsberga 24, kyrkoh. i Sventorp 28, kommin. i Mariestad sed. 34, domkyrkosysslom. sed. s. å., las :pred. sed. 35. Carlsson, Gustaf Börje, komminister, Hok, f. 5/4/07 i Sunnersberg, Ska-rab. av Emil C. o. Anna Gustafs-dotter. G. 34 m. Ruby Sölvén. Barn: Anders f. 37, Peter 43. — Stud:ex. i Jönköp. 27, teol. fil. ex. i Lund 29, teol. kand. samt prakt. teod. prov 33, prästv. f. Växjö stift 34. Varit past:-adj. i Fryele, v. kommin. i 0’skars-hamn ^samt v. pastor i Björkö, Tolg o Barkeryd, v. kommin. i Svenarum 38, kommin. där sed. 42. Carlsson, Johan Gustaf, läroverksadjunkt, Göteborg, f. 7/7/84 i Växjö av Carl Arvidi&amp;son o. Märta Pettersdotter. G. 12 m. Signe Holm. Barn: Per Sköldenberg f. 13, civ:ing., Bengt Sköldenberg 18, fil. kand., journal. — Mog:ex. i Växjö 03’, fil. kand. i Lund 08, provår 12. Res. t. Tyskl. 08, 23, 27 o. 29, Österr. 23, Belg. o. Frankr. 34, stud :vist. v. Kristinebergs zoolog, stat. 05, ri o. 1(2 m. m. E. o. aman. v. zoolog, inst. i Lund 06-09, e. o. lär. i Lund 08, vik. adj. i Kalmar 09, lär. i Eslöv 09-10, vik. lektor i Kalmar 10-11, adj. i Karlshamn 12, i Ystad 18, adj. i geogr. o. biol. m. hälsolära v. Hvitfeldtska h. a. 1. i Gbg sed. 31. Led. av riksd. första kamm. 20-23, var i Ystad bl. a. led. av stadsfullm., ordf. i stadsrev., rev. f. las. o. sjukh., v. ordf. i Klosterstyr. samt led. av styr. f. fornminneisfören., förest, f. Gen-tr :byrån f. pop :vet rskapd. föreläsn. i Gbg sed. 38. Skr.: vet i.skapl. avh. o. upps., pop :vet :’skapl. art. o. rec.",
    "translated": "China, Japan, South Africa, and the USA. Works: Around the World (1923). Hobbies: sailing, golf. Member of the Royal Swedish Academy of Sciences, Royal Norwegian Order, Royal Danish Order, Royal Finnish Order of the White Rose, Royal Norwegian Society of Sciences and Letters: #002, Gothenburg Royal Sailing Society honorary member. \n\nCarlsson, Gustaf Adolf, vicar, Mariestad, born on 6/11/1890 in Alingsås to estate owner Olaus C. and Augusta Carlsson. Married on 26 to Ingeborg Andersson. Children: Britta born in 1929. Education: graduated from Skara in 1911, Bachelor of Arts in 1921, Bachelor of Theology and ordained in Skara Diocese in 1923. Vicar in Fägre in 1923, curate in Korsberga in 1924, parish priest in Sventorp in 1928, curate in Mariestad since 1934, cathedral notary since the same year, appointed as a vicar in 1935.\n\nCarlsson, Gustaf Börje, vicar, Hok, born on 5/4/1907 in Sunnersberg, Skaraborg County, to Emil C. and Anna Gustafsdotter. Married on 34 to Ruby Sölvén. Children: Anders born in 1937, Peter in 1943. Education: Graduated from Jönköping in 1927, studied theology and received a Bachelor of Philosophy from Lund in 1929, Bachelor of Theology and passed practical theological examination in 1933, ordained in Växjö Diocese in 1934. Has served as an assistant minister in Fryele, deputy vicar in Öskarshamn, and vice pastor in Björkö, Tolg, and Barkeryd. Vicar in Svenarum in 1938 and has served there since 1942.\n\nCarlsson, Johan Gustaf, high school teacher, Gothenburg, born on 7/7/1884 in Växjö to Carl Arvidsson and Märta Pettersdotter. Married on 12 to Signe Holm. Children: Per Sköldenberg, born in 1913, civil engineer, Bengt Sköldenberg, born in 1918, Bachelor of Arts, journalist. Education: Master's degree in Växjö in 1903, Bachelor of Arts from Lund in 1908, probationary year in 1912. Traveled to Germany in 1908, 1923, 1927, and 1929, Austria in 1923, Belgium and France in 1934. Visitors at the Kristineberg Zoological Station in 1905, scholar and assistant at the zoological institute in Lund from 1906 to 1909, temporary teacher in Kalmar in 1909, teacher in Eslöv from 1909 to 1910, temporary lecturer in Kalmar from 1910 to 1911, assistant in Karlshamn in 1912, in Ystad in 1918, adjutant in geography and biology with a health science specialty at Hvitfeldtska high school in Gothenburg since 1931. Member of the First Chamber of the Parliament from 1920 to 1923, holding various positions in Ystad, including member of the city council, chairman of the city audit committee, review officer for the county hospital, and deputy chairman of the monastery board, as well as member of the board for antiquities. Speaker for the Population Bureau for Popular Science Seminars in Gothenburg since 1938. Works: scientific dissertations and essays in popular scientific journals, reviews.",
    "structured_raw": "{\n  \"name\": \"Gustaf Adolf Carlsson\",\n  \"jobTitle\": \"Vicar\",\n  \"birthDate\": \"1890-11-06\",\n  \"birthPlace\": \"Alingsås, Sweden\",\n  \"nationality\": \"Swedish\",\n  \"workLocation\": \"Mariestad\",\n  \"spouse\": \"Ingeborg Andersson\",\n  \"children\": [\n    {\n      \"name\": \"Britta Carlsson\",\n      \"birthDate\": \"1929\"\n    }\n  ],\n  \"education\": [\n    {\n      \"degree\": \"Bachelor of Arts\",\n      \"date\": \"1921\",\n      \"institution\": \"Skara\"\n    },\n    {\n      \"degree\": \"Bachelor of Theology\",\n      \"date\": \"1923\",\n      \"institution\": \"Skara Diocese\"\n    }\n  ],\n  \"affiliations\": [\n    {\n      \"name\": \"Royal Swedish Academy of Sciences\"\n    },\n    {\n      \"name\": \"Royal Norwegian Order\"\n    },\n    {\n      \"name\": \"Royal Danish Order\"\n    },\n    {\n      \"name\": \"Royal Finnish Order of the White Rose\"\n    },\n    {\n      \"name\": \"Royal Norwegian Society of Sciences and Letters\",\n      \"membershipNumber\": \"#002\"\n    },\n    {\n      \"name\": \"Gothenburg Royal Sailing Society\",\n      \"honoraryMember\": true\n    }\n  ],\n  \"hobbies\": [\n    \"sailing\",\n    \"golf\"\n  ]\n}",
    "structured": {
        "name": "Gustaf Adolf Carlsson",
        "jobTitle": "Vicar",
        "birthDate": "1890-11-06",
        "birthPlace": "Alingsås, Sweden",
        "nationality": "Swedish",
        "workLocation": "Mariestad",
        "spouse": "Ingeborg Andersson",
        "children": [
            {
                "name": "Britta Carlsson",
                "birthDate": "1929"
            }
        ],
        "education": [
            {
                "degree": "Bachelor of Arts",
                "date": "1921",
                "institution": "Skara"
            },
            {
                "degree": "Bachelor of Theology",
                "date": "1923",
                "institution": "Skara Diocese"
            }
        ],
        "affiliations": [
            {
                "name": "Royal Swedish Academy of Sciences"
            },
            {
                "name": "Royal Norwegian Order"
            },
            {
                "name": "Royal Danish Order"
            },
            {
                "name": "Royal Finnish Order of the White Rose"
            },
            {
                "name": "Royal Norwegian Society of Sciences and Letters",
                "membershipNumber": "#002"
            },
            {
                "name": "Gothenburg Royal Sailing Society",
                "honoraryMember": true
            }
        ],
        "hobbies": [
            "sailing",
            "golf"
        ]
    }
}