{
    "original": "Hyllner, Oskar Magnus, kyrkoherde, kontraktsprost, Kungsbacka, f. 12/9/88 i Tryde, Krist. 1. — Stud:ex. i Lund 14, teol. fil. ex. 15, _ teol. kand. 18, prakt. teol. ex. o. prästv. 18. Res. t. Tyskl., Ital., Österr., Schweiz. V. pastor i Köpinge past. t. 20, tf. kyrkoh. i Hesslunda 20-23, kyrkoh. i Tölö, Lindome o. Älvsàkers past. sed. 23, kontr :prost i Fjäre o. Viske kontr. sed. 34. Ordf. i Tölö, Lindome o. Älvsåkers kyrkostämmor o. ’barnav:-ndn i Lindome 23-30, i Tölö t. 32 o. i Älvsåker t. 33, led. av Tölö komm:-fulilm. 24-33 o. fr. .39, ordf. i Töllö-Lindome o. Älvs åkers skoktyr. sed. 32, i sitift. Gbfgs hemsikoilla v. Annelberg sied. 36, i Töilö o. Älvsåkers Röda kors-krets sed. 41, led. av styr. f. Hall. 1. barnav :nd o. fören. VaWdaheimnüet, led. av eckJl. bositällsnd sed. 30^ Sv. kyrkans miss:styr. omib. sed. 3’2. LVO 44. Hyltén-Cavallius, Björn Gösta, rytt-mästare, Torne, f. 29/1/94 i Sthlm av översten o. chef. f. Kronob. reg. Gösta H.-C. o. Anna Astrup. G. 21 m. Harriet Lundquist. Barn: Gunlög f. 22, g. m. jägm. Hans Hartelius, Elsa 23’, g. m. insp. Fabian af Petersens, Björn 26, stud., Gösta 28, stud., Hans 38, stud. — Stud:ex. v. Lundsbergs sk. 15, RS, SS. Fänir. v. Smål. hus :reg. 17, und :löjtn. 19, löjtn. på överg:stat v. Livreg. hus. 28, ryttmåstare 32. Äg. o. brukar Sunnanviks gård. Ordf. i skogsv :styr. f. Kronob. 1. o. i Sydöstra Sv:es skogsäg:fören. RSO.",
    "translated": "Hyllner, Oskar Magnus, pastor, dean, Kungsbacka, b. 12/9/88 in Tryde, Krist. 1. — Graduated from Lund with a high school diploma in 1914, a bachelor's degree in theology in 1915, a theological candidate's degree in 1918, a practical theology exam and ordination in 1918. Travelled to Germany, Italy, Austria and Switzerland. Deputy Pastor in Köpinge Parish from 1920, Acting Vicar in Hesslunda from 1920-1923, Vicar in Tölö, Lindome and Älvsåker Parishes from 1923, Dean of Fjäre and Viske deaneries from 1934. Chairman of Tölö, Lindome and Älvsåkers church councils and the children's committee in Lindome from 1923-1930, in Tölö in 1932 and in Älvsåker in 1933. Member of the Tölö municipal council from 1924-1933 and again from 1939, chairman of the Tölö-Lindome and Älvsåkers school boards from 1932, at Annelberg home for the elderly in Gbg from 1936 and in the Tölö and Älvsåkers Red Cross districts from 1941. Member of the board of directors of Hall. 1. Children's Committee and VaWdaheimnüet Association, member of the Epilepsy Board from 1930 and the Swedish Church's Missionary Board from 1932. Received the Order of Vasa in 1944. Hyltén-Cavallius, Björn Gösta, cavalry captain, Torne, b. 29/1/94 in Stockholm to Colonel and Chief of the Kronoborg Regiment Gösta H-C and Anna Astrup. Married Harriet Lundquist in 1921. Children: Gunlög b. 1922, married to forest ranger Hans Hartelius; Elsa b. 1923, married to inspector Fabian af Petersens; Björn b. 1926, student; Gösta b. 1928, student; Hans b. 1938, student. Attended Lundberg school, graduated in 1915. Entered the Småland Hussar Regiment in 1917, promoted to Second Lieutenant in 1919, and to Lieutenant in the Royal Life Guards in 1928. Became a cavalry captain in 1932. Owns and runs Sunnanviks estate. Chairman of the Kronoborg Forest Association and the Southeast Swedish Forestry Association. Knight of the Royal Order of the Sword.",
    "structured_raw": "{\n  \"@context\": \"https://schema.org\",\n  \"@type\": \"Person\",\n  \"name\": \"Oskar Magnus Hyllner\",\n  \"birthDate\": \"1888-09-12\",\n  \"birthPlace\": \"Tryde, Krist. 1\",\n  \"nationality\": \"Swedish\",\n  \"occupation\": [\n    \"Pastor\",\n    \"Dean\"\n  ],\n  \"memberOf\": [\n    {\n      \"@type\": \"Organization\",\n      \"name\": \"Tölö-Lindome and Älvsåkers School Boards\",\n      \"startDate\": \"1932\"\n    },\n    {\n      \"@type\": \"Organization\",\n      \"name\": \"Swedish Church's Missionary Board\",\n      \"startDate\": \"1932\"\n    },\n    {\n      \"@type\": \"Organization\",\n      \"name\": \"Tölö, Lindome and Älvsåkers Church Councils\",\n      \"startDate\": \"1923\",\n      \"endDate\": \"1930\"\n    },\n    {\n      \"@type\": \"Organization\",\n      \"name\": \"Children's Committee in Lindome\",\n      \"startDate\": \"1923\",\n      \"endDate\": \"1930\"\n    },\n    {\n      \"@type\": \"Organization\",\n      \"name\": \"Hall. 1. Children's Committee\",\n      \"startDate\": \"1930\"\n    },\n    {\n      \"@type\": \"Organization\",\n      \"name\": \"VaWdaheimnüet Association\"\n    },\n    {\n      \"@type\": \"Organization\",\n      \"name\": \"Tölö Municipal Council\",\n      \"startDate\": \"1924\",\n      \"endDate\": \"1933\"\n    },\n    {\n      \"@type\": \"Organization\",\n      \"name\": \"Annelberg Home\",\n      \"startDate\": \"1936\"\n    },\n    {\n      \"@type\": \"Organization\",\n      \"name\": \"Tölö and Älvsåkers Red Cross Districts\",\n      \"startDate\": \"1941\"\n    },\n    {\n      \"@type\": \"Organization\",\n      \"name\": \"Kronoborg Forest Association\"\n    },\n    {\n      \"@type\": \"Organization\",\n      \"name\": \"Southeast Swedish Forestry Association\"\n    }\n  ],\n  \"education\": [\n    {\n      \"@type\": \"EducationalOccupationalCredential\",\n      \"name\": \"Lund High School Diploma\",\n      \"educationalLevel\": \"HighSchool\",\n      \"yearCredentialGranted\": \"1914\"\n    },\n    {\n      \"@type\": \"EducationalOccupationalCredential\",\n      \"name\": \"Bachelor's Degree in Theology\",\n      \"educationalLevel\": \"Bachelor'sDegree\",\n      \"yearCredentialGranted\": \"1915\"\n    },\n    {\n      \"@type\": \"EducationalOccupationalCredential\",\n      \"name\": \"Theological Candidate's Degree\",\n      \"yearCredentialGranted\": \"1918\"\n    },\n    {\n      \"@type\": \"EducationalOccupationalCredential\",\n      \"name\": \"Practical Theology Exam\",\n      \"yearCredentialGranted\": \"1918\"\n    },\n    {\n      \"@type\": \"EducationalOccupationalCredential\",\n      \"name\": \"Ordination\",\n      \"yearCredentialGranted\": \"1918\"\n    }\n  ],\n  \"spouse\": {\n    \"@type\": \"Person\",\n    \"name\": \"Harriet Lundquist\",\n    \"marriageDate\": \"1921\"\n  },\n  \"children\": [\n    {\n      \"@type\": \"Person\",\n      \"name\": \"Gunlög\",\n      \"birthDate\": \"1922\",\n      \"spouse\": {\n        \"@type\": \"Person\",\n        \"name\": \"Hans Hartelius\"\n      }\n    },\n    {\n      \"@type\": \"Person\",\n      \"name\": \"Elsa\",\n      \"birthDate\": \"1923\",\n      \"spouse\": {\n        \"@type\": \"Person\",\n        \"name\": \"Fabian af Petersens\"\n      }\n    },\n    {\n      \"@type\": \"Person\",\n      \"name\": \"Björn\",\n      \"birthDate\": \"1926\",\n      \"occupation\": \"Student\"\n    },\n    {\n      \"@type\": \"Person\",\n      \"name\": \"Gösta\",\n      \"birthDate\": \"1928\",\n      \"occupation\": \"Student\"\n    },\n    {\n      \"@type\": \"Person\",\n      \"name\": \"Hans\",\n      \"birthDate\": \"1938\",\n      \"occupation\": \"Student\"\n    }\n  ],\n  \"memberOf\": [\n    {\n      \"@type\": \"Organization\",\n      \"name\": \"Köpinge Parish\",\n      \"roleName\": \"Deputy Pastor\",\n      \"startDate\": \"1920\",\n      \"endDate\": \"1923\"\n    },\n    {\n      \"@type\": \"Organization\",\n      \"name\": \"Hesslunda\",\n      \"roleName\": \"Acting Vicar\",\n      \"startDate\": \"1920\",\n      \"endDate\": \"1923\"\n    },\n    {\n      \"@type\": \"Organization\",\n      \"name\": \"Tölö, Lindome and Älvsåker Parishes\",\n      \"roleName\": \"Vicar\",\n      \"startDate\": \"1923\"\n    },\n    {\n      \"@type\": \"Organization\",\n      \"name\": \"Fjäre and Viske Deaneries\",\n      \"roleName\": \"Dean\",\n      \"startDate\": \"1934\"\n    }\n  ],\n  \"alumniOf\": [\n    {\n      \"@type\": \"EducationalOrganization\",\n      \"name\": \"Lundsbergs Skola\",\n      \"alumniOf\": \"Lundsbergs sk\",\n      \"yearGraduated\": \"1915\"\n    }\n  ],\n  \"award\": {\n    \"@type\": \"Order\",\n    \"name\": \"Order of Vasa\",\n    \"dateAwarded\": \"1944\"\n  }\n}\n",
    "structured": {
        "@context": "https://schema.org",
        "@type": "Person",
        "name": "Oskar Magnus Hyllner",
        "birthDate": "1888-09-12",
        "birthPlace": "Tryde, Krist. 1",
        "nationality": "Swedish",
        "occupation": [
            "Pastor",
            "Dean"
        ],
        "memberOf": [
            {
                "@type": "Organization",
                "name": "Köpinge Parish",
                "roleName": "Deputy Pastor",
                "startDate": "1920",
                "endDate": "1923"
            },
            {
                "@type": "Organization",
                "name": "Hesslunda",
                "roleName": "Acting Vicar",
                "startDate": "1920",
                "endDate": "1923"
            },
            {
                "@type": "Organization",
                "name": "Tölö, Lindome and Älvsåker Parishes",
                "roleName": "Vicar",
                "startDate": "1923"
            },
            {
                "@type": "Organization",
                "name": "Fjäre and Viske Deaneries",
                "roleName": "Dean",
                "startDate": "1934"
            }
        ],
        "education": [
            {
                "@type": "EducationalOccupationalCredential",
                "name": "Lund High School Diploma",
                "educationalLevel": "HighSchool",
                "yearCredentialGranted": "1914"
            },
            {
                "@type": "EducationalOccupationalCredential",
                "name": "Bachelor's Degree in Theology",
                "educationalLevel": "Bachelor'sDegree",
                "yearCredentialGranted": "1915"
            },
            {
                "@type": "EducationalOccupationalCredential",
                "name": "Theological Candidate's Degree",
                "yearCredentialGranted": "1918"
            },
            {
                "@type": "EducationalOccupationalCredential",
                "name": "Practical Theology Exam",
                "yearCredentialGranted": "1918"
            },
            {
                "@type": "EducationalOccupationalCredential",
                "name": "Ordination",
                "yearCredentialGranted": "1918"
            }
        ],
        "spouse": {
            "@type": "Person",
            "name": "Harriet Lundquist",
            "marriageDate": "1921"
        },
        "children": [
            {
                "@type": "Person",
                "name": "Gunlög",
                "birthDate": "1922",
                "spouse": {
                    "@type": "Person",
                    "name": "Hans Hartelius"
                }
            },
            {
                "@type": "Person",
                "name": "Elsa",
                "birthDate": "1923",
                "spouse": {
                    "@type": "Person",
                    "name": "Fabian af Petersens"
                }
            },
            {
                "@type": "Person",
                "name": "Björn",
                "birthDate": "1926",
                "occupation": "Student"
            },
            {
                "@type": "Person",
                "name": "Gösta",
                "birthDate": "1928",
                "occupation": "Student"
            },
            {
                "@type": "Person",
                "name": "Hans",
                "birthDate": "1938",
                "occupation": "Student"
            }
        ],
        "alumniOf": [
            {
                "@type": "EducationalOrganization",
                "name": "Lundsbergs Skola",
                "alumniOf": "Lundsbergs sk",
                "yearGraduated": "1915"
            }
        ],
        "award": {
            "@type": "Order",
            "name": "Order of Vasa",
            "dateAwarded": "1944"
        }
    }
}