{
    "original": "Alvin, Erik Gustaf Marcus, musikdirektör, Vänersborg, f. 6/5/02 i Norrköp. av Karl A. o. Hilda Öhrström. G. 39 m. Inga Sahlin. — Stud:ex. i Norrköp. 20, org:ex. 23, musiklär:- o. kyrkosångarex. 28 v. mu.sikhö’gsk. Stud:resa t. Frankr. 26. — Musiklär. v. Vänersk h. a. 1. sed. 32. Org. o. kantor v. Vänersb. kyrka ’sed. s. å. Timlär. v. komm. flicksk. sed. 32. Di-rig. v. Vänersb. orkifören. sed. 44, v. sångsällsk. Sjung, sjung sed. 33, förste förb :dirig. v. Dalsl. sång:förb. sed. 33. Komp. kantat., manskvart., romanser m. m. Hobbies: tennis, segl. P. A. Bergs jeton i orgelspel 23, Mus. ak. jeton i komp. 24, Dalsl. sångiförb. ftjGM 33, Sv. sångiförb. ftjGM 38.",
    "translated": "Alvin, Erik Gustaf Marcus, musical director, Vänersborg, born May 6th, 1902 in Norrköping to Karl A. and Hilda Öhrström. Married in 1939 to Inga Sahlin. He graduated from high school in Norrköping in 1920, obtained his organist degree in 1923, his music teacher and church singer degree in 1928 from the music college. He traveled to France in 1926 for study purposes. He has been a music teacher at Vänersborg high school since 1932 and an organist and cantor at Vänersborg church since the same year. He has been a hourly teacher at the municipal girls' school since 1932. He directed the Vänersborg orchestra association from 1944 and the singing society \"Sjung, sjung\" since 1933, as well as the first association conductor of Dalsland's singing association since 1933. He composed cantatas, male quartets, romances, etc. His hobbies are tennis and sailing. He received the P.A. Berg's token in organ playing in 1923, the Music Academy token in composition in 1924, the Dalsland's singing association silver medal in 1933, and the Swedish singing association silver medal in 1938.",
    "structured": {
        "@context": "https://schema.org",
        "@type": "Person",
        "name": "Erik Gustaf Marcus Alvin",
        "jobTitle": "Musical Director",
        "birthPlace": "Norrköping, Sweden",
        "birthDate": "1902-05-06",
        "parents": [
            {
                "@type": "Person",
                "name": "Karl A. Alvin"
            },
            {
                "@type": "Person",
                "name": "Hilda Öhrström"
            }
        ],
        "spouse": {
            "@type": "Person",
            "name": "Inga Sahlin",
            "marriageDate": "1939"
        },
        "education": [
            {
                "@type": "EducationalOccupationalCredential",
                "name": "Stud:ex. (High School Diploma)",
                "issuer": "Norrköping",
                "dateIssued": "1920"
            },
            {
                "@type": "EducationalOccupationalCredential",
                "name": "Org:ex. (Organist Degree)",
                "issuer": "Unknown",
                "dateIssued": "1923"
            },
            {
                "@type": "EducationalOccupationalCredential",
                "name": "Musiklär:- o. kyrkosångarex. (Music Teacher and Church Singer Degree)",
                "issuer": "Music College",
                "dateIssued": "1928"
            },
            {
                "@type": "EducationalOccupationalCredential",
                "name": "Stud:resa t. Frankr. (Study trip to France)",
                "issuer": "Unknown",
                "dateIssued": "1926"
            }
        ],
        "workLocation": [
            {
                "@type": "Place",
                "name": "Vänersborg"
            }
        ],
        "worksFor": [
            {
                "@type": "Organization",
                "name": "Vänersborg High School",
                "startDate": "1932",
                "jobTitle": "Music Teacher"
            },
            {
                "@type": "Organization",
                "name": "Vänersborg Church",
                "startDate": "1932",
                "jobTitle": "Organist and Cantor"
            },
            {
                "@type": "Organization",
                "name": "Municipal Girls' School",
                "startDate": "1932",
                "jobTitle": "Hourly Teacher"
            },
            {
                "@type": "Organization",
                "name": "Vänersborg Orchestra Association",
                "startDate": "1944",
                "jobTitle": "Director"
            },
            {
                "@type": "Organization",
                "name": "Sjung, Sjung",
                "startDate": "1933",
                "jobTitle": "Director"
            },
            {
                "@type": "Organization",
                "name": "Dalsland's Singing Association",
                "startDate": "1933",
                "jobTitle": "First Association Conductor"
            }
        ],
        "awards": [
            {
                "@type": "MusicAward",
                "name": "P.A. Berg's Token in Organ Playing",
                "dateReceived": "1923"
            },
            {
                "@type": "MusicAward",
                "name": "Music Academy Token in Composition",
                "dateReceived": "1924"
            },
            {
                "@type": "MusicAward",
                "name": "Dalsland's Singing Association Silver Medal",
                "dateReceived": "1933"
            },
            {
                "@type": "MusicAward",
                "name": "Swedish Singing Association Silver Medal",
                "dateReceived": "1938"
            }
        ],
        "memberOf": [
            {
                "@type": "Organization",
                "name": "Dalsl. sång:förb. (Dalsland's Singing Association)",
                "membershipType": "ftjGM",
                "startDate": "1933"
            },
            {
                "@type": "Organization",
                "name": "Sv. sångiförb. (Swedish Singing Association)",
                "membershipType": "ftjGM",
                "startDate": "1938"
            }
        ],
        "knowsAbout": [
            "Tennis",
            "Sailing"
        ]
    }
}