{
    "original": "Fries, Elias Harald, prakt, läkare, Göteborg, f. 27/12/78 i Gbg av med. dr Robert F. o. Sofia Elisabet Bergman. G. 23 m. Anna Carlander. — Mog:ex. i Gbg 96, med. fil. ex. i Upps. 97 o. med. kand. där 01, med. lic. i Sthlm 06. Tf. epid:läk. i Upps. 05, und:läk. v. Kristinehamns hosp. 06, v. Karl-stiatds liaiSL 06-08, aman. o. andre Häk. v. SaMgr. sjukh. 08-10, tf. distr :làk. samt ’läk. v. Stampens lungsjukh. i Gbg 13-22, tf. prov:iläk. i Gbgs distr. kort. tider årl. 20-23 samt 24-26, järn-v:.läk. 17-43, läk. v. Gbgs folksk. 21-43, officiell ympare i Gbg 26, prakjt. läk. i Gbg. Led. av styr. f. Gbgs träd-g:fören. Skr.: Gbgs o. Boh. 1. fanero-gamer o. ormbunkar (45) samt art. i botan. ämnen. Hobby: botanik. RVO.",
    "translated": "Fries, Elias Harald, practical doctor, Gothenburg, born on December 27th, 1878 in Gothenburg to medical doctor Robert F. and Sofia Elisabet Bergman. Married in 23 years with Anna Carlander. Completed his Master's degree in Gothenburg in 1896, Bachelor of Science in Uppsala in 1897 and Bachelor of Medicine there in 1901, Medical degree in Stockholm in 1906. Temporary epidemic doctor in Uppsala in 1905, assistant physician at Kristinehamns hospital in 1906, at Karlstad's Hospital from 1906-1908, assistant and second physician at Sahlgren's Hospital from 1908-1910, temporary district doctor and physician at Stampen Lung Hospital in Gothenburg from 1913-1922, temporary inspector physician in Gothenburg district for short periods annually from 1920-1923 and 1924-1926, iron-refinery physician from 1917-1943, physician at Gothenburg primary school from 1921-1943, official vaccinator in Gothenburg in 1926, practical doctor in Gothenburg. Member of the board of directors for Gothenburg's tree society. Publications include \"Gothenburg's and Bohemia's fern and fern allies\" (1945) and articles on botanical subjects. Hobby: botany. Received the Order of Vasa.",
    "structured_raw": "{\n  \"@context\": \"http://schema.org\",\n  \"@type\": \"Person\",\n  \"name\": \"Elias Harald Fries\",\n  \"birthDate\": \"1878-12-27\",\n  \"birthPlace\": \"Gothenburg\",\n  \"deathDate\": \"1943\",\n  \"deathPlace\": \"Gothenburg\",\n  \"jobTitle\": \"Practical Doctor\",\n  \"nationality\": \"Swedish\",\n  \"parent\": [\n    {\n      \"@type\": \"Person\",\n      \"name\": \"Robert F.\",\n      \"jobTitle\": \"Medical Doctor\"\n    },\n    {\n      \"@type\": \"Person\",\n      \"name\": \"Sofia Elisabet Bergman\"\n    }\n  ],\n  \"spouse\": {\n    \"@type\": \"Person\",\n    \"name\": \"Anna Carlander\",\n    \"marriageDate\": \"23\"\n  },\n  \"education\": [\n    {\n      \"@type\": \"EducationalOccupationalCredential\",\n      \"credentialCategory\": \"Master's degree\",\n      \"earnedBy\": \"Gothenburg\",\n      \"dateEarned\": \"1896\"\n    },\n    {\n      \"@type\": \"EducationalOccupationalCredential\",\n      \"credentialCategory\": \"Bachelor's degree\",\n      \"earnedBy\": \"Uppsala\",\n      \"dateEarned\": \"1897\"\n    },\n    {\n      \"@type\": \"EducationalOccupationalCredential\",\n      \"credentialCategory\": \"Bachelor of Medicine\",\n      \"earnedBy\": \"Uppsala\",\n      \"dateEarned\": \"1901\"\n    },\n    {\n      \"@type\": \"EducationalOccupationalCredential\",\n      \"credentialCategory\": \"Medical Degree\",\n      \"earnedBy\": \"Stockholm\",\n      \"dateEarned\": \"1906\"\n    }\n  ],\n  \"worksFor\": {\n    \"@type\": \"Organization\",\n    \"name\": \"Gothenburg\"\n  },\n  \"medicalSpecialty\": [\n    {\n      \"@type\": \"MedicalSpecialty\",\n      \"name\": \"Epidemic Doctor\"\n    },\n    {\n      \"@type\": \"MedicalSpecialty\",\n      \"name\": \"Assistant Physician\"\n    },\n    {\n      \"@type\": \"MedicalSpecialty\",\n      \"name\": \"Physician\"\n    },\n    {\n      \"@type\": \"MedicalSpecialty\",\n      \"name\": \"Inspector Physician\"\n    },\n    {\n      \"@type\": \"MedicalSpecialty\",\n      \"name\": \"Iron-refinery Physician\"\n    },\n    {\n      \"@type\": \"MedicalSpecialty\",\n      \"name\": \"Vaccinator\"\n    },\n    {\n      \"@type\": \"MedicalSpecialty\",\n      \"name\": \"Practical Doctor\"\n    }\n  ],\n  \"memberOf\": {\n    \"@type\": \"Organization\",\n    \"name\": \"Gothenburg's Tree Society\"\n  },\n  \"additionalName\": \"RVO\",\n  \"description\": \"Author of 'Gothenburg's and Bohemia's fern and fern allies' (1945) and articles on botanical subjects. Hobby: botany.\"\n}",
    "structured": {
        "@context": "http://schema.org",
        "@type": "Person",
        "name": "Elias Harald Fries",
        "birthDate": "1878-12-27",
        "birthPlace": "Gothenburg",
        "deathDate": "1943",
        "deathPlace": "Gothenburg",
        "jobTitle": "Practical Doctor",
        "nationality": "Swedish",
        "parent": [
            {
                "@type": "Person",
                "name": "Robert F.",
                "jobTitle": "Medical Doctor"
            },
            {
                "@type": "Person",
                "name": "Sofia Elisabet Bergman"
            }
        ],
        "spouse": {
            "@type": "Person",
            "name": "Anna Carlander",
            "marriageDate": "23"
        },
        "education": [
            {
                "@type": "EducationalOccupationalCredential",
                "credentialCategory": "Master's degree",
                "earnedBy": "Gothenburg",
                "dateEarned": "1896"
            },
            {
                "@type": "EducationalOccupationalCredential",
                "credentialCategory": "Bachelor's degree",
                "earnedBy": "Uppsala",
                "dateEarned": "1897"
            },
            {
                "@type": "EducationalOccupationalCredential",
                "credentialCategory": "Bachelor of Medicine",
                "earnedBy": "Uppsala",
                "dateEarned": "1901"
            },
            {
                "@type": "EducationalOccupationalCredential",
                "credentialCategory": "Medical Degree",
                "earnedBy": "Stockholm",
                "dateEarned": "1906"
            }
        ],
        "worksFor": {
            "@type": "Organization",
            "name": "Gothenburg"
        },
        "medicalSpecialty": [
            {
                "@type": "MedicalSpecialty",
                "name": "Epidemic Doctor"
            },
            {
                "@type": "MedicalSpecialty",
                "name": "Assistant Physician"
            },
            {
                "@type": "MedicalSpecialty",
                "name": "Physician"
            },
            {
                "@type": "MedicalSpecialty",
                "name": "Inspector Physician"
            },
            {
                "@type": "MedicalSpecialty",
                "name": "Iron-refinery Physician"
            },
            {
                "@type": "MedicalSpecialty",
                "name": "Vaccinator"
            },
            {
                "@type": "MedicalSpecialty",
                "name": "Practical Doctor"
            }
        ],
        "memberOf": {
            "@type": "Organization",
            "name": "Gothenburg's Tree Society"
        },
        "additionalName": "RVO",
        "description": "Author of 'Gothenburg's and Bohemia's fern and fern allies' (1945) and articles on botanical subjects. Hobby: botany."
    }
}