{
    "original": "Karl Gustaf, distriktsveterinär, Vaggeryd, f. 10/3/05 i Skara av kyrkoh. Gustaf W. o. Lydia Kristina Malmström. G. 34 m. Ingrid Carlson. Barn: Britt f. 36, Kristina 38, Olof 39, Lars 45. — Stud:ex. i Skara 24, ve-terinärex. 31. Andre assist :veter. v. östergötl. 1. hush:sällsk. i Linköp. 35, distriktsveterinär i Vaggeryd fr. 39. , Nils Arvid, koimminis-ter. Borgstena, f. 25/8/02 i Skara av kyrkoh. Gustaf W. o. Lydia Kristina Malmström. G. 33 m. Valborg Norrman. Barn: Margareta f. 34, Anders 38. — Stud:ex i Skara 21, teol. fil. ex. i Gbg 22, teol. kand. i Upps. 31, prästex. i Skara s. å., prästv. 3(1. Tjg. s. v. past. i 64 Saldby o. v. komm. i Stora Melliby. Kortniminister i Borgstena fr. 24-. Ordf. i kyrkostämma, barnav:nd o. skolråd. ^Westerberg, Carl Oswald, bankkamrer, jur. kand., Göteborg, f. 16/8/04 i Gbg. G. 3’4 m. prakt. läk. Gerd Blume. Barn: Helena Christina (Bitte) f. 36, Peter 37, Nicola 41. — Stud:ex. 23, jur. kand. 3’1, DHS 34. E. o. hovr :not. 31, tjg. v. Södertörns doms. 31-34, intr. i A-B Gbgs Banks tj. 34, kamrer där sed. 41.",
    "translated": "Karl Gustaf, district veterinarian, Vaggeryd, b. 10/3/05 in Skara, the son of pastor Gustaf W. and Lydia Kristina Malmström. Married in 1934 to Ingrid Carlson. Children: Britt b. 1936, Kristina b. 1938, Olof b. 1939, Lars b. 1945. Graduated from Skara in 1924, veterinary exam in 1931. Assistant veterinarian in Östergötland, 1st household companion in Linköping in 1935, district veterinarian in Vaggeryd from 1939. \n\nNils Arvid, parish minister, Borgstena, b. 25/8/02 in Skara, the son of pastor Gustaf W. and Lydia Kristina Malmström. Married in 1933 to Valborg Norrman. Children: Margareta b. 1934, Anders b. 1938. Graduated from Skara in 1921, theology and philosophy exam in Gothenburg in 1922, theology degree in Uppsala in 1931, ordained in Skara the same year. Serving as assistant parish minister in Saldby and deputy vicar in Stora Melliby. Local minister in Borgstena from 1924. Chairman of the church assembly, child welfare, and school council. \n\nCarl Oswald Westerberg, bank clerk, law degree, Gothenburg, b. 16/8/04 in Gothenburg. Married in 1934 to a practicing doctor, Gerd Blume. Children: Helena Christina (Bitte) b. 1936, Peter b. 1937, Nicola b. 1941. Graduated in 1923, law degree in 1931, postgraduate studies in 1934. Acting notary public in 1931, served in Södertörn district court from 1931-1934, joined A-B Gothenburg Bank in 1934, promoted to clerk in 1941.",
    "structured_raw": "{\n  \"@context\": \"https://schema.org\",\n  \"@type\": \"Person\",\n  \"name\": \"Karl Gustaf\",\n  \"jobTitle\": \"District Veterinarian\",\n  \"birthDate\": \"1905-03-10\",\n  \"birthPlace\": \"Skara\",\n  \"parents\": [\n    {\n      \"@type\": \"Person\",\n      \"name\": \"Gustaf W.\",\n      \"jobTitle\": \"Pastor\"\n    },\n    {\n      \"@type\": \"Person\",\n      \"name\": \"Lydia Kristina Malmström\"\n    }\n  ],\n  \"spouse\": {\n    \"@type\": \"Person\",\n    \"name\": \"Ingrid Carlson\"\n  },\n  \"children\": [\n    {\n      \"@type\": \"Person\",\n      \"name\": \"Britt\",\n      \"birthDate\": \"1936\"\n    },\n    {\n      \"@type\": \"Person\",\n      \"name\": \"Kristina\",\n      \"birthDate\": \"1938\"\n    },\n    {\n      \"@type\": \"Person\",\n      \"name\": \"Olof\",\n      \"birthDate\": \"1939\"\n    },\n    {\n      \"@type\": \"Person\",\n      \"name\": \"Lars\",\n      \"birthDate\": \"1945\"\n    }\n  ],\n  \"education\": [\n    {\n      \"@type\": \"EducationalOccupationalCredential\",\n      \"credentialCategory\": \"graduation\",\n      \"educationalLevel\": \"HighSchool\",\n      \"educationalProgram\": \"Stud:ex.\",\n      \"educationalInstitution\": \"Skara\",\n      \"startDate\": \"1924\",\n      \"endDate\": \"1924\"\n    },\n    {\n      \"@type\": \"EducationalOccupationalCredential\",\n      \"credentialCategory\": \"graduation\",\n      \"educationalLevel\": \"VocationalSchool\",\n      \"educationalProgram\": \"Veterinarian\",\n      \"educationalInstitution\": \"Skara\",\n      \"startDate\": \"1931\",\n      \"endDate\": \"1931\"\n    }\n  ],\n  \"work\": [\n    {\n      \"@type\": \"JobPosting\",\n      \"title\": \"Assistant Veterinarian\",\n      \"startDate\": \"1931\",\n      \"endDate\": \"1935\",\n      \"location\": \"Östergötland\"\n    },\n    {\n      \"@type\": \"JobPosting\",\n      \"title\": \"Household Companion\",\n      \"startDate\": \"1935\",\n      \"endDate\": \"1939\",\n      \"location\": \"Linköping\"\n    },\n    {\n      \"@type\": \"JobPosting\",\n      \"title\": \"District Veterinarian\",\n      \"startDate\": \"1939\",\n      \"location\": \"Vaggeryd\"\n    }\n  ]\n}",
    "structured": {
        "@context": "https://schema.org",
        "@type": "Person",
        "name": "Karl Gustaf",
        "jobTitle": "District Veterinarian",
        "birthDate": "1905-03-10",
        "birthPlace": "Skara",
        "parents": [
            {
                "@type": "Person",
                "name": "Gustaf W.",
                "jobTitle": "Pastor"
            },
            {
                "@type": "Person",
                "name": "Lydia Kristina Malmström"
            }
        ],
        "spouse": {
            "@type": "Person",
            "name": "Ingrid Carlson"
        },
        "children": [
            {
                "@type": "Person",
                "name": "Britt",
                "birthDate": "1936"
            },
            {
                "@type": "Person",
                "name": "Kristina",
                "birthDate": "1938"
            },
            {
                "@type": "Person",
                "name": "Olof",
                "birthDate": "1939"
            },
            {
                "@type": "Person",
                "name": "Lars",
                "birthDate": "1945"
            }
        ],
        "education": [
            {
                "@type": "EducationalOccupationalCredential",
                "credentialCategory": "graduation",
                "educationalLevel": "HighSchool",
                "educationalProgram": "Stud:ex.",
                "educationalInstitution": "Skara",
                "startDate": "1924",
                "endDate": "1924"
            },
            {
                "@type": "EducationalOccupationalCredential",
                "credentialCategory": "graduation",
                "educationalLevel": "VocationalSchool",
                "educationalProgram": "Veterinarian",
                "educationalInstitution": "Skara",
                "startDate": "1931",
                "endDate": "1931"
            }
        ],
        "work": [
            {
                "@type": "JobPosting",
                "title": "Assistant Veterinarian",
                "startDate": "1931",
                "endDate": "1935",
                "location": "Östergötland"
            },
            {
                "@type": "JobPosting",
                "title": "Household Companion",
                "startDate": "1935",
                "endDate": "1939",
                "location": "Linköping"
            },
            {
                "@type": "JobPosting",
                "title": "District Veterinarian",
                "startDate": "1939",
                "location": "Vaggeryd"
            }
        ]
    }
}