{
    "original": "Åkesson, Nils Johan, lasarettsläkare, Finspång, f. 25/10/95 i Gbg av lärov:-adj. Jöns Å. o. Hanna Larsson. G. 23 m. med. lic. Hilda Bengtsson. Barn: Bengt-Åke f, 24, med. kand., Ingrid 30, Karin 39. — Stud :ex. i Gbg 14, med. kand. 18 o. med. lic. 24 i Lund. Div. förordn. v. klin. o. las. 20-25, tf. und:-läk. v. Landskr. o. Trelleb. las. samt e. läk. v. röntgenklin. i Lund 26, andre und :läk. v. Falu las. kir. avd. 27-30, därunder vik. förste und’:’läk. sexton mån., tf. las :läk. i Avesta 30, tf. aman. o. tf. und:läk. v. Maria sjukh. kir. klin. s. å., aman. där 31, därunder tf. un-diläk. åtta mån., tf. und:läk. där samt e. o. aman. v. Sabbatsb. sjukh. öronpoliklin. 32, e. läk. v. Maria sjukh. kir. klin. 33, und:läk. där 33-38, därunder vik. överläk. åtta mån., und:-läk. v. med. avd. där 38-39, förste und :läk. o. bitr. las :läk. v. Falu las. kir. avd. 39, las :läk. i Finspång sed. 43’. Bat:läk. i Fik res. 27.",
    "translated": "Åkesson, Nils Johan, hospital physician, Finspång, born on October 25, 1895 in Gothenburg, son of secondary school teacher Jöns Å. and Hanna Larsson. Married since 1923 to medical licentiate Hilda Bengtsson. Children: Bengt-Åke, born in 1924, medical candidate; Ingrid, born in 1930; Karin, born in 1939. \n\nEducation: Graduated from secondary school in Gothenburg in 1914; medical candidate in 1918; medical licentiate in 1924 from Lund University. Various appointments as clinical and hospital physician from 1920 to 1925, acting assistant physician at Landskrona and Trelleborg hospitals; radiology physician in Lund in 1926; second assistant physician at Falun Hospital surgical department from 1927 to 1930, including a temporary position as first assistant physician for sixteen months; acting hospital physician in Avesta in 1930; assistant physician and temporary acting assistant physician at Maria Hospital surgical clinic in the same year, assistant physician there in 1931, including a temporary position as assistant physician for eight months; assistant physician and temporary acting assistant physician at Sabbatsberg Hospital ear clinic in 1932, assistant physician at Maria Hospital surgical clinic in 1933, assistant physician there from 1933 to 1938, including a temporary position as acting senior physician for eight months; assistant physician at the medical department there from 1938 to 1939, first assistant physician and deputy hospital physician at Falun Hospital surgical department in 1939; hospital physician in Finspång since 1943. Military: Battalion physician in the Field Reserve in 1927.",
    "structured_raw": "{\n  \"@context\": \"https://schema.org\",\n  \"@type\": \"Person\",\n  \"name\": \"Åkesson, Nils Johan\",\n  \"birthDate\": \"1895-10-25\",\n  \"birthPlace\": \"Gothenburg\",\n  \"description\": \"Hospital physician\",\n  \"spouse\": {\n    \"@type\": \"Person\",\n    \"name\": \"Hilda Bengtsson\",\n    \"medicalLicentiate\": true\n  },\n  \"children\": [\n    {\n      \"@type\": \"Person\",\n      \"name\": \"Bengt-Åke\",\n      \"birthDate\": \"1924\",\n      \"medicalCandidate\": true\n    },\n    {\n      \"@type\": \"Person\",\n      \"name\": \"Ingrid\",\n      \"birthDate\": \"1930\"\n    },\n    {\n      \"@type\": \"Person\",\n      \"name\": \"Karin\",\n      \"birthDate\": \"1939\"\n    }\n  ],\n  \"education\": [\n    {\n      \"description\": \"Secondary school\",\n      \"startDate\": \"1914\",\n      \"endDate\": \"1914\",\n      \"location\": \"Gothenburg\"\n    },\n    {\n      \"description\": \"Medical candidate\",\n      \"startDate\": \"1918\",\n      \"endDate\": \"1918\",\n      \"university\": \"Lund University\"\n    },\n    {\n      \"description\": \"Medical licentiate\",\n      \"startDate\": \"1924\",\n      \"endDate\": \"1924\",\n      \"university\": \"Lund University\"\n    }\n  ],\n  \"appointments\": [\n    {\n      \"description\": \"Clinical and hospital physician\",\n      \"startDate\": \"1920\",\n      \"endDate\": \"1925\"\n    },\n    {\n      \"description\": \"Acting assistant physician\",\n      \"startDate\": \"1927\",\n      \"endDate\": \"1930\",\n      \"location\": \"Landskrona and Trelleborg hospitals\"\n    },\n    {\n      \"description\": \"Radiology physician\",\n      \"startDate\": \"1926\",\n      \"endDate\": \"1926\",\n      \"location\": \"Lund\"\n    },\n    {\n      \"description\": \"Second assistant physician\",\n      \"startDate\": \"1927\",\n      \"endDate\": \"1930\",\n      \"location\": \"Falun Hospital surgical department\"\n    },\n    {\n      \"description\": \"Acting hospital physician\",\n      \"startDate\": \"1930\",\n      \"endDate\": \"1930\",\n      \"location\": \"Avesta\"\n    },\n    {\n      \"description\": \"Assistant physician and temporary acting assistant physician\",\n      \"startDate\": \"1930\",\n      \"endDate\": \"1930\",\n      \"location\": \"Maria Hospital surgical clinic\"\n    },\n    {\n      \"description\": \"Assistant physician\",\n      \"startDate\": \"1931\",\n      \"endDate\": \"1931\",\n      \"location\": \"Maria Hospital surgical clinic\"\n    },\n    {\n      \"description\": \"Assistant physician and temporary acting assistant physician\",\n      \"startDate\": \"1932\",\n      \"endDate\": \"1932\",\n      \"location\": \"Sabbatsberg Hospital ear clinic\"\n    },\n    {\n      \"description\": \"Assistant physician\",\n      \"startDate\": \"1933\",\n      \"endDate\": \"1938\",\n      \"location\": \"Maria Hospital surgical clinic\"\n    },\n    {\n      \"description\": \"Assistant physician\",\n      \"startDate\": \"1938\",\n      \"endDate\": \"1939\",\n      \"location\": \"Maria Hospital medical department\"\n    },\n    {\n      \"description\": \"First assistant physician and deputy hospital physician\",\n      \"startDate\": \"1939\",\n      \"endDate\": \"1939\",\n      \"location\": \"Falun Hospital surgical department\"\n    },\n    {\n      \"description\": \"Hospital physician\",\n      \"startDate\": \"1943\",\n      \"location\": \"Finspång\"\n    }\n  ],\n  \"militaryService\": [\n    {\n      \"description\": \"Battalion physician\",\n      \"startDate\": \"1927\",\n      \"endDate\": \"1927\"\n    }\n  ]\n}",
    "structured": {
        "@context": "https://schema.org",
        "@type": "Person",
        "name": "Åkesson, Nils Johan",
        "birthDate": "1895-10-25",
        "birthPlace": "Gothenburg",
        "description": "Hospital physician",
        "spouse": {
            "@type": "Person",
            "name": "Hilda Bengtsson",
            "medicalLicentiate": true
        },
        "children": [
            {
                "@type": "Person",
                "name": "Bengt-Åke",
                "birthDate": "1924",
                "medicalCandidate": true
            },
            {
                "@type": "Person",
                "name": "Ingrid",
                "birthDate": "1930"
            },
            {
                "@type": "Person",
                "name": "Karin",
                "birthDate": "1939"
            }
        ],
        "education": [
            {
                "description": "Secondary school",
                "startDate": "1914",
                "endDate": "1914",
                "location": "Gothenburg"
            },
            {
                "description": "Medical candidate",
                "startDate": "1918",
                "endDate": "1918",
                "university": "Lund University"
            },
            {
                "description": "Medical licentiate",
                "startDate": "1924",
                "endDate": "1924",
                "university": "Lund University"
            }
        ],
        "appointments": [
            {
                "description": "Clinical and hospital physician",
                "startDate": "1920",
                "endDate": "1925"
            },
            {
                "description": "Acting assistant physician",
                "startDate": "1927",
                "endDate": "1930",
                "location": "Landskrona and Trelleborg hospitals"
            },
            {
                "description": "Radiology physician",
                "startDate": "1926",
                "endDate": "1926",
                "location": "Lund"
            },
            {
                "description": "Second assistant physician",
                "startDate": "1927",
                "endDate": "1930",
                "location": "Falun Hospital surgical department"
            },
            {
                "description": "Acting hospital physician",
                "startDate": "1930",
                "endDate": "1930",
                "location": "Avesta"
            },
            {
                "description": "Assistant physician and temporary acting assistant physician",
                "startDate": "1930",
                "endDate": "1930",
                "location": "Maria Hospital surgical clinic"
            },
            {
                "description": "Assistant physician",
                "startDate": "1931",
                "endDate": "1931",
                "location": "Maria Hospital surgical clinic"
            },
            {
                "description": "Assistant physician and temporary acting assistant physician",
                "startDate": "1932",
                "endDate": "1932",
                "location": "Sabbatsberg Hospital ear clinic"
            },
            {
                "description": "Assistant physician",
                "startDate": "1933",
                "endDate": "1938",
                "location": "Maria Hospital surgical clinic"
            },
            {
                "description": "Assistant physician",
                "startDate": "1938",
                "endDate": "1939",
                "location": "Maria Hospital medical department"
            },
            {
                "description": "First assistant physician and deputy hospital physician",
                "startDate": "1939",
                "endDate": "1939",
                "location": "Falun Hospital surgical department"
            },
            {
                "description": "Hospital physician",
                "startDate": "1943",
                "location": "Finspång"
            }
        ],
        "militaryService": [
            {
                "description": "Battalion physician",
                "startDate": "1927",
                "endDate": "1927"
            }
        ]
    }
}