{
    "original": "Perulf, Nils Sture, med. lic, prakt,\nläkare, Malmö, f. 28/12/07 i Lund.   G.\n\n39 m. Astrid Andersson. Barn:\nPeter f. 40, Marianne 42, Thomas 43. —\nStud :ex. i Lund 27, med. kand. 32 o.\nmed. lic. 39 i Lund. Div. kort.\nför-ordn. s. munic:- o. prov:läk. 36, 37 o.\n38, vik. und :läk. v. las. i Trelleb., S :t\nLars sjukh. i Lund, röntgenavd. v. las.\ni Hälsingb. o. v. Sjö-Gunnarsbo san.\no. med. avd. v. las. i Halmstad 39-40,\nund:läk. v. kir. klin. i Malmö 41-44,\nv. med. klin. där 44-46, prakt. läk. i\nMalmö sed. 46.\n\nPetersen, Carl Rasmus, disponent,\nEslöv, f. 5/4/84 i Danm. av grossh. W.\nP. o. Laura Mailing. G. 10 m. Ellen\nBenzon. Barn: Boye f. 15,\natelier-chef, Lund, Gertie 19, g. m. mej :ing.\nErik Pollack, Vänersb. — Prel:ex.,\nhand:sk. Anst. i spannm:- o.\n’foderämnesfirmor i Danm., Tyskl., Engl. o.\nFrankr., disp. v. A-B Carl Engström i\nEslöv fr. 16. Led. av Sv. skiljend f.\nspannm:- o. foderämneshand. o. av\nSkånes hand:kamm. skiljend, av sv.\nhand:deleg. i Budapest 42. Medl. av\nEslövs ihemv. förtr :nd, v. ordf. i\nEslövs hemv. kamratfören., medl. av\nFrimurarorden. Hobbies: jakt, skjutning.\nProPatrstGM, DFrM, SkytteGM,\nB ef :utb :förb. komp : Gm, Mil. idrGm,\nGångförb. vandrGm.\n\nPetersen, Peter Gustav Theodor,\nmed. lic,\nuniversitetsinstrumentmaka-re, Lund, f. 31/3/02 i Halmstad av dir.\nKuno P. o. Ruth Tilliman. G. 34 m.\nMargit Engström. Barn: Malin f. 34,\nPeter 36, Eva 39, Sven 41. — Stud :ex.\ni Gbg 21, med. kand. 27, med. lic. 32\ni Lund. E. o. aman. v. fysiolog, inst.\ni Lund 25-26, aman. där 26-28, e. o.\naman. där 28-32 o. assist, där 32-35.\nUtn. t. univ :instr :ma’k. 32, inneh. av\nuniv. instr :makeri 32-40.\nProdukt:-cihef i Järnhs El, A-B i Sthlm 40-45,\nsed. 45 eg. rör. i Lund und. firma\nInstrumentverkstaden.\n\naf PeSersens, Fritz Axel, major,\nHälsingborg, f. 4/10/83 i Sävsjöström,\nKronob. 1., av här :hövd. Gösta af P.\no. Lotten Ribbing. G. 17 m. Sigrid\nBennet. Barn: Fritz f. 18, jur. kand.,\nlöjtn. i 1.1 res., Jan 20, kapten v.\nFlottan, Sthlm. — Off:vol. 02, AIHS, RS\no. SS. Und :löjtn. v. Wendes art :reg.\n04, kapten 18, major 33.   RSO, RDDO.\n\naf Petersens, Carl Lennart\nSebastian, major, Löddeköpinge, f. 13/6/81\npå Sävsjöström, Lenlrovda, Kronob. 1.,\nav v. här :hövd. Gustaf Herman af P.\n\no. Christina Charlotta Ribbing. G. 10\nm. Jacquette Bennet. Barn: Louise\nf. 11, g. m. commander Selwyn\nHar-rison, London, Fredrik 13, disp.,\nMalmö, Wilhelm 15, kapten, Sthlm,\nIngegärd 17, g. m. hovr :not. Sten Ohlsson,\nSthlm, Margaretha 23, g. m. frih.,\nkapt. v. P.2 Bror Carl Cederström^\nHässleholm. — Off:ex. 00, RS 01-02,\nKHS 06-08. Und:löjtn. v. Kronpr.\nhus :reg. 00, löjtn. 03’, ryttm. på res\n:-stat 24, transp. t. Norrl. drag:reg. res.\n28, avsk, 31, major i armén. Äg.\nLöddesborg i Skåne. RSO 21, ÖRKHt2kl.\n\nPeterzén, Åke Wilhelm, ingen jör,\ndirektör, Hälsingborg, f. 5/4/07 i\nLin-köp. G. 37 m. Birgit Borg. Barn: Ulla\nf. 41. — Avg:ex. v. tekn. elem:sk. i\nNorrköp. (färgtekn.) 28. Stud. v. univ. i\nBasel 29-30, stud :res. t. Tyskl., Schweiz,\nFrankr. o. 11 al. Anst. v. A. Borgs\nSöner A-B i Hälsingb. sed. 33, verk st.\ndir. där sed. 45. Rev. i Red. A-B\nSigne i Hälsingb. sed. 47. Medl. i 0’dd\nFellow o. Round Täble. Hobbies:\nrodd, bowling.   BowlSm.\n\nPetrén, Ebbe Oskar Sigfrid, fd.\növerläkare, Malmö, f. 18/5/78 i\nHalmstad, Malmöh. 1., av kyrkoh. Edv. P.\no. Charlotte Göransson. G. 14 m.\nBojan Arwidsson.    Barn: Karl-Ebbe f.\n\n18,  löjtn. v. I.il7, Siri 20, g. m. civ:ing.\nOlle Wiik, Malmö, Karin 23, g. m.\nlöjtn. L. Liljenström, Malmö. — Med.\nkand. i Lund 00, med. lic. 04, med.\nhed:dr 3!2, Aman. o. assist, v. patol.\ninst. i Lund, öv:läk. v. Malmö\nepid:-sjukh. 08-43, bitr. lär. v. med. fak. i\nLund 11-43, bakteriolog o. serolog v.\nMalmö allm. sjukh. 17-43. Vetemsk.\nråd i epidemiol. f. arméns sjukv:styr.,\nled. av komm. ang. vissa epidemiol.\nfrågor  18.    Skr.: upps. i epidemiol.\n\nPetrén, Erik Gustaf, professor emer.,\nLund, f. 11/8/74 i Halmstad, Malmöh.\n1., av kyrkoh. Edvard P. o. Charlotte\nGöransson. G. 11 im. fil. kand.\nTorborg Sylwan. Barn: Otto f. 12,\nhov-r:assess.,  Gustav  17, hovr :fiskal, Erik\n\n19,   fil. lic, Elsi 21, med. lic. — Fil.\nkand. i Lund 95, med. kand. 99, med.\nlic. 04, med. dr 11. Doc. i kir. 11,\nprof. i kir. i Upps. o. överläk. v. Akad.\nsjukh. 18, prof. i kir. i Lund 21-39,\növerläk. v. las. där s. å. Ordf. i styr.\nf. Södra Sv.es sjuksköt :hem 21-45,\nhedrled. av Dansk Kir. Selskab 43.\nSkr. tills. m. Nicolaysen o. Rovsing:\nNord. lärob. i kir. (22, andra uppl. tills.\n\nm. Ingebrigtsen o. Kjaergaard 32-34,\ntredje uppl. 40), vetensk. arb. o. tid\n-skr :upps.\n\nPetrén, Inge Henrik Eskil,\nläroverksadjunkt, Hälsingborg, f. 22/12/96\ni Åhus, Krist. 1., av lotsförman\nHerman P. o. Anna Staffansson. —\nStud:-ex. i Lund 15, fil. mag. där 20. Res.\nt. Tyskl., Engl, Frankr. Provar v.\nnorra latin ii Sthlm 24. Tjg. i\nKristinehamn, Tomelilla, Lysekil, Sthltm,\nHalmstad, Hälsingb. 20-3;6, adj. v. h.\na. 1. i Malmö 36-47, adj. i tyska o.\neng. v. h. a. 1. f. g. i Hälsingb. sed.\n47.\n\nPetrén, Gustaf Otto Edvard,\nhovrättsassessor, Malmö, f. 7/10/12 i Lund\nav prof. Gustaf P. o. Torborg Sylwan.\nG. 42 m. Margit Winroth. Barn:\nKarin f. 43, Rolf 46. — Stud :ex. i Lund\n30, jur. kand. där 35. Tingstjg. i\nVem-menhögs, Ljunits o. Herrestads doms.\n35-38, fiskal i Skånska hovr. 39,\nassessor där fr. 46.\n\nPetrén, Torborg Margareta, fru,\nLund, f. 27/5/79 i Vaxholm av\növ:-löjtn. O. Ch. Sylwan o. Ida Wendel.\nG. 11 m. prof. Gustaf Petrén. Barn:\nse denne. — Stud :ex. 98, fil. kand. 03.\nLär. v. Sigr. Rudebecks sk. i Gbg\n03-11, led. av stadsfurlm. i Lund 36-42, fd.\nled. av ett il ert. styr. o. ndr m. komm.\nel. soc. uppg. samt i Fredr.\nBremer-förb.   styr.\n\n",
    "structured": {
        "0": {
            "full_name": "Perulf, Nils Sture",
            "location": "Malmö",
            "occupation": "prakt, läkare",
            "birth_details": {
                "date": "28/12/1907",
                "place": "Lund"
            },
            "education": [
                {
                    "degree": "Stud.ex.",
                    "year": "1927",
                    "institution": "Lund"
                },
                {
                    "degree": "med. kand.",
                    "year": "1932",
                    "institution": "Lund"
                },
                {
                    "degree": "med. lic.",
                    "year": "1939",
                    "institution": "Lund"
                }
            ],
            "career": [
                {
                    "position": "div. kort. för-ordn. s. munic:- o. prov:läk.",
                    "years": {
                        "start_year": 1936,
                        "end_year": 1938
                    },
                    "organization": "Trelleborgs lasarett"
                },
                {
                    "position": "vik. und :läk. v. las.",
                    "years": {
                        "start_year": 1936,
                        "end_year": 1938
                    },
                    "organization": "S:t Lars sjukhus i Lund"
                },
                {
                    "position": "röntgenavd. v. las.",
                    "years": {
                        "start_year": 1936,
                        "end_year": 1938
                    },
                    "organization": "Hälsingborg"
                },
                {
                    "position": "v. Sjö-Gunnarsbo san. o. med. avd. v. las.",
                    "years": {
                        "start_year": 1939,
                        "end_year": 1940
                    }
                },
                {
                    "position": "und:läk. v. kir. klin. i Malmö",
                    "years": {
                        "start_year": 1941,
                        "end_year": 1944
                    }
                },
                {
                    "position": "v. med. klin. där",
                    "years": {
                        "start_year": 1944,
                        "end_year": 1946
                    }
                },
                {
                    "position": "prakt. läk. i Malmö",
                    "years": {
                        "start_year": 1946
                    }
                }
            ],
            "family": {
                "spouse": "Astrid Andersson",
                "marriage_year": "1939",
                "children": [
                    {
                        "name": "Peter",
                        "birth_year": "1940"
                    },
                    {
                        "name": "Marianne",
                        "birth_year": "1942"
                    },
                    {
                        "name": "Thomas",
                        "birth_year": "1943"
                    }
                ]
            }
        },
        "1": {
            "full_name": "Petersen, Carl Rasmus",
            "location": "Eslöv",
            "occupation": "disponent",
            "birth_details": {
                "date": "5/4/1884",
                "place": "Danmark"
            },
            "education": [
                {
                    "degree": "Prel:ex.",
                    "institution": "hand:sk"
                }
            ],
            "career": [
                {
                    "position": "disp. v. A-B Carl Engström i Eslöv",
                    "years": {
                        "start_year": 1916
                    }
                },
                {
                    "position": "Led. av Sv. skiljend f. spannm:- o. foderämneshand",
                    "organization": "Skånes hand:kamm."
                },
                {
                    "position": "medl. av Eslövs ihemv. förtr :nd"
                },
                {
                    "position": "v. ordf. i Eslövs hemv. kamratfören."
                }
            ],
            "family": {
                "spouse": "Ellen Benzon",
                "marriage_year": "1910",
                "children": [
                    {
                        "name": "Boye",
                        "birth_year": "1915"
                    },
                    {
                        "name": "Gertie"
                    }
                ]
            },
            "hobbies": [
                "jakt",
                "skjutning"
            ]
        },
        "2": {
            "full_name": "Petersen, Peter Gustav Theodor",
            "location": "Lund",
            "occupation": "universitetsinstrumentmakare",
            "birth_details": {
                "date": "31/3/1902",
                "place": "Halmstad"
            },
            "education": [
                {
                    "degree": "Stud.ex.",
                    "year": "1921",
                    "institution": "Gbg"
                },
                {
                    "degree": "med. kand.",
                    "year": "1927",
                    "institution": "Lund"
                },
                {
                    "degree": "med. lic.",
                    "year": "1932",
                    "institution": "Lund"
                }
            ],
            "career": [
                {
                    "position": "E. o. aman. v. fysiolog, inst. i Lund",
                    "years": {
                        "start_year": 1925,
                        "end_year": 1928
                    }
                },
                {
                    "position": "Produkt:-cihef i Järnhs El, A-B i Sthlm",
                    "years": {
                        "start_year": 1940,
                        "end_year": 1945
                    }
                }
            ],
            "family": {
                "spouse": "Margit Engström",
                "marriage_year": "1934",
                "children": [
                    {
                        "name": "Malin",
                        "birth_year": "1934"
                    },
                    {
                        "name": "Peter",
                        "birth_year": "1936"
                    },
                    {
                        "name": "Eva",
                        "birth_year": "1939"
                    },
                    {
                        "name": "Sven",
                        "birth_year": "1941"
                    }
                ]
            }
        },
        "3": {
            "full_name": "af PeSersens, Fritz Axel",
            "location": "Hälsingborg",
            "occupation": "major",
            "birth_details": {
                "date": "4/10/1883",
                "place": "Sävsjöström, Kronob. 1."
            },
            "career": [
                {
                    "position": "Off:vol.",
                    "organization": "AIHS, RS, SS"
                },
                {
                    "position": "Und :löjtn. v. Wendes art :reg.",
                    "years": {
                        "start_year": 1904,
                        "end_year": 1918
                    }
                },
                {
                    "position": "kapten v. Flottan",
                    "organization": "Sthlm"
                }
            ],
            "honorary_titles": [
                {
                    "title": "RSO"
                },
                {
                    "title": "RDDO"
                }
            ]
        },
        "4": {
            "full_name": "af Petersens, Carl Lennart Sebastian",
            "location": "Löddeköpinge",
            "occupation": "major",
            "birth_details": {
                "date": "13/6/1881",
                "place": "Sävsjöström, Lenlrovda, Kronob. 1."
            },
            "career": [
                {
                    "position": "Off:ex."
                },
                {
                    "position": "ÖRKHt2kl."
                }
            ],
            "family": {
                "spouse": "Jacquette Bennet",
                "marriage_year": "1910",
                "children": [
                    {
                        "name": "Louise",
                        "birth_year": "1911"
                    },
                    {
                        "name": "Fredrik",
                        "birth_year": "1913"
                    },
                    {
                        "name": "Wilhelm",
                        "birth_year": "1915"
                    },
                    {
                        "name": "Ingegärd",
                        "birth_year": "1917"
                    },
                    {
                        "name": "Margaretha",
                        "birth_year": "1923"
                    }
                ]
            }
        },
        "5": {
            "full_name": "Peterzén, Åke Wilhelm",
            "location": "Hälsingborg",
            "occupation": "ingenjör, direktör",
            "birth_details": {
                "date": "5/4/1907",
                "place": "Linköp."
            },
            "education": [
                {
                    "degree": "Avg:ex. v. tekn. elem:sk. i Norrköp.",
                    "year": "1928"
                }
            ],
            "career": [
                {
                    "position": "Anst. v. A. Borgs Söner A-B i Hälsingb",
                    "years": {
                        "start_year": 1933
                    }
                },
                {
                    "position": "verk st. dir. där",
                    "years": {
                        "start_year": 1945
                    }
                }
            ],
            "family": {
                "spouse": "Birgit Borg",
                "marriage_year": "1937",
                "children": [
                    {
                        "name": "Ulla",
                        "birth_year": "1941"
                    }
                ]
            },
            "hobbies": [
                "rodd",
                "bowling"
            ]
        },
        "6": {
            "full_name": "Petrén, Ebbe Oskar Sigfrid",
            "location": "Malmö",
            "occupation": "fd. överläkare",
            "birth_details": {
                "date": "18/5/1878",
                "place": "Halmstad, Malmöh. 1."
            },
            "education": [
                {
                    "degree": "Med. kand.",
                    "year": "1900",
                    "institution": "Lund"
                }
            ],
            "career": [
                {
                    "position": "öv:läk. v. Malmö epid:-sjukh.",
                    "years": {
                        "start_year": 1908,
                        "end_year": 1943
                    }
                },
                {
                    "position": "bitr. lär. v. med. fak. i Lund",
                    "years": {
                        "start_year": 1911,
                        "end_year": 1943
                    }
                },
                {
                    "position": "bakteriolog o. serolog v. Malmö allm. sjukh.",
                    "years": {
                        "start_year": 1917,
                        "end_year": 1943
                    }
                }
            ],
            "family": {
                "spouse": "Bojan Arwidsson",
                "marriage_year": "1914",
                "children": [
                    {
                        "name": "Karl-Ebbe",
                        "birth_year": "1918"
                    },
                    {
                        "name": "Siri",
                        "birth_year": "1920"
                    },
                    {
                        "name": "Karin",
                        "birth_year": "1923"
                    }
                ]
            }
        },
        "7": {
            "full_name": "Petrén, Erik Gustaf",
            "location": "Lund",
            "occupation": "professor emer.",
            "birth_details": {
                "date": "11/8/1874",
                "place": "Halmstad, Malmöh. 1."
            },
            "education": [
                {
                    "degree": "Fil. kand.",
                    "year": "1895",
                    "institution": "Lund"
                },
                {
                    "degree": "med. kand.",
                    "year": "1899",
                    "institution": "Lund"
                },
                {
                    "degree": "med. lic.",
                    "year": "1904",
                    "institution": "Lund"
                },
                {
                    "degree": "med. dr",
                    "year": "1911"
                }
            ],
            "career": [
                {
                    "position": "Doc. i kir.",
                    "years": {
                        "start_year": 1911
                    },
                    "organization": "Upps."
                },
                {
                    "position": "prof. i kir.",
                    "years": {
                        "start_year": 1921,
                        "end_year": 1939
                    },
                    "organization": "Lund"
                }
            ],
            "family": {
                "spouse": "Torborg Sylwan",
                "marriage_year": "1911",
                "children": [
                    {
                        "name": "Otto",
                        "birth_year": "1912"
                    },
                    {
                        "name": "Gustav",
                        "birth_year": "1917"
                    },
                    {
                        "name": "Erik",
                        "birth_year": "1919"
                    },
                    {
                        "name": "Elsi",
                        "birth_year": "1921"
                    }
                ]
            }
        },
        "8": {
            "full_name": "Petrén, Inge Henrik Eskil",
            "location": "Hälsingborg",
            "occupation": "läroverksadjunkt",
            "birth_details": {
                "date": "22/12/1896",
                "place": "Åhus, Krist. 1."
            },
            "education": [
                {
                    "degree": "Stud:-ex.",
                    "year": "1915",
                    "institution": "Lund"
                },
                {
                    "degree": "fil. mag.",
                    "year": "1920",
                    "institution": "Lund"
                }
            ],
            "career": [
                {
                    "position": "adj. v. h. a. 1. i Malmö",
                    "years": {
                        "start_year": 1936,
                        "end_year": 1947
                    }
                }
            ]
        },
        "9": {
            "full_name": "Petrén, Gustaf Otto Edvard",
            "location": "Malmö",
            "occupation": "hovrättsassessor",
            "birth_details": {
                "date": "7/10/1912",
                "place": "Lund"
            },
            "education": [
                {
                    "degree": "Stud:-ex.",
                    "year": "1930",
                    "institution": "Lund"
                },
                {
                    "degree": "jur. kand.",
                    "year": "1935",
                    "institution": "Lund"
                }
            ],
            "career": [
                {
                    "position": "Tingstjg. i Vemmenhögs, Ljunits o. Herrestads doms.",
                    "years": {
                        "start_year": 1935,
                        "end_year": 1938
                    }
                },
                {
                    "position": "fiskal i Skånska hovr.",
                    "years": {
                        "start_year": 1939,
                        "end_year": 1946
                    }
                }
            ],
            "family": {
                "spouse": "Margit Winroth",
                "marriage_year": "1942",
                "children": [
                    {
                        "name": "Karin",
                        "birth_year": "1943"
                    },
                    {
                        "name": "Rolf",
                        "birth_year": "1946"
                    }
                ]
            }
        },
        "10": {
            "full_name": "Petrén, Torborg Margareta",
            "location": "Lund",
            "family": {
                "spouse": "prof. Gustaf Petrén",
                "marriage_year": "1911"
            },
            "education": [
                {
                    "degree": "Stud:-ex.",
                    "year": "1898",
                    "institution": "Vaxholm"
                },
                {
                    "degree": "fil. kand.",
                    "year": "1903"
                }
            ],
            "community_involvement": [
                {
                    "role": "led. av stadsfurlm. i Lund",
                    "years": "1936-1942"
                },
                {
                    "role": "fd. led. av ett il ert. styr. o. ndr m. komm. el. soc. uppg. samt i Fredr. Bremerförb. styr."
                }
            ]
        }
    }
}