{
    "original": "Persson, Torsten Fritiof,\ncivilingenjör, Malmö, f. 28/9/12 i Vinslöv, Krist.\n1, G. 38 m. Inez Clarkson. Barn:\nElisabeth 1 43, Thomas 47. —\nStud:-ex. i Kristianstad 31, avg:ex. v. KTH\n(V) 36. Chef f. vägavd. v. A-B\nMa-taki  i  Malmö.\n\nPersson, Karl Thorsten, jur. kand.,\nadvokat, Kristianstad, if. 21/7/96 i\nKrist, av grossh. Thure P. o. Alfrida\nBygren. G. 25 m. Eva Åkerman. Barn:\nNils-Thure   f.   26,   Hans-Thorsten   33.\n\n— Stud:ex. i Krist. 14, jur. kand. i\nLund 18. Tingstjg. i Ö. Göinge doms.\n19-22, tf. ass. v. rådh:rätt. i Hälsingb.\n22, tf. borgm. i Sölvesborg 22, anst. å\nadv:byrå i Malmö 23-25, adv. i Sthlm\n25-33-, kronouppb :kassör i Krist. 33L34,\nadv. i Krist. sed. 34. Led. av Sv:es\nadv :samf. sed. 34.\n\nPersson, Thure Henry,\nfolkskollärare, Marieholm, f. 25/2/01 i Malmö av\nNils o. Thilda P. G. 29 m. Ella\nMaria Bengtsson. Barn: Hans-Börje f.\n31, Åke 37. — Folkskoll:ex. 26. Vik.\nfolkskoll. i Marieholm 26, i Alnarp o.\nN. Åsum 27, i Reslöv 27, ord. där sed.\n29, underv. i slöjd o. forts :sk. Ordf.\ni komm:fullm. o. fattigv:styr., led. av\nkomm:nd, kyrkofullm., kyrkoråd o.\npens :nd. Lär :kår. repr. Res. i Tyskl. o.\nFrankr. 37.\n\nPehrsson-Bramstorp, Axel Alarik,\nriksdagsman, iörutv. statsminister,\nSödra Åby, f. 19/8/83 i Öja, Malmöh.\n1., av förv. Jac. P. o. Ingrid P. G.\n08 :m. Sigrid Nilsson. — Genomg.\nfolk-högsk. Eg. jordbr. sed. 08, arrend. L.\nIsie kronobost. sed. 20. Led. av\nMalmöh. 1. landst. sed. 12, ordf. i dess\nfin:- o. ciiv:utsk. sed. 27, ordf. i L.\nIsie komm :nd o. -stämma sed. 14, led.\nav riksd. andra kamm. 18-21, 29-32 o.\nsed. 34 (talm:konf., utr:nd, b’f),\nstatsråd o. chef f. jordbr :dep. 36-45,\nstatsmin. 19/6-28/9 36, led. av Malmöh. 1.\nprövn :nd sed. 22, Vemmenhögs här.\nvägstyr. sed. 20, ordf. där sed. 26, v.\nordf. i Malmön. ,1. hush :sällsk. sed.\n27, led. av styr. f. A-B Skånska\nBanken i Malmö sed. 28, f. Vemmenhögs\nHär. Sparbank 29-40, Jordberga\nbet-odl :’fören. 23-43, ordf. där 29, led. av\nstyr. f. Skånska betodl. centr :tfören.\n22-43, ordf. där fr. 31, led. av o. v. ordf.\ni styr. f. Sydv. Skånes andelsslakt\n:-fören. samt ordf. i arb :utsk. 23-41, led.\nav styr. f. Fören. av ,sv. andelsslakt. fr.\n26, ordf. där 27-36, led. av s. k. jordbr\n:-utredn. 29-34, led. o. v. ordf. i stat.\nspannm :nd sed. 30, stat. repr. i styr.\nf. Allm. Sv. Utsädes A-B á Svalöv\nsamt i Sv:es utsädesfören. 25-36, ordf.\ni eckl. bost :nd f. Oxie o. Skytts här.\ndoms. o. Vemimenhögs m. fl. här.\ndoms. 27-35, led. av styr. f. Sv:es allm.\nlantbr :sällsk. sed. 30, ordf. i Sv:es\nlantbr:för!b. sed. 46. KmstkNO, RVO,\nStkFinlVRO, StkNedONO, LLA.\n\n",
    "structured": {
        "1": {
            "full_name": "Torsten Fritiof Persson",
            "location": "Malmö",
            "occupation": "Civilingenjör",
            "birth_details": {
                "date": "28/09/1912",
                "place": "Vinslöv"
            },
            "family": {
                "spouse": "Inez Clarkson",
                "marriage_year": "1938",
                "children": [
                    {
                        "name": "Elisabeth",
                        "birth_year": "1943"
                    },
                    {
                        "name": "Thomas",
                        "birth_year": "1947"
                    }
                ]
            },
            "education": [
                {
                    "degree": "Stud:ex.",
                    "year": "1931",
                    "institution": "Kristianstad"
                },
                {
                    "degree": "Avg:ex. v. KTH (V)",
                    "year": "1936",
                    "institution": "KTH"
                }
            ],
            "career": [
                {
                    "position": "Chef f. vägavd. v. A-B Ma-taki",
                    "years": {
                        "start_year": null,
                        "end_year": null
                    },
                    "organization": "Malmö"
                }
            ]
        },
        "2": {
            "full_name": "Karl Thorsten Persson",
            "location": "Kristianstad",
            "occupation": "Advokat",
            "birth_details": {
                "date": "21/07/1896",
                "place": "Kristianstad"
            },
            "family": {
                "spouse": "Eva Åkerman",
                "marriage_year": "1925",
                "children": [
                    {
                        "name": "Nils-Thure",
                        "birth_year": "1926"
                    },
                    {
                        "name": "Hans-Thorsten",
                        "birth_year": "1933"
                    }
                ]
            },
            "education": [
                {
                    "degree": "Stud:ex.",
                    "year": "1914",
                    "institution": "Kristianstad"
                },
                {
                    "degree": "Jur. kand.",
                    "year": "1918",
                    "institution": "Lund"
                }
            ],
            "career": [
                {
                    "position": "Adv.",
                    "years": {
                        "start_year": 1925,
                        "end_year": 1933
                    },
                    "organization": "Sthlm"
                },
                {
                    "position": "Tf. ass. v. rådh:rätt. i Hälsingb.",
                    "years": {
                        "start_year": 1922,
                        "end_year": 1922
                    },
                    "organization": "NULL"
                },
                {
                    "position": "Tf. borgm. i Sölvesborg",
                    "years": {
                        "start_year": 1922,
                        "end_year": 1922
                    },
                    "organization": "NULL"
                },
                {
                    "position": "Anst. å adv:byrå i Malmö",
                    "years": {
                        "start_year": 1923,
                        "end_year": 1925
                    },
                    "organization": "NULL"
                },
                {
                    "position": "Kronouppb :kassör i Krist.",
                    "years": {
                        "start_year": 1933,
                        "end_year": 1934
                    },
                    "organization": "NULL"
                },
                {
                    "position": "Adv. i Krist.",
                    "years": {
                        "start_year": 1934,
                        "end_year": 1934
                    },
                    "organization": "NULL"
                }
            ]
        },
        "3": {
            "full_name": "Thure Henry Persson",
            "location": "Marieholm",
            "occupation": "Folkskollärare",
            "birth_details": {
                "date": "25/02/1901",
                "place": "Malmö"
            },
            "family": {
                "spouse": "Ella Maria Bengtsson",
                "marriage_year": "1929",
                "children": [
                    {
                        "name": "Hans-Börje",
                        "birth_year": "1931"
                    },
                    {
                        "name": "Åke",
                        "birth_year": "1937"
                    }
                ]
            },
            "education": [
                {
                    "degree": "Folksk:ex.",
                    "year": "1926",
                    "institution": "NULL"
                }
            ],
            "career": [
                {
                    "position": "Ord.",
                    "years": {
                        "start_year": 1929,
                        "end_year": 1929
                    },
                    "organization": "Reslöv"
                },
                {
                    "position": "Ordf.",
                    "years": {
                        "start_year": null,
                        "end_year": null
                    },
                    "organization": "komm:fullm."
                },
                {
                    "position": "Ord.",
                    "years": {
                        "start_year": null,
                        "end_year": null
                    },
                    "organization": "komm:nd"
                },
                {
                    "position": "Ordf.",
                    "years": {
                        "start_year": null,
                        "end_year": null
                    },
                    "organization": "kyrkofullm."
                },
                {
                    "position": "Ordf.",
                    "years": {
                        "start_year": null,
                        "end_year": null
                    },
                    "organization": "kyrkoråd"
                },
                {
                    "position": "Lär :kår. repr.",
                    "years": {
                        "start_year": 1937,
                        "end_year": 1937
                    },
                    "organization": "Tyskland"
                },
                {
                    "position": "Lär :kår. repr.",
                    "years": {
                        "start_year": 1937,
                        "end_year": 1937
                    },
                    "organization": "Frankrike"
                }
            ]
        },
        "4": {
            "full_name": "Axel Alarik Pehrsson-Bramstorp",
            "location": "Södra Åby",
            "occupation": "Riksdagsman, Förutv. statsminister",
            "birth_details": {
                "date": "19/08/1883",
                "place": "Öja"
            },
            "family": {
                "spouse": "Sigrid Nilsson",
                "marriage_year": "1908",
                "children": []
            },
            "education": [
                {
                    "degree": "Genomg.",
                    "year": "NULL",
                    "institution": "folk-högsk."
                }
            ],
            "career": [
                {
                    "position": "Eg. jordbr.",
                    "years": {
                        "start_year": 1908,
                        "end_year": 1908
                    },
                    "organization": "NULL"
                },
                {
                    "position": "Led. av Malmöh. 1. landst.",
                    "years": {
                        "start_year": 1912,
                        "end_year": 1912
                    },
                    "organization": "NULL"
                },
                {
                    "position": "Ordf.",
                    "years": {
                        "start_year": 1914,
                        "end_year": 1914
                    },
                    "organization": "L. Isie komm :nd o. -stämma"
                },
                {
                    "position": "Led. av riksd. andra kamm.",
                    "years": {
                        "start_year": 1918,
                        "end_year": 1921
                    },
                    "organization": "NULL"
                },
                {
                    "position": "Statsråd o. chef f. jordbr :dep.",
                    "years": {
                        "start_year": 1936,
                        "end_year": 1945
                    },
                    "organization": "NULL"
                },
                {
                    "position": "Ordf.",
                    "years": {
                        "start_year": 1926,
                        "end_year": 1926
                    },
                    "organization": "Vemmenhögs här. vägstyr."
                },
                {
                    "position": "V. ordf.",
                    "years": {
                        "start_year": null,
                        "end_year": null
                    },
                    "organization": "Malmöh. ,1. hush :sällsk."
                },
                {
                    "position": "Led. av styr. f. A-B Skånska Banken i Malmö",
                    "years": {
                        "start_year": 1928,
                        "end_year": 1928
                    },
                    "organization": "Vemmenhögs Här. Sparbank"
                },
                {
                    "position": "Ordf.",
                    "years": {
                        "start_year": 1929,
                        "end_year": 1940
                    },
                    "organization": "Jordberga bet-odl :’fören."
                },
                {
                    "position": "Led. av styr.",
                    "years": {
                        "start_year": 1922,
                        "end_year": 1943
                    },
                    "organization": "Skånska betodl. centr :tfören."
                },
                {
                    "position": "Ordf.",
                    "years": {
                        "start_year": 1931,
                        "end_year": 1943
                    },
                    "organization": "Skånska betodl. centr :tfören."
                },
                {
                    "position": "Ordf.",
                    "years": {
                        "start_year": 1927,
                        "end_year": 1927
                    },
                    "organization": "styr. f. Fören. av ,sv. andelsslakt."
                },
                {
                    "position": "Led. av styr.",
                    "years": {
                        "start_year": 1926,
                        "end_year": 1936
                    },
                    "organization": "Sv:es allm. lantbr :sällsk."
                },
                {
                    "position": "Ordf.",
                    "years": {
                        "start_year": 1946,
                        "end_year": 1946
                    },
                    "organization": "Sv:es lantbr:förb."
                }
            ],
            "honorary_titles": [
                {
                    "title": "KmstkNO",
                    "institution": "NULL",
                    "year": "NULL"
                },
                {
                    "title": "RVO",
                    "institution": "NULL",
                    "year": "NULL"
                },
                {
                    "title": "StkFinlVRO",
                    "institution": "NULL",
                    "year": "NULL"
                },
                {
                    "title": "StkNedONO",
                    "institution": "NULL",
                    "year": "NULL"
                },
                {
                    "title": "LLA",
                    "institution": "NULL",
                    "year": "NULL"
                }
            ]
        }
    }
}