{
    "original": "Planthin, J. Birger E.,\nfolkskollärare, kantor, Jordholmen, f. 20/10/05 i\nVäsby, Malmöh. 1., av tegelmäst. J. W.\no. Hilda P. G. 30 m. Agnes Rosberg.\nBarn: Ingegerd f. 32. — Folks kol 1: ex.\ni Lund 28, org:- o. kyrkosrex. i Växjö\n\n31.     Org. o. folkskoll. i Särslöv 29-39,\ni V. Ingelstad sed. 40. Ordf. i V.\nIngelstads GIF sed. 41, v. ordf. i\nMåns torps skyttegille sed. 42.\nHolb-bies:  skytte, biskötsel.\n\nPlantin, Gustav Henry Sigvard,\nkomminister, Eket, f. 7/7/10 i Östra\nGrevie, Malmöh. 1. G. m. Sonja\nIngegerd Lundh. Barn: Jan f. 37,\nCatharina 42. — Stud:ex. i Malmö 30, teol\nfil. ex. 3’2, teol. kand. o. prästv. f.\nLunds stift 36. Tjg. s. v. pastor i\nVitt-skövle o. Billeberga, past :adj. där o.\ni B år slö v, tf. kommin. i Sillhövda,\nkoimmin. i Örkelljunga o. Rya sed. 47.\n\nvon Plåten, David Julius Gösta, fd.\nryttmästare,, Malmö, «f. 6/3/82 i\nKallna, Krist. 1, av överste Gustaf v. P.\no. Alida Hummel. G. 12 m. Elsa\nMuller. Barn: Brita f. 19, g. m. löjtn.\nCarl-Axel Falck, Kristianstad. —\nStud:ex. i Lund 00, offrex. 03, GCI\n08-10, SS. Und:löjtn. v. Kronpr.\nhus:-reg.   03,   löjtn.   07,   ryttmäst.   18,   avsk.\n\n32,   i Kav. res. t. 47. Led. av\nstads-fullm. i Malmö 20-24 o. 30-38 samt av\nmuseistyr., v. ordf. i styr. f. Skånska\nBrandförsäkr :inrättn., stj^rrled. i A-B\nTretorn, rev. i Skand. Bank. A-B o.\nverkst. dir. i A-B Hippodromen. RSO,\nRVO, RBLeopO, 2 GM.\n\nvon Plåten, Wilhelm Algernon,\ngodsägare, Övrabyborg, Svenstorp, f.\n16/7/87 i Källstorp, Malmöh. 1, av\nkammarh. W. von P. o. Sophie\nMat-zen. G. 17 m. Greta Franzén. Barn:\nAchates f. 18. —■ Genomg. Alnarps\nlantbr:inst. 06-08, lantbr :stud. i Tyskl.\n09. Dir. i A-B Övrabyborg,\nNämndeman i Ingelstads o. Järrestads här\n:-rätt. RJohO.\n\n",
    "structured": {
        "0": {
            "full_name": "Planthin, J. Birger E.",
            "location": "Jordholmen",
            "occupation": "folkskollärare, kantor",
            "birth_details": {
                "date": "20/10/1905",
                "place": "Väsby"
            },
            "education": [
                {
                    "degree": "folks kol 1",
                    "year": "1928",
                    "institution": "Lund"
                }
            ],
            "career": [
                {
                    "position": "org:- o. kyrkosrex. i Växjö",
                    "years": {
                        "start_year": 1931,
                        "end_year": 0
                    },
                    "organization": "Växjö"
                },
                {
                    "position": "Org. o. folkskoll. i Särslöv",
                    "years": {
                        "start_year": 1929,
                        "end_year": 1939
                    },
                    "organization": "Särslöv"
                },
                {
                    "position": "i V. Ingelstad",
                    "years": {
                        "start_year": 1940,
                        "end_year": 0
                    },
                    "organization": "V. Ingelstad"
                }
            ],
            "family": {
                "spouse": "Agnes Rosberg",
                "marriage_year": "1930",
                "children": [
                    {
                        "name": "Ingegerd",
                        "birth_year": "1932"
                    }
                ]
            }
        },
        "1": {
            "full_name": "Plantin, Gustav Henry Sigvard",
            "location": "Eket",
            "occupation": "komminister",
            "birth_details": {
                "date": "7/7/1910",
                "place": "Östra Grevie"
            },
            "education": [
                {
                    "degree": "Stud:ex.",
                    "year": "1930",
                    "institution": "Malmö"
                },
                {
                    "degree": "teol fil. ex.",
                    "year": "1932",
                    "institution": "Lunds stift"
                }
            ],
            "career": [
                {
                    "position": "tjg. s. v. pastor i Vitt-skövle o. Billeberga",
                    "years": {
                        "start_year": 0,
                        "end_year": 0
                    },
                    "organization": "Vitt-skövle o. Billeberga"
                },
                {
                    "position": "past :adj. där o. i B år slö v",
                    "years": {
                        "start_year": 0,
                        "end_year": 0
                    },
                    "organization": "B år slö v"
                },
                {
                    "position": "tf. kommin. i Sillhövda",
                    "years": {
                        "start_year": 0,
                        "end_year": 0
                    },
                    "organization": "Sillhövda"
                },
                {
                    "position": "koimmin. i Örkelljunga o. Rya",
                    "years": {
                        "start_year": 1947,
                        "end_year": 0
                    },
                    "organization": "Örkelljunga o. Rya"
                }
            ],
            "family": {
                "spouse": "Sonja Ingegerd Lundh",
                "marriage_year": "NULL",
                "children": [
                    {
                        "name": "Jan",
                        "birth_year": "1937"
                    },
                    {
                        "name": "Catharina",
                        "birth_year": "1942"
                    }
                ]
            }
        },
        "2": {
            "full_name": "von Plåten, David Julius Gösta",
            "location": "Malmö",
            "occupation": "fd. ryttmästare",
            "birth_details": {
                "date": "6/3/1882",
                "place": "Kallna"
            },
            "education": [
                {
                    "degree": "Stud:ex.",
                    "year": "1900",
                    "institution": "Lund"
                },
                {
                    "degree": "offrex.",
                    "year": "1903",
                    "institution": "NULL"
                }
            ],
            "career": [
                {
                    "position": "löjtn.",
                    "years": {
                        "start_year": 1907,
                        "end_year": 0
                    },
                    "organization": "NULL"
                },
                {
                    "position": "ryttmäst.",
                    "years": {
                        "start_year": 1918,
                        "end_year": 1932
                    },
                    "organization": "NULL"
                },
                {
                    "position": "avsk.",
                    "years": {
                        "start_year": 1932,
                        "end_year": 1947
                    },
                    "organization": "Kav. res."
                }
            ],
            "family": {
                "spouse": "Elsa Muller",
                "marriage_year": "1912",
                "children": [
                    {
                        "name": "Brita",
                        "birth_year": "1919",
                        "NULL": "löjtn."
                    }
                ]
            }
        },
        "3": {
            "full_name": "von Plåten, Wilhelm Algernon",
            "location": "Svenstorp",
            "occupation": "godsägare",
            "birth_details": {
                "date": "16/7/1887",
                "place": "Källstorp"
            },
            "education": [
                {
                    "degree": "NULL",
                    "year": "NULL",
                    "institution": "Alnarps lantbr:inst. 06-08"
                },
                {
                    "degree": "NULL",
                    "year": "NULL",
                    "institution": "lantbr :stud. i Tyskl. 09"
                }
            ],
            "career": [
                {
                    "position": "Dir. i A-B Övrabyborg",
                    "years": {
                        "start_year": 0,
                        "end_year": 0
                    },
                    "organization": "A-B Övrabyborg"
                }
            ],
            "family": {
                "spouse": "Greta Franzén",
                "marriage_year": "1917",
                "children": [
                    {
                        "name": "Achates",
                        "birth_year": "1918"
                    }
                ]
            }
        }
    }
}