{
    "original": "Björkman, Carl Magnus, överste,\nKalmar, f. 20/12/92 i Eksjö av\nmajoren Axel Edvard B. o. Daisy Goslett.\nG. 18 m. Märta Lokrantz. Barn:\nBengt f. 19, flyging., Britta 20, g. m.\ntrafikled. Frank af Petersens, Lars 29.\n— Stud:ex. i Linköp. 12, off :ex. 14,\nGCI 23, KHS 24-26. Stud. tyska arméns\noff :utbildn. v. Kriegsschule Dresden o.\nInfanterieschule Döberitz 37.\nUnd:-löjtn. v. Andra livgren :reg. 14, löjtn.\n18, kapt. i Livgren :reg. 29, v. reg. 33,\nmajor v. Norra skånska inf :reg. 37,\nmajor o. ställf. chef v. KS 40,\növ:-löjtn. v. Västernorrl. reg. 41, överste\ni armén o. fobefälh. i Kalmar fo 44,\nfobefälhav. i Kalmar-Växjö fo sed. 47.\nOrdf. i Kalmar fo bef :utb :förb. sed.\n45, led. av styr. (ordf. i verkst. utsk.)\nf. Kalmar 1. hemv:förb. sed. 45, ordf. i\n\n\nsamarb ikomm. f. friv. försv:org. i\nKailmar 1. sed. 45, Kgd. Maj :ts omb. i\nstyr. f. Kalmar 1. s. skytteförb. sed.\n47. RSO, RFinlVROlkl, RDDO,\nLandst:’SM, Kalmar Fo bfb GM,\nÖs-tergötl. o. ’landst :förb. SM, SkytteM.\n\nBjörkman, Carl Fridolf Emanuel,\ntandläkare, Göteborg, f. 26/9/92 i\nJämjö, Blek. 1., av folkskollär. N.\nBjörkman o. Karolina Sjögren. G. 16\nm. tandl. Kerstin Billing. Barn:\nMargit f. 21, Inger 25. — Studiex. i Lund\n12, tandhkand. 13, tandl. 15. Prakt,\ni Gbg sed. 16. Skattmäst. i Gbgs\ntandl isällsk. 23-25, sekr. 26, ordf. i\nAeoilus club.\n\nBjörkman, Göran Linus Gösta\nRai-mundo, kyrkoherde. Ringas, f. 16/3/07\ni Sthlm av förste aktuarien i\nkomm:-koll., fil. dr Göran B. o. Ebba Frey.\n— Stud:ex. i Sthlm 26, teol. fil. ex.\n28, teol. kand., prakt. teol. prov samt\nprästv. f. Linköp. stift 31. V.\nkom-min. i Risinge 31, kyrkoadj. där 32,\nkommdn. i Järeda 36, utn. kyrkoh. i\nOdensvi 39, i Örtomta sed. 45.\n\n",
    "structured": {
        "1": {
            "full_name": "Björkman, Carl Magnus",
            "location": "Kalmar",
            "occupation": "Överste",
            "birth_details": {
                "date": "20/12/1892",
                "place": "Eksjö",
                "parents": "majoren Axel Edvard B. o. Daisy Goslett"
            },
            "education": [
                {
                    "degree": "Stud:ex.",
                    "year": "1912",
                    "institution": "Linköp"
                },
                {
                    "degree": "Off :ex.",
                    "year": "1914",
                    "institution": "NULL"
                },
                {
                    "degree": "GCI",
                    "year": "1923",
                    "institution": "NULL"
                },
                {
                    "degree": "KHS",
                    "year": "1924-1926",
                    "institution": "NULL"
                },
                {
                    "degree": "Stud. tyska arméns off :utbildn.",
                    "year": "1937",
                    "institution": "Kriegsschule Dresden o. Infanterieschule Döberitz"
                }
            ],
            "career": [
                {
                    "position": "Und:-löjtn. v. Andra livgren :reg.",
                    "years": {
                        "start_year": 1914,
                        "end_year": 1918
                    },
                    "organization": "NULL"
                },
                {
                    "position": "Löjtn.",
                    "years": {
                        "start_year": 1918,
                        "end_year": 1929
                    },
                    "organization": "NULL"
                },
                {
                    "position": "Kapt. i Livgren :reg.",
                    "years": {
                        "start_year": 1929,
                        "end_year": 1933
                    },
                    "organization": "NULL"
                },
                {
                    "position": "V. reg.",
                    "years": {
                        "start_year": 1933,
                        "end_year": 1937
                    },
                    "organization": "NULL"
                },
                {
                    "position": "Major v. Norra skånska inf :reg.",
                    "years": {
                        "start_year": 1937,
                        "end_year": 1940
                    },
                    "organization": "NULL"
                },
                {
                    "position": "Major o. ställf. chef v. KS",
                    "years": {
                        "start_year": 1940,
                        "end_year": 1941
                    },
                    "organization": "NULL"
                },
                {
                    "position": "Öv:-löjtn. v. Västernorrl. reg.",
                    "years": {
                        "start_year": 1941,
                        "end_year": 1944
                    },
                    "organization": "NULL"
                },
                {
                    "position": "Överste i armén o. fobefälh. i Kalmar",
                    "years": {
                        "start_year": 1944,
                        "end_year": "s.d."
                    },
                    "organization": "NULL"
                }
            ],
            "family": {
                "spouse": "Märta Lokrantz",
                "marriage_year": "NULL",
                "children": [
                    {
                        "name": "Bengt",
                        "birth_year": "1919"
                    },
                    {
                        "name": "Britta",
                        "birth_year": "1920"
                    },
                    {
                        "name": "Lars",
                        "birth_year": "1929"
                    }
                ]
            }
        },
        "2": {
            "full_name": "Björkman, Carl Fridolf Emanuel",
            "location": "Göteborg",
            "occupation": "Tandläkare",
            "birth_details": {
                "date": "26/09/1892",
                "place": "Jämjö, Blek. 1.",
                "parents": "folkskollär. N. Björkman o. Karolina Sjögren"
            },
            "education": [
                {
                    "degree": "Studiex.",
                    "year": "1912",
                    "institution": "Lund"
                },
                {
                    "degree": "Tandhkand.",
                    "year": "1913",
                    "institution": "NULL"
                },
                {
                    "degree": "Tandl.",
                    "year": "1915",
                    "institution": "NULL"
                }
            ],
            "career": {
                "position": "Prakt, i Gbg",
                "years": {
                    "start_year": 1916,
                    "end_year": "s.d."
                },
                "organization": "NULL"
            },
            "family": {
                "spouse": "tandl. Kerstin Billing",
                "marriage_year": "NULL",
                "children": [
                    {
                        "name": "Margit",
                        "birth_year": "1921"
                    },
                    {
                        "name": "Inger",
                        "birth_year": "1925"
                    }
                ]
            }
        },
        "3": {
            "full_name": "Björkman, Göran Linus Gösta Raimundo",
            "location": "Ringas",
            "occupation": "Kyrkoherde",
            "birth_details": {
                "date": "16/03/1907",
                "place": "Sthlm",
                "parents": "förste aktuarien i komm:-koll., fil. dr Göran B. o. Ebba Frey"
            },
            "education": [
                {
                    "degree": "Stud:ex.",
                    "year": "1926",
                    "institution": "Sthlm"
                },
                {
                    "degree": "Teol. fil. ex.",
                    "year": "1928",
                    "institution": "NULL"
                },
                {
                    "degree": "Teol. kand., prakt. teol. prov samt prästv. f. Linköp. stift",
                    "year": "1931",
                    "institution": "NULL"
                }
            ],
            "career": [
                {
                    "position": "V. kom-min. i Risinge",
                    "years": {
                        "start_year": 1931,
                        "end_year": "s.d."
                    },
                    "organization": "NULL"
                },
                {
                    "position": "Kyrkoadj. där",
                    "years": {
                        "start_year": 1932,
                        "end_year": "s.d."
                    },
                    "organization": "NULL"
                },
                {
                    "position": "Kommdn. i Järeda",
                    "years": {
                        "start_year": 1936,
                        "end_year": "s.d."
                    },
                    "organization": "NULL"
                },
                {
                    "position": "Utn. kyrkoh. i Odensvi",
                    "years": {
                        "start_year": 1939,
                        "end_year": "s.d."
                    },
                    "organization": "NULL"
                },
                {
                    "position": "I Örtomta",
                    "years": {
                        "start_year": 1945,
                        "end_year": "s.d."
                    },
                    "organization": "NULL"
                }
            ],
            "family": "NULL"
        }
    }
}