{
    "original": "Bobeck, Carl Filip, överingenjör,\nBorås, f. 28/3/88 i Fildpstad av f-abr.\nCarl Wilhelm B. o. Wilhelmina\nEricsson. G. 18 m. Kerstin Sundeli. Barn:\nWilhelm f. 20, Stina o. Ulla ff. 22.\n–Mog:ex. v. norra real i Sthlm 05,\nciv:ing:ex. v. KTH 09. Res. t.\nNorge, Danm., Finl., Frankr., Engl.,\nTyskl., Ryssl. o. Bortre Ind.\nDrifts-ing:assist. v. stat. vattenf :verk,\nTroll-hätte kraftverk, 09-15, distr :ing. i\nSkara-distr. 16-17, konsult, ing. v.\nelektr. prövn:anst. i Sthlm 17-19,\nförest. f. kraftstat :byrån v. ASEA i\nVästerås 20-26, f. elektrotekn. avd. v.\nA-B Vattenbyggn :byråns o. Messrs\nRendel, Palmer &amp; Tritton’s gemens,\nhydroelektr. kont. i London 27-30,\ndärv. konsult, ing. f. den elektr.\nut-rustn. f. ett större kraftv :system å\nMalackahalvön, konsult, ing. v. A-B\nVattenbyggn :byrån i Sthlm 30-35, tf.\növering. v. Borås elverk 35-36, övering.\ndär sed. 36. Ordf. i Tekn. förb. i\nBorås 41-45, led. av Sv. tekn:fören.\n\nBobeck, Harald Jakob Gleerup, leg.\nläkare, Falköping, f. 27/7/18 i Lund av\nkyrkoh. F. B. o. Laura Gleerup. G.\n44 m. Maja Lund. Barn: Måns f. 45.\n\n—\tStud:ex. i Malmö 38, med. kand.\n41, med. lic. 46. Und:läk. v.\nFalköpings las. sed. 46. Hobbies: ridning,\ntennis.\n\nBoberg, Anders Ivar, bankdirektör,\nVimmerby, f. 1/1/88 i Brunskog,\nVärml. 1., av Magnus B. o. Charlotta\nPersson. G. 25 m. Ellen Haller. —\nRealex. v. Karlstads h. a. 1. E. o.\nlandskansl. i Växjö t. 18, anst. v. A-B\nSkånska hand rbanken 18-19, i Skand.\nbanken sed. 19, dir. sed. 31. V. ordf.\ni fattigv :styr. o. pens :nd. Led. av\nstadsfulim.\n\nBoberg, Johan Paul, arkitekt, Växjö,\nf. 14/8/84 i Brunskog, Värml. 1., av\nMagnus B. o. Charlotta Persson. G.\n27 m. Hedvig Rudelius. Barn:\nJan-Arne f. 29, Birgitta 34, Ingegerd 37.\n— Stud. v. Tekn. sk. i Sthlm 04, HKS\n05, teckn :lär :ex. 08. Stud:res. t.\nTyskl. o. Engl. 08, t. Tyskl. 22. Lär.\nv. byggn :yrkessk. 07-09, vik. lär. v.\nKungsholmens h. a. 1. i Sthlm 07-08,\nteckn :lär. v. Växjö h. a. 1. sed. 09.\nArkit :verksamh. sed. 09, utf. ritn. t.\nett stort antal ensk. o. offentl. byggn.,\nhandhaft o. ordn. ett flertal utställn.\nRiksantikv. ombud, förest, f. Smål.\nmus. i Växjö 25-40, led. av styr. f.\nKronob. läns hemslöjdsfören., styr. i.\nSkand. bankens avdrkont.,\nstads-fullm., drätselkamm., brandstyr.,\nbygg-n:ndn, ordf. i styr. f. System A-B i\nVäxjö 39, verkst. dir. i Växjö Teater\nA-B. RNO, RVO, ProPGM,\nPatrst-GM, Sv. Skidförb. SM, KorrespHA.\n\n",
    "structured": {
        "0": {
            "full_name": "Bobeck, Carl Filip",
            "location": "Borås",
            "occupation": "Överingenjör",
            "birth_details": {
                "date": "28/03/1888",
                "place": "Fildpstad"
            },
            "education": [
                {
                    "degree": "Mog:ex. v. norra real i Sthlm",
                    "year": "1905",
                    "institution": "norra real i Sthlm"
                },
                {
                    "degree": "civ:ing:ex. v. KTH",
                    "year": "1909",
                    "institution": "KTH"
                }
            ],
            "career": [
                {
                    "position": "Drifts-ing:assist. v. stat. vattenf :verk",
                    "years": {
                        "start_year": 1909,
                        "end_year": 1915
                    },
                    "organization": "Trollhätte kraftverk"
                },
                {
                    "position": "distr :ing. i Skara-distr.",
                    "years": {
                        "start_year": 1916,
                        "end_year": 1917
                    },
                    "organization": "Skaraborgs Län"
                },
                {
                    "position": "förest. f. kraftstat :byrån v. ASEA i Västerås",
                    "years": {
                        "start_year": 1920,
                        "end_year": 1926
                    },
                    "organization": "ASEA"
                },
                {
                    "position": "f. elektrotekn. avd. v. A-B Vattenbyggn :byråns o. Messrs Rendel, Palmer & Tritton’s gemens",
                    "years": {
                        "start_year": 1927,
                        "end_year": 1930
                    },
                    "organization": "A-B Vattenbyggn :byrån & Messrs Rendel, Palmer & Tritton"
                },
                {
                    "position": "konsult, ing. v. A-B Vattenbyggn :byrån i Sthlm",
                    "years": {
                        "start_year": 1930,
                        "end_year": 1935
                    },
                    "organization": "A-B Vattenbyggn :byrån"
                },
                {
                    "position": "tf. övering. v. Borås elverk",
                    "years": {
                        "start_year": 1935,
                        "end_year": 1936
                    },
                    "organization": "Borås elverk"
                },
                {
                    "position": "övering. där",
                    "years": {
                        "start_year": 1936,
                        "end_year": null
                    }
                }
            ],
            "family": {
                "spouse": "Kerstin Sundeli",
                "marriage_year": "18",
                "children": [
                    {
                        "name": "Wilhelm",
                        "birth_year": "1920"
                    },
                    {
                        "name": "Stina",
                        "birth_year": "1922"
                    },
                    {
                        "name": "Ulla",
                        "birth_year": "1922"
                    }
                ]
            }
        },
        "1": {
            "full_name": "Bobeck, Harald Jakob Gleerup",
            "location": "Falköping",
            "occupation": "Leg. läkare",
            "birth_details": {
                "date": "27/07/1918",
                "place": "Lund"
            },
            "education": [
                {
                    "degree": "Stud:ex. i Malmö",
                    "year": "1938",
                    "institution": "Malmö"
                },
                {
                    "degree": "med. kand.",
                    "year": "1941",
                    "institution": null
                },
                {
                    "degree": "med. lic.",
                    "year": "1946",
                    "institution": null
                }
            ],
            "career": [
                {
                    "position": "Und:läk. v. Falköpings las.",
                    "years": {
                        "start_year": 1946,
                        "end_year": null
                    },
                    "organization": "Falköpings las."
                }
            ],
            "family": {
                "spouse": "Maja Lund",
                "marriage_year": "44",
                "children": [
                    {
                        "name": "Måns",
                        "birth_year": "1945"
                    }
                ]
            },
            "hobbies": [
                "ridning",
                "tennis"
            ]
        },
        "2": {
            "full_name": "Boberg, Anders Ivar",
            "location": "Vimmerby",
            "occupation": "Bankdirektör",
            "birth_details": {
                "date": "01/01/1888",
                "place": "Brunskog, Värml. 1."
            },
            "education": [
                {
                    "degree": "Realex. v. Karlstads h. a. 1.",
                    "year": "",
                    "institution": "Karlstads h. a. 1."
                }
            ],
            "career": [
                {
                    "position": "ansed. v. A-B Skånska hand rbanken",
                    "years": {
                        "start_year": 1918,
                        "end_year": 1919
                    },
                    "organization": "A-B Skånska hand rbanken"
                },
                {
                    "position": "i Skand. banken",
                    "years": {
                        "start_year": 1919,
                        "end_year": null
                    },
                    "organization": "Skand. banken"
                }
            ],
            "family": {
                "spouse": "Ellen Haller",
                "marriage_year": "25",
                "children": null
            }
        },
        "3": {
            "full_name": "Boberg, Johan Paul",
            "location": "Växjö",
            "occupation": "Arkitekt",
            "birth_details": {
                "date": "14/08/1884",
                "place": "Brunskog, Värml. 1."
            },
            "education": [
                {
                    "degree": "Stud. v. Tekn. sk. i Sthlm",
                    "year": "1904",
                    "institution": "Tekn. sk. i Sthlm"
                },
                {
                    "degree": "HKS",
                    "year": "1905",
                    "institution": null
                }
            ],
            "career": [
                {
                    "position": "Lär. v. byggn :yrkessk.",
                    "years": {
                        "start_year": 1907,
                        "end_year": 1909
                    },
                    "organization": "Byggn :yrkessk."
                },
                {
                    "position": "teckn :lär. v. Växjö h. a. 1.",
                    "years": {
                        "start_year": 1909,
                        "end_year": null
                    },
                    "organization": "Växjö h. a. 1."
                }
            ],
            "family": {
                "spouse": "Hedvig Rudelius",
                "marriage_year": "27",
                "children": [
                    {
                        "name": "Jan-Arne",
                        "birth_year": "1929"
                    },
                    {
                        "name": "Birgitta",
                        "birth_year": "1934"
                    },
                    {
                        "name": "Ingegerd",
                        "birth_year": "1937"
                    }
                ]
            }
        }
    }
}