{
    "original": "ALFZON, ERIC W, kronofogde, Umeå,\nf i Åsarna, Jämtl l, 28/9/17 av faktor\nAlf Larsson o Edla Larsson.\nStud:ex Hermods 40, distr:åkl:ex Sthlm\n46i polisch :kurs 47, utmätn:man\nRamnäs 47, bitr landsfiskal Fagersta 52,\nlandsfiskal Bjurholm 57, kronofogde\nUmeå sed 65. - Hobbies: jakt, fiske,\nfärgfoto.\n\n\"Gift 48 m Erna Lindberg f 20, dtr t\nstat :mast Edvard L o Astrid Eriksson.\n-Barn: Mona-Lisa f 51.\n\nALGERS,   J   ÅKE,   distriktsveterinär,\n\nLövånger, f i Sätila, Älvsb l, 3/10/18 av\nagr Knut A o Ida Olsson.\nVet:ex   VHS  48,   Al-vet   Nykpgsortens\nseminfören Gnesta 48-50, öl vet :förordn\n50-56, chefsvet Gävleb seminfören\nBollnäs  56,  distr :vet Lövånger sed 58,\nbe-siktn:vet kontr :slakt Vebomark sed 61.\n- Led hälsov:ndn Lövånger sed 59.\nGift m sjuksköt Britt-Marie Langenborg\n\nf 18, dtr t ing Einar L o Anna L.\n-Barn: Göran f 48, Cecilia f 56.\n\nALGRIM, TORSTEN, lantmätare,\nHärnösand, f i Ovansjö, Gävleb l, 19/10/28\nav fabr Teodor A o Berta Pettersson.\nStud:ex Gävle 48, KTH 53, anst lantmät\nGbgs o Bohus samt Vnorrl l 53-58,\nlant-mät:styr utredn:byrå 59-61,\nvattenfallsstyr byggn :tekn byrå 61, bitr\növerlant-mät Jämtl l 62, lekt tekn gymn\nHärnösand sed 63. - Dir o ag\nLantmäterikon-sult Algrim ab. - Medl FrimO, Round\nTable. - Hobbies: konst, fjällsport.\nGift 54 m Karin Bergman f 29, dtr t\ntullförvalt Bore B o Inga B. - Barn:\nAnders f 56, Torun f 60.\n\nALINDER, ANDERS G, rektor,\nGävle, f i Häverö, Sthlms l, 22/7/22.\nFolkskollär:ex 46, fil kand 63, rekt obl\nskolväs Valbo kn. - Kapt Iv res.\nGift 47 m Mari Ericsson. - Barn: Johan\nf 48, Lars f 53.\n\n",
    "structured": {
        "0": {
            "full_name": "Eric W Alfzon",
            "location": "Umeå",
            "occupation": "kronofogde",
            "birth_details": {
                "date": "28/09/1917",
                "place": "Åsarna, Jämtlands län",
                "parents": "faktor Alf Larsson and Edla Larsson"
            },
            "education": [
                {
                    "degree": "Stud:ex",
                    "year": "1940",
                    "institution": "Hermods"
                },
                {
                    "degree": "distr:åkl:ex",
                    "year": "1946",
                    "institution": "Sthlm"
                }
            ],
            "career": [
                {
                    "position": "utmätn:man",
                    "years": {
                        "start_year": 1947,
                        "end_year": 1947
                    },
                    "organization": "Ramnäs"
                },
                {
                    "position": "bitr landsfiskal",
                    "years": {
                        "start_year": 1952,
                        "end_year": 1957
                    },
                    "organization": "Fagersta"
                },
                {
                    "position": "landsfiskal",
                    "years": {
                        "start_year": 1957,
                        "end_year": 1965
                    },
                    "organization": "Bjurholm"
                },
                {
                    "position": "kronofogde",
                    "years": {
                        "start_year": 1965,
                        "end_year": null
                    },
                    "organization": "Umeå"
                }
            ],
            "family": {
                "spouse": "Erna Lindberg",
                "marriage_year": "1948",
                "children": [
                    {
                        "name": "Mona-Lisa",
                        "birth_year": "1951"
                    }
                ]
            },
            "hobbies": [
                "jakt",
                "fiske",
                "färgfoto"
            ]
        },
        "1": {
            "full_name": "J Åke Algers",
            "location": "Lövånger",
            "occupation": "distriktsveterinär",
            "birth_details": {
                "date": "03/10/1918",
                "place": "Sätila, Älvsborgs län",
                "parents": "agr Knut A and Ida Olsson"
            },
            "education": [
                {
                    "degree": "Vet:ex",
                    "year": "1948",
                    "institution": "VHS"
                },
                {
                    "degree": "Al-vet",
                    "year": null,
                    "institution": "Nykpgsortens seminfören Gnesta"
                }
            ],
            "career": [
                {
                    "position": "öl vet :förordn",
                    "years": {
                        "start_year": 1950,
                        "end_year": 1956
                    },
                    "organization": null
                },
                {
                    "position": "chefsvet",
                    "years": {
                        "start_year": 1956,
                        "end_year": null
                    },
                    "organization": "Gävleb seminfören Bollnäs"
                },
                {
                    "position": "distr :vet",
                    "years": {
                        "start_year": 1958,
                        "end_year": null
                    },
                    "organization": "Lövånger"
                },
                {
                    "position": "be-siktn:vet",
                    "years": {
                        "start_year": 1961,
                        "end_year": null
                    },
                    "organization": "Vebomark"
                }
            ],
            "family": {
                "spouse": "Britt-Marie Langenborg",
                "marriage_year": null,
                "children": [
                    {
                        "name": "Göran",
                        "birth_year": "1948"
                    },
                    {
                        "name": "Cecilia",
                        "birth_year": "1956"
                    }
                ]
            }
        },
        "2": {
            "full_name": "Torsten Algrim",
            "location": "Härnösand",
            "occupation": "lantmätare",
            "birth_details": {
                "date": "19/10/1928",
                "place": "Ovansjö, Gävleborgs län",
                "parents": "fabr Teodor A and Berta Pettersson"
            },
            "education": [
                {
                    "degree": "Stud:ex",
                    "year": "1948",
                    "institution": "Gävle"
                },
                {
                    "degree": null,
                    "year": "1953",
                    "institution": "KTH"
                }
            ],
            "career": [
                {
                    "position": "anst lantmät",
                    "years": {
                        "start_year": 1953,
                        "end_year": 1958
                    },
                    "organization": "Gbgs o Bohus samt Vnorrl l"
                },
                {
                    "position": "lantmät:styr",
                    "years": {
                        "start_year": 1959,
                        "end_year": 1961
                    },
                    "organization": "utredn:byrå"
                },
                {
                    "position": "vattenfallsstyr",
                    "years": {
                        "start_year": 1961,
                        "end_year": null
                    },
                    "organization": "byggn :tekn byrå"
                },
                {
                    "position": "bitr överlant-mät",
                    "years": {
                        "start_year": 1962,
                        "end_year": 1963
                    },
                    "organization": "Jämtlands län"
                },
                {
                    "position": "lekt tekn gymn",
                    "years": {
                        "start_year": 1963,
                        "end_year": null
                    },
                    "organization": "Härnösand"
                }
            ],
            "family": {
                "spouse": "Karin Bergman",
                "marriage_year": "1954",
                "children": [
                    {
                        "name": "Anders",
                        "birth_year": "1956"
                    },
                    {
                        "name": "Torun",
                        "birth_year": "1960"
                    }
                ]
            },
            "hobbies": [
                "konst",
                "fjällsport"
            ]
        },
        "3": {
            "full_name": "Anders G Alinder",
            "location": "Gävle",
            "occupation": "rektor",
            "birth_details": {
                "date": "22/07/1922",
                "place": "Häverö, Stockholms län",
                "parents": null
            },
            "education": [
                {
                    "degree": "Folkskollär:ex",
                    "year": "1946",
                    "institution": null
                },
                {
                    "degree": "filosofie kandidat",
                    "year": "1963",
                    "institution": null
                }
            ],
            "career": [
                {
                    "position": "rekt obl skolväs",
                    "years": {
                        "start_year": null,
                        "end_year": null
                    },
                    "organization": "Valbo kn"
                }
            ],
            "family": {
                "spouse": "Mari Ericsson",
                "marriage_year": "1947",
                "children": [
                    {
                        "name": "Johan",
                        "birth_year": "1948"
                    },
                    {
                        "name": "Lars",
                        "birth_year": "1953"
                    }
                ]
            }
        }
    }
}