{
    "original": "AARFLOT, STEN L R A, eo lektor,\nGammelstad, f i Norrkpg 28/7/27 av rev\nHelmer A o Ellen Eriksson.\nStud:ex Norrkpg 46, fil mag Upps 56,\nadj i matem o kemi hal Luleå sed 56,\neo lekt där sed 66. - Hobbies: golf,\nskytte, musik.\n\nGift 52 m Ingrid Lindgren, dtr t kyrkoh\nArtur L o Signe Franck. - Barn:\nAndreas f 54, Karin f 57, Anna f 65.\n\nAARO, BENGT E, bergsingenjör,\nKiruna, f i Pajala, Norrb l, 12/2/31 av\nhandl Edvin A o småskollär Hilma\nLeh-mivaara.\n\nStud:ex Haparanda 51, KTH 58, gruving\nLKAB Malmberget 58, drifting o ch\nras-brytn Kiirunavaara LKAB Kiruna sed\n65. - Styr:led Kiruna högerfören sed 65.\n- Medl FrimO, Odd Fellow. - Hobbies:\njakt, konst, historia.\n\nGift 53 m Margareta Lindgren f 31, dtr\nt Nils L o M Eriksson. - Barn: Mikael\nf 55, Elisabeth f 58, Catherine f 63.\n\nAARO, CALLA S M, apotekare, Luleå,\nf i Lund 19/11/34 av fil mag Manne\nMohlin o Nanna Klang.\n\nStud:ex Trelleborg 55, apot:ex 62. - Elev\nTrelleborg 55-56, Lejonet Malmö 59,\nVita Björnen Sthlm 61-62, anst Ockelbo\n62, S:t Erik Sthlm 62, Lejonet Luleå sed 62.\n\nGift 57 m civ :ing Torsten Aarö. - Barn:\nBjörn f 58, Ingrid f 64.\n\nAARO, PAUL R, läroverksadjunkt,\nHaparanda, f i Pajala, Norrb l, 1/10/25\nav handl Edvin A o småskollär Hilma\nLehmivaara.\n\nStud:ex Haparanda 46, fil mag Upps 56,\nadj i matem o fys hal Haparanda sed 56.\n\nGift 63 m adj Anita Lorentzon f 32, dtr\nt hemm:äg Olof L o Gunborg Gilljam.\n\n",
    "structured": {
        "0": {
            "full_name": "STEN L R A AARFLOT",
            "location": "Gammelstad",
            "occupation": "eo lektor",
            "birth_details": {
                "date": "28/07/1927",
                "place": "Norrköping"
            },
            "education": [
                {
                    "degree": "Stud:ex",
                    "year": "1946",
                    "institution": "Norrköping"
                },
                {
                    "degree": "fil mag",
                    "year": "1956",
                    "institution": "Uppsala"
                }
            ],
            "career": [
                {
                    "position": "adj i matem o kemi",
                    "years": {
                        "start_year": 1956,
                        "end_year": 1966
                    },
                    "organization": "Luleå"
                }
            ],
            "family": {
                "spouse": "Ingrid Lindgren",
                "marriage_year": "1952",
                "children": [
                    {
                        "name": "Andreas",
                        "birth_year": "1954"
                    },
                    {
                        "name": "Karin",
                        "birth_year": "1957"
                    },
                    {
                        "name": "Anna",
                        "birth_year": "1965"
                    }
                ]
            },
            "hobbies": [
                "golf",
                "skytte",
                "musik"
            ]
        },
        "1": {
            "full_name": "BENGT E AARO",
            "location": "Kiruna",
            "occupation": "bergsingenjör",
            "birth_details": {
                "date": "12/02/1931",
                "place": "Pajala, Norrbotten"
            },
            "education": [
                {
                    "degree": "Stud:ex",
                    "year": "1951",
                    "institution": "Haparanda"
                },
                {
                    "degree": "KTH",
                    "year": "1958",
                    "institution": "Stockholm"
                }
            ],
            "career": [
                {
                    "position": "gruving",
                    "years": {
                        "start_year": 1958,
                        "end_year": 1965
                    },
                    "organization": "LKAB Malmberget"
                },
                {
                    "position": "drifting o ch rasbrytn",
                    "years": {
                        "start_year": 1965
                    },
                    "organization": "Kiirunavaara LKAB Kiruna"
                }
            ],
            "family": {
                "spouse": "Margareta Lindgren",
                "marriage_year": "1953",
                "children": [
                    {
                        "name": "Mikael",
                        "birth_year": "1955"
                    },
                    {
                        "name": "Elisabeth",
                        "birth_year": "1958"
                    },
                    {
                        "name": "Catherine",
                        "birth_year": "1963"
                    }
                ]
            },
            "hobbies": [
                "jakt",
                "konst",
                "historia"
            ]
        },
        "2": {
            "full_name": "CALLA S M AARO",
            "location": "Luleå",
            "occupation": "apotekare",
            "birth_details": {
                "date": "19/11/1934",
                "place": "Lund"
            },
            "education": [
                {
                    "degree": "Stud:ex",
                    "year": "1955",
                    "institution": "Trelleborg"
                },
                {
                    "degree": "apot:ex",
                    "year": "1962"
                }
            ],
            "career": [
                {
                    "position": "Elev",
                    "years": {
                        "start_year": 1955,
                        "end_year": 1956
                    },
                    "organization": "Trelleborg"
                },
                {
                    "position": "anst",
                    "years": {
                        "start_year": 1962
                    },
                    "organization": "Ockelbo"
                },
                {
                    "position": "anst",
                    "years": {
                        "start_year": 1962
                    },
                    "organization": "S:t Erik Sthlm"
                },
                {
                    "position": "Lejonet Luleå",
                    "years": {
                        "start_year": 1962
                    }
                }
            ],
            "family": {
                "spouse": "civ :ing Torsten Aarö",
                "marriage_year": "1957",
                "children": [
                    {
                        "name": "Björn",
                        "birth_year": "1958"
                    },
                    {
                        "name": "Ingrid",
                        "birth_year": "1964"
                    }
                ]
            }
        },
        "3": {
            "full_name": "PAUL R AARO",
            "location": "Haparanda",
            "occupation": "läroverksadjunkt",
            "birth_details": {
                "date": "01/10/1925",
                "place": "Pajala, Norrbotten"
            },
            "education": [
                {
                    "degree": "Stud:ex",
                    "year": "1946",
                    "institution": "Haparanda"
                },
                {
                    "degree": "fil mag",
                    "year": "1956",
                    "institution": "Uppsala"
                }
            ],
            "career": [
                {
                    "position": "adj i matem o fys",
                    "years": {
                        "start_year": 1956
                    },
                    "organization": "Haparanda"
                }
            ],
            "family": {
                "spouse": "adj Anita Lorentzon",
                "marriage_year": "1963"
            }
        }
    }
}