{
    "original": "JANELID, E INGVAR, professor,\nDjursholm, f i Ludvika 10/10/14 av\nbyggmäst Gustav Jansson o Anna\nSvensson.\n\nKTH 40, bitr gruving Ställbergs grufve\nab Ludvika 40, platsch Sikfors bruk o\navd:ch gruvförvaltn Hellefors bruks ab\n42-47, anst tekn avd Skånska cement ab\nSthlm 48, prof i gruvbrytning med\ngruvmätning KTH sed 53. - Ordf\nberg-sprängn:komm, styr:led Ställbergs\ngrufve ab, Stripa gruvab, Idkerbergets grufab\n54, medl ett fl&lt;ert gruvtekn f ören i Sv: e\no utl, LSvTF, LIVA 61. - Skr i\nberg-brytn:- o sprängn:teknik. - Utm: RNO.\n\n-  Hobby: sport.\n\nGift 41 m Britta Lewald f 17, dtr t dir\nMartin L o Ingeborg Karlsson. - Barn:\nKerstin f 42, Gudrun f 44, Lennart f 46.\nJANÉR, CARL-OLOF H, agronom,\nSthlm, f i St Malm, Södermani l,\n19/3/21 av agronom Helge J o\nElisabet Winqvist.\n\nStud:ex Sthlm 40, agnex 50, M Se\nJournalism Oklahoma Univ USA 52,\nred:sekr Lantmannen - Sv land 52, red\n\n59,   ch:red Lantmannen sed 61. - Led\njordbr upplysn:nd 61, 2:e v ordf Fören\nsv fackpress 62, led Lantbr:högsk\nstud:-kårs råd 56, medl Sthlms agronomklubb\n56, Sv:es pomolog fören 59, Sthlms\nlant-br:kiubb 60. - Skr: A Comparative\nCon-tent Analysis of Selected American and\n\nSwedish Agricultural Publications (akad\n\navh 52). - Hobbies: musik, foto, hor-\n\ntikultur.\n\nGift 56 m Monica Berg f 31, dtr t rytt-\n\nmäst Nils B o Astrid Nordenankar. -\n\nBarn: Sten f 58, Eva f 61.\n\n",
    "structured": {
        "0": {
            "full_name": "JANELID, E INGVAR",
            "location": "Djursholm",
            "occupation": "professor",
            "birth_details": {
                "date": "10/10/1914",
                "place": "Ludvika",
                "parents": "byggmäst Gustav Jansson o Anna Svensson"
            },
            "education": [
                {
                    "degree": "KTH",
                    "year": "1940",
                    "institution": "Kungliga Tekniska högskolan"
                }
            ],
            "career": [
                {
                    "position": "bitr gruving Ställbergs grufve ab",
                    "years": {
                        "start_year": 1940,
                        "end_year": 1940
                    },
                    "organization": "Ludvika"
                },
                {
                    "position": "platsch Sikfors bruk o avd:ch gruvförvaltn Hellefors bruks ab",
                    "years": {
                        "start_year": 1942,
                        "end_year": 1947
                    },
                    "organization": "Hellefors bruks ab"
                },
                {
                    "position": "anst tekn avd Skånska cement ab Sthlm",
                    "years": {
                        "start_year": 1948,
                        "end_year": 1948
                    },
                    "organization": "Skånska cement ab Sthlm"
                },
                {
                    "position": "prof i gruvbrytning med gruvmätning KTH",
                    "years": {
                        "start_year": 1953,
                        "end_year": null
                    },
                    "organization": "Kungliga Tekniska högskolan"
                }
            ],
            "family": {
                "spouse": "Britta Lewald",
                "marriage_year": "1941",
                "children": [
                    {
                        "name": "Kerstin",
                        "birth_year": "1942"
                    },
                    {
                        "name": "Gudrun",
                        "birth_year": "1944"
                    },
                    {
                        "name": "Lennart",
                        "birth_year": "1946"
                    }
                ]
            },
            "hobbies": [
                "sport"
            ]
        },
        "1": {
            "full_name": "JANÉR, CARL-OLOF H",
            "location": "Sthlm",
            "occupation": "agronom",
            "birth_details": {
                "date": "19/3/1921",
                "place": "St Malm, Södermani l",
                "parents": "agronom Helge J o Elisabet Winqvist"
            },
            "education": [
                {
                    "degree": "Stud:ex",
                    "year": "1940",
                    "institution": "Sthlm"
                },
                {
                    "degree": "agnex",
                    "year": "1950",
                    "institution": "NULL"
                },
                {
                    "degree": "M Se Journalism",
                    "year": "1952",
                    "institution": "Oklahoma Univ USA"
                }
            ],
            "career": [
                {
                    "position": "red:sekr Lantmannen - Sv land",
                    "years": {
                        "start_year": 1952,
                        "end_year": 1959
                    },
                    "organization": "Lantmannen - Sv land"
                },
                {
                    "position": "ch:red Lantmannen",
                    "years": {
                        "start_year": 1959,
                        "end_year": null
                    },
                    "organization": "Lantmannen"
                }
            ],
            "family": {
                "spouse": "Monica Berg",
                "marriage_year": "1956",
                "children": [
                    {
                        "name": "Sten",
                        "birth_year": "1958"
                    },
                    {
                        "name": "Eva",
                        "birth_year": "1961"
                    }
                ]
            },
            "publications": [
                {
                    "title": "A Comparative Content Analysis of Selected American and Swedish Agricultural Publications",
                    "year": "1952",
                    "type": "akad avh"
                }
            ],
            "hobbies": [
                "musik",
                "foto",
                "hortikultur"
            ]
        }
    }
}