{
    "original": "led Sv  försäkr:bol  förvaltn:nd  o\nförsäkr:bol förhandl:deleg.\nGift 33 m Ingrid Oden f 10. - Barn:\nThoma® f 36, Peder f 39.\n\nJAHR, J ADOLF R, skådespelare,\nStora Essingen, f i Sundsvall 23/6/93\nav byggmäst Reinhold Johansson o\nMatilda Levelin.\n\nÖrebro hal, stud sång f M Öhman o i\nWien, kabaretsångare Trondheim o\nHelsingfors, eng St teat Gbg 22-23,\nHippo-dromteat Malmö 24-26 o 27-29, S:a teat,\nFolkteat, Odéonteat o Oscarsteat Sthlm\n29-35, Dram teat 61-62, verks\nfilmbranschen, radio o TV. - Medl TSO. -\nHobbies: fiske, schack.\nGift 37-43 m Margit Tirkkonen.\n\nJAKOBSON, J E ALLAN, aukt revisor, \nSthlm, f i Lidkpg, Skarab l, 13/12/24.\n\nStud:ex Skara 43, DHG 46, aukt rev\n54, ass Lantbrrförb rev:byrå ab Sthlm\n47, kamr rass Nitroglycerin ab  Gyttorp\n48, rev:ass Egneils revrbyrå Sthlm 50-\n55, deläg sed 55.\n\nGift 51 m Anna-Britta Kjellqvist f 26.\n- Barn: Gunnar f 53, Anne f 55.\n\nJACOBSSON, K BENGT, fil dr, lektor, \nSolna, f i Sommen, Jönkpgs l, 23/4/18 av \nkontorist Verner J o Sigrid Rasmusson.\n\nStud:ex Linkpg 38, fil kand Upps 41,\nfil lic 48, fil dr 51. - Lektor Bollnäs 48,\nhal Solna sed 50. - Skr: drsavh 51, art\no rec i facktidskr.\n\nGift 57 m Greta Reichenberg f 29, dtr\nt major Erik R o Ingeborg Möller.\n- Barn: Per f 58, Bo f 61.\n\n<b>JAKOBSON, BERNT G, civilingenjör,</b>\nSthlm, f i Yxenhult, Kristianst l,\n18/11/09 av disp Carl J o Thérese Gemmel.\n\nTekn gymn Örebro 28, KTH 33;\nres:off:ex 31, kapt VVK 41, major VVK\n59. - Ing Vattenf:- o VV:styr 34-43,\nGeotekn inst 44-56, ch konsult avd 45,\nforsknravd 48, spec:lär geotekn KTH\n48-59, överinsp Wrstyr sed 58. - Ordf\nstatsverkets ing:förb 47-51, Sv geotekn\nfören sed 50, led styr o AU Sthlmshögern \n50-55, LSvTF. - Skr: div avh o\nupps i geotekn. - Utm: RVO.\n\n",
    "structured": {
        "0": {
            "full_name": "JAHR, J ADOLF R",
            "location": "Stora Essingen",
            "occupation": "skådespelare",
            "birth_details": {
                "date": "23/06/1893",
                "place": "Sundsvall",
                "parents": "byggmäst Reinhold Johansson o Matilda Levelin"
            },
            "education": [
                {
                    "degree": "stud sång",
                    "year": "M Öhman"
                },
                {
                    "degree": "kabaretsångare",
                    "year": "Trondheim o Helsingfors"
                }
            ],
            "career": [
                {
                    "position": "eng St teat Gbg",
                    "years": {
                        "start_year": 1922,
                        "end_year": 1923
                    },
                    "organization": "Hippodromteat Malmö"
                },
                {
                    "position": "S:a teat",
                    "years": {
                        "start_year": 1929,
                        "end_year": 1935
                    },
                    "organization": "Folkteat, Odéonteat o Oscarsteat Sthlm"
                },
                {
                    "position": "Dram teat",
                    "years": {
                        "start_year": 1961,
                        "end_year": 1962
                    }
                }
            ],
            "family": {
                "spouse": "Ingrid Oden",
                "marriage_year": "1933",
                "children": [
                    {
                        "name": "Thoma®",
                        "birth_year": "1936"
                    },
                    {
                        "name": "Peder",
                        "birth_year": "1939"
                    }
                ]
            },
            "hobbies": [
                "fiske",
                "schack"
            ]
        },
        "1": {
            "full_name": "JAKOBSON, J E ALLAN",
            "location": "Sthlm",
            "occupation": "aukt revisor",
            "birth_details": {
                "date": "13/12/1924",
                "place": "Lidkpg, Skarab l"
            },
            "education": [
                {
                    "degree": "Stud:ex",
                    "year": "1943"
                },
                {
                    "degree": "DHG",
                    "year": "1946"
                },
                {
                    "degree": "aukt rev",
                    "year": "1954"
                }
            ],
            "career": [
                {
                    "position": "ass",
                    "years": {
                        "start_year": 1950,
                        "end_year": 1955
                    },
                    "organization": "Egneils revrbyrå Sthlm"
                }
            ],
            "family": {
                "spouse": "Anna-Britta Kjellqvist",
                "marriage_year": "1951",
                "children": [
                    {
                        "name": "Gunnar",
                        "birth_year": "1953"
                    },
                    {
                        "name": "Anne",
                        "birth_year": "1955"
                    }
                ]
            }
        },
        "2": {
            "full_name": "JACOBSSON, K BENGT",
            "location": "Solna",
            "occupation": "lektor",
            "birth_details": {
                "date": "23/04/1918",
                "place": "Sommen, Jönkpgs l",
                "parents": "kontorist Verner J o Sigrid Rasmusson"
            },
            "education": [
                {
                    "degree": "Stud:ex",
                    "year": "1938"
                },
                {
                    "degree": "fil kand",
                    "year": "1941",
                    "institution": "Upps"
                },
                {
                    "degree": "fil lic",
                    "year": "1948"
                },
                {
                    "degree": "fil dr",
                    "year": "1951"
                }
            ],
            "career": [
                {
                    "position": "Lektor",
                    "years": {
                        "start_year": 1948
                    },
                    "organization": "Bollnäs"
                },
                {
                    "position": "hal",
                    "years": {
                        "start_year": 1950
                    },
                    "organization": "Solna"
                }
            ],
            "family": {
                "spouse": "Greta Reichenberg",
                "marriage_year": "1957",
                "children": [
                    {
                        "name": "Per",
                        "birth_year": "1958"
                    },
                    {
                        "name": "Bo",
                        "birth_year": "1961"
                    }
                ]
            }
        },
        "3": {
            "full_name": "JAKOBSON, BERNT G",
            "location": "Sthlm",
            "occupation": "civilingenjör",
            "birth_details": {
                "date": "18/11/1909",
                "place": "Yxenhult, Kristianst l",
                "parents": "disp Carl J o Thérese Gemmel"
            },
            "education": [
                {
                    "degree": "Tekn gymn",
                    "year": "1928"
                },
                {
                    "degree": "KTH",
                    "year": "1933"
                },
                {
                    "degree": "res:off:ex",
                    "year": "1931"
                }
            ],
            "career": [
                {
                    "position": "kapt",
                    "years": {
                        "start_year": 1941
                    },
                    "organization": "VVK"
                },
                {
                    "position": "major",
                    "years": {
                        "start_year": 1959
                    },
                    "organization": "VVK"
                },
                {
                    "position": "Ing",
                    "years": {
                        "start_year": 1934,
                        "end_year": 1943
                    },
                    "organization": "Vattenf:- o VV:styr"
                },
                {
                    "position": "spec:lär",
                    "years": {
                        "start_year": 1948,
                        "end_year": 1959
                    },
                    "organization": "KTH"
                },
                {
                    "position": "överinsp",
                    "years": {
                        "start_year": 1958
                    },
                    "organization": "Wrstyr"
                },
                {
                    "position": "ordf",
                    "years": {
                        "start_year": 1947,
                        "end_year": 1951
                    },
                    "organization": "statsverkets ing:förb"
                },
                {
                    "position": "led",
                    "organization": "styr o AU Sthlmshögern"
                }
            ],
            "family": {
                "spouse": "NULL",
                "marriage_year": "NULL",
                "children": "NULL"
            },
            "honorary_titles": [
                {
                    "title": "RVO"
                }
            ]
        }
    }
}