{
    "original": "OLANDER,   BENGT  E  F,   direktör,\n\nBorås, f i Simrishamn 10/8/30 av\ndistr:-ch Arvid O o Elise Love.\nRealex, hdlI 48, repr Kilsunds ab 49-56,\nverkst dir o inneh ab Skoglund &amp;\nHultner Borås sed 60. - Styr:led Borås\nfält-ridklubb. - Medl PB, Borås\njuniorhdls-kamm. - Hobbies: sport, tennis, ridning.\nGift 53 m Ulla Björmander f 30, dtr t\nfolkskollär Gunnar B o Esther Kildén.\n-Barn: Lars f 54, Ylva f 57, Edward f 61.\n\nOLANDER, BJÖRN V, civilingenjör,\n\nV Frölunda, f i Nybro 8/7/33 av dir\nWilhelm O o Ruth Olsson.\nStud:ex Kalmar 53, CTH 60, ass inst f\nelektronik CTH sed 60. - Hobby: musik.\nGift 60 m Mona Fagerlund f 38, dtr t\nlantbr Harry F o Ajna Rydén. - Barn:\nHans Wilhelm f 64.\n\nOLANDER, ERIK H, tandläkare,\nLinköping, f i Valstad, Skarab l, 3/4/05 av\nlantbr Natanael O o Wilhelmina\nAndersson.\n\nStud:ex Skara 26, telegraf ass :ex Sthlm\n28, telegrafass Gbg, Sundsvall, Malmö o\nSthlm 28-37, tandl:ex Sthlm 38, vik\nAlunda 38-40, priv:prakt Linkpg sed 40.\n- Sekr Österg v:a tandl:fören 47-51.\n-Medl FrimO. - Hobbies: jakt, fiske,\ngenealogi.\n\nGift 1) 41 m Birgitta Janson f 10 d 53,\n2) 56 m Maj Nilsson, f Krafve f 17.\n-Barn: Eva f 46, Anne-Marie f 50,\nChristina f 57.\n\nOLAUSSON, ERIC V, fil dr, docent,\n\nGbg, f i Hede, Gbgs o Boh l, 26/1/23 av\nlantbr Hans O o Anna Johansson.\nAnst i lantbr t 48, stud:ex Hermods 48,\nfil kand 51 o fil lic Lund 55, fil dr\nUpps 61, doc i oceanografi, särsk marin\nsedimentologi Gbgs univ sed 63. - Aman\nkvartärgeol inst 49-52, SGU 52-54, ass\nresp tf labor oceanograf inst Gbgs univ\nsed 56. - Visit research prof The Marine\nLab Univ of Miami USA 61-62. - Skr\nett 20-tal arb i oceanografi m m. -\nHobbies: botanik, ornitologi, historia,\nantikviteter.\n\nGift 53 m småskollär Barbro Strinnholm,\ndtr t Arvid S o Ida Börlin. - Barn:\nIngrid f 58, Torbjörn f 64.\n\n",
    "structured": {
        "0": {
            "full_name": "Bengt E F Olander",
            "location": "Borås",
            "occupation": "direktör",
            "birth_details": {
                "date": "10/08/1930",
                "place": "Simrishamn"
            },
            "education": [
                {
                    "degree": "Realexamen",
                    "year": "1948",
                    "institution": "hdlI"
                }
            ],
            "career": [
                {
                    "position": "repr",
                    "years": {
                        "start_year": 1949,
                        "end_year": 1956
                    },
                    "organization": "Kilsunds ab"
                },
                {
                    "position": "verkst dir",
                    "years": {
                        "start_year": 1960
                    },
                    "organization": "Skoglund & Hultner Borås"
                }
            ],
            "family": {
                "spouse": "Ulla Björmander",
                "marriage_year": "1953",
                "children": [
                    {
                        "name": "Lars",
                        "birth_year": "1954"
                    },
                    {
                        "name": "Ylva",
                        "birth_year": "1957"
                    },
                    {
                        "name": "Edward",
                        "birth_year": "1961"
                    }
                ]
            },
            "hobbies": [
                "sport",
                "tennis",
                "ridning"
            ]
        },
        "1": {
            "full_name": "Björn V Olander",
            "location": "V Frölunda",
            "occupation": "civilingenjör",
            "birth_details": {
                "date": "08/07/1933",
                "place": "Nybro"
            },
            "education": [
                {
                    "degree": "Studexamen",
                    "year": "1953",
                    "institution": "Kalmar"
                },
                {
                    "degree": "CTH",
                    "year": "1960"
                }
            ],
            "career": [
                {
                    "position": "ass inst f elektronik",
                    "years": {
                        "start_year": 1960
                    },
                    "organization": "CTH"
                }
            ],
            "family": {
                "spouse": "Mona Fagerlund",
                "marriage_year": "1960",
                "children": [
                    {
                        "name": "Hans Wilhelm",
                        "birth_year": "1964"
                    }
                ]
            },
            "hobbies": [
                "musik"
            ]
        },
        "2": {
            "full_name": "Erik H Olander",
            "location": "Linköping",
            "occupation": "tandläkare",
            "birth_details": {
                "date": "03/04/1905",
                "place": "Valstad, Skarab l"
            },
            "education": [
                {
                    "degree": "Studexamen",
                    "year": "1926",
                    "institution": "Skara"
                },
                {
                    "degree": "examen",
                    "year": "1928",
                    "institution": "Sthlm"
                }
            ],
            "career": [
                {
                    "position": "vik",
                    "years": {
                        "start_year": 1938,
                        "end_year": 1940
                    },
                    "organization": "Alunda"
                },
                {
                    "position": "priv:prakt",
                    "years": {
                        "start_year": 1940
                    },
                    "organization": "Linkpg"
                }
            ],
            "family": {
                "spouse": "1) Birgitta Janson",
                "marriage_year": "1941",
                "children": [
                    {
                        "name": "Eva",
                        "birth_year": "1946"
                    },
                    {
                        "name": "Anne-Marie",
                        "birth_year": "1950"
                    },
                    {
                        "name": "Christina",
                        "birth_year": "1957"
                    }
                ]
            },
            "hobbies": [
                "jakt",
                "fiske",
                "genealogi"
            ]
        },
        "3": {
            "full_name": "Eric V Olausson",
            "location": "Gbg",
            "occupation": "fil dr, docent",
            "birth_details": {
                "date": "26/01/1923",
                "place": "Hede, Gbgs o Boh l"
            },
            "education": [
                {
                    "degree": "studexamen",
                    "year": "1948",
                    "institution": "Hermods"
                },
                {
                    "degree": "fil kandidat",
                    "year": "1951"
                },
                {
                    "degree": "fil lic",
                    "year": "1955",
                    "institution": "Lund"
                },
                {
                    "degree": "fil dr",
                    "year": "1961",
                    "institution": "Upps"
                }
            ],
            "career": [
                {
                    "position": "anst i lantbr",
                    "years": {
                        "start_year": 1948
                    }
                },
                {
                    "position": "ass resp tf labor oceanograf inst",
                    "years": {
                        "start_year": 1956
                    },
                    "organization": "Gbgs univ"
                }
            ],
            "family": {
                "spouse": "småskollär Barbro Strinnholm",
                "marriage_year": "1953",
                "children": [
                    {
                        "name": "Ingrid",
                        "birth_year": "1958"
                    },
                    {
                        "name": "Torbjörn",
                        "birth_year": "1964"
                    }
                ]
            },
            "hobbies": [
                "botanik",
                "ornitologi",
                "historia",
                "antikviteter"
            ]
        }
    }
}