{
    "original": "OLSSON, STIG B, leg läkare, Askim,\nf i Gbg 28/9/25 av köpm Carl O o\nCecilia Wennerholm.\nStud:ex Sthlm 45, farm kand 50, med\nkand 52 o med lic Gbg 57, underläk\nröntgenavd Mölndals las 57-60,\nröntgen-diagn avd II Sahlgr sjh 60-62 o sed 63,\nGustaf V:s jub :klin 62-63. - Skr i\nrönt-gendiagn.\n\nGift 53 m Ingeborg Henning f 25, dtr t\napot Richard H o Sofie Häuserer.\n-Barn: Annika f 57, Nina f 59, Mette\nf 61.\n\nOLSSON, STIG E I, förste\ntaxeringsinspektör, Kalmar, f i Vissefjärda, Kalmar\nl, 12/1/36 av jv:tjm Ernst O o Hilma\nHjelm.\n\nStud:ex Kalmar 56, DHG 60, tjm\nlänsstyr Kalmar 60, l:e tax:insp där sed 63.\n- Fänr A 6 res 60.\n\nGift 60 m Astrid Johansson f 38, dtr t\nköpm Harald J o Maria Nelson. - Barn:\nClas f 62, Jonas f 65.\nOLSSON, SVEN G, ombudsman,\nMölndal, f i Mölndal 15/4/21 av margarinarb\nAugust O o Anna Nicklasson.\nAnst telev Gbg 36-63, omb :man HSB\nMölndal sed 63. - Ordf Stadsfullm\nMölndal sed 57, led DK sed 58, ordf o led öl\nkomm ndr o styr, fullm regionpl:förb\nGbg m omgivn, led förortsförb. -\nStyr:-led Sv:es kreditbk Mölndal sed 58, ab\nÅbyfältet, ab Mölndals resebyrå,\nMölndals konstisbana ek fören. - Medl\nRotary, IOGT, MHF.\n\nGift m Elsa Sundberg f 18, dtr t jv:tjm\nJ T S o Mathilde Andersen. - Barn:\nGun f 39, Ulla f 40.\n\nOLSSON,   SVEN   G   L,   skoldirektör,\n\nMariestad, f i Lund 29/1/25 av rekt\nSven O o Britta Andersson.\nStud:ex 45, folkskollär :ex 48 o fil mag\nLund 56; folkskollär Vellinge 48-57, adj\nsamrealsk Vellinge 57-58, rekt komm\nrealsk Jörn 58-61, samrealsk Storvik\n61-63, skoldir Mariestad sed 63. - Sekr\ngymnasieutredn f Gävleb l 61,\nrationa-liser:utred’n SO 62-63. - Led\nskolbyggn:-komm, byggn :nd. - Medl Rotary. - Utg:\nPM för rektorsexpeditioner (59 ff).\n-Hobbies: pistolskytte, boxning, musik.\nGift 48 m Sylva Andersson f 27, dtr t\ndisp Hugo A o Rica Gylldorff. - Barn:\nKarin f 49, Magnus f 51, Kerstin f 52,\nBjörn f 59.\n\n",
    "structured": {
        "0": {
            "full_name": "STIG B OLSSON",
            "location": "Askim, Göteborg",
            "occupation": "leg läkare",
            "birth_details": {
                "date": "28/09/1925",
                "place": "Göteborg",
                "parents": "köpm Carl O o Cecilia Wennerholm"
            },
            "education": [
                {
                    "degree": "Stud:ex",
                    "year": "1945",
                    "institution": "Stockholm"
                },
                {
                    "degree": "farm kand",
                    "year": "1950",
                    "institution": "NULL"
                },
                {
                    "degree": "med kand",
                    "year": "1952",
                    "institution": "NULL"
                },
                {
                    "degree": "med lic",
                    "year": "1957",
                    "institution": "Göteborg"
                }
            ],
            "career": [
                {
                    "position": "underläk röntgenavd",
                    "years": {
                        "start_year": 1957,
                        "end_year": 1960
                    },
                    "organization": "Mölndals las"
                },
                {
                    "position": "röntgen-diagn avd II",
                    "years": {
                        "start_year": 1960,
                        "end_year": 1962
                    },
                    "organization": "Sahlgr sjh"
                },
                {
                    "position": "Gustaf V:s jub :klin",
                    "years": {
                        "start_year": 1962,
                        "end_year": 1963
                    },
                    "organization": "NULL"
                }
            ],
            "family": {
                "spouse": "Ingeborg Henning",
                "marriage_year": "1953",
                "children": [
                    {
                        "name": "Annika",
                        "birth_year": "1957"
                    },
                    {
                        "name": "Nina",
                        "birth_year": "1959"
                    },
                    {
                        "name": "Mette",
                        "birth_year": "1961"
                    }
                ]
            }
        },
        "1": {
            "full_name": "STIG E I OLSSON",
            "location": "Kalmar",
            "occupation": "förste taxeringsinspektör",
            "birth_details": {
                "date": "12/01/1936",
                "place": "Vissefjärda, Kalmar"
            },
            "education": [
                {
                    "degree": "Stud:ex",
                    "year": "1956",
                    "institution": "Kalmar"
                },
                {
                    "degree": "DHG",
                    "year": "1960",
                    "institution": "NULL"
                }
            ],
            "career": [
                {
                    "position": "tjm länsstyr",
                    "years": {
                        "start_year": 1960,
                        "end_year": 1963
                    },
                    "organization": "Kalmar"
                }
            ],
            "family": {
                "spouse": "Astrid Johansson",
                "marriage_year": "1960",
                "children": [
                    {
                        "name": "Clas",
                        "birth_year": "1962"
                    },
                    {
                        "name": "Jonas",
                        "birth_year": "1965"
                    }
                ]
            }
        },
        "2": {
            "full_name": "SVEN G OLSSON",
            "location": "Mölndal",
            "occupation": "ombudsman",
            "birth_details": {
                "date": "15/04/1921",
                "place": "Mölndal"
            },
            "career": [
                {
                    "position": "omb :man HSB",
                    "years": {
                        "start_year": 1963,
                        "end_year": null
                    },
                    "organization": "Mölndal"
                }
            ],
            "family": {
                "spouse": "Elsa Sundberg",
                "marriage_year": "NULL",
                "children": [
                    {
                        "name": "Gun",
                        "birth_year": "1939"
                    },
                    {
                        "name": "Ulla",
                        "birth_year": "1940"
                    }
                ]
            }
        },
        "3": {
            "full_name": "SVEN G L OLSSON",
            "location": "Mariestad",
            "occupation": "skoldirektör",
            "birth_details": {
                "date": "29/01/1925",
                "place": "Lund"
            },
            "education": [
                {
                    "degree": "Stud:ex",
                    "year": "1945",
                    "institution": "NULL"
                },
                {
                    "degree": "folkskollär :ex",
                    "year": "1948",
                    "institution": "Lund"
                },
                {
                    "degree": "fil mag",
                    "year": "1956",
                    "institution": "Lund"
                }
            ],
            "career": [
                {
                    "position": "folkskollär",
                    "years": {
                        "start_year": 1948,
                        "end_year": 1957
                    },
                    "organization": "Vellinge"
                },
                {
                    "position": "adj samrealsk",
                    "years": {
                        "start_year": 1957,
                        "end_year": 1958
                    },
                    "organization": "Vellinge"
                },
                {
                    "position": "rekt komm realsk",
                    "years": {
                        "start_year": 1958,
                        "end_year": 1961
                    },
                    "organization": "Jörn"
                },
                {
                    "position": "samrealsk",
                    "years": {
                        "start_year": 1961,
                        "end_year": 1963
                    },
                    "organization": "Storvik"
                },
                {
                    "position": "skoldir",
                    "years": {
                        "start_year": 1963,
                        "end_year": null
                    },
                    "organization": "Mariestad"
                }
            ],
            "family": {
                "spouse": "Sylva Andersson",
                "marriage_year": "1948",
                "children": [
                    {
                        "name": "Karin",
                        "birth_year": "1949"
                    },
                    {
                        "name": "Magnus",
                        "birth_year": "1951"
                    },
                    {
                        "name": "Kerstin",
                        "birth_year": "1952"
                    },
                    {
                        "name": "Björn",
                        "birth_year": "1959"
                    }
                ]
            },
            "hobbies": [
                "pistolskytte",
                "boxning",
                "musik"
            ]
        }
    }
}