{
    "original": "ORDELL,   RUNE   O   G,   överläkare,\n\nJönköping, f i Luleå 20/10/20 av\nstat:-skriv Anders O o Therese Zennström.\nStud:ex Sthlm 38, med kand 43 o med\nlic Sthlm 48, aman, ass o bitr lär kem\ninst Karol inst 42-44 o 46-48, lär RK\nÖsterr 49, 2:e underläk kem centrallab\nSödersjh 50-52, med klin-kem lab\nSeraf:-las 52-55, vik överläk resp las :läk Karol\nsjh, Seraf :las o Stocksunds las periodv\n50-57, l:e underläk klin-kem centrallab\nSeraf :las 55-58, överläk klin-kem lab\nJönkpgs las sed 59. - Skeppsläk M/S\nMargaret Johnson 46. - Red Med fören\ntidskr 45-47. - Led kem lab :as\nexpertgrupp i SJURA (sjh:ens rationalis:råd)\nsed 63. - Skr i klin enzymforskning, allm\no klin kemi.\nGift 51 m leg läk Inga-Britt Joner f 24.\n\n-  Barn: Nina f 52, Lars f 54, Erik f 58.\n\nORDQVIST,  SVEN O, assessor, Gbg,\n\nf i Gbg 5/11/21 av fil kand Oscar O o\nfolkskollär Milan Berghult.\nStud:ex 40, jur kand Lund 47, tingstjg\n48-50, fiskal hovr f V Sv:e 51, stadsnot\nrådhusr Gbg 55 (e 51), assess där sed 61.\nGift 48 m Ulla Svensson f 25. - Barn:\nInga f 51.\n\nOREHAG, N LENNART H, bitr\nskoldirektör, Norrköping, f i Gävle 15/2/25\nav köpm Helge Olson o Hulda Norberg.\nStud:ex 45, folkskollär :ex Karlstad 47,\nfolkskollär Hille 47, Kälarne 49,\ndistr:-överlär där 54, rekt Alfta 59, byrådir\nSO 60, bitr skoldir Norrkpg sed 63.\n-Medl Rotary. - Hobbies: fiske,\nskidåkning, körsång.\n\nGift 47 m Röde Isakson f 24, dtr t\npastor Simon I o Anna Langer. - Barn:\nIngrid f 48, Karin f 53.\n\nORHAUG, TORLEIV A A, tekn dr,\nuniversitetslektor, Lerum, f i Lebesby,\nNorge, 29/3/29 av folkskollär Torleiv O\no Kathinka Eriksen.\n\nCTH 54, tekn lic 59 o tekn dr CTH 65.\n-Ass CTH 55-60, gästforsk National\nRadio Astronomy Observatory Green Bank\nUSA 60-62, univ:lekt i elektronfysik I\nCTH sed 62. - Led Tekn samf Gbg,\nAmer Astronomical Soc. - Skr i\nelektronfysik m m.\nGift 55 m Eivor Simonsson.\n\n",
    "structured": {
        "0": {
            "full_name": "RUNE O ORDELL",
            "location": "Jönköping",
            "occupation": "överläkare",
            "birth_details": {
                "date": "20/10/1920",
                "place": "Luleå",
                "parents": "Anders Ordeell och Therese Zennström"
            },
            "education": [
                {
                    "degree": "Stud:ex",
                    "year": "1938",
                    "institution": "Sthlm"
                },
                {
                    "degree": "med kand",
                    "year": "1943",
                    "institution": "Sthlm"
                },
                {
                    "degree": "med lic",
                    "year": "1948",
                    "institution": "Sthlm"
                }
            ],
            "career": [
                {
                    "position": "aman",
                    "years": {
                        "start_year": 1942,
                        "end_year": 1944
                    },
                    "organization": "Karol inst"
                },
                {
                    "position": "ass",
                    "years": {
                        "start_year": 1946,
                        "end_year": 1948
                    },
                    "organization": "kem inst Karol inst"
                },
                {
                    "position": "bitr lär kem",
                    "years": {
                        "start_year": 1946,
                        "end_year": 1948
                    },
                    "organization": "Karol inst"
                },
                {
                    "position": "2:e underläk kem centrallab",
                    "years": {
                        "start_year": 1950,
                        "end_year": 1952
                    },
                    "organization": "Södersjh"
                },
                {
                    "position": "med klin-kem lab",
                    "years": {
                        "start_year": 1952,
                        "end_year": 1955
                    },
                    "organization": "Seraf:-las"
                },
                {
                    "position": "vik överläk resp las :läk Karol sjh",
                    "years": {
                        "start_year": 1952,
                        "end_year": 1955
                    },
                    "organization": "Seraf:-las"
                },
                {
                    "position": "Seraf :las o Stocksunds las periodv",
                    "years": {
                        "start_year": 1950,
                        "end_year": 1957
                    }
                },
                {
                    "position": "l:e underläk klin-kem centrallab",
                    "years": {
                        "start_year": 1955,
                        "end_year": 1958
                    },
                    "organization": "Seraf :las"
                },
                {
                    "position": "överläk klin-kem lab",
                    "years": {
                        "start_year": 1959
                    },
                    "organization": "Jönkpgs las"
                }
            ],
            "family": {
                "spouse": "leg läk Inga-Britt Joner",
                "marriage_year": "1951",
                "children": [
                    {
                        "name": "Nina",
                        "birth_year": "1952"
                    },
                    {
                        "name": "Lars",
                        "birth_year": "1954"
                    },
                    {
                        "name": "Erik",
                        "birth_year": "1958"
                    }
                ]
            }
        },
        "1": {
            "full_name": "SVEN O ORDQVIST",
            "location": "Gbg",
            "occupation": "assessor",
            "birth_details": {
                "date": "5/11/1921",
                "place": "Gbg",
                "parents": "fil kand Oscar Ordqvist och folkskollär Milan Berghult"
            },
            "education": [
                {
                    "degree": "Stud:ex",
                    "year": "1940"
                },
                {
                    "degree": "jur kand",
                    "year": "1947",
                    "institution": "Lund"
                }
            ],
            "career": [
                {
                    "position": "tingstjg",
                    "years": {
                        "start_year": 1948,
                        "end_year": 1950
                    }
                },
                {
                    "position": "fiskal hovr",
                    "years": {
                        "start_year": 1951
                    },
                    "organization": "V Sv:e"
                },
                {
                    "position": "stadsnot rådhusr",
                    "years": {
                        "start_year": 1955
                    },
                    "organization": "Gbg"
                },
                {
                    "position": "assess",
                    "years": {
                        "start_year": 1961
                    },
                    "organization": "Gbg"
                }
            ],
            "family": {
                "spouse": "Ulla Svensson",
                "marriage_year": "1948",
                "children": [
                    {
                        "name": "Inga",
                        "birth_year": "1951"
                    }
                ]
            }
        },
        "2": {
            "full_name": "N LENNART H OREHAG",
            "location": "Norrköping",
            "occupation": "bitr skoldirektör",
            "birth_details": {
                "date": "15/2/1925",
                "place": "Gävle",
                "parents": "köpm Helge Olson och Hulda Norberg"
            },
            "education": [
                {
                    "degree": "Stud:ex",
                    "year": "1945"
                },
                {
                    "degree": "folkskollär :ex",
                    "year": "1947",
                    "institution": "Karlstad"
                }
            ],
            "career": [
                {
                    "position": "distr:-överlär",
                    "years": {
                        "start_year": 1954
                    },
                    "organization": "Alfta"
                },
                {
                    "position": "rekt",
                    "years": {
                        "start_year": 1959
                    },
                    "organization": "Alfta"
                },
                {
                    "position": "byrådir",
                    "years": {
                        "start_year": 1960
                    },
                    "organization": "SO"
                },
                {
                    "position": "bitr skoldir",
                    "years": {
                        "start_year": 1963
                    },
                    "organization": "Norrkpg"
                }
            ],
            "family": {
                "spouse": "Röde Isakson",
                "marriage_year": "1947",
                "children": [
                    {
                        "name": "Ingrid",
                        "birth_year": "1948"
                    },
                    {
                        "name": "Karin",
                        "birth_year": "1953"
                    }
                ]
            },
            "hobbies": [
                "fiske",
                "skidåkning",
                "körsång"
            ]
        },
        "3": {
            "full_name": "TORLEIV A A ORHAUG",
            "location": "Lerum",
            "occupation": "tekn dr, universitetslektor",
            "birth_details": {
                "date": "29/3/1929",
                "place": "Lebesby, Norge",
                "parents": "folkskollär Torleiv Orhaug och Kathinka Eriksen"
            },
            "education": [
                {
                    "degree": "CTH",
                    "year": "1954"
                },
                {
                    "degree": "tekn lic",
                    "year": "1959"
                },
                {
                    "degree": "tekn dr",
                    "year": "1965"
                }
            ],
            "career": [
                {
                    "position": "Ass CTH",
                    "years": {
                        "start_year": 1955,
                        "end_year": 1960
                    }
                },
                {
                    "position": "gästforsk",
                    "years": {
                        "start_year": 1960,
                        "end_year": 1962
                    },
                    "organization": "National Radio Astronomy Observatory Green Bank, USA"
                },
                {
                    "position": "univ:lekt i elektronfysik I CTH",
                    "years": {
                        "start_year": 1962
                    }
                }
            ],
            "family": {
                "spouse": "Eivor Simonsson",
                "marriage_year": "1955"
            }
        }
    }
}