{
    "original": "Heijbel, Robert Hugo, länsveterinär,\n\nJönköping, f. 24/7/84 i TorshäMa\nlands-förs., Södermani. 1. G. 11 m. Ella\n\nLaigerhiolim. Bairn: Britt f. 12, g. m.\nstadslläk. S. Ahnlund, Karlskrona, Rolf\n\n15,\tlas:läk., Karlskrona. — Moig:ex. i\nÖrebro^ 06i veter:ex. 08. Stud :ires. t.\nDianim. 12 o, 201 Am,an. v. kem. lab.\n05-08, tf. länsveiter. i Ö’Sitergöt!l. 1. 08,\nd)i-’Str:veter. i Alvesta 08-10, i Askersund\n10-21,, länsveter, i Jönköp. 1. s,ed. 21,\nstadsveter. i Jönlköp. sed. 23. besiilktn\n:-man v. köttbeisiktn :byrån i Jönköp.\nsed. 24, chef f. miedic.:styr. e. byrå i\nJöniköp. 25. Sekr. i Sv. länsiveter\n:-’förlen. 26-412, 0’rd’f. i Simål. veter:fören.\n•sed. 3’5, h’ed:ledi. i Sv. llänsveter :förein.\n44. Hobbiies : jakt o. fiske. RVO,\nJönköp. 1. hush :sfäl’lisik. GM, Skand.\nKrea-tUirsförsiäkr :bol. GM, Sv. jägairförb.\nhed:t. i guld.\n\nHeijde, Anne-Marie, tandläkare,\nGöteborg, f. i Asen, Sikarab. 1., av\ng^ods-äg. Oscar Johansson o. h. h. G. m.\ntandl. Victor Heijde. Barn: Stig\nVictor Lennart, Bengt Victor. —\nStud:-ex. v. Lyceum f. fl. i Sthlm, tandl\n:-ex. Prakt, i Gbg.\n\nHeijl, Bo Gillis, advokat, Borås, f.\n27/12/04 i Sthlm av majoren Robert\nH. o. Ebba Roberg. G. 36 m. Rut\nGranström. Barn: Christina f. 40,\nAnders 45. — Stud:ex. i Linköp. 22, jur.\nkand. i Upps. 29. Tingstjg. i\nSödertörns doms. 29 O’. Kinds o. Redvägs\ndoms. 30-33, ensam inneh. av\nadv:fir-ma i Ulricehamn 33-40, förest, f.\nÄlvsb. 1. s. rättshjälpsanst. i Borås\nsed, 40. Led. av Sv:es adv:samf. sed.\n35.\n\nHeijne, Otto Henrik, civilingenjör,\ndisponent, Jönköping, f. 10/4/93 i\nKvidinge, Krist. 1., av stat:insp. Olof\nAnderson o. Augusta Heijne. G. 29 m.\nMärtha Skeppstedt. Barn: Inga f. 30,\nHans 31. — Stud:ex. 12, utex. fr. KTH\n\n16.\tAnst. v. Hellefors Bruks A-B\n19-22, Spruce Falls Co. &amp; Kimberley\nClark Co. 22-25, Munksjö A-B sed. 26,\nverkst. dir. i Munksjökoncernen sed.\n39. Ordf. i styr. f. A-B Skånska\nBankens a:vd:kont. i Jönköp., Tàd:n. A-B\nSmålands Allehanda o. Jönköp. Tryck.\nA-B, v. ordf. i Syds’v. virkesfören.,\nSv:es Pappersfbr :’förb. o. Sv.\nPappersi-br. Hand. A-B^ led. av styr. ’f.\nMunksjö A-B, La,gamlil!lis A-B, Sv.\npappers-br:förein!., FÖrsäkr. A-B Alllmiänina\nBrand,, Eörsäkr :bol. Hero samt Furen\no. Fliårems regler:föret. m. m. RVO.\n\n",
    "structured": {
        "0": {
            "full_name": "Heijbel, Robert Hugo",
            "location": "Jönköping",
            "occupation": "länsveterinär",
            "birth_details": {
                "date": "24/07/1884",
                "place": "TorshäMa lands-förs."
            },
            "education": [
                {
                    "degree": "medic. dr.",
                    "year": "1912",
                    "institution": "Kem. lab."
                }
            ],
            "career": [
                {
                    "position": "tf. länsveiter.",
                    "years": {
                        "start_year": 1908,
                        "end_year": 1910
                    },
                    "organization": "Ö’Sitergöt!l."
                },
                {
                    "position": "länsveter.",
                    "years": {
                        "start_year": 1910,
                        "end_year": 1921
                    },
                    "organization": "Askersund"
                },
                {
                    "position": "länsveter.",
                    "years": {
                        "start_year": 1921,
                        "end_year": 1923
                    },
                    "organization": "Jönköp."
                },
                {
                    "position": "stadsveter.",
                    "years": {
                        "start_year": 1923,
                        "end_year": null
                    },
                    "organization": "Jönlköp."
                },
                {
                    "position": "besiilktn :-man v. köttbeisiktn :byrån",
                    "years": {
                        "start_year": 1924,
                        "end_year": null
                    },
                    "organization": "Jönköp."
                },
                {
                    "position": "chef f. miedic.:styr. e. byrå",
                    "years": {
                        "start_year": 1925,
                        "end_year": null
                    },
                    "organization": "Jöniköp."
                }
            ],
            "family": {
                "spouse": "Ella Laigerhiolim",
                "marriage_year": "NULL",
                "children": [
                    {
                        "name": "Britt",
                        "birth_year": "12"
                    },
                    {
                        "name": "Rolf",
                        "birth_year": "15"
                    }
                ]
            },
            "hobbies": [
                "jakt",
                "fiske"
            ],
            "honorary_titles": [
                {
                    "title": "RCO",
                    "institution": "NULL",
                    "year": "NULL"
                },
                {
                    "title": "GM",
                    "institution": "Skand. Krea-tUirsförsiäkr :bol.",
                    "year": "NULL"
                },
                {
                    "title": "GM",
                    "institution": "Sv. jägairförb.",
                    "year": "NULL"
                }
            ]
        },
        "1": {
            "full_name": "Heijde, Anne-Marie",
            "location": "Göteborg",
            "occupation": "tandläkare",
            "birth_details": {
                "date": "NULL",
                "place": "Asen, Skarab. l."
            },
            "education": [
                {
                    "degree": "tandl. :-ex.",
                    "year": "NULL",
                    "institution": "Prakt, i Gbg."
                }
            ],
            "family": {
                "spouse": "tandl. Victor Heijde",
                "marriage_year": "NULL",
                "children": [
                    {
                        "name": "Stig Victor Lennart",
                        "birth_year": "NULL"
                    },
                    {
                        "name": "Bengt Victor",
                        "birth_year": "NULL"
                    }
                ]
            }
        },
        "2": {
            "full_name": "Heijl, Bo Gillis",
            "location": "Borås",
            "occupation": "advokat",
            "birth_details": {
                "date": "27/12/1904",
                "place": "Sthlm"
            },
            "education": [
                {
                    "degree": "jur. kand.",
                    "year": "1929",
                    "institution": "Upps."
                }
            ]
        },
        "3": {
            "full_name": "Heijne, Otto Henrik",
            "location": "Jönköping",
            "occupation": "civilingenjör, disponent",
            "birth_details": {
                "date": "10/4/1893",
                "place": "Kvidinge, Krist. l."
            },
            "education": [
                {
                    "degree": "NULL",
                    "year": "16",
                    "institution": "KTH"
                }
            ],
            "career": [
                {
                    "position": "anst. v. Hellefors Bruks A-B",
                    "years": {
                        "start_year": 1919,
                        "end_year": 1922
                    },
                    "organization": "NULL"
                },
                {
                    "position": "Spruce Falls Co. & Kimberley Clark Co.",
                    "years": {
                        "start_year": 1922,
                        "end_year": 1925
                    },
                    "organization": "NULL"
                },
                {
                    "position": "verkst. dir. i Munksjökoncernen",
                    "years": {
                        "start_year": 1939,
                        "end_year": null
                    },
                    "organization": "NULL"
                }
            ],
            "family": {
                "spouse": "Märtha Skeppstedt",
                "marriage_year": "NULL",
                "children": [
                    {
                        "name": "Inga",
                        "birth_year": "30"
                    },
                    {
                        "name": "Hans",
                        "birth_year": "31"
                    }
                ]
            },
            "honorary_titles": [
                {
                    "title": "RVO",
                    "institution": "NULL",
                    "year": "NULL"
                }
            ]
        }
    }
}