{
    "original": "KÄMPINGE, STIG H S,\nbergsingenjör, Sandviken, f i Sthlm 30/9/19 av\nciv :ing Sixten Nilsson o Greta Suwe.\nStud:ex Strängnäs 39, KTH 45, lab:ing\nab Bofors 45, lab :ch Wikmanshytte\nbruks ab 51, forskn:ing metallurg lab ab\nNynäs-Petroleum 61, Sandvikens jernv\nab sed 63. - Hobbies: jakt, fiske.\nGift 2) 53 m Ulla Påhlsson f 25, dtr t\ndisp Carl P o Eva Holmquist. - Barn:\ni l :a akt Jan Olof f 47.\n\nKÄRRLANDER, E HARALD, fd\nriksdagsman, Sollefteå, f i Dal, Västernorrl\nl, 29/5/02 av insp Edvard K o Dorotea\nFlodin.\n\nLed AK 47-66, styr:led Sv tobaks ab,\nSkandiakoncernen. - Led Vnorrl l landst\no ordf dess FU, ordf Stadsfullm Sollefteå\n59-66.\n\nGift 36 m Ingegerd Fagerlund. - Barn:\nSvante f 47.\n\nKÄTTSTRÖM,   TORE   G,   ingenjör,\n\nSkellefteå, f i Falun 5/7/00 av kassör\nAlbert K o Ulla Olsson.\nBergssk Falun 22, ing Bolidens gruv ab\n23, avd:ch 37-65, konsult i\ngruvmätn:-frågor där sed 65. - Led Sv gruvfören\nständ gruvmätarkomm. - Utm:\nPatrS-GM. - Hobbies: sport, bridge, filateli.\n\nGift  27   m  Alida  Bergmark.   -   Barn:\nÅke f 29, Une f 32.\n\nKÖHLIN, PER G T, överläkare,\nBoden, f i Lund 6/6/24 av kapt Harald K\no Märta Persson.\n\nStud:ex Sthlm 42, med kand 45 o med\nlic Sthlm 50; eo aman Nobelinst f med\ncellforskn 46-49, vik underläk Sachsska\nbarnsjh 50-52, underläk Gbgs barnsjh\n53-60, med barnklin Umeå las 61, bitr\növerläk där 62-66, överläk med barnklin\nBoden sed 66. - Marinläk:stip 52-53,\nmarinläk av 2:a gr i mlk 53-57, i res\n57, marinläk av l:a gr i res sed 64.\nGift 51 m Ingrid Ericson f 32, dtr t fil\nmag Gösta E o Inga Hernroth. - Barn:\nHelena f 52, Birgitta f 53, Catharina\nf 56, Bengt f 61.\n\n",
    "structured": {
        "1": {
            "full_name": "Kämpinge, Stig H S",
            "location": "Sandviken",
            "occupation": "Bergsingenjör",
            "birth_details": {
                "date": "30/09/1919",
                "place": "Stockholm"
            },
            "education": [
                {
                    "degree": "Stud:ex",
                    "year": "1939",
                    "institution": "Strängnäs"
                },
                {
                    "degree": "KTH",
                    "year": "1945",
                    "institution": "Kungliga Tekniska högskolan"
                }
            ],
            "career": [
                {
                    "position": "Lab:ing",
                    "years": {
                        "start_year": 1945,
                        "end_year": 1945
                    },
                    "organization": "Bofors"
                },
                {
                    "position": "Lab:ch",
                    "years": {
                        "start_year": 1951,
                        "end_year": 1951
                    },
                    "organization": "Wikmanshytte bruks ab"
                },
                {
                    "position": "Forskn:ing metallurg",
                    "years": {
                        "start_year": 1961,
                        "end_year": null
                    },
                    "organization": "Nynäs-Petroleum"
                },
                {
                    "position": null,
                    "years": {
                        "start_year": 1963,
                        "end_year": null
                    },
                    "organization": "Sandvikens jernv ab"
                }
            ],
            "family": {
                "spouse": "Ulla Påhlsson",
                "marriage_year": "1953",
                "children": [
                    {
                        "name": "Jan Olof",
                        "birth_year": "1947"
                    }
                ]
            },
            "hobbies": [
                "jakt",
                "fiske"
            ]
        },
        "2": {
            "full_name": "Kärrlander, E Harald",
            "location": "Sollefteå",
            "occupation": "Fd riksdagsman",
            "birth_details": {
                "date": "29/05/1902",
                "place": "Dal, Västernorrland"
            },
            "career": [
                {
                    "position": "Led AK",
                    "years": {
                        "start_year": 1947,
                        "end_year": 1966
                    },
                    "organization": null
                },
                {
                    "position": "Styr:led",
                    "years": {
                        "start_year": null,
                        "end_year": null
                    },
                    "organization": "Sv tobaks ab"
                },
                {
                    "position": "Led Vnorrl l landst",
                    "years": {
                        "start_year": null,
                        "end_year": null
                    },
                    "organization": null
                },
                {
                    "position": "Ordf",
                    "years": {
                        "start_year": 1959,
                        "end_year": 1966
                    },
                    "organization": "Stadsfullm Sollefteå"
                }
            ],
            "family": {
                "spouse": "Ingegerd Fagerlund",
                "marriage_year": "1936",
                "children": [
                    {
                        "name": "Svante",
                        "birth_year": "1947"
                    }
                ]
            }
        },
        "3": {
            "full_name": "Kättström, Tore G",
            "location": "Skellefteå",
            "occupation": "Ingenjör",
            "birth_details": {
                "date": "05/07/1900",
                "place": "Falun"
            },
            "education": [
                {
                    "degree": null,
                    "year": "1922",
                    "institution": "Bergssk Falun"
                }
            ],
            "career": [
                {
                    "position": "Ing",
                    "years": {
                        "start_year": 1923,
                        "end_year": null
                    },
                    "organization": "Bolidens gruv ab"
                },
                {
                    "position": null,
                    "years": {
                        "start_year": 1965,
                        "end_year": null
                    },
                    "organization": "Konsult i gruvmätn:-frågor"
                }
            ],
            "family": {
                "spouse": "Alida Bergmark",
                "marriage_year": "1927",
                "children": [
                    {
                        "name": "Åke",
                        "birth_year": "1929"
                    },
                    {
                        "name": "Une",
                        "birth_year": "1932"
                    }
                ]
            },
            "hobbies": [
                "sport",
                "bridge",
                "filateli"
            ]
        },
        "4": {
            "full_name": "Köhlin, Per G T",
            "location": "Boden",
            "occupation": "Överläkare",
            "birth_details": {
                "date": "6/6/1924",
                "place": "Lund"
            },
            "education": [
                {
                    "degree": "Stud:ex",
                    "year": "1942",
                    "institution": "Stockholm"
                },
                {
                    "degree": "Med kand",
                    "year": "1945",
                    "institution": "Stockholm"
                },
                {
                    "degree": "Med lic",
                    "year": "1950",
                    "institution": "Stockholm"
                }
            ],
            "career": [
                {
                    "position": "Eo aman",
                    "years": {
                        "start_year": 1946,
                        "end_year": 1949
                    },
                    "organization": "Nobelinst f med cellforskn"
                },
                {
                    "position": "Vik underläk",
                    "years": {
                        "start_year": 1950,
                        "end_year": 1952
                    },
                    "organization": "Sachsska barnsjh"
                },
                {
                    "position": "Underläk",
                    "years": {
                        "start_year": 1953,
                        "end_year": 1960
                    },
                    "organization": "Göteborgs barnsjukhus"
                },
                {
                    "position": "Bitr överläk",
                    "years": {
                        "start_year": 1961,
                        "end_year": 1966
                    },
                    "organization": "Umeå las"
                },
                {
                    "position": "Överläk",
                    "years": {
                        "start_year": 1966,
                        "end_year": null
                    },
                    "organization": "Boden"
                }
            ],
            "family": {
                "spouse": "Ingrid Ericson",
                "marriage_year": "1951",
                "children": [
                    {
                        "name": "Helena",
                        "birth_year": "1952"
                    },
                    {
                        "name": "Birgitta",
                        "birth_year": "1953"
                    },
                    {
                        "name": "Catharina",
                        "birth_year": "1956"
                    },
                    {
                        "name": "Bengt",
                        "birth_year": "1961"
                    }
                ]
            }
        }
    }
}