{
    "original": "Rydbeck, Carl Wilhelm, assessor,\nMalmö, f. 20/10/89 i Lund av urmak.\nCarl Henrik R. o. Christina Friberg.\nG. 24 m. Louisie de Ge er af Leufsta.\nBarn: Louis f. 26. — Stud:ex. d Lund\n\n08, jur. kand. där 12. E. o. nöt. i\nSkånska hovr. 12, tingstjg. 14-15, polisnot.\nv. rådhusr. i Maillmö 17, aktuarie 19,\nassess. 20, tillika inskrivn:- o.\nägodell-n :dom. Ombudsm. i riksbank,\navd:-kont. i Malmö sed. 32. Ordf. i tax:nd\n32-45. Svensk, skand., dansk o. balt.\nmast. i golf uppr. ggr, distr :mäst. f.\nSkåne 12, 19, 20. RVO 44, RF dipl.,\nSkånes idr:förb. dipl.\n\nRydbeck, Carl Axel Emil, direktör,\nMalmö, ;f. 22/2/82 i Sundsvall av\nstads-ing. Eimlll R. o. Jenny Björck. G. 11 m.\nAnrfa Trotzig. Barn: Kerstin» -f. 12, g.\nm. tandlläk. Erik Holmgren, Lund,\nClaes 15, dir., Gbg, Åke 17. —\nStud:-ex. i Sundsvall 00, avg:ex. fr. KTH\n04. Div. anst. i ,Sv:e o. Amerika 04-09,\nbrandinsp. i Brand- o. Lifförsäkr. A-B\nSkåne 09-19, gen :agent i Sthlm f.\nSkåne, Malmö o. Gauthiod 19-30,\nverlkst. dir. i Brand- o. Lifförsäkr. A-B\nSkåne 30-32, verkst. dir. i\nSkåne-koncernen 32-48.\n\nRydbeck, Sven Otto Henrik,\nprofessor emer., Lund, f. 25/8/72 i Lund av\nC. H. R. o. Christina Friberg. G. 05 m.\nLaura Ringius. Barn: Monica &lt;f. 06,\ndocent, antikvarie, Sthlm, Elisabeth 10,\npoliissyster, Malmö, Cecilia 15, lär.,\nNorrköp., Otto 17, lantbr., Lund. —\nMed. fil. ex. i Lund 91, fil. kand. 99’,\nfill. lic. O¾ fil. dr 05, Stud. i uti. Förest,\nf. hist. mus. samt mynt- o. miedaljkab.\n04, docent i nord. konstarkeol. 09, prof.\ni förhist. o. imedeltidsarkeol. 19-37.\nOrdnat Lunds urliv. hist. mus. o.\ndomkyrkomus., kontr. o. lett restaurer. av\nskånska kyrkor, särsk. restaur. av\nLunds domkyrka 39-44. Ordf. i Etnol.\nfören. o. i för en. Det gamla Lund, led.\nav domkyrkoråd, i Lund 22-42, av\nNord. oldskr. selsk. 05, av Danske\nSellsk. f. Faedrel. Hist. o. Sprog 18,\nLLHS 19, LHA 24, LES 29, korrL\nArch. Inst. d. Deutsch. Reiches 36,\nverks. s. vetensk. teckn. o.\nportr:skulp-tör. Bl. skr.: Medeltida kalkmålningar\ni Skånes kyrkor (04), Lunds\ndomkyrka (11, 15, 20 o. 39), Bidr. t. Lunds\ndomkyrkas byggn :hist. (15), Lunds\ndomkyrkas byggn:hist. (23), Stud. i\nSkånes renässans o. barockskulpt. (17),\nTvå märkl. kon-st n. (18), Ärkebisik.\nAndreas Sunessons grav i Lunds\ndomkyrka (tills. m. Furst o. Branting 26),\nStenåldershavets nivåförändr. o.\nNordens äldsta bebyggelse (28),\nGlim-mingehus   (32 o. 47), Den med :tida bor-\n\ngen i Skanör (35), Fangkultur u.\nMega-lithkultur in der sÜdskand Steinzeit\n(38), Tre lundens, ärkebiskop, i\narkeol.-antmpol. belysn. (41), Knut d. hel.\nLaurentiuskyrka (42), Den arkeol.\nforskn, o. hist. mus. v. Lunds univ.\n1735-1937 (4¾, Momuiment o.\nmänniskor i forntid. Skåne (44), Dädesjö\nkyrka o. dess målningar (44), Lunds\ndomkyrka, desis1 byggn. o. äldre invent.\n(46). KN!02kl, RVO, RDDO.\n\n",
    "structured": {
        "0": {
            "full_name": "Carl Wilhelm Rydbeck",
            "location": "Malmö",
            "occupation": "assessor",
            "birth_details": {
                "date": "20/10/1889",
                "place": "Lund",
                "parents": "Carl Henrik R. and Christina Friberg",
                "place_coordinates": {
                    "Latitude": 55.7046601,
                    "Longitude": 13.1910073
                }
            },
            "education": [
                {
                    "degree": "Stud:ex.",
                    "year": "Lund 08",
                    "institution": "Lund",
                    "institution_coordinates": {
                        "Latitude": 55.7046601,
                        "Longitude": 13.1910073
                    }
                },
                {
                    "degree": "jur. kand.",
                    "year": "Lund 12",
                    "institution": "Lund",
                    "institution_coordinates": {
                        "Latitude": 55.7046601,
                        "Longitude": 13.1910073
                    }
                }
            ],
            "career": [
                {
                    "position": "E. o. not.",
                    "years": {
                        "start_year": 1912,
                        "end_year": 1919
                    },
                    "organization": "Skånska hovr."
                },
                {
                    "position": "tingstjg.",
                    "years": {
                        "start_year": 1914,
                        "end_year": 1915
                    }
                },
                {
                    "position": "polisnot. v. rådhusr.",
                    "years": {
                        "start_year": 1917
                    }
                },
                {
                    "position": "aktuarie",
                    "years": {
                        "start_year": 1919
                    }
                },
                {
                    "position": "assess.",
                    "years": {
                        "start_year": 1920
                    },
                    "organization": "ägodell-n :dom."
                },
                {
                    "position": "Ombudsm.",
                    "organization": "riksbank, avd:-kont.",
                    "years": "sed. 32"
                },
                {
                    "position": "Ordf.",
                    "organization": "tax:nd",
                    "years": "32-45"
                }
            ],
            "family": {
                "spouse": "Louisie de Ge er af Leufsta",
                "marriage_year": "24",
                "children": [
                    {
                        "name": "Louis",
                        "birth_year": "26"
                    }
                ]
            },
            "location_coordinates": {
                "Latitude": 55.604981,
                "Longitude": 13.003822
            },
            "occupation_hisco_code": 124,
            "occupation_cosine_similarity": 0.6091035923886271,
            "occupation_hisco_occupation": "Solicitors"
        },
        "1": {
            "full_name": "Carl Axel Emil Rydbeck",
            "location": "Malmö",
            "occupation": "direktör",
            "birth_details": {
                "date": "22/2/1882",
                "place": "Sundsvall",
                "parents": "Eimlll R. o. Jenny Björck",
                "place_coordinates": {
                    "Latitude": 62.390811,
                    "Longitude": 17.306927
                }
            },
            "education": [
                {
                    "degree": "Stud:-ex.",
                    "year": "Sundsvall 00",
                    "institution": "Sundsvall",
                    "institution_coordinates": {
                        "Latitude": 62.390811,
                        "Longitude": 17.306927
                    }
                },
                {
                    "degree": "avg:ex. fr. KTH",
                    "year": "04"
                }
            ],
            "career": [
                {
                    "position": "gen :agent",
                    "years": {
                        "start_year": 1919,
                        "end_year": 1930
                    },
                    "organization": "Sthlm f. Skåne, Malmö o. Gauthiod"
                },
                {
                    "position": "verlkst. dir.",
                    "organization": "Brand- o. Lifförsäkr. A-B Skåne",
                    "years": "30-32"
                },
                {
                    "position": "verkst. dir.",
                    "organization": "Skåne-koncernen",
                    "years": "32-48"
                }
            ],
            "family": {
                "spouse": "Anrfa Trotzig",
                "marriage_year": "11",
                "children": [
                    {
                        "name": "Kerstin",
                        "birth_year": "12",
                        "spouse": "tandlläk. Erik Holmgren",
                        "institution": "Lund"
                    },
                    {
                        "name": "Claes",
                        "birth_year": "15",
                        "occupation": "dir.",
                        "location": "Gbg"
                    },
                    {
                        "name": "Åke",
                        "birth_year": "17"
                    }
                ]
            },
            "location_coordinates": {
                "Latitude": 55.604981,
                "Longitude": 13.003822
            },
            "occupation_hisco_code": 211,
            "occupation_cosine_similarity": 0.639446261605922,
            "occupation_hisco_occupation": "General Managers"
        },
        "2": {
            "full_name": "Sven Otto Henrik Rydbeck",
            "location": "Lund",
            "occupation": "professor emer.",
            "birth_details": {
                "date": "25/8/1872",
                "place": "Lund",
                "parents": "C. H. R. o. Christina Friberg",
                "place_coordinates": {
                    "Latitude": 55.7046601,
                    "Longitude": 13.1910073
                }
            },
            "education": [
                {
                    "degree": "Med. fil. ex.",
                    "year": "Lund 91",
                    "institution": "Lund",
                    "institution_coordinates": {
                        "Latitude": 55.7046601,
                        "Longitude": 13.1910073
                    }
                },
                {
                    "degree": "fil. kand.",
                    "year": "99",
                    "institution": "Lund",
                    "institution_coordinates": {
                        "Latitude": 55.7046601,
                        "Longitude": 13.1910073
                    }
                },
                {
                    "degree": "fill. lic.",
                    "year": "O¾"
                },
                {
                    "degree": "fil. dr",
                    "year": "05"
                }
            ],
            "family": {
                "spouse": "Laura Ringius",
                "marriage_year": "05",
                "children": [
                    {
                        "name": "Monica",
                        "birth_year": "06",
                        "occupation": "docent",
                        "location": "Sthlm"
                    },
                    {
                        "name": "Elisabeth",
                        "birth_year": "10",
                        "occupation": "poliissyster",
                        "location": "Malmö"
                    },
                    {
                        "name": "Cecilia",
                        "birth_year": "15",
                        "occupation": "lär.",
                        "location": "Norrköp."
                    },
                    {
                        "name": "Otto",
                        "birth_year": "17",
                        "occupation": "lantbr.",
                        "location": "Lund"
                    }
                ]
            },
            "location_coordinates": {
                "Latitude": 55.7046601,
                "Longitude": 13.1910073
            },
            "occupation_hisco_code": 12,
            "occupation_cosine_similarity": 0.5239577165430901,
            "occupation_hisco_occupation": "Physicists"
        }
    }
}