{
    "original": "MATS, SUG O, direktör, Falun, f i\nEnviken,  Kopparb  l,   11/11/19  av  dir\nMats Nils Ersson o Märta Ersson.\nRealex   37,   Bröd   Påhlmans   hdlI   41,\nverkst dir Wasatrafik-företagen sed 51.\n\n-   Ordf  Dalarnas   omnibusäg:fören   50,\nordf Sv omnibusäg:förb  63,  styr:suppl\nBiltraf   arb:giv:förb   58,   led   Envikens\nturistkomm 62, styr :led Falubygdens\ntu-ristfören 62; fd ordf komm :ndn o\nbrandstyr samt led komm:fullm o ind :komm\nm m. - Hobby: jakt.\n\nGift 42 m Birgit Rönnlund f 22, dtr t\nHenning R o Amy Levin. - Barn: Carin\nf 42, Olle f 44, Staffan f 47.\n\nMATSSON se MATTSON\n\nMATTHIESEN, BENGT W, förste\nlänsnotarie, Örebro, f i Sthlm 6/2/15 av\nbankdir Svante M o Anna Nääs.\nStud:ex 33, jur kand Sthlm 39, tingsnot\nSkövde doms 41-43, länsbokh o länsnot\nlänsstyr Värml l 47-58, l:e länsnot\nÖrebro l sed 58. - Sekr hyresnd Karlstad\n49-57. - Medl W-sex. - Hobby: tennis.\n\nGift 50 m Sigbritt Carlsson f 30, dtr t\nskrädd C G C o Maja Kjellberg. - Barn:\nEva f 51, Anne f 54, Åsa f 56.\n\nMATTHIS, HENRY PETER,\nförfattare, Tullinge, f i Gbg 16/1/92 av\nsnic-karmäst Johan Peter Mattson o Hedvig\nOlsson.\n\nStud:ex 12, stud GbgHS o Lunds univ\n13-20, lär Gamleby folkhögsk 21-29.\n-Styr:led Sv:es förf:fören 39-48, ordf\nSv-rumän fören 50, sv komm f\nÖstersjövec-kan 59, sekr Skand konstnärskr 43-46.\n-Skr: novelldebut i pressen (09), Livets\nlekar (19), Gudsbarnet (26),\nMänniskornas son (28), Nådens dag (30), Hjälten\nlever (32), Nya människor (34), Den\nnordiska flaggstången (essäer 35),\nNybyggarna som odlade guld (40),\nBröllopsresa i karusell (nov 41), Nordisk\nmosaik (essäer o reseskildr 44), Finska\nfolksagor (tills m Katri Vala 44), Vårt\nhjärtas villospår (44), Jag binder en\nkrans (46), Den vackraste muskeln (nov\n46), Den stora dagen (folkuppl 46),\nÄlven kommer (folkuppl 47), Rumänska\nrikedomar (essäer 52), Kvinnor på väg\n(54, under pseud Hedvig Pauline). - Sign:\nH P M.\n\nGift 23 m Marth Galaasen f 95, dtr t\nlantbr, köpm Peter G o Kjersti\nNord-gaard. - Barn: Eilif f 24, Hildegun f 27,\nBjörn f 28, Boel f 33, Sköld Peter f 37.\n\n",
    "structured": {
        "1": {
            "full_name": "MATS, SUG O, direktör",
            "location": "Falun",
            "occupation": "direktör",
            "birth_details": {
                "date": "11/11/1919",
                "place": "Enviken, Kopparbergs län",
                "parents": "Mats Nils Ersson o Märta Ersson"
            },
            "education": [
                {
                    "degree": "Realex",
                    "year": "1937",
                    "institution": "NULL"
                },
                {
                    "degree": "Bröd Påhlmans hdlI",
                    "year": "1941",
                    "institution": "NULL"
                }
            ],
            "career": [
                {
                    "position": "verkst dir Wasatrafik-företagen",
                    "years": {
                        "start_year": 1951,
                        "end_year": 0
                    },
                    "organization": "NULL"
                }
            ],
            "family": {
                "spouse": "Birgit Rönnlund",
                "marriage_year": "1942",
                "children": [
                    {
                        "name": "Carin",
                        "birth_year": "1942"
                    },
                    {
                        "name": "Olle",
                        "birth_year": "1944"
                    },
                    {
                        "name": "Staffan",
                        "birth_year": "1947"
                    }
                ]
            }
        },
        "2": {
            "full_name": "MATTHIESEN, BENGT W, förste länsnotarie",
            "location": "Örebro",
            "occupation": "förste länsnotarie",
            "birth_details": {
                "date": "06/02/1915",
                "place": "Sthlm",
                "parents": "Svante M o Anna Nääs"
            },
            "education": [
                {
                    "degree": "Stud:ex",
                    "year": "1933",
                    "institution": "NULL"
                },
                {
                    "degree": "jur kand",
                    "year": "1939",
                    "institution": "Sthlm"
                }
            ],
            "career": [
                {
                    "position": "landsknecht",
                    "years": {
                        "start_year": 0,
                        "end_year": 0
                    },
                    "organization": "NULL"
                }
            ],
            "family": {
                "spouse": "Sigbritt Carlsson",
                "marriage_year": "1950",
                "children": [
                    {
                        "name": "Eva",
                        "birth_year": "1951"
                    },
                    {
                        "name": "Anne",
                        "birth_year": "1954"
                    },
                    {
                        "name": "Åsa",
                        "birth_year": "1956"
                    }
                ]
            }
        },
        "3": {
            "full_name": "MATTHIS, HENRY PETER",
            "location": "Tullinge",
            "occupation": "författare",
            "birth_details": {
                "date": "16/01/1892",
                "place": "Gbg",
                "parents": "Johan Peter Mattson o Hedvig Olsson"
            },
            "education": [
                {
                    "degree": "Stud:ex",
                    "year": "1912",
                    "institution": "NULL"
                },
                {
                    "degree": "NULL",
                    "year": "NULL",
                    "institution": "GbgHS"
                }
            ],
            "career": [
                {
                    "position": "NULL",
                    "years": {
                        "start_year": 0,
                        "end_year": 0
                    },
                    "organization": "NULL"
                }
            ],
            "family": {
                "spouse": "Marth Galaasen",
                "marriage_year": "1923",
                "children": [
                    {
                        "name": "Eilif",
                        "birth_year": "1924"
                    },
                    {
                        "name": "Hildegun",
                        "birth_year": "1927"
                    },
                    {
                        "name": "Björn",
                        "birth_year": "1928"
                    },
                    {
                        "name": "Boel",
                        "birth_year": "1933"
                    },
                    {
                        "name": "Sköld Peter",
                        "birth_year": "1937"
                    }
                ]
            }
        }
    }
}