{
    "original": "MONTGOMERY-CEDERHIELM, J\nRICHARD O R, överstelöjtnant,\nOdensbacken, f i Skövde 8/7/17 av öv:löjtn\nJohn M-C o Ebba Silfverstolpe.\nStud:ex Hbg 35, off:ex 38, KHS 48-50,\nfänr K 3 38, löjtn 40, ryttm v kav 46,\nmajor 57, I 10 58, fö 51-61, öv:löjtn\n62, stabsch Örebro f ostab sed 61. -\nInneh Segersjö fideikommiss. - Medl\nCon-cordia. - Utm: RSO, SkytteM. -\nHobbies: jakt, fiske.\n\nGift 43-63 m Gull Bengtson f 17, dtr t\nköpm Carl-Edvard B o Elisabeth\nHenricsson. - Barn: Anne f 44, Cecilia f 46,\nRobert f 48, Patrik f 52.\n\nMONTHAN, T OLOF, tulldirektör,\nDalarö, f i Sthlm 19/6/06 av förman\nThure M o Ellen Nyström.\nStud:ex 26, tullsk 30, ch Ö:a kustdistr\n46, l:e byråinsp gen :tullstyr 56,\ntullöver-insp centraltullkamm Sthlm 60, tulldir o\nch där sed 61. - Sekr komm ang\nutvidgade arb:uppg f tullv kustbevakn 41,\narb:tidskomm o arb:tidsdeleg f tullv\nkust- o gränsbevakn 47-48, led dess\narb:-tidsnd 49-60, tullv donationsnd 59, lär i\nförfattn:kunskap o arb:ledn tullsk 44,\nförest tullmus 53, ordf Sv:es allm\ntull-tjm:fören 50-59 (kassör 37, sekr 44, hedL\n59), styr:led SR 51-60. - Utm: FinlQl-\n\nftjK. - Hobbies: tullmuseet, byggnads- o\n\nplaneringsverksamhet.\n\nGift 32 m Maj Johansson f 11. - Barn:\n\nChristina f  37, Agneta f 40, Ingegerd\n\nf 43, Margareta f 47.\n\nMORANDER, K RAGNAR, lektor,\nFalun, f i Nykpg 25/6/07 av disp Carl\nJohansson o Hilma Andersson.\nStud:ex 26, folksk:ex Växjö 35, fil lic\nUpps 38, fil mag 44, folkskollär Gbg 35,\nvik lekt folksk:sem Falun 45, vik\nämneslär Gbgs komm mellansk 46, adj\nsmå-sk:sem Norrkpg 47, lekt folksk:sem\nFalun sed 48. - S kr: upps i bot o pedagog\nämnen. - Hobbies: natur, färgfoto.\nGift 38 m Anna-Stina Grönbeck f 13,\ndtr t bankkamr Gösta G o Agnes\nFro-mell. - Barn: Karl-Erik f 40, Göran f 46.\n\n",
    "structured": {
        "1": {
            "full_name": "Montgomery-Cederhielm, J Richard O R",
            "location": "Odensbacken",
            "occupation": "Överstelöjtnant",
            "birth_details": {
                "date": "08/07/1917",
                "place": "Skövde"
            },
            "education": [
                {
                    "degree": "Stud:ex",
                    "year": "1935",
                    "institution": "Hbg"
                },
                {
                    "degree": "Off:ex",
                    "year": "1938",
                    "institution": "KHS"
                }
            ],
            "career": [
                {
                    "position": "Fänrik",
                    "years": {
                        "start_year": 1938,
                        "end_year": 1940
                    },
                    "organization": "K 3"
                },
                {
                    "position": "Löjtnant",
                    "years": {
                        "start_year": 1940,
                        "end_year": 1946
                    },
                    "organization": "Kav"
                },
                {
                    "position": "Ryttmästare",
                    "years": {
                        "start_year": 1946,
                        "end_year": 1957
                    },
                    "organization": "Kav"
                },
                {
                    "position": "Major",
                    "years": {
                        "start_year": 1957,
                        "end_year": 1958
                    },
                    "organization": "I 10"
                },
                {
                    "position": "Överstelöjtnant",
                    "years": {
                        "start_year": 1962,
                        "end_year": null
                    },
                    "organization": "Stabsch Örebro f ostab"
                }
            ],
            "family": {
                "spouse": "Gull Bengtson",
                "marriage_year": "1943",
                "children": [
                    {
                        "name": "Anne",
                        "birth_year": "1944"
                    },
                    {
                        "name": "Cecilia",
                        "birth_year": "1946"
                    },
                    {
                        "name": "Robert",
                        "birth_year": "1948"
                    },
                    {
                        "name": "Patrik",
                        "birth_year": "1952"
                    }
                ]
            },
            "hobbies": [
                "Jakt",
                "Fiske"
            ]
        },
        "2": {
            "full_name": "Monthan, T Olof",
            "location": "Dalarö",
            "occupation": "Tulldirektör",
            "birth_details": {
                "date": "19/06/1906",
                "place": "Sthlm"
            },
            "education": [
                {
                    "degree": "Stud:ex",
                    "year": "1926",
                    "institution": null
                },
                {
                    "degree": "Tullsk",
                    "year": "1930",
                    "institution": null
                }
            ],
            "career": [
                {
                    "position": "Ch Ö:a kustdistr",
                    "years": {
                        "start_year": 1946,
                        "end_year": null
                    },
                    "organization": null
                },
                {
                    "position": "L:e byråinsp gen",
                    "years": {
                        "start_year": null,
                        "end_year": 1956
                    },
                    "organization": "Tullstyr"
                },
                {
                    "position": "Tullöver-insp centraltullkamm Sthlm",
                    "years": {
                        "start_year": 1960,
                        "end_year": null
                    },
                    "organization": null
                }
            ],
            "family": {
                "spouse": "Maj Johansson",
                "marriage_year": "1932",
                "children": [
                    {
                        "name": "Christina",
                        "birth_year": "1937"
                    },
                    {
                        "name": "Agneta",
                        "birth_year": "1940"
                    },
                    {
                        "name": "Ingegerd",
                        "birth_year": "1943"
                    },
                    {
                        "name": "Margareta",
                        "birth_year": "1947"
                    }
                ]
            },
            "hobbies": [
                "Tullmuseet",
                "Byggnads- o planeringsverksamhet"
            ]
        },
        "3": {
            "full_name": "Morander, K Ragnar",
            "location": "Falun",
            "occupation": "Lektor",
            "birth_details": {
                "date": "25/06/1907",
                "place": "Nykpg"
            },
            "education": [
                {
                    "degree": "Stud:ex",
                    "year": "1926",
                    "institution": null
                },
                {
                    "degree": "Folksk:ex",
                    "year": "1935",
                    "institution": "Växjö"
                },
                {
                    "degree": "Fil lic",
                    "year": "1938",
                    "institution": "Upps"
                },
                {
                    "degree": "Fil mag",
                    "year": "1944",
                    "institution": null
                }
            ],
            "career": [
                {
                    "position": "Folkskollärare",
                    "years": {
                        "start_year": 1935,
                        "end_year": null
                    },
                    "organization": "Gbg"
                },
                {
                    "position": "Vik lektor",
                    "years": {
                        "start_year": 1948,
                        "end_year": null
                    },
                    "organization": "Falun"
                }
            ],
            "family": {
                "spouse": "Anna-Stina Grönbeck",
                "marriage_year": "1938",
                "children": [
                    {
                        "name": "Karl-Erik",
                        "birth_year": "1940"
                    },
                    {
                        "name": "Göran",
                        "birth_year": "1946"
                    }
                ]
            },
            "hobbies": [
                "Natur",
                "Färgfoto"
            ]
        }
    }
}