{
    "original": "MALM, LÄRS-BERTIL, kapten,\ninköpschef, Eskilstuna, f i Eskilstuna 22/6/\n13 av lokför Bertil Fredriksson o Anna\nLundström.\n\nStud:ex, kassör Sv Shell Eskilstuna 30,\ninköpsch Bröd Söderberg ab sed 34.\n-Kapt F l res. - Hobbies: konst,\nlitteratur.\n\nGift m Dagny Andersson f 26. - Barn:\nEva-Lotta f 53, Anna f 61,\n\nMALM, L TORSTEN, advokat,\nÖrebro, f i Wilkinsburg, Pä, USA, 13/7/04\nav civiling Sven M o Edla Larsson.\nStud:ex Karlstad 22, jur kand Upps 27,\ntingstjg Östernärkes doms 28-30, bitr jur\nadv C Ljung Örebro 31, deläg\nAdvokaterna Ljung o Malm sed 33. - LSA 33.\n-Styr :led ab Lättbetong, Ytongbol,\nLäns-tidn tryckeri ab m fi. - Led barnav:nd\n45-58. - Utm: RVO. - Hobbies: jakt,\nfiske.\n\nGift 34 m Annalisa Isakson f 09, dtr t\ngrossh Per I o Signe Jonsson. - Barn:\nGunilla f 35, Lars f 37, Lennart f 42,\nCaroline f 46.\n\nMALMBERG,    EINAR   H,    rådman,\n\nUppsala, f i Sthlm 27/4/23 av major H\n\nM o Dagmar Sandström.\n\nJur kand StHS 47, tingstjg Ångermani s\n\ndoms   47-49,   hovr :fisk  Hovr  f  Nedre\n\nNorrl 50, assess rådhusr Upps 56, rådm\n\ndär sed 59. - Bitr lär i processr Upps\n\nuniv sed 57, auditör o kontr:off över-\n\nvakn:kommiss Korea 55, auditör o pers:-\n\nch sv FN-bat Kongo 61.\n\nGift 2) 58 m Sargit Berg f 23. - Barn:\n\nElizabeth f 44, Susanne f 48.\n\n",
    "structured": {
        "1": {
            "full_name": "Malm, Lärs-Bertil",
            "location": "Eskilstuna",
            "occupation": "Kapten, Inköpschef",
            "birth_details": {
                "date": "22/06/1913",
                "place": "Eskilstuna",
                "parents": "lokför Bertil Fredriksson o Anna Lundström"
            },
            "education": [
                {
                    "degree": "Stud:ex",
                    "year": "1930",
                    "institution": "kassör Sv Shell Eskilstuna"
                }
            ],
            "career": [
                {
                    "position": "inköpsch Bröd Söderberg ab",
                    "years": {
                        "start_year": 1934,
                        "end_year": null
                    },
                    "organization": null
                }
            ],
            "family": {
                "spouse": "Dagny Andersson",
                "marriage_year": null,
                "children": [
                    {
                        "name": "Eva-Lotta",
                        "birth_year": "1953"
                    },
                    {
                        "name": "Anna",
                        "birth_year": "1961"
                    }
                ]
            },
            "hobbies": [
                "konst",
                "litteratur"
            ]
        },
        "2": {
            "full_name": "Malm, L Torsten",
            "location": "Örebro",
            "occupation": "Advokat",
            "birth_details": {
                "date": "13/07/1904",
                "place": "Wilkinsburg, Pä, USA",
                "parents": "civiling Sven M o Edla Larsson"
            },
            "education": [
                {
                    "degree": "Stud:ex",
                    "year": "1922",
                    "institution": "Karlstad"
                },
                {
                    "degree": "jur kand",
                    "year": "1927",
                    "institution": "Upps"
                }
            ],
            "career": [
                {
                    "position": "tingstjg Östernärkes doms",
                    "years": {
                        "start_year": 1928,
                        "end_year": 1930
                    },
                    "organization": null
                },
                {
                    "position": "bitr jur adv C Ljung Örebro",
                    "years": {
                        "start_year": 1931,
                        "end_year": null
                    },
                    "organization": "Advokaterna Ljung o Malm"
                }
            ],
            "family": {
                "spouse": "Annalisa Isakson",
                "marriage_year": "1934",
                "children": [
                    {
                        "name": "Gunilla",
                        "birth_year": "1935"
                    },
                    {
                        "name": "Lars",
                        "birth_year": "1937"
                    },
                    {
                        "name": "Lennart",
                        "birth_year": "1942"
                    },
                    {
                        "name": "Caroline",
                        "birth_year": "1946"
                    }
                ]
            },
            "honorary_titles": [
                "LSA 33"
            ],
            "hobbies": [
                "jakt",
                "fiske"
            ]
        },
        "3": {
            "full_name": "Malmberg, Einar H",
            "location": "Uppsala",
            "occupation": "Rådman",
            "birth_details": {
                "date": "27/04/1923",
                "place": "Sthlm",
                "parents": "major H M o Dagmar Sandström"
            },
            "education": [
                {
                    "degree": "Jur kand",
                    "year": "1947",
                    "institution": "StHS"
                }
            ],
            "career": [
                {
                    "position": "tingstjg Ångermanis doms",
                    "years": {
                        "start_year": 1947,
                        "end_year": 1949
                    },
                    "organization": null
                },
                {
                    "position": "hovr:fisk Hovr f Nedre Norrl",
                    "years": {
                        "start_year": 1950,
                        "end_year": null
                    },
                    "organization": null
                },
                {
                    "position": "assess rådhusr Upps",
                    "years": {
                        "start_year": 1956,
                        "end_year": null
                    },
                    "organization": null
                }
            ],
            "family": {
                "spouse": "Sargit Berg",
                "marriage_year": "1958",
                "children": [
                    {
                        "name": "Elizabeth",
                        "birth_year": "1944"
                    },
                    {
                        "name": "Susanne",
                        "birth_year": "1948"
                    }
                ]
            }
        }
    }
}