{
    "original": "MINELL, GUSTAF H,\ncivilförsvars-direktör, Uppsala, f i Arvika 2/12/04 av\njv:tjm Gustaf M o Maria Fernau.\nLandsfisk:ex 28, krigsfisk:ex 40, FHS\n54. - Anst landsstat Värml l 23-43,\nlandsfisk Charlottenbergs dt 43-51, Vingåkers\ndt 51-53, civilförsv:dir Upps l sed 53.\n-Medl FrimO. - Utm: RNO, SCFSMoGt,\nSRKSM, SLKSM, HvSM, FAKGM,\nNFrK, FrftjM.\nGift 35 m Elsa Rülcker f 10, dtr t disp\n\nEugen R o Aina Lydén.  - Barn: Olle\nf 37, Hugo f 43.\nde   MINK,   HENRI   L,   civilingenjör,\n\nTumba, f i Rotterdam 18/8/31 av\növerlär Jaap de M o Nelly Maas.\nStud:ex Schiedam 49, Tekn högsk Delft\n\n56,  ing LME 56, verkst dir o styr :led\nInternat Documentation Centre ab sed\n\n57.   - Medl Rotary.  - Hobbies: musik,\nlitteratur, tennis, schack.\n\nGift 59 m Oetje van der Plas f 33, dtr t\nGerrit v d P o Jacoba Roos. - Barn:\nMirjam f 59, Monica f 61.\nMINNING, SVEN J,\nsågverksförvaltare, Vikarbyn, f i Skön, Västernorrl l,\n20/11/09 av köpm Johan Johanson o h h.\nRealex, anst Sunds ab Sunds o Nyviks\nsågverk 26, sågv:insp o platsch Yxvikens\nsågverk Fiskeby fabr ab 48, sågv:förv\no platsch Vikarby ångsåg Grycksbo\npappersbruk ab sed 55. - Företr f\nband-sågn:metodens inf o utveckl i sv\nsågv:-ind. - Medl Odd Fellow. - Utm:\nSv-rifbftjM. - Hobbies: jakt, fiske.\nGift 34 m Göta Backström f 10, dtr t\nbyggm E B o h h. - Barn: Karin f 37,\nLars Erik f 42, Håkan f 46.\n\nMITLIN, MARK, direktör, Östertälje,\nf i Sthlm 23/10/18 av dir Wulf M o\nAnna Kaplan.\n\nStud:ex 38, Bar-Lock-Inst 40, verkst dir\nMarcus &amp; Co ab Järna sed 46. - Ordf\nSMS komm. - Medl S:ta Ragnhilds gille.\n- Hobbies: sport, curling.\nGift 46 m Annika Gratte, dtr t köpman\nLorentz G o Emma Olsson. - Barn:\nPeter f 47.\n\n",
    "structured": {
        "1": {
            "full_name": "Gustaf H Minell",
            "location": "Uppsala",
            "occupation": "Civilförsvars-direktör",
            "birth_details": {
                "date": "02/12/1904",
                "place": "Arvika"
            },
            "education": [
                {
                    "degree": "Landsfisk:ex",
                    "year": "1928",
                    "institution": "NULL"
                },
                {
                    "degree": "Krigsfisk:ex",
                    "year": "1940",
                    "institution": "NULL"
                },
                {
                    "degree": "FHS",
                    "year": "1954",
                    "institution": "NULL"
                }
            ],
            "career": [
                {
                    "position": "Anst landsstat",
                    "years": {
                        "start_year": 1923,
                        "end_year": 1943
                    },
                    "organization": "Värml l"
                },
                {
                    "position": "Landfisk",
                    "years": {
                        "start_year": 1943,
                        "end_year": 1951
                    },
                    "organization": "Charlottenbergs dt"
                },
                {
                    "position": "Vingåkers dt",
                    "years": {
                        "start_year": 1951,
                        "end_year": 1953
                    },
                    "organization": "NULL"
                },
                {
                    "position": "Civilförsv:dir",
                    "years": {
                        "start_year": 1953,
                        "end_year": "NULL"
                    },
                    "organization": "Upps l"
                }
            ],
            "family": {
                "spouse": "Elsa Rülcker",
                "marriage_year": "1935",
                "children": [
                    {
                        "name": "Olle",
                        "birth_year": "1937"
                    },
                    {
                        "name": "Hugo",
                        "birth_year": "1943"
                    }
                ]
            },
            "publications": "NULL",
            "community_involvement": "NULL",
            "board_memberships": "NULL",
            "honorary_titles": "NULL",
            "hobbies": "NULL"
        },
        "2": {
            "full_name": "Henri L Mink",
            "location": "Tumba",
            "occupation": "Civilingenjör",
            "birth_details": {
                "date": "18/08/1931",
                "place": "Rotterdam"
            },
            "education": [
                {
                    "degree": "Stud:ex",
                    "year": "1949",
                    "institution": "Schiedam"
                },
                {
                    "degree": "Tekn högsk Delft",
                    "year": "1956",
                    "institution": "NULL"
                }
            ],
            "career": {
                "position": "Verkst dir o styr :led",
                "years": {
                    "start_year": 1957,
                    "end_year": "NULL"
                },
                "organization": "Internat Documentation Centre ab"
            },
            "family": {
                "spouse": "Oetje van der Plas",
                "marriage_year": "1959",
                "children": [
                    {
                        "name": "Mirjam",
                        "birth_year": "1959"
                    },
                    {
                        "name": "Monica",
                        "birth_year": "1961"
                    }
                ]
            },
            "publications": "NULL",
            "community_involvement": "NULL",
            "board_memberships": "NULL",
            "honorary_titles": "NULL",
            "hobbies": [
                "musik",
                "litteratur",
                "tennis",
                "schack"
            ]
        },
        "3": {
            "full_name": "Sven J Minning",
            "location": "Vikarbyn",
            "occupation": "Sågverksförvaltare",
            "birth_details": {
                "date": "20/11/1909",
                "place": "Skön, Västernorrl l"
            },
            "education": {
                "degree": "Realex",
                "year": "NULL",
                "institution": "NULL"
            },
            "career": [
                {
                    "position": "Sågv:insp o platsch",
                    "years": {
                        "start_year": 1948,
                        "end_year": "NULL"
                    },
                    "organization": "Yxvikens sågverk Fiskeby fabr ab"
                },
                {
                    "position": "Sågv:förv o platsch",
                    "years": {
                        "start_year": 1955,
                        "end_year": "NULL"
                    },
                    "organization": "Vikarby ångsåg Grycksbo pappersbruk ab"
                }
            ],
            "family": {
                "spouse": "Göta Backström",
                "marriage_year": "1934",
                "children": [
                    {
                        "name": "Karin",
                        "birth_year": "1937"
                    },
                    {
                        "name": "Lars Erik",
                        "birth_year": "1942"
                    },
                    {
                        "name": "Håkan",
                        "birth_year": "1946"
                    }
                ]
            },
            "publications": "NULL",
            "community_involvement": "NULL",
            "board_memberships": "NULL",
            "honorary_titles": "NULL",
            "hobbies": [
                "jakt",
                "fiske"
            ]
        },
        "4": {
            "full_name": "Mark Mitlin",
            "location": "Östertälje",
            "occupation": "Direktör",
            "birth_details": {
                "date": "23/10/1918",
                "place": "Sthlm"
            },
            "education": [
                {
                    "degree": "Stud:ex",
                    "year": "1938",
                    "institution": "NULL"
                },
                {
                    "degree": "Bar-Lock-Inst",
                    "year": "1940",
                    "institution": "NULL"
                }
            ],
            "career": {
                "position": "Verkst dir",
                "years": {
                    "start_year": 1946,
                    "end_year": "NULL"
                },
                "organization": "Marcus & Co ab Järna"
            },
            "family": {
                "spouse": "Annika Gratte",
                "marriage_year": "1946",
                "children": {
                    "name": "Peter",
                    "birth_year": "1947"
                }
            },
            "publications": "NULL",
            "community_involvement": "NULL",
            "board_memberships": "SMS komm",
            "honorary_titles": "NULL",
            "hobbies": [
                "sport",
                "curling"
            ]
        }
    }
}