{
    "original": "FRANCKE, FOLKE B J, överste,\nKristianstad, f i Visby 18/10/02 av kapt\nBengt F o Anna Scholander.\nStud:ex Sthlm 20, fänr I 25 23, kapt I 7\n3’8, major 11\\ 42, öv:löjtn I 7 47,1 16 48,\növerste o fobef Krist fö 54-66. - KHS\n31-33, FHS 57. - Kadettoff KS off:kurs\n34^-38, l:e adjut l:a arméfördeln stab\n38-41. - Utm: KSOlkl, CFBGM, HvGM,\nKrist l bfbGM, SLKGM, SCFftjt.\n-Hobby: filateli.\n\nGift 28 m Hjördis Zaff f 06, dtr t\nkyr-koh Nils Z o Elin Dawidsson. - Barn:\nUlf f 29, Jan f 34 (avi), Bo f 38.\n\nFRANK, BENGT A, civilekonom, Hbg,\nf i Hbg 18/8/34 av svetsare Tage F o\nDagny Larsson.\n\nStud:ex 53, DHG 59, anst ab Tretorn 59^\nÖl’, adj Hbgs städs yrkessk sed 62. - V\nordf TDV:s lokalkomm 65, kassör dess\ndistr:komm Malmöh l 65i. - Ordf tax:nd\n651 - Styr:led Hbgs FN-fören 65, medl\nSydsv geogr sällsk.\n\nGift 60 m Lempi Saveljeva f 31, dtr t\nFeodor S o h h. - Barn: Mikael f 61,\nElisabeth f 6(2.\n\nFRANCK, M O BERTIL, stiftsadjunkt,\n\nSkagen, Danm, f i Gbg 9/2/38 av\nkontr:-prost Gunnar F o Lilly Wallin.\nTeol kand Lund 61, past:adj Martin\nLuthers förs Halmstad 62-63, kyrkoadj där\n64, stiftsadj  Gbgs stift m plac Skagen\nDanm sed 65. - Medl VasaO av Amer.\nGift 62 m fil mag Margit Josefson f 38,\ndtr t kontr:prost Harry J o Märtha\nBergström. - Barn: Magnus f 63, Katarina\nf 64.\n\nFRANKLAND, FRANK G E,\nbokhandlare, Hbg, f i Kalmar 5/10/91 av\n\nFrans   Aron   Andersson   o   Mathilda\n\nSvensson.\n\nRealex 08, anst N A Dillbergs bokhdl\n\nKalmar  08,   anst  ab  Külbergs  bokhdl\n\nHbg 18, verkst dir där 37-65, verkst dir\n\nByggn ab Unionen. - Fd ordf Sv bok-\n\nhandl:fören o dess Skånekrets. - Medl\n\nRotary, Odd Fellow, FrimO.\n\nGift 16 m Maja Nil’sson, dtr t verkm A\n\nN o Mathilda N. - Barn: Raja f 36.\n\n",
    "structured": {
        "0": {
            "full_name": "Folke B J Francke",
            "location": "Kristianstad",
            "occupation": "Överste",
            "birth_details": {
                "date": "18/10/1902",
                "place": "Visby",
                "parents": "Kapt Bengt F o Anna Scholander"
            },
            "education": [
                {
                    "degree": "Stud:ex",
                    "year": "1920",
                    "institution": "Sthlm"
                },
                {
                    "degree": "KHS",
                    "year": "1931-1933",
                    "institution": "Krigshögskolan"
                },
                {
                    "degree": "FHS",
                    "year": "1957",
                    "institution": "Försvarshögskolan"
                }
            ],
            "career": [
                {
                    "position": "Utm: KSOlkl",
                    "years": {
                        "start_year": 1934,
                        "end_year": 1938
                    },
                    "organization": "Kadettoff KS"
                }
            ],
            "family": {
                "spouse": "Hjördis Zaff",
                "marriage_year": "1928",
                "children": [
                    {
                        "name": "Ulf",
                        "birth_year": "1929"
                    },
                    {
                        "name": "Jan",
                        "birth_year": "1934"
                    },
                    {
                        "name": "Bo",
                        "birth_year": "1938"
                    }
                ]
            },
            "hobbies": [
                "Filateli"
            ]
        },
        "1": {
            "full_name": "Bengt A Frank",
            "location": "Hbg",
            "occupation": "Civilekonom",
            "birth_details": {
                "date": "18/8/1934",
                "place": "Hbg",
                "parents": "Svetsare Tage F o Dagny Larsson"
            },
            "education": [
                {
                    "degree": "Stud:ex",
                    "year": "1953",
                    "institution": ""
                },
                {
                    "degree": "DHG",
                    "year": "1959",
                    "institution": ""
                }
            ],
            "career": [
                {
                    "position": "Ordf",
                    "years": {
                        "start_year": 1965,
                        "end_year": null
                    },
                    "organization": "TDV:s lokalkomm"
                }
            ],
            "family": {
                "spouse": "Lempi Saveljeva",
                "marriage_year": "1960",
                "children": [
                    {
                        "name": "Mikael",
                        "birth_year": "1961"
                    },
                    {
                        "name": "Elisabeth",
                        "birth_year": "1962"
                    }
                ]
            }
        },
        "2": {
            "full_name": "M O Bertil Franck",
            "location": "Skagen, Danm",
            "occupation": "Stiftsadjunkt",
            "birth_details": {
                "date": "9/2/1938",
                "place": "Gbg",
                "parents": "Kontr:-prost Gunnar F o Lilly Wallin"
            },
            "education": [
                {
                    "degree": "Teol kand",
                    "year": "1961",
                    "institution": "Lund"
                }
            ],
            "career": [
                {
                    "position": "Stiftsadj",
                    "years": {
                        "start_year": 1965,
                        "end_year": null
                    },
                    "organization": "Gbgs stift"
                }
            ],
            "family": {
                "spouse": "Margit Josefson",
                "marriage_year": "1962",
                "children": [
                    {
                        "name": "Magnus",
                        "birth_year": "1963"
                    },
                    {
                        "name": "Katarina",
                        "birth_year": "1964"
                    }
                ]
            }
        },
        "3": {
            "full_name": "Frank G E Frankland",
            "location": "Hbg",
            "occupation": "Bokhandlare",
            "birth_details": {
                "date": "5/10/1891",
                "place": "Kalmar",
                "parents": "Frans Aron Andersson o Mathilda Svensson"
            },
            "education": [
                {
                    "degree": "Realex",
                    "year": "1908",
                    "institution": ""
                }
            ],
            "career": [
                {
                    "position": "Verkst dir",
                    "years": {
                        "start_year": 1937,
                        "end_year": 1965
                    },
                    "organization": "Byggn ab Unionen"
                }
            ],
            "family": {
                "spouse": "Maja Nil’sson",
                "marriage_year": "1916",
                "children": [
                    {
                        "name": "Raja",
                        "birth_year": "1936"
                    }
                ]
            },
            "hobbies": [
                "Rotary",
                "Odd Fellow",
                "FrimO"
            ]
        }
    }
}