{
    "original": "FRISTEDT,   A   GUNNAR,   direktör,\n\nMalmö, f i Malmö 30/9/18 av folkskollär\nAxel F o Hulda Tufvesson.\nOff:ex 40, DHS 51; off på aktiv stat P l\n40-46, verkst dir Sintrade Prod ab\nÄlvsjö 48-50, adj HTL Mal’mö 51-56, dir\nab Al’lhems tryckerier 57L59, verkst dir\nab Motorslip 60-64, verkst dir o inneh\nEdo maskin ab sed 65. - Led div\nspec:-utredn; styr :led ab Motorslip o Bilrikt\ni Malmö ab 60-64, Edo maskin ab sed\n65. - Skr: Grunderna i\nkostnadsredovisning (516), kap Banker o\naffärsfinansiering i Handelsteknik o Bokföring\n(Tek-nograf inst handb, 58&gt;). - Hobbies:\nskogsvård, bridge.\n\nGift 2) 48 m Ebba Karlsson f 17, dtr t\nYngve K o M’argareta Danielsdotter.\n-Barn: Gunilla Chatarina f 42, Pia\nMonica f 46.\n\nFRITZ, JOHNNY I, tandläkare,\nVel-linge, f i Svedala, Malmöh l, 4/3/17 av\nköpm Nils F o Betty Andersson.\nStud:ex Malmö  37, tandl:ex Sthlm 43,\npriv:prakt Vellinge sed 46.\nGift 47 m Solveig Egardt f 18. - Barn:\nBarbro f 48, Robert f 52, Claes f 54.\n\nFRITZ,    S   A   MAURITZ,    adjunkt,\n\nKarlskrona, f i Ljungby 6/4/19 av\nmis-sionspast E M F o Anny Olsson.\nStud:ex Kristinehamn 38, fil kand Upps\n\n42,  teol kand 49, fil mag Lund 59. - E\nämneslär resp adj Gävle, Folkärna,\nÖrebro, Sthlm, Söderhamn o Hultsfred\n44-5$, adj komm flicksk Karlskrona 53, i\nkristend o hist m samh :lära hal\nKarlskrona sed 5*7. - Hobby: musik (medl av\nstråkkvartett).\n\nGift 45 m Greta Wigforss f 24, dtr t lekt\nFrits W o Clara Strömfors. - Barn:\nAnna f 54.\n\nFRITZDORF, KURT B,\nsjukhusdirektör, Hbg, f i Sthlm 16/3/13 av dir Birger\nF o Sandra Alderin.\nStud:ex 31, postelevkurs 32-35, postass\n35, l:e postass gen:poststyr 44, jur kand\nSthlm 46, asp Sthlms rådhusr 46, bitr jur\nSandström &amp; Fritzdorfs jur byrå\nKarlskrona 46, omb :man Sv:es\nkommunal-tjmförb 49, lönesekr Sv landstingsförb\n54, lönedir där 60, sjh :dir S:ta Maria sjh\nHbg sed 63.\n\nGift m Ulla Sandström. - Barn: Staffan\nf 41, Anders f 45, Johan f 49.\n\n",
    "structured": {
        "1": {
            "full_name": "FRISTEDT, A GUNNAR",
            "location": "Malmö",
            "occupation": "direktör",
            "birth_details": {
                "date": "30/09/1918",
                "place": "Malmö",
                "parents": "Axel F o Hulda Tufvesson"
            },
            "education": [
                {
                    "degree": "off:ex",
                    "year": "1940",
                    "institution": "DHS"
                }
            ],
            "career": [
                {
                    "position": "off på aktiv stat P l",
                    "years": {
                        "start_year": 1940,
                        "end_year": 1946
                    }
                },
                {
                    "position": "verkst dir Sintrade Prod ab",
                    "years": {
                        "start_year": 1948,
                        "end_year": 1950
                    }
                },
                {
                    "position": "adj HTL Mal'mö",
                    "years": {
                        "start_year": 1951,
                        "end_year": 1956
                    }
                },
                {
                    "position": "dir ab Al'hems tryckerier",
                    "years": {
                        "start_year": 1957,
                        "end_year": 1959
                    }
                },
                {
                    "position": "verkst dir ab Motorslip",
                    "years": {
                        "start_year": 1960,
                        "end_year": 1964
                    }
                },
                {
                    "position": "verkst dir o inneh Edo maskin ab",
                    "years": {
                        "start_year": 1965
                    }
                }
            ],
            "family": {
                "spouse": "Ebba Karlsson",
                "marriage_year": "1948",
                "children": [
                    {
                        "name": "Gunilla Chatarina",
                        "birth_year": "1942"
                    },
                    {
                        "name": "Pia Monica",
                        "birth_year": "1946"
                    }
                ]
            },
            "publications": [
                {
                    "title": "Grunderna i kostnadsredovisning",
                    "year": "1956",
                    "type": "book"
                },
                {
                    "title": "Banker o affärsfinansiering i Handelsteknik o Bokföring",
                    "year": "1958",
                    "type": "book"
                }
            ],
            "hobbies": [
                "skogsvård",
                "bridge"
            ]
        },
        "2": {
            "full_name": "FRITZ, JOHNNY I",
            "location": "Vellinge",
            "occupation": "tandläkare",
            "birth_details": {
                "date": "04/03/1917",
                "place": "Svedala, Malmöh l",
                "parents": "Nils F o Betty Andersson"
            },
            "education": [
                {
                    "degree": "Stud:ex",
                    "year": "1937",
                    "institution": "Malmö"
                },
                {
                    "degree": "tandl:ex",
                    "year": "1943",
                    "institution": "Sthlm"
                }
            ],
            "career": [
                {
                    "position": "priv:prakt Vellinge",
                    "years": {
                        "start_year": 1946
                    }
                }
            ],
            "family": {
                "spouse": "Solveig Egardt",
                "marriage_year": "1947",
                "children": [
                    {
                        "name": "Barbro",
                        "birth_year": "1948"
                    },
                    {
                        "name": "Robert",
                        "birth_year": "1952"
                    },
                    {
                        "name": "Claes",
                        "birth_year": "1954"
                    }
                ]
            }
        },
        "3": {
            "full_name": "FRITZ, S A MAURITZ",
            "location": "Karlskrona",
            "occupation": "adjunkt",
            "birth_details": {
                "date": "06/04/1919",
                "place": "Ljungby",
                "parents": "missionspast E M F o Anny Olsson"
            },
            "education": [
                {
                    "degree": "Stud:ex",
                    "year": "1938",
                    "institution": "Kristinehamn"
                },
                {
                    "degree": "fil kand",
                    "year": "1942",
                    "institution": "Upps"
                },
                {
                    "degree": "teol kand",
                    "year": "1949"
                },
                {
                    "degree": "fil mag",
                    "year": "1959",
                    "institution": "Lund"
                }
            ],
            "career": [
                {
                    "position": "ämneslär resp adj",
                    "years": {
                        "start_year": 1944,
                        "end_year": 1953
                    }
                },
                {
                    "position": "adj komm flicksk",
                    "years": {
                        "start_year": 1953
                    }
                }
            ],
            "family": {
                "spouse": "Greta Wigforss",
                "marriage_year": "1945",
                "children": [
                    {
                        "name": "Anna",
                        "birth_year": "1954"
                    }
                ]
            },
            "hobbies": [
                "musik (medl av stråkkvartett)"
            ]
        },
        "4": {
            "full_name": "FRITZDORF, KURT B",
            "location": "Hbg",
            "occupation": "sjukhusdirektör",
            "birth_details": {
                "date": "16/03/1913",
                "place": "Sthlm",
                "parents": "dir Birger F o Sandra Alderin"
            },
            "education": [
                {
                    "degree": "Stud:ex",
                    "year": "1931"
                },
                {
                    "degree": "jur kand",
                    "year": "1946",
                    "institution": "Sthlm"
                }
            ],
            "career": [
                {
                    "position": "l:e postass gen:poststyr",
                    "years": {
                        "start_year": 1944
                    }
                },
                {
                    "position": "omb :man Sv:es kommunal-tjmförb",
                    "years": {
                        "start_year": 1949
                    }
                },
                {
                    "position": "lönesekr Sv landstingsförb",
                    "years": {
                        "start_year": 1954
                    }
                },
                {
                    "position": "lönedir där",
                    "years": {
                        "start_year": 1960
                    }
                },
                {
                    "position": "sjh :dir S:ta Maria sjh Hbg",
                    "years": {
                        "start_year": 1963
                    }
                }
            ],
            "family": {
                "spouse": "Ulla Sandström",
                "children": [
                    {
                        "name": "Staffan",
                        "birth_year": "1941"
                    },
                    {
                        "name": "Anders",
                        "birth_year": "1945"
                    },
                    {
                        "name": "Johan",
                        "birth_year": "1949"
                    }
                ]
            }
        }
    }
}