{
    "original": "FORSSELL-GILLSÄTER,  HARRIET,\n\nskådespelerska, Malmö, f i Sthlm 27/5/34\nav rörmontör Olof Forssell o Eizy\nZan-dell.\n\nRålambshovs flicksk 52, Malmö\nmusikkonserv 60, eng ab Knäppupp 62-63,\nHimlaspelet Leksand 63, ab Sv teat 62,\n63 o 64, Malmö stadsteat 39-61 o sed 64.\n- Medv i bl a: My Fair Lady, Lilla\nHelgonet, Pyjamasleken, Chardasfurstinnan,\nNymånen, Min syster o jag, Hur man\nlyckas i affärer, Oklahoma, Hello Dolly,\nTrollkarlen från Oz.\nGift 64 m fotogr Sven Gillsäter f 21.\n\nFORSSMAN,  GÖSTA  F,  överläkare,\n\nLandskrona,   f  i   Mariestad  9/1/03   av\nmajor Fredrik F o Anna Rohdin.\nStud:ex Vänersborg 21, med kand Upps\n26, med lic Sthlm 31, underläk med avd\n\n0  röntgenavd1 S:t Görans sjh 32-40, bitr\növerläk 371-39, underläk Radiumhemmet\n40-43, röntgendiagn avd Karol sjh 43’-44,\növerläk röntgenavd Landskrona las sed\n44, styresm sed 48. - Stadsfullm sed 51,\nlandst:man sed 515, led Landskrona las\nbyggn :komm sed 48, Landskrona städs\nberedn :utskott 53-64, hälsov:nd sed 57,\nhuvudm  Rönnebergs  sparbk sed 65.\n-Ordf Nordy Skånes läk :f ören 56’. - Skr:\n\n1   röntgendiagn  o   radioterapi.   -   Utm:\nRNO.\n\nGift 30 m Ingrid Nilsén f 06, dtr t\ngodsäg Karl N o Anna Nelson. - Barn: Lars\nf 32, Anna Lena f 35’, Kristina f 47.\n\nFORSSTRÖM, GÖSTA, fil dr,\nuniversitetslektor, Lund, f i Lund 4/1/14 av\nlekt Gustaf F o Ellen Österberg.\nStud:ex Lund 32, fil mag 37i, fil lic 45,\nfil dr 49; lekt hal Ängelholm 49^512,\nfolk-sk:sem Lund 5\"2-60 (tji 54-60), univ:lekt i\nengelska språket Lunds univ sed 61 (tf\n54-60). - Skr: The Verb \"To Be\" in\nMiddle English (drsavh 4’8&lt;). - Utm:\nRNO. - Hobbies: tennis, golf.\nGift 45 m Kersti Anderzon f 21, dtr t\nl :e baning Nils A o Gertrud Ohlsson.\n-Barn: Göran f 47, Pia f 50, Ånn f 531,\nPer f 57’.\n\n",
    "structured": {
        "0": {
            "full_name": "FORSELL-GILLSÄTER, HARRIET",
            "location": "Malmö",
            "occupation": "skådespelerska",
            "birth_details": {
                "date": "27/05/1934",
                "place": "Stockholm"
            },
            "education": [
                {
                    "degree": "Rålambshovs flicksk",
                    "year": "1952",
                    "institution": "Rålambshovs flicksk, Malmö"
                },
                {
                    "degree": "Malmö musikkonserv",
                    "year": "1960",
                    "institution": "Malmö musikkonserv"
                }
            ],
            "career": [
                {
                    "position": "ab Knäppupp",
                    "years": {
                        "start_year": 1962,
                        "end_year": 1963
                    },
                    "organization": "ab Knäppupp"
                },
                {
                    "position": "Himlaspelet Leksand",
                    "years": {
                        "start_year": 1963,
                        "end_year": 1963
                    },
                    "organization": "Himlaspelet Leksand"
                },
                {
                    "position": "ab Sv teat",
                    "years": {
                        "start_year": 1962,
                        "end_year": 1963
                    },
                    "organization": "ab Sv teat"
                },
                {
                    "position": "My Fair Lady",
                    "years": {
                        "start_year": null,
                        "end_year": null
                    },
                    "organization": null
                },
                {
                    "position": "Lilla Helgonet",
                    "years": {
                        "start_year": null,
                        "end_year": null
                    },
                    "organization": null
                },
                {
                    "position": "Pyjamasleken",
                    "years": {
                        "start_year": null,
                        "end_year": null
                    },
                    "organization": null
                },
                {
                    "position": "Chardasfurstinnan",
                    "years": {
                        "start_year": null,
                        "end_year": null
                    },
                    "organization": null
                },
                {
                    "position": "Nymånen",
                    "years": {
                        "start_year": null,
                        "end_year": null
                    },
                    "organization": null
                },
                {
                    "position": "Min syster o jag",
                    "years": {
                        "start_year": null,
                        "end_year": null
                    },
                    "organization": null
                },
                {
                    "position": "Hur man lyckas i affärer",
                    "years": {
                        "start_year": null,
                        "end_year": null
                    },
                    "organization": null
                },
                {
                    "position": "Oklahoma",
                    "years": {
                        "start_year": null,
                        "end_year": null
                    },
                    "organization": null
                },
                {
                    "position": "Hello Dolly",
                    "years": {
                        "start_year": null,
                        "end_year": null
                    },
                    "organization": null
                },
                {
                    "position": "Trollkarlen från Oz",
                    "years": {
                        "start_year": null,
                        "end_year": null
                    },
                    "organization": null
                }
            ],
            "family": {
                "spouse": "Sven Gillsäter",
                "marriage_year": "1964",
                "children": []
            }
        },
        "1": {
            "full_name": "FORSSMAN, GÖSTA F",
            "location": "Landskrona",
            "occupation": "överläkare",
            "birth_details": {
                "date": "09/01/1903",
                "place": "Mariestad"
            },
            "education": [],
            "career": [
                {
                    "position": "överläk röntgenavd Landskrona las",
                    "years": {
                        "start_year": 1944,
                        "end_year": null
                    },
                    "organization": "Landskrona las"
                }
            ],
            "family": {
                "spouse": "Ingrid Nilsén",
                "marriage_year": "1930",
                "children": [
                    {
                        "name": "Lars",
                        "birth_year": "1932"
                    },
                    {
                        "name": "Anna Lena",
                        "birth_year": "1935"
                    },
                    {
                        "name": "Kristina",
                        "birth_year": "1947"
                    }
                ]
            }
        },
        "2": {
            "full_name": "FORSSTRÖM, GÖSTA",
            "location": "Lund",
            "occupation": "fil dr, universitetslektor",
            "birth_details": {
                "date": "04/01/1914",
                "place": "Lund"
            },
            "education": [
                {
                    "degree": "Stud:ex Lund",
                    "year": "1932",
                    "institution": "Lund"
                },
                {
                    "degree": "fil mag",
                    "year": "1937",
                    "institution": null
                },
                {
                    "degree": "fil lic",
                    "year": "1945",
                    "institution": null
                },
                {
                    "degree": "fil dr",
                    "year": "1949",
                    "institution": "Lunds univ"
                }
            ],
            "career": [
                {
                    "position": "univ:lekt i engelska språket Lunds univ",
                    "years": {
                        "start_year": 1961,
                        "end_year": null
                    },
                    "organization": "Lunds univ"
                }
            ],
            "family": {
                "spouse": "Kersti Anderzon",
                "marriage_year": "1945",
                "children": [
                    {
                        "name": "Göran",
                        "birth_year": "1947"
                    },
                    {
                        "name": "Pia",
                        "birth_year": "1950"
                    },
                    {
                        "name": "Ånn",
                        "birth_year": "1953"
                    },
                    {
                        "name": "Per",
                        "birth_year": "1957"
                    }
                ]
            }
        }
    }
}