{
    "original": "FAGERSTRÖM, GUSTAF J A,\nredaktör, Halmstad, f i Karlskrona 17/3/04 av\nhamnkapt Carl F o Anna Svensson.\nStud:ex Halmstad 22, reporter, nattred,\nutr :red o red :sekr tidn Halland 22-59,\nch GHT:s Halmstadsred sed 59. - Sekr\n\nHall journ:fören 30-40. - Sign: Bp,\nGes-tus, Fager. - Hobby: sportfiske.\nGift 28 m Eyvor Carlsson, dtr tf distr :ch\nSamuel C o h h, f Lindman. - Barn:\nGunilla f 34, Rutger f 38, Torkel f 43.\n\nFAGERSTRÖM,   OTTO   L,   direktör,\n\nHbg, f i Lund 1/3/20 av skom:mäst\nMagnus Svensson-F o Hulda Pettersson.\nAnst ab Elektroengros Hbg 36’, lagerbitr\n38, tel:försälj 47!, resande 54, försäljn:ch\n59, verkst dir där sed 61. - Hobbies:\nfiske, filateli.\n\nGift 41 m Rigmor Pettersson f 19.\n-Barn: Britt-Marie f 41, Bo-Inge f 45’.\n\nFAGRELL, FOLKE J, förste\nbesikt-ningsveterinär, Hässleholm, f i Gbg 8/5/\n21 av godsäg Erik F o Dagmar Lignell.\nStud:ex Lund 41, vet:ex 56; ass SVA 5’2,\ntf stads- o imp:besiktin:vet Sthlm S’S’, tf\ndistr:vet Töreboda 5’S, l:e besiktn :vet\nHässleholm sed 5&gt;9, tf länsvet Krist l 64,\n65-66. - Food Hygiene Adviser FN Gaza\n64-65. - Ordf hälsov:nd 64-68. - Medl\nRotary, FrimO. - Hobbies: segling, jakt.\nGift 48 m Barbro Eklund f 251. - Barn:\nStefan f 48, Tim f 52, Dan f 56,\nJohanna f 66.\n\nFAHL,     GUSTAF-GILLIS,     kamrer,\n\nMalmö, f i Sthlm 3/1/14 av kommin\nGustaf F o Anna v Heideman.\nFilip Holmqvists hdlI 351, res:off:ex 38,\ntjm Försäkr ab Skandia Gbg 3’8, kamr\nab Nils P Lundh Malmö sed 41. -\nStyr:-led Västerbottens grusförädl ab 63, ab\nBåstad makadamfabr 65, styr:suppl ab\nNils P Lundh 62. - Rev Res:off :fören i\nSkåne 53-64. - Kapt I 17 res 51. - Medl\nLions club, PB.\n\nGift 43 m hush:lär Margit Nilson f 15,\ndtr t komm:ndsordf Pontus N o Ellen\nZachrisson. - Barn: Henrik f 44, Gudrun\nf 46.\n\n",
    "structured": {
        "1": {
            "full_name": "GUSTAF J A FAGERSTRÖM",
            "location": "Halmstad",
            "occupation": "redaktör",
            "birth_details": {
                "date": "17/03/1904",
                "place": "Karlskrona"
            },
            "education": [
                {
                    "degree": "Stud:ex",
                    "year": "1922",
                    "institution": "Halmstad"
                }
            ],
            "career": [
                {
                    "position": "reporter",
                    "years": {
                        "start_year": 1922,
                        "end_year": 1959
                    },
                    "organization": "tidn Halland"
                },
                {
                    "position": "nattred",
                    "years": {
                        "start_year": 1922,
                        "end_year": 1959
                    },
                    "organization": "tidn Halland"
                },
                {
                    "position": "red :sekr",
                    "years": {
                        "start_year": 1922,
                        "end_year": 1959
                    },
                    "organization": "GHT:s Halmstadsred"
                }
            ],
            "family": {
                "spouse": "Eyvor Carlsson",
                "marriage_year": "1928",
                "children": [
                    {
                        "name": "Gunilla",
                        "birth_year": "1934"
                    },
                    {
                        "name": "Rutger",
                        "birth_year": "1938"
                    },
                    {
                        "name": "Torkel",
                        "birth_year": "1943"
                    }
                ]
            }
        },
        "2": {
            "full_name": "OTTO L. FAGERSTRÖM",
            "location": "Hbg",
            "occupation": "direktör",
            "birth_details": {
                "date": "01/03/1920",
                "place": "Lund"
            },
            "career": [
                {
                    "position": "lagerbitr",
                    "years": {
                        "start_year": 1938,
                        "end_year": null
                    },
                    "organization": "Elektroengros Hbg"
                },
                {
                    "position": "tel:försälj",
                    "years": {
                        "start_year": 1947,
                        "end_year": null
                    },
                    "organization": null
                },
                {
                    "position": "resande",
                    "years": {
                        "start_year": 1954,
                        "end_year": null
                    },
                    "organization": null
                },
                {
                    "position": "försäljn:ch",
                    "years": {
                        "start_year": 1959,
                        "end_year": null
                    },
                    "organization": null
                },
                {
                    "position": "verkst dir",
                    "years": {
                        "start_year": 1961,
                        "end_year": null
                    },
                    "organization": null
                }
            ],
            "family": {
                "spouse": "Rigmor Pettersson",
                "marriage_year": "1941",
                "children": [
                    {
                        "name": "Britt-Marie",
                        "birth_year": "1941"
                    },
                    {
                        "name": "Bo-Inge",
                        "birth_year": "1945"
                    }
                ]
            }
        },
        "3": {
            "full_name": "FOLKE J. FAGRELL",
            "location": "Hässleholm",
            "occupation": "förste besikt-ningsveterinär",
            "birth_details": {
                "date": "08/05/1921",
                "place": "Göteborg"
            },
            "education": [
                {
                    "degree": "Stud:ex",
                    "year": "1941",
                    "institution": "Lund"
                },
                {
                    "degree": "vet:ex",
                    "year": "1956",
                    "institution": null
                }
            ],
            "career": [
                {
                    "position": "tf stads- o imp:besiktin:vet",
                    "years": {
                        "start_year": 1958,
                        "end_year": null
                    },
                    "organization": "Töreboda"
                },
                {
                    "position": "l:e besiktn :vet",
                    "years": {
                        "start_year": 1959,
                        "end_year": null
                    },
                    "organization": "Hässleholm"
                },
                {
                    "position": "tf länsvet",
                    "years": {
                        "start_year": 1964,
                        "end_year": 1965
                    },
                    "organization": "Krist"
                }
            ],
            "family": {
                "spouse": "Barbro Eklund",
                "marriage_year": "1948",
                "children": [
                    {
                        "name": "Stefan",
                        "birth_year": "1948"
                    },
                    {
                        "name": "Tim",
                        "birth_year": "1952"
                    },
                    {
                        "name": "Dan",
                        "birth_year": "1956"
                    },
                    {
                        "name": "Johanna",
                        "birth_year": "1966"
                    }
                ]
            }
        },
        "4": {
            "full_name": "GUSTAF-GILLIS FAHL",
            "location": "Malmö",
            "occupation": "kamrer",
            "birth_details": {
                "date": "03/01/1914",
                "place": "Stockholm"
            },
            "education": [
                {
                    "degree": "Filip Holmqvists hdlI 35",
                    "year": "1935",
                    "institution": null
                },
                {
                    "degree": "res:off:ex",
                    "year": "1938",
                    "institution": null
                }
            ],
            "career": [
                {
                    "position": "tjm",
                    "years": {
                        "start_year": 1938,
                        "end_year": null
                    },
                    "organization": "Försäkr ab Skandia Gbg"
                },
                {
                    "position": "kamr",
                    "years": {
                        "start_year": 1941,
                        "end_year": null
                    },
                    "organization": "ab Nils P Lundh Malmö"
                }
            ],
            "family": {
                "spouse": "Margit Nilson",
                "marriage_year": "1943",
                "children": [
                    {
                        "name": "Henrik",
                        "birth_year": "1944"
                    },
                    {
                        "name": "Gudrun",
                        "birth_year": "1946"
                    }
                ]
            }
        }
    }
}