{
    "original": "FRIDH, ÅKE, musikdirektör,\nRonneby, f i Karlskrona 20/9/28 av maskinist\nFranz F o Nanny Svensson.\nKant:- o org:ex 52, musiklär:ex MA 58,\nmusiklär S:t Petri hal 58, hal Ronneby\nsed 59. - Dirig Ronneby musiksällsk sed\n59, ledare Ronneby kommunala musiksk\nsed 60. - Hobbies: konsthistoria, fiske.\nGift 51 m Ingrid Håkansson f 30, dtr t\nfastigh:äg Karl H o Elisabeth H.\n\nFRIDLIZIUS, J GUNNAR F, fil dr, e\n\npreceptor, Lund, f i Uvered, Skarab l,\n29/6/22 av folkskollär Joel F o Greta\nWickelberg.\n\nStud:ex Skara 42, fil mag Lund 49, fil\nlic 52, disput 57, doc i ekonomisk\nhistoria 57 o fil dr Lunds univ 58; l:e aman\nekon:hist inst periodv 52-57, doc:tj där\n57-64, e precept i ekonomisk historia sed\n64. - Skr: Swedish corn export in the\nfree trade era (drsavh 57) m fi vet arb i\nekon hist.\n\nGift 51 m Irene Scalia f 24, dtr t köpm\nAntonio S o Alfhild Carlsson. - Barn:\nMartin f 54, Sandro f 56, Tonio f 58.\n\nFRIDNER,   ELIS   J,   docent,   lektor,\n\nMalmö, f i Blidsberg, Älvsb l, 22/12/99\nav kommin Alfred F o Anna von\nStrokirch.\n\nStud:ex Lund 18, fil kand 23, fil måg 31,\nfil lic 53, fil dr 61, doc i engelska\nspråket Lunds univ sed 61; lär Ulricehamn,\nBoden, Kristianstad, Karlskrona, Lund,\n\nLaholm o Tomelilla 24-42, adj Boden 42,\nSlottsstadens lärov Malmö 53, lekt i eng\no ty S:t Petri lärov 58-66. - Tf univ:lekt\nLund sed 63 (e 5&gt;8, tf prof 61-62). - Skr:\nAn English Fourteenth Century\nApoca-lypse Version with a Prose Commentary\n(drsavh 61). - Utm: RNO.\nGift 35 m adj Lisa Paulson f 09, dtr t\nköpm Oscar P o Frida Svensson.\n\n",
    "structured": {
        "0": {
            "full_name": "FRIDH, ÅKE",
            "location": "Ronneby",
            "occupation": "musikdirektör",
            "birth_details": {
                "date": "20/09/1928",
                "place": "Karlskrona",
                "parents": "maskinist Franz F o Nanny Svensson"
            },
            "education": [
                {
                    "degree": "Kantarexamen",
                    "year": "1952",
                    "institution": "Musiklärarexamen MA 1958"
                }
            ],
            "career": [
                {
                    "position": "Musiklärare",
                    "years": {
                        "start_year": 1958,
                        "end_year": 1958
                    },
                    "organization": "S:t Petri hal"
                },
                {
                    "position": "Dirigent",
                    "years": {
                        "start_year": 1959,
                        "end_year": 1959
                    },
                    "organization": "Ronneby musiksällsk"
                }
            ],
            "family": {
                "spouse": "Ingrid Håkansson",
                "marriage_year": "1951",
                "children": [
                    {
                        "name": "NULL",
                        "birth_year": "NULL"
                    }
                ]
            },
            "hobbies": [
                "konsthistoria",
                "fiske"
            ]
        },
        "1": {
            "full_name": "FRIDLIZIUS, J GUNNAR F",
            "location": "Lund",
            "occupation": "fil dr, e preceptor",
            "birth_details": {
                "date": "29/06/1922",
                "place": "Uvered, Skarab l",
                "parents": "folkskollär Joel F o Greta Wickelberg"
            },
            "education": [
                {
                    "degree": "Stud:ex",
                    "year": "1942",
                    "institution": "Skara"
                },
                {
                    "degree": "Fil mag",
                    "year": "1949",
                    "institution": "Lund"
                },
                {
                    "degree": "Fil lic",
                    "year": "1952",
                    "institution": "Lunds univ"
                }
            ],
            "career": [
                {
                    "position": "L:e aman ekon:hist inst",
                    "years": {
                        "start_year": 1952,
                        "end_year": 1957
                    },
                    "organization": "Lunds univ"
                },
                {
                    "position": "Doc:tj",
                    "years": {
                        "start_year": 1957,
                        "end_year": 1964
                    },
                    "organization": "Lunds univ"
                },
                {
                    "position": "E precept i ekonomisk historia",
                    "years": {
                        "start_year": 1964,
                        "end_year": "NULL"
                    },
                    "organization": "Lunds univ"
                }
            ],
            "family": {
                "spouse": "Irene Scalia",
                "marriage_year": "1951",
                "children": [
                    {
                        "name": "Martin",
                        "birth_year": "1954"
                    },
                    {
                        "name": "Sandro",
                        "birth_year": "1956"
                    },
                    {
                        "name": "Tonio",
                        "birth_year": "1958"
                    }
                ]
            }
        },
        "2": {
            "full_name": "FRIDNER, ELIS J",
            "location": "Malmö",
            "occupation": "docent, lektor",
            "birth_details": {
                "date": "22/12/1899",
                "place": "Blidsberg, Älvsb l",
                "parents": "kommin Alfred F o Anna von Strokirch"
            },
            "education": [
                {
                    "degree": "Stud:ex",
                    "year": "1918",
                    "institution": "Lund"
                },
                {
                    "degree": "Fil kand",
                    "year": "1923",
                    "institution": "Lund"
                },
                {
                    "degree": "Fil måg",
                    "year": "1931",
                    "institution": "NULL"
                },
                {
                    "degree": "Fil lic",
                    "year": "1953",
                    "institution": "NULL"
                },
                {
                    "degree": "Fil dr",
                    "year": "1961",
                    "institution": "NULL"
                }
            ],
            "career": [
                {
                    "position": "Doc i engelska språket",
                    "years": {
                        "start_year": 1961,
                        "end_year": "NULL"
                    },
                    "organization": "Lunds univ"
                }
            ],
            "family": {
                "spouse": "Lisa Paulson",
                "marriage_year": "1935",
                "children": [
                    {
                        "name": "NULL",
                        "birth_year": "NULL"
                    }
                ]
            }
        }
    }
}