{
    "original": "FRIMAN, KARL-ERIK R, tandläkare,\n\nKristianstad, f i Åmål 15/1/20 av smed\nGottfrid F o Gerda Andréasson.\nStud:ex Karlstad 39, tandl:ex Sthlm 47,\nass:tandl Karlstad 47, tandl folktandv\nÅmål, Borås o Degeberga 47-50,\nass:tandl Kristianstad 50-57, priv :prakt\nKristianstad sed 57.\n\n17 ska\n\nGift 49 m folkskollär Margit Jansson\nf 25. - Barn: Bo f 49, Tomas f 50,\nSten-Åke f 57.\n\nFRIMAN, PER, ekonomichef, Malmö,\nf i Karlskoga 6/10/22 av dir Martin F o\nCarin Carlsson.\n\nStud:ex Örebro 42, DHG 48, jur kand\nSthlm 60; kamr Mell Sv:es linodl:fören\nKristinehamn 48-52, kamr o stf ekon :dir\nSv:es slakteriförb 52-65, ekon:ch ab\nMa-zetti Malmö sed 66. - Hobbies: tennis,\nbordtennis, motorsport.\nGift 49 m Karin Sjöholm f 24, dtr t\nlokför Thure S o Elsa Olsson. - Barn:\nElisabet f 64.\n\nFRIMODIG, LARS I, civilekonom,\ndirektör, Malmö, f i Gbg 28/9/31 av\ntele-graftjm Albert F o Margit Bryntesson.\nRes:off:ex 54’, DHG 58, anst) geogr inst\nHHG 5», repr IBM sv ab 58,, verkst dir\nSkånska dagbl ab sed 66. - Gen:sekr SFS\n58, ordf Malmö J:ör Chamber of\nCom-merce 65 (v ordf 64’). - Skr: Turism i\nBohuslän - En ny industri (59). - Löjtn\nLv res. - Hobbies: sportflyg, segling.\nGift 62 m Margareta Dymlind f 34, dtr\nt fabr John Johansson o Ester Berglund.\n- Barn: Ann-Charlotte f 62, Elisabet\nf 64.\n\nFRINNMAN, NILS-ERIC V,\nstadsbibliotekarie, Sölvesborg, f i Sthlm 26/5/29\nav sparv :man Ernst Nilsson o Hanna\nJohansson.\n\nStud:ex 48, fil kand Sthlm 52, DBS 54,\nstadsbibl :ie Sölvesborg sed 55. - Ordf\nSkrivark! Sölvesborg 64. - Utg:\nEnköpingsbibliografi I (tills m B Järbe, 56),\nSölvesborgs stadsbibliotek 1908-1958 (580,\nlektor Bibliotekstjänst sed 56.\n\n",
    "structured": {
        "0": {
            "full_name": "FRIMAN, KARL-ERIK R",
            "location": "tandläkare, Kristianstad",
            "occupation": "tandläkare",
            "birth_details": {
                "date": "15/01/1920",
                "place": "Åmål"
            },
            "education": [
                {
                    "degree": "Stud:ex",
                    "year": "1939",
                    "institution": "Karlstad"
                },
                {
                    "degree": "tandl:ex",
                    "year": "1947",
                    "institution": "Sthlm"
                }
            ],
            "career": [
                {
                    "position": "ass:tandl",
                    "years": {
                        "start_year": 1947,
                        "end_year": 1950
                    },
                    "organization": "Karlstad"
                },
                {
                    "position": "tandl folktandv",
                    "years": {
                        "start_year": 1947,
                        "end_year": 1950
                    },
                    "organization": "Åmål, Borås o Degeberga"
                },
                {
                    "position": "ass:tandl",
                    "years": {
                        "start_year": 1950,
                        "end_year": 1957
                    },
                    "organization": "Kristianstad"
                },
                {
                    "position": "priv :prakt",
                    "years": {
                        "start_year": 1957
                    }
                }
            ],
            "family": {
                "spouse": "folkskollär Margit Jansson",
                "marriage_year": "1949",
                "children": [
                    {
                        "name": "Bo",
                        "birth_year": "1949"
                    },
                    {
                        "name": "Tomas",
                        "birth_year": "1950"
                    },
                    {
                        "name": "Sten-Åke",
                        "birth_year": "1957"
                    }
                ]
            }
        },
        "1": {
            "full_name": "FRIMAN, PER",
            "location": "ekonomichef, Malmö",
            "occupation": "ekonomichef",
            "birth_details": {
                "date": "6/10/1922",
                "place": "Karlskoga"
            },
            "education": [
                {
                    "degree": "Stud:ex",
                    "year": "1942",
                    "institution": "Örebro"
                },
                {
                    "degree": "DHG",
                    "year": "1948"
                },
                {
                    "degree": "jur kand",
                    "year": "1960",
                    "institution": "Sthlm"
                }
            ],
            "career": [
                {
                    "position": "kamr",
                    "years": {
                        "start_year": 1948,
                        "end_year": 1952
                    },
                    "organization": "Mell Sv:es linodl:fören Kristinehamn"
                },
                {
                    "position": "kamr o stf ekon :dir",
                    "years": {
                        "start_year": 1952,
                        "end_year": 1965
                    },
                    "organization": "Sv:es slakteriförb"
                },
                {
                    "position": "ekon:ch",
                    "years": {
                        "start_year": 1966
                    },
                    "organization": "ab Mazetti Malmö"
                }
            ],
            "family": {
                "spouse": "Karin Sjöholm",
                "marriage_year": "1949",
                "children": [
                    {
                        "name": "Elisabet",
                        "birth_year": "1964"
                    }
                ]
            },
            "hobbies": [
                "tennis",
                "bordtennis",
                "motorsport"
            ]
        },
        "2": {
            "full_name": "FRIMODIG, LARS I",
            "location": "direktör, Malmö",
            "occupation": "direktör",
            "birth_details": {
                "date": "28/09/1931",
                "place": "Gbg"
            },
            "education": [
                {
                    "degree": "Res:off:ex",
                    "year": "1954"
                },
                {
                    "degree": "DHG",
                    "year": "1958"
                }
            ],
            "career": [
                {
                    "position": "anst) geogr inst",
                    "years": {
                        "start_year": 1954
                    },
                    "organization": "HHG 5"
                },
                {
                    "position": "repr",
                    "years": {
                        "start_year": 1958
                    },
                    "organization": "IBM sv ab"
                },
                {
                    "position": "verkst dir",
                    "years": {
                        "start_year": 1966
                    },
                    "organization": "Skånska dagbl ab"
                }
            ],
            "family": {
                "spouse": "Margareta Dymlind",
                "marriage_year": "1962",
                "children": [
                    {
                        "name": "Ann-Charlotte",
                        "birth_year": "1962"
                    },
                    {
                        "name": "Elisabet",
                        "birth_year": "1964"
                    }
                ]
            },
            "hobbies": [
                "sportflyg",
                "segling"
            ]
        },
        "3": {
            "full_name": "FRINNMAN, NILS-ERIC V",
            "location": "stadsbibliotekarie, Sölvesborg",
            "occupation": "stadsbibliotekarie",
            "birth_details": {
                "date": "26/05/1929",
                "place": "Sthlm"
            },
            "education": [
                {
                    "degree": "Stud:ex",
                    "year": "1948"
                },
                {
                    "degree": "fil kand",
                    "year": "1952",
                    "institution": "Sthlm"
                },
                {
                    "degree": "DBS",
                    "year": "1954"
                }
            ],
            "career": [
                {
                    "position": "stadsbibl :ie",
                    "years": {
                        "start_year": 1955
                    },
                    "organization": "Sölvesborg"
                }
            ],
            "family": {
                "spouse": "Hanna Johansson",
                "marriage_year": "1954"
            },
            "publications": [
                {
                    "title": "Enköpingsbibliografi I",
                    "year": "1956",
                    "type": "tills m B Järbe"
                },
                {
                    "title": "Sölvesborgs stadsbibliotek 1908-1958",
                    "year": "1960",
                    "type": "lektor Bibliotekstjänst"
                }
            ]
        }
    }
}