{
    "original": "FRANZ, LENNART F B,\ndriftingenjör, Malmö, f i Malmö 2/10/35 av Axel\nJönsson o Linnea F.\n\nIng:ex HTL Malmö 58’, drifting Syrgas\nab Alfax sed 58. - Hobbies: fiske, schack.\nGift 38 m B’ritt Andersson f 35, dtr t\nfastigh :äg Josef A o Viola Olsson.\n-Barn: Rikard f 64.\n\nFRANZÉN, ARNE V, provinsialläkare,\n\nGärsnäs, f i N Ljunga, Jönkpgs l, 27/3/\n\n11 av kantor Axel F o Mikal\nGustavsson.\n\nStud:ex Växjö 30, med kand 41 o med\nlic 47 Upps, öl läk:förordn 47-51, e\nprov:läk Gärsnäs distr 51-56, prov:läk\ndär sed 56. - Bat:läk v flk 51, i flk res\nsed 55.\n\nGift 38 m Margareta Alstermark f 17,\ndtr t lekt Bror A o Margaretha\nLeijonancker. - Barn: Ulf f 38, Birgitta f 40,\nLennart f 42, Kerstin f 50.\n\nFRANZÉN, BENGT G, direktör,\nÅstorp, f i Nässjö 4/5/21 av stat:mäst\nAnton F o Berta Bengtsson.\nStud:ex Eksjö 42, stud CTH 44^46; eg\nrörelse 46-59, verkst dir o deläg\nTransportverken ab o Industritransmissioner\nab Åstorp sed’ 59. - Sv deleg inom Féder\nEurop de la Manutention o Internat\nStandard O’rg. - Medl Rotary. - Hobbies:\nfilateli, konst.\n\nGift 49 m Birgit Malm» f 19, dtr t lantbr\nGustaf M o Emma Nordh. - Barn: Karin\nf 61.\n\nFRANZÉN,   BENGT   M,   överläkare,\n\nHbg, f i Kristianstad 22/4/07 av\nlärov:-adj Elis F o Sofie Segerberg.\nStud:ex Kristianstod 25, med kand Lund\n31, med lic Sthlm 36, tjg som sjh :läk o\ntjänsteläk 36’-4i5, tjg inom mentalsjv sed\n46, överläk i hjälpverksamh Gullberna\nsjh 58’-62, S:ta Maria sjh sed 62. -\nKonsult psyk v Hall l landst sed 62, priv\nprakt sed 63. - Marinläk av l :a gr i mlk\nres sed 49. - Stip f stud i London 56*.\n-Skr i socialpsykiatri o socioterapi.\nGift 47 m Ingrid von Malmborg f 22,\ndtr t kapt Nife v M p Torborg\nGöös-Vidinghoff. - Barn: Michael f 48, Johan\nf 50, Herbert f 54.\n\nFRANZÉN, N ERIK, civilingenjör\nSVR, kapten VVK, Hittarp, f i V\nSked-vi, Västmanl l, 4/2/21 av folkskollär\nNils F o Sigrid Johansson.\nStud:ex Nykpg 42, KTH 48, konsult ing\nKjessler o Mannerstråle ab Hbgskont\nsed 48. - Hobby: filateli.\nGift 2) 518 m Otöthy Olsson f 25, dtr t\nguldsmed Otto O o Ellen Svensson.\n-Barn: i l:a akt Björn f 47., Margareta\nf 49, Thomas f 51, i 2:a akt Claes f 59.\n\nFRANZÉN, S GEORG, komminister,\n\nBromölla, f i Slätthög, Kronob l, 31/8/15\nav hemm:äg Johan F o Tilda Karlsson.\nStud:ex Växjö 36, teol kand Lund 43,\nprästv 43, div prästtj 43l-57, kommm\nBerga 57, Ivetofta-Gualöv sed 62. - Kårch\nOskarshamns scoutkår 46-56, led Sv\nscoutförb överstyr o distr :ch Kalm l 52-\n\n61, led förb:styr 57-60, ordf Lunds stifts\nkyrkl ungd:förb, ordf stiftets scoututsk.\n- Medl FrimO.\n\nGift 45 m Margit Jakobsson f 22, dtr t\nprost Gustaf J o Gurli Spångberg.\n-Barn: Gunilla f 47, Annika f 50.\n\n",
    "structured": {
        "1": {
            "full_name": "FRANZ, LENNART F B",
            "location": "Malmö",
            "occupation": "Driftingenjör",
            "birth_details": {
                "date": "02/10/1935",
                "place": "Malmö",
                "parents": "Axel Jönsson och Linnea F"
            },
            "education": [
                {
                    "degree": "Ing:ex HTL",
                    "year": "1958",
                    "institution": "Malmö"
                }
            ],
            "career": [
                {
                    "position": "Drifting Syrgas",
                    "years": {
                        "start_year": 1958
                    },
                    "organization": "Alfax"
                }
            ],
            "family": {
                "spouse": "B’ritt Andersson",
                "marriage_year": "1938",
                "children": [
                    {
                        "name": "Rikard",
                        "birth_year": "1964"
                    }
                ]
            },
            "hobbies": [
                "fiske",
                "schack"
            ]
        },
        "2": {
            "full_name": "FRANZÉN, ARNE V",
            "location": "Gärsnäs",
            "occupation": "Provinsialläkare",
            "birth_details": {
                "date": "27/03/1911",
                "place": "N Ljunga, Jönkpgs l",
                "parents": "Axel F och Mikal Gustavsson"
            },
            "education": [
                {
                    "degree": "Stud:ex Växjö",
                    "year": "1930",
                    "institution": "Växjö"
                },
                {
                    "degree": "Med kand",
                    "year": "1941",
                    "institution": "Upps"
                },
                {
                    "degree": "Med lic",
                    "year": "1947",
                    "institution": "Upps"
                }
            ],
            "career": [
                {
                    "position": "Prov:läk",
                    "years": {
                        "start_year": 1951,
                        "end_year": 1956
                    },
                    "organization": "Gärsnäs"
                },
                {
                    "position": "Bat:läk",
                    "years": {
                        "start_year": 1951
                    }
                }
            ],
            "family": {
                "spouse": "Margareta Alstermark",
                "marriage_year": "1938",
                "children": [
                    {
                        "name": "Ulf",
                        "birth_year": "1938"
                    },
                    {
                        "name": "Birgitta",
                        "birth_year": "1940"
                    },
                    {
                        "name": "Lennart",
                        "birth_year": "1942"
                    },
                    {
                        "name": "Kerstin",
                        "birth_year": "1950"
                    }
                ]
            }
        },
        "3": {
            "full_name": "FRANZÉN, BENGT G",
            "location": "Åstorp",
            "occupation": "Direktör",
            "birth_details": {
                "date": "04/05/1921",
                "place": "Nässjö",
                "parents": "Anton F och Berta Bengtsson"
            },
            "education": [
                {
                    "degree": "Stud:ex Eksjö",
                    "year": "1942",
                    "institution": "Eksjö"
                }
            ],
            "career": [
                {
                    "position": "Verkst dir",
                    "years": {
                        "start_year": 1959
                    },
                    "organization": "Transportverken ab o Industritransmissioner ab Åstorp"
                }
            ],
            "family": {
                "spouse": "Birgit Malm»",
                "marriage_year": "1949",
                "children": [
                    {
                        "name": "Karin",
                        "birth_year": "1961"
                    }
                ]
            },
            "hobbies": [
                "filateli",
                "konst"
            ]
        },
        "4": {
            "full_name": "FRANZÉN, BENGT M",
            "location": "Hbg",
            "occupation": "Överläkare",
            "birth_details": {
                "date": "22/04/1907",
                "place": "Kristianstad",
                "parents": "Elis F o Sofie Segerberg"
            },
            "education": [
                {
                    "degree": "Stud:ex Kristianstod",
                    "year": "1925",
                    "institution": "Kristianstad"
                },
                {
                    "degree": "Med kand",
                    "year": "1931",
                    "institution": "Lund"
                },
                {
                    "degree": "Med lic",
                    "year": "1936",
                    "institution": "Sthlm"
                }
            ],
            "career": [
                {
                    "position": "Överläk i hjälpverksam",
                    "years": {
                        "start_year": 1958,
                        "end_year": 1962
                    },
                    "organization": "Gullberna sjh"
                },
                {
                    "position": "Överläk i hjälpverksam",
                    "years": {
                        "start_year": 1962
                    },
                    "organization": "S:ta Maria sjh"
                },
                {
                    "position": "Konsult psyk",
                    "years": {
                        "start_year": 1962
                    },
                    "organization": "Hall l landst"
                },
                {
                    "position": "Priv prakt",
                    "years": {
                        "start_year": 1963
                    }
                },
                {
                    "position": "Marinläk av l: a gr i mlk res",
                    "years": {
                        "start_year": 1949
                    }
                }
            ],
            "family": {
                "spouse": "Ingrid von Malmborg",
                "marriage_year": "1947",
                "children": [
                    {
                        "name": "Michael",
                        "birth_year": "1948"
                    },
                    {
                        "name": "Johan",
                        "birth_year": "1950"
                    },
                    {
                        "name": "Herbert",
                        "birth_year": "1954"
                    }
                ]
            }
        },
        "5": {
            "full_name": "FRANZÉN, N ERIK",
            "location": "Hittarp",
            "occupation": "Civilingenjör SVR, Kapten VVK",
            "birth_details": {
                "date": "04/02/1921",
                "place": "V Sked-vi, Västmanl l",
                "parents": "Nils F och Sigrid Johansson"
            },
            "education": [
                {
                    "degree": "Stud:ex Nykpg",
                    "year": "1942",
                    "institution": "Nykpg"
                },
                {
                    "degree": "KTH",
                    "year": "1948",
                    "institution": "KTH"
                }
            ],
            "career": [
                {
                    "position": "Konsult ing",
                    "years": {
                        "start_year": 1948
                    },
                    "organization": "Kjessler o Mannerstråle ab Hbgskont"
                }
            ],
            "family": {
                "spouse": "Otöthy Olsson",
                "marriage_year": "1958",
                "children": [
                    {
                        "name": "Björn",
                        "birth_year": "1947"
                    },
                    {
                        "name": "Margareta",
                        "birth_year": "1949"
                    },
                    {
                        "name": "Thomas",
                        "birth_year": "1951"
                    },
                    {
                        "name": "Claes",
                        "birth_year": "1959"
                    }
                ]
            },
            "hobbies": [
                "filateli"
            ]
        },
        "6": {
            "full_name": "FRANZÉN, S GEORG",
            "location": "Bromölla",
            "occupation": "Komminister",
            "birth_details": {
                "date": "31/08/1915",
                "place": "Slätthög, Kronob l",
                "parents": "Johan F o Tilda Karlsson"
            },
            "education": [
                {
                    "degree": "Stud:ex Växjö",
                    "year": "1936",
                    "institution": "Växjö"
                },
                {
                    "degree": "Teol kand",
                    "year": "1943",
                    "institution": "Lund"
                }
            ],
            "career": [
                {
                    "position": "Kommm",
                    "years": {
                        "start_year": 1962
                    },
                    "organization": "Ivetofta-Gualöv"
                }
            ],
            "family": {
                "spouse": "Margit Jakobsson",
                "marriage_year": "1945",
                "children": [
                    {
                        "name": "Gunilla",
                        "birth_year": "1947"
                    },
                    {
                        "name": "Annika",
                        "birth_year": "1950"
                    }
                ]
            },
            "community_involvement": [
                {
                    "role": "Kårch",
                    "organization": "Oskarshamns scoutkår",
                    "years": "1946-1956"
                },
                {
                    "role": "Led förb:styr",
                    "organization": "Sv scoutförb",
                    "years": "1957-1960"
                },
                {
                    "role": "Ordf stiftets scoututsk"
                }
            ],
            "hobbies": [
                "FrimO"
            ]
        }
    }
}