{
    "original": "NYLANDER, J C YNGVE,\npolisintendent, Örebro, f i Charlottenberg,\nVärml l, 22/10/27 av tullförv Curt N o\nEva Creutz.\n\nStud:ex Umeå 47, distr:åkl:ex Sthlm 51,\npolisch:k 52, jur kand Sthlm 54, tingstjg\nKarlskoga doms 54-56, vik åkl 57,\npolisnot o polissekr statspolisintend 57-62,\npolisintend Örebro sed 62. - Sekr\nÖrebro stads trafikråd. - Medl Lions Club.\n\n-  Red:sekr Nord krim:tekn tidskr 60-62.\n\n-  Hobbies: sport, filateli.\n\nGift 52 m Gullan Wiking f 29. - Barn:\nAnn-Sofi f 55, Annika f 62.\n\nNYLÉN, BENGT O S, med dr, docent,\n\nUppsala, f i Stavsnäs, Sthlms l, 18/7/23\nav prof Olle N o Lisa Bengtson.\nStud:ex Upps 42, med kand 45, med lic\n50, med dr o doc i plastikkirurgi Upps\nuniv 1961. - Eo aman, aman o ass histol\ninst Upps univ 44-47, ass :läk kir klin\nAkad sjh 48, tf aman o e läk öronklin\n49-50, 2:e o l:e underläk kir klin 51-52,\nass resident otolaryngol dept\nPresby-terian Hosp USA 53, resident i\nplastik-kir Huntington Memorial Hosp\nPasa-dena Calif 53-54, l:e underläk\nplastik-kir klin Akad sjh 55-61, bitr överläk\nplastikkir klin Karol sjh Sthlm sed 61.\n-KorrL Amer Soc of plastic surgery.\n-Skr i histol, öronhistopatol o plastikkir.\n\n- Hobbies: segling, fiske.\n\nGift 49 m Ingrid Ericsson f 25, dtr t\nakademifogde John E o Stina\nPettersson. - Barn: Eric f 54, Margareta f 55,\nViveka f 57, Bengt f 58, Krister f 60.\n\nNYLÉN, C-O (OLLE) S, professor\nemeritus, Uppsala, f i Upps 30/6/92 av\nreg :läk Sixtus N o Anna Chöler.\nStud:ex Jönkpg 10, med kand 13, med\nlic 18, underläk Jönkpg o Sthlm 18-23,\nmed dr 23, doc i öron-, näs- o halssjukd\nKarol inst, bitr lär o förest öron-,\nnäs-o halspoliklin Seraf:las 23-35, prof i\nöron-, näs- o halssjukd Upps univ samt\növerläk Akad sjh 37-58.- Sekr Sv oto-lar\nfören 28-30, ordf 49, gen:sekr Nord\noto-lar fören 30-33, styr:led 33-49, v\nordf Hörselfrämj riksförb 40-59, ordf\nAkad sällsk 43-46, Insp:konv 56-58,\npresid Båråny-Soc 60-63. - Insp Smal\nnät Upps 40-58, hedL där. - LVS 52,\nLVSU 56. - V ordf Sv tennisförb 45-58\no Int lawn-tennis club of Sweden 38-53,\nstyr :led Kungl lawntenniskl 28-44, ordf\nUpps tenniskl 38-41, Upps stud IF\n39-42, SM i tennis 15, 16, 17 o 25, balt mast\n14 m m. - Skr: ett 100-tal med arb särsk\nrör labyrinten o dess centrala\nförbindelser, huvudred Nord lärob i Oto-Rhino-\n\nLaryng (58), medarb i med tidskr o\nidr:-publ, bl a Kon Gustaf o sv tennis\njubilera (28, 38 o 43). - Utm: KNO, Sv\nläk :sällsk Alvarengapris 31.\nGift 17 m Lisa Bengtson f 91, dtr t\nbyggm N J B o Carolina Jonson. - Barn:\nAnna-Lisa f 18, Ulla f 19, Brita f 21,\nBengt f 23, Dagmar f 25, Ingrid f 26,\nCarl-Olof f 33.\n\nNYLÉN, PAUL, professor emeritus,\nUppsala, f i Bälaryd, Jönkpgs l, 8/9/92\nav kyrkoh Joh N o Alma Pettersson.\nStud:ex Linkpg 11, fil kand Upps 14,\nfil mag 17, fil lic 20, fil dr 31, lär i\nkemi med fakult Upps 18-34, doc i kemi\nUpps 30, KTH 44, prof i färg- o\nlackkemi där 50-58. - Lär arméns\nunderoff:-sk 30-36, tf prof NTH Trondheim 37,\nchefkem Askim Gummivarefabr\ncentral-lab 39, lab :ch stat hantv:inst 40-50, ch\nsv färg- o fernissind:s forskn :lab 44-58,\nordf Kem sällsk Upps 34-37. - Medl\nSHT. - Skr: ett 40-tal vetensk avh i\nkemi o kem tekn, läroböcker, medarb\nhandböcker, ref i tidskr. - Utm: RVO.\nGift 32 m Héléne Ahlford f 03, dtr t\nrådm T A o Ellen Sandberg. - Barn:\nLeif f 39, Birgitta f 41.\n\n",
    "structured": {
        "0": {
            "full_name": "NYLANDER, J C YNGVE",
            "location": "Örebro",
            "occupation": "polisintendent",
            "birth_details": {
                "date": "22/10/1927",
                "place": "Charlottenberg"
            },
            "education": [
                {
                    "degree": "Stud:ex",
                    "year": "1947",
                    "institution": "Umeå"
                },
                {
                    "degree": "distr:åkl:ex",
                    "year": "1951",
                    "institution": "Sthlm"
                },
                {
                    "degree": "jur kand",
                    "year": "1954",
                    "institution": "Sthlm"
                }
            ],
            "career": [
                {
                    "position": "tingstjg Karlskoga doms",
                    "years": {
                        "start_year": 1954,
                        "end_year": 1956
                    }
                },
                {
                    "position": "vik åkl",
                    "years": {
                        "start_year": 1957,
                        "end_year": 1957
                    }
                },
                {
                    "position": "polisnot o polissekr statspolisintend",
                    "years": {
                        "start_year": 1957,
                        "end_year": 1962
                    }
                },
                {
                    "position": "polisintend Örebro",
                    "years": {
                        "start_year": 1962,
                        "end_year": null
                    }
                }
            ],
            "family": {
                "spouse": "Gullan Wiking",
                "marriage_year": "1952",
                "children": [
                    {
                        "name": "Ann-Sofi",
                        "birth_year": "1955"
                    },
                    {
                        "name": "Annika",
                        "birth_year": "1962"
                    }
                ]
            },
            "hobbies": [
                "sport",
                "filateli"
            ]
        },
        "1": {
            "full_name": "NYLÉN, BENGT O S",
            "location": "Uppsala",
            "occupation": "med dr, docent",
            "birth_details": {
                "date": "18/7/1923",
                "place": "Stavsnäs, Sthlms l"
            },
            "education": [
                {
                    "degree": "Stud:ex",
                    "year": "1942",
                    "institution": "Upps"
                },
                {
                    "degree": "med kand",
                    "year": "1945",
                    "institution": "Upps"
                },
                {
                    "degree": "med lic",
                    "year": "1950",
                    "institution": "Upps"
                },
                {
                    "degree": "med dr o doc i plastikkirurgi",
                    "year": "1961",
                    "institution": "Upps univ"
                }
            ],
            "career": [
                {
                    "position": "e läk öronklin",
                    "years": {
                        "start_year": 1949,
                        "end_year": 1950
                    },
                    "organization": "Akad sjh"
                },
                {
                    "position": "l:e underläk plastik-kir klin",
                    "years": {
                        "start_year": 1955,
                        "end_year": 1961
                    },
                    "organization": "Akad sjh"
                },
                {
                    "position": "bitr överläk plastikkir klin",
                    "years": {
                        "start_year": 1961,
                        "end_year": null
                    },
                    "organization": "Karol sjh"
                }
            ],
            "family": {
                "spouse": "Ingrid Ericsson",
                "marriage_year": "1949",
                "children": [
                    {
                        "name": "Eric",
                        "birth_year": "1954"
                    },
                    {
                        "name": "Margareta",
                        "birth_year": "1955"
                    },
                    {
                        "name": "Viveka",
                        "birth_year": "1957"
                    },
                    {
                        "name": "Bengt",
                        "birth_year": "1958"
                    },
                    {
                        "name": "Krister",
                        "birth_year": "1960"
                    }
                ]
            },
            "hobbies": [
                "segling",
                "fiske"
            ]
        },
        "2": {
            "full_name": "NYLÉN, C-O (OLLE) S",
            "location": "Uppsala",
            "occupation": "professor emeritus",
            "birth_details": {
                "date": "30/6/1892",
                "place": "Upps"
            },
            "education": [
                {
                    "degree": "Stud:ex",
                    "year": "1910",
                    "institution": "Jönkpg"
                },
                {
                    "degree": "med kand",
                    "year": "1913",
                    "institution": null
                },
                {
                    "degree": "med lic",
                    "year": "1918",
                    "institution": null
                },
                {
                    "degree": "med dr",
                    "year": "1923",
                    "institution": null
                }
            ],
            "career": [
                {
                    "position": "underläk",
                    "years": {
                        "start_year": 1918,
                        "end_year": 1923
                    },
                    "organization": "Jönkpg o Sthlm"
                },
                {
                    "position": "överläk",
                    "years": {
                        "start_year": 1937,
                        "end_year": 1958
                    },
                    "organization": "Akad sjh"
                }
            ],
            "family": {
                "spouse": "Lisa Bengtson",
                "marriage_year": "1917",
                "children": [
                    {
                        "name": "Anna-Lisa",
                        "birth_year": "1918"
                    },
                    {
                        "name": "Ulla",
                        "birth_year": "1919"
                    },
                    {
                        "name": "Brita",
                        "birth_year": "1921"
                    },
                    {
                        "name": "Bengt",
                        "birth_year": "1923"
                    },
                    {
                        "name": "Dagmar",
                        "birth_year": "1925"
                    },
                    {
                        "name": "Ingrid",
                        "birth_year": "1926"
                    },
                    {
                        "name": "Carl-Olof",
                        "birth_year": "1933"
                    }
                ]
            },
            "hobbies": null
        },
        "3": {
            "full_name": "NYLÉN, PAUL",
            "location": "Uppsala",
            "occupation": "professor emeritus",
            "birth_details": {
                "date": "8/9/1892",
                "place": "Bälaryd, Jönkpgs l"
            },
            "education": [
                {
                    "degree": "Stud:ex",
                    "year": "1911",
                    "institution": "Linkpg"
                },
                {
                    "degree": "fil kand",
                    "year": "1914",
                    "institution": "Upps"
                },
                {
                    "degree": "fil mag",
                    "year": "1917",
                    "institution": "Upps"
                },
                {
                    "degree": "fil lic",
                    "year": "1920",
                    "institution": "Upps"
                }
            ],
            "career": [
                {
                    "position": "lär i kemi med fakult",
                    "years": {
                        "start_year": 1918,
                        "end_year": 1934
                    }
                },
                {
                    "position": "prof i färg- o lackkemi",
                    "years": {
                        "start_year": 1950,
                        "end_year": 1958
                    }
                }
            ],
            "family": {
                "spouse": "Héléne Ahlford",
                "marriage_year": "1932",
                "children": [
                    {
                        "name": "Leif",
                        "birth_year": "1939"
                    },
                    {
                        "name": "Birgitta",
                        "birth_year": "1941"
                    }
                ]
            },
            "hobbies": null
        }
    }
}