{
    "original": "NYQUIST, J E ORVAR, tekn lic,\nSurahammar, f i Ödeshög, Östergötl l, 22/3/\n33 av verkm Erik N o Asta Johansson.\nStud:ex Strängnäs 52, bergsing KTH 58,\nMäss Inst of Techn USA 60-61, tekn lic\nKTH 61, forskn :ass Jernkont 58-60,\nforskn:ing Surahammars bruks ab sed\n61. - Skr: upps behandl studier över\nsintringsprocessen samt vissa\ntermodynamiska storheter inom\nhögtemperaturke-mien.\n\nGift 60 m Margareta Giertz f 36, dtr t\nkamr Sven G o Brita Persson. - Barn:\nJohan f 61, Mikael f 63.\n\nNYQVIST, H RAGNAR, civilingenjör,\n\nVästerås, f i Karlskoga 29/8/29 av ing\nHalvar N o Märta Kron.\nStud:ex  49,  CTH  54,  ing  Gbgs  stads\nelverk 53,  AEG Sthlm  54,  beräkn:ing\nAsea 55. - Hobbies: motor, sport,\nGift 53 m Ulla Svensson f 29,  dtr t\ndistr :ch Alrik S o Sigrid Olsson. - Barn:\nCarina f 57, Staffan f 60.\n\nNYQVIST, N TÖRE, kansliråd,\nVen-delsö, f i Gbg 5/11/14 av handl Johan\nN o Hanna Brask.\n\nStud:ex Karlstad 33, jur kand Upps 38,\ntingstjg Älvdals o Nyeds doms 39-42,\nlänsbokh länsstyr Värml l 42, tax:insp\ndär 46, länsassess 52, tax:intend 58 (bitr\n57), kansliråd o ch landsstatsavd inr:dep\nsed 61. - Sekr Stadsfullm Karlstad 52-61.\n\n-   Medl  SHT.  -   Utm:  Karlstads  stads\nminnespenning.\n\nGift 44 m Mary Larsson f 20, dtr t\nhemm:äg Per L o Gerda Emilsson.\n-Barn: Elisabet f 45.\n\nNYQUIST, G UNO, ingenjör,\nStorfors, f i Storfors, Värml l, 10/12/10 av\nställ Viktor N o Emma Edgren.\n\nIng:ex Bergssk Filipstad 46, prakt stud\nUSA 50-51, valsv:förman Uddeholms ab\nStorforsverken 37, verkm 43, 2:e\nvalsv:-ing 47, valsv:ch där sed 55. - Prakt stud\nm anst v Globe Steel Tube Comp,\nMil-waukee, Wise, o National Tube, Gary,\nInd, USA 50-51. - Ordf skolstyr 50-63;\nCharterpresid Rotary. - Hobby: jakt.\nGift 35 m Sonja Johansson, dtr t Viktor\nJ o Anna Söder. - Barn: Dän f 44.\n\n",
    "structured": {
        "0": {
            "full_name": "J E Orvar Nyquist",
            "location": "Surahammar",
            "occupation": "tekn lic",
            "birth_details": {
                "date": "22/03/1933",
                "place": "Ödeshög",
                "parents": "verkm Erik N o Asta Johansson"
            },
            "education": [
                {
                    "degree": "Stud:ex",
                    "year": "1952",
                    "institution": "Strängnäs"
                },
                {
                    "degree": "bergsing",
                    "year": "1958",
                    "institution": "KTH"
                },
                {
                    "degree": "tekn lic",
                    "year": "1961",
                    "institution": "KTH"
                }
            ],
            "career": [
                {
                    "position": "forskn :ass",
                    "years": {
                        "start_year": 1958,
                        "end_year": 1960
                    },
                    "organization": "Jernkont"
                },
                {
                    "position": "forskn:ing",
                    "years": {
                        "start_year": 1961
                    },
                    "organization": "Surahammars bruks ab"
                }
            ],
            "family": {
                "spouse": "Margareta Giertz",
                "marriage_year": "1960",
                "children": [
                    {
                        "name": "Johan",
                        "birth_year": "1961"
                    },
                    {
                        "name": "Mikael",
                        "birth_year": "1963"
                    }
                ]
            }
        },
        "1": {
            "full_name": "H Ragnar Nyqvist",
            "location": "Västerås",
            "occupation": "civilingenjör",
            "birth_details": {
                "date": "29/08/1929",
                "place": "Karlskoga",
                "parents": "ing Halvar N o Märta Kron"
            },
            "education": [
                {
                    "degree": "Stud:ex",
                    "year": "1949",
                    "institution": "CTH"
                },
                {
                    "degree": "ing",
                    "year": "1954",
                    "institution": "Gbgs stads elverk"
                }
            ],
            "career": [
                {
                    "position": "beräkn:ing",
                    "years": {
                        "start_year": 1955
                    },
                    "organization": "Asea"
                }
            ],
            "family": {
                "spouse": "Ulla Svensson",
                "marriage_year": "1953",
                "children": [
                    {
                        "name": "Carina",
                        "birth_year": "1957"
                    },
                    {
                        "name": "Staffan",
                        "birth_year": "1960"
                    }
                ]
            },
            "hobbies": [
                "motor",
                "sport"
            ]
        },
        "2": {
            "full_name": "N Töre Nyqvist",
            "location": "Vendelsö",
            "occupation": "kansliråd",
            "birth_details": {
                "date": "05/11/1914",
                "place": "Gbg",
                "parents": "handl Johan N o Hanna Brask"
            },
            "education": [
                {
                    "degree": "Stud:ex",
                    "year": "1933",
                    "institution": "Karlstad"
                },
                {
                    "degree": "jur kand",
                    "year": "1938",
                    "institution": "Upps"
                }
            ],
            "career": [
                {
                    "position": "tingstjg",
                    "years": {
                        "start_year": 1939,
                        "end_year": 1942
                    },
                    "organization": "Älvdals o Nyeds doms"
                },
                {
                    "position": "länsbokh",
                    "years": {
                        "start_year": 1942
                    },
                    "organization": "länsstyr Värml l"
                },
                {
                    "position": "tax:insp",
                    "years": {
                        "start_year": 1946
                    },
                    "organization": "där"
                },
                {
                    "position": "länassess",
                    "years": {
                        "start_year": 1952
                    }
                },
                {
                    "position": "tax:intend",
                    "years": {
                        "start_year": 1958,
                        "end_year": 1958
                    }
                },
                {
                    "position": "kansliråd o ch landsstatsavd inr:dep",
                    "years": {
                        "start_year": 1961
                    }
                },
                {
                    "position": "Sekr",
                    "years": {
                        "start_year": 1952,
                        "end_year": 1961
                    },
                    "organization": "Stadsfullm Karlstad"
                }
            ],
            "family": {
                "spouse": "Mary Larsson",
                "marriage_year": "1944",
                "children": [
                    {
                        "name": "Elisabet",
                        "birth_year": "1945"
                    }
                ]
            },
            "community_involvement": [
                {
                    "role": "Medl",
                    "organization": "SHT"
                }
            ],
            "honorary_titles": [
                {
                    "title": "Utm",
                    "institution": "Karlstads stads minnespenning"
                }
            ]
        },
        "3": {
            "full_name": "G Uno Nyquist",
            "location": "Storfors",
            "occupation": "ingenjör",
            "birth_details": {
                "date": "10/12/1910",
                "place": "Storfors, Värml l",
                "parents": "ställ Viktor N o Emma Edgren"
            },
            "education": [
                {
                    "degree": "Ing:ex",
                    "year": "1946",
                    "institution": "Bergssk Filipstad"
                }
            ],
            "career": [
                {
                    "position": "valsv:förman",
                    "years": {
                        "start_year": 1937
                    },
                    "organization": "Uddeholms ab Storforsverken"
                },
                {
                    "position": "2:e valsv:-ing",
                    "years": {
                        "start_year": 1947
                    }
                },
                {
                    "position": "valsv:ch",
                    "years": {
                        "start_year": 1955
                    },
                    "organization": "där"
                }
            ],
            "family": {
                "spouse": "Sonja Johansson",
                "marriage_year": "1935",
                "children": [
                    {
                        "name": "Dän",
                        "birth_year": "1944"
                    }
                ]
            },
            "board_memberships": [
                {
                    "position": "Ordf",
                    "organization": "skolstyr",
                    "years": "50-63"
                },
                {
                    "position": "Charterpresid",
                    "organization": "Rotary"
                }
            ],
            "hobbies": [
                "jakt"
            ]
        }
    }
}