{
    "original": "NYSTRÖM, S (SAM) J, direktör,\nVästerås, f i Vaxholm 11/5/89 av distr :f örest\nC F N o Sofia Andersson.\nSjälvstud, ol anst det:- o grosshdl 03-25,\ndisp ab John H Ericsson Västerås 25,\nverkst dir där sed 27. - Styr:led\nVästmanl l bost:kreditfören,\nstadshypot:-fören, Sv papp:grossistförb, led\nhdlskamm o dess AU, Stadsfullm Västerås\n39-55 (l:e v ordf 51-55), styr:led\nVästerås miss :förs 30, ordf 42-56. - Medl\nOdd Fellow, Rotary.\nGift 1) 22 m Greta Eriksson f Ol d 52,\n2) 56 m Margareta Holm f 04. - Barn:\nSam-Erik o Lennart ff 24.\n\nNÄLSÉN, FRITZ N, fd bankdirektör,\n\nMärsta, f i Mjölby 2/6/81 av\nskomakar-mäst August N o Selma Danielsson.\nStud:ex 00, anst Sthlms ensk bk 00,\navd :ch British Bank of Northern\nCom-merce, London 12, korresp:ch Sv\nhdlsbkn Sthlm 16, dir:ass 17, kassadir\nförs:-bol Sv Veritas o Tellus 20, verkst dir ab\nKreditbkn 21-30, Kreditkassans\nemiss:-ab 21-26, v verkst dir ab Jordbr:bkn 30,\nverkst dir dess Gbg-kontor 35-42. - Utm:\nRVO.\n\nGift 07 m Omika Molin f  81,  dtr t\nskräddarmäst Oscar M o Maria Larsson.\n\nNÄSLUND,   JOHN   D,   ombudsman,\n\nGrängesberg, f i Styrnäs, Västernorrl l,\n\n20/1/16 av yrkeslär Johan N o Annie\n\nKallin.\n\nReparatör Bolidens gruv ab 30-55, omb:-\n\nman  Sv  gruvind :arb :f örb   Grängesberg\n\nsed 55. - Styr :led ab Statsgruvor.\n\nGift 41 m Nanny Jansson f  12, dtr t\n\nhemm:äg Anders J o h h. - Barn: Elsie\n\nf 38, Kristin f 42, Anders f 48.\n\n",
    "structured": {
        "1": {
            "full_name": "NYSTRÖM, S (SAM) J",
            "location": "Västerås",
            "occupation": "direktör",
            "birth_details": {
                "date": "11/05/1889",
                "place": "Vaxholm",
                "parents": "distr :f örest C F N o Sofia Andersson"
            },
            "education": [],
            "career": [
                {
                    "position": "självstud",
                    "years": {
                        "start_year": 1903,
                        "end_year": 1925
                    },
                    "organization": "ol anst det"
                },
                {
                    "position": "disp ab",
                    "years": {
                        "start_year": 1925,
                        "end_year": 1927
                    },
                    "organization": "John H Ericsson Västerås"
                },
                {
                    "position": "verkst dir",
                    "years": {
                        "start_year": 1927
                    },
                    "organization": "John H Ericsson Västerås"
                }
            ],
            "family": {
                "spouse": "Greta Eriksson",
                "marriage_year": "22",
                "children": [
                    {
                        "name": "Sam-Erik",
                        "birth_year": "1924"
                    },
                    {
                        "name": "Lennart",
                        "birth_year": "1924"
                    }
                ]
            }
        },
        "2": {
            "full_name": "NÄLSÉN, FRITZ N",
            "location": "Märsta",
            "occupation": "fd bankdirektör",
            "birth_details": {
                "date": "02/06/1881",
                "place": "Mjölby",
                "parents": "skomakar-mäst August N o Selma Danielsson"
            },
            "education": [
                {
                    "degree": "stud:ex",
                    "year": "1900",
                    "institution": "Sthlms ensk bk"
                }
            ],
            "career": [
                {
                    "position": "anst Sthlms ensk bk",
                    "years": {
                        "start_year": 1900
                    },
                    "organization": "Sthlms ensk bk"
                },
                {
                    "position": "kassadir förs:-bol",
                    "years": {
                        "start_year": 1920,
                        "end_year": 1926
                    },
                    "organization": "Sv Veritas o Tellus"
                },
                {
                    "position": "verkst dir ab Kreditbkn",
                    "years": {
                        "start_year": 1921,
                        "end_year": 1930
                    },
                    "organization": "Kreditbkn"
                },
                {
                    "position": "verkst dir dess Gbg-kontor",
                    "years": {
                        "start_year": 1935,
                        "end_year": 1942
                    },
                    "organization": "Jordbr:bkn"
                }
            ],
            "family": {
                "spouse": "Omika Molin",
                "marriage_year": "1907",
                "children": []
            }
        },
        "3": {
            "full_name": "NÄSLUND,   JOHN   D",
            "location": "Grängesberg",
            "occupation": "ombudsman",
            "birth_details": {
                "date": "20/01/1916",
                "place": "Styrnäs, Västernorrl l",
                "parents": "yrkeslär Johan N o Annie Kallin"
            },
            "education": [],
            "career": [
                {
                    "position": "reparatör Bolidens gruv ab",
                    "years": {
                        "start_year": 1930,
                        "end_year": 1955
                    },
                    "organization": "Bolidens gruv ab"
                },
                {
                    "position": "omb:man  Sv  gruvind :arb :f örb",
                    "years": {
                        "start_year": 1955
                    },
                    "organization": "Grängesberg"
                }
            ],
            "family": {
                "spouse": "Nanny Jansson",
                "marriage_year": "1941",
                "children": [
                    {
                        "name": "Elsie",
                        "birth_year": "1938"
                    },
                    {
                        "name": "Kristin",
                        "birth_year": "1942"
                    },
                    {
                        "name": "Anders",
                        "birth_year": "1948"
                    }
                ]
            }
        }
    }
}