{
    "original": "NYMAN,  HARALD   W,  tandläkare,\n\nKöping, f i Grangärde, Kopparb l, 3/7 /\n03 av skogvakt Olof N o Karin\nDanielsdotter.\n\nStud:ex Norrkpg 24, stud i Greifswald,\ntysk tandläk:ex 33, sv tandläk:ex 36.\n-Eg praktik i Köping. - Medl FrimO,\nOdd Fellow. - Hobbies: jakt, fiske,\ncel-lospelning.\n\nGift 36 m Nea Axelsson, dtr t fabr Axel\nAndersson o h h. - Barn: Elisabeth f 43,\nPeter f 44.\n\nNYMAN, HENRIK O J, borgmästare,\n\nEskilstuna, f i Strängnäs 12/12/08 av rekt\nNils N o Thekla Bergquist.\nStud:ex Umeå 27, jur kand Sthlm 31,\ntingstjg Umeå doms 31-34, fisk Svea\nhovr 35, rådm Eskilstuna 39, borgm sed\n50 (tf 40-44). - Ordf Eskilstuna sparbk.\n-Utm: RNO.\n\nGift 39 m Barbro Carlsson f 17, dtr t\npast Herman C o Elma Holmgren.\n-Barn: Harald f 47’, Torbjörn f 51.\n\nNYMAN, OLLE, universitetslektor,\ndocent, Uppsala, f i Kyrkefalla, Skarab l,\n16/1/20 av form Henning N o Maria\nJohansson.\n\nFil kand Upps 44, fil lic 45, fil dr 47,\ndoc i statskunskap Upps 47, univ :lektor\nsed 60. - Stadsfullm sed 51, led Upps\nstads gen:pl:komm 51-61, byggn:ndn\n51-63, ordf besvärsndn sed 59, led\ndrätsel-kamm 60-63 m fi allm uppdr. - Skr:\nKrisuppgörelsen mellan\nsocialdemokraterna o bondeförbundet 1933 (44), Sv\nparlamentarism 1932—1936 (drsavh 47),\nParlamentarismen i Sv :e. Huvuddragen\nav utvecklingen efter 1917 (50, 4:e uppl\n63), Högern o kungamakten 1911—1914\n(57), Svenskt 1900-tal i dokumentens\nbelysning (tills m H Sellberg 59), Der\nwestdeutsche Föderalismus (60), småskr\no upps i samtidshist, statsvetensk o\npo-lit ämnen i StvT, Sv Tidskr, SvD m fi.\nGift 53 m Margareta Keijser f 29, dtr t\nbefallningsmannen Axel K o Ida\nEriksson. - Barn: Helene f 54, Jan f 56,\nKristina f 61.\n\n",
    "structured": {
        "0": {
            "full_name": "HARALD W NYMAN",
            "location": "Köping",
            "occupation": "tandläkare",
            "birth_details": {
                "date": "03/07/1903",
                "place": "Grangärde, Kopparbergs län",
                "parents": "skogvakt Olof N och Karin Danielsdotter"
            },
            "education": [
                {
                    "degree": "Stud:ex",
                    "year": "1924",
                    "institution": "Norrköping"
                },
                {
                    "degree": "tysk tandläk:ex",
                    "year": "1933",
                    "institution": "Greifswald"
                },
                {
                    "degree": "sv tandläk:ex",
                    "year": "1936",
                    "institution": "NULL"
                }
            ],
            "career": [
                {
                    "position": "Eg praktik i Köping",
                    "years": {
                        "start_year": 1936,
                        "end_year": "NULL"
                    },
                    "organization": "NULL"
                }
            ],
            "family": {
                "spouse": "Nea Axelsson",
                "marriage_year": "1936",
                "children": [
                    {
                        "name": "Elisabeth",
                        "birth_year": "1943"
                    },
                    {
                        "name": "Peter",
                        "birth_year": "1944"
                    }
                ]
            },
            "hobbies": [
                "jakt",
                "fiske",
                "cellospelning"
            ]
        },
        "1": {
            "full_name": "HENRIK O J NYMAN",
            "location": "Eskilstuna",
            "occupation": "borgmästare",
            "birth_details": {
                "date": "12/12/1908",
                "place": "Strängnäs",
                "parents": "rekt Nils N och Thekla Bergquist"
            },
            "education": [
                {
                    "degree": "Stud:ex",
                    "year": "1927",
                    "institution": "Umeå"
                },
                {
                    "degree": "jur kand",
                    "year": "1931",
                    "institution": "Sthlm"
                }
            ],
            "career": [
                {
                    "position": "tingstjg Umeå doms",
                    "years": {
                        "start_year": 1931,
                        "end_year": 1934
                    },
                    "organization": "NULL"
                },
                {
                    "position": "fisk Svea hovr",
                    "years": {
                        "start_year": 1935,
                        "end_year": "NULL"
                    },
                    "organization": "NULL"
                },
                {
                    "position": "rådm Eskilstuna",
                    "years": {
                        "start_year": 1939,
                        "end_year": "NULL"
                    },
                    "organization": "NULL"
                },
                {
                    "position": "borgm",
                    "years": {
                        "start_year": 1950,
                        "end_year": "NULL"
                    },
                    "organization": "Eskilstuna"
                }
            ],
            "family": {
                "spouse": "Barbro Carlsson",
                "marriage_year": "1939",
                "children": [
                    {
                        "name": "Harald",
                        "birth_year": "1947"
                    },
                    {
                        "name": "Torbjörn",
                        "birth_year": "1951"
                    }
                ]
            }
        },
        "2": {
            "full_name": "OLLE NYMAN",
            "location": "Uppsala",
            "occupation": "universitetslektor, docent",
            "birth_details": {
                "date": "16/01/1920",
                "place": "Kyrkefalla, Skarab län",
                "parents": "form Henning N och Maria Johansson"
            },
            "education": [
                {
                    "degree": "Fil kand",
                    "year": "1944",
                    "institution": "Upps"
                },
                {
                    "degree": "fil lic",
                    "year": "1945",
                    "institution": "NULL"
                },
                {
                    "degree": "fil dr",
                    "year": "1947",
                    "institution": "NULL"
                },
                {
                    "degree": "doc i statskunskap",
                    "year": "1947",
                    "institution": "Upps"
                }
            ],
            "career": [
                {
                    "position": "univ :lektor",
                    "years": {
                        "start_year": 1960,
                        "end_year": "NULL"
                    },
                    "organization": "NULL"
                },
                {
                    "position": "Stadsfullm",
                    "years": {
                        "start_year": 1951,
                        "end_year": "NULL"
                    },
                    "organization": "NULL"
                }
            ],
            "family": {
                "spouse": "Margareta Keijser",
                "marriage_year": "1953",
                "children": [
                    {
                        "name": "Helene",
                        "birth_year": "1954"
                    },
                    {
                        "name": "Jan",
                        "birth_year": "1956"
                    },
                    {
                        "name": "Kristina",
                        "birth_year": "1961"
                    }
                ]
            },
            "publications": [
                {
                    "title": "Krisuppgörelsen mellan socialdemokraterna o bondeförbundet",
                    "year": "1933 (44)",
                    "type": "NULL"
                },
                {
                    "title": "Sv parlamentarism",
                    "year": "1932—1936 (drsavh 47)",
                    "type": "NULL"
                },
                {
                    "title": "Parlamentarismen i Sv :e. Huvuddragen av utvecklingen efter 1917",
                    "year": "1950 (4:e uppl 63)",
                    "type": "NULL"
                },
                {
                    "title": "Högern o kungamakten 1911—1914",
                    "year": "1957",
                    "type": "NULL"
                },
                {
                    "title": "Svenskt 1900-tal i dokumentens belysning",
                    "year": "NULL",
                    "type": "tills m H Sellberg 59"
                },
                {
                    "title": "Der westdeutsche Föderalismus",
                    "year": "1960",
                    "type": "NULL"
                }
            ],
            "community_involvement": [
                {
                    "role": "led Upps stads gen:pl:komm",
                    "organization": "NULL",
                    "years": "51-61"
                },
                {
                    "role": "byggn:ndn",
                    "organization": "NULL",
                    "years": "51-63"
                },
                {
                    "role": "ordf besvärsndn",
                    "organization": "NULL",
                    "years": "59"
                },
                {
                    "role": "led drätsel-kamm",
                    "organization": "NULL",
                    "years": "60-63"
                }
            ],
            "honorary_titles": [
                {
                    "title": "NULL",
                    "institution": "NULL",
                    "year": "NULL"
                }
            ],
            "hobbies": "NULL"
        }
    }
}