{
    "original": "NILSON, CARL, godsägare, Häljevad,\nf i Gillberga, Värml l, 16/4/09 av\nlandst:-man Nils N o Amalia Karlsson.\nLantm:sk, inneh Södra Högsäters gård.\n-Styr :led Werml ensk bks avd :kont Värml\nNysäter sed 51, Werml brandst:bol, led\nlantbr :ndn Värml l, v ordf komm:fullm,\nled komm:nd.\n\nGift 41 m Greta Nyman, dtr t skogsch\nErik N o Gerda Edlund. - Barn: Anna\nKarin f 42 d 55, Elisabeth f 44, Kerstin\nf 46, Nils Erik f 50.\n\nNILSSON, DAG Y, civilingenjör,\nKatrineholm, f i Fristad, Älvsb l, 18/6/28\nav tillskärare Carl N o Hulda\nJohansson.\n\nStud:ex Borås 47, CTH 52, bitr ing Gbgs\nstads vattenv 52, ab AIB Gbg 53,\nKatrineholm 57, eg konsult ing :byrå o l:e\nämneslär Katrineholms tekn sk sed 59.\n-Hobbies: fiske, sport, fotografering.\nGift 54 m Edda Gabrielsson f 30, dtr t\nköpm Ragnar G o Lulla Stefansdöttir.\n-Barn: Torbjörn f 56, Stefan f 58, Yngve\nf 63.\n\nNILSSON, DAVID N, advokat,\nUppsala, f i Lägga, Sthlms l, 23/1/06 av\nlantbr Manne N o Lotten Andersson.\nStud:ex Upps 26, jur kand 32, tingstjg\nSödertörns samt Piteå doms 32-35, bitr\njurist h adv R Ahlgren Umeå 35,\nadv:-verksamh Upps sed 51. - LSA 47.\n\nNILSSON, ELIS H,  direktör,\nEskilstuna, f i Jämshög,  Blek l,   11/2/97  av\nverkm Arvid N o Georgine Janzén.\nCTI   17,  anst  ab  Separator  Sthlm   18,\nverkst:ing Eskilstuna  stålpressn  ab   18,\növering där 31, dir 48-62.\nGift 25 m Hildur Ekman f 97. - Barn:\nStig f 26, Bo f 32.\n\nNILSSON, ELSA M, stadsbibliotekarie,\nHedemora, f i  Säf f le 22/6/12 av Karl\nLeander o Anna Jansson.\nHdlsutbildn 35, bibi:kurs 55, forts:kurs\n59.  -  Stadsbibl:ie Hedemora sed  54.  -\n\nOrdf Dalakr RF deltidsanst folkbibl:er\nsed 56, styr:led Sällsk bibl vänner sed\n58, kyrkofullm Hedemora 55-58,\nkonsulent Dalarnas bibl:förb sed 61. - Stip :res\nt Danm 55, Norge 57, Finl 58. - Medarb\ni Bibl:bl 56, tidn Läste Ni 60.\nGift 41 m kassör Claes Nilsson f 07.\n-Barn: Claes-Peter f 45.\n\n",
    "structured": {
        "0": {
            "full_name": "CARL NILSON",
            "location": "Häljevad",
            "occupation": "godsägare",
            "birth_details": {
                "date": "16/04/1909",
                "place": "Gillberga, Värml l",
                "parents": "landst:-man Nils N o Amalia Karlsson"
            },
            "education": {
                "0": {
                    "degree": "Lantm:sk",
                    "year": "NULL",
                    "institution": "Södra Högsäters gård"
                }
            },
            "career": {
                "0": {
                    "position": "Styr :led",
                    "years": {
                        "start_year": 1951,
                        "end_year": "NULL"
                    },
                    "organization": "Werml ensk bks avd :kont Värml Nysäter"
                }
            },
            "family": {
                "spouse": "Greta Nyman",
                "marriage_year": "1941",
                "children": [
                    {
                        "name": "Anna Karin",
                        "birth_year": "1942"
                    },
                    {
                        "name": "Elisabeth",
                        "birth_year": "1944"
                    },
                    {
                        "name": "Kerstin",
                        "birth_year": "1946"
                    },
                    {
                        "name": "Nils Erik",
                        "birth_year": "1950"
                    }
                ]
            }
        },
        "1": {
            "full_name": "DAG Y NILSSON",
            "location": "Katrineholm",
            "occupation": "civilingenjör",
            "birth_details": {
                "date": "18/06/1928",
                "place": "Fristad, Älvsb l",
                "parents": "tillskärare Carl N o Hulda Johansson"
            },
            "education": {
                "0": {
                    "degree": "Stud:ex",
                    "year": "1947",
                    "institution": "Borås"
                },
                "1": {
                    "degree": "CTH",
                    "year": "1952",
                    "institution": "Göteborg"
                }
            },
            "career": {
                "0": {
                    "position": "bitr ing",
                    "years": {
                        "start_year": 1952,
                        "end_year": "NULL"
                    },
                    "organization": "Gbgs stads vattenv"
                },
                "1": {
                    "position": "eg konsult ing :byrå o l:e ämneslär",
                    "years": {
                        "start_year": 1959,
                        "end_year": "NULL"
                    },
                    "organization": "Katrineholms tekn sk"
                }
            },
            "family": {
                "spouse": "Edda Gabrielsson",
                "marriage_year": "1954",
                "children": [
                    {
                        "name": "Torbjörn",
                        "birth_year": "1956"
                    },
                    {
                        "name": "Stefan",
                        "birth_year": "1958"
                    },
                    {
                        "name": "Yngve",
                        "birth_year": "1963"
                    }
                ]
            },
            "hobbies": [
                "fiske",
                "sport",
                "fotografering"
            ]
        },
        "2": {
            "full_name": "DAVID N NILSSON",
            "location": "Uppsala",
            "occupation": "advokat",
            "birth_details": {
                "date": "23/01/1906",
                "place": "Lägga, Sthlms l",
                "parents": "lantbr Manne N o Lotten Andersson"
            },
            "education": {
                "0": {
                    "degree": "Stud:ex",
                    "year": "1926",
                    "institution": "Uppsala"
                },
                "1": {
                    "degree": "jur kand",
                    "year": "1932",
                    "institution": "NULL"
                }
            },
            "career": {
                "0": {
                    "position": "tingstjg",
                    "years": {
                        "start_year": 1932,
                        "end_year": 1935
                    },
                    "organization": "Södertörns doms"
                },
                "1": {
                    "position": "tingstjg",
                    "years": {
                        "start_year": 1932,
                        "end_year": 1935
                    },
                    "organization": "Piteå doms"
                },
                "2": {
                    "position": "adv:-verksam",
                    "years": {
                        "start_year": 1951,
                        "end_year": "NULL"
                    },
                    "organization": "Uppsala"
                }
            },
            "family": {
                "spouse": "NULL",
                "marriage_year": "NULL",
                "children": []
            },
            "publications": [],
            "community_involvement": [],
            "board_memberships": [],
            "honorary_titles": [],
            "hobbies": []
        },
        "3": {
            "full_name": "ELIS H NILSSON",
            "location": "Eskilstuna",
            "occupation": "direktör",
            "birth_details": {
                "date": "11/02/1897",
                "place": "Jämshög, Blek l",
                "parents": "verkm Arvid N o Georgine Janzén"
            },
            "education": {
                "0": {
                    "degree": "CTI",
                    "year": "1917",
                    "institution": "NULL"
                }
            },
            "career": {
                "0": {
                    "position": "anst  ab",
                    "years": {
                        "start_year": 1918,
                        "end_year": "NULL"
                    },
                    "organization": "Separator Sthlm"
                },
                "1": {
                    "position": "verkst:ing",
                    "years": {
                        "start_year": 1918,
                        "end_year": "NULL"
                    },
                    "organization": "Eskilstuna stålpressn ab"
                },
                "2": {
                    "position": "övering",
                    "years": {
                        "start_year": 1931,
                        "end_year": "NULL"
                    },
                    "organization": "Eskilstuna stålpressn ab"
                }
            },
            "family": {
                "spouse": "Hildur Ekman",
                "marriage_year": "1925",
                "children": [
                    {
                        "name": "Stig",
                        "birth_year": "1926"
                    },
                    {
                        "name": "Bo",
                        "birth_year": "1932"
                    }
                ]
            },
            "hobbies": []
        },
        "4": {
            "full_name": "ELSA M NILSSON",
            "location": "Hedemora",
            "occupation": "stadsbibliotekarie",
            "birth_details": {
                "date": "22/06/1912",
                "place": "Säffle",
                "parents": "Karl Leander o Anna Jansson"
            },
            "education": {
                "0": {
                    "degree": "Hdlsutbildn",
                    "year": "1935",
                    "institution": "NULL"
                },
                "1": {
                    "degree": "bibi:kurs",
                    "year": "1955",
                    "institution": "NULL"
                },
                "2": {
                    "degree": "forts:kurs",
                    "year": "1959",
                    "institution": "NULL"
                }
            },
            "career": {
                "0": {
                    "position": "Stadsbibl:ie",
                    "years": {
                        "start_year": 1954,
                        "end_year": "NULL"
                    },
                    "organization": "Hedemora"
                }
            },
            "family": {
                "spouse": "kassör Claes Nilsson",
                "marriage_year": "1941",
                "children": [
                    {
                        "name": "Claes-Peter",
                        "birth_year": "1945"
                    }
                ]
            },
            "publications": [
                {
                    "title": "Bibl:bl",
                    "year": "1956",
                    "type": "NULL"
                },
                {
                    "title": "Läste Ni",
                    "year": "1960",
                    "type": "tidn"
                }
            ],
            "community_involvement": [
                {
                    "role": "Ordf",
                    "organization": "Dalakr RF",
                    "years": "sed 56"
                }
            ],
            "board_memberships": [
                {
                    "position": "styr:led",
                    "organization": "Sällsk bibl vänner",
                    "years": "sed 58"
                }
            ],
            "hobbies": []
        }
    }
}