{
    "original": "NORDKVIST, KARL-AXEL,\ntandläkare, Oxelösund, f i Ringkarleby,\nÖrebro l, 17/4/27 av lantbr Axel N o Maja\nBerggren.\n\nStud:ex Örebro 47, res:off:ex,\ntand-läk:ex Sthlm 54, anst folktandv Nykpg\n55, ass:tandläk 57, prakt Oxelösund sed\n58. - Medl Lions Club. - Fänr A 9 res\n51, löjtn 56. - Hobbies: sport, friluftsliv.\nGift 53 m Berit Saeby-Olsson f 29, dtr t\ngodsäg Gottfrid Olsson o Aagot Saeby.\n- Barn: Lars-Johan f 55, Örjan f 63.\n\nNORDQUIST, MAGNUS, skog dr,\nciviljägmästare, Falun, f i Skön,\nVäster-norrl l, 24/11/90 av sågv:ch Alfred N o\nNella Fernlund.\n\nStud:ex Luleå 10, fil kand Upps 12,\nSkI (hk) 14, jägm:förordn Bergsl:distr\n15, skogsch :ass 17 o skogsch 25-26, bitr\nskogsch St Kopparb bergsl ab 40-55,\nkonsult verks :h ss skogssakk sed 56.\n-Byråch f skogsind :byrån BK 46, sekr 33\nårs skogsind :sakk 33-35, led 37 års\nriks-skogstax :nd 37-46, virkesmätn:sakk\n43-60, flottn:sakk 44-46, ordf flert år\n\nAmungen-Hosjöy Olov-Olsåns o\nTeste-boåns flottn:fören, v ordf Dalarnas\njaktv:förb 47-60, styr:led SvJägF\növerstyr sed 48, dess förb:styr 48-61,\nDalälvarnas virkesmätn :f ören 25-56, Sv:es\nskogsäg:förb 46-56, led länsarb:ndn\nKopparb l 40-57, virkesmätn :råd 49-57,\nordf älgskadendn Kopparb l sed 52, sakk\nrör svårföryngr o skyddsskogar 49-54,\nskogssakk gruvskogskomm sed 60, ch\nbränsleförsörjn :detalj inom länsstyr ekon\nförsv:sekt 53^62. - LIVA 47 (hedL 55),\nLSLA 52, skog hed:dr 63. - Medl FrimO,\nDalarnas Andreasbröder. - Skr: medarb\nHandbok i skogsteknologi (22), Sv:es\nskogar (28), Sv:es skogar under 100 år\n(59), c:a 500 bidr skogl o skogsind\nfackpressen. - Sign: M N, Forester, Wood,\nSqui. - Utm: KVO, RNO, ProPGM,\nDalarnas jaktvfbGM, SvskogsvförenstSM,\nSvJägFSM, JubSM o HtG,\nSkogsvstyrfb-SM, SödermanljaktvförenHt m m.\n-Hobbies: jakt, resor, publ verksamh.\nGift 16 m Gunhild Keiller f 89, dtr t\nbruksäg David K o Tekla Tydén.\n\n",
    "structured": {
        "1": {
            "full_name": "Karl-Axel Nordkvist",
            "location": "Oxelösund",
            "occupation": "Tandläkare",
            "birth_details": {
                "date": "17/04/1927",
                "place": "Ringkarleby, Örebro län",
                "parents": "Lantbr Axel N o Maja Berggren"
            },
            "education": [
                {
                    "degree": "Stud:ex",
                    "year": "1947",
                    "institution": "Örebro"
                },
                {
                    "degree": "Res:off:ex",
                    "year": "1954",
                    "institution": "Sthlm"
                },
                {
                    "degree": "Tand-läk:ex",
                    "year": "1954",
                    "institution": "Sthlm"
                }
            ],
            "career": [
                {
                    "position": "Anst folktandv",
                    "years": {
                        "start_year": 1955,
                        "end_year": null
                    },
                    "organization": "Nykpg"
                },
                {
                    "position": "Ass:tandläk",
                    "years": {
                        "start_year": 1957,
                        "end_year": null
                    },
                    "organization": null
                },
                {
                    "position": "Prakt",
                    "years": {
                        "start_year": 1958,
                        "end_year": null
                    },
                    "organization": "Oxelösund"
                }
            ],
            "family": {
                "spouse": "Berit Saeby-Olsson",
                "marriage_year": "1953",
                "children": [
                    {
                        "name": "Lars-Johan",
                        "birth_year": "1955"
                    },
                    {
                        "name": "Örjan",
                        "birth_year": "1963"
                    }
                ]
            },
            "hobbies": [
                "Sport",
                "Friluftsliv"
            ]
        },
        "2": {
            "full_name": "Magnus Nordquist",
            "location": "Falun",
            "occupation": "Skog Doctor, Civiljägmästare",
            "birth_details": {
                "date": "24/11/1890",
                "place": "Skön, Västernorrlands län",
                "parents": "Sågv:ch Alfred N o Nella Fernlund"
            },
            "education": [
                {
                    "degree": "Stud:ex",
                    "year": "1910",
                    "institution": "Luleå"
                },
                {
                    "degree": "Fil kand",
                    "year": "1912",
                    "institution": "Upps"
                },
                {
                    "degree": "SkI (hk)",
                    "year": "1914",
                    "institution": null
                }
            ],
            "career": [
                {
                    "position": "Jägm:förordn",
                    "years": {
                        "start_year": 1915,
                        "end_year": null
                    },
                    "organization": "Bergsl:distr"
                },
                {
                    "position": "Bitr skogsch",
                    "years": {
                        "start_year": 1925,
                        "end_year": 1926
                    },
                    "organization": null
                },
                {
                    "position": "Konsult verks :h ss skogssakk",
                    "years": {
                        "start_year": 1956,
                        "end_year": null
                    },
                    "organization": null
                }
            ],
            "family": {
                "spouse": "Gunhild Keiller",
                "marriage_year": "1916",
                "children": null
            },
            "publications": [
                {
                    "title": "Handbok i skogsteknologi"
                },
                {
                    "title": "Sv:es skogar"
                },
                {
                    "title": "Sv:es skogar under 100 år"
                }
            ],
            "community_involvement": [
                {
                    "role": "Byråch f skogsind",
                    "organization": "BK",
                    "years": "1946"
                },
                {
                    "role": "Sekr",
                    "organization": "33 års skogsind :sakk",
                    "years": "1933-1935"
                }
            ],
            "board_memberships": null,
            "honorary_titles": [
                "Skog hed:dr"
            ],
            "hobbies": [
                "Jakt",
                "Resor",
                "Publ verksamh"
            ]
        }
    }
}