{
    "original": "NILSSON, TORE R, rektor, Örebro,\nf i Malmö 18/4/12 av järnarb Hans N\no Klara Mårtensson.\n\nFil dr Lund 46, lab :ch ab Ferrosan\nMalmö 42-44, avd :ch forskn :lab LKB\nÄppelviken 46, stat provn:anst Sthlm 56,\nrekt tekn gymn Örebro sed 62. - Expert\nfacksk:utredn, normalpappersutredn, led\ndiv komm inom VDN o SIS. - Red Sv\nkem tidskr 47-55. - Hobby: friluftsliv.\nGift m Ann Margret Antonsson f 12,\ndtr t hdlslär Magnus A o Hedvig Dahlin.\n- Barn: Karin f 41, Mats f 43, Ingrid\nf 46, Anders f 47.\n\nNILSSON, N THURE F, byggmästare,\n\nTrosa, f i Trosa 16/10/08 av byggm\nRobert N o Elin Jansson.\nPrakt i byggn :branschen, byggn\n:verksamh tills m fadern, eg byggn :verksamh\nTrosa sed 45. - Ordf Stadsfullm sed 58\n(led 42).\n\nGift 33 m Astrid Sjöberg f 08, dtr t\ngjutmäst Carl M S o Mathilda Berglund.\n\nNILSSON, ULF L, civilingenjör,\nKarlstad,   f   i  Arvika   18/12/32   av   civiling\nHarry N o Elvira Johansson.\nCTH 56, anst Gbgs vattenverk 56, Allm\ning :byrån Karlstad sed 59.\nGift 56 m Ulla Carlherth f 29,  dtr t\nfolkskollär John C o Siri Gustavsson.\n-Barn: Lars f 56, Per f 59.\n\nNIORDSON, KARL GUSTAF O N,\nkapten, Örebro, f i Sydafr 6/7/21 av\nbergsing Niord Gustafson o Ellen de\nMakkeff.\n\nStud:ex Örebro 42, Off:ex 45, kapt I 3\n57. - Utm: SkytteM.\n\nGift m Viola Björk, dtr t köpman Erik\nB o h h. - Barn: Mikael f 57.\n\nNISKER, S ALLAN, tandläkare,\nDegerfors, f i Nyed, Värml l, 10/12/07 av\nköpman Carl Gustaf Nilsson o Lovisa\nJansson,\n\nStud:ex Karlstad 28, tandläk:ex 33, prakt\nDegerfors sed 34.\n\nGift 37 m Wivan Edlund f 14. - Barn:\nMona f 40, Jan-Christer f 44.\n\n",
    "structured": {
        "0": {
            "full_name": "NILSSON, TORE R",
            "location": "Örebro",
            "occupation": "rektor",
            "birth_details": {
                "date": "18/04/1912",
                "place": "Malmö",
                "parents": "järnarb Hans N o Klara Mårtensson"
            },
            "education": [
                {
                    "degree": "Filosofie doktor",
                    "year": "1946",
                    "institution": "Lund"
                }
            ],
            "career": [
                {
                    "position": "lab :ch",
                    "years": {
                        "start_year": 1942,
                        "end_year": 1944
                    },
                    "organization": "Ferrosan Malmö"
                },
                {
                    "position": "avd :ch forskn :lab",
                    "years": {
                        "start_year": 1946,
                        "end_year": 1956
                    },
                    "organization": "LKB Äppelviken"
                },
                {
                    "position": "stat provn:anst",
                    "years": {
                        "start_year": 1956,
                        "end_year": null
                    },
                    "organization": "Sthlm"
                },
                {
                    "position": "rekt tekn gymn",
                    "years": {
                        "start_year": 1962,
                        "end_year": null
                    },
                    "organization": "Örebro"
                }
            ],
            "family": {
                "spouse": "Ann Margret Antonsson",
                "marriage_year": "NULL",
                "children": [
                    {
                        "name": "Karin",
                        "birth_year": "1941"
                    },
                    {
                        "name": "Mats",
                        "birth_year": "1943"
                    },
                    {
                        "name": "Ingrid",
                        "birth_year": "1946"
                    },
                    {
                        "name": "Anders",
                        "birth_year": "1947"
                    }
                ]
            }
        },
        "1": {
            "full_name": "NILSSON, N THURE F",
            "location": "Trosa",
            "occupation": "byggmästare",
            "birth_details": {
                "date": "16/10/1908",
                "place": "Trosa",
                "parents": "byggm Robert N o Elin Jansson"
            },
            "education": null,
            "career": [
                {
                    "position": "eg byggn :verksamh",
                    "years": {
                        "start_year": 1945,
                        "end_year": null
                    },
                    "organization": "Trosa"
                },
                {
                    "position": "Ordf Stadsfullm",
                    "years": {
                        "start_year": 1958,
                        "end_year": null
                    },
                    "organization": "Trosa"
                }
            ],
            "family": {
                "spouse": "Astrid Sjöberg",
                "marriage_year": "1933",
                "children": null
            }
        },
        "2": {
            "full_name": "NILSSON, ULF L",
            "location": "Karlstad",
            "occupation": "civilingenjör",
            "birth_details": {
                "date": "18/12/1932",
                "place": "Arvika",
                "parents": "civiling Harry N o Elvira Johansson"
            },
            "education": [
                {
                    "degree": "CTH",
                    "year": "1956",
                    "institution": "Chalmers tekniska högskola"
                }
            ],
            "career": [
                {
                    "position": "anst Gbgs vattenverk",
                    "years": {
                        "start_year": 1956,
                        "end_year": null
                    },
                    "organization": null
                },
                {
                    "position": "Allm ing :byrån",
                    "years": {
                        "start_year": 1959,
                        "end_year": null
                    },
                    "organization": "Karlstad"
                }
            ],
            "family": {
                "spouse": "Ulla Carlherth",
                "marriage_year": "1956",
                "children": [
                    {
                        "name": "Lars",
                        "birth_year": "1956"
                    },
                    {
                        "name": "Per",
                        "birth_year": "1959"
                    }
                ]
            }
        },
        "3": {
            "full_name": "NIORDSON, KARL GUSTAF O N",
            "location": "Örebro",
            "occupation": "kapten",
            "birth_details": {
                "date": "06/07/1921",
                "place": "Sydafrika",
                "parents": "bergsing Niord Gustafson o Ellen de Makkeff"
            },
            "education": [
                {
                    "degree": null,
                    "year": null,
                    "institution": null
                }
            ],
            "career": [
                {
                    "position": "kapt I 3",
                    "years": {
                        "start_year": 1957,
                        "end_year": null
                    },
                    "organization": null
                }
            ],
            "family": {
                "spouse": "Viola Björk",
                "marriage_year": "NULL",
                "children": [
                    {
                        "name": "Mikael",
                        "birth_year": "1957"
                    }
                ]
            }
        },
        "4": {
            "full_name": "NISKER, S ALLAN",
            "location": "Degerfors",
            "occupation": "tandläkare",
            "birth_details": {
                "date": "10/12/1907",
                "place": "Nyed, Värmland",
                "parents": "köpman Carl Gustaf Nilsson o Lovisa Jansson"
            },
            "education": [
                {
                    "degree": null,
                    "year": "1928",
                    "institution": "Karlstad"
                },
                {
                    "degree": "tandläk:ex",
                    "year": "1933",
                    "institution": "NULL"
                }
            ],
            "career": [
                {
                    "position": "prakt",
                    "years": {
                        "start_year": 1934,
                        "end_year": null
                    },
                    "organization": "Degerfors"
                }
            ],
            "family": {
                "spouse": "Wivan Edlund",
                "marriage_year": "1937",
                "children": [
                    {
                        "name": "Mona",
                        "birth_year": "1940"
                    },
                    {
                        "name": "Jan-Christer",
                        "birth_year": "1944"
                    }
                ]
            }
        }
    }
}