{
    "original": "NILSSON, STIG V, bankdirektör,\nKöping, f i Ludvika 11/6/22 av polisman\nGustaf N o Anna Hedström.\nRealex 39, anst Sv hdlsbkn Ludvika 40,\nLeksand 46, Falun 47, Västerås 50,\nlåne-kamr där 57, avd :kamr Umeå 59,\nVästerås 60, dir Köping sed 63. - Medl Odd\nFellow.\n\nGift 51 m Karin Jansson f 25, dtr t\nlantbr Johan J o Edit Andersson. - Barn:\nAnders f 57, Göran f 63.\n\nNILSSON, K STURE,\ndistriktsveterinär, Säffle, f i Odensvi, Kalmar l,\n19/6/00 av lantbr Carl N o Elise Larsson.\nStud:ex Lund 22, vet:ex 27, ass VHS\n28, distr :veterinär Gysinge 32, distr:- o\nbesiktn :veterinär Säffle sed 39. - Utm:\nRNO. - Hobby: segling.\nGift 35 m Edit Nilsson f 04. - Barn:\nSture f 38, Erik f 39, Lennart f 42,\nChrister f 44.\n\nNILSSON, STURE, direktör, Torshälla,\nf i Eskilstuna 27/1/08 av dir Sixten N\no Sigrid Ekman.\n\nStud:ex 27, DHS 30, verkst dir o\nstyr:led Aug Stenman ab sed 47. - Styr :led\nSv:es mekanförb sed 56 (ordf 61-64),\nSv:es ind:förb sed 59, fullm Eskilstuna\nfabr:fören sed 44 (ordf 53-62). - HedL\nSödermanl-Nerikes nät Upps 61. - Utm:\nRVO.\n\nGift 31 m Brita Forssberg f 09, dtr t\ndir Erik F o Martha Andersson. - Barn:\nUlla-Brita f 33, Ulf f 35, Håkan f 40,\nMonica f 43.\n\nNILSSON, SVEN A, civilingenjör,\nEskilstuna, f i Eskilstuna 13/2/26 av disp\nArvid N o Ruth Persson.\nKTH 51, anst Husqvarna vapenfabr ab\n52, C O Öberg &amp; Co:s ab Eskilstuna 53,\nGeneral Electric 55, verkst dir C O\nÖberg &amp; Co:s ab sed 58. - Hobbies:\nsegling, musik.\n\nGift 55 m Ulrika Flyborg, dtr t vet\nSigurd F o Helga Andersson. - Barn:\nPer f 57, Anna f 59, Eva f 61.\n\n",
    "structured": {
        "0": {
            "full_name": "STIG V NILSSON",
            "location": "Köping",
            "occupation": "bankdirektör",
            "birth_details": {
                "date": "11/06/1922",
                "place": "Ludvika",
                "parents": "polisman Gustaf N o Anna Hedström"
            },
            "education": [
                {
                    "degree": "Realex",
                    "year": "1939",
                    "institution": "Sv hdlsbkn Ludvika"
                }
            ],
            "career": [
                {
                    "position": "avd :kamr",
                    "years": {
                        "start_year": 1957,
                        "end_year": 1959
                    },
                    "organization": "Umeå"
                },
                {
                    "position": "dir",
                    "years": {
                        "start_year": 1963,
                        "end_year": null
                    },
                    "organization": "Köping"
                }
            ],
            "family": {
                "spouse": "Karin Jansson",
                "marriage_year": "1951",
                "children": [
                    {
                        "name": "Anders",
                        "birth_year": "1957"
                    },
                    {
                        "name": "Göran",
                        "birth_year": "1963"
                    }
                ]
            }
        },
        "1": {
            "full_name": "K STURE NILSSON",
            "location": "Säffle",
            "occupation": "distriktsveterinär",
            "birth_details": {
                "date": "19/06/1900",
                "place": "Odensvi, Kalmar l",
                "parents": "lantbr Carl N o Elise Larsson"
            },
            "education": [
                {
                    "degree": "Stud:ex",
                    "year": "1922",
                    "institution": "Lund"
                },
                {
                    "degree": "vet:ex",
                    "year": "1927",
                    "institution": "VHS"
                }
            ],
            "career": [
                {
                    "position": "distr :veterinär",
                    "years": {
                        "start_year": 1939,
                        "end_year": null
                    },
                    "organization": "Säffle"
                }
            ],
            "family": {
                "spouse": "Edit Nilsson",
                "marriage_year": "1935",
                "children": [
                    {
                        "name": "Sture",
                        "birth_year": "1938"
                    },
                    {
                        "name": "Erik",
                        "birth_year": "1939"
                    },
                    {
                        "name": "Lennart",
                        "birth_year": "1942"
                    },
                    {
                        "name": "Christer",
                        "birth_year": "1944"
                    }
                ]
            },
            "honorary_titles": [
                {
                    "title": "RNO",
                    "institution": null,
                    "year": null
                }
            ],
            "hobbies": [
                "segling"
            ]
        },
        "2": {
            "full_name": "STURE NILSSON",
            "location": "Torshälla",
            "occupation": "direktör",
            "birth_details": {
                "date": "27/01/1908",
                "place": "Eskilstuna",
                "parents": "dir Sixten N o Sigrid Ekman"
            },
            "education": [
                {
                    "degree": "Stud:ex",
                    "year": "1927",
                    "institution": null
                },
                {
                    "degree": "DHS",
                    "year": "1930",
                    "institution": null
                }
            ],
            "career": [
                {
                    "position": "verkst dir o styr:led",
                    "years": {
                        "start_year": 1947,
                        "end_year": null
                    },
                    "organization": "Aug Stenman ab"
                }
            ],
            "family": {
                "spouse": "Brita Forssberg",
                "marriage_year": "1931",
                "children": [
                    {
                        "name": "Ulla-Brita",
                        "birth_year": "1933"
                    },
                    {
                        "name": "Ulf",
                        "birth_year": "1935"
                    },
                    {
                        "name": "Håkan",
                        "birth_year": "1940"
                    },
                    {
                        "name": "Monica",
                        "birth_year": "1943"
                    }
                ]
            },
            "honorary_titles": [
                {
                    "title": "RVO",
                    "institution": null,
                    "year": null
                }
            ]
        },
        "3": {
            "full_name": "SVEN A NILSSON",
            "location": "Eskilstuna",
            "occupation": "civilingenjör",
            "birth_details": {
                "date": "13/02/1926",
                "place": "Eskilstuna",
                "parents": "disp Arvid N o Ruth Persson"
            },
            "education": [
                {
                    "degree": null,
                    "year": "1951",
                    "institution": "KTH"
                }
            ],
            "career": [
                {
                    "position": "verkst dir",
                    "years": {
                        "start_year": 1958,
                        "end_year": null
                    },
                    "organization": "C O Öberg & Co:s ab"
                }
            ],
            "family": {
                "spouse": "Ulrika Flyborg",
                "marriage_year": "1955",
                "children": [
                    {
                        "name": "Per",
                        "birth_year": "1957"
                    },
                    {
                        "name": "Anna",
                        "birth_year": "1959"
                    },
                    {
                        "name": "Eva",
                        "birth_year": "1961"
                    }
                ]
            },
            "hobbies": [
                "segling",
                "musik"
            ]
        }
    }
}