{
    "original": "FRIDEGÅRD, JAN F, författare,\nUppsala, f i Enkpgs-Näs, Upps l, 14/6/97 av\nlantarb Johan Johansson-From o Anna\nLyster.\n\nKorpr 15-18, affärsbitr, gårdfarihandl,\naff:bitr o eg antikvariat 18-33. - Skr:\nDen svarta lutan (31), En natt i juli\n(33), Jag Lars Hård (35), Tack för\nHim-lastegen (36), Barmhärtighet (36), Offer\n(37), Äran o hjältarna (38), Statister (39),\nTrägudars land (40), Torntuppen (41),\nHär är min hand (42), Kvarnbudet (44),\nGryningsfolket (44), Fäderna (47),\nOfferrök (49), Kvinnoträdet (50), Lars\nHård går vidare (51), Porten kallas\ntrång (52), Johan Vallareman o andra\nsagor (52), Vägen heter smal (53),\nSommarorgel (54), Lyktgubbarna (55),\nFlyttfåglarna (56), Arvtagarna (57), En bland\neder (58), Svensk soldat (59), Muren\n(59), Soldathustrun (60), Mot öster —\nsoldat! (61), Soldatens kärlek (62),\nHemkomsten (63), Den gåtfulla vägen (63).\n-Medl Sv förf:fören, Lions Club,\nPenn-klubb, Ortnamnssällsk, STF, Soc\nIntel-lectualis Seniorem Upsaliensis; hedL\nUppl nät Upps, Ungdomsringen m fi.\n-Utm: Uppsala stads ftJM. - Hobby:\nfornkunskap.\n\nGift 37 m Gudrun Nilsson f 14, dtr t\nåkare Johan N o Ruth Bergqvist.\n-Barn: Aase f 37, Stefan f 42.\n\nFRIDELL, FOLKE, direktör, Karlstad,\nf i Luleå 1/6/03.\n\nDir Värml lantmäns centralfören upa\nKarlstad. - Styr :led Gbgs fodervaru ab.\n\nFRIDÉN, SIGURD, läroverksadjunkt,\nSigtuna, f i Örebro 20/12/99 av\nfolksk:-insp Alfred F o Melin Larsson.\nStud:ex Linkpg 19, fil mag Upps 25, adj\nSigtunastift hum lärov sed 26, bibl där.\n\n-   Utm:  SCFftjtG.   - Hobbies:  segling,\nträdgårdsskötsel.\n\nGift 35 m Ingrid Nilsson f 08, dtr t\ntåg-mast Carl N o Hanna Johansson.\n",
    "structured": {
        "1": {
            "full_name": "F Jan Fridegård",
            "location": "Uppsala",
            "occupation": "författare",
            "birth_details": {
                "date": "14/06/1897",
                "place": "Enkpgs-Näs, Uppsala l"
            },
            "education": [],
            "career": [
                {
                    "position": "Korpr",
                    "years": {
                        "start_year": 1915,
                        "end_year": 1918
                    },
                    "organization": "NULL"
                },
                {
                    "position": "affärsbitr",
                    "years": {
                        "start_year": 1918,
                        "end_year": 1933
                    },
                    "organization": "NULL"
                }
            ],
            "family": {
                "spouse": "Gudrun Nilsson",
                "marriage_year": "1937",
                "children": [
                    {
                        "name": "Aase",
                        "birth_year": "1937"
                    },
                    {
                        "name": "Stefan",
                        "birth_year": "1942"
                    }
                ]
            },
            "publications": [
                {
                    "title": "Den svarta lutan",
                    "year": "1931",
                    "type": "NULL"
                },
                {
                    "title": "En natt i juli",
                    "year": "1933",
                    "type": "NULL"
                }
            ],
            "community_involvement": [],
            "board_memberships": [],
            "honorary_titles": [],
            "hobbies": [
                "fornkunskap"
            ]
        },
        "2": {
            "full_name": "Folke Fridell",
            "location": "Karlstad",
            "occupation": "direktör",
            "birth_details": {
                "date": "01/06/1903",
                "place": "Luleå"
            },
            "education": [],
            "career": [
                {
                    "position": "Dir Värml lantmäns centralfören",
                    "years": {
                        "start_year": null,
                        "end_year": null
                    },
                    "organization": "upa Karlstad"
                },
                {
                    "position": "led Gbgs fodervaru ab",
                    "years": {
                        "start_year": null,
                        "end_year": null
                    },
                    "organization": "NULL"
                }
            ],
            "family": {
                "spouse": "NULL",
                "marriage_year": "NULL",
                "children": []
            }
        },
        "3": {
            "full_name": "Sigurd Fridén",
            "location": "Sigtuna",
            "occupation": "läroverksadjunkt",
            "birth_details": {
                "date": "20/12/1899",
                "place": "Örebro"
            },
            "education": [
                {
                    "degree": "Stud:ex",
                    "year": "1925",
                    "institution": "Linkpg"
                },
                {
                    "degree": "fil mag",
                    "year": "1925",
                    "institution": "Upps"
                }
            ],
            "career": [
                {
                    "position": "adj Sigtunastift hum lärov",
                    "years": {
                        "start_year": 1926,
                        "end_year": null
                    },
                    "organization": "NULL"
                },
                {
                    "position": "bibl",
                    "years": {
                        "start_year": null,
                        "end_year": null
                    },
                    "organization": "där"
                }
            ],
            "family": {
                "spouse": "Ingrid Nilsson",
                "marriage_year": "1935",
                "children": []
            },
            "community_involvement": [],
            "board_memberships": [],
            "honorary_titles": [],
            "hobbies": [
                "segling",
                "trädgårdsskötsel"
            ]
        }
    }
}