{
    "original": "FLODEN, CARL-HENRIK A, med\ndr, docent, Karlstad, f i Uddevalla 16/3/\n17 av major Axel F o Jane Wolff.\nStud:ex Sthlm 35, med kand 38, med lic\n43, med dr 55, doc i dermat ologi o\nvene-reologi Karol inst 55. - Underläk Sthlms\ngarn :sjh 45-46, kir avd o hud- o\nköns-sjukavd S:t Görans sjh 45-47, aman\nhudklin Karol sjh 46-48, l:e underläk o\nbitr överläk 48, konsult läk hud- o\nköns-sjukd Karlstads las 57-59, överläk där\nsed 59. - Tf föredragande hos med :styr\ni ärenden rör könssjv o internat hälsov\n51-52, korrL Soc francaise de dermatol\net syphilis, Finl dermatol sällsk, Acad\nEspanola de Dermatol y Sifiligrafia,\nDermatol Soc of the Med Assoc of\nIsrael, Sociedad di Dermatol de\nVenezuela, gen :sekr XI :e internat\ndermato-logkongr Sthlm 57. - Utg: skr i\ndermatol o venereol.\n\nGift 46 m leg läk Sonja Noraeus f 06.\n-Barn: Tom f 37 (adoptivson), Christer\nf 49.\n\nFLODERUS, HANS Å, arkitekt SAR,\n\nUppsala, f i Nässjö 3/4/22 av ing\nStyrbjörn F o Annie Nyberg.\nStud:ex Falun 43, KTH 51, anst ol\nar-kit:kont 50-55, eg arkit :verksamh sed\n55, stadsarkit Norberg sed 57, Avesta\nsed 59. - Utarb gen :planer f Köping,\nHallstahammar, Norberg o Avesta.\nGift 50 m arkit SAR Åsel Mutén f 25,\ndtr t kamr Robert M o ämneslär\nIngeborg Heurlinger. - Barn: Ylva f 52,\nBritt f 54, Nina f 57, Sören f 58.\n\nFLODERUS, H THORE,\nstadsbibliotekarie, Enköping, f i Vittangi, Norrb l,\n5/7/20 av ing Styrbjörn F o Annie\nNyberg.\n\nStud:ex Falun 41, fil kand Sthlm 49, SO\nbibl:sk 51, ass:bibl stifts- o landsbibi\nVästerås 51, stadsbibl Sala 54, Enkpg\nsed 57. - Ordf Sydv Uppl kulturhist fören\nsed 63, styr:led Uppl f ornm :f ören sed 61,\nsekr komm f utg av Enkpgs hist sed 58.\n\n-  Medl FrimO.\n\nGift 53 m fil kand Elisabeth von\nEngeström f 24, dtr t prof Sigfrid v E o\nMargareta Cavallin. - Barn: Eugenie f\n55, Alfhild f 58, Gustaf f 63.\n",
    "structured": {
        "1": {
            "full_name": "FLODEN, CARL-HENRIK A",
            "location": "Karlstad",
            "occupation": "med dr, docent",
            "birth_details": {
                "date": "16/03/1917",
                "place": "Uddevalla",
                "parents": "major Axel F o Jane Wolff"
            },
            "education": [
                {
                    "degree": "Stud:ex",
                    "year": "1935",
                    "institution": "Sthlm"
                },
                {
                    "degree": "med kand",
                    "year": "1938",
                    "institution": "NULL"
                },
                {
                    "degree": "med lic",
                    "year": "1943",
                    "institution": "NULL"
                },
                {
                    "degree": "med dr",
                    "year": "1955",
                    "institution": "NULL"
                }
            ],
            "career": [
                {
                    "position": "Underläk",
                    "years": {
                        "start_year": 1945,
                        "end_year": 1946
                    },
                    "organization": "Sthlms garn :sjh"
                },
                {
                    "position": "kir avd o hud- o köns-sjukavd",
                    "years": {
                        "start_year": 1945,
                        "end_year": 1947
                    },
                    "organization": "S:t Görans sjh"
                },
                {
                    "position": "aman hudklin",
                    "years": {
                        "start_year": 1946,
                        "end_year": 1948
                    },
                    "organization": "Karol sjh"
                },
                {
                    "position": "l:e underläk o bitr överläk",
                    "years": {
                        "start_year": 1948,
                        "end_year": null
                    },
                    "organization": "NULL"
                },
                {
                    "position": "konsult läk hud- o köns-sjukd",
                    "years": {
                        "start_year": 1957,
                        "end_year": 1959
                    },
                    "organization": "Karlstads las"
                },
                {
                    "position": "överläk",
                    "years": {
                        "start_year": 1959,
                        "end_year": null
                    },
                    "organization": "Karlstads las"
                },
                {
                    "position": "Tf föredragande",
                    "years": {
                        "start_year": 1951,
                        "end_year": 1952
                    },
                    "organization": "NULL"
                }
            ],
            "family": {
                "spouse": "Sonja Noraeus",
                "marriage_year": "1946",
                "children": [
                    {
                        "name": "Tom",
                        "birth_year": "1937"
                    },
                    {
                        "name": "Christer",
                        "birth_year": "1949"
                    }
                ]
            }
        },
        "2": {
            "full_name": "FLODERUS, HANS Å",
            "location": "Uppsala",
            "occupation": "arkitekt SAR",
            "birth_details": {
                "date": "03/04/1922",
                "place": "Nässjö",
                "parents": "ing Styrbjörn F o Annie Nyberg"
            },
            "education": [
                {
                    "degree": "Stud:ex",
                    "year": "1943",
                    "institution": "Falun"
                },
                {
                    "degree": "KTH",
                    "year": "1951",
                    "institution": "NULL"
                }
            ],
            "career": [
                {
                    "position": "anst ol ar-kit:kont",
                    "years": {
                        "start_year": 1950,
                        "end_year": 1955
                    },
                    "organization": "NULL"
                },
                {
                    "position": "stadsarkit",
                    "years": {
                        "start_year": 1957,
                        "end_year": null
                    },
                    "organization": "Avesta"
                }
            ],
            "family": {
                "spouse": "SAR Åsel Mutén",
                "marriage_year": "1950",
                "children": [
                    {
                        "name": "Ylva",
                        "birth_year": "1952"
                    },
                    {
                        "name": "Britt",
                        "birth_year": "1954"
                    },
                    {
                        "name": "Nina",
                        "birth_year": "1957"
                    },
                    {
                        "name": "Sören",
                        "birth_year": "1958"
                    }
                ]
            }
        },
        "3": {
            "full_name": "FLODERUS, H THORE",
            "location": "Enköping",
            "occupation": "stadsbibliotekarie",
            "birth_details": {
                "date": "05/07/1920",
                "place": "Vittangi, Norrb l",
                "parents": "ing Styrbjörn F o Annie Nyberg"
            },
            "education": [
                {
                    "degree": "Stud:ex",
                    "year": "1941",
                    "institution": "Falun"
                },
                {
                    "degree": "fil kand",
                    "year": "1949",
                    "institution": "Sthlm"
                },
                {
                    "degree": "SO bibl:sk",
                    "year": "1951",
                    "institution": "NULL"
                }
            ],
            "career": [
                {
                    "position": "ass:bibl stifts- o landsbibi",
                    "years": {
                        "start_year": 1951,
                        "end_year": 1953
                    },
                    "organization": "Västerås"
                },
                {
                    "position": "stadsbibl",
                    "years": {
                        "start_year": 1957,
                        "end_year": null
                    },
                    "organization": "Enkpg"
                }
            ],
            "family": {
                "spouse": "fil kand Elisabeth von Engeström",
                "marriage_year": "1953",
                "children": [
                    {
                        "name": "Eugenie",
                        "birth_year": "1955"
                    },
                    {
                        "name": "Alfhild",
                        "birth_year": "1958"
                    },
                    {
                        "name": "Gustaf",
                        "birth_year": "1963"
                    }
                ]
            },
            "hobbies": [
                "Medl FrimO"
            ]
        }
    }
}