{
    "original": "FLINK, BRITA, läroverksadjunkt,\nÖrebro, f i Säby, Malmöhus l, 6/6/08 av\nsmedmäst Ernst Berglund o Selma\nSvensson.\n\nStud:ex Landskrona 26, fil kand Lund\n29, fil mag 31, e lär o vik ämneslär ol\nplatser 32-38, eo adj Malmö 38, Lund 38,\nadj Karol hal Örebro sed 40. - Styr :led\nsamf Örebro stads- o länsbibi vänner sed\n51. - Ordf Damernas Concordia sed 55.\n- Utm: LNO. - Hobbies: litteratur,\nteater, musik.\nGift 37 m fil lic Gunnar Flink d 38.\n\nFLINTA, JAN E, civilingenjör, Nykpg,\nf i Hedemora 24/9/18 av dir Erland F o\nMargot Johansson.\n\nTekn gymn Örebro 40, KTH 56, anst\nFinspongs metallv 41, jvstyr 42, FOA\n47, ab Atomenergi 50, ch dess sekt f\nexp värmetekn o mek Studsvik sed 57.\n-S kr i fackämnen. - Hobby:\nträdgårdsskötsel.\n\nGift 55 m Elsa Brennert f 21, dtr t\nciviling Ernst Ohlsson o Esther Hederén. •\nBarn: Christofer f 57, Cecilia f 59.\n\nFLISMARK, K ÅKE G, bankdirektör,\nNyköping, f i Urshult, Kronob l, 8/4/21\nav trav :handl Ernst Fransson o Emilia\nJohansson.\n\nRealex 38, Påhlmans hdlsl 39, anst\nJord-br:bkn (nuv Sv:es kreditbk) 39, kamr\nVimmerby sparbk 48, Sv:es kreditbk 50,\nkamr 54, dir o ch Sv:es kreditbk Nykpg\nsed 60. - Styr:led Sv:es kreditbk Nykpg,\nab Exportlist. - Medl Odd Fellow,\nW-sex.\nBarn: i tid akt Gunvor f 46, Björn f 48.\n\nFLODELL, C ERIC G, direktör,\nEskilstuna, f i Eskilstuna 20/10/08.\n\nKorresp :stud, anst ol föret\ngrossistbransch o metallfabrikation 23-45, kamr\nab F A Stenmans iåsfabr Eskilstuna 45,\nverkst dlr där sed 59. - Medl IOGT, TR.\n\n- Hobbies: musik, sång.\n\nGift 43 m Astrid Öhman f 14. - Barn:\nÅke f 45, Inga f 50.\n\n",
    "structured": {
        "1": {
            "full_name": "BRITA FLINK",
            "location": "Örebro",
            "occupation": "läroverksadjunkt",
            "birth_details": {
                "date": "06/06/1908",
                "place": "Säby, Malmöhus l",
                "parents": "smedmäst Ernst Berglund o Selma Svensson"
            },
            "education": [
                {
                    "degree": "Stud:ex",
                    "year": "1926",
                    "institution": "Landskrona"
                },
                {
                    "degree": "filosofie kandidat",
                    "year": "1929",
                    "institution": "Lund"
                },
                {
                    "degree": "filosofie magister",
                    "year": "1931",
                    "institution": "Lund"
                }
            ],
            "career": [
                {
                    "position": "e lär o vik ämneslär",
                    "years": {
                        "start_year": 1932,
                        "end_year": 1938
                    },
                    "organization": "ol platser"
                },
                {
                    "position": "eo adj",
                    "years": {
                        "start_year": 1938,
                        "end_year": 1938
                    },
                    "organization": "Malmö"
                },
                {
                    "position": "eo adj",
                    "years": {
                        "start_year": 1938,
                        "end_year": 1938
                    },
                    "organization": "Lund"
                },
                {
                    "position": "adj Karol hal",
                    "years": {
                        "start_year": 1940,
                        "end_year": null
                    },
                    "organization": "Örebro"
                }
            ],
            "family": {
                "spouse": "fil lic Gunnar Flink",
                "marriage_year": "1937",
                "children": [
                    {
                        "name": "NULL",
                        "birth_year": "NULL"
                    }
                ]
            },
            "hobbies": [
                "litteratur",
                "teater",
                "musik"
            ]
        },
        "2": {
            "full_name": "JAN E FLINTA",
            "location": "Nykpg",
            "occupation": "civilingenjör",
            "birth_details": {
                "date": "24/09/1918",
                "place": "Hedemora",
                "parents": "dir Erland F o Margot Johansson"
            },
            "education": null,
            "career": null,
            "family": {
                "spouse": "Elsa Brennert",
                "marriage_year": "1955",
                "children": [
                    {
                        "name": "Christofer",
                        "birth_year": "1957"
                    },
                    {
                        "name": "Cecilia",
                        "birth_year": "1959"
                    }
                ]
            },
            "hobbies": [
                "trädgårdsskötsel"
            ]
        },
        "3": {
            "full_name": "K ÅKE G FLISMARK",
            "location": "Nyköping",
            "occupation": "bankdirektör",
            "birth_details": {
                "date": "08/04/1921",
                "place": "Urshult, Kronob l",
                "parents": "trav :handl Ernst Fransson o Emilia Johansson"
            },
            "education": [
                {
                    "degree": "Realex",
                    "year": "1938",
                    "institution": "NULL"
                },
                {
                    "degree": "Påhlmans hdlsl",
                    "year": "1939",
                    "institution": "NULL"
                }
            ],
            "career": [
                {
                    "position": "anst Jord-br:bkn",
                    "years": {
                        "start_year": 1939,
                        "end_year": null
                    },
                    "organization": "(nuv Sv:es kreditbk)"
                },
                {
                    "position": "kamr Vimmerby sparbk",
                    "years": {
                        "start_year": 1948,
                        "end_year": null
                    },
                    "organization": "NULL"
                },
                {
                    "position": "kamr",
                    "years": {
                        "start_year": 1954,
                        "end_year": null
                    },
                    "organization": "Sv:es kreditbk"
                },
                {
                    "position": "dir o ch Sv:es kreditbk",
                    "years": {
                        "start_year": 1960,
                        "end_year": null
                    },
                    "organization": "Nykpg"
                }
            ],
            "family": {
                "spouse": "NULL",
                "marriage_year": "NULL",
                "children": [
                    {
                        "name": "Gunvor",
                        "birth_year": "1946"
                    },
                    {
                        "name": "Björn",
                        "birth_year": "1948"
                    }
                ]
            }
        },
        "4": {
            "full_name": "C ERIC G FLODELL",
            "location": "Eskilstuna",
            "occupation": "direktör",
            "birth_details": {
                "date": "20/10/1908",
                "place": "Eskilstuna",
                "parents": "NULL"
            },
            "education": null,
            "career": [
                {
                    "position": "anst ol föret grossistbransch",
                    "years": {
                        "start_year": 1923,
                        "end_year": 1945
                    },
                    "organization": "NULL"
                },
                {
                    "position": "kamr ab F A Stenmans iåsfabr",
                    "years": {
                        "start_year": 1945,
                        "end_year": 1959
                    },
                    "organization": "Eskilstuna"
                },
                {
                    "position": "verkst dlr",
                    "years": {
                        "start_year": 1959,
                        "end_year": null
                    },
                    "organization": "ab F A Stenmans iåsfabr Eskilstuna"
                }
            ],
            "family": {
                "spouse": "Astrid Öhman",
                "marriage_year": "1943",
                "children": [
                    {
                        "name": "Åke",
                        "birth_year": "1945"
                    },
                    {
                        "name": "Inga",
                        "birth_year": "1950"
                    }
                ]
            },
            "hobbies": [
                "musik",
                "sång"
            ]
        }
    }
}