{
    "original": "FREDBERGER, RAGNAR A,\ndomprost, Uppsala, f i Sthlm 21 /12/02 av\nfil dr Theodor Fredrikson o Ada\nHermanson.\n\nStud:ex Upps 21, teol kand o prästv 29,\npast:adj Upps 30, mil:past I 8 31-42,\npred Akad sjh 36-61, kommin Upps 39,\nkontr :prost o domprost där sed 62.\n-Led kyrkofullm 39-46, barnav:ndn\n39-62. - Medl Rotary. - Utm: LNO.\nGift 30 m Bothild Viken f 04. - Barn:\nAnders f 31, Ragnhild f 34, Gunilla f 36,\nGunnar f 43.\n\nFREDGA, ARNE, professor, Uppsala,\nf i Upps 18/7/02 av las :läk Carl F o\nElin Cassel.\n\nFil mag Upps 25, fil lic 29, fil dr o doc\ni kemi 35, prof i kemi (m\nundervisn:-skyldighet i organisk kemi) Upps sed\n39. - Ordf Upps stud:kår 32-33, stat\ngarantilånend 46-52, Kemiska sällsk\nUpps 39-51, led VA:s Nobelkomm f\nkemi sed 44, stat natur vetensk\nforskn:-råd 52-54, nät :komm f kemi 56-62, insp\nVärml nät 49-56 (hedL sed 39). - LVS\n42, LVA 43, LFS 61, LFinlVS 63, HedL\nBelgiska kem sällsk 62. - Skr: 120-tal\navh i org o hist kemi, art i ol ämnen,\nreferat m m. - Utm: KNO, VA:s\nLindbomska belön 37, Björkénska priset 53,\nCelsiusM 63.\n\nGift 31 m Brita Ohlin f 07, dtr t grossh\nIvan Ö o Märta Collijn. - Barn: Sven\nf 32, Karl f 34, Kerstin f 35, Märta f 39,\nBjörn f 44.\n\nFREDHOLM,   ERIK   O,   kyrkoherde,\n\nFrövi, f i Västerås 18/8/12 av fotograf\nO N F o Gerda Westenius.\nStud:ex Västerås 31, teol kand 36,\npast:adj Ljusnarsberg, v past Grythyttan, v\nkommin Ore, past:adj Orsa o kommin\nSöderbärke 40, kyrkoh Näsby-Ervalla\n50, Näsby sed 62. - Ordf kyrkofullm,\n\nDKSM   Örebro   l,   Näsby  hemb:fören,\n\nstyr :led Frövi nykterh:v samarb :komm\n\nm m, kårch Frövi scoutkår. - Medarb\n\nuppsl:verket Sv:es bebyggelse. - Hobby:\n\nresor.\n\nGift 39 m Margareta Sjöström. - Barn:\n\nHans o Gerda ff 40, Bengt f 43.\n\n",
    "structured": {
        "0": {
            "full_name": "Ragnar A. Fredberger",
            "location": "Uppsala",
            "occupation": "domprost",
            "birth_details": {
                "date": "21/12/1902",
                "place": "Stockholm"
            },
            "education": [
                {
                    "degree": "teol kand",
                    "year": "1929",
                    "institution": "Uppsala"
                }
            ],
            "career": [
                {
                    "position": "past:adj",
                    "years": {
                        "start_year": 1930,
                        "end_year": 1939
                    },
                    "organization": "Upps"
                },
                {
                    "position": "mil:past I",
                    "years": {
                        "start_year": 1931,
                        "end_year": 1942
                    },
                    "organization": "I 8"
                },
                {
                    "position": "pred Akad",
                    "years": {
                        "start_year": 1936,
                        "end_year": 1961
                    },
                    "organization": "sjh"
                },
                {
                    "position": "kommin",
                    "years": {
                        "start_year": 1939,
                        "end_year": null
                    },
                    "organization": "Upps"
                },
                {
                    "position": "kontr :prost o domprost",
                    "years": {
                        "start_year": 1962,
                        "end_year": null
                    },
                    "organization": "Upps"
                }
            ],
            "family": {
                "spouse": "Bothild Viken",
                "marriage_year": "1930",
                "children": [
                    {
                        "name": "Anders",
                        "birth_year": "1931"
                    },
                    {
                        "name": "Ragnhild",
                        "birth_year": "1934"
                    },
                    {
                        "name": "Gunilla",
                        "birth_year": "1936"
                    },
                    {
                        "name": "Gunnar",
                        "birth_year": "1943"
                    }
                ]
            }
        },
        "1": {
            "full_name": "Arne Fredga",
            "location": "Uppsala",
            "occupation": "professor",
            "birth_details": {
                "date": "18/07/1902",
                "place": "Uppsala"
            },
            "education": [
                {
                    "degree": "fil dr",
                    "year": "1935",
                    "institution": "Upps"
                }
            ],
            "career": [
                {
                    "position": "prof i kemi",
                    "years": {
                        "start_year": 1939,
                        "end_year": null
                    },
                    "organization": "Upps"
                }
            ],
            "family": {
                "spouse": "Brita Ohlin",
                "marriage_year": "1931",
                "children": [
                    {
                        "name": "Sven",
                        "birth_year": "1932"
                    },
                    {
                        "name": "Karl",
                        "birth_year": "1934"
                    },
                    {
                        "name": "Kerstin",
                        "birth_year": "1935"
                    },
                    {
                        "name": "Märta",
                        "birth_year": "1939"
                    },
                    {
                        "name": "Björn",
                        "birth_year": "1944"
                    }
                ]
            }
        },
        "2": {
            "full_name": "Erik O. Fredholm",
            "location": "Frövi",
            "occupation": "kyrkoherde",
            "birth_details": {
                "date": "18/08/1912",
                "place": "Västerås"
            },
            "education": [
                {
                    "degree": "teol kand",
                    "year": "1936",
                    "institution": "Västerås"
                }
            ],
            "career": [
                {
                    "position": "past:adj",
                    "years": {
                        "start_year": null,
                        "end_year": 1940
                    },
                    "organization": "Ljusnarsberg"
                },
                {
                    "position": "v past",
                    "years": {
                        "start_year": null,
                        "end_year": null
                    },
                    "organization": "Grythyttan"
                },
                {
                    "position": "v kommin",
                    "years": {
                        "start_year": null,
                        "end_year": null
                    },
                    "organization": "Ore"
                },
                {
                    "position": "past:adj",
                    "years": {
                        "start_year": null,
                        "end_year": null
                    },
                    "organization": "Orsa"
                },
                {
                    "position": "kommin",
                    "years": {
                        "start_year": null,
                        "end_year": 1940
                    },
                    "organization": "Söderbärke"
                },
                {
                    "position": "kyrkoh",
                    "years": {
                        "start_year": 1950,
                        "end_year": null
                    },
                    "organization": "Näsby-Ervalla"
                },
                {
                    "position": null,
                    "years": {
                        "start_year": 1962,
                        "end_year": null
                    },
                    "organization": "Näsby"
                }
            ],
            "family": {
                "spouse": "Margareta Sjöström",
                "marriage_year": "1939",
                "children": [
                    {
                        "name": "Hans",
                        "birth_year": null
                    },
                    {
                        "name": "Gerda",
                        "birth_year": "1940"
                    },
                    {
                        "name": "Bengt",
                        "birth_year": "1943"
                    }
                ]
            },
            "hobbies": [
                "resor"
            ]
        }
    }
}