{
    "original": "GUSTAVSSON, K RUNE,\nombudsman, riksdagsman, Alvesta, f i Skatelövs\nsn, Kronob l, 2/12/20 av lantbr Gustaf\nJohansson o Eva Andersson.\nGmg Grenslöfs lantbr :sk 42-43,\nSånga-Säby f ören :sk 45-46, DSI 61; omb :man\nRLF Kronob l sed 44. - AK (cp) sed\n58, led 2:a lagutsk sed 65 (suppl 58),\npensionsförsäkr:komm sed 63,\nfilmcen-surutredn sed 64; landst:man sed 54, led\nlandst undervisn:nd sed 64, soc:ndn\nAlvesta sed 63. - Medl Lions club. -\nHobbies: fotografering, hästar.\nGift 47 m Valborg Andersson f 24 d 53.\n- Barn: Marie-Louise f 49, Jan-Ingvar\nf 53.\n\nGUSTAFSSON, RUNE B,\nbyggnadsingenjör, Bottnaryd, f i Mjölby 28/8/20\nav byggm David G o Agnes Johansson.\nIng :ex GTI 46, ing Stellan Jakobsson\nGbg 46, Melker Andersson Linkpg 47,\nByggn :tekn byrån Jönkpg 50, eg\nkonsult verksamh sed 64.\nGift 53 m Signe Andersson f 23, dtr t\nsågv :arb Karl A o Ester Smedlund.\n-Barn: Anna f 55, Miaria f 57, Åsa f 60.\n\nGUSTAFSSON, K SVANTE, förste\nlänsassessor, Vänersborg, f i Skruv,\nKronob l, 12/12/01 av bruksäg Per G o\nSigrid Hammarlund.\n\nStud:ex Växjö 21, jur kand StHS 29,\ntingstjg Nås o Malungs doms 29-32, e\nlänsnot länsstyr Älvsb l 33, länsassess\n49, l:e länsassess där sed 53. -Omb:man\nSparbkn Vänersborg sed 56,\ntryckfrih:-omb 43, kronans omb Västg-Dals\nstads-hyp:fören o Västg-Dals bost:kreditfören\n58, led Vänernkomm 57-59, suppl\nVänerns seglationsstyr, ordf Älvsb l\nkon-junkturut jämn :f ond 60-61, Älvsb l f öret\n:-fören 62. - Ordf hyresnd V Tunhem sed\n43, Vänersborg 44-54. - Utm:\nHvftj-plakS, SkidlmG, SkyttemS,\nKulsprute-pistskmS.\n\nGift 39 m Brita Halldin f 17, dtr t\nverkm Hjalmar H o Nanny H. - Barn:\nBarbro f 41, Göran f 43, Birgitta f 47.\n\n",
    "structured": {
        "1": {
            "full_name": "GUSTAVSSON, K RUNE",
            "location": "Alvesta, Kronob l",
            "occupation": "ombudsman, riksdagsman",
            "birth_details": {
                "date": "02/12/1920",
                "place": "Skatelövs sn",
                "parents": "lantbr Gustaf Johansson and Eva Andersson"
            },
            "education": [
                {
                    "degree": "Gmg Grenslöfs lantbr",
                    "year": "1942",
                    "institution": "NULL"
                },
                {
                    "degree": "Sånga-Säby f ören",
                    "year": "1945",
                    "institution": "NULL"
                },
                {
                    "degree": "DSI",
                    "year": "1961",
                    "institution": "NULL"
                }
            ],
            "career": [
                {
                    "position": "omb",
                    "years": {
                        "start_year": 1944,
                        "end_year": 1961
                    },
                    "organization": "RLF Kronob l"
                }
            ],
            "family": {
                "spouse": "Valborg Andersson",
                "marriage_year": "1947",
                "children": [
                    {
                        "name": "Marie-Louise",
                        "birth_year": "1949"
                    },
                    {
                        "name": "Jan-Ingvar",
                        "birth_year": "1953"
                    }
                ]
            },
            "hobbies": [
                "fotografering",
                "hästar"
            ]
        },
        "2": {
            "full_name": "GUSTAFSSON, RUNE B",
            "location": "Bottnaryd",
            "occupation": "byggnadsingenjör",
            "birth_details": {
                "date": "28/08/1920",
                "place": "Mjölby",
                "parents": "byggm David G o Agnes Johansson"
            },
            "education": [
                {
                    "degree": "Ing :ex GTI",
                    "year": "1946",
                    "institution": "NULL"
                },
                {
                    "degree": "ing Stellan Jakobsson",
                    "year": "1946",
                    "institution": "NULL"
                },
                {
                    "degree": "Melker Andersson Linkpg",
                    "year": "1947",
                    "institution": "NULL"
                },
                {
                    "degree": "Byggn :tekn byrån Jönkpg",
                    "year": "1950",
                    "institution": "NULL"
                }
            ],
            "family": {
                "spouse": "Signe Andersson",
                "marriage_year": "1953",
                "children": [
                    {
                        "name": "Anna",
                        "birth_year": "1955"
                    },
                    {
                        "name": "Miaria",
                        "birth_year": "1957"
                    },
                    {
                        "name": "Åsa",
                        "birth_year": "1960"
                    }
                ]
            }
        },
        "3": {
            "full_name": "GUSTAFSSON, K SVANTE",
            "location": "Vänersborg",
            "occupation": "förste länsassessor",
            "birth_details": {
                "date": "12/12/1901",
                "place": "Skruv, Kronob l",
                "parents": "bruksäg Per G o Sigrid Hammarlund"
            },
            "education": [
                {
                    "degree": "Stud:ex Växjö",
                    "year": "1921",
                    "institution": "NULL"
                },
                {
                    "degree": "jur kand StHS",
                    "year": "1929",
                    "institution": "NULL"
                }
            ],
            "career": [
                {
                    "position": "tingstjg Nås o Malungs doms",
                    "years": {
                        "start_year": 1929,
                        "end_year": 1932
                    },
                    "organization": "NULL"
                },
                {
                    "position": "e länsnot länsstyr Älvsb l",
                    "years": {
                        "start_year": 1933,
                        "end_year": 1949
                    },
                    "organization": "NULL"
                },
                {
                    "position": "länsassess",
                    "years": {
                        "start_year": 1949,
                        "end_year": 1953
                    },
                    "organization": "NULL"
                }
            ],
            "family": {
                "spouse": "Brita Halldin",
                "marriage_year": "1939",
                "children": [
                    {
                        "name": "Barbro",
                        "birth_year": "1941"
                    },
                    {
                        "name": "Göran",
                        "birth_year": "1943"
                    },
                    {
                        "name": "Birgitta",
                        "birth_year": "1947"
                    }
                ]
            },
            "honorary_titles": [
                {
                    "title": "Hvftj-plakS",
                    "institution": "NULL",
                    "year": "NULL"
                },
                {
                    "title": "SkidlmG",
                    "institution": "NULL",
                    "year": "NULL"
                },
                {
                    "title": "SkyttemS",
                    "institution": "NULL",
                    "year": "NULL"
                },
                {
                    "title": "Kulsprute-pistskmS",
                    "institution": "NULL",
                    "year": "NULL"
                }
            ]
        }
    }
}