{
    "original": "GRANDIN, EMK G, tandläkare,\nValdemarsvik, f i Norrkpg 21/2/03 av\nstat:-insp Carl G o Olga Stenberg.\nStud:ex Skövde 21, tandl:ex Sthlm 25,\npriv:prakt Valdemarsvik sed 25. - Medl\nOdd Fellow, FrimO.\nGift 41  m Brita Gabrielsson f 20, dtr\nt kamr Henning G o Signe Pettersson.\n-Barn: Stellan f 43, Ulf f 47.\n\nGRANDIN,  K LENNART, ingenjör,\n\nGbg, f i Spånga 14/10/20 av Karl G o\nMaria Andersson.\n\nIng :ex STI 40, off :ex pansartrupp 43,\nReklamfören Gbg 46. - Tidstud:ing\nUlvsunda gummifabr 41, kontr:- o\nverkst:ing arméförv 43, serviceing ab Volvo\nGbg 45, verkst:ch ab Bil o Truck 47,\ninneh Esso servicestn Kungsportsbron\nGbg (Sv:es äldsta bensinstn) sed 54.\n-Led Sv bensinhandl riksförb, ordf dess\nGbgskrets sed 61. - Medl Lions club\n(presid 64-65). - Utm: SMKftjt. -\nHobbies: motorsport, hästsport.\nGift 43 m Ingegärd Sjösten f 21, dtr t\nCarl S o Olga S. - Barn: Monica f 46,\nLars f 51.\n\nGRANDINSON, BROR A,\ncivilingenjör, överingenjör, Gbg, f i Västerås 16/3/\n02 av bankdir Valdemar G o Anne\nMar-garethe Gagge.\n\nStud:ex Sthlm 20, KTH 25, stud USA\n26-28, konstr Munktells 28, Hesselman\nMotor Corp 31, ab Volvo 36, inköpare\no tf inköpsch där 37, planer:- o inköpsch\nSv flygmotor ab 43, ass tekn ch ab\nVolvo 45, tf personalch där 52, övering o ch\navd f tekn information sed 55. - Styr :led\nTekn litt :samf o ordf dess lokalavd Gbg\nsed 61. - Hobbies: fjällvandr, snickeri,\nfilateli.\n\nGift 31 m Gull Velander, dtr t prof\nSten V o Lisa Fjällbäck. - Barn: Åke,\nAnn Mari, Bertil, Jens.\n\n",
    "structured": {
        "1": {
            "full_name": "Emk G Grandin",
            "location": "Valdemarsvik",
            "occupation": "Tandläkare",
            "birth_details": {
                "date": "21/02/1903",
                "place": "Norrköping"
            },
            "education": [
                {
                    "degree": "Stud:ex",
                    "year": "1921",
                    "institution": "Skövde"
                },
                {
                    "degree": "Tandl:ex",
                    "year": "1925",
                    "institution": "Sthlm"
                }
            ],
            "career": [
                {
                    "position": "Priv:prakt",
                    "years": {
                        "start_year": 1925,
                        "end_year": null
                    },
                    "organization": "Valdemarsvik"
                }
            ],
            "family": {
                "spouse": "Brita Gabrielsson",
                "marriage_year": "1941",
                "children": [
                    {
                        "name": "Stellan",
                        "birth_year": "1943"
                    },
                    {
                        "name": "Ulf",
                        "birth_year": "1947"
                    }
                ]
            }
        },
        "2": {
            "full_name": "K Lennart Grandin",
            "location": "Gbg",
            "occupation": "Ingenjör",
            "birth_details": {
                "date": "14/10/1920",
                "place": "Spånga"
            },
            "education": [
                {
                    "degree": "Ing :ex",
                    "year": "1940",
                    "institution": "STI"
                },
                {
                    "degree": "Off :ex pansartrupp",
                    "year": "1943",
                    "institution": null
                }
            ],
            "career": [
                {
                    "position": "Inneh Esso servicestn Kungsportsbron",
                    "years": {
                        "start_year": 1954,
                        "end_year": null
                    },
                    "organization": "Gbg"
                }
            ],
            "family": {
                "spouse": "Ingegärd Sjösten",
                "marriage_year": "1943",
                "children": [
                    {
                        "name": "Monica",
                        "birth_year": "1946"
                    },
                    {
                        "name": "Lars",
                        "birth_year": "1951"
                    }
                ]
            },
            "hobbies": [
                "Motorsport",
                "Hästsport"
            ]
        },
        "3": {
            "full_name": "Bror A Grandinson",
            "location": "Gbg",
            "occupation": "Civilingenjör, överingenjör",
            "birth_details": {
                "date": "16/03/1902",
                "place": "Västerås"
            },
            "education": [
                {
                    "degree": "Stud:ex",
                    "year": "1920",
                    "institution": "Sthlm"
                },
                {
                    "degree": null,
                    "year": null,
                    "institution": "USA"
                }
            ],
            "career": [
                {
                    "position": "Övering o ch avd f tekn information",
                    "years": {
                        "start_year": 1955,
                        "end_year": null
                    },
                    "organization": null
                }
            ],
            "family": {
                "spouse": "Gull Velander",
                "marriage_year": "1931",
                "children": [
                    {
                        "name": "Åke",
                        "birth_year": null
                    },
                    {
                        "name": "Ann Mari",
                        "birth_year": null
                    },
                    {
                        "name": "Bertil",
                        "birth_year": null
                    },
                    {
                        "name": "Jens",
                        "birth_year": null
                    }
                ]
            },
            "hobbies": [
                "Fjällvandr",
                "Snickeri",
                "Filateli"
            ]
        }
    }
}