{
    "original": "GRUNDITZ, S ÅKE, advokat,\nJönköping, f i Hjo 25/2/24 av nämndeman\nOscar Johansson o Astrid Grunditz.\nStud:ex Skara 44, jur kand Upps 49,\ntingstjg N Roslags doms 49-52, bitr\njurist h adv H Lidén Oskarshamn 52 o\nadv B Skantze Jönkpg sed 56. - Ordf ab\nJönkpgs bostäder sed 59, led idr:ndn.\n-Medl FrimO, SHT, PB. - Hobbies: sport,\nfilateli, numismatik, trädgårdsskötsel.\nGift 50 m Sylwa Kullberg f 26, dtr t\ndisp Hjalmar K o Ewa Gustafsson.\n-Barn: Ewa f 51, Lena f 52, Maria f 57,\nKarin f 61.\n\nGRUNDSTRÖM, INGEGERD E,\nförste länsnotarie, Växjö, f i Örnsköldsvik\n1/3/29 av prov:läk Helmer Niklasson o\nInga Wiberg.\n\nStud:ex Eslöv 49, jur kand Lund 54, e\nlänsnot Kronob l 57, tax:insp 58, l:e\nlänsnot där sed 62. - Ordf tax:nd 57-59,\n61-62.\n\nGift 59-63 m lekt Sven Grundström\nf 07. - Barn: Marie f 60.\n\nGRUNDSTRÖM, SVEN, lektor,\nKalmar, f i Karlskoga 2/9/07 av bruksdisp\nAlexis G o Sigrid Dahl.\nStud:ex Örebro 26, folkskollär :ex Växjö\n32, fil kand 36, fil lic 47 o fil mag Lund\n54; folkskollär Lund, Malmö m fi 32-37,\nämneslär Malmö o öl folkhögsk 37-39,\naman arb :led :inst Sv:es ind :förb 41,\nSv:es lantbr :förb 44, bitr sekr Norrb l\nnäringsutredn 46-47, vik lekt folksk:sem\nLund o Kristianstad 51, provar\nflick-lärov Malmö 55, eo adj komm flicksk\nMalmö 56, vik lekt folksk:sem Sthlm\n57, lekt i hist o geogr hal Kalmar sed\n60. - Konsult i lokaliser:ärenden f\nkommuner i Östergötl. - Utredn :man 42 års\njordbr:komm 44-46, småbruksutredn 54.\n- Delt i geogr exp t Sicilien 49. - Löjtn\ning:tr res 36. - Skr: art i kulturgeogr,\nnäringsekon, transp:polit, lokaliseringsfr\no utr:polit ämn i dags- o fackpr 50-64,\ngeogr art i Sv Uppslagsbok 50-54, red\nArbeitsledningsrevy 42-44. - Hobbies:\nantikviteter, naturvård, frisksport.\nGift 59-63 m l:e länsnot Ingegerd\nNiklasson f 29, dtr t prov:läk Helmer N o\nInga Wiberg. - Barn: Marie f 60.\n\n",
    "structured": {
        "0": {
            "full_name": "Grunditz, S Åke",
            "location": "Jönköping",
            "occupation": "advokat",
            "birth_details": {
                "date": "25/02/1924",
                "place": "Hjo",
                "parents": "Oscar Johansson o Astrid Grunditz"
            },
            "education": [
                {
                    "degree": "Stud:ex",
                    "year": "1944",
                    "institution": "Skara"
                },
                {
                    "degree": "jur kand",
                    "year": "1949",
                    "institution": "Upps"
                }
            ],
            "career": [
                {
                    "position": "tingstjg",
                    "years": {
                        "start_year": 1949,
                        "end_year": 1952
                    },
                    "organization": "N Roslags doms"
                },
                {
                    "position": "bitr jurist",
                    "years": {
                        "start_year": 1952,
                        "end_year": 1956
                    },
                    "organization": "H Lidén Oskarshamn"
                },
                {
                    "position": "adv",
                    "years": {
                        "start_year": 1956
                    },
                    "organization": "B Skantze Jönkpg"
                }
            ],
            "family": {
                "spouse": "Sylwa Kullberg",
                "marriage_year": "1950",
                "children": [
                    {
                        "name": "Ewa",
                        "birth_year": "1951"
                    },
                    {
                        "name": "Lena",
                        "birth_year": "1952"
                    },
                    {
                        "name": "Maria",
                        "birth_year": "1957"
                    },
                    {
                        "name": "Karin",
                        "birth_year": "1961"
                    }
                ]
            }
        },
        "1": {
            "full_name": "Grundström, Ingegerd E",
            "location": "Växjö",
            "occupation": "förste länsnotarie",
            "birth_details": {
                "date": "01/03/1929",
                "place": "Örnsköldsvik",
                "parents": "prov:läk Helmer Niklasson o Inga Wiberg"
            },
            "education": [
                {
                    "degree": "Stud:ex",
                    "year": "1949",
                    "institution": "Eslöv"
                },
                {
                    "degree": "jur kand",
                    "year": "1954",
                    "institution": "Lund"
                }
            ],
            "career": [
                {
                    "position": "e länsnot",
                    "years": {
                        "start_year": 1957
                    },
                    "organization": "Kronob l"
                },
                {
                    "position": "tax:insp",
                    "years": {
                        "start_year": 1958
                    }
                },
                {
                    "position": "l:e länsnot",
                    "years": {
                        "start_year": 1962
                    }
                }
            ],
            "family": {
                "spouse": "lekt Sven Grundström",
                "marriage_year": "1959",
                "children": [
                    {
                        "name": "Marie",
                        "birth_year": "1960"
                    }
                ]
            }
        },
        "2": {
            "full_name": "Grundström, Sven",
            "location": "Kalmar",
            "occupation": "lektor",
            "birth_details": {
                "date": "02/09/1907",
                "place": "Karlskoga",
                "parents": "bruksdisp Alexis G o Sigrid Dahl"
            },
            "education": [
                {
                    "degree": "Stud:ex",
                    "year": "1926",
                    "institution": "Örebro"
                },
                {
                    "degree": "folkskollär :ex",
                    "year": "1932",
                    "institution": "Växjö"
                },
                {
                    "degree": "fil kand",
                    "year": "1936",
                    "institution": "Lund"
                },
                {
                    "degree": "fil lic",
                    "year": "1947",
                    "institution": "Lund"
                }
            ],
            "career": [
                {
                    "position": "folkskollär",
                    "years": {
                        "start_year": 1932,
                        "end_year": 1937
                    },
                    "organization": "Malmö"
                },
                {
                    "position": "ämneslär",
                    "years": {
                        "start_year": 1937,
                        "end_year": 1939
                    },
                    "organization": "Malmö o öl folkhögsk"
                },
                {
                    "position": "bitr sekr",
                    "years": {
                        "start_year": 1946,
                        "end_year": 1947
                    },
                    "organization": "Norrb l näringsutredn"
                },
                {
                    "position": "lekt i hist o geogr",
                    "years": {
                        "start_year": 1960
                    },
                    "organization": "Kalmar"
                }
            ],
            "family": {
                "spouse": "l:e länsnot Ingegerd Niklasson",
                "marriage_year": "1959",
                "children": [
                    {
                        "name": "Marie",
                        "birth_year": "1960"
                    }
                ]
            }
        }
    }
}