{
    "original": "GÖRANSSON, KJELL, tandläkare,\nSkövde, f i Raus, Malmöh l, 11/7/24 av\nköpm Sigfrid G o Anna Nilsson.\nStud:ex 43, schweizisk tandl:ex 52 o dr\nmed dent 53, tandl:ex Malmö 60,\nskol-tandl Bern, Schweiz, tandl folktandv\nHuskvarna, l :e skoltandl Skövde sed 60.\n- Skr i farmakologi.\n\nGift 53 m Evelyne Trög f 32, dtr t\ndisp E T o Paulette Feberth (Schweiz).\n-Barn: Patrick f 56.\n\nGÖRANSSON, B PAUL A, tandläkare,\nGbg, f i Gbg 19/11/07 av tillskär\nAnders G o Marie Greiller.\nStud:ex Gbg 27, tandl:ex Sthlm 32, Dr\nof Dental Surgery Northwestern Univ,\nChicago, USA, 47, tandl folktandv Gbg\n32, priv:prakt Gbg sed 33, skoltandl\nGbg 33, lär Stat tandtekn:sk Gbg sed\n48. - Ordf Gbgs tandl:sällsk stud:nd\n51-55, Gbgs tandl:sällsk 56-58, presid Amer\nDental Soc of Sweden sed 64, of Europé\nsed 65. - Skr i protetik o\nbettrekonstruktion.\n\nGift 44 m Kerstin Sjöstedt f 23. - Barn:\nAnders f 45, Elisabeth f 47, Bengt f 49.\n\nGÖRANSSON, PEHR-GUNNAR H,\ndisponent, Norrköping, f i Malmö 14/9/\n20 av l:e stat:skriv Pehr-Gottfrid G o\nThea Bergqvist.\n\nMalmö hdlsgymn 39, DHG 43; försälj\nLME 41, avd :ch Esselte kartonnage Gbg\n43, Esselte-förpackn Malmö 49,\nmarkn:-ch Esseltepac ab Norrkpg sed 60.\n-Hobbies: jakt, segling.\nGift 45 m Stina Johansson f 26, dtr t\n\nköpm J E J o Karin Pettersson. - Barn:\nAnders f 47, Stefan f 50, Jan f 52.\n\nGÖRANSSON,   SVEN  E,   disponent,\nSävsjö, f i Kvidinge, Kristianst l, 14/11/\n22 av Göran Jönsson o Astrid Meisner.\nHbgs   hdlsgymn   42,  Härnösands  tekn\nskogs- o sågv:sk 45, verkst dir ab\nLig-nitverken Sävsjö sed 46. - Res:off:ex 45,\nkapt trängtr res 59. - Medl Rotary.\nGift 47 m Svea Larsson f 21, dtr t\nsjh:-intend J W L o Signe Brewitz. - Barn:\nBoel f 53, Eric f 59.\n\n",
    "structured": {
        "0": {
            "full_name": "Kjell Göransson",
            "location": "Skövde",
            "occupation": "Tandläkare",
            "birth_details": {
                "date": "11/07/1924",
                "place": "Raus, Malmöh l",
                "parents": "köpm Sigfrid G o Anna Nilsson"
            },
            "education": [
                {
                    "degree": "Stud:ex",
                    "year": "1943",
                    "institution": "NULL"
                },
                {
                    "degree": "Schweizisk tandl:ex",
                    "year": "1952",
                    "institution": "NULL"
                },
                {
                    "degree": "Dr med dent",
                    "year": "1953",
                    "institution": "NULL"
                }
            ],
            "career": [
                {
                    "position": "Tandläkare",
                    "years": {
                        "start_year": 1960,
                        "end_year": 1960
                    },
                    "organization": "folktandv Huskvarna"
                },
                {
                    "position": "l :e skoltandl",
                    "years": {
                        "start_year": 1960,
                        "end_year": 1960
                    },
                    "organization": "Skövde"
                }
            ],
            "family": {
                "spouse": "Evelyne Trög",
                "marriage_year": "1953",
                "children": [
                    {
                        "name": "Patrick",
                        "birth_year": "1956"
                    }
                ]
            }
        },
        "1": {
            "full_name": "Paul A Göransson",
            "location": "Gbg",
            "occupation": "Tandläkare",
            "birth_details": {
                "date": "19/11/1907",
                "place": "Gbg",
                "parents": "tillskär Anders G o Marie Greiller"
            },
            "education": [
                {
                    "degree": "Stud:ex",
                    "year": "1927",
                    "institution": "Gbg"
                },
                {
                    "degree": "Dr of Dental Surgery",
                    "year": "1947",
                    "institution": "Northwestern Univ, Chicago, USA"
                }
            ],
            "career": [
                {
                    "position": "tandl folktandv",
                    "years": {
                        "start_year": 1932,
                        "end_year": 1932
                    },
                    "organization": "Gbg"
                },
                {
                    "position": "priv:prakt",
                    "years": {
                        "start_year": 1933,
                        "end_year": 1933
                    },
                    "organization": "Gbg"
                },
                {
                    "position": "skoltandl",
                    "years": {
                        "start_year": 1933,
                        "end_year": 1933
                    },
                    "organization": "Gbg"
                },
                {
                    "position": "lär",
                    "years": {
                        "start_year": 1948,
                        "end_year": 1948
                    },
                    "organization": "Stat tandtekn:sk Gbg"
                }
            ],
            "family": {
                "spouse": "Kerstin Sjöstedt",
                "marriage_year": "1944",
                "children": [
                    {
                        "name": "Anders",
                        "birth_year": "1945"
                    },
                    {
                        "name": "Elisabeth",
                        "birth_year": "1947"
                    },
                    {
                        "name": "Bengt",
                        "birth_year": "1949"
                    }
                ]
            }
        },
        "2": {
            "full_name": "Pehr-Gunnar H Göransson",
            "location": "Norrköping",
            "occupation": "Disponent",
            "birth_details": {
                "date": "14/09/1920",
                "place": "Malmö",
                "parents": "l:e stat:skriv Pehr-Gottfrid G o Thea Bergqvist"
            },
            "education": [
                {
                    "degree": "Malmö hdlsgymn",
                    "year": "1939",
                    "institution": "NULL"
                },
                {
                    "degree": "DHG",
                    "year": "1943",
                    "institution": "NULL"
                }
            ],
            "career": [
                {
                    "position": "markn:-ch",
                    "years": {
                        "start_year": 1960,
                        "end_year": 1960
                    },
                    "organization": "Esseltepac ab Norrkpg"
                }
            ],
            "family": {
                "spouse": "Stina Johansson",
                "marriage_year": "1945",
                "children": [
                    {
                        "name": "Anders",
                        "birth_year": "1947"
                    },
                    {
                        "name": "Stefan",
                        "birth_year": "1950"
                    },
                    {
                        "name": "Jan",
                        "birth_year": "1952"
                    }
                ]
            },
            "hobbies": [
                "jakt",
                "segling"
            ]
        },
        "3": {
            "full_name": "Sven E Göransson",
            "location": "Sävsjö",
            "occupation": "Disponent",
            "birth_details": {
                "date": "14/11/1922",
                "place": "Kvidinge, Kristianst l",
                "parents": "Göran Jönsson o Astrid Meisner"
            },
            "education": [
                {
                    "degree": "Hbgs hdlsgymn",
                    "year": "1942",
                    "institution": "NULL"
                },
                {
                    "degree": "Härnösands tekn skogs- o sågv:sk",
                    "year": "1945",
                    "institution": "NULL"
                }
            ],
            "career": [
                {
                    "position": "verkst dir",
                    "years": {
                        "start_year": 1946,
                        "end_year": 1946
                    },
                    "organization": "ab Lignitverken Sävsjö"
                }
            ],
            "family": {
                "spouse": "Svea Larsson",
                "marriage_year": "1947",
                "children": [
                    {
                        "name": "Boel",
                        "birth_year": "1953"
                    },
                    {
                        "name": "Eric",
                        "birth_year": "1959"
                    }
                ]
            },
            "community_involvement": [
                {
                    "role": "Medl",
                    "organization": "Rotary",
                    "years": "NULL"
                }
            ]
        }
    }
}