{
    "original": "Eldh, Carl Johan, bildhuggare,\nprofessor, Sthlm, f. i Film, Upps. L, 10/57\n73. G. 15 m. Elise Persson. Stud. v.\nTekn. sk. i Sthlm, ornamentsbildh, v.\nrestaur. av Upps. domkyrka, i Paris 95,\nelev av Injalbert o. stud. anatomi i\nÉcole des Beaux-Arts, erh. prof. namn\n36. Medl. av Sthlms skönhetsråd.\nKV02kl, RNO, LFrKA.\nElde, Karl Hilmer, komminister,\nÄngby, f. 6/3/89 i Åby, Kalm. 1. G. 20 m.\nMaj Jonsson. Barn: Gunnar Valdemar,\nf. 21, Kerstin Maria, f. 23, Birgitta\nMaria, f. 28, Torsten Ingemar, f. 32,\nStig Ansgar, f. 33, Bengt Christoffer,\nf. 39. Stud:ex. i Upps. 13, teol. fil.\nex. 16, teol. kand. 19, prakt. teol. prov\n19. Prästv. f. Luleå stift 19,\nkontr:-adj. i Lappmarkens 3:e kontr. 19, t. f.\nkomm. i Vitträsk 19, l :e komm. i\nNordmaling 25, kyrkoh. i Resele 30, komm.\ni Bromma 36.\nElfroos, Gustaf Albin, direktör,\nSthlm, f. 10/12/78 i Åseda förs.,\nKronob. 1., av häradsdom. Wilh. Nilsson\no. Gustava Nilsén. G. 04 m. Jenny\nIsaksson. Anst. o. prakt, i Engl. 98-99,\nanst. v. Jönköp. Jurid. Byrå 00-02,\nsta-tionsskr. v. Växjö-Västervik järnv.\n02-09, verkst, dir. i AB Flora Automaten\ni Sthlm 10-19, ag. av fastigheter i\nSthlm, Köpenh. o. Berlin 19-23.\nInit:-tag. o. medl. av Fören. Bivacken, medl.\nav Odd Fellow o. 1878 års män m. fi.\nHobby: Resor.\nElfstrand, Daniel, läroboksförfattare,\nf. d. lärare, Djursholms-ösby, f. i\növergran, Upps. L, 6/3/58 av possess. Vilh.\nE. o. Carolina Utterström. G. 1. 90 m.\nOlga Elfstrand, d. 94, 2. 07 m. Olga\nFischer, 3. 18 m. Gerda Hedman, d. 41.\nFil. kand. Upps. 88, ord. lär. v. Gävle\nborgarsk. 91-23. Skr.: Fem års\nerfarenhet m. den imitat. metoden (föredr.\nv. 7:de nord. skolm. i Sthlm 95),\nTjugufem års erfarenh. m. d. indukt.-imit.\nmetoden (Mod. spr. 15), Ön the\nPhone-tic Alphabet (ib. 17), Språkunderv. (ib.\n20), Ön English Intonation (ib. 23), The\nRationalization of Mod. Foreign Lang.\nTeaching in Schools (ib. 33), utg. fi.\neng. läro- o. läseb. RNO.\n",
    "structured": {
        "1": {
            "full_name": "Eldh, Carl Johan",
            "occupation": "bildhuggare, professor",
            "location": "Sthlm",
            "birth_details": {
                "date": "10/05/1857",
                "place": "Film, Uppsala Län"
            },
            "education": [
                {
                    "degree": "Stud. v.",
                    "year": "Paris 1895",
                    "institution": "Tekn. sk. i Sthlm"
                }
            ],
            "career": [
                {
                    "position": "ornamentsbildh",
                    "years": {
                        "start_year": 1895,
                        "end_year": 1936
                    },
                    "organization": "restaur. av Upps. domkyrka"
                },
                {
                    "position": "elev av Injalbert o. stud. anatomi",
                    "years": {
                        "start_year": 1895,
                        "end_year": null
                    },
                    "organization": "École des Beaux-Arts"
                }
            ],
            "family": {
                "spouse": "Elise Persson",
                "marriage_year": "15",
                "children": []
            }
        },
        "2": {
            "full_name": "Elde, Karl Hilmer",
            "occupation": "komminister",
            "location": "Ängby",
            "birth_details": {
                "date": "06/03/1889",
                "place": "Åby, Kalmar Län"
            },
            "education": [
                {
                    "degree": "Stud:ex.",
                    "year": "1913",
                    "institution": "Uppsala"
                },
                {
                    "degree": "teol. fil. ex.",
                    "year": "1916",
                    "institution": null
                },
                {
                    "degree": "teol. kand.",
                    "year": "1919",
                    "institution": null
                }
            ],
            "career": [
                {
                    "position": "kontr:-adj.",
                    "years": {
                        "start_year": 1919,
                        "end_year": null
                    },
                    "organization": "Lappmarkens 3:e kontr."
                },
                {
                    "position": "t. f. komm.",
                    "years": {
                        "start_year": 1919,
                        "end_year": null
                    },
                    "organization": "Vitträsk"
                },
                {
                    "position": "l :e komm.",
                    "years": {
                        "start_year": 1925,
                        "end_year": null
                    },
                    "organization": "Nordmaling"
                },
                {
                    "position": "kyrkoh.",
                    "years": {
                        "start_year": 1930,
                        "end_year": null
                    },
                    "organization": "Resele"
                },
                {
                    "position": "komm.",
                    "years": {
                        "start_year": 1936,
                        "end_year": null
                    },
                    "organization": "Bromma"
                }
            ],
            "family": {
                "spouse": "Maj Jonsson",
                "marriage_year": "20",
                "children": [
                    {
                        "name": "Gunnar Valdemar",
                        "birth_year": "21"
                    },
                    {
                        "name": "Kerstin Maria",
                        "birth_year": "23"
                    },
                    {
                        "name": "Birgitta Maria",
                        "birth_year": "28"
                    },
                    {
                        "name": "Torsten Ingemar",
                        "birth_year": "32"
                    },
                    {
                        "name": "Stig Ansgar",
                        "birth_year": "33"
                    },
                    {
                        "name": "Bengt Christoffer",
                        "birth_year": "39"
                    }
                ]
            }
        },
        "3": {
            "full_name": "Elfroos, Gustaf Albin",
            "occupation": "direktör",
            "location": "Sthlm",
            "birth_details": {
                "date": "10/12/1878",
                "place": "Åseda förs., Kronob. län"
            },
            "career": [
                {
                    "position": "stationsskr.",
                    "years": {
                        "start_year": 1902,
                        "end_year": 1909
                    },
                    "organization": "Växjö-Västervik järnv."
                },
                {
                    "position": "verkst, dir.",
                    "years": {
                        "start_year": 1910,
                        "end_year": 1919
                    },
                    "organization": "AB Flora Automaten i Sthlm"
                }
            ],
            "family": {
                "spouse": "Jenny Isaksson",
                "marriage_year": "04",
                "children": []
            },
            "hobbies": [
                "Resor"
            ]
        },
        "4": {
            "full_name": "Elfstrand, Daniel",
            "occupation": "läroboksförfattare, f. d. lärare",
            "location": "Djursholms-ösby",
            "birth_details": {
                "date": "06/03/1858",
                "place": "Övergran, Uppsala Län"
            },
            "education": [
                {
                    "degree": "Fil. kand.",
                    "year": "1888",
                    "institution": "Uppsala"
                }
            ],
            "career": [
                {
                    "position": "ord. lär.",
                    "years": {
                        "start_year": 1891,
                        "end_year": 1923
                    },
                    "organization": "Gävleborgarsk."
                }
            ],
            "family": {
                "spouse": "Olga Elfstrand",
                "marriage_year": "90",
                "children": []
            },
            "publications": [
                {
                    "title": "Fem års erfarenhet m. den imitat. metoden (föredr. v. 7:de nord. skolm. i Sthlm 95)",
                    "year": null,
                    "type": null
                },
                {
                    "title": "Tjugufem års erfarenh. m. d. indukt.-imit. metoden (Mod. spr. 15)",
                    "year": null,
                    "type": null
                },
                {
                    "title": "Ön the\nPhone-tic Alphabet (ib. 17)",
                    "year": null,
                    "type": null
                },
                {
                    "title": "Språkunderv. (ib. 20)",
                    "year": null,
                    "type": null
                },
                {
                    "title": "Ön English Intonation (ib. 23)",
                    "year": null,
                    "type": null
                },
                {
                    "title": "The Rationalization of Mod. Foreign Lang. Teaching in Schools (ib. 33)",
                    "year": null,
                    "type": null
                }
            ],
            "hobbies": [
                "Resor"
            ]
        }
    }
}