{
    "original": "FRÖBERG,  K  NILS  E,\ngeneralkonsul,   Lidingö,   f   i   Asker,   Örebro   l,\n17/5/95  av  Karl  F  o   Augusta\nHermansson.\nStud:ex Sthlm 15, HHS 17, stud Schweiz\n\no Frankr, agenturverksamh Alger,\nCasablanca o Marseille, sv gen-.konsul\nTanger 22.\nFRÖBERG,   PAUL   J, fil dr, lektor,\n\nSthlm, f i Femsjö, Jönkpgs l, 17/5/99\nav handelsres Sven F o Ida Johansson.\nStudrex Uddevalla 19, fil mag Gbg\n23, fil lic Sthlm 33, fil dr 43. - Medl\nred Bohus Posten 19, ass Inst f\nortsnamns- o dialektforskn GbgHS 20-23, lär\nRonneby 23, Skövde 24, medl red\nBonniers konv:lex 25-29, provar Norra\nlatinlärov Sthlm 29, lär Kungsh lärov\n30-34, adj Norra latinlärov 34, lektor i\nmodersmål o historia hal Enskede sed 48.\n\n-  Sekr Modersmåislär fören Sthlm 37-44.\n\n-    Skr:   Smärtans   o   kärlekens\nkavaljer, Från C W Bottigers ungdom (30),\nSkalden Böttiger, Studier i svensk\nsenromantik  (drsavh  43),  J  L  Runeberg.\nFänrik Ståls sägner. Urval, inledning o\nkommentarer (tills m fil dr Daniel\nAn-drese   57),   Malla\nMontgomery-Silfver-stolpe. Memoarer. I urval o   med\ninledning (60), Stil. Översikt av\nspråkutveckling,   stilarter,   diktarter   o   versformer\n(2:a utök uppl 61), art o upps i dagspress\n\n0  tidskr. - Utm: RNO. - Hobbies: resor,\nförfattarskap.\n\nGift 26 m Dagny Larsson f 96, dtr t\nrektor Robert L o h h. - Barn: Dag\nf 33, Ubbe f 35, Gudmund f 36.\n\nFRÖDIN, A HENRY, prakt läkare,\nBromma, f i Sthlm 10/7/13 av ing\nEmil F o Elisabet Arndtz.\nStudrex 31, med kand 34, med lic 38,\ne läk Vadstena o Västerhaninge distr\n38, tf underläk med avd S:t Görans\nsjh 39 o 42, Garphytte sanat 39, med\navd Sthlms garn:sjh 40, med avd Ersta\nsjh 42, röntgenavd S:t Görans sjh 43,\ne läk pediatr klin Akad sjh, Norrtulls\nsjh, Västerås las 44-45, Sthlms\nepid:-sjh 46, underläk barnavd Karlstads las\n45-48, tf las:läk 49, prakt barnläk\nBromma sed 49. - Skolläk Bromma o\nVällingby.\n\n•Gift 40 m Inga Smith f 15, dtr t dir\nCarl S o Ada Nyman’. - Barn: Gösta\nf 43, Thomas f 46, Jan-Erik f 52.\n\n",
    "structured": {
        "0": {
            "full_name": "Fröberg, K Nils E",
            "location": "Lidingö",
            "occupation": "Generalkonsul",
            "birth_details": {
                "date": "17/05/1895",
                "place": "Asker, Örebro l",
                "parents": "Karl F o Augusta Hermansson"
            },
            "education": [
                {
                    "degree": "Stud:ex",
                    "year": "1915",
                    "institution": "Sthlm"
                },
                {
                    "degree": "HHS",
                    "year": "1917",
                    "institution": "NULL"
                }
            ],
            "career": [
                {
                    "position": "Agenturverksamh",
                    "years": {
                        "start_year": 1922,
                        "end_year": 1922
                    },
                    "organization": "Alger, Casablanca o Marseille"
                },
                {
                    "position": "Sv gen-.konsul",
                    "years": {
                        "start_year": 1922,
                        "end_year": 1922
                    },
                    "organization": "Tanger"
                }
            ],
            "family": {
                "spouse": "NULL",
                "marriage_year": "NULL",
                "children": []
            }
        },
        "1": {
            "full_name": "Fröberg, Paul J",
            "location": "Sthlm",
            "occupation": "Fil dr, lektor",
            "birth_details": {
                "date": "17/05/1899",
                "place": "Femsjö, Jönkpgs l",
                "parents": "Sven F o Ida Johansson"
            },
            "education": [
                {
                    "degree": "Studrex",
                    "year": "1919",
                    "institution": "Uddevalla"
                },
                {
                    "degree": "Fil mag",
                    "year": "1923",
                    "institution": "Gbg"
                },
                {
                    "degree": "Fil lic",
                    "year": "1933",
                    "institution": "Sthlm"
                },
                {
                    "degree": "Fil dr",
                    "year": "1943",
                    "institution": "NULL"
                }
            ],
            "career": [
                {
                    "position": "Ass Inst f ortsnamns- o dialektforskn",
                    "years": {
                        "start_year": 1920,
                        "end_year": 1923
                    },
                    "organization": "GbgHS"
                },
                {
                    "position": "Lär",
                    "years": {
                        "start_year": 1923,
                        "end_year": 1923
                    },
                    "organization": "Ronneby"
                },
                {
                    "position": "Lär",
                    "years": {
                        "start_year": 1924,
                        "end_year": 1924
                    },
                    "organization": "Skövde"
                },
                {
                    "position": "Provar",
                    "years": {
                        "start_year": 1929,
                        "end_year": 1929
                    },
                    "organization": "Norra latinlärov Sthlm"
                },
                {
                    "position": "Lär",
                    "years": {
                        "start_year": 1930,
                        "end_year": 1934
                    },
                    "organization": "Kungsh lärov"
                },
                {
                    "position": "Adj",
                    "years": {
                        "start_year": 1934,
                        "end_year": 1934
                    },
                    "organization": "Norra latinlärov"
                },
                {
                    "position": "Lektor",
                    "years": {
                        "start_year": 1948,
                        "end_year": 1948
                    },
                    "organization": "Enskede"
                }
            ],
            "family": {
                "spouse": "Dagny Larsson",
                "marriage_year": "1926",
                "children": [
                    {
                        "name": "Dag",
                        "birth_year": "1933"
                    },
                    {
                        "name": "Ubbe",
                        "birth_year": "1935"
                    },
                    {
                        "name": "Gudmund",
                        "birth_year": "1936"
                    }
                ]
            }
        },
        "2": {
            "full_name": "Frödin, A Henry",
            "location": "Bromma",
            "occupation": "Prakt läkare",
            "birth_details": {
                "date": "10/07/1913",
                "place": "Sthlm",
                "parents": "Ing Emil F o Elisabet Arndtz"
            },
            "education": [
                {
                    "degree": "Studrex",
                    "year": "1931",
                    "institution": "NULL"
                },
                {
                    "degree": "Med kand",
                    "year": "1934",
                    "institution": "NULL"
                },
                {
                    "degree": "Med lic",
                    "year": "1938",
                    "institution": "NULL"
                }
            ],
            "career": [
                {
                    "position": "E läk",
                    "years": {
                        "start_year": 1938,
                        "end_year": 1938
                    },
                    "organization": "Vadstena o Västerhaninge distr"
                },
                {
                    "position": "Tf underläk med avd",
                    "years": {
                        "start_year": 1939,
                        "end_year": 1939
                    },
                    "organization": "S:t Görans sjh"
                },
                {
                    "position": "Tf underläk med avd",
                    "years": {
                        "start_year": 1942,
                        "end_year": 1942
                    },
                    "organization": "S:t Görans sjh"
                },
                {
                    "position": "Med avd",
                    "years": {
                        "start_year": 1940,
                        "end_year": 1940
                    },
                    "organization": "Ersta sjh"
                },
                {
                    "position": "Röntgenavd",
                    "years": {
                        "start_year": 1943,
                        "end_year": 1943
                    },
                    "organization": "S:t Görans sjh"
                },
                {
                    "position": "E läk",
                    "years": {
                        "start_year": 1944,
                        "end_year": 1945
                    },
                    "organization": "Västerås las"
                },
                {
                    "position": "Underläk",
                    "years": {
                        "start_year": 1945,
                        "end_year": 1948
                    },
                    "organization": "Karlstads las"
                },
                {
                    "position": "Tf las:läk",
                    "years": {
                        "start_year": 1949,
                        "end_year": 1949
                    },
                    "organization": "NULL"
                },
                {
                    "position": "Prakt barnläk",
                    "years": {
                        "start_year": 1949,
                        "end_year": 1949
                    },
                    "organization": "Bromma"
                }
            ],
            "family": {
                "spouse": "Inga Smith",
                "marriage_year": "1940",
                "children": [
                    {
                        "name": "Gösta",
                        "birth_year": "1943"
                    },
                    {
                        "name": "Thomas",
                        "birth_year": "1946"
                    },
                    {
                        "name": "Jan-Erik",
                        "birth_year": "1952"
                    }
                ]
            }
        }
    }
}