{
    "original": "RISSLER, SVEN G, tandläkare,\nFrösön, f i Östersund 25/5/91 av landssekr\nGottlieb R o Julia Dehlin.\nStud:ex Karlstad 11, tandl:ex Sthlm 16,\npriv :prakt Östersund sed 16, Frösön sed\n50. - V ordf Jämtl l tandl:fören 20-50.\n- Medl FrimO, Rotary. - Hobbies:\nfilateli, fotografering, golf.\nGift 16 m Karin Vendel f 92, dtr t fabr\nPer Birger V o Mathilda Jonsson.\n-Barn: Marianne f 17, Margareta f 21,\nGöran f 30.\n\nRISVEDEN, S BERTIL, lantmätare,\növeringenjör, Sundsvall, f i Erska, Älvsb\nl, 2/6/16 av stat :insp Emil Andersson\nö Klara Svensson.\n\nStud:ex Skara 34, KTH 39, lantmät:tjg\nKrist, Gbgs o Boh, Älvsb o Västerb l\n39-48, stadsing Sundsvall 48-65, övering\no kont :ch kommunernas konsultbyrå\nLBF sed 65. - Ett flert komm o kyrkl\nuppdr Sundsvall. - Medl Rotary.\nGift 42 m Ulla Hising f 17, dtr t\nbergsing Harald H o Ingrid Aschan. - Barn:\nHarald f 43, Kerstin f 45.\n\nRITZÉN,    E    HILDING,    lappfogde,\n\nUmeå, f i Burträsk, Västerb l, 20/5/04\nav kommin Erik Eriksson o Hilda\nPersson.\n\nLandsfiskalsex 28, landsfiskal Västerb l\n34, lappfogde o l :e konsulent\nlappväsendet sed 53. - Led sv-norska\nrenbetes-komm 64. - Utm: RNO, FMpbh.\n-Hobbies: fjällvandr, träslöjd.\nGift 33 m Ragnhild Grönlund, dtr t\nhäradsdom August G o Hulda\nDanielsson. - Barn: Per-Erik f 34, Martin f 37.\n\nROBERTSSON, B ALLAN J,\nkomminister, Bergnäset, f i Lövånger, Västerb\nl, 31/1/36 av hemm:äg Olof R o Ebba\nJohansson.\n\nTeol kand Upps 62, kyrkoadj Arjeplog\no Laisvall 62-64, kommin Nederluleå\nsed 65. - Led fångv:anst Luleå,\nhdlsflot-tans välfärdsråds Luleå-sekt, flottiljpast\nF 21. - Medl FrimO.\nGift 59 m Inger Jonsson, dtr t\nsmältv:-arb Joel J o Elin Holmqvist. - Barn:\nSimon f 63, Anton f 65.\n\n",
    "structured": {
        "1": {
            "full_name": "RISSLER, SVEN G",
            "location": "Frösön, Östersund",
            "occupation": "Tandläkare",
            "birth_details": {
                "date": "25/05/1891",
                "place": "Östersund",
                "parents": "landssekr Gottlieb R o Julia Dehlin"
            },
            "education": [
                {
                    "degree": "Stud:ex",
                    "year": "1911",
                    "institution": "Karlstad"
                },
                {
                    "degree": "Tandl:ex",
                    "year": "1916",
                    "institution": "Sthlm"
                }
            ],
            "career": [
                {
                    "position": "priv :prakt",
                    "years": {
                        "start_year": 1916,
                        "end_year": 1950
                    },
                    "organization": "Östersund"
                },
                {
                    "position": "V ordf Jämtl l tandl:fören",
                    "years": {
                        "start_year": 1920,
                        "end_year": 1950
                    }
                }
            ],
            "family": {
                "spouse": "Karin Vendel",
                "marriage_year": "1916",
                "children": [
                    {
                        "name": "Marianne",
                        "birth_year": "1917"
                    },
                    {
                        "name": "Margareta",
                        "birth_year": "1921"
                    },
                    {
                        "name": "Göran",
                        "birth_year": "1930"
                    }
                ]
            },
            "hobbies": [
                "filateli",
                "fotografering",
                "golf"
            ]
        },
        "2": {
            "full_name": "RISVEDEN, S BERTIL",
            "location": "Sundsvall",
            "occupation": "Lantmätare, Överingenjör",
            "birth_details": {
                "date": "02/06/1916",
                "place": "Erska, Älvsborg",
                "parents": "stat :insp Emil Andersson ö Klara Svensson"
            },
            "education": [
                {
                    "degree": "Stud:ex",
                    "year": "1934",
                    "institution": "Skara"
                },
                {
                    "degree": "KTH",
                    "year": "1939",
                    "institution": "KTH"
                }
            ],
            "career": [
                {
                    "position": "lantmät:tjg",
                    "years": {
                        "start_year": 1939,
                        "end_year": 1948
                    },
                    "organization": "Krist, Gbgs o Boh, Älvsb o Västerb l"
                },
                {
                    "position": "stadsing",
                    "years": {
                        "start_year": 1948,
                        "end_year": 1965
                    },
                    "organization": "Sundsvall"
                },
                {
                    "position": "övering o kont :ch",
                    "years": {
                        "start_year": 1965
                    },
                    "organization": "kommunernas konsultbyrå LBF"
                }
            ],
            "family": {
                "spouse": "Ulla Hising",
                "marriage_year": "1942",
                "children": [
                    {
                        "name": "Harald",
                        "birth_year": "1943"
                    },
                    {
                        "name": "Kerstin",
                        "birth_year": "1945"
                    }
                ]
            }
        },
        "3": {
            "full_name": "RITZÉN, E HILDING",
            "location": "Umeå",
            "occupation": "Lappfogde",
            "birth_details": {
                "date": "20/05/1904",
                "place": "Burträsk, Västerb l",
                "parents": "kommin Erik Eriksson o Hilda Persson"
            },
            "education": [
                {
                    "degree": "Landsfiskalsex",
                    "year": "1928",
                    "institution": "N/A"
                },
                {
                    "degree": "landsfiskal",
                    "year": "1934",
                    "institution": "Västerb l"
                }
            ],
            "career": [
                {
                    "position": "lappfogde o l :e konsulent",
                    "years": {
                        "start_year": 1953
                    },
                    "organization": "lappväsendet"
                }
            ],
            "family": {
                "spouse": "Ragnhild Grönlund",
                "marriage_year": "1933",
                "children": [
                    {
                        "name": "Per-Erik",
                        "birth_year": "1934"
                    },
                    {
                        "name": "Martin",
                        "birth_year": "1937"
                    }
                ]
            },
            "hobbies": [
                "fjällvandr",
                "träslöjd"
            ]
        },
        "4": {
            "full_name": "ROBERTSSON, B ALLAN J",
            "location": "Bergnäset, Lövånger, Västerb l",
            "occupation": "Komminister",
            "birth_details": {
                "date": "31/01/1936",
                "place": "Lövånger, Västerb l",
                "parents": "hemm:äg Olof R o Ebba Johansson"
            },
            "education": [
                {
                    "degree": "Teol kand",
                    "year": "1962",
                    "institution": "Upps"
                }
            ],
            "career": [
                {
                    "position": "kyrkoadj",
                    "years": {
                        "start_year": 1962,
                        "end_year": 1964
                    },
                    "organization": "Arjeplog o Laisvall"
                },
                {
                    "position": "kommin",
                    "years": {
                        "start_year": 1965
                    },
                    "organization": "Nederluleå"
                }
            ],
            "family": {
                "spouse": "Inger Jonsson",
                "marriage_year": "1959",
                "children": [
                    {
                        "name": "Simon",
                        "birth_year": "1963"
                    },
                    {
                        "name": "Anton",
                        "birth_year": "1965"
                    }
                ]
            }
        }
    }
}