{
    "original": "ROSENIUS,    RAGNHILD    E,    bitr\nlänsarkitekt, Östersund, f i Risinge,\nÖs-terg l, 14/2/32 av häradsdom David\nOlsson o Greta Nilsson.\nStud:ex Lund 53, KTH 58, arkit\nläns-arkit:kont Visby 57, byggn:ndn där 59,\nlänsarkit :kont   Karlstad   62,   Mariestad\n64, bitr länsarkit Östersund sed 65.\nGift 57 m stadsing Olof Rosenius f 30.\n- Barn: Ulla f 59.\n\nROSS, HANS I, bergsingenjör,\nAdak-gruvan, f i Fana, Norge, 25/6/18 av arkit\nErling R o Elisa Mårtens.\nNTH 43, gruving AS Vigsnes\nKobber-verk 43, anrikn:ing AS Stordö Kisgruber\n46, bitr gruving Bolidens gruv ab\nKristineberg 56, anrikn:ing Bolidens gruv ab\nLaisvall 56, Boliden ab Adak sed 58.\nGift 44 m Inger Haugen f 22, dtr t\nrev:-ch Nils H o Ingrid Langlo. - Barn:\nErling f 44, Björn f 46.\n\nROTH, STEN G, länsassessor, Luleå,\nf i Vänersborg 20/2/26 av bankjur Sven\nR o Margit Lundberg.\nStud:ex Karlstad 46, jur kand Upps 54,\nbitr länsstyr Värml l 54, asp Gotl l 55,\neo länsnot 56, eo tax :insp Värml l 57,\nl:e tax:insp där 60-61, Norrb l 61, tf\nlänsassess 63, länsassess där sed 66.\n-Ordf beredn:nd 56, tax:nd 57-64,\nkrono-omb 56-57, tax :konsulent 58-60.\nGift 66 m Birgit Lundin.\n\nROTHELIUS, CARL HUGO, kapten,\n\nLjusne, f i Sthlm 6/12/14 av disp Carl\nGustaf R o Signe Aplanius.\nStud:ex 34, Schartaus HdlI 37, res:off:ex\n40; tjm Thulebolagen 37-41, samh:ch\nStröm-Ljusne ab sed 42. - Ordf Sv\nhdlsbkn Ljusne sed 66, styr:led Ljusne bost\nab sed 63; led Söderala kommuns\nbrandstyr sed 47. - Ordf Hälsingl simförb 60,\nstyr:led Hälsingl ishockeyförb 47. - Medl\nOdd Fellow. - Utm: Hälsingl ifb ftjtG,\nHälsingl ishockeyförb ftjtG. - Hobbies:\nsport, fiske.\n\nGift 46 m Karin Bolin f 20, dtr t dr\nAlvar B o Ingrid Danielsson. - Barn:\nPeter f 47, Catharina f 49, Charlotta\nf 55.\n\n",
    "structured": {
        "0": {
            "full_name": "ROSENIUS, RAGNHILD E",
            "location": "Östersund",
            "occupation": "bitr länsarkitekt",
            "birth_details": {
                "date": "14/02/1932",
                "place": "Risinge, Östergötland"
            },
            "education": [
                {
                    "degree": "Stud:ex",
                    "year": "1953",
                    "institution": "Lund"
                },
                {
                    "degree": "KTH",
                    "year": "1958",
                    "institution": "Kungliga Tekniska högskolan"
                }
            ],
            "career": [
                {
                    "position": "arkit länsarkit:kont",
                    "years": {
                        "start_year": 1957,
                        "end_year": 1959
                    },
                    "organization": "Visby"
                },
                {
                    "position": "byggn:ndn",
                    "years": {
                        "start_year": 1959,
                        "end_year": 1962
                    },
                    "organization": "Östersund"
                }
            ],
            "family": {
                "spouse": "Olof Rosenius",
                "marriage_year": "1957",
                "children": [
                    {
                        "name": "Ulla",
                        "birth_year": "1959"
                    }
                ]
            }
        },
        "1": {
            "full_name": "ROSS, HANS I",
            "location": "Adak-gruvan",
            "occupation": "bergsingenjör",
            "birth_details": {
                "date": "25/06/1918",
                "place": "Fana, Norge"
            },
            "education": [
                {
                    "degree": "NTH",
                    "year": "1943",
                    "institution": "Norges teknisk-naturvitenskapelige universitet"
                }
            ],
            "career": [
                {
                    "position": "bitr gruving",
                    "years": {
                        "start_year": 1956,
                        "end_year": 1956
                    },
                    "organization": "Bolidens gruv ab Kristineberg"
                },
                {
                    "position": "anrikn:ing",
                    "years": {
                        "start_year": 1956,
                        "end_year": 1956
                    },
                    "organization": "Bolidens gruv ab Laisvall"
                }
            ],
            "family": {
                "spouse": "Inger Haugen",
                "marriage_year": "1944",
                "children": [
                    {
                        "name": "Erling",
                        "birth_year": "1944"
                    },
                    {
                        "name": "Björn",
                        "birth_year": "1946"
                    }
                ]
            }
        },
        "2": {
            "full_name": "ROTH, STEN G",
            "location": "Luleå",
            "occupation": "länsassessor",
            "birth_details": {
                "date": "20/02/1926",
                "place": "Vänersborg"
            },
            "education": [
                {
                    "degree": "Stud:ex",
                    "year": "1946",
                    "institution": "Karlstad"
                },
                {
                    "degree": "jur kand",
                    "year": "1954",
                    "institution": "Uppsala universitet"
                }
            ],
            "career": [
                {
                    "position": "eo länsnot",
                    "years": {
                        "start_year": 1957,
                        "end_year": 1957
                    },
                    "organization": "Värml l"
                },
                {
                    "position": "l:e tax:insp",
                    "years": {
                        "start_year": 1960,
                        "end_year": 1961
                    },
                    "organization": "Norrb l"
                }
            ],
            "family": {
                "spouse": "Birgit Lundin",
                "marriage_year": "1966"
            }
        },
        "3": {
            "full_name": "ROTHELIUS, CARL HUGO",
            "location": "Ljusne",
            "occupation": "kapten",
            "birth_details": {
                "date": "06/12/1914",
                "place": "Stockholm"
            },
            "education": [
                {
                    "degree": "Stud:ex",
                    "year": "1934"
                }
            ],
            "career": [
                {
                    "position": "tjm",
                    "years": {
                        "start_year": 1937,
                        "end_year": 1941
                    },
                    "organization": "Thulebolagen"
                },
                {
                    "position": "samh:ch",
                    "years": {
                        "start_year": 1942
                    },
                    "organization": "Ström-Ljusne ab"
                }
            ],
            "family": {
                "spouse": "Karin Bolin",
                "marriage_year": "1946",
                "children": [
                    {
                        "name": "Peter",
                        "birth_year": "1947"
                    },
                    {
                        "name": "Catharina",
                        "birth_year": "1949"
                    },
                    {
                        "name": "Charlotta",
                        "birth_year": "1955"
                    }
                ]
            },
            "hobbies": [
                "sport",
                "fiske"
            ]
        }
    }
}