{
    "original": "RÅÅ, INGVAR, civilingenjör, Gävle,\nf i Bergen 16/11/24 av poliskommiss\nOlav R o Ida Korsvold.\nStud:ex 44, KTH 50, byråing VV:styr\n50, ing Firma Vestergren &amp; Houen\nSthlm 52, HKB 54, avd:ch HKB Gävle\n57, inneh Civ:ing SVR Ingvar Råå\nkonsult ing:firma sed 62. - Medl sällsk NT.\n\n-  Hobbies: fiske, golf, bowling.\n\nGift 57 m Inger Nilsson f 30, dtr t l:e\npolisass Gottfrid N o Valborg\nAndersson. - Barn: Inger-Johanne f 57,\nKristian f 60, Jörgen f 63.\n\nRAGNARSON, NILS H, tandläkare,\n\nBjurholm, f i Rundviksverken, Västerb\nl, 16/1/35 av Ragnar Johansson o Maja\nHedman.\n\nStud:ex Upps 55, tandl:ex Sthlm 60,\ndistr :tandl Lycksele 60-61, ass avd f\nproteslära TI Umeå 61-63, l:e distr:tandl\no förest distr:tandpol Bjurholm sed 63.\n\n- Hobby: fiske.\n\nGift 57 m Gun-Britt Gustafson f 35, dtr\nt Abel G o Signe Danielsson. - Barn:\nMats f 60, Lena f 65.\n\nRAGNE, CARL-OTTO I, kapten,\nHärnösand, f i Upps 29/11/24 av kapt Ivan\nR o Aina Widner.\n\nStud:ex 49, Off:ex 50; vol I 2 42, furir\n45, sergeant 46, fänr I 21 50, löjtn 52,\nkapt 60, fst 61 m plac s mil :ass länsstyr\nVnorrl l sed 61. - Medl FrimO. -\nHobbies: sport, radioteknik (sändaramatör\nSM3CJD).\n\nGift m Inga-Lill Johansson f 29, dtr t\nköpm Martin J o Vega Svensk. - Barn:\nMarie f 55, Anders f 62.\n\nRAHM, BERTIL V, ingenjör,\nÖstersund, f i Frösön, Jämtl l,  11/7/12 av\ndisp Vilhelm R o Elin Bertilsson.\nIng :ex GTI  32, ag Rahms maskin ab\n(bilelektr  grossistfirma)   Östersund   sed\n39. - Hobby: skidsport.\nGift 39 m Gun Molander f 13, dtr t\nAgaton M o Ingeborg Eriksson.\n\n",
    "structured": {
        "1": {
            "full_name": "INGVAR RÅÅ",
            "location": "Gävle",
            "occupation": "civilingenjör",
            "birth_details": {
                "date": "16/11/1924",
                "place": "Bergen"
            },
            "education": [
                {
                    "degree": "Stud:ex",
                    "year": "1944",
                    "institution": "KTH"
                }
            ],
            "career": [
                {
                    "position": "byråing VV:styr",
                    "years": {
                        "start_year": 1950,
                        "end_year": 1950
                    },
                    "organization": null
                },
                {
                    "position": "ing Firma Vestergren & Houen Sthlm",
                    "years": {
                        "start_year": 1952,
                        "end_year": 1952
                    },
                    "organization": null
                },
                {
                    "position": "HKB",
                    "years": {
                        "start_year": 1954,
                        "end_year": 1954
                    },
                    "organization": null
                },
                {
                    "position": "avd:ch HKB Gävle",
                    "years": {
                        "start_year": 1957,
                        "end_year": 1957
                    },
                    "organization": null
                },
                {
                    "position": "inh Civ:ing SVR Ingvar Råå",
                    "years": {
                        "start_year": 1962,
                        "end_year": null
                    },
                    "organization": "konsult ing:firma"
                }
            ],
            "family": {
                "spouse": "Inger Nilsson",
                "marriage_year": "1957",
                "children": [
                    {
                        "name": "Inger-Johanne",
                        "birth_year": "1957"
                    },
                    {
                        "name": "Kristian",
                        "birth_year": "1960"
                    },
                    {
                        "name": "Jörgen",
                        "birth_year": "1963"
                    }
                ]
            },
            "hobbies": [
                "fiske",
                "golf",
                "bowling"
            ]
        },
        "2": {
            "full_name": "NILS H RAGNARSON",
            "location": "Bjurholm",
            "occupation": "tandläkare",
            "birth_details": {
                "date": "16/01/1935",
                "place": "Rundviksverken, Västerb"
            },
            "education": [
                {
                    "degree": "Stud:ex",
                    "year": "1955",
                    "institution": "Upps"
                }
            ],
            "career": [
                {
                    "position": "distr: tandl",
                    "years": {
                        "start_year": 1960,
                        "end_year": 1961
                    },
                    "organization": "Lycksele"
                },
                {
                    "position": "ass avd f proteslära",
                    "years": {
                        "start_year": 1961,
                        "end_year": 1963
                    },
                    "organization": "TI Umeå"
                },
                {
                    "position": "l:e distr:tandl o förest distr:tandpol Bjurholm",
                    "years": {
                        "start_year": 1963,
                        "end_year": null
                    },
                    "organization": null
                }
            ],
            "family": {
                "spouse": "Gun-Britt Gustafson",
                "marriage_year": "1957",
                "children": [
                    {
                        "name": "Mats",
                        "birth_year": "1960"
                    },
                    {
                        "name": "Lena",
                        "birth_year": "1965"
                    }
                ]
            },
            "hobbies": [
                "fiske"
            ]
        },
        "3": {
            "full_name": "CARL-OTTO I RAGNE",
            "location": "Härnösand",
            "occupation": "kapten",
            "birth_details": {
                "date": "29/11/1924",
                "place": "Upps"
            },
            "education": [
                {
                    "degree": "Stud:ex",
                    "year": "1949",
                    "institution": null
                },
                {
                    "degree": "Off:ex",
                    "year": "1950",
                    "institution": null
                }
            ],
            "career": [
                {
                    "position": "fst 61",
                    "years": {
                        "start_year": 1961,
                        "end_year": null
                    },
                    "organization": "mil:ass länsstyr Vnorrl l"
                }
            ],
            "family": {
                "spouse": "Inga-Lill Johansson",
                "marriage_year": null,
                "children": [
                    {
                        "name": "Marie",
                        "birth_year": "1955"
                    },
                    {
                        "name": "Anders",
                        "birth_year": "1962"
                    }
                ]
            },
            "hobbies": [
                "sport",
                "radioteknik (sändaramatör SM3CJD)"
            ]
        },
        "4": {
            "full_name": "BERTIL V RAHM",
            "location": "Östersund",
            "occupation": "ingenjör",
            "birth_details": {
                "date": "11/7/1912",
                "place": "Frösön, Jämtl l"
            },
            "education": [
                {
                    "degree": "Ing:ex",
                    "year": "1932",
                    "institution": "GTI"
                }
            ],
            "career": [
                {
                    "position": null,
                    "years": {
                        "start_year": 1939,
                        "end_year": null
                    },
                    "organization": "Rahms maskin ab (bilelektr grossistfirma) Östersund"
                }
            ],
            "family": {
                "spouse": "Gun Molander",
                "marriage_year": "1939",
                "children": null
            },
            "hobbies": [
                "skidsport"
            ]
        }
    }
}