{
    "original": "LINDEMAN, ANDERS E,\ndistriktsveterinär, Haparanda, f i Ottawa,\nKanada, 25/12/08 av bergmäst Einar L o\nKirsten Erichssen.\n\nStud:ex Falun 28, vet:ex VHS 35,\ndistr:-vet Hede 39, Haparanda sed 45. - Utm:\nRNO. - Hobby: bridge.\nGift 39 m musiklär Malin Bengtsson,\ndtr t bapt:past Sven B o Elina Dufva.\n-Barn: Christina f 40, Pontus f 42,\nRichard f 44, Brita f 50.\n\nLINDEN, BO C I, ingenjör, Umeå, f i\nSthlm 10/5/33 av konstn Helge L o\nHanna Johansson.\n\nRealex Umeå 52, ing :ex tekn gymn\nHärnösand 59, ing ab Bofors Nobelkrut 59,\nplatsch Thigers elektr konstr :byrå ab sed\n64. - Hobbies: filateli, foto.\nGift 62 m Hillevi Persson, dtr t\nHenning P o Anna Mårtensson. - Barn:\nElisabet f 63, Erik f 65.\n\nvan der LINDEN, WILLEM J, med\ndr, docent, Östersund, f i Velsen,\nHolland, 5/9/23 av dir Arie v d L o Jo\nVaber.\n\nStud:ex Eindhoven, Holland 42, med\nkand Groningen 45, med lic Lund 52,\nmed dr o doc i kirurgi Umeå univ sed\n61; öl läk:förordn 52-53, underläk kir\navd Gällivare las 54-55, kir avd\nÖstersunds las 56-59, bitr överläk kir klin\nÖstersunds las sed 64.\n\nGift 51 m Gunilla Odelberg f 29, dtr t\nkapt Torsten O o Görvel Gyllenstierna.\n- Barn: Sten f 53, Jan f 54, Olga f 56.\n\nLINDÉN,  S  GUSTAF  T,  apotekare,\n\nBollnäs, f i Eksjö 30/8/28 av tandl\nRagnar L o Karin Andrae.\nStud:ex Sthlm 49, receptarie 54, apot:ex\n59, elev Tranås 51, anst Gislaved 54,\nEksjö o Tomelilla 55, Eksjö o Sälen\nSthlm 56, C V Scheele Sthlm 57,\nBollnäs sed 59. - Fullm o sekr\nGävleborgs-Dalakretsen Sv:es farm:förb sed 63.\nGift 59 m receptarie Kerstin Brette\nf 34, dtr t landsfiskal Nils B o Karin\nWetterwik. - Barn: Karin f 61, Jonas\nf 65.\n\nLINDÉN, J GÖRAN, direktör,\nEdsbyn, f i Sthlm 6/6/22 av skohandl Petrus\nL o Signe Olsson.\n\nIng :ex tekn gymn Västerås 43,\nanläggn:ing Asea Västerås 43, driftsing Bollnäs\nkraft ab 53, driftch ab Edsbyns elverk\n63, verkst dir där sed 65, Elektr\ninställ:-byrån i Bollnäs ab sed 66. - Led Gävleb\nlokalavd av EAF sed 66. - Medl Odd\nFellow, Lions club. - Skr art i\nfacktid-skr.\n\nGift 45 m May Hammarqvist f 24.\n-Barn: Bengt o Ove ff 57.\n\nLINDÉN, LEIF-ARNE E, advokat,\nÖstersund, f i Grums, Värml l, 17/9/21 av\nfolkskollär Gustaf L o Olga Nilsson.\nStud:ex Karlstad 43, jur kand Upps 49,\ntingstjg N Hälsingl doms 49-51,\nSollentuna o Färentuna doms 51-52, bitr jur\nF Victors adv :byrå Östersund 52, deläg\nsed 65. - LSA 55.\n\nGift 45 m Karin Seeberg f 18, dtr t kont\nManne S o Helena Fjellström. - Barn:\nAnnika f 49.\n\nLINDÉN, ROLF H, ingenjör, Luleå, f\ni Kristinehamn 2/9/32 av ing Oscar L o\nSigne Larsson.\n\nBergssk Filipstad 55, lab :ing ab Bofors\n55, driftsing där 56, Norrb järnverk ab\n61, ch elektrostålverket där sed 66.\n-Hobbies: golf, fiske.\nGift 57 m Ingegerd Reinholdz f 32, dtr\nt ing Erik R o Ingrid Edlund. - Barn:\nEric f 62, Åsa f 65.\n\nLINDÉN, A STAFFAN,\nläroverksadjunkt, Gävle, f i Bollnäs 31/5/26 av\nskohandl Petrus L o Signe Olsson.\nStud:ex 46 o fil mag Upps 51, lär Gävle\no Västervik 52, red Bulls presstjänst\nSthlm 53-54, lär hal Östersund 54-59,\nlärov:adj Gävle sed 59. - Tecknare MB\n57-58, SvD sed 58, Röster i Radio-TV\nsed 61, Jordbrukarnas f ören :blad sed 62.\n\n-   Bokillustratör.   -   Medl  Konstn :gillet,\nW-sex. - Utg: Staffans Stoilar (sed 57),\nSångmusen Filip (57), Jag — En lärare\n(66). - Hobby: träsvarvning.\n\nGift 54 m Ulla-Märta Öhman f 32.\n-Barn: Lasse f 57, Mats f 60.\n\n",
    "structured": {
        "1": {
            "full_name": "Anders E Lindeman",
            "occupation": "Distriktsveterinär",
            "location": "Haparanda",
            "birth_details": {
                "date": "25/12/1908",
                "place": "Ottawa, Kanada"
            },
            "education": [
                {
                    "degree": "Stud:ex",
                    "year": "1928",
                    "institution": "Falun"
                },
                {
                    "degree": "Vet:ex",
                    "year": "1935",
                    "institution": "VHS"
                }
            ],
            "career": [
                {
                    "position": "Distr:-vet",
                    "years": {
                        "start_year": 1939,
                        "end_year": 1945
                    },
                    "organization": "Haparanda"
                }
            ],
            "family": {
                "spouse": "Malin Bengtsson",
                "marriage_year": "1939",
                "children": [
                    {
                        "name": "Christina",
                        "birth_year": "1940"
                    },
                    {
                        "name": "Pontus",
                        "birth_year": "1942"
                    },
                    {
                        "name": "Richard",
                        "birth_year": "1944"
                    },
                    {
                        "name": "Brita",
                        "birth_year": "1950"
                    }
                ]
            },
            "hobbies": [
                "Bridge"
            ]
        },
        "2": {
            "full_name": "Bo C I Linden",
            "occupation": "Ingenjör",
            "location": "Umeå",
            "birth_details": {
                "date": "10/5/1933",
                "place": "Sthlm"
            },
            "education": [
                {
                    "degree": "Realex",
                    "year": "1952",
                    "institution": "Umeå"
                },
                {
                    "degree": "Ing :ex",
                    "year": "1959",
                    "institution": "Tekn gymn Härnösand"
                }
            ],
            "career": [
                {
                    "position": "Driftch",
                    "years": {
                        "start_year": 1963
                    },
                    "organization": "Edsbyns elverk"
                }
            ],
            "family": {
                "spouse": "Hillevi Persson",
                "marriage_year": "1962",
                "children": [
                    {
                        "name": "Elisabet",
                        "birth_year": "1963"
                    },
                    {
                        "name": "Erik",
                        "birth_year": "1965"
                    }
                ]
            },
            "hobbies": [
                "Filateli",
                "Foto"
            ]
        },
        "3": {
            "full_name": "Willem J van der Linden",
            "occupation": "Med dr, Docent",
            "location": "Östersund",
            "birth_details": {
                "date": "5/9/1923",
                "place": "Velsen, Holland"
            },
            "education": [
                {
                    "degree": "Stud:ex",
                    "year": "1942",
                    "institution": "Eindhoven, Holland"
                },
                {
                    "degree": "Med kand",
                    "year": "1945",
                    "institution": "Groningen"
                },
                {
                    "degree": "Med lic",
                    "year": "1952",
                    "institution": "Lund"
                },
                {
                    "degree": "Med dr, Doc i kirurgi",
                    "year": "1961",
                    "institution": "Umeå univ"
                }
            ],
            "career": [
                {
                    "position": "Bitr överläk",
                    "years": {
                        "start_year": 1964
                    },
                    "organization": "Kir klin Östersunds las"
                }
            ],
            "family": {
                "spouse": "Gunilla Odelberg",
                "marriage_year": "1951",
                "children": [
                    {
                        "name": "Sten",
                        "birth_year": "1953"
                    },
                    {
                        "name": "Jan",
                        "birth_year": "1954"
                    },
                    {
                        "name": "Olga",
                        "birth_year": "1956"
                    }
                ]
            }
        },
        "4": {
            "full_name": "S Gustaf T Lindén",
            "occupation": "Apotekare",
            "location": "Bollnäs",
            "birth_details": {
                "date": "30/8/1928",
                "place": "Eksjö"
            },
            "education": [
                {
                    "degree": "Stud:ex",
                    "year": "1949",
                    "institution": "Sthlm"
                },
                {
                    "degree": "Receptarie",
                    "year": "1954",
                    "institution": "NULL"
                },
                {
                    "degree": "Apot:ex",
                    "year": "1959",
                    "institution": "NULL"
                }
            ],
            "career": [
                {
                    "position": "Receptarie",
                    "years": {
                        "start_year": 1954
                    },
                    "organization": "Gislaved"
                },
                {
                    "position": "Lärov",
                    "years": {
                        "start_year": 1959
                    },
                    "organization": "Bollnäs"
                }
            ],
            "family": {
                "spouse": "Kerstin Brette",
                "marriage_year": "1959",
                "children": [
                    {
                        "name": "Karin",
                        "birth_year": "1961"
                    },
                    {
                        "name": "Jonas",
                        "birth_year": "1965"
                    }
                ]
            }
        },
        "5": {
            "full_name": "J Göran Lindén",
            "occupation": "Direktör",
            "location": "Edsbyn",
            "birth_details": {
                "date": "6/6/1922",
                "place": "Sthlm"
            },
            "education": [
                {
                    "degree": "Ing :ex",
                    "year": "1943",
                    "institution": "Tekn gymn Västerås"
                }
            ],
            "career": [
                {
                    "position": "Verkst dir",
                    "years": {
                        "start_year": 1965
                    },
                    "organization": "Edsbyns elverk"
                }
            ],
            "family": {
                "spouse": "May Hammarqvist",
                "marriage_year": "1945",
                "children": [
                    {
                        "name": "Bengt",
                        "birth_year": "1957"
                    },
                    {
                        "name": "Ove",
                        "birth_year": "1957"
                    }
                ]
            }
        },
        "6": {
            "full_name": "Leif-Arne E Lindén",
            "occupation": "Advokat",
            "location": "Östersund",
            "birth_details": {
                "date": "17/9/1921",
                "place": "Grums, Värml l"
            },
            "education": [
                {
                    "degree": "Stud:ex",
                    "year": "1943",
                    "institution": "Karlstad"
                },
                {
                    "degree": "Jur kand",
                    "year": "1949",
                    "institution": "Upps"
                }
            ],
            "career": [
                {
                    "position": "Deläg",
                    "years": {
                        "start_year": 1965
                    },
                    "organization": "Victors adv :byrå Östersund"
                }
            ],
            "family": {
                "spouse": "Karin Seeberg",
                "marriage_year": "1945",
                "children": [
                    {
                        "name": "Annika",
                        "birth_year": "1949"
                    }
                ]
            }
        },
        "7": {
            "full_name": "Rolf H Lindén",
            "occupation": "Ingenjör",
            "location": "Luleå",
            "birth_details": {
                "date": "2/9/1932",
                "place": "Kristinehamn"
            },
            "education": [
                {
                    "degree": "Bergssk",
                    "year": "1955",
                    "institution": "Filipstad"
                }
            ],
            "career": [
                {
                    "position": "Ch Elektrostålverket",
                    "years": {
                        "start_year": 1966
                    },
                    "organization": "Norrb järnverk ab"
                }
            ],
            "family": {
                "spouse": "Ingegerd Reinholdz",
                "marriage_year": "1957",
                "children": [
                    {
                        "name": "Eric",
                        "birth_year": "1962"
                    },
                    {
                        "name": "Åsa",
                        "birth_year": "1965"
                    }
                ]
            },
            "hobbies": [
                "Golf",
                "Fiske"
            ]
        },
        "8": {
            "full_name": "A Staffan Lindén",
            "occupation": "Läroverksadjunkt",
            "location": "Gävle",
            "birth_details": {
                "date": "31/5/1926",
                "place": "Bollnäs"
            },
            "education": [
                {
                    "degree": "Stud:ex",
                    "year": "1946",
                    "institution": "NULL"
                },
                {
                    "degree": "Fil mag",
                    "year": "1951",
                    "institution": "Upps"
                }
            ],
            "career": [
                {
                    "position": "Lärov:adj",
                    "years": {
                        "start_year": 1959
                    },
                    "organization": "Gävle"
                }
            ],
            "family": {
                "spouse": "Ulla-Märta Öhman",
                "marriage_year": "1954",
                "children": [
                    {
                        "name": "Lasse",
                        "birth_year": "1957"
                    },
                    {
                        "name": "Mats",
                        "birth_year": "1960"
                    }
                ]
            },
            "publications": [
                {
                    "title": "Staffans Stoilar",
                    "year": "1957",
                    "type": "NULL"
                },
                {
                    "title": "Sångmusen Filip",
                    "year": "1957",
                    "type": "NULL"
                },
                {
                    "title": "Jag — En lärare",
                    "year": "1966",
                    "type": "NULL"
                }
            ],
            "community_involvement": [
                {
                    "role": "Medl",
                    "organization": "Konstn :gillet",
                    "years": "NULL"
                },
                {
                    "role": "Utval:led",
                    "organization": "W-sex",
                    "years": "NULL"
                }
            ],
            "hobbies": [
                "Träsvarvning"
            ]
        }
    }
}