{
    "original": "LUNDIN, JAN-OLA, tandläkare,\nÄlvsbyn, f i Ådals-Liden, Vnorrl l, 20/5/36\nav hemm:äg Albert L o Mia Engström.\nStud:ex Sollefteå 56, tandl:ex Sthlm 61,\ndistr:tandl   Sollefteå   61-64,   priv:prakt\nÄlvsbyn sed 64. - Hobby: bridge.\nGift 60 m Siv Berggren f 38, dtr t dir\nBengt B o Frida Normark. - Barn: Mats\nf 62, Niklas f 63.\n\nLUNDIN, NILS O, överingenjör, Gbg,\nf i Sala 24/3/13 av förest Otto L o Ebba\nThorn.\n\nKTH 40; konsult ing S Sv:es\nångpanne-fören 39, driftsing Höganäs-Billesholms\nab 40, övering Sv skifferolje ab Närkes\nKvarntorp 52, Mo o Domsjö ab\nSte-nungsund 62, Calvert &amp; Co Gbg sed 67.\n\n- Skr upps i tekn tidskr.\nLUNDKVIST se LUNDQVIST\nLUNDMAN, JOHN V, lektor, Luleå,\n\nf i Norrfjärden, Norrb l, 16/7/26 av\nbyggn:snick Wilhelm L o Kristina\nEriksson.\n\nIng:ex Tekn gymn Luleå 49, KTH 55,\ning vägförvaltn Luleå 55-56, adj tekn\ngymn 56-58, ing Jönkpgs stads\nbyggn:-kont 58-61, lekt tekn gymn Luleå sed\n61. - Inneh Luleå stjärnslöjd sed 65.\n-Skr: komp i vattenförsörjn:- o\navloppsteknik (62). - Hobbies: träslöjd, musik.\nGift 56 m Ingrid Hellström f 26, dtr t\npredik Leonard H o Amalia Sundberg.\n\n-   Barn:   Ann-Charlotte  f   57,   Vilhelm\nf 58, Ellinor f 59, Per f 60, Kjell f 63,\nSune f 65.\n\nLUNDMARK, J GUNNAR,\nriksdagsman, Lycksele, f i Byske, Västerb l,\n27/2/07 av hemm:äg Jonas L o Hulda\nSundqvist.\n\nFolkhögsk, lantm:sk; vandr:rätt Tärna\n31, jordbr:instr Lycksele 38, jordbr:ass\ndär sed 64 (tji); led AK sed 57; ordf\nStadsfullm Lycksele sed 58, led DK,\nstyr:ordf Lycksele bost:stift; landst:man\no ordf direkt f Lycksele las. - Hobby:\nsportfiske.\n\nGift 32 m Anna Stina Bergstrand, dtr t\nJohan B o Axelina Andersdotter. - Barn:\nGunilla f 38.\n\n",
    "structured": {
        "1": {
            "full_name": "LUNDIN, JAN-OLA",
            "location": "Älvsbyn, Ådals-Liden, Västernorrlands län",
            "occupation": "tandläkare",
            "birth_details": {
                "date": "20/05/1936",
                "place": "Ådals-Liden, Västernorrlands län",
                "parents": "Albert L o Mia Engström"
            },
            "education": [
                {
                    "degree": "Stud:ex",
                    "year": "1956",
                    "institution": "Sollefteå"
                },
                {
                    "degree": "tandl:ex",
                    "year": "1961",
                    "institution": "Sthlm"
                }
            ],
            "career": [
                {
                    "position": "distr:tandl",
                    "years": {
                        "start_year": 1961,
                        "end_year": 1964
                    },
                    "organization": "Sollefteå"
                },
                {
                    "position": "priv:prakt Älvsbyn",
                    "years": {
                        "start_year": 1964
                    }
                }
            ],
            "family": {
                "spouse": "Siv Berggren",
                "marriage_year": "1960",
                "children": [
                    {
                        "name": "Mats",
                        "birth_year": "1962"
                    },
                    {
                        "name": "Niklas",
                        "birth_year": "1963"
                    }
                ]
            },
            "hobbies": [
                "bridge"
            ]
        },
        "2": {
            "full_name": "LUNDIN, NILS O",
            "location": "Göteborg, Sala",
            "occupation": "överingenjör",
            "birth_details": {
                "date": "24/03/1913",
                "place": "Sala",
                "parents": "Otto L o Ebba Thorn"
            },
            "education": [
                {
                    "degree": "KTH",
                    "year": "1940",
                    "institution": "Sv:es ångpanne-fören"
                }
            ],
            "career": [
                {
                    "position": "konsult ing",
                    "years": {
                        "start_year": 1939
                    },
                    "organization": "Sv:es ångpanne-fören"
                },
                {
                    "position": "driftsing",
                    "years": {
                        "start_year": 1940
                    },
                    "organization": "Höganäs-Billesholms ab"
                },
                {
                    "position": "övering",
                    "years": {
                        "start_year": 1952
                    },
                    "organization": "Sv skifferolje ab Närkes Kvarntorp"
                },
                {
                    "position": "overing",
                    "years": {
                        "start_year": 1962
                    },
                    "organization": "Mo o Domsjö ab Ste-nungsund"
                },
                {
                    "position": "Calvert & Co",
                    "years": {
                        "start_year": 1967
                    },
                    "organization": "Göteborg"
                }
            ]
        },
        "3": {
            "full_name": "LUNDMAN, JOHN V",
            "location": "Luleå, Norrfjärden, Norrbottens län",
            "occupation": "lektor",
            "birth_details": {
                "date": "16/07/1926",
                "place": "Norrfjärden, Norrbottens län",
                "parents": "Wilhelm L o Kristina Eriksson"
            },
            "education": [
                {
                    "degree": "Ing:ex",
                    "year": "1949",
                    "institution": "Tekn gymn Luleå"
                },
                {
                    "degree": "KTH",
                    "year": "1955",
                    "institution": "KTH"
                }
            ],
            "career": [
                {
                    "position": "ing vägförvaltn",
                    "years": {
                        "start_year": 1955,
                        "end_year": 1956
                    },
                    "organization": "Luleå"
                },
                {
                    "position": "adj tekn gymn",
                    "years": {
                        "start_year": 1956,
                        "end_year": 1958
                    }
                },
                {
                    "position": "ing",
                    "years": {
                        "start_year": 1958,
                        "end_year": 1961
                    },
                    "organization": "Jönköpings stadsbyggnadskontor"
                },
                {
                    "position": "lekt",
                    "years": {
                        "start_year": 1961
                    },
                    "organization": "tekn gymn Luleå"
                }
            ],
            "family": {
                "spouse": "Ingrid Hellström",
                "marriage_year": "1956",
                "children": [
                    {
                        "name": "Ann-Charlotte",
                        "birth_year": "1957"
                    },
                    {
                        "name": "Vilhelm",
                        "birth_year": "1958"
                    },
                    {
                        "name": "Ellinor",
                        "birth_year": "1959"
                    },
                    {
                        "name": "Per",
                        "birth_year": "1960"
                    },
                    {
                        "name": "Kjell",
                        "birth_year": "1963"
                    },
                    {
                        "name": "Sune",
                        "birth_year": "1965"
                    }
                ]
            },
            "publications": [
                {
                    "title": "komp i vattenförsörjn:- o avloppsteknik",
                    "year": "1962",
                    "type": "teknik"
                }
            ],
            "hobbies": [
                "träslöjd",
                "musik"
            ]
        },
        "4": {
            "full_name": "LUNDMARK, J GUNNAR",
            "location": "Lycksele, Byske, Västerbottens län",
            "occupation": "riksdagsman",
            "birth_details": {
                "date": "27/02/1907",
                "place": "Byske, Västerbottens län",
                "parents": "Jonas L o Hulda Sundqvist"
            },
            "education": [
                {
                    "degree": "Folkhögsk",
                    "institution": "lantm:sk"
                }
            ],
            "career": [
                {
                    "position": "vandr:rätt",
                    "years": {
                        "start_year": 1931
                    },
                    "organization": "Tärna"
                },
                {
                    "position": "jordbr:instr",
                    "years": {
                        "start_year": 1938
                    },
                    "organization": "Lycksele"
                },
                {
                    "position": "jordbr:ass",
                    "years": {
                        "start_year": 1964
                    },
                    "organization": "Lycksele"
                }
            ],
            "community_involvement": [
                {
                    "role": "led",
                    "organization": "AK",
                    "years": "sed 1957"
                },
                {
                    "role": "ordf",
                    "organization": "Stadsfullm Lycksele",
                    "years": "sed 1958"
                }
            ],
            "honorary_titles": [
                {
                    "title": "landst:man",
                    "institution": "Lycksele las"
                }
            ],
            "hobbies": [
                "sportfiske"
            ],
            "family": {
                "spouse": "Anna Stina Bergstrand",
                "marriage_year": "1932",
                "children": [
                    {
                        "name": "Gunilla",
                        "birth_year": "1938"
                    }
                ]
            }
        }
    }
}