{
    "original": "LJUSBERG,  G  BENGT  O,  advokat,\n\nSundsvall, f i Sundsvall 15/6/23 av fabr\nG A L o Linnea Frisk.\nStud:ex 42, jur kand Upps 47, tingstjg\nSödertörns doms 47-48, bitr jur Sthlms\nstads rättshj :anst 49, sekr o dir :ass HAO\n50-56, inneh Ljusbergs adv :byrå\nSundsvall sed 56. - LSA 57. - Styr:led ab\nIsacson &amp; Co, C Bäckström Måleri &amp;\nBillackering ab, Norrl konstr :byrån ab.\n-Led Stadsfullm sed 66, soc ndrna,\nbost:-förmedl m fi komm uppdr. - Medl\nFrimO.\n\nGift 47 m Barbro Söderström f 25, dtr t\nskogsförv Erik S o Sigrid Rosander.\n-Barn: Helena f 51, Katarina f 55.\n\nLOCKMARK, KARL-ERIK G,\ncivilingenjör, Sundsvall, f i Norrkpg 11/7/31.\nTekn gymn Norrkpg, KTH 56,\nforsloi:-ass inst f tekn oorg kemi KTH 56,\navd:-ch forskn :lab SCA 57, driftsing\nMatfors-Ovikens pappersbruk SCA sed 59.\nGift 56 m Birgitta Jerlin f 34, dtr t dir\nGustaf J o Maggie J. - Barn: Agneta\nf 57, Anders f 61.\n\nLODIN, GUNNAR, komminister, Ta-\n\nvelsjö, f i Björna, Vnorrl l, 19/6/16 av\nkyrkoh Joel L o Clara Nilsson.\nTeol kand Upps 45, präst Kågedalen,\nByske, Degerfors, Sävar, Jörn,\nNordmaling, Granö, Björna, Nysätra o Fällfors\n45-61, kommin Tavelsjö sed 61. -\nStifts-omb f Lutherhj Luleå stift.\nGift 50 m Linnea Karlsson, dtr t\nkyrkvärd Magnus K o Henny Hellgren.\n-Barn: Anders f 51, Per f 53, Johannes\nf 56, Lars f 59.\n\nLODIN, E GUSTAF, överste, Boden,\nf i Falun 30/8/19 av kapt Karl L o Signe\nMorling.\n\nStud:ex Falun 38, fänr I 13 41, kapt 49,\nmajor gst 59, öv:löjtn I 21 63, överste\ndär 66. - FHS 59. - Byråch o driftv:ch\njv:styr:s försv:byrå 59-64, bat:ch o\nutb:-off I 21 64-66, tf fobef Bodens o\nJokkmokks fö sed 66. - Medl Rotary. - Utm:\nRSO, SCFGM, HvftjM, SkytteM.\nGift 51 m Gunvor Falk f 19. - Barn:\nPer f 56.\n\n",
    "structured": {
        "0": {
            "full_name": "Bengt O. Ljusberg",
            "location": "Sundsvall",
            "occupation": "Advokat",
            "birth_details": {
                "date": "15/06/1923",
                "place": "Sundsvall",
                "parents": "G A L o Linnea Frisk"
            },
            "education": [
                {
                    "degree": "Stud:ex",
                    "year": "1942",
                    "institution": "NULL"
                },
                {
                    "degree": "Jur kand",
                    "year": "1947",
                    "institution": "Upps"
                }
            ],
            "career": [
                {
                    "position": "Tingstjg",
                    "years": {
                        "start_year": 1947,
                        "end_year": 1948
                    },
                    "organization": "Södertörns doms"
                },
                {
                    "position": "Bitr jur",
                    "years": {
                        "start_year": 1949,
                        "end_year": 1956
                    },
                    "organization": "Sthlms stads rättshj :anst"
                },
                {
                    "position": "Sekr o dir :ass",
                    "years": {
                        "start_year": 1950,
                        "end_year": 1956
                    },
                    "organization": "HAO"
                }
            ],
            "family": {
                "spouse": "Barbro Söderström",
                "marriage_year": "1947",
                "children": [
                    {
                        "name": "Helena",
                        "birth_year": "1951"
                    },
                    {
                        "name": "Katarina",
                        "birth_year": "1955"
                    }
                ]
            }
        },
        "1": {
            "full_name": "Karl-Erik G. Lockmark",
            "location": "Sundsvall",
            "occupation": "Civilingenjör",
            "birth_details": {
                "date": "11/07/1931",
                "place": "Norrköping",
                "parents": "NULL"
            },
            "education": [
                {
                    "degree": "Tekn gymn",
                    "year": "NULL",
                    "institution": "Norrköping"
                },
                {
                    "degree": "KTH",
                    "year": "1956",
                    "institution": "NULL"
                }
            ],
            "career": [
                {
                    "position": "Forsloi:-ass",
                    "years": {
                        "start_year": 1956,
                        "end_year": 1959
                    },
                    "organization": "KTH"
                },
                {
                    "position": "Driftsing",
                    "years": {
                        "start_year": 1959,
                        "end_year": "NULL"
                    },
                    "organization": "Matfors-Ovikens pappersbruk SCA"
                }
            ],
            "family": {
                "spouse": "Birgitta Jerlin",
                "marriage_year": "1956",
                "children": [
                    {
                        "name": "Agneta",
                        "birth_year": "1957"
                    },
                    {
                        "name": "Anders",
                        "birth_year": "1961"
                    }
                ]
            }
        },
        "2": {
            "full_name": "Gunnar Lodin",
            "location": "Tavelsjö",
            "occupation": "Komminister",
            "birth_details": {
                "date": "19/06/1916",
                "place": "Björna, Vnorrl l",
                "parents": "kyrkoh Joel L o Clara Nilsson"
            },
            "education": [
                {
                    "degree": "Teol kand",
                    "year": "1945",
                    "institution": "Upps"
                }
            ],
            "career": [
                {
                    "position": "Präst",
                    "years": {
                        "start_year": 1945,
                        "end_year": 1961
                    },
                    "organization": "Kågedalen, Byske, Degerfors, Sävar, Jörn, Nordmaling, Granö, Björna, Nysätra o Fällfors"
                },
                {
                    "position": "Kommin",
                    "years": {
                        "start_year": 1961,
                        "end_year": "NULL"
                    },
                    "organization": "Tavelsjö"
                }
            ],
            "family": {
                "spouse": "Linnea Karlsson",
                "marriage_year": "1950",
                "children": [
                    {
                        "name": "Anders",
                        "birth_year": "1951"
                    },
                    {
                        "name": "Per",
                        "birth_year": "1953"
                    },
                    {
                        "name": "Johannes",
                        "birth_year": "1956"
                    },
                    {
                        "name": "Lars",
                        "birth_year": "1959"
                    }
                ]
            }
        },
        "3": {
            "full_name": "E. Gustaf Lodin",
            "location": "Boden",
            "occupation": "Överste",
            "birth_details": {
                "date": "30/08/1919",
                "place": "Falun",
                "parents": "kapt Karl L o Signe Morling"
            },
            "education": [
                {
                    "degree": "Stud:ex",
                    "year": "1938",
                    "institution": "Falun"
                }
            ],
            "career": [
                {
                    "position": "Fänr",
                    "years": {
                        "start_year": 1941,
                        "end_year": "NULL"
                    },
                    "organization": "I 13"
                },
                {
                    "position": "Kapt",
                    "years": {
                        "start_year": 1949,
                        "end_year": "NULL"
                    },
                    "organization": "NULL"
                },
                {
                    "position": "Major",
                    "years": {
                        "start_year": 1959,
                        "end_year": "NULL"
                    },
                    "organization": "gst"
                },
                {
                    "position": "Öv:löjtn",
                    "years": {
                        "start_year": 1963,
                        "end_year": "NULL"
                    },
                    "organization": "I 21"
                },
                {
                    "position": "Överste",
                    "years": {
                        "start_year": 1966,
                        "end_year": "NULL"
                    },
                    "organization": "där"
                }
            ],
            "family": {
                "spouse": "Gunvor Falk",
                "marriage_year": "1951",
                "children": [
                    {
                        "name": "Per",
                        "birth_year": "1956"
                    }
                ]
            }
        }
    }
}