{
    "original": "LANDSTRÖM, J OLOF,\nlandstingsman, Gällivare, f i Dokkas, Norrb l,\n25/1/29 av köpm Oskar L o Anna Lasu.\nEg lastbilsåkeri sed 51. - Styr:led\nGällivare lastbilcentral, Norrb åkerifören,\nKilafors ind ab. - Landst:man sed 67, led\n\nkomm:fullm sed 63,  komm:nd sed 64,\n\nstyr :led Stift Gällivare-hem sed 64, stift\n\nDundrets friluftsanläggn sed 67. - Hobby:\n\nsport.\n\nGift 53 m Mairitt Juntti f 31, dtr t Vil-\n\nhard J o Emma Lehto. - Barn: Inger\n\nf 54, Karin f 55, Eva f 57.\n\nLANGE, HÅKAN J A, fd landsfiskal,\n\nDelsbo, f 24/9/01 av landsfogde J V L o\nHermanna Ihre.\n\nLandsfiskalsex 25, e landsfiskal Ramnäs\ndistr 22, landsfiskal Delsbo distr 35-64.\n- Ordf brandstyr 37-58. - Utm: RNO,\nSvBrfbftjtG, SvJägFftjtG, Sv djursk:förb\nftjtG, SCFftjtG. - Hobbies: fiske, jakt.\nGift 35 m Maj Ehrenberg, dtr t agr Nils\nE o Dagmar Matthiesen. - Barn:\nHarald f 35, Johan f 36, Dagmar f 44.\n\nLANNÉR, JAN R F, direktör, Frösön,\nf i Härnösand 12/12/14 av grossh Folke\nL o Elise Svanholm.\n\nStud:ex 35, anst Sundsvallsbkn 36, kamr\nMell Norrl centr:kassa f jordbr:kredit\nÖstersund 46, verkst dir där sed 57.\n-Medl Odd Fellow. - Hobby: bridge.\nGift 40 m Sylvia Kristoffersson f 14,\ndtr t snick:mast Olof K o Olivia\nKarlsson. - Barn: Ingegerd f 40, Jan-Olof\nf 44, Stig f 46.\n\nLANNÅS, BÖRJE H,\nbyggnadsingenjör SBR, Ljusdal, f i Gävle 24/3/17.\nTekn yrkessk Skutskär 34-35, Bröd\nPåhl-mans hdlI 43, ing :ex STI byggn 46 samt\nVoV 48; byggn:ing Allm byggn ab\nALBA Sthlm 47, mätn:man\nByggmäst:-fören 47, komm:ing Arbrå 50, proj:led\no kontr konsultfirma Byggteknik\nLjusdal 55, eg konsult verksamh sed 57.\n-Medl Rotary, TempelrO, NTO.\nGift 59 m sjuksköt Gunn Johansson\nf 25. - Barn: Staffan f 60, Mårten f 63.\n\n",
    "structured": {
        "0": {
            "full_name": "J Olof Landström",
            "location": "Gällivare",
            "occupation": "Landstingsman",
            "birth_details": {
                "date": "25/01/1929",
                "place": "Dokkas, Norrbotten",
                "parents": "Oskar L o Anna Lasu"
            },
            "education": [],
            "career": [
                {
                    "position": "Styr:led",
                    "years": {
                        "start_year": 1967,
                        "end_year": null
                    },
                    "organization": "Gällivare lastbilcentral"
                },
                {
                    "position": "Styr:led",
                    "years": {
                        "start_year": 1967,
                        "end_year": null
                    },
                    "organization": "Dundrets friluftsanläggn"
                }
            ],
            "family": {
                "spouse": "Mairitt Juntti",
                "marriage_year": "1953",
                "children": [
                    {
                        "name": "Inger",
                        "birth_year": "1954"
                    },
                    {
                        "name": "Karin",
                        "birth_year": "1955"
                    },
                    {
                        "name": "Eva",
                        "birth_year": "1957"
                    }
                ]
            }
        },
        "1": {
            "full_name": "Håkan J A Lange",
            "location": "Delsbo",
            "occupation": "Fd Landsfiskal",
            "birth_details": {
                "date": "24/09/1901",
                "place": null,
                "parents": "J V L o Hermanna Ihre"
            },
            "education": [],
            "career": [
                {
                    "position": "Landsfiskalsex",
                    "years": {
                        "start_year": 1925,
                        "end_year": null
                    },
                    "organization": null
                },
                {
                    "position": "Utm",
                    "years": {
                        "start_year": 1935,
                        "end_year": 1964
                    },
                    "organization": null
                }
            ],
            "family": {
                "spouse": "Maj Ehrenberg",
                "marriage_year": "1935",
                "children": [
                    {
                        "name": "Harald",
                        "birth_year": "1935"
                    },
                    {
                        "name": "Johan",
                        "birth_year": "1936"
                    },
                    {
                        "name": "Dagmar",
                        "birth_year": "1944"
                    }
                ]
            }
        },
        "2": {
            "full_name": "Jan R F Lannér",
            "location": "Frösön",
            "occupation": "Direktör",
            "birth_details": {
                "date": "12/12/1914",
                "place": "Härnösand",
                "parents": "Folke L o Elise Svanholm"
            },
            "education": [],
            "career": [
                {
                    "position": "Verkst dir",
                    "years": {
                        "start_year": 1957,
                        "end_year": null
                    },
                    "organization": "Östersund"
                }
            ],
            "family": {
                "spouse": "Sylvia Kristoffersson",
                "marriage_year": "1940",
                "children": [
                    {
                        "name": "Ingegerd",
                        "birth_year": "1940"
                    },
                    {
                        "name": "Jan-Olof",
                        "birth_year": "1944"
                    },
                    {
                        "name": "Stig",
                        "birth_year": "1946"
                    }
                ]
            }
        },
        "3": {
            "full_name": "Börje H Lannås",
            "location": "Ljusdal",
            "occupation": "Byggnadsingenjör SBR",
            "birth_details": {
                "date": "24/03/1917",
                "place": "Gävle",
                "parents": null
            },
            "education": [],
            "career": [
                {
                    "position": "Proj:led",
                    "years": {
                        "start_year": 1955,
                        "end_year": null
                    },
                    "organization": "Ljusdal"
                }
            ],
            "family": {
                "spouse": "Gunn Johansson",
                "marriage_year": "1959",
                "children": [
                    {
                        "name": "Staffan",
                        "birth_year": "1960"
                    },
                    {
                        "name": "Mårten",
                        "birth_year": "1963"
                    }
                ]
            }
        }
    }
}