{
    "original": "LILLE, GUNNAR T, tandläkare,\nArvidsjaur, f i Sthlm 16/1/17 av tjm Albin\nL o Märta Jansson.\n\nStud:ex 44 o tandl:ex 56 Sthlm, tandl\nfolktandv Sthlms l 56, skoltandl Sthlm\n57, distr :tandl o förest distr :tandpol\nStora Skedvi 58-60, priv:prakt\nArvidsjaur sed 60 o Sorsele sed 62.\nGift 1) 47-59 m Margit Sundin f 12, 2)\n63 m Monica Franklin f 39. - Barn:\ni l:a akt Christer f 48, Staffan f 52,\ni 2:a akt Nils-Gunnar f 64.\n\nLILLJE B ACK,   ERIK   O,   disponent,\n\nGällivare, f  i Luleå  8/1/27  av grossh\n\nOscar L o Lilly Ringdahl.\n\nLuleå  HdlI  45,  anst  VV:verket  Luleå\n\n45-57,   försäljn:ch   Philipsons   i   Luleå\n\nbil ab 58, disp Philipsons Gällivare o\n\nKiruna  sed  62.  - Led undervisn :rådet\n\nGällivare komm yrkessk. - Medl Round\n\nTable,  Odd  Fellow.  -  Hobbies: fiske,\n\nsegling, bowling, schack.\n\nGift 51 m Sonja Johansson, dtr t Arvid\n\nJ o Agda J.\n\nLILLJEKVIST, RAGNHILD E, leg\nläkare, Umeå, f i Sthlm 13/1/20 av\nciv:-ing Ragnar L o Maja Hall.\nStud:ex Vänersborg 38, med kand 43 o\nmed lic Upps 50, underläk Bollnäs las\n50-53, kir avd Sala las 53-56, med avd\nBollnäs las 55-56, l:e underläk kir avd\nSala las 57-60, anestesiklin Umeå las\n60-61, plastikkir klin där sed 61. - Stud\nUSA 51-52. - Styr:led Yrkeskvinnors\nsamarb :f örb sed 60.\n\n",
    "structured": {
        "0": {
            "full_name": "Gunnar T Lille",
            "location": "Arvidsjaur",
            "occupation": "Tandläkare",
            "birth_details": {
                "date": "16/01/1917",
                "place": "Stockholm",
                "parents": "tjm Albin L o Märta Jansson"
            },
            "education": [
                {
                    "degree": "Stud:ex",
                    "year": "1944",
                    "institution": "Stockholm"
                },
                {
                    "degree": "tandl:ex",
                    "year": "1956",
                    "institution": "Stockholm"
                }
            ],
            "career": [
                {
                    "position": "tandl folktandv",
                    "years": {
                        "start_year": 1956,
                        "end_year": 1956
                    },
                    "organization": "Sthlms l"
                },
                {
                    "position": "skoltandl",
                    "years": {
                        "start_year": 1957,
                        "end_year": 1957
                    },
                    "organization": "Sthlm"
                },
                {
                    "position": "distr :tandl o förest distr :tandpol",
                    "years": {
                        "start_year": 1958,
                        "end_year": 1960
                    },
                    "organization": "Stora Skedvi"
                },
                {
                    "position": "priv:prakt",
                    "years": {
                        "start_year": 1960
                    },
                    "organization": "Arvidsjaur"
                },
                {
                    "position": "priv:prakt",
                    "years": {
                        "start_year": 1962
                    },
                    "organization": "Sorsele"
                }
            ],
            "family": {
                "spouse": "Margit Sundin",
                "marriage_year": "1947",
                "children": [
                    {
                        "name": "Christer",
                        "birth_year": "1948"
                    },
                    {
                        "name": "Staffan",
                        "birth_year": "1952"
                    },
                    {
                        "name": "Nils-Gunnar",
                        "birth_year": "1964"
                    }
                ]
            }
        },
        "1": {
            "full_name": "Erik O Lilljeback",
            "location": "Gällivare",
            "occupation": "Disponent",
            "birth_details": {
                "date": "08/01/1927",
                "place": "Luleå",
                "parents": "grossh Oscar L o Lilly Ringdahl"
            },
            "education": [
                {
                    "degree": "Luleå HdlI",
                    "year": "1945",
                    "institution": "Luleå"
                }
            ],
            "career": [
                {
                    "position": "anst VV:verket",
                    "years": {
                        "start_year": 1945,
                        "end_year": 1957
                    },
                    "organization": "Luleå"
                },
                {
                    "position": "försäljn:ch",
                    "years": {
                        "start_year": 1958
                    },
                    "organization": "Philipsons i Luleå bil ab"
                },
                {
                    "position": "disp",
                    "years": {
                        "start_year": 1962
                    },
                    "organization": "Philipsons Gällivare o Kiruna"
                }
            ],
            "family": {
                "spouse": "Sonja Johansson",
                "marriage_year": "1951"
            },
            "hobbies": [
                "fiske",
                "segling",
                "bowling",
                "schack"
            ]
        },
        "2": {
            "full_name": "Ragnhild E Lilljekvist",
            "location": "Umeå",
            "occupation": "Leg läkare",
            "birth_details": {
                "date": "13/01/1920",
                "place": "Stockholm",
                "parents": "civ:-ing Ragnar L o Maja Hall"
            },
            "education": [
                {
                    "degree": "Stud:ex",
                    "year": "1938",
                    "institution": "Vänersborg"
                },
                {
                    "degree": "med kand",
                    "year": "1943",
                    "institution": "Upps"
                },
                {
                    "degree": "med lic",
                    "year": "1950",
                    "institution": "Upps"
                }
            ],
            "career": [
                {
                    "position": "underläk Bollnäs las",
                    "years": {
                        "start_year": 1950,
                        "end_year": 1953
                    }
                },
                {
                    "position": "kir avd Sala las",
                    "years": {
                        "start_year": 1953,
                        "end_year": 1956
                    }
                },
                {
                    "position": "med avd Bollnäs las",
                    "years": {
                        "start_year": 1955,
                        "end_year": 1956
                    }
                },
                {
                    "position": "l:e underläk kir avd Sala las",
                    "years": {
                        "start_year": 1957,
                        "end_year": 1960
                    }
                },
                {
                    "position": "anestesiklin Umeå las",
                    "years": {
                        "start_year": 1960,
                        "end_year": 1961
                    }
                },
                {
                    "position": "plastikkir klin",
                    "years": {
                        "start_year": 1961
                    },
                    "organization": "Umeå las"
                }
            ],
            "family": {
                "spouse": "NULL",
                "marriage_year": "NULL"
            },
            "community_involvement": [
                {
                    "role": "Styr:led",
                    "organization": "Yrkeskvinnors samarb :f örb",
                    "years": "sed 1960"
                }
            ]
        }
    }
}