{
    "original": "MELLQUIST, LARS E G, fd överste,\nSthlm, f i V Vingåker, Södermani l,\n\n28/5/84 av godsarrendator Eric M o\nIda Petersson.\n\nUnderlöjtn I 16 06, l’öjtn 10, kapt gst\n19, I 18 25, major gst 28, överstelöjtn\ndär 32, I 4 33, överste på resistat 37,\nres 44. - Lär i strategi KHS 2(V25,\ngsttjänst 27-28, taktik 31-33-. - LKrVA.\n\n-     Utm:    RSO,    RVO,    OffLitGedO,\nRFinlVROlkl.\n\nGift 13 m Greta Sonesson, f 91, dtr t\nhandl Axel S o Maria Sjöholm.\n\nM ELLSTRÖM, G ÅKE,\nekonomidirektör, Sthlm, f i Gbg 23/11/13 av\növerlär Gustaf M o Thea Carlberg.\nHdlsgymn 34, stud Pittsburgh Univ 59.\n-Ekonomidir Sv Esso ab sed 62. -\nSkattmäst 13 års män sed 57. - Utm:\nPro-PatrstGM. - Hobbies: schack, bridge,\ntennis.\n\nGift 41 m Kajsa Andersson f 17.\n-Barn: Hans f 42, Kerstin f 46.\n\nMELO, BERNHARD B, tandläkare,\nSthlm, f i Tessaloniki, Grekland, 21/4/24\nav dr Abraham M o Eleonore\nFlorentine.\n\nStudrex Grekl, med kand Aten’ 43,\ntand-läk :ex Malmö 54, stud Roms o Paris\nmed fak 58. - Förest o distr :tandläk\nfol’ktandv Sthlms l 56, praktik Sthlm\nsed 58. - Stud o tandFäk öl eng odont\nanst 60. - Styr:led Sv:es reseledares\nriksförb. - Medl Sv:es tandläkiförb,\nSthlms tandläk:fören, Sv tandläkrsällsk.\n\n-   Skr:  på  grek,  ital  o  sp  spr  i  med\nodont    ämnen.    -    Hobbies:    filologi,\nspråk,    målning,    fotografering,    sport,\ntennis.\n\nMENDEL, JOSEF, apotekare, Tumba,\nf i Gbg 7/10/02 av handl I M o h h.\nStud:ex 22, farm kand 26, apot:ex 31,\ninneh apot Tumba m filialapot i\nHuddinge sed 48.\n\nGift m Helga Åhsberg, dtr t gjutmäst\nC Å o Josefine Å. - Barn: Margareta\nf 33, Lennart f 35.\n\nvon   MENTZER,   CARL   W   R   L,\n\növerste, Oslo, f i Rödbo, Gbgs o Bohus\nl, 24/1/10 av kapten C A L v M o\nfrihran Toni v Malapert-Neufville.\nStud:ex Halmstad 28, off:ex 31, löjtn\nI 16 35, kapt 42, major 50, öv:löjtn\n56, överste v fst o i I 16 62. - KHS\n42-44. - Bitr miliatt Berlin 38-39, lär\nKS 44-47, t ordf i bef:utredn:s förfog\n51-53, tjg Korea 53-54, skolch InfKS\n57-60, försvratt Oslo sed 61. - Utm:\nRSO, KIranHYO, CFBSM, SFKftjSM.\nGift 34 m Greta Schönbeck f 10. - Barn:\nCarl Johan f 35, Carl Fredrik f 36, Carl\nGustaf f 39, Carl Mikael f 44.\n\n",
    "structured": {
        "0": {
            "full_name": "Lars E G Mellquist",
            "location": "Sthlm",
            "occupation": "fd överste",
            "birth_details": {
                "date": "28/05/1884",
                "place": "V Vingåker, Södermani l",
                "parents": "godsarrendator Eric M o Ida Petersson"
            },
            "education": [],
            "career": [
                {
                    "position": "Underlöjtn",
                    "years": {
                        "start_year": 1906,
                        "end_year": 1910
                    },
                    "organization": "I 16"
                },
                {
                    "position": "l’öjtn",
                    "years": {
                        "start_year": 1910,
                        "end_year": 1925
                    },
                    "organization": "I 18"
                },
                {
                    "position": "kapt gst",
                    "years": {
                        "start_year": 1925,
                        "end_year": 1928
                    },
                    "organization": "I 18"
                },
                {
                    "position": "major gst",
                    "years": {
                        "start_year": 1928,
                        "end_year": 1932
                    },
                    "organization": "I 4"
                },
                {
                    "position": "överstelöjtn",
                    "years": {
                        "start_year": 1932,
                        "end_year": 1933
                    },
                    "organization": "I 4"
                },
                {
                    "position": "överste på resistat",
                    "years": {
                        "start_year": 1933,
                        "end_year": 1937
                    }
                },
                {
                    "position": "res",
                    "years": {
                        "start_year": 1937,
                        "end_year": 1944
                    }
                }
            ],
            "family": {
                "spouse": "Greta Sonesson",
                "marriage_year": "1913",
                "children": []
            }
        },
        "1": {
            "full_name": "G Åke Mellström",
            "location": "Sthlm",
            "occupation": "ekonomidirektör",
            "birth_details": {
                "date": "23/11/1913",
                "place": "Gbg",
                "parents": "överlär Gustaf M o Thea Carlberg"
            },
            "education": [
                {
                    "degree": "Hdlsgymn",
                    "year": "1934",
                    "institution": "NULL"
                },
                {
                    "degree": "stud Pittsburgh Univ",
                    "year": "1959",
                    "institution": "NULL"
                }
            ],
            "career": [],
            "family": {
                "spouse": "Kajsa Andersson",
                "marriage_year": "1941",
                "children": [
                    {
                        "name": "Hans",
                        "birth_year": "1942"
                    },
                    {
                        "name": "Kerstin",
                        "birth_year": "1946"
                    }
                ]
            }
        },
        "2": {
            "full_name": "Bernhard B Melo",
            "location": "Sthlm",
            "occupation": "tandläkare",
            "birth_details": {
                "date": "21/04/1924",
                "place": "Tessaloniki, Grekland",
                "parents": "dr Abraham M o Eleonore Florentine"
            },
            "education": [
                {
                    "degree": "Studrex Grekl",
                    "year": "1943",
                    "institution": "NULL"
                },
                {
                    "degree": "med kand Aten’",
                    "year": "1943",
                    "institution": "NULL"
                },
                {
                    "degree": "tand-läk :ex Malmö",
                    "year": "1954",
                    "institution": "NULL"
                },
                {
                    "degree": "stud Roms o Paris med fak",
                    "year": "1958",
                    "institution": "NULL"
                }
            ],
            "career": [
                {
                    "position": "Förest o distr :tandläk fol’ktandv",
                    "years": {
                        "start_year": 1956,
                        "end_year": 1958
                    },
                    "organization": "Sthlms l"
                },
                {
                    "position": "praktik",
                    "years": {
                        "start_year": 1958,
                        "end_year": "NULL"
                    },
                    "organization": "Sthlm"
                }
            ],
            "family": {
                "spouse": "NULL",
                "marriage_year": "NULL",
                "children": []
            }
        },
        "3": {
            "full_name": "Josef Mendel",
            "location": "Tumba",
            "occupation": "apotekare",
            "birth_details": {
                "date": "07/10/1902",
                "place": "Tessaloniki, Grekland",
                "parents": "handl I M o h h"
            },
            "education": [
                {
                    "degree": "Stud:ex",
                    "year": "1922",
                    "institution": "NULL"
                },
                {
                    "degree": "farm kand",
                    "year": "1926",
                    "institution": "NULL"
                },
                {
                    "degree": "apot:ex",
                    "year": "1931",
                    "institution": "NULL"
                }
            ],
            "career": [],
            "family": {
                "spouse": "Helga Åhsberg",
                "marriage_year": "NULL",
                "children": [
                    {
                        "name": "Margareta",
                        "birth_year": "1933"
                    },
                    {
                        "name": "Lennart",
                        "birth_year": "1935"
                    }
                ]
            }
        },
        "4": {
            "full_name": "Carl W R L von Mentzer",
            "location": "Oslo",
            "occupation": "överste",
            "birth_details": {
                "date": "24/01/1910",
                "place": "Rödbo, Gbgs o Bohus l",
                "parents": "kapten C A L v M o frihran Toni v Malapert-Neufville"
            },
            "education": [
                {
                    "degree": "Stud:ex",
                    "year": "1928"
                },
                {
                    "degree": "off:ex",
                    "year": "1931"
                }
            ],
            "career": [
                {
                    "position": "löjtn",
                    "years": {
                        "start_year": 1935,
                        "end_year": 1942
                    },
                    "organization": "I 16"
                },
                {
                    "position": "kapt",
                    "years": {
                        "start_year": 1942,
                        "end_year": 1950
                    },
                    "organization": "NULL"
                },
                {
                    "position": "major",
                    "years": {
                        "start_year": 1950,
                        "end_year": 1956
                    },
                    "organization": "NULL"
                },
                {
                    "position": "öv:löjtn",
                    "years": {
                        "start_year": 1956,
                        "end_year": 1962
                    },
                    "organization": "NULL"
                },
                {
                    "position": "överste v fst o i",
                    "years": {
                        "start_year": 1962,
                        "end_year": "NULL"
                    },
                    "organization": "I 16"
                }
            ],
            "family": {
                "spouse": "Greta Schönbeck",
                "marriage_year": "1934",
                "children": [
                    {
                        "name": "Carl Johan",
                        "birth_year": "1935"
                    },
                    {
                        "name": "Carl Fredrik",
                        "birth_year": "1936"
                    },
                    {
                        "name": "Carl Gustaf",
                        "birth_year": "1939"
                    },
                    {
                        "name": "Carl Mikael",
                        "birth_year": "1944"
                    }
                ]
            }
        }
    }
}