{
    "original": "MALMBERG, C J GUNNAR,\nbergsingenjör, Sthlm, f i Sthlm 21/4/82 av\ning Fredrik M o Isabella Boklund.\nStudrex 01, KTH 05, ritare Cambria\nSteel Co Jonsto wn 07, kemist o\nmikroskopist Kohlswa jernvrab 08,\nmartin-o provnring där 09, chefsmetalltirg\nSurahammars bruk 19-48. - Skr: upps i JKA.\n- Utm: IVArs mindre GM (f uppfinn\nav carbometern).\nGift 10 m Karin Sundstedt f 88, dtr t\n\nkapten Johan S o Sophie Forsstrand.\n-Barn: Gunnar fil, Ingvor f 14, Einar\nf 14, Bertil f 16, Birgit f 19, Lisbeth f 25.\n\nMALMBERG, F GUNNAR,\ntandläkare Bromma, f i Östhammar 7/6/27\nav apot Nils Eriksson o Signe\nMalmberg.\n\nStudrex Nykpg 46, tandläkrex Sthlm 52,\ndistrrtandläk 52, ass i privatpraktik 54,\neg prakt sed 56. - Medl Sv\ntandläkr-förb, Sthlms tandläkrfören, Sv\ntandläkr-sällsk. - Hobbies: tennis, sjöidrott.\nGift 55 m Gunilla Hermansson f 33,\ndtr t försäljnrchef Erik H o Astrid\nGraucob. - Barn: Per f 56, Jan f 57.\n\nMALMBERG, HANS H, fotograf,\nVällingby, f i Solna 20/9/27 av verkmäst\nLinus Eugen M o Zewi Andersson.\nFotograf kurs 41-43, pressfotograf 43,\nfree lance reportagefotograf sed 46, medl\nTio fotografer sed 58. - Reportageres\nt ett flert länder i Europa o t Japan,\nKorea o USA. - Delt i utst Family of\nMan. - Repr Natrmus, Mus of Modern\nArt New York. - Skr: Island (51) o\nIceknd (54) (till’s m Helgi Briem),\nDalälven - Industrifloden (tills m Sven\nRydberg 57).\n\nGift 50 m Margret Gudmundsdottir f\n28, dtr t kapten G Gudmundsson o\nMargret Jönsdotter. - Barn: Leif f 52,\nKristina f 54, Asa f 57.\n\nMALMBERG, O HARALD, fd\ngeneraldirektör, Sthlm, f i Malmö 4/6/83 av\nsparbanksvaktmäst Nils M o Anna\nJönsson.\n\nStudrex 01, lantmätrex 04, aman\nlant-mätrstyr 08, byråing där 10, eo\ndistrr-lantmät Kalmar 13, l re lantaät Jönkpgs\nl 19, överlantmät Kopparb l 24, genrdir\no ch lantmätrstyr 33’-48. - Stadsfullm\nFalun, ordf länets exproprrndr, led\nKopparb l:s landsting 31-34, las rdirekt\nFalun 31-33, soc jordutredn 33-36, ordf\nutredn f kommunal samv 39^45,\nkartvr-utredn 35-37, 36 års egnahrutredn 36-39,\nkartvrkomm 37-48, civilist:s\nunderstöds-n&lt;d 37-48, Sthlms stads kristidsnd\n40-49, fastighrbildnrsakk 39^53’, styrrled Sv\nallmogehems småbrukarfond 40-60, KTH\n41-47, ordf Djurgårdsndn 47-54, led\negnahemsstyr 37-48, stadspir utredn 42-45,45\nårs markkommiss 45-48, lantbr:styr\n48-53, deleg f förhandl om Bromma\nflygplats 54-57, stat rev Sv hdlsbkn 48-54,\nutredn rman rör ströängar i Lappl o\nmyr-slogar i Dalarne 53-59, led lantbrrsakk\n45, ordf Frimrbarnhusets direkt 50.\n-LSLA 45. - Utm: KmstkNO, RCXIIIrs\nO, RVO, KFinlVROlkl, KNSrtOOmstj,\nSrtEM, Iqml 12:e storl.\n\nGift 11 m Edith Westberg f 86. - Barn:\nBritta f 13, Marianne f 16.\n\n",
    "structured": {
        "1": {
            "full_name": "MALMBERG, C J GUNNAR",
            "location": "Sthlm",
            "occupation": "bergsingenjör",
            "birth_details": {
                "date": "21/04/1882",
                "place": "Sthlm",
                "parents": "ing Fredrik M o Isabella Boklund"
            },
            "education": [
                {
                    "degree": "Studrex",
                    "year": "1901",
                    "institution": "KTH"
                }
            ],
            "career": [
                {
                    "position": "ritare",
                    "years": {
                        "start_year": 1905,
                        "end_year": 1907
                    },
                    "organization": "Cambria Steel Co Jonsto wn"
                },
                {
                    "position": "kemist o mikroskopist",
                    "years": {
                        "start_year": 1908,
                        "end_year": 1909
                    },
                    "organization": "Kohlswa jernvrab"
                },
                {
                    "position": "martin-o provnring",
                    "years": {
                        "start_year": 1909,
                        "end_year": 1919
                    },
                    "organization": "Surahammars bruk"
                }
            ],
            "family": {
                "spouse": "Karin Sundstedt",
                "marriage_year": "1910",
                "children": [
                    {
                        "name": "Gunnar fil",
                        "birth_year": "1911"
                    },
                    {
                        "name": "Ingvor",
                        "birth_year": "1914"
                    },
                    {
                        "name": "Einar",
                        "birth_year": "1914"
                    },
                    {
                        "name": "Bertil",
                        "birth_year": "1916"
                    },
                    {
                        "name": "Birgit",
                        "birth_year": "1919"
                    },
                    {
                        "name": "Lisbeth",
                        "birth_year": "1925"
                    }
                ]
            }
        },
        "2": {
            "full_name": "MALMBERG, F GUNNAR",
            "location": "Bromma",
            "occupation": "tandläkare",
            "birth_details": {
                "date": "7/06/1927",
                "place": "Östhammar",
                "parents": "apot Nils Eriksson o Signe Malmberg"
            },
            "education": [
                {
                    "degree": "Studrex",
                    "year": "1946",
                    "institution": "Nykpg"
                },
                {
                    "degree": "tandläkrex",
                    "year": "1952",
                    "institution": "Sthlm"
                }
            ],
            "career": [
                {
                    "position": "distrrtandläk",
                    "years": {
                        "start_year": 1952,
                        "end_year": null
                    }
                },
                {
                    "position": "ass i privatpraktik",
                    "years": {
                        "start_year": 1954,
                        "end_year": null
                    }
                }
            ],
            "family": {
                "spouse": "Gunilla Hermansson",
                "marriage_year": "1955",
                "children": [
                    {
                        "name": "Per",
                        "birth_year": "1956"
                    },
                    {
                        "name": "Jan",
                        "birth_year": "1957"
                    }
                ]
            },
            "hobbies": [
                "tennis",
                "sjöidrott"
            ]
        },
        "3": {
            "full_name": "MALMBERG, HANS H",
            "location": "Vällingby",
            "occupation": "fotograf",
            "birth_details": {
                "date": "20/09/1927",
                "place": "Solna",
                "parents": "verkmäst Linus Eugen M o Zewi Andersson"
            },
            "career": [
                {
                    "position": "pressfotograf",
                    "years": {
                        "start_year": 1943,
                        "end_year": null
                    }
                },
                {
                    "position": "free lance reportagefotograf",
                    "years": {
                        "start_year": 1946,
                        "end_year": null
                    }
                }
            ],
            "family": {
                "spouse": "Margret Gudmundsdottir",
                "marriage_year": "1950",
                "children": [
                    {
                        "name": "Leif",
                        "birth_year": "1952"
                    },
                    {
                        "name": "Kristina",
                        "birth_year": "1954"
                    },
                    {
                        "name": "Asa",
                        "birth_year": "1957"
                    }
                ]
            }
        },
        "4": {
            "full_name": "MALMBERG, O HARALD",
            "location": "Sthlm",
            "occupation": "fd generaldirektör",
            "birth_details": {
                "date": "4/06/1883",
                "place": "Malmö",
                "parents": "sparbanksvaktmäst Nils M o Anna Jönsson"
            },
            "education": [
                {
                    "degree": "Studrex",
                    "year": "1901",
                    "institution": null
                },
                {
                    "degree": "lantmätrex",
                    "year": "1904",
                    "institution": null
                }
            ],
            "career": [
                {
                    "position": "aman lantmätrstyr",
                    "years": {
                        "start_year": 1908,
                        "end_year": 1910
                    }
                },
                {
                    "position": "genrdir o ch lantmätrstyr",
                    "years": {
                        "start_year": 1933,
                        "end_year": 1948
                    }
                }
            ],
            "family": {
                "spouse": "Edith Westberg",
                "marriage_year": "1911",
                "children": [
                    {
                        "name": "Britta",
                        "birth_year": "1913"
                    },
                    {
                        "name": "Marianne",
                        "birth_year": "1916"
                    }
                ]
            }
        }
    }
}