{
    "original": "MANNERFELT, NILS O G,\nhovrättsassessor, Johanneshov, f i Solna 11/6/24\nav landsh Carl M o Maja Lindbom.\nStud:ex Skara 43&lt;, jur kand Upps 48,\ntingstjg Inlands doms 49-52, fiskal Svea\nhovr, adj led 57-59, assess sed 59.\n-Bitr expert stat orgrnd 54-55, sekr\narb:-domst 55-57, föredr riksd särsk\npens:-utsk 59, sekr 58 års näringsrättssakk\n59-62.\n\nGift 49 m Ulla Hemmingsson, f 26, dtr\nt l:e provrläk Sixten H o Elli H.\n\nMANNERSTEDT, FOLKE K E,\ncivilingenjör, Bromma, f i Sthlm 5/4/01\nav överstelöjtn P M o Elin Kling.\nStudrex 19, KTH 27, ch\nmotorcykel-tillverkn Husqvarna vapenfabr ab\n29-35, konstr:ch Lovén &amp; Co ab 39-41, lär\nAIHS, STI sed 36, eg konsult\nverksamh Sthlm sed 35. - Konstr segrande\nmotorcykl i sv, fr o ital Grand Prix, sv\narm motorcykl (fi mod), SRM-motorn,\n\n-  Led KAKrs o M:s tekn komm, SKIF,\nLSvTF.\n\nGift 25 m Karin Palmqvist f 04, dtr\nt Axel P o Emma Jansson. - Barn:\nMargareta f 26, Ann-Marie f 27, Märta\nf 29, Per-Magnus f 34, Ulf f 43.\n\nMANNERSTRÅLE, G H MÅRTEN,\ndirektör, Sthlm, f i Linkpg 29/12/16\nav major Gustav M o Kjerstin\nTillberg.\n\nStudrex 37, KTH 44, konstr Sv ab\nChris-tiani &amp; Nielsen 44, verkst dir Allm sv\nstädn ab sed 46. - Sakk städnrutredn\n51-53, medl golvgruppen stat nd f\nbyggn:forskn 55-60.\n\nGift 44 m Marianne Svenson f 20, dtr t\nköpman Fritz S o Elsa S. - Barn:\nChristina f 44, Ulf f 46, Henrik f 53,\n\nMANNFELT, SIGURD F M,\ntandläkare, Bromma, f i Sthlm 1/7/07 av\nlärov: ad j Frans M o Ingrid Sandberg.\nStud:ex Gbg 26, odont kand 28,\ntand:-läk:ex 31, ass Tandläkrinst\ntandfylln:-avd 34-36, e lär 37, vik laborator 3$,\ntf laborator 42-44, prakt Sthlm sed 3-3.\n\n-   Led   fortsättnrkursndn   36,   sekr   där\n36-42,   stynled   Sv   tandläk:sällsk   36,\nskattmäst 38. - Utm: RVO.\n\nGift 31 m Stina Hal’lberg. - Barn: Lars\nf 35, Lena f 37, Anita f 39.\n",
    "structured": {
        "1": {
            "full_name": "MANNERFELT, NILS O G",
            "location": "Johanneshov",
            "occupation": "hovrättsassessor",
            "birth_details": {
                "date": "11/06/1924",
                "place": "Solna",
                "parents": "landsh Carl M o Maja Lindbom"
            },
            "education": [
                {
                    "degree": "Studex",
                    "year": "1943",
                    "institution": "Skara"
                },
                {
                    "degree": "jur kand",
                    "year": "1948",
                    "institution": "Upps"
                }
            ],
            "career": [
                {
                    "position": "tingstjg",
                    "years": {
                        "start_year": 1949,
                        "end_year": 1952
                    },
                    "organization": "Inlands doms"
                },
                {
                    "position": "fiskal",
                    "years": {
                        "start_year": 1957,
                        "end_year": 1959
                    },
                    "organization": "Svea hovr"
                }
            ],
            "family": {
                "spouse": "Ulla Hemmingsson",
                "marriage_year": "1949",
                "children": [
                    {
                        "name": "l:e provrläk Sixten H o Elli H",
                        "birth_year": "26"
                    }
                ]
            }
        },
        "2": {
            "full_name": "MANNERSTEDT, FOLKE K E",
            "location": "Bromma",
            "occupation": "civilingenjör",
            "birth_details": {
                "date": "5/4/1901",
                "place": "Sthlm",
                "parents": "överstelöjtn P M o Elin Kling"
            },
            "education": [
                {
                    "degree": "Studrex",
                    "year": "1919",
                    "institution": "KTH 27"
                }
            ],
            "career": [
                {
                    "position": "motorcykel-tillverkn",
                    "years": {
                        "start_year": 1929,
                        "end_year": 1935
                    },
                    "organization": "Husqvarna vapenfabr ab"
                }
            ],
            "family": {
                "spouse": "Karin Palmqvist",
                "marriage_year": "1925",
                "children": [
                    {
                        "name": "Margareta",
                        "birth_year": "1926"
                    },
                    {
                        "name": "Ann-Marie",
                        "birth_year": "1927"
                    },
                    {
                        "name": "Märta",
                        "birth_year": "1929"
                    },
                    {
                        "name": "Per-Magnus",
                        "birth_year": "1934"
                    },
                    {
                        "name": "Ulf",
                        "birth_year": "1943"
                    }
                ]
            }
        },
        "3": {
            "full_name": "MANNERSTRÅLE, G H MÅRTEN",
            "location": "Sthlm",
            "occupation": "direktör",
            "birth_details": {
                "date": "29/12/1916",
                "place": "Linkpg",
                "parents": "major Gustav M o Kjerstin Tillberg"
            },
            "education": [
                {
                    "degree": "Studrex",
                    "year": "1937",
                    "institution": "KTH 44"
                }
            ],
            "career": [
                {
                    "position": "verkst dir",
                    "years": {
                        "start_year": 1946
                    },
                    "organization": "Allm sv städn ab"
                }
            ],
            "family": {
                "spouse": "Marianne Svenson",
                "marriage_year": "1944",
                "children": [
                    {
                        "name": "Christina",
                        "birth_year": "1944"
                    },
                    {
                        "name": "Ulf",
                        "birth_year": "1946"
                    },
                    {
                        "name": "Henrik",
                        "birth_year": "1953"
                    }
                ]
            }
        },
        "4": {
            "full_name": "MANNFELT, SIGURD F M",
            "location": "Bromma",
            "occupation": "tandläkare",
            "birth_details": {
                "date": "1/7/1907",
                "place": "Sthlm",
                "parents": "lärov: ad j Frans M o Ingrid Sandberg"
            },
            "education": [
                {
                    "degree": "Stud:ex",
                    "year": "1926",
                    "institution": "Gbg"
                },
                {
                    "degree": "odont kand",
                    "year": "1928",
                    "institution": "odont kand"
                }
            ],
            "career": [
                {
                    "position": "ass",
                    "years": {
                        "start_year": 1934,
                        "end_year": 1936
                    },
                    "organization": "Tandläkrinst tandfylln:-avd"
                }
            ],
            "family": {
                "spouse": "Stina Hallberg",
                "marriage_year": "1931",
                "children": [
                    {
                        "name": "Lars",
                        "birth_year": "1935"
                    },
                    {
                        "name": "Lena",
                        "birth_year": "1937"
                    },
                    {
                        "name": "Anita",
                        "birth_year": "1939"
                    }
                ]
            }
        }
    }
}