{
    "original": "MALMGREN, K EINAR F, tandläkare,\n\nSaltsjö-Duvnäs, f i Lund 5/6/22 av\ndir Edvard M o Elma Boberg.\nStud:ex Växjö 43, tandläk: ex 50, aman\no ass Tandläk:högsk Malmö 50, vik\ntandläk Tomelilla 55, eg praktik\nSaltsjöbaden sed 56. - Hobby: fotografering.\nGift 49 m tandläk Inga-Lis Tufvesson\nf 25, dtr t lantbr Alfred T o Elsa\nCarlsson. - Barn: Elisabet f 54, Carl-Henrik\nf 56.\n\nMALMGREN, OLOF P, arkitekt SAR,\nSthlm, f i Sthlm 23/12/22 av byråch\nE F M o Maria Jacobsson.\nStud:ex 43, KTH 51, anst h arkit SAR\nSture Frölén 52, eg arkit:verksamh 58,\ninneh Malmgren &amp; Ersahin arkit\nkontor ab sed 61. - Stud:resa t USA. - Bl\nutf arb: kyrka i Traneberg,\nförsaml:-hus, studenthus m m. - Hobbies:\nmusik, idrott, föreningsliv.\nGift 52 m Ingrid Palmgren f 21, dtr t\ning Nils P o Rut Crusell. - Barn:\nKarin f 53, Per f 56.\n\nMALMGREN, STIG E, leg läkare,\nSundbyberg, f i Sthlm 25/7/24 av\nbyrådir Einar M o Elin Morin.\nStud:ex 43, med kand 47, med lic 51,\nvik underläk kir avd Ersta sjh 51 o 52,\nunderläk Sophiahemmet 53, narkosutbildn\nKarol inst 54, underläk Norrbackainst\nsed 54.\n\nGift 48 m Anna-Nora Dahlström f 27.\n-Barn: Bo f 49.\n\nMALMKVIST se MALMQUIST\n\nMALMLÖW, E GÖTHE, tekn dr,\nDjursholm, f i Vännäs, Västerb l, 18/\n6/15 av lokförare Hilding M o Jenny\nLindström.\n\nElektrotekn facksk Västerås 36, KTH\n43, tekn dr 48, lab:ing Asea Västerås\n38, ch Aseas utbildn:sekt 45, dinass\nAsea Västerås 47, ch Aseas dotterbol\nNew York 49, Minnesota Mining &amp;\nMfg Co S:t Paul 56, tekn dir ab\nAtomenergi Sthlm sed 57. - Stynled\nKarlskronavarvet ab 61. - Skr: inom\nområdena material f elektroind, utrusttr.r f\nstål- o gruvind :na o kärnreaktorers\nkonstr o användn f kraft- o\nvärmeproduktion.\n\nGift 1) 40-54 m Kristina Holmberg f\n16 d 54, 2) m Lili Hyltén-Cavallius f\n17, dtr t regissör Ragnar H-C o Maud\nWarburg. - Barn: Monica f 42, Bo f 46.\n\n",
    "structured": {
        "1": {
            "full_name": "Malmgren, K Einar F",
            "location": "Saltsjö-Duvnäs",
            "occupation": "Tandläkare",
            "birth_details": {
                "date": "05/06/1922",
                "place": "Lund",
                "parents": "dir Edvard M o Elma Boberg"
            },
            "education": [
                {
                    "degree": "Stud:ex",
                    "year": "1943",
                    "institution": "Växjö"
                },
                {
                    "degree": "Tandläk: ex",
                    "year": "1950",
                    "institution": "Tandläk:högsk Malmö"
                }
            ],
            "career": [
                {
                    "position": "Aman o ass Tandläk:högsk Malmö",
                    "years": {
                        "start_year": 1950,
                        "end_year": 1950
                    }
                },
                {
                    "position": "Vik tandläk Tomelilla",
                    "years": {
                        "start_year": 1955,
                        "end_year": 1955
                    }
                },
                {
                    "position": "Eg praktik Saltsjöbaden",
                    "years": {
                        "start_year": 1956
                    }
                }
            ],
            "family": {
                "spouse": "tandläk Inga-Lis Tufvesson",
                "marriage_year": "1949",
                "children": [
                    {
                        "name": "Elisabet",
                        "birth_year": "1954"
                    },
                    {
                        "name": "Carl-Henrik",
                        "birth_year": "1956"
                    }
                ]
            },
            "hobbies": [
                "fotografering"
            ]
        },
        "2": {
            "full_name": "Malmgren, Olof P",
            "location": "Sthlm",
            "occupation": "Arkitekt SAR",
            "birth_details": {
                "date": "23/12/1922",
                "place": "Sthlm",
                "parents": "byråch E F M o Maria Jacobsson"
            },
            "education": [
                {
                    "degree": "Stud:ex",
                    "year": "1943"
                },
                {
                    "degree": "KTH",
                    "year": "1951"
                }
            ],
            "career": [
                {
                    "position": "Anst h arkit SAR",
                    "years": {
                        "start_year": 1952
                    }
                },
                {
                    "position": "Eg arkit:verksamh",
                    "years": {
                        "start_year": 1958
                    }
                },
                {
                    "position": "Inneh Malmgren & Ersahin arkit kontor ab",
                    "years": {
                        "start_year": 1961
                    }
                }
            ],
            "family": {
                "spouse": "Ingrid Palmgren",
                "marriage_year": "1952",
                "children": [
                    {
                        "name": "Karin",
                        "birth_year": "1953"
                    },
                    {
                        "name": "Per",
                        "birth_year": "1956"
                    }
                ]
            },
            "hobbies": [
                "musik",
                "idrott",
                "föreningsliv"
            ]
        },
        "3": {
            "full_name": "Malmgren, Stig E",
            "location": "Sundbyberg",
            "occupation": "Leg läkare",
            "birth_details": {
                "date": "25/07/1924",
                "place": "Sthlm",
                "parents": "byrådir Einar M o Elin Morin"
            },
            "education": [
                {
                    "degree": "Stud:ex",
                    "year": "1943"
                },
                {
                    "degree": "Med kand",
                    "year": "1947"
                },
                {
                    "degree": "Med lic",
                    "year": "1951"
                }
            ],
            "career": [
                {
                    "position": "Vik underläk kir avd Ersta sjh",
                    "years": {
                        "start_year": 1951,
                        "end_year": 1952
                    }
                },
                {
                    "position": "Underläk Sophiahemmet",
                    "years": {
                        "start_year": 1953
                    }
                },
                {
                    "position": "Narkosutbildn Karol inst",
                    "years": {
                        "start_year": 1954
                    }
                },
                {
                    "position": "Underläk Norrbackainst",
                    "years": {
                        "start_year": 1954
                    }
                }
            ],
            "family": {
                "spouse": "Anna-Nora Dahlström",
                "marriage_year": "1948",
                "children": [
                    {
                        "name": "Bo",
                        "birth_year": "1949"
                    }
                ]
            }
        },
        "4": {
            "full_name": "Malmkvist",
            "location": "NULL",
            "occupation": "NULL",
            "birth_details": {
                "date": "NULL",
                "place": "NULL",
                "parents": "NULL"
            },
            "education": [],
            "career": [],
            "family": {},
            "hobbies": []
        },
        "5": {
            "full_name": "Malmkvist",
            "location": "NULL",
            "occupation": "NULL",
            "birth_details": {
                "date": "NULL",
                "place": "NULL",
                "parents": "NULL"
            },
            "education": [],
            "career": [],
            "family": {},
            "hobbies": []
        },
        "6": {
            "full_name": "Malmkvist",
            "location": "NULL",
            "occupation": "NULL",
            "birth_details": {
                "date": "NULL",
                "place": "NULL",
                "parents": "NULL"
            },
            "education": [],
            "career": [],
            "family": {},
            "hobbies": []
        },
        "7": {
            "full_name": "Malmkvist",
            "location": "NULL",
            "occupation": "NULL",
            "birth_details": {
                "date": "NULL",
                "place": "NULL",
                "parents": "NULL"
            },
            "education": [],
            "career": [],
            "family": {},
            "hobbies": []
        }
    }
}