{
    "original": "MIKAELSSON, JOHN F,\ntransport-arbetare, gångare, Sundbyberg, f i\nKristinehamn 6/12/13 av timmerman\nAugust M o Maria Karlsson.\nAnst Örliogsvarvet marinverkstäderna\nSthlm sed 46. - Vann EM 46,\nguldmedalj på 10 km OS 48 o 52, har noterats\nf 16 världsrekord. - Utm: Prins\nGustav Adolfs MM, Sv GångförbGplakmm.\nGift 42 m Svea Thelin f 17, dtr t\nverk-stadsarb Hädar T o Hulda Schönning.\n-Barn: Gun f 44.\n\nMILLAR, NILS E, förste\nhovintendent, Sthlm, f i Sthlm 23/7/07 av\nförman Axel M o Johanna Svensson.\nStud:ex 26, resebyråtjm 27-35, sekr\nKronprinsens hovmarskalksämb 36,\nhovkamrer 43, hovintend 45, l:e\nhovintendent sed 58. - Delt i kronprinsparets\nresor t Främre Orienten 34-35, USA\n38. - Utm: GV:sJmtII, RNO, RVO,\nNyaSvM, KIranKrO, RDDO,\nOffEt-SO, RFinlVROlkl, RIFO, OffNedOHO,\nRNS:tOOlkl, OffStbVO, EgyptNilO5kl,\nRGrFenO, IrakRO5kl, IranHYO5kl.\nGift 42 m Kerstin Lagerquist f 17, dtr\nt överstelöjtn Birger L o Elsa\nPihl-ström. - Barn: Charlotte f 43, Peter f\n48.\n\nMILLES,    OLGA,    porträttmålarinna,\n\nCranbrook, Bloomfield Hills, Mich, USA\nf i Leibnitz 24/1/74 av f in: kontrollör\nAnton Granner o Rosalia Kornberger.\nStud Graz Malerakad 87-92, Azbe\nMünchen 93-95, Colarossi Paris 99-01.\n\n-   Utf talr portr, mest i pastell. - Ordf\nstift Carl o Olga Milles Lidingöhem 56.\nGift 05 m prof Carl M f 75 d 55.\n\nMILLES,  ROLF  A  E,   civilingenjör,\n\nLidingö, f i Sthlm 15/1/15 av dir T M\n\n0   Thora Rutensköld.\n\nKTH 38, anst ab Hg Relay pat 39,\navd:ch Sv ab Philips, Elektronikbol ab,\nverkst dir f:a Johan Lagercrantz,\nförsal jn:ch Ingrab Elenik sed 59. -\nStyrr-led Granit ab Kullgrens Enka, medl\nRadiotekn sällsk.\n\nGift 44 m Ulla Wernstedt, dtr t överste\nLudvig W o Lotty Lagercrantz.\nBarn: Pia f 49, Arvid f 54.\n",
    "structured": {
        "1": {
            "full_name": "Mikaelsson, John F",
            "location": "Sundbyberg",
            "occupation": "Transport-arbetare, gångare",
            "birth_details": {
                "date": "06/12/1913",
                "place": "Kristinehamn",
                "parents": "August M o Maria Karlsson"
            },
            "education": [],
            "career": [
                {
                    "position": "Anst Örliogsvarvet marinverkstäderna",
                    "years": {
                        "start_year": 1946,
                        "end_year": null
                    },
                    "organization": "Sthlm"
                }
            ],
            "family": {
                "spouse": "Svea Thelin",
                "marriage_year": "1942",
                "children": [
                    {
                        "name": "Gun",
                        "birth_year": "1944"
                    }
                ]
            }
        },
        "2": {
            "full_name": "Millar, Nils E",
            "location": "Sthlm",
            "occupation": "Förste hovintendent",
            "birth_details": {
                "date": "23/07/1907",
                "place": "Sthlm",
                "parents": "Axel M o Johanna Svensson"
            },
            "education": [
                {
                    "degree": "Stud:ex",
                    "year": "1926",
                    "institution": null
                }
            ],
            "career": [
                {
                    "position": "resebyråtjm",
                    "years": {
                        "start_year": 1927,
                        "end_year": 1935
                    },
                    "organization": null
                },
                {
                    "position": "sekr Kronprinsens hovmarskalksämb",
                    "years": {
                        "start_year": 1936,
                        "end_year": null
                    },
                    "organization": null
                },
                {
                    "position": "hovkamrer",
                    "years": {
                        "start_year": 1943,
                        "end_year": null
                    },
                    "organization": null
                },
                {
                    "position": "hovintend",
                    "years": {
                        "start_year": 1945,
                        "end_year": 1958
                    },
                    "organization": null
                },
                {
                    "position": "l:e hovintendent",
                    "years": {
                        "start_year": 1958,
                        "end_year": null
                    },
                    "organization": null
                }
            ],
            "family": {
                "spouse": "Kerstin Lagerquist",
                "marriage_year": "1942",
                "children": [
                    {
                        "name": "Charlotte",
                        "birth_year": "1943"
                    },
                    {
                        "name": "Peter",
                        "birth_year": "1948"
                    }
                ]
            }
        },
        "3": {
            "full_name": "Milles, Olga",
            "location": "Cranbrook, Bloomfield Hills, Mich, USA",
            "occupation": "Porträttmålarinna",
            "birth_details": {
                "date": "24/01/1874",
                "place": "Leibnitz",
                "parents": "Anton Granner o Rosalia Kornberger"
            },
            "education": [
                {
                    "degree": null,
                    "year": "87-92",
                    "institution": "Graz Malerakad"
                },
                {
                    "degree": null,
                    "year": "93-95",
                    "institution": "Azbe München"
                },
                {
                    "degree": null,
                    "year": "99-01",
                    "institution": "Colarossi Paris"
                }
            ],
            "career": [],
            "family": {
                "spouse": "Carl M",
                "marriage_year": "1905",
                "children": []
            }
        },
        "4": {
            "full_name": "Milles, Rolf A E",
            "location": "Lidingö",
            "occupation": "Civilingenjör",
            "birth_details": {
                "date": "15/01/1915",
                "place": "Sthlm",
                "parents": "T M 0 Thora Rutensköld"
            },
            "education": [
                {
                    "degree": null,
                    "year": "38",
                    "institution": "KTH"
                }
            ],
            "career": [
                {
                    "position": "anst ab Hg Relay pat",
                    "years": {
                        "start_year": 1939,
                        "end_year": null
                    },
                    "organization": null
                },
                {
                    "position": "avd:ch Sv ab Philips, Elektronikbol ab",
                    "years": {
                        "start_year": null,
                        "end_year": null
                    },
                    "organization": null
                },
                {
                    "position": "verkst dir f:a Johan Lagercrantz",
                    "years": {
                        "start_year": null,
                        "end_year": null
                    },
                    "organization": "försal"
                },
                {
                    "position": "jn:ch Ingrab Elenik",
                    "years": {
                        "start_year": 1959,
                        "end_year": null
                    },
                    "organization": "Styrr-led Granit ab Kullgrens Enka, medl Radiotekn sällsk"
                }
            ],
            "family": {
                "spouse": "Ulla Wernstedt",
                "marriage_year": "1944",
                "children": [
                    {
                        "name": "Pia",
                        "birth_year": "1949"
                    },
                    {
                        "name": "Arvid",
                        "birth_year": "1954"
                    }
                ]
            }
        }
    }
}