{
    "original": "MODIN, SVEN O, civilingenjör,\npatentombud, Sthlm, f i Ovanåker,\nGävleb l, 7/5/11 av jägmäst A M o Svea\nBerghmark.\n\nStud:ex Sthlm 29, KTH 35, bitr ing\nAxel Ehrners pat:byrå Sthlm 35, inneh\nsed 42, verkst dir Axel Ehrners\npat:-byrå ab sed 53. - LSvTF 35, medl Sv\npat:omb:fören sed 41, Sv uppfinnarfören\nsed 42, Sv fören f ind rättsskydd.\n-Hobby: sjösport.\n\nGift 37 m Kerstin Nordenson dtr t sekr\nCarl N o h h. - Barn: Birgitta f 39,\nJan f 43,\n\nMODIN, B A UNO, författare,\nDrevviken, f i Falkpg 20/2/05 av\ncharkute-rist Axel Hellström o Hilma M.\nBrunnsviks  folkhögsk   33-35,   skogs-   o\njvarb,   kontorist,    omb:man,   journ.    -\n\nOrdf Sv:es ungd:förf:fören 56,\nstyr:-ted Sv:es förf:fond 57, FLYCO 57, medl\nSv:es förf:fören 58. - Skr: ett flert\nungd:böcker, bl a Spökbrigaden,\nBrandklipparen, Kari XI:s stridshäst, Bonni,\nrådjurskidet, Med äventyrens vindar,\nDen underbara skattkistan,\nradiopjäser.\n\nGift 1) 39-43 m Ella Svensson f 16,\n2) 45 m Gurli Levau f 12. - Barn:\ni 2:a akt Jan f 50.\n\nMOGENDORFF, ADOLF, direktör,\nDanderyd, f i Haag 9/1/29 av Johan\nM o Sientjen Vromen.\nNetherlands inst f service abroad 50,\nanst Unilever NV Rotterdam o Belg\n52-54, dir:ass Turk Unilever Istanbul\n54, produktich ab Vinolia Sthlm 58,\nverkst dir där sed 60. - Medl Sv-holl\nfören. - Hobbies: schack, bridge,\ntennis, bordtennis.\n\nGift 53 m Joyce Hesselaar f 27, dtr t\nFrancois H o Jessie Pereira. - Barn:\nJennifer f 54, Martin f 56.\n\n",
    "structured": {
        "1": {
            "full_name": "MODIN, SVEN O",
            "location": "Stockholm",
            "occupation": "civilingenjör, patentombud",
            "birth_details": {
                "date": "07/05/1911",
                "place": "Ovanåker, Gävleborgs län",
                "parents": "jägmäst A M o Svea Berghmark"
            },
            "education": [
                {
                    "degree": "Stud:ex",
                    "year": "1929",
                    "institution": "Stockholm"
                },
                {
                    "degree": "KTH",
                    "year": "1935",
                    "institution": "Kungliga Tekniska högskolan"
                }
            ],
            "career": [
                {
                    "position": "bitr ing",
                    "years": {
                        "start_year": 1935,
                        "end_year": 1942
                    },
                    "organization": "Axel Ehrners pat:byrå Sthlm"
                },
                {
                    "position": "inneh",
                    "years": {
                        "start_year": 1942,
                        "end_year": 1953
                    },
                    "organization": "Axel Ehrners pat:byrå ab"
                },
                {
                    "position": "verkst dir",
                    "years": {
                        "start_year": 1953
                    },
                    "organization": "Axel Ehrners pat:-byrå ab"
                }
            ],
            "family": {
                "spouse": "Kerstin Nordenson",
                "marriage_year": "1937",
                "children": [
                    {
                        "name": "Birgitta",
                        "birth_year": "1939"
                    },
                    {
                        "name": "Jan",
                        "birth_year": "1943"
                    }
                ]
            },
            "hobbies": [
                "sjösport"
            ]
        },
        "2": {
            "full_name": "MODIN, B A UNO",
            "location": "Drevviken",
            "occupation": "författare",
            "birth_details": {
                "date": "20/02/1905",
                "place": "Falköping"
            },
            "education": {
                "degree": "Folkhögsk",
                "year": "1933-1935",
                "institution": "Brunnsviks"
            },
            "career": {
                "position": "kontorist, omb:man, journ",
                "organization": "NULL"
            },
            "family": {
                "spouse": "1) Ella Svensson, 2) Gurli Levau",
                "marriage_year": "1) 1939-1943, 2) 1945",
                "children": [
                    {
                        "name": "Jan",
                        "birth_year": "1950"
                    }
                ]
            },
            "publications": [
                {
                    "title": "Spökbrigaden",
                    "year": "NULL",
                    "type": "ungd:böcker"
                },
                {
                    "title": "Brandklipparen",
                    "year": "NULL",
                    "type": "ungd:böcker"
                },
                {
                    "title": "Kari XI:s stridshäst",
                    "year": "NULL",
                    "type": "ungd:böcker"
                },
                {
                    "title": "Bonni",
                    "year": "NULL",
                    "type": "ungd:böcker"
                },
                {
                    "title": "rådjurskidet",
                    "year": "NULL",
                    "type": "ungd:böcker"
                },
                {
                    "title": "Med äventyrens vindar",
                    "year": "NULL",
                    "type": "ungd:böcker"
                },
                {
                    "title": "Den underbara skattkistan",
                    "year": "NULL",
                    "type": "ungd:böcker"
                },
                {
                    "title": "radiopjäser",
                    "year": "NULL",
                    "type": "ungd:böcker"
                }
            ]
        },
        "3": {
            "full_name": "MOGENDORFF, ADOLF",
            "location": "Danderyd",
            "occupation": "direktör",
            "birth_details": {
                "date": "09/01/1929",
                "place": "Haag"
            },
            "education": {
                "degree": "Netherlands inst f service abroad",
                "year": "1950",
                "institution": "Netherlands"
            },
            "career": [
                {
                    "position": "anst",
                    "years": {
                        "start_year": 1952,
                        "end_year": 1954
                    },
                    "organization": "Unilever NV Rotterdam o Belg"
                },
                {
                    "position": "dir:ass",
                    "years": {
                        "start_year": 1954
                    },
                    "organization": "Turk Unilever Istanbul"
                },
                {
                    "position": "produktich ab",
                    "years": {
                        "start_year": 1958
                    },
                    "organization": "Vinolia Sthlm"
                },
                {
                    "position": "verkst dir",
                    "years": {
                        "start_year": 1960
                    },
                    "organization": "Vinolia Sthlm"
                }
            ],
            "family": {
                "spouse": "Joyce Hesselaar",
                "marriage_year": "1953",
                "children": [
                    {
                        "name": "Jennifer",
                        "birth_year": "1954"
                    },
                    {
                        "name": "Martin",
                        "birth_year": "1956"
                    }
                ]
            },
            "hobbies": [
                "schack",
                "bridge",
                "tennis",
                "bordtennis"
            ]
        }
    }
}