{
    "original": "MEINERTZ, AAGE F, verkst\ndirektör, Sthlm, f i Esbjerg, Danmark, 18/\n4/04 av kapten Peder M o Agnete\nFaber.\n\nCand phil, anst Goodyear gummi fabr\nab Sthlm 26, verkst dir där sed 60,\nstyr:-ted. - Utm: ChX:sFrM. - Hobbies:\nlitteratur, friluftsliv.\n\nGift 54 m Inger Vendelboe-Petersen f\n16.\n\nMEIXNER, LISE, dr phil, fd\nprofessor, Sthlm, f i Wien 7/11/78.\nProf i fysik Berlin, avd :förest Kaiser\nWilhelm-Inst fur Chemie 17-38,\nverksam Nobelinst f fysik Sthlm 38-47, IVA\nsed 47. - Fil hed:dr Sthlm 50,\nVästberlin 57, LVVS 41, LVA 45, LNVA,\n\nLDVS. - Skr rör kärnfysik blå Fission\nof Uranium. - Utm: RTyskPleMér.\nMEITON,   GUNNAR,   kyrkoadjunkt,\n\nSthlm,   f   i   Örebro   21/8/20   av   jv:tjm\nHjalmar M o Gunhild Storm.\nStud:ex Sthlm 38, teol kand 42, v\nkomminister  Huddinge   43,   Sollentuna   43,\nkyrkoadj Matteus förs Sthlm sed 46.\n-Pastor Sabbatsbergs vård- o\nålderdomshem sed 45, lär RK sjuksköterskesk.\nGift m  Grethe  Nilsson.   -  Barn:\nBirgitta f 46, Agneta f 48, Åke f 50.\n\nMEITON, SVEN, civilingenjör,\nDjursholm, f i Örebro 20/8/16 av lokför\nHjalmar M o Gunhild Storm.\nStud:ex Sthlm 35, KTH 41, anst\nvat-tenfrstyr 42, Erbings maskinaffär Sthlm\nsed 48.\n\nGift 46 m Elsa-Clara Erbing f 21, dtr\nt ing Harald E o Clara Almlöf.\n-Barn: Gösta f 47, Ingmar f 49, Ulf f\n55, Johan f 59.\n\nMEJEGÄRD, O SIGVARD V,\nhovrättsråd, Hägersten, f i Traryd, Kronob\nl, 24/21’18 av köpman Einar M o Alma\nJonasson.\n\nStudrex Kristianstad 37, jur kand Lund\n41, tingstjg Livgedingets, Oppunda o\nVillåttinge doms 41-44, hovnfiskal 45,\ntingssekr Ångermani mel! doms 47, tf\ntingsdom Västerb v doms 48, assess\nSvea hovr 50, tf tingsdom Södertörns\ndoms 53, sakk fin:dep 55, rev:sekr 56,\nhovr:råd Svea hovr sed 60.\nGift 44 m adjunkt Kerstin Bodemar f\n17, dtr t lokmäst Knut Andersson o\nh h. - Barn: Eva f 47, Agneta f 48,\nMari-Ann f 50, Lena f 58.\n\n",
    "structured": {
        "0": {
            "full_name": "MEINERTZ, AAGE F",
            "location": "Stockholm",
            "occupation": "verkst",
            "birth_details": {
                "date": "18/04/1904",
                "place": "Esbjerg, Danmark"
            },
            "education": [
                {
                    "degree": "Cand phil",
                    "year": "1926",
                    "institution": "Goodyear gummi fabr ab Sthlm"
                }
            ],
            "career": [
                {
                    "position": "verkst dir",
                    "years": {
                        "start_year": 1926,
                        "end_year": null
                    },
                    "organization": "Goodyear gummi fabr ab Sthlm"
                }
            ],
            "family": {
                "spouse": "Inger Vendelboe-Petersen",
                "marriage_year": "1954",
                "children": []
            }
        },
        "1": {
            "full_name": "MEIXNER, LISE",
            "location": "Stockholm",
            "occupation": "professor",
            "birth_details": {
                "date": "07/11/1878",
                "place": "Wien"
            },
            "education": [],
            "career": [
                {
                    "position": "Prof i fysik",
                    "years": {
                        "start_year": 1917,
                        "end_year": 1938
                    },
                    "organization": "Berlin"
                },
                {
                    "position": "verksam Nobelinst f fysik",
                    "years": {
                        "start_year": 1938,
                        "end_year": 1947
                    },
                    "organization": "Sthlm"
                },
                {
                    "position": "IVA",
                    "years": {
                        "start_year": 1947,
                        "end_year": null
                    },
                    "organization": null
                }
            ],
            "family": {
                "spouse": null,
                "marriage_year": null,
                "children": []
            }
        },
        "2": {
            "full_name": "MEITON, GUNNAR",
            "location": "Stockholm",
            "occupation": "kyrkoadjunkt",
            "birth_details": {
                "date": null,
                "place": null
            },
            "education": [
                {
                    "degree": "Stud:ex",
                    "year": "1938",
                    "institution": "Sthlm"
                },
                {
                    "degree": "teol kand",
                    "year": "1942",
                    "institution": null
                }
            ],
            "career": [
                {
                    "position": "v komminister",
                    "years": {
                        "start_year": 1943,
                        "end_year": 1943
                    },
                    "organization": "Huddinge"
                },
                {
                    "position": "kyrkoadj",
                    "years": {
                        "start_year": 1946,
                        "end_year": null
                    },
                    "organization": "Matteus förs Sthlm"
                }
            ],
            "family": {
                "spouse": "Grethe Nilsson",
                "marriage_year": null,
                "children": [
                    {
                        "name": "Birgitta",
                        "birth_year": "1946"
                    },
                    {
                        "name": "Agneta",
                        "birth_year": "1948"
                    },
                    {
                        "name": "Åke",
                        "birth_year": "1950"
                    }
                ]
            }
        },
        "3": {
            "full_name": "MEITON, SVEN",
            "location": "Djursholm",
            "occupation": "civilingenjör",
            "birth_details": {
                "date": null,
                "place": null
            },
            "education": [
                {
                    "degree": "Stud:ex",
                    "year": "1935",
                    "institution": "Sthlm"
                },
                {
                    "degree": null,
                    "year": "1941",
                    "institution": "KTH"
                }
            ],
            "career": [
                {
                    "position": "anst vattenfrstyr",
                    "years": {
                        "start_year": 1942,
                        "end_year": null
                    },
                    "organization": null
                },
                {
                    "position": null,
                    "years": null,
                    "organization": "Erbings maskinaffär Sthlm"
                }
            ],
            "family": {
                "spouse": "Elsa-Clara Erbing",
                "marriage_year": "1946",
                "children": [
                    {
                        "name": "Gösta",
                        "birth_year": "1947"
                    },
                    {
                        "name": "Ingmar",
                        "birth_year": "1949"
                    },
                    {
                        "name": "Ulf",
                        "birth_year": "1955"
                    },
                    {
                        "name": "Johan",
                        "birth_year": "1959"
                    }
                ]
            }
        },
        "4": {
            "full_name": "MEJEGÄRD, O SIGVARD V",
            "location": "Hägersten",
            "occupation": "hovrättsråd",
            "birth_details": {
                "date": "24/21/1918",
                "place": "Traryd, Kronob l"
            },
            "education": [
                {
                    "degree": "Studrex",
                    "year": "1937",
                    "institution": "Kristianstad"
                },
                {
                    "degree": "jur kand",
                    "year": "1941",
                    "institution": "Lund"
                }
            ],
            "career": [
                {
                    "position": "tingstjg",
                    "years": {
                        "start_year": 1941,
                        "end_year": 1944
                    },
                    "organization": "Livgedingets, Oppunda o Villåttinge doms"
                },
                {
                    "position": "hovnfiskal",
                    "years": {
                        "start_year": 1945,
                        "end_year": null
                    },
                    "organization": null
                },
                {
                    "position": "sakk fin:dep",
                    "years": {
                        "start_year": 1955,
                        "end_year": 1955
                    },
                    "organization": null
                },
                {
                    "position": "hovr:råd",
                    "years": {
                        "start_year": 1960,
                        "end_year": null
                    },
                    "organization": "Svea hovr"
                }
            ],
            "family": {
                "spouse": "adjunkt Kerstin Bodemar",
                "marriage_year": "1944",
                "children": [
                    {
                        "name": "Eva",
                        "birth_year": "1947"
                    },
                    {
                        "name": "Agneta",
                        "birth_year": "1948"
                    },
                    {
                        "name": "Mari-Ann",
                        "birth_year": "1950"
                    },
                    {
                        "name": "Lena",
                        "birth_year": "1958"
                    }
                ]
            }
        }
    }
}