{
    "original": "MEIER, WILHELM, direktör,\nDjursholm, f i Sthlm 18/2/13 av dir Paul M\no Ingrid Karlsson.\nJur kand 38; tingstjg o tjg Svea ;hovr\n\n38-42, anst Grand Hötel-koncernen 42,\nverkst dir sed 49. - Styr:led Sv:es\narb:-givifören f hotell o rest (ordf 49-57),\nSv.es hotell- o rest:förb (ordf 50-52, v\nordf 53-57), Musiketabl f ören (ordf sed\n49), Internat hotel assoc, Sthlms\nhotell- o rest :fören, presid Nord hotellr\n\n0   resf.förb  51-52,  fullm  Sthlms\nhdlskamm sed 51. - Hobby: musik.\n\nGift 43 m Margareta Gester f 23, dtr\nt konteramiral Eskil G o Elsa Sjöberg.\n- Barn: Anita f 44, Ingrid f 46, Elsa f 53.\nMEIJER, HANS A B, docent,\nSaltsjöbaden, f i Växjö 9/3/22 av kapt\nCarl-Axel M o Elisabeth Wrede.\nStudiex Växjö 40, pol mag Lund 48,\nfil lic 51, fil dr 57. - Bitr lär Lunds\nuniv 54, doc i statskunskap 56, lektor\n\n1   statskunskap StSI sed 58, rektor sed\n60.   -   Notarie   riksd   konstitutionsutsk\n51-53,  led  Sthlms  statsstipmd  sed  61,\nfångvårdsstyr  studiend  sed  60.  -  Skr:\nKommittépolitik o kommittéarbete\n(drs-avh   56),   Regeringsformen  -   150\nårsminnet   (59),   statsvetensk   art   i\nfack-tidskr o dagspress.\n\nGift 47 m tandläk Minna\nCarstens-Johannsen f 25, dtr t l:e stadsläk E\nC-J o Karin Uggla. - Barn: Carsten\nf 48, Helénef 51.\n\nMEIJER, F OTTO, stadsfiskal, Sthlm,\nf i Kristianstad 7/11/10 av köpman\nFrans M o Olga Malmström.\nStudiex Malmö 29, jur kand Lund 34,\ntingstjg Gärds o Albo doms 34-37,\nfiskal hovr över Skåne o Blek 38, tf\npo-lismäst Karlskrona 40, Halmstad 42, e\nstadsfiskal Sthlm 44, eo 49, stadsfiskal\nsed 53. - Ordf taxerind Sthlm, led\nkyrkofullm Essinge förs. - Utm: RNO.\nGift 38 m Margit Widén f 11, dtr t\nköpman Nils W o Alma Persson.\n-Barn: Karl-Henrik f 41, Ingrid f 41,\nGunilla f 43.\n\n",
    "structured": {
        "0": {
            "full_name": "MEIER, WILHELM",
            "location": "Djursholm",
            "occupation": "direktör",
            "birth_details": {
                "date": "18/02/1913",
                "place": "Stockholm",
                "parents": "dir Paul M o Ingrid Karlsson"
            },
            "education": [
                {
                    "degree": "Jur kand",
                    "year": "1938",
                    "institution": "Svea hovr"
                }
            ],
            "career": [
                {
                    "position": "anst Grand Hötel-koncernen",
                    "years": {
                        "start_year": 1942,
                        "end_year": 1949
                    },
                    "organization": "Grand Hötel-koncernen"
                },
                {
                    "position": "verkst dir",
                    "years": {
                        "start_year": 1949
                    }
                }
            ],
            "family": {
                "spouse": "Margareta Gester",
                "marriage_year": "1943",
                "children": [
                    {
                        "name": "Anita",
                        "birth_year": "1944"
                    },
                    {
                        "name": "Ingrid",
                        "birth_year": "1946"
                    },
                    {
                        "name": "Elsa",
                        "birth_year": "1953"
                    }
                ]
            },
            "hobbies": [
                "musik"
            ]
        },
        "1": {
            "full_name": "MEIJER, HANS A B",
            "location": "Saltsjöbaden",
            "occupation": "docent",
            "birth_details": {
                "date": "09/03/1922",
                "place": "Växjö",
                "parents": "kapt Carl-Axel M o Elisabeth Wrede"
            },
            "education": [
                {
                    "degree": "Studiex",
                    "year": "1940",
                    "institution": "Växjö"
                },
                {
                    "degree": "pol mag",
                    "year": "1948",
                    "institution": "Lund"
                },
                {
                    "degree": "fil lic",
                    "year": "1951"
                },
                {
                    "degree": "fil dr",
                    "year": "1957"
                }
            ],
            "career": [
                {
                    "position": "Bitr lär",
                    "years": {
                        "start_year": 1954
                    },
                    "organization": "Lunds univ"
                },
                {
                    "position": "doc i statskunskap",
                    "years": {
                        "start_year": 1956
                    }
                },
                {
                    "position": "lektor statskunskap",
                    "years": {
                        "start_year": 1958
                    },
                    "organization": "StSI"
                }
            ],
            "family": {
                "spouse": "Minna Carstens-Johannsen",
                "marriage_year": "1947",
                "children": [
                    {
                        "name": "Carsten",
                        "birth_year": "1948"
                    },
                    {
                        "name": "Heléne",
                        "birth_year": "1951"
                    }
                ]
            }
        },
        "2": {
            "full_name": "MEIJER, F OTTO",
            "location": "Stockholm",
            "occupation": "stadsfiskal",
            "birth_details": {
                "date": "07/11/1910",
                "place": "Kristianstad",
                "parents": "köpman Frans M o Olga Malmström"
            },
            "education": [
                {
                    "degree": "Studiex",
                    "year": "1929",
                    "institution": "Malmö"
                },
                {
                    "degree": "jur kand",
                    "year": "1934",
                    "institution": "Lund"
                }
            ],
            "career": [
                {
                    "position": "tingstjg",
                    "years": {
                        "start_year": 1934,
                        "end_year": 1937
                    },
                    "organization": "Gärds o Albo doms"
                },
                {
                    "position": "fiskal hovr över Skåne o Blekinge",
                    "years": {
                        "start_year": 1938
                    }
                },
                {
                    "position": "stadsfiskal Sthlm",
                    "years": {
                        "start_year": 1953
                    }
                }
            ],
            "family": {
                "spouse": "Margit Widén",
                "marriage_year": "1938",
                "children": [
                    {
                        "name": "Karl-Henrik",
                        "birth_year": "1941"
                    },
                    {
                        "name": "Ingrid",
                        "birth_year": "1941"
                    },
                    {
                        "name": "Gunilla",
                        "birth_year": "1943"
                    }
                ]
            },
            "honorary_titles": [
                {
                    "title": "RNO"
                }
            ]
        }
    }
}