{
    "original": "MÖLLER, TAGE G H O, leg läkare,\nSthlm, f i Solna 16/2/18 av major Oscar\nM o Anna Åhström.\nStud’:ex Sthlm 38, med kand 41, med\nlic 48, med dr 62, ass:läk o vik underläk\nmed avd o cardiot lab Kronpr Lovisas\nbarnsjh 48^-50, vik underläk Sthlms\n\nepid:sjh 50, e läk o l:e underläk med\navd Kronpr Lovisas barnsjh 51-57, vik\nlas:läk barnavd Hudiksvalls las 53,\nBodens garn :sjh 54, tf överläk med avd\nperiodv 54-56, bitr överläk cardiol lab\nKronpr Lovisas barnsjh sed 57. - Skr\ni pediatr o cardiol.\n\nGift 42 m Birgit Bergström, dtr t dlr\nBirger B o Svea Jerner. - Barn: Yvonne\nf 44, Louise f 50.\n\nMÖLLER, TOM, keramiker, Sthlm, f\ni Gävle 31/5/14 av dir Hennan M o\nMärtha Pihl.\n\nSep:utst Sthlm 47 o 52, delt i utst i utl.\n- Repr i Nät :mus, Victoria and Albert\nMus London.\n\nGift 43 m keramiker Grete Möller, f\n15, dtr t köpman Erik Gisseman o\nJeanette Tengstedt.\n\nvon MÖLLER, C G PETER,\nhov-rättsfiskal, Sthlm, f i Hbg 5/2/27 av\nryttmästare Gösta v M o Carin\nTersmeden.\n\nStud:ex Lundsberg 45, Hbgs hdlsgymn\n46, jur kand Upps 51, adj led\nvatten-överdomst Svea hovr 61.\nGift 57 m jur kand Ingrid Lech f 27,\ndtr t just :rådet Halvar L o Ragna\nSiwerson.\n\nMÖLLERBERG, CARL G, arkitekt\nSAR, Sthlm, f i Malakoff, Seine,\nFrankrike, 16/7/25 av skulpt, prof Nils M o\nInga Hellman.\n\nStud:ex Sthlm 44, KTH 50, KKH\n52-56. - Arkit Sture Fröléns arkit:kontor\n50, Hakon Ahlbergs arkit:kontor 53,\nen av chefsarkit:na där sed 55. - Stud:res\nTyskl 38, Frankr 39 o 50, Engl 47 o 54,\nItal 48, Algeriet 50, Skott! 54. - Medl\nSv:es allm konstfören, Sv sjh :f ören.\n-Hobbies: konst, litteratur, fotografering.\nGift 51 m Henny Hansen. - Barn:\nUlla f 52, Agneta f 53, Eva f 57, John\nf 59.\n\n",
    "structured": {
        "0": {
            "full_name": "MÖLLER, TAGE G H O",
            "location": "Sthlm",
            "occupation": "leg läkare",
            "birth_details": {
                "date": "16/2/1918",
                "place": "Solna",
                "parents": "major Oscar M o Anna Åhström"
            },
            "education": [
                {
                    "degree": "studenter",
                    "year": "1938",
                    "institution": "Sthlm"
                },
                {
                    "degree": "med kand",
                    "year": "1941",
                    "institution": "Sthlm"
                },
                {
                    "degree": "med lic",
                    "year": "1948",
                    "institution": "Sthlm"
                },
                {
                    "degree": "med dr",
                    "year": "1962",
                    "institution": "NULL"
                }
            ],
            "career": [
                {
                    "position": "ass:läk o vik underläk med avd o cardiot lab Kronpr Lovisas barnsjh",
                    "years": {
                        "start_year": 1948,
                        "end_year": 1950
                    },
                    "organization": "NULL"
                },
                {
                    "position": "vik underläk Sthlms epid:sjh",
                    "years": {
                        "start_year": 1950,
                        "end_year": 1951
                    },
                    "organization": "NULL"
                },
                {
                    "position": "e läk o l:e underläk med avd Kronpr Lovisas barnsjh",
                    "years": {
                        "start_year": 1951,
                        "end_year": 1957
                    },
                    "organization": "NULL"
                },
                {
                    "position": "vik las:läk barnavd Hudiksvalls las",
                    "years": {
                        "start_year": 1953,
                        "end_year": 1953
                    },
                    "organization": "NULL"
                },
                {
                    "position": "Bodens garn :sjh",
                    "years": {
                        "start_year": 1954,
                        "end_year": 1954
                    },
                    "organization": "NULL"
                },
                {
                    "position": "tf överläk med avd periodv",
                    "years": {
                        "start_year": 1954,
                        "end_year": 1956
                    },
                    "organization": "NULL"
                },
                {
                    "position": "bitr överläk cardiol lab Kronpr Lovisas barnsjh",
                    "years": {
                        "start_year": 1957,
                        "end_year": 1957
                    },
                    "organization": "NULL"
                }
            ],
            "family": {
                "spouse": "Birgit Bergström",
                "marriage_year": "1942",
                "children": [
                    {
                        "name": "Yvonne",
                        "birth_year": "1944"
                    },
                    {
                        "name": "Louise",
                        "birth_year": "1950"
                    }
                ]
            }
        },
        "1": {
            "full_name": "MÖLLER, TOM",
            "location": "Sthlm",
            "occupation": "keramiker",
            "birth_details": {
                "date": "31/5/1914",
                "place": "Gävle",
                "parents": "dir Hennan M o Märtha Pihl"
            },
            "education": [],
            "career": [],
            "family": {
                "spouse": "keramiker Grete Möller",
                "marriage_year": "1943",
                "children": []
            }
        },
        "2": {
            "full_name": "von MÖLLER, C G PETER",
            "location": "Sthlm",
            "occupation": "hov-rättsfiskal",
            "birth_details": {
                "date": "5/2/1927",
                "place": "Hbg",
                "parents": "ryttmästare Gösta v M o Carin Tersmeden"
            },
            "education": [
                {
                    "degree": "stud",
                    "year": "1945",
                    "institution": "Lundsberg"
                },
                {
                    "degree": "Hbgs hdlsgymn",
                    "year": "1946",
                    "institution": "Hbg"
                },
                {
                    "degree": "jur kand",
                    "year": "1951",
                    "institution": "Upps"
                }
            ],
            "career": [
                {
                    "position": "adj led vatten-överdomst Svea hovr",
                    "years": {
                        "start_year": 1961,
                        "end_year": 1961
                    },
                    "organization": "NULL"
                }
            ],
            "family": {
                "spouse": "jur kand Ingrid Lech",
                "marriage_year": "1957",
                "children": []
            }
        },
        "3": {
            "full_name": "MÖLLERBERG, CARL G",
            "location": "Sthlm",
            "occupation": "arkitekt SAR",
            "birth_details": {
                "date": "16/7/1925",
                "place": "Malakoff, Seine, Frankrike",
                "parents": "skulpt, prof Nils M o Inga Hellman"
            },
            "education": [
                {
                    "degree": "KTH",
                    "year": "1950",
                    "institution": "NULL"
                },
                {
                    "degree": "KKH",
                    "year": "1956",
                    "institution": "NULL"
                }
            ],
            "career": [
                {
                    "position": "en av chefsarkit:na där",
                    "years": {
                        "start_year": 1955,
                        "end_year": 1955
                    },
                    "organization": "NULL"
                }
            ],
            "family": {
                "spouse": "Henny Hansen",
                "marriage_year": "1951",
                "children": [
                    {
                        "name": "Ulla",
                        "birth_year": "1952"
                    },
                    {
                        "name": "Agneta",
                        "birth_year": "1953"
                    },
                    {
                        "name": "Eva",
                        "birth_year": "1957"
                    },
                    {
                        "name": "John",
                        "birth_year": "1959"
                    }
                ]
            },
            "hobbies": [
                "konst",
                "litteratur",
                "fotografering"
            ]
        }
    }
}