{
    "original": "MÖRNER, MARIANNE,\nhovsångerska, Sthlm, f i Örebro 14/5/95 av\ngreve Birger M o Ebeth Brink.\nKonststud Dresden, München, Konstind\nsk Sthlm 17-19, sångstud f Clary\nMorales, R E Weiss, C M Vanzo, Roon\nzur Mühlen, stud röstfysiologi o\nanatomi Dresden, München, Berlin,\nKö-penh, Sthlm. - Debut s sång :a\nMünchen o på K teat Sthlm 22, symf :konsert,\nork :konsert o romansaftn i Sv :e o\nutl. - Jenny Lind-stip 25, Kristina\nNils-son-stip 31, hovång:a 28, sångped o\nlogoped i Sthlm. - Medl Internat fören\nf logopedi o foniatri, Sthlms kvinnl\nbilkår, Sthlms kvinnors skyttefören, Le\nDroit Humain, Sv scoutförb, SLK,\nFrimO, Zonta. - Skr: sångböcker f\nSv flickscouter (33) o SLK (34), The\nVoice Organs (59), upps om röstvård o\nsång i facktidskr. - Utm: GV:sJmtll,\nLitt et Art, CFBSM, FMpbh, Sthlms\nkvinnl bilkårs ftjG. - Hobbies: pistolL\nskytte, konstnärlig verksamhet.\n\nMÖRNER, C STELLAN G, greve,\nkonstnär, Saltsjöbaden, f i Örebro 3/2/\n96 av landsh, greve Axel M o frih:an\nStina Djurklou.\n\nStud:ex Djursholm 15, fil kand Sthlm\n22, KKH 25-29; medv v bild av\nHalmstadgruppen 29, utf måln, teckn o portr,\ndekor arb i Halmstads nya rådhus 38,\nUppsala stadsbibl 41-42, konstn utsmyckn\nHalmstads stadsbibl 53, Halmstads Nya\nteat 54, Reymersholms nybyggn Hbg\n55, Mössebergssk 58, Falkenbergs\nstadshus 59, Rostask Örebro 60; delt\nHalmstadsgruppens samtl utst, internat utst\nLondon 36 o 37, Paris 38, Köpenh 42,\n\nOslo 48, Rom 55, sep :utst Sthlm 41,\n46 o 53; utf dekor t Shakespeare:\nTrettondagsafton (Dram teat 46) m fi.\n-Repr franska stat saml Paris,\nNasjonal-gall Oslo, Nät :mus, Gbgs konstmus o\nUpps univ saml. - Medl Eva Bonniers\ndon:nd 41-46, stat konstråd 53-58,\nBrandkontorets överstyr, Sv:es författarfören\n60, styr:ordf Nord konstförb sv sekt 58,\nstift Esplunda arkiv o bibl,\nEsplunda-stift, patr Skytteanska stift, kurator\nRib-bingska gravkorskassans stift. - LFrKA\n50. - Skr: Timmarna innan (47), Resa\nmed flaggstång (56), upps i tidskr o\ndagspress. - Utm: RVO.\nGift 31 m Maria Polechko f 05, dtr t\növerste Nikolaj P o Sophie Smirnoff.\n-Barn: Agneta f 34, Nils-Axel f 38,\nHans f 46.\n\n",
    "structured": {
        "1": {
            "full_name": "MARIANNE MÖRNER",
            "location": "Stockholm",
            "occupation": "Hovsångerska",
            "birth_details": {
                "date": "14/05/1895",
                "place": "Örebro",
                "parents": "greve Birger M, Ebeth Brink"
            },
            "education": [
                {
                    "degree": "Konststud",
                    "year": "1917-1919",
                    "institution": "Dresden, München, Konstind sk Sthlm"
                },
                {
                    "degree": "Sångstud",
                    "year": "Dresden, München, Berlin, Kö-penh, Sthlm",
                    "institution": "Clary Morales, R E Weiss, C M Vanzo, Roon zur Mühlen"
                }
            ],
            "career": [
                {
                    "position": "Debut s sång :a",
                    "years": {
                        "start_year": 1922,
                        "end_year": null
                    },
                    "organization": "München"
                },
                {
                    "position": "Symf :konsert, ork :konsert",
                    "years": {
                        "start_year": null,
                        "end_year": null
                    },
                    "organization": "Sv :e o utl"
                }
            ],
            "family": {
                "spouse": null,
                "marriage_year": null,
                "children": []
            },
            "publications": [
                {
                    "title": "The Voice Organs",
                    "year": "1959",
                    "type": null
                }
            ],
            "community_involvement": [
                {
                    "role": "Skr",
                    "organization": "Sv flickscouter",
                    "years": "33"
                },
                {
                    "role": "Skr",
                    "organization": "SLK",
                    "years": "34"
                }
            ],
            "board_memberships": [],
            "honorary_titles": {
                "title": "GV:sJmtll, Litt et Art, CFBSM, FMpbh"
            },
            "hobbies": [
                "pistolL skytte",
                "konstnärlig verksamhet"
            ]
        },
        "2": {
            "full_name": "C STELLAN G MÖRNER",
            "location": "Saltsjöbaden",
            "occupation": "Konstnär",
            "birth_details": {
                "date": "03/02/1896",
                "place": "Örebro",
                "parents": "landsh, greve Axel M, frih:an Stina Djurklou"
            },
            "education": [
                {
                    "degree": "Stud:ex",
                    "year": "1915",
                    "institution": "Djursholm"
                },
                {
                    "degree": "Fil kand",
                    "year": "1922",
                    "institution": "Sthlm"
                }
            ],
            "career": [
                {
                    "position": "Medv v bild",
                    "years": {
                        "start_year": 1929,
                        "end_year": null
                    },
                    "organization": "Halmstadgruppen"
                },
                {
                    "position": "Utf måln, teckn o portr",
                    "years": {
                        "start_year": 1929,
                        "end_year": null
                    },
                    "organization": null
                }
            ],
            "family": {
                "spouse": "Maria Polechko",
                "marriage_year": "1931",
                "children": [
                    {
                        "name": "Agneta",
                        "birth_year": "1934"
                    },
                    {
                        "name": "Nils-Axel",
                        "birth_year": "1938"
                    },
                    {
                        "name": "Hans",
                        "birth_year": "1946"
                    }
                ]
            },
            "publications": [
                {
                    "title": "Timmarna innan",
                    "year": "1947",
                    "type": null
                },
                {
                    "title": "Resa med flaggstång",
                    "year": "1956",
                    "type": null
                }
            ],
            "community_involvement": [
                {
                    "role": "Medl",
                    "organization": "Eva Bonniers don:nd",
                    "years": "41-46"
                },
                {
                    "role": "Stat konstråd",
                    "organization": null,
                    "years": "53-58"
                }
            ],
            "board_memberships": [],
            "honorary_titles": {
                "title": "LFrKA 50"
            },
            "hobbies": []
        }
    }
}