{
    "original": "MONTGOMERY, J HENRY A,\nhovrättsassessor, Sthlm, f i Skövde 3/8/27 av\növerstelöjtn John M-Cederhielm o Ebba\nMascoll-Süfverstolpe.\nStudrex Örebro 45, jur kand Upps 51,\ntingstjg Livgedingets doms 52-55, eo\nfiskal Svea hovr 55, tingssekr S Roslags\ndoms 56^-58, anst advrbyrå 58-59,\nfiskalskompetent bitr Svartlösa döms 59,\nad-jung led Svea hovr 59, assess där 61,\nbitr sekr riksd 3:e lagutsk sed’ 61.\n-Styriordf ab Arbrå kraftverk o ab\nVäring, styrrled Kopparfors ab 9\nBrossfors ab.\n\nGift 52 m Barbro Söderberg f 30, dtr\nt genrkonsul Ragnar S o Ingegerd\nWal’l’enberg. - Barn: CaroMoe f 56,\nCharlotte f 58.\n\nde MONTGOMERY, NED A E,\ngreve, Sthlm, f i Gbg 26/12/02 av\nfängelse-dir Albert M o h h f Wennerström.\nÖrebro tekn gymn, diploming :ex\nAmsterdam, bakteriol analysex Batavia 25, stud\nHoll, Belg o Tyskl; kemist höll vulkantj\nBandoeng, Java, kemist o bakteriolog\nprovstation f vattenren Batavia, Java,\ndriftsing f lodvattenren: verket\nPalem-bang, Sumatra, l:e ass inst f jäsnilära\nKTH 44-58, ass stat bakteriol lab, tekn\nbakteriolog Holmens bruks- o fabr ab\nHallstavik, konsult kemist o bakteriolog\n\n1   vattenfrågor.   -   Utm:   SiamVEOlkl,\nOffBKrO.\n\nGift 43 m Britte Hedenblad, dtr t kapt\nPer Henrik H O Elsa Thunberg. - Barn:\n\nHenry f 43, Edward f 44, Elisabeth f\n46, David f 50.\n\n<b>MOORE, ROLF A, civilingenjör,</b>\nSollentuna, f i Sthlm 5/10/08 av\nexp:förest Anton M o folkskollär Anna\nPettersson.\n\nStud:ex 28, KTH 35, ing telestyr\nradiobyrå 35, besiktn:ing S l tyganst\n36, gymnasielär Viggbyholmssk 38,\nra-dioing S l B 40, ch elektrosekt\narméförvaltn tygdep 42, anst FOA 45,\nlaborator där sed 51. - FHS 59. - Även eg\nvetensk verksamh sed 58. - Led Sv\nkomm f rymdforskn, LSvTF 30, medl\nSEIF, Interplanetär sälsk, Sv astronom\nsällsk, ol segelsällsk m m. - Skr: art rör\nsatelliter, prognoser ang satelliters\npassagetider, banberäkn f ol\nrymdfarkoster, funktionssäkerh:statistik.\n\nGift 36 m Dagmar Eriksson, dtr t\nAugust E o Anna E.\n\n<b>MORALES, H C (CHRISTER), fil\nlic, förste statsmeteorolog,</b> Sthlm, f\ni Sthlm  17/2/19 av prof Olallo M  o\nsångpedagog Clary Asplund.\n\nStud:ex 38, fil kand Upps 49, fil lic\n58. - Meteorolog Sv:es meteorol o\nhydrol inst 45, statsmeteorolog 58, 1:e\nstatsmeteorolog där sed 59. - 1:e ass\nmeteorol inst Upps univ 53-57. - Ordf Sv\nmeteorol sällsk 59-61, delt meteorol kongr\nBergen 58, Turin 59, Helsingfors 61.\n- Skr: inom meteorologi.\n\nGift 58 m Birgitta Berg-Gustafsson f 24,\ndtr t brukskassör E Gustafsson o Rut Berg.\n\n<b>MORÉN, AXEL T E, fd överfältveterinär,</b>\nSthlm, f i Almby, Örebro l, \n25/4/85 av bankkassör J M o Alma Lund.\nStud:ex 03, vet:ex 07, bat:veterinär Ing\n2  08, Östgöta trängkår 11, reg:veterinär\no byråassist arméförvaltn   sjvstyr   19,\nfältveterinär VI arméfördeln 24,\növer-fältveterinär o ch sjvstyr\nfältveterinär-byrå 31, ch fältveterinärkåren, insp\narméns veterinärväsende o ch häst- o\nvet:-materielbyrån intend:dep 37-45,\ngen:-majors  tjkl. - Hedl  Sv\nmiliveterinär-sällsk, Sv:es veterinärförb,\nVeterinär-med fören, Sv Blå Stjärnan, ständ led\nSthlms kapplöpn: sällsk, led\nJockeyklubben, Sv galoppsportens centralförb\nskilje-domst. - LKrVA. - Utg:  red  Svensk\nstuteribok för fullblod 51-56.  -   Utm:\nKNO1kl, KVO, KFinlLO, KNS:tOO,\nFFrK2klmsv, SBSGM, FMMpbh. -\nHobby: hästsport.\n\n<b>MORÉN, MAJA, leg läkare,</b> Sthlm,\nf i Sthlm 8/5/02 av civiling Karl M o\nAnna Johansson.\n\nStud:ex 21, med kand 25, med lic\nSthlm 32, ass:läk kir avd Örebro las\n30 o 31, tf underläk kir avd Vänersbgs\nlas 33, underläk Pro Patria 34, 2:e\nunderläk kir avd Vänersbgs las 34, 3:e\nunderläk kir avd Lidkpgs las 35-36, 2:e\nunderläk Vänersbgs las 36-38, l:e\nunderläk o bitr överläk Södra BB 39-42,\nl:e underläk gynekol klin Sabbatsb sjh\n42-46, prakt läk Sthlm sed 46, - \nKonsult gynekolog Sthlms stads folksk,\nkomm realsk o komm flicksk sed 46.\n\n<i>Gift</i> 46 m tjm Paul Frykenstedt f 06,\nson t byggmäst Alfred Andersson o\nAugusta Hindersson.\n\n<b>MORÉN, N OLOF, civilingenjör,</b>\nSaltsjöbaden, f i Sthlm 8/5/24 av kassör\nOlle M o Signe Wikström.\n\nStud:ex 43, res:off:ex 47, KTH 50,\nanst Skoind forskn:inst 50, SvD 54,\nSv djuptryck sed 59. - Styr:led Sv\nmekanisters riksförb 51-58, ordf KAK:s\nungd:förb 53-55. - Skr: MTM - ett\nväsentligt framsteg inom\narbetsstudietek-niken (tills m a 52), Riktiga ackord\n(tills m a 53).\n\nGift 49 m Marianne Schultz f 25, dtr\nt dir Gunnar S o Birgit Wallberg.\n-Barn: Kerstin f 52, John Gunnar f 56,\nNils Olof f 58.\n\n<b>MORFELDT, CARL-OLOF, geolog,\ndirektör,</b> Lidingö, f i Hedemora 19/5/19\nav missionär Oskar M o missionär Judit\nJohansson.\n\nStud:ex 40, konsult geolog 47-57, ass\nKTH 49-57, spec:lär där 58-60, anst\nHagconsult ab 57, verkst dir där sed 61.\n- Skr: upps i bergtekn o byggn:tekn\nfrågor.\n\nGift 45 m Littie Lind f 22, dtr t dir\nCarl L o Ruth Lind. - Barn: Jan-Olof\nf 46, Dan f 48, Linda f 50, Caj f 53,\nChristian f 54, Eva f 59.\n\n<b>MORIN, BERTIL L, direktör,</b> Sthlm,\nf i Sthlm 5/3/24 av tjm Eric M o\nHulda Svensson.\n\nStudiex 43, HHS 47, omb:man Sv:es\ngrossistförb 47, bitr dir Gevaert sv ab\n55, dir ab Sevonia 60, verkst dir ab\nLoha sed 61, (stynmedl). - Hobbies:\nskidor, golf.\n\nGift 48 m Inga Håkansson, dtr t dir\nErnst H o Greta Blomqvist. - Barn:\nGunnar f 53, Anders f 56.\n\n<b>MORIN, GÖSTA, överbibliotekarie,</b>\nSthlm, f i Ludvika 14/4/00 av\ngrosshandl Gustaf M o Maria Tillæus.\n\nStud:ex 20, fil kand 27, fil lic Upps 29,\nbibl v MA 33, 1:e bibl 53, överbibl 58,\nstud Berlin bl a f A Schering, J Wolf\no H J Moser 28-29, 30, bibl:stud USA\n37, sekr Mus konstfören 36-55 (ordf\nsed 55), Sv samf musikforskn 37-44,\nW Peterson-Bergersällsk 44, stynled\nMusikhist mus 36, Sv:es vetensk\nspec:-bibl:s fören 45, Sv bibliotekariesamf 51,\nordf sv sekt av Ass Internat des\nBib-liothéques Musicales 53, Sv.es repr i\ndess exekutivkomm 54, led sv sekt\nInternat Music Council 54, medl red f ser\nMonumenta musicae Sueciae 54,\nstyr:-led Sv samf f musikforskn sed 59.\n-LMA 38, hedL Gesöllsch die Freunde\ndes Internat Musiker-Brief-Archivs EV.\n- Skr: upps i bl a Tidskr för kyrkomus\n\no   sv tidskrift för musikforskn,\nhuvudred  Sohlmans  musiklex  (4   bd  48-52),\nmedarb   ol  uppsl:verk.   -   Utm:   RNO,\nSORftjM.\n\nGift 28 m Gunhild (Gullan) Brundin f\n04, dtr t domprost Gunnar B o Elsa\nNettelbladt.\n\n",
    "structured": {
        "0": {
            "full_name": "Montgomery, J Henry A",
            "location": "Skövde",
            "occupation": "Hovrättsassessor",
            "birth_details": {
                "date": "03/08/1927",
                "place": "Skövde"
            },
            "education": [
                {
                    "degree": "Studrex",
                    "year": "1945",
                    "institution": "Örebro"
                },
                {
                    "degree": "Jur kand",
                    "year": "1951",
                    "institution": "Uppsala"
                }
            ],
            "career": [
                {
                    "position": "Tingssekr",
                    "years": {
                        "start_year": 1956,
                        "end_year": 1958
                    },
                    "organization": "S Roslags Doms"
                }
            ],
            "family": {
                "spouse": "Barbro Söderberg",
                "marriage_year": "1952",
                "children": [
                    {
                        "name": "CaroMoe",
                        "birth_year": "1956"
                    },
                    {
                        "name": "Charlotte",
                        "birth_year": "1958"
                    }
                ]
            }
        },
        "1": {
            "full_name": "de Montgomery, Ned A E",
            "location": "Göteborg",
            "occupation": "Greve",
            "birth_details": {
                "date": "26/12/1902",
                "place": "Göteborg"
            },
            "education": [
                {
                    "degree": "Diploming ex",
                    "year": "1925",
                    "institution": "Amsterdam"
                }
            ],
            "career": [
                {
                    "position": "Driftsing f lodvattenren",
                    "years": {
                        "start_year": 1951,
                        "end_year": 1959
                    },
                    "organization": "Palem-bang, Sumatra"
                }
            ],
            "family": {
                "spouse": "Britte Hedenblad",
                "marriage_year": "1943",
                "children": [
                    {
                        "name": "Henry",
                        "birth_year": "1943"
                    },
                    {
                        "name": "Edward",
                        "birth_year": "1944"
                    },
                    {
                        "name": "Elisabeth",
                        "birth_year": "1946"
                    },
                    {
                        "name": "David",
                        "birth_year": "1950"
                    }
                ]
            }
        },
        "2": {
            "full_name": "Moore, Rolf A",
            "location": "Stockholm",
            "occupation": "Civilingenjör",
            "birth_details": {
                "date": "05/10/1908",
                "place": "Stockholm"
            },
            "education": [
                {
                    "degree": "Stud:ex",
                    "year": "1928",
                    "institution": "Stockholm"
                },
                {
                    "degree": "FHS",
                    "year": "1959"
                }
            ],
            "career": [
                {
                    "position": "Besiktn:ing S l tyganst",
                    "years": {
                        "start_year": 1936,
                        "end_year": 1938
                    },
                    "organization": null
                },
                {
                    "position": "Eg vetensk verksamh",
                    "years": {
                        "start_year": 1958
                    },
                    "organization": null
                }
            ],
            "family": {
                "spouse": "Dagmar Eriksson",
                "marriage_year": "1936",
                "children": null
            }
        },
        "3": {
            "full_name": "Morales, H C (Christer)",
            "location": "Stockholm",
            "occupation": "Fil lic, förste statsmeteorolog",
            "birth_details": {
                "date": "17/02/1919",
                "place": "Stockholm"
            },
            "education": [
                {
                    "degree": "Stud:ex",
                    "year": "1938",
                    "institution": "Stockholm"
                },
                {
                    "degree": "Fil kand",
                    "year": "1949",
                    "institution": "Uppsala"
                },
                {
                    "degree": "Fil lic",
                    "year": "1958",
                    "institution": null
                }
            ],
            "career": [
                {
                    "position": "Statsmeteorolog",
                    "years": {
                        "start_year": 1958
                    },
                    "organization": "Sv:es meteorol o hydrol inst"
                }
            ],
            "family": {
                "spouse": "Birgitta Berg-Gustafsson",
                "marriage_year": "1958",
                "children": null
            }
        },
        "4": {
            "full_name": "Morén, Axel T E",
            "location": "Stockholm",
            "occupation": "Fd överfältveterinär",
            "birth_details": {
                "date": "25/04/1885",
                "place": "Almby, Örebro l"
            },
            "education": [
                {
                    "degree": "Vet:ex",
                    "year": "1907",
                    "institution": null
                },
                {
                    "degree": "Bat:veterinär Ing 2",
                    "year": "1908",
                    "institution": null
                }
            ],
            "career": [
                {
                    "position": "Ch fältveterinärkåren",
                    "years": {
                        "start_year": 1937,
                        "end_year": 1945
                    },
                    "organization": null
                }
            ],
            "family": null
        },
        "5": {
            "full_name": "Morén, Maja",
            "location": "Stockholm",
            "occupation": "Leg läkare",
            "birth_details": {
                "date": "08/05/1902",
                "place": "Stockholm"
            },
            "education": [
                {
                    "degree": "Stud:ex",
                    "year": "1921",
                    "institution": null
                },
                {
                    "degree": "Med kand",
                    "year": "1925",
                    "institution": null
                },
                {
                    "degree": "Med lic",
                    "year": "1932",
                    "institution": "Stockholm"
                }
            ],
            "career": [
                {
                    "position": "Prakt läk",
                    "years": {
                        "start_year": 1946
                    },
                    "organization": null
                }
            ],
            "family": {
                "spouse": "Paul Frykenstedt",
                "marriage_year": "1946",
                "children": null
            }
        },
        "6": {
            "full_name": "Morén, N Olof",
            "location": "Saltsjöbaden",
            "occupation": "Civilingenjör",
            "birth_details": {
                "date": "08/05/1924",
                "place": "Stockholm"
            },
            "education": [
                {
                    "degree": "Stud:ex",
                    "year": "1943",
                    "institution": "Stockholm"
                }
            ],
            "career": [
                {
                    "position": "Director",
                    "years": {
                        "start_year": 1951,
                        "end_year": 1958
                    },
                    "organization": null
                }
            ],
            "family": {
                "spouse": "Marianne Schultz",
                "marriage_year": "1949",
                "children": [
                    {
                        "name": "Kerstin",
                        "birth_year": "1952"
                    },
                    {
                        "name": "John Gunnar",
                        "birth_year": "1956"
                    },
                    {
                        "name": "Nils Olof",
                        "birth_year": "1958"
                    }
                ]
            }
        },
        "7": {
            "full_name": "Morfeldt, Carl-Olof",
            "location": "Lidingö",
            "occupation": "Geolog, direktör",
            "birth_details": {
                "date": "19/05/1919",
                "place": "Hedemora"
            },
            "education": [
                {
                    "degree": "Stud:ex",
                    "year": "1940",
                    "institution": null
                }
            ],
            "career": [
                {
                    "position": "Verkst dir",
                    "years": {
                        "start_year": 1961
                    },
                    "organization": "Hagconsult ab"
                }
            ],
            "family": {
                "spouse": "Littie Lind",
                "marriage_year": "1945",
                "children": [
                    {
                        "name": "Jan-Olof",
                        "birth_year": "1946"
                    },
                    {
                        "name": "Dan",
                        "birth_year": "1948"
                    },
                    {
                        "name": "Linda",
                        "birth_year": "1950"
                    },
                    {
                        "name": "Caj",
                        "birth_year": "1953"
                    },
                    {
                        "name": "Christian",
                        "birth_year": "1954"
                    },
                    {
                        "name": "Eva",
                        "birth_year": "1959"
                    }
                ]
            }
        },
        "8": {
            "full_name": "Morin, Bertil L",
            "location": "Stockholm",
            "occupation": "Direktör",
            "birth_details": {
                "date": "05/03/1924",
                "place": "Stockholm"
            },
            "education": [
                {
                    "degree": "Studiex",
                    "year": "1943",
                    "institution": "Stockholm"
                },
                {
                    "degree": "HHS",
                    "year": "1947"
                }
            ],
            "career": null,
            "family": {
                "spouse": "Inga Håkansson",
                "marriage_year": "1948",
                "children": [
                    {
                        "name": "Gunnar",
                        "birth_year": "1953"
                    },
                    {
                        "name": "Anders",
                        "birth_year": "1956"
                    }
                ]
            }
        },
        "9": {
            "full_name": "Morin, Gösta",
            "location": "Ludvika",
            "occupation": "Överbibliotekarie",
            "birth_details": {
                "date": "14/04/1900",
                "place": "Ludvika"
            },
            "education": [
                {
                    "degree": "Stud:ex",
                    "year": "1920",
                    "institution": "Ludvika"
                },
                {
                    "degree": "Fil kand",
                    "year": "1927",
                    "institution": "Uppsala"
                },
                {
                    "degree": "Fil lic",
                    "year": "1929",
                    "institution": "Uppsala"
                }
            ],
            "career": null,
            "family": {
                "spouse": "Gunhild (Gullan) Brundin",
                "marriage_year": "1928",
                "children": null
            }
        }
    }
}