{
    "original": "CELANDER, LILY H G, fd rektor,\n\nKristianstad, f i New York 21/9/95 av\nkamr Janne C o Ester Ydström.\nH lär:sem 16, ämneslär Elem:lärov f fi\nKristianstad 17i, Komm flicksk 34, rekt\ndär 451-61. - Led kyrkofullm 51-58’.\n-Medl FBF, Kyrkl lärarförb, Bibl:fören,\nUngd RK. - Utm: LNO, SRKSM.\n\nCEMBRAEUS, FOLKE V G, opera-\n\nsångare, Vejbystrand, f i Eskilstuna 4/3/\n95 av konditor Wilhelm Lundström o\nChristina Anderson.\n\nJur stud StHS, elev t Gillis Bratt,\nTorsten Lennartsson m fi, elev Operask, eng\nK teat 21-49 (baryton). - Utm: RVO.\nGift 36 m sång:an Gulli Värnlund f 02.\n\nCENTERWALL,   I  DORIS  A  L  H,\n\ntandläkare, Hbg, f i Hörby, Malmöh l,\n\n27/11/10 av stadsmät Lars C o Ingrid\n\nCarlsson.\n\nStud:ex Landskrona 29, Handl :ex Sthlm\n\n34, vik Ed 35, ass:tandl Lund o Tranås\n\n3’5i, priv :prakt Hbg sed 35.\n\nCERNE, PER-GUNNAR, leg läkare,\n\nHbg, f i Lund 6/4/27 av apot Gunnar C\n\no Elsa Arndt.\n\nStud:ex 49, med kand 53 o med lic Lund\n\n5i7, underläk lüngklin Lunds las 57-60,\n\nHbgs las sed 61.\n\nGift 56 m leg läk Ingela O’svald f 32,\n\ndtr t med:råd Olof O1 o tändt- Gunny\n\nFalk. - Barn: Martin f 57, Anna f 60,\n\nMalin f 62, Johan f 64.\n\n",
    "structured": {
        "1": {
            "full_name": "Lily H G Celande",
            "location": "Kristianstad",
            "occupation": "fd rektor",
            "birth_details": {
                "date": "21/09/1895",
                "place": "New York"
            },
            "education": [
                {
                    "degree": "lär:sem",
                    "year": "1916",
                    "institution": "ämn"
                },
                {
                    "degree": "ämn:lärorv",
                    "year": "17i",
                    "institution": "Komm flicksk"
                }
            ],
            "career": [
                {
                    "position": "rekt",
                    "years": {
                        "start_year": 1945,
                        "end_year": 1961
                    },
                    "organization": "Kristianstad"
                }
            ],
            "family": {
                "spouse": "Janne C",
                "marriage_year": "NULL",
                "children": []
            }
        },
        "2": {
            "full_name": "Folke V G Cembraeus",
            "location": "Vejbystrand",
            "occupation": "operasångare",
            "birth_details": {
                "date": "04/03/1895",
                "place": "Eskilstuna"
            },
            "education": [
                {
                    "degree": "jur stud",
                    "year": "NULL",
                    "institution": "StHS"
                }
            ],
            "career": [
                {
                    "position": "elev t Gillis Bratt",
                    "years": {
                        "start_year": "NULL",
                        "end_year": "NULL"
                    },
                    "organization": "Torsten Lennartsson m fi"
                },
                {
                    "position": "elev Operask",
                    "years": {
                        "start_year": 1921,
                        "end_year": 1949
                    },
                    "organization": "eng K teat"
                }
            ],
            "family": {
                "spouse": "Gulli Värnlund",
                "marriage_year": "1936",
                "children": []
            }
        },
        "3": {
            "full_name": "I DORIS A L H Centerwall",
            "location": "Hbg",
            "occupation": "tandläkare",
            "birth_details": {
                "date": "27/11/1910",
                "place": "Hörby, Malmöh l"
            },
            "education": [
                {
                    "degree": "stud:ex",
                    "year": "1929",
                    "institution": "Landskrona"
                },
                {
                    "degree": "Handl :ex",
                    "year": "1934",
                    "institution": "Sthlm"
                }
            ],
            "career": [
                {
                    "position": "vik Ed",
                    "years": {
                        "start_year": 1935,
                        "end_year": "NULL"
                    },
                    "organization": "NULL"
                },
                {
                    "position": "ass:tandl",
                    "years": {
                        "start_year": 1935,
                        "end_year": "NULL"
                    },
                    "organization": "Lund o Tranås 3’5i"
                },
                {
                    "position": "priv :prakt",
                    "years": {
                        "start_year": 1935,
                        "end_year": "NULL"
                    },
                    "organization": "Hbg"
                }
            ],
            "family": {
                "spouse": "Lars C",
                "marriage_year": "NULL",
                "children": []
            }
        },
        "4": {
            "full_name": "Per-Gunnar Cerne",
            "location": "Hbg",
            "occupation": "leg läkare",
            "birth_details": {
                "date": "06/04/1927",
                "place": "Lund"
            },
            "education": [
                {
                    "degree": "Stud:ex",
                    "year": "1949",
                    "institution": "NULL"
                },
                {
                    "degree": "med kand",
                    "year": "1953",
                    "institution": "Lund"
                },
                {
                    "degree": "med lic",
                    "year": "1957",
                    "institution": "Lund"
                }
            ],
            "career": [
                {
                    "position": "underläk lüngklin Lunds las",
                    "years": {
                        "start_year": 1957,
                        "end_year": 1960
                    },
                    "organization": "Lunds las"
                },
                {
                    "position": "Hbgs las",
                    "years": {
                        "start_year": 1961,
                        "end_year": "NULL"
                    },
                    "organization": "NULL"
                }
            ],
            "family": {
                "spouse": "Ingela O’svald",
                "marriage_year": "1956",
                "children": [
                    {
                        "name": "Martin",
                        "birth_year": "1957"
                    },
                    {
                        "name": "Anna",
                        "birth_year": "1960"
                    },
                    {
                        "name": "Malin",
                        "birth_year": "1962"
                    },
                    {
                        "name": "Johan",
                        "birth_year": "1964"
                    }
                ]
            }
        }
    }
}