{
    "original": "CEDERBERG, T DANIEL,\nkyrkoherde, Staffanstorp, f i Malmö 10/3/08 av\nbyggm Anders C o Anna Wallén.\nStud:ex 26, fil kand Lund’ 30, t’eol kand\n32, prästv 3&gt;2, sjömansv:ass Danzig 31,\nsjöm :präst Gdynia 3’2, tf kyrkoh\nUpp-åkra 3$, kyrkoh Staffanstorp sed 44.\n-Predik S:t Lars sjh 3&lt;9^60, tf sjöm:präst\no konsularagent Szczecin Polen 61.\n-Kyrk världsråds deleg f hj :verksamh\nPolen 46-47, 58-59, verkst led o kassaförv\nLutherhj 44-57, ordf Luth världsförb\nLatinamer:-komm 52-57, Masurienhj\n46-48. - Medl TSO. - Red Kyrkor under\nKorset 45-47, Lutherhjälpen 47-57.\n-Utm: LNO, RFinlLOlkl, OffTyskRFO,\nPolFKlkl.\n\nGift 32 m Stina Tofft, dtr t kontr:prost\nLars T o Maria Lindblad. - Barn: Tora\nf 33, Annmari f 35, Dan f 37, Irka f 42,\nIngemar f 43i, Tord) f 48*.\n\nCEDERBERG,  ERIK  M,  tandläkare,\n\nVarberg, f  i Ystad 28/3/10 av urmak\nAnders C o Karin Persson.\nStud:ex Skara 30, cand med dent Rostock\n32, tandl:ex Sthlm  35, priv:prakt\nVarberg sed 35.\n\nGift 38 m Barbro Andréen f 12. - Barn:\nAnders f 38, Lars f 40, Hans f 43.\n\nCEDERBERG, GUSTAF O, ingenjör,\n\nMalmö, f i Sthlm 19/7/20 av slip Olof C\no Susanna Schelin.\n\nSthlms stads tekn aftonsk 46, ing ab\nFlygmotor Trollhättan 46, ab Separator\nLund 48, ab Addo Malmö sed 531 - Medl\nPar Bricole. - Hobbies: litteratur,\nfotografering.\n\nGift 52 m Ingrid Wassenius f 22, dtr t\nlantbr Edmund W o Ellen Thorén.\n-Barn: Ulrika f 63.\n\nCEDERBERG,    C-GÖSTA,    adjunkt,\n\nMalmö, f i Trollhättan 21/3/27 av\nverk-st:ing Vilhelm C o Elsa Andersson.\nStud:ex Vänersborg 46&gt;, res:off:ex 49, fil\nmag Lund 54, eo adj o vik rekt Lund\n54-56, adj Malmö borgars’k 57-61, Johannes\nkomm gymn sed 61. - Ordf Malmö\nlärar-förb, led LR:s distr:styr. - Kurat Västg\nnät Lund 53&gt;-54. - Kapt A 4 res 62.\n-Ansv utg av Pedagogen.\nGift 53 m Ingrid Waldén f 28^, dtr t\nlärov :adj Harald W o Ester Steneberg.\n-Barn: Eva f 55, Hans f 57, Per f 61.\n\n",
    "structured": {
        "1": {
            "full_name": "CEDERBERG, T DANIEL",
            "location": "Staffanstorp",
            "occupation": "kyrkoherde",
            "birth_details": {
                "date": "10/03/1908",
                "place": "Malmö",
                "parents": "byggm Anders C o Anna Wallén"
            },
            "education": [
                {
                    "degree": "Stud:ex",
                    "year": "1926",
                    "institution": "Lund"
                },
                {
                    "degree": "filosofie kandidat",
                    "year": "1930",
                    "institution": "Lund"
                },
                {
                    "degree": "teologie kandidat",
                    "year": "1932",
                    "institution": "NULL"
                }
            ],
            "career": [
                {
                    "position": "sjömansv:ass Danzig",
                    "years": {
                        "start_year": 1931,
                        "end_year": 1931
                    },
                    "organization": "NULL"
                },
                {
                    "position": "sjöm :präst Gdynia",
                    "years": {
                        "start_year": 1932,
                        "end_year": 1932
                    },
                    "organization": "NULL"
                },
                {
                    "position": "tf kyrkoh Upp-åkra",
                    "years": {
                        "start_year": 1935,
                        "end_year": 1944
                    },
                    "organization": "NULL"
                },
                {
                    "position": "kyrkoh Staffanstorp",
                    "years": {
                        "start_year": 1944,
                        "end_year": "present"
                    },
                    "organization": "NULL"
                }
            ],
            "family": {
                "spouse": "Stina Tofft",
                "marriage_year": "1932",
                "children": [
                    {
                        "name": "Tora",
                        "birth_year": "1933"
                    },
                    {
                        "name": "Annmari",
                        "birth_year": "1935"
                    },
                    {
                        "name": "Dan",
                        "birth_year": "1937"
                    },
                    {
                        "name": "Irka",
                        "birth_year": "1942"
                    },
                    {
                        "name": "Ingemar",
                        "birth_year": "1943"
                    },
                    {
                        "name": "Tord",
                        "birth_year": "1948"
                    }
                ]
            }
        },
        "2": {
            "full_name": "CEDERBERG, ERIK M",
            "location": "Varberg",
            "occupation": "tandläkare",
            "birth_details": {
                "date": "28/03/1910",
                "place": "Ystad",
                "parents": "urmak Anders C o Karin Persson"
            },
            "education": [
                {
                    "degree": "Stud:ex",
                    "year": "1930",
                    "institution": "Skara"
                },
                {
                    "degree": "cand med dent",
                    "year": "1932",
                    "institution": "Rostock"
                },
                {
                    "degree": "tandl:ex",
                    "year": "1935",
                    "institution": "Sthlm"
                }
            ],
            "career": [
                {
                    "position": "priv:prakt Varberg",
                    "years": {
                        "start_year": 1935,
                        "end_year": "present"
                    },
                    "organization": "NULL"
                }
            ],
            "family": {
                "spouse": "Barbro Andréen",
                "marriage_year": "1938",
                "children": [
                    {
                        "name": "Anders",
                        "birth_year": "1938"
                    },
                    {
                        "name": "Lars",
                        "birth_year": "1940"
                    },
                    {
                        "name": "Hans",
                        "birth_year": "1943"
                    }
                ]
            }
        },
        "3": {
            "full_name": "CEDERBERG, GUSTAF O",
            "location": "Malmö",
            "occupation": "ingenjör",
            "birth_details": {
                "date": "19/07/1920",
                "place": "Sthlm",
                "parents": "slip Olof C o Susanna Schelin"
            },
            "education": [
                {
                    "degree": "Sthlms stads tekn aftonsk",
                    "year": "1946",
                    "institution": "NULL"
                }
            ],
            "career": [
                {
                    "position": "ing ab Flygmotor Trollhättan",
                    "years": {
                        "start_year": 1946,
                        "end_year": "NULL"
                    },
                    "organization": "NULL"
                },
                {
                    "position": "ab Separator Lund",
                    "years": {
                        "start_year": 1948,
                        "end_year": "NULL"
                    },
                    "organization": "NULL"
                },
                {
                    "position": "ab Addo Malmö",
                    "years": {
                        "start_year": 1953,
                        "end_year": "present"
                    },
                    "organization": "NULL"
                }
            ],
            "family": {
                "spouse": "Ingrid Wassenius",
                "marriage_year": "1952",
                "children": [
                    {
                        "name": "Ulrika",
                        "birth_year": "1963"
                    }
                ]
            },
            "hobbies": [
                "litteratur",
                "fotografering"
            ]
        },
        "4": {
            "full_name": "CEDERBERG, C-GÖSTA",
            "location": "Malmö",
            "occupation": "adjunkt",
            "birth_details": {
                "date": "21/03/1927",
                "place": "Trollhättan",
                "parents": "verkst:ing Vilhelm C o Elsa Andersson"
            },
            "education": [
                {
                    "degree": "Stud:ex",
                    "year": "1946",
                    "institution": "Vänersborg"
                },
                {
                    "degree": "filosofie magister",
                    "year": "1954",
                    "institution": "Lund"
                }
            ],
            "career": [
                {
                    "position": "eo adj o vik rekt Lund",
                    "years": {
                        "start_year": 1954,
                        "end_year": 1956
                    },
                    "organization": "NULL"
                },
                {
                    "position": "adj Malmö borgars'k",
                    "years": {
                        "start_year": 1957,
                        "end_year": 1961
                    },
                    "organization": "NULL"
                },
                {
                    "position": "Johannes komm gymn",
                    "years": {
                        "start_year": 1961,
                        "end_year": "present"
                    },
                    "organization": "NULL"
                }
            ],
            "family": {
                "spouse": "Ingrid Waldén",
                "marriage_year": "1953",
                "children": [
                    {
                        "name": "Eva",
                        "birth_year": "1955"
                    },
                    {
                        "name": "Hans",
                        "birth_year": "1957"
                    },
                    {
                        "name": "Per",
                        "birth_year": "1961"
                    }
                ]
            }
        }
    }
}