{
    "original": "ROSENGREN, RAGNAR,\ndiplomingenjör, Visby, f i Britt Indien 5/8/02 av\nViktor R o Lina Bergström.\n\nStud:ex 21, dipl:ing Karlsruhe Tyskl 30.\n\n-   Anst   Elektr   ab   Skandia   Sthlm   23,\nSkellefteå  stads  kraftverk  30,  S  Sv:es\nångpannefören    Malmö    35,    elverksch\nTranås 39, Visby sed 54.\n\nGift 32 m Karin Franzén f 04, dtr t\nmissionsläk Gustav F o Ingegärd Höjer.\n\n-   Barn: Lars  f  33,  Martin f  34, Erik\nf 36.\n\nROSENGREN, STIG L,\nhäradshövding, Strömstad, f i Falkenberg 10/9/09\nav postmast Fritz R o Anna Alsen.\nJur kand Lund 33, tingstjg 34-37, fiskal\nhovr över Skåne o Blek 37, tingssekr\nLuggude doms 44-46, hovr :assess 47,\ntingsdom V Göinge doms 48, tf rev :sekr\n51-54, häradsh Norrvikens doms sed 54.\n\n-   Styr :led Strömstads sparbk, led\nskol-styr. - Medl Odd Fellow. - Utm: RNO.\nGift  47   m  Elsa  Englund  f   12,   dtr  t\nBengt  E   o   Annie  Johansson.   -  Barn:\nMarianne f 48.\n\nROSENHALL, GUNNAR J H, lektor,\nV Frölunda, f i Kristianstad 10/5/02 av\ntillsyn :man Fritz R o Johanna Johnson.\nStud:ex Sthlm 21, fil mag 26 o fil lic\nSthlm 36, ämneslär i matem, fys o kemi\nprakt mellansk Sthlm 39, lekt i fys o\nmatem tekn gymn Norrkpg 46, tekn\ngymn Gbg sed 56. - Skr:\nUndersökningar betr palladium-väte o\npalladium-sil-ver-väte (33 o 35). - Utm: RNO.\nGift 34 m Lilie Bergqvist f 04, dtr t\nfolkskollär o musikinstrukt J A B o Julia\nPettersson. - Barn: Leif f 36, Ulf f 40.\n\nROSENIUS, NILS O H, fd\nlandssekreterare, Linköping, f i Ockelbo,\nGävleb l, 10/7/98 av källarmäst Hjalmar R\no Stina Ekengren.\n\nJur kand Upps 23, länsstyr :tjg Örebro,\nUpps o Kopparb l, landssekr Jämtl l\n43-52, Östergötl l 52-63. - Utm: KNO.\nGift 27 m Greta Edlund f 02, dtr t\nbruksförv Ernst E o Agnes Granquist.\n-Barn: Olof f 30, Jan f 37.\n\n",
    "structured": {
        "1": {
            "full_name": "Ragnar Rosengren",
            "location": "Visby",
            "occupation": "Diplomingenjör",
            "birth_details": {
                "date": "05/08/1902",
                "place": "Britt Indien",
                "parents": "Viktor R o Lina Bergström"
            },
            "education": [
                {
                    "degree": "Stud:ex",
                    "year": "1921",
                    "institution": "NULL"
                },
                {
                    "degree": "Diplomingenjör",
                    "year": "1930",
                    "institution": "Karlsruhe Tyskland"
                }
            ],
            "career": [
                {
                    "position": "Anst Elektr",
                    "years": {
                        "start_year": 1923,
                        "end_year": "NULL"
                    },
                    "organization": "ab Skandia Sthlm"
                },
                {
                    "position": "Skellefteå stads kraftverk",
                    "years": {
                        "start_year": 1930,
                        "end_year": "NULL"
                    },
                    "organization": "NULL"
                },
                {
                    "position": "Sv:es ångpannefören Malmö",
                    "years": {
                        "start_year": 1935,
                        "end_year": "NULL"
                    },
                    "organization": "NULL"
                },
                {
                    "position": "Elverksch Tranås",
                    "years": {
                        "start_year": 1939,
                        "end_year": "NULL"
                    },
                    "organization": "NULL"
                },
                {
                    "position": "Elverksch Visby",
                    "years": {
                        "start_year": 1954,
                        "end_year": "NULL"
                    },
                    "organization": "NULL"
                }
            ],
            "family": {
                "spouse": "Karin Franzén",
                "marriage_year": "1932",
                "children": [
                    {
                        "name": "Lars",
                        "birth_year": "1933"
                    },
                    {
                        "name": "Martin",
                        "birth_year": "1934"
                    },
                    {
                        "name": "Erik",
                        "birth_year": "1936"
                    }
                ]
            }
        },
        "2": {
            "full_name": "Stig L Rosengren",
            "location": "Strömstad",
            "occupation": "Häradshövding",
            "birth_details": {
                "date": "10/09/1909",
                "place": "Falkenberg",
                "parents": "Fritz R o Anna Alsen"
            },
            "education": [
                {
                    "degree": "Jur kand",
                    "year": "1933",
                    "institution": "Lund"
                }
            ],
            "career": [
                {
                    "position": "Tingstjg",
                    "years": {
                        "start_year": 1934,
                        "end_year": 1937
                    },
                    "organization": "NULL"
                },
                {
                    "position": "Fiskal hovr över Skåne o Blek",
                    "years": {
                        "start_year": 1937,
                        "end_year": "NULL"
                    },
                    "organization": "NULL"
                },
                {
                    "position": "Tingssekr Luggude doms",
                    "years": {
                        "start_year": 1944,
                        "end_year": 1946
                    },
                    "organization": "NULL"
                },
                {
                    "position": "Hovr :assess",
                    "years": {
                        "start_year": 1947,
                        "end_year": "NULL"
                    },
                    "organization": "NULL"
                },
                {
                    "position": "Tingsdom V Göinge doms",
                    "years": {
                        "start_year": 1948,
                        "end_year": "NULL"
                    },
                    "organization": "NULL"
                },
                {
                    "position": "Häradsh Norrvikens doms",
                    "years": {
                        "start_year": 1954,
                        "end_year": "NULL"
                    },
                    "organization": "NULL"
                }
            ],
            "family": {
                "spouse": "Elsa Englund",
                "marriage_year": "1947",
                "children": [
                    {
                        "name": "Marianne",
                        "birth_year": "1948"
                    }
                ]
            }
        },
        "3": {
            "full_name": "Gunnar J H Rosenhall",
            "location": "V Frölunda",
            "occupation": "Lektor",
            "birth_details": {
                "date": "10/05/1902",
                "place": "Kristianstad",
                "parents": "Fritz R o Johanna Johnson"
            },
            "education": [
                {
                    "degree": "Stud:ex",
                    "year": "1921",
                    "institution": "Sthlm"
                },
                {
                    "degree": "Fil mag",
                    "year": "1926",
                    "institution": "NULL"
                },
                {
                    "degree": "Fil lic",
                    "year": "1936",
                    "institution": "Sthlm"
                }
            ],
            "career": [
                {
                    "position": "Ämneslär i matem, fys o kemi prakt mellansk",
                    "years": {
                        "start_year": 1939,
                        "end_year": "NULL"
                    },
                    "organization": "Sthlm"
                },
                {
                    "position": "Lekt i fys o matem tekn gymn",
                    "years": {
                        "start_year": 1946,
                        "end_year": "NULL"
                    },
                    "organization": "Norrkpg"
                },
                {
                    "position": "Tekn gymn",
                    "years": {
                        "start_year": 1956,
                        "end_year": "NULL"
                    },
                    "organization": "Gbg"
                }
            ],
            "family": {
                "spouse": "Lilie Bergqvist",
                "marriage_year": "1934",
                "children": [
                    {
                        "name": "Leif",
                        "birth_year": "1936"
                    },
                    {
                        "name": "Ulf",
                        "birth_year": "1940"
                    }
                ]
            }
        },
        "4": {
            "full_name": "Nils O H Rosenius",
            "location": "Linköping",
            "occupation": "Fd Landssekreterare",
            "birth_details": {
                "date": "10/07/1898",
                "place": "Ockelbo, Gävleb l",
                "parents": "Hjalmar R o Stina Ekengren"
            },
            "education": [
                {
                    "degree": "Jur kand",
                    "year": "1923",
                    "institution": "Upps"
                }
            ],
            "career": [
                {
                    "position": "Länsstyr :tjg",
                    "years": {
                        "start_year": "NULL",
                        "end_year": "NULL"
                    },
                    "organization": "Örebro, Upps o Kopparb l"
                },
                {
                    "position": "Landssekr",
                    "years": {
                        "start_year": 1943,
                        "end_year": 1952
                    },
                    "organization": "Jämtl l"
                },
                {
                    "position": "Landssekr",
                    "years": {
                        "start_year": 1952,
                        "end_year": 1963
                    },
                    "organization": "Östergötl l"
                }
            ],
            "family": {
                "spouse": "Greta Edlund",
                "marriage_year": "1927",
                "children": [
                    {
                        "name": "Olof",
                        "birth_year": "1930"
                    },
                    {
                        "name": "Jan",
                        "birth_year": "1937"
                    }
                ]
            }
        }
    }
}