{
    "original": "RASK, K BERTIL H, musikdirektör,\n\nVäxjö, f i Växjö 7/3/08 av polism A R\no Anna Samuelsson.\n\nStud:ex 27, folkskollär :ex Växjö 29, h\nkant:ex Sthlm 51, h musiklär:ex 52, h\norg:ex 54. - Folkskollär Växjö 29,\nfolkskollär o kant Öjaby 35, folkskollär\no övn:skollär Växjö 51, musiklär\nfolk-sk:sem Växjö sed 63 (e 56). - Inneh\nFörlag B Rask (sångboksförl). - Led\nkom-m:fullm o komm:nd 35-50. - FÖrb:dirig\nSv:es körförb sed 57 o Sv sångarförb\nsed 64. - Skr: upps i fackpr, sångsaml\nHär ska sjungas. - Utm: GMmf, Sv\nsångarfb stftjt, Sv:es körfb stftjt.\nGift 44 m Birgitta Gustafson f 20.\n-Barn: Lars Olof f 45, Kerstin f 47,\nGunilla f 48, Örjan f 50, Erling f 54,\nIngemar f 59.\n\nRASKE, E R GERHARD, tandläkare,\n\nHjo, f i Gbg 14/2/04 av dir Carl Gustav\nEriksson o Estrid Wåhlin.\nStud:ex Gbg 23, cand med dent Berlin\n29, tandl:ex Sthlm 32, priv:prakt Hjo sed\n32. - Hobbies: tennis, konst.\nGift 32 m Greta Öhman f 09 d 64, dtr t\nkonsul Gustaf Ö o Siri Trolle. - Barn:\nBo f 34, Leif f 37, Ulla f 40, Jan f 41,\nGunilla f 43, Anita f 45, Eva f 46,\nLärs-Åke f 49.\n\nRASMUSSEN, HANS H, direktör,\nryttmästare, Gbg, f i Kävlinge, Malmöh l,\n31/8/12 av grossh Peder R o Sigrid\nPaul-sen.\n\nStud:ex Lund 33, utl:stud 37-38, off:ex\n40, verkst dir Engblads tapetfabr k/b\nGbg, ab Ljungqvists tapetfabr Norrkpg,\nEricsson &amp; Köhlers nya ab Sthlm o\nTapetbol ab Gbg sed 51. - Ryttm K 3\nres. - Styr :led Graf arb :giv :f örb, Sv\nridsportens centralförb, Ridfrämj\ncentralstyr, Skand pälsberedn &amp; färgeri ab\nSvenljunga. - GM i ridning OS 56.\n-Utm: SvRspHt, SRCstGM,\n",
    "structured": {
        "0": {
            "full_name": "RASK, K BERTIL H",
            "location": "Växjö",
            "occupation": "musikdirektör",
            "birth_details": {
                "date": "07/03/1908",
                "place": "Växjö",
                "parents": "polism A R o Anna Samuelsson"
            },
            "education": [
                {
                    "degree": "Stud:ex",
                    "year": "1927",
                    "institution": "NULL"
                },
                {
                    "degree": "folkskollär",
                    "year": "1929",
                    "institution": "Växjö"
                },
                {
                    "degree": "kant:ex",
                    "year": "1951",
                    "institution": "Sthlm"
                },
                {
                    "degree": "musiklär:ex",
                    "year": "1952",
                    "institution": "NULL"
                },
                {
                    "degree": "org:ex",
                    "year": "1954",
                    "institution": "NULL"
                }
            ],
            "career": [
                {
                    "position": "Folkskollär",
                    "years": {
                        "start_year": 1929,
                        "end_year": 1951
                    },
                    "organization": "Växjö"
                },
                {
                    "position": "folkskollär",
                    "years": {
                        "start_year": 1935,
                        "end_year": 1951
                    },
                    "organization": "Öjaby"
                },
                {
                    "position": "folkskollär",
                    "years": {
                        "start_year": 1951,
                        "end_year": 1951
                    },
                    "organization": "Växjö"
                },
                {
                    "position": "musiklär",
                    "years": {
                        "start_year": 1951,
                        "end_year": "NULL"
                    },
                    "organization": "folk-sk:sem Växjö"
                }
            ],
            "family": {
                "spouse": "Birgitta Gustafson",
                "marriage_year": "1944",
                "children": [
                    {
                        "name": "Lars Olof",
                        "birth_year": "1945"
                    },
                    {
                        "name": "Kerstin",
                        "birth_year": "1947"
                    },
                    {
                        "name": "Gunilla",
                        "birth_year": "1948"
                    },
                    {
                        "name": "Örjan",
                        "birth_year": "1950"
                    },
                    {
                        "name": "Erling",
                        "birth_year": "1954"
                    },
                    {
                        "name": "Ingemar",
                        "birth_year": "1959"
                    }
                ]
            }
        },
        "1": {
            "full_name": "RASKE, E R GERHARD",
            "location": "Hjo",
            "occupation": "tandläkare",
            "birth_details": {
                "date": "14/02/1904",
                "place": "Göteborg",
                "parents": "dir Carl Gustav Eriksson o Estrid Wåhlin"
            },
            "education": [
                {
                    "degree": "Stud:ex",
                    "year": "1923",
                    "institution": "Göteborg"
                },
                {
                    "degree": "cand med dent",
                    "year": "1929",
                    "institution": "Berlin"
                },
                {
                    "degree": "tandl:ex",
                    "year": "1932",
                    "institution": "Stockholm"
                }
            ],
            "career": [
                {
                    "position": "priv:prakt",
                    "years": {
                        "start_year": 1932,
                        "end_year": "NULL"
                    },
                    "organization": "Hjo"
                }
            ],
            "family": {
                "spouse": "Greta Öhman",
                "marriage_year": "1932",
                "children": [
                    {
                        "name": "Bo",
                        "birth_year": "1934"
                    },
                    {
                        "name": "Leif",
                        "birth_year": "1937"
                    },
                    {
                        "name": "Ulla",
                        "birth_year": "1940"
                    },
                    {
                        "name": "Jan",
                        "birth_year": "1941"
                    },
                    {
                        "name": "Gunilla",
                        "birth_year": "1943"
                    },
                    {
                        "name": "Anita",
                        "birth_year": "1945"
                    },
                    {
                        "name": "Eva",
                        "birth_year": "1946"
                    },
                    {
                        "name": "Lärs-Åke",
                        "birth_year": "1949"
                    }
                ]
            },
            "hobbies": [
                "tennis",
                "konst"
            ]
        },
        "2": {
            "full_name": "RASMUSSEN, HANS H",
            "location": "Göteborg",
            "occupation": "direktör, ryttmästare",
            "birth_details": {
                "date": "31/08/1912",
                "place": "Kävlinge, Malmöh l",
                "parents": "grossh Peder R o Sigrid Paul-sen"
            },
            "education": [
                {
                    "degree": "Stud:ex",
                    "year": "1933",
                    "institution": "Lund"
                },
                {
                    "degree": "off:ex",
                    "year": "1940",
                    "institution": "NULL"
                }
            ],
            "career": [
                {
                    "position": "verkst dir",
                    "years": {
                        "start_year": "NULL",
                        "end_year": "NULL"
                    },
                    "organization": "Engblads tapetfabr k/b Gbg"
                },
                {
                    "position": "ab Ljungqvists tapetfabr",
                    "years": {
                        "start_year": "NULL",
                        "end_year": "NULL"
                    },
                    "organization": "Norrkpg"
                },
                {
                    "position": "Ericsson & Köhlers nya ab",
                    "years": {
                        "start_year": "NULL",
                        "end_year": "NULL"
                    },
                    "organization": "Sthlm"
                },
                {
                    "position": "Tapetbol ab",
                    "years": {
                        "start_year": 1951,
                        "end_year": "NULL"
                    },
                    "organization": "Gbg"
                },
                {
                    "position": "Ryttm K 3 res",
                    "years": {
                        "start_year": "NULL",
                        "end_year": "NULL"
                    },
                    "organization": "NULL"
                }
            ],
            "family": {
                "spouse": "NULL",
                "marriage_year": "NULL",
                "children": []
            },
            "hobbies": []
        }
    }
}