{
    "original": "RÖNNHEDH,   P   GÖRAN,   direktör,\nRävlanda, f i Växjö  17/6/24 av köpm\nGustaf R o Greta Roswall.\nRealex, hdlssk,  dir o inneh ab  P  G\nRönnhedh o ab Formi sed 50.\nGift 50 m Wivan Svensson f 27, dtr t\ninsp Hugo S o Ingeborg Gross. - Barn:\nLars, Jan, Bengt.\n\nRÖNNHOLM, S V WALTER,\ningenjör, Huskvarna, f i Härnösand 10/6/06\nav tullöveruppsyn:man Vilhelm R o\nGöta Häggkvist.\n\nIng :ex HTL Härnösand 26, verkst:ing\nDanziger Metallwarenwerke AG Gdansk\n27, konstr SKF Gbg 30, maskinkonstr\nLME Sthlm 39, verkst:ing Husqvarna\nvapenfabr ab sed 44. - Hobbies: jakt,\nfiske.\nGift 36 m Margit Åslund f 08, dtr t\n\nErnst Å o Lova Nyström. - Barn: Åsa\nf 39, Bodil f 42, Per-Vilhelm f 51.\n\nRÖNNMARK, LENNART C A,\nprofessor, Gbg, f i Hörby, Malmöh l, 25/1/\n09 av apot Peter R o Alma Wretling.\nKTH 32, konstr h prof Hj Granholm\n32-34, Sthlms stads slussbyggn:komm 34,\narb :ch ab Skånska cementgjut Sthlm\n34-39, ch dess Gbgsavd 39-51, prof i\nbyggnadsekonomi o byggnadsorganisation\nCTH sed 52 (tf 51), rekt CTH sed 58.\n-Ordf prod :utsk Stat råd f byggn :forskn\nGbg sed 52, styr:ordf ADB-Inst Gbg sed\n58, styr:led Chalmers provn:anst sed 58,\nStift f röntgentelev sed 63, ordf\nSilikat-forskn:inst sed 64. - Expert 54 års mil\nfastigh :förvaltn :utredn, 56 års utredn om\nsinnessjh fastigh, led gen :pl :utredn f\nCTH 56-58. - Led Stadsfullm sed 55 (h),\nDK 56-59. - Styr:ordf ab Sv fryserierna,\nstyr:led Apot droghdl ab (ADA), Gbgs\no Boh l sparbk. - Ordf Byggn :tekn fören\nGbg 47-48, Sv VV-bygg riksförb\nGbgsavd 51-52, Tekn samf avd VV 51-53,\nSv-Nederl fören Gbg sed 52, Nord\nbygg-dag sed 59, Byggcentrum i Gbg sed 60,\nv ordf Fören f Gbgs försv sed 59, SvTF\n60-63. - Ordf Kvibergs sf sed 51, v ordf\nGbgs o Boh l sfb sed 50, led\nSkytteförbundens överstyr sed 58. - Sv mast i\ngevärsskytte 34 o 38. - V preses IVA 65,\nLVVS. - Skr: om byggn :ekon o byggn\n:-org. - Utm: KNO, KNedONO. - Hobby:\nSkytte.\n\nGift 34 m Maja Granholm f 10, dtr t\nlöjtn Per G o Hilda Forsberg. - Barn:\nKarin f 37, Eva f 42, Magnus f 46.\n\n",
    "structured": {
        "0": {
            "full_name": "GÖRAN RÖNNHEDH",
            "location": "Rävlanda",
            "occupation": "direktör",
            "birth_details": {
                "date": "17/06/1924",
                "place": "Växjö",
                "parents": "köpm Gustaf R o Greta Roswall"
            },
            "education": [
                {
                    "degree": "Realex",
                    "year": "NULL",
                    "institution": "NULL"
                },
                {
                    "degree": "hdlssk",
                    "year": "NULL",
                    "institution": "NULL"
                }
            ],
            "career": [
                {
                    "position": "dir o inneh ab P G Rönnhedh o ab Formi",
                    "years": {
                        "start_year": 1950,
                        "end_year": 1950
                    },
                    "organization": "NULL"
                }
            ],
            "family": {
                "spouse": "Wivan Svensson",
                "marriage_year": "1950",
                "children": [
                    {
                        "name": "Lars",
                        "birth_year": "NULL"
                    },
                    {
                        "name": "Jan",
                        "birth_year": "NULL"
                    },
                    {
                        "name": "Bengt",
                        "birth_year": "NULL"
                    }
                ]
            }
        },
        "1": {
            "full_name": "WALTER S V RÖNNHOLM",
            "location": "Huskvarna",
            "occupation": "ingenjör",
            "birth_details": {
                "date": "10/06/1906",
                "place": "Härnösand",
                "parents": "tullöveruppsyn:man Vilhelm R o Göta Häggkvist"
            },
            "education": [
                {
                    "degree": "Ing :ex HTL",
                    "year": "1926",
                    "institution": "Härnösand"
                }
            ],
            "career": [
                {
                    "position": "verkst:ing Husqvarna vapenfabr ab",
                    "years": {
                        "start_year": 1944,
                        "end_year": null
                    },
                    "organization": "NULL"
                }
            ],
            "family": {
                "spouse": "Margit Åslund",
                "marriage_year": "1936",
                "children": [
                    {
                        "name": "Åsa",
                        "birth_year": "1939"
                    },
                    {
                        "name": "Bodil",
                        "birth_year": "1942"
                    },
                    {
                        "name": "Per-Vilhelm",
                        "birth_year": "1951"
                    }
                ]
            },
            "hobbies": [
                "jakt",
                "fiske"
            ]
        },
        "2": {
            "full_name": "LENNART C A RÖNNMARK",
            "location": "Gbg",
            "occupation": "professor",
            "birth_details": {
                "date": "25/01/1909",
                "place": "Hörby, Malmöh l",
                "parents": "apot Peter R o Alma Wretling"
            },
            "education": [
                {
                    "degree": "KTH",
                    "year": "1932",
                    "institution": "NULL"
                }
            ],
            "career": [
                {
                    "position": "prof i byggnadsekonomi o byggnadsorganisation CTH",
                    "years": {
                        "start_year": 1952,
                        "end_year": null
                    },
                    "organization": "NULL"
                },
                {
                    "position": "rekt CTH",
                    "years": {
                        "start_year": 1958,
                        "end_year": null
                    },
                    "organization": "NULL"
                }
            ],
            "family": {
                "spouse": "Maja Granholm",
                "marriage_year": "1934",
                "children": [
                    {
                        "name": "Karin",
                        "birth_year": "1937"
                    },
                    {
                        "name": "Eva",
                        "birth_year": "1942"
                    },
                    {
                        "name": "Magnus",
                        "birth_year": "1946"
                    }
                ]
            },
            "publications": [
                {
                    "title": "Skr: om byggn :ekon o byggn :-org",
                    "year": "NULL",
                    "type": "NULL"
                }
            ],
            "community_involvement": [
                {
                    "role": "styr:led Chalmers provn:anst sed",
                    "organization": "58",
                    "years": "NULL"
                },
                {
                    "role": "Stift f röntgentelev sed",
                    "organization": "63",
                    "years": "NULL"
                }
            ],
            "board_memberships": [
                {
                    "position": "led SvTF",
                    "organization": "60-63",
                    "years": "NULL"
                }
            ],
            "honorary_titles": [
                {
                    "title": "KNO",
                    "institution": "NULL",
                    "year": "NULL"
                },
                {
                    "title": "KNedONO",
                    "institution": "NULL",
                    "year": "NULL"
                }
            ],
            "hobbies": [
                "Skytte"
            ]
        }
    }
}