{
    "original": "Lindfors, Per Hugo Edmond, fil, lic.,\nSthlm, f. 1/8/08 i Sthlm. G. m. Noomi\nJörgensén. Barn: Claes, Kerstin o.\nMarianne. Studiex. 26, pianosp. f. Nils\nBjörkander o. Algot Haquinius, kontrap.\no. dirig. f. Ernst Eliberg ö. Olallo\nMorales 31-33 v. Musik. akad. konservat.,\nfil. kand. 37, fil. lic. 38. Res. i Norge,\nDanm., Tyskl., Tjeckoslov., Österr, o.\nEngl. f. stud. av den musik, verksamh.\nv. resp. radioföretag. Hallåman o.\ngrammofonch. samt medarb, på\nmusik-avd. i Radiotjänst 33, intendent 39.\nRadioprogr. m. Musikens mästare,\nmusik, frågesport, \"Den flygande mikrof.\npå musik, önskerond\" m. m. Skr.:\nDiv. populärart, om musik. Hobbies:\nSport, medicin.\nLindgren, Algot, överstelöjtnant,\nSthlm, f. 22/7/79 i Nysätra, Västerb. L,\nav apot. Gari Gustaf L. o. Edla\nEden-quist. Stud:ex. 97, avg:ex. v. KTH 02,\nres:off:ex. 03. Stud:res. i Tyskl.,\nÖsterr., Ungern o. Frankr. 08 samt Italien\no. Nordafrika 09. Löjtn, i VVK 08,\nkapten 16, major 30, överstelöjtn. 38.\nByråing. i Arméns Kasernbyggnad\n09-14, arb :ch. h. Sv. Betong A-B 14-16,\nByggn. A-B Contractor 16-21, deläg. i\nByggn :f :an Algot Lindegren fr. 21. RNO,\nRVO, SARHt.\nLindgren, Arvid Ludvig, direktör,\nSthlm, f. 30/12/87 i Släp, Hallands 1.\nG. 14 m. Elisabeth Pettersson. Dir. o.\nhuvuddeläg. i Färg- &amp; Ferniss Fabriks\nA-B Arvid Lindgren &amp; Co. i Sthlm.\nStynmedl. i Färg- o.\nfernissfabrikan-ternas fören., i Sv. lack- o.\nfärgforskni-inst., i Färghandelns leverantörfören.\nLindgren, Assaf Daniel, sekreterare,\nSthlm, f. 2/1/86 i Hiborg av köpman\nJohan Einar L. o. Anna-Charlotta Pfeiff.\nG. 27 m. Ebba Augusta Maxe. Studiex.\n07, stud. i Lund 07-15. Byråförest, h.\nFörb. f. medborgarfrihet, sekr. o. chef\nf. F. H. Kis Mejeriavd., anst. h. Sthlms\nDagbl. 26-31, Skånska Dagbl.\nSthlms-repr. 32. Stynmedl. i Skånegillet sed.\n32 o. i fören. Kristianstadsstudenter i\nSthlm sed. f ören is stift. 27. Medl. av\ndirekt, f. Sällskapet C C i Sthlm sed. 17.\n",
    "structured": {
        "0": {
            "full_name": "Lindfors, Per Hugo Edmond",
            "location": "Sthlm",
            "occupation": "intendent",
            "birth_details": {
                "date": "01/08/1908",
                "place": "Sthlm"
            },
            "family": {
                "spouse": "Noomi Jörgensén",
                "marriage_year": "NULL",
                "children": [
                    {
                        "name": "Claes",
                        "birth_year": "NULL"
                    },
                    {
                        "name": "Kerstin",
                        "birth_year": "NULL"
                    },
                    {
                        "name": "Marianne",
                        "birth_year": "NULL"
                    }
                ]
            },
            "education": [
                {
                    "degree": "pianosp.",
                    "year": "1926",
                    "institution": "Nils Björkander o. Algot Haquinius"
                },
                {
                    "degree": "kontrap. o. dirig.",
                    "year": "NULL",
                    "institution": "Ernst Eliberg"
                },
                {
                    "degree": "filosofie kandidat",
                    "year": "1937",
                    "institution": "NULL"
                },
                {
                    "degree": "filosofie licentiat",
                    "year": "1938",
                    "institution": "NULL"
                }
            ],
            "career": [
                {
                    "position": "Löjtn",
                    "years": {
                        "start_year": 1908,
                        "end_year": 1916
                    },
                    "organization": "VVK"
                },
                {
                    "position": "kapten",
                    "years": {
                        "start_year": 1916,
                        "end_year": 1930
                    },
                    "organization": "NULL"
                },
                {
                    "position": "major",
                    "years": {
                        "start_year": 1930,
                        "end_year": 1938
                    },
                    "organization": "NULL"
                }
            ]
        },
        "1": {
            "full_name": "Lindgren, Algot",
            "location": "Sthlm",
            "occupation": "deläg. i Byggn :f :an",
            "birth_details": {
                "date": "22/07/1879",
                "place": "Nysätra, Västerb. L"
            },
            "family": {
                "spouse": "NULL",
                "marriage_year": "NULL",
                "children": []
            },
            "education": [
                {
                    "degree": "avgångsexamen v. KTH",
                    "year": "1902",
                    "institution": "NULL"
                }
            ],
            "career": [
                {
                    "position": "Löjtn",
                    "years": {
                        "start_year": 1908,
                        "end_year": 1916
                    },
                    "organization": "VVK"
                },
                {
                    "position": "kapten",
                    "years": {
                        "start_year": 1916,
                        "end_year": 1930
                    },
                    "organization": "NULL"
                },
                {
                    "position": "major",
                    "years": {
                        "start_year": 1930,
                        "end_year": 1938
                    },
                    "organization": "NULL"
                }
            ],
            "board_memberships": [
                {
                    "position": "NULL",
                    "organization": "Byggn :f :an Algot Lindegren",
                    "years": "1921"
                }
            ],
            "honorary_titles": [
                {
                    "title": "RNO",
                    "institution": "NULL",
                    "year": "NULL"
                },
                {
                    "title": "RVO",
                    "institution": "NULL",
                    "year": "NULL"
                },
                {
                    "title": "SARHt",
                    "institution": "NULL",
                    "year": "NULL"
                }
            ]
        },
        "2": {
            "full_name": "Lindgren, Arvid Ludvig",
            "location": "Sthlm",
            "occupation": "dir. o. huvuddeläg. i Färg- & Ferniss Fabriks A-B Arvid Lindgren & Co.",
            "birth_details": {
                "date": "30/12/1887",
                "place": "Släp, Hallands 1"
            },
            "family": {
                "spouse": "Elisabeth Pettersson",
                "marriage_year": "1914",
                "children": []
            }
        },
        "3": {
            "full_name": "Lindgren, Assaf Daniel",
            "location": "Sthlm",
            "occupation": "chef f. F. H. Kis Mejeriavd.",
            "birth_details": {
                "date": "02/01/1886",
                "place": "Hiborg"
            },
            "family": {
                "spouse": "Ebba Augusta Maxe",
                "marriage_year": "1927",
                "children": []
            }
        }
    }
}