{
    "original": "Verkst, f. sv. mattor o. vävnader A-B,\nCarl Malmsten A-B samt Skarab. Ensk.\nBanks Sthlmskont., v. ordf. i\nSthlms-luftv :reg :s kamratfören. RVO.\nWennerholm, Hugo Axel Lars,\nbyråchef, Sthlm, f. 5/7/93 i Sthlm av aud.\nHugo W. o. Agnes Isacson. G. 28 m.\nSigny Adamsen. Stud :ex., jur. kand. i\nSthlm 16. Studieresor t. Frankr.,\nCours-de Vacances, 13. Tingstjg., aman. i\nciv:dep. 19, i soc:dep. 20, tjg. i komm\n:-koll. 19-22, t. f. 2:e kanslisekr. i\njust:-dep. 29, 2 :e kanslisekr. 30, handsekr.\nh. statsministern 26-32, tj :man h. riksd.\n26-29, sekr. h. fångv :styr. 36, byråchef\ndär 40. Sekr. i Sthlms Allm.\nLawn-tennis Klubb (SALK) 24-36, suppl, i\nstyr. f. Sv. Lawntennisförb. 24-28.\nHobby: målning. RNO, Sv.\nLawntennisförb :s ftJM.\nWennerholm,, Ture Jean, arkitekt,\nSthlm, f. 20/11/92 i Sthlm av byggm.\nAugust W. o. Hilda Svenson. G. 28 m.\nLiten-Karin Sundberg. KTH 19,\nKonst-akad. 19-21, h. prof. Tengbom m. fi.\n17-28, egen arkit rverksamh. fr. 28, ark.\ni Byggn:styr. fr. 29, arkit. h. Utridep.,\nlär. v. Tekn. skolan 22-29, v. KTH 29.\nStud:res. (konstak :stip.) i Europa o. t.\nAfrika 21-24, medalj, o. diplom i\ninternat, arkit :utst. i New York, Budapest,\nMilano, Bryssel, pris i fi. arkit :tävl., bl.\na. om Sthlmsutst., Kanslihuset,\nStortorget i Lund, Chalmers TH, utf. ritn. L\nbl. a. Tennisstadion, Sthlm, kontors- o.\nfabr:byggn. f. ASEA, Esselte, L. M.\nEricsson 36-44, Alpha, Kifa, Fructus,\nSthlm, Almqvist &amp; Wicksell, Uppsala,\nSieverts Kabelverk, Sundbyberg, Nord.\nyllefabr., Norrköp., Sv. järnv rverkst.,\nLinköp., nybyggn. f. A-B Alpha i\nSund-byb., SARA-rest. Hotell Baltic i Gävle,\nrestaur. Alhambra o. österport m. fi.\nSARA-rest., villor o. hyreshus. Medv.\ni Sv. slöjdfören:s utställn. Kontakt m.\nnyttokonstnären i Nät :mus. 44. Skr.:\nIndustriell planläggning (35),\nNybyggnad f. Telefon A-B L. M. E. v.\nMidsommarkransen (42).\nVennersten, Axel Fredrik,\nriksmarskalk, förutv, statsråd, Sthlm, f. i\nBorås 20/1/63 av fabrådk. Jo-h. Fr. V. o.\nOlivia Siedberg. G. 89 m. Adéle\nJagen-burg. 6 kl. i Gtbgs lat :lärov., v. tekn.\nlärov, i Rheydt, Tyskl., 80-81, diplom.\nss. kem. ing. fr. École de chimie i\nMülhausen 83, kem. i kattuntryck. i\nMülhausen 83-87, kem. h. färgfirm. i\nNew York 87-88, deläg. i firm. J. F.\nVennersten i Borås 88-95, sed. verkst,\ndir. där. Stadsfullm. 95-14 o. landst :m.\n03-14, statsråd o. ch. f. fin:dep. 17/2 14-\nso/3 17, riksmarskalk (exc.) sed. 36, A.\nK. 06-20 (v. ordf. i beviutsk. 12-14), F.\nK. 21-36 (bev :utsk., statsutsk., utr :nd.\n24, h), ordf. i nät. partiet i F. K. o. i\npartiets förtr :råd 24, talman i F. K.\n28-36. Led. av tuütaxekomm. 06-09, en av\nund:handl. ang. ty. hdlstrakt. 10, 11, 21\no. 26 (ordf.), trakt. m. Polen 24 (ordf.),\ndelt. i N. F. 25, 27, 30 o. 31, v. ordf. i\ntull- o. traktatkomm. traktatavd., ordf.\ni järnbruksutredn. 27, i 1928 års\ntull-komm. 28, i lägre hdlsund :visn :komm.\n13, bl. komm. f. utr. rör. Gustaf V:s\n80-årsfond 38, sakk. i processkommiss.\nHed :led. av Västg. nät. i Upps. 16, d:o\ni Lund 33, hed :ordf. i Västergötl. o.\nn :a Hall. handelskamm., ordf. i Sthlms\nhdlskamm. 32-39, i direkt, o. insp. f.\nSthlms hdlshögsk. 35-39, ordf. i Stat.\nindustrikomm. 14-17, Sv. Sockerfabr.\nA-B 17-44, Aokumul :fabr. A-B Tudor o.\nSv. järnväg, arb :giv :fören. R o. K av\nKMO, GV :sJmt, KVOlkl, RCXIII :sO,\nStkDDO m br, StkFinlVRO, StkNS :tOO,\nStkPolRest, RPrKr02kl.\nWennersten, Nils Gustav, leg. läkare,\nmed. lic., Sthlm, f. 27/3/95 i Sthlm av\nmålrmäst. Gustaf W. o. Selma Matilda\nJonson. Studiex. i Sthlm 13, med.\nkand. i Sthlm 17, utlandsstud. 19-25,\nmed. lic. i Sthlm 34. E. läk. v.\nRe-stads sjukh. 34, t. f. andre läk. där\n34-35, sed. 35 prakt. läk. i Sthlm\n(psykoterapi, hormonterapi).\nWennerström, Anders Knut, direktör,\nSthlm, f. 04 i Sthlm, av dir. Knut A. K.\nW. o. Karin Swartz. G. m. Ulla\nRingborg. Barn: Kerstin f. 38, Lasse f. 39,\nAgneta f. 42. Verkst, dir. i faderns f :a\nKnut A. K. Wennerström A-B, Sthlm,\ngrund. 50.\nWennerström, Gösta Esaias,\ncivilingenjör, Sthlm, f. 11/8/99 i Norrköping\nav rektorn o. civ:ing. G. A. W. o. Anna\nWennerström. G. 39 m. Lilly\nOden-falk. Styvbarn: Jan f. 32. Stud:ex. i\nNorrköping 18, avg:ex. v. KTH (VoV)\n23. Ing. v. A-B Lindholmen-Motalas\nbrokonstruktionsbyrå i Motala Verkst.\n24-25, v. A-B Vattenbyggnadsbyrån i\nSthlm sed. 25, kontr. h. Väg-o.\nVatten-byggn:styr. f. brobyggn. v. Eriksund o.\nÅtorp 32, ing. v. Slussbyggn :komm :s\nkonstr :kont. i Sthlm 34, nu i\nVatten-byggn :byrån. Stud :resor t. Tyskland,\nSchweiz, Österr, o. Ungern 23, Frankr,\no. Spanien 29, tj :resor t. Norge 25 o.\nt. Ryssl. 32 o, 33.\nWennerström, Nils, köpman, Lidingö,\nf. 24/1/08 i Sthlm av dir. Knut A. K.\nW. o. Karin Swartz. G. 36 m. Karin\nMargareta Forsberg. Barn: Knut Olof\nf. 36, Björn Alfred f. 39. Stud. v.\nLidingö lärov., Sthlms stads handelsskola\n32-34, prakt, i tennisbranschen i Engl.\n30 o. i Tyskl. 31. Anst. i Widforss H.\nA-B i Sthlm 27-30, inneh, f :a\nWenner-ströms Tennisartiklar, grund. 32.\nTill-lika deläg. i Knut A. K. Wennerström\nA-B i Sthlm. Hobbies: tennis, segling,\nskid- o. skridskoåkning.\nWennerström, Thorsten Carl Axel,\nf. d. överstelöjtnant, Sthlm, f. i Sthlm\n27/12/72 av grossh. D. Gonstans W. o.\nWendela Runberg. G. 98 m. Hedvig\nSundström. Und:löjtn. v. Gotl. art :kår\n95, v. Norrl, art :reg. 96, Posit :art :reg.\n04, lär. v. Krigssk. 08-12, språkstud. i\nFrankr. 01, i Ryssl. 13-14, major å res\n:-stat. v. Posit :art :reg. 18, avsk. 27, i\nSmal. arméart :reg :s res. 29,\növerste-löjtn. i armén 32. Aktuar. v. gen:stab.\n21-33, tjg. v. gen:stab. 33-37, sekr. v.\nund :handl. i S :t Petersb. mell. sv. o.\nry. R. K. 17, sv, R.K:s repr. f. övervak,\nav de ry. krigsfång, intress, i Tyskl. o.\nÖsterrike 15-17, chef f. sv. R. K :s org.\ni Ryssl. 17-18, medl. av ty.\nkrigsfånge-komm. i Ryssl. 18, av sv. R. K:s\nhjälp-komm. f. krigsfångar 18, sv. omb. ang.\nhemsänd. av i RyssL vist. svenskar\n19-20, led. av styr. f. Sthlms lokalfören.\nav riksfören. f. svenskhet, bev. i utl.\n18-29, sekr. där 20-26, en av stift, av\nden s. k. Ålandskomm. 39. Medarb, i\nSthlms Dagbl. 14-17, red. f. tidn.\nFolk-försv:t fr. 41. Skr.: Med sv. R. K.\nunder världskriget (27), Sv :e i ry. presseri\nunder världskriget (29), Svenskarna i\nFinl. o. Estl. (31), Den svenskspråkiga\nfolkrörelsen i Finland (34), Personhist.\nuppgifter fr. K. Krigsakademien o. K.\nKrigsskolan 1792-1935 (36), Sthlms\nborgargarde (37), ett flert. upps. i mil.\no. polit. ämn. i dagspressen. RSO, RVO,\nSvRKGM, SthlmssfbSM, RItS :tMLO,\nBulgKrgM, PrRKM2o.3kl, RRKHt,\nTysk-RKHt2kl, TRHM, öRKOffHt, UngRKHk,\nAIHS, KHS, 16GS.\nWennerström-Hartmann, Eva Lovisa,\nfil. lic., rektor, Nockeby, f. i Arvika av\nverkm. Fridolf W. o. Signe Olsson. G.\n39 m. fil. lic. Lennart Hartmann. Fil.\nkand. o. fil. mag. i Upps. 31, fil. lic. 35.\nE. o. ämneslär :a v. Upps. ensk. lärov.\n35, ämneslär :a där 42-45, rektor v.\nHöglandsskolan fr. 1/7/45. Medarb, i Idun\nfr. 43. Upps. stud:kårs v. ordf. 38-39.\nSkr.: Stilstudier i Almquists Songes\n(35), Beväringssvenska (tills. m. Gari\nCederblad, 40), Värmlandshistorier\n(43), Nya Värmlandshistorier (44); i\nradio bl. a. krönikespelet Magdalena\nRudenschöld (43).\nWennfors, Ivar Ruben, fil. lic.,\nLidingö, f. 6/12/00 i Långared, Älvsb. 1.\nG. 30 m. Esther Maria Karlsson. Barn :\nBjörn Ove (Dobbo) f. 40. Avg:ex. v.\nMissionsskolan, Miss :förb :s teol.\nse-min., Lidingö, 27, stud :ex. v. Lunds\npriv. elem :skola 29, fil. kand. 30, fil. lic.\n32, teol. kand. i Lund 37, stud. f. teol.\nlic. i Upps., stud. v. tyska o.\nschweiziska univ. 37-39. Föret, flera resor på\nkontin. under 30-talet. Pastor i Sv.\nM.iss:förb. (SMF) 27-34, sekr. i Sv.\nMiss :förb :s Ungdom (SMU) 35-37,\nstud:rektor i SMU 38-41, lär. v.\nMissionsskolan, SMF :s teol. semin., sed. 41.\nMedarb, i bl. a. Sv. Morgonbladet. Ordf.\ni Fria Kristl. Studentfören. (FKS)\n37-44, ordf. i Komm. f. Sv :es fören.\nkristna studentrörelser 38-40 o. 41-43, ordf.\ni Predikanternas riksförb. inom SMS’\nsed. 38. Led. av folkberedsk ;s nd\n40-41 o. av försvarsväs :s personalvårdsnd\nsed. 42. Skr.: Kristen kallelse, öppen\nf. Gud, Guds ord o. vi, Bekännelse t.\nKristus. Det urkristna dopet.\nWennmark, Johan Torsten Daniel,\njägmästare, Stocksund, f. 16/9/95 i\nöre-bro. G. 33 m. Ingrid Lindblad.\nSkogs-högsk. 22, tjg. v. Statis\nskogsförsöks-anst. o. v. Skogshögsk. 23^25, assist, i\ndomänv. 23, jägm. i domänstyr, fr. 42.\nSekr. i De extra jägmäst:as förb. 32-35,\ni Sv. jägareförb. fr. 37, styr :led. i dess\nSthlms-avd. fr. 33. RVO, Sv.\njägareförbundets hed:m.\nWennström, Inge Emil Nils Holger,\nauktoriserad revisor, Sthlm, f. 8/1/12\ni Mjölby, Östergötl. 1. G. 42 m. Rosa\nBlomqvist. Stud:ex. 31, DHG 36. Egen\nrevisionsbyrå i Sthlm sed. 41.\nWerkmäster, Jerk, konstnär, Sthlm,\nf. 1/10/96 i Rättvik, Kopparbergs L, av\nkyrkv. Werkmäster Anders Jonsson o.\nBlylods Kerstin Ersdtr. G. 27 m.\nDagmar Vougt. Stud. v. H. konstindustr.\nsk. i Sthlm 16-19, v. Konstakad. 19-22.\nLedare av jubil:utst. i Gtbg dekor. 23,\nkonstnärl. led. v. Nittsjö keram:fabr.\nsed. 33. Bl. arb.: dekorativ utstyrsel\ni träsnitt, E. A. Karlfeldts\nDalmålningar på rim, altartavla t. Väddö\nkyrka 26, t. Staffanskyrkan, Gävle, 32,\nt. Malexanders kyrka 32, dekor.\nCar-landerska sjukhemmet i Gtbg 26,\ndekor. 1. kl. sällskrrum å \"Kungsholm1’\ni intarsiainläggn. 28, dekor. Grand Ho-\ntel, Falun, 30, väggintarsia t. (Eltham\nPalace, London, 36, sv. avd. å utst.\nS1LI i H M’ors 38, sv. avd. å utst. i\nLiége 39, jub :utst. i Falun 41 o. Växjö\n42, dekor :arb. f. Tekn. mus., Sthlm,\nStora Kopparb., Falun, Hofors\nkom-munalh., Norrtälje rådhus, Grängesb.\njvg:stat., Rättviks turisthotell,\nBingsjö kapell, Persborgs hotell,\nIdregår-den, Grövelsjöns turiststat., restiarb.\npå Rättviks kyrka. IVA :s de LavalSM.\nWerneman, Harald, med. lic.,\npraktiserande läkare, Sthlm, f. 28/1/89 i\nSthlm. G. 19 m. Malin Andersson.\nBarn: Hans f. 20, Åke f. 22, Göran f. 27.\nMog :ex. 07, med. kand. 11, med. lic. 18.\nUnd :läk. v. S :t Eriks sjukh., Åsö sjukh.,\nSöderby sjukh. o. Sabbatsbergs sjukh..\n16-24, badläk. i Borgholm 25-27. Prakt,\nläk. i Sthlm sed. 24.\nWerner, Arnold Israel, komminister^\nSthlm, f, 1/12/95 i Milwaukee, U. S. A.,\nav övering. Per Efr. W. o. Emy\nörtegren. G. 23 m. Vera Wretlind. Barn r\nHans f. 25, Göran f. 29, Per-Erik f. 31,\nMargareta f. 38. Stud:ex. i Sthlm 15,\nteol. kand. i Upps. 22, prakt. teol. ex.\no. pv. s. å. Sekr. f. Sv:es kristl,\nstud:-rörelse 22-29, dess v. ordf. 30, dess\nutr :led. 30-34, red. f. dess tidskr. Uppåt.\n21-23, led. av kristl, stud :världsförb.\nGeneral Gommittee 24-33, v. kommin. i\nKlara förs. i Sthlm 23-24, pastradj. där\n24-25, kyrkoadj. 25-41, kommin. i S :t\nGörans förs. fr. 41. Stud. v. Marburgs\nuniv. 22, resor i studrrörelsens o. den\nekumen. rör. tjänst t. ett flert. länder,\nsekr. i Sthlms prästsällsk. 31-35, dess\nordf. fr. 41, sekr. i Sv. ekumen. fören.\n33-36, i Sv. ekum. ndn 36-37 o. fr. 39,.\ndess kassaförv. fr. 36, led. i Sv. ekum,\nndens Faith and Ordercomm. fr. 32,\nordf. i Klara förs:bibl:s styr. 33-42,\nomb. i de ekum. varIdskonf. 37, kanslist\no. utsk:sekr. v. 34, 36 o. 41 års\nkyrkomöten, bitr. sekr. i 37 års\npsalmboks-komm., sekr. åt ärkeb. v. utredn, av år\n41 beslut, kyrkohandboken, sekr. i\nRe-lig :vetensk. Sällsk. i Sthlm fr. 35,\nverksam i öl. komm. f. hjälp av flyktingar\nfr. 38 m. fi. Sekr. o. kassaförv. i\nför-valtnindn f. Nathan Söderbloms\nminnesfond fr. 38, ordf. i Klara\nluftsk:-fören. 38-42. Led. av Sthlms stiftsråd\nfr. 43. Skr.: S :ta Clara kyrkog. (36),\nVår nya psalmbok (37), uppsatser i\nkristligt-internat. fråg. bl. a. i Vår\nlösen, medl. av dess red. 27-31, utg. av\nS:ta Clara Kyrkoblad 30-42 o. S :t\nGörans Kyrkobiad fr. 43, utg. en saml.\nbetrakt.: Herrens bön  (33), rec. relig.\nlitt. i Sv. Dagbl. 35-40.\nWerner, Charles, direktör, Sthlm, f.\n26/6/90 i Sthlm av dir. Charles Oskar\nW. o. Marie Johannesen. G. 13 m. Aina\nOest. Barn: Charles Otto f. 19,\nbergsing.; Margareta f. 15; Ulla f. 18, g. m.\njur. kand. Sven Wahlberg; Eva f. 20,\ng. m. R. Andresénz; Göran f. 26, stud.\nStud:ex. 08, undilöjtn. v. Livreg.\ngre-nadj. 10, kansliex. 14, avsk. fr. krigstj.\n16, verkst, dir. o. styr :led. i A-B Sv.\nExporttackjärn. Led. av styr. f. Fören.\nf. Sthlms fasta försv., Kronpr :an\nMargaretas landstormsfond,\nHemvärnsfonden o. Djursh. samsk., ordf. i styr. f.\nA-B Sv. Telegr :byr., styr :led. i\nJärn-verksfören. o. A-B Fawernos. KN02kl,\nKV02kl, ProPstGM, LandstGM.\nWerner, Einar Olof Raoul, advokat,\nSthlm, f. 13/9/99 i Sollefteå av majoren\nOscar W. o. Hilma Kylander. G. 33 m.\nAnnmari Hardt. Barn: Lars f. 34, Karin\nf. 36, Brittmari f. 37, Mats f. 43. Stud :ex.\nreallinj. 18, latinstud. 19, jur. kand. v.\nSthlms Högsk. 22, landst :off :kurs 43.\nStud:res. t. Engl., Frankr., Tyskl. 21,\n22-23. Anst, å advokatkont. i Dieppe,\nFrankr., 22, å adv:byrå i Sthlm 26-30,\ndeläg. 30-34, t. f. rådm., t. f. polismäst.,\nt. f. länsnot, i Örebro i olika perioder\n24-25, t. f. domhav, i östernärkes doms.\n25, egen adv :rör. i Sthlm sed. 34. Ordf.\ni Damkonf :fören. i Sthlm sed. 35, omb\n:-man o. sekr. i Sthlms\nMöbelhandl:fö-ren. sed. 37, i Sv :es Möbelhandl :s\nGen-traJförb. sed. 37, i Skattefria\nBryggeriers Riksförb., Sthlmskretsen, sed. 41,\ni Kontorsmöbelfabrikanternas Fören.\nsed. 42, ordf. i Kontorsmöbelbranschens\nsamarbetsnd sed. 42, styr :led. i Sthlms\nDetaljistförb. 36-43, styr :suppl. i Sthlms\nKöpmannaförb. sed. 43. Sv res\nScout-förb :s förtj :M, PistolskytteMS.\nWerner, John Hugo, med. lic., prakt,\nläkare, marinläk. av l :a gr. i reserven,\nSthlm, f. 11/1/02 i Gtbg av juvel. John\nE. W. o. Hildegard Hagard. G. 28 m.\nNaemi Eneborg. Barn: Lennart f. 31,\nBirgitta f. 37, Gunilla f. 42. Stud :ex. i\nGtbg 23, med. kand. 28 o. med. lic. 33 i\nSthlm. E. läk. v. Sabbatsb. sjukh. 34,\nkortare förordn, s. provrläk. o. s.\nassist :läk. o. undiläk. v. S :t Eriks sjukh.,\nSäters sjukh. o. Örebro las. 35,\nassist:-läk. v. Garnisjukh. i Sthlm med. avd.\n35-36, 2:e und :läk. v. Sthlms sjukhem\n36-37, l:e und :läk. där 37-38, kortare\nförordn, s. med :rådsassist. v. hälsov :-\nbyrån 36-37. Prakt, läk. i Sthlm sed.\n38, verksläk. sed. 39.\nWerner, Nils Erik Magnus Gunnar,\nförsäkringsdirektör, Sthlm, f. 18/2/05 i\nSthlm av J. O. W. o. Anna Paulsson.\nStudiex. i Upps. 23, kansliex. där 28.\nAnst. i Riksförsäkr ranst. 31, aman. där\n35-38, i Arbetsgiv:s oms.\nOlycksfalls-försäkr:bol. sed. 38, v. verkst, dir. o.\nstyrrsuppl. där 43-45, verkst, dir. o. led.\nav styrelsen fr. 45. Styr :led. i De\nömsesidiga So^cialförsäkr ibolagcns Fören.\nfr. 45.\nWerner, Nils Ragnar,\nkommendörkapten, Äppelviken, f. 28/6/83 i Sthlm av\nsjökapten Johan W. o. Louise Printz.\nG. 17 m. Elisabeth Aust. Und:löjtn. v.\nflottan 05, löjtn. 07, kapten 16,\növerg:-stat 26, komm .’kapten i marinen 36.\nChef f. Ångf. A-B Göta Kanals\nSthlms-avd. 26, verkst, dir. i A-B Fören.\nSpe-dHions- o. Rederiagent, i Sthlm 34-44.\nRSO, RVO, KERK2kl, OffFrd’A.\nWerner, Oscar, major, f. d. förste\nbaningenjör, Sthlm, f. 20/10/71 i\nKarlstad. G. 98 m. Hilma Kylander. Barn:\nEinar f. 99, advokat i Sthlm; Gudrun f.\n02, g. m. dir. Tom Björklund, Sthlm.\nMogrex. 90, avg:ex. fr. KTH 94. Assist.\nv. KTH 94-96, avd :ing. v. örebro-Svartfi\njärnv :byggn. o. Ramnäs-Kolbäcks\njärn-vägsbyggn. 96-99, baning. v. S. J. 02,\nl :e baning. 14-36, löjtn, i VVK 99, kapt.\n09, major 25. Förest, f. Järnv:mus. i\nSthlm 15-36, förest, o. lär. v.\nutbildn:-kurser v. S. J. 15-36. Led. av ett flert.\nkomm. f. behandl. av järnv :tekn. fråg.\n05-17, led. av kommma f. utredn, ang.\nTekn. mus. 19 o. 31 ang. Sv :es delt. i\ninternat, utst. 1933 i Chicago, ordn.\nut-st. i ett flert. städ. i Sv:e o. utl. 21-36.\nKronoomb. o. sakk. v. fi.\nvattenrättsmål i Västernorrl. 1. 99-06, verkst,\nflott-ledsförrättn. där 02-09, kontr. o. arb\n:-led. v. kasernbyggn. i Sollefteå 06-10,\nSthlm 16-23 o. fr. 42. Skr. o. upps.\ninom järnv :tekn. omr. bl. a. i Uppf. bok\n(Järnvägar, 29), i Tekn. folkbibi.\n(Vägar o. järnvägar 39), Statsfo :tjm :för :s\nminnesskr. 40. RNO, RVO, SvRKSM,\nKBKrO, KSpCf02kl, OffFrHL, OffltKrO,\nOffPolRest, RFinlVROlkl.\nWerner, Per Wilhelm, civilingenjör,\nSthlm, f. 25/6/93 i Ytterhogdal av\nhäradsdom. Olof W. o. Karin Trumstedt,\nG. 29 m. Olga Margareta Högström.\nBarn: Karin f. 31, Sven f. 36. Stud:ex.\ni Östersund 13, KTH (VoV) 19, spec\n:-stud. v. KSH o. Mass. Inst, of\nTechnology, Boston, U. S. A., 24-25, A-B Vat-\ntenbyggn ibyrån,   Sthlm,   19-23   o.   sed.\n25.    Stud:res. i Mellaneuropa o. Italien\n22, U. S. A. 23-25, tj :res. i Ryssl. 25-26,\nEngland 27, Norge 29, Nya Zeeland 30,\nEstl.,   LettL,   Lit.   35-40.     Led.   av   Sv.\nTekn :fören.  Skr.: Publ. ett 50-tal upps.\nrör. tekn. f råg. i sv., tyska o.\namerikanska tidn. o. tidskr.\nWerner, Sven Gösta, redaktör, Sthlm,\nf. 15/5/08 i ö. Wemmenhög, Malmöh. 1.,\nav teokn:lär., fil. dr Gari W. o.\nElisabeth Cederberg. G. 35 m. Kaj\nBjörkdahl. Barn: Tony f. 37, Meg f. 39, Ylva\nf. 44. Stud :ex. i Lund 27, fil. kand. 30.\nStudieres, t. de flesta europ, länd., bl.\na. Island, Ryssl. o. Balkanländ.\nJournalist 33-34, fr. o. m. 34 verksam inom\nfilmbr. s. filmred., textöversätt.,\nfilmklipp,, journal- o. kortfilmsregissör.\nSekr. i Sv. Filmsamfundet,\nFilmpublicist. Fören., Filmförfattarefören. i\nSverige, stynled. i Svenska Filmklubben,\nhed:led. i Lunds Studenters Filmstudio.\nSkr.: Kameran går (Sthlm 44) samt\nsmärre bibliogr, arb. om film.\nWerner,, Ture, civilingenjör, Sthlm, f.\n1/6/00 i Färed, Skarab. 1. Stud:ex. i\nSkara 19, KTH (kemi) 21-25,\ngalvano-tokn. stud. i Tyskl. 29. Ing. v. C. G.\nHallbergs Guldsmeds A-B i Sthlm sed.\n26,  nu driftsingenjör där.   Led. av Sv.\nTekn :f ören.\nWernlund, Axel Oskar, f. d.\nvägin-genjör, Sthlm, f. 23/3/75 i Sundsvall av\nköpm. Osk. W. o. Lovis Ohlson.\nAvg:-ex. v. KTH 97, off :ex. 97. Stud. organ,\nav Corps des ponts et chaussées samt\nrnod. system f. järnv :entrepren. i\nFrankr. 08-09, fiskehamnar v. Östersjön\no. Västerhavet i Tyskland, Danmark o.\nNorge 22, smågatstenens användning\nss. vägbeläggn:mater. samt\ntungvägtrafik i Danm., Tyskl. o. Frankr. 31-32.\nKapten i VVK 12-35. Bitr. ing. v.\nKry Ib o-örebro järnv :byggn. 98, i\nVäg-o. Vattenbyggn :styr. 98-99, i mell.\nväg-o. vattenbyggn :distr. 99-00, i SJ :s\nbangårdsbyrå 01-03, entreprenör- o.\narbetschef f. mell. Södermani :s\njärnv:-byggn. 05-07, kontrollör v. Tisnare\nka-nalbyggn. 10-12, hämning, i Väg- o.\nVattenbyggn :styr. 13, stat. väging. i\nJönköpings län 32-41, sekr. i komm. f.\nVVK:s omorgan. 14-15. RVO.\nWernstedt, Folke Lago Fredrik,\nmajor, Sthlm, f. 1/8/86 i ö. Torsås förs.,\nKronobergs 1., av kapten C. E. M.\nBolivar W. o. Nina L. Cervin. G. 1. 11\nm. Märtha Ringborg, d. 43; 2. 44 m.\nsekr. v. Metallogr. inst. Dorothy\nBergius, f. Bernton, i h. 2 :a g. Barn (i\nl :a g.) : Christer f. 12, fil. lic., aman. v.\nWenner-Grensmst. v. Sthlms högsk., g.\n38 m. Agnes Krogh; Melchior f. 17,\nbil-rnek., anst. v. Sthlms sparv., g. 42 m*\nBrita Lindroth; Margaretha f. 20, g. 44’\nm. godsäg. Anders Lindqvist. — Mog :ex.\nv. H. allm. lärov, i Växjö 04, off :ex. 07,\navg:ex. fr. Krigshögsk. 17, inskr. v.\nuniv. i Montpellier i Frankr. 08.\nUnd:-löjtn. v. Kronob, reg. 07, löjtn. 11, asp.\nv. Gen:staben 18-21, kapt. 21, på\növer-g:stat 26, intr. i reg. res. 36, major i\narmén 41. Förest, f. Krigsarkiv :s\nkart-saml. 21^28, förest., ordn. o. förteckn.\nRiksarkiv :s kartsaml. 30-36, anst. v.\nBiddarh:s genealog, avd. sed. 36.\nLedarn, av Karol. f örb :s o. Geneal. f ören :s\nstyrelser, ledarn, av Samf. f. utg. av\nhandskr. rör. Skand:s hist. (LSkS).\nSkr.: Ståthållaren Christoffer\nWernstedt (29), Järnkrämare i Sthlm\n1651-1890 (35), Fullmäktige i\nRiksgäldskontoret 1789-1939 (utg. på uppdr. av\nRiks-gäldsfullm. 39), upps. i hist. o.\nperson-hist. ämnen i facktidskr. o. tidningar.\nRSO.\nWernstedt, Gustaf Lågo, major.\nHöglandstorget, f. 25/11/74 i Strängnäs av\nborgm. Lage W. o. Hanna Ringborg.\nG. 02 m. Anna Amalia Hjelm. Off :ex.,\nprimus, 97. Und:löjtn. v. Norrl,\ndrag:-reg. 97, löjtn. 99, ryttm. 07, major i\narmén 19, major o. bat:ch. v. Sk.\ndrag:-reg. 20, v. Sk. kav :reg. 28. Stadsfullm,\nunder Umeåtiden. Uppfinnare, patent:\nkompasslinjalen 08, kartfodral 38, 40,\nriktskiva 38, hållare 39. Konstr, flera\nkompasstyper. Föreläsn. i\nFolkbildn:-förb. rör. friluftsliv, skidl., flygn.,\norientering. Avd :ordf. i Bromma f. Sthlms\nFastighetsäg :fören. Skr.: Karta,\nKompass, Orientering (42), art. i På Skidor.\nRSO, SkidlGM, SkytteGM, IdrottsGM,\nKHS, SS, 2GS.\nWernstedt, Hjalmar, kammarherre,\ngodsägare, Sthlm o. Näs säteri, ö.\nStenby, f.’ i Strängnäs 22/6/76 av borgm.\nLåge W. o. Hanna Ringborg. G. 00 m.\nAnna Hultenheim. Und:löjtn. v.\nflottan 97, löjtn. 00, kapten 06, avsk. 11,\ngodsäg, å Näs säteri 11, kammarn, h.\nDrottn. Victoria 14, ordf. i kommun :nd,\n-st. o. fattigv :styr. i ö. Stenby 14-18,\nled. av tax:nd. 11, ordf. i Vikbolandets\nhush:gille 22-41, i styr. f. Vikbolandets\nKraft A-B 28-34, ö :a Östergötl, lantbr\n:-klubb 20-35, i Fiskerikomm. i Östergötl.\n1. 33, led. i hush :sällsk. förv:utsk. i\nÖstergötl. 1. 29-41, ordf. i förtroenderåd,\nf. Lantm:s mjölkförsäljn :bol.\nNorr-kpgsavd. 32, led. av detta bolags f\nörv:-rad 39, led. av kommun :nd 12, -fullm.\n38, av styr. f. östkinds hdsallmänn. 32,\nav styr. f. Östergötl, fornm :es o.\nmusei :fören. 33. Skr.: upps. i lantbr :fråg.\nGVisJmt, KNO, RSO, RVO, RJohO,\nKDD02gr, KFinlVRO, RNS :tOO.\nWernstedt,, Ludvig, överste, Sthlm,\nf. 29/9/82 i Strängnäs av borgm. Lage\nW. o. Hanna Ringborg. G. 13 m.\nCharlotta Lagercrantz. Barn: Ulla f. 14, g.\nm. civ:ing. R. Milles; Lage f. 16, löjtn.;\nGustaf f. 19, jur. kand. Und:löjtn. i\nFörsta Svea art :reg. 03, löjtn. 06, kapt.\n15, major 28, v. Göta art:reg. 29,\növers-telöjtn. v. Bodens art :reg. 33, t. f. chef\n34, överstelöjtn. v. Svea art :reg. 36,\növerste 37, avsk. s. å. Gmg. AIHS\n05-06, GCI 04, KHS 10-12 samt art:skjutsk.\nSpr:stud. i Frankr. 08. 2 :e adjut. i IV.\narméförd. 13-17, l :e adjut. 17 o. 26,\nkurs f. ballongspanare 15 o. 16. Chef\nt. instruktionsdiv. v. art:skjutsk. å\nSkillingaryd 27, chef f. art :of f :aspir :sk.\ni Kristianstad 27-29, medl. av\nart:-komm. 30-31, repr. f. försvarsväs, i 6:e\ndistr :styr. av SvRK 30-33, tjg. v.\nart:-staben 35, försv :omr ibefälh. 40-42,\nsakk. i luftskyddsinspekt. 43-44. RSO,\nKSpMfOvk2kl, OffFrdel’Ip.\nWernstedt, Wilhelm Edvard,\nprofessor em., Sthlm, f. 29/8/72 i Strängnäs\nav borgmäst. Lage W. o. Hanna\nRingborg. G. 13 m. Tyra Krantz. Barn:\nChristopher f. 18, fil. stud.; Barbro f.\n19. Med. kand. i Upps. 96, med. lic. v.\nKarol. inst. 01, med. dr 06, aman. v.\nAllm. barnh., Sthlm, 02-03, und:läk. där\n03-10, aman. v. Kronpr :an Lovisas\nvårdanst. 10-11, e. assist, v. stat. med. anst.\nt&gt;akteriol. labor. 11-12, marinläk. av 2.\ngr. v. marinläk :kår. 03, i flottans res.\n’06, av 1. gr. 10, badläk. v. Furusund 07\no. v. Målen 13, doc. i pediatr. v. Karol.\ninst. 13 o. i Lund 14-21, överläk. v.\n\"Flensburgs vårdanst. i Malmö 13-21,\nprof. i pediatr. v. Karol. inst. 21-37,\növerläk. o. dir. v. Kronpr :an Lovisas\nvårdanst. 21, överläk. o. styresman v.\nNorrtulls sjukh. 32-37. Vice presid. i\nla Société internat, pour la pédagogie\nde l’enfance déficiente 38, korresp,\nmedl. av Deutsche Gesellschaft f.\nKin-derheilkunde 40. Skr.: utg. ett 150-tal\nvetensk. skr., arb. o. upps. ang.\nbarn-sjukd., barnhygien o. barnpsykol., bl.\na. över barnförl :n, pylorospasm.\nspas–mofili, de vita blodkr:s växlingar un-\nder vaka o. sömn, barnens själsliv,\nuppfostringssvårigheter.\nWersén, David Axel Hjalmar,\naktuarie, Smedslätten, f. 3/7/80 i Skövde av\nbyggm. August W. o. Lovisa\nJohansson. G. 12 m. Gurly Lund. Barn:\nArne f. 13, försäkr :tj man; Gunnar f. 16,\nreklamred. Mog:ex. 99, fil. kand. 05.\nStudieresa t. Danmark s. Sv. Försäkr\n:-f ören :s nord. resestipendiat 24. Tj :m.\ni Livförsäkr. A-B Thule 07, bitr.\naktuarie 18, aktuarie 31-40, aktuarie i\nApo-tekarkårens Livränte- o. Pensionskassa\n20-40. Div. matem. utredn, på uppdrag\nav Apotekssakk. av år 31.\n",
    "structured": {
        "0": {
            "full_name": "Wennerholm, Hugo Axel Lars",
            "location": "Sthlm",
            "occupation": "Byråchef",
            "birth_details": {
                "date": "5/7/1893",
                "place": "Sthlm",
                "parents": "Hugo W. o. Agnes Isacson"
            },
            "education": [
                {
                    "degree": "Stud :ex.",
                    "year": "NULL",
                    "institution": "NULL"
                },
                {
                    "degree": "Jur. kand.",
                    "year": "1916",
                    "institution": "Sthlm"
                }
            ],
            "career": [
                {
                    "position": "Tingstjg.",
                    "years": {
                        "start_year": 1913,
                        "end_year": "NULL"
                    },
                    "organization": "NULL"
                },
                {
                    "position": "Aman.",
                    "years": {
                        "start_year": 1919,
                        "end_year": "NULL"
                    },
                    "organization": "civ:dep."
                },
                {
                    "position": "Tf. 2:e kanslisekr.",
                    "years": {
                        "start_year": 1929,
                        "end_year": "NULL"
                    },
                    "organization": "just:-dep."
                }
            ],
            "family": {
                "spouse": "28 m. Signy Adamsen",
                "marriage_year": "NULL",
                "children": []
            }
        },
        "1": {
            "full_name": "Wennerholm, Ture Jean",
            "location": "Sthlm",
            "occupation": "Arkitekt",
            "birth_details": {
                "date": "20/11/1892",
                "place": "Sthlm",
                "parents": "Byggm. August W. o. Hilda Svenson"
            },
            "education": [
                {
                    "degree": "KTH",
                    "year": "1919",
                    "institution": "NULL"
                },
                {
                    "degree": "Konst-akad.",
                    "year": "1919-1921",
                    "institution": "NULL"
                }
            ],
            "career": [
                {
                    "position": "Egen arkit. verksamh.",
                    "years": {
                        "start_year": 1928,
                        "end_year": "NULL"
                    },
                    "organization": "NULL"
                }
            ],
            "family": {
                "spouse": "28 m. Liten-Karin Sundberg",
                "marriage_year": "NULL",
                "children": []
            }
        },
        "2": {
            "full_name": "Vennersten, Axel Fredrik",
            "location": "Sthlm",
            "occupation": "Riksmarskalk",
            "birth_details": {
                "date": "20/1/1863",
                "place": "Borås",
                "parents": "Fabrådk. Joh. Fr. V. o. Olivia Siedberg"
            },
            "education": [
                {
                    "degree": "6 kl.",
                    "year": "NULL",
                    "institution": "Gtbgs lat :lärov."
                },
                {
                    "degree": "Diplom. ss. Kem. ing.",
                    "year": "1883",
                    "institution": "École de chimie i Mülhausen"
                }
            ],
            "career": [
                {
                    "position": "Deläg. i firm.",
                    "years": {
                        "start_year": 1888,
                        "end_year": 1895
                    },
                    "organization": "J. F. Vennersten i Borås"
                },
                {
                    "position": "Landst :m.",
                    "years": {
                        "start_year": 1903,
                        "end_year": 1914
                    },
                    "organization": "NULL"
                },
                {
                    "position": "Statsråd",
                    "years": {
                        "start_year": 17,
                        "end_year": 3
                    },
                    "organization": "NULL"
                }
            ],
            "family": {
                "spouse": "89 m. Adéle Jagenburg",
                "marriage_year": "NULL",
                "children": []
            }
        },
        "3": {
            "full_name": "Wennersten, Nils Gustav",
            "location": "Sthlm",
            "occupation": "Leg. Läkare",
            "birth_details": {
                "date": "27/3/1895",
                "place": "Sthlm",
                "parents": "Målrmäst. Gustaf W. o. Selma Matilda Jonson"
            },
            "education": [
                {
                    "degree": "Studiex.",
                    "year": "1913",
                    "institution": "NULL"
                },
                {
                    "degree": "Med. kand.",
                    "year": "1917",
                    "institution": "Sthlm"
                }
            ],
            "career": [
                {
                    "position": "E. läk. v. Re-stads sjukh.",
                    "years": {
                        "start_year": 1934,
                        "end_year": "NULL"
                    },
                    "organization": "NULL"
                }
            ],
            "family": {
                "spouse": "19 m. Malin Andersson",
                "marriage_year": "NULL",
                "children": []
            }
        },
        "4": {
            "full_name": "Wennerström, Anders Knut",
            "location": "Sthlm",
            "occupation": "Direktör",
            "birth_details": {
                "date": "04/1900",
                "place": "Sthlm",
                "parents": "Dir. Knut A. K. W. o. Karin Swartz"
            },
            "education": [
                {
                    "degree": "NULL",
                    "year": "NULL",
                    "institution": "Missionsskolan"
                }
            ],
            "career": [
                {
                    "position": "Verkst. dir.",
                    "years": {
                        "start_year": 1950,
                        "end_year": "NULL"
                    },
                    "organization": "faderns f :a Knut A. K. Wennerström A-B"
                }
            ],
            "family": {
                "spouse": "NULL",
                "marriage_year": "NULL",
                "children": []
            }
        },
        "5": {
            "full_name": "Wennerström, Gösta Esaias",
            "location": "Sthlm",
            "occupation": "Civilingenjör",
            "birth_details": {
                "date": "11/8/99",
                "place": "Norrköping",
                "parents": "Rektorn o. Civ:ing. G. A. W. o. Anna Wennerström"
            },
            "education": [
                {
                    "degree": "Stud:ex.",
                    "year": "1918",
                    "institution": "Norrköping"
                },
                {
                    "degree": "Avg:ex. v. KTH",
                    "year": "23",
                    "institution": "NULL"
                }
            ],
            "career": [
                {
                    "position": "V. A-B Vattenbyggnadsbyrån",
                    "years": {
                        "start_year": 1925,
                        "end_year": 1925
                    },
                    "organization": "Sthlm"
                }
            ],
            "family": {
                "spouse": "39 m. Lilly Odenfalk",
                "marriage_year": "NULL",
                "children": [
                    {
                        "name": "Jan",
                        "birth_year": "32"
                    }
                ]
            }
        },
        "6": {
            "full_name": "Wennerström, Nils",
            "location": "Lidingö",
            "occupation": "Köpman",
            "birth_details": {
                "date": "24/1/08",
                "place": "Sthlm",
                "parents": "Dir. Knut A. K. W. o. Karin Swartz"
            },
            "education": [
                {
                    "degree": "NULL",
                    "year": "32-34",
                    "institution": "Sthlms stads handelsskola"
                }
            ],
            "career": [
                {
                    "position": "Anst. i Widforss H. A-B i Sthlm",
                    "years": {
                        "start_year": 1927,
                        "end_year": 1930
                    },
                    "organization": "NULL"
                }
            ],
            "family": {
                "spouse": "36 m. Karin Margareta Forsberg",
                "marriage_year": "NULL",
                "children": [
                    {
                        "name": "Knut Olof",
                        "birth_year": "36"
                    },
                    {
                        "name": "Björn Alfred",
                        "birth_year": "39"
                    }
                ]
            }
        }
    }
}