{
    "original": "Vestergren, Erik Arvid, arkitekt,\nSthlm, f. 1/1/85 i Gävle. KTH 06-08.\nStudieresor t. Danm., Tyskl. o. Italien.\nPraktik å arkit :kont. t. 14, därefter\n•egen verksamhet i Gävle t. 27 o. sed.\ncless i Sthlm. Arb.: kommunala o.\npriv. byggn. på öl. platser inom landet\nävensom i Tyskl. o. Norge.\nWestergren,, Håkan Gari Leonard,\nskådespelare, Nockeby, f. 29/4/99 i\nSthlm av köpm. John W. o. Ella\nHåkansson. G. 31 m. skådesp :an Inga\nTidblad. Barn: Lena, Margareta,\nClaes-Håkan. Stud :ex. i Sthlm 19, Dram.\nteat. elevsk. 20-22, eng. i Wasa, Finl.,\n22-23, Blancheteat. 24-28, Oscarsteatern\n28-31, Dram. teat. 32-34, Blancheteatern\n-34-35, v. Kom :teat. samt fast eng. v.\nS. F. 35-36, turné tills. m. makan höst.\n35. Bl. roll.: Robert i Odygdens\nbelöning samt roller i Männen v. Fronten,\nÖver Evne, Guds Gröna Ängar,\nFamiljen Kantery, Kungl. Familjen, Ung\nKärlek, Det Svaga Könet, Turturduvans\nröst m. fi. Medv. i ett flert. filmer.\nMedl. av TSO, Sv. Teat:förb. Hobbies:\ntennis, fotboll.\nWestergård, Anton Hilmer, fil. dr,\nSthlm, f. 8/5/80 i Ränneslöv, Hallands 1.\nFil. kand. i Lund 02, fil. lic. 09, fil. dr\n10, docent i geol. i Lund 09-10.\nStats-geolog 10, museiförest. v. Sv.es geol.\nundersökn. sed. 10. Studieresor t. ett\nflertal europ, länder o. U. S. A.\nKorresp, led. av Paleont. Soc. of America\n25 o. av Acad. of Natural Sciences,\nPhiladelphia, 39. Skr.: utg. ett flertal\navh. o, upps. om Sv :es kambro-ordov.\no. kvartära bildn. RNO, RVO, G. D.\nWalcottM av Nät. Acad. of Sciences i\nWashington.\nWestergård, Bertil Magnus,\nflygdirektör, Lidingö, f. 10/10/04 i Sthlm av\nlöjtn. O. M. W. o. Maria Kjelldahl. G.\n34 m. Brita Kindman. Barn: Magnus\nf. 35, Bengt f. 39. Giviling:ex. 31. Chef\ni Flygf örvaltn :s flygplanbyrå.\nWesterlind, Vilhelm Gottfrid,\nprovinsialläkare, Dalarö, f. 29/10/99 i\nKöping. G. 42 m. Ingeborg Maria Gelhaar.\nStud :ex. i Eskilstuna 19, med. kand. 24\no med. lic. 32 i Sthlm. Förordn, s. e.\nund:läk. o. t. f. aman. v Seraf:las:s\nögonpoliklin. 27 o. 28, v. dess öron-,\nnas- o. halspoliklin. 33. Assist :läk. v.\nÖrnsköldsviks las. kirurg, avd. o. v.\nSahlgrenska sjukh. kirurg, avd. 29,\nresp. 34. T. f. und :läk. v. Söderhamns\nlas. o. Kristianstads las :s kirurg, avd.\n33-34, v. Ersta sjukh. kirurg, o. med.\navd. 35-37, v. Västerås las :s kirurg,\navd. o. Hudiksvalls las. 38, förordn, s.\nprov:läk. o. e. prov:läk. i Åkersberga,\nKristianst :s, Åhus, Njurunda, Malungs,\nSäffje, TlngsrydSi o. Njutångers distr,\nund. åren 32-38, und :läk. v. Ersta sjukh.\nmed. avd. 38-41, förste und:läk. v.\nSthlms läns sanat. v. Uttran 42-43, e.\nprov:läk. i Dalarö sed. 43.\nWesterling, Sven Gerhard,\növerstelöjtnant, Sthlm, f. 3/8/84 i Sthlm av\nkanslisekr. Hjalmar W. o. Hedda\nBerens. G. 16 m. Ingrid Elisabeth\nLindqvist. Und:löjtn. v. fortif. 05, löjtn.09,\nkapt. 17, major i armén 33, tjg. v. flygv.\nsed. 36, ch. f. underhållsbyrån v.\nflyg-förvaltn :s byggn :avd. 43, öv:löjtn. 44.\nRSO, OffLettTSO, GV:s01M, SvmifbGM,\nSkytteM, AIHShk, RS.\nWestermark, Johan Herbert, med. dr,\nmarinöverläkare, Sthlm, f. 30/8/91 i\nSthlm av prof. Frans WT. o. Maggie\nCnattingius. G. 20 m. Elly Garlström.\nStud:ex. 10, med. kand. 13, med. lic. 18,\nmed. dr 26. Marinläk. av 2 :a gr. 18,\nav l :a gr. 20, förste marinläk. 36,\nma-rinöverläk. o. chef f. marinläk :kåren\nsamt inspektör f. marinens hälso- o.\nsjukvård 37. Chef f. marinförvaltn :s\ndåv. sanitetsavd. 37-43. Led. av Sv.\nLäkarsällsk. nd 30, en av huvudm. f.\nOscar II :s jub :fond 37, suppl, i direkt,\nf. Allm. barnbördshuset 42, suppl, i\ndirekt, f. Allm. änfce- o. pupillkassan\n44. Skr.: grad:avh. 25. KVO, RNO,\nGV :sOl,GM, SvRKSM, LÖS, LKrVA, hed\n:-led. av The Assoc, of Military Surgeons,\nU. S. A.\nWestermark, Nils Johan Hugo, med.\ndr, docent, överläkare, Sthlm, f. 9/9/92\ni Sthlm av prof., med. dr Frans W. o.\nMaggie Cnattingius. G. 22 m. Jane\nIngrid Bergliot Weidenhielm. Barn:\nJane Bergliot Marianne f. 23, Jane Berit\nMargaret f. 24, Jan Erik Nils f. 26, Per\nErik Nils f. 29. Stud:ex. i Sthlm 11,\nmed. kand. 14, med. lic. 19, med. dr 30\no. docent i med. radiologi s. å., allt v.\nKarol. inst. i Sthlm. Aman. v. Karol.\ninst,, underläk förordn, v. fi. las. samt\nv. sjukh. i Sthlm 13-19, underläk, v.\nSabbatsb. sjukh. röntgenavd. 20-21 o.\nv. Radiumhemmet 22-23, aman. v.\nSe-raf:las. röhtgeninst. 24, bitr. läk. där\n25-29, därunder t. f. överläk. v. öl.\nsjukh., t. f. prof. i med. radiologi 27-31,\nläk. o. förest, f. S :t Eriks sjukh.\nröntgenavd. 22-29, överläk. v. S :t Görans\nsjukh. röntgen- o. ljusavd. sed. 30. Utr.\nstudieresor 21, 24, 28, 34 o. 37. Skr.:\nett 50-tal skr., huvudsakl. inom med.\nradiol. o. dess gränsomr.   RNO,\nGV:s-OIGM.\nWesterståhl, Johan Olof, advokat,\nSthlm, f. 22/6/84 i Gtbg av postmast.\nJohan Louis W. o. Agnes Thorstenson.\nG. 14 m. Sonja Branting. Barn:\nHans-Jörgen f. 16. Studiex. i Sthlm 01, jur.\nkand. 16. Anst. å S. Aronssons\nAdvokatbyrå i Sthlm 17-27, egen advrverks.\ni Sthlm sed. .27. Led. av Sv.es\nAdv:-samf. 26.\nWestgren,, Arne Fredrik, professor,\nvetenskapsakademiens ständige sekr.,\nSthlm, f. 11/7/89 i Årjäng, Värml. 1., av\napot. Anders W. o. Selma Hammar. G.\n15 m. Elsa Nilson. Barn: Anders f. 16,\nIngrid f. 18, Anna Birgitta f. 19, d. 29.\nMog:ex. v. h. allm. lärov, i Upps. 07,\nfil. kand. i Upps. 10, fil. måg. 11, fil.\nlic. 14, fil. dr 15, stud. v. univ. i\nGöttingen 15-16. Doc. i fysikal. kemi v.\nuniv. i Upps. 17-19, anst. v. SKP i Gtbg\n18-20, v. Metallograf. inst. i Sthlm 21-26,\ndocent i metallografi v. Sthlms Högsk.\n21-27, prof. i allm. o. oorg. kemi där\n27-43, VA:s ständ. sekr. 43. Sekr. i\nVA :s Nobelkomm :r 26-43, led. av\nNobel-komm. f. kemi 42, ordf. 44, led. av\nFarm. inst :s styr. fr. 35. Dr-ing, h. c.\nv. Techn. Hochschule i Darmstadt 36,\nfil. dr h. c. i Dorpat 39. Skr.: avhandl,\nom Brownska rörelsen, legeringars\nstruktur m. m. RNO, LVA, LFS, LVS,\nLIVA.\nWestheimer, James Napoleon,\nskådespelare, operasångare, Sthlm, f. 17/11/\n84 i Sthlm. G. 41 m. Ester Carlsson.\nStud. violin v. Musikkonserv, i Sthlm\n02-06. Varit eng. v. östermalmsteat.\n(även verks. s. konsertmäst. därst.), v.\nSvenska Teat., v. Operan 10-35, bl. roll.:\nLöpar-Nisse, iEnterich i\nTiggarstudenten, Antonio i Figaros Bröllop, Benoit\no. Alcindor i Bohéme m. fi. Har sed.\n35 huvudsakl. varit verks. s.\nlutsångare, framför allt s. tolkare av Elias\nSehlstedt. Är ofta eng. v. Radioteat.\nsamt varit eng. v. ett flertal turnéer,\nund. fi. säsonger v. Skansens\nFrilufts-teat. i Sthlm, v. Liseberg i Gtbg 39 o.\n40, bl. roll.: Assessor Svale i Äventyr\npå Fotvandring, Jan Hansson i\nWärm-länningarna m. fi. Började i filmbr.\n35. Medv. s. skådespelare i filmerna:\nKungen kommer, Adolf Armstarke,\ninneh, titelrollen i en August\nBlanche-film. Medl. av Sv. Teat:förb., T. S. O.,\nP. B., W 6 Orden, Sveaorden, 1884 års\nmän o. Stallmästargårdens Vänner.\nWestholm, Daniel Alfred, docent,\nSthlm, f. 22/6/04 av lektor Alfred W.\no. Anna Bäckström. G. 40 m.\nIngegärd Beskow. Fil. kand. 32, fil. lic. 32,\nfil. dr o. docent i konsthist. v. Sthlms.\nHögsk. 36. Delt. i de arkeol, exp. t.\nAsine 26, Dendra 26-27, Cypern 27-31,\nförest, f. Gypernsaml. i Sthlm 34-45.\nSv res delegat v. N. F :s kongress f.\narkeol, utgrävn. i Kairo 37. Forskn\n:-resor t. de fi. europ, länder, Främre\nOrienten, Nordafrika o. U. S. A. Skr.:\nThe Paphian temple of Aphrodite (33),\nThe ternples of Soli (36), Built tombs\nin Cyprus (39), medarb, i The Swedish\nCyprus Exp. I-III (34-37), utg. av Asine,\nfinds and resuits of the Swedish Excav.\n1922-30 (38). RVO.\nWestholm, Johan Sigurd, f. d.\nstadsarkitekt, Norrviken, f. 4/12/71 i\nVästerås av kontr :prost. G. A. W. o. Ulla\nEricsson. G. 04 m. Elin Berglöf. Avg\n:-ex. fr. byggn :yrkessk. i Sthlm 92, fr.\nKTH 98, v. Konstakad. 98-00. Idk. ensk.\narkit :verks :h., delvis tills. m. arkit. J.\nA. Bagger, e. arkit. h. Sthlms stads\nbyggn :nd 04, stadsarkit. i Sthlm 16-40?\nsakk. h. statens byggn :lånebyrå 41.\nTjg. arkit, i byggn :styr. 21, ordf. i\nFö-ren. Sv :es Stadsarkitekter 23-41. KVO,\nRNO.\nWestin, Frits Georg Gabriel, kapten,\nbankkamrer, Lidingö, f. 1/8/87 i\nVaxholm av öv:löjtn. Hugo Werner W. o.\nGabriella Silfverswärd. G. 14 m. Vera\nAmelie Maria Freidenfelt. Barn: Gösta\nf. 16, kont.; Britte-Marie f. 17, g. m.\ning. Karl Cederlund J :r; Christer f. 19,\nfänrik v. I. 12; Bo f. 21, ing. o. fänrik;\nMargareta f. 23, g. m. försäkr :tj :man.\no. löjtn. Rolf Rygart; Jan-Sture f. 25,\nlantbr :elev; Frits f. 27; Gunnar f. 29.\nMog:ex. i Karlskrona 07. Res:off:ex.\n09, löjtn. 14, kapt. 25. Tj :man i Bank\nA-B Södra Sv :e i Karlskrona 07, anst. i\nSkånska Hdlsbanken i Sthlm 12, i\nBurman &amp; Co. 18-23, i Skand. Banken A-B\ni Sthlm 23, kamr. där 34. Av Sthlms\nHdlskamm, godk. granskn :man. Styr\n:-led. i Fören. Godkända Granskn :män.\nUtövar rev :verksamh.\nWestin, Gustaf Axel Hugo, f. d.\nkansliråd, Sthlm, f. 2/5/78 i Sthlm av v.\nhhövd. Eugene W. o. Aurora Swahn.\nG. 13 m. Elisabet Bylund. Barn:\nGunnar f. 14, fil. lic., amanuens, g. m.\nMarja Svärd; Ingrid f. 17, g. m. andre\nantikvarien, fil. lic. H. Hansson. Jur.\nutr. kand. i Upps. 04, Aman. i\nlant-försv:dep. 08, e. kanslise’kr. 16, l :e\nkanslisekr.   17,   kansliråd   i   försv:dep.\n21-43.    KNO.\nWestin, Gösta Egon Natanael,\nprofessor, Sthlm, f. 27/10/95 i Ystad av\nfolk-skollär. Nils W. o. Maria Nilsson. G.\n20 m, Anna Lundholm. Odont. kand.\n15, tandläk :ex. 18, med. hed :dr i Sthlm\n42. Assist, v. Tandl:inst. 19, t. f.\nlaborator där 24-25, ord. 25-27, t. f. lär. 27,\nord. lär. i tandfylln :konst 28, prof. i\nämnet 43, doc. l odontol. v. Kar öl. inst.\n32, disp. ss. f. med. drsgr.\n(dispens) 31, stud. tänd. patohistol. i\nBerlin 23, 24 o. 30, repr. f. Tandlänst. v.\nF. D. l :s internat, kongr, i Köpenh. 27,\nf. Sthlms stad v. Eastman klinik i\nLondon 30, sekr. v. S. O. L :s kongr, i\nSthlm 30, led. f. tandundersökn. v.\nmecl :styr :s soc :hyg. undersökn. i övre\nNorrl. 29-34, led. av näringsrådet sed.\n36, sakk. inom med :styr. f. utredn, av\ntandsjukd:s profylax 40, led. av\nförsv:-vüsendets tandv :utredn. 41, led. f.\nar-mésjukv :styr :s tandundersökn. på vpl.\n42, led. av komm. f. utredn, om med.\nforskn :råd 43, av komm. f. tandl\n:un-dervisn :s ordn. 43, vetenskapl. råd i\nfärsv iväsenclets sjukv iförvaltning 43.\nSkr.: ett 30-tal skrifter inom\ntandpatologin (spec. rörande vitaminbristernas\nskelett- o. tandinverkan, tandkaries o.\nparadentopatiernas etiologi o.\npatoge-nes, hårdsubstansombyggnadens teori\netc.), om tandsjukd:s utbredn.,\nfrekvens, statistik o. profylax samt upps.\ni soc :med. frågor, särsk. rör.\nfolktandvård o. undervisn. RISTO, RVO, RDDO.\nWestin, Ingiald (Inge) Henrik,\ninredningsarkitekt, Sthlm, f. 4/12/01 i Gtbg\nav adv. Karl Egron W. o. Thorborg\nCarlson. G. 33 m. frih :an Marianne\nStjernstedt. Barn: Johan f. 35, Karl f.\n39. Stud. v. Upps. univ., tekn. o.\nkonst-närl. stud. i Sthlm o. Paris. Start. 31\nInredn :f :an Domus, ’har delt, i ett stort\nantal utst. i såväl Sv :e s. utl.\nWestin, Jolin Gunnar, ingenjör, Sthlm,\nf. 30/12/83 i Sthlm av prof. O. E. W. o.\nLisen Nilsson. G. 32 m. Signe\nNordström. Barn: Gunvor f. 33. Ex. v.\nSchartaus hdlsinst. 02, mog:ex. i Sthlm\n05, KTH (maskinbyggn. o. mek. tekn.)\n05-08. Anst. v. S. J :s rep :verkst. v.\nLiljeholmen 08, v. Nationella iBolaget f.\nVärmeapparater i BuenoiS Aires 09-10,\nbitr. ing. h. vattenstyr, där 10-11, stud.\nväg- o. vattenbyggn ikonst i Tyskl.\n12-16, ing :ex. v. Polytechn. Inst. i Strelitz,\nbyggn :ing. v. Berlins elverk 16-19,\nkonstr, v. A-B Bofors 19-21, anst. v. Präzi-\nsionswerkstätten T’h. Rengman,\nBerlin-Charlottenburg, 22-23, repr. i Sthlm f.\nA-B Götaverken 24-26, anst. v. Buenos\nAires Great Southern Railway 26-29, v.\nA-B Westin &amp; Backlund i Sthlm sed.\n32. Led. av Sv. Tekn :fören.\nWestin, Josef Gunnar, lektor, Sthlm,\nf. 15/2/97 i Köpmanholmen, Västern. L,\nav faktorn P. W. o. Anna Persdtr. G.\n29 m. fil. måg. Margit Weideman. Stud\n:-ex. i Lund 20, fil. måg. i Lund 25, fil.\nlic. 27, fil. dr 30. E. lär. 23, lektor i\nhist. o. geogr. v. ’högre allm. lärov. f.\ngossar å Söderm. fr. 39. Skr.: Kultur^\ngeogr. stud. inom Nätra-, Naske- o.\nütbyäarnas flodomr. (akad. avh., 30),\nNelson-Westin: Lärob. i geogr. f.\nrealsk, o. kommun, mellansk. (30),\nÅngermani, hist. under Gustav Vasas o. hans\nsöners tid (44).\nWestin, Kjell, arkitekt SAR, Sthlm, f.\n21/1/96 på Frösön, Jämtl. 1., av\növerste-löjtn. Gerhard \\Vestin o. Agnes\nAndersson. G. 24 m. Anna Esberg. Barn:\nBirgitta f. 27, Anna-Lena f. 30, Torkel\nf. 32. Stud:ex. i Härnösand 14, ex. v.\nChalmers Tekn. Högsk, i Gtbg 17, egen\narkit :verksamh. i Sthlm SQå. 24. Bland\nutf. arb. märkas ett flert. restauranter\nf. Norma, SARA o. systembol. i Sthlm\no. landsorten, privata re’stauranter i\nSthlm, bankbyggn. o. inredn. f. A-B Sv.\nHdlsbanken, Riksbanken, Sundsv. Ensk.\nBank, Härnösands Sparbank, Östergötl.\nEnsk. Bank, Skarabörgsbanken,\nmilitära matinrättn. m. m.\nVestin,, Per Gustav, civilingenjör,\nDjursholm, f. 19/6/99 i Dalhiem, Kalmar\nL, av Vilhelm övid V. o. Maria\nSvanberg. G. 27 m. Margareta Svensson.\nBarn: Ingrid Serla Maria f. 28, Ulla\nMargareta f. 29, Carin Margareta f. 38.\nStud:ex. i Linköp. 17, KTH (VoV)\n19-23. Res:off :ex. 19, fänrik i fortif :s res.\n20, und:löjtn. 22, löjtn. VVK 28, kapten\nVVK 34. Anst. v. Bergsunds Mek.\nVerkst. A-B i Sthlm 24, bitr. h. statens\nlantbr ring. i Luleå 25, anst. v. Tekn.\nBergendahl &amp; Höckert i Sthlm 41-45, h.\nTolls Byggnads A-B i Sthlm sed. 45.\nWestling, Arvid William,\n’Civilingen-jör, Sthlm, f. 31/8/00 i Piteå av\njärnbandi. Wilh. W. o. Emilia Åström. G.\n32 m. Kerstin Zeinwoldt. Stud:ex. i\nLuleå 19, KTH 23, stud :res. t. Tyskl.,\nEngl., Österr., Holland o. Frankr. 23-25,\nASEAis elevkurs 24-25. Försäljning,\nv. ASEA 25-29, anst. v. Pat:- o.\nregistr:-verket 29, v. Sv. Radio A-JB 29-31, v.\nLME fr. 31, avd:ch. där.\nWestling, Erik Axel (Acke),\nstatssekreterare, Stocksund, f. 10/10/97 i\nÖrebro av rektor K. A. W. o. Karolina\nAndersson. G. 22 m. Aina Stuart. Barn:\nHarald f. 23, jur. stud.; Ann-Sofi f. 25,\nBarbro f. 30, Erik f. 36. Fil. kand. i\nGtbg 19. Aman. i soc :dep. 22, t. f. l :e\nkanslisekr. i kommunik :dep. 29, i fin\n:-dep. 32, l :e kanslisekr. där 33,\nkansliråd 36, exp :ch. 34-42, statssekr. i\nkommunik :dep. fr. 42. Statsmin :s\nhand-sekr. 23-24, sekr. i 21 års pens :komm.\n25, i studiedeleg. f. hosp :byggn :fråg. 28,\ni komm. f. riksd ;s arb iformer 31, led.\nav 34 års mil :pens isakk., ordf. i pens\n:-komm. f. riksdis verk 38, led. o.\nhu-vudsekr. 36-40 o. ordf. fr. 38 i 36 års\nlönekomm., ordf. i 38 års pens :sakk. o.\ni 41 års pens rkomm. f. riksd :s verk,\nled. av investeringsutredn. 43, ordf. i\n44 års personalutredn., led. av styr. f.\nstat. pens :anst. 33-34 o. ordf.fr. 40, not.\ni riksd :s bankoutsk. 20-27, sekr. 28-33.\nKNOlkl.\nWestling, Per Valdemar Nikolaus,\nadvokat, statens förlikningsman, Sthlm,\nf. 22/12/00 i Örebro av rekt. K. A. W.\no. Karolina Andersson. G. 1.29 ini. Elsa\nLilliestierna, d. 37; 2. 40 m. Elsa\nLindström. Realsk :ex. 15, i jordbr. 15-16,\ntj :m. i Gtbgs städs mantalsv. 16-22,\nstud :ex. s. priv. 20, aman. i Skolöverst.\n25, jur. kand. 26, notarie i Askims\nhäradsrätt 26, adv. i Linköping 27-41,\ni Sthlm fr. 42. Sekr. h. öistergötl. läns\nlandsting 33-41, taxeringsndns ordf.\n27-40, ordf. 1. led. i ett flert. styr. o. ndr,\nstat :s förlikn :man i arb itvister fr. 37,\nordf. 1. led. i ett flert.\nmedlingskom-miss. RVO.\nWestlund, Per, tandläkare, Sthlm, f.\n15/5/10 i Hede,sunda, Gävleb. 1. G. 38\nm. Eva Berggren. Barn: Ulf f. 40, Stig\nf. 41. Stud:ex. v. Karolinska lärov.-i\nÖrebro 30, med. stud. v. med. fakult. i\nUpps. vt. 31, tandl:kand. 32, tandl. 35.\nPraktik i Sthlm sed. 35.\nWestman, Axel Edvard, professor,\növerläkare, Sthlm, f. 29/12/94 i Sthlm\nav kyrkoh. Emil W. o. Elisabeth W.\nG. 24 ,m. Ruth Bengtson. Barn:\nElisabeth f. 27, Ann-Margret f. 31. Med.\nkand. 17, med. ilic. 22, med. dr 26, doc.\ni obstetr. o. gynekol. v. Karol. inst. 27,\nprof. i d:o i Upps. o. överläk. v. Akad.\nsjukh 32-35, prof. i d:o i Lund o.\növer-läk, v. länslas. där 35, prof. l d:o v.\nKarol. inst. fr. 42, överläk. v. Karol.\nsjukh. sed. 43. Ett flert. utl. stud:res.\nSkr.: Utg. ett 150-tail skr. i radiol., fy-\nsiol., obstetr. o. gynekol samt läro- o.\npop :vetenskapl. böcker. RNO, LVA,\nLFS, led. i flera utl. sällsk.\nWestman, Ernst Ragnar, ingenjör,\nSaltsjöbaden, f. 24/9/94 i Brooklyn, N.\n\\., U. S. A., av arkit. E. G. W. o. Elin\nAndersson. G. 28 m. Hildegard\nEkeroth. Barn: Lars Gustaf f. 34, Staffan\nf. 37. Stud :ex. v. Palmgrenska samsk.\ni Sthlm 14, KTH 16-18 o. 18-20\n(maskin-byggn. o. mek. tekn.). Rit. v. General\nElectric Co. i Schenectady, N. Y., U. S.\nA., 20-21, prakt, i U. S. A. 21-22, rit. o.\nkonstr, f. ångturbiner v. Allis\nChalmers Mfg. Co., Milwaukee, Wise., 22-23,\nkonsult, ing. v. Me’k. prövn ranst. i\nSthlm 26-34, v. Mell. o. N :a Sv:es\nÅng-pannefören. i Sundsvall 34, nu i Sthlm.\nWestman, Fredrik Viktor Agathon,\nbanktjänsteman, Sthlm, f. 22/8/87 i\nBollnäs av postmast. Fredrik W. o\nVendela Schönning. G. 21 m. Ruth\nEdith Pettersson. Barn: Hans f. 22,\nEva f. 25. Stud :ex. v. Upps. h. allm.\nlärov. 06, univ :stud. 06-13. Anst. s.\navd :led. i Bränslekommiss. 15-16,\nverkstadskamrer i A-B Slipmateriel,\n",
    "structured": {
        "1": {
            "full_name": "Vestergren, Erik Arvid",
            "location": "Sthlm",
            "occupation": "arkitekt",
            "birth_details": {
                "date": "01/01/1885",
                "place": "Gävle"
            },
            "education": [
                {
                    "degree": "filosofie kandidat",
                    "year": "1906",
                    "institution": "KTH"
                }
            ],
            "career": [
                {
                    "position": "praktik å arkit :kont",
                    "years": {
                        "start_year": 1914,
                        "end_year": 1927
                    },
                    "organization": "egen verksamhet i Gävle"
                },
                {
                    "position": "egen verksamhet i Sthlm",
                    "years": {
                        "start_year": 1927
                    }
                }
            ]
        },
        "2": {
            "full_name": "Westergren, Håkan Gari Leonard",
            "location": "Nockeby",
            "occupation": "skådespelare",
            "birth_details": {
                "date": "29/04/1899",
                "place": "Sthlm"
            },
            "education": [
                {
                    "degree": "stud :ex.",
                    "year": "1919",
                    "institution": "Sthlm"
                },
                {
                    "degree": "Dram. teat. elevsk.",
                    "year": "1920-1922"
                }
            ],
            "career": [
                {
                    "position": "eng.",
                    "years": {
                        "start_year": 1922,
                        "end_year": 1923
                    },
                    "organization": "Wasa, Finl."
                },
                {
                    "position": "blancheteat.",
                    "years": {
                        "start_year": 1924,
                        "end_year": 1928
                    },
                    "organization": "Blancheteatern"
                },
                {
                    "position": "oscarsteatern",
                    "years": {
                        "start_year": 1928,
                        "end_year": 1931
                    },
                    "organization": "Oscarsteatern"
                },
                {
                    "position": "dram. teat.",
                    "years": {
                        "start_year": 1932,
                        "end_year": 1934
                    },
                    "organization": "Dram. teat."
                },
                {
                    "position": "blancheteatern",
                    "years": {
                        "start_year": 1934,
                        "end_year": 1935
                    },
                    "organization": "Blancheteatern"
                }
            ],
            "family": {
                "spouse": "Inga Tidblad",
                "marriage_year": "1931",
                "children": [
                    {
                        "name": "Lena",
                        "birth_year": "NULL"
                    },
                    {
                        "name": "Margareta",
                        "birth_year": "NULL"
                    },
                    {
                        "name": "Claes-Håkan",
                        "birth_year": "NULL"
                    }
                ]
            },
            "hobbies": [
                "tennis",
                "fotboll"
            ]
        },
        "3": {
            "full_name": "Westergård, Anton Hilmer",
            "location": "Sthlm",
            "occupation": "fil. dr",
            "birth_details": {
                "date": "08/05/1880",
                "place": "Ränneslöv, Hallands 1"
            },
            "education": [
                {
                    "degree": "fil. kand.",
                    "year": "1902",
                    "institution": "Lund"
                },
                {
                    "degree": "fil. lic.",
                    "year": "1909",
                    "institution": "Lund"
                },
                {
                    "degree": "fil. dr",
                    "year": "1910",
                    "institution": "Lund"
                }
            ]
        },
        "4": {
            "full_name": "Westergård, Bertil Magnus",
            "location": "Lidingö",
            "occupation": "flygdirektör",
            "birth_details": {
                "date": "10/10/1904",
                "place": "Sthlm"
            },
            "family": {
                "spouse": "Brita Kindman",
                "marriage_year": "1934",
                "children": [
                    {
                        "name": "Magnus",
                        "birth_year": "1935"
                    },
                    {
                        "name": "Bengt",
                        "birth_year": "1939"
                    }
                ]
            }
        },
        "5": {
            "full_name": "Westerlind, Vilhelm Gottfrid",
            "location": "Dalarö",
            "occupation": "provinsialläkare",
            "birth_details": {
                "date": "29/10/1899",
                "place": "Köping"
            },
            "family": {
                "spouse": "Ingeborg Maria Gelhaar",
                "marriage_year": "1942"
            }
        },
        "6": {
            "full_name": "Westerling, Sven Gerhard",
            "location": "Sthlm",
            "occupation": "överstelöjtnant",
            "birth_details": {
                "date": "3/8/1884",
                "place": "Sthlm"
            },
            "family": {
                "spouse": "Ingrid Elisabeth Lindqvist",
                "marriage_year": "1916"
            }
        },
        "7": {
            "full_name": "Westermark, Johan Herbert",
            "location": "Sthlm",
            "occupation": "med. dr",
            "birth_details": {
                "date": "30/8/1891",
                "place": "Sthlm"
            },
            "family": {
                "spouse": "Elly Garlström",
                "marriage_year": "1920"
            }
        },
        "8": {
            "full_name": "Westermark, Nils Johan Hugo",
            "location": "Sthlm",
            "occupation": "med. dr, docent, överläkare",
            "birth_details": {
                "date": "9/9/1892",
                "place": "Sthlm"
            },
            "family": {
                "spouse": "Jane Ingrid Bergliot Weidenhielm",
                "marriage_year": "1922",
                "children": [
                    {
                        "name": "Jane Bergliot Marianne",
                        "birth_year": "1923"
                    },
                    {
                        "name": "Jane Berit Margaret",
                        "birth_year": "1924"
                    },
                    {
                        "name": "Jan Erik Nils",
                        "birth_year": "1926"
                    },
                    {
                        "name": "Per Erik Nils",
                        "birth_year": "1929"
                    }
                ]
            }
        },
        "9": {
            "full_name": "Westerståhl, Johan Olof",
            "location": "Sthlm",
            "occupation": "advokat",
            "birth_details": {
                "date": "22/6/1884",
                "place": "Gtbg"
            },
            "family": {
                "spouse": "Sonja Branting",
                "marriage_year": "1914",
                "children": [
                    {
                        "name": "Hans-Jörgen",
                        "birth_year": "1916"
                    }
                ]
            }
        },
        "10": {
            "full_name": "Westgren, Arne Fredrik",
            "location": "Sthlm",
            "occupation": "professor, vetenskapsakademiens ständige sekr.",
            "birth_details": {
                "date": "11/7/1889",
                "place": "Årjäng, Värml. 1."
            },
            "education": [
                {
                    "degree": "mog:ex.",
                    "year": "1907",
                    "institution": "h. allm. lärov"
                },
                {
                    "degree": "fil. kand.",
                    "year": "1910",
                    "institution": "Upps."
                },
                {
                    "degree": "fil. måg.",
                    "year": "1911",
                    "institution": "Upps."
                },
                {
                    "degree": "fil. lic.",
                    "year": "1914",
                    "institution": "Upps."
                },
                {
                    "degree": "fil. dr",
                    "year": "1915",
                    "institution": "Göttingen"
                }
            ],
            "family": {
                "spouse": "Elsa Nilson",
                "marriage_year": "1915",
                "children": [
                    {
                        "name": "Anders",
                        "birth_year": "1916"
                    },
                    {
                        "name": "Ingrid",
                        "birth_year": "1918"
                    },
                    {
                        "name": "Anna Birgitta",
                        "birth_year": "1919",
                        "death_year": "1929"
                    }
                ]
            }
        },
        "11": {
            "full_name": "Westheimer, James Napoleon",
            "location": "Sthlm",
            "occupation": "skådespelare, operasångare",
            "birth_details": {
                "date": "17/11/1884",
                "place": "Sthlm"
            },
            "family": {
                "spouse": "Ester Carlsson",
                "marriage_year": "1941"
            }
        },
        "12": {
            "full_name": "Westholm, Daniel Alfred",
            "location": "Sthlm",
            "occupation": "docent",
            "birth_details": {
                "date": "22/6/1904",
                "place": "NULL"
            },
            "family": {
                "spouse": "Ingegärd Beskow",
                "marriage_year": "1940"
            }
        },
        "13": {
            "full_name": "Westholm, Johan Sigurd",
            "location": "Norrviken",
            "occupation": "f. d. stadsarkitekt",
            "birth_details": {
                "date": "4/12/1871",
                "place": "Västerås"
            },
            "family": {
                "spouse": "Ulla Ericsson",
                "marriage_year": "1904"
            }
        },
        "14": {
            "full_name": "Westin, Frits Georg Gabriel",
            "location": "Lidingö",
            "occupation": "kapten, bankkamrer",
            "birth_details": {
                "date": "1/8/1887",
                "place": "Vaxholm"
            },
            "family": {
                "spouse": "Vera Amelie Maria Freidenfelt",
                "marriage_year": "1914",
                "children": [
                    {
                        "name": "Gösta",
                        "birth_year": "1916"
                    },
                    {
                        "name": "Britte-Marie",
                        "birth_year": "1917"
                    },
                    {
                        "name": "Christer",
                        "birth_year": "1919"
                    },
                    {
                        "name": "Bo",
                        "birth_year": "1921"
                    },
                    {
                        "name": "Margareta",
                        "birth_year": "1923"
                    },
                    {
                        "name": "Jan-Sture",
                        "birth_year": "1925"
                    },
                    {
                        "name": "Frits",
                        "birth_year": "1927"
                    },
                    {
                        "name": "Gunnar",
                        "birth_year": "1929"
                    }
                ]
            }
        },
        "15": {
            "full_name": "Westin, Gustaf Axel Hugo",
            "location": "Sthlm",
            "occupation": "f. d. kansliråd",
            "birth_details": {
                "date": "2/5/1878",
                "place": "Sthlm"
            },
            "family": {
                "spouse": "Elisabet Bylund",
                "marriage_year": "1913",
                "children": [
                    {
                        "name": "Gunnar",
                        "birth_year": "1914"
                    },
                    {
                        "name": "Ingrid",
                        "birth_year": "1917"
                    }
                ]
            }
        },
        "16": {
            "full_name": "Westin, Gösta Egon Natanael",
            "location": "Sthlm",
            "occupation": "professor",
            "birth_details": {
                "date": "27/10/1895",
                "place": "Ystad"
            },
            "education": [
                {
                    "degree": "odont. kand.",
                    "year": "1915",
                    "institution": "NULL"
                },
                {
                    "degree": "tandläk :ex.",
                    "year": "1918",
                    "institution": "NULL"
                }
            ],
            "family": {
                "spouse": "Anna Lundholm",
                "marriage_year": "1920"
            }
        },
        "17": {
            "full_name": "Westin, Ingiald",
            "location": "Sthlm",
            "occupation": "inredningsarkitekt",
            "birth_details": {
                "date": "4/12/1901",
                "place": "NULL"
            },
            "family": {
                "spouse": "frih :an Marianne Stjernstedt",
                "marriage_year": "NULL",
                "children": [
                    {
                        "name": "Johan",
                        "birth_year": "1935"
                    },
                    {
                        "name": "Karl",
                        "birth_year": "1939"
                    }
                ]
            }
        },
        "18": {
            "full_name": "Westin, Jolin Gunnar",
            "location": "Sthlm",
            "occupation": "ingenjör",
            "birth_details": {
                "date": "30/12/1883",
                "place": "Sthlm"
            },
            "family": {
                "spouse": "Signe Nordström",
                "marriage_year": "1932",
                "children": [
                    {
                        "name": "Gunvor",
                        "birth_year": "1933"
                    }
                ]
            }
        },
        "19": {
            "full_name": "Westling, Arvid William",
            "location": "Sthlm",
            "occupation": "statssekreterare",
            "birth_details": {
                "date": "10/10/1897",
                "place": "Örebro"
            },
            "family": {
                "spouse": "Aina Stuart",
                "marriage_year": "1922",
                "children": [
                    {
                        "name": "Harald",
                        "birth_year": "1923"
                    },
                    {
                        "name": "Ann-Sofi",
                        "birth_year": "1925"
                    },
                    {
                        "name": "Barbro",
                        "birth_year": "1930"
                    },
                    {
                        "name": "Erik",
                        "birth_year": "1936"
                    }
                ]
            }
        },
        "20": {
            "full_name": "Westling, Per Valdemar Nikolaus",
            "location": "Sthlm",
            "occupation": "advokat, statens förlikningsman",
            "birth_details": {
                "date": "22/12/1900",
                "place": "Örebro"
            },
            "family": {
                "spouse": "Elsa Lilliestierna, d. 1937",
                "marriage_year": "1929"
            }
        },
        "21": {
            "full_name": "Westlund, Per",
            "location": "Sthlm",
            "occupation": "tandläkare",
            "birth_details": {
                "date": "15/5/1910",
                "place": "Hedesunda, Gävleb. 1."
            },
            "family": {
                "spouse": "Eva Berggren",
                "marriage_year": "1938",
                "children": [
                    {
                        "name": "Ulf",
                        "birth_year": "1940"
                    },
                    {
                        "name": "Stig",
                        "birth_year": "1941"
                    }
                ]
            }
        },
        "22": {
            "full_name": "Westman, Axel Edvard",
            "location": "Sthlm",
            "occupation": "professor, överläkare",
            "birth_details": {
                "date": "29/12/1894",
                "place": "Sthlm"
            },
            "family": {
                "spouse": "Ruth Bengtson",
                "marriage_year": "1924",
                "children": [
                    {
                        "name": "Elisabeth",
                        "birth_year": "1927"
                    },
                    {
                        "name": "Ann-Margret",
                        "birth_year": "1931"
                    }
                ]
            }
        },
        "23": {
            "full_name": "Westman, Ernst Ragnar",
            "location": "Sthlm",
            "occupation": "banktjänsteman",
            "birth_details": {
                "date": "22/8/1887",
                "place": "Bollnäs"
            },
            "family": {
                "spouse": "Hildegard Ekeroth",
                "marriage_year": "1928",
                "children": [
                    {
                        "name": "Lars Gustaf",
                        "birth_year": "1934"
                    },
                    {
                        "name": "Staffan",
                        "birth_year": "1937"
                    }
                ]
            }
        }
    }
}