{
    "original": "Valberg, Gustaf Einar, civilingenjör,\nSthlm, f. 14/10/91 i Västerås. G. 22 m.\nElsa Hilma Elvira Pettersson. Barn:\nElsa Gerd Ann-Mari f. 26. Stud:ex. i\nVästerås 10, avg:ex. v. KTH 15. Anst..\nh. prof. Karl Ljungberg 15-22, deläg. i\ndennes ing:byrå 22-39, assist, i\nhållfasthetslära v. KTH 22-42, inneh, egen\ning :byrå i Sthlm f. planering o. konstr,\nav fabr:byggn., byggn :konstr. o.\nbygg-n:tekn. sed. 39. Har i samarb. m. prof.\nK.Ljungberg utf. konstr, f. S:a\nKungstornet, PUB :s affärshus m. fi.,\nfabriks-o. lagerbyggn. f. L. M. Ericsson,\nKvarnen Tre Kronor, ASEA, Stora Kopparb.\nBergslags A-B, KF, m. fi. Vunnit l :a\ninköp. v. tävlan om Västerbron i Sthlm,\nutarb. förslag t. montagebågar f.\nTranebergsbron m. fi. broar i in- o. utl.\nUtf. hållfasthetsund :sökn. f. en mängd\nmaskinkonstr., f. radiomaster v. Hörby,\nLuleå, Borlänge, Stavsnäs m. fi. Resa\nt. Engl. m. stip. fr. Komm :koll. f.\nstudier av hållfasthetslab. 24, besökt\nTyskl., Norge o. Danm. Skr.: upps. i\nfacktidskr., lett utgiv. av avh. Byggn\n:-teor. i samlingsverket Byggn :konsten\n(28).\nWalberg, Sven, kapten, direktör,\nSthlm, f. 10/2/99 i Skön, Västernorrl. L,\nav förvalt. S. G. W. o. Kristina\nBre-denberg. G. 23 m. Barbro Huldt. Barn:\nBarbro Svensdotter f. 24, Sven-Krister\nSvensson f. 32, Ulf Svensson f. 35.\nStud:ex. i Sundsv. 18, sjöoff :ex. o. fänr.\nv. flottan 21, löjtn. 23, löjtn. v. flottans\nres. 31, kapten 36. Avd:chef f.\nPulvis-avd. v. J. &amp; G. G. Bolinders Mek. Verkst.\nA-B, Sthlm, 29-33, försäljn :chef v.\nBolinders Fabr. A-B, Sthlm, 33-34, dir. där\nsed. 35, verkst, dir. f. Ångfartygs A-B\nGotland, Visby, sed. 45. Medl. av Sthlms\nSportfiskeklubb, Skidfrämj., Sv.\nTurist-f ören., Flott. Res :off :förb., Sv. Teknol\n:-fören., Motormännens Riksförb. Skr.:\nett ant. art. o. upps. i tidn. o. tidskr.\nWaldekranz, Rune, fil. måg., Sthlm,\nf. 14/9/11 i Turinge, Sthlms 1., av Einar\nW. o. Olga Emthén. G. 43 m. Ebon\nRingblom. Studiex. i Södertälje 31,\nfil. kand. i Upps. 35, fil. mag. 37.\nStudieresor t. Tyskl., Österrike, Ungern,\nItalien 34. Medarb, i Sv. Dagbl. 39-42,\nproduktionschef i Sandrew-Produktion.\nSkr.: Filmen växer upp (Gebers förlag\n41). Hobby: Film- o. teaterhist.\nWaldén, Sven Gunnar, tandläkare,\nSthlm, f. 5/11/04 i Älvkarleby, Upps. L,\nav trafikchefen Otto W. o. Maria\nMo-nie. G. 29 m. Birgit Lundquist. Barn:\nBritt-Marie f. 31, Björn f. 34, Svante f.\n43. Stud:ex. v. Saltsjöbadens samsk.\n23, med. kand. v. Karol. inst. 27, tandl\n:-ex. 29. Praktik i Sthlm sed. 30. Medl.\nav Saltsjöbadens kommunalfullm,,\nkommunalnämnd m. m.\nvon Waldén, Georg Natanael,\ningenjör, Sthlm, f. 22/12/09 i Nysätra, Upps.\n1., av Johan Albert von W. o. h. h.\nAlma Carolina. Stud. v.\nMaskinyrkesskolan 30-32, v. STI (elektr.) 32-34,\ning:ex. där 34, stud. v. Sthlms\nSam-gymn. 35. Verkst :ing. v. Paals Electr.\n35-36, egen fabriks- o. hdlsrör.,\nIng:-firman Valvo, i Sundbyberg sed. 36.\nTillv. apparater m. m. f. frisörbransch.,\nkonsult, ing-.verksamh., exp. egna\ntill-verkn. t. Norge, Finl., Holl., Belgien,\nSchweiz, Portugal, Brasilien, U. S. A.,\nf. n. förhandl. m. Spanien o. Slovakien.\nWaldenström, Erland, civilingenjör,\nSthlm, f. 4/6/11 i Malmö av dir. M. E.\nW. o. Hedvig Lion. Stud:ex. i Nyköp.\n29, avg :ex. v. KTH 33. Ing. v. Korsnäs\nSågverks A-B 34 o. 36-40, tekn. sekr. v.\nSv. Ind:förb. 40-42, chef f. Sv. Cellulosa\nA-B :s tekn. byrå sed. 42. Föret, stud\n:-resor t. U. S. A. o. Canada 34-35,\nFrankrike 35 samt resor t. England, Tyskl.,\nHolland, Belgien, Italien m. fi. länder.\nSkr.: Till frågan om det industriella\nframåtskridandet i Sv:e (tills. m. I.\nSvennilsson), ,skr. f. Ind:s\nNorrlands-utredn. samt ett flert. upps. i tekn. o.\nekon. fråg. Led. av Sv. Tekn:fören.\nfr. 33.\nWaldenström, Esaias, f. d.\nkammarrättsråd, Djursholm, f. 22/1/74 i Upps.\nav lekt. P. P. W. o. Mathilda Hallgren.\nG. 12 m. Julia Hultman. Barn: Ingrid\nf. 12, e. landskont.; Paul f. 13, sjökapt.;\nSigurd f. 15, jur. kand.; Karin f. 16,\nskolkökslär:a; Erik f. 18, jur. stud.;\nAnders f. 19, tj :man. Jur. utr. kand. i\nUpps. 01, not. i Jämtl. 1. v:a doms.\n01-04, aman. i järnv :styr. 06-08, not. i\nbev:utsk. 07, sekr. i kamm:rätten 09,\nkammarr :råd 12-41, avg. 41. Red. f.\nkamm:rätt:s årsbok 26-41. Skr.: ref.\nav fattigv:mål. KNO.\nWaldenström, Johan Henning,\nprofessor emeritus, Lidingö, f. i Uppsala\n14/8/77 av prof. Joh. W. o. Elisabeth\nGibson. G. 1. 05-27 m. Elsa Laurin, d.\n39; 2. 27 m. Ella Wijk. Med. kand.\nKarol. inst. 01, med. lic. 06. Und:kir.\nv. Kronpr :an Lovisas vårdanst. 074)9,\ndisp. f. drsgrad. 10, doc. i ortoped. kir.\n10-36, överläk. v. S :t Görans avd. f. kir.\ntuberk. 10-36, prof. i ortopedi v. Karol.\ninst. o. överläk. v. Vanföreanst. i Sthlm\n36-42. Medl. av styr. f. Gustaf V :s\n80-års fond 38, av med :styr :s vetensk. råd,\nhed:led. av Brit. Orthop. Assoc., av\nAmer. Acad. of Orthop. Surgeons, av\nSoc. franQ. d’orthopédie o. av Deutsche\northopäd. Ges. Utg. skr. huv.sakl.\ninom bensyst. skador o. sjukd., medarb,\ni Nord. lärob. i kir. KNO, FFrK3kl,\nRFrHL.\nWaldenström, Johannes,, advokat,\nSthlm, f. 14/9/72 i Umeå av lekt. P. P.\nW. o. Mathilda Hallgren. G. 32 m.\nCe-oilie Liljewalch, f. Rustad. Jur. fil. ex.\n93, stud. i Tyskl. 95-96, jur. utr. kand.\n99. Tjg. i Ås o. Gäsene doms. 99-00, i\nS:a Möre härads doms. 00-03, ss. t. f.\nhhövd. und. 02 o. 03, tjg. i Svea hovr.\no. Sthlms rådst:r. 03, å riksbank, omb\n:-exp. 02-04, egen adv :verksamh. i Sthlm\nsed. 03.\nWaldenström, Martin lEmanuel,\ndirektör, Sthlm, f. 1/5/81 i Gävle av lekt.\nP. P. W. o. Mathilda Hallgren. G. 07\nm. Hedvig Lion. Barn: Elisabet f. 08,\nErland f. 11, Lars f. 12. Hovr :ex. i\nUpps. 03. Anst. å Nils Setterwall\nadv:byrå i Sthlm 03-06, deläg. i adv\n:-f :a Bendz &amp; Waldenström i Malmö\n06-11, inneh. adv:byrå und. eg. namn där\n11-17, adv. i Sthlm 18-21, dir. i Skand.\nKredit A-B 21-28, styr :led. där sed. 22,\nv. verkst, dir. i Trafik A-te\nGrängesberg-Oxelösund o.\nLuossavaara-Kiirunavaara A-B 28, verkst, dir. där sed. 30.\nStyr :led. i Sv. arb :giv :fören., Sv. allm.\nexportfören. o. Sv. ind:förb., fullm. i\nSthlms hdlskamm. KmstkNO, KVOlkl.\nWaldenström, Olof Alfred, kanslichef,\nSthlm, f. 17/2/00 i Ljungby, Kalmar 1.,\nav hhövd. Alfred W. o. Gabriella\nRom-dahl. G. 25 m. Brita Elmquist. Barn:\nJohan f. 26, Magnus f. 29, Christina f.\n33. Jur. kand. Upps. 26, sekr. i Stat.\nsockerkommiss. 28, anst. i Sv. Hdlsbk.\n29, sekr. i Sv. arb :giv :fören. 30-39,\nkanslichef fr. 40. Suppl, i Arbetsrådet\nfr. 39, i Folkberedsk:ndn fr. 42, led. av\nstyr. f. Näringslivets granskn :nd fr. 45,\nsekr. i komm. f. arbetshjälp åt Finl., i\nhjälpkomm. f. Finl. invalider. RVO,\nKFinlLO, FFrKSkl, RFinlVROlkl.\nWaldenström,, Torsten Emanuel,\ntandläkare, Sthlm, f. 15/11/11 i Sthlm av\nciv ring. Einar W. o. Hill Sandström.\nStudrex. v. Nyköp. h. allm. lärov. 32,\ntandl:kand. 36, tandl:ex. 39. Eg. prakt,\ni Sthlm sed. 42.\nWaldimir, Sune, kapellmästare, Sthlm,\nf. 15/11/07 i Västerås. Barn i föreg,\näktenskap: Birgit f. 31, Anders f. 34,\nLars f. 39, Lillemor f. 42. Realex, i\nVästerås 24, Kgl. Musikkons, i Sthlm t.\n28.    Anst. s. repetitör v. Kgl. Teat.\n26-30,  musikal,  led. f. Wiggerskvartetten\n29-35, varit anst. v. grammofonbolagen\nOdéon o. Decca samt Husbondens Röst.\nEng. s. kapellm. v. Radiotjänst sed. 36.\nBörj.’i filmbr. 30 m. musikarr. t.\nBrokiga Blad, arb. f. S. F., Terrafilm, Film\nA-B Paramount m. fi.   Medv. m. musik\nt. film.: Ungdom av i dag, Melodin fr.\nGamla sta’n, Åh, en så’n grabb, Kungl,\npatrasket m. fi.   Gästdir. i Norge,\nDanmark, Finland, England, v. Oscarsteat.\ni   Sthlm   i   Blåjackor   o.   Teaterbåten.\nStudieresor t. England ett flertal ggr.\nMedl.  av  TSO,  Odd Fellow-Orden,\nBifrost o. PB-Orden.\n",
    "structured": {
        "1": {
            "full_name": "Valberg, Gustaf Einar",
            "location": "Stockholm",
            "occupation": "Civilingenjör",
            "birth_details": {
                "date": "14/10/1891",
                "place": "Västerås"
            },
            "family": {
                "spouse": "Elsa Hilma Elvira Pettersson",
                "marriage_year": "1922",
                "children": [
                    {
                        "name": "Elsa Gerd Ann-Mari",
                        "birth_year": "1926"
                    }
                ]
            },
            "education": [
                {
                    "degree": "Stud:ex.",
                    "year": "1910",
                    "institution": "Västerås"
                },
                {
                    "degree": "Avg:ex. v. KTH",
                    "year": "1915",
                    "institution": "KTH"
                }
            ],
            "career": [
                {
                    "position": "Assist, i hållfasthetslära v. KTH",
                    "years": {
                        "start_year": 1922,
                        "end_year": 1942
                    }
                },
                {
                    "position": "Inneh, egen ing :byrå i Sthlm",
                    "years": {
                        "start_year": 1939
                    }
                }
            ]
        },
        "2": {
            "full_name": "Walberg, Sven",
            "location": "Stockholm",
            "occupation": "Kapten, Direktör",
            "birth_details": {
                "date": "10/02/1899",
                "place": "Skön, Västernorrl. L"
            },
            "family": {
                "spouse": "Barbro Huldt",
                "marriage_year": "1923",
                "children": [
                    {
                        "name": "Barbro Svensdotter",
                        "birth_year": "1924"
                    },
                    {
                        "name": "Sven-Krister Svensson",
                        "birth_year": "1932"
                    },
                    {
                        "name": "Ulf Svensson",
                        "birth_year": "1935"
                    }
                ]
            },
            "education": [
                {
                    "degree": "Stud:ex.",
                    "year": "1918",
                    "institution": "Sundsv."
                },
                {
                    "degree": "Sjöoff :ex. o. fänr. v. flottan",
                    "year": "1921"
                }
            ],
            "career": [
                {
                    "position": "Verkst, dir. f. Ångfartygs A-B Gotland, Visby",
                    "years": {
                        "start_year": 1945
                    }
                }
            ]
        },
        "3": {
            "full_name": "Waldekranz, Rune",
            "location": "Stockholm",
            "occupation": "Fil. Mag.",
            "birth_details": {
                "date": "14/09/1911",
                "place": "Turinge, Sthlms 1."
            },
            "family": {
                "spouse": "Ebon Ringblom",
                "marriage_year": "1943"
            },
            "education": [
                {
                    "degree": "Studiex.",
                    "year": "1931",
                    "institution": "Södertälje"
                },
                {
                    "degree": "Fil. Kand.",
                    "year": "1935",
                    "institution": "Uppsala"
                },
                {
                    "degree": "Fil. Mag.",
                    "year": "1937"
                }
            ],
            "career": [
                {
                    "position": "Produktionschef i Sandrew-Produktion",
                    "years": {
                        "start_year": 1939,
                        "end_year": 1942
                    }
                }
            ],
            "hobbies": [
                "Film- o. teaterhist."
            ]
        },
        "4": {
            "full_name": "Waldén, Sven Gunnar",
            "location": "Stockholm",
            "occupation": "Tandläkare",
            "birth_details": {
                "date": "5/11/1904",
                "place": "Älvkarleby, Upps. L"
            },
            "family": {
                "spouse": "Birgit Lundquist",
                "marriage_year": "1929",
                "children": [
                    {
                        "name": "Britt-Marie",
                        "birth_year": "1931"
                    },
                    {
                        "name": "Björn",
                        "birth_year": "1934"
                    },
                    {
                        "name": "Svante",
                        "birth_year": "1943"
                    }
                ]
            },
            "education": [
                {
                    "degree": "Stud:ex.",
                    "year": "1923",
                    "institution": "Saltsjöbadens samsk."
                },
                {
                    "degree": "Med. Kand.",
                    "year": "1927",
                    "institution": "Karol. inst."
                },
                {
                    "degree": "Tandl :ex.",
                    "year": "1929"
                }
            ]
        },
        "5": {
            "full_name": "von Waldén, Georg Natanael",
            "location": "Stockholm",
            "occupation": "Ingenjör",
            "birth_details": {
                "date": "22/12/1909",
                "place": "Nysätra, Upps. 1."
            },
            "education": [
                {
                    "degree": "Stud. v. Maskinyrkesskolan",
                    "year": "1930-1932"
                },
                {
                    "degree": "V. STI (elektr.)",
                    "year": "1932-1934"
                },
                {
                    "degree": "Ing:ex. där",
                    "year": "1934"
                },
                {
                    "degree": "Stud. v. Sthlms Sam-gymn.",
                    "year": "1935"
                }
            ],
            "career": [
                {
                    "position": "Egen fabriks- o. hdlsrör. Ing:-firman Valvo",
                    "years": {
                        "start_year": 1936
                    }
                }
            ]
        },
        "6": {
            "full_name": "Waldenström, Erland",
            "location": "Stockholm",
            "occupation": "Civilingenjör",
            "birth_details": {
                "date": "4/6/1911",
                "place": "Malmö"
            },
            "family": {
                "spouse": "Hedvig Lion"
            },
            "education": [
                {
                    "degree": "Stud:ex.",
                    "year": "1929",
                    "institution": "Nyköp."
                },
                {
                    "degree": "Avg:ex. v. KTH",
                    "year": "1933",
                    "institution": "KTH"
                }
            ]
        },
        "7": {
            "full_name": "Waldenström, Esaias",
            "location": "Djursholm",
            "occupation": "F. d. Kammarrättsråd",
            "birth_details": {
                "date": "22/1/1874",
                "place": "Uppsala"
            },
            "family": {
                "spouse": "Julia Hultman",
                "children": [
                    {
                        "name": "Ingrid",
                        "birth_year": "1912"
                    },
                    {
                        "name": "Paul",
                        "birth_year": "1913"
                    },
                    {
                        "name": "Sigurd",
                        "birth_year": "1915"
                    },
                    {
                        "name": "Karin",
                        "birth_year": "1916"
                    },
                    {
                        "name": "Erik",
                        "birth_year": "1918"
                    },
                    {
                        "name": "Anders",
                        "birth_year": "1919"
                    }
                ]
            },
            "education": [
                {
                    "degree": "Jur. Utr. Kand.",
                    "year": "1901",
                    "institution": "Upps."
                },
                {
                    "degree": "Not. i Jämtl. 1. v:a Doms.",
                    "year": "1901-1904"
                },
                {
                    "degree": "Aman. i Järnv :styr.",
                    "year": "1906-1908"
                }
            ]
        },
        "8": {
            "full_name": "Waldenström, Johan Henning",
            "location": "Lidingö",
            "occupation": "Professor Emeritus",
            "birth_details": {
                "date": "14/8/1877",
                "place": "Uppsala"
            },
            "family": {
                "children": [
                    {
                        "name": "Elsa Laurin"
                    }
                ]
            }
        },
        "9": {
            "full_name": "Waldenström, Johannes",
            "location": "Stockholm",
            "occupation": "Advokat",
            "birth_details": {
                "date": "14/9/1872",
                "place": "Umeå"
            },
            "family": {
                "spouse": "Ce-oilie Liljewalch, f. Rustad",
                "marriage_year": "1932"
            },
            "education": [
                {
                    "degree": "Jur. Fil. Ex.",
                    "year": "1893"
                },
                {
                    "degree": "Jur. Utr. Kand.",
                    "year": "1899"
                }
            ]
        },
        "10": {
            "full_name": "Waldenström, Martin lEmanuel",
            "location": "Stockholm",
            "occupation": "Direktör",
            "birth_details": {
                "date": "1/5/1881",
                "place": "Gävle"
            },
            "family": {
                "spouse": "Hedvig Lion",
                "children": [
                    {
                        "name": "Elisabet",
                        "birth_year": "1908"
                    },
                    {
                        "name": "Erland",
                        "birth_year": "1911"
                    },
                    {
                        "name": "Lars",
                        "birth_year": "1912"
                    }
                ]
            }
        },
        "11": {
            "full_name": "Waldenström, Olof Alfred",
            "location": "Stockholm",
            "occupation": "Kanslichef",
            "birth_details": {
                "date": "17/2/1900",
                "place": "Ljungby, Kalmar 1."
            },
            "family": {
                "spouse": "Brita Elmquist",
                "children": [
                    {
                        "name": "Johan",
                        "birth_year": "1926"
                    },
                    {
                        "name": "Magnus",
                        "birth_year": "1929"
                    },
                    {
                        "name": "Christina",
                        "birth_year": "1933"
                    }
                ]
            },
            "education": [
                {
                    "degree": "Jur. Kand.",
                    "year": "1926",
                    "institution": "Upps."
                }
            ]
        },
        "12": {
            "full_name": "Waldenström, Torsten Emanuel",
            "location": "Stockholm",
            "occupation": "Tandläkare",
            "birth_details": {
                "date": "15/11/1911",
                "place": "Stockholm"
            },
            "education": [
                {
                    "degree": "Studrex. v. Nyköp. h. allm. lärov.",
                    "year": "1932"
                },
                {
                    "degree": "Tandl:kand.",
                    "year": "1936"
                },
                {
                    "degree": "Tandl:ex.",
                    "year": "1939"
                }
            ]
        },
        "13": {
            "full_name": "Waldimir, Sune",
            "location": "Stockholm",
            "occupation": "Kapellmästare",
            "birth_details": {
                "date": "15/11/1907",
                "place": "Västerås"
            },
            "family": {
                "children": [
                    {
                        "name": "Birgit",
                        "birth_year": "1931"
                    },
                    {
                        "name": "Anders",
                        "birth_year": "1934"
                    },
                    {
                        "name": "Lars",
                        "birth_year": "1939"
                    },
                    {
                        "name": "Lillemor",
                        "birth_year": "1942"
                    }
                ]
            },
            "education": [
                {
                    "degree": "Realex.",
                    "year": "1924"
                },
                {
                    "degree": "Kgl. Musikkons.",
                    "year": "1928"
                }
            ]
        }
    }
}