{
    "original": "DINKELSPIEL, MAX, Dr Jur,\ndirektör, Sthlm, f i Trieste 12/7/98 av\nkonsul Adolf D o Emilie Nordlinger.\nVerkst dir bankirf:a E Öhman j:r ab.\n-Ag Trångsunds gård Södertörn. - Utm:\nRVO, RÖF02kl.\n\nGift 36 m Brita Björnstjerna f 13, dtr\nt kapten Roger B o Sigrid Kleen.\n-Barn: Gunilla f 37, Ulf f 39, Claes\nf 41.\n\nDINTER, ZVONIMIR, docent,\nNäsbypark, f i Osijek, Jugoslavien, 24/\n10/14.\n\nStud:ex 33, teg veterinär Zagreb\nJugoslavien 38, doc i virologi där 43, doc\nVHS Sthlm 59. - Ass Veterinärfak\nZagreb 41, vetensk medarb öl tyska inst\n42, ass SVA 49, laborator 50,\navdeln:-förest sed 53 (tf 51), med tjg v Virolog\ninst Upps univ sed 56. - Medl Sv\nlakar-sälli$k:s mikrobiol sekt, Sällsk f\nvet:-med forskn. - Skr: ett 70-tal upps i\nfacktidisfcr rör bakteriol o virol av öl\nhusdjursjukd. - Utm: RNO.\nGift 2) 55 m Elsie Bucht f 28, dtr t\ndir Harry B o Lisa Bodman!. - Barn:\ni l:a akt Peter f 47, i 2:a akt Anna\nf 56, Lena f 58.\n\nDIRKE, S OLLE, direktör, Nacka, f\ni Lindesberg, Örebro l, 5/12/24 av fil\nmag Erik Johansson o Rut Johanson.\nStud:ex Kristinehamn 43, KTH 48,\nanst STAL Finspång 48, konsult ing\nmek prövn:anst Sthlm 50, STAL\n51, övering o verkst:ch 58, dir\nTurbin ab de Laval Ljungström sed 61,\nplatsch i Nacka. - Styr:led de Laval\nLjungström apparat ab Linkpg, Sv:es\nrationaliser:fören. - Hobbies: musik,\nidrott.\nGift 55 m Barbro Söderberg f 32,\n\ndtr t prof Richard S o Stina Löfstedt.\n- Barn: Peter f 56, Lars f 58,\nKristina f 60.\n\n",
    "structured": {
        "1": {
            "full_name": "DINKELSPIEL, MAX",
            "location": "Sthlm",
            "occupation": "Direktör",
            "birth_details": {
                "date": "12/07/1898",
                "place": "Trieste",
                "parents": "Adolf Dinkelspiel, Emilie Nordlinger"
            },
            "education": [],
            "career": [
                {
                    "position": "Verkst dir bankirf",
                    "years": {
                        "start_year": 0,
                        "end_year": 0
                    },
                    "organization": "E Öhman j:r ab"
                }
            ],
            "family": {
                "spouse": "Brita Björnstjerna",
                "marriage_year": "1936",
                "children": [
                    {
                        "name": "Gunilla",
                        "birth_year": "1937"
                    },
                    {
                        "name": "Ulf",
                        "birth_year": "1939"
                    },
                    {
                        "name": "Claes",
                        "birth_year": "1941"
                    }
                ]
            }
        },
        "2": {
            "full_name": "DINTER, ZVONIMIR",
            "location": "Näsbypark",
            "occupation": "Docent",
            "birth_details": {
                "date": "24/10/1914",
                "place": "Osijek, Jugoslavien",
                "parents": null
            },
            "education": [
                {
                    "degree": "Stud:ex",
                    "year": "1933",
                    "institution": "Zagreb, Jugoslavien"
                },
                {
                    "degree": "Veterinär",
                    "year": "1938",
                    "institution": "Zagreb, Jugoslavien"
                }
            ],
            "career": [
                {
                    "position": "Ass Veterinärfak",
                    "years": {
                        "start_year": 1941,
                        "end_year": 0
                    },
                    "organization": "Zagreb, Jugoslavien"
                },
                {
                    "position": "Vetensk medarb",
                    "years": {
                        "start_year": 1942,
                        "end_year": 0
                    },
                    "organization": "Tyska inst"
                },
                {
                    "position": "Ass SVA",
                    "years": {
                        "start_year": 1949,
                        "end_year": 0
                    },
                    "organization": null
                },
                {
                    "position": "Laborator",
                    "years": {
                        "start_year": 1950,
                        "end_year": 0
                    },
                    "organization": null
                },
                {
                    "position": "Avdeln:-förest",
                    "years": {
                        "start_year": 1953,
                        "end_year": 0
                    },
                    "organization": null
                }
            ],
            "family": {
                "spouse": "Elsie Bucht",
                "marriage_year": "1955",
                "children": [
                    {
                        "name": "Peter",
                        "birth_year": "1947"
                    },
                    {
                        "name": "Anna",
                        "birth_year": "1956"
                    },
                    {
                        "name": "Lena",
                        "birth_year": "1958"
                    }
                ]
            }
        },
        "3": {
            "full_name": "DIRKE, S OLLE",
            "location": "Nacka",
            "occupation": "Direktör",
            "birth_details": {
                "date": "05/12/1924",
                "place": "Lindesberg, Örebro l",
                "parents": "Erik Johansson, Rut Johanson"
            },
            "education": [
                {
                    "degree": "Stud:ex",
                    "year": "1943",
                    "institution": "Kristinehamn"
                },
                {
                    "degree": null,
                    "year": "1948",
                    "institution": "KTH"
                }
            ],
            "career": [
                {
                    "position": "Anst STAL",
                    "years": {
                        "start_year": 0,
                        "end_year": 0
                    },
                    "organization": "Finspång"
                },
                {
                    "position": "Konsult ing",
                    "years": {
                        "start_year": 0,
                        "end_year": 0
                    },
                    "organization": "Mek prövn:anst Sthlm"
                },
                {
                    "position": "Övering o verkst:ch",
                    "years": {
                        "start_year": 1958,
                        "end_year": 0
                    },
                    "organization": "Turbin ab de Laval Ljungström"
                },
                {
                    "position": "Platsch i",
                    "years": {
                        "start_year": 0,
                        "end_year": 0
                    },
                    "organization": "Nacka"
                }
            ],
            "family": {
                "spouse": "Barbro Söderberg",
                "marriage_year": "1955",
                "children": [
                    {
                        "name": "Peter",
                        "birth_year": "1956"
                    },
                    {
                        "name": "Lars",
                        "birth_year": "1958"
                    },
                    {
                        "name": "Kristina",
                        "birth_year": "1960"
                    }
                ]
            },
            "hobbies": [
                "musik",
                "idrott"
            ]
        }
    }
}