{
    "original": "DYRENDAHL, SVEN E L,\nprofessor, Enebyberg, f i Öxnevalla, Älvsb\nl, 10/5/13 av godsäg Anders D o Signe\nEliasson.\n\nStudiex Lund 33, stud Lunds univ\n34-35, vet:ex 42, vet:med dr 49,\ndistr:-vet:tj 42, ass VHS 44, laborator 46,\nprof i avelsbiologi o husdjurshygien\nVHS sed 59. - Ordf IV:e distr stat\nhästpremier: ndr 49, sekr fören Nords v\nhästen 48, medl arméns vet:väs vetensk råd\n60, vet:styr vetensk råd 60, stynled stat\nforskn:anst f lantm:byggn 59, fonden f\nfrämj av forskn o försöksverksarnh på\njordbr:omr 60, stat:s led styr f\nhingst-uppf:anst Wången 61. - Skr i vet:med o\nhippolog ämnen. - Utm: RNO, Peter\nHernquistSM.\n\nGift 43 m Maj-Inger Jönsson f 16,\ndtr t köpman Otto J o Ebba Bredberg.\n- Barn: Britta f 44, Anders f 46,\nChristina f 52.\n\nDYRSSEN, DAVID W, docent,\nDjursholm, f i Tarrytown, New York,\n10/6/22 av övering Waldemar D o\nEugene Baker. - Adoptivföräldrar:\ngen:-löjtn Gustaf D o Maia Wennerholm.\n\nStud:ex Visby 41, fil mag Sthlm 49,\nfil lic 53, fil dr 56, doc i fysikalisk\nkemi StU 56-60, i oorganisk kemi KTH\n60. - Anst FOA 48, laborator där.\n-Red Naturvetaren 51-55. - Sekr 51 års\nlab:inventering, medl internat\nkemi-unionens komm f jämviktsdata, medl\nAU o sekt:ch 62 års internat kongr\ni koordinationskemi, sekr Sthlmskretsen\nav Sv kemistsamf 57-58, v ordf Sv:es\nnaturvetareförb 56-57. - Skr: ett 40-tal\nupps inom oorganisk kemi, fysikalisk\nkemi o kärnkemi, Investigations ön\nchelating agents for the extraction of\nlanthanide and actinide elements\n(drs-avh 56). - Hobby: golf.\nGift 46 m Margareta Ising f 25, dtr\nt prof Gustaf I o Aina Schoug.\n-Barn: Agneta f 47, Catharina f 49,\nHenrik f 51, Cecilia f 58.\n\n",
    "structured": {
        "0": {
            "full_name": "DYRENDAHL, SVEN E L",
            "location": "Enebyberg",
            "occupation": "Professor",
            "birth_details": {
                "date": "10/05/1913",
                "place": "Öxnevalla, Älvsborgs län",
                "parents": "Anders D and Signe Eliasson"
            },
            "education": [
                {
                    "degree": "Studiex",
                    "year": "1933",
                    "institution": "Lund"
                },
                {
                    "degree": "Vet:ex",
                    "year": "1942",
                    "institution": "Lunds universitet"
                },
                {
                    "degree": "Vet:med dr",
                    "year": "1949",
                    "institution": "Lunds universitet"
                }
            ],
            "career": [
                {
                    "position": "Distr:-vet:tj",
                    "years": {
                        "start_year": 1942,
                        "end_year": 1942
                    },
                    "organization": "Unknown"
                },
                {
                    "position": "Ass VHS",
                    "years": {
                        "start_year": 1944,
                        "end_year": null
                    },
                    "organization": "Unknown"
                },
                {
                    "position": "Laborator",
                    "years": {
                        "start_year": 1946,
                        "end_year": null
                    },
                    "organization": "Unknown"
                },
                {
                    "position": "Prof i avelsbiologi o husdjurshygien",
                    "years": {
                        "start_year": 1959,
                        "end_year": null
                    },
                    "organization": "VHS"
                }
            ],
            "family": {
                "spouse": "Maj-Inger Jönsson",
                "marriage_year": "1943",
                "children": [
                    {
                        "name": "Britta",
                        "birth_year": "1944"
                    },
                    {
                        "name": "Anders",
                        "birth_year": "1946"
                    },
                    {
                        "name": "Christina",
                        "birth_year": "1952"
                    }
                ]
            }
        },
        "1": {
            "full_name": "DYRSSEN, DAVID W",
            "location": "Djursholm",
            "occupation": "Docent",
            "birth_details": {
                "date": "10/06/1922",
                "place": "Tarrytown, New York",
                "parents": "Waldemar D and Eugene Baker"
            },
            "education": [
                {
                    "degree": "Stud:ex",
                    "year": "1941",
                    "institution": "Visby"
                },
                {
                    "degree": "Fil mag",
                    "year": "1949",
                    "institution": "Stockholm"
                },
                {
                    "degree": "Fil lic",
                    "year": "1953",
                    "institution": "Unknown"
                },
                {
                    "degree": "Fil dr",
                    "year": "1956",
                    "institution": "Unknown"
                }
            ],
            "career": [
                {
                    "position": "Doc i fysikalisk kemi",
                    "years": {
                        "start_year": 1956,
                        "end_year": 1960
                    },
                    "organization": "StU"
                },
                {
                    "position": "I oorganisk kemi",
                    "years": {
                        "start_year": 1960,
                        "end_year": null
                    },
                    "organization": "KTH"
                },
                {
                    "position": "Anst FOA",
                    "years": {
                        "start_year": 1948,
                        "end_year": null
                    },
                    "organization": "Unknown"
                },
                {
                    "position": "Laborator",
                    "years": {
                        "start_year": null,
                        "end_year": null
                    },
                    "organization": "FOA"
                },
                {
                    "position": "Red Naturvetaren",
                    "years": {
                        "start_year": 1951,
                        "end_year": 1955
                    },
                    "organization": "Unknown"
                }
            ],
            "family": {
                "spouse": "Margareta Ising",
                "marriage_year": "1946",
                "children": [
                    {
                        "name": "Agneta",
                        "birth_year": "1947"
                    },
                    {
                        "name": "Catharina",
                        "birth_year": "1949"
                    },
                    {
                        "name": "Henrik",
                        "birth_year": "1951"
                    },
                    {
                        "name": "Cecilia",
                        "birth_year": "1958"
                    }
                ]
            },
            "hobbies": [
                "Golf"
            ]
        }
    }
}