{
    "original": "DORMLING, JOHN E,\nträdgårdsarkitekt, Roslags Näsby, f i Krokstad,\nGbgs o Boh l, 17/11/25 av lantbr Erik\nOlsson o Alma Johansson.\nÖnnestads lantmannask 48,\nVästerhaninge folkhögsk 49, KLA:s\nträd-gårdssk Experimentalfältet 51,\nhorto-nomex 58. - Trädgårdsinstr Jönkpgs l\nhushållnrsällsk 51, medarb h\nträdgårds-arkit Jange Blomkvist Västerås 53, sv\nstatsstip f prakt trädgårdsstud Schweiz\n54 o Skottl 55, medarb h trädgårdsarkit:\nna S A Hermelin o I Wedborn Sthlm\n58, egen konsult\nträdgårdsarkit:verksamhet sed 60. - Medl Sv\nträdgårdsungdom, Jönkpg-Huskvarnafören (ordf\n52), Sthlms gartnersällsk (sekr 61), f ören\nSv trädg:arkit:er. - Hobbies:\nfotografering, fiske.\n\nGift 58 m hortonom Ingegerd Lundblad\nf 29, dtr t statsagronom Karl L o Frida\nLindberg. - Barn: Svante f 61.\n\nDORPH, W (BILL) K, tandläkare,\nmed kand, Sthlm, f i Niagara Falls,\nUSA, 4/8/28 av civiling Kurt D o\nMargot Sjöstam.\n\nTandläk:högsk Sthlm 54, stud Karol\ninst sed 61. - Eg praktik Eskilstuna\n54-61. - Hobby: idrott.\n\nd’OTRANTE, LOUIS D, greve,\nadvokat, Sthlm, f i Björnlunda, Södermani l,\n5/3/17 av överhovstallmäst, hertig\nCharles d’O o grev:an Madeleine Douglas.\nStud:ex Sigtuna 35, jur kand Sthlm 42,\ntjg ÖÄ 44, bitr jurist K Hultins\nadv:-byrå Sthlm 46, eg adv:verksamh sed\n58. - LSA 49. - Res:off:ex 38, löjtn kav\nres 40, ryttmäst sed 59. - Hobbies: jakt,\nfotografering.\n\nGift 44 m Birgitta Tham f 15, dtr t\nmajor Adolf T o Ebba Virgin. - Barn:\nMadeleine f 46, Marie f 48.\n\nDOUGLAS, G ARCHIBALD, greve,\nverkst direktör, Sthlm, f i Sthlm 3/10/10\nav gen:löjtn, greve Wilhelm D o Astri\nHenschen.\n\n10\n\nStudrex 28, Schartaus hdll 29, DHS\n36, tjg Sthlms ensk bk 36-43, dir ab\nIn vester 43-46, verkst dir Förvalta ab\nProvidentia 46-58 (styrrled), Sv:a\ndataregister ab sed 58. - Resroffrex 32,\nryttmäst kav res 44. - Kammarherre\n52. - V ordf fastigh ab Drott, styr:led\nab Na vigare, Acierex ab, Monroe\nCal&lt;-culating Machine Co Inc, Orange N J\nUSA, London Office Machines Ltd\nLondon. - Utm: RVO, KNedOHO, RDDO.\n- Hobbies: segling, skidsport.\nGift 45 m Margareta Lagerfelt f 24, dtr\nt gen:major frih Axel L o Stina von\nStockenström. - Barn: Louise f 46,\nArchibald f 49, Richard f 52.\n\nDOWÉN, SVEN-ARNE S, leg läkare,\nSthlm, f i Sthlm 13/9/24 av löjtn Karl\nD o Ingeborg Andersson.\nMed lic Sthlm 55, underläk med tbcavd\nS:t Görans sjh 52-53, l:e underläk\nröntgenavd Sabbatsb sjh 55-59, l:e\nunderläk röntgenavd Seraf:las sed 59.\n\nBRÄCKE, LARS E J, tandläkare,\nSthlm, f i Järeda, Kalmar l, 21/3/25 av\nmöbelhandl Ernst D o Hanna Janson.\nStudrex 45, tandläkrex 50, praktik Sthlm\nsed 53. - Hobby: golf.\nGift 54 m Brita Näsström, dtr t\nläns-skoleinsp Yngve N o Anna-Stina\nLin-dohf. - Barn: Johan f 55, Cecilia f 56,\nChristopher f 60.\n\n",
    "structured": {
        "1": {
            "full_name": "DORMLING, JOHN E",
            "location": "Roslags Näsby",
            "occupation": "trädgårdsarkitekt",
            "birth_details": {
                "date": "17/11/1925",
                "place": "Krokstad, Gbgs o Boh l",
                "parents": "lantbr Erik Olsson o Alma Johansson"
            },
            "education": [
                {
                    "degree": "lantmannask",
                    "year": "1948",
                    "institution": "Önnestads"
                },
                {
                    "degree": "folkhögsk",
                    "year": "1949",
                    "institution": "Västerhaninge"
                },
                {
                    "degree": "träd-gårdssk",
                    "year": "1951",
                    "institution": "KLA"
                },
                {
                    "degree": "hortonomex",
                    "year": "1958",
                    "institution": "experimentalfältet"
                }
            ],
            "career": [
                {
                    "position": "trädgårdsinstr",
                    "years": {
                        "start_year": 1951,
                        "end_year": null
                    },
                    "organization": "Jönkpgs l hushållnrsällsk"
                },
                {
                    "position": "medarb",
                    "years": {
                        "start_year": 1953,
                        "end_year": null
                    },
                    "organization": "Jange Blomkvist Västerås"
                }
            ],
            "family": {
                "spouse": "hortonom Ingegerd Lundblad",
                "marriage_year": "1958",
                "children": [
                    {
                        "name": "Svante",
                        "birth_year": "1961"
                    }
                ]
            }
        },
        "2": {
            "full_name": "DORPH, W (BILL) K",
            "location": "Sthlm",
            "occupation": "tandläkare",
            "birth_details": {
                "date": "04/08/1928",
                "place": "Niagara Falls, USA",
                "parents": "civiling Kurt D o Margot Sjöstam"
            },
            "education": [
                {
                    "degree": "Tandläk:högsk",
                    "year": "1954",
                    "institution": "Sthlm"
                },
                {
                    "degree": null,
                    "year": "1961",
                    "institution": "Karol inst"
                }
            ],
            "career": [
                {
                    "position": null,
                    "years": {
                        "start_year": 1954,
                        "end_year": 1961
                    },
                    "organization": "praktik Eskilstuna"
                }
            ],
            "family": {
                "spouse": null,
                "marriage_year": null,
                "children": []
            }
        },
        "3": {
            "full_name": "d’OTRANTE, LOUIS D",
            "location": "Sthlm",
            "occupation": "advokat",
            "birth_details": {
                "date": "05/03/1917",
                "place": "Björnlunda, Södermani l",
                "parents": "överhovstallmäst, hertig Charles d’O o grev:an Madeleine Douglas"
            },
            "education": [
                {
                    "degree": "Stud:ex",
                    "year": "1935",
                    "institution": "Sigtuna"
                },
                {
                    "degree": "jur kand",
                    "year": "1942",
                    "institution": "Sthlm"
                }
            ],
            "career": [
                {
                    "position": "tjg",
                    "years": {
                        "start_year": 1944,
                        "end_year": null
                    },
                    "organization": "ÖÄ"
                },
                {
                    "position": "bitr jurist",
                    "years": {
                        "start_year": 1946,
                        "end_year": null
                    },
                    "organization": "K Hultins adv:-byrå Sthlm"
                }
            ],
            "family": {
                "spouse": "Birgitta Tham",
                "marriage_year": "1944",
                "children": [
                    {
                        "name": "Madeleine",
                        "birth_year": "1946"
                    },
                    {
                        "name": "Marie",
                        "birth_year": "1948"
                    }
                ]
            }
        },
        "4": {
            "full_name": "DOUGLAS, G ARCHIBALD",
            "location": "Sthlm",
            "occupation": "verkst direktör",
            "birth_details": {
                "date": "03/10/1910",
                "place": "Sthlm",
                "parents": "gen:löjtn, greve Wilhelm D o Astri Henschen"
            },
            "education": [
                {
                    "degree": null,
                    "year": "1928",
                    "institution": "Studrex"
                },
                {
                    "degree": null,
                    "year": "1929",
                    "institution": "Schartaus hdll"
                },
                {
                    "degree": null,
                    "year": "1936",
                    "institution": "DHS"
                }
            ],
            "career": [
                {
                    "position": "tjg",
                    "years": {
                        "start_year": 1936,
                        "end_year": 1943
                    },
                    "organization": "Sthlms ensk bk"
                },
                {
                    "position": "dir",
                    "years": {
                        "start_year": 1943,
                        "end_year": 1946
                    },
                    "organization": "ab In vester"
                }
            ],
            "family": {
                "spouse": "Margareta Lagerfelt",
                "marriage_year": "1945",
                "children": [
                    {
                        "name": "Louise",
                        "birth_year": "1946"
                    },
                    {
                        "name": "Archibald",
                        "birth_year": "1949"
                    },
                    {
                        "name": "Richard",
                        "birth_year": "1952"
                    }
                ]
            }
        },
        "5": {
            "full_name": "DOWÉN, SVEN-ARNE S",
            "location": "Sthlm",
            "occupation": "leg läkare",
            "birth_details": {
                "date": "13/09/1924",
                "place": "Sthlm",
                "parents": "löjtn Karl D o Ingeborg Andersson"
            },
            "education": [
                {
                    "degree": "Med lic",
                    "year": "1955",
                    "institution": "Sthlm"
                }
            ],
            "career": [
                {
                    "position": "l:e underläk",
                    "years": {
                        "start_year": 1955,
                        "end_year": 1959
                    },
                    "organization": "röntgenavd Sabbatsb sjh"
                }
            ],
            "family": {
                "spouse": null,
                "marriage_year": null,
                "children": []
            }
        },
        "6": {
            "full_name": "BRÄCKE, LARS E J",
            "location": "Sthlm",
            "occupation": "tandläkare",
            "birth_details": {
                "date": "21/03/1925",
                "place": "Järeda, Kalmar l",
                "parents": "möbelhandl Ernst D o Hanna Janson"
            },
            "education": [
                {
                    "degree": null,
                    "year": "1945",
                    "institution": "Studrex"
                },
                {
                    "degree": null,
                    "year": "1950",
                    "institution": "tandläkrex"
                }
            ],
            "career": [
                {
                    "position": null,
                    "years": {
                        "start_year": 1953,
                        "end_year": null
                    },
                    "organization": "praktik Sthlm"
                }
            ],
            "family": {
                "spouse": "Brita Näsström",
                "marriage_year": "1954",
                "children": [
                    {
                        "name": "Johan",
                        "birth_year": "1955"
                    },
                    {
                        "name": "Cecilia",
                        "birth_year": "1956"
                    },
                    {
                        "name": "Christopher",
                        "birth_year": "1960"
                    }
                ]
            }
        }
    }
}