{
    "original": "DYRSSEN, GÖSTA P T,\nhovrättsassessor, Bandhagen, f i Sthlm 5/9/19 av\nkommendörkapten Thede D o frih: an\nElisabeth Leuhusen.\n\nStud:ex 38, jur kand 46, tin’gstjg\nOppunda o Villåttin’ge doms 46-48, fiskal\nSvea hovr 48, vattenrättssekr\nMellanbygdens o Norrbygdens vattend’omstolar\n50-55, adj led Svea hovr 55, assess sed\n57. - Sekr utredn ang vattendomstol’arnas\norg 56^60, sakk just:dep sed 58, expert\nmalmutredn f Norrb sed 60.\nGift 50 m farm kand Inger Särnvall\nf 25, dtr t lärov:adj Harald S o Iris\nPalmqvist. - Barn: Gustaf f 52, Göran\nf 56, Erik f 60.\n\nDYRSSEN, KARL G P V, leg\nläkare, Sollentuna, f i Karlskrona 31/8/\n19 av kommendörkapten Karl-Gustaf D\no Anna Thorén.\n\nStud:ex 41, med kand Sthlm 45, med\nlic 50, vik underläk Sollefteå garn:sjh\n50 o 51, underläk 51-54, l:e underläk\n54-58, l:e underläk neurol klin Södersjh\n59, psyk klin sed 61; vik underläk\nSeraf :las neurol klin 55-59. - Stud EEG\nOslo 51-52. - E baf.läk 50-58. - Hobby:\nfotografering.\n\nGift 51 m Anna-Brita Stenström f 19,\ndtr t sjökapten Gustav S o Signe\nÖsterberg. - Barn: Peder f 51, Claes f 54,\nAnn-Charlotte f 57.\n\nDYSTER-AAS, BO C, tandläkare,\nJo-hanneshov, f i Säf f le 21/10/21 av dir\nHans D-A o Ruth Bjerner.\nStud:ex Lundsbergs sk 41, tandläkiex\n47, praktik Sundsvall 48, Sthlm sed 50.\n-Tjg SRK:s sjukhus Korea 52, sv\nFN-bat Gaza 59, Kongo 61.\nGift 44 m Greta Nordlin’g f 15, dtr t\nkontraktsprost G N o h h. - Barn:\nHans-Christian f 46, An-n-Christin f 48,\nBo-Johan f 58.\n\nDÄUMICHEN, GUNTER M W F,\nbyrådirektör, Sthlm, f i Sthlm 7/11/18\nav gen:konsul Max D o Martha Springer.\nStud:ex 38, KTH 45, anst ftygförvaltn\n45, byrådir o ch robotbyråns\nutprovn:-sektion där sed 54.\n\nGift 53 m Maiken Neiglick, i h 2:a\nakt, dtr t köpman Gunnar Bergkind o\nElsa Dandanell. - Barn: Per-Gunnar\n(adoptivson) f 46, Henrik f 54.\n\nvon DÖBELN, D J WILHELM,\nlaborator, Sthlm, f i Upps 21/11/12 av fil\ndr Ernst v D o Sophie Carlsson-Heijl.\nStud:ex 30, med kand 33, med lic 39,\nmed dr Sthlm 57. - Aman univ Upps\n39-40, underläk med klin Seraf:las 42,\nass fysiol inst GCI 45-46, laborator i\nflygmedicin sed 48 (tf 46). - Marinläk\nlia gr mlk 45, flygläk l:a gr FV 49.\n\n-   Skr  i   fysiol   o   militärmed   -   Utm:\nRNO.\n\nGift 39 m Ulrika Mellgren f 15, dtr t\ndisp Gunnar M o Dagmar Spånberg.\n-Barn: Johan f 40, Wilhelm f 45.\n",
    "structured": {
        "1": {
            "full_name": "Gösta P T Dyrssen",
            "location": "Bandhagen",
            "occupation": "Hovrättsassessor",
            "birth_details": {
                "date": "05/09/1919",
                "place": "Stockholm"
            },
            "education": [
                {
                    "degree": "Stud:ex",
                    "year": "1938",
                    "institution": "Unknown"
                },
                {
                    "degree": "Juris kandidat",
                    "year": "1946",
                    "institution": "Unknown"
                }
            ],
            "career": [
                {
                    "position": "Tin’gstjg",
                    "years": {
                        "start_year": 1946,
                        "end_year": 1948
                    },
                    "organization": "Oppunda o Villåttin’ge doms"
                },
                {
                    "position": "Fiskal",
                    "years": {
                        "start_year": 1948,
                        "end_year": 1955
                    },
                    "organization": "Svea hovr"
                },
                {
                    "position": "Vattenrättssekr",
                    "years": {
                        "start_year": 1950,
                        "end_year": 1955
                    },
                    "organization": "Mellanbygdens o Norrbygdens vattend’omstolar"
                },
                {
                    "position": "Adj led",
                    "years": {
                        "start_year": 1955,
                        "end_year": 1957
                    },
                    "organization": "Svea hovr"
                },
                {
                    "position": "Assess",
                    "years": {
                        "start_year": 1957,
                        "end_year": null
                    },
                    "organization": "Unknown"
                }
            ],
            "family": {
                "spouse": "Inger Särnvall",
                "marriage_year": "1950",
                "children": [
                    {
                        "name": "Gustaf",
                        "birth_year": "1952"
                    },
                    {
                        "name": "Göran",
                        "birth_year": "1956"
                    },
                    {
                        "name": "Erik",
                        "birth_year": "1960"
                    }
                ]
            }
        },
        "2": {
            "full_name": "Karl G P V Dyrssen",
            "location": "Sollentuna",
            "occupation": "Leg läkare",
            "birth_details": {
                "date": "31/08/1919",
                "place": "Karlskrona"
            },
            "education": [
                {
                    "degree": "Stud:ex",
                    "year": "1941",
                    "institution": "Unknown"
                },
                {
                    "degree": "Med kand",
                    "year": "1945",
                    "institution": "Stockholm"
                },
                {
                    "degree": "Med lic",
                    "year": "1950",
                    "institution": "Unknown"
                }
            ],
            "career": [
                {
                    "position": "Vik underläk",
                    "years": {
                        "start_year": 1950,
                        "end_year": 1951
                    },
                    "organization": "Sollefteå garn:sjh"
                },
                {
                    "position": "Underläk",
                    "years": {
                        "start_year": 1951,
                        "end_year": 1954
                    },
                    "organization": "Unknown"
                },
                {
                    "position": "L:e underläk",
                    "years": {
                        "start_year": 1954,
                        "end_year": 1958
                    },
                    "organization": "Unknown"
                },
                {
                    "position": "L:e underläk neurol klin",
                    "years": {
                        "start_year": 1959,
                        "end_year": null
                    },
                    "organization": "Södersjh"
                },
                {
                    "position": "Psyk klin",
                    "years": {
                        "start_year": 1961,
                        "end_year": null
                    },
                    "organization": "Unknown"
                }
            ],
            "family": {
                "spouse": "Anna-Brita Stenström",
                "marriage_year": "1951",
                "children": [
                    {
                        "name": "Peder",
                        "birth_year": "1951"
                    },
                    {
                        "name": "Claes",
                        "birth_year": "1954"
                    },
                    {
                        "name": "Ann-Charlotte",
                        "birth_year": "1957"
                    }
                ]
            }
        },
        "3": {
            "full_name": "Bo C Dyster-Aas",
            "location": "Johanneshov",
            "occupation": "Tandläkare",
            "birth_details": {
                "date": "21/10/1921",
                "place": "Säffle"
            },
            "education": [
                {
                    "degree": "Stud:ex",
                    "year": "1941",
                    "institution": "Lundsbergs sk"
                },
                {
                    "degree": "Tandläkiex",
                    "year": "1947",
                    "institution": "Unknown"
                }
            ],
            "career": [
                {
                    "position": "Praktik",
                    "years": {
                        "start_year": 1948,
                        "end_year": null
                    },
                    "organization": "Sundsvall"
                },
                {
                    "position": "Unknown",
                    "years": {
                        "start_year": 1950,
                        "end_year": null
                    },
                    "organization": "Sthlm"
                },
                {
                    "position": "Tjg",
                    "years": {
                        "start_year": 1952,
                        "end_year": null
                    },
                    "organization": "SRK:s sjukhus Korea"
                },
                {
                    "position": "Sv FN-bat",
                    "years": {
                        "start_year": 1959,
                        "end_year": null
                    },
                    "organization": "Gaza"
                },
                {
                    "position": "Sv FN-bat",
                    "years": {
                        "start_year": 1961,
                        "end_year": null
                    },
                    "organization": "Kongo"
                }
            ],
            "family": {
                "spouse": "Greta Nordling",
                "marriage_year": "1944",
                "children": [
                    {
                        "name": "Hans-Christian",
                        "birth_year": "1946"
                    },
                    {
                        "name": "Ann-Christin",
                        "birth_year": "1948"
                    },
                    {
                        "name": "Bo-Johan",
                        "birth_year": "1958"
                    }
                ]
            }
        },
        "4": {
            "full_name": "Gunter M W F Däumichen",
            "location": "Sthlm",
            "occupation": "Byrådirektör",
            "birth_details": {
                "date": "07/11/1918",
                "place": "Stockholm"
            },
            "education": [
                {
                    "degree": "Stud:ex",
                    "year": "1938",
                    "institution": "Unknown"
                },
                {
                    "degree": "Unknown",
                    "year": "1945",
                    "institution": "KTH"
                }
            ],
            "career": [
                {
                    "position": "Anst ftygförvaltn",
                    "years": {
                        "start_year": 1945,
                        "end_year": null
                    },
                    "organization": "Unknown"
                },
                {
                    "position": "Byrådir o ch robotbyråns utprovn:-sektion",
                    "years": {
                        "start_year": 1954,
                        "end_year": null
                    },
                    "organization": "Unknown"
                }
            ],
            "family": {
                "spouse": "Maiken Neiglick",
                "marriage_year": "1953",
                "children": [
                    {
                        "name": "Per-Gunnar (adoptivson)",
                        "birth_year": "1946"
                    },
                    {
                        "name": "Henrik",
                        "birth_year": "1954"
                    }
                ]
            }
        },
        "5": {
            "full_name": "D J Wilhelm von Döbeln",
            "location": "Sthlm",
            "occupation": "Laborator",
            "birth_details": {
                "date": "21/11/1912",
                "place": "Uppsala"
            },
            "education": [
                {
                    "degree": "Stud:ex",
                    "year": "1930",
                    "institution": "Unknown"
                },
                {
                    "degree": "Med kand",
                    "year": "1933",
                    "institution": "Unknown"
                },
                {
                    "degree": "Med lic",
                    "year": "1939",
                    "institution": "Stockholm"
                },
                {
                    "degree": "Med dr",
                    "year": "1957",
                    "institution": "Stockholm"
                }
            ],
            "career": [
                {
                    "position": "Aman univ",
                    "years": {
                        "start_year": 1939,
                        "end_year": 1940
                    },
                    "organization": "Upps"
                },
                {
                    "position": "Underläk med klin",
                    "years": {
                        "start_year": 1942,
                        "end_year": 1945
                    },
                    "organization": "Seraf:las"
                },
                {
                    "position": "Ass fysiol inst",
                    "years": {
                        "start_year": 1945,
                        "end_year": 1946
                    },
                    "organization": "GCI"
                },
                {
                    "position": "Laborator i flygmedicin",
                    "years": {
                        "start_year": 1948,
                        "end_year": null
                    },
                    "organization": "Unknown"
                }
            ],
            "family": {
                "spouse": "Ulrika Mellgren",
                "marriage_year": "1939",
                "children": [
                    {
                        "name": "Johan",
                        "birth_year": "1940"
                    },
                    {
                        "name": "Wilhelm",
                        "birth_year": "1945"
                    }
                ]
            }
        }
    }
}