{
    "original": "DENSLOE, G HARRY G, advokat,\nBromma, f i Karlskrona 5/6/96 av dir\nCarl Svensson o Elin Larsson.\nStudiex 13, jur kand Lund 19, bitr\njurist Jönkpgs jurid byrå Sthlm 20, eg\nadv:verksamh sed 32. - Resioffiex 17,\nkapten I 11 42-52. - LSA 24. - Hobbies:\nidrott, bridge, hortikultur.\nGift 20 m Elly Lindahl f 95, dtr t bkdir\nIsak L o Elin Karlsson. - Barn: Ulla\nf 21.\n\nDERKERT, CARLO V, intendent,\nSthlm, f i Neapel, Ital, 13/7/15 av\nkonstnär Valle Rosenberg o konstnär i an Siri\nDerkert.\n\nStudiex  Sthlm,  fil  kand  45,  studieled\nNät mus 46, intend Moderna mus sed\n\n60.  - Skr: Theory and practice in van\n\nGogh’s Dutch painting (Konsthist\ntidskr 46), Det moderna måleriets\ngenombrott i Sverige (i serien Nord\nmålarkonst, publ i Radions konstatias 50).\nGift m Kerstin Hildinger f 24. - Barn:\nTora f 48, Johanna f 51, Jacob f 57,\nPål Sebastian f 59.\n\nDERKERT, SIRI K, konstnärinna,\nLidingö, f i Sthlm 30/8/88 av köpman\nEdvard D o Valborg Fogelin.\nKKH 12, 13, stud Frankr o Ital 13-16,\nSpan 20. - Styr:led KRO. - Utf:\nfigur-måln, interiörer, barnportr, miniatyrer,\nskulptur, stuckatur. - Utst Lund 19 o 46,\nSthlm 32, 44, 50 o 60, Gbg 44. - Repr\nNatrmus, Gbgs konstmus.\nGift m konstnären Bertil Lybeck f 87\nd 45.\n\nDESSLE,     INGVAR,     bryggingenjör,\nJohanneshov,   f   i   Sthlm    1/2/14   av\nbryggmäst  N  A  D   o   Signe   Boije.\nStud:ex   35,   res:off:ex   37,   Norrkpgs\nhdlsgymn   41,   bryggmästarex   42,   vik\nbryggmäst Kiruna, Jönkpg o Eksjö 43,\nSödertälje   bryggeri   ab   44,   ab   Sthlms\nbryggerier 45,  ord  bryggmäst  Nya  ab\nVisby   bryggeri   45,   ab   Sthlms\nbryggerier, Tekn byrån 46-47, l:e bryggmäst\nS:t Eriks bryggeri Sthlm 47, ab Sthlms\nbryggerier, Tekn byrån sed 51. - Kapt\nA  l  res 47. - Skr: art i Sv\nbryggeri-tidskr 49.\nGift m Ulla Elback.\n\n",
    "structured": {
        "1": {
            "full_name": "G Harry G Densloe",
            "location": "Bromma",
            "occupation": "Advokat",
            "birth_details": {
                "date": "5/6/1896",
                "place": "Karlskrona",
                "parents": "Dir Carl Svensson o Elin Larsson"
            },
            "education": [
                {
                    "degree": "Studiex",
                    "year": "1913",
                    "institution": "Lund"
                },
                {
                    "degree": "Jur kand",
                    "year": "1919",
                    "institution": "Lund"
                }
            ],
            "career": [
                {
                    "position": "Bitr jurist",
                    "years": {
                        "start_year": 1920,
                        "end_year": 1932
                    },
                    "organization": "Jönkpgs jurid byrå Sthlm"
                },
                {
                    "position": "Eg adv:verksamh",
                    "years": {
                        "start_year": 1932,
                        "end_year": null
                    },
                    "organization": null
                },
                {
                    "position": "Kapten",
                    "years": {
                        "start_year": 1942,
                        "end_year": 1952
                    },
                    "organization": "Resioffiex 17, I 11"
                }
            ],
            "family": {
                "spouse": "Elly Lindahl",
                "marriage_year": "1920",
                "children": [
                    {
                        "name": "Ulla",
                        "birth_year": "1921"
                    }
                ]
            },
            "hobbies": [
                "Idrott",
                "Bridge",
                "Hortikultur"
            ]
        },
        "2": {
            "full_name": "Carlo V Derkert",
            "location": "Sthlm",
            "occupation": "Intendent",
            "birth_details": {
                "date": "13/7/1915",
                "place": "Neapel, Ital",
                "parents": "Konstnär Valle Rosenberg o Konstnärinna Siri Derkert"
            },
            "education": [
                {
                    "degree": "Studiex",
                    "year": null,
                    "institution": "Sthlm"
                },
                {
                    "degree": "Fil kand",
                    "year": "1945",
                    "institution": "Sthlm"
                },
                {
                    "degree": "Studieled Nät mus",
                    "year": "1946",
                    "institution": null
                },
                {
                    "degree": "Intend Moderna mus",
                    "year": "1960",
                    "institution": null
                }
            ],
            "publications": [
                {
                    "title": "Theory and practice in van Gogh’s Dutch painting",
                    "year": "1946",
                    "type": "Konsthist tidskr"
                },
                {
                    "title": "Det moderna måleriets genombrott i Sverige",
                    "year": "1950",
                    "type": "Nord målarkonst, Radions konstatias"
                }
            ],
            "family": {
                "spouse": "Kerstin Hildinger",
                "marriage_year": null,
                "children": [
                    {
                        "name": "Tora",
                        "birth_year": "1948"
                    },
                    {
                        "name": "Johanna",
                        "birth_year": "1951"
                    },
                    {
                        "name": "Jacob",
                        "birth_year": "1957"
                    },
                    {
                        "name": "Pål Sebastian",
                        "birth_year": "1959"
                    }
                ]
            }
        },
        "3": {
            "full_name": "Siri K Derkert",
            "location": "Lidingö",
            "occupation": "Konstnärinna",
            "birth_details": {
                "date": "30/8/1888",
                "place": "Sthlm",
                "parents": "Köpman Edvard D o Valborg Fogelin"
            },
            "education": [
                {
                    "degree": "KKH",
                    "year": "1912",
                    "institution": null
                },
                {
                    "degree": "KKH",
                    "year": "1913",
                    "institution": null
                },
                {
                    "degree": "Stud Frankr o Ital",
                    "year": "1913-1916",
                    "institution": null
                },
                {
                    "degree": "Span",
                    "year": "1920",
                    "institution": null
                }
            ],
            "community_involvement": [
                {
                    "role": "Styr:led",
                    "organization": "KRO",
                    "years": "NULL"
                }
            ],
            "hobbies": [
                "figur-måln",
                "interiörer",
                "barnportr",
                "miniatyrer",
                "skulptur",
                "stuckatur"
            ],
            "family": {
                "spouse": "Bertil Lybeck",
                "marriage_year": "NULL",
                "children": null
            }
        },
        "4": {
            "full_name": "Ingvar Dessle",
            "location": "Johanneshov",
            "occupation": "Bryggingenjör",
            "birth_details": {
                "date": "1/2/1914",
                "place": "Sthlm",
                "parents": "Bryggmäst N A D o Signe Boije"
            },
            "education": [
                {
                    "degree": "Stud:ex",
                    "year": "1935",
                    "institution": null
                },
                {
                    "degree": "Res:off:ex",
                    "year": "1937",
                    "institution": null
                },
                {
                    "degree": "Norrkpgs hdlsgymn",
                    "year": "1941",
                    "institution": null
                },
                {
                    "degree": "Bryggmästarex",
                    "year": "1942",
                    "institution": null
                }
            ],
            "career": [
                {
                    "position": "Vik bryggmäst",
                    "years": {
                        "start_year": 1943,
                        "end_year": null
                    },
                    "organization": "Kiruna, Jönkpg o Eksjö"
                },
                {
                    "position": "L:e bryggmäst",
                    "years": {
                        "start_year": 1947,
                        "end_year": null
                    },
                    "organization": "S:t Eriks bryggeri Sthlm"
                }
            ],
            "family": {
                "spouse": "Ulla Elback",
                "marriage_year": "NULL",
                "children": null
            }
        }
    }
}