{
    "original": "TIDEBÄCK, GUNNAR A,\ndriftingenjör, Umeå, f i Sthlm 16/7/24 av Johan\nT o Märtha Hed.\n\nIng:ex HTL Sthlm 49, ing vattenf:styr\n49, Norrl:kraft ab 51, drifting dess tekn\navd Umeå sed 57. - Styr:led Fastigh ab\nDöbeln. - Medl Odd Fellow. - Hobbies:\nsång, musik.\n\nGift 47 m Marianne Söderberg f 24, dtr\nt Fritz S o Sara S. - Barn: Elisabeth\nf 53.\n\nTIETZE, HELLMUT H M,\nregionschef, Sundsvall, f i Stuttgart, Tyskl, 17/6/\n18 av H T o Kläre Giersberg.\nIng:ex STI 45, distr :ch Sv Siemens ab\nSthlm, reg :ch f Norrl firma Elof\nHansson Gbg, reg :ch Gylling telesystem ab\nSundsvall sed 61. - Medl W-sex. -\nHobbies: schack, fiske, foto, silversmide.\nGift 47 m Inger Kjellberg f 23, dtr t\nköpm Henry K o h h. - Barn: Elisabet\nf 48, Monica f 58.\n\nTIGERSTEDT, LARS R,\nprovinsialläkare, Ånäset, f i Giessen, Tyskl, 27/7/\n11 av prof Carl T o konstn:an Helny\nKalima.\n\nStud:ex Hfors 30, finsk läk:ex 44, Kungl\nMaj:ts tillst att i Sv:e utöva läkekonsten\n52; öl läk:förordn Finl 43-49, underläk\nKalix las 48-49, kir avd Uemå las 49-51,\nobstetr-gynekol avd Eskilstuna las 51-52,\nprov:läk Nysätra distr sed 54 (tf 53-54).\n- Läk fältsjh samt bat:läk o sekt:läk\n39-44; sanitetslöjtn 40, sanitetskapt 44.\n-Medl S:t Georgs gille. - Utm: FMM.\n-Hobbies: litteratur, fotografering, sport.\nGift 39 m Aino-Marie Thomé f 16, dtr t\nskeppsbyggn:ing Alfred T o Olga\nH0egh-Nissen. - Barn: Ulv f 43, Björn f 44, Lo\nf 48.\n\nTIMNER, GUNNAR, läroverksadjunkt,\n\nSkellefteå, f i Umeå 10/9/34 av prov:läk\nK G T o gymn :dir Gudrun Froste.\nStud:ex 52, fil mag Upps 57, eo adj\nSkellefteå stads försökssk 58, komm\ngymn Kramfors 60, provar hal Umeå\n62, adj i matem o fysik hal Skellefteå\nsed 63. - Styr :led Sv orienter:förb sed\n66. - Hobby: orientering.\n\nf            f Aftt GUSTAV J B, p*\n\nvinsialläkare, Vännäs, f i Bottnaryd,\nJönkpgs l, 25/6/01 av kyrkoh David T o\nAugusta Svensson.\n\nStud:ex Skövde 20, med kand Upps 24,\nmed lic Sthlm 28, öl läk:förordn 28-30,\nunderläk Skellefteå las 30-34, Stora\nEke-bergs sanat 35-36, med avd Vänersborgs\nlas 36-37, tf prov:läk Kågedalens distr\n37-38, prov:läk Övertorneå distr 38-44,\nVännäs distr sed 44. - Medl Rotary.\n-Skr: art i Sv läk:tidn, Sv jakt o\nÄlgjägarens bok. - Utm: RNO. - Hobbies:\njakt, ballistik.\n\nGift 33 m gymn :dir Gudrun Froste f 07,\ndtr t las :läk Carl C:son F o Eva\nRydman. - Barn: Gunnar f 34, Anders f 36,\nLars f 40, Göran f 43.\n\n",
    "structured": {
        "1": {
            "full_name": "TIDEBÄCK, GUNNAR A",
            "location": "Umeå",
            "occupation": "Driftingenjör",
            "birth_details": {
                "date": "16/07/1924",
                "place": "Stockholm"
            },
            "education": [
                {
                    "degree": "HTL Sthlm",
                    "year": "1949",
                    "institution": "Sthlm"
                }
            ],
            "career": [
                {
                    "position": "Drifting dess tekn",
                    "years": {
                        "start_year": 1957
                    },
                    "organization": "Norrl:kraft ab"
                }
            ],
            "family": {
                "spouse": "Marianne Söderberg",
                "marriage_year": "1947",
                "children": [
                    {
                        "name": "Elisabeth",
                        "birth_year": "1953"
                    }
                ]
            },
            "hobbies": [
                "sång",
                "musik"
            ]
        },
        "2": {
            "full_name": "TIETZE, HELLMUT H M",
            "location": "Sundsvall",
            "occupation": "Regionschef",
            "birth_details": {
                "date": "17/06/1918",
                "place": "Stuttgart, Tyskland"
            },
            "education": [
                {
                    "degree": "STI",
                    "year": "1945",
                    "institution": "Stuttgart"
                }
            ],
            "career": [
                {
                    "position": "Distr:ch Sv Siemens ab",
                    "years": {
                        "start_year": 1951
                    },
                    "organization": "Sv Siemens ab Sthlm"
                },
                {
                    "position": "Reg:ch Gylling telesystem ab",
                    "years": {
                        "start_year": 1961
                    },
                    "organization": "Gylling telesystem ab"
                }
            ],
            "family": {
                "spouse": "Inger Kjellberg",
                "marriage_year": "1947",
                "children": [
                    {
                        "name": "Elisabet",
                        "birth_year": "1948"
                    },
                    {
                        "name": "Monica",
                        "birth_year": "1958"
                    }
                ]
            },
            "hobbies": [
                "schack",
                "fiske",
                "foto",
                "silversmide"
            ]
        },
        "3": {
            "full_name": "TIGERSTEDT, LARS R",
            "location": "Ånäset",
            "occupation": "Provinsialläkare",
            "birth_details": {
                "date": "27/07/1911",
                "place": "Giessen, Tyskland"
            },
            "education": [
                {
                    "degree": "Stud:ex Hfors",
                    "year": "1930",
                    "institution": "Hfors"
                },
                {
                    "degree": "Finsk läk:ex",
                    "year": "1944",
                    "institution": "Finland"
                }
            ],
            "career": [
                {
                    "position": "Prov:läk Nysätra distr",
                    "years": {
                        "start_year": 1954
                    },
                    "organization": "Nysätra distr"
                }
            ],
            "family": {
                "spouse": "Aino-Marie Thomé",
                "marriage_year": "1939",
                "children": [
                    {
                        "name": "Ulv",
                        "birth_year": "1943"
                    },
                    {
                        "name": "Björn",
                        "birth_year": "1944"
                    },
                    {
                        "name": "Lo",
                        "birth_year": "1948"
                    }
                ]
            },
            "hobbies": [
                "litteratur",
                "fotografering",
                "sport"
            ]
        },
        "4": {
            "full_name": "TIMNER, GUNNAR",
            "location": "Skellefteå",
            "occupation": "Läroverksadjunkt",
            "birth_details": {
                "date": "10/09/1934",
                "place": "Umeå"
            },
            "education": [
                {
                    "degree": "Stud:ex",
                    "year": "1952",
                    "institution": "Umeå"
                },
                {
                    "degree": "Fil mag",
                    "year": "1957",
                    "institution": "Uppsala"
                }
            ],
            "career": [
                {
                    "position": "Adj i matem o fysik",
                    "years": {
                        "start_year": 1963
                    },
                    "organization": "Skellefteå"
                }
            ],
            "family": {
                "spouse": "Gudrun Froste",
                "marriage_year": "NULL",
                "children": "NULL"
            },
            "hobbies": [
                "orientering"
            ]
        }
    }
}