{
    "original": "THORSSELL, NILS-ERIK A, direktör,\nJohanneshov,  f  i  Sthlm  9/2/20  av dir\nErik T o Anna Hammar.\nPåhlman» hdlI 37, anst ab Kantens\nhatt-fabr 37, verkst dir där sed 55’. -\nHobbies: scouting, Skytte, fotografering.\nGift 57 m Anna-Britt Åström f 33.\n-Barn: Magn’us f 58, Mikael f 61.\n\nTHORSSON se THORSON\n\nTHORSTENSSON se TORSTENSSON\n\nTHOURÉN se  THORÉN\n\nTHOURSIE, RAGNAR D A,\nförfattare, Sthlm, f i Katrineholm 30/9/19\nav lokförare Algot T o Signe Hebel.\nStud:ex Hbg 39, fil kand 43, bitr 42-44\no ord aman 44-45 StHS institut f\npsykologi o pedagogik, aman RFA 45-48 o\n51-53, byråsekr där 53&gt;-55,\narb:markn:-styr 55-60, l:e byråinsp sed 60. - Litt\nrådgiv Ljus förlag 49, Tiden 50, red\nveckotidn Tidsbilden 51. - Skr:\nEmaljögat (45), Kulissbygget - Tyskland\nmellan Molotov och Marshall (tills m E\nKötting 48), Nya sidor och dagsljus\n(52), Mod att leva (57), red f Moderna\ndrakar - en debatt om dagspress :s\nproblem (49), medarb i Inför 60-talet -\ndebattbok om socialismens framtid (59).\nGift 44 m Britta Karlson f 19, dtr t\nrektor Nils K o Lilly Hellberg.\n\nTHRAN, J ULLRICH, Dr-ing,\nBromma, f i Königsberg 16/6/12.\nStud:ex 30, diploming Breslau, Dr-ing\n39. - Ol anst Tyskl 35-47, byrådir\nvat-tenf:styr 60, tekn ch ab Nordströms\nlinbanor sed 60. - Led ol komm IVA.\nGift 39 m Charlotte Neumann f 12.\n\nTHRAP-OLSEN, C EINAR, direktör,\nNeuilly-sur-Seine, f i Berlin 8/6/21 av\ning Lauritz T-O o Dagmar Gullstrand.\nStud:ex Lidingö 40, KTH 44, anst ab\n\nElectrolux Sthlm 44, Electrolux S A\nParis 57, verkst dir där sed 58.\nGift 48 m Vilemo Lindfeldt f 25, dtr t\nkomm :kapten Wilhelm L o Anna-Lisa\nRydqvist. - Barn: Maria f 52, Helena f\n54, Suzanne f 58.\n\n",
    "structured": {
        "1": {
            "full_name": "NILS-ERIK A THORSSELL",
            "location": "Johanneshov",
            "occupation": "direktör",
            "birth_details": {
                "date": "09/02/1920",
                "place": "Stockholm",
                "parents": "dir Erik T o Anna Hammar"
            },
            "education": [],
            "career": [
                {
                    "position": "anst ab Kantens hatt-fabr",
                    "years": {
                        "start_year": 1937,
                        "end_year": 1955
                    },
                    "organization": "Kantens hatt-fabr"
                }
            ],
            "family": {
                "spouse": "Anna-Britt Åström",
                "marriage_year": "1957",
                "children": [
                    {
                        "name": "Magn’us",
                        "birth_year": "1958"
                    },
                    {
                        "name": "Mikael",
                        "birth_year": "1961"
                    }
                ]
            },
            "hobbies": [
                "scouting",
                "Skytte",
                "fotografering"
            ]
        },
        "2": {
            "full_name": "RAGNAR D A THOURSIE",
            "location": "Stockholm",
            "occupation": "författare",
            "birth_details": {
                "date": "30/09/1919",
                "place": "Katrineholm",
                "parents": "lokförare Algot T o Signe Hebel"
            },
            "education": [
                {
                    "degree": "Stud:ex",
                    "year": "1939",
                    "institution": "Hbg"
                },
                {
                    "degree": "filosofie kandidat",
                    "year": "1943",
                    "institution": "StHS institut f psykologi o pedagogik"
                }
            ],
            "career": [
                {
                    "position": "bitr",
                    "years": {
                        "start_year": 1942,
                        "end_year": 1944
                    },
                    "organization": "StHS institut f psykologi o pedagogik"
                },
                {
                    "position": "ord aman",
                    "years": {
                        "start_year": 1944,
                        "end_year": 1945
                    },
                    "organization": "StHS institut f psykologi o pedagogik"
                },
                {
                    "position": "l:e byråinsp",
                    "years": {
                        "start_year": 1960,
                        "end_year": null
                    }
                }
            ],
            "family": {
                "spouse": "Britta Karlson",
                "marriage_year": "1944",
                "children": []
            },
            "publications": [
                {
                    "title": "Emaljögat",
                    "year": "1945",
                    "type": null
                },
                {
                    "title": "Kulissbygget - Tyskland mellan Molotov och Marshall",
                    "year": "1948",
                    "type": null
                },
                {
                    "title": "Nya sidor och dagsljus",
                    "year": "1952",
                    "type": null
                },
                {
                    "title": "Mod att leva",
                    "year": "1957",
                    "type": null
                },
                {
                    "title": "Moderna drakar - en debatt om dagspress :s problem",
                    "year": "1949",
                    "type": null
                }
            ]
        },
        "3": {
            "full_name": "J ULLRICH THRAN",
            "location": "Bromma",
            "occupation": "Dr-ing",
            "birth_details": {
                "date": "16/06/1912",
                "place": "Königsberg",
                "parents": null
            },
            "education": [
                {
                    "degree": "Stud:ex",
                    "year": "1930",
                    "institution": null
                },
                {
                    "degree": "diploming",
                    "year": "1939",
                    "institution": "Breslau"
                }
            ],
            "career": [
                {
                    "position": "Ol anst",
                    "years": {
                        "start_year": 1935,
                        "end_year": 1947
                    },
                    "organization": "Tyskl"
                },
                {
                    "position": "byrådir vat-tenf:styr",
                    "years": {
                        "start_year": 1960,
                        "end_year": null
                    }
                }
            ],
            "family": {
                "spouse": "Charlotte Neumann",
                "marriage_year": "1939",
                "children": []
            },
            "board_memberships": [],
            "hobbies": []
        },
        "4": {
            "full_name": "C EINAR THRAP-OLSEN",
            "location": "Neuilly-sur-Seine",
            "occupation": "direktör",
            "birth_details": {
                "date": "08/06/1921",
                "place": "Berlin",
                "parents": "ing Lauritz T-O o Dagmar Gullstrand"
            },
            "education": [
                {
                    "degree": "Stud:ex",
                    "year": "1940",
                    "institution": "Lidingö"
                },
                {
                    "degree": null,
                    "year": "1944",
                    "institution": "KTH"
                }
            ],
            "career": [
                {
                    "position": "anst ab Electrolux Sthlm",
                    "years": {
                        "start_year": 1944,
                        "end_year": 1957
                    },
                    "organization": "Electrolux Sthlm"
                },
                {
                    "position": "verkst dir",
                    "years": {
                        "start_year": 1958,
                        "end_year": null
                    },
                    "organization": "Electrolux S A Paris"
                }
            ],
            "family": {
                "spouse": "Vilemo Lindfeldt",
                "marriage_year": "1948",
                "children": [
                    {
                        "name": "Maria",
                        "birth_year": "1952"
                    },
                    {
                        "name": "Helena",
                        "birth_year": "1954"
                    },
                    {
                        "name": "Suzanne",
                        "birth_year": "1958"
                    }
                ]
            },
            "hobbies": []
        }
    }
}