{
    "original": "THULIN, GEORG Å L,\nstatspolisintendent, Bromma, f i Falun 4/4/02 av\nvaktkonstapel Ludvig T o Emelia\nPettersson.\n\nStud:ex 22, jur kand Upps 28, tingstjg\no polisutbildn 29-33, landsfogde\nVäster-norrl l 33, statspolisintend 37,\nbevakn:-insp 41-48. - Styr :led stat kriminaltekn\n\nanst 39, utl:komm 48, NTF 50, stat\ntrafiksäkerh:råd 52, stat polisskola 61,\nsakk:uppdr i pols- o därm sammanh\nfrågor. - Utm: KNOlkl, RVO, KDDO,\nKFinlVRO, KNS:tOO, FFrK3kl.\nGift 33 m Kerstin Jansson f 07, dtr t\ndistr :ch Johan J o Anna Hedén. - Barn:\nUlf f 39, Boel f 40, Jan f 44.\n\nTHULIN, GÖSTA G,\nhäradshövding, Lidingö, f i Sthlm 17/12/05 av\nreg :råd Gabriel T o Maria Janzon.\nStud:ex 23, jur kand 28, tingstjg\n29-31, tjg Svea hovr 32, tf fiskal 33, bitr\njust:dep 34, adj led 36, ass 39,\nvattenrättssekr Söderbygdens\nvatten-domst 39, tf rev:sekr 42, hovr :råd Svea\nhovr 45, rev :sekr 46, sekr\nfiskerätts-komm 43-47, sakk just:-, försv:- o\njordbr:dep 47-56, ånyo hovr :råd Svea\nhovr 50, v ordf vattenöverdomst\n52-57, ordf avd 58, häradsh Sthlms l v:a\ndoms sed 59. - Ordf Sv fiskevårdsförb\n48-54, Fiskefrämj 50-54, sekr Lidingö\nnatur- o kulturskyddskomm. - Utg: Fritt\nfiske o enskilt (50), Fiskelag o\nvattengräns (tills m C Romberg 55), art i\nNorstedts jurid handbok, Sv\nfiskelexikon 55 o i fackpress. - Utm: RNO.\n-Hobbies: naturvård, fiol, språk.\nGift 35 m Karin Söderwall f 09, dtr t\nreg :råd Knut S o Klara Lundquist.\n-Barn: Erik f 38, Ingela f 40, Solvig\nf 42, Gabriel f 44, Dag f 44, Mikael\nf 49, Göran f 50.\n\nTHULIN, INGRID L, skådespelerska,\nDanderyd, f i Sollefteå 27/1/29 av Adam\nT o Nana Larsson.\n\nDram teat elevsk 48-50, eng Dram teat\n50-52, Nya teat 52-53, Malmö stadsteat\n56-60, Sthlms stadsteat sed 60, medv i\nett flert filmer i Sv:e o utl samt i TV.\nGift 1) 52-55 m regissör Claes\nSyl-wander, 2) 56 m dir Harry Schein.\n\n",
    "structured": {
        "0": {
            "full_name": "GEORG Å L THULIN",
            "location": "Bromma",
            "occupation": "statspolisintendent",
            "birth_details": {
                "date": "04/04/1902",
                "place": "Falun",
                "parents": "vaktkonstapel Ludvig T o Emelia Pettersson"
            },
            "education": [
                {
                    "degree": "Stud:ex",
                    "year": "1922",
                    "institution": "NULL"
                },
                {
                    "degree": "jur kand",
                    "year": "1928",
                    "institution": "Upps"
                }
            ],
            "career": [
                {
                    "position": "landsfogde",
                    "years": {
                        "start_year": 1933,
                        "end_year": 1937
                    },
                    "organization": "Väster-norrl"
                },
                {
                    "position": "statspolisintend",
                    "years": {
                        "start_year": 1937,
                        "end_year": 1948
                    },
                    "organization": "NULL"
                },
                {
                    "position": "bevakn:-insp",
                    "years": {
                        "start_year": 1941,
                        "end_year": 1948
                    },
                    "organization": "NULL"
                }
            ],
            "family": {
                "spouse": "Kerstin Jansson",
                "marriage_year": "1933",
                "children": [
                    {
                        "name": "Ulf",
                        "birth_year": "1939"
                    },
                    {
                        "name": "Boel",
                        "birth_year": "1940"
                    },
                    {
                        "name": "Jan",
                        "birth_year": "1944"
                    }
                ]
            }
        },
        "1": {
            "full_name": "GÖSTA G THULIN",
            "location": "Lidingö",
            "occupation": "häradshövding",
            "birth_details": {
                "date": "17/12/1905",
                "place": "Sthlm",
                "parents": "reg :råd Gabriel T o Maria Janzon"
            },
            "education": [
                {
                    "degree": "Stud:ex",
                    "year": "1923",
                    "institution": "NULL"
                },
                {
                    "degree": "jur kand",
                    "year": "1928",
                    "institution": "NULL"
                }
            ],
            "career": [
                {
                    "position": "tingstjg",
                    "years": {
                        "start_year": 1929,
                        "end_year": 1931
                    },
                    "organization": "NULL"
                },
                {
                    "position": "hovr :råd",
                    "years": {
                        "start_year": 1945,
                        "end_year": 1959
                    },
                    "organization": "Svea hovr"
                }
            ],
            "family": {
                "spouse": "Karin Söderwall",
                "marriage_year": "1935",
                "children": [
                    {
                        "name": "Erik",
                        "birth_year": "1938"
                    },
                    {
                        "name": "Ingela",
                        "birth_year": "1940"
                    },
                    {
                        "name": "Solvig",
                        "birth_year": "1942"
                    },
                    {
                        "name": "Gabriel",
                        "birth_year": "1944"
                    },
                    {
                        "name": "Dag",
                        "birth_year": "1944"
                    },
                    {
                        "name": "Mikael",
                        "birth_year": "1949"
                    },
                    {
                        "name": "Göran",
                        "birth_year": "1950"
                    }
                ]
            },
            "publications": [
                {
                    "title": "Fritt fiske o enskilt",
                    "year": "1950",
                    "type": "NULL"
                },
                {
                    "title": "Fiskelag o vattengräns",
                    "year": "NULL",
                    "type": "NULL"
                },
                {
                    "title": "art i Norstedts jurid handbok",
                    "year": "NULL",
                    "type": "NULL"
                }
            ],
            "hobbies": [
                "naturvård",
                "fiol",
                "språk"
            ]
        },
        "2": {
            "full_name": "INGRID L THULIN",
            "location": "Danderyd",
            "occupation": "skådespelerska",
            "birth_details": {
                "date": "27/01/1929",
                "place": "Sollefteå",
                "parents": "Adam T o Nana Larsson"
            },
            "education": [
                {
                    "degree": "NULL",
                    "year": "NULL",
                    "institution": "Dram teat elevsk 48-50"
                }
            ],
            "career": [
                {
                    "position": "medv i ett flert filmer i Sv:e o utl samt i TV",
                    "years": {
                        "start_year": 1950,
                        "end_year": 1960
                    },
                    "organization": "Malmö stadsteat"
                }
            ],
            "family": {
                "spouse": "Harry Schein",
                "marriage_year": "1956",
                "children": []
            }
        }
    }
}