{
    "original": "THORN, LARS E W, fabrikör,\nBromma, f i Eskilstuna 26/9/04 av\nverkstads-arb Emil T o Emilie T.\nFinmekaniker, seglare, vann\nguldpokalen Sandhamn 59, guld i segling OS\nMelbourne 56 m m.\n\nGift 32 m Anna Lidell f 10, dtr t Filip\nL o Elin Göransson.\n\nTHORN, LENNART F,\ncivilingenjör, Bromma, f i Sande bei Hamburg\n2311122 av civiling Folke T o Emmy\nOhl.\n\nStud:ex Reinbek bei Hamburg 41,\nTechn Hochsch Darmstadt 44, KTH\n46. - Anst SAAB Linkpg 48,\nSandvikens Jernverks ab 54, Ulvsunda\nverkstäder ab 57, verkstadschef ab Atlas\nCopco, Sicklaverken 60, övering sed 61.\n- LSvTF, medl SVIF.\nGift 53 m Astrid Torfgård f 29, dtr\nt l’antbr Olof Pettersson o Helena\nKarlsson. - Barn: Anders f 58.\n\nTHORN, NILS J, apotekare,\nBromma, f i Hjo 20/1/09 av polisman Oskar\nT o Ida Sjöberg.\n\nApot :ex 37, spec:stud KTH 46-48, farm\nlic 52. - Aman Farm inst 35-37, e lär\n\n0 laborator där 39-48, priv apot Lokatten\nSthlm 48, inrättade apot Arian Gröndal\n51, priv apot Vita Björnen Sthlm sed\n54.   -   Förordn   s   instruktionsapot   sed\n50,   ordf  ndn  f  Apot:soc  lab :avd   54,\nstyr:led Apot kontr:lab 49-53, led\nApot:soc direkt 53, Sv farmakopékomm 53.\n-Utg: skr m farm-kem innehåll, medarb\n\n1 läroböcker. - Utm: RVO.\n\nGift 37 m Margit Elf f 12, dtr t ing\nErik E o Alma Nilsson. - Barn: Anders\nf 39, Kersti f 44, Ingegerd f 46, Eva f 49.\n\nTHÖRNBERG, ERIK R, kanslichef,\nSthlm, f i Ronneby 14/6/07 av\ntrycksvarvare Wiktor T o Ida Johansson.\nStud Brunnsviks folkhögsk l:a o 2:a\nårskurs, LO :s sk, studieomb :man 36 o\nförb:sekr 38 i sv metallind:arb:förb, ch\narbetarskyddsndns kansli sed 45,\nStadsfullm Ronneby, styr :led Blekinge l\narb:-förmedl 34-36, led arb :rådet 41, expert\ndär 46, led LO :s repr :skåp 41-46, sekr\nmetallind:arb:s arb :lösh :kassa 41-46,\ntillsynsmyndigh repr i kassan sed 53,\nordf Jordbr skyddspropag sed 48, v ordf\nSRK :s överstyr sed 58.\nGift 33 m Iris Svensson f 05, dtr t\nhemm:äg Sven Abrahamsson o Ingrid\nAndersson. - Barn: Lennart.\n\n",
    "structured": {
        "1": {
            "full_name": "Thorn, Lars E W",
            "location": "Bromma",
            "occupation": "Fabrikör",
            "birth_details": {
                "date": "26/09/1904",
                "place": "Eskilstuna",
                "parents": "Verkstads-arb Emil T o Emilie T"
            },
            "education": null,
            "career": [
                {
                    "position": "Finmekaniker",
                    "years": {
                        "start_year": 1959,
                        "end_year": 1959
                    },
                    "organization": "Guldpokalen Sandhamn"
                },
                {
                    "position": "Seglare",
                    "years": {
                        "start_year": 1956,
                        "end_year": 1956
                    },
                    "organization": "OS Melbourne"
                }
            ],
            "family": {
                "spouse": "Anna Lidell",
                "marriage_year": "1932",
                "children": null
            }
        },
        "2": {
            "full_name": "Thorn, Lennart F",
            "location": "Bromma",
            "occupation": "Civilingenjör",
            "birth_details": {
                "date": "23/11/1922",
                "place": "Sande bei Hamburg",
                "parents": "Civilingenj Folke T o Emmy Ohl"
            },
            "education": [
                {
                    "degree": "Stud:ex",
                    "year": "1941",
                    "institution": "Reinbek bei Hamburg"
                },
                {
                    "degree": null,
                    "year": "1944",
                    "institution": "Techn Hochsch Darmstadt"
                },
                {
                    "degree": null,
                    "year": "1946",
                    "institution": "KTH"
                }
            ],
            "career": [
                {
                    "position": "Anst SAAB",
                    "years": {
                        "start_year": 1948,
                        "end_year": 1948
                    },
                    "organization": "Linköping"
                },
                {
                    "position": "Sandvikens Jernverks ab",
                    "years": {
                        "start_year": 1954,
                        "end_year": 1954
                    },
                    "organization": null
                },
                {
                    "position": "Ulvsunda verkstäder ab",
                    "years": {
                        "start_year": 1957,
                        "end_year": 1957
                    },
                    "organization": null
                },
                {
                    "position": "Verkstadschef ab Atlas Copco, Sicklaverken",
                    "years": {
                        "start_year": 1960,
                        "end_year": 1960
                    },
                    "organization": null
                },
                {
                    "position": "Övering",
                    "years": {
                        "start_year": 1961,
                        "end_year": 1961
                    },
                    "organization": null
                }
            ],
            "family": {
                "spouse": "Astrid Torfgård",
                "marriage_year": "1953",
                "children": [
                    {
                        "name": "Anders",
                        "birth_year": "1958"
                    }
                ]
            }
        },
        "3": {
            "full_name": "Thorn, Nils J",
            "location": "Bromma",
            "occupation": "Apotekare",
            "birth_details": {
                "date": "20/01/1909",
                "place": "Hjo",
                "parents": "Polisman Oskar T o Ida Sjöberg"
            },
            "education": [
                {
                    "degree": "Apot:ex",
                    "year": "1937",
                    "institution": null
                },
                {
                    "degree": "Spec:stud",
                    "year": "1946-1948",
                    "institution": "KTH"
                },
                {
                    "degree": "Farm lic",
                    "year": "1952",
                    "institution": null
                }
            ],
            "career": [
                {
                    "position": "Aman Farm inst",
                    "years": {
                        "start_year": 1935,
                        "end_year": 1937
                    },
                    "organization": null
                },
                {
                    "position": "E lär laborator",
                    "years": {
                        "start_year": 1939,
                        "end_year": 1948
                    },
                    "organization": "Farm inst"
                },
                {
                    "position": "Priv apot",
                    "years": {
                        "start_year": 1948,
                        "end_year": 1948
                    },
                    "organization": "Lokatten Sthlm"
                },
                {
                    "position": "Inrättade apot",
                    "years": {
                        "start_year": 1951,
                        "end_year": 1951
                    },
                    "organization": "Arian Gröndal"
                },
                {
                    "position": "Priv apot",
                    "years": {
                        "start_year": 1954,
                        "end_year": 1954
                    },
                    "organization": "Vita Björnen Sthlm"
                }
            ],
            "family": {
                "spouse": "Margit Elf",
                "marriage_year": "1937",
                "children": [
                    {
                        "name": "Anders",
                        "birth_year": "1939"
                    },
                    {
                        "name": "Kersti",
                        "birth_year": "1944"
                    },
                    {
                        "name": "Ingegerd",
                        "birth_year": "1946"
                    },
                    {
                        "name": "Eva",
                        "birth_year": "1949"
                    }
                ]
            }
        },
        "4": {
            "full_name": "Thörnberg, Erik R",
            "location": "Sthlm",
            "occupation": "Kanslichef",
            "birth_details": {
                "date": "14/06/1907",
                "place": "Ronneby",
                "parents": "Trycksvarvare Wiktor T o Ida Johansson"
            },
            "education": [
                {
                    "degree": null,
                    "year": null,
                    "institution": "Brunnsviks folkhögsk l:a o 2:a årskurs, LO :s sk"
                }
            ],
            "career": [
                {
                    "position": "Stadsfullm",
                    "years": {
                        "start_year": 1941,
                        "end_year": 1946
                    },
                    "organization": "Ronneby"
                },
                {
                    "position": "Styr :led",
                    "years": {
                        "start_year": 1958,
                        "end_year": 1958
                    },
                    "organization": "SRK :s överstyr"
                }
            ],
            "family": {
                "spouse": "Iris Svensson",
                "marriage_year": "1933",
                "children": [
                    {
                        "name": "Lennart",
                        "birth_year": null
                    }
                ]
            }
        }
    }
}