{
    "original": "TÖRNQVIST, KARL-ERIK, leg läkare,\nEnskede, f i Sthlm 4/7/20 av ing Helmer\nT o Elsa Mattson.\n\nStud:ex 40, med kand 45, med lic 50,\nvik underläk Säters sjh 47, S:ta\nGertruds sjh 47, Beckomberga sjh 48, Rätts-\n\npsykiatr klin 49, med avd Södersjh 50,\nvik l:e underläk psykiatr klin Karol sjh\n50-51, l:e underläk 51-54, 2:e läk\nRätts-psykiatr klin sed1 54. - Expert\nSäker-hetsanst:utredn 53, expert åt reg\ndelegat v European consult group ön the\nprevention of crime and the treatment\nof offenders Geneve 58, suppl\nInterne-ringsndn sed 59.\n\nGift 2) 60 m fil kand, socionom\nGreta-Lisa Magnusson f 27, dtr t hemmansäg\nMagnus M o Klara Andersson. - Barn:\ni l:a akt Uno f 51.\n\nTÖRNSTEN, ERIK H C, leg läkare,\n\nSollentuna, f i Karlstad 29/1/25 av\nriks-banksrev Einar T o Anna Möller.\nStud:ex Sthlm 43, med kand 47, med\nlic 51, aman Karol inst anat inst 46, vik\nprov :läk   Haparanda   o   Ramnäs   distr\n\n51,  underläk Torsby las 52, l:e underläk\nröntgendiagn avd Södersjh 53, underläk\nröntgendiagn avd Karol sjh 58, l:e\nunderläk radioterapiavd Södersjh sed 60.\nGift 54 m Anne-Marie Roos f 28, dtr t\ndir Knut R o h h. - Barn: Lärs-Erik\nf 55, Charlotte f 58.\n\nTÖRNSÄTER, CURT B,\nförsäljningschef, Stuvsta, f i Sthlm 4/3/18 av Karl\nAndersson o Elisabet Hedström.\nIFU:s diplomkurs f skadeförsäkr :insp\n45. - Anst Mercur 33, ins’p Iris 44,\ndistr :ch Hermes-Securrtas 45, Iris 52,\norg:ch 53, Skåne-konc 59-61, försäljn:ch\nFramtiden sed 62. - Ordf Mercurs\npers:kl 40-44, sekr Försäkr :tjm :f or b\nSmål:fcrets 50-52, led dess fälStutsk 50-\n\n52,  styr :led Förb f religionsfrihet, medl\nSiJ 49, SF 53.\n\nGift 43 m Brith Ek f 20, dtr t Otto\nE o Selma Persson. - Barn: Staffan\nf 44, Göran f 47, Angela f 50, Marie f\n55.\n\n",
    "structured": {
        "0": {
            "full_name": "KARL-ERIK TÖRNQVIST",
            "location": "Enskede",
            "occupation": "leg läkare",
            "birth_details": {
                "date": "04/07/1920",
                "place": "Stockholm",
                "parents": "Helmer Törnqvist, Elsa Mattson"
            },
            "education": [
                {
                    "degree": "stud:ex",
                    "year": "1940",
                    "institution": "NULL"
                },
                {
                    "degree": "med kand",
                    "year": "1945",
                    "institution": "NULL"
                },
                {
                    "degree": "med lic",
                    "year": "1950",
                    "institution": "NULL"
                }
            ],
            "career": [
                {
                    "position": "vik underläk",
                    "years": {
                        "start_year": 1947,
                        "end_year": 1947
                    },
                    "organization": "Säters sjh"
                },
                {
                    "position": "vik underläk",
                    "years": {
                        "start_year": 1947,
                        "end_year": 1947
                    },
                    "organization": "S:ta Gertruds sjh"
                },
                {
                    "position": "vik underläk",
                    "years": {
                        "start_year": 1948,
                        "end_year": 1948
                    },
                    "organization": "Beckomberga sjh"
                },
                {
                    "position": "vik l:e underläk",
                    "years": {
                        "start_year": 1950,
                        "end_year": 1951
                    },
                    "organization": "med avd Södersjh"
                },
                {
                    "position": "l:e underläk",
                    "years": {
                        "start_year": 1951,
                        "end_year": 1954
                    },
                    "organization": "Karol sjh"
                },
                {
                    "position": "2:e läk",
                    "years": {
                        "start_year": 1954,
                        "end_year": "NULL"
                    },
                    "organization": "Rätts-psykiatr klin"
                }
            ],
            "family": {
                "spouse": "Greta-Lisa Magnusson",
                "marriage_year": "1960",
                "children": [
                    {
                        "name": "Uno",
                        "birth_year": "1951"
                    }
                ]
            }
        },
        "1": {
            "full_name": "ERIK H C TÖRNSTEN",
            "location": "Sollentuna",
            "occupation": "leg läkare",
            "birth_details": {
                "date": "29/01/1925",
                "place": "Karlstad",
                "parents": "Einar Törnsten, Anna Möller"
            },
            "education": [
                {
                    "degree": "stud:ex",
                    "year": "1943",
                    "institution": "Sthlm"
                },
                {
                    "degree": "med kand",
                    "year": "1947",
                    "institution": "NULL"
                },
                {
                    "degree": "med lic",
                    "year": "1951",
                    "institution": "NULL"
                }
            ],
            "career": [
                {
                    "position": "vik prov :läk",
                    "years": {
                        "start_year": 1951,
                        "end_year": "NULL"
                    },
                    "organization": "Haparanda"
                },
                {
                    "position": "vik prov :läk",
                    "years": {
                        "start_year": 1951,
                        "end_year": "NULL"
                    },
                    "organization": "Ramnäs distr"
                },
                {
                    "position": "underläk",
                    "years": {
                        "start_year": 1952,
                        "end_year": "NULL"
                    },
                    "organization": "Torsby las"
                },
                {
                    "position": "l:e underläk",
                    "years": {
                        "start_year": 1953,
                        "end_year": "NULL"
                    },
                    "organization": "röntgendiagn avd Södersjh"
                },
                {
                    "position": "underläk",
                    "years": {
                        "start_year": 1958,
                        "end_year": "NULL"
                    },
                    "organization": "röntgendiagn avd Karol sjh"
                },
                {
                    "position": "l:e underläk",
                    "years": {
                        "start_year": 1960,
                        "end_year": "NULL"
                    },
                    "organization": "radioterapiavd Södersjh"
                }
            ],
            "family": {
                "spouse": "Anne-Marie Roos",
                "marriage_year": "1954",
                "children": [
                    {
                        "name": "Lärs-Erik",
                        "birth_year": "1955"
                    },
                    {
                        "name": "Charlotte",
                        "birth_year": "1958"
                    }
                ]
            }
        },
        "2": {
            "full_name": "CURT B TÖRNSÄTER",
            "location": "Stuvsta",
            "occupation": "försäljningschef",
            "birth_details": {
                "date": "04/03/1918",
                "place": "Stockholm",
                "parents": "Karl Andersson, Elisabet Hedström"
            },
            "education": [],
            "career": [
                {
                    "position": "org:ch",
                    "years": {
                        "start_year": 1962,
                        "end_year": "NULL"
                    },
                    "organization": "Framtiden"
                }
            ],
            "family": {
                "spouse": "Brith Ek",
                "marriage_year": "1943",
                "children": [
                    {
                        "name": "Staffan",
                        "birth_year": "1944"
                    },
                    {
                        "name": "Göran",
                        "birth_year": "1947"
                    },
                    {
                        "name": "Angela",
                        "birth_year": "1950"
                    },
                    {
                        "name": "Marie",
                        "birth_year": "1955"
                    }
                ]
            }
        }
    }
}