{
    "original": "Rydin, Anders Folke, tandläkare,\nSthlm, f. 17/2/01 i Burseryd, Jönköp. 1.\nStud:ex. i Jönköp. 20, med. kand:ex. i\nUpps. 24, tandl :ex. 26. Prakt, i Kumla\n26-31, prakt, i Sthlm sed. 31.\nRydin, Gari Håkan, med. dr, docent,\nÄppelviken, f. 30/8/02 i Seglora förs.,\nÄlvsborgs 1. G. 35 m. fil. kand. Asta\nRentzhog. Barn: Elisabeth f. 36,\nBertil f. 39, Bengt f. 42. Stud:ex. i Borås\n21, med. kand. 25, med. lic. 33, med. dr\n35, allt i Upps. Docent i farmakologi\nv. univ. i Upps. 35-38, däreft. v. Karol.\ninst. i Sthlm o. förest, f. Statens Farm.\nLab. fr. 41. Studieresor t. Bern,\nBerlin, U. S. A. samt s. Rockefellerstip. t.\nEngl. 34 o. 35-36. Skr.: Ett 60-tal skr.\ninom fanmakologiens o. fysiologiens\narb :omr. Hobbies: Skidsport o.\nsegling. RLettTSO.\nRydin, Hans Folke Axel,\ncivilingenjör, Sthlm, f. 5/10/95 i Lidköping av\nborgmäst. Axel R. o. Lisa Roos af\nHjelmsäter. KTH 17, driftsing. v.\nLjungaverken 18-39, övering. 41-42 o.\nverkst, dir. fr. 42 v. Sthlms Superfos-\nfat Fabr. A-B. Byggde fabriker i\nRyssland 27-30 o. Stockviksverken 39-40.\nRyding-Cederlund, Anna-Lisa,,\nskådespelerska, Sthlm, f. i Gtbg. G. m.\nskådespel. Gösta Cederlund. Stud. v.\nRu-debeokska skolan i Gtbg, Ebingers\nteaterskola i Berlin. Studieresor t.\nTyskland, Engl., Frankrike o. Italien. Eng.\nv. Allan Rydings teater, Stadsteat. i\nHiborg, Vasateatern i Sthlm.\nSångturnéer o. teaterturn.\nRydman, Sven Vilhelm Gabriel,\növerstelöjtnant, generalsekreterare, Sthlm,\nf. 27/5/85 i Barkarö, Västmanl. 1. G.\n12 m. Karin Holmin. Barn:\nSven-Georg f. 13, civ:ing. Stud:ex. 05,\noff:-ex. 07, intend :ex. 12. Undilöjtn. v.\nVästmanl. reg. 07, löjtn, där 10, intend.\nv. Intend :kåren 12, major 28, öv:löjtn.\n35. Regiintend. v. A. 7 12-17, bef. f.\nstud:avd. 17-18, adj. h. genrintend.\n19-25, reg:intend. v. I. l 26-27, v.\nArmé-förvaltn :s intend :dep. 27-34,\nfästn:in-tend. i Boden 34-36. V. gen :sekr. i Sv.\nRöda Korset 36-43, gen :sekr. sed. 43.\nInneh. div. offentliga uppdr. rör. milit.\norganisationer. Res. t. Holl. 24, Tyskl.,\nUng. o. Belg. 37, Frankr, o. Engl. 38.\n",
    "structured": {
        "0": {
            "full_name": "Rydin, Anders Folke",
            "location": "Sthlm",
            "occupation": "tandläkare",
            "birth_details": {
                "date": "17/02/1901",
                "place": "Burseryd, Jönköp."
            },
            "education": [
                {
                    "degree": "Stud:ex.",
                    "year": "1920",
                    "institution": "i Jönköp."
                },
                {
                    "degree": "med. kand:ex.",
                    "year": "1924",
                    "institution": "i Upps."
                },
                {
                    "degree": "tandl :ex.",
                    "year": "1926",
                    "institution": "NULL"
                }
            ],
            "career": [
                {
                    "position": "Prakt, i Kumla",
                    "years": {
                        "start_year": 1926,
                        "end_year": 1931
                    },
                    "organization": "NULL"
                },
                {
                    "position": "prakt, i Sthlm",
                    "years": {
                        "start_year": 1931,
                        "end_year": "NULL"
                    },
                    "organization": "NULL"
                }
            ],
            "family": {
                "spouse": "NULL",
                "marriage_year": "NULL",
                "children": []
            }
        },
        "1": {
            "full_name": "Rydin, Gari Håkan",
            "location": "Äppelviken",
            "occupation": "med. dr, docent",
            "birth_details": {
                "date": "30/08/1902",
                "place": "Seglora förs., Älvsborgs 1."
            },
            "education": [
                {
                    "degree": "Stud:ex.",
                    "year": "1921",
                    "institution": "i Borås"
                },
                {
                    "degree": "med. kand.",
                    "year": "1925",
                    "institution": "i Upps."
                },
                {
                    "degree": "med. lic.",
                    "year": "1933",
                    "institution": "NULL"
                },
                {
                    "degree": "med. dr",
                    "year": "1935",
                    "institution": "NULL"
                }
            ],
            "career": [
                {
                    "position": "Docent i farmakologi",
                    "years": {
                        "start_year": 1935,
                        "end_year": 1938
                    },
                    "organization": "v. univ. i Upps."
                },
                {
                    "position": "förest, f. Statens Farm. Lab.",
                    "years": {
                        "start_year": 1941,
                        "end_year": "NULL"
                    },
                    "organization": "NULL"
                }
            ],
            "family": {
                "spouse": "fil. kand. Asta Rentzhog",
                "marriage_year": "1935",
                "children": [
                    {
                        "name": "Elisabeth",
                        "birth_year": "1936"
                    },
                    {
                        "name": "Bertil",
                        "birth_year": "1939"
                    },
                    {
                        "name": "Bengt",
                        "birth_year": "1942"
                    }
                ]
            }
        },
        "2": {
            "full_name": "Rydin, Hans Folke Axel",
            "location": "Sthlm",
            "occupation": "civilingenjör",
            "birth_details": {
                "date": "05/10/1895",
                "place": "Lidköping"
            },
            "education": [],
            "career": [
                {
                    "position": "drifting. v. Ljungaverken",
                    "years": {
                        "start_year": 1918,
                        "end_year": 1939
                    },
                    "organization": "NULL"
                },
                {
                    "position": "övering.",
                    "years": {
                        "start_year": 1941,
                        "end_year": 1942
                    },
                    "organization": "NULL"
                },
                {
                    "position": "verkst, dir. fr. 42 v. Sthlms Superfos- phat Fabr. A-B",
                    "years": {
                        "start_year": "NULL",
                        "end_year": "NULL"
                    },
                    "organization": "NULL"
                }
            ],
            "family": {
                "spouse": "NULL",
                "marriage_year": "NULL",
                "children": []
            }
        },
        "3": {
            "full_name": "Ryding-Cederlund, Anna-Lisa",
            "location": "Sthlm",
            "occupation": "skådespelerska",
            "birth_details": {
                "date": "NULL",
                "place": "Gtbg."
            },
            "education": [
                {
                    "degree": "NULL",
                    "year": "NULL",
                    "institution": "Rudebeokska skolan i Gtbg"
                },
                {
                    "degree": "NULL",
                    "year": "NULL",
                    "institution": "Ebingers teaterskola i Berlin"
                }
            ],
            "career": [
                {
                    "position": "Eng. v. Allan Rydings teater",
                    "years": {
                        "start_year": "NULL",
                        "end_year": "NULL"
                    },
                    "organization": "NULL"
                },
                {
                    "position": "NULL",
                    "years": {
                        "start_year": "NULL",
                        "end_year": "NULL"
                    },
                    "organization": "Stadsteat. i Hiborg, Vasateatern i Sthlm"
                }
            ],
            "family": {
                "spouse": "skådespel. Gösta Cederlund",
                "marriage_year": "NULL",
                "children": []
            }
        },
        "4": {
            "full_name": "Rydman, Sven Vilhelm Gabriel",
            "location": "Sthlm",
            "occupation": "överstelöjtnant, generalsekreterare",
            "birth_details": {
                "date": "27/05/1885",
                "place": "Barkarö, Västmanl. 1."
            },
            "education": [
                {
                    "degree": "Stud:ex.",
                    "year": "1905",
                    "institution": "NULL"
                },
                {
                    "degree": "off:-ex.",
                    "year": "1907",
                    "institution": "NULL"
                },
                {
                    "degree": "intend :ex.",
                    "year": "1912",
                    "institution": "NULL"
                }
            ],
            "career": [
                {
                    "position": "Undilöjtn. v. Västmanl. reg.",
                    "years": {
                        "start_year": 1907,
                        "end_year": 1910
                    },
                    "organization": "NULL"
                },
                {
                    "position": "löjtn. där",
                    "years": {
                        "start_year": 1910,
                        "end_year": "NULL"
                    },
                    "organization": "NULL"
                },
                {
                    "position": "intend. v. Intend :kåren",
                    "years": {
                        "start_year": 1912,
                        "end_year": "NULL"
                    },
                    "organization": "NULL"
                },
                {
                    "position": "fästn:in-tend. i Boden",
                    "years": {
                        "start_year": 1934,
                        "end_year": 1936
                    },
                    "organization": "NULL"
                },
                {
                    "position": "gen :sekr. i Sv. Röda Korset",
                    "years": {
                        "start_year": 1943,
                        "end_year": "NULL"
                    },
                    "organization": "NULL"
                }
            ],
            "family": {
                "spouse": "Karin Holmin",
                "marriage_year": "1912",
                "children": [
                    {
                        "name": "Sven-Georg",
                        "birth_year": "1913"
                    }
                ]
            }
        }
    }
}