{
    "original": "Rune, Isak Filip, sekreterare, Ängby,\nf. 19/7/02 i Sthlm av l :e tillsyningsm.\nFritiof R. o. Elin Magnusson. G. 32 m.\nSonja Maria Elisabeth Stocklassa.\nBarn: Erik Ingvar f. 33, Isak Hilding\nf. 34, Sigbritt f. 41. Stud:ex. v. H.\nla-tinlärov. å Norrmalm i Sthlm 21, jur.\nkand. 28. Tingstjg. 28-30, tjg. i\nförsäkr :råd. 30-36, därvid ss. föredrag, fr.\n31, sekr. i arb :råd. 36. Skr.: Div. art.\ni facktidskr.\nRuneberg, Bengt, ingenjör, Sthlm, f.\n15/3/93 i Visby av traf :ch. Alfred R. o.\nJosefina Petersson. G. 22 m. Margareta\nHeggblad. Avg:ex. v. CTL Fänr. i\nGotl. inf:reg. res. 16, underlöjtn. 19,\nlöjtn. 21, kapten 32, kulspr:kurs 15-16,\nKaptK 31. Anst. v. Ljungströms\nÅngturbin 18-30, 33-43, S. J. i Argentina\n25-28, Ruthsaccumulator 31-32, v. Mek.\nPrövn :anst. (T. Nordensson) fr. 44.\nMedl. av Chalmeristfören.,\nRes:off:-förb. o. Gotl. Gille,\nRunemark, Per Simon, t. f.\ngeneraldirektör, Sthlm, f. 19/2/83 i Fornåsa,\nÖstergötl. 1. G. 44 rn. Margareta\nGrön-quist. Anst. i Soc :styr. 11,\nRiksför-säkr ranst. 16, aktuarie i Järnv :styr. 17,\nl :e aktuarie i Fin :dep. 20, byråchef i\nRiksräkensk :v. 29, t. f. gen :dir. i\nRiks-räkensk:v. 40. Led. av budgetsakk. 36,\nav 39 års finansfullmaktssakk., av 40\nårs finansstatistiksakk., av Sv.\nTobaksmonopolets styr. 34, v. ordf. 41.\nHobby : Saml. av modern konst.\nRunfelt, Erik Gunnar Wallentin,\nmajor, Lidingö, f. 22/9/93 i Gtbg. G. 22\nm. Valborg Håkanson. Barn: Anders\nErik f. 23, Gunilla Eriksdotter f. 28.\nStudrex. i Gtbg 12, stud. i Lund 13,\noff:ex. 17, fänr. v. Älvsborgs reg. 17,\nlöjtn. 19, kapt. 32, kapt. v. Gen:staben\n35, v. Hallands reg. 38, major 39, ch. f.\nArméns brevsk. 42. RSO, RFinlVROlkl.\nRunius, Sten, civilingenjör,\nbrandingenjör, Sthlm, f. 6/7/02 i Norrköp, av\nfil. dr J. A. R. o. Sigrid Rundström.\nG. 28 m. Marguerite Bonnevier. Barn &lt;\nBarbro f. 31, Göran f. 34. Studiex. 20,\nciviling. 25. Assist, v. KTH, bitr.\ndrifts-ing. v. Wifstavarfs A-B, driftsing. o.\ndisp :assist. h. Sv. Sockerfabriks A-B,\nbranding. i Städ. Allm. Brandstodsbol:\nsed. 33. Suppl, i Brandförsvarskomm.,\nstyr :suppl. i Brandförsäkringsbolagens\nTekn. Civilriskcentral.\nRunius,, Torsten, överstelöjtnant,\nSthlm, f. 12/12/95 i Norrköping. G. m.\nBirgit Margareta Asschier. Barn: Aina,\nBengt o. Ulf. Stud:ex. 14, offrex. 16\n(Kgl. Sjökrigssk.). Studieresor t. Engl.\no. Polen. Fänrik v. Kgl. Kustart. 16,\nlöjtn. v. flygvapnet 26, kapt. 27, major\n38, överstelöjtn. 42. RSO, RDDO,\n",
    "structured": {
        "1": {
            "full_name": "Rune, Isak Filip",
            "location": "Ängby",
            "occupation": "sekreterare",
            "birth_details": {
                "date": "19/07/1902",
                "place": "Sthlm",
                "parents": "Fritiof R. o. Elin Magnusson"
            },
            "education": [
                {
                    "degree": "Stud:ex.",
                    "year": "1921",
                    "institution": "Norrmalm i Sthlm"
                },
                {
                    "degree": "jur. kand.",
                    "year": "1928",
                    "institution": "NULL"
                }
            ],
            "career": [
                {
                    "position": "Tingstjg.",
                    "years": {
                        "start_year": 1928,
                        "end_year": 1930
                    },
                    "organization": "NULL"
                },
                {
                    "position": "tjg. i försäkr :råd.",
                    "years": {
                        "start_year": 1930,
                        "end_year": 1936
                    },
                    "organization": "NULL"
                },
                {
                    "position": "sekr. i arb :råd.",
                    "years": {
                        "start_year": 1936,
                        "end_year": 1941
                    },
                    "organization": "NULL"
                }
            ],
            "family": {
                "spouse": "Sonja Maria Elisabeth Stocklassa",
                "marriage_year": "1932",
                "children": [
                    {
                        "name": "Erik Ingvar",
                        "birth_year": "1933"
                    },
                    {
                        "name": "Isak Hilding",
                        "birth_year": "1934"
                    },
                    {
                        "name": "Sigbritt",
                        "birth_year": "1941"
                    }
                ]
            }
        },
        "2": {
            "full_name": "Runeberg, Bengt",
            "location": "Sthlm",
            "occupation": "ingenjör",
            "birth_details": {
                "date": "15/03/1893",
                "place": "Visby",
                "parents": "traf :ch. Alfred R. o. Josefina Petersson"
            },
            "education": [
                {
                    "degree": "Avg:ex.",
                    "year": "NULL",
                    "institution": "CTL"
                }
            ],
            "career": [
                {
                    "position": "Fänr. i Gotl. inf:reg. res.",
                    "years": {
                        "start_year": 1916,
                        "end_year": 1919
                    },
                    "organization": "NULL"
                },
                {
                    "position": "löjtn.",
                    "years": {
                        "start_year": 1921,
                        "end_year": 1921
                    },
                    "organization": "NULL"
                },
                {
                    "position": "kapten",
                    "years": {
                        "start_year": 1932,
                        "end_year": 1932
                    },
                    "organization": "NULL"
                }
            ],
            "family": {
                "spouse": "Margareta Heggblad",
                "marriage_year": "1922",
                "children": []
            }
        },
        "3": {
            "full_name": "Runemark, Per Simon",
            "location": "Sthlm",
            "occupation": "t. f. generaldirektör",
            "birth_details": {
                "date": "19/02/1883",
                "place": "Fornåsa, Östergötl. l",
                "parents": "NULL"
            },
            "education": [],
            "career": [
                {
                    "position": "anst. i Soc :styr.",
                    "years": {
                        "start_year": 1911,
                        "end_year": 1916
                    },
                    "organization": "NULL"
                },
                {
                    "position": "l :e aktuarie i Fin :dep.",
                    "years": {
                        "start_year": 1920,
                        "end_year": 1929
                    },
                    "organization": "NULL"
                },
                {
                    "position": "t. f. gen :dir. i Riksräkensk :v.",
                    "years": {
                        "start_year": 1940,
                        "end_year": 1945
                    },
                    "organization": "NULL"
                }
            ],
            "family": {
                "spouse": "Margareta Grön- quist",
                "marriage_year": "1944",
                "children": []
            }
        },
        "4": {
            "full_name": "Runfelt, Erik Gunnar Wallentin",
            "location": "Lidingö",
            "occupation": "major",
            "birth_details": {
                "date": "22/09/1893",
                "place": "Gtbg",
                "parents": "NULL"
            },
            "education": [
                {
                    "degree": "Studrex.",
                    "year": "1912",
                    "institution": "Gtbg"
                },
                {
                    "degree": "stud.",
                    "year": "1913",
                    "institution": "Lund"
                },
                {
                    "degree": "off:ex.",
                    "year": "1917",
                    "institution": "NULL"
                }
            ],
            "career": [
                {
                    "position": "fänr. v. Älvsborgs reg.",
                    "years": {
                        "start_year": 1917,
                        "end_year": 1919
                    },
                    "organization": "NULL"
                },
                {
                    "position": "löjtn. v. flygvapnet",
                    "years": {
                        "start_year": 1926,
                        "end_year": 1935
                    },
                    "organization": "NULL"
                },
                {
                    "position": "major",
                    "years": {
                        "start_year": 1939,
                        "end_year": 1945
                    },
                    "organization": "NULL"
                }
            ],
            "family": {
                "spouse": "Valborg Håkanson",
                "marriage_year": "1922",
                "children": [
                    {
                        "name": "Anders Erik",
                        "birth_year": "1923"
                    },
                    {
                        "name": "Gunilla Eriksdotter",
                        "birth_year": "1928"
                    }
                ]
            }
        },
        "5": {
            "full_name": "Runius, Sten",
            "location": "Sthlm",
            "occupation": "civilingenjör, brandingenjör",
            "birth_details": {
                "date": "06/07/1902",
                "place": "Norrköp",
                "parents": "fil. dr J. A. R. o. Sigrid Rundström"
            },
            "education": [
                {
                    "degree": "Studiex.",
                    "year": "1920",
                    "institution": "NULL"
                },
                {
                    "degree": "civiling.",
                    "year": "1925",
                    "institution": "NULL"
                }
            ],
            "career": [
                {
                    "position": "Assist, v. KTH",
                    "years": {
                        "start_year": 1925,
                        "end_year": 1928
                    },
                    "organization": "NULL"
                },
                {
                    "position": "branding. i Städ. Allm. Brandstodsbol",
                    "years": {
                        "start_year": 1933,
                        "end_year": 1940
                    },
                    "organization": "NULL"
                }
            ],
            "family": {
                "spouse": "Marguerite Bonnevier",
                "marriage_year": "1928",
                "children": [
                    {
                        "name": "Barbro",
                        "birth_year": "1931"
                    },
                    {
                        "name": "Göran",
                        "birth_year": "1934"
                    }
                ]
            }
        },
        "6": {
            "full_name": "Runius, Torsten",
            "location": "Sthlm",
            "occupation": "överstelöjtnant",
            "birth_details": {
                "date": "12/12/1895",
                "place": "Norrköping",
                "parents": "NULL"
            },
            "education": [
                {
                    "degree": "Stud:ex.",
                    "year": "1914",
                    "institution": "NULL"
                },
                {
                    "degree": "offrex.",
                    "year": "1916",
                    "institution": "Kgl. Sjökrigssk."
                }
            ],
            "career": [
                {
                    "position": "t. Engl. o. Polen",
                    "years": {
                        "start_year": 1927,
                        "end_year": 1930
                    },
                    "organization": "NULL"
                },
                {
                    "position": "löjtn. v. flygvapnet",
                    "years": {
                        "start_year": 1926,
                        "end_year": 1935
                    },
                    "organization": "NULL"
                }
            ],
            "family": {
                "spouse": "Birgit Margareta Asschier",
                "marriage_year": "1921",
                "children": [
                    {
                        "name": "Aina",
                        "birth_year": "NULL"
                    },
                    {
                        "name": "Bengt",
                        "birth_year": "NULL"
                    },
                    {
                        "name": "Ulf",
                        "birth_year": "NULL"
                    }
                ]
            }
        }
    }
}