{
    "original": "Richert, Ebba Cecilia, författarinna,\nSthlm, f. i Sthlm av revisorn Johan R.\no. Amanda Ohlson. G. 34 m. t j imaii.\nKarl Hugogård. Språk- o. studieresor\nt. Tyskl. o. Frankr. Journalistiskt\nverksam 29-34. Skr.: romanerna Le j de träsk\n(37), Brödernas kvinna (41, film 42),\nGod afton fröken Madeleine (42), En\nanständig kvinna (43).....som\ndrömmar vävas av (44).\nRichert, Johan Gabriel, sekreterare,\nSthlm, f. 6/10/85 i Gtbg. G. 27 m.\nBlenda Gajander. Fil. lic. Sekr. h.\nKgl. Socistyr., medarb, i ett flert. tidn.\no. tidskr., utgivit bl. a. Barrabas (25).\nRichert, Josef Gustaf (Gösta),\ncivilingenjör, direktör, Sthlm, f. 22/12/88 i\nGtbg av prof. G. R. o. Ellen af\nBill-bergh. G. 15 m. Bertha Salin. Barn:\nKarin f, 16, fil. måg., g. m. civiling.\nSvante Gawell; Gunnar f. 17, ing.;\nGunilla f. 22, barnträdgårdslärar:a; Sven\nf. 24. Studiex. i Sthlm 07, avg :ex. v.\nKTH 13. Undilöjtn. v. Svea trängkår\n10, löjtn. 14, avsk. 22. Ing. h. The\nCedars Rapids Mfg and Power Co.,\nCanada, 13-14, v. A-B Vattenbyggn :byrån,\nSthlm, 15-18, kontr. v.\ngrundvatten-verksanläggn. o. vattenkraftanläggn.\n15-18, arb :ch. f. flodregi, o. hamnarb. i\nKina 19-21, undersökn. på Java o. resor\ni Asien, Afrika o. Europa 21, åter i\nA-B Vattenbyggn :byrån, Sthlm, tidv. i\nLondon, fr. 21, verkst, dir. fr. 40. Res.\ni Polen, Rumänien, Grekl. 29. Styr :led.\ni Sv. Tekn :fören. 32-37, i Sv. Konsult.\nIng. Fören. fr. 28, v. ordf. fr. 43, i\nWhitlockska samsk. fr. 42, v. ordf. i\nstyr. f, Forskn :inst. f. cement o. betong\nv. KTH fr. 42. Skr.: upps. i bl. a. Sv.\nvattenkraftfören. publ. o. Tekn. tidskr,\nrör. kraftförsörjning samt i ing :etiska\nfråg., Ing. ss. sakk. i rättstvister (i\nhyllri :skr. t, S. Lübeck). RVO.\nRichnau, Claes Gunnar Wilhelm,\nprakt, läkare, med. lic., Sthlm, f. 24/77\n74 i Sthlm av civiling. Claes Hjalmar\nR. o. Ida Carolina R. G. m. tandl.\nIrene Fröberg. Stud:ex. i Sthlm 93,\nmed. kand. i Sthlm 01, med. lic. där 11,\nguvernör f. H. K. H., Hertigen av\nVäst-mani. 02-05 o. 07, t. f. aman. v. gynekol.\nklin. å Seraf:las. 06, t. f. aman. v.\nof-talmiatr. avd. å Sabbatsberg våren 10,\nund:läk. v. las. i Växjö 11, aman. v.\notiatr. poliklin. å Seraf:las. 12-13,\naman. v. otolog. avd. å Sabbatsberg\n13-14. Prakt. läk. i Sthlm. Uppsatser\ni med. facktidskr., tonsättare, publ. ett\nflert. sånger o. musikstycken. Hobby:\nMusik. GV:sJmt, RVO.\n",
    "structured": {
        "1": {
            "full_name": "Richert, Ebba Cecilia",
            "location": "Sthlm",
            "occupation": "författarinna",
            "birth_details": {
                "date": "NULL",
                "place": "Sthlm",
                "parents": "revisorn Johan R. o. Amanda Ohlson"
            },
            "education": [],
            "career": [
                {
                    "position": "journalistiskt verksam",
                    "years": {
                        "start_year": 1929,
                        "end_year": 1934
                    },
                    "organization": "NULL"
                }
            ],
            "family": {
                "spouse": "Karl Hugogård",
                "marriage_year": "1934",
                "children": []
            }
        },
        "2": {
            "full_name": "Richert, Johan Gabriel",
            "location": "Sthlm",
            "occupation": "sekreterare",
            "birth_details": {
                "date": "6/10/1885",
                "place": "Gtbg",
                "parents": "NULL"
            },
            "education": [],
            "career": [],
            "family": {
                "spouse": "Blenda Gajander",
                "marriage_year": "1927",
                "children": []
            }
        },
        "3": {
            "full_name": "Richert, Josef Gustaf (Gösta)",
            "location": "Sthlm",
            "occupation": "civilingenjör, direktör",
            "birth_details": {
                "date": "22/12/1888",
                "place": "Gtbg",
                "parents": "prof. G. R. o. Ellen af Bill-bergh"
            },
            "education": [
                {
                    "degree": "Studiex.",
                    "year": "1907",
                    "institution": "Sthlm"
                }
            ],
            "career": [
                {
                    "position": "Undilöjtn. v. Svea trängkår",
                    "years": {
                        "start_year": 1910,
                        "end_year": 1914
                    },
                    "organization": "NULL"
                },
                {
                    "position": "löjtn.",
                    "years": {
                        "start_year": 1914,
                        "end_year": 1922
                    },
                    "organization": "NULL"
                }
            ],
            "family": {
                "spouse": "Bertha Salin",
                "marriage_year": "1915",
                "children": [
                    {
                        "name": "Karin",
                        "birth_year": "1916"
                    },
                    {
                        "name": "Gunnar",
                        "birth_year": "1917"
                    },
                    {
                        "name": "Gunilla",
                        "birth_year": "1922"
                    },
                    {
                        "name": "Sven",
                        "birth_year": "1924"
                    }
                ]
            }
        },
        "4": {
            "full_name": "Richnau, Claes Gunnar Wilhelm",
            "location": "Sthlm",
            "occupation": "prakt, läkare, med. lic.",
            "birth_details": {
                "date": "24/07/1874",
                "place": "Sthlm",
                "parents": "civiling. Claes Hjalmar R. o. Ida Carolina R."
            },
            "education": [
                {
                    "degree": "Stud:ex.",
                    "year": "1893",
                    "institution": "Sthlm"
                },
                {
                    "degree": "med. kand.",
                    "year": "1901",
                    "institution": "Sthlm"
                },
                {
                    "degree": "med. lic.",
                    "year": "1911",
                    "institution": "Sthlm"
                }
            ],
            "career": [
                {
                    "position": "Prakt. läk. i Sthlm",
                    "years": {
                        "start_year": 1911,
                        "end_year": "NULL"
                    },
                    "organization": "NULL"
                }
            ],
            "family": {
                "spouse": "tandl. Irene Fröberg",
                "marriage_year": "NULL",
                "children": []
            },
            "publications": [],
            "community_involvement": [],
            "board_memberships": [],
            "honorary_titles": [],
            "hobbies": [
                "Musik"
            ]
        }
    }
}