{
    "original": "TURESSON, A GUNNAR, tonsättare,\nsångare, Hammarö, f i Arvika 6/10/06\nav orgelbygg P E T o Karin Pettersson.\n\nMusikstud f bl a prof Zetterqvist,\nkonsertturnéer i Skand o Amer,\ngrammofon-insjungn, komp över 500 sånger t text\nav bl a Prins Wilhelm, Gullberg, Ferlin,\nGabriel Jönsson, ett urv övers t eng, utg\nbl a 14 visor t dikter av Dan Andersson\n(32), Lutans ballader (36), De tolv\nsträngarna (45), Visor i moll o dur (52),\nÄldsta dikten o musiken (61), Säter livets\nlock- o arbetssånger (63) m fi. - Styr :led\nEkelöf &amp; Svenson ab, riksantikv omb\nHammarö, medl STIM, LGAA, Sv\nLin-né-sällsk, Internat Folk Music Council,\nVärml Sällsk. - Utm: Värml sällskM.\nGift 49 m tandläk Birgit Hellsing, i h\n2:a akt, f Ol, dtr t dir Wilhelm Welin o\nEmmy Gillblad.\n\nTUVESON, TORSTEN, förste rektor,\n\nOxelösund, f i Knislinge, Kristianst l,\n20/12/17 av över lär Teodor T o Hilda\nMöller.\n\nStud:ex Kristianstad 36, folkskollär :ex\nLinkpg 40, folkskollär Visingsö 42,\nKnislinge 43, överlär Tunaberg 51, l:e rekt\nOxelösund sed 56.\n\nGift 42 m Sonja Andersson f 20, dtr t\nkyrkoh Elon A o Anna Olausson.\n-Barn: Torbjörn f 43, Tryggve f 46,\nElisabet f 50.\n\nTVETEN, HANS, direktör, Vaxholm,\nf i Oslo 9/12/26 av kapt Yngvar T o\nHarriet Svendsen.\n\nStud:ex Oslo 45, Befälssk 46, Krigssk 48,\nhdlsgymn 49, Akad f näringslivet 51,\nsekr Shipping Services 49-54, Englebert\ngummi 54, traffic off SAS 56, dir :ass\nScandinavia bilutleie 60, disp\nScandina-via biluthyrn Gbg 61, verkst dir\nScandinavia biluthyrn Sthlm sed 63. - Utm:\nNDM. - Hobby: filateli.\nGift 58 m Anne-Lise Grindalen, dtr t\nSigurd G o Jenny G. - Barn: Mörten\nf 58, Anne-Christine f 60, Inger-Merethe\nf 62.\n\nTYDÉN, C HAKON E,\nstiftssekreterare, Karlstad, f i Sthlm 8/9/06 av kapt\nCarl T o Alice Forssell.\nStud:ex 24, jur kand Upps 33, tingstjg\nÖlands doms 34, Göta hovr 36, aman\ndomkap Karlstad 38, stiftsnot där 40,\nI:t stiftsnot 52, s’tift’ssekr sed 64. - Sekr\nkyrkoråd, kyrkofullm, kyrkogårdsnd.\nGift 44 m Ingrid Rehnborg f 17, dtr t\ndisp L R o Lydia Nilsson. - Barn: Hans\nf 46, Gunilla o Eva ff 51.\n\nTYDÉN, ÅKE M, direktör, Köping,\nf i Karlskrona 21/W/il av byråch Adolf\nT o Elsa Forsell.\n\nStud:ex Sthlm 36, jur kand 41, tingstjg\nSthlms rådhusr o Södertörns doms 41-\n\n42, bitr jur Otto Schultz adv:byrå Sthlm\n42, omb :man o ekon :ch Sv skifferolje\nab 48, ekon:dir där 53, ab Sv\nsalpeterverken sed 62. - Led Sv:es ind:förb\nvatten- o luf tv :komm, styr :led\nNyköpings-åns vattenv:förb. - Medl Concordia.\n-Skr: art i fackpress.\n\nGift 40 m Gun Swedhner f 20, dtr t\nköpman Ossian S o Beata Carlo. - Barn:\nHans f 43, Olof f 47, Johan f 54.\n\n",
    "structured": {
        "0": {
            "full_name": "TURESSON, A GUNNAR",
            "location": "Hammarö",
            "occupation": "tonsättare, sångare",
            "birth_details": {
                "date": "06/10/1906",
                "place": "Arvika",
                "parents": "orgelbygg P E T o Karin Pettersson"
            },
            "education": [
                {
                    "degree": "Musikstud",
                    "year": "Zetterqvist",
                    "institution": "prof"
                }
            ],
            "career": [
                {
                    "position": "konsertturnéer",
                    "years": {
                        "start_year": 0,
                        "end_year": 0
                    },
                    "organization": "Skand o Amer"
                },
                {
                    "position": "grammofon-insjungn",
                    "years": {
                        "start_year": 0,
                        "end_year": 0
                    },
                    "organization": null
                }
            ],
            "family": {
                "spouse": "Birgit Hellsing",
                "marriage_year": "1949",
                "children": [
                    {
                        "name": "Ol",
                        "birth_year": "NULL"
                    }
                ]
            }
        },
        "1": {
            "full_name": "TUVESON, TORSTEN",
            "location": "Oxelösund",
            "occupation": "förste rektor",
            "birth_details": {
                "date": "20/12/1917",
                "place": "Knislinge, Kristianst l",
                "parents": "över lär Teodor T o Hilda Möller"
            },
            "education": null,
            "career": [
                {
                    "position": "överlär",
                    "years": {
                        "start_year": 0,
                        "end_year": 0
                    },
                    "organization": "Tunaberg"
                },
                {
                    "position": "l:e rekt",
                    "years": {
                        "start_year": 1956,
                        "end_year": 0
                    },
                    "organization": "Oxelösund"
                }
            ],
            "family": {
                "spouse": "Sonja Andersson",
                "marriage_year": "1942",
                "children": [
                    {
                        "name": "Torbjörn",
                        "birth_year": "1943"
                    },
                    {
                        "name": "Tryggve",
                        "birth_year": "1946"
                    },
                    {
                        "name": "Elisabet",
                        "birth_year": "1950"
                    }
                ]
            }
        },
        "2": {
            "full_name": "TVETEN, HANS",
            "location": "Vaxholm",
            "occupation": "direktör",
            "birth_details": {
                "date": "09/12/1926",
                "place": "Oslo",
                "parents": "kapt Yngvar T o Harriet Svendsen"
            },
            "education": [
                {
                    "degree": "Stud",
                    "year": "Oslo",
                    "institution": null
                },
                {
                    "degree": "Befälssk",
                    "year": "Krigssk 48",
                    "institution": null
                },
                {
                    "degree": "hdlsgymn",
                    "year": "49",
                    "institution": null
                },
                {
                    "degree": "Akad f näringslivet",
                    "year": "51",
                    "institution": null
                }
            ],
            "career": [
                {
                    "position": "sekr",
                    "years": {
                        "start_year": 1956,
                        "end_year": 0
                    },
                    "organization": "Shipping Services"
                },
                {
                    "position": "dir :ass",
                    "years": {
                        "start_year": 1963,
                        "end_year": 0
                    },
                    "organization": "Scandinavia biluthyrn Sthlm"
                }
            ],
            "family": {
                "spouse": "Anne-Lise Grindalen",
                "marriage_year": "1958",
                "children": [
                    {
                        "name": "Mörten",
                        "birth_year": "1958"
                    },
                    {
                        "name": "Anne-Christine",
                        "birth_year": "1960"
                    },
                    {
                        "name": "Inger-Merethe",
                        "birth_year": "1962"
                    }
                ]
            }
        },
        "3": {
            "full_name": "TYDÉN, C HAKON E",
            "location": "Karlstad",
            "occupation": "stiftssekreterare",
            "birth_details": {
                "date": "08/09/1906",
                "place": "Sthlm",
                "parents": "kapt Carl T o Alice Forssell"
            },
            "education": [
                {
                    "degree": "Stud:ex",
                    "year": "24",
                    "institution": null
                },
                {
                    "degree": "jur kand",
                    "year": "Upps 33",
                    "institution": null
                }
            ],
            "career": [
                {
                    "position": "tingstjg",
                    "years": {
                        "start_year": 1934,
                        "end_year": 1936
                    },
                    "organization": "Göta hovr"
                },
                {
                    "position": "stiftsnot",
                    "years": {
                        "start_year": 1952,
                        "end_year": 0
                    },
                    "organization": "I:t stiftsnot"
                }
            ],
            "family": {
                "spouse": "Ingrid Rehnborg",
                "marriage_year": "1944",
                "children": [
                    {
                        "name": "Hans",
                        "birth_year": "1946"
                    },
                    {
                        "name": "Gunilla",
                        "birth_year": "1951"
                    },
                    {
                        "name": "Eva",
                        "birth_year": "1951"
                    }
                ]
            }
        },
        "4": {
            "full_name": "TYDÉN, ÅKE M",
            "location": "Köping",
            "occupation": "direktör",
            "birth_details": {
                "date": "21/11/NULL",
                "place": "Karlskrona",
                "parents": "byråch Adolf T o Elsa Forsell"
            },
            "education": [
                {
                    "degree": "Stud:ex",
                    "year": "36",
                    "institution": null
                },
                {
                    "degree": "jur kand",
                    "year": "41",
                    "institution": null
                }
            ],
            "career": [
                {
                    "position": "bitr jur",
                    "years": {
                        "start_year": 1942,
                        "end_year": 1942
                    },
                    "organization": "Otto Schultz adv:byrå Sthlm"
                },
                {
                    "position": "ekon:dir",
                    "years": {
                        "start_year": 1953,
                        "end_year": 0
                    },
                    "organization": "ab Sv salpeterverken"
                }
            ],
            "family": {
                "spouse": "Gun Swedhner",
                "marriage_year": "1940",
                "children": [
                    {
                        "name": "Hans",
                        "birth_year": "1943"
                    },
                    {
                        "name": "Olof",
                        "birth_year": "1947"
                    },
                    {
                        "name": "Johan",
                        "birth_year": "1954"
                    }
                ]
            }
        }
    }
}