{
    "original": "TEGLUND, G ARTUR, överingenjör,\nGustafsberg, f i Luleå 22/12/99 av\nsnickare Anders T o Anna Olson.\nIng:ex STI 34, verkst:ing ab Skoglund o\nOlson Gävle 34, arb:studiech ab\nLiljeholmens kabelfabr Sthlm 37,\nrationaliser:ing Gustafsbergs fabr 45, ch f\nsani-tetstillv där 46, övering o tekn ch sed\n50. - Ordf Rörledn :fackets\nrationalisen-komm 46-49. - Utm: RVO. - Hobby:\nfriluftsliv.\n\nGift 23 m Märta Svensson f Ol, dtr t\nspinnmäst Albert S o Améli Lundin.\n\nTEGNÉR, KARL-BERTIL, leg läkare,\nUppsala, f i Växjö 1/3/27 av dr\nYelver-ton T o Gertrud Corneille.\nStud:ex 47, med kand Upps 51, med lic\nSthlm 56, underläk med avd Eksjö 56,\nEksjö sanat 57, med klin Örebro 59,\n\nröntgenklin  där  62,  underläk  lungklin\nAkad sjh Upps sed 63.\nGift 56 m Ulla Billström, dtr t fil måg\nTorsten B  o Vivi Andersson.  - Barn:\nKatarina f 61, Agneta f 63.\n\nTEGNÉR, ANN-MARIE,\nläroverksadjunkt, Sigtuna, f i Sthlm 18/6/17 av\nkont:ch Uno T o Edith Stenfelt.\nStud:ex 36, fil måg StHS 42, timlär\nKursverksamh v StHS 39-43,\nSigtunastift hum lärov 43, N latin Sthlm 48, adj\nSigtunastift hum lärov sed 50. - Led\nStadsfullm Sigtuna sed 56, skolstyr sed\n57; s tyr :led Sigtuna human förb sed 50,\nSv klassikerförb sed 57. - Stip Sv inst\nRom o Aten 58. - Hobby: resor.\n\nTEGNÉR, CLAES P, fil lic,\nSödertälje, f i Sthlm 4/2/22 av komm :kapt\nCarl T o Greta Geber.\nStud:ex 42, ing:ex STI 44, fil kand StU\n50, fil lic 53, aman StU 49, ass där 53,\nlab :led ab Astras forskn :lab 54, pat :ing\nsed 63. - Skr: vetensk arb inom\norganisk kemi.\n\nGift 52 m Gunnel Nystedt f 29, dtr t\nlärov :ad j Elias N o Ellen Norrbom.\n-Barn: Agneta f 54, Tomas f 56.\n\n",
    "structured": {
        "0": {
            "full_name": "G Artur Teglund",
            "location": "Gustafsberg",
            "occupation": "överingenjör",
            "birth_details": {
                "date": "22/12/1899",
                "place": "Luleå",
                "parents": "snickare Anders T o Anna Olson"
            },
            "education": [
                {
                    "degree": "Ing",
                    "year": "1934",
                    "institution": "STI"
                }
            ],
            "career": [
                {
                    "position": "verkst:ing",
                    "years": {
                        "start_year": 1934,
                        "end_year": 1934
                    },
                    "organization": "ab Skoglund o Olson Gävle"
                },
                {
                    "position": "arb:studiech",
                    "years": {
                        "start_year": 1937,
                        "end_year": 1937
                    },
                    "organization": "Liljeholmens kabelfabr Sthlm"
                },
                {
                    "position": "rationaliser:ing",
                    "years": {
                        "start_year": 1945,
                        "end_year": 1945
                    },
                    "organization": "Gustafsbergs fabr"
                },
                {
                    "position": "sani-tetstillv",
                    "years": {
                        "start_year": 1946,
                        "end_year": 1946
                    },
                    "organization": "Gustafsbergs fabr"
                },
                {
                    "position": "övering o tekn ch",
                    "years": {
                        "start_year": 1950,
                        "end_year": null
                    },
                    "organization": "Gustafsbergs fabr"
                }
            ],
            "family": {
                "spouse": "Märta Svensson",
                "marriage_year": "1923",
                "children": [
                    {
                        "name": "NULL",
                        "birth_year": "NULL"
                    }
                ]
            }
        },
        "1": {
            "full_name": "Karl-Bertil Tegnér",
            "location": "Uppsala",
            "occupation": "leg läkare",
            "birth_details": {
                "date": "1/3/1927",
                "place": "Växjö",
                "parents": "dr Yelverton T o Gertrud Corneille"
            },
            "education": [
                {
                    "degree": "Stud",
                    "year": "1947",
                    "institution": "NULL"
                },
                {
                    "degree": "med kand",
                    "year": "1951",
                    "institution": "Upps"
                },
                {
                    "degree": "med lic",
                    "year": "1956",
                    "institution": "Sthlm"
                }
            ],
            "career": [
                {
                    "position": "underläk",
                    "years": {
                        "start_year": 1956,
                        "end_year": 1956
                    },
                    "organization": "avd Eksjö"
                },
                {
                    "position": "NULL",
                    "years": {
                        "start_year": 1957,
                        "end_year": 1957
                    },
                    "organization": "Eksjö sanat"
                },
                {
                    "position": "med klin",
                    "years": {
                        "start_year": 1959,
                        "end_year": 1959
                    },
                    "organization": "Örebro"
                },
                {
                    "position": "röntgenklin",
                    "years": {
                        "start_year": 1962,
                        "end_year": 1962
                    },
                    "organization": "NULL"
                },
                {
                    "position": "underläk",
                    "years": {
                        "start_year": 1963,
                        "end_year": "NULL"
                    },
                    "organization": "lungklin Akad sjh Upps"
                }
            ],
            "family": {
                "spouse": "Ulla Billström",
                "marriage_year": "1956",
                "children": [
                    {
                        "name": "Katarina",
                        "birth_year": "1961"
                    },
                    {
                        "name": "Agneta",
                        "birth_year": "1963"
                    }
                ]
            }
        },
        "2": {
            "full_name": "Ann-Marie Tegnér",
            "location": "Sigtuna",
            "occupation": "läroverksadjunkt",
            "birth_details": {
                "date": "18/6/1917",
                "place": "Sthlm",
                "parents": "kont:ch Uno T o Edith Stenfelt"
            },
            "education": [
                {
                    "degree": "Stud",
                    "year": "1936",
                    "institution": "NULL"
                },
                {
                    "degree": "fil måg",
                    "year": "1942",
                    "institution": "StHS"
                }
            ],
            "career": [
                {
                    "position": "timlär",
                    "years": {
                        "start_year": 1939,
                        "end_year": 1943
                    },
                    "organization": "Kursverksamh v StHS"
                },
                {
                    "position": "adj",
                    "years": {
                        "start_year": 1950,
                        "end_year": "NULL"
                    },
                    "organization": "Sigtunastift hum lärov"
                }
            ],
            "family": {
                "spouse": "NULL",
                "marriage_year": "NULL",
                "children": [
                    {
                        "name": "NULL",
                        "birth_year": "NULL"
                    }
                ]
            }
        },
        "3": {
            "full_name": "Claes P Tegnér",
            "location": "Södertälje",
            "occupation": "fil lic",
            "birth_details": {
                "date": "4/2/1922",
                "place": "Sthlm",
                "parents": "komm :kapt Carl T o Greta Geber"
            },
            "education": [
                {
                    "degree": "Stud",
                    "year": "1942",
                    "institution": "NULL"
                },
                {
                    "degree": "ing",
                    "year": "1944",
                    "institution": "STI"
                },
                {
                    "degree": "fil kand",
                    "year": "1950",
                    "institution": "StU"
                },
                {
                    "degree": "fil lic",
                    "year": "1953",
                    "institution": "NULL"
                }
            ],
            "career": [
                {
                    "position": "aman",
                    "years": {
                        "start_year": 1949,
                        "end_year": 1949
                    },
                    "organization": "StU"
                },
                {
                    "position": "ass",
                    "years": {
                        "start_year": 1953,
                        "end_year": 1953
                    },
                    "organization": "NULL"
                },
                {
                    "position": "lab :led",
                    "years": {
                        "start_year": 1954,
                        "end_year": 1954
                    },
                    "organization": "Astras forskn :lab"
                },
                {
                    "position": "pat :ing",
                    "years": {
                        "start_year": 1963,
                        "end_year": "NULL"
                    },
                    "organization": "NULL"
                }
            ],
            "family": {
                "spouse": "Gunnel Nystedt",
                "marriage_year": "1952",
                "children": [
                    {
                        "name": "Agneta",
                        "birth_year": "1954"
                    },
                    {
                        "name": "Tomas",
                        "birth_year": "1956"
                    }
                ]
            }
        }
    }
}