{
    "original": "NILSSON, NILS IVAR A,\ncivilekonom, Umeå, f i Umeå 29/8/30 av\ndrät-seldir Nils Hjalmar N o Clara Norgren.\nDHG 55, ekon:ch Scharin &amp; Co KB\nUmeå 55, adj i redovisn o admin m\nföret:org Umeå hdlsgymn sed 62. -\nInneh Civ :ekon N I Nilsson ab sed 62.\n-Ordf Umeå Jr Chamber of Comm 68.\nGift 60 m Britt Sundqvist f 34, dtr t\nkamr J E S o Emy Högberg. - Barn:\nPer Olof f 61, Hans Erik f 65.\n\nNILSSON, R H OLAV, konstnär,\nGammelstad, f i Luleå 2/8/36 av Hasse N o\nRut Gustavsson.\n\nHKS 57-61. - Bl arb: relief i järnsmide\nKiruna 63, huset Ormen Långe Vårby\nSthlm 64, ridå o trärelief Bergssk Luleå\n65, betongrelief Skand bkn Luleå 65,\nbetongmur kv Isbjörnen Kiruna 66,\ntextil Piteå Heat 67. - .Utst länsmus\nÖstersund 612, delt i saml:uts t Norrb mus 63’,\n6&lt;4&lt; 66, Galerie S:t Nikolaus Sthlm 64,\n\nS:t Eriksmässan 65, Nät :mus 66,\nvandr:-utst Norrlänningar 65*-66, Unga\nnorrbottningar 6T. - Repr i Östersunds mus.\n-Medl KRO, Sv-polska fören. - Hobby:\ntennis.\n\nGift 60 m Disa Lundström f 35, dtr t\nGeorg L o Dagmar Nilsson. - Barn:\nJesper f 61, Jerker f 64, Jakob f 67.\n\nNILSSON, N PER-ERIK,\nhovrättsassessor, Umeå, f i Arvidsjaur, Norrb l,\n5/1/30 av jägm Erik N o Elsa Åkesson.\nStud:ex Skellefteå 49, jur kand Upps 56,\ntingstjg Piteå doms 57-59, fiskal Ö Norrl\n60, tingssekr Torneå doms 61-63, assess\nhovr Ö Norrl sed 64, sekr 65 års valtekn\nutredn sed 65.\n\nGift 60 m ämneslär Margaretha\nEriksson f 35, dtr t A E o Gerda Lyxell.\n-Barn: Nils f 61, Anna Karin f 63, Erika\nf 67.\n\nNILSSON, RUNO B A,\nläroverksadjunkt,   Ånge,   f   i   Sundsvall   9/1/30  av\nkonduktör N A N o A I M Larsson.\nStud:ex priv 51, fil mag 57, adj i sv o\nhist  m  samh:lära  samrealsk,  num\nBo-bergssk, Ånge sed 61 (eo 57).\nGift 57 m Inga Lilja, dtr t mur John L\no  Anna  Blåns-Persson.   -  Barn:  Sigun\nf 58.\n\n",
    "structured": {
        "1": {
            "full_name": "NILSSON, NILS IVAR A",
            "location": "Umeå",
            "occupation": "civilekonom",
            "birth_details": {
                "date": "29/08/1930",
                "place": "Umeå",
                "parents": "drätseldir Nils Hjalmar N och Clara Norgren"
            },
            "education": [
                {
                    "degree": "DHG",
                    "year": "1955",
                    "institution": "ekonomi:ch Scharin & Co KB Umeå"
                }
            ],
            "career": [
                {
                    "position": "adj i redovisn",
                    "years": {
                        "start_year": 1962,
                        "end_year": null
                    },
                    "organization": "admin m föret:org Umeå hdlsgymn"
                },
                {
                    "position": "Innehavare Civilekonom",
                    "years": {
                        "start_year": 1962,
                        "end_year": null
                    },
                    "organization": "N I Nilsson ab"
                }
            ],
            "family": {
                "spouse": "Britt Sundqvist",
                "marriage_year": "1960",
                "children": [
                    {
                        "name": "Per Olof",
                        "birth_year": "1961"
                    },
                    {
                        "name": "Hans Erik",
                        "birth_year": "1965"
                    }
                ]
            }
        },
        "2": {
            "full_name": "NILSSON, R H OLAV",
            "location": "Gammelstad",
            "occupation": "konstnär",
            "birth_details": {
                "date": "02/08/1936",
                "place": "Luleå",
                "parents": "Hasse N och Rut Gustavsson"
            },
            "education": [
                {
                    "degree": "HKS",
                    "year": "1957-1961",
                    "institution": null
                }
            ],
            "career": [
                {
                    "position": "Bl arb: relief i järnsmide Kiruna",
                    "years": {
                        "start_year": 1963,
                        "end_year": null
                    },
                    "organization": null
                },
                {
                    "position": "häuste Ormen Långe Vårby Sthlm",
                    "years": {
                        "start_year": 1964,
                        "end_year": null
                    },
                    "organization": null
                },
                {
                    "position": "ridå o trärelief Bergssk Luleå",
                    "years": {
                        "start_year": 1965,
                        "end_year": null
                    },
                    "organization": null
                },
                {
                    "position": "betongrelief Skand bkn Luleå",
                    "years": {
                        "start_year": 1965,
                        "end_year": null
                    },
                    "organization": null
                },
                {
                    "position": "betongmur kv Isbjörnen Kiruna",
                    "years": {
                        "start_year": 1966,
                        "end_year": null
                    },
                    "organization": null
                },
                {
                    "position": "textil Piteå Heat",
                    "years": {
                        "start_year": 1967,
                        "end_year": null
                    },
                    "organization": null
                }
            ],
            "family": {
                "spouse": "Disa Lundström",
                "marriage_year": "1960",
                "children": [
                    {
                        "name": "Jesper",
                        "birth_year": "1961"
                    },
                    {
                        "name": "Jerker",
                        "birth_year": "1964"
                    },
                    {
                        "name": "Jakob",
                        "birth_year": "1967"
                    }
                ]
            },
            "hobbies": [
                "tennis"
            ]
        },
        "3": {
            "full_name": "NILSSON, N PER-ERIK",
            "location": "Umeå",
            "occupation": "hovrättsassessor",
            "birth_details": {
                "date": "05/01/1930",
                "place": "Arvidsjaur, Norrb l",
                "parents": "jägm Erik N och Elsa Åkesson"
            },
            "education": [
                {
                    "degree": "Stud:ex",
                    "year": "1949",
                    "institution": "Skellefteå"
                },
                {
                    "degree": "jur kand",
                    "year": "1956",
                    "institution": "Upps"
                }
            ],
            "career": [
                {
                    "position": "tingstjg",
                    "years": {
                        "start_year": 1957,
                        "end_year": 1959
                    },
                    "organization": "Piteå doms"
                },
                {
                    "position": "fiskal",
                    "years": {
                        "start_year": 1960,
                        "end_year": null
                    },
                    "organization": "Ö Norrl"
                },
                {
                    "position": "tingssekr",
                    "years": {
                        "start_year": 1961,
                        "end_year": 1963
                    },
                    "organization": "Torneå doms"
                },
                {
                    "position": "hovrättsassessur",
                    "years": {
                        "start_year": 1964,
                        "end_year": null
                    },
                    "organization": "hovr Ö Norrl"
                }
            ],
            "family": {
                "spouse": "Margaretha Eriksson",
                "marriage_year": "1960",
                "children": [
                    {
                        "name": "Nils",
                        "birth_year": "1961"
                    },
                    {
                        "name": "Anna Karin",
                        "birth_year": "1963"
                    },
                    {
                        "name": "Erika",
                        "birth_year": "1967"
                    }
                ]
            }
        },
        "4": {
            "full_name": "NILSSON, RUNO B A",
            "location": "Ånge",
            "occupation": "läroverksadjunkt",
            "birth_details": {
                "date": "09/01/1930",
                "place": "Sundsvall",
                "parents": "konduktör N A N och A I M Larsson"
            },
            "education": [
                {
                    "degree": "Stud:ex",
                    "year": "1951",
                    "institution": "priv"
                },
                {
                    "degree": "fil mag",
                    "year": "1957",
                    "institution": null
                }
            ],
            "career": [
                {
                    "position": "adj i sv o hist",
                    "years": {
                        "start_year": null,
                        "end_year": null
                    },
                    "organization": "samh:lära samrealsk, num Bo-bergssk, Ånge"
                }
            ],
            "family": {
                "spouse": "Inga Lilja",
                "marriage_year": "1957",
                "children": [
                    {
                        "name": "Sigun",
                        "birth_year": "1958"
                    }
                ]
            },
            "hobbies": [
                "tennis"
            ]
        }
    }
}