{
    "original": "NORDSTRÖM, S £ TORE,\nstadsbibliotekarie, Örnsköldsvik, f i Sthlm 5/3/24\nav Karl Ejnar N o Lisa Sterner.\nStud:ex 44, off:ex 48, DSI 50, Bibl:sk\n55; förest Timrå hemgård 50-54,\nstads-bibl:ie Örnsköldsvik sed 55. - Led SAB :s\norg :utredn 64-65, Västernorrl l landst\nPR-utredn sed 65, landst bibl :utredn sed\n66; led byggn:nd sed 65. - Red o utg\ntidskr Filmrutan 58-62; Sv:es radios omb\nsed 62. - Gen:sekr 67 års skid-SM.\n-Kapt KA 5 res. - Hobbies: orientering,\nskidsport, musik.\n\nGift 50 m Eva Josefsson f 24, dtr t Axel\nJ o Svea Lindgren. - Barn: Birgitta f 53.\n\nNORDWALL, A GUNNAR,\növerjägmästare, Skellefteå, f i Gävle 13/5/06 av\nlekt J F N o Helmi Öller.\nStud:ex 24, SkHS 29, anst domänv sed\n35, jägm Gällivare revir 45 (bitr 42),\növerjägm Skellefteå distr sed 48. - Särsk\nled kammarr sed 51, led Västerb l\npröv-n:nd sed 53; styr :ordf Skellefteå samt\nByske o Åby älvars flottn:fören sed 51.\n- Utm: RNO.\n\nGift 32 m Karin Lindow f 06, dtr t\nlokomotivmäst Robert L o Maria\nWes-termark. - Barn: Birgitta f 33, Anders\nf 37, Ingrid f 43.\n\nNORDWALL, RUT B, eo lektor,\nKiruna, f i Tärnaby, Västerb l, 5/7/32 av\nkommin Joel Karlsson o Brita Berglund.\nFil mag Upps 58, eo adj komm realsk\nBjurholm 59-61, eo lekt i sv o hist m\nsamh:lära hal Kiruna sed 63.\nGift 60 m polisman Siwert Nordwall.\n-Barn: Torkel f 65.\n\nNORELL, ERIQ U, redaktör,\nSandviken, f i Fagersta 8/7/27.\nLokalred Fagersta-Posten/Avesta Tidn\nNorberg 62, platsch Fagersta-Posten\nFagersta 63, chefred o ansv utg Sandvikens\nTidn sed 66.\n\nNORELL, OLLE, chefredaktör,\nÖrnsköldsvik, f i Norrkpg 9/5/23 av org\nKnut N o Olga Hamberg.\nStud:ex Lund 44, anst Å&amp;Å 46, Nord\nrotogravyr 51, Idun 53, Sv:es radio-TV\n62, TV-krönikör Expressen 63, chefred\nÖrnsköldsviks Allen sed 65. - Sign:\nPalisander.\n\nGift 45 m Ingegerd Sjöström, dtr t E G\nS o Hulda Jonsson. - Barn: Agneta f 46,\nJohan Petter f 65.\n\nNORÉN, A HELGE, redaktör,\nSkellefteå, f i Holmsund, Västerb l, 3/9/25 av\nsågv :arb Axel N o Ellen Lundgren.\nRealex Umeå 42, Umeå hdlsgymn 44,\nkont Övre Norrl kraftv 47-49, sportch\ntidn Norra Västerbotten 49-52 o 54-56,\nsportred tidn Expressen 53-54, dess\nriks-red f Norrl sed 56. - Utm: Västerb\nidr:-förb GM, Sv ishockeyförb SM,\nRIFftjt-G, Västerb ishockeyförb ftjtGoS,\nVästerb bordtennisförb ftjtS m fi utm.\n-Hobby: tennis.\n\nGift 46 m Eleonor Eriksson f 23, dtr t\nhemm:äg Erik Antonsson o Hildur\nLönnberg. - Barn: Lena f 49, Per-Mikael f 54,\nMårten f 56, Jan-Erik f 58.\n\nNORÉN, E INGVAR, lantmätare,\nSkellefteå, f i Bingsjö, Kopparb l, 4/6/31 av\nhemm:äg Erik N o Eva Eriksson.\nStud:ex Falun 52, KTH 59, lantmät:tjg\nVästerb o Kopparb l 59, Skellefteå n o\ns distr 64, bitr fastigh :ch Skellefteå stad\nsed 66. - Hobbies: bridge, fiske, sport.\nGift 57 m Birgit Rundgren, dtr t\nKarl-Axel   R   o   Edith   Fahlgren.   -   Barn:\nMikael f 58, Anders f 61.\n\nNORÉUS, FOLKE A T, revisor,\nLjusdal, f i Sthlm 16/3/05 av verkm Harald\nN o Hillivi Quist.\n\nRealex 21, korresp:stud 33-36; kont\nSinger Co symaskins ab Sthlm 22, bokh\nab A Wiklunds maskin &amp; velocipedfabr\n27-32, kont :ch ab Ljusdals bilcentral\n37-59, inneh ab Folke Noréus rev:- &amp;\nbokför:byrå sed 59. - Led Sundsvallsbkn\nLjusdal sed 61, styr :led SARA-bol\nLjusdal sed 56; ordf Ljusdals f p :avd sed 66.\n- Led Gävleb l landst sed 50, dess\nhäl-sov:utsk samt sjv:komm; ordf\nkomm:-fullm 61-62 o sed 67 (led 50), v ordf\nkomm:nd sed 50, v ordf las :direkt sed\n64 (ordf 60-63) m fi allm uppdr. - Medl\nOdd Fellow.\n\nGift 29 m Dagmar Jacobsson f 06, dtr\nt sjökapt Oscar J o Alma Jacobsson.\n-Barn: Anne-Marie f 29, Ulla f 35,\nMonica f 43, Harald f 46.\n\n",
    "structured": {
        "1": {
            "full_name": "Nordström, S€tore",
            "location": "Örnsköldsvik",
            "occupation": "Stadsbibliotekarie",
            "birth_details": {
                "date": "05/03/1924",
                "place": "Stockholm",
                "parents": "Karl Ejnar Nordström, Lisa Sterner"
            },
            "education": [
                {
                    "degree": "Stud:ex",
                    "year": "1944",
                    "institution": "NULL"
                },
                {
                    "degree": "Off:ex",
                    "year": "1948",
                    "institution": "NULL"
                },
                {
                    "degree": "DSI",
                    "year": "1950",
                    "institution": "NULL"
                },
                {
                    "degree": "Bibl:sk",
                    "year": "1955",
                    "institution": "NULL"
                }
            ],
            "career": [
                {
                    "position": "Förest Timrå hemgård",
                    "years": {
                        "start_year": 1950,
                        "end_year": 1954
                    },
                    "organization": "NULL"
                },
                {
                    "position": "Stadsbibl:ie Örnsköldsvik",
                    "years": {
                        "start_year": 1955,
                        "end_year": null
                    },
                    "organization": "NULL"
                }
            ],
            "family": {
                "spouse": "Eva Josefsson",
                "marriage_year": "1950",
                "children": [
                    {
                        "name": "Birgitta",
                        "birth_year": "1953"
                    }
                ]
            },
            "publications": "NULL",
            "community_involvement": "NULL",
            "board_memberships": "NULL",
            "honorary_titles": "NULL",
            "hobbies": [
                "orientering",
                "skidsport",
                "musik"
            ]
        },
        "2": {
            "full_name": "Nordwall, A Gunnar",
            "location": "Skellefteå",
            "occupation": "Överjägmästare",
            "birth_details": {
                "date": "13/05/1906",
                "place": "Gävle",
                "parents": "J F Nordwall, Helmi Öller"
            },
            "education": [
                {
                    "degree": "Stud:ex",
                    "year": "1924",
                    "institution": "NULL"
                },
                {
                    "degree": "SkHS",
                    "year": "1929",
                    "institution": "NULL"
                }
            ],
            "career": [
                {
                    "position": "Anst Domänv",
                    "years": {
                        "start_year": 1935,
                        "end_year": null
                    },
                    "organization": "NULL"
                },
                {
                    "position": "Jägm Gällivare revir",
                    "years": {
                        "start_year": 1945,
                        "end_year": null
                    },
                    "organization": "NULL"
                },
                {
                    "position": "Överjägm Skellefteå distr",
                    "years": {
                        "start_year": 1948,
                        "end_year": null
                    },
                    "organization": "NULL"
                }
            ],
            "family": {
                "spouse": "Karin Lindow",
                "marriage_year": "1932",
                "children": [
                    {
                        "name": "Birgitta",
                        "birth_year": "1933"
                    },
                    {
                        "name": "Anders",
                        "birth_year": "1937"
                    },
                    {
                        "name": "Ingrid",
                        "birth_year": "1943"
                    }
                ]
            },
            "publications": "NULL",
            "community_involvement": "NULL",
            "board_memberships": "NULL",
            "honorary_titles": [
                "RNO"
            ],
            "hobbies": "NULL"
        },
        "3": {
            "full_name": "Nordwall, Rut B",
            "location": "Kiruna",
            "occupation": "Eo lektor",
            "birth_details": {
                "date": "05/07/1932",
                "place": "Tärnaby, Västerb l",
                "parents": "Joel Karlsson, Brita Berglund"
            },
            "education": [
                {
                    "degree": "Fil mag",
                    "year": "1958",
                    "institution": "Upps"
                },
                {
                    "degree": "Eo adj komm realsk",
                    "year": "1959-1961",
                    "institution": "NULL"
                },
                {
                    "degree": "Eo lekt i sv o hist m samh:lära",
                    "year": "1963",
                    "institution": "NULL"
                }
            ],
            "career": [
                {
                    "position": "Eo lekt i sv o hist m samh:lära",
                    "years": {
                        "start_year": 1963,
                        "end_year": null
                    },
                    "organization": "Kiruna"
                }
            ],
            "family": {
                "spouse": "Polisman Siwert Nordwall",
                "marriage_year": "1960",
                "children": [
                    {
                        "name": "Torkel",
                        "birth_year": "1965"
                    }
                ]
            },
            "publications": "NULL",
            "community_involvement": "NULL",
            "board_memberships": "NULL",
            "honorary_titles": "NULL",
            "hobbies": "NULL"
        },
        "4": {
            "full_name": "Norell, Eriq U",
            "location": "Sandviken",
            "occupation": "Redaktör",
            "birth_details": {
                "date": "08/07/1927",
                "place": "Fagersta",
                "parents": "NULL"
            },
            "education": "NULL",
            "career": [
                {
                    "position": "Chefred o ansv utg",
                    "years": {
                        "start_year": 1966,
                        "end_year": null
                    },
                    "organization": "Sandvikens Tidn"
                }
            ],
            "family": "NULL",
            "publications": "NULL",
            "community_involvement": "NULL",
            "board_memberships": "NULL",
            "honorary_titles": "NULL",
            "hobbies": "NULL"
        },
        "5": {
            "full_name": "Norell, Olle",
            "location": "Örnsköldsvik",
            "occupation": "Chefredaktör",
            "birth_details": {
                "date": "09/05/1923",
                "place": "Norrkpg",
                "parents": "Knut N, Olga Hamberg"
            },
            "education": [
                {
                    "degree": "Stud:ex",
                    "year": "1944",
                    "institution": "Lund"
                }
            ],
            "career": [
                {
                    "position": "Chefred",
                    "years": {
                        "start_year": 1965,
                        "end_year": null
                    },
                    "organization": "Örnsköldsviks Allen"
                }
            ],
            "family": {
                "spouse": "Ingegerd Sjöström",
                "marriage_year": "1945",
                "children": [
                    {
                        "name": "Agneta",
                        "birth_year": "1946"
                    },
                    {
                        "name": "Johan Petter",
                        "birth_year": "1965"
                    }
                ]
            },
            "publications": "NULL",
            "community_involvement": "NULL",
            "board_memberships": "NULL",
            "honorary_titles": "NULL",
            "hobbies": "NULL"
        },
        "6": {
            "full_name": "Norén, A Helge",
            "location": "Skellefteå",
            "occupation": "Redaktör",
            "birth_details": {
                "date": "03/09/1925",
                "place": "Holmsund, Västerb l",
                "parents": "Axel N, Ellen Lundgren"
            },
            "education": [
                {
                    "degree": "Realex",
                    "year": "1942",
                    "institution": "Umeå hdlsgymn"
                }
            ],
            "career": [
                {
                    "position": "Realex",
                    "years": {
                        "start_year": 1949,
                        "end_year": 1952
                    },
                    "organization": "NULL"
                },
                {
                    "position": "Sportred tidn Expressen",
                    "years": {
                        "start_year": 1953,
                        "end_year": 1954
                    },
                    "organization": "NULL"
                },
                {
                    "position": "Dess riks-red f Norrl",
                    "years": {
                        "start_year": 1956,
                        "end_year": null
                    },
                    "organization": "NULL"
                }
            ],
            "family": {
                "spouse": "Eleonor Eriksson",
                "marriage_year": "1946",
                "children": [
                    {
                        "name": "Lena",
                        "birth_year": "1949"
                    },
                    {
                        "name": "Per-Mikael",
                        "birth_year": "1954"
                    },
                    {
                        "name": "Mårten",
                        "birth_year": "1956"
                    },
                    {
                        "name": "Jan-Erik",
                        "birth_year": "1958"
                    }
                ]
            },
            "publications": "NULL",
            "community_involvement": "NULL",
            "board_memberships": "NULL",
            "honorary_titles": "NULL",
            "hobbies": [
                "tennis"
            ]
        },
        "7": {
            "full_name": "Norén, E Ingvar",
            "location": "Skellefteå",
            "occupation": "Lantmätare",
            "birth_details": {
                "date": "04/06/1931",
                "place": "Bingsjö, Kopparb l",
                "parents": "Erik N, Eva Eriksson"
            },
            "education": [
                {
                    "degree": "Stud:ex",
                    "year": "1952",
                    "institution": "KTH"
                }
            ],
            "career": [
                {
                    "position": "Bitr fastigh :ch Skellefteå stad",
                    "years": {
                        "start_year": 1966,
                        "end_year": null
                    },
                    "organization": "NULL"
                }
            ],
            "family": {
                "spouse": "Birgit Rundgren",
                "marriage_year": "1957",
                "children": [
                    {
                        "name": "Mikael",
                        "birth_year": "1958"
                    },
                    {
                        "name": "Anders",
                        "birth_year": "1961"
                    }
                ]
            },
            "publications": "NULL",
            "community_involvement": "NULL",
            "board_memberships": "NULL",
            "honorary_titles": "NULL",
            "hobbies": [
                "bridge",
                "fiske",
                "sport"
            ]
        },
        "8": {
            "full_name": "Noréus, Folke A T",
            "location": "Ljusdal",
            "occupation": "Revisor",
            "birth_details": {
                "date": "16/03/1905",
                "place": "Sthlm",
                "parents": "Harald N, Hillivi Quist"
            },
            "education": [
                {
                    "degree": "Realex",
                    "year": "1921",
                    "institution": "NULL"
                },
                {
                    "degree": "Korresp:stud",
                    "year": "1933-1936",
                    "institution": "NULL"
                }
            ],
            "career": [
                {
                    "position": "Inneh ab Folke Noréus rev:",
                    "years": {
                        "start_year": 1959,
                        "end_year": null
                    },
                    "organization": "bokför:byrå"
                }
            ],
            "family": {
                "spouse": "Dagmar Jacobsson",
                "marriage_year": "1929",
                "children": [
                    {
                        "name": "Anne-Marie",
                        "birth_year": "1929"
                    },
                    {
                        "name": "Ulla",
                        "birth_year": "1935"
                    },
                    {
                        "name": "Monica",
                        "birth_year": "1943"
                    },
                    {
                        "name": "Harald",
                        "birth_year": "1946"
                    }
                ]
            },
            "publications": "NULL",
            "community_involvement": [
                {
                    "role": "Ordf Ljusdals f p :avd",
                    "organization": "NULL",
                    "years": "1966"
                }
            ],
            "board_memberships": [
                {
                    "position": "Styr :led SARA-bol",
                    "organization": "Ljusdal",
                    "years": "56"
                }
            ],
            "honorary_titles": "NULL",
            "hobbies": "NULL"
        }
    }
}