{
    "original": "NILSSON, JAN H, civilekonom,\nHärnösand, f i Gbg 21/9/39 av svetsare\nHelge N o Elin Wedlin.\n\nStud:ex Gbg 58, DHG 63, tf l:e tax:rev\nÖÄ 63-65, anst Vnorrl l föret:fören sed\n66. - Konsult verksamh o kreditbedömn.\n- Hobbies: litteratur, fiske, skidsport.\nGift 63 m Inez Zetterlund f 37, dtr t\ndroskäg Harald Z o Lilly Jacobsson.\n-Barn: Thomas f .65.\n\nNILSSON, JAN-IVAN N,\nriksdagsman, Tvärålund, f i Tvärålund, Västerb\nl, 14/3/24 av hemm:äg Nils Johansson\no Elin J.\n\nEg lantbr sed 49. - Led AK sed 61, led\nyrkesutb :utredn, utlänn:utredn; led\nkom-m:ndn. - Styr:led Skogsäg riksförb, ab\nÖvre Norrl fastigh :kredit, Västerb l\nRLF, ordf Västerb skogsäg:fören,\nVästerb traf örädl :f ören. - Styr :ordf ab\nÖbac-ka såg. - Medl TempelrO. - Utm: RNO.\nGift 49 m Inga-Maj Samuelsson, dtr t\nhemm:äg Joel S o Inga S. - Barn: Eva\nf 50, Anders f 53.\n\nNILSSON, JOHN E, fd förste\ntrafikinspektor, Umeå, f i Grevie, Krist l,\n12/8/91 av lantbr Andreas N o Kristine\nWieslander.\n\nRealex Hbg 07, anst SJ 07, l:e stat:skr\n34, byråass 42, l:e trafikinsp Umeå\n47-56. - Medl FrimO. - Utm: RVO,\nGM-nor. - Hobbies: fiske, bridge.\nGift 35 m Dagmar Holmström, dtr t\nprof Olof H o h h.\n\nNILSSON,   KJELL   A,   järnhandlare,\n\nJärpen, f i Sunne, Jämtl l, 14/8/30 av\njärnhandl Sigurd N o Ragny Hedström.\nRealex Undersåker 47, hdlssk Sundsvall\n52; verkst dir ab Järpens järnhdl sed 55\n(deläg o styr:led). - Hobbies: jakt, fiske,\nsport, filateli.\n\nGift- 53 m Solvei Sundell f 32, dtr t\narb:förmedl:förest Valter S o Clara\nAbrahamsson. - Barn: Arne f 55, Åke\nf 60, Marie f 67.\n\n",
    "structured": {
        "0": {
            "full_name": "JAN H NILSSON",
            "location": "Härnösand",
            "occupation": "civilekonom",
            "birth_details": {
                "date": "21/09/1939",
                "place": "Göteborg",
                "parents": "svetsare Helge N o Elin Wedlin"
            },
            "education": [
                {
                    "degree": "Stud:ex",
                    "year": "1958",
                    "institution": "Göteborg"
                },
                {
                    "degree": "DHG",
                    "year": "1963",
                    "institution": "NULL"
                }
            ],
            "career": [
                {
                    "position": "tf l:e tax:rev ÖÄ",
                    "years": {
                        "start_year": 1963,
                        "end_year": 1965
                    },
                    "organization": "Vnorrl l föret:fören"
                }
            ],
            "family": {
                "spouse": "Inez Zetterlund",
                "marriage_year": "1963",
                "children": [
                    {
                        "name": "Thomas",
                        "birth_year": "1965"
                    }
                ]
            },
            "hobbies": [
                "litteratur",
                "fiske",
                "skidsport"
            ]
        },
        "1": {
            "full_name": "JAN-IVAN N NILSSON",
            "location": "Tvärålund",
            "occupation": "riksdagsman",
            "birth_details": {
                "date": "14/03/1924",
                "place": "Tvärålund, Västerb l",
                "parents": "hemm:äg Nils Johansson o Elin J"
            },
            "career": [
                {
                    "position": "Eg lantbr",
                    "years": {
                        "start_year": 1949,
                        "end_year": null
                    },
                    "organization": "NULL"
                }
            ],
            "family": {
                "spouse": "Inga-Maj Samuelsson",
                "marriage_year": "1949",
                "children": [
                    {
                        "name": "Eva",
                        "birth_year": "1950"
                    },
                    {
                        "name": "Anders",
                        "birth_year": "1953"
                    }
                ]
            },
            "board_memberships": [
                {
                    "position": "Styr:led",
                    "organization": "Skogsäg riksförb",
                    "years": "NULL"
                },
                {
                    "position": "Styr :ordf",
                    "organization": "ab Öbacka såg",
                    "years": "NULL"
                }
            ],
            "honorary_titles": [
                {
                    "title": "Utm: RNO",
                    "institution": "NULL",
                    "year": "NULL"
                }
            ]
        },
        "2": {
            "full_name": "JOHN E NILSSON",
            "location": "Umeå",
            "occupation": "fd förste trafikinspektor",
            "birth_details": {
                "date": "12/08/1891",
                "place": "Grevie, Krist l",
                "parents": "lantbr Andreas N o Kristine Wieslander"
            },
            "education": [
                {
                    "degree": "Realex",
                    "year": "1907",
                    "institution": "Hbg"
                }
            ],
            "career": [
                {
                    "position": "l:e stat:skr",
                    "years": {
                        "start_year": 1934,
                        "end_year": null
                    },
                    "organization": "NULL"
                },
                {
                    "position": "byråass",
                    "years": {
                        "start_year": 1942,
                        "end_year": null
                    },
                    "organization": "NULL"
                },
                {
                    "position": "l:e trafikinsp Umeå",
                    "years": {
                        "start_year": 1947,
                        "end_year": 1956
                    },
                    "organization": "NULL"
                }
            ],
            "family": {
                "spouse": "Dagmar Holmström",
                "marriage_year": "1935",
                "children": []
            },
            "honorary_titles": [
                {
                    "title": "Utm: RVO",
                    "institution": "NULL",
                    "year": "NULL"
                }
            ],
            "hobbies": [
                "fiske",
                "bridge"
            ]
        },
        "3": {
            "full_name": "KJELL A NILSSON",
            "location": "Järpen",
            "occupation": "järnhandlare",
            "birth_details": {
                "date": "14/08/1930",
                "place": "Sunne, Jämtl l",
                "parents": "järnhandl Sigurd N o Ragny Hedström"
            },
            "education": [
                {
                    "degree": "Realex",
                    "year": "1947",
                    "institution": "Undersåker"
                },
                {
                    "degree": "hdlssk",
                    "year": "1952",
                    "institution": "Sundsvall"
                }
            ],
            "career": [
                {
                    "position": "verkst dir ab Järpens järnhdl",
                    "years": {
                        "start_year": 1955,
                        "end_year": null
                    },
                    "organization": "NULL"
                }
            ],
            "family": {
                "spouse": "Solvei Sundell",
                "marriage_year": "1953",
                "children": [
                    {
                        "name": "Arne",
                        "birth_year": "1955"
                    },
                    {
                        "name": "Åke",
                        "birth_year": "1960"
                    },
                    {
                        "name": "Marie",
                        "birth_year": "1967"
                    }
                ]
            },
            "hobbies": [
                "jakt",
                "fiske",
                "sport",
                "filateli"
            ]
        }
    }
}