{
    "original": "NYLANDER, ARNE O H, tandläkare,\n\nSjälevad, f i Härnösand 15/7/12 av köpm\n\nOscar N o Karin Norden.\n\nStud:ex Härnösand 31, tandl:ex Sthlm\n\n35, ass:tandl Tierp 35, priv:prakt Sthlm\n\n35-36, tandl komm tandklin Själevad 36-\n\n46, distr :tandl o förest distr :tandpol där\n\nsed 46.\n\nGift 36 m Märta Fryklund f 08, dtr t\n\nAdolf   F   o   Elin   Hemström.   -   Barn:\n\nCarin f 38, Eva f 41, Harald f 47.\n\nNYLANDER, A CLAES B,\nläroverksadjunkt, Hudiksvall, f i Sthlm 16/2/30 av\nkapt Alf N o Helny Söderdahl.\nStud:ex Karlskrona 48, fil mag Sthlm\n54, e adj hal Jönkpg 54, Karol hal\nÖrebro 54, Avesta hal 57, adj i modersm o\nhist m samh :lära Hudiksvalls hal sed 60.\nGift 65 m Marianne Sjöberg f 30, dtr t\növerste Olof S o Margit Rooth. - Barn:\nJohan f 65, Margareta f 67.\n\nNYLANDER, N INGVAR M,\nprofessor, överläkare, Umeå, f i Mariestad\n17/5/22 av folksk:insp Martin N o\nEmma Forsberg.\n\nStud:ex Uddevalla 41, med kand Upps\n41, med lic där 48, med dr o doc i\nbarnpsykiatri Karol inst 60, prof i\nbarnpsykiatri Umeå univ sed 66. - Bitr\növerläk barn- o ungd:psyk klin Kronpr\nLovisas barnsjh Sthlm 57-63, soc:läk Sthlms\nstads barnav:nd 64-65, överläk barnpsyk\nklin Umeå las sed 66. - Skr i\nbarnpsykiatri, pediatrik o soc:medicin.\nGift 48 m Kerstin Andersson f 21, dtr t\ning Isak A o Ester Ahlqvist. - Barn:\nMartin f 50, Staffan f 54.\n\n",
    "structured": {
        "1": {
            "full_name": "ARNE O H NYLANDER",
            "location": "Själevad",
            "occupation": "tandläkare",
            "birth_details": {
                "date": "15/07/1912",
                "place": "Härnösand",
                "parents": "Oscar Norden, Karin Norden"
            },
            "education": [
                {
                    "degree": "Stud:ex",
                    "year": "1931",
                    "institution": "Härnösand"
                },
                {
                    "degree": "tandl:ex",
                    "year": "1935",
                    "institution": "Sthlm"
                }
            ],
            "career": [
                {
                    "position": "ass:tandl",
                    "years": {
                        "start_year": 1935,
                        "end_year": 1935
                    },
                    "organization": "Tierp"
                },
                {
                    "position": "priv:prakt",
                    "years": {
                        "start_year": 1935,
                        "end_year": 1936
                    },
                    "organization": "Sthlm"
                },
                {
                    "position": "tandl komm",
                    "years": {
                        "start_year": 1936,
                        "end_year": 1946
                    },
                    "organization": "Själevad"
                },
                {
                    "position": "distr :tandl o förest distr :tandpol",
                    "years": {
                        "start_year": 1946
                    },
                    "organization": "Själevad"
                }
            ],
            "family": {
                "spouse": "Märta Fryklund",
                "marriage_year": "1936",
                "children": [
                    {
                        "name": "Carin",
                        "birth_year": "1938"
                    },
                    {
                        "name": "Eva",
                        "birth_year": "1941"
                    },
                    {
                        "name": "Harald",
                        "birth_year": "1947"
                    }
                ]
            }
        },
        "2": {
            "full_name": "A CLAES B NYLANDER",
            "location": "Hudiksvall",
            "occupation": "läroverksadjunkt",
            "birth_details": {
                "date": "16/02/1930",
                "place": "Sthlm",
                "parents": "Alf Nylander, Helny Söderdahl"
            },
            "education": [
                {
                    "degree": "Stud:ex",
                    "year": "1948",
                    "institution": "Karlskrona"
                },
                {
                    "degree": "fil mag",
                    "year": "1954",
                    "institution": "Sthlm"
                }
            ],
            "career": [
                {
                    "position": "e adj hal",
                    "years": {
                        "start_year": 1954,
                        "end_year": 1954
                    },
                    "organization": "Jönkpg"
                },
                {
                    "position": "Karol hal",
                    "years": {
                        "start_year": 1954,
                        "end_year": 1954
                    },
                    "organization": "Örebro"
                },
                {
                    "position": "Avesta hal",
                    "years": {
                        "start_year": 1957
                    },
                    "organization": null
                },
                {
                    "position": "adj i modersm o hist m samh :lära",
                    "years": {
                        "start_year": 1960
                    },
                    "organization": "Hudiksvalls hal"
                }
            ],
            "family": {
                "spouse": "Marianne Sjöberg",
                "marriage_year": "1965",
                "children": [
                    {
                        "name": "Johan",
                        "birth_year": "1965"
                    },
                    {
                        "name": "Margareta",
                        "birth_year": "1967"
                    }
                ]
            }
        },
        "3": {
            "full_name": "N INGVAR M NYLANDER",
            "location": "Umeå",
            "occupation": "professor, överläkare",
            "birth_details": {
                "date": "17/05/1922",
                "place": "Mariestad",
                "parents": "Martin Nylander, Emma Forsberg"
            },
            "education": [
                {
                    "degree": "Stud:ex",
                    "year": "1941",
                    "institution": "Uddevalla"
                },
                {
                    "degree": "med kand",
                    "year": "1941",
                    "institution": "Upps"
                },
                {
                    "degree": "med lic",
                    "year": "1948",
                    "institution": "Upps"
                },
                {
                    "degree": "med dr o doc i barnpsykiatri",
                    "year": "1960",
                    "institution": "Karol inst"
                }
            ],
            "career": [
                {
                    "position": "Bitr överläk",
                    "years": {
                        "start_year": 1957,
                        "end_year": 1963
                    },
                    "organization": "Kronpr Lovisas barnsjh Sthlm"
                },
                {
                    "position": "soc:läk",
                    "years": {
                        "start_year": 1964,
                        "end_year": 1965
                    },
                    "organization": "Sthlms stads barnav:nd"
                },
                {
                    "position": "överläk barnpsyk klin Umeå las",
                    "years": {
                        "start_year": 1966
                    },
                    "organization": null
                }
            ],
            "family": {
                "spouse": "Kerstin Andersson",
                "marriage_year": "1948",
                "children": [
                    {
                        "name": "Martin",
                        "birth_year": "1950"
                    },
                    {
                        "name": "Staffan",
                        "birth_year": "1954"
                    }
                ]
            }
        }
    }
}