{
    "original": "NORIN,   F   TORSTEN,    överläkare,\n\nGävle, f i Lima, Kopparb l, 17/6/23 av\nbyråch Folke N o Ebba Lindqvist.\nStud:ex Gbg 42, med kand 45 o med lic\nLund 49, underläk Jub-klin Sahlgr sjh\n49-61, överläk radioterap klin Gävle las\nsed 61. - Skr i radioterapi.\nGift 48 m fil lic Marianne Nilsson f 26,\ndtr t rekt Johan N o Gertrud Feuk. -\n\nBarn: Klas f 49, Wända f 52, Jonas f 56,\nAnnika f 61.\n\nNORINDER, CARL-ROBERT,\ndirektör, Kilafors, f i Sthlm 25/5/09 av\növerste Axel N o Maja Almström.\nStud:ex 28 o jur kand Sthlm 34, tingstjg\nTveta, Vista o Mo doms 34-37, tjg Svea\nhovr 37-38, sekr amiralitetsrådet\nmarin-förv 38-42, tjg o tf byråch FCF 42-47,\nverkst dir Kilafors jernv ab sed 47.\nGift 1) 40 m Inga-Britt Håkansson d 44,\n2) 45 m Anna Lisa Johansson, f Ahlgren,\nd 66, 3) 67 m Eva Kristina Tamm.\n- Barn: i l:a akt Patrik f 41, i 2:a akt\nÄnne Elisabeth f 47’. - Adoptivbarn: Ulf\nf 34, Birgitta f 38, Marie f 64.\n\nNORINDER, EGON  O W, med dr,\n\növerläkare, Ljusdal, f i Norrkpg 24/6/\n03 av lokomotivmäst Ernst N o Ellen\nJonsson.\n\nStud:ex Upps 22, med kand 26, med lic\n32 o med dr Upps 39; ass patol inst\nUpps 33, öl läk:förordn 32-35, underläk\nVanföreanst Härnösand 35-37, aman KK\nAkad sjh 37-41, underläk kir klin 41-45,\ntf överläk kir avd Uddevalla las 46,\nunderläk kir o med klin Sahlgr sjh 45-51,\növerläk o styresm Ljusdals las 51-56,\növerläk kir avd Sandvikens las 56-57\n(tji), överläk Ljusdals las sed 57. -\nBåt:-läk flk res sed 51. - Skr i kirurgi,\npatologi o gynekologi. - Utm: RNO. -\nHobbies: jakt, fiske, skidsport.\nGift 44 m med lic Ing-Marie Fagerberg\nf 13. - Barn: Hans f 45, Claes f 47, Erik\nf 50, Britt-Marie f 51.\n\nNORLÉN, E ARTHUR,\nlänsskolinspektör, Gävle, f i Bodum, Jämtl l, 16/5/\n05 av byggm August N o Augusta\nPålsson.\n\nFolkskollär:ex 28, folkskollär Resele 29,\növerlär Arbrå 43, folkskolinsp 51,\nläns-skolinsp Gävleb l sed 62. - Led stat\nkonstutredn 46-54, Sv:es radio-TV:s\nskol-komm, styr f Fören konst i skolan,\nHembygdsrådet i Gävle. - Medl\nTem-pelrO. - Skr lärob om slöjd,\nhembygdskunskap o konst m m. - Utm: RNO.\n-Hobbies: konst, botanik.\nGift 30 m Hildur Wikner. - Barn:\nSverker f 31, Margaretha f 35, Urban f 40.\n\nNORLÉN, BENGT A,\nlandstingsdirektör, Gävle, f i Ovansjö sn, Gävleb l,\n3/1/19 av stat:insp John N o Ida\nSundberg.\n\nStud:ex  Gävle 40, jur kand Upps 47,\ntingstjg Gästrikl ö doms, landst:dir\nGävleb l landst Gävle sed 59.\nGift 60 m Ann Kihlström f 36. - Barn:\nEva f 61, Jonas f 63.\n\nNORLÉN, GUNNAR A P,\nbankdirektör, Östersund, f i Brunflo, Jämtl l, 11/5/\n08 av banktjm Per N o Brita Nycander.\nRealex Östersund 26, tjm Jämtl folkbk\n29, v verkst dir där sed 54. - Medl\nFrim-O. - Hobby: friluftsliv.\nGift 40 m Gunnel Ewertz f 10, dtr t\nbokhåll Kristian E o Ruth Skoglund.\n-Barn: Per-Gunnar f 42, Elisabeth f 45,\nLars-Magnus f 47.\n\nNORLÉN, E A SVERKER,\navdelningschef, Umeå, f i Sollefteå 8/9/31 av\nlänsskolinsp Arthur N o Hildur Wikner.\nStud:ex Bollnäs 51, res:off:ex 54, jur pol\nmag Upps 57, aman SO 57, budgetsekr\nVästerb l landst 58, ch allm avd 62,\nsjv:-avd där sed 63. - Sekr regionsjv:ndn sed\n\n64,  led Umeå stud :kårs hälsov:styr sed\n\n65.  - Styr:led Akad fören Umeå sed 66.\n- Hobby: sport.\n\nGift 58 m Tora Sjömark, dtr t köpm\nAxel S o Lotten Öhlund. - Barn: Maria\nf 58, Carl Magnus f 62.\n\n",
    "structured": {
        "1": {
            "full_name": "Torsten Norin",
            "location": "Gävle",
            "occupation": "överläkare",
            "birth_details": {
                "date": "17/06/1923",
                "place": "Lima, Kopparbergs län",
                "parents": "Folke N o Ebba Lindqvist"
            },
            "education": [
                {
                    "degree": "Stud:ex",
                    "year": "1942",
                    "institution": "Gbg"
                },
                {
                    "degree": "med kand",
                    "year": "1945",
                    "institution": "NULL"
                },
                {
                    "degree": "med lic",
                    "year": "1949",
                    "institution": "Lund"
                }
            ],
            "career": [
                {
                    "position": "underläk Jub-klin Sahlgr sjh",
                    "years": {
                        "start_year": 1949,
                        "end_year": 1961
                    },
                    "organization": "NULL"
                },
                {
                    "position": "överläk radioterap klin Gävle las",
                    "years": {
                        "start_year": 1961,
                        "end_year": null
                    },
                    "organization": "NULL"
                }
            ],
            "family": {
                "spouse": "fil lic Marianne Nilsson",
                "marriage_year": "1948",
                "children": [
                    {
                        "name": "Klas",
                        "birth_year": "1949"
                    },
                    {
                        "name": "Wända",
                        "birth_year": "1952"
                    },
                    {
                        "name": "Jonas",
                        "birth_year": "1956"
                    },
                    {
                        "name": "Annika",
                        "birth_year": "1961"
                    }
                ]
            }
        },
        "2": {
            "full_name": "Carl-Robert Norinder",
            "location": "Kilafors",
            "occupation": "direktör",
            "birth_details": {
                "date": "25/05/1909",
                "place": "Sthlm",
                "parents": "överste Axel N o Maja Almström"
            },
            "education": [
                {
                    "degree": "Stud:ex",
                    "year": "1928",
                    "institution": "NULL"
                },
                {
                    "degree": "jur kand",
                    "year": "1934",
                    "institution": "Sthlm"
                }
            ],
            "career": [
                {
                    "position": "tingstjg Tveta, Vista o Mo doms",
                    "years": {
                        "start_year": 1934,
                        "end_year": 1937
                    },
                    "organization": "NULL"
                },
                {
                    "position": "verkst dir Kilafors jernv ab",
                    "years": {
                        "start_year": 1947,
                        "end_year": null
                    },
                    "organization": "NULL"
                }
            ],
            "family": {
                "spouse": "Inga-Britt Håkansson",
                "marriage_year": "1940",
                "children": [
                    {
                        "name": "Patrik",
                        "birth_year": "1941"
                    },
                    {
                        "name": "Änne Elisabeth",
                        "birth_year": "1947"
                    },
                    {
                        "name": "Ulf",
                        "birth_year": "1934"
                    },
                    {
                        "name": "Birgitta",
                        "birth_year": "1938"
                    },
                    {
                        "name": "Marie",
                        "birth_year": "1964"
                    }
                ]
            }
        },
        "3": {
            "full_name": "Egon W Norinder",
            "location": "Ljusdal",
            "occupation": "med dr, överläkare",
            "birth_details": {
                "date": "24/06/1903",
                "place": "Norrköping",
                "parents": "lokomotivmäst Ernst N o Ellen Jonsson"
            },
            "education": [
                {
                    "degree": "Stud:ex",
                    "year": "1922",
                    "institution": "Upps"
                },
                {
                    "degree": "med kand",
                    "year": "1926",
                    "institution": "NULL"
                },
                {
                    "degree": "med lic",
                    "year": "1932",
                    "institution": "NULL"
                },
                {
                    "degree": "med dr",
                    "year": "1939",
                    "institution": "Upps"
                }
            ],
            "career": [
                {
                    "position": "ass patol inst Upps",
                    "years": {
                        "start_year": 1933,
                        "end_year": null
                    },
                    "organization": "NULL"
                },
                {
                    "position": "överläk Ljusdals las",
                    "years": {
                        "start_year": 1957,
                        "end_year": null
                    },
                    "organization": "NULL"
                }
            ],
            "family": {
                "spouse": "med lic Ing-Marie Fagerberg",
                "marriage_year": "1944",
                "children": [
                    {
                        "name": "Hans",
                        "birth_year": "1945"
                    },
                    {
                        "name": "Claes",
                        "birth_year": "1947"
                    },
                    {
                        "name": "Erik",
                        "birth_year": "1950"
                    },
                    {
                        "name": "Britt-Marie",
                        "birth_year": "1951"
                    }
                ]
            },
            "hobbies": [
                "jakt",
                "fiske",
                "skidsport"
            ]
        },
        "4": {
            "full_name": "Arthur Norlén",
            "location": "Gävle",
            "occupation": "länsskolinspektör",
            "birth_details": {
                "date": "16/05/1905",
                "place": "Bodum, Jämtlands län",
                "parents": "byggm August N o Augusta Pålsson"
            },
            "education": [
                {
                    "degree": "Folkskollär:ex",
                    "year": "1928",
                    "institution": "NULL"
                }
            ],
            "career": [
                {
                    "position": "folkskollär Resele",
                    "years": {
                        "start_year": 1929,
                        "end_year": 1943
                    },
                    "organization": "NULL"
                },
                {
                    "position": "foksolinsp",
                    "years": {
                        "start_year": 1951,
                        "end_year": null
                    },
                    "organization": "NULL"
                }
            ],
            "family": {
                "spouse": "Hildur Wikner",
                "marriage_year": "1930",
                "children": [
                    {
                        "name": "Sverker",
                        "birth_year": "1931"
                    },
                    {
                        "name": "Margaretha",
                        "birth_year": "1935"
                    },
                    {
                        "name": "Urban",
                        "birth_year": "1940"
                    }
                ]
            },
            "community_involvement": [
                {
                    "role": "Led stat konstutredn",
                    "organization": "NULL",
                    "years": "1946-1954"
                },
                {
                    "role": "Sv:es radio-TV:s skol-komm",
                    "organization": "NULL",
                    "years": "NULL"
                }
            ],
            "honorary_titles": [
                {
                    "title": "RNO",
                    "institution": "NULL",
                    "year": "NULL"
                }
            ],
            "hobbies": [
                "konst",
                "botanik"
            ]
        },
        "5": {
            "full_name": "Bengt A Norlén",
            "location": "Gävle",
            "occupation": "landstingsdirektör",
            "birth_details": {
                "date": "3/1/1919",
                "place": "Ovansjö sn, Gävleborgs län",
                "parents": "stat:insp John N o Ida Sundberg"
            },
            "education": [
                {
                    "degree": "Stud:ex",
                    "year": "1940",
                    "institution": "Gävle"
                },
                {
                    "degree": "jur kand",
                    "year": "1947",
                    "institution": "Upps"
                }
            ],
            "career": [
                {
                    "position": "tingstjg Gästrikl ö doms",
                    "years": {
                        "start_year": "NULL",
                        "end_year": "NULL"
                    },
                    "organization": "NULL"
                },
                {
                    "position": "landst:dir",
                    "years": {
                        "start_year": 1959,
                        "end_year": null
                    },
                    "organization": "landst Gävle"
                }
            ],
            "family": {
                "spouse": "Ann Kihlström",
                "marriage_year": "1960",
                "children": [
                    {
                        "name": "Eva",
                        "birth_year": "1961"
                    },
                    {
                        "name": "Jonas",
                        "birth_year": "1963"
                    }
                ]
            }
        },
        "6": {
            "full_name": "Gunnar A P Norlén",
            "location": "Östersund",
            "occupation": "bankdirektör",
            "birth_details": {
                "date": "11/5/1908",
                "place": "Brunflo, Jämtlands län",
                "parents": "banktjm Per N o Brita Nycander"
            },
            "education": [
                {
                    "degree": "Realex",
                    "year": "1926",
                    "institution": "Östersund"
                }
            ],
            "career": [
                {
                    "position": "v verkst dir",
                    "years": {
                        "start_year": 1954,
                        "end_year": null
                    },
                    "organization": "Jämtl folkbk"
                }
            ],
            "family": {
                "spouse": "Gunnel Ewertz",
                "marriage_year": "1940",
                "children": [
                    {
                        "name": "Per-Gunnar",
                        "birth_year": "1942"
                    },
                    {
                        "name": "Elisabeth",
                        "birth_year": "1945"
                    },
                    {
                        "name": "Lars-Magnus",
                        "birth_year": "1947"
                    }
                ]
            },
            "hobbies": [
                "friluftsliv"
            ]
        },
        "7": {
            "full_name": "Sverker Norlén",
            "location": "Umeå",
            "occupation": "avdelningschef",
            "birth_details": {
                "date": "8/9/1931",
                "place": "Sollefteå",
                "parents": "länsskolinsp Arthur N o Hildur Wikner"
            },
            "education": [
                {
                    "degree": "Stud:ex",
                    "year": "1951",
                    "institution": "Bollnäs"
                },
                {
                    "degree": "res:off:ex",
                    "year": "1954",
                    "institution": "NULL"
                },
                {
                    "degree": "jur pol mag",
                    "year": "1957",
                    "institution": "Upps"
                }
            ],
            "career": [
                {
                    "position": "aman SO",
                    "years": {
                        "start_year": 1957,
                        "end_year": null
                    },
                    "organization": "NULL"
                },
                {
                    "position": "ch allm avd",
                    "years": {
                        "start_year": 1962,
                        "end_year": null
                    },
                    "organization": "Västerb l landst"
                }
            ],
            "family": {
                "spouse": "Tora Sjömark",
                "marriage_year": "1958",
                "children": [
                    {
                        "name": "Maria",
                        "birth_year": "1958"
                    },
                    {
                        "name": "Carl Magnus",
                        "birth_year": "1962"
                    }
                ]
            },
            "hobbies": [
                "sport"
            ]
        }
    }
}