{
    "original": "Jönsson, Arvid, disponent,\nHälsingborg, f. 1885 i Hälsingb. G. in. Bbbia\nMathilda Johnsison. Barn: Gustaf L.\nRingslbo f. 16, bryggm., Klippan, g. m.\nInger Qhristensen, Rut Margareta, g.\nm. fil. ’lic. Ingvar Bernunger,\n.Sandviken. — Amst. v. Ringstorps brygg.\n00, dtisp. v. Eisilövis brygg. 19, v. A-B\nSikånebrygg. i Hälsingb. 40, v. verks t.\ndiir. dlär fr. 44. Und. Eslövstid. inneh.\nett ifl’ert. komm. upip dr., fd.\nnämndeman i Esilöivs o. Frosta här. tingsl.\nhär : rätt.  P&gt;ro’Patrst GM.\n\nJönsson, Axel, (lektor, Malmö, f. 213/\n3/90 i Långaröd, Malmön. 1, av Jöns\nOlsson o. Hanna Persson. G. 21 an.\nGertrud Manning. Barn: Klas-Görian\ni. 27, Bo Axell 30. — .Stud:ex. i Lund\n09, tffil. nuag. 11, ful. lic. 13’, fil. dr 17.\nProvar i Lund 16. Stud. v. Miinchenis\nuniiv. 20, Göttingens und v. 23, Utrechts\nuniiv, 25. ’Observatör v. ’meteoro1!.\nob&lt;-serv. å Pårtetjåkko’ 14-15. E. o. lektor\ni Landskr. 17-20, lektor i Jonköp. 20,\nlektor i fysik o. matem. v. h. a. 1. i\nMalmö fr. 27. Lär. v. nav :isk, 29-33’, v.\nAlnarps h. mej :inst. 33-, v. Hvilaras\nfolikhög¾k. 31-3I3 o. v. Henmodls prep\n:-kurs. Skr.: ett tiotal aVh. o. a. skr. av\nfyslikail. o. astron. inneh. RNO 36.\n\nJönsson, Axel, fd.\nsparbaniksdirek-tör, Landskrona, if, 23/3/67 i Raus,\nMalmöih. 1., av gods fö rv. Per J. o.\nHelena Runnenströim. G. 96 m. Nanny\nBergellin. Barn: Kjell ’f. 97, v. konsul\ni Rouen, Seth 00, sjökapt., San\nFrancisco, Maja 06. — Skolstud. v.\nÄnged-hoilnis lärov. Eg. ifirma i Landskr.\n94-19, verksit. dlir. i Landskr. sparb. 19-38,\nled. av styr. där sed. 10, ordf. 38-44.\nLed. av kyrkoråd 10-35, av lok :styr. f.\nSkand.  Banken A-B  20-40,  av komm.\n\nf. Skånska Briandförsäkr :inrättn. i\nLund 22-37, kyrkans kassaförv. 16-34,\nled. av styr. if. Landskr. Teait. A-B\n36-47, Gjörloffska don -Jfond. RVO 36.\n\n",
    "structured": {
        "1": {
            "full_name": "Jönsson, Arvid",
            "location": "Hälsingborg",
            "occupation": "Disponent",
            "birth_details": {
                "date": "1885",
                "place": "Hälsingborg"
            },
            "family": {
                "spouse": "Bbbia Mathilda Johnsison",
                "marriage_year": "NULL",
                "children": [
                    {
                        "name": "Gustaf L. Ringslbo",
                        "birth_year": "16"
                    },
                    {
                        "name": "Rut Margareta",
                        "birth_year": "NULL"
                    }
                ]
            },
            "education": [],
            "career": [
                {
                    "position": "Amst. v. Ringstorps brygg. 00",
                    "years": {
                        "start_year": 19,
                        "end_year": 19
                    },
                    "organization": "NULL"
                },
                {
                    "position": "dtisp. v. Eisilövis brygg. 19",
                    "years": {
                        "start_year": 19,
                        "end_year": 19
                    },
                    "organization": "NULL"
                },
                {
                    "position": "v. A-B Sikånebrygg. i Hälsingb. 40",
                    "years": {
                        "start_year": 40,
                        "end_year": 40
                    },
                    "organization": "NULL"
                },
                {
                    "position": "v. verks t. diir. dlär fr. 44",
                    "years": {
                        "start_year": 44,
                        "end_year": 44
                    },
                    "organization": "NULL"
                },
                {
                    "position": "Und. Eslövstid. inneh. ett ifl’ert. komm. upip dr.",
                    "years": {
                        "start_year": "NULL",
                        "end_year": "NULL"
                    },
                    "organization": "NULL"
                }
            ]
        },
        "2": {
            "full_name": "Jönsson, Axel",
            "location": "Malmö",
            "occupation": "Lektor",
            "birth_details": {
                "date": "213/3/90",
                "place": "Långaröd, Malmön"
            },
            "family": {
                "spouse": "Gertrud Manning",
                "marriage_year": "21",
                "children": [
                    {
                        "name": "Klas-Görian",
                        "birth_year": "27"
                    },
                    {
                        "name": "Bo Axell",
                        "birth_year": "30"
                    }
                ]
            },
            "education": [
                {
                    "degree": "Stud:ex.",
                    "year": "09",
                    "institution": "Lund"
                },
                {
                    "degree": "tffil. nuag.",
                    "year": "11",
                    "institution": "NULL"
                },
                {
                    "degree": "ful. lic.",
                    "year": "13",
                    "institution": "NULL"
                },
                {
                    "degree": "fil. dr",
                    "year": "17",
                    "institution": "NULL"
                }
            ],
            "career": [
                {
                    "position": "E. o. lektor i Landskr. 17-20",
                    "years": {
                        "start_year": 17,
                        "end_year": 20
                    },
                    "organization": "NULL"
                },
                {
                    "position": "lektor i Jonköp. 20",
                    "years": {
                        "start_year": 20,
                        "end_year": 20
                    },
                    "organization": "NULL"
                },
                {
                    "position": "lektor i fysik o. matem. v. h. a. 1. i Malmö fr. 27",
                    "years": {
                        "start_year": 27,
                        "end_year": "NULL"
                    },
                    "organization": "NULL"
                }
            ]
        },
        "3": {
            "full_name": "Jönsson, Axel",
            "location": "Landskrona",
            "occupation": "fd. sparbaniksdirek-tör",
            "birth_details": {
                "date": "23/3/67",
                "place": "Raus, Malmöih. 1."
            },
            "family": {
                "spouse": "Nanny Bergellin",
                "marriage_year": "96",
                "children": [
                    {
                        "name": "Kjell",
                        "birth_year": "97"
                    },
                    {
                        "name": "Seth",
                        "birth_year": "00"
                    },
                    {
                        "name": "Maja",
                        "birth_year": "06"
                    }
                ]
            },
            "education": [],
            "career": [
                {
                    "position": "Eg. ifirma i Landskr. 94-19",
                    "years": {
                        "start_year": 94,
                        "end_year": 19
                    },
                    "organization": "NULL"
                },
                {
                    "position": "verksit. dlir. i Landskr. sparb. 19-38",
                    "years": {
                        "start_year": 19,
                        "end_year": 38
                    },
                    "organization": "NULL"
                },
                {
                    "position": "led. av styr. där sed. 10",
                    "years": {
                        "start_year": "NULL",
                        "end_year": "NULL"
                    },
                    "organization": "NULL"
                }
            ]
        }
    }
}