{
    "original": "ANDERSSON,   LARS   B,   tandläkare,\n\nÅrjäng, f i Malmö 25/11/34 av avd:ch\n\nArtur A o Helga Wendt.\n\nStud:ex 54, THM, distr:tandläk Årjäng\n\n59, priv prakt där sed 61. - Medl Lions\n\nInternational.   -   Hobbies:   fiske,   sport,\n\nfoto.\n\nGift 59 m sjuksköt Berit Skoog.\n\nANDERSSON, LÄRS-OLOV, direktör,\nSthlm o Upps, f i Upps 1/1/29 av\nlagerch Elon A o Nelly Österström.\nStud:ex Upps 47, Schartaus hdlI 53, jur\nkand Upps 55, tingstjg V Hälsingl doms\n55-57, omb :man Norrlandskraft ab 58,\nverkst dir SAR sed 60. - Hobbies:\netnografi, simsport.\n\nGift 51 m fil kand Sonja Friberg, dtr t\nanlägg Waldemar F o Aina Johansson.\n- Barn: Annika f 61.\nANDERSSON, MARGIT V, lektor,\nEskilstuna, f i Falkenberg 29/11/12 av\nmekaniker Evald A o Hanna Gustafsson.\nStud:ex 36, fil kand 41, fil lic 44, TLS\nkurs f ind :bibl 49, fil mag 57. - Aman\nBotan lab Lund 40 o 42-44, Stat centr\nf rö kontr :anst 46-49, vik ind :bibl Skånska\ncement ab 50, lärartjg Ystad 44 o 52-55,\nHöör o Falkenberg 57, folksk:sem\nLandskrona 58-59, lekt hal Eskilstuna\nsed 59. - Skr: Einige\nernärungsphysio-logische Versuche mit Ulva und\nEntero-morpha (42), Zur Kenntnis der\nStich-stoffquellen von Ulva und\nEnteromor-pha (43). - Hobbies: musik, friluftsliv.\n\nANDERSSON, NILS, fd länsveterinär,\nKarlstad, f i Västerstad, Malmöh l, 13/7/\n94 av lantbr Anders Håkansson o\nKristina Friberg.\n\nStud:ex Lund 14, vet :ex Sthlm 18,\nprivatprakt o div vik 19-28, distr :veterinär\nEmmaboda 28, Hemse 30, länsveterinär\nVärml l 43-60, besiktn :veterinär Grums\n59-63. - Ordf Värml allm\ndjurskydds-fören 44, styr :led Värml l hälsov:förb\n43-60, sekr Sv länsvet:fören 45-57.\n-Medl FrimO 29, Rotary 46. - Skr: art\növer djurskyddsproblem,\nlivsmedelshygien o vissa djursjukdomar i fackpress.\n-Utm: RVO, Sv:es djursk:fören GM,\nVärml l hälsov:förb GM, SRKSM.\nGift 19 m Vanda Möller f 97, dtr t\ngodsarrend Gottfrid M o Amalia\nNyström. - Barn: Lars f 19, Bengt f 23,\nMaj o Ulla f f 31.\n\n",
    "structured": {
        "1": {
            "full_name": "Lars B Andersson",
            "location": "Årjäng",
            "occupation": "Tandläkare",
            "birth_details": {
                "date": "25/11/1934",
                "place": "Malmö",
                "parents": "Artur A o Helga Wendt"
            },
            "education": [
                {
                    "degree": "Stud:ex",
                    "year": "1954",
                    "institution": "THM"
                },
                {
                    "degree": "Distr:tandläk",
                    "year": "1959",
                    "institution": "Årjäng"
                }
            ],
            "career": [
                {
                    "position": "Priv prakt",
                    "years": {
                        "start_year": 1961
                    },
                    "organization": "Årjäng"
                }
            ],
            "family": {
                "spouse": "Berit Skoog",
                "marriage_year": "1959",
                "children": [],
                "parents": null
            },
            "hobbies": [
                "Fiske",
                "Sport",
                "Foto"
            ]
        },
        "2": {
            "full_name": "Lärs-Olov Andersson",
            "location": "Sthlm o Upps",
            "occupation": "Direktör",
            "birth_details": {
                "date": "1/1/1929",
                "place": "Upps"
            },
            "education": [
                {
                    "degree": "Stud:ex",
                    "year": "1947",
                    "institution": "Upps"
                },
                {
                    "degree": "Schartaus hdlI",
                    "year": "1953",
                    "institution": null
                },
                {
                    "degree": "Jur kand",
                    "year": "1955",
                    "institution": "Upps"
                }
            ],
            "career": [
                {
                    "position": "Tingstjg V Hälsingl doms",
                    "years": {
                        "start_year": 1955,
                        "end_year": 1957
                    },
                    "organization": null
                },
                {
                    "position": "Omb :man",
                    "years": {
                        "start_year": 1958
                    },
                    "organization": "Norrlandskraft ab"
                },
                {
                    "position": "Verkst dir SAR",
                    "years": {
                        "start_year": 1960
                    },
                    "organization": null
                }
            ],
            "family": {
                "spouse": "Sonja Friberg",
                "marriage_year": "1951",
                "children": [
                    {
                        "name": "Annika",
                        "birth_year": "1961"
                    }
                ],
                "parents": null
            },
            "hobbies": [
                "Etnografi",
                "Simsport"
            ]
        },
        "3": {
            "full_name": "Margit V Andersson",
            "location": "Eskilstuna",
            "occupation": "Lektor",
            "birth_details": {
                "date": "29/11/1912",
                "place": "Falkenberg",
                "parents": "Evald A o Hanna Gustafsson"
            },
            "education": [
                {
                    "degree": "Stud:ex",
                    "year": "1936",
                    "institution": null
                },
                {
                    "degree": "Fil kand",
                    "year": "1941",
                    "institution": null
                },
                {
                    "degree": "Fil lic",
                    "year": "1944",
                    "institution": null
                },
                {
                    "degree": "TLS kurs f ind :bibl",
                    "year": "1949",
                    "institution": null
                },
                {
                    "degree": "Fil mag",
                    "year": "1957",
                    "institution": null
                }
            ],
            "career": [
                {
                    "position": "Aman Botan lab Lund",
                    "years": {
                        "start_year": 1940,
                        "end_year": 1940
                    },
                    "organization": null
                },
                {
                    "position": "Stat centr f rö kontr :anst",
                    "years": {
                        "start_year": 1946,
                        "end_year": 1949
                    },
                    "organization": null
                },
                {
                    "position": "Vik ind :bibl Skånska cement ab",
                    "years": {
                        "start_year": 1950,
                        "end_year": 1950
                    },
                    "organization": null
                },
                {
                    "position": "Lärartjg",
                    "years": {
                        "start_year": 1952,
                        "end_year": 1955
                    },
                    "organization": "Ystad"
                },
                {
                    "position": "Lekt hal",
                    "years": {
                        "start_year": 1959,
                        "end_year": null
                    },
                    "organization": "Eskilstuna"
                }
            ],
            "family": {
                "spouse": null,
                "marriage_year": null,
                "children": [],
                "parents": null
            },
            "hobbies": [
                "Musik",
                "Friluftsliv"
            ]
        },
        "4": {
            "full_name": "Nils Andersson",
            "location": "Karlstad",
            "occupation": "Före detta länsveterinär",
            "birth_details": {
                "date": "13/07/1894",
                "place": "Västerstad, Malmö l",
                "parents": "Anders Håkansson o Kristina Friberg"
            },
            "education": [
                {
                    "degree": "Stud:ex",
                    "year": "1914",
                    "institution": "Lund"
                },
                {
                    "degree": "Vet :ex",
                    "year": "1918",
                    "institution": "Sthlm"
                }
            ],
            "career": [
                {
                    "position": "Privatprakt o div vik",
                    "years": {
                        "start_year": 1919,
                        "end_year": 1928
                    },
                    "organization": null
                },
                {
                    "position": "Distr :veterinär",
                    "years": {
                        "start_year": 1928,
                        "end_year": 1930
                    },
                    "organization": "Emmaboda"
                },
                {
                    "position": "Hemse",
                    "years": {
                        "start_year": 1930,
                        "end_year": null
                    },
                    "organization": null
                },
                {
                    "position": "Länsveterinär",
                    "years": {
                        "start_year": 1943,
                        "end_year": 1960
                    },
                    "organization": "Värml l"
                },
                {
                    "position": "Besiktn :veterinär Grums",
                    "years": {
                        "start_year": 1959,
                        "end_year": 1963
                    },
                    "organization": null
                }
            ],
            "family": {
                "spouse": "Vanda Möller",
                "marriage_year": "1919",
                "children": [
                    {
                        "name": "Lars",
                        "birth_year": "1919"
                    },
                    {
                        "name": "Bengt",
                        "birth_year": "1923"
                    },
                    {
                        "name": "Maj",
                        "birth_year": "1931"
                    },
                    {
                        "name": "Ulla f",
                        "birth_year": "1931"
                    }
                ],
                "parents": null
            },
            "hobbies": null
        }
    }
}