{
    "original": "AAGESEN, GUNNAR W D, överläkare, \nEskilstuna, f i Gbg 3/5/20 av dir\nWilhelm A o Dagmar Christensen.\n\nStud:ex Gbg 40, med kand Upps 44,\nmed lic 49, ol läk:förordn 48-49, underläk \nkir avd Nykpgs las 50, med avd 54,\nunderläk anestesiavd I Sahlgr sjh 54,\növerläk anestesiavd Eskilstuna las sed\n57. - Sekr Södermani l läk:fören, medl\nSHT, Rotary.\n\nGift 49 m Lilleba Munther f 20, dtr t\nGustaf M o Ebba Fermæus. - Barn:\nBertil f 50, Eva f 52, Karin o Magnus\nff 54.\n\nAALTO, BENGT A, provinsialläkare,\nDeje, f i Sthlm 9/6/18 av skräddarn\nHugo A o Jenny Johansson.\n\nStud:ex Sthlm 37, med kand 41, med\nlic 47, vik underläk med avd Kalmar\nlas o Köpings las 47, vik underläk o 1:e\nunderläk Säffle las 48, stadsläk Hagfors\n52, prov:läk Deje sed 60. - Medl\nbarnav:nd, nykterh:nd o hälsov:nd.\n\nGift 46 m Cajsy Löf f 21, dtr t\nlinjemäst Helmer L o Ebba Renström.\n\nAALTO-SETÄLÄ, PEKKA s, dipiomingenjör, \nLudvika, f i Hirvensalmi, Finl,\n20/7/28 av folkskollär Yrjö A-S o Impi\nBreitholtz.\n\nStud:ex 47, diploming FTH 53, ing Asea\nVästerås 54, avd:ch Gadelius &amp; Co Ltd\nKobe Japan 57, ing Asea Hfors 61,\nanläggn:ing strömriktarbyrån Asea \nLudvika sed 61. - Hobbies: språk,\nträdgårdsskötsel.\n\nGift 49 m Maija Lindholm f 27, dtr t\nred Sigge L o Olga Tuominen. - Barn:\nPirjo f 50, Elli f 56.\n\nAANES, MARVIN, civilingenjör,\nVästerås, f i Norge 25 av entrepr Olaf A o\nIngeborg Andersen.\n\nNTH 51, anst a/s Glommens träsliperi\n52, beräkn:ing Asea 55, pat:ing där.\n\nGift 52 m Ruth Andersen f 22, dtr t\nsjökapt Anton A. - Barn: Brynhild f 53,\nÖivind f 56.\n\n",
    "structured": {
        "0": {
            "full_name": "Aagesen, Gunnar W D",
            "location": "Eskilstuna",
            "occupation": "Överläkare",
            "birth_details": {
                "date": "03/05/1920",
                "place": "Göteborg",
                "parents": "dir Wilhelm A o Dagmar Christensen"
            },
            "education": [
                {
                    "degree": "Stud:ex",
                    "year": "1940",
                    "institution": "Göteborg"
                },
                {
                    "degree": "Med kand",
                    "year": "1944",
                    "institution": "Uppsala"
                },
                {
                    "degree": "Med lic",
                    "year": "1949",
                    "institution": "NULL"
                }
            ],
            "career": [
                {
                    "position": "Oltraek",
                    "years": {
                        "start_year": 1957,
                        "end_year": 1957
                    },
                    "organization": "Eskilstuna las"
                }
            ],
            "family": {
                "spouse": "Lilleba Munther",
                "marriage_year": "1949",
                "children": [
                    {
                        "name": "Bertil",
                        "birth_year": "1950"
                    },
                    {
                        "name": "Eva",
                        "birth_year": "1952"
                    },
                    {
                        "name": "Karin",
                        "birth_year": "1954"
                    },
                    {
                        "name": "Magnus",
                        "birth_year": "1954"
                    }
                ]
            }
        },
        "1": {
            "full_name": "Aalto, Bengt A",
            "location": "Deje",
            "occupation": "Provinsialläkare",
            "birth_details": {
                "date": "09/06/1918",
                "place": "Stockholm",
                "parents": "skräddarn Hugo A o Jenny Johansson"
            },
            "education": [
                {
                    "degree": "Stud:ex",
                    "year": "1937",
                    "institution": "Stockholm"
                },
                {
                    "degree": "Med kand",
                    "year": "1941",
                    "institution": "NULL"
                },
                {
                    "degree": "Med lic",
                    "year": "1947",
                    "institution": "NULL"
                }
            ],
            "career": [
                {
                    "position": "Stadsläk",
                    "years": {
                        "start_year": 1952,
                        "end_year": 1952
                    },
                    "organization": "Hagfors"
                },
                {
                    "position": "Prov:läk",
                    "years": {
                        "start_year": 1960,
                        "end_year": 1960
                    },
                    "organization": "Deje"
                }
            ],
            "family": {
                "spouse": "Cajsy Löf",
                "marriage_year": "1946",
                "children": []
            }
        },
        "2": {
            "full_name": "Aalto-Setälä, Pekka S",
            "location": "Ludvika",
            "occupation": "Dipiomingenjör",
            "birth_details": {
                "date": "20/07/1928",
                "place": "Hirvensalmi, Finland",
                "parents": "folkskollär Yrjö A-S o Impi Breitholtz"
            },
            "education": [
                {
                    "degree": "Stud:ex",
                    "year": "1947",
                    "institution": "NULL"
                },
                {
                    "degree": "Diploming",
                    "year": "1953",
                    "institution": "FTH"
                },
                {
                    "degree": "Ing",
                    "year": "1954",
                    "institution": "Asea Västerås"
                }
            ],
            "career": [
                {
                    "position": "Anläggn:ing",
                    "years": {
                        "start_year": 1961,
                        "end_year": 1961
                    },
                    "organization": "Asea Ludvika"
                }
            ],
            "family": {
                "spouse": "Maija Lindholm",
                "marriage_year": "1949",
                "children": [
                    {
                        "name": "Pirjo",
                        "birth_year": "1950"
                    },
                    {
                        "name": "Elli",
                        "birth_year": "1956"
                    }
                ]
            }
        },
        "3": {
            "full_name": "Aanes, Marvin",
            "location": "Västerås",
            "occupation": "Civilingenjör",
            "birth_details": {
                "date": "25/NULL",
                "place": "Norge",
                "parents": "entrepr Olaf A o Ingeborg Andersen"
            },
            "education": [
                {
                    "degree": "NTH",
                    "year": "1951",
                    "institution": "NULL"
                }
            ],
            "career": [
                {
                    "position": "Pat:ing",
                    "years": {
                        "start_year": 1955,
                        "end_year": 1955
                    },
                    "organization": "NULL"
                }
            ],
            "family": {
                "spouse": "Ruth Andersen",
                "marriage_year": "1952",
                "children": [
                    {
                        "name": "Brynhild",
                        "birth_year": "1953"
                    },
                    {
                        "name": "Öivind",
                        "birth_year": "1956"
                    }
                ]
            }
        }
    }
}