{
    "original": "ALEMAN, ULLA E F, överläkare,\nSödertälje, f i Växjö 15/5/18 av överläk\nViktor Henrikson o Anna Rydberg.\nStud:ex Eskilstuna 36, med kand Sthlm\n39, med lic 45. - Ol underläk :förordn\n41-45, 2:e underläk kir avd Sabbatsb sjh\n46, med avd S:t Görans sjh 48,\nanestesi-avd Sabbatsb sjh 49, kir avd Södertälje\nlas 50, l:e underläk KK Sabbatsb sjh\n53, tf underläk o med :styr stip\nanestesi-avd Karol sjh 54, l:e underläk\nanestesi-avd S:t Görans sjh 55, överläk\nanestesi-avd Södertälje las sed 57. - Medl Sv\nanestesiolog fören, Sv kir :f ören.\nGift 45 m l:e byråinsp Allan Aleman\nf 13. - Barn: Louise f 45, Héléne f 48,\nMarie f 50, Charlotte f 52.\n\nALESTIG,   GÖSTA  A,  rektor,\nKarlstad, f i Åmål 22/5/21 av byggm Ludvig\nA o Ragnhild Johansson.\nStud:ex Karlstad 40, fil kand Upps 46,\nfil mag 47,  ol  lär:förordn 47-53,  rekt\nKarlstads hdlsgymn sed 53.\nGift 51 m Gunvor Holm f 28, dtr t past\nSam H o Signe H. - Barn: Göran f 53,\nInger f 55, Merit f 60.\n\nALESTIG, L RUNE I, civilingenjör,\nKristinehamn, f i Åmål 19/3/24 av\nbyggmäst Ludvig A o Ragnhild Johansson.\nCTH 49, ing SAAB 49, turbinlab ab\nKarlstads mek verkst sed 55. - Hobby:\nfiske.\n\nGift 49 m Gerthie Carlsson f 25, dtr t\nsjökapt Wilhelm C o Agnes Dahlström.\n- Barn: Kerstin f 53, Barbro f 56.\n\nALEXANDERSON, CARL H H,\növeringenjör, Oxelösund, f i Bogsta,\nSödermani l, 7/12/17 av förv Hugo A o Emma\nJohansson.\n\nStud:ex Sthlm 37, KTH 43, anst VV:styr\nbrobyrå 43, jv:styr bantekn byrå 44,\narb :markn :komm 45, konstr :avd\nSandvikens jernverk 46, övering o ch\nny-byggn:- o underhållsavd där 54, övering\no ch anläggn:avd Oxelösunds järnverk\nTGO sed 57. - Led nybyggn Sandvikens\njernv USA 53-54, Engl 55-57. - Led\nutredn ang konsumtion av byggn :virke\n45 (konj :inst), 45 års bensinskatteutredn\n(f in :dep); led kyrkofullm Sandviken,\nsuppl drätselkamm där 50-57. - Medl\nFrimO.\n\nGift m Astrid Palmeth f 17, dtr t ing\nArne P o Kate Callerström. - Barn:\nMonica f 38, Kerstin f 43, Helene f 48.\n\n",
    "structured": {
        "1": {
            "full_name": "Ulla E F Aleman",
            "location": "Södertälje",
            "occupation": "överläkare",
            "birth_details": {
                "date": "15/05/1918",
                "place": "Växjö",
                "parents": "överläk Viktor Henrikson o Anna Rydberg"
            },
            "education": [
                {
                    "degree": "Stud:ex",
                    "year": "1936",
                    "institution": "Eskilstuna"
                },
                {
                    "degree": "med kand",
                    "year": "1939",
                    "institution": "Sthlm"
                },
                {
                    "degree": "med lic",
                    "year": "1945",
                    "institution": "NULL"
                }
            ],
            "career": [
                {
                    "position": "Ol underläk :förordn",
                    "years": {
                        "start_year": 1941,
                        "end_year": 1945
                    },
                    "organization": "NULL"
                },
                {
                    "position": "2:e underläk kir avd",
                    "years": {
                        "start_year": 1946,
                        "end_year": 1948
                    },
                    "organization": "Sabbatsb sjh"
                },
                {
                    "position": "NULL",
                    "years": {
                        "start_year": 1949,
                        "end_year": 1950
                    },
                    "organization": "S:t Görans sjh"
                },
                {
                    "position": "NULL",
                    "years": {
                        "start_year": 1950,
                        "end_year": 1953
                    },
                    "organization": "Södertälje las"
                },
                {
                    "position": "NULL",
                    "years": {
                        "start_year": 1953,
                        "end_year": 1954
                    },
                    "organization": "NULL"
                },
                {
                    "position": "NULL",
                    "years": {
                        "start_year": 1954,
                        "end_year": 1955
                    },
                    "organization": "S:t Görans sjh"
                },
                {
                    "position": "NULL",
                    "years": {
                        "start_year": 1955,
                        "end_year": 1957
                    },
                    "organization": "Södertälje las"
                }
            ],
            "family": {
                "spouse": "l:e byråinsp Allan Aleman",
                "marriage_year": "1945",
                "children": [
                    {
                        "name": "Louise",
                        "birth_year": "1945"
                    },
                    {
                        "name": "Héléne",
                        "birth_year": "1948"
                    },
                    {
                        "name": "Marie",
                        "birth_year": "1950"
                    },
                    {
                        "name": "Charlotte",
                        "birth_year": "1952"
                    }
                ]
            }
        },
        "2": {
            "full_name": "Gösta A Alestig",
            "location": "Karlstad",
            "occupation": "rektor",
            "birth_details": {
                "date": "22/05/1921",
                "place": "Åmål",
                "parents": "byggm Ludvig A o Ragnhild Johansson"
            },
            "education": [
                {
                    "degree": "Stud:ex",
                    "year": "1940",
                    "institution": "Karlstad"
                },
                {
                    "degree": "fil kand",
                    "year": "1946",
                    "institution": "Upps"
                },
                {
                    "degree": "fil mag",
                    "year": "1947",
                    "institution": "NULL"
                }
            ],
            "career": [
                {
                    "position": "ol lär:förordn",
                    "years": {
                        "start_year": 1947,
                        "end_year": 1953
                    },
                    "organization": "NULL"
                }
            ],
            "family": {
                "spouse": "Gunvor Holm",
                "marriage_year": "1951",
                "children": [
                    {
                        "name": "Göran",
                        "birth_year": "1953"
                    },
                    {
                        "name": "Inger",
                        "birth_year": "1955"
                    },
                    {
                        "name": "Merit",
                        "birth_year": "1960"
                    }
                ]
            }
        },
        "3": {
            "full_name": "L Rune I Alestig",
            "location": "Kristinehamn",
            "occupation": "civilingenjör",
            "birth_details": {
                "date": "19/03/1924",
                "place": "Åmål",
                "parents": "byggmäst Ludvig A o Ragnhild Johansson"
            },
            "education": [
                {
                    "degree": "CTH",
                    "year": "1949",
                    "institution": "NULL"
                },
                {
                    "degree": "ing SAAB",
                    "year": "1949",
                    "institution": "NULL"
                }
            ],
            "career": [
                {
                    "position": "turbinlab ab Karlstads mek verkst",
                    "years": {
                        "start_year": 1955,
                        "end_year": 1955
                    },
                    "organization": "NULL"
                }
            ],
            "family": {
                "spouse": "Gerthie Carlsson",
                "marriage_year": "1949",
                "children": [
                    {
                        "name": "Kerstin",
                        "birth_year": "1953"
                    },
                    {
                        "name": "Barbro",
                        "birth_year": "1956"
                    }
                ]
            },
            "hobbies": [
                "fiske"
            ]
        },
        "4": {
            "full_name": "Carl H H Alexanderson",
            "location": "Oxelösund",
            "occupation": "överingenjör",
            "birth_details": {
                "date": "07/12/1917",
                "place": "Bogsta, Södermani l",
                "parents": "förv Hugo A o Emma Johansson"
            },
            "education": [
                {
                    "degree": "Stud:ex",
                    "year": "1937",
                    "institution": "Sthlm"
                },
                {
                    "degree": "KTH",
                    "year": "1943",
                    "institution": "NULL"
                }
            ],
            "career": [
                {
                    "position": "NULL",
                    "years": {
                        "start_year": 1957,
                        "end_year": 1957
                    },
                    "organization": "Oxelösunds järnverk TGO"
                }
            ],
            "family": {
                "spouse": "Astrid Palmeth",
                "marriage_year": "NULL",
                "children": [
                    {
                        "name": "Monica",
                        "birth_year": "1938"
                    },
                    {
                        "name": "Kerstin",
                        "birth_year": "1943"
                    },
                    {
                        "name": "Helene",
                        "birth_year": "1948"
                    }
                ]
            },
            "community_involvement": [
                {
                    "role": "Led kyrkofullm",
                    "organization": "Sandviken",
                    "years": "1950-1957"
                }
            ],
            "board_memberships": [
                {
                    "position": "suppl drätselkamm",
                    "organization": "Sandviken",
                    "years": "1950-1957"
                }
            ],
            "honorary_titles": [
                {
                    "title": "Medl FrimO",
                    "institution": "NULL",
                    "year": "NULL"
                }
            ],
            "hobbies": [
                "NULL"
            ]
        }
    }
}