{
    "original": "ANDERLING, A NATAN,\nfolkhögskolerektor, Vagnhärad, f i Eritrea,\nAfrika, 4/8/08 av miss:past August\nAndersson o folkskollär Octavia Lindström.\nStud:ex 28, agr:ex 32, res:off:ex 41, fil\nkand 45, aman KLH 34, ämneslär Sör-\n\nängens folkhögsk 36, Stensunds\nfolkhögsk 50, rektor där sed 54. - Inneh\ngård i Hökerum. - Ordf Trosa\nABF-avd 53, styr:led Sörml ABF-distr 55, Sv\nfrisksp:förb 52. - Hobbies: sport, fiske,\nfotografering.\n\nGift 59 m Gerd Svensson f 26, dtr t\njvtjm Karl S o Inez Larsson. - Barn:\nGunnar f 60, Lena f 62.\n\nANDERMAN, J ENOK,\nsocialvårdschef, Sala, f i Skogs förs, Gävleb l,\n6/12/13 av diakon Johan Andersson o\nWilhelmina Ekvall.\n\nDiakon 40, DSI 41, soc:ass Sthlm o\nUpps 41-43, soc:omb:man Hällefors 44,\nsoc:v:ch Sala sed 47. - Led dir f\nSal-berga sjh, anst:ndn v fångy:kolonien\nHyttan. - Medl TR.\nGift 44 m Karin Edén, dtr t jvtjm Johan\nE o Elin Rask.\n\nANDERMAN, GUNNAR J,\nkyrkoherde, Odensala, f i Skog, Gävleb l,\n28/3/04 av diakon Johan Andersson o\nWilhelmina Ekvall.\n\nStud:ex Fjellstedtska sk Upps 29, teol\nkand där 32, prästv 33, kyrkoadj\nBjuråker 35, kommin Lingbo 36, Valbo\n42-58, tf kyrkoh Knivsta 55, kyrkoh\nOdensala o Husby-Ärlmghundra sed 58.\n-Led stiftsrådet sed 62, ordf\nkyrkostämma o församl :deleg 58, kyrkoråd 64,\nled barnav:nd 58.\n\nGift 36 m Alma Sandström f 04, dtr t\nmejerist Axel S o Ida Andersdtr. - Barn:\nStaffan f 37, Bengt f 39, Tomas f 42,\nPer f 45.\n\n",
    "structured": {
        "1": {
            "full_name": "ANDERLING, A NATAN",
            "location": "Vagnhärad",
            "occupation": "folkhögskolerektor",
            "birth_details": {
                "date": "04/08/1908",
                "place": "Eritrea, Afrika",
                "parents": "miss:past August Andersson o folkskollär Octavia Lindström"
            },
            "education": [
                {
                    "degree": "Stud:ex",
                    "year": "1928",
                    "institution": "NULL"
                },
                {
                    "degree": "agr:ex",
                    "year": "1932",
                    "institution": "NULL"
                },
                {
                    "degree": "res:off:ex",
                    "year": "1941",
                    "institution": "NULL"
                },
                {
                    "degree": "filosofie kandidat",
                    "year": "1945",
                    "institution": "NULL"
                },
                {
                    "degree": "aman KLH",
                    "year": "1934",
                    "institution": "NULL"
                },
                {
                    "degree": "ämneslär Sörängens folkhögsk",
                    "year": "1936",
                    "institution": "NULL"
                },
                {
                    "degree": "NULL",
                    "year": "NULL",
                    "institution": "Stensunds folkhögsk"
                }
            ],
            "career": [
                {
                    "position": "rektor",
                    "years": {
                        "start_year": 1954,
                        "end_year": null
                    },
                    "organization": "Stensunds folkhögsk"
                }
            ],
            "family": {
                "spouse": "Gerd Svensson",
                "marriage_year": "1959",
                "children": [
                    {
                        "name": "Gunnar",
                        "birth_year": "1960"
                    },
                    {
                        "name": "Lena",
                        "birth_year": "1962"
                    }
                ]
            },
            "hobbies": [
                "sport",
                "fiske",
                "fotografering"
            ]
        },
        "2": {
            "full_name": "ANDERMAN, J ENOK",
            "location": "Sala",
            "occupation": "socialvårdschef",
            "birth_details": {
                "date": "06/12/1913",
                "place": "Skogs förs, Gävleb l",
                "parents": "diakon Johan Andersson o Wilhelmina Ekvall"
            },
            "education": [
                {
                    "degree": "NULL",
                    "year": "NULL",
                    "institution": "NULL"
                }
            ],
            "career": [
                {
                    "position": "soc:v:ch",
                    "years": {
                        "start_year": 1947,
                        "end_year": null
                    },
                    "organization": "Sala"
                }
            ],
            "family": {
                "spouse": "Karin Edén",
                "marriage_year": "1944",
                "children": []
            },
            "hobbies": []
        },
        "3": {
            "full_name": "ANDERMAN, GUNNAR J",
            "location": "Odensala",
            "occupation": "kyrkoherde",
            "birth_details": {
                "date": "28/03/1904",
                "place": "Skog, Gävleb l",
                "parents": "diakon Johan Andersson o Wilhelmina Ekvall"
            },
            "education": [
                {
                    "degree": "Stud:ex",
                    "year": "1929",
                    "institution": "Fjellstedtska sk Upps"
                },
                {
                    "degree": "teol kand",
                    "year": "1932",
                    "institution": "Fjellstedtska sk Upps"
                }
            ],
            "career": [
                {
                    "position": "kyrkoh",
                    "years": {
                        "start_year": 1958,
                        "end_year": null
                    },
                    "organization": "Odensala o Husby-Ärlmghundra"
                },
                {
                    "position": "tf kyrkoh",
                    "years": {
                        "start_year": 1955,
                        "end_year": null
                    },
                    "organization": "Knivsta"
                }
            ],
            "family": {
                "spouse": "Alma Sandström",
                "marriage_year": "1936",
                "children": [
                    {
                        "name": "Staffan",
                        "birth_year": "1937"
                    },
                    {
                        "name": "Bengt",
                        "birth_year": "1939"
                    },
                    {
                        "name": "Tomas",
                        "birth_year": "1942"
                    },
                    {
                        "name": "Per",
                        "birth_year": "1945"
                    }
                ]
            },
            "hobbies": []
        }
    }
}