{
    "original": "ANDERSSON, HUGO T, direktör,\nEskilstuna, f i Råby-Rekarne, Södermani\nl, 3/1/82 av snickare Karl A o Ida\nRydstedt.\n\nAnst Munktells mek verkst 96-11, verkst\ndir o inneh Eskilstuna gjut ab sed 11.\n-Medl TR, missionsförs. - Utm: RVO.\n-Hobby: sommarstuga.\nGift 1) 06 m Hulda Hellberg, dtr t\nmöbelh Lars H o Karolina H, 2) 43 m\n\nJenny Andersson. - Barn: Hugo f 07,\nAina f 12.\n\nANDERSSON, IVAN F, kamrer,\nSödertälje, f i Södertälje 26/10/16 av\nme-tallarb Filip A o Lovisa Johansson.\nKorresp :stud, anst ab Astra Södertälje\n36, finansier:ch där sed 63. - Medl S:ta\nRagnhilds gille.  - Hobby: friluftsliv.\nGift 42 m Signe Eriksson f 19, dtr t\nelektr Axel E o Ellen Larsson. - Barn:\nLärs-Gunnar f 44.\n\nANDERSSON, JOHN A, skogvaktare,\nInsjön, f i Forsand, Norge, 5/7/20 av\nstenarb Fritjof A o Johanne A.\nSkogssk Skinnskatteberg o no skogssk\nInsjön 44-45, e länsskogvakt skogsv:styr\nFalun 45, stämpl:förman där 47,\nskog-vakt Dalarnas skogsäg:fören upa\nFalun sed 60. - Hobbies: trädgårdsskötsel,\nfiske.\n\nGift 53 m Valborg Roligs f 25, dtr t\nflottn :förman Roligs Daniel Andersson\no Karin Larsdtr. - Barn: Britt-Marie f\n54, Christina f 58, Lärs-Olov f 62.\n\nANDERSSON, JOHN S L, direktör,\nSala, f i Sala 10/3/19 av fabr J Aug A\no Elin Andersson.\n\nBygg:ing:ex TI 38, dir o inneh John\nAnderssons bil ab, Sala sed 54. - Medl\nOdd Fellow. - Hobby: motorsport.\nGift 44 m Anna-Lisa Nord f 14, dtr t\nkyrkoh Carl Axel N o Anna Edlund.\n-Barn: Bengt Åke f 48, Lars Ove f 52.\n\n",
    "structured": {
        "0": {
            "full_name": "Hugo T Andersson",
            "location": "Eskilstuna",
            "occupation": "direktör",
            "birth_details": {
                "date": "03/01/1882",
                "place": "Råby-Rekarne, Södermanland",
                "parents": "snickare Karl A o Ida Rydstedt"
            },
            "education": [
                {
                    "degree": "NULL",
                    "year": "NULL",
                    "institution": "Munktells mek verkst 96-11"
                }
            ],
            "career": [
                {
                    "position": "verkst dir",
                    "years": {
                        "start_year": 1911,
                        "end_year": "NULL"
                    },
                    "organization": "Eskilstuna gjut ab"
                }
            ],
            "family": {
                "spouse": "Jenny Andersson",
                "marriage_year": "1943",
                "children": [
                    {
                        "name": "Hugo",
                        "birth_year": "1907"
                    },
                    {
                        "name": "Aina",
                        "birth_year": "1912"
                    }
                ]
            },
            "hobbies": [
                "sommarstuga"
            ]
        },
        "1": {
            "full_name": "Ivan F Andersson",
            "location": "Södertälje",
            "occupation": "kamrer",
            "birth_details": {
                "date": "26/10/1916",
                "place": "Södertälje",
                "parents": "metallarb Filip A o Lovisa Johansson"
            },
            "education": [],
            "career": [
                {
                    "position": "finansier:ch",
                    "years": {
                        "start_year": 1963,
                        "end_year": "NULL"
                    },
                    "organization": "ab Astra Södertälje"
                }
            ],
            "family": {
                "spouse": "Signe Eriksson",
                "marriage_year": "1942",
                "children": [
                    {
                        "name": "Lärs-Gunnar",
                        "birth_year": "1944"
                    }
                ]
            },
            "hobbies": [
                "friluftsliv"
            ]
        },
        "2": {
            "full_name": "John A Andersson",
            "location": "Insjön",
            "occupation": "skogvaktare",
            "birth_details": {
                "date": "05/07/1920",
                "place": "Forsand, Norge",
                "parents": "stenarb Fritjof A o Johanne A"
            },
            "education": [],
            "career": [
                {
                    "position": "stämpl:förman",
                    "years": {
                        "start_year": 1947,
                        "end_year": "NULL"
                    },
                    "organization": "skogsv:styr Falun"
                }
            ],
            "family": {
                "spouse": "Valborg Roligs",
                "marriage_year": "1953",
                "children": [
                    {
                        "name": "Britt-Marie",
                        "birth_year": "1954"
                    },
                    {
                        "name": "Christina",
                        "birth_year": "1958"
                    },
                    {
                        "name": "Lärs-Olov",
                        "birth_year": "1962"
                    }
                ]
            },
            "hobbies": [
                "trädgårdsskötsel",
                "fiske"
            ]
        },
        "3": {
            "full_name": "John S L Andersson",
            "location": "Sala",
            "occupation": "direktör",
            "birth_details": {
                "date": "10/03/1919",
                "place": "Sala",
                "parents": "fabr J Aug A o Elin Andersson"
            },
            "education": [
                {
                    "degree": "bygg:ing:ex TI 38",
                    "year": "NULL",
                    "institution": "NULL"
                }
            ],
            "career": [
                {
                    "position": "dir o inneh",
                    "years": {
                        "start_year": 1954,
                        "end_year": "NULL"
                    },
                    "organization": "John Anderssons bil ab, Sala"
                }
            ],
            "family": {
                "spouse": "Anna-Lisa Nord",
                "marriage_year": "1944",
                "children": [
                    {
                        "name": "Bengt Åke",
                        "birth_year": "1948"
                    },
                    {
                        "name": "Lars Ove",
                        "birth_year": "1952"
                    }
                ]
            },
            "hobbies": [
                "motorsport"
            ]
        }
    }
}