{
    "original": "ANDERSSON, E FOLKE,\noperasångare, Hälleforsnäs, f i Eskilstuna 16/12/92\nav Methodius A o Vilhelmina Gustaf\ns-dtr.\nSångstud h Josef Söderholtz, Tekla Ho-\n\nfer o Torsten Lennartsson. - Debut K\nteat 21, eng där 22-24 (tenor), Oscarsteat\n\n0  St teat Gbg, turnéer sv landsort, Finl,\nUSA o Ryssl, framtr i radio o TV.\n-Skulpturstud h Knut Jern, tecknare o\nskulptör. - Roller: Almaviva i\nBarberaren i Sevilla, Zephoris i Konung f en\ndag, Wilhelm Meister i Mignon, Walter\nvon der Vogelweide i Tannhäuser,\nhuvudpartiet i Ökensången, Geishan,\nJungfruburen, Lilla helgonet o Läderlappen\nm fi. - Utm: Eskilstuna stads ftJM.\nGift 33 m Elisabeth Westberg. - Barn:\nKristina f 34, Anders f 35, Jan f 37,\nLena f 38.\n\nANDERSSON, J FOLKE, tandläkare,\nVaxholm, f i Västerås 25/2/07 av\nköpman Reinhold A o Olga Degerström.\nStud:ex 27, Cand med dent Berlin 29,\nodont kand 29, tandläk:ex 32, ass Tierp\n32, eg prakt Vaxholm sed 34. - Förest\nmil tandklin KA l sed 44.\nGift 33 m Karin Widén. - Barn: Hasse\nf 33, Margareta f 36, Kerstin f 40,\nBirgitta f 45.\n\nANDERSSON,   B    GEORG,    rektor,\nMolkom, f i Värmskog, Värml l, 22/10/03\nav hemm:äg August A o Jenny\nJonasson.\nStud:ex Karlstad 25, fil mag Upps 31,\n\n01  lär:förordn 31-36, adj samrealsk\nVärnamo 36, småsk:sem Falun 47,\nfolksk:-sem Strängnäs sed  53, rekt  samrealsk\nMolkom sed 52,  l:e rekt Nyeds\nkommun sed 58. - Utm: RNO.\n\nGift 34 m Edith Gustavsson f 03, dtr t\nhemm:äg August G o Maria Johansson.\n- Barn: Leif f 35, Sten f 38, Bengt f 46.\n\n",
    "structured": {
        "1": {
            "full_name": "E Folke Andersson",
            "location": "Hälleforsnäs",
            "occupation": "Operasångare",
            "birth_details": {
                "date": "16/12/1892",
                "place": "Eskilstuna",
                "parents": "Methodius A o Vilhelmina Gustaf"
            },
            "education": [
                {
                    "degree": "Sångstud",
                    "year": "1921",
                    "institution": "Josef Söderholtz"
                },
                {
                    "degree": "Sångstud",
                    "year": "1922-1924",
                    "institution": "Oscarsteat, St teat Gbg"
                },
                {
                    "degree": "Skulpturstud",
                    "year": null,
                    "institution": "Knut Jern"
                }
            ],
            "career": [
                {
                    "position": "Debut K",
                    "years": {
                        "start_year": 1921,
                        "end_year": 1922
                    },
                    "organization": "teat"
                }
            ],
            "family": {
                "spouse": "Elisabeth Westberg",
                "marriage_year": "1933",
                "children": [
                    {
                        "name": "Kristina",
                        "birth_year": "1934"
                    },
                    {
                        "name": "Anders",
                        "birth_year": "1935"
                    },
                    {
                        "name": "Jan",
                        "birth_year": "1937"
                    },
                    {
                        "name": "Lena",
                        "birth_year": "1938"
                    }
                ]
            }
        },
        "2": {
            "full_name": "J Folke Andersson",
            "location": "Vaxholm",
            "occupation": "Tandläkare",
            "birth_details": {
                "date": "25/02/1907",
                "place": "Västerås",
                "parents": "Reinhold A o Olga Degerström"
            },
            "education": null,
            "career": [
                {
                    "position": "Eg prakt",
                    "years": {
                        "start_year": 1934,
                        "end_year": null
                    },
                    "organization": "Vaxholm"
                }
            ],
            "family": {
                "spouse": "Karin Widén",
                "marriage_year": "1933",
                "children": [
                    {
                        "name": "Hasse",
                        "birth_year": "1933"
                    },
                    {
                        "name": "Margareta",
                        "birth_year": "1936"
                    },
                    {
                        "name": "Kerstin",
                        "birth_year": "1940"
                    },
                    {
                        "name": "Birgitta",
                        "birth_year": "1945"
                    }
                ]
            }
        },
        "3": {
            "full_name": "B Georg Andersson",
            "location": "Molkom",
            "occupation": "Rektor",
            "birth_details": {
                "date": "22/10/1903",
                "place": "Värmskog, Värml l",
                "parents": "August A o Jenny Jonasson"
            },
            "education": [
                {
                    "degree": "Stud:ex",
                    "year": "1925",
                    "institution": "Karlstad"
                },
                {
                    "degree": "Fil mag",
                    "year": "1931",
                    "institution": "Upps"
                }
            ],
            "career": [
                {
                    "position": "Lär:förordn",
                    "years": {
                        "start_year": 1931,
                        "end_year": 1936
                    },
                    "organization": null
                },
                {
                    "position": "Adj samrealsk",
                    "years": {
                        "start_year": 1936,
                        "end_year": null
                    },
                    "organization": "Värnamo"
                },
                {
                    "position": "Folksk:-sem",
                    "years": {
                        "start_year": 1953,
                        "end_year": null
                    },
                    "organization": "Strängnäs"
                },
                {
                    "position": "Rekt samrealsk",
                    "years": {
                        "start_year": 1952,
                        "end_year": null
                    },
                    "organization": "Molkom"
                },
                {
                    "position": "L:e rekt",
                    "years": {
                        "start_year": 1958,
                        "end_year": null
                    },
                    "organization": "Nyeds kommun"
                }
            ],
            "family": {
                "spouse": "Edith Gustavsson",
                "marriage_year": "1934",
                "children": [
                    {
                        "name": "Leif",
                        "birth_year": "1935"
                    },
                    {
                        "name": "Sten",
                        "birth_year": "1938"
                    },
                    {
                        "name": "Bengt",
                        "birth_year": "1946"
                    }
                ]
            }
        }
    }
}