{
    "original": "MILLER, BIGGE, fabrikschef,\nBanke-ryd, f i Gbg 3/2/21 av dir Einar M o\nElin Gunnesson.\n\nStud NKI, Bröd Miller ab Bankeryd.\n-Led komm:fullm 54, ordf brandstyr\n58-62, v ordf ab Bankerydshem. - Medl\nRo-tary. - Hobbies: motorsport, fiske,\nvattensport, akvarier.\n\nGift 42 m Maud Wickman, dtr t\nbruks-tjm Karl W o Tora Hallen. - Barn:\nSture f 43, Christer f 45, Ann f 51.\n\nMILLER, L GÖSTA, ingenjör,\nBanke-ryd, f i Jönkpg 28/8/24 av fabr Uno M\no Elin Karlsson.\n\nRealex 42, ing :ex Gbg 44, deläg\nBanke-ryds maskin ab 46, föret:led o verkst:ch\ndär sed 49 (styr:led). - V ordf skolstyr\n64, ordf byggn :komm f högstadiesk 63.\n-Hobby: sport.\n\nGift 47 m Birgit Martinsson f 22, dtr t\nfabr Torsten M o Linnea M. - Barn:\nMartin f 48, Elisabeth f 51, Torbjörn\nf 58.\n\nMILLERS, HANS-FREDRIK,\ncivilingenjör, Mölndal, f i Jönkpg 16/4/33 av\nsped :ch Hans M o Svea Olsson.\nStud:ex 52, CTH 57, M Se MIT USA\n64; anst Sv flygmotor ab Trollhättan 57,\nelektroniklab Saab Gbg 60, sekt :ch där\nsed 62. - Sv:e-Amer stift stip 63.\n\nMILLINGER, PER-ÅKE I, tandläkare,\n\nLinköping, f i Kisa, Österg l, 21/12/23\nav dir C A Johansson o Kerstin Jonsson.\nStud:ex Linkpg 44, res:off:ex 47,\ntandl:-ex Sthlm 50, aman rotfylln:avd THS\nSthlm 50, distr:tandl Linkpg 50-51,\nass:-tandl o vik tandl Örebro o Västervik\n51-55, tandl folktandv Linkpg 55-58, l:e\ndistr:tandl där 58-64, tandv:insp sed 64.\n- Sekr Österg v:a tandl :f ören 58-59, Sv:es\ntj:tandl lokalavd 58.\n\nGift 54 m Birgit Andersson f 30. - Barn:\nEva f 55, Anna f 58.\n\n",
    "structured": {
        "1": {
            "full_name": "BIGGE MILLER",
            "location": "Banke-ryd",
            "occupation": "fabrikschef",
            "birth_details": {
                "date": "03/02/1921",
                "place": "Göteborg",
                "parents": "dir Einar M o Elin Gunnesson"
            },
            "education": [
                {
                    "degree": "Stud NKI",
                    "year": "NULL",
                    "institution": "Bröd Miller ab Bankeryd"
                }
            ],
            "career": [
                {
                    "position": "komm:fullm",
                    "years": {
                        "start_year": 1954,
                        "end_year": 1954
                    },
                    "organization": "NULL"
                },
                {
                    "position": "ordf brandstyr",
                    "years": {
                        "start_year": 1958,
                        "end_year": 1962
                    },
                    "organization": "NULL"
                },
                {
                    "position": "v ordf ab Bankerydshem",
                    "years": {
                        "start_year": "NULL",
                        "end_year": "NULL"
                    },
                    "organization": "NULL"
                }
            ],
            "family": {
                "spouse": "Maud Wickman",
                "marriage_year": "1942",
                "children": [
                    {
                        "name": "Sture",
                        "birth_year": "1943"
                    },
                    {
                        "name": "Christer",
                        "birth_year": "1945"
                    },
                    {
                        "name": "Ann",
                        "birth_year": "1951"
                    }
                ]
            },
            "hobbies": [
                "motorsport",
                "fiske",
                "vattensport",
                "akvarier"
            ]
        },
        "2": {
            "full_name": "L GÖSTA MILLER",
            "location": "Banke-ryd",
            "occupation": "ingenjör",
            "birth_details": {
                "date": "28/08/1924",
                "place": "Jönköping",
                "parents": "fabr Uno M o Elin Karlsson"
            },
            "education": [
                {
                    "degree": "Realex",
                    "year": "1942",
                    "institution": "NULL"
                },
                {
                    "degree": "ing :ex",
                    "year": "1944",
                    "institution": "Göteborg"
                }
            ],
            "career": [
                {
                    "position": "deläg",
                    "years": {
                        "start_year": 1946,
                        "end_year": 1946
                    },
                    "organization": "Banke-ryds maskin ab"
                },
                {
                    "position": "v ordf skolstyr",
                    "years": {
                        "start_year": 1964,
                        "end_year": 1964
                    },
                    "organization": "NULL"
                },
                {
                    "position": "ordf byggn :komm f högstadiesk",
                    "years": {
                        "start_year": 1963,
                        "end_year": 1963
                    },
                    "organization": "NULL"
                }
            ],
            "family": {
                "spouse": "Birgit Martinsson",
                "marriage_year": "1947",
                "children": [
                    {
                        "name": "Martin",
                        "birth_year": "1948"
                    },
                    {
                        "name": "Elisabeth",
                        "birth_year": "1951"
                    },
                    {
                        "name": "Torbjörn",
                        "birth_year": "1958"
                    }
                ]
            },
            "hobbies": [
                "sport"
            ]
        },
        "3": {
            "full_name": "HANS-FREDRIK MILLERS",
            "location": "Mölndal",
            "occupation": "civilingenjör",
            "birth_details": {
                "date": "16/04/1933",
                "place": "Jönköping",
                "parents": "sped :ch Hans M o Svea Olsson"
            },
            "education": [
                {
                    "degree": "Stud:ex",
                    "year": "1952",
                    "institution": "NULL"
                },
                {
                    "degree": "CTH",
                    "year": "1957",
                    "institution": "NULL"
                },
                {
                    "degree": "M Se MIT USA",
                    "year": "1964",
                    "institution": "NULL"
                }
            ]
        },
        "4": {
            "full_name": "PER-ÅKE I MILLINGER",
            "location": "Linköping",
            "occupation": "tandläkare",
            "birth_details": {
                "date": "21/12/1923",
                "place": "Kisa, Östergötland",
                "parents": "dir C A Johansson o Kerstin Jonsson"
            },
            "education": [
                {
                    "degree": "Stud:ex",
                    "year": "1944",
                    "institution": "Linköping"
                },
                {
                    "degree": "res:off:ex",
                    "year": "1947",
                    "institution": "NULL"
                },
                {
                    "degree": "tandl:-ex",
                    "year": "1950",
                    "institution": "Stockholm"
                }
            ],
            "career": [
                {
                    "position": "aman rotfylln:avd THS",
                    "years": {
                        "start_year": 1950,
                        "end_year": 1950
                    },
                    "organization": "Stockholm"
                },
                {
                    "position": "distr:tandl",
                    "years": {
                        "start_year": 1950,
                        "end_year": 1951
                    },
                    "organization": "Linköping"
                },
                {
                    "position": "l:e distr:tandl",
                    "years": {
                        "start_year": 1958,
                        "end_year": 1964
                    },
                    "organization": "Linköping"
                }
            ],
            "family": {
                "spouse": "Birgit Andersson",
                "marriage_year": "1954",
                "children": [
                    {
                        "name": "Eva",
                        "birth_year": "1955"
                    },
                    {
                        "name": "Anna",
                        "birth_year": "1958"
                    }
                ]
            }
        }
    }
}