{
    "original": "Pärpe, Bengt Georg, kyrkoadjunkt,\nMalmö, f. 2/3/06 i Hälsingborg. G.\n39 m. KarirALund. Barn: Eva-Lena\nf. 40. — St£Fd:ex. i Hälsingb. 26, fil.\nkand. 30, teol. kand., prakt. teol. prov\no. prästv. f. Lunds stift 35.    Olika för-\n\nordn. s. past :adj., v. kommln. o. v.\npastor 36-42, kyrkoadj. i Malmö sed.\n42. Sekr. i Malmö prästsällsk.,\nstyr:-led. i Lunds stifts kyrkosångförb. m.\nm. Hobbies: sång, musik. Lunds\nstud:sångfören. SM.\n\nQ\n\nQuensel, Carl-Erik, professor, Lund,\nf. 9/10/07 i Malmö av kassör Conrad\nQ. o. Ester Grönvalil. G. 42 m.\nBirgitta Sederholm. Barn: Maria f. 47,\nElisabeth 48. — Fil. mag. i Lund 30,\nfil. lic. 35, fil. dr 38. Doc. i statistik\n38, tf. prof. 39-41, prof. i statistik v.\nLunds univ. fr. 41. Skr.: ett flert. skr.\nspec. i befolkn:statistik, Lärob. i den\nteor. statistikens grunder (44). RNO,\nLLHS, LLVS.     .\n\nQuiding, Carl, direktör för\nsjömans-förmedlingen, Hälsingborg, f. 27/1/02 i\nKarlskrona av hamnkapten Uno Q. o.\nThyra Wilhelmina Ohrström. G. 26\nm. Rutin Mårtensson. Barm: Birgit f.\n28, Allan 29, Robert 37. — Sjökapt:ex.\n24. Dir. f. off. arb rförmedl. i\nKarlskrona 33, i länsarbmd f. Blek. 1. 40,\nf. sjömansförmedl. i Hälsingb. sed. 48.\nMedl. i SFMK (KFMF)  sed. 37, fän-\n\nrik där, medl. i Odd Fellow.    Hobby:\nfilateli.   DFrM.\n\nQvarnström, Sven Birger,\nläroverksadjunkt, Landskrona, f. 22/6/97 i\nVis-sefjärda, Kalm. 1., av kyrkoh.\nJolhan-nes Q. o. h. h. f. Mattisson. G. 1. 29-46\nm. lä rov :adj. Elisabeth Scholander ; 2.\n47 m. journ. fil. mag. Birgit Wadin.\nBarn: Sven f. 35. — Stud:ex. i\nKristianstad 17, fil. mag. i Lund 30,\nprov-år där 40. Res. t. Tyskl. o. Engl. Tjg.\ni Bollnäs 33, Hälsingb. h. a. 1. 34,\nFalkenberg 34, Eskilstuna o. v. Malmö h.\na. 1. f. fl. 3’5, v. Malmö realsk. s. å., i\nArvika 36, v. Örebro h. a. 1.\n36-38, Vetlanda 39, Uddevalla s. å,\nKristianstad 40-41, Sunne 41-43, adj. i\nmodersm. o. eng. v. h. a. 1. i Landiskr.\nsed. 43i. Fd. medarb. i ol. tidn:föret.\nSkr.: Michel Nostradanius. Några\nakt. komment. t. hans profetior (41),\nett flert.  tidn :art.\n\nR\n\n",
    "structured": {
        "0": {
            "full_name": "Pärpe, Bengt Georg",
            "location": "Malmö",
            "occupation": "kyrkoadjunkt",
            "birth_details": {
                "date": "02/03/1906",
                "place": "Hälsingborg"
            },
            "education": [
                {
                    "degree": "Stud:ex.",
                    "year": "1926",
                    "institution": "Hälsingborg"
                },
                {
                    "degree": "filosofie kandidat",
                    "year": "1930",
                    "institution": "Hälsingborg"
                },
                {
                    "degree": "teol. kand.",
                    "year": "undefined",
                    "institution": "undefined"
                }
            ],
            "career": [
                {
                    "position": "past:adj.",
                    "years": {
                        "start_year": 1936,
                        "end_year": 1942
                    },
                    "organization": "undefined"
                },
                {
                    "position": "v. kommln. o. v. pastor",
                    "years": {
                        "start_year": 1936,
                        "end_year": 1942
                    },
                    "organization": "undefined"
                },
                {
                    "position": "kyrkoadj.",
                    "years": {
                        "start_year": 1942,
                        "end_year": "undefined"
                    },
                    "organization": "Malmö"
                }
            ],
            "family": {
                "spouse": "KarirALund",
                "marriage_year": "undefined",
                "children": [
                    {
                        "name": "Eva-Lena",
                        "birth_year": "1940"
                    }
                ]
            },
            "hobbies": [
                "sång",
                "musik"
            ]
        },
        "1": {
            "full_name": "Quensel, Carl-Erik",
            "location": "Lund",
            "occupation": "professor",
            "birth_details": {
                "date": "09/10/1907",
                "place": "Malmö"
            },
            "education": [
                {
                    "degree": "Fil. mag.",
                    "year": "1930",
                    "institution": "Lund"
                },
                {
                    "degree": "fil. lic.",
                    "year": "1935",
                    "institution": "Lund"
                },
                {
                    "degree": "fil. dr",
                    "year": "1938",
                    "institution": "Lund"
                }
            ],
            "career": [
                {
                    "position": "Doc. i statistik",
                    "years": {
                        "start_year": 1938,
                        "end_year": "undefined"
                    },
                    "organization": "undefined"
                },
                {
                    "position": "tf. prof.",
                    "years": {
                        "start_year": 1939,
                        "end_year": 1941
                    },
                    "organization": "undefined"
                },
                {
                    "position": "prof. i statistik",
                    "years": {
                        "start_year": 1941,
                        "end_year": "undefined"
                    },
                    "organization": "Lunds univ."
                }
            ],
            "family": {
                "spouse": "Birgitta Sederholm",
                "marriage_year": "1942",
                "children": [
                    {
                        "name": "Maria",
                        "birth_year": "1947"
                    },
                    {
                        "name": "Elisabeth",
                        "birth_year": "1948"
                    }
                ]
            }
        },
        "2": {
            "full_name": "Quiding, Carl",
            "location": "Hälsingborg",
            "occupation": "direktör för sjömansförmedlingen",
            "birth_details": {
                "date": "27/01/1902",
                "place": "Karlskrona"
            },
            "education": [
                {
                    "degree": "Sjökapt:ex.",
                    "year": "1924",
                    "institution": "undefined"
                }
            ],
            "career": [
                {
                    "position": "Dir. f. off. arb rförmedl.",
                    "years": {
                        "start_year": 1948,
                        "end_year": "undefined"
                    },
                    "organization": "Hälsingborg"
                }
            ],
            "family": {
                "spouse": "Rutin Mårtensson",
                "marriage_year": "1926",
                "children": [
                    {
                        "name": "Birgit",
                        "birth_year": "1928"
                    },
                    {
                        "name": "Allan",
                        "birth_year": "1929"
                    },
                    {
                        "name": "Robert",
                        "birth_year": "1937"
                    }
                ]
            },
            "hobbies": [
                "filateli"
            ]
        },
        "3": {
            "full_name": "Qvarnström, Sven Birger",
            "location": "Landskrona",
            "occupation": "läroverksadjunkt",
            "birth_details": {
                "date": "22/06/1897",
                "place": "Vissefjärda, Kalm. l."
            },
            "education": [
                {
                    "degree": "Stud:ex.",
                    "year": "1917",
                    "institution": "Kristianstad"
                },
                {
                    "degree": "fil. mag.",
                    "year": "1930",
                    "institution": "Lund"
                },
                {
                    "degree": "prov-år",
                    "year": "1940",
                    "institution": "Lund"
                }
            ],
            "career": [
                {
                    "position": "adj. i modersm. o. eng.",
                    "years": {
                        "start_year": 1943,
                        "end_year": "undefined"
                    },
                    "organization": "Landskrona"
                }
            ],
            "family": {
                "spouse": "Elisabeth Scholander",
                "marriage_year": "1929-1946",
                "children": [
                    {
                        "name": "Sven",
                        "birth_year": "1935"
                    }
                ]
            }
        }
    }
}