{
    "original": "Renwik, Gustaf Adolf, kyrkoherde,\nAxelvold, f. 22/12/94 i Ottarp,\nMalmön. 1. G. m. Margit Elisabet\nArm-stedt. Barn: Inga-Britt f. 26,\npost-exp., Bodil Margareta 34. — Stud:ex.\ni Hälsingb.’ 15, fil. kand. 17, teol. kand,,\nprakt. teol. prov o. prästv. f. Lunds\nstift 25. Vik. o. e. o. ämneslär. i\nÅstorps komm. mellansk, 20-21, e. o.\nämneslär. v. Getinge h. folk sk. 21-23,\ntim-lär. i Anderslövs komm. mellansk.\n26-27, ständ. adj. i Dalköpinge 25-28, vik.\nkommin. i Karlshamn 28-29, kommin.\ndär 29-32, kyrkoh. i Halmstad o.\nSi-re köp in ge  sed.  32.\n\nResare, Oscar Eric Vilhelm,\nläroverksadjunkt, Eslöv, f. 1/12/07 i\nSödertälje av godsäg. Anders R, o. Emma\nAndersson. G. 39 m. Karin Arman.\nBarn: Lena f. 40, Anita 41,\nMargareta 44. — Studiex. i Malmö 29!, fil.\nmag. i Lund 37. Provar v. Gbgs\nfolk-sk :sem. 42. Viik. ämneslär. i\nKlintehamn 36, e. adj. v. Gbgs västra real\n37-38, i LuÜeå 38-42, ii Kiruna 43, e. o.\nämneslär. i Strömsnäsbruk 43-44, ord.\ndär 44, adj. i biol. m. hälsol.. o. kemi\nv. h. a. 1. i Eslöv fr. 46. Hemsk xhef\ni Strömsnäsbruk 44.    Bibi. i Eslöv 47.\n\nReumark, Ragnar Ossian, affär\ns-chef, Hälsingborg, f. 27/10/12 i Malmö\nav lagerchef Ossian R. o. Augusta\nPersson. G. 38 m. Torgerd\nHägerström. Barn: Göran f. 40), Birgitta\n43i. — Realex. i Malmö 28, hand :stud.\nv. Hermods korr:inst. o. afton sk. Res.\nt.   Engl.   34,   Tyskl.   32,   33,   34   o,   38.\n\nAnst. v. A-B Herman Gotthard! i\nMalmö  28-30,  v.  firmorna  J.   H.   Jonsson\n\n0.  Oscar Alm i Malmö 30-32, v. Tempo\nA-B i Sthlm 33- chef v. Tempo A-B i\nVisby 39, v. Tempo A-B i Hälsingb.\nsed. 42. Tj :man i Odd Fellow.\nHobby: fotograferling.   Civ. o. mil. IdrSm.\n\nReuterskiöld, Fredrik Fabian\nJan-Axel, fil. dr, lektor, Malmö, f. 18/9/96\ni Upps. av prof. C. L. A. A. R. o.\nGerda Odenius. G. 36 m. Barbro\nCol-liander. — Stud:ex. i Upps. 14, fil.\nkand. 20, fil. mag. 26, fil. lic. 30, fil.\ndr 39, doc. i kemi 39. Provar i Upps.\n39-40. Aman. v. Upps. univ. kem. inst.\n31-41, vik. lekt. v. Borås tekn. gymn.\n42-44, v. Norrköp. tekn. gymn. 44-45,\nlektor i kemi o. kem. lab. v. Malmö\ntekn. lärov. fr. 45. Skr.: Spaltung d.\nÄthylien-bissulphonessiigsäure in alkal.\nLösung. Üb.\nPropylen-bis-thioglykol-säure und\nPropylen-bis-sulphonessig-säure m. fl.\n\n",
    "structured": {
        "1": {
            "full_name": "Renwik, Gustaf Adolf",
            "location": "Axelvold, Ottarp, Malmön",
            "occupation": "kyrkoherde",
            "birth_details": {
                "date": "22/12/1894",
                "place": "Ottarp"
            },
            "education": [
                {
                    "degree": "Stud:ex.",
                    "year": "1915",
                    "institution": "Hälsingborgs"
                },
                {
                    "degree": "filosofie kandidat",
                    "year": "1917",
                    "institution": "NULL"
                },
                {
                    "degree": "teol. kand., prakt. teol. prov o. prästv.",
                    "year": "1925",
                    "institution": "Lunds stift"
                }
            ],
            "career": [
                {
                    "position": "vik. o. e. o. ämneslär.",
                    "years": {
                        "start_year": 1920,
                        "end_year": 1921
                    },
                    "organization": "Åstorps komm."
                },
                {
                    "position": "e. o. ämneslär.",
                    "years": {
                        "start_year": 1921,
                        "end_year": 1923
                    },
                    "organization": "Getinge h. folk sk."
                },
                {
                    "position": "tim-lär.",
                    "years": {
                        "start_year": 1926,
                        "end_year": 1927
                    },
                    "organization": "Anderslövs komm."
                },
                {
                    "position": "ständ. adj.",
                    "years": {
                        "start_year": 1925,
                        "end_year": 1928
                    },
                    "organization": "Dalköpinge"
                },
                {
                    "position": "vik. kommin.",
                    "years": {
                        "start_year": 1928,
                        "end_year": 1929
                    },
                    "organization": "Karlshamn"
                },
                {
                    "position": "kommin.",
                    "years": {
                        "start_year": 1929,
                        "end_year": 1932
                    },
                    "organization": "Halmstad o. Sireköpinge"
                },
                {
                    "position": "kyrkoh.",
                    "years": {
                        "start_year": 1932,
                        "end_year": null
                    },
                    "organization": "Halmstad o. Sireköpinge"
                }
            ],
            "family": {
                "spouse": "Margit Elisabet Armstedt",
                "marriage_year": "NULL",
                "children": [
                    {
                        "name": "Inga-Britt",
                        "birth_year": "1926"
                    },
                    {
                        "name": "Bodil Margareta",
                        "birth_year": "1934"
                    }
                ]
            }
        },
        "2": {
            "full_name": "Resare, Oscar Eric Vilhelm",
            "location": "Eslöv",
            "occupation": "läroverksadjunkt",
            "birth_details": {
                "date": "1/12/1907",
                "place": "Södertälje"
            },
            "education": [
                {
                    "degree": "Studiex.",
                    "year": "1929",
                    "institution": "Malmö"
                },
                {
                    "degree": "fil. mag.",
                    "year": "1937",
                    "institution": "Lund"
                }
            ],
            "career": [
                {
                    "position": "provar v. Gbgs folk-sk :sem.",
                    "years": {
                        "start_year": 1942,
                        "end_year": null
                    },
                    "organization": "NULL"
                },
                {
                    "position": "viik. ämneslär.",
                    "years": {
                        "start_year": 1936,
                        "end_year": null
                    },
                    "organization": "Klintehamn"
                },
                {
                    "position": "e. adj. v. Gbgs västra real",
                    "years": {
                        "start_year": 1937,
                        "end_year": 1938
                    },
                    "organization": "NULL"
                },
                {
                    "position": "e. o. ämneslär.",
                    "years": {
                        "start_year": 1943,
                        "end_year": 1944
                    },
                    "organization": "Strömsnäsbruk"
                },
                {
                    "position": "ord. där",
                    "years": {
                        "start_year": 1944,
                        "end_year": null
                    },
                    "organization": "Strömsnäsbruk"
                },
                {
                    "position": "adj. i biol. m. hälsol.. o. kemi",
                    "years": {
                        "start_year": 1946,
                        "end_year": null
                    },
                    "organization": "Eslöv"
                }
            ],
            "family": {
                "spouse": "Karin Arman",
                "marriage_year": "1939",
                "children": [
                    {
                        "name": "Lena",
                        "birth_year": "1940"
                    },
                    {
                        "name": "Anita",
                        "birth_year": "1941"
                    },
                    {
                        "name": "Margareta",
                        "birth_year": "1944"
                    }
                ]
            }
        },
        "3": {
            "full_name": "Reumark, Ragnar Ossian",
            "location": "Hälsingborg",
            "occupation": "affärsschef",
            "birth_details": {
                "date": "27/10/1912",
                "place": "Malmö"
            },
            "education": [
                {
                    "degree": "Realex.",
                    "year": "1928",
                    "institution": "Malmö"
                }
            ],
            "career": [
                {
                    "position": "anst. v. A-B Herman Gotthard!",
                    "years": {
                        "start_year": 1928,
                        "end_year": 1930
                    },
                    "organization": "Malmö"
                },
                {
                    "position": "v. firmorna J. H. Jonsson o. Oscar Alm",
                    "years": {
                        "start_year": 1930,
                        "end_year": 1932
                    },
                    "organization": "Malmö"
                },
                {
                    "position": "v. Tempo A-B i Sthlm",
                    "years": {
                        "start_year": 1933,
                        "end_year": null
                    },
                    "organization": "Sthlm"
                },
                {
                    "position": "chef v. Tempo A-B i Visby",
                    "years": {
                        "start_year": 1939,
                        "end_year": null
                    },
                    "organization": "Visby"
                },
                {
                    "position": "v. Tempo A-B i Hälsingb.",
                    "years": {
                        "start_year": 1942,
                        "end_year": null
                    },
                    "organization": "Hälsingborg"
                }
            ],
            "family": {
                "spouse": "Torgerd Hägerström",
                "marriage_year": "1938",
                "children": [
                    {
                        "name": "Göran",
                        "birth_year": "1940"
                    },
                    {
                        "name": "Birgitta",
                        "birth_year": "1943"
                    }
                ]
            },
            "hobbies": [
                "fotograferling.   Civ. o. mil. IdrSm."
            ]
        },
        "4": {
            "full_name": "Reuterskiöld, Fredrik Fabian Jan-Axel",
            "location": "Malmö",
            "occupation": "lektor",
            "birth_details": {
                "date": "18/9/1896",
                "place": "Upps."
            },
            "education": [
                {
                    "degree": "Stud:ex.",
                    "year": "1914",
                    "institution": "Upps."
                },
                {
                    "degree": "fil. kand.",
                    "year": "1920",
                    "institution": "NULL"
                },
                {
                    "degree": "fil. mag.",
                    "year": "1926",
                    "institution": "NULL"
                },
                {
                    "degree": "fil. lic.",
                    "year": "1930",
                    "institution": "NULL"
                },
                {
                    "degree": "fil. dr",
                    "year": "1939",
                    "institution": "NULL"
                },
                {
                    "degree": "doc. i kemi",
                    "year": "1939",
                    "institution": "NULL"
                }
            ],
            "career": [
                {
                    "position": "aman. v. Upps. univ. kem. inst.",
                    "years": {
                        "start_year": 1931,
                        "end_year": 1941
                    },
                    "organization": "Upps."
                },
                {
                    "position": "vik. lekt. v. Borås tekn. gymn.",
                    "years": {
                        "start_year": 1942,
                        "end_year": 1944
                    },
                    "organization": "Borås"
                },
                {
                    "position": "v. Norrköp. tekn. gymn.",
                    "years": {
                        "start_year": 1944,
                        "end_year": 1945
                    },
                    "organization": "Norrköp."
                },
                {
                    "position": "lektor i kemi o. kem. lab. v. Malmö tekn. lärov.",
                    "years": {
                        "start_year": 1945,
                        "end_year": null
                    },
                    "organization": "Malmö"
                }
            ],
            "family": {
                "spouse": "Barbro Colliander",
                "marriage_year": "NULL",
                "children": []
            },
            "publications": [
                {
                    "title": "Spaltung d. Äthylien-bissulphonessiigsäure in alkal. Lösung. Üb. Propylen-bis-thioglykol-säure",
                    "year": "NULL",
                    "type": "NULL"
                }
            ]
        }
    }
}