{
    "original": "Ranger, Anders Mauritz,\nkyrkoherde,   Linderöd,   f.   22/9/91   i   Gylle,\n\nMalmöh. 1. G. 35 m. Berta Möller.\nBarn: Anders f. 37. — Stud:ex. i Lund\n13, ex. v. Malmö hand :gymn. 15,\nhand rkorr. 16-19, stud. i Tyskl. 21, i\nEngl. 22, teol. fil. ex. i Lund 26, teol.\nkand., prakt. teol. prov o. prästv. f.\nLunds stift 28. V. past. i Ö. Torp 28,\nkommin. där 32, kyrkoh. i Linderöd o.\nÄsphult sed. 41. Ordf. i båda förs.\nkyrkoråd o. kyrkostämmor, ers. f. led.\ni XI ibost:distr. i Gärds kontr.\n\nRanhamn, Ernst Rolf, tandläkare,\nMalmö, f. 14/4/07 i N. Råda, Värml. 1.\n— Stud:ex. i Karlstad 27, med. stud. i\nLund 30-32, tandläk :kand. 33,\ntandläk: ex. 37. Assist, i Svalöv scmm. 37, i\nMalmö 38, egen praktik i Malmö sed.\n46.\n\nRanke, Sigrurd; med. lic, prakt,\nläkare, Malmö, f. 16/5/931 i Orsa,\nKop-parb. 1. — Stud:ex. i Falun 12, ined.\nkand. i Upps. 17, med. lic. i Sthlm 22.\nE. läk. i Gävlcb. 1. 2 mån. 18, tf. andre\nund :läk. v. Högibo tub:sjukh. 6 mån.\n21, e. läk. v. Kronpr. Lovisas vårdanst.\nmed. avd. 22-23, und :lläk. där 23-24,\nund :läk. v. Flens’burgska vårdanst.\n25-29, läk. v. Malmö mjölkdroppe sed. 24,\nv. Malmö ’barnsjukh. 30-34, v. Maltmö\nborgarsk. sed. 31, v. Östra o. Södra\nbarnkrubb. i Malmö sed. 31, prakt, i\nMalmö sed. 29.\n\nRanklev, Sven Daniel, leg. läkare,\nHälsingborg, f. 19/5/16 i Stöde,\nVäster-norrl. 1., av stat :mäst. Helmer Persson\no. Naemi Westenius. G. 43 m. Karin\nJönsson. Barn: Ingrid i. 43, Ulla 46. —\nStud:ex. 35, med. kand. 39, med. lic.\n45. Div. iförordn. v. Torsiby, Falköp. o.\nGällivare las., kir. avd. v. Hälsingb.\nlas., bakt. avd. v. Lunds las., Barnsjukh.\ni Hälsingb. o. s. prov :läk. i filera\nrepriser. Tf. ’flottiljläk. v. Ljungbyhed\nfr. 47. Hobby:  amatörfotografering.\n\n",
    "structured": {
        "1": {
            "full_name": "Ranger, Anders Mauritz",
            "location": "Linderöd",
            "occupation": "kyrkoherde",
            "birth_details": {
                "date": "22/09/1891",
                "place": "Gylle"
            },
            "education": [
                {
                    "degree": "Stud:ex.",
                    "year": "1913",
                    "institution": "Lund"
                },
                {
                    "degree": "teol. fil. ex.",
                    "year": "1926",
                    "institution": "Lund"
                },
                {
                    "degree": "teol. kand., prakt. teol. prov",
                    "year": "1928",
                    "institution": "Lunds stift"
                }
            ],
            "career": [
                {
                    "position": "V. past.",
                    "years": {
                        "start_year": 1928,
                        "end_year": 1932
                    },
                    "organization": "Ö. Torp"
                },
                {
                    "position": "kommin.",
                    "years": {
                        "start_year": 1932,
                        "end_year": null
                    },
                    "organization": "Ö. Torp"
                },
                {
                    "position": "kyrkoh.",
                    "years": {
                        "start_year": 1941,
                        "end_year": null
                    },
                    "organization": "Linderöd o. Äsphult"
                }
            ],
            "family": {
                "spouse": "Berta Möller",
                "marriage_year": "1935",
                "children": [
                    {
                        "name": "Anders",
                        "birth_year": "1937"
                    }
                ]
            }
        },
        "2": {
            "full_name": "Ranhamn, Ernst Rolf",
            "location": "Malmö",
            "occupation": "tandläkare",
            "birth_details": {
                "date": "14/04/1907",
                "place": "N. Råda, Värml."
            },
            "education": [
                {
                    "degree": "Stud:ex.",
                    "year": "1927",
                    "institution": "Karlstad"
                },
                {
                    "degree": "tandläk: ex.",
                    "year": "1937",
                    "institution": null
                }
            ],
            "career": [
                {
                    "position": "Assist.",
                    "years": {
                        "start_year": 1937,
                        "end_year": null
                    },
                    "organization": "Malmö"
                }
            ],
            "family": null
        },
        "3": {
            "full_name": "Ranke, Sigrurd",
            "location": "Malmö",
            "occupation": "med. lic, prakt, läkare",
            "birth_details": {
                "date": "16/05/1931",
                "place": "Orsa, Kopparb."
            },
            "education": [
                {
                    "degree": "Stud:ex.",
                    "year": "1912",
                    "institution": "Falun"
                },
                {
                    "degree": "med. lic.",
                    "year": "1922",
                    "institution": "Sthlm"
                }
            ],
            "career": [
                {
                    "position": "E. läk.",
                    "years": {
                        "start_year": 1921,
                        "end_year": null
                    },
                    "organization": "Gävlcb."
                }
            ],
            "family": null
        },
        "4": {
            "full_name": "Ranklev, Sven Daniel",
            "location": "Hälsingborg",
            "occupation": "leg. läkare",
            "birth_details": {
                "date": "19/05/1916",
                "place": "Stöde, Västernorrland"
            },
            "education": [
                {
                    "degree": "Stud:ex.",
                    "year": "1935",
                    "institution": null
                },
                {
                    "degree": "med. kand.",
                    "year": "1939",
                    "institution": null
                },
                {
                    "degree": "med. lic.",
                    "year": "1945",
                    "institution": null
                }
            ],
            "career": [
                {
                    "position": "Tf. ’flottiljläk.",
                    "years": {
                        "start_year": 1947,
                        "end_year": null
                    },
                    "organization": "Ljungbyhed"
                }
            ],
            "family": {
                "spouse": "Karin Jönsson",
                "marriage_year": "1943",
                "children": [
                    {
                        "name": "Ingrid",
                        "birth_year": "1943"
                    },
                    {
                        "name": "Ulla",
                        "birth_year": "1946"
                    }
                ]
            },
            "hobbies": [
                "amatörfotografering"
            ]
        }
    }
}