{
    "original": "Reimann, Odd, doktoringenjör,\nLandskrona, f. 3:1/12/90 i Osilo, Norge,\nav dir. Jens Aarup R. o. G. A.\nNielsen, G. 1. 18 m. Harriet Österlund; 2.\n39 m. Selma Andersson. Barn:\nGunnel f. 19, Jens Aarup 21, Aagot\nKerstin 22. — Stud:ex. i Norge 10,\ndi-iplO!ming:ex. i Tyskl. l¾ doktoring. 16.\nAnst. s;. kemist, metallurg o.\ndrifts-ing. inom järn- o. stålind. 16-23J, i\nSverige, Norge o*. USA 23-28, i Tyskl.\n28-31, s. kemist i A-B Kemiska Patenter\ni Landskr. sed. 3!1, num. För en.\nSuper-fosfatfabrikers forskn :läb. Skr.: Das\nVerhalten d. Phosphors bei d.\nelektro-;lyt. Raffination v. Roheiisen\n(grad:-aVh. 16).\n\nReimer, Ebbe Waildemar, med. lic,\nprakt, läkare, Malmö, f. 21/7/09 i\nMalmö av kassör Anders R. o. Elise\nHansson. G. 42! m. Ingrid Norden. Barn:\nArne f. 43, Ålke 4¾ Ulla 47. —\nStud:-ex. i Malmö 28, med. kand. 32 o. med.\nlic. 37 i Lund. Tf. prov:läk. i Delsbo\ndistr. isoimm. 36 o. i Värnamo distr.\nvåren 38, tf. andre und :läk. v.\nSjö-Gunnar sb!o san. 5 mån. 37, tjgj. v. Ryhovs\no. S :t Sigfrids sjukh. 2 mån. 38, tf.\nandre und :läk. v. Broby san. 5 mån.\n38, ord. där 38-40, röntgenunderläk.\nv. Linköp. ltas. 40-41, vik. på med. avd.\npå oil. las. 42, ord. und :läk. v. Linköp.\nlas. 42-45, prakt. läk. i Malmö sed. 45.\n\nReimiers, Otta Emil Nilsson,\növerläkare, Tyringe, f. 24/1/65 i Kattarp,\nMalmöh. 1., av Nils Jönsson o.\nPer-nilila Persson. G. 04 m. Sigrid Wilén\nfr. Finl. Barn: Sigyn f. 05, husm. v.\nTyringe san., Inger 06, journalist,\nArne 10, med. lic, läk. v. Tyringe san.,\nGuilveig (Gulle) 18, försäkr :tj :man,\ng. m. leg:tj:man Ch. Vernon. — Med.\nlic 03’. Stud :res. t. Tyskl., Engl., Ital.\no. USA. Läk. v. Tyringe badanst. o.\nsan. fr. 05, dess grund!, o. skapare.\nArb. f. fysik.-diet. sjukd :behandl. Led.\nav Tyringe hälsov :nd, LNF, Int. Soc\nof  Med.  Hydrology.   RNO 311.\n\n",
    "structured": {
        "0": {
            "full_name": "Odd Reimann",
            "location": "Landskrona",
            "occupation": "doktoringenjör",
            "birth_details": {
                "date": "03/01/1890",
                "place": "Osilo, Norge",
                "parents": "av dir. Jens Aarup R. o. G. A. Nielsen"
            },
            "education": [
                {
                    "degree": "Stud:ex.",
                    "year": "1910",
                    "institution": "i Norge"
                },
                {
                    "degree": "diploming:ex.",
                    "year": "1916",
                    "institution": "Tyskland"
                },
                {
                    "degree": "doktoring",
                    "year": "1916",
                    "institution": "Tyskland"
                }
            ],
            "career": [
                {
                    "position": "Anst. s;. kemist, metallurg o. drifts-ing. inom järn- o. stålind.",
                    "years": {
                        "start_year": 1916,
                        "end_year": 1923
                    },
                    "organization": "Sverige, Norge o*. USA"
                },
                {
                    "position": "s. kemist",
                    "years": {
                        "start_year": 1928,
                        "end_year": 1931
                    },
                    "organization": "A-B Kemiska Patenter i Landskr."
                }
            ]
        },
        "1": {
            "full_name": "Ebbe Waldemar Reimer",
            "location": "Malmö",
            "occupation": "med. lic, prakt, läkare",
            "birth_details": {
                "date": "21/07/1909",
                "place": "Malmö",
                "parents": "av kassör Anders R. o. Elise Hansson"
            },
            "education": [
                {
                    "degree": "Stud:ex.",
                    "year": "1928",
                    "institution": "i Malmö"
                },
                {
                    "degree": "med. kand.",
                    "year": "1932",
                    "institution": "Lund"
                },
                {
                    "degree": "med. lic.",
                    "year": "1937",
                    "institution": "Lund"
                }
            ],
            "career": [
                {
                    "position": "Tf. prov:läk. i Delsbo distr.",
                    "years": {
                        "start_year": 1936,
                        "end_year": 1936
                    }
                },
                {
                    "position": "ord. und :läk. v. Linköp. las.",
                    "years": {
                        "start_year": 1942,
                        "end_year": 1945
                    }
                },
                {
                    "position": "prakt. läk.",
                    "years": {
                        "start_year": 1945,
                        "end_year": null
                    },
                    "organization": "Malmö"
                }
            ],
            "family": {
                "spouse": "Ingrid Norden",
                "marriage_year": "42!",
                "children": [
                    {
                        "name": "Arne",
                        "birth_year": "43"
                    },
                    {
                        "name": "Ålke",
                        "birth_year": "4¾"
                    },
                    {
                        "name": "Ulla",
                        "birth_year": "47"
                    }
                ]
            }
        },
        "2": {
            "full_name": "Otta Emil Nilsson Reimiers",
            "location": "Tyringe",
            "occupation": "överläkare",
            "birth_details": {
                "date": "24/01/1865",
                "place": "Kattarp, Malmöh. 1.",
                "parents": "av Nils Jönsson o. Per-nilila Persson"
            },
            "education": {
                "degree": "Med. lic",
                "year": "03",
                "institution": "Stud :res. t. Tyskl., Engl., Ital. o. USA"
            },
            "career": {
                "position": "Läk. v. Tyringe badanst. o. san.",
                "years": {
                    "start_year": 1905,
                    "end_year": null
                },
                "organization": "Tyringe"
            },
            "family": {
                "spouse": "Sigrid Wilén",
                "marriage_year": "04",
                "children": [
                    {
                        "name": "Sigyn",
                        "birth_year": "05"
                    },
                    {
                        "name": "Inger",
                        "birth_year": "06"
                    },
                    {
                        "name": "Arne",
                        "birth_year": "10"
                    },
                    {
                        "name": "Guilveig (Gulle)",
                        "birth_year": "18"
                    }
                ]
            }
        }
    }
}