{
    "original": "Behring, Caspar Victor,\nbankdirektör, Ystad, f. 8/4/90 i Färlövs förs.,\nKrist. 1., av kassören Olof Andersson\no. Kerstin Andersson. G. 35 m.\nIngeborg Gustafsson. Barn: Märta f. 32.\n— Stud:ex. i Kristianstad 07. Anst. i\ndåv. Bank A-B Södra Sverige i\nKristianstad fr. 07, tj :man v. bankens\nkont.   i  Jönköp.  08,   kassör   13,   kamr.\n\n17,   dir. v. Sv. Hand :bankens kont. i\nYstad sed. 25. Led. av styr. f. System\nA-B i Ystad o. Ystads Teater A-B.M\n\nBehrman, Otto Wilhelm,\nlasaretts-läkare, Hälsingborg, f. 6/11/94 i Kung\nKarl, Västmanl. 1,, av prov:läk. Wirth.\n\nB.   o. Maria Brakel. G. 22 m. Ellen\nÖström. B!arn: Bertil f. 23;, Anna\nMaria 26, Karin 28, Greta 37. — Med.\nlic. 21, sned. dr 36. Und :läk. v.\nHu-diksvalils las. 22-26, sjukstuguläik. i\nKalix 26-31, und:läk. v. öronklin. i Upps.\n311-36, å öronavd. v. Sahlgr. sjukh. i\nGbg 36-37, las:läk, v. öronavd. å\nSithlms 1. centr:las. 37-42, å Hälsingb.\nlas. Ifr. 42. Skr.: Der Zeugeversuch\n(gradiavh.), div. andra skr. inotn\nöron-,  n(äs- o.  halssjukd. otmr.\n\nBeijer, Gottfried Per Gunnar,\narkitekt, Lomma, f. 25/11/91 i Malmö av\nPer Hjalmar B. o. Agnes Amalia\nElisabet Hedman. G. 28 m. Liv Berlin.\nBarn: Per f. 30, Lars 35. — Ex. fr.\ntekn. elem:sk. i Malmö 11, stud. v.\nTechn. Hochsch. i Darmstadt 11-18,\narkit: ex. där. Anst. v. arkit: firman\nEwe &amp; Melin i Malmö 18-20, h. arkit.\n\nC.   B. Comstock i New York 20-22, h.\nlänsarkit. Nils A. Blanck i Malmö\n22-23, lär. v. Hvilans lantm:- o.\nfolk-högsk. 25-35, förste lär. v. Samf. f.\nhemb :vård byggmäst :sk. å Hvilan\n27-35, lär. v. tekn. lärov. i Malmö\n31-35, ämneslär. i husbyggn :lära o.\nritn. v. Alnarp fr. 35. Bl. a. utf.\nkont:-¾yggn. f. Skånska Cement A-B i\nLimhamn (25), rest. Stranden där (25),\nfolkhögsk :byggn. å Hvilan (30, 34), i\nSkurup (33), kont :byggn. f. Iföverken\ni Bromölla (35), bon:hus, lantgård,\nm. m. Tills. m. fil. lic. F. Hazelius\nredig. Skånska gårdar o. hus (26-32).\nSkr.: Stud. rör. lantm :byggn. (32),\nVentilation av husdj :stallar (34), upps.\ni div. fackpubl. LSTF 30-36.\n\n",
    "structured": {
        "1": {
            "full_name": "Caspar Victor Behring",
            "location": "Ystad",
            "occupation": "Bankdirektör",
            "birth_details": {
                "date": "08/04/1890",
                "place": "Färlöv",
                "parents": "Olof Andersson o. Kerstin Andersson"
            },
            "education": [
                {
                    "degree": "Stud:ex.",
                    "year": "1907",
                    "institution": "Kristianstad"
                }
            ],
            "career": [
                {
                    "position": "Anst. i dåv. Bank A-B Södra Sverige i Kristianstad",
                    "years": {
                        "start_year": 1907,
                        "end_year": 1908
                    },
                    "organization": "dåv. Bank A-B Södra Sverige"
                },
                {
                    "position": "tj:man v. bankens kont.",
                    "years": {
                        "start_year": 1908,
                        "end_year": 1913
                    },
                    "organization": "bankens kont. i Jönköp."
                },
                {
                    "position": "kassör",
                    "years": {
                        "start_year": 1913,
                        "end_year": 1917
                    },
                    "organization": "Sv. Hand :bankens kont."
                },
                {
                    "position": "kamr.",
                    "years": {
                        "start_year": 1917,
                        "end_year": null
                    },
                    "organization": "Sv. Hand :bankens kont. i Ystad"
                }
            ],
            "family": {
                "spouse": "Ingeborg Gustafsson",
                "marriage_year": "1935",
                "children": [
                    {
                        "name": "Märta",
                        "birth_year": "1932"
                    }
                ]
            }
        },
        "2": {
            "full_name": "Otto Wilhelm Behrman",
            "location": "Hälsingborg",
            "occupation": "Lasaretts-läkare",
            "birth_details": {
                "date": "06/11/1894",
                "place": "Kung Karl, Västmanl. 1",
                "parents": "prov:läk. Wirth. B. o. Maria Brakel"
            },
            "education": [
                {
                    "degree": "Med. lic.",
                    "year": "1921",
                    "institution": null
                },
                {
                    "degree": "sned. dr",
                    "year": "1936",
                    "institution": null
                }
            ],
            "career": [
                {
                    "position": "Und :läk. v. Hudiksvall's las.",
                    "years": {
                        "start_year": 1922,
                        "end_year": 1926
                    },
                    "organization": "Hudiksvall's las."
                },
                {
                    "position": "sjukstuguläik. i Kalix",
                    "years": {
                        "start_year": 1926,
                        "end_year": 1931
                    },
                    "organization": null
                },
                {
                    "position": "und:läk. v. öronklin. i Upps.",
                    "years": {
                        "start_year": 1931,
                        "end_year": 1936
                    },
                    "organization": "öronklin. i Upps."
                },
                {
                    "position": "å öronavd. v. Sahlgr. sjukh.",
                    "years": {
                        "start_year": 1936,
                        "end_year": 1937
                    },
                    "organization": "Sahlgr. sjukh."
                },
                {
                    "position": "las:läk, v. öronavd. å Hälsingb. las.",
                    "years": {
                        "start_year": 1942,
                        "end_year": null
                    },
                    "organization": "Hälsingb. las."
                }
            ],
            "family": {
                "spouse": "Ellen Öström",
                "marriage_year": "1922",
                "children": [
                    {
                        "name": "Bertil",
                        "birth_year": "1923"
                    },
                    {
                        "name": "Anna Maria",
                        "birth_year": "1926"
                    },
                    {
                        "name": "Karin",
                        "birth_year": "1928"
                    },
                    {
                        "name": "Greta",
                        "birth_year": "1937"
                    }
                ]
            }
        },
        "3": {
            "full_name": "Gottfried Per Gunnar Beijer",
            "location": "Lomma",
            "occupation": "Arkitekt",
            "birth_details": {
                "date": "25/11/1891",
                "place": "Malmö",
                "parents": "Per Hjalmar B. o. Agnes Amalia Elisabet Hedman"
            },
            "education": [
                {
                    "degree": "Ex. fr. tekn. elem:sk. i Malmö",
                    "year": "1911",
                    "institution": "tekn. elem:sk. i Malmö"
                },
                {
                    "degree": "stud. v. Techn. Hochsch. i Darmstadt",
                    "year": "1911-1918",
                    "institution": "Techn. Hochsch. i Darmstadt"
                },
                {
                    "degree": "arkit: ex. där",
                    "year": null,
                    "institution": "Darmstadt"
                }
            ],
            "career": [
                {
                    "position": "Anst. v. arkit: firman Ewe & Melin i Malmö",
                    "years": {
                        "start_year": 1918,
                        "end_year": 1920
                    },
                    "organization": "arkit: firman Ewe & Melin"
                },
                {
                    "position": "h. arkit.C. B. Comstock i New York",
                    "years": {
                        "start_year": 1920,
                        "end_year": 1922
                    },
                    "organization": "C. B. Comstock i New York"
                },
                {
                    "position": "h. länsarkit. Nils A. Blanck i Malmö",
                    "years": {
                        "start_year": 1922,
                        "end_year": 1923
                    },
                    "organization": "Nils A. Blanck i Malmö"
                },
                {
                    "position": "lär. v. Hvilans lantm:- o. folk-högsk.",
                    "years": {
                        "start_year": 1925,
                        "end_year": 1935
                    },
                    "organization": "Hvilans lantm:- o. folk-högsk."
                },
                {
                    "position": "lär. v. Samf. f. hemb :vård byggmäst :sk. å Hvilan",
                    "years": {
                        "start_year": 1927,
                        "end_year": 1935
                    },
                    "organization": "Samf. f. hemb :vård byggmäst :sk. å Hvilan"
                },
                {
                    "position": "lär. v. tekn. lärov. i Malmö",
                    "years": {
                        "start_year": 1931,
                        "end_year": 1935
                    },
                    "organization": "tekn. lärov. i Malmö"
                },
                {
                    "position": "ämneslär. i husbyggn :lära o. ritn. v. Alnarp",
                    "years": {
                        "start_year": 1935,
                        "end_year": null
                    },
                    "organization": "Alnarp"
                }
            ],
            "family": {
                "spouse": "Liv Berlin",
                "marriage_year": "1928",
                "children": [
                    {
                        "name": "Per",
                        "birth_year": "1930"
                    },
                    {
                        "name": "Lars",
                        "birth_year": "1935"
                    }
                ]
            }
        }
    }
}