{
    "original": "JEANSSON, J BIRGER, direktör,\nryttmästare, Kalmar, f i Kalmar 27/7/94 av\nkonsul John J o Sigrid Maijström.\nRes:off:ex 14, DHS 17, verkst dir\nÅngbåts ab Kalmarsund 20-65 o Kalmar\nånigkvarns K/B 52-57. - Ryttm K 3\n29-64. - Ordf Sv hdlsbkns lokalstyr 36-52,\nv ordf Smal o Blek hdlskamm 42-64,\nstyr :led Städernas allm brandstodsbol\n44-64. - Utm: KVO, RNO,\nRFinl-VROlkl. - Hobbies: jakt, fiske, segling.\nGift 21 m Henrietta Norberg f 98, dtr\nt brukspatron Per Henrik N o Olga\nGiörud. - Barn: Ebba f 26.\n\nJEANSSON,   GÖSTA   T,   vicekonsul,\n\nKalmar, f i Kalmar 21/2/01 av dir\nRagnar L J o Tyra Bruun.\nStud:ex 20, stud hdlshögsk Köln 20-21,\ni Engl 23, tjg sv gen :konsulatet\nMarseille 21-22, etabl firma Neico G\nJeansson &amp; Co Hamburg 23, verkst dir där\n24-28, disp Margarin ab Svea sed 28,\nab Liva fabr sed 46, verkst dir K/B\n\nRagnar L Jeansson &amp; Söner sed 42, ab\nKalmar marzipanfabr sed 52. - Styr :led\novanst bol o Margarinbolaget ab, led\nKalmar hamndirektion 29-50, ch\nKalmarsunds SVF 34-46. - Nederl\nvicekonsul Kalmar sed 29. - Utm: RVO,\nKGr-S:tGKO, Of f NedONO, SVKGM,\nSvFMSM, NedSM, DTK. - Hobbies: jakt, golf,\nmotorsport.\n\nGift 24 m Ann-Marie Ericson f 01, dtr\nt syssloman A T E o Hildegard Sjögren.\n- Barn: Gösta, Anita.\n\nJEANSSON, JAN C-H, revisor,\nKalmar, f i Kalmar 26/7/35 av rev Heimer\nJ o Irma Emilsson.\n\nStud:ex 54, DHG 59, eo tax:rev länsstyr\nUpps 59, l :e tax:rev där 60, rev Heimer\nJeanssons rev :byrå ab Kalmar sed 62.\n-Hobby: golf.\n\nGift 59 m Agneta Brunzell f 37, dtr t\ntillsynslär Olof B o Karin B. - Barn:\nJonas f 61, Magnus f 63.\n\n",
    "structured": {
        "0": {
            "full_name": "JEANSSON, J BIRGER",
            "location": "Kalmar",
            "occupation": "direktör, rytmmästare",
            "birth_details": {
                "date": "27/07/1894",
                "place": "Kalmar",
                "parents": "konsul John J o Sigrid Maijström"
            },
            "education": [
                {
                    "degree": "Res:off:ex",
                    "year": "1914",
                    "institution": "DHS"
                },
                {
                    "degree": "verkst dir",
                    "year": "1917",
                    "institution": "Ångbåts ab Kalmarsund"
                }
            ],
            "career": [
                {
                    "position": "Ryttm K 3",
                    "years": {
                        "start_year": 1929,
                        "end_year": 1964
                    },
                    "organization": null
                },
                {
                    "position": "Ordf Sv hdlsbkns lokalstyr",
                    "years": {
                        "start_year": 1936,
                        "end_year": 1952
                    },
                    "organization": null
                }
            ],
            "family": {
                "spouse": "Henrietta Norberg",
                "marriage_year": "1921",
                "children": [
                    {
                        "name": "Ebba",
                        "birth_year": "1926"
                    }
                ],
                "parents": null
            },
            "hobbies": [
                "jakt",
                "fiske",
                "segling"
            ]
        },
        "1": {
            "full_name": "JEANSSON, GÖSTA T",
            "location": "Kalmar",
            "occupation": "vicekonsul",
            "birth_details": {
                "date": "21/02/1901",
                "place": "Kalmar",
                "parents": "dir Ragnar L J o Tyra Bruun"
            },
            "education": [
                {
                    "degree": "Stud:ex",
                    "year": "1920",
                    "institution": null
                },
                {
                    "degree": null,
                    "year": "20-21",
                    "institution": "stud hdlshögsk Köln"
                },
                {
                    "degree": null,
                    "year": "23",
                    "institution": "i Engl"
                }
            ],
            "career": [
                {
                    "position": null,
                    "years": {
                        "start_year": 1921,
                        "end_year": 1922
                    },
                    "organization": "sv gen :konsulatet Marseille"
                },
                {
                    "position": "verkst dir",
                    "years": {
                        "start_year": 1924,
                        "end_year": 1928
                    },
                    "organization": "Neico G Jeansson & Co Hamburg"
                },
                {
                    "position": "disp",
                    "years": {
                        "start_year": 1928,
                        "end_year": null
                    },
                    "organization": "Margarin ab Svea"
                },
                {
                    "position": "verkst dir",
                    "years": {
                        "start_year": 1942,
                        "end_year": null
                    },
                    "organization": "ab Kalmar marzipanfabr"
                }
            ],
            "family": {
                "spouse": "Ann-Marie Ericson",
                "marriage_year": "1924",
                "children": [
                    {
                        "name": "Gösta",
                        "birth_year": null
                    },
                    {
                        "name": "Anita",
                        "birth_year": null
                    }
                ],
                "parents": null
            },
            "hobbies": [
                "jakt",
                "golf",
                "motorsport"
            ]
        },
        "2": {
            "full_name": "JEANSSON, JAN C-H",
            "location": "Kalmar",
            "occupation": "revisor",
            "birth_details": {
                "date": "26/07/1935",
                "place": "Kalmar",
                "parents": "rev Heimer J o Irma Emilsson"
            },
            "education": [
                {
                    "degree": "Stud:ex",
                    "year": "1954",
                    "institution": null
                },
                {
                    "degree": "tax:rev",
                    "year": "1959",
                    "institution": "l :e tax:rev"
                }
            ],
            "career": [
                {
                    "position": "eo tax:rev",
                    "years": {
                        "start_year": 1960,
                        "end_year": null
                    },
                    "organization": "länsstyr Upps"
                },
                {
                    "position": null,
                    "years": null,
                    "organization": "Heimer Jeanssons rev :byrå ab Kalmar"
                }
            ],
            "family": {
                "spouse": "Agneta Brunzell",
                "marriage_year": "1959",
                "children": [
                    {
                        "name": "Jonas",
                        "birth_year": "1961"
                    },
                    {
                        "name": "Magnus",
                        "birth_year": "1963"
                    }
                ],
                "parents": null
            },
            "hobbies": [
                "golf"
            ]
        }
    }
}