{
    "original": "JOHNSON, MARTIN W, tandläkare,\nTranås, f i Åshammar, Gävleb l, 30/11/\n17 av hemm:äg Oscar J o Johanna\nJönsson.\n\nStud:ex Gbg 37, tandl:ex Sthlm 43,\nass :tandl Tranås 43, distr :tandl o förest\ndistr:tandpoliklin Tranås 43-48,\npriv:prakt Tranås sed 48. - Medl Odd\nFellow, Rotary, SHT. - Hobbies:\nrecitation, foto.\n\nGift 43 m tandl Ingrid Spetz f 18, dtr\nt övering Emil S o Annie Anderson.\n-Barn: Lennart f 45, Eva f 47, Annika\nf 50.\n\nJONSSON, NILS-ÅKE, chefsåklagare,\nVisby, f i Karlstad 8/5/25 av plåtsl:mäst\nWaldemar J o Ester Berggren.\nStud:ex Karlstad 46, jur kand Sthlm 54,\nstadsfisk :ass Sthlm 54, e stadsfisk Gävle\n55-56, tingstjg Gästrikl ö doms 57-58,\nlandsfogdeass öl län 59-64, chefsåkl\nVisby sed 65.\n\nGift 56 m Ulla Edvardsson f 28, dtr t\nköpm John Edvard Eriksson o Vendia\nE.\nJOHNSSON, J OLOF, fd kanslichef,\n\nGbg, f i Asarum, Blek l, 11/9/86 av\nlantbr John J o Carolina Möller.\nJur kand Lund 10, tingstjg 10-12, tjg\nSvea hovr 12-17, not i riksd\nbevilln:-utsk 14 o 15, i Gbgs DK 17-26, sekr\nStadsfullm 26-5(2, kanslich Gbgs\nstadskoll 32-52. - Led styr för förvaltn av\napot Fredr Mossbergs donation 25-52,\nGbgs städs rättshj:anst 26-51, sekr Gbgs\npensionärshemsnd 18-59, Olof o\nCaro-line Wijks stift 25-61, Bost ab Nutiden\n17-63, Gbgs o Boh l bost:kred:fören\n30-56. - Utm: KVO, RNO, KFinlLO,\nGs-Ftjt.\n\nGift 40 m Vivan Johnsson f 06, dtr t\nlantbr Nils J o Ida Bengtsson.\n\nJONSON, OSKAR G V, disponent,\nNybro, f i Lenhovda, Kronob l, 18/4/05\nav hemm:äg Albert J o Hulda\nJohannis-dotter.\n\nKalmar språk- o hdlsl 21, disp o ag\nTegelbruks ab Kalksandtegelfabr Nybro\nsed 26 (styr:led). - Nämndeman S Möre\nhäradsr 47-62, komm:fullm Madesjö kn\n50-56, rev där 40-56, Madesjö o Örsjö\nsparbk sed 55. - Medl Lions club.\nGift 42 m Gotty Jeansson f 12. - Barn:\nGudrun f 42, Birgitta f 43.\n\n",
    "structured": {
        "1": {
            "full_name": "MARTIN W JOHNSON",
            "location": "Tranås",
            "occupation": "tandläkare",
            "birth_details": {
                "date": "30/11/1917",
                "place": "Åshammar, Gävleb l",
                "parents": "Oscar J o Johanna Jönsson"
            },
            "education": [
                {
                    "degree": "Stud:ex",
                    "year": "1937",
                    "institution": "Gbg"
                },
                {
                    "degree": "tandl:ex",
                    "year": "1943",
                    "institution": "Sthlm"
                }
            ],
            "career": [
                {
                    "position": "ass :tandl",
                    "years": {
                        "start_year": 1943,
                        "end_year": 1943
                    },
                    "organization": "Tranås"
                },
                {
                    "position": "distr :tandl o förest distr:tandpoliklin",
                    "years": {
                        "start_year": 1943,
                        "end_year": 1948
                    },
                    "organization": "Tranås"
                },
                {
                    "position": "priv:prakt",
                    "years": {
                        "start_year": 1948
                    },
                    "organization": "Tranås"
                }
            ],
            "family": {
                "spouse": "Ingrid Spetz",
                "marriage_year": "1943",
                "children": [
                    {
                        "name": "Lennart",
                        "birth_year": "1945"
                    },
                    {
                        "name": "Eva",
                        "birth_year": "1947"
                    },
                    {
                        "name": "Annika",
                        "birth_year": "1950"
                    }
                ]
            },
            "hobbies": [
                "recitation",
                "foto"
            ]
        },
        "2": {
            "full_name": "NILS-ÅKE JONSSON",
            "location": "Visby",
            "occupation": "chefsåklagare",
            "birth_details": {
                "date": "08/05/1925",
                "place": "Karlstad",
                "parents": "Waldemar J o Ester Berggren"
            },
            "education": [
                {
                    "degree": "Stud:ex",
                    "year": "1946",
                    "institution": "Karlstad"
                },
                {
                    "degree": "jur kand",
                    "year": "1954",
                    "institution": "Sthlm"
                }
            ],
            "career": [
                {
                    "position": "stadsfisk :ass",
                    "years": {
                        "start_year": 1954
                    },
                    "organization": "Sthlm"
                },
                {
                    "position": "chefsåkl",
                    "years": {
                        "start_year": 1965
                    },
                    "organization": "Visby"
                }
            ],
            "family": {
                "spouse": "Ulla Edvardsson",
                "marriage_year": "1956"
            }
        },
        "3": {
            "full_name": "JOHNSSON, J OLOF",
            "location": "Gbg",
            "occupation": "fd kanslichef",
            "birth_details": {
                "date": "11/09/1886",
                "place": "Asarum, Blek l",
                "parents": "lantbr John J o Carolina Möller"
            },
            "education": [
                {
                    "degree": "Jur kand",
                    "year": "1910",
                    "institution": "Lund"
                }
            ],
            "career": [
                {
                    "position": "tingstjg",
                    "years": {
                        "start_year": 1910,
                        "end_year": 1912
                    }
                },
                {
                    "position": "tjg",
                    "years": {
                        "start_year": 1912,
                        "end_year": 1917
                    },
                    "organization": "Svea hovr"
                }
            ],
            "family": {
                "spouse": "Vivan Johnsson",
                "marriage_year": "1940"
            }
        },
        "4": {
            "full_name": "OSKAR G V JONSON",
            "location": "Nybro",
            "occupation": "disponent",
            "birth_details": {
                "date": "18/04/1905",
                "place": "Lenhovda, Kronob l",
                "parents": "Albert J o Hulda Johannis-dotter"
            },
            "education": [
                {
                    "degree": "Kalmar språk- o hdlsl",
                    "year": "1921",
                    "institution": "Kalmar"
                }
            ],
            "career": [
                {
                    "position": "disp o ag",
                    "years": {
                        "start_year": 1926
                    },
                    "organization": "Tegelbruks ab Kalksandtegelfabr Nybro"
                }
            ],
            "family": {
                "spouse": "Gotty Jeansson",
                "marriage_year": "1942",
                "children": [
                    {
                        "name": "Gudrun",
                        "birth_year": "1942"
                    },
                    {
                        "name": "Birgitta",
                        "birth_year": "1943"
                    }
                ]
            }
        }
    }
}