{
    "original": "JACOBSON, ANDERS, disponent,\nBorås, f i Borås 21/3/21 av dir Oscar J o\nJenny Olsen.\n\nAnst Oscar Jacobson ab Borås 39, verkst\ndir o disp där sed 57 (styr :led). -\nStyr:-led Skand bkn Borås.\n\nGift 50 m Ann-Ida Jacobson f 29, dtr t\nStellan J o Viola J. - Barn: Robert f 51,\nAnna-Mika f 55, Katarina f 63.\nJACOBSSON, BENGT A M, leg\nläkare, Gbg, f i Örebro 18/9/19 av\nmissionär Gustaf J o Ester Storm.\nStud:ex Örebro 38, med kand Upps 40,\nmed lic Sthlm 46, underläk neurokir o\nkir klin Seraf :las 47-48, kir o ortop avd\nÖrebro las 49-54, underläk kir klin II\nSahlgr sjh 55-58, bitr överläk där 59-62,\nchefsläk SKF sed 63. - Skr i\ngallvägarnas kirurgi o i röntgenologi.\nGift 45 m Maja Lisa Johanson f 19, dtr\nt grossh Carl J o Lydia Jansson. - Barn:\nUlrika f 46, Per f 48, Mats f 51,\nHarriet f 52.\n\nJAKOBSSON,   BENGT  F,   professor,\n\nGbg, f i Gbg 5/1/16 av ing Charles J o\nHelfrid Pettersson.\n\nCTH 37, tekn dr 48, doc 48, prof i läran\nom maskinelement CTH sed 50. - Anst\nSKF Gbg 38-39, Åtvidabergs ind 39-41,\nlär Tekn gymn Gbg 41-43;, assist CTH\n41-44, beräkn:dh Sv flygmotor ab 44-50.\n\n-  LIVA, ordf IVA :s svetskomm sed 63.\n\n-  Skr: Styrning av bandfordon (drsavh\n47) m m rörande maskinelement. - Utm:\nRNO.\n\nGift 42 m Margareta Eiding f 14, dtr t\nkantor Gillis E o Karin Eriksson.\n-Barn: Håkan f 43, Staffan f 45.\nJACOBSSON, BIRGER H,\ndistrikts-läkare, Motala, f i Frustuna, Södermani\nl, 16/4/21 av kantor John J o Elsa\nAndersson.\n\nStud:ex Norrkpg 41, med kand 44 o\nmed lic Upps 50, öl läk:förordn 47-49,\nunderläk med avd Karlskrona las 50-53,\npediatr avd Hudiksvalls las 53-58,\ndistr:-läk Miotala sed 57. - Hobbies: musik,\nsport, fiske.\n\nGift 50 m fil mag Carin Sundvall f 24,\ndtr t fil kand Gösta S o Svea Jonsson.\n-Barn: Christina f 50, Lena f 52.\n",
    "structured": {
        "0": {
            "full_name": "Anders Jacobson",
            "location": "Borås",
            "occupation": "Disponent",
            "birth_details": {
                "date": "21/03/1921",
                "place": "Borås",
                "parents": "dir Oscar J o Jenny Olsen"
            },
            "education": [],
            "career": [
                {
                    "position": "anst Oscar Jacobson ab Borås",
                    "years": {
                        "start_year": 1939,
                        "end_year": 1957
                    },
                    "organization": "Oscar Jacobson ab Borås"
                },
                {
                    "position": "verkst dir o disp",
                    "years": {
                        "start_year": 1957
                    },
                    "organization": "Oscar Jacobson ab Borås"
                }
            ],
            "family": {
                "spouse": "Ann-Ida Jacobson",
                "marriage_year": "1950",
                "children": [
                    {
                        "name": "Robert",
                        "birth_year": "1951"
                    },
                    {
                        "name": "Anna-Mika",
                        "birth_year": "1955"
                    },
                    {
                        "name": "Katarina",
                        "birth_year": "1963"
                    }
                ]
            }
        },
        "1": {
            "full_name": "Bengt A M Jacobsson",
            "location": "Gbg",
            "occupation": "Läkare",
            "birth_details": {
                "date": "18/09/1919",
                "place": "Örebro",
                "parents": "missionär Gustaf J o Ester Storm"
            },
            "education": [
                {
                    "degree": "Stud:ex",
                    "year": "1938",
                    "institution": "Örebro"
                },
                {
                    "degree": "med kand",
                    "year": "1940",
                    "institution": "Upps"
                },
                {
                    "degree": "med lic",
                    "year": "1946",
                    "institution": "Sthlm"
                }
            ],
            "career": [
                {
                    "position": "underläk neurokir o kir klin Seraf :las",
                    "years": {
                        "start_year": 1947,
                        "end_year": 1948
                    },
                    "organization": "Seraf :las"
                },
                {
                    "position": "underläk kir klin II Sahlgr sjh",
                    "years": {
                        "start_year": 1955,
                        "end_year": 1958
                    },
                    "organization": "Sahlgr sjh"
                }
            ],
            "family": {
                "spouse": "Maja Lisa Johanson",
                "marriage_year": "1945",
                "children": [
                    {
                        "name": "Ulrika",
                        "birth_year": "1946"
                    },
                    {
                        "name": "Per",
                        "birth_year": "1948"
                    },
                    {
                        "name": "Mats",
                        "birth_year": "1951"
                    },
                    {
                        "name": "Harriet",
                        "birth_year": "1952"
                    }
                ]
            }
        },
        "2": {
            "full_name": "Bengt F Jacobsson",
            "location": "Gbg",
            "occupation": "Professor",
            "birth_details": {
                "date": "05/01/1916",
                "place": "Gbg",
                "parents": "ing Charles J o Helfrid Pettersson"
            },
            "education": [
                {
                    "degree": "CTH",
                    "year": "1937",
                    "institution": "CTH"
                },
                {
                    "degree": "tekn dr",
                    "year": "1948",
                    "institution": "CTH"
                }
            ],
            "career": [
                {
                    "position": "prof i läran om maskinelement CTH",
                    "years": {
                        "start_year": 1950
                    },
                    "organization": "CTH"
                },
                {
                    "position": "beräkn:dh Sv flygmotor ab",
                    "years": {
                        "start_year": 1944,
                        "end_year": 1950
                    },
                    "organization": "Sv flygmotor ab"
                }
            ],
            "family": {
                "spouse": "Margareta Eiding",
                "marriage_year": "1942",
                "children": [
                    {
                        "name": "Håkan",
                        "birth_year": "1943"
                    },
                    {
                        "name": "Staffan",
                        "birth_year": "1945"
                    }
                ]
            }
        },
        "3": {
            "full_name": "Birger H Jacobsson",
            "location": "Motala",
            "occupation": "Distriktläkare",
            "birth_details": {
                "date": "16/04/1921",
                "place": "Frustuna, Södermanil",
                "parents": "kantor John J o Elsa Andersson"
            },
            "education": [
                {
                    "degree": "Stud:ex",
                    "year": "1941",
                    "institution": "Norrkpg"
                },
                {
                    "degree": "med kand",
                    "year": "1944",
                    "institution": "Upps"
                },
                {
                    "degree": "med lic",
                    "year": "1950",
                    "institution": "Upps"
                }
            ],
            "career": [
                {
                    "position": "underläk med avd Karlskrona las",
                    "years": {
                        "start_year": 1950,
                        "end_year": 1953
                    },
                    "organization": "Karlskrona las"
                },
                {
                    "position": "pediatr avd Hudiksvalls las",
                    "years": {
                        "start_year": 1953,
                        "end_year": 1958
                    },
                    "organization": "Hudiksvalls las"
                }
            ],
            "family": {
                "spouse": "fil mag Carin Sundvall",
                "marriage_year": "1950",
                "children": [
                    {
                        "name": "Christina",
                        "birth_year": "1950"
                    },
                    {
                        "name": "Lena",
                        "birth_year": "1952"
                    }
                ]
            },
            "hobbies": [
                "musik",
                "sport",
                "fiske"
            ]
        }
    }
}