{
    "original": "JANSON,     CARL-AXEL     AX:SON,\n\ntandläkare, Partilie, f i Västerås 2/5/18\nav köpm Axel J o Nanny Pehrson.\nStud:ex Örebro 37, res:off:ex 40,\ntandl:-ex Sthlm 45, distr:tandl Lysekil 45-46,\npriv:prakt Gbg 46^48, priv:prakt\nPar-tille sed 48, skoltandl 48-50. - Kapt\nträngtr res sed 51.\n\nGift 44 m Anne-Maj Karlen tf 19, dtr t\nlas :syssloman C Hj K o Anna\nAndersson. - Barn: Marianne f 47.\n\nJANSSON, O N EILERT, disponent,\n\nJönköping,   f   i  Uleåborg,   Finl,   1/7/07\nav disp Otto J o Eleonora Broman.\nHdlssk, skofacksk Tyskl, verkst dir, ag\no styr :led ab Oltto Janssons skofabr\nJön-kpg sed 35. - Finl v konsul i Jönkpg\nsed  60.   -   Medl  PB,   Rotary.   -   Utm:\nRVO. - Hobby: golf.\nGift 39 m Evy Strandberg f 08, dtr t\nKristian S o Hilma Johansson. - Barn:\nMarianne f 40, Stefan f 43, Eva f 44.\n\nJANSON, S ERIK, filialchef,\nJönköping, f i Boden 20/11/10 av l:e banmäst\nOlof J o Kristina Johansson.\nRealex 28, ing :ex Stat elektrotekn facksk\nVästerås 38, anläggn:ing Asea Västerås\n38, montageing där 44, ch Asea Spanien\n51-61, Aseas filial Jönkpg sed 63. -\nStyr:-ordf Sv hdlskamm Madrid 59-61\n(styrled 51-61), styr :led Asea Spanien 51-61.\n-Hobby: musik.\n\nGift 38 m Sonja Lindhe f 10, dtr t\nsko-handl Carl L o Clara Johnson. - Barn:\nAnders f 39, Kristina f 43.\n\nJANZON, K GUNNAR, civilingenjör,\n\nVänersborg, f i Sthlm 28/12/09 av ing\nKarl J o Signe Karlsson.\nStud:ex Djursholm 28, KTH 33, ing\nVV:-styr s hamnarb:distr 33, avd:ing n:e n\nhamnarb :distr 37, arb :ch där 39, bitr\narb :ch ab Vägförbättringar s avd 46,\navd:ing Malmö hamnförvaltn 48,\nläns-ing Älvsb l sed 50.\n\nGift 40 m Ruth Lawaetz f 17, dtr t\ngodsäg Joh L o Else-Marie Stokkebye.\n-Barn: Harriet f 42, Anders f 43,\nLennart f 46, Elisabeth f 48.\n\n",
    "structured": {
        "1": {
            "full_name": "Carl-Axel Ax:son Janson",
            "location": "Partille",
            "occupation": "tandläkare",
            "birth_details": {
                "date": "02/05/1918",
                "place": "Västerås",
                "parents": "köpm Axel J o Nanny Pehrson"
            },
            "education": [
                {
                    "degree": "Stud:ex",
                    "year": "1937",
                    "institution": "Örebro"
                },
                {
                    "degree": "res:off:ex",
                    "year": "1940",
                    "institution": "NULL"
                },
                {
                    "degree": "tandl:-ex",
                    "year": "1945",
                    "institution": "Sthlm"
                }
            ],
            "career": [
                {
                    "position": "Kapt trängtr res",
                    "years": {
                        "start_year": 1951,
                        "end_year": "NULL"
                    },
                    "organization": "NULL"
                }
            ],
            "family": {
                "spouse": "Anne-Maj Karlen",
                "marriage_year": "1944",
                "children": [
                    {
                        "name": "Marianne",
                        "birth_year": "1947"
                    }
                ]
            }
        },
        "2": {
            "full_name": "O Neilert Janson",
            "location": "Jönköping",
            "occupation": "disponent",
            "birth_details": {
                "date": "01/07/1907",
                "place": "Uleåborg, Finl",
                "parents": "disp Otto J o Eleonora Broman"
            },
            "education": [
                {
                    "degree": "Hdlssk",
                    "year": "NULL",
                    "institution": "NULL"
                },
                {
                    "degree": "skofacksk Tyskl",
                    "year": "NULL",
                    "institution": "NULL"
                }
            ],
            "career": [
                {
                    "position": "verkst dir, ag o styr :led",
                    "years": {
                        "start_year": 1935,
                        "end_year": "NULL"
                    },
                    "organization": "ab Oltto Janssons skofabr Jön-kpg"
                }
            ],
            "family": {
                "spouse": "Evy Strandberg",
                "marriage_year": "1939",
                "children": [
                    {
                        "name": "Marianne",
                        "birth_year": "1940"
                    },
                    {
                        "name": "Stefan",
                        "birth_year": "1943"
                    },
                    {
                        "name": "Eva",
                        "birth_year": "1944"
                    }
                ]
            }
        },
        "3": {
            "full_name": "Erik Janson",
            "location": "Jönköping",
            "occupation": "filialchef",
            "birth_details": {
                "date": "20/11/1910",
                "place": "Boden",
                "parents": "l:e banmäst Olof J o Kristina Johansson"
            },
            "education": [
                {
                    "degree": "Realex",
                    "year": "1928",
                    "institution": "NULL"
                },
                {
                    "degree": "ing :ex Stat elektrotekn facksk",
                    "year": "1938",
                    "institution": "Västerås"
                }
            ],
            "career": [
                {
                    "position": "Aseas filial Jönkpg",
                    "years": {
                        "start_year": 1963,
                        "end_year": "NULL"
                    },
                    "organization": "Asea"
                }
            ],
            "family": {
                "spouse": "Sonja Lindhe",
                "marriage_year": "1938",
                "children": [
                    {
                        "name": "Anders",
                        "birth_year": "1939"
                    },
                    {
                        "name": "Kristina",
                        "birth_year": "1943"
                    }
                ]
            }
        },
        "4": {
            "full_name": "Gunnar Janzon",
            "location": "Vänersborg",
            "occupation": "civilingenjör",
            "birth_details": {
                "date": "28/12/1909",
                "place": "Sthlm",
                "parents": "ing Karl J o Signe Karlsson"
            },
            "education": [
                {
                    "degree": "Stud:ex",
                    "year": "1928",
                    "institution": "Djursholm"
                },
                {
                    "degree": "KTH",
                    "year": "1933",
                    "institution": "NULL"
                }
            ],
            "career": [
                {
                    "position": "bitr arb :ch",
                    "years": {
                        "start_year": 1946,
                        "end_year": "NULL"
                    },
                    "organization": "ab Vägförbättringar s avd"
                }
            ],
            "family": {
                "spouse": "Ruth Lawaetz",
                "marriage_year": "1940",
                "children": [
                    {
                        "name": "Harriet",
                        "birth_year": "1942"
                    },
                    {
                        "name": "Anders",
                        "birth_year": "1943"
                    },
                    {
                        "name": "Lennart",
                        "birth_year": "1946"
                    },
                    {
                        "name": "Elisabeth",
                        "birth_year": "1948"
                    }
                ]
            }
        }
    }
}