{
    "original": "JÖNSSON, ROLF C W, förste\nstadsdistriktsläkare, Växjö, f i Malmö 18/9/20\nav kamr Edvin J o Alli Carlsen.\nStud:ex Lund 39, med kand 42 o med\nlic Lund 47, underläk med avd\nKarlskrona las 47-49, med avd Hässleholms\nlas 49-52, Westergrenska barnsjh Gävle\n52-5(3, barnavd Växjö las 53)-55, Malmö\nepid:&amp;jh 55-57, 2:e stadsläk Växjö 57,\nl:e stadsdistr:läk där sed 61. - Hobby:\ngolf.\n\nGift 49 m Catharina Stenberg f 20, dtr\nt ing William S o Elsa Nilsson. - Barn:\nUlf f 52, Åsa f 55, Sven o Karin ff 58.\n\nJÖNSSON, STIG, disponent, Mariestad,\nf i Trelleborg 20/9/23 av Åke J o Frida\nSjöberg.\n\nIng:ex Katrineholm 48, ink:ch Atlas sv\nförsäljn ab Malmö 54, Elektro IWO ab\nMariestad 61, disp o verkst dir ab\nIn-terma sed 62. - Led turistndn sed 64.\nGift 55 m Astrid Johanson f 28, dtr t\nCarl J o Karin Appelqvist.\n\nJÖNSSON, STIG B, läroverksadjunkt,\nTranås, f i Örsjö, Malmöh l, 14/6/31 av\nHilding J o Signe Olsson.\nStud:ex 53 o’ fil mag Lund 59. - Kont\nuppb :verket Malmö 48, uppb :verket\nLund 49-50, adj hal Tranås sed 59.\n-Medl Round Table.\n\nGift 57 m Gunilla Löfgren f 34, dtr t\nl :e byråsekr Allan L o Maja Ekelund.\n-Barn: My f 62, Ola f 65.\n\nJÖNSSON, SVEN K A, aukt revisor,\nGbg, f i Gbg 20/8/16 av stat:mäst\nGottfrid J o Hilda Werdelin.\nGbgHdlI 35, rev:ex HHG 49; öl\nprakti-kantanst J Svensson &amp; Bourghardt KB,\nab F W Hasselblad &amp; Co, ab Nord\nrese-bureau o Skand bkn 35-40, anst Leo\n\nBredbergs rev :byrå ab Gbg sed 40\n(del-äg sed 49). - Rev ett flert bolag. - Aukt\nrev 49.\n\nGift 43 m Karin Martinsson f 18, dtr t\nstat :mast Viktor M o Olga Olsson.\n-Barn: Ulf f 48.\n\n",
    "structured": {
        "1": {
            "full_name": "JÖNSSON, ROLF C W",
            "location": "Växjö",
            "occupation": "Förste stadsdistriktsläkare",
            "birth_details": {
                "date": "18/09/1920",
                "place": "Malmö",
                "parents": "Kamr Edvin J och Alli Carlsen"
            },
            "education": [
                {
                    "degree": "Stud:ex",
                    "year": "1939",
                    "institution": "Lund"
                },
                {
                    "degree": "Med kand",
                    "year": "1942",
                    "institution": "Lund"
                },
                {
                    "degree": "Med lic",
                    "year": "1947",
                    "institution": "Lund"
                }
            ],
            "career": [
                {
                    "position": "Underläk",
                    "years": {
                        "start_year": 1947,
                        "end_year": 1949
                    },
                    "organization": "Karlskrona las"
                },
                {
                    "position": "Med avd",
                    "years": {
                        "start_year": 1949,
                        "end_year": 1952
                    },
                    "organization": "Hässleholms las"
                },
                {
                    "position": "Westergrenska barnsjh",
                    "years": {
                        "start_year": 1952,
                        "end_year": 1953
                    },
                    "organization": "Gävle"
                },
                {
                    "position": "Barnavd",
                    "years": {
                        "start_year": 1953,
                        "end_year": 1955
                    },
                    "organization": "Växjö las"
                },
                {
                    "position": "Epid&jh",
                    "years": {
                        "start_year": 1955,
                        "end_year": 1957
                    },
                    "organization": "Malmö"
                },
                {
                    "position": "2:e stadsläk",
                    "years": {
                        "start_year": 1957,
                        "end_year": 1961
                    },
                    "organization": "Växjö"
                },
                {
                    "position": "L:e stadsdistr:läk",
                    "years": {
                        "start_year": 1961
                    },
                    "organization": "Växjö"
                }
            ],
            "family": {
                "spouse": "Catharina Stenberg",
                "marriage_year": "1949",
                "children": [
                    {
                        "name": "Ulf",
                        "birth_year": "1952"
                    },
                    {
                        "name": "Åsa",
                        "birth_year": "1955"
                    },
                    {
                        "name": "Sven",
                        "birth_year": "1958"
                    },
                    {
                        "name": "Karin",
                        "birth_year": "1958"
                    }
                ]
            },
            "hobbies": [
                "Golf"
            ]
        },
        "2": {
            "full_name": "JÖNSSON, STIG",
            "location": "Mariestad",
            "occupation": "Disponent",
            "birth_details": {
                "date": "20/09/1923",
                "place": "Trelleborg",
                "parents": "Åke J och Frida Sjöberg"
            },
            "education": [
                {
                    "degree": "Ing:ex",
                    "year": "1948",
                    "institution": "Katrineholm"
                }
            ],
            "career": [
                {
                    "position": "Ink:ch",
                    "years": {
                        "start_year": 1954
                    },
                    "organization": "Atlas sv försäljn ab Malmö"
                },
                {
                    "position": "Disp o verkst dir",
                    "years": {
                        "start_year": 1962
                    },
                    "organization": "Interma"
                }
            ],
            "family": {
                "spouse": "Astrid Johanson",
                "marriage_year": "1955"
            }
        },
        "3": {
            "full_name": "JÖNSSON, STIG B",
            "location": "Tranås",
            "occupation": "Läroverksadjunkt",
            "birth_details": {
                "date": "14/06/1931",
                "place": "Örsjö, Malmö"
            },
            "education": [
                {
                    "degree": "Stud:ex",
                    "year": "1953"
                },
                {
                    "degree": "Fil mag",
                    "year": "1959",
                    "institution": "Lund"
                }
            ],
            "career": [
                {
                    "position": "Adj hal",
                    "years": {
                        "start_year": 1959
                    },
                    "organization": "Tranås"
                }
            ],
            "family": {
                "spouse": "Gunilla Löfgren",
                "marriage_year": "1957",
                "children": [
                    {
                        "name": "My",
                        "birth_year": "1962"
                    },
                    {
                        "name": "Ola",
                        "birth_year": "1965"
                    }
                ]
            }
        },
        "4": {
            "full_name": "JÖNSSON, SVEN K A",
            "location": "Gbg",
            "occupation": "Aukt revisor",
            "birth_details": {
                "date": "20/08/1916",
                "place": "Gbg",
                "parents": "Stat:mäst Gottfrid J och Hilda Werdelin"
            },
            "education": [
                {
                    "degree": "GbgHdlI",
                    "year": "1935"
                },
                {
                    "degree": "Rev:ex",
                    "year": "1949",
                    "institution": "HHG"
                }
            ],
            "career": [
                {
                    "position": "Aukt rev",
                    "years": {
                        "start_year": 1949
                    }
                }
            ],
            "family": {
                "spouse": "Karin Martinsson",
                "marriage_year": "1943",
                "children": [
                    {
                        "name": "Ulf",
                        "birth_year": "1948"
                    }
                ]
            }
        }
    }
}