{
    "original": "Aggeryd, Bengt Ture Axel,\ncivilingenjör, Höganäs, f. 17/9/19 i Sollefteå\nav kÖpm. David Andersson o. Hilly\nSandström. G. 46 m. civ:ing. Barbro\nWik. — Stud:ex. i Luleå 38, CTH (k)\n\n44.  Assist, h. prof. J. A. Hedvall v.\nin-st.   f.   silikatkem.   forskn.  v.   CTH 44-\n\n45,   forskn :ing. v. Höganäs-Billesholms\nA-B centrilab. 45-46, driftsing. v.\nsamma föret. fabr. i Höganäs sed. 47.\nLed. av styr. f. Chalmers stud :kår\n43-•44 o. f. Höganäsbol. tj :mannafören.\nsed. 46. Skr.: Tegelundersökningar (del\nI tills. m. J. A. Hedvall o. Claes\nHedin 44), Kalkens reaktivitet i\npulverblandningar m. kiseldioxid,\naluminiumoxid o. fältspat (45). Hobbies: musik,\nfiske o. bridge.\n\nAgrell, Ivar Per Sigurd, docent,\nLund, f. 2/7/12 i Lund av prof. Sigurd\nA. o. Anna Österman. G. 35 m.\nInga-Greta  Fryklöf.    Barn:  Per  Sigurd  f.\n\n37,   Beata 44. — Studrex. v.\nKatedr:-sk. i Lund 30,  fil. kand. 36,  fil. mag.\n\n38,    fil. lic. 41, disp. f. drsgr. 41 v.\nLunds univ. E. o. aman. v. zool. in st.\ni Lund 32-40, aman. där 40-42, doc. i\nzool. fr. 42. Ordf. f. Lunds\nstud:-kår 42, f. Lunds stud:kårs intr :byrå\nsed. 44. Skr.: vetensk. arb. huv:sakl.\növ. insektekologi, -fysiol. o.\n-systematik.\n\nAhde, Sven Hugo, advokat, notarius\npublicus, Hässleholm, f. 28/2/82 i\nHässleholm. G. 16 m. Ruth Åkerman. —\nMog:ex. v. Lunds priv. elem:sk. 01,\njur. prel :ex. 02, hovr:ex. 10. E. o.\nnot. i Skånska hovr. 10, tingstjg. i\nBräkne här. doms. 11-12, förordn. s.\nborgm., tjg. i länsstyr. Eg. adv:rör. i\nHässleholm sed. 15. Led. av Sv:es\nadv:samf. sed. 19. Not. publ. i\nHässleholm sed. 34, led. av byggn :nd\n23-37, av stadsstyr. 24-37, ordf. 28-37, av\n\nbrandstyr. 25-37, av hälsov:nd 28-37,\nordf. i hyresnd i Hässleholms stad o.\nOsby köp. sed. 42, i Bjärnums\nmun:-samh.  sed.  45.\n\n",
    "structured": {
        "0": {
            "full_name": "Bengt Ture Axel Aggeryd",
            "location": "Höganäs",
            "occupation": "civilingenjör",
            "birth_details": {
                "date": "17/09/1919",
                "place": "Sollefteå",
                "parents": "kÖpm. David Andersson & Hilly Sandström"
            },
            "education": [
                {
                    "degree": "Stud:ex.",
                    "year": "1938",
                    "institution": "Luleå"
                },
                {
                    "degree": "Civ:ing.",
                    "year": "1944",
                    "institution": "CTH (k)"
                }
            ],
            "career": [
                {
                    "position": "Assist",
                    "years": {
                        "start_year": 1944,
                        "end_year": 1945
                    },
                    "organization": "h. prof. J. A. Hedvall v. in-st. f. silikatkem. forskn. v. CTH"
                },
                {
                    "position": "forskn :ing.",
                    "years": {
                        "start_year": 1945,
                        "end_year": 1946
                    },
                    "organization": "Höganäs-Billesholms A-B centrilab"
                },
                {
                    "position": "driftsing.",
                    "years": {
                        "start_year": 1947
                    },
                    "organization": "samma föret. fabr. i Höganäs"
                }
            ],
            "family": {
                "spouse": "civ:ing. Barbro Wik",
                "marriage_year": "1946",
                "children": [],
                "parents": "kÖpm. David Andersson & Hilly Sandström"
            },
            "publications": [
                {
                    "title": "Tegelundersökningar",
                    "year": "1944",
                    "type": "del I tills. m. J. A. Hedvall & Claes Hedin"
                },
                {
                    "title": "Kalkens reaktivitet i pulverblandningar",
                    "year": "1945",
                    "type": "m. kiseldioxid, aluminiumoxid o. fältspat"
                }
            ],
            "hobbies": [
                "musik",
                "fiske",
                "bridge"
            ]
        },
        "1": {
            "full_name": "Ivar Per Sigurd Agrell",
            "location": "Lund",
            "occupation": "docent",
            "birth_details": {
                "date": "02/07/1912",
                "place": "Lund",
                "parents": "prof. Sigurd A. & Anna Österman"
            },
            "education": [
                {
                    "degree": "Studrex.",
                    "year": "1930",
                    "institution": "Katedr:-sk. i Lund"
                },
                {
                    "degree": "fil. kand.",
                    "year": "1936",
                    "institution": "Lund"
                },
                {
                    "degree": "fil. mag.",
                    "year": "1938",
                    "institution": "Lund"
                },
                {
                    "degree": "fil. lic.",
                    "year": "1941",
                    "institution": "Lunds univ."
                }
            ],
            "career": [
                {
                    "position": "E. o. aman.",
                    "years": {
                        "start_year": 1940,
                        "end_year": 1942
                    },
                    "organization": "zool. in st. i Lund"
                },
                {
                    "position": "doc.",
                    "years": {
                        "start_year": 1942
                    },
                    "organization": "zool. fr. 42"
                }
            ],
            "family": {
                "spouse": "Inga-Greta Fryklöf",
                "marriage_year": "1935",
                "children": [
                    {
                        "name": "Per Sigurd",
                        "birth_year": "1937"
                    },
                    {
                        "name": "Beata",
                        "birth_year": "1944"
                    }
                ],
                "parents": "prof. Sigurd A. & Anna Österman"
            }
        },
        "2": {
            "full_name": "Sven Hugo Ahde",
            "location": "Hässleholm",
            "occupation": "advokat, notarius publicus",
            "birth_details": {
                "date": "28/02/1882",
                "place": "Hässleholm"
            },
            "education": [
                {
                    "degree": "Mog:ex.",
                    "year": "1901",
                    "institution": "Lunds priv. elem:sk."
                },
                {
                    "degree": "jur. prel:ex.",
                    "year": "1902"
                }
            ],
            "career": [
                {
                    "position": "E. o. not.",
                    "years": {
                        "start_year": 1910
                    },
                    "organization": "Skånska hovr."
                }
            ],
            "family": {
                "spouse": "Ruth Åkerman",
                "marriage_year": "1916"
            },
            "community_involvement": [
                {
                    "role": "Ordf.",
                    "organization": "Lunds stud:-kår",
                    "years": "1942"
                }
            ],
            "board_memberships": [
                {
                    "position": "ordf.",
                    "organization": "hyresnd i Hässleholms stad o. Osby köp.",
                    "years": "1942"
                }
            ],
            "hobbies": []
        }
    }
}