{
    "original": "Anshelm, Carl, teol. dr, kyrkoherde,\nkontraktsprost, Förslövsholm, f. 21/4/\n82 i Gråmanstorp, Krist. 1. G. 13 m.\nAnna-Kristina (Lisen) Sundman.\nBlarn: Gunnar f. 14, paisit:adj. —\nStud:-ex. i Hälsingb. 01, teol. kand. i Lund\no. prästv. 08, teol. dr 35. Stud:res. t.\nTyskl., Schweiz o. Engl.\nDomkyrkov:-past. i Lund 12, resesekr. i Sv. kyrk.\ninliss :styr. 14, domkyrkokommin. i\nLund 16, kyrkoh. i Förslöv o. Grevie\n32, kontr :prost i Bjäre kontr. 45. Ordf.\ni Lunds miss :sällsk. o. i stiftets miss\n:-råd 22-23-, i kyrkofulilm. o.\nkyrkostämmor. Skr.: Svensk mission (25), Bisk.\nHans Peter Hallbeck I-II (27), Peter\nFjellstedt I-II (30, 35). LNO 43.\n\nAppelin, Carl Anders Folke,\nbankdirektör, Lund, f. 28/9/89 i Mailmö av\nstat:skriv. Carl A. o. Anna Westerberg.\nG. 28 m. Magnhild Engström. Barn:\nInger f. 30, Marianne 33. — Stud:ex.\ni Skara 07, res:off:ex. 09. Und:löjtn.\ni Skarab. reg. res. 09, löjtn. 16, avsk.\n20. Anst. v. Sv. Lantm. Bank 18, kassör\ni Vadstena 19, kamrer i Skara 22,\nkamrer v. Jordbr :bank. i Skara 23&gt;, kon t\n:-chef 29, dir. i Karlstad 36, i Lund fr.\n42. Stadsrev. i Skara 32, ordf. 33-36,\nlänsstyr. rev. i Värml. rnruseifören.\n37-42,  styr:led. i  fil:fören.  av  Sv.  bank-\n\nm:fören. 22-29, ordf. 29-36.\nBankm:-fören. hed :t.\n\nAraskog, Nils, kronokamrerare,\nMalmö, f. 18/2/92 i Hyby, Malmöh. 1.,\nav kontr :prosten A. N. A. o. Carolina\nBenedikta Grönberg. G. 1. 20 m. Lisa\nKallstenius; 2. 41 m. Anna Olsson.\nBarn: Nils f. 22, Rolf 24, Carin 26. —\nS’tud:ex. i Lund 10, jur. kand. där\n15. E. not. v. rådhusr. i Malmö 18-20,\nexekutionsnot. 20, assessor 21,\nkrono-kamr. i Malmö sed. 32. Sekr. i\nMalmö stads sammansatta kyrkoråd\n18-22, i lönend 22-41, sekr. samt\nsuppl. i styr. f. Flensburgska\nvård-anst. i Malmö 25-30, av länsstyr.\nutsedd led. av en av Malmö stads\ntax:ndr 20-28,  ordf.  i dito  sed. 29.\n\n",
    "structured": {
        "1": {
            "full_name": "Carl Anshelm",
            "location": "Förslövsholm",
            "occupation": "teol. dr, kyrkoherde, kontraktsprost",
            "birth_details": {
                "date": "21/04/1882",
                "place": "Gråmanstorp"
            },
            "education": [
                {
                    "degree": "Stud:-ex.",
                    "year": "1901",
                    "institution": "Hälsingborg"
                },
                {
                    "degree": "teol. kand.",
                    "year": "1908",
                    "institution": "Lund"
                },
                {
                    "degree": "prästv.",
                    "year": "1908",
                    "institution": "Lund"
                },
                {
                    "degree": "teol. dr",
                    "year": "1935",
                    "institution": "NULL"
                }
            ],
            "career": [
                {
                    "position": "Domkyrkov:-past. i Lund",
                    "years": {
                        "start_year": 1912,
                        "end_year": 1916
                    },
                    "organization": "NULL"
                },
                {
                    "position": "domkyrkokommin. i Lund",
                    "years": {
                        "start_year": 1916,
                        "end_year": 1932
                    },
                    "organization": "NULL"
                },
                {
                    "position": "kyrkoh. i Förslöv o. Grevie",
                    "years": {
                        "start_year": 1932,
                        "end_year": 1945
                    },
                    "organization": "NULL"
                },
                {
                    "position": "kontr :prost i Bjäre kontr.",
                    "years": {
                        "start_year": 1945,
                        "end_year": 1945
                    },
                    "organization": "NULL"
                }
            ],
            "family": {
                "spouse": "Anna-Kristina (Lisen) Sundman",
                "marriage_year": "NULL",
                "children": [
                    {
                        "name": "Gunnar",
                        "birth_year": "14"
                    }
                ]
            }
        },
        "2": {
            "full_name": "Carl Anders Folke Appelin",
            "location": "Lund",
            "occupation": "bankdirektör",
            "birth_details": {
                "date": "28/09/1889",
                "place": "Mailmö"
            },
            "education": [
                {
                    "degree": "Stud:ex.",
                    "year": "1907",
                    "institution": "Skara"
                },
                {
                    "degree": "res:off:ex.",
                    "year": "1909",
                    "institution": "NULL"
                }
            ],
            "career": [
                {
                    "position": "avsk.",
                    "years": {
                        "start_year": 1920,
                        "end_year": 1920
                    },
                    "organization": "NULL"
                },
                {
                    "position": "dir. i Karlstad",
                    "years": {
                        "start_year": 1936,
                        "end_year": 1942
                    },
                    "organization": "NULL"
                },
                {
                    "position": "i Lund",
                    "years": {
                        "start_year": 1942,
                        "end_year": 1942
                    },
                    "organization": "NULL"
                }
            ],
            "family": {
                "spouse": "Magnhild Engström",
                "marriage_year": "28",
                "children": [
                    {
                        "name": "Inger",
                        "birth_year": "30"
                    },
                    {
                        "name": "Marianne",
                        "birth_year": "33"
                    }
                ]
            }
        },
        "3": {
            "full_name": "Nils Araskog",
            "location": "Malmö",
            "occupation": "kronokamrerare",
            "birth_details": {
                "date": "18/02/1892",
                "place": "Hyby"
            },
            "education": [
                {
                    "degree": "S’tud:ex.",
                    "year": "1910",
                    "institution": "Lund"
                },
                {
                    "degree": "jur. kand.",
                    "year": "1915",
                    "institution": "Lund"
                }
            ],
            "career": [
                {
                    "position": "exekutionsnot.",
                    "years": {
                        "start_year": 1920,
                        "end_year": 1920
                    },
                    "organization": "NULL"
                },
                {
                    "position": "krono-kamr. i Malmö",
                    "years": {
                        "start_year": 1932,
                        "end_year": 1932
                    },
                    "organization": "NULL"
                }
            ],
            "family": {
                "spouse": "Anna Olsson",
                "marriage_year": "41",
                "children": [
                    {
                        "name": "Nils",
                        "birth_year": "22"
                    },
                    {
                        "name": "Rolf",
                        "birth_year": "24"
                    },
                    {
                        "name": "Carin",
                        "birth_year": "26"
                    }
                ]
            }
        }
    }
}