{
    "original": "Andersson, Gunnar,\ntaxeringsintendent, Malmö, f. 13/11/93 i Högseröd,\nMalmöh. 1., av godsäg. N. A. o. Maria\nMårtensson. G. m. Elisabeth\nAndersson. Barn: Arne Gunnarsson f. 20,\ning., Sven Gunnarsson 25, jur. stud.,\nHelena Gunnarsson 30, fil. stud., Eskil\nGunnarsson 32. — Stud:ex. i Lund 12,\njur. kand. där 21. Bitr. jurist v.\nlänsstyr, i Malmö’ 21, länsbokh. 25,\nlänsassessor 39 o. taxdntend. sed. 44. V.\nordf. i sällsk. Isbjörnarna sed. 43.\nHobby:  vinterbadning.  RVO.\n\nAndersson, Erik Gunnar,\ncivilingenjör, Arlöv, f. 15/9/06 i Nora bergsfors.,\nÖrebro 1., av August A. o. Ida\nAndersson. G. 39 m. Frida Olsson. ■—\nS’tud:ex. v. Lunds priv. elem:sk. 26,\nutex. fr. KTH (kemi o. kem. tekn.) 31.\nAnst. v. Sv. Sockerfabr. A-B sed. 31.\nLed. av Sv. tekn:fören. sed. 46,\nSkånska ing:kl. sed. 36 o. Kem. fören. i\nLund sed. 46.\n\nAndersson, Gösta Arvid Anders,\nfolkskollärare, kantor, Skåne-Ask, f.\n25/6/05 i Villie, Malmöh. 1., av Anders\nJohansson o. Maria Andersson. G. 46\nm. Margit Gave. Barn: Per-Göran f.\n47. — Folksk :lär :ex. i Lund 27,\nkan-torsex. 34. E. o. folksk :lär. i Klippan\n27-38, ord. folksk :lär. o. kantor i Ask\nsed. 39.\n\nAndersson, Carl Gösta, fil. dr,\nSva-löv, f. 12/6/09 i Bjuv, Malmöh. 1., av\nCarl A. o. Emma Svensson. G. 39 m.\nKerstin Mundt-Petersson. Barn: Leif\nf. 40, Inger 42, Gudrun 44. — Stud:ex.\nv. Hälsingborgs h. a. 1. 28, fil. mag. v.\nLunds univ. 34, fil. lic. 43, fil. dr 44.\nStud. v. Köpenhamns univ. botan. inst.\n35. E. assist, v. S’v:es utsädesfören. i\nSvalöv 32-38, förädl :led. f. oljeväxter,\nsoja, majs m. m. 38-44, sekr. o.\nekonomichef v. Sv:es utsädesfören. samt\nförest, f. oljeväxtavd. sed. 44. Brukare\nav jordbr :fastigh. St. Mörshög nr 2 i\nBjuvs köp. sed. 46. Sakk. rör.\noljeväxter i Spannmålsbol. i Sthlm 41-44,\nh. Oljeväxtcentr. o. Oljeväxtodl.\ncentr:fören. i Malmö sed. 44, ordf. i\nSvalövs komm:fören. sed. 43, led. av\nkyrkofullm. sed. 43, av komm:fullm.\nsed. 47 o. av skolrådet sed. 48. Skr.:\nStudien Über die Winterfestigkeit des\nRoggens (35), Sojabönan samt\nmetoder o. möjligheter f. dess förädling i\nSv:e (38), Odling av olje- o.\nspånads-växter (40), Redogörelse f. arbeten m.\nsoja v. Sv:es utsädesfören. åren\n1938-40, 1941-43 o. 1944-46, Gas change and\nfrost hardening studies in winter\nce-reals (44), förf. brevkurs om\noljeväxtodling f. L. T. korresp:sk. (43), ett\nflert. art. i fack- o. dagspressen.\n\n",
    "structured": {
        "0": {
            "full_name": "Gunnar Andersson",
            "location": "Malmö",
            "occupation": "taxeringsintendent",
            "birth_details": {
                "date": "13/11/1893",
                "place": "Högseröd"
            },
            "education": [
                {
                    "degree": "Stud:ex.",
                    "year": "1912",
                    "institution": "Lund"
                },
                {
                    "degree": "jur. kand.",
                    "year": "1921",
                    "institution": "Lund"
                }
            ],
            "career": [
                {
                    "position": "Bitr. jurist",
                    "years": {
                        "start_year": 1921,
                        "end_year": 1921
                    },
                    "organization": "länsstyr, i Malmö"
                },
                {
                    "position": "länsbokh.",
                    "years": {
                        "start_year": 1925,
                        "end_year": 1925
                    },
                    "organization": "länsstyr, i Malmö"
                },
                {
                    "position": "länsassessor",
                    "years": {
                        "start_year": 1939,
                        "end_year": 1939
                    },
                    "organization": "länsstyr, i Malmö"
                },
                {
                    "position": "taxdntend.",
                    "years": {
                        "start_year": 1944,
                        "end_year": 1944
                    }
                }
            ],
            "family": {
                "spouse": "Elisabeth Andersson",
                "marriage_year": "NULL",
                "children": [
                    {
                        "name": "Arne Gunnarsson",
                        "birth_year": "1920"
                    },
                    {
                        "name": "Sven Gunnarsson",
                        "birth_year": "1925"
                    },
                    {
                        "name": "Helena Gunnarsson",
                        "birth_year": "1930"
                    },
                    {
                        "name": "Eskil Gunnarsson",
                        "birth_year": "1932"
                    }
                ]
            }
        },
        "1": {
            "full_name": "Erik Gunnar Andersson",
            "location": "Arlöv",
            "occupation": "civilingenjör",
            "birth_details": {
                "date": "15/09/1906",
                "place": "Nora bergsfors., Örebro"
            },
            "education": [
                {
                    "degree": "Stud:ex.",
                    "year": "1926",
                    "institution": "Lunds priv. elem:sk."
                },
                {
                    "degree": "utex.",
                    "year": "1931",
                    "institution": "KTH (kemi o. kem. tekn.)"
                }
            ],
            "career": [
                {
                    "position": "Anst.",
                    "years": {
                        "start_year": 1931,
                        "end_year": "NULL"
                    },
                    "organization": "Sv. Sockerfabr. A-B"
                }
            ],
            "family": {
                "spouse": "Frida Olsson",
                "marriage_year": "1939",
                "children": "NULL"
            }
        },
        "2": {
            "full_name": "Gösta Arvid Andersson",
            "location": "Skåne-Ask",
            "occupation": "folkskollärare, kantor",
            "birth_details": {
                "date": "25/06/1905",
                "place": "Villie, Malmöh"
            },
            "education": [
                {
                    "degree": "Folksk :lär :ex.",
                    "year": "1927",
                    "institution": "Lund"
                },
                {
                    "degree": "kantorsex.",
                    "year": "1934",
                    "institution": "NULL"
                }
            ],
            "career": [
                {
                    "position": "E. o. folksk :lär.",
                    "years": {
                        "start_year": 1927,
                        "end_year": 1938
                    },
                    "organization": "Klippan"
                },
                {
                    "position": "ord. folksk :lär. o. kantor",
                    "years": {
                        "start_year": 1939,
                        "end_year": "NULL"
                    },
                    "organization": "Ask"
                }
            ],
            "family": {
                "spouse": "Margit Gave",
                "marriage_year": "1946",
                "children": [
                    {
                        "name": "Per-Göran",
                        "birth_year": "1947"
                    }
                ]
            }
        },
        "3": {
            "full_name": "Carl Gösta Andersson",
            "location": "Svalöv",
            "occupation": "fil. dr",
            "birth_details": {
                "date": "12/06/1909",
                "place": "Bjuv, Malmöh"
            },
            "education": [
                {
                    "degree": "Stud:ex.",
                    "year": "1928",
                    "institution": "Hälsingborgs h. a. l."
                },
                {
                    "degree": "fil. mag.",
                    "year": "1934",
                    "institution": "Lunds univ."
                },
                {
                    "degree": "fil. lic.",
                    "year": "1943",
                    "institution": "NULL"
                },
                {
                    "degree": "fil. dr",
                    "year": "1944",
                    "institution": "NULL"
                }
            ],
            "career": [
                {
                    "position": "assist.",
                    "years": {
                        "start_year": 1932,
                        "end_year": 1938
                    },
                    "organization": "S’v:es utsädesfören."
                },
                {
                    "position": "förädl :led.",
                    "years": {
                        "start_year": 1938,
                        "end_year": 1944
                    },
                    "organization": "oljeväxter, soja, majs m. m."
                },
                {
                    "position": "sekr. o. ekonomichef",
                    "years": {
                        "start_year": 1944,
                        "end_year": "NULL"
                    },
                    "organization": "Sv:es utsädesfören."
                }
            ],
            "family": {
                "spouse": "Kerstin Mundt-Petersson",
                "marriage_year": "1939",
                "children": [
                    {
                        "name": "Leif",
                        "birth_year": "1940"
                    },
                    {
                        "name": "Inger",
                        "birth_year": "1942"
                    },
                    {
                        "name": "Gudrun",
                        "birth_year": "1944"
                    }
                ]
            }
        }
    }
}