{
    "original": "Odelstierna, Torsten E:son,\ndisponent, Drottningholm, f. 1/5/89 i\nLindesberg av prof. Erik O. o, Ellen\nRinman. G. 15 m. Iris Lindahl. Barn:\nKarin f. 16, g. Hamilton af Hageby;\nLennart f. 18; Christina f. 20, g.\nHultman; Lars f. 21. Civ: ing. 10,\ndrifts-ing. v. Munktells Papp :f abr. A-B,\nGrycksbo, 10-13, Riksbankens papp\n:-br., Tumba, 13-18, v. Genrstab. Litogr.\nAnst., A. Börtzells Tryck. A-B o.\nJacob Bagges sedeltryckeri 18-24, disp. v.\nWald. Zachrissons Boktr. A-B 24-26,\nd:o o. verkst, dir. f. Gtbgs Litogr. A-B\n26-38, disp. v. A-B Svanströms\nPappersagentur 38, verkst, dir. fr. 39.\nOrdf. i Sv:es litogr. tryck :äg. förb.\nsed. 33, styr:led. i Sundby Tegelbr.\nA-B sed. 26. Led. av komm:fullm. o.\nkomm:nämnd. i Lovö sed. 42. Medl.\nav Timmermansorden. Hobbies: jakt,\nhemvärn.\nOdencrants, Gerard Hartvig, prakt,\nläk., fil. måg., med. lic., Sthlm, f. Il/\nS/88 i Gtbg av hhövd. Thor O. o.\nLeo-nore Ekman. G. 29 m. Marie Augusta\n(Mary) Lagercrantz. Stud:ex. i Gtbg\n08, fil. mag. 14, med. kand. i Upps. 18,\nmed. lic. i Sthlm 24. E. o. aman. i\npatologi v. Karol. inst. 21, e. o. aman. v.\nögonpoliklin. s. å., aman. där s. å.,\nassist :läk. o. t. f. und :läk. å S :t Eriks\nsjukh. 22-23, läk. v. Storliens högf\njälls-sanat. somr. 24-26, e. o. aman. v.\nneurolog, klin. å Seraf:las. 24-25 o. 27,\nt. f. förest, v. poliklin. där 25 o. 27,\naman. å Sthlms hosp. 25-27, prakt,\nläk. i Sthlm sed. 27. Lärare i\nhälsolära v. Birkagårdens folkhögskola sed.\n26. Studieresa t. Wien 27. Skr.:\nnågra uppsatser i hypnos och psykoanalys.\nOdencrants, Thor Arvid Emil,\nprofessor, Sthlm, f. 7/8/81 i Örgryte,\nGtbgs o. Boh. 1., av hhövd. Thor O. o.\nLeonore Ekman. G. 14 m. Gunh.\nLjunggren d. 36. Fil. kand. Upps. 04, fil. lic.\n10, fil. dr o. doe. i fys. i Upps. 15, doc.\nI vetensk. fotogr. v. Sthlms högsk. 19,\nprof :s namn 33, dr ing. h.c. 39. Stud\n:-resor i vetenskapl. syfte o. f. delt. i\nnaturvet iskapl. kongr, i Norge, Danm.\no. Tyskl., m. statsansl. t. Tyskl. 25,\n.26, 27, 28, 31, 35, 36, 38 o. 39, t.\nSchweiz 30 o. 35, t. Lettl., Estl. o.\nFinl. 27, 31 o. 38. Sv :es offic. repr. v.\ninternat, kongr. f. vetenskapl. fotogr.\ni Tyskl., Frankr, o. Engl. 35, v. kongr,\nf. fotogrammetri i Ital. 38. På inbjud,\nföreläst om fotogr. v. univ. i Oslo,\nTrondhjem, Hfors, Åbo o. Riga. Lär.\no. sakk. i fotogr. o. dess användn. v.\nöl. milit. kurser, förest, f. fotogr.\ncen-trrlabor. v. f örsv rstab. fr. 37. Skr.:\nom Spektralanalys o. särsk. den\nvetensk. fotogr. o. fotogrammetrien samt\ndess användn. på öl. prakt. omr. bl. a.:\nModern kinematografi (26), Fotografi\no. fotogrammetri (29), tidskr, o.\ntid-nrupps. RNO, RCXIII :sO, EöK2kl,\nRFinlVROlkl, Adelsköld. SM, Fotogr.\nför:s f ört j: SM, KrVASM, LKrVA.\n",
    "structured": {
        "0": {
            "full_name": "Odelstierna, Torsten E:son",
            "location": "Drottningholm",
            "occupation": "disponent",
            "birth_details": {
                "date": "01/05/1889",
                "place": "Lindesberg"
            },
            "education": [
                {
                    "degree": "Civ. ing.",
                    "year": "1910",
                    "institution": "NULL"
                },
                {
                    "degree": "Drifts-ing.",
                    "year": "NULL",
                    "institution": "Munktells Papp :f abr. A-B, Grycksbo"
                }
            ],
            "career": [
                {
                    "position": "drifts-ing. v. Munktells Papp :f abr. A-B",
                    "years": {
                        "start_year": 1910,
                        "end_year": 1913
                    },
                    "organization": "Grycksbo"
                },
                {
                    "position": "Riksbankens papp :-br.",
                    "years": {
                        "start_year": 1913,
                        "end_year": 1918
                    },
                    "organization": "Tumba"
                },
                {
                    "position": "disp. v. Wald. Zachrissons Boktr. A-B",
                    "years": {
                        "start_year": 1924,
                        "end_year": 1926
                    },
                    "organization": "NULL"
                },
                {
                    "position": "disp. v. A-B Svanströms Pappersagentur",
                    "years": {
                        "start_year": 1938,
                        "end_year": 1939
                    },
                    "organization": "NULL"
                }
            ],
            "family": {
                "spouse": "Iris Lindahl",
                "marriage_year": "NULL",
                "children": [
                    {
                        "name": "Karin",
                        "birth_year": "1916"
                    },
                    {
                        "name": "Lennart",
                        "birth_year": "1918"
                    },
                    {
                        "name": "Christina",
                        "birth_year": "1920"
                    },
                    {
                        "name": "Lars",
                        "birth_year": "1921"
                    }
                ]
            }
        },
        "1": {
            "full_name": "Odencrants, Gerard Hartvig",
            "location": "Sthlm",
            "occupation": "prakt, läk., fil. måg., med. lic.",
            "birth_details": {
                "date": "11/05/1888",
                "place": "Gtbg"
            },
            "education": [
                {
                    "degree": "Stud:ex.",
                    "year": "1908",
                    "institution": "Gtbg"
                },
                {
                    "degree": "Fil. mag.",
                    "year": "1914",
                    "institution": "NULL"
                },
                {
                    "degree": "Med. kand.",
                    "year": "1918",
                    "institution": "Upps."
                },
                {
                    "degree": "Med. lic.",
                    "year": "1924",
                    "institution": "Sthlm"
                }
            ],
            "career": [
                {
                    "position": "prakt. läk. i Sthlm",
                    "years": {
                        "start_year": 1927,
                        "end_year": "NULL"
                    },
                    "organization": "NULL"
                },
                {
                    "position": "Lärare i hälsolära v. Birkagårdens folkhögskola",
                    "years": {
                        "start_year": 1926,
                        "end_year": "NULL"
                    },
                    "organization": "NULL"
                }
            ],
            "family": {
                "spouse": "Marie Augusta (Mary) Lagercrantz",
                "marriage_year": "NULL",
                "children": []
            }
        },
        "2": {
            "full_name": "Odencrants, Thor Arvid Emil",
            "location": "Sthlm",
            "occupation": "professor",
            "birth_details": {
                "date": "07/08/1881",
                "place": "Örgryte, Gtbgs o. Boh. 1."
            },
            "education": [
                {
                    "degree": "Fil. kand.",
                    "year": "1904",
                    "institution": "Upps."
                },
                {
                    "degree": "Fil. lic.",
                    "year": "1910",
                    "institution": "NULL"
                },
                {
                    "degree": "Fil. dr o. doe. i fys.",
                    "year": "1915",
                    "institution": "Upps."
                }
            ],
            "career": [
                {
                    "position": "doc. I vetensk. fotogr. v. Sthlms högsk.",
                    "years": {
                        "start_year": 1933,
                        "end_year": "NULL"
                    },
                    "organization": "NULL"
                }
            ],
            "family": {
                "spouse": "Gunh. Ljunggren d. 36",
                "marriage_year": "1936",
                "children": []
            }
        }
    }
}