{
    "original": "Olsgård, Sven Oscar Adolf, direktör,\nSthlm, f. 3/8/94 i Sthlm. G. 36 rn.\nAina Samuelson. Stud. v. hdlsskola i\nSthlm. Anst. i f :a Fritz Moll, Sthlm,\n09-13, i f :a Axel Robert Bildt, Sthlm,\n13-17, kontorsch, i A-B Bonthron &amp;\nWretlind, Sthlm, 17-19, därav sista\nåret i Melandsö, Bonthron &amp; Co. A-S,\nKristiania, kontorsch, i f:a Hjalmar\nCarlson, Kristiania, 20, eg. rörelse i\nKristiania 20-23, egen agentur- o.\nen-grosf :a i Sthlm sed. 23. Grund. A-B\nSven Olsgård i Sthlm 23, m. spec.\nHals’ centrifugalfriktionskoppling,\nexploaterat i Sv :e, Finl. o. Balticum\nEsso prisbelönta vedkapsågar m. nda\nkoppling, sed. 39 dir. i Esso A-B,\nSthlm. Ombud f. Sv. järnbrukens\nträ-kolsfören. i Bränslekomm. 17, sekr. i\nSvenskmannaklubben i Kristiania\n19-23, v. ordf. i Motorsportklubben MSK\n33-36.\nOhlson, Arne Oliver Kjell,\nopera-sångare, Sthlm, f. 2/1/11 i Uddevalla.\nG. 39 m. Eva Karlsson. Stud. sång f.\nAugustin Kock 34-36, elev i musikteori\nav Sven E. Svensson, lekt. i\nviolin-speln. f. Lars Zetterquist 33-34, elev i\nOperask. 36-39 av Joseph Hislop, John\nForsell o. Gerda Lundequist, Kristina\nNiLssori-stip. 36. Upprep, eng. i radio.\nEn av init:tag. t. Arionkvart. Debut,\no. anst. som stipendiat v. Kungl, teak\n41, engagerad v. Kungl. teat. sedan\n44. Roller: Don Ottavio i Don Juan,\nFurst Andrej Howanskij i\nHowant-schina, Remendado i Carmen, Henrik\nSkrivaren i Tannhäuser, Cassio i\nOthello, Greve Almaviva i Barberaren\ni Sevilla, Beppo i Pajazzo.\nOlsson, Axel Emil, advokat, Sthlm,\nf. 5/9/73 i Malexander, Östergötl. 1.,\nav lantbr. August O. o. Christ.\nJohansson. G. 05 m. Anna Hansson. Stud :ex.\ni Linköp. 93, jur. utr. kand. i Upps,\n00. Anst. i adv:firman Tjerneld £\nMorssing i Sthlm 02-17, egen\nadv:-firma sed. 17. Led. av Sv. Advisamf.\nsed. 04.\nOlsson, Axel Ferdinand Napoleon,\nadvokat, Sthlm, f. 19/6/72 i\nHällestad, Älvsb. L, av grossh. i Sthlm\nOlaus O. o. Anna Brita Andersson. G.\n03 m. Hildur Victorin. Barn: Hildur\n(Etty) f. 04, g. m. direktör Gösta\nBelfrage; Margareta (Gret) f. 04, g.\nm. kamrern i A-B Gtbgs bank Sven\nHägerstedt; Birgit f. 06, g. m.\nbok-handl. Erik Wallenius. Mog:ex. i\nNy-köp. 91, jur. fil. ex. 92, jur. utr. kand.\n97. E. o. not. i Svea hovr. 97, ordf. i\nNorrb. 1. gränstullrätt 98, tingstjg.\n98-99, t. f. domhav, i Torneå doms. 98-99,\ntillsyn :man v. kronoh. i Haparanda\n99, aman. i cividep. 99-04 o. därund.\nt. f. registrator o. kanslisekr. Anst. a\nadv:byrå i Sthlm 00-05, egen\nadv:-verksamh, i Sthlm sed. 05, rev. i\nSthlms stadshyp :för. sed. 09.\nStyr:-led. i styr. f. Olaus Olssons Kolimp.\nA-B o. dess ordf. 12-22, verkst, dir.\ni Herrängs Gruv A-B 18-22, delt. i\nbild. av Sv. Exporttack jämför, u.p.a.\no. A-B Svenskt Exporttackjärn 18,\nled. av styr. för det senare bol. 18-22,\nv. ordf. 20-22, delt. i bild. av fören.\nSthlms Hamnarbetskontor 09 o. dess\nv. ordf. 20-23. Led. av Sv :es\nAdv:-samf. 09.\n",
    "structured": {
        "1": {
            "full_name": "Olsgård, Sven Oscar Adolf",
            "location": "Sthlm",
            "occupation": "Direktör",
            "birth_details": {
                "date": "03/08/1894",
                "place": "Sthlm"
            },
            "education": [
                {
                    "degree": "Stud. V. Hdlsskola",
                    "year": "N/A",
                    "institution": "Sthlm"
                }
            ],
            "career": [
                {
                    "position": "Anst. I F :A Fritz Moll",
                    "years": {
                        "start_year": 1909,
                        "end_year": 1913
                    },
                    "organization": "Sthlm"
                },
                {
                    "position": "Anst. I F :A Axel Robert Bildt",
                    "years": {
                        "start_year": 1913,
                        "end_year": 1917
                    },
                    "organization": "Sthlm"
                },
                {
                    "position": "Kontorsch, I A-B Bonthron & Wretlind",
                    "years": {
                        "start_year": 1917,
                        "end_year": 1919
                    },
                    "organization": "Sthlm"
                },
                {
                    "position": "Ombud F. Sv. Järnbrukens Trä-Kolsfören.",
                    "years": {
                        "start_year": 1917,
                        "end_year": null
                    },
                    "organization": "Bränslekomm."
                },
                {
                    "position": "Sekr. I Svenskmannaklubben I Kristiania",
                    "years": {
                        "start_year": 1919,
                        "end_year": 1923
                    },
                    "organization": "Kristiania"
                }
            ],
            "family": {
                "spouse": "Aina Samuelson",
                "marriage_year": "1936",
                "children": []
            }
        },
        "2": {
            "full_name": "Ohlson, Arne Oliver Kjell",
            "location": "Sthlm",
            "occupation": "Opera-sångare",
            "birth_details": {
                "date": "02/01/1911",
                "place": "Uddevalla"
            },
            "education": [
                {
                    "degree": "Stud.",
                    "year": "N/A",
                    "institution": "Augustin Kock"
                },
                {
                    "degree": "Elev I Musikteori",
                    "year": "N/A",
                    "institution": "Sven E. Svensson"
                }
            ],
            "career": [
                {
                    "position": "Anst. Som Stipendiat V. Kungl, Teak",
                    "years": {
                        "start_year": 1941,
                        "end_year": null
                    },
                    "organization": "Kungl. teat."
                }
            ],
            "family": {
                "spouse": "Eva Karlsson",
                "marriage_year": "1939",
                "children": [
                    {
                        "name": "Hildur (Etty)",
                        "birth_year": "1904"
                    },
                    {
                        "name": "Margareta (Gret)",
                        "birth_year": "1904"
                    },
                    {
                        "name": "Birgit",
                        "birth_year": "1906"
                    }
                ]
            }
        },
        "3": {
            "full_name": "Olsson, Axel Emil",
            "location": "Sthlm",
            "occupation": "Advokat",
            "birth_details": {
                "date": "05/09/1873",
                "place": "Malexander, Östergötl. 1."
            },
            "education": [
                {
                    "degree": "Stud",
                    "year": "1893",
                    "institution": "Linköp"
                },
                {
                    "degree": "Jur. Utr. Kand.",
                    "year": "1900",
                    "institution": "Upps"
                }
            ],
            "career": [
                {
                    "position": "Led. Av Sv. Advisamf.",
                    "years": {
                        "start_year": 1904,
                        "end_year": null
                    },
                    "organization": "N/A"
                }
            ],
            "family": {
                "spouse": "Anna Hansson",
                "marriage_year": "1905",
                "children": []
            }
        },
        "4": {
            "full_name": "Olsson, Axel Ferdinand Napoleon",
            "location": "Sthlm",
            "occupation": "Advokat",
            "birth_details": {
                "date": "19/06/1872",
                "place": "Hällestad, Älvsb. L"
            },
            "education": [
                {
                    "degree": "Mog",
                    "year": "1891",
                    "institution": "Ny-köp"
                },
                {
                    "degree": "Jur. Fil. Ex.",
                    "year": "1892",
                    "institution": "Ny-köp"
                }
            ],
            "career": [
                {
                    "position": "Rev. I Sthlms Stadshyp :för.",
                    "years": {
                        "start_year": 1909,
                        "end_year": null
                    },
                    "organization": "Sthlms Stadshyp :för."
                },
                {
                    "position": "Styr.led. I Styr. F. Olaus Olssons Kolimp. A-B Och Delt. I Bild. Av Sv. Exporttack",
                    "years": {
                        "start_year": 1922,
                        "end_year": null
                    },
                    "organization": "N/A"
                }
            ],
            "family": {
                "spouse": "Hildur Victorin",
                "marriage_year": "1903",
                "children": [
                    {
                        "name": "Hildur (Etty)",
                        "birth_year": "1904"
                    },
                    {
                        "name": "Margareta (Gret)",
                        "birth_year": "1904"
                    },
                    {
                        "name": "Birgit",
                        "birth_year": "1906"
                    }
                ]
            }
        }
    }
}