{
    "original": "Ossmark, Josef Ossian Leopold,\nbyråsekreterare, Ängby, f. 15/11/05 i\nSundbyberg. G. 32 m. Märta\nWiller-man. Barn: Bengt f. 33, Jan f. 35,\nStaffan f. 41, Gunilla f. 43. Stud:ex.\ni Sthlm 24, jur. kand. 29. Tingstjg, i\nAska, Dals o. Bobergs doms. 29-32, tjg.\ni Svea hovr. o. i Sthlms rådhusrätt\n32-33, aman. i Lantbr :styr. 33-38, bitr.\njur. v. Örebro 1. rättshjälpsanst 38,\nbyråsekr. (not.) i Lantbr :styr. 38.\nBitr. sekr. i hushålln :sällskapsutredn.\nÖsterman, John Christoffer,\ncivilingenjör, direktör, Sthlm, f. 16/11/77 i\nKarlskrona av kommendör J. Ch. O.\no. Fredrika Borg. G. 07 m. Margareta\nFaber. Barn: Ragnar f. 08, ing.,\nförsäljn :ch. v. Elektr. A-B John\nÖsterman; Karin f. 09, g. m. civ äng. Törd\nBohlin; Lennart f. 11, ing., v. dir. i\nA-B Hans Österman. Ex. v. CTH 02.\nIng. v. Stanley El. Mfg Co., Pittsfield,\nU. S. A., 02-04, Boston &amp; Northern\nStreet Railway Co. 04, ASEA,\nVästerås, 05-06, Siemens-Schuckert, Berlin,\n06-07, driftsing. o. dir:assist. i\nYngeredsfors Kraft A-B 07-16, ch. för tekn.\navd. v. Christian Berner, Gtbg, 16-18,\ndir: assist, i A-B Elektraverken, Sthlm,\n18-29, dir. i A-B Osram-Elektraverken,\nSthlm, 29-33, övert. Osram-Elektraver-\nElektraverkens tillverkn. av installationsmat, o.\nvärmeapparater 34 o. bild. El. A-B\nJohn Österman, verkst, dir. o. huv\n:-deläg. i detta bol. Medl. av\nFrimurareorden, KAK, Sv. Teknol :f ören.\nResor t. U. S. A. 02-04, Tyskl. 06-07,\nstudieresor t. Engl., Holland, Schweiz,\nFrankr., Finl., Italien. Hobbies:\nsegling o. filateli. RVO.\n\nOsterman, John Lennart, ingenjör,\ndirektör, Sthlm, f. 1/10/11 i Mölndal\nav dir. John Ch. O. o. Margarete\nFaber.. Tekn. gymn. i Örebro 32, DHS\n35, Gen. Motor School of Techn. 36.\nAnst. v. Chevrolet Motor Co., Detroit,\n36-37, försäljn :ch. v. A-B Hans\nÖsterman 37-38, verkst :ch. 38-41, verkst,\ndir. 41. Styr:led. i A-B Hans\nÖsterman, A-B Bil- o. Metallprodukter,\nSthlms Automobilhandl :fören. samt\nSthlms Stads o. Läns Automobilhandl\n:-fören. Medl. av KAK, KSSS, KSAK,\nFrimurareorden. Resor i U. S. A.\n35-37. Hobbies: segling o. flygning.\n\n",
    "structured": {
        "0": {
            "full_name": "Ossmark, Josef Ossian Leopold",
            "location": "Ängby",
            "occupation": "byråsekreterare",
            "birth_details": {
                "date": "15/11/1905",
                "place": "Sundbyberg"
            },
            "education": [
                {
                    "degree": "Stud:ex.",
                    "year": "1924",
                    "institution": "Sthlm"
                },
                {
                    "degree": "jur. kand.",
                    "year": "1929",
                    "institution": "Svea hovr."
                }
            ],
            "career": [
                {
                    "position": "Tingstjg",
                    "years": {
                        "start_year": 1929,
                        "end_year": 1932
                    },
                    "organization": "Aska, Dals o. Bobergs doms."
                },
                {
                    "position": "tjg. i Svea hovr. o. i Sthlms rådhusrätt",
                    "years": {
                        "start_year": 1932,
                        "end_year": 1933
                    }
                },
                {
                    "position": "aman. i Lantbr :styr.",
                    "years": {
                        "start_year": 1933,
                        "end_year": 1938
                    }
                },
                {
                    "position": "bitr. jur. v. Örebro 1. rättshjälpsanst",
                    "years": {
                        "start_year": 1938
                    }
                },
                {
                    "position": "byråsekr. (not.) i Lantbr :styr.",
                    "years": {
                        "start_year": 1938
                    }
                },
                {
                    "position": "Bitr. sekr. i hushålln :sällskapsutredn."
                }
            ],
            "family": {
                "spouse": "Märta Willerman",
                "marriage_year": "1932",
                "children": [
                    {
                        "name": "Bengt",
                        "birth_year": "1933"
                    },
                    {
                        "name": "Jan",
                        "birth_year": "1935"
                    },
                    {
                        "name": "Staffan",
                        "birth_year": "1941"
                    },
                    {
                        "name": "Gunilla",
                        "birth_year": "1943"
                    }
                ]
            }
        },
        "1": {
            "full_name": "Österman, John Christoffer",
            "location": "Sthlm",
            "occupation": "civilingenjör, direktör",
            "birth_details": {
                "date": "16/11/1877",
                "place": "Karlskrona"
            },
            "education": [
                {
                    "degree": "Ex. v. CTH",
                    "year": "1902"
                }
            ],
            "career": [
                {
                    "position": "Ing. v. Stanley El. Mfg Co., Pittsfield, U. S. A.",
                    "years": {
                        "start_year": 1902,
                        "end_year": 1904
                    }
                },
                {
                    "position": "Boston & Northern Street Railway Co.",
                    "years": {
                        "start_year": 1904
                    }
                },
                {
                    "position": "driftsing. o. dir:assist. i Yngeredsfors Kraft A-B",
                    "years": {
                        "start_year": 1907,
                        "end_year": 1916
                    }
                },
                {
                    "position": "ch. för tekn. avd. v. Christian Berner, Gtbg",
                    "years": {
                        "start_year": 1916,
                        "end_year": 1918
                    }
                },
                {
                    "position": "dir: assist, i A-B Elektraverken, Sthlm",
                    "years": {
                        "start_year": 1918,
                        "end_year": 1929
                    }
                },
                {
                    "position": "dir. i A-B Osram-Elektraverken, Sthlm",
                    "years": {
                        "start_year": 1929,
                        "end_year": 1933
                    }
                },
                {
                    "position": "övert. Osram-Elektraver-Elektraverkens tillverkn. av installationsmat, o. värmeapparater",
                    "years": {
                        "start_year": 1934
                    }
                },
                {
                    "position": "bild. El. A-B John Österman, verkst, dir. o. huv :-deläg. i detta bol."
                }
            ],
            "family": {
                "spouse": "Margareta Faber",
                "marriage_year": "1907",
                "children": [
                    {
                        "name": "Ragnar",
                        "birth_year": "1908"
                    },
                    {
                        "name": "Karin",
                        "birth_year": "1909"
                    },
                    {
                        "name": "Lennart",
                        "birth_year": "1911"
                    }
                ]
            },
            "hobbies": [
                "segling",
                "filateli"
            ],
            "honorary_titles": [
                {
                    "title": "RVO"
                }
            ]
        },
        "2": {
            "full_name": "Osterman, John Lennart",
            "location": "Sthlm",
            "occupation": "ingenjör, direktör",
            "birth_details": {
                "date": "1/10/1911",
                "place": "Mölndal"
            },
            "education": [
                {
                    "degree": "Tekn. gymn.",
                    "year": "1932",
                    "institution": "Örebro"
                },
                {
                    "degree": "DHS",
                    "year": "1935"
                },
                {
                    "degree": "Gen. Motor School of Techn.",
                    "year": "1936"
                }
            ],
            "career": [
                {
                    "position": "Anst. v. Chevrolet Motor Co., Detroit",
                    "years": {
                        "start_year": 1936,
                        "end_year": 1937
                    }
                },
                {
                    "position": "försäljn :ch. v. A-B Hans Österman",
                    "years": {
                        "start_year": 1937,
                        "end_year": 1938
                    }
                },
                {
                    "position": "verkst :ch.",
                    "years": {
                        "start_year": 1938,
                        "end_year": 1941
                    }
                },
                {
                    "position": "verkst, dir.",
                    "years": {
                        "start_year": 1941
                    }
                }
            ],
            "family": {
                "spouse": "Törd Bohlin",
                "marriage_year": "NULL",
                "children": [
                    {
                        "name": "NULL",
                        "birth_year": "NULL"
                    }
                ]
            },
            "hobbies": [
                "segling",
                "flygning"
            ]
        }
    }
}