{
    "original": "LAGERKVIST-PERSSON, E VIVEKA, bibliotekarie, \nVäxjö, f i Karlshamn 31/12/18 av \nkant Klas L o Ellen Petersson.\n\nFil mag Lund 44, stat bibl :sk 45, e\nbibl:-ass stadsbibl Kristianstad 44, stadsbibl\nNorrkpg 45, stadsbibl:ie Nybro 46,\nbibl:ie stifts- o landsbibi Växjö sed 58.\n- Led Stadsfullm Nybro 55-58.\nGift 47 m antikv:handl Johan Persson\nf 10. - Barn: Kajsa f 48.\n\nLAGERSTRÖM, LARS OLOV, polissekreterare, \nMotala, f i Valdemarsvik, Östergötl l, 22/6/26 \nav folkskollär Gustaf L o Laura Holmström.\n\nStud:ex 47, distr:åkl:ex Sthlm 54,\npolisch:kurs Stat polissk 54-55, polissekr\nMotala polisdistr sed 65.\n\nGift 62 m Birgit Eriksson f 29, dtr t\nFrans E o Anna Ekdahl.\n\nLAGERWALL, CLAES-AXEL, direktör, \nGbg, f i Gbg 3/7/08 av folksk:insp,\nfil dr Axel L o Ebba Berlin.\n\nStud:ex 27, fackk GbgHdlI 28, dir\nBlidberg &amp; Lagerwall ab 37-45, Adolf Bratt\n&amp; Co o Rederi ab Götha 48-59, verkst\ndir o inneh H Alpen ab o C-A\nLagerwall ab sed 60 (styr:led). - Styr:led ab\nAxel Andrén &amp; Co, Fören f Gbgs\nförsvar, SvFfb, ordf Res:off:sällsk Gbg,\nGbgs fäktförb, Gbgs fäktklubb. \n- Utm: CFBSM, SvFfbftjtG, SvRoffht, \nRes:off:fören Danm ht, Finl res:off:förb ht, \nVpl off fören Norge ht. - Hobbies: fäktning,\npistolskjutning, segling.\n\nGift 38 m Inga Sternhagen, dtr t\ngen:konsul Fritz S o Ella Wilkens. - Barn:\nChristina f 39, Hans f 41, Elisabeth f 44.\n\nLAGERWALL, JAN M, prakt läkare,\nGbg, f i Gbg 13/4/07 av folksk:insp, fil\ndr Axel L o Ebba Berlin.\n\nStud:ex 27, fil kand 35, med kand 38 o\nmed lic Lund 43, ol läk:förordn 41-48,\nunderläk med avd Linkpgs las 49-51, vik\nläk psykiatr klin Sahlgr sjh 51, prakt\nläk Gbg sed 51. - Hobby: segling.\n\nGift 40 m Ella Skoog f 12. - Barn: Åke\nf 43, Leif f 45, Mats f 46.\n\n<b>LAGERVALL, NILS, rektor,</b> Degerhamn, \nf i Ölmstad, Jönkpgs l, 12/4/29 av\nhemm:äg Gottfrid L o Edit Andersson.\nRealex Tranås 46 (priv), folkskollär :ex\nJönkpg 51, akad stud i statskunsk o\nnat:ekon 64-65, ämneslär:behörigh 65.\n-  Eo folkskollär Finnerödja 51, Tenhult\n52, Tiveden o Hova 53, Skärstad 55,\nfolkskollär Haverö 57-60 (tf rekt 58),\nrekt o skolch Ottenby kn sed 60.\nGift 53 m Bergljot Revhaug f 29, dtr t\nrekt Olaus R o Reidun Lund (Norge).\n- Barn: Björn f 53, Maria f 58, Berit f 60.\n",
    "structured": {
        "0": {
            "full_name": "Lagerkvist-Persson, E Viveka",
            "location": "Växjö",
            "occupation": "bibliotekarie",
            "birth_details": {
                "date": "31/12/1918",
                "place": "Karlshamn",
                "parents": "kant Klas L o Ellen Petersson"
            },
            "education": [
                {
                    "degree": "Filosofie magister",
                    "year": "1944",
                    "institution": "Lund"
                }
            ],
            "career": [
                {
                    "position": "bibl:-ass",
                    "years": {
                        "start_year": 1944,
                        "end_year": 1945
                    },
                    "organization": "stadsbibl Kristianstad"
                },
                {
                    "position": "bibl:ie",
                    "years": {
                        "start_year": 1945,
                        "end_year": 1946
                    },
                    "organization": "stadsbibl Norrköping"
                },
                {
                    "position": "bibl:ie",
                    "years": {
                        "start_year": 1946,
                        "end_year": 1958
                    },
                    "organization": "stifts- o landsbibi Växjö"
                }
            ],
            "family": {
                "spouse": "antikv:handl Johan Persson",
                "marriage_year": "1947",
                "children": [
                    {
                        "name": "Kajsa",
                        "birth_year": "1948"
                    }
                ]
            }
        },
        "1": {
            "full_name": "Lagerström, Lars Olov",
            "location": "Motala",
            "occupation": "polissekreterare",
            "birth_details": {
                "date": "22/06/1926",
                "place": "Valdemarsvik, Östergötland"
            },
            "education": [
                {
                    "degree": "Stud:ex",
                    "year": "1947",
                    "institution": null
                },
                {
                    "degree": "distr:åkl:ex",
                    "year": "1954",
                    "institution": "Sthlm"
                },
                {
                    "degree": "polisch:kurs",
                    "year": "1954-1955",
                    "institution": "Stat polissk"
                }
            ],
            "career": [
                {
                    "position": "polissekr",
                    "years": {
                        "start_year": 1965,
                        "end_year": null
                    },
                    "organization": "Motala polisdistr"
                }
            ],
            "family": {
                "spouse": "Birgit Eriksson",
                "marriage_year": "1962",
                "children": null
            }
        },
        "2": {
            "full_name": "Lagerwall, Claes-Axel",
            "location": "Göteborg",
            "occupation": "direktör",
            "birth_details": {
                "date": "03/07/1908",
                "place": "Göteborg"
            },
            "education": [
                {
                    "degree": "Stud:ex",
                    "year": "1927",
                    "institution": null
                },
                {
                    "degree": "fackk",
                    "year": "1928",
                    "institution": "GbgHdlI"
                }
            ],
            "career": [
                {
                    "position": "dir",
                    "years": {
                        "start_year": 1937,
                        "end_year": 1945
                    },
                    "organization": "Blidberg & Lagerwall ab"
                },
                {
                    "position": "verkst dir",
                    "years": {
                        "start_year": 1960,
                        "end_year": null
                    },
                    "organization": "H Alpen ab o C-A Lagerwall ab"
                }
            ],
            "family": {
                "spouse": "Inga Sternhagen",
                "marriage_year": "1938",
                "children": [
                    {
                        "name": "Christina",
                        "birth_year": "1939"
                    },
                    {
                        "name": "Hans",
                        "birth_year": "1941"
                    },
                    {
                        "name": "Elisabeth",
                        "birth_year": "1944"
                    }
                ]
            },
            "hobbies": [
                "fäktning",
                "pistolskjutning",
                "segling"
            ]
        },
        "3": {
            "full_name": "Lagerwall, Jan M",
            "location": "Göteborg",
            "occupation": "prakt läkare",
            "birth_details": {
                "date": "13/04/1907",
                "place": "Göteborg"
            },
            "education": [
                {
                    "degree": "Stud:ex",
                    "year": "1927",
                    "institution": null
                },
                {
                    "degree": "fil kand",
                    "year": "1935",
                    "institution": null
                },
                {
                    "degree": "med kand",
                    "year": "1938",
                    "institution": null
                },
                {
                    "degree": "med lic",
                    "year": "1943",
                    "institution": "Lund"
                }
            ],
            "career": [
                {
                    "position": "vik läk",
                    "years": {
                        "start_year": 1951,
                        "end_year": null
                    },
                    "organization": "psykiatr klin Sahlgr sjh"
                },
                {
                    "position": "prakt läk",
                    "years": {
                        "start_year": 1951,
                        "end_year": null
                    },
                    "organization": "Gbg"
                }
            ],
            "family": {
                "spouse": "Ella Skoog",
                "marriage_year": "1940",
                "children": [
                    {
                        "name": "Åke",
                        "birth_year": "1943"
                    },
                    {
                        "name": "Leif",
                        "birth_year": "1945"
                    },
                    {
                        "name": "Mats",
                        "birth_year": "1946"
                    }
                ]
            },
            "hobbies": [
                "segling"
            ]
        },
        "4": {
            "full_name": "Lagervall, Nils",
            "location": "Degerhamn",
            "occupation": "rektor",
            "birth_details": {
                "date": "12/04/1929",
                "place": "Ölmstad, Jönköpings l"
            },
            "education": [
                {
                    "degree": "Realex",
                    "year": "1946",
                    "institution": "Tranås (priv)"
                },
                {
                    "degree": "folkskollär :ex",
                    "year": "1951",
                    "institution": "Jönköping"
                },
                {
                    "degree": "akad stud i statskunsk o nat:ekon",
                    "year": "1964-1965",
                    "institution": null
                },
                {
                    "degree": "ämneslär:behörigh",
                    "year": "1965",
                    "institution": null
                }
            ],
            "career": [
                {
                    "position": "rekt o skolch",
                    "years": {
                        "start_year": 1960,
                        "end_year": null
                    },
                    "organization": "Ottenby kn"
                }
            ],
            "family": {
                "spouse": "Bergljot Revhaug",
                "marriage_year": "1953",
                "children": [
                    {
                        "name": "Björn",
                        "birth_year": "1953"
                    },
                    {
                        "name": "Maria",
                        "birth_year": "1958"
                    },
                    {
                        "name": "Berit",
                        "birth_year": "1960"
                    }
                ]
            }
        }
    }
}