{
    "original": "LIND,   SVEN-HUGO   G,   tandläkare,\n\nNorrköping, f i Lidkpg 3/6/28 av köpm\n\nHugo L o Karin Djup.\n\nStud:ex   Skara  47,   tandl:ex  Sthlm   52,\n\npriv:prakt   Åkersberga   54-57,   Norrkpg\n\nsed 57.\n\nGift 54 m Birgitta Hultin f 29, dtr t\n\nköpm  Ferd  H  o  Anna  Gustavsson.  -\n\nBarn: Mats f 55, Annika f 59.\n\nLIND, TORSTEN I, distriktsåklagare,\n\nJönköping, f i Motala 8/6/30 av kamr\nJohan Walfridson o Ebba Lind.\nStud:ex Örebro 50, Örebro hdlsgymn\n51, distr:åkl:ex Sthlm 55, stat polissk 56,\njur kand 58, tingstjg Norrkpg 58-61, bitr\nstadsfiskal 62, distr:åkl Jönkpg sed 65.\n-Medl Odd Fellow. - Hobbies: jakt, fiske,\nfotografering.\n\nGift 62 m Britt Larsson f 29, dtr t köpm\nNils L o Isa Thörnström. - Barn:\nAnders f 64.\n\nLIND, WILGOT F, konstnär, direktör,\n\nGbg, f i Gbg 1/10/15 av köpm Axel L\no Clara Eliasson.\n\nHdlssk 30, dir F:a Axel T Lind o F:a\nGbgs kont :centrum. - Sep:utst (måleri)\nGbg 50 o 62, Sthlm 52, delt i saml:utst\nSv:e, Skand o USA. - Repr i Gbgs stads\nsaml, The Brooklyn Mus New York, off\no priv saml i ett flert länder. - Medl\nKRO, Grupp 54. - Hobbies: sinologi,\nnumismatik, filateli.\n\nGift 43 m Ingeborg Erlandsson, dtr t\nbyggm Axel E o Kristina Gudmundsson.\n- Barn: Björn f 45, Staffan f 49, Jörgen\nf 57.\n\n",
    "structured": {
        "1": {
            "full_name": "Sven-Hugo Lind",
            "location": "Norrköping",
            "occupation": "tandläkare",
            "birth_details": {
                "date": "03/06/1928",
                "place": "Lidköping",
                "parents": "Hugo L o Karin Djup"
            },
            "education": [
                {
                    "degree": "Stud:ex",
                    "year": "1947",
                    "institution": "Skara"
                },
                {
                    "degree": "tandl:ex",
                    "year": "1952",
                    "institution": "Sthlm"
                }
            ],
            "career": [
                {
                    "position": "priv:prakt",
                    "years": {
                        "start_year": 1954,
                        "end_year": 1957
                    },
                    "organization": "Åkersberga"
                },
                {
                    "position": "Norrkpg",
                    "years": {
                        "start_year": 1957,
                        "end_year": 1957
                    }
                }
            ],
            "family": {
                "spouse": "Birgitta Hultin",
                "marriage_year": "1954",
                "children": [
                    {
                        "name": "Mats",
                        "birth_year": "1955"
                    },
                    {
                        "name": "Annika",
                        "birth_year": "1959"
                    }
                ]
            }
        },
        "2": {
            "full_name": "Torsten I Lind",
            "location": "Jönköping",
            "occupation": "distriktsåklagare",
            "birth_details": {
                "date": "08/06/1930",
                "place": "Motala",
                "parents": "Johan Walfridson o Ebba Lind"
            },
            "education": [
                {
                    "degree": "Stud:ex",
                    "year": "1950",
                    "institution": "Örebro"
                },
                {
                    "degree": "Örebro hdlsgymn",
                    "year": "1951"
                },
                {
                    "degree": "distr:åkl:ex",
                    "year": "1955",
                    "institution": "Sthlm"
                },
                {
                    "degree": "stat polissk",
                    "year": "1956"
                },
                {
                    "degree": "jur kand",
                    "year": "1958"
                }
            ],
            "career": [
                {
                    "position": "tingstjg",
                    "years": {
                        "start_year": 1958,
                        "end_year": 1961
                    },
                    "organization": "Norrkpg"
                },
                {
                    "position": "bitr stadsfiskal",
                    "years": {
                        "start_year": 1962,
                        "end_year": null
                    }
                },
                {
                    "position": "distr:åkl",
                    "years": {
                        "start_year": 1965,
                        "end_year": null
                    },
                    "organization": "Jönkpg"
                }
            ],
            "family": {
                "spouse": "Britt Larsson",
                "marriage_year": "1962",
                "children": [
                    {
                        "name": "Anders",
                        "birth_year": "1964"
                    }
                ]
            },
            "hobbies": [
                "jakt",
                "fiske",
                "fotografering"
            ]
        },
        "3": {
            "full_name": "Wilgot F Lind",
            "location": "Gbg",
            "occupation": "konstnär, direktör",
            "birth_details": {
                "date": "01/10/1915",
                "place": "Gbgs",
                "parents": "Axel L o Clara Eliasson"
            },
            "education": [
                {
                    "degree": "Hdlssk",
                    "year": "1930"
                }
            ],
            "career": [
                {
                    "position": "dir F:a Axel T Lind",
                    "organization": "F:a Gbgs kont :centrum"
                }
            ],
            "family": {
                "spouse": "Ingeborg Erlandsson",
                "marriage_year": "1943",
                "children": [
                    {
                        "name": "Björn",
                        "birth_year": "1945"
                    },
                    {
                        "name": "Staffan",
                        "birth_year": "1949"
                    },
                    {
                        "name": "Jörgen",
                        "birth_year": "1957"
                    }
                ]
            },
            "hobbies": [
                "sinologi",
                "numismatik",
                "filateli"
            ]
        }
    }
}