{
    "original": "LAURENT, C HELGE, direktör,\nNorrköping, f i Norrkpg 24/2/82 av grossh\nEdward L o Axelina Goletsky.\nStud hal o hdlssk, hdlsstud i utl 02-03,\ngrund Hdlsf:a C H Laurent 09, verkst\ndir Hdls ab C H Laurent 17-48,\nstyr:-ordf sed 48. - Medl FrimO, W-sex.\nGift m Walberg Eriksson, dtr t\nskeppsred Per E o Hildur Hultqvist. - Barn:\nMarianne f 17, Kurt f 20.\n\nLAURENT,  KURT P  E,  tandläkare,\n\nNorrköping, f i Norrkpg 24/9/20 av dir\n\nHelge L o Walberg Eriksson.\n\nStud:ex Norrkpg 40, tandl:ex Sthlm 46,\n\ndistr:tandl Skärblacka 46-47, priv:prakt\nGusum 47-49,  priv :prakt Norrkpg  sed\n49. - Hobbies: jakt, segling.\nGift   47   m   tandl   Gunvor   Högstadius\nf 22. - Barn: Claes-Göran f 48.\nLAURIN, RICHARD H, fd\nlandssekreterare, Visby, f i Malmö 11/12/93 av\nfolkskollär Oscar L o Augusta Hansson.\nJur  kand  Lund  22,  tingstjg  Sevede  o\nTunaläns   doms   22-26,   länsnot   l:a  kl\nGotl   l   36,   länsassess   Kopparb   l   44,\nlandssekr Gotl l 46-59. - Styr :ordf\nriks-bkns avd:kont 53-63 (styr:led 51), Sv:es\nallm hyp:bks omb i Gotl hyp:fören\n45-64. - Led lokalstyr Visby hal 45-57.\n-Utm: KNO. - Hobby: målning.\nGift 29 m Gertrud Melin, dtr t\nlands-kamr  Gustaf   M   o   Regina  Janson.\n-Barn: Curt f 36.\n\nLAVEMARK,  SVEN A G,  direktör,\n\nGbg, f i Trelleborg 16/11/20 av byggm\nOlof B Larsson o Hilda Wiberg.\nTekn lärov Malmö 40, CTH 46, tekn lic\nCTH 52. - l:e ass CTH 46, ing\nvattenf:-styr 48, driftsing Gbgs elverk 49, byråing\nSthlms elverk 55, byråch Gbgs elverk 56,\növering där 63, dir Gbgs gas- o elverk\nsed 64; spec:lär CTH 52-63, univ:lekt\ndär 62-64. - Led normkomm f\nhögspän-ningsbrytare sed 55. - Skr: The\nTreat-ment of the load in electric powersystem\nstability studies (52), Vad kostar en\ntransformators förluster? (56). -\nHobbies: friluftsliv, simning.\nGift 48 m Elsa Lindstedt f 24, dtr t\nfolkskollär Nils L o Alice Wik. - Barn:\nOlof f 49, Hans f 53.\n",
    "structured": {
        "1": {
            "full_name": "Laurent, C Helge",
            "location": "Norrköping",
            "occupation": "direktör",
            "birth_details": {
                "date": "24/02/1882",
                "place": "Norrköping",
                "parents": "grosshandlare Edward L och Axelina Goletsky"
            },
            "education": [
                {
                    "degree": "Stud hal o hdlssk, hdlsstud",
                    "year": "02-03",
                    "institution": "Hdlsf:a C H Laurent 09"
                }
            ],
            "career": [
                {
                    "position": "verkst dir",
                    "years": {
                        "start_year": 1917,
                        "end_year": 1948
                    },
                    "organization": "Hdls ab C H Laurent"
                }
            ],
            "family": {
                "spouse": "Walberg Eriksson",
                "marriage_year": "NULL",
                "children": [
                    {
                        "name": "Marianne",
                        "birth_year": "1917"
                    },
                    {
                        "name": "Kurt",
                        "birth_year": "1920"
                    }
                ]
            }
        },
        "2": {
            "full_name": "Laurent, Kurt P E",
            "location": "Norrköping",
            "occupation": "tandläkare",
            "birth_details": {
                "date": "24/09/1920",
                "place": "Norrköping",
                "parents": "direktör Helge L and Walberg Eriksson"
            },
            "education": [
                {
                    "degree": "Stud:ex",
                    "year": "1940",
                    "institution": "Norrkpg"
                },
                {
                    "degree": "tandl:ex",
                    "year": "1946",
                    "institution": "Sthlm"
                }
            ],
            "career": [
                {
                    "position": "distr:tandl",
                    "years": {
                        "start_year": 1946,
                        "end_year": 1947
                    },
                    "organization": "Skärblacka"
                },
                {
                    "position": "priv:prakt",
                    "years": {
                        "start_year": 1947,
                        "end_year": 1949
                    },
                    "organization": "Gusum"
                },
                {
                    "position": "priv:prakt",
                    "years": {
                        "start_year": 1949
                    },
                    "organization": "Norrköping"
                }
            ],
            "family": {
                "spouse": "tandl Gunvor Högstadius",
                "marriage_year": "1947",
                "children": [
                    {
                        "name": "Claes-Göran",
                        "birth_year": "1948"
                    }
                ]
            },
            "hobbies": [
                "jakt",
                "segling"
            ]
        },
        "3": {
            "full_name": "Laurin, Richard H",
            "location": "Visby",
            "occupation": "fd landssekreterare",
            "birth_details": {
                "date": "11/12/1893",
                "place": "Malmö",
                "parents": "folkskollär Oscar L o Augusta Hansson"
            },
            "education": [
                {
                    "degree": "Jur kand",
                    "year": "1922",
                    "institution": "Lund"
                }
            ],
            "career": [
                {
                    "position": "tingstjg",
                    "years": {
                        "start_year": 1922,
                        "end_year": 1926
                    },
                    "organization": "Sevede  o Tunaläns doms"
                },
                {
                    "position": "länsnot l:a kl",
                    "years": {
                        "start_year": 1936
                    },
                    "organization": "Gotl l"
                },
                {
                    "position": "länsassess",
                    "years": {
                        "start_year": 1944
                    },
                    "organization": "Kopparb l"
                },
                {
                    "position": "landssekr",
                    "years": {
                        "start_year": 1946,
                        "end_year": 1959
                    },
                    "organization": "Gotl l"
                }
            ],
            "family": {
                "spouse": "Gertrud Melin",
                "marriage_year": "1929",
                "children": [
                    {
                        "name": "Curt",
                        "birth_year": "1936"
                    }
                ],
                "hobbies": [
                    "målning"
                ]
            }
        },
        "4": {
            "full_name": "Lavemark, Sven A G",
            "location": "Gbg",
            "occupation": "direktör",
            "birth_details": {
                "date": "16/11/1920",
                "place": "Trelleborg",
                "parents": "byggm Olof B Larsson o Hilda Wiberg"
            },
            "education": [
                {
                    "degree": "Tekn lärov",
                    "year": "1940",
                    "institution": "Malmö"
                },
                {
                    "degree": "CTH",
                    "year": "1946",
                    "institution": "CTH"
                },
                {
                    "degree": "tekn lic",
                    "year": "1952",
                    "institution": "CTH"
                }
            ],
            "career": [
                {
                    "position": "l:e ass",
                    "years": {
                        "start_year": 1946
                    },
                    "organization": "CTH"
                },
                {
                    "position": "ing vattenf:-styr",
                    "years": {
                        "start_year": 1948
                    }
                },
                {
                    "position": "driftsing",
                    "years": {
                        "start_year": 1949,
                        "end_year": 1955
                    },
                    "organization": "Gbgs elverk"
                },
                {
                    "position": "byråing",
                    "years": {
                        "start_year": 1955,
                        "end_year": 1956
                    },
                    "organization": "Sthlms elverk"
                },
                {
                    "position": "byråch",
                    "years": {
                        "start_year": 1956
                    },
                    "organization": "Gbgs elverk"
                },
                {
                    "position": "övering",
                    "years": {
                        "start_year": 1963
                    },
                    "organization": "Gbgs gas- o elverk"
                },
                {
                    "position": "spec:lär",
                    "years": {
                        "start_year": 1952,
                        "end_year": 1963
                    },
                    "organization": "CTH"
                },
                {
                    "position": "univ:lekt",
                    "years": {
                        "start_year": 1962,
                        "end_year": 1964
                    }
                }
            ],
            "family": {
                "spouse": "Elsa Lindstedt",
                "marriage_year": "1948",
                "children": [
                    {
                        "name": "Olof",
                        "birth_year": "1949"
                    },
                    {
                        "name": "Hans",
                        "birth_year": "1953"
                    }
                ],
                "hobbies": [
                    "friluftsliv",
                    "simning"
                ]
            },
            "publications": [
                {
                    "title": "The Treatment of the load in electric powersystem stability studies",
                    "year": "1952",
                    "type": "NULL"
                },
                {
                    "title": "Vad kostar en transformators förluster?",
                    "year": "1956",
                    "type": "NULL"
                }
            ]
        }
    }
}