{
    "original": "LINDHE, F OLOF R, lektor, Växjö,\nf i Hjortsberga, Kronob l, 3/10/08 av\njvtjm Edvard L o Eva Johansson.\nStud:ex Vänersborg 31, fil kand Upps\n36, teol kand Upps 40, fil lic Lund 44,\nvik lekt folksk:sem Umeå 46, eo adj\nsmåsk:sem Strängnäs 48, vik lekt\nfolksk:sem Kristianstad 49, lekt folksk:sem\nLuleå 51, eo lekt folksk:sem Växjö 62,\nlekt Guldhedens folksk:sem Gbg sed 64.\n\n-    Psykoterapeut   Sthlm   40-45;   konstn\n\nverksamh (skulptur). - Skr: Hur vi är i\nvåra drömmar (47).\n\nGift 2) 63 m Greta Bredenborg f 22, dtr\nt lantbr Johan B o Hanna Johansson.\n-Barn: i l :a akt Eva f 46.\n\nLINDHOFF, K FOLKE I, direktör,\nBorås, f i Skövde 17/1/11 av köpm Carl\nL o Maria Nilsson.\n\nUnderoff:ex 36, mil stud:ex 38, off:ex\nFV 41-; tjg FV 29-46, kapt FV res 47.\n-Org:ch Thule 47, regionch Borås 53,\nre-gionch Skandiakonc Borås sed 65.\n-Länsflygch Älvsb l sed 62. - Led Borås\nhdlskamm. - Medl FrimO, PB. - Utm:\nThuleSM, FV:s luftstridsm. - Hobbies:\njakt, skogsbruk, sportflygning.\nGift 38’ m Ken Johnson, dtr t Henning\nJ o Jenny J. - Barn: Björn f 41, Marie\n(Pia) f 43.\n\nLINDHOLM, ARNE H, kyrkoherde,\nGrohed, f i Sthlm 2/7/07 av hovpred,\nkontr:prost Hjalmar L o Mannie\nHeuman.\n\nTeol kand Upps 31, prästv 32, kyrkoadj\nCarl Johans förs Gbg 33, kommin där\n42, kyrkoh Forshälla sed 52. - Styr:led\nstift Pro Caritate, Åh stiftsgård.\nGift 34 m Marie-Louise Freidenfelt f\n08, dtr t kapt Natanael F o Helene\nPeterson. - Barn: Britt f 35, Ann f 37.\n\nLINDHOLM,  BJÖRN U,  leg läkare,\n\nGbg, f i Brasilien 19/7/29 av dir Uno L\no Margareta Petersen.\nStud:ex Sthlm 48, med kand 53 o med\nlic Gbg 58; aman o ass anat inst Gbgs\nuniv 52-57, vik underläk med klin I o II\nSahlgr sjh 57-58, underläk allergol klin\n58-62, klin aman med klin II där 62-64,\nklin kem inst Gbgs univ sed 64. - Skattm\nMed fören Gbg 53, ordf 54, internat\nsekr 55 o 56, not sen:koll sed 57; styr:led\nGbgs under läk :f ören sed 63. - Folke\nBernadotte-stip 55. - Medl FrimO,\nJunior Chamber of Commerce, Round\nTable m fi. - Skr: ett 20-tal arb inom\ninv med o inv :med allergologi. -\nHobbies: golf, havskappsegling.\nGift 57 m Gunilla Sjöcrona f 34, dtr t\nsjökapt Jan S o Gudrun Kjellegård.\n-Barn: Thomas f 58, Niklas f 59, Katinka\nf 63.\n\n",
    "structured": {
        "1": {
            "full_name": "F OLOF R LINDHE",
            "location": "Växjö",
            "occupation": "lektor",
            "birth_details": {
                "date": "3/10/1908",
                "place": "Hjortsberga, Kronob l",
                "parents": "jvtjm Edvard L o Eva Johansson"
            },
            "education": [
                {
                    "degree": "Stud:ex",
                    "year": "1931",
                    "institution": "Vänersborg"
                },
                {
                    "degree": "filosofie kandidat",
                    "year": "1936",
                    "institution": "Upps"
                },
                {
                    "degree": "teologisk kandidat",
                    "year": "1940",
                    "institution": "Upps"
                },
                {
                    "degree": "filosofie licentiat",
                    "year": "1944",
                    "institution": "Lund"
                }
            ],
            "career": [
                {
                    "position": "vik lekt",
                    "years": {
                        "start_year": 1946,
                        "end_year": 1948
                    },
                    "organization": "folksk:sem Umeå"
                },
                {
                    "position": "eo adj småsk:sem",
                    "years": {
                        "start_year": 1948,
                        "end_year": 1949
                    },
                    "organization": "Strängnäs"
                },
                {
                    "position": "vik lekt folksk:sem",
                    "years": {
                        "start_year": 1949,
                        "end_year": 1951
                    },
                    "organization": "Kristianstad"
                },
                {
                    "position": "lekt folksk:sem",
                    "years": {
                        "start_year": 1951,
                        "end_year": 1962
                    },
                    "organization": "Luleå"
                },
                {
                    "position": "eo lekt folksk:sem",
                    "years": {
                        "start_year": 1962,
                        "end_year": null
                    },
                    "organization": "Växjö"
                },
                {
                    "position": "lekt",
                    "years": {
                        "start_year": 1964,
                        "end_year": null
                    },
                    "organization": "Guldhedens folksk:sem Gbg"
                },
                {
                    "position": "Psykoterapeut",
                    "years": {
                        "start_year": 1940,
                        "end_year": 1945
                    },
                    "organization": "Sthlm"
                },
                {
                    "position": "konstnverksamh",
                    "years": {
                        "start_year": null,
                        "end_year": null
                    },
                    "organization": null
                }
            ],
            "family": {
                "spouse": "Greta Bredenborg",
                "marriage_year": "1963",
                "children": [
                    {
                        "name": "Eva",
                        "birth_year": "1946"
                    }
                ]
            }
        },
        "2": {
            "full_name": "K FOLKE I LINDHOFF",
            "location": "Borås",
            "occupation": "direktör",
            "birth_details": {
                "date": "17/1/1911",
                "place": "Skövde",
                "parents": "köpm Carl L o Maria Nilsson"
            },
            "education": null,
            "career": [
                {
                    "position": "tjg",
                    "years": {
                        "start_year": 1929,
                        "end_year": 1946
                    },
                    "organization": "FV"
                },
                {
                    "position": "kapt FV res",
                    "years": {
                        "start_year": 1947,
                        "end_year": null
                    },
                    "organization": null
                },
                {
                    "position": "Org:ch",
                    "years": {
                        "start_year": 1947,
                        "end_year": 1953
                    },
                    "organization": "Thule"
                },
                {
                    "position": "regionch",
                    "years": {
                        "start_year": 1953,
                        "end_year": 1965
                    },
                    "organization": "Borås"
                },
                {
                    "position": "regionch",
                    "years": {
                        "start_year": 1965,
                        "end_year": null
                    },
                    "organization": "Skandiakonc Borås"
                },
                {
                    "position": "Länsflygch",
                    "years": {
                        "start_year": 1962,
                        "end_year": null
                    },
                    "organization": "Älvsb l"
                }
            ],
            "family": {
                "spouse": "Ken Johnson",
                "marriage_year": "1938",
                "children": [
                    {
                        "name": "Björn",
                        "birth_year": "1941"
                    },
                    {
                        "name": "Marie (Pia)",
                        "birth_year": "1943"
                    }
                ]
            }
        },
        "3": {
            "full_name": "ARNE H LINDHOLM",
            "location": "Grohed",
            "occupation": "kyrkoherde",
            "birth_details": {
                "date": "2/7/1907",
                "place": "Sthlm",
                "parents": "hovpred, kontr:prost Hjalmar L o Mannie Heuman"
            },
            "education": [
                {
                    "degree": "Teologisk kandidat",
                    "year": "1931",
                    "institution": "Upps"
                }
            ],
            "career": [
                {
                    "position": "kyrkoadj",
                    "years": {
                        "start_year": 1933,
                        "end_year": 1942
                    },
                    "organization": "Carl Johans förs Gbg"
                },
                {
                    "position": "kommin",
                    "years": {
                        "start_year": 1942,
                        "end_year": 1952
                    },
                    "organization": "Forshälla"
                }
            ],
            "family": {
                "spouse": "Marie-Louise Freidenfelt",
                "marriage_year": "1934",
                "children": [
                    {
                        "name": "Britt",
                        "birth_year": "1935"
                    },
                    {
                        "name": "Ann",
                        "birth_year": "1937"
                    }
                ]
            }
        },
        "4": {
            "full_name": "BJÖRN U LINDHOLM",
            "location": "Gbg",
            "occupation": "leg läkare",
            "birth_details": {
                "date": "19/7/1929",
                "place": "Brasilien",
                "parents": "dir Uno L o Margareta Petersen"
            },
            "education": [
                {
                    "degree": "Stud:ex",
                    "year": "1948",
                    "institution": "Sthlm"
                },
                {
                    "degree": "med kand",
                    "year": "1953",
                    "institution": null
                }
            ],
            "career": [
                {
                    "position": "aman o ass anat inst",
                    "years": {
                        "start_year": 1952,
                        "end_year": 1957
                    },
                    "organization": "Gbgs univ"
                },
                {
                    "position": "vik underläk",
                    "years": {
                        "start_year": 1957,
                        "end_year": 1958
                    },
                    "organization": "Sahlgr sjh"
                },
                {
                    "position": "underläk",
                    "years": {
                        "start_year": 1958,
                        "end_year": 1962
                    },
                    "organization": "allergol klin"
                },
                {
                    "position": "klin aman",
                    "years": {
                        "start_year": 1962,
                        "end_year": 1964
                    },
                    "organization": "Gbgs univ"
                },
                {
                    "position": "klin kem inst",
                    "years": {
                        "start_year": 1964,
                        "end_year": null
                    },
                    "organization": "Gbgs univ"
                }
            ],
            "family": {
                "spouse": "Gunilla Sjöcrona",
                "marriage_year": "1957",
                "children": [
                    {
                        "name": "Thomas",
                        "birth_year": "1958"
                    },
                    {
                        "name": "Niklas",
                        "birth_year": "1959"
                    },
                    {
                        "name": "Katinka",
                        "birth_year": "1963"
                    }
                ]
            }
        }
    }
}