{
    "original": "Lerum, f i Lund 14/11/21 av adj Otto L\no Mixa Törnqvist.\n\nStud:ex Sthlm 40, KTH 46, ass inst f\nverktygsmaskiner KTH 46, ch mättekn\no elektron lab SKF 47, ass ch f\nGbgs-verken SKF 54, tekn dir konc Joh\nMu-stad ab Gbg sed 58. - Skr: Mätteknik\nför verkstäder (tills m a 56). - Medl The\nRoyal Bachelors Club. - Hobbies: golf,\nfoto.\n\nGift 47 m Marianne Avander f 23, dtr t\ning Fritz A o Karin Gullberg. - Barn:\nKarin f 49, Arne f 52, Åke f 57.\n\nLINDBERG, ALF G N, konstnär,\nMölndal, f i Gbg 05.\nValands konstsk 27-30. - Utf figursaker,\nlandskap, stilleben. - Utst i bl a Sthlm\n59. - Repr i bl a Nät :mus, Gbgs\nkonstmus, Nasjonalgaleriet Oslo. - LFrKA\n59.\n\nLINDBERG, K ARNE, kronofogde,\nBorås, f i Säffle 22/9/20.\nStud:ex Karlstad 40, distr:åkl:ex StHS\n46, polisch:kurs Stat polissk 46,\nlands-fiskalsass Värml l 47-52, bitr landsfiskal\nSunne distr 53, eo landsfiskal Svartlösa\ndistr 59, landsfiskal Munkfors distr 61,\nkronofogde Borås sed 65. - Expert\npolis-beredn. - Sekr Fören Sv:es landsfiskaler\n55-65.\n\nGift 47 m Helga Porat. - Barn: Christer\nf 48, Peter f 57.\n\nLINDBERG,  BENGT J,  professor,\növerläkare, Gbg, f i Gävle 28/3/04 av\nkont :ch Helmer L o Ester Sjödin.\nMed lic 32, med dr o doc i psykiatri\nLund   38,  doc  i  psykologi  o  psykiatri\nGbg 39-53, prof i psykiatri Gbg sed 53,\növerläk Sahlgr sjh sed 46 (l:e underläk\n39, bitr överläk 42). - Skr i psykologi o\npsykiatri. - LVVS 56.\nGift 32 m Sara Ternell f 06, dtr t dir\nSvante T o Anna Olsson. - Barn: Göran\nf 33, Karin f 35, Gunvor f 39.\n\n",
    "structured": {
        "0": {
            "full_name": "Mixo Törnqvist",
            "location": "Lund",
            "occupation": "Koncernchef, Joh Mu-stad ab Gbg",
            "birth_details": {
                "date": "14/11/1921",
                "place": "Lund"
            },
            "education": [
                {
                    "degree": "Stud:ex",
                    "year": "1940",
                    "institution": "Sthlm"
                },
                {
                    "degree": "KTH",
                    "year": "1946",
                    "institution": "KTH"
                }
            ],
            "career": [
                {
                    "position": "Ass inst f verktygsmaskiner",
                    "years": {
                        "start_year": 1946,
                        "end_year": 46
                    },
                    "organization": "KTH"
                },
                {
                    "position": "Ch mättekn o elektron lab",
                    "years": {
                        "start_year": 1947,
                        "end_year": 54
                    },
                    "organization": "SKF"
                },
                {
                    "position": "Ass ch f Gbgs-verken",
                    "years": {
                        "start_year": 1954,
                        "end_year": 58
                    },
                    "organization": "SKF"
                }
            ],
            "family": {
                "spouse": "Marianne Avander",
                "marriage_year": "1947",
                "children": [
                    {
                        "name": "Karin",
                        "birth_year": "1949"
                    },
                    {
                        "name": "Arne",
                        "birth_year": "1952"
                    },
                    {
                        "name": "Åke",
                        "birth_year": "1957"
                    }
                ]
            },
            "hobbies": [
                "golf",
                "foto"
            ]
        },
        "1": {
            "full_name": "Alf G N Lindberg",
            "location": "Mölndal",
            "occupation": "Konstnär",
            "birth_details": {
                "date": "1905",
                "place": "Gbg"
            },
            "education": [
                {
                    "degree": "Valands konstsk",
                    "year": "1927-1930",
                    "institution": "Valands konstsk"
                }
            ],
            "career": [
                {
                    "position": "Konstnär",
                    "years": {
                        "start_year": null,
                        "end_year": null
                    },
                    "organization": null
                }
            ],
            "publications": [
                {
                    "title": "LFrKA 59",
                    "year": null,
                    "type": null
                }
            ]
        },
        "2": {
            "full_name": "Karne Lindberg",
            "location": "Borås",
            "occupation": "Kronofogde",
            "birth_details": {
                "date": "22/9/1920",
                "place": "Säffle"
            },
            "education": [
                {
                    "degree": "Stud:ex",
                    "year": "1940",
                    "institution": "Karlstad"
                },
                {
                    "degree": "Distr:åkl:ex",
                    "year": "1946",
                    "institution": "StHS"
                },
                {
                    "degree": "Polisch:kurs",
                    "year": "1946",
                    "institution": "Stat polissk"
                }
            ],
            "career": [
                {
                    "position": "Lands-fiskalsass",
                    "years": {
                        "start_year": 1947,
                        "end_year": 1952
                    },
                    "organization": "Värml l"
                },
                {
                    "position": "Bitr landsfiskal",
                    "years": {
                        "start_year": 1953,
                        "end_year": 1959
                    },
                    "organization": "Sunne distr"
                },
                {
                    "position": "Eo landsfiskal",
                    "years": {
                        "start_year": 1961,
                        "end_year": null
                    },
                    "organization": "Munkfors distr"
                },
                {
                    "position": "Kronofogde",
                    "years": {
                        "start_year": 1965,
                        "end_year": null
                    },
                    "organization": "Borås"
                }
            ],
            "family": {
                "spouse": "Helga Porat",
                "marriage_year": "1947",
                "children": [
                    {
                        "name": "Christer",
                        "birth_year": "1948"
                    },
                    {
                        "name": "Peter",
                        "birth_year": "1957"
                    }
                ]
            },
            "community_involvement": [
                {
                    "role": "Sekr",
                    "organization": "Fören Sv:es landsfiskaler",
                    "years": "1955-1965"
                }
            ]
        },
        "3": {
            "full_name": "Bengt J Lindberg",
            "location": "Gbg",
            "occupation": "Professor, överläkare",
            "birth_details": {
                "date": "28/3/1904",
                "place": "Gävle"
            },
            "education": [
                {
                    "degree": "Med lic",
                    "year": "1932",
                    "institution": null
                },
                {
                    "degree": "Med dr o doc i psykiatri",
                    "year": "1938",
                    "institution": "Lund"
                }
            ],
            "career": [
                {
                    "position": "Doc i psykologi o psykiatri",
                    "years": {
                        "start_year": 1939,
                        "end_year": 1953
                    },
                    "organization": "Gbg"
                },
                {
                    "position": "Prof i psykiatri",
                    "years": {
                        "start_year": 1953,
                        "end_year": null
                    },
                    "organization": "Gbg"
                },
                {
                    "position": "Överläk",
                    "years": {
                        "start_year": 1946,
                        "end_year": null
                    },
                    "organization": "Sahlgr sjh"
                }
            ],
            "family": {
                "spouse": "Sara Ternell",
                "marriage_year": "1932",
                "children": [
                    {
                        "name": "Göran",
                        "birth_year": "1933"
                    },
                    {
                        "name": "Karin",
                        "birth_year": "1935"
                    },
                    {
                        "name": "Gunvor",
                        "birth_year": "1939"
                    }
                ]
            },
            "board_memberships": [],
            "honorary_titles": [
                {
                    "title": "LVVS 56",
                    "institution": null,
                    "year": null
                }
            ]
        }
    }
}