{
    "original": "LINDEKRANTZ, S IVAR,\nbildhuggare, Gbg, f i Gbg 30/12/02 av\npianosnickare Carl L o Ellen Johansson.\nDelt i restaur:arbeten i äldre\nlandsortskyrkor, utf träskulpturer t Sundsvalls,\nFristads, Söderleds o Aspeboda kyrkor,\nutomhusskulptur av trä i Guldheden\nGbg. - Delt Nord utst Gbg 57. - Utm:\nLFrKA 59.\n\nGift 55 m Maria Wallerius f 14, dtr t\nkyrkoh Ivar W o Agnes Fjellman.\n\nLINDEKRANTZ, PER G, konstnär,\nFärjestaden, f i Gbg 20/1/13 av\npianosnickare Carl L o Ellen Johansson.\nValands målarsk, Acad de la Grande\nChaumiére Paris. - Bl arb: Mosaikgolv\nLandsstatshuset Karlskrona, väggmåln\nSv hdlsbkn Gbg, keramik Folkets hus\nVästerås. - Sep:uist Sthlm 39, delt i\nsaml :utst Sthlm, Gbg, Hfors, Dublin,\nParis, New York. - Repr i Nät :mus,\nGbgs konstmus, Waldemarsudde m fi.\nGift 52 m Eva Brdlik f 22, dtr t dr\nMilos B o Emanuela Hotowetz (skilsm).\n\nLINDELL, KARL-ERIK H, ingenjör,\nHuskvarna, f i N Solberga, Jönkpgs l,\n17/1/16 av skräddarm Carl-Johan L o\nHilma Johansson.\n\nRealex 33, korresp:- o egna stud i\nbyggn :tekn o arkitektur 34-44. -\nMätn:-biträde stadsing :kont Huskvarna 34,\nmätn :tekniker o byggn :insp där 42,\nbyggn:ing Henningsons byggn ab 46, ch\nHenningsons arkit:kont sed 58. - Sekr\nHuskvarna stads skönhetsråd 49-59; medl\nOdd Fellow. - Bl arb: projekt ett flert\nkyrkobyggn o bilserviceverkst:er, utfört\narkit :ritn t en större ind f pulvertillverkn\ni Sao Paolo Brasilien. - Hobbies: jakt,\nfiske, sport, konst.\n\nGift 41 m Siri Carlsson f 17, dtr t Thure\nC o Adina Åström. - Barn: Inger f 44,\nAnders f 48.\n\nLINDELL,   NILS  G  M,  kyrkoherde,\nÖlands  Skogsby,  f  i  Örsjö,  Kalmar  l,\n17/9/04 av kyrkoh Axel L o Herta\nEngström.\nStud:ex Kalmar 23, fil mag 26 o teol\n\nkand Lund 28, lär Vaxholms samrealsk\n29, kommin Örsjö 32, kyrkoh Älmeboda\n39, Torslunda sed 53. - Ordf kyrkoråd,\nkyrkofullm o folksk:styr, v ordf\nkomm:-fullm. - Utm: LNO.\n\nGift 32 m Carin Wångdahl, dtr t handl\nAlbert W o Hulda Larsson. - Barn:\nMonika f 33, Kerstin f 36, Ingegerd f 40,\nBarbro f 43.\n\n",
    "structured": {
        "0": {
            "full_name": "LINDEKRANTZ, S IVAR",
            "location": "Göteborg",
            "occupation": "bildhuggare",
            "birth_details": {
                "date": "30/12/1902",
                "place": "Göteborg",
                "parents": "Carl L o Ellen Johansson"
            },
            "education": [],
            "career": [
                {
                    "position": "Delt i restaur:arbeten",
                    "years": {
                        "start_year": 1950,
                        "end_year": 1950
                    },
                    "organization": "äldre landsortskyrkor"
                },
                {
                    "position": "utf träskulpturer",
                    "years": {
                        "start_year": 1950,
                        "end_year": 1950
                    },
                    "organization": "Sundsvalls, Fristads, Söderleds o Aspeboda kyrkor"
                },
                {
                    "position": "utomhusskulptur av trä",
                    "years": {
                        "start_year": 1950,
                        "end_year": 1950
                    },
                    "organization": "Guldheden Göteborg"
                }
            ],
            "family": {
                "spouse": "Maria Wallerius",
                "marriage_year": "1955",
                "children": []
            }
        },
        "1": {
            "full_name": "LINDEKRANTZ, PER G",
            "location": "Färjestaden",
            "occupation": "konstnär",
            "birth_details": {
                "date": "20/01/1913",
                "place": "Göteborg",
                "parents": "Carl L o Ellen Johansson"
            },
            "education": [
                {
                    "degree": "Valands målarsk",
                    "year": "1950",
                    "institution": "Acad de la Grande Chaumiére Paris"
                }
            ],
            "career": [
                {
                    "position": "Mosaikgolv",
                    "years": {
                        "start_year": 1950,
                        "end_year": 1950
                    },
                    "organization": "Landsstatshuset Karlskrona"
                },
                {
                    "position": "väggmåln",
                    "years": {
                        "start_year": 1950,
                        "end_year": 1950
                    },
                    "organization": "Sv hdlsbkn Gbg"
                },
                {
                    "position": "keramik",
                    "years": {
                        "start_year": 1950,
                        "end_year": 1950
                    },
                    "organization": "Folkets hus Västerås"
                }
            ],
            "family": {
                "spouse": "Eva Brdlik",
                "marriage_year": "1952",
                "children": []
            }
        },
        "2": {
            "full_name": "LINDELL, KARL-ERIK H",
            "location": "Huskvarna",
            "occupation": "ingenjör",
            "birth_details": {
                "date": "17/01/1916",
                "place": "N Solberga, Jönköpings l",
                "parents": "Carl-Johan L o Hilma Johansson"
            },
            "education": [],
            "career": [
                {
                    "position": "Mätn:-biträde",
                    "years": {
                        "start_year": 1950,
                        "end_year": 1950
                    },
                    "organization": "stadsing :kont Huskvarna"
                },
                {
                    "position": "mätn :tekniker",
                    "years": {
                        "start_year": 1950,
                        "end_year": 1950
                    },
                    "organization": "byggn :insp Huskvarna"
                },
                {
                    "position": "byggn:ing",
                    "years": {
                        "start_year": 1950,
                        "end_year": 1950
                    },
                    "organization": "Henningsons byggn ab"
                },
                {
                    "position": "ch Henningsons arkit:kont",
                    "years": {
                        "start_year": 1958,
                        "end_year": 1958
                    }
                }
            ],
            "family": {
                "spouse": "Siri Carlsson",
                "marriage_year": "1941",
                "children": [
                    {
                        "name": "Inger",
                        "birth_year": "1944"
                    },
                    {
                        "name": "Anders",
                        "birth_year": "1948"
                    }
                ]
            },
            "hobbies": [
                "jakt",
                "fiske",
                "sport",
                "konst"
            ]
        },
        "3": {
            "full_name": "LINDELL,   NILS  G  M",
            "location": "Ölands Skogsby",
            "occupation": "kyrkoherde",
            "birth_details": {
                "date": "17/09/1904",
                "place": "Örsjö, Kalmar l",
                "parents": "kyrkoh Axel L o Herta Engström"
            },
            "education": [
                {
                    "degree": "stud:ex",
                    "year": "1923",
                    "institution": "Kalmar"
                },
                {
                    "degree": "fil mag",
                    "year": "1926",
                    "institution": "Lund"
                },
                {
                    "degree": "teol kand",
                    "year": "1928",
                    "institution": "Lund"
                }
            ],
            "career": [
                {
                    "position": "lär",
                    "years": {
                        "start_year": 1929,
                        "end_year": 1929
                    },
                    "organization": "Vaxholms samrealsk"
                },
                {
                    "position": "kommin",
                    "years": {
                        "start_year": 1932,
                        "end_year": 1932
                    },
                    "organization": "Örsjö"
                },
                {
                    "position": "kyrkoh",
                    "years": {
                        "start_year": 1939,
                        "end_year": 1939
                    },
                    "organization": "Älmeboda"
                },
                {
                    "position": "Torslunda",
                    "years": {
                        "start_year": 1953,
                        "end_year": 1953
                    }
                }
            ],
            "family": {
                "spouse": "Carin Wångdahl",
                "marriage_year": "1932",
                "children": [
                    {
                        "name": "Monika",
                        "birth_year": "1933"
                    },
                    {
                        "name": "Kerstin",
                        "birth_year": "1936"
                    },
                    {
                        "name": "Ingegerd",
                        "birth_year": "1940"
                    },
                    {
                        "name": "Barbro",
                        "birth_year": "1943"
                    }
                ]
            }
        }
    }
}