{
    "original": "Hagberg, Nils E’mil, jägmästare,\ndocent, Sthlm, f. 22/10/96 i Laske, Vedum,\nSkarab. 1. Stud:ex. i Uddevalla 17,\nut-&lt;3X. fr. Skogshögsk. 22. Stip :res. t.\ngrannländerna, mellaneuropa o. Italien.\nAnst. v. Domänverket 24, Skogshögsk.\n29. Docent i skogsuppskattn. o.\nskogs-indeln. 37, t. f. prof. 44. V. ordf. i\nAka-dem. skyttekomp. 30-38, skattm. 41-43\ni Sv. Sällsk. f. fotogrammetri. Hobbies:\nSkytte, konst. SkytteGM, SkytteM.\nHagbrink, Eric Sven Arthur,\ndirektör, Sthlm, f. 19/9/99 i Sthlm. Stud :ex.\nv. östra Real i Sthlm 18, DHS 22.\nSpråk- o. företagsstud. i Tyskl. 14, 21,\n31, 37, i Engl. 25, 30, i Amerika 35, i\nFrankr. 39, Norge 24, Finl. 28, Danm.\n38. Anst. v. A-B Sv. Tobaksmonop :s\nhuv:kont. i Sthlm 19-20, 22-24, Sv.\nKvarnfören :s Försäljn. A-B i Sthlm 24-\n33, Dagens Nyheters A-B fr. 33. Sekr.\ni Företagsekonom. Fören. sed. 39,\nHobbies: Fotografering, naturstudier,\nresor, historiska biografier.\nHagelbäck, Ture Sigfrid,\ncivilingenjör, Sthlm, f. 16/5/96 i Härnösand av\ntrafikch. o. dir. T. J. F. H. o. Ulrika\nLyttkens. G. 33 m. Kerstin Bildt.\nStud:ex. l Härnösand 15, KTH 15-17 o.\n19-21. Ing. v. elektrifier. av\nKlarälvs-ban. 21, v. Telegr:verk. 22-25, v. S. J :s\ntelegr :ing :exp. 25-26, elektro- o.\nsig-naling. v. Gtbg-Borås o. Borås-Alvesta\njärnv. 26-30, telefoning. i Siam 30-32,\nanst. h. Telef. A-B L. M. Ericsson,\nSthlm, sed. 32. LSTF.\nHagelin, Boris Caesar Wilhelm,\ndirektör, civilingenjör, Sthlm, f. 2/7/92 i\nHadschikent, Aserbeidjan, av gen:kons.\nK. W. H. o. Hilda Kinander. G. m.\nAnnie Barth. Stud:ex. 10, ex. fr. KTH\n44. Anst. v. ASEA 15-20, Standard Oil\nCo. of N. J. i New York 21, eg.\nuppfinnare- o. industriverksamhet, verkst,\ndir. t. 42 samt huv :intressent i A-B\nCryptotekn., Sthlm. Hobbies: Musik o.\nmotorsport. RVO, RFrHL.\nHagelin, Elmar Richard Edward,\nmajor, Sthlm, f. 29/4/85 i Kungälv av\napot. o. rådm. E. G. H. o. Maria\nPalmborg. Off:ex. 08, genomg.\nInfanteri-skjutsk., vapenoff :kurs,\nflygspanarut-bildn. Und:löjtn. v. Kgl. Jämtl.\nfältj:-reg. 08, löjtn. 13, kapt. 23, major i\narmén 43. RSO.\n",
    "structured": {
        "1": {
            "full_name": "Hagberg, Nils E’mil",
            "location": "Sthlm",
            "occupation": "jägmästare, docent",
            "birth_details": {
                "date": "22/10/1896",
                "place": "Laske, Vedum, Skaraborgs Län"
            },
            "education": [
                {
                    "degree": "Stud:ex.",
                    "year": "1917",
                    "institution": "Uddevalla"
                },
                {
                    "degree": "Skogshögsk.",
                    "year": "1922",
                    "institution": "Sthlm"
                }
            ],
            "career": [
                {
                    "position": "Anst. v. Domänverket",
                    "years": {
                        "start_year": 1924,
                        "end_year": null
                    },
                    "organization": null
                },
                {
                    "position": "Docent i skogsuppskattn. o. skogs-indeln.",
                    "years": {
                        "start_year": 1937,
                        "end_year": null
                    },
                    "organization": null
                },
                {
                    "position": "t. f. prof.",
                    "years": {
                        "start_year": 1944,
                        "end_year": null
                    },
                    "organization": null
                }
            ],
            "family": {
                "spouse": null,
                "marriage_year": null,
                "children": [],
                "parents": null
            },
            "publications": [],
            "community_involvement": [],
            "board_memberships": [],
            "honorary_titles": [],
            "hobbies": [
                "Skytte",
                "konst"
            ],
            "other_information": "Stip :res. t. grannländerna, mellaneuropa o. Italien. V. ordf. i Akadem. skyttekomp. 30-38, skattm. 41-43 i Sv. Sällsk. f. fotogrammetri. SkytteGM, SkytteM."
        },
        "2": {
            "full_name": "Hagbrink, Eric Sven Arthur",
            "location": "Sthlm",
            "occupation": "direktör",
            "birth_details": {
                "date": "19/9/1899",
                "place": "Sthlm"
            },
            "education": [
                {
                    "degree": "Stud :ex.",
                    "year": "1918",
                    "institution": "östra Real i Sthlm"
                },
                {
                    "degree": "DHS",
                    "year": "1922",
                    "institution": null
                }
            ],
            "career": [
                {
                    "position": "Anst. v. A-B Sv. Tobaksmonop :s huv:kont.",
                    "years": {
                        "start_year": 1919,
                        "end_year": 1920
                    },
                    "organization": "Sthlm"
                },
                {
                    "position": "Sekr. i Företagsekonom. Fören. ",
                    "years": {
                        "start_year": 1939,
                        "end_year": null
                    },
                    "organization": null
                }
            ],
            "family": {
                "spouse": null,
                "marriage_year": null,
                "children": [],
                "parents": null
            },
            "publications": [],
            "community_involvement": [],
            "board_memberships": [],
            "honorary_titles": [],
            "hobbies": [
                "Fotografering",
                "naturstudier",
                "resor",
                "historiska biografier"
            ]
        },
        "3": {
            "full_name": "Hagelbäck, Ture Sigfrid",
            "location": "Sthlm",
            "occupation": "civilingenjör",
            "birth_details": {
                "date": "16/5/1896",
                "place": "Härnösand"
            },
            "education": [
                {
                    "degree": "Stud:ex.",
                    "year": "1915",
                    "institution": "Härnösand"
                },
                {
                    "degree": "KTH",
                    "year": "1915-1917, 1919-1921",
                    "institution": null
                }
            ],
            "career": [
                {
                    "position": "Ing. v. elektrifier. av Klarälvs-ban.",
                    "years": {
                        "start_year": 1921,
                        "end_year": null
                    },
                    "organization": null
                },
                {
                    "position": "LSTF",
                    "years": {
                        "start_year": null,
                        "end_year": null
                    },
                    "organization": null
                }
            ],
            "family": {
                "spouse": "Kerstin Bildt",
                "marriage_year": "1933",
                "children": [],
                "parents": null
            },
            "publications": [],
            "community_involvement": [],
            "board_memberships": [],
            "honorary_titles": [],
            "hobbies": []
        },
        "4": {
            "full_name": "Hagelin, Boris Caesar Wilhelm",
            "location": "Sthlm",
            "occupation": "direktör, civilingenjör",
            "birth_details": {
                "date": "2/7/1892",
                "place": "Hadschikent, Aserbeidjan"
            },
            "education": [
                {
                    "degree": "Stud:ex.",
                    "year": "1910",
                    "institution": null
                },
                {
                    "degree": "KTH",
                    "year": "1944",
                    "institution": null
                }
            ],
            "career": [
                {
                    "position": "Anst. v. ASEA",
                    "years": {
                        "start_year": 1915,
                        "end_year": 1920
                    },
                    "organization": null
                },
                {
                    "position": "Standard Oil Co. of N. J. i New York",
                    "years": {
                        "start_year": 1921,
                        "end_year": null
                    },
                    "organization": null
                }
            ],
            "family": {
                "spouse": "Annie Barth",
                "marriage_year": null,
                "children": [],
                "parents": {
                    "parents": "gen:kons. K. W. H. o. Hilda Kinander"
                }
            },
            "publications": [],
            "community_involvement": [],
            "board_memberships": [],
            "honorary_titles": [
                {
                    "title": "RVO",
                    "institution": null,
                    "year": null
                },
                {
                    "title": "RFrHL",
                    "institution": null,
                    "year": null
                }
            ],
            "hobbies": [
                "Musik",
                "motorsport"
            ]
        },
        "5": {
            "full_name": "Hagelin, Elmar Richard Edward",
            "location": "Sthlm",
            "occupation": "major",
            "birth_details": {
                "date": "29/4/1885",
                "place": "Kungälv"
            },
            "education": [],
            "career": [
                {
                    "position": "löjtn.",
                    "years": {
                        "start_year": 1913,
                        "end_year": null
                    },
                    "organization": "Kungälv"
                },
                {
                    "position": "major i armén",
                    "years": {
                        "start_year": 1943,
                        "end_year": null
                    },
                    "organization": null
                }
            ],
            "family": {
                "spouse": null,
                "marriage_year": null,
                "children": [],
                "parents": {
                    "mother": "Maria Palmborg",
                    "father": "apot. o. rådm. E. G. H."
                }
            },
            "publications": [],
            "community_involvement": [],
            "board_memberships": [],
            "honorary_titles": [
                {
                    "title": "RSO",
                    "institution": null,
                    "year": null
                }
            ],
            "hobbies": []
        }
    }
}