{
    "original": "Hall, Mac Ivar, försäkringsdirektör,\nDjursholm, f. 16/11/92 i Sundsvall av\nfondmäkl. A. H. o. Laura Carlson. G.\nm. Astrid Grahm. Barn: Inger-Britt\nf. 21. Stud:ex., stud. v.-Handelshögsk.\nAnst. v. Försäkr. A-B Heimdall 13-15,\nFörsäkr. A-B Fylgia sed. 15, v. dir. där\nsed. 21, v. verkst, dir. där sed. 43. Ordf.\ni div. tariffsammanslutn. bl.\nförsäkr:-bol., styrrled. i Allm. Hagelskadeförs\n:-bol. Stud:res. inom Europa o. U. S. A.\nSkr.: div. försäkringslitt. RVO.\nHälla, Nils, arkitekt, Sthlm, f. 8/7/12\ni Mjöbäck, Älvsb. 1. G. m. Anna-Greta\nFalländer. CTH, KTH samt stud. i utl.\nMedarb, v. ett flert. utställn., arb. s.\nnyttokonstnär inom textilbranschen.\nArk. i Kgl. Egnah :styr. 41, t. f. byråing.\nv. styr :s byggn :kont. 43. Spec.: sysslat\nm. lantkökens inredn. o. planering av\nkollektiva tvätterier.\nHalländer-Widing, Edla Eira Maria,\ntandläkare, Sthlm, f. i Skara av prof.\nJohan Wilh. Halländer o. Edla Maria\nCecilia Dunér. G. 25 m. kapt. v.\nVärm-1 :s reg. Klas Widing, d. 28. Barn:\nBritta f. 26. Student v. Sigrid Rudebecks\ngymn. f. flickor, Gtbg, 19, tandl:kand.\n21, taridl. 24. Assist, h. tandl. Gustaf\nSvensson, Karlstad, 24, vik. i\nMalmberget 24, prakt, i Boden 25-35, förest, f.\nmilitära tandpol, v. Bodens garn.\nsamma tid, skoltandl. i Boden 30-35,\nskol-tandl. i Sollentuna sed. hösten 35,\nprakt, i Sthlm sed. 36.\nHallberg, Bengt Christian Schuwert,\nmed. lic., Sthlm, f. 15/10/97 i\nKöpenhamn av red. Alfr. H. o. Anna Olsen.\nStud :ex. i H rborg 15, med. kand. i\nLund 19, med. lic. 25. Assist :läk. v.\nLjungby las. 21, e. läk. i Norsjö 22 o.\ni Kinna distr. 22-23, e. undrlak. v.\nSe-raf :läs. ögonpoliklin. 24-25, aman.\ndärst. 25-26, därund. t. f. poliklin :förest. 2\nmån., t. f. aman. v. Sahlgrenska sjukh.\n24 o. 26, proviläk. 25 o. 26, prakt. läk.\ni Norrköp. 27-32, förordn, att uppeh.\nbefattn. s. läk. v. Norrköp, stads\nfat-tigv. 30-32, s. ajssist :läk. o/t. f. und:läk.\nv. S:t Eriks sjukh. med. avd. 33-34, t. f.\n2:e läk. v. S :ta Maria sjukh. 34-36, e. o.\n2:e läk. v. S:t Olofs sjukh. 37, 2:e läk.\ndärst. fr. 39. Stud:res. t. Frankr. 20\nsamt t. ett flert. europ. länd. 30-39.\nSkr.: ett 100-t. art. i populärmed. o.\nsoc. ämnen samt reseskildr.\n",
    "structured": {
        "0": {
            "full_name": "Hall, Mac Ivar",
            "location": "Djursholm",
            "occupation": "Försäkringsdirektör",
            "birth_details": {
                "date": "16/11/1892",
                "place": "Sundsvall",
                "parents": "fondmäkl. A. H. o. Laura Carlson"
            },
            "education": [
                {
                    "degree": "Stud:ex.",
                    "year": "NULL",
                    "institution": "Handelshögsk"
                }
            ],
            "career": [
                {
                    "position": "Anst. v. Försäkr. A-B Heimdall",
                    "years": {
                        "start_year": 1913,
                        "end_year": 1915
                    },
                    "organization": "NULL"
                },
                {
                    "position": "Försäkr. A-B Fylgia",
                    "years": {
                        "start_year": 1915,
                        "end_year": 1943
                    },
                    "organization": "NULL"
                }
            ],
            "family": {
                "spouse": "Astrid Grahm",
                "marriage_year": "NULL",
                "children": [
                    {
                        "name": "Inger-Britt",
                        "birth_year": "21"
                    }
                ]
            }
        },
        "1": {
            "full_name": "Hälla, Nils",
            "location": "Sthlm",
            "occupation": "Arkitekt",
            "birth_details": {
                "date": "8/7/1912",
                "place": "Mjöbäck, Älvsb. 1",
                "parents": "NULL"
            },
            "education": [
                {
                    "degree": "CTH, KTH",
                    "year": "NULL",
                    "institution": "NULL"
                }
            ],
            "career": [
                {
                    "position": "Ark. i Kgl. Egnah :styr.",
                    "years": {
                        "start_year": 1941,
                        "end_year": "NULL"
                    },
                    "organization": "NULL"
                }
            ],
            "family": {
                "spouse": "Anna-Greta Falländer",
                "marriage_year": "NULL",
                "children": [
                    {
                        "name": "NULL",
                        "birth_year": "NULL"
                    }
                ]
            }
        },
        "2": {
            "full_name": "Halländer-Widing, Edla Eira Maria",
            "location": "Sthlm",
            "occupation": "Tandläkare",
            "birth_details": {
                "date": "NULL",
                "place": "Skara",
                "parents": "prof. Johan Wilh. Halländer o. Edla Maria Cecilia Dunér"
            },
            "education": [
                {
                    "degree": "Student v. Sigrid Rudebecks gymn.",
                    "year": "19",
                    "institution": "Gtbg"
                }
            ],
            "career": [
                {
                    "position": "NULL",
                    "years": {
                        "start_year": "NULL",
                        "end_year": "NULL"
                    },
                    "organization": "NULL"
                }
            ],
            "family": {
                "spouse": "kapt. v. Värm-1 :s reg. Klas Widing",
                "marriage_year": "25",
                "children": [
                    {
                        "name": "Britta",
                        "birth_year": "26"
                    }
                ]
            }
        },
        "3": {
            "full_name": "Hallberg, Bengt Christian Schuwert",
            "location": "Sthlm",
            "occupation": "Med. lic.",
            "birth_details": {
                "date": "15/10/1897",
                "place": "Köpenhamn",
                "parents": "red. Alfr. H. o. Anna Olsen"
            },
            "education": [
                {
                    "degree": "Stud :ex. i H rborg",
                    "year": "15",
                    "institution": "NULL"
                }
            ],
            "career": [
                {
                    "position": "Assist :läk. v. Ljungby las.",
                    "years": {
                        "start_year": 1921,
                        "end_year": "NULL"
                    },
                    "organization": "NULL"
                },
                {
                    "position": "e. läk. i Norsjö",
                    "years": {
                        "start_year": 1922,
                        "end_year": 1923
                    },
                    "organization": "NULL"
                }
            ],
            "family": {
                "spouse": "NULL",
                "marriage_year": "NULL",
                "children": [
                    {
                        "name": "NULL",
                        "birth_year": "NULL"
                    }
                ]
            }
        }
    }
}