{
    "original": "Heniieberg, Carl Albert Theodor,\ntonsättare, Sthlm, f. i Sthlm 27/3/01 av\nhovkapellm. Rich. H. o. Thyra\nGyllenskepp. G. 22 m. Irma Malmgren. Stud\n:-ex. 20, stud. v. musikkonservat.,\nkon-trap. o. kpmpos. f. prof. E. Ellberg, av.\nundivisn. i pianospel o. diriger. 20-24,\nerh. stat. tonsätt :stip. 26-30, stud. i\nWien o. Paris, fr. 31 verks, i fören. Sv.\ntonsättares internat, musikbyrå Stim,\nu. p. a. Bl. komp.: Inka (tråg. opera,\nChemnitz 37), Det jäser i Småland (kom.\nopera, Chemnitz 39), Den lyckliga sta-\nden (tråg. opera), 5 symf., kantat. Det\nljusa landet, körverket Vår,\nkammar-symf., 2 stråkkvart., en symf. dikt\nVal-borgsmässonatt, pianokons., cellokons.,\ntrumpetkons., basunkons, m. m.\nHenning, Bengt Filip Daniel, verkst,\ndirektör, Sthlm, f. 15/1/91 i Gtbg. G.\n19 m. Lisen Dalgren. Barn: Inga\nMargareta f. 20, Bengt Walter f. 21,\nEjan Barbro Kristina f. 23, Elsa\nMargareta f. 29. Realex, v. Gtbgs Högre\nLa-tinlärov. 08, avg:ex. v. Gtbgs Hdlsinst.\n20, Tj :m. h. A-B Gtbgs Bk,\nKungsbacka, 10-11, tj :m. i A-B Gtbgs Bk, Gtbg,\n11-18, kamr:assist. v. ASEA, Västerås,\n18-19, kamrer i A-B Elektrolytverken,\nVästerås, 19-21, kamrer i Skattebetal :s\nFören., Sthlm, 21-22, kamrer i A-B\nSystema, Sthlm, 22-24, v. verkst, dir. därst.\n24-27, verkst, dir. sed. 28. Styr :led. i\nKFUM, Gentralfören. o. dess verkst,\nutsk, sed. 32, i KFUM:s Riksförb. o. dess\nverkst, utsk. sed. 36, i KFUM:s Vänner\no. KFUM:s Vänners Centralråd sed. 36.\nHenning, Carl Henning,\növerstelöjtnant, Sthlm, f. 24/2/77 i Hässjö,\nVäster-norrl. G. 04 m. Garoline Kirstine\nHol-ter-Hedström. Und:löjtn. v.\nVäster-norrl. reg. 98, löjtn. 00, kapt. 14, major\nv. Västerb. reg. 21, övrlöjtn. v.\nVäster-norrl. reg. 26, i res. 29. RSO. KHS.\nHenning, Eva, skådespelerska, Sthlm,\nf. i Newark, N. Y., U. S. A., av ing.\nEdgar Voss Wetlesen o. Ragni Frisell\n(styvdotter t. skådespel. Uno Henning).\nG. 43 m. frih. Jochum Beck-Friis. Stud.\ni Annask. o. Lyceum f. flickor i Sthlm,\nDram. teat :s elevsk. 38-40. Spelade\nDiana i Diana går på jakt på Nya teat. o.\nVasateat. 40-41, på Blancheteat. i\nHyggliga människor, På solsidan o.\nVäninnor, o. på Nya teat. i revytidn. Taggen\no. Natten till den 17 januari Filmer:\nSnapphanar, Det är min musik, Generai\nvon Döbeln, Elvira Madigan o. Stopp!\nTänk på något annat.\n",
    "structured": {
        "0": {
            "full_name": "Heniieberg, Carl Albert Theodor",
            "location": "Sthlm",
            "occupation": "Tonsättare",
            "birth_details": {
                "date": "27/03/1901",
                "place": "Sthlm"
            },
            "education": [
                {
                    "degree": "Stud:-ex.",
                    "year": "1920",
                    "institution": "Stud. v. musikkonservat."
                }
            ],
            "career": [
                {
                    "position": "Prof.",
                    "years": {
                        "start_year": 1920,
                        "end_year": 1924
                    },
                    "organization": "Undivisn. i pianospel o. diriger."
                },
                {
                    "position": "Erh. stat. tonsätt",
                    "years": {
                        "start_year": 1926,
                        "end_year": 1930
                    },
                    "organization": "Sv. tonsättares internat, musikbyrå Stim"
                }
            ],
            "family": {
                "spouse": "Irma Malmgren",
                "marriage_year": "1922",
                "children": []
            }
        },
        "1": {
            "full_name": "Henning, Bengt Filip Daniel",
            "location": "Sthlm",
            "occupation": "Verkst direktör",
            "birth_details": {
                "date": "15/01/1891",
                "place": "Gtbg"
            },
            "education": [
                {
                    "degree": "Realex",
                    "year": "1908",
                    "institution": "Gtbgs Högre La-tinlärov."
                }
            ],
            "career": [
                {
                    "position": "Tj :m",
                    "years": {
                        "start_year": 1910,
                        "end_year": 1911
                    },
                    "organization": "A-B Gtbgs Bk, Kungsbacka"
                },
                {
                    "position": "Kamr:assist.",
                    "years": {
                        "start_year": 1911,
                        "end_year": 1918
                    },
                    "organization": "ASEA, Västerås"
                },
                {
                    "position": "Kamrer",
                    "years": {
                        "start_year": 1919,
                        "end_year": 1921
                    },
                    "organization": "A-B Elektrolytverken, Västerås"
                },
                {
                    "position": "Kamrer",
                    "years": {
                        "start_year": 1921,
                        "end_year": 1922
                    },
                    "organization": "Skattebetal :s Fören., Sthlm"
                },
                {
                    "position": "Verkst",
                    "years": {
                        "start_year": 1924,
                        "end_year": 1927
                    },
                    "organization": "A-B Systema, Sthlm"
                }
            ],
            "family": {
                "spouse": "Lisen Dalgren",
                "marriage_year": "1919",
                "children": [
                    {
                        "name": "Inga Margareta",
                        "birth_year": "1920"
                    },
                    {
                        "name": "Bengt Walter",
                        "birth_year": "1921"
                    },
                    {
                        "name": "Ejan Barbro Kristina",
                        "birth_year": "1923"
                    },
                    {
                        "name": "Elsa Margareta",
                        "birth_year": "1929"
                    }
                ]
            }
        },
        "2": {
            "full_name": "Henning, Carl Henning",
            "location": "Sthlm",
            "occupation": "Överstelöjtnant",
            "birth_details": {
                "date": "24/02/1877",
                "place": "Hässjö, Väster-norrl"
            },
            "career": [
                {
                    "position": "Und:löjtn.",
                    "years": {
                        "start_year": 1898,
                        "end_year": 1900
                    },
                    "organization": "Väster-norrl. reg."
                },
                {
                    "position": "Löjtn.",
                    "years": {
                        "start_year": 1900,
                        "end_year": 1914
                    },
                    "organization": "Väster-norrl. reg."
                },
                {
                    "position": "Kapt.",
                    "years": {
                        "start_year": 1914,
                        "end_year": 1921
                    },
                    "organization": "Västerb. reg."
                },
                {
                    "position": "Övrlöjtn.",
                    "years": {
                        "start_year": 1926,
                        "end_year": 1929
                    },
                    "organization": "Väster-norrl. reg."
                }
            ],
            "family": {
                "spouse": "Garoline Kirstine Hol-ter-Hedström",
                "marriage_year": "1904",
                "children": []
            }
        },
        "3": {
            "full_name": "Henning, Eva",
            "location": "Sthlm",
            "occupation": "Skådespelerska",
            "birth_details": {
                "place": "Newark, N. Y., U. S. A."
            },
            "career": [
                {
                    "position": "Skådespelerska",
                    "years": {
                        "start_year": 1943
                    },
                    "organization": "Nya teat."
                }
            ],
            "family": {
                "spouse": "Frih. Jochum Beck-Friis",
                "marriage_year": "1943",
                "children": []
            }
        }
    }
}