{
    "original": "Hedin, Wilhelm Ireneus, kamrer,\nSthlm, f. 28/7/00 i Sveg av köpm. C. W.\nHedin o. Ada Andersson. G. 25 m.\nLinnea Lehnberg. Barn: Gunnar f. 32,\nLars f. 34. Realskoleex. v. Sundsvalls\nlärov. 17, Sundsvalls Hdlsgymn. 17-18.\nTj :m. v. A-B Köpmannabanken o.\nSödermanlands Ensk. Bank 18-21, skilda\nkontor sanställn. i Sthlm 22-26, t j :m. h.\nGoodyear Gummi A-B 26, huv :bokf. 31,\nkassör där 32, kamrer sed. 39 i det t.\nGoodvear Gummi Fabr. A-B ändr. bol.\nKyrkofullm. i Högalids förs., led. av\nskolråd., av fattigv :styr. i Högalids förs.\nMedl. av sällsk:t Sundsvallspojkarna.\nHedlund, Bertil Adolf (Bull),\nkonstnär, Sthlm, f. i Falun 9/4/93 av fabr.\nCarl A. H. o. Henrica Norgren. G. 1.\n18 m. Karin Ericsson, 2. 36 m. Karin\nArehn. Falu h. a. L, Tekn. sk., Sthlm,\n11-13, Konsthögsk. 14-15, i Frankr.\n12-14, Köpenh.18, stud :res. 19-23 i Frankr.,\nItal., Span., Nordafr., Tyskl., 38-39 i\nFrankr., Holl., Belg. Utf. bl. a.: 111. t.\nDalarne s. sv. ideal av G. Näsström (37),\nt. In memoriam av K. R. Gierow (39),\nt. Promenader av G. Ekelöf (41), t. De\ntolv söndagarna av Ludv. Nordström\n(42), etsn :sviter t. verk av Anatole\nFrance, bokomsl. o. tidnrill., exlibris,\nutst. Paris, Lond., Köpenh., USA,\nVenedig; repr. i Nät :mus., Gtbgs\nkonst-rnus., Da. stat. saml.\nHedlund, Erik Harald, musikdirektör,\nÄngby, f. 1/4/07 i Torsåker, Gästrikl.,\nav bokf. Per Erik H. o. Hanna Löf.\nG. 35 m. Iris Ståhlberg. Barn: Kersti\nf. 36. Elev v. Musikkonserv, i Sthlm\n27-34, organ :ex. 29, kyrkosångareex. 30,\nrnus :lär :ex. 31, spec :stud. i piano,\nkontrapunkt o. orkesterdirig. Organ. o.\nkörled. i Immanuelskyrk. i Sthlm\n32-43, organ. o. klockare i Bromma förs. i\nSthlm sed. 43, förste förbidirigent f.\nSthlms körförb. inom Sv. Missionsförb.\nKomponerat kantater o. solosånger.\nHedlund, Hans,, jägmästare,\nÄppelviken, f. 16/9/01 i Gtbg. Utex. fr.\nSkogs-högsk. 26. Anst. i Uddeholms A-B\n26-27, assist, h. Skogsv :styr. i Sthlms 1.\n27-33, däreft. bitr. aff :led. i Sthlms l :s\nskogsäg rfören. Dessutom skogsförvalt.\nv. Lång-, Seming- o. Ärlinghundra 34\no. v. Sollentuna härads allm. 37.\n",
    "structured": {
        "1": {
            "full_name": "Wilhelm Ireneus Hedin",
            "location": "Sthlm",
            "occupation": "kamrer",
            "birth_details": {
                "date": "28/07/1900",
                "place": "Sveg",
                "parents": "köpm. C. W. Hedin o. Ada Andersson"
            },
            "education": [
                {
                    "degree": "Realskoleex.",
                    "year": "1917",
                    "institution": "Sundsvalls lärov."
                },
                {
                    "degree": "Sundsvalls Hdlsgymn.",
                    "year": "1917-1918",
                    "institution": "Sundsvalls Hdlsgymn."
                }
            ],
            "career": [
                {
                    "position": "t j :m.",
                    "years": {
                        "start_year": 1918,
                        "end_year": 1921
                    },
                    "organization": "A-B Köpmannabanken o. Södermanlands Ensk. Bank"
                },
                {
                    "position": "t j :m. h.",
                    "years": {
                        "start_year": 1922,
                        "end_year": 1926
                    },
                    "organization": "skilda kontor sanställn. i Sthlm"
                },
                {
                    "position": "t j :m.",
                    "years": {
                        "start_year": 1926,
                        "end_year": 1931
                    },
                    "organization": "Goodyear Gummi A-B"
                },
                {
                    "position": "huv :bokf.",
                    "years": {
                        "start_year": 1931,
                        "end_year": 1932
                    },
                    "organization": "Goodyear Gummi A-B"
                },
                {
                    "position": "kassör",
                    "years": {
                        "start_year": 1932,
                        "end_year": 1939
                    },
                    "organization": "Goodvear Gummi Fabr. A-B"
                }
            ],
            "family": {
                "spouse": "Linnea Lehnberg",
                "marriage_year": "25 m.",
                "children": [
                    {
                        "name": "Gunnar",
                        "birth_year": "1932"
                    },
                    {
                        "name": "Lars",
                        "birth_year": "1934"
                    }
                ]
            }
        },
        "2": {
            "full_name": "Bertil Adolf (Bull) Hedlund",
            "location": "Sthlm",
            "occupation": "konstnär",
            "birth_details": {
                "date": "09/04/1893",
                "place": "Falun",
                "parents": "fabr. Carl A. H. o. Henrica Norgren"
            },
            "education": [
                {
                    "degree": "Falu h. a. L",
                    "year": "NULL",
                    "institution": "Tekn. sk., Sthlm"
                },
                {
                    "degree": "Konsthögsk.",
                    "year": "1914-1915",
                    "institution": "Konsthögsk."
                }
            ],
            "career": [
                {
                    "position": "Utf.",
                    "years": {
                        "start_year": 1919,
                        "end_year": 1923
                    },
                    "organization": "stud :res. 19-23 i Frankr., Ital., Span., Nordafr., Tyskl."
                },
                {
                    "position": "Utf.",
                    "years": {
                        "start_year": 1938,
                        "end_year": 1939
                    },
                    "organization": "stud :res. 38-39 i Frankr., Holl., Belg."
                }
            ],
            "family": {
                "spouse": "Karin Arehn",
                "marriage_year": "36 m.",
                "children": []
            }
        },
        "3": {
            "full_name": "Erik Harald Hedlund",
            "location": "Ängby",
            "occupation": "musikdirektör",
            "birth_details": {
                "date": "01/04/1907",
                "place": "Torsåker, Gästrikl.",
                "parents": "bokf. Per Erik H. o. Hanna Löf"
            },
            "education": [
                {
                    "degree": "Musikkonserv.",
                    "year": "1927-1934",
                    "institution": "Elev v. Musikkonserv, i Sthlm"
                },
                {
                    "degree": "organ :ex.",
                    "year": "1929",
                    "institution": "organ :ex."
                },
                {
                    "degree": "kyrkosångareex.",
                    "year": "1930",
                    "institution": "kyrkosångareex."
                },
                {
                    "degree": "rnus :lär :ex.",
                    "year": "1931",
                    "institution": "rnus :lär :ex."
                }
            ],
            "career": [
                {
                    "position": "Organ. o. körled.",
                    "years": {
                        "start_year": 1932,
                        "end_year": 1943
                    },
                    "organization": "Immanuelskyrk. i Sthlm"
                },
                {
                    "position": "organ. o. klockare",
                    "years": {
                        "start_year": 1943,
                        "end_year": null
                    },
                    "organization": "Bromma förs. i Sthlm"
                }
            ],
            "family": {
                "spouse": "Iris Ståhlberg",
                "marriage_year": "35 m.",
                "children": [
                    {
                        "name": "Kersti",
                        "birth_year": "1936"
                    }
                ]
            }
        },
        "4": {
            "full_name": "Hans Hedlund",
            "location": "Äppelviken",
            "occupation": "jägmästare",
            "birth_details": {
                "date": "16/09/1901",
                "place": "Gtbg",
                "parents": "NULL"
            },
            "education": [
                {
                    "degree": "Utex.",
                    "year": "1926",
                    "institution": "Skogshögsk."
                }
            ],
            "career": [
                {
                    "position": "Anst.",
                    "years": {
                        "start_year": 1926,
                        "end_year": 1927
                    },
                    "organization": "i Uddeholms A-B"
                },
                {
                    "position": "assist",
                    "years": {
                        "start_year": 1927,
                        "end_year": 1933
                    },
                    "organization": "h. Skogsv :styr. i Sthlms 1."
                },
                {
                    "position": "bitr. aff :led.",
                    "years": {
                        "start_year": 1933,
                        "end_year": null
                    },
                    "organization": "Sthlms l :s skogsäg rfören."
                }
            ],
            "family": {
                "spouse": "NULL",
                "marriage_year": "NULL",
                "children": []
            }
        }
    }
}