{
    "original": "Hoff, Johan, komminister,\nmilitärpastor, Sthlm, f. 6/2/00 i Teckomatorp,\nMalmöh. 1. G. 25 m, Agnes Lindström.\nStud:ex. i Landskrona 18, teol. kand. o.\nprästvigd i Lund 23. Past:adj. i\nSilv-åkra o. Revinge 23, ungdomssekr. i Sv.\nkyrk. diakonistyr, o. resesekr. i Sv.\nKristl, seminariströr. 24-29, ständ. adj.\ni Katarina, Sthlm, 28-35, kyrkoadj.\n35-37 o. kommln.fr. 37 i Oscars förs. Bitr.\ni andl. vården v. Göta livg. 36-39 o. v.\nSvea livg. 36-39, mil:past. där fr. 39.\nLed. av komm. f. Sv. missionen i Kina\no. av dess arb :utsk., ombud f. Sv.\nkyrkans missionsstyr., v. ordf. i Nord.\nKristl. Buddistmissionens sv. komm.,\nordf. i dess arb :utsk. sed. 43, insp. f.\nGärdets förberedande elem :sk. sed. 41,\nkårch. i Oscars Scoutkår. Stud :resor t.\nTyskl., Tjeckoslov., Ungern,\nBalkanlän-derna, Turkiet, Italien, Danm., Norge,\nFinl. Skr.: Beredskap, Till männen i\nrikets försvar 39. OffUngFO.\nHoffsten, Carl David, bokförläggare,\nSthlm, f. i Sthlm 1/4/73 av bokf. Vikt.\nCarlson (Hoffsten) o. Mathilda\nDahlgren. G. 1. 07 m. Ida Maria Lindquist,\nd. 16, 2. 32 m. Clara Elisabeth\nLindquist. Stud :ex. Sthlm 91, v. Upps. univ.\n91-94, dir. f. A. V. Carlsons bokförl :a-b\nsed. 05, inneh, en del uppdr. av Sv.\nbokförl :fören. o. dyl. föret. RVO.\nvon Hofsten, Erik Gustaf Nils,\nbankdirektör, Sthlm, f. 2/11/74 i Gerum,\nSkarab. L, av godsäg. Nils von H. o.\ngrev :an Anna Sparre. G. 01 m. Kate\nBaines. Barn: Vera f. 03, Bengt f. 05,\nJohan f. 09, Maud f. 14. Stud :ex., hdls\n:-inst. Tj :man i olika befattn. i sv. bkr\no. utl. bankirhus 95-08, kamr.,\nsedermera kont:ch. i Sv:es allm. hyp :bk\n08-36, verkst, dir. 36-44. Aukt. rev.\n12-26, rev. h. stat. kristidskommiss. 17-21,\nstat. kolkontr. 20-21, sed. 21 v. öl. tillf,\nsekr. resp. led. av komm. o. sakk:utr.\nå jordbr :kred. omr., verkst, dlr. i Ensk.\njärnvis pens :kassa 16-38, sekr. i\nkreditkassan av år 1922 22-37, led. av stat.\nsekundärnd f. jordbr:kred. fr. 35, av\ndirekt, f. Tomteboda blindinst. fr. 36,\nav riddarhusdirekt. fr. 41, varit styr\n:-led. el. styr :ordf. i företag inom bank-,\nbankir-, hdls- o. industriomr., led. i\ntax:nd, kyrkoråd, kyrkofullm. m. m.\nKV02kl, RNO, GM.\nvon Hofsten,, Erland Adolf Gerhard,\nfil. lic., aktuarie, Enskede, f. 22/5/11 i\nUpps, G. 36 m. Karin Birgitta Ek.\nStud:ex. 29, fil. kand. 34, fil. lic. 41.\nArist. v. Sthlms stads statistiska kontor\nsed. 35, t j :led. 40-43, Sthlms städs\nkris-tidsnd 40-41, Stat. livsmed :komm. 41-42,\nSocialv :komm. 42-43. Sekr. h. Sthlms\nstads stadsplanend sed. 44. Skr.: Hur\nden svenska landsbygden avfolkas 39,\nDemografiska undersökn. ang. Sthlms\nfolkm rtillväxt 42, Praktisk statistik 42,\nVägvisare i sv. statistik 43, Utredn, ang.\nstadsplanen f. Gubbängen 44 samt tidn\n:-o. tidskr rart. Hobby: Böcker.\nvon Hofsten, Karin Birgitta,\nsekreterare, Enskede, f. i Upps. G. 36 m.\nErland v. H. (se denne). Gnmg. Sthlms\nKindergartenseminarium, diplom :d fr.\nSocialvetenskapl. inst. 36. Kurator v.\nCentralfängelset å Långholmen 36-37,\nassist, å Konsums Hemtjänst 38-39,\nby-råassist. å Fredrika-Bremer-Förbundet\n42-43, sekr. i ungdomsvårdskomm. 43.\nMedl. av styr. f. Samrealsk. i Enskede,\nFredrika-Bremer-Förbundet, Engelbr :s\nBarnavårds o. Husmodersskola. Skr.:\nDeltidsarbete 41, tills. m. Inga Bagger\nSjöbä.ck: Ett barn eller fyra? 41,\nFamiljen vill veta 42, Vad 900 kvinnor\ntycker 43.\nvon Hofsten, Sixten Eschelsson,\nmajor, Sthlm, f. 16/12/83 av överste Bengt\nErland Eberhard (Ebbe) von H. o.\nEllen A. Eschelsson. G. 15 m. Karin\nWilhelmina Santesson. Und:löjtn. v.\nFörsta livgren :reg. 04, löjtn. 07, löjtn,\nv. Intendenturkår. 15, kapt. därst. 16,\növerg :stat 28. Reg :intend. v. Väster-\nnorrl. reg. 16-18, intend, v. inst:st. 18-\n21,   exp:int.  v.  IV  arméfördeln.  21-23,\nreg :intend.  v.   Kronpr.  hus :reg.  23-28.\nUtarb.   Biografiska  uppg.   över\nInten-denturkårens pers. 1880-1930 29-30,\nredogör, v. Kavalleriinsp. o.\nRemonter:-väs. 31-44.    Sed. 29 tävl:led. o. senare\nordf. i Sthlms bågskjutn:klubb, sed. 32\nv. president i Internat,\nbågskjutnings-federationen,  organisatör  o. ledare av\nVM-tävl.  i bågskytte  i  Båstad 34,  sv.\nledare v. VM-tävl. i bågskytte i London\n38 o. i Oslo 39.   Redog. f. Sv. Röda\nKorsets hjälp t. Belgien o. Frankr. 41-44.\nMedl.   av   Sv.   Revisorsamf.,\nTimmermansorden,   Sv.   Biodlarefören.     RSO,\nRBLeopO,  FFrK4kl m sv,\nöstergötlfb-SM, KHS.\n",
    "structured": {
        "0": {
            "full_name": "Hoff, Johan",
            "location": "Sthlm",
            "occupation": "komminister, militärpastor",
            "birth_details": {
                "date": "06/02/1900",
                "place": "Teckomatorp, Malmöh"
            },
            "education": [
                {
                    "degree": "Stud:ex.",
                    "year": "1918",
                    "institution": "Landskrona"
                },
                {
                    "degree": "teol. kand.",
                    "year": "1923",
                    "institution": "Lund"
                }
            ],
            "career": [
                {
                    "position": "Past:adj.",
                    "years": {
                        "start_year": 1923,
                        "end_year": 1923
                    },
                    "organization": "Silv-åkra o. Revinge"
                },
                {
                    "position": "ungdomssekr.",
                    "years": {
                        "start_year": 1924,
                        "end_year": 1929
                    },
                    "organization": "Sv. kyrk. diakonistyr."
                },
                {
                    "position": "ständ. adj.",
                    "years": {
                        "start_year": 1928,
                        "end_year": 1935
                    },
                    "organization": "Katarina, Sthlm"
                },
                {
                    "position": "kyrkoadj.",
                    "years": {
                        "start_year": 1935,
                        "end_year": 1937
                    }
                },
                {
                    "position": "kommln.fr.",
                    "years": {
                        "start_year": 1937
                    },
                    "organization": "Oscars förs."
                }
            ],
            "family": {
                "spouse": "Agnes Lindström",
                "marriage_year": "1925",
                "children": null
            },
            "publications": [],
            "community_involvement": [],
            "board_memberships": [],
            "honorary_titles": [],
            "hobbies": [],
            "other": {
                "stud_resor": "Tyskl., Tjeckoslov., Ungern, Balkanlän-derna, Turkiet, Italien, Danm., Norge, Finl."
            }
        },
        "1": {
            "full_name": "Hoffsten, Carl David",
            "location": "Sthlm",
            "occupation": "bokförläggare",
            "birth_details": {
                "date": "01/04/1873",
                "place": "Sthlm"
            },
            "education": [
                {
                    "degree": "Stud :ex.",
                    "year": "1891",
                    "institution": "Sthlm"
                }
            ],
            "career": [
                {
                    "position": "dir. f. A. V. Carlsons bokförl :a-b",
                    "years": {
                        "start_year": 1905
                    }
                }
            ],
            "family": {
                "spouse": "Clara Elisabeth Lindquist",
                "marriage_year": "1932",
                "children": null
            },
            "publications": [],
            "community_involvement": [],
            "board_memberships": [],
            "honorary_titles": [],
            "hobbies": []
        },
        "2": {
            "full_name": "von Hofsten, Erik Gustaf Nils",
            "location": "Sthlm",
            "occupation": "bankdirektör",
            "birth_details": {
                "date": "02/11/1874",
                "place": "Gerum, Skarab. L"
            },
            "education": [
                {
                    "degree": "Stud :ex."
                }
            ],
            "career": [
                {
                    "position": "verkst, dir.",
                    "years": {
                        "start_year": 1936,
                        "end_year": 1944
                    }
                }
            ],
            "family": {
                "spouse": "Kate Baines",
                "marriage_year": "1901",
                "children": [
                    {
                        "name": "Vera",
                        "birth_year": "1903"
                    },
                    {
                        "name": "Bengt",
                        "birth_year": "1905"
                    },
                    {
                        "name": "Johan",
                        "birth_year": "1909"
                    },
                    {
                        "name": "Maud",
                        "birth_year": "1914"
                    }
                ]
            },
            "publications": [],
            "community_involvement": [],
            "board_memberships": [],
            "honorary_titles": [],
            "hobbies": []
        },
        "3": {
            "full_name": "von Hofsten, Erland Adolf Gerhard",
            "location": "Enskede",
            "occupation": "fil. lic., aktuarie",
            "birth_details": {
                "date": "22/05/1911",
                "place": "Upps"
            },
            "education": [
                {
                    "degree": "Stud:ex.",
                    "year": "1929"
                },
                {
                    "degree": "fil. kand.",
                    "year": "1934"
                },
                {
                    "degree": "fil. lic.",
                    "year": "1941"
                }
            ],
            "career": [
                {
                    "position": "Arist. v. Sthlms stads statistiska kontor",
                    "years": {
                        "start_year": 1935
                    }
                },
                {
                    "position": "Sekr. h. Sthlms stads stadsplanend",
                    "years": {
                        "start_year": 1944
                    }
                }
            ],
            "family": {
                "spouse": "Karin Birgitta Ek",
                "marriage_year": "1936",
                "children": null
            },
            "publications": [
                "Hur den svenska landsbygden avfolkas 39",
                "Demografiska undersökn. ang. Sthlms folkm rtillväxt 42",
                "Praktisk statistik 42",
                "Vägvisare i sv. statistik 43",
                "Utredn, ang. stadsplanen f. Gubbängen 44"
            ],
            "community_involvement": [],
            "board_memberships": [],
            "honorary_titles": [],
            "hobbies": [
                "Böcker"
            ]
        },
        "4": {
            "full_name": "von Hofsten, Karin Birgitta",
            "location": "Enskede",
            "occupation": "sekreterare",
            "birth_details": {
                "place": "Upps."
            },
            "family": {
                "spouse": "Erland v. H.",
                "marriage_year": "1936",
                "children": null
            },
            "publications": [
                "Deltidsarbete 41",
                "Ett barn eller fyra? 41",
                "Familjen vill veta 42",
                "Vad 900 kvinnor tycker 43"
            ],
            "community_involvement": [],
            "board_memberships": [],
            "honorary_titles": [],
            "hobbies": []
        },
        "5": {
            "full_name": "von Hofsten, Sixten Eschelsson",
            "location": "Sthlm",
            "occupation": "major",
            "birth_details": {
                "date": "16/12/1883"
            },
            "family": {
                "spouse": "Karin Wilhelmina Santesson",
                "marriage_year": "1915",
                "children": null
            },
            "publications": [],
            "community_involvement": [],
            "board_memberships": [],
            "honorary_titles": [
                "RSO",
                "RBLeopO",
                "FFrK4kl m sv",
                "östergötlfb-SM",
                "KHS"
            ],
            "hobbies": []
        }
    }
}