{
    "original": "GARDEFELDT, K TORE L, arkitekt\nSAR, Örebro, f i Örebro 28/1/20 av\nKonrad Gustafsson o Tora Blomqvist.\nSjälvstudier, anst stadsarkit:konit Örebro\n42, ch projekt :byrån där sed 53. - Medl\nSAR, Odd Fellow.\n\nGift 44 m Ann Stenström f 21, dtr t\nstenhugg Gunnar S o Ester Nyman.\n-Barn: Ola f 46, Mats f 50.\n\nCARELIUS, GÖSTA A W, tandläkare,\nÖrebro, f i Ulricehamn 22/2/10 av\nrådman Axel Jacobson o Ebba Sjöberg.\nStud:ex Skara 28, THS 32, prakt tandläk\nMariestad 32-47, Örebro sed 47.\nGift 47 m gymn:dir Brita Eliasson f 17,\ndtr t godsäg Anders E o h h. - Barn:\nBirgitta f 50.\n\nGARENBERG, B O (OLLE) S,\nråd-man, Eskilstuna, f i Sthlm 25/7/15 av\nstadsfiskal Gunnar Andersson o\nGunhild österberg.\n\nStud:ex Jönkpg 35, jur kand Sthlm 41,\ntingsnot Gästrikl ö doms 41-43, fiskal\nSvea hovr 44, tingssekr Jämtl n o\nLiv-gedingets doms :or 46-48, assess rådhusr\nVästerås 48, rådman Eskilstuna sed 51.\n\n-  Stadsfullm 54, ordf polisnd 58, v ordf\nbyggn:nd 52, suppl DK 59.\n\nGift 41 m Annika Koch f 15, dtr t\nträdg:m Josef K o Anna Kristiansson.\n-Barn: Björn f 44, Anders f 47, Mats\nf 51.\n\nGARFORS, ÅKE F,\ndistriktslantmä-tare, Uppsala, f i Vittinge, Västmanl l,\n17/1/08 av stat:insp Albert Gustafsson\no Naemi Jakobsson.\nStud:ex Upps 27, lantmät:ex 31, e\nlant-mät Västerb l 31, Södermani l 37,\ndistr:-lantmät Flens distr 45, ch lantmät\nspec:-enh Upps l 61, distr :lantmät Upps n:a\ndistr sed 62. - Huvudm Villåttinge\nhds sparbk 55-61, styr:led 58-61, led\nlantmät centr företagsnd sed 56, v ordf\nStadsfullm o skolstyr, ordf brandstyr m\nfi komm uppdr Flen 50-61. - Utm:\nRNO. - Hobbies: foto, bokbinderi.\nGift 35 m Gunvor Öhman f 12, dtr t\nlandsfisk Ragnar Ö o Märta Wallborg.\n-Barn: Ingrid f 47, Bengt f 51.\n\nGARFVÉ, EINAR, leg läkare,\nLudvika, f i Sollerö, Kopparb l, 13/9/08 av\nfolksk:lär Mats Larsson o Alma Garfvé.\nStud:ex Upps 27, med kand 31, med lic\nSthlm 37. - E läk med avd o röntgenavd\nSundsvalls las 37, underläk röntgenavd\n39, underläk Piteå las 40, 2:e o l:e\nunderläk, tf las :läk Ludvika las 41,\nunderläk Fagereds sanat 46, l :e underläk med\navd Kalmar las 46, 2:e stadsläk Ludvika\n47, ind :läk v Ludvikaverken 51. - Medl\nOdd Fellow.\n\nGift 37 m Karin Nordin f 09, dtr t dir\nCarl N o Ester Karlsson. - Barn:\nBirgitta f 39, Per-Einar f 43, Kerstin f 45.\n\n",
    "structured": {
        "0": {
            "full_name": "K Tore L Gardefeldt",
            "location": "Örebro",
            "occupation": "Arkitekt",
            "birth_details": {
                "date": "28/01/1920",
                "place": "Örebro",
                "parents": "Konrad Gustafsson o Tora Blomqvist"
            },
            "education": [],
            "career": [
                {
                    "position": "anst stadsarkit:konit Örebro",
                    "years": {
                        "start_year": 1942,
                        "end_year": 1953
                    },
                    "organization": "stadsarkit:konit Örebro"
                }
            ],
            "family": {
                "spouse": "Ann Stenström",
                "marriage_year": "1944",
                "children": [
                    {
                        "name": "Ola",
                        "birth_year": "1946"
                    },
                    {
                        "name": "Mats",
                        "birth_year": "1950"
                    }
                ]
            }
        },
        "1": {
            "full_name": "Gösta A W Carelius",
            "location": "Örebro",
            "occupation": "Tandläkare",
            "birth_details": {
                "date": "22/02/1910",
                "place": "Ulricehamn",
                "parents": "rådman Axel Jacobson o Ebba Sjöberg"
            },
            "education": [
                {
                    "degree": "Stud:ex",
                    "year": "1928",
                    "institution": "Skara"
                },
                {
                    "degree": "THS",
                    "year": "1932",
                    "institution": "Mariestad"
                }
            ],
            "career": [
                {
                    "position": "prakt tandläk Mariestad",
                    "years": {
                        "start_year": 1932,
                        "end_year": 1947
                    },
                    "organization": "Mariestad"
                },
                {
                    "position": "Tandläk Örebro",
                    "years": {
                        "start_year": 1947
                    }
                }
            ],
            "family": {
                "spouse": "Brita Eliasson",
                "marriage_year": "1947",
                "children": [
                    {
                        "name": "Birgitta",
                        "birth_year": "1950"
                    }
                ]
            }
        },
        "2": {
            "full_name": "B O (Olle) S Garenberg",
            "location": "Eskilstuna",
            "occupation": "Rådman",
            "birth_details": {
                "date": "25/07/1915",
                "place": "Sthlm",
                "parents": "stadsfiskal Gunnar Andersson o Gunhild Österberg"
            },
            "education": [
                {
                    "degree": "Stud:ex",
                    "year": "1935",
                    "institution": "Jönkpg"
                },
                {
                    "degree": "jur kand",
                    "year": "1941",
                    "institution": "Sthlm"
                }
            ],
            "career": [
                {
                    "position": "fiskal Svea hovr",
                    "years": {
                        "start_year": 1944,
                        "end_year": 1944
                    },
                    "organization": "Svea hovr"
                },
                {
                    "position": "tingssekr Jämtl n o Liv-gedingets doms :or",
                    "years": {
                        "start_year": 1946,
                        "end_year": 1948
                    }
                },
                {
                    "position": "assess rådhusr Västerås",
                    "years": {
                        "start_year": 1948
                    }
                },
                {
                    "position": "rådman Eskilstuna",
                    "years": {
                        "start_year": 1951
                    }
                }
            ],
            "family": {
                "spouse": "Annika Koch",
                "marriage_year": "1941",
                "children": [
                    {
                        "name": "Björn",
                        "birth_year": "1944"
                    },
                    {
                        "name": "Anders",
                        "birth_year": "1947"
                    },
                    {
                        "name": "Mats",
                        "birth_year": "1951"
                    }
                ]
            }
        },
        "3": {
            "full_name": "Åke F Garfors",
            "location": "Uppsala",
            "occupation": "Distriktslantmätare",
            "birth_details": {
                "date": "17/01/1908",
                "place": "Vittinge, Västmanl l",
                "parents": "stat:insp Albert Gustafsson o Naemi Jakobsson"
            },
            "education": [
                {
                    "degree": "Stud:ex",
                    "year": "1927",
                    "institution": "Upps"
                },
                {
                    "degree": "lantmät:ex",
                    "year": "1931",
                    "institution": "Upps"
                }
            ],
            "career": [
                {
                    "position": "distr:-lantmät Flens distr",
                    "years": {
                        "start_year": 1945
                    },
                    "organization": "Flens distr"
                },
                {
                    "position": "ch lantmät spec:-enh Upps l",
                    "years": {
                        "start_year": 1961
                    },
                    "organization": "Upps l"
                },
                {
                    "position": "distr :lantmät Upps n:a distr",
                    "years": {
                        "start_year": 1962
                    },
                    "organization": "Upps n:a distr"
                }
            ],
            "family": {
                "spouse": "Gunvor Öhman",
                "marriage_year": "1935",
                "children": [
                    {
                        "name": "Ingrid",
                        "birth_year": "1947"
                    },
                    {
                        "name": "Bengt",
                        "birth_year": "1951"
                    }
                ]
            },
            "hobbies": [
                "foto",
                "bokbinderi"
            ]
        },
        "4": {
            "full_name": "Einar Garfvé",
            "location": "Ludvika",
            "occupation": "Leg Läkare",
            "birth_details": {
                "date": "13/09/1908",
                "place": "Sollerö, Kopparb l",
                "parents": "folksk:lär Mats Larsson o Alma Garfvé"
            },
            "education": [
                {
                    "degree": "Stud:ex",
                    "year": "1927",
                    "institution": "Upps"
                },
                {
                    "degree": "med kand",
                    "year": "1931",
                    "institution": "Sthlm"
                },
                {
                    "degree": "med lic",
                    "year": "1937",
                    "institution": "Sthlm"
                }
            ],
            "career": [
                {
                    "position": "ind :läk v Ludvikaverken",
                    "years": {
                        "start_year": 1951
                    },
                    "organization": "Ludvikaverken"
                }
            ],
            "family": {
                "spouse": "Karin Nordin",
                "marriage_year": "1937",
                "children": [
                    {
                        "name": "Birgitta",
                        "birth_year": "1939"
                    },
                    {
                        "name": "Per-Einar",
                        "birth_year": "1943"
                    },
                    {
                        "name": "Kerstin",
                        "birth_year": "1945"
                    }
                ]
            }
        }
    }
}