{
    "original": "GÖRAN, A NIKLAS, skulptör,\nHällefors, f i Arvika 25/6/13 av konstsmed\nGöran G o Mia Persson.\nKonstsmedsutbildn 27-35, KKH 46-51.\n-Bl arb: keramikmosaik Smedjebackens\nrealsk 53, smidesgaller telehuset\nSundsvall 59, skulptur Norrstrandssk gård\nKarlstad 61. - Repr i Nät :mus, Värml\nmus o Norrkpgs mus. - Styr:led (repr f\nVärml) KRO 58.\n\nGift 1) 34 m Ragna Lundberg, dtr t\npostmast Rudolf L o Gerda Svärd, 2)\n43 m konstn:an Gerd Akre f 19, dtr t\ndisp Guthorm A o Hild Övergaard.\n-Barn: i l:a akt Britta f 37, i 2:a akt\nLena f 45, Malin f 46, Per f 50, Mia\nf 57, Annika f 61.\n\nGÖRANBER, E GUNNAR,\nprovinsialläkare, Mariefred, f i Grude, Älvsb l,\n3/11/00 av lantbr August G o Henny\nJosefsson.\n\nStud:ex Vänersborg 22, med kand 25 o\nmed lic Stlhlm 29, aman patol inst Karol\ninst o assist :läk med avd Stocksunds las\n29-30, underläk Spenshults sanat 30,\nmed avd Örnsköldsviks las 31,\nKarlshamns las 33, e läk Säters sjh 34,\nunderläk Simrishamns las 36, e läk pediatr\navd Norrtulls sjh 38, civil läk:stip 38-39,\ntf prov :läk Ramsele, Rätansbyn o\nMör-sils distr ol per 35-38, prov:läk o\nsjuk-stugeläk Sorsele 39-51^ Mariefred sed\n51. - Skr i bakteriol, med o kir. - Utm:\nRNO.\n\nGift 31 m Adéle Pettersson f 00, dtr t\ngodsäg Johannes P o Elin Lindholm.\n-Barn: Gun f 32, Lars Erik f 34, Annika\nf 37, Henny f 44.\n\nGÖRANSSON, ANTON G,\ndiplomin-genjör, fd rektor, Katrineholm, f i N\n\nNöbbelöv, Malmöh l, 18/11/95 av lantbr\nGöran Larsson o Kjerstin Jeppsson.\nStud:ex Lund 17, diploming :ex Tekn\nhögsk Dresden Tyskl 25, ing The Ohio\nBell Telephone Company Cleveland USA\n26-29, LME Sthlm o Warszawa Polen\n29, avd :ch LME Buenos Aires\nArgentina 31-32, lär elektroteknik\nKatrineholms tekn sk 33, överlär där 40, rektor\n59-60. - Medl FrimO. - Hobbies: jakt,\nskytte, filateli.\n\nGift 30 m Elly Gebauer f 02. - Barn:\nLennart f 37, Kjerstin f 40.\n\n",
    "structured": {
        "1": {
            "full_name": "Göran, A Niklas",
            "location": "Hällefors",
            "occupation": "Skulptör",
            "birth_details": {
                "date": "25/06/1913",
                "place": "Arvika",
                "parents": "konstsmed Göran G o Mia Persson"
            },
            "education": [
                {
                    "degree": "konstsmedsutbildn",
                    "year": "1927-1935",
                    "institution": "KKH"
                }
            ],
            "career": [
                {
                    "position": "keramikmosaik Smedjebackens realsk",
                    "years": {
                        "start_year": 1953,
                        "end_year": 1953
                    },
                    "organization": "Smedjebackens realsk"
                },
                {
                    "position": "smidesgaller telehuset Sundsvall",
                    "years": {
                        "start_year": 1959,
                        "end_year": 1959
                    },
                    "organization": "telehuset Sundsvall"
                },
                {
                    "position": "skulptur Norrstrandssk gård Karlstad",
                    "years": {
                        "start_year": 1961,
                        "end_year": 1961
                    },
                    "organization": "Norrstrandssk gård Karlstad"
                }
            ],
            "family": {
                "spouse": "Ragna Lundberg",
                "marriage_year": "1934",
                "children": [
                    {
                        "name": "Britta",
                        "birth_year": "1937"
                    },
                    {
                        "name": "Lena",
                        "birth_year": "1945"
                    },
                    {
                        "name": "Malin",
                        "birth_year": "1946"
                    },
                    {
                        "name": "Per",
                        "birth_year": "1950"
                    },
                    {
                        "name": "Mia",
                        "birth_year": "1957"
                    },
                    {
                        "name": "Annika",
                        "birth_year": "1961"
                    }
                ]
            }
        },
        "2": {
            "full_name": "Göranber, E Gunnar",
            "location": "Mariefred",
            "occupation": "Provinsialläkare",
            "birth_details": {
                "date": "03/11/1900",
                "place": "Grude, Älvsborgs län",
                "parents": "lantbr August G o Henny Josefsson"
            },
            "education": [
                {
                    "degree": "Stud:ex",
                    "year": "1922",
                    "institution": "Vänersborg"
                },
                {
                    "degree": "med kand",
                    "year": "1925",
                    "institution": "Stlhlm"
                },
                {
                    "degree": "med lic",
                    "year": "1929",
                    "institution": "Stlhlm"
                }
            ],
            "career": [
                {
                    "position": "aman patol inst",
                    "years": {
                        "start_year": 1929,
                        "end_year": 1930
                    },
                    "organization": "Karol inst"
                },
                {
                    "position": "underläk Spenshults sanat",
                    "years": {
                        "start_year": 1930,
                        "end_year": 1930
                    },
                    "organization": "Spenshults sanat"
                },
                {
                    "position": "med avd Örnsköldsviks las",
                    "years": {
                        "start_year": 1931,
                        "end_year": 1931
                    },
                    "organization": "Örnsköldsviks las"
                },
                {
                    "position": "Karlshamns las",
                    "years": {
                        "start_year": 1933,
                        "end_year": 1933
                    },
                    "organization": "Karlshamns las"
                },
                {
                    "position": "e läk Säters sjh",
                    "years": {
                        "start_year": 1934,
                        "end_year": 1934
                    },
                    "organization": "Säters sjh"
                },
                {
                    "position": "underläk Simrishamns las",
                    "years": {
                        "start_year": 1936,
                        "end_year": 1936
                    },
                    "organization": "Simrishamns las"
                },
                {
                    "position": "e läk pediatr avd Norrtulls sjh",
                    "years": {
                        "start_year": 1938,
                        "end_year": 1938
                    },
                    "organization": "Norrtulls sjh"
                },
                {
                    "position": "prov:läk o sjuk-stugeläk",
                    "years": {
                        "start_year": 1939,
                        "end_year": 1951
                    },
                    "organization": "Sorsele"
                },
                {
                    "position": "provinsialläkare",
                    "years": {
                        "start_year": 1951,
                        "end_year": 1951
                    },
                    "organization": "Mariefred"
                }
            ],
            "family": {
                "spouse": "Adéle Pettersson",
                "marriage_year": "1931",
                "children": [
                    {
                        "name": "Gun",
                        "birth_year": "1932"
                    },
                    {
                        "name": "Lars Erik",
                        "birth_year": "1934"
                    },
                    {
                        "name": "Annika",
                        "birth_year": "1937"
                    },
                    {
                        "name": "Henny",
                        "birth_year": "1944"
                    }
                ]
            }
        },
        "3": {
            "full_name": "Göransson, Anton G",
            "location": "Katrineholm",
            "occupation": "Diplomingenjör, fd rektor",
            "birth_details": {
                "date": "18/11/1895",
                "place": "Nöbbelöv, Malmöhus län",
                "parents": "lantbr Göran Larsson o Kjerstin Jeppsson"
            },
            "education": [
                {
                    "degree": "Stud:ex",
                    "year": "1917",
                    "institution": "Lund"
                },
                {
                    "degree": "diploming :ex",
                    "year": "1925",
                    "institution": "Tekn högsk Dresden"
                }
            ],
            "career": [
                {
                    "position": "ing The Ohio Bell Telephone Company",
                    "years": {
                        "start_year": 1926,
                        "end_year": 1929
                    },
                    "organization": "Cleveland USA"
                },
                {
                    "position": "LME Sthlm o Warszawa Polen",
                    "years": {
                        "start_year": 1929,
                        "end_year": 1931
                    },
                    "organization": "Warszawa Polen"
                },
                {
                    "position": "avd :ch LME",
                    "years": {
                        "start_year": 1931,
                        "end_year": 1932
                    },
                    "organization": "Buenos Aires Argentina"
                },
                {
                    "position": "lär elektroteknik",
                    "years": {
                        "start_year": 1933,
                        "end_year": 1933
                    },
                    "organization": "Katrineholms tekn sk"
                },
                {
                    "position": "överlär",
                    "years": {
                        "start_year": 1940,
                        "end_year": 1940
                    },
                    "organization": "Katrineholms tekn sk"
                },
                {
                    "position": "rektor",
                    "years": {
                        "start_year": 1959,
                        "end_year": 1960
                    },
                    "organization": "Katrineholm"
                }
            ],
            "family": {
                "spouse": "Elly Gebauer",
                "marriage_year": "1930",
                "children": [
                    {
                        "name": "Lennart",
                        "birth_year": "1937"
                    },
                    {
                        "name": "Kjerstin",
                        "birth_year": "1940"
                    }
                ]
            },
            "hobbies": [
                "jakt",
                "skytte",
                "filateli"
            ]
        }
    }
}