{
    "original": "GROUNES,  MIKAEL,  bergsingenjör,\n\nNyköping, f i Warszawa 5/9/33 av dir\n\nJacob G o Dorotea Tylbor.\n\nStud:ex Sthlm 51, KTH 56, M Se MIT,\n\nUSA 64, forskn:ing Jernkont 56, 58, ab\n\nAtomenergi Sthlm 58, Studsvik sed 59. -\n\nSkr: upps i metallurg ämn.  - Hobby:\n\nbildarkiv   över   krigsfartyg.\n\nGift 55 m Birgitta Hellkvist f 31, dtr t\n\ntjm Olof H o Rind Swenson. - Barn:\n\nJan f 56, Lena f 59.\n\nGRUDER,   ASTRID   M,   leg   läkare,\n\nHuddinge, f i Upps 20/6/23 av köpm\nJohn Ferm o Sigrid Säflund.\nStud:ex Upps 42, med kand 45, med lic\n54. - Vik underläk kir avd Lidkpgs las\no Kullbergska las Katrineholm 52-54,\nmed avd Nykpgs las 54, 2 :e underläk\nkir avd Kullbergska las Katrineholm 55,\nl:e underläk där 58, vik 2:e underläk\ngynekol avd Eskilstuna las 59, 2:e\nunderläk 59, l:e underläk där 62, underläk\nSödra BB sed 63.\nBarn: Sule Tari f 46.\n\nGRUMMAS, ERIK E, kamrer, Stora\nSkedvi, f i Mora, Kopparb l, 8/10/18 av\nhemmansäg Olof G o Ester Lindqvist.\nRealex 35, anst Gbgs bk 40, kont :f örest\nbkns kont Gustafs 59, kont :ch Berga\nFärgeri &amp; Ullspinneri ab St Skedvi sed\n61.\n\nGift 45 m May Granholm f 21, dtr t\nmaskinist Gustaf G o Anna Helleberg.\n- Barn: Claes-Erik f 47, Agneta f 50,\nIngrid f 55.\n\n",
    "structured": {
        "1": {
            "full_name": "Mikael Grounes",
            "location": "Nyköping",
            "occupation": "bergsingenjör",
            "birth_details": {
                "date": "05/09/1933",
                "place": "Warszawa",
                "parents": "dir Jacob G o Dorotea Tylbor"
            },
            "education": [
                {
                    "degree": "Stud:ex",
                    "year": "1951",
                    "institution": "Sthlm"
                },
                {
                    "degree": "KTH",
                    "year": "1956",
                    "institution": "Kungliga Tekniska högskolan"
                },
                {
                    "degree": "M Se",
                    "year": "1964",
                    "institution": "MIT, USA"
                }
            ],
            "career": [
                {
                    "position": "forskn:ing",
                    "years": {
                        "start_year": 1956,
                        "end_year": 1958
                    },
                    "organization": "Jernkont"
                },
                {
                    "position": "forskn:ing",
                    "years": {
                        "start_year": 1958,
                        "end_year": 1964
                    },
                    "organization": "ab Atomenergi Sthlm"
                },
                {
                    "position": "forskn:ing",
                    "years": {
                        "start_year": 1959,
                        "end_year": null
                    },
                    "organization": "Studsvik"
                }
            ],
            "family": {
                "spouse": "Birgitta Hellkvist",
                "marriage_year": "1955",
                "children": [
                    {
                        "name": "Jan",
                        "birth_year": "1956"
                    },
                    {
                        "name": "Lena",
                        "birth_year": "1959"
                    }
                ]
            }
        },
        "2": {
            "full_name": "Astrid M Gruder",
            "location": "Huddinge",
            "occupation": "leg läkare",
            "birth_details": {
                "date": "20/06/1923",
                "place": "Upps"
            },
            "education": [
                {
                    "degree": "Stud:ex",
                    "year": "1942",
                    "institution": "Upps"
                },
                {
                    "degree": "med kand",
                    "year": "1945",
                    "institution": "Upps"
                },
                {
                    "degree": "med lic",
                    "year": "1954",
                    "institution": "Upps"
                }
            ],
            "career": [
                {
                    "position": "Vik underläk",
                    "years": {
                        "start_year": 1952,
                        "end_year": 1954
                    },
                    "organization": "kir avd Lidkpgs las"
                },
                {
                    "position": "med avd",
                    "years": {
                        "start_year": 1954,
                        "end_year": null
                    },
                    "organization": "Nykpgs las"
                },
                {
                    "position": "2 :e underläk",
                    "years": {
                        "start_year": 1955,
                        "end_year": 1958
                    },
                    "organization": "kir avd Kullbergska las Katrineholm"
                },
                {
                    "position": "l:e underläk",
                    "years": {
                        "start_year": 1958,
                        "end_year": 1962
                    },
                    "organization": "där"
                },
                {
                    "position": "underläk",
                    "years": {
                        "start_year": 1963,
                        "end_year": null
                    },
                    "organization": "Södra BB"
                }
            ],
            "family": {
                "spouse": null,
                "marriage_year": null,
                "children": [
                    {
                        "name": "Sule Tari",
                        "birth_year": "1946"
                    }
                ]
            }
        },
        "3": {
            "full_name": "Erik E Grummas",
            "location": "Stora Skedvi",
            "occupation": "kamrer",
            "birth_details": {
                "date": null,
                "place": "Mora, Kopparb l"
            },
            "education": [
                {
                    "degree": "Realex",
                    "year": "1935",
                    "institution": null
                }
            ],
            "career": [
                {
                    "position": "anst",
                    "years": {
                        "start_year": 1940,
                        "end_year": null
                    },
                    "organization": "Gbgs bk"
                },
                {
                    "position": "kont :f örest",
                    "years": {
                        "start_year": 1959,
                        "end_year": null
                    },
                    "organization": "bkns kont Gustafs"
                },
                {
                    "position": "kont :ch",
                    "years": {
                        "start_year": 1961,
                        "end_year": null
                    },
                    "organization": "Berga Färgeri & Ullspinneri ab St Skedvi"
                }
            ],
            "family": {
                "spouse": "May Granholm",
                "marriage_year": "1945",
                "children": [
                    {
                        "name": "Claes-Erik",
                        "birth_year": "1947"
                    },
                    {
                        "name": "Agneta",
                        "birth_year": "1950"
                    },
                    {
                        "name": "Ingrid",
                        "birth_year": "1955"
                    }
                ]
            }
        }
    }
}