{
    "original": "Sandbäck, Bengt Theodor,\nläroverksadjunkt, Jönköping, f. 1/2/05 i Kaltmar\nav med. lic. Karl Danielssoin o. h. h.,\nf. Sandbäck. G. 33 m. Maj Bolling.\nBarn: Lars f. 34, Kristina 39. — Stud\n:-ex. i Kalto. 24, fil. mag. i Upps. 30,\nprovår v. folksk :sem. i StMtm 36. E. o.\nämneslär. i Östhammar 3il-3l2, v. Upps.\nh. folksk. 32, vik. ilektor v. Gbgs\nfolksk :sem. 37, adj. i modiersm., hist. m.\nsamlh :lära o. geogr. v. Jönköp. li. a. 1.\nsed. 37.\n\naf Sandeberg, Ernst Nils David,\növerste, Kullebo, Gössäter, f. 12/5/71\ni N:a Lundby, Skarab. 1., av kapt.\nJohn D. af S. o. Hilma Norman. G.\n01 m. Anna Engdahl. — Stud:ex. i\nSkara 89, off:ex. 91, KHS 94-96, mil.\nstud. i Tyskl. 10 o. 18. Und:löjtn. v.\nVästg. reg. 91, komp :off. o. adjut. v.\nkrigssk. 99-05, förste adjut. v. HL\nar-méförd. stab 06-09, chef f. krigssk.\nres:-off:kurs 13 o. 14, major v. södra sk.\ninf:reg. 15, chef f. inf:sk. å\nKarlsborg 17-19, öv:löjtn. v. Kronob. reg.\n18, tf. chef f. Gotl. inf:reg. 19-22, f.\nVästg. reg. 22-27, f. 6:e inf :brig.\n23-27, sek:chef f. Livreg. gren. 28-31,\növerste i res. Ordf. i komm:nd m. fl.\nkomm. uppdr. i Svennevad 32-37, åter i\nmil:tj. s. fobef. 39-42. KSOlkl,\nRBay-Mf04kl m krona, RNS :t001kl,\nLand-stSM.\n\naf Sandeberg, John David Fredrik,\njur. kand., kammarherre, kapten,\nMo-holm, f. 6/1/84 i Vänersborg av kapt.\nFredrik af S. o. Jane Dickson. G. 24\nm. Tyra Bratt. Barn: Fredrik-Adolf f.\n25, Jane 26. — Stud:ex. 03, res:off:ex.\n05, jur. kand. i Upps. 22. E.o. not. i\nSvea hovr., prakt, jurist i Sthlm,\nTrollhättan, Karlshamn o. Borås t. 32. Kapt.\ni Västg. reg. res. 21, kammarherre v.\nH. M. Konungens hov 32. Ägde o.\nbeb. Lövås i Älvsb. 1. 27-37, äg. o.\nbeb. Moholms sät. i Skarab. 1. fr. 36.\nLed. av styr. f. Västergötl.\nfornm:-fören. o. dess arb:utsk., Västergötl.\nturist- o. traf :för’b., Västg. reg.\nkamr:-fÖren., fl. bol:styr. Hed:led. av Västg.\nnat. i Upps. RVO, RJohO.\n\naf Sandeberg, William David, major,\nGöteborg, f. 25/11/74 å Sjötorp,\nSkarab. 1., av kapt. Fredrik af S. o. Jane\nDickson. G. 12 m. Margareta (Greta)\nKilman. Barn: Edward f. 13, kapt. v.\n\nflottan,’ Sthlm, Gösta 14, förste aman.\ni försv:dep., Sthlm, Helene 16, g. m.\nAnders Lagström, Borås. — Mog:ex.\ni Vänersb. 92, AIHS 96-98, ridsk.\n01-02, skjutsk. 05, skidlöpn ikurs 13 m. m.\nUndilöjtn. v. GÖta art:reg. 95, löjtn.\ni reg. 00, v. reg. 03, kapt. 07, major i\narmén 24. Vapenoff. 07-08,\nregikvar-termäst. 08-11, kasernoff. 20-24. RSO.\n\n",
    "structured": {
        "0": {
            "full_name": "Sandbäck, Bengt Theodor",
            "location": "Jönköping",
            "occupation": "läroverksadjunkt",
            "birth_details": {
                "date": "01/02/1905",
                "place": "Kaltmar"
            },
            "education": [
                {
                    "degree": "Stud",
                    "year": "1924",
                    "institution": "i Kalto"
                },
                {
                    "degree": "fil. mag.",
                    "year": "1930",
                    "institution": "i Upps"
                }
            ],
            "career": [
                {
                    "position": "E. o. ämneslär.",
                    "years": {
                        "start_year": 1930,
                        "end_year": 1932
                    },
                    "organization": "i Östhammar"
                },
                {
                    "position": "v. Upps. h. folksk.",
                    "years": {
                        "start_year": 1932,
                        "end_year": null
                    },
                    "organization": null
                },
                {
                    "position": "vik. ilektor v. Gbgs",
                    "years": {
                        "start_year": 1937,
                        "end_year": null
                    },
                    "organization": "folksk :sem"
                },
                {
                    "position": "adj. i modiersm., hist. m. samlh :lära o. geogr.",
                    "years": {
                        "start_year": 1937,
                        "end_year": null
                    },
                    "organization": "v. Jönköp. li. a."
                }
            ],
            "family": {
                "spouse": "Maj Bolling",
                "marriage_year": "1933",
                "children": [
                    {
                        "name": "Lars",
                        "birth_year": "1934"
                    },
                    {
                        "name": "Kristina",
                        "birth_year": "1939"
                    }
                ]
            }
        },
        "1": {
            "full_name": "af Sandeberg, Ernst Nils David",
            "location": "Kullebo, Gössäter",
            "occupation": "överste",
            "birth_details": {
                "date": "12/05/1871",
                "place": "N:a Lundby, Skarab. l."
            },
            "education": [
                {
                    "degree": "Stud",
                    "year": "1889",
                    "institution": "i Skara"
                },
                {
                    "degree": "off:ex.",
                    "year": "1891",
                    "institution": null
                },
                {
                    "degree": "KHS",
                    "year": "1894-1896",
                    "institution": null
                },
                {
                    "degree": "mil. stud.",
                    "year": "1910",
                    "institution": "i Tyskl."
                },
                {
                    "degree": "mil. stud.",
                    "year": "1918",
                    "institution": "i Tyskl."
                }
            ],
            "career": [
                {
                    "position": "Und:löjtn. v. Västg. reg.",
                    "years": {
                        "start_year": 1891,
                        "end_year": null
                    },
                    "organization": null
                },
                {
                    "position": "chef f. krigssk. res:-off:kurs",
                    "years": {
                        "start_year": 1913,
                        "end_year": 1914
                    },
                    "organization": null
                },
                {
                    "position": "chef f. inf:sk. å Karlsborg",
                    "years": {
                        "start_year": 1917,
                        "end_year": 1919
                    },
                    "organization": null
                },
                {
                    "position": "öv:löjtn. v. Kronob. reg.",
                    "years": {
                        "start_year": 1918,
                        "end_year": null
                    },
                    "organization": null
                },
                {
                    "position": "överste i res.",
                    "years": {
                        "start_year": null,
                        "end_year": null
                    },
                    "organization": null
                }
            ],
            "family": {
                "spouse": "Anna Engdahl",
                "marriage_year": "1901",
                "children": null
            }
        },
        "2": {
            "full_name": "af Sandeberg, John David Fredrik",
            "location": "Moholm",
            "occupation": "jur. kand., kammarherre, kapten",
            "birth_details": {
                "date": "06/01/1884",
                "place": "Vänersborg"
            },
            "education": [
                {
                    "degree": "Stud:ex",
                    "year": "1903",
                    "institution": null
                },
                {
                    "degree": "res:off:ex.",
                    "year": "1905",
                    "institution": null
                },
                {
                    "degree": "jur. kand.",
                    "year": "1922",
                    "institution": "i Upps"
                }
            ],
            "career": [
                {
                    "position": "E.o. not. i Svea hovr.",
                    "years": {
                        "start_year": null,
                        "end_year": null
                    },
                    "organization": null
                },
                {
                    "position": "prakt, jurist",
                    "years": {
                        "start_year": null,
                        "end_year": null
                    },
                    "organization": "i Sthlm, Trollhättan, Karlshamn o. Borås"
                },
                {
                    "position": "kapt. i Västg. reg.",
                    "years": {
                        "start_year": null,
                        "end_year": 1921
                    },
                    "organization": "res"
                },
                {
                    "position": "kammarherre v. H. M. Konungens hov",
                    "years": {
                        "start_year": 1932,
                        "end_year": null
                    },
                    "organization": null
                }
            ],
            "family": {
                "spouse": "Tyra Bratt",
                "marriage_year": "1924",
                "children": [
                    {
                        "name": "Fredrik-Adolf",
                        "birth_year": "1925"
                    },
                    {
                        "name": "Jane",
                        "birth_year": "1926"
                    }
                ]
            }
        },
        "3": {
            "full_name": "af Sandeberg, William David",
            "location": "Göteborg",
            "occupation": "major",
            "birth_details": {
                "date": "25/11/1874",
                "place": "Sjötorp, Skarab. l."
            },
            "education": [
                {
                    "degree": "Mog:ex.",
                    "year": "1892",
                    "institution": "i Vänersb."
                },
                {
                    "degree": "AIHS",
                    "year": "1896-1898",
                    "institution": null
                },
                {
                    "degree": "ridsk.",
                    "year": "1901-1902",
                    "institution": null
                },
                {
                    "degree": "skjutsk.",
                    "year": "1905",
                    "institution": null
                },
                {
                    "degree": "skidlöpn ikurs",
                    "year": "1913",
                    "institution": null
                }
            ],
            "career": [
                {
                    "position": "Undilöjtn. v. GÖta art:reg.",
                    "years": {
                        "start_year": 1895,
                        "end_year": null
                    },
                    "organization": null
                },
                {
                    "position": "kapt. i Västg. reg.",
                    "years": {
                        "start_year": null,
                        "end_year": 1921
                    },
                    "organization": "res"
                },
                {
                    "position": "major i armén",
                    "years": {
                        "start_year": 1924,
                        "end_year": null
                    },
                    "organization": null
                }
            ],
            "family": {
                "spouse": "Margareta (Greta) Kilman",
                "marriage_year": "1912",
                "children": [
                    {
                        "name": "Edward",
                        "birth_year": "1913"
                    },
                    {
                        "name": "Gösta",
                        "birth_year": "1914"
                    },
                    {
                        "name": "Helene",
                        "birth_year": "1916"
                    }
                ]
            }
        }
    }
}