{
    "original": "HELLSTEN, BJÖRN A, leg läkare,\nVällingby, f i Sthlm 9/1/17 av ing\nArthur H o Johanne Petersen.\nStudrex 34, med kand 38, med lic 45,\nassrläk o tf underläk röntgenavd\nSab-bat’sb sjh 46, med avd Södersjh 46, tf\nunderläk venereol garru:avd Karol sjh\n47, med garniavd 47 o 50-54, l :e\nunderläk där 54-57, tf överläk 57, underläk\n\nBlackebergs sjh sed 61. - Batiläk flk\n51-57, i res 57. - Grund o inneh ing:firm\nVolux (num ab Volux) Sthlm sed 36.\nGift 43 m Rut Arnberg f 16, dtr t\ncivil&lt;-ing Wilhelm A o Elsa Lindström.\n-Barn: Hans f 46, Eva f 52.\n\nHELLSTEN, CARL GÖRAN,\ncivilingenjör, Bandhagen, f i Falun 1/7/23\nav rektor Carl Gustaf H o Ruth\nLindeberg.\n\nStud:ex Bromma 42, KTH 48,\nbrokontrollant vägförvaltn Västernorrl l 48,\nkonstr gatukontoret Malmö 49,\nutredn:-ass h civiling Nils Tengvik Malmö 50,\ntekn dr M Jacobsson Lidingö 51, l:e\nbyråing bostadsstyr Sthlm 54, bitr dir\nab Elementhus Mockfjärd 58,\nforskn:-led stat inst f byggn:forskn sed 61.\n-Exp 56 års bostadspolit utredn, ordf\nMockfjärds byggn:nd 59, timlär Sthlms\nh tekn lärov 54-55, fackred Tekn tidskr\n55-58.\n\nGift 52 m Gerd Forsberg f 29, dtr t\nvaktmäst Oscar F o Valborg Asp.\n-Barn: Per Anders f 52, Ann-Mari f 56,\nMats Göran f 59.\n\nHELLSTEN, K MARTIN E,\nlaboratoriechef, Rönninge, f i Hfors 8/5/24\nav dir Karl H o fil mag Märta Lindhe.\nStud:ex Gbg 41, CTH 45, tekn lic 62,\nf orskn: ass f orskn: lab LKB Äppelviken\n46, lab:ch ab Henkel-Helios sed 51.\n-Medl Sv kemiing riksförb, fullnv.led sed\n57. - Hobby: segling.\nGift 58 m Marianne Geisler f 34, dtr\nt folkskollär Paul G o Elfriede Camp.\n- Barn: Magnus f 59, Linda f 62.\n\n",
    "structured": {
        "0": {
            "full_name": "BJÖRN A HELLSTEN",
            "location": "Vällingby",
            "occupation": "leg läkare",
            "birth_details": {
                "date": "09/01/1917",
                "place": "Stockholm",
                "parents": "ing Arthur H o Johanne Petersen"
            },
            "education": [
                {
                    "degree": "Studrex",
                    "year": "1934",
                    "institution": null
                },
                {
                    "degree": "med kand",
                    "year": "1938",
                    "institution": null
                },
                {
                    "degree": "med lic",
                    "year": "1945",
                    "institution": null
                }
            ],
            "career": [
                {
                    "position": "assrläk o tf underläk röntgenavd",
                    "years": {
                        "start_year": 1946,
                        "end_year": 1946
                    },
                    "organization": "Sab-bat'sb sjh"
                },
                {
                    "position": "med avd",
                    "years": {
                        "start_year": 1946,
                        "end_year": 1946
                    },
                    "organization": "Södersjh"
                },
                {
                    "position": "tf underläk venereol garru:avd",
                    "years": {
                        "start_year": 1947,
                        "end_year": 1947
                    },
                    "organization": "Karol sjh"
                },
                {
                    "position": "med garniavd",
                    "years": {
                        "start_year": 1947,
                        "end_year": 1947
                    },
                    "organization": null
                },
                {
                    "position": "l :e underläk där",
                    "years": {
                        "start_year": 1954,
                        "end_year": 1957
                    },
                    "organization": null
                },
                {
                    "position": "tf överläk",
                    "years": {
                        "start_year": 1957,
                        "end_year": 1957
                    },
                    "organization": null
                }
            ],
            "family": {
                "spouse": "Rut Arnberg",
                "marriage_year": "1943",
                "children": [
                    {
                        "name": "Hans",
                        "birth_year": "1946"
                    },
                    {
                        "name": "Eva",
                        "birth_year": "1952"
                    }
                ]
            }
        },
        "1": {
            "full_name": "CARL GÖRAN HELLSTEN",
            "location": "Bandhagen",
            "occupation": "civilingenjör",
            "birth_details": {
                "date": "01/07/1923",
                "place": "Falun",
                "parents": "rektor Carl Gustaf H o Ruth Lindeberg"
            },
            "education": [
                {
                    "degree": null,
                    "year": null,
                    "institution": "Stud:ex Bromma 42"
                },
                {
                    "degree": null,
                    "year": null,
                    "institution": "KTH 48"
                }
            ],
            "career": [
                {
                    "position": "brokontrollant vägförvaltn Västernorrl l",
                    "years": {
                        "start_year": 1948,
                        "end_year": 1953
                    },
                    "organization": null
                },
                {
                    "position": "konstr gatukontoret Malmö",
                    "years": {
                        "start_year": 1954,
                        "end_year": 1954
                    },
                    "organization": null
                },
                {
                    "position": "utredn:-ass h civiling Nils Tengvik Malmö",
                    "years": {
                        "start_year": 1950,
                        "end_year": 1952
                    },
                    "organization": null
                },
                {
                    "position": "tekn dr M Jacobsson Lidingö",
                    "years": {
                        "start_year": 1951,
                        "end_year": 1951
                    },
                    "organization": null
                },
                {
                    "position": "l:e byråing bostadsstyr Sthlm",
                    "years": {
                        "start_year": 1954,
                        "end_year": 1957
                    },
                    "organization": null
                },
                {
                    "position": "bitr dir ab Elementhus Mockfjärd",
                    "years": {
                        "start_year": 1958,
                        "end_year": null
                    },
                    "organization": null
                },
                {
                    "position": "forskn:-led stat inst f byggn:forskn",
                    "years": {
                        "start_year": 1961,
                        "end_year": null
                    },
                    "organization": null
                }
            ],
            "family": {
                "spouse": "Gerd Forsberg",
                "marriage_year": "1952",
                "children": [
                    {
                        "name": "Per Anders",
                        "birth_year": "1952"
                    },
                    {
                        "name": "Ann-Mari",
                        "birth_year": "1956"
                    },
                    {
                        "name": "Mats Göran",
                        "birth_year": "1959"
                    }
                ]
            }
        },
        "2": {
            "full_name": "K MARTIN E HELLSTEN",
            "location": "Rönninge",
            "occupation": "laboratoriechef",
            "birth_details": {
                "date": "08/05/1924",
                "place": "Hfors",
                "parents": "dir Karl H o fil mag Märta Lindhe"
            },
            "education": [
                {
                    "degree": null,
                    "year": null,
                    "institution": "Stud:ex Gbg 41"
                },
                {
                    "degree": null,
                    "year": null,
                    "institution": "CTH 45"
                },
                {
                    "degree": "tekn lic",
                    "year": "1962",
                    "institution": null
                }
            ],
            "career": [
                {
                    "position": "f orskn: ass f orskn: lab LKB Äppelviken",
                    "years": {
                        "start_year": 1946,
                        "end_year": 1946
                    },
                    "organization": null
                },
                {
                    "position": "lab:ch ab Henkel-Helios",
                    "years": {
                        "start_year": 1951,
                        "end_year": null
                    },
                    "organization": null
                }
            ],
            "family": {
                "spouse": "Marianne Geisler",
                "marriage_year": "1958",
                "children": [
                    {
                        "name": "Magnus",
                        "birth_year": "1959"
                    },
                    {
                        "name": "Linda",
                        "birth_year": "1962"
                    }
                ]
            },
            "hobbies": [
                "segling"
            ]
        }
    }
}