{
    "original": "HALL,     L     GÖSTA,     civilingenjör,\nDanderyd, f i  Mjölby 22/7/28  av\naffärschef A H o Eleonora Johansson.\nStud:ex Sthlm 47, KTH 55, l:e\nforskn:-ing FOA sed 55.\n\nGift m Marianne Bendel. - Barn:\nYvonne f 57, Thomas f 59, Annika f 61.\n\nHALL, KARL, redaktör, Sthlm, f i\nÖstersund 5/5/21 av löjtn Ernst H o\nHulda Andersson.\n\nStud:ex Sthlm 40, medarb ST 43,\nPR-ch Sv BP olje ab Sthlm sed 55.\nGift m Ingrid Wessblad.\n\nHALL, MAC I, fd försäkringsdirektör,\nDjursholm, f i Sundsvall 16/11/92 av\nfondmäkl Arvid H o Laura Carlson.\nStudiex 11, HHS 11-12, anst försäkr\nab Heimdall 13, ab Fylgia 15, v dir 21,\nverkst dir Fylgia o Valkyrian 45-55.\n-Fd ordf i flera tariffsammanslutn o\nkomm inom försäkr:bol; stynordf åter-\n\nförsäkr ab Atlas 55, brandförsäkr ab\nTrygg, v ordf Allm\nhagelskadeförsäkr:-bol, styr:led Fylgia, Valkyrian. - Skr:\nFörsäkr:fören studiehandbok om\nbilförsäkring, Sv trafikförsäkring (tills\nm a). - Utm: KVO.\nGift 20 m Astrid Grahm f 96, dtr t\ngymnrdir Alfred G o Hildur Möller.\n-Barn: Inger-Britt f 21.\n\nHALLANDER-WIDING, E EIRA M,\ntandläkare, Sthlm, f i Skara av prof\nWilhelm H o Edla Dunér.\nStud:ex Gbg 19, odont kand 21,\ntand:-läk:ex 24, ass tandläk Karlst 24, vik\ntandläk Malmberget 24, prakt Boden\n25-35, skoltandläk Sollentuna 35-50, prakt\nSthlm sed 36. - Förest mil tandpoliklin\nBoden garn 25-35, skoltandläk Boden\n30-35. - Medl Sv tandläk:fören, Sv\ntandläk :sällsk.\n\nGift 25 m kapt Klas Widing d 28.\n-Barn: Britta f 26.\n\n",
    "structured": {
        "0": {
            "full_name": "Gösta Hall",
            "location": "Danderyd",
            "occupation": "civilingenjör",
            "birth_details": {
                "date": "22/07/1928",
                "place": "Mjölby",
                "parents": "affärschef A H o Eleonora Johansson"
            },
            "education": [
                {
                    "degree": "Stud:ex",
                    "year": "1947",
                    "institution": "Sthlm"
                },
                {
                    "degree": "KTH",
                    "year": "1955",
                    "institution": "l:e forskning FOA"
                }
            ],
            "career": [
                {
                    "position": "l:e forskn:-ing",
                    "years": {
                        "start_year": 1955
                    },
                    "organization": "FOA"
                }
            ],
            "family": {
                "spouse": "Marianne Bendel",
                "marriage_year": "NULL",
                "children": [
                    {
                        "name": "Yvonne",
                        "birth_year": "1957"
                    },
                    {
                        "name": "Thomas",
                        "birth_year": "1959"
                    },
                    {
                        "name": "Annika",
                        "birth_year": "1961"
                    }
                ]
            }
        },
        "1": {
            "full_name": "Karl Hall",
            "location": "Sthlm",
            "occupation": "redaktör",
            "birth_details": {
                "date": "05/05/1921",
                "place": "Östersund",
                "parents": "löjtn Ernst H o Hulda Andersson"
            },
            "education": [
                {
                    "degree": "Stud:ex",
                    "year": "1940",
                    "institution": "Sthlm"
                }
            ],
            "career": [
                {
                    "position": "medarb",
                    "years": {
                        "start_year": 1943
                    },
                    "organization": "ST"
                },
                {
                    "position": "PR-ch",
                    "years": {
                        "start_year": 1955
                    },
                    "organization": "Sv BP olje ab Sthlm"
                }
            ],
            "family": {
                "spouse": "Ingrid Wessblad",
                "marriage_year": "NULL",
                "children": []
            }
        },
        "2": {
            "full_name": "Mac I Hall",
            "location": "Djursholm",
            "occupation": "fd försäkringsdirektör",
            "birth_details": {
                "date": "16/11/1892",
                "place": "Sundsvall",
                "parents": "fondmäkl Arvid H o Laura Carlson"
            },
            "education": [
                {
                    "degree": "Studiex",
                    "year": "1911",
                    "institution": "NULL"
                },
                {
                    "degree": "HHS",
                    "year": "1911-1912",
                    "institution": "NULL"
                }
            ],
            "career": [
                {
                    "position": "anst försäkr ab Heimdall",
                    "years": {
                        "start_year": 1913
                    },
                    "organization": "NULL"
                },
                {
                    "position": "ab Fylgia",
                    "years": {
                        "start_year": 1915
                    },
                    "organization": "NULL"
                },
                {
                    "position": "v dir",
                    "years": {
                        "start_year": 1921
                    },
                    "organization": "Fylgia o Valkyrian"
                },
                {
                    "position": "verkst dir",
                    "years": {
                        "start_year": 1945,
                        "end_year": 1955
                    },
                    "organization": "Fylgia o Valkyrian"
                }
            ],
            "family": {
                "spouse": "Astrid Grahm",
                "marriage_year": "1920",
                "children": [
                    {
                        "name": "Inger-Britt",
                        "birth_year": "1921"
                    }
                ]
            }
        },
        "3": {
            "full_name": "Eira M Hallander-Widing",
            "location": "Sthlm",
            "occupation": "tandläkare",
            "birth_details": {
                "date": "NULL",
                "place": "Skara",
                "parents": "prof Wilhelm H o Edla Dunér"
            },
            "education": [
                {
                    "degree": "Stud:ex",
                    "year": "1919",
                    "institution": "Gbg"
                },
                {
                    "degree": "odont kand",
                    "year": "1921",
                    "institution": "NULL"
                },
                {
                    "degree": "tand:-läk:ex",
                    "year": "1924",
                    "institution": "NULL"
                }
            ],
            "career": [
                {
                    "position": "Ass",
                    "years": {
                        "start_year": 1924
                    },
                    "organization": "tandläk Karlst"
                },
                {
                    "position": "prakt",
                    "years": {
                        "start_year": 1936,
                        "end_year": 1950
                    },
                    "organization": "Sthlm"
                }
            ],
            "family": {
                "spouse": "Klas Widing",
                "marriage_year": "1925",
                "children": [
                    {
                        "name": "Britta",
                        "birth_year": "1926"
                    }
                ]
            }
        }
    }
}