{
    "original": "HAGSTRÖMER,   ANNA-LISA,   aukt\nrevisor,  Sthlm,  f i  Sthlm  31/1/18.\nStud:ex   43,   DHS   46,   deläg   revrbyrå\nSthlm sed 51. - Skattmäst o stynled YK\n60.\n\nGift 52 m ekonrdir Lennart H. - Barn:\nCecilia f 53, Göran f 54.\n\nHAGSTRÖMER, P J GÖSTA S:SON,\nhovrättsråd, Sthlm, f i Sthlm 11/7/08 av\nlandshövd Sven H o Sigrid Wising.\nStud:ex Karlskrona 27, jur kand Upps\n31, tingstjg Upps l n doms 31-34,\ntings-sekr 37-39, tf tingsdom 44-45, tf\nkrigs-hovr:råd 41-43, e fiskal Svea hovr 35,\nadj led 39, assess 42, revrsekr 50,\nhovr:-råd sed 51, v ordf på avd 57. - Led\no sekr 49 års rättshjälpskomm 49-51.\n-Utm: RNO.\n\nGift 42 m Ingvor Barthen f 20, dtr t\nkonsul Ivar B o Ernestine Anderson.\n-Barn: Sven f 43, Claes f 45, Pierre f 49.\n\nHAGWALL, ANNA-BRITTA,\nredaktör, Sthlm, f i Jukkasjärvi, Norrb l,\n15/10/16 av läroverksadj Olof\nNorrman o Signe Andersson.\n\nStud:ex Västerås 35, journ Västmanl\nl tidn 35, öl landsortstidn 37-39,\nmedarb Åhlén &amp; Åkerlunds förl 41-43,\nomb:man Sv befolkniförb (styr:led 46)\no red Social aspekt 45, Målsmännens\nriksförb o Barn i hem-skola-samhälle\n46-48, TT:s Sthlms- o riksdagsred 51,\nred Järnhandlaren sed 59. - Styr:led\nArosbröderna. - Skr: Den ljusnande\nframtid (45), Såna djur finns inte (46).\nGift 49 m red Gunnar Hagwall f 06.\n- Barn: Jan Peter f 50.\n\nHAHN, ERIK G, civilingenjör,\nLidingö, f i Kristiania 15/5/02 av\nskräd-darmäst Arvid H o Jenny Dahlin.\nStud:ex Sthlm 21, KTH 26,\narb:-ledare Sv ab Christiani &amp; Nielsen 26-29,\ning byggmäst Olle Engkvist 29-30,\narb:-ch Monberg &amp; Thorsen ab Sthlm\n30-35, avdrch ab Bergendahl &amp; Höckert\nSthlm 35-39, eg verksamh 39-40,\nVV:-styr sed 41, byrådir överstyr f ekon\nförsv:beredskap sed 60. - Stadsfullm\nLidingö 48-58, led Lidingö\ndrätselkammare 46-50, LSvTF.\nGift 31 m Gertrud Thomasson f 02, dtr\nt justitierådet Åke T o Gertrud\nEkenman. - Barn: Margareta f 30,\nKristina f 32, Gunilla f 35, Karin f 37,\nBirgitta f 39, Torbjörn f 41.\n\n",
    "structured": {
        "1": {
            "full_name": "ANNA-LISA HAGSTRÖMER",
            "location": "Sthlm",
            "occupation": "aukt revisor",
            "birth_details": {
                "date": "31/01/1918",
                "place": "Sthlm"
            },
            "education": [
                {
                    "degree": "Stud:ex",
                    "year": "1943",
                    "institution": "DHS"
                }
            ],
            "career": [
                {
                    "position": "deläg revrbyrå",
                    "years": {
                        "start_year": 1951
                    },
                    "organization": "Sthlm"
                },
                {
                    "position": "Skattmäst o stynled YK",
                    "years": {
                        "start_year": 1960
                    }
                }
            ],
            "family": {
                "spouse": "Lennart H",
                "marriage_year": "1952",
                "children": [
                    {
                        "name": "Cecilia",
                        "birth_year": "1953"
                    },
                    {
                        "name": "Göran",
                        "birth_year": "1954"
                    }
                ]
            }
        },
        "2": {
            "full_name": "P J GÖSTA S:SON HAGSTRÖMER",
            "location": "Sthlm",
            "occupation": "hovrättsråd",
            "birth_details": {
                "date": "11/07/1908",
                "place": "Sthlm",
                "parents": "landshövd Sven H o Sigrid Wising"
            },
            "education": [
                {
                    "degree": "Stud:ex",
                    "year": "1927",
                    "institution": "Karlskrona"
                },
                {
                    "degree": "jur kand",
                    "year": "1931",
                    "institution": "Upps"
                }
            ],
            "career": [
                {
                    "position": "tingstjg",
                    "years": {
                        "start_year": 1931,
                        "end_year": 1934
                    },
                    "organization": "Upps l n doms"
                },
                {
                    "position": "tings-sekr",
                    "years": {
                        "start_year": 1937,
                        "end_year": 1939
                    }
                },
                {
                    "position": "tf tingsdom",
                    "years": {
                        "start_year": 1944,
                        "end_year": 1945
                    }
                },
                {
                    "position": "tf krigs-hovr:råd",
                    "years": {
                        "start_year": 1941,
                        "end_year": 1943
                    }
                },
                {
                    "position": "e fiskal",
                    "years": {
                        "start_year": 1935
                    },
                    "organization": "Svea hovr"
                },
                {
                    "position": "adj led",
                    "years": {
                        "start_year": 1939
                    }
                },
                {
                    "position": "assess",
                    "years": {
                        "start_year": 1942
                    }
                },
                {
                    "position": "revrsekr",
                    "years": {
                        "start_year": 1950
                    }
                },
                {
                    "position": "hovr:-råd",
                    "years": {
                        "start_year": 1951
                    }
                },
                {
                    "position": "v ordf på avd",
                    "years": {
                        "start_year": 1957
                    }
                }
            ],
            "family": {
                "spouse": "Ingvor Barthen",
                "marriage_year": "1942",
                "children": [
                    {
                        "name": "Sven",
                        "birth_year": "1943"
                    },
                    {
                        "name": "Claes",
                        "birth_year": "1945"
                    },
                    {
                        "name": "Pierre",
                        "birth_year": "1949"
                    }
                ]
            }
        },
        "3": {
            "full_name": "ANNA-BRITTA HAGWALL",
            "location": "Sthlm",
            "occupation": "redaktör",
            "birth_details": {
                "date": "15/10/1916",
                "place": "Jukkasjärvi, Norrb l",
                "parents": "läroverksadj Olof Norrman o Signe Andersson"
            },
            "education": [
                {
                    "degree": "Stud:ex",
                    "year": "1935",
                    "institution": "Västerås"
                }
            ],
            "career": [
                {
                    "position": "redaktör",
                    "years": {
                        "start_year": 1959
                    },
                    "organization": "Järnhandlaren"
                }
            ],
            "family": {
                "spouse": "Gunnar Hagwall",
                "marriage_year": "1949",
                "children": [
                    {
                        "name": "Jan Peter",
                        "birth_year": "1950"
                    }
                ]
            },
            "publications": [
                {
                    "title": "Den ljusnande framtid",
                    "year": "1945"
                },
                {
                    "title": "Såna djur finns inte",
                    "year": "1946"
                }
            ],
            "community_involvement": [
                {
                    "role": "omb:man",
                    "organization": "Sv befolkniförb",
                    "years": "46"
                },
                {
                    "role": "red Social aspekt",
                    "organization": "Målsmännens riksförb o Barn i hem-skola-samhälle",
                    "years": "46-48"
                },
                {
                    "role": "TT:s Sthlms- o riksdagsred",
                    "years": "51"
                }
            ]
        },
        "4": {
            "full_name": "ERIK G HAHN",
            "location": "Lidingö",
            "occupation": "civilingenjör",
            "birth_details": {
                "date": "15/05/1902",
                "place": "Kristiania",
                "parents": "skräddarmäst Arvid H o Jenny Dahlin"
            },
            "education": [
                {
                    "degree": "Stud:ex",
                    "year": "1921",
                    "institution": "Sthlm"
                }
            ],
            "career": [
                {
                    "position": "arb:-ledare",
                    "years": {
                        "start_year": 1926,
                        "end_year": 1929
                    },
                    "organization": "Sv ab Christiani & Nielsen"
                },
                {
                    "position": "ing byggmäst",
                    "years": {
                        "start_year": 1929,
                        "end_year": 1930
                    },
                    "organization": "Olle Engkvist"
                },
                {
                    "position": "arb:-ch",
                    "years": {
                        "start_year": 1930,
                        "end_year": 1935
                    },
                    "organization": "Monberg & Thorsen ab Sthlm"
                },
                {
                    "position": "avdrch",
                    "years": {
                        "start_year": 1935,
                        "end_year": 1939
                    },
                    "organization": "ab Bergendahl & Höckert Sthlm"
                },
                {
                    "position": "VV:-styr",
                    "years": {
                        "start_year": 1941
                    }
                },
                {
                    "position": "byrådir överstyr f ekon försv:beredskap",
                    "years": {
                        "start_year": 1960
                    }
                }
            ],
            "family": {
                "spouse": "Gertrud Thomasson",
                "marriage_year": "1931",
                "children": [
                    {
                        "name": "Margareta",
                        "birth_year": "1930"
                    },
                    {
                        "name": "Kristina",
                        "birth_year": "1932"
                    },
                    {
                        "name": "Gunilla",
                        "birth_year": "1935"
                    },
                    {
                        "name": "Karin",
                        "birth_year": "1937"
                    },
                    {
                        "name": "Birgitta",
                        "birth_year": "1939"
                    },
                    {
                        "name": "Torbjörn",
                        "birth_year": "1941"
                    }
                ]
            }
        }
    }
}