{
    "original": "Martin, Frank Hugo, ryttmästare,\nDjursholm, f. 30/12/85 av &gt;gen:dir. Hugo\nWilhelm M. o. Hilda Fredrika Rydberg.\nG. 09 m. frih :an Eva Arma Louise af\nUgglas. Barn: Hugo f. 10, civ:ing.,\nMalmö, Tyr f. 15, konstnär, Roland f.\n17, flygkadett, d. 40, Norah f. 23, Gari\nf. 25, stud. Und:löjtn. v. Livreg. drag.\n06, löjtn. 09, ryttm. 21, på överg:stat v.\nLivreg. t. häst 28. Delt. i finska\nvinterkriget 40. Medarb, i Sv. Dagbladet\n28-40, medarb, i div. tidn. o. tidskr, i\nmilitära o. politiska ämn. sed. 40,\nmedarb, i Sv. män o. kvinnor, Nordisk\nFamiljeboks sportlex., tills. m. N.\nFischerström utg. Ridskolan på Strömsholm\n5Q år (18), i red:komm. o. medarb, i\nHästen i Sverige, Hästar o. hästfolk i\nvåra dagars Sverige. RSO, GVisOlM,\nBMilK2kl, RDDO, FPrK4kl m sv,\nFFält-tM m sv, KHS, RS, SS.\nMartin, Jan Herbert, sekreterare,\nLidingö, f. 19/9/12 i Lidingö. G. m.\ntextil-konstn :an Eo Ina Johanson. Barn:\nSuzanne f. 34, Joakim f. 40, Barbara f. 42.\nStud:ex. i Upps. 30, jur. kand. i Sthlm\n36. Tingstjg, i Upps. läns s :a doms.\n36-37, Sthlms rådhusrätt 37-39, not. v,\nSthlms städs kansli 39-40, sekr. v. sa.\nkansli (h. borgarrådet f.\nstadsbyggn:-roteln) 40.\nMartin, Karl August Martin\nJohansson, disponent, Vaxholm, f. 7/1/80 i\nSödertälje. G. m. Marta Holmqvist.\nUnd:off:ex. 01, löjtn, i marinen fr. 35.\nOrdf. i Vaxholms Stadsfullm, fr. 19, i\nkyrkofullm. fr. 38, led. av andra kamm.\nJ0-14, landst:m. 10-26, v. ordf. i landst.\n19-26, ordf. i landst. finiutsk. o. 2.\nhälsov:utsk., led. av landst. förvrutsk.\no. sjukvind, av lotsv. löneregi:komm.\n12, sakk. inom försv :dep. rör. friköp\nav Vaxh itomter 26, en av utredn :män.\no. sekr. rör. fiskets administr. 36-37,\nled. av 35 års fiskeriutredn. 35-37,\nen-manskomm. rör. fiskarnas orgtväs.\n38-39, sekr. i 40 års fiskeriutredn., ordf. i\nSv. fiskredskapsimp. fören.,\nvattenr:s-nämndeman. RVO, GMmf.\nMartin, Knut Alfred, regissör, Sthlm,\nf. 28/5/99 i Karlstad. G. m. Marta\nIngegerd Wallberg. Barn: Peter Arosin f.\n29, Christine Arosin f. 41. Avi.\nstud:-ex. 19, bedrivit akad. stud. i Tyskland\n20-22 .o. v. Sthlms Högsk. 22-23, Kungl.\nDram. Teat. elevsk. 23-25, premiärelev\n26, stud :res. t. Frankr., Engl. o. Amer.\nSkådesp. v. Komediteat. 27-30, v.\nEkmanteatrarna 30-33 samt varit verks,\ns. regissör. Intr. i filmbranschen 33.\nVerks. s. kortfilmsregissör v. A-B Sv.\nFilmindustri 33-44. Me’dl, av Sv.\nTea-terförb. Utg. \"Före äktenskapet\"\n(ska-desp.), \"Kungen kommer\" o. för övr.\nvarit journalistiskt verksam. Fackman\no. kännare av 1700-talskonst (silver o.\nmöbler). RVO.\n",
    "structured": {
        "1": {
            "full_name": "Martin, Frank Hugo",
            "location": "Djursholm",
            "occupation": "Ryttmästare",
            "birth_details": {
                "date": "30/12/1885",
                "place": "Djursholm",
                "parents": "Hugo Wilhelm Martin och Hilda Fredrika Rydberg"
            },
            "education": [],
            "career": [
                {
                    "position": "Und:löjtn. v. Livreg. drag.",
                    "years": {
                        "start_year": 1906,
                        "end_year": 1909
                    },
                    "organization": "Livreg. drag."
                },
                {
                    "position": "Löjtn.",
                    "years": {
                        "start_year": 1909,
                        "end_year": 1921
                    },
                    "organization": "Livreg. t. häst"
                }
            ],
            "family": {
                "spouse": "Eva Arma Louise af Ugglas",
                "marriage_year": "1909",
                "children": [
                    {
                        "name": "Hugo",
                        "birth_year": "1910"
                    },
                    {
                        "name": "Tyr",
                        "birth_year": "1915"
                    },
                    {
                        "name": "Roland",
                        "birth_year": "1917"
                    },
                    {
                        "name": "Norah",
                        "birth_year": "1923"
                    },
                    {
                        "name": "Gari",
                        "birth_year": "1925"
                    }
                ]
            }
        },
        "2": {
            "full_name": "Martin, Jan Herbert",
            "location": "Lidingö",
            "occupation": "Sekreterare",
            "birth_details": {
                "date": "19/09/1912",
                "place": "Lidingö",
                "parents": "NULL"
            },
            "education": [],
            "career": [
                {
                    "position": "Tingstjg, i Upps. läns s :a doms.",
                    "years": {
                        "start_year": 1936,
                        "end_year": 1937
                    },
                    "organization": "Upps. läns s :a doms."
                },
                {
                    "position": "Sekr. v. sa. kansli",
                    "years": {
                        "start_year": 1940,
                        "end_year": "NULL"
                    },
                    "organization": "h. borgarrådet f. stadsbyggn:-roteln"
                }
            ],
            "family": {
                "spouse": "Eo Ina Johanson",
                "marriage_year": "NULL",
                "children": [
                    {
                        "name": "Suzanne",
                        "birth_year": "1934"
                    },
                    {
                        "name": "Joakim",
                        "birth_year": "1940"
                    },
                    {
                        "name": "Barbara",
                        "birth_year": "1942"
                    }
                ]
            }
        },
        "3": {
            "full_name": "Martin, Karl August Martin Johansson",
            "location": "Vaxholm",
            "occupation": "Disponent",
            "birth_details": {
                "date": "07/01/1880",
                "place": "Södertälje",
                "parents": "NULL"
            },
            "education": [],
            "career": [],
            "family": {
                "spouse": "Marta Holmqvist",
                "marriage_year": "NULL",
                "children": []
            }
        },
        "4": {
            "full_name": "Martin, Knut Alfred",
            "location": "Sthlm",
            "occupation": "Regissör",
            "birth_details": {
                "date": "28/05/1899",
                "place": "Karlstad",
                "parents": "NULL"
            },
            "education": [],
            "career": [],
            "family": {
                "spouse": "Marta Ingegerd Wallberg",
                "marriage_year": "NULL",
                "children": [
                    {
                        "name": "Peter Arosin",
                        "birth_year": "1929"
                    },
                    {
                        "name": "Christine Arosin",
                        "birth_year": "1941"
                    }
                ]
            }
        }
    }
}