{
    "original": "PETTERSSON, GÖRAN A B,\napotekare, Boden, f i Älvsbyn, Norrb l, 12/9/\n15 av köpm J A P o Hulda Benjamin.\nStud:ex Luleå 36, farm kand 40, apot:ex\n46. - Elev Ugglan Sthlm 38, anst Piteå\n40, Haparanda 41, Renen Umeå 41,\nSkellefteå 46, Boden 47, Lejonet\nSundsvall 52, mil:- o sjhapot Boden (förest)\n56, priv apot Boden sed 64. - Norrb l\nlandst läkemedelskonsult 56-64, lär i\nläkemedelslära SRK:s sjuksköt:sk Boden\n50-52 o 56-64. - Fullm Övre nordsv\nkretsen av Sv:es farm:förb 58-61, sekr 58-63,\nled Apot:soc direktion sed 65. - Medl\nRotary. - Skr: Ett distributionssystem\nför läkemedel (58), En signatur för\nsjukhusleveranser (58), Förråd av\n\"akut\"-läkemedel (61). - Hobbies: curling,\nfjällsport.\n\nGift 45 m Inger Lindquist, dtr t\nfolkskollär Hjalmar L o Gertrud Svensson.\n-Barn: Petter f 47, Britta f 51.\n\nPETERSON, HANS H,\nfiskerikonsu-lent, Sörberge, f i Torsåker, Gävleb l,\n28/8/21 av fiskaren Axel Pettersson o\nAnna Forsström.\n\nStat fiskerisk 42, fiskeriinstr Västerb l\nhush:sällsk 43, fiskerikonsulent\nBergeforsens kraft ab sed 51, ch Bergeforsens\nlaxodling sed 63. - Sakk:uppdr i\nsportfiskefrågor h vattendomst, konsultuppdr\nCanada. - Styr :led Sv sportfiskareförb o\nled överstyr Fiskefrämj sed 59; led\nkomm:fullm Timrå 59-62. - Medl Lions\nclub. - Skr: Harren (64), övers\nSportfiske o sportfiskar (66). - Hobbies: fiske,\njakt, filateli, foto.\n\nGift 54 m Carin Bengtsson f 20, dtr t\nrekt Sam B o Maja Gustafsson. - Barn:\nPer f 58, Hans-Jörgen f 59.\n\nPETERSSON, J C INGEMAR,\nadjunkt, Gullänget, f i Nybro 9/2/36 av\nkassör John P o Märta Franzén.\nStud:ex Kalmar 54, fil mag Upps 58, eo\nadj Bandhagens komm gymn 62, adj\nÄngetsk Gullänget sed 62. - Deläg f:a\nÄngetprodukter sed 66. - Led LR :s\ndistr:styr Vnorrl l sed 66. - Skr: Look,\nListen and Work (66), Att läsa (tills m a\n67). - Hobbies: fiske, schack.\nGift 59 m Maud Halldin f 36, dtr t\nmaskinist Einar H o Valdy Gunnar.\n-Barn: Jonas f 63.\n\n",
    "structured": {
        "0": {
            "full_name": "Göran A B Pettersson",
            "location": "Boden",
            "occupation": "Apotekare",
            "birth_details": {
                "date": "12/09/1915",
                "place": "Älvsbyn, Norrbottens län"
            },
            "education": [
                {
                    "degree": "Stud:ex",
                    "year": "1936",
                    "institution": "Luleå"
                },
                {
                    "degree": "Farm kand",
                    "year": "1940",
                    "institution": "Okänt"
                },
                {
                    "degree": "Apot:ex",
                    "year": "1946",
                    "institution": "Okänt"
                }
            ],
            "career": [
                {
                    "position": "Elev",
                    "years": {
                        "start_year": 1938,
                        "end_year": 1938
                    },
                    "organization": "Ugglan Sthlm"
                },
                {
                    "position": "Anställd",
                    "years": {
                        "start_year": 1940,
                        "end_year": 1940
                    },
                    "organization": "Piteå"
                },
                {
                    "position": "Anställd",
                    "years": {
                        "start_year": 1941,
                        "end_year": 1941
                    },
                    "organization": "Haparanda"
                },
                {
                    "position": "Anställd",
                    "years": {
                        "start_year": 1941,
                        "end_year": 1941
                    },
                    "organization": "Renen Umeå"
                },
                {
                    "position": "Anställd",
                    "years": {
                        "start_year": 1946,
                        "end_year": 1946
                    },
                    "organization": "Skellefteå"
                },
                {
                    "position": "Anställd",
                    "years": {
                        "start_year": 1947,
                        "end_year": 1947
                    },
                    "organization": "Boden"
                },
                {
                    "position": "Anställd",
                    "years": {
                        "start_year": 1952,
                        "end_year": 1956
                    },
                    "organization": "Sundsvall"
                },
                {
                    "position": "Mil:- och sjukhusapotekare",
                    "years": {
                        "start_year": 1956,
                        "end_year": 1956
                    },
                    "organization": "Boden"
                },
                {
                    "position": "Privat apotekare",
                    "years": {
                        "start_year": 1964
                    },
                    "organization": "Boden"
                }
            ],
            "family": {
                "spouse": "Inger Lindquist",
                "marriage_year": "1945",
                "children": [
                    {
                        "name": "Petter",
                        "birth_year": "1947"
                    },
                    {
                        "name": "Britta",
                        "birth_year": "1951"
                    }
                ]
            },
            "publications": [
                {
                    "title": "Ett distributionssystem för läkemedel",
                    "year": "1958",
                    "type": "Okänt"
                },
                {
                    "title": "En signatur för sjukhusleveranser",
                    "year": "1958",
                    "type": "Okänt"
                },
                {
                    "title": "Förråd av 'akut'-läkemedel",
                    "year": "1961",
                    "type": "Okänt"
                }
            ],
            "community_involvement": [
                {
                    "role": "Fullmäktig",
                    "organization": "Övre nordsv kretsen av Sv:es farm:förb",
                    "years": "1958-1961"
                }
            ],
            "board_memberships": null,
            "honorary_titles": null,
            "hobbies": [
                "Curling",
                "Fjällsport"
            ]
        },
        "1": {
            "full_name": "Hans H Peterson",
            "location": "Sörberge",
            "occupation": "Fiskerikonsulent",
            "birth_details": {
                "date": "28/08/1921",
                "place": "Torsåker, Gävleborgs län"
            },
            "education": null,
            "career": [
                {
                    "position": "Stat fiskerisk",
                    "years": {
                        "start_year": 1942,
                        "end_year": 1942
                    },
                    "organization": "Okänt"
                },
                {
                    "position": "Fiskeriinstr",
                    "years": {
                        "start_year": 1943,
                        "end_year": 1943
                    },
                    "organization": "Västerb l hush:sällsk"
                },
                {
                    "position": "Fiskerikonsulent",
                    "years": {
                        "start_year": 1951
                    },
                    "organization": "Bergeforsens kraft ab"
                },
                {
                    "position": "Ch",
                    "years": {
                        "start_year": 1963
                    },
                    "organization": "Bergeforsens laxodling"
                }
            ],
            "family": {
                "spouse": "Carin Bengtsson",
                "marriage_year": "1954",
                "children": [
                    {
                        "name": "Per",
                        "birth_year": "1958"
                    },
                    {
                        "name": "Hans-Jörgen",
                        "birth_year": "1959"
                    }
                ]
            },
            "publications": [
                {
                    "title": "Harren",
                    "year": "1964",
                    "type": "Okänt"
                },
                {
                    "title": "Sportfiske o sportfiskar",
                    "year": "1966",
                    "type": "Övers"
                }
            ],
            "community_involvement": null,
            "board_memberships": null,
            "honorary_titles": null,
            "hobbies": [
                "Fiske",
                "Jakt",
                "Filateli",
                "Foto"
            ]
        },
        "2": {
            "full_name": "J C Ingemar Petersson",
            "location": "Gullänget",
            "occupation": "Adjunkt",
            "birth_details": {
                "date": "09/02/1936",
                "place": "Nybro"
            },
            "education": [
                {
                    "degree": "Stud:ex",
                    "year": "1954",
                    "institution": "Kalmar"
                },
                {
                    "degree": "Fil mag",
                    "year": "1958",
                    "institution": "Upps"
                }
            ],
            "career": [
                {
                    "position": "Eo adj",
                    "years": {
                        "start_year": 1962
                    },
                    "organization": "Bandhagens komm gymn"
                },
                {
                    "position": "Adj",
                    "years": {
                        "start_year": 1962
                    },
                    "organization": "Ängetsk Gullänget"
                },
                {
                    "position": "Delägare",
                    "years": {
                        "start_year": 1966
                    },
                    "organization": "Ängetprodukter"
                }
            ],
            "family": {
                "spouse": "Maud Halldin",
                "marriage_year": "1959",
                "children": [
                    {
                        "name": "Jonas",
                        "birth_year": "1963"
                    }
                ]
            },
            "publications": [
                {
                    "title": "Look, Listen and Work",
                    "year": "1966",
                    "type": "Okänt"
                },
                {
                    "title": "Att läsa",
                    "year": "Okänt",
                    "type": "tills m a 67"
                }
            ],
            "community_involvement": null,
            "board_memberships": null,
            "honorary_titles": null,
            "hobbies": [
                "Fiske",
                "Schack"
            ]
        }
    }
}