{
    "original": "PILSTRÖM, KARL-FRITJOF,\nkyrkoherde, Kramfors, f i Ekebyborna,\nÖsterg l, 24/7/07 av kantor Fritiof P o\nEllen Andersson.\n\nStud:ex Motala 25, teol kand Upps 33,\nkommin Nämndö 34, Rasbokil 37,\nkyr-koh Ramsjö 40, kommin Staffans förs\nGävle 48, kyrkoh Gudmundrå sed 60.\n-Styr:led Sv eldbegängelsefören sed 65.\n-Medl S H-n. - Utm: LNO. - Hobby:\nfiske.\n\nGift 34 m Siri Andersson f 10, dtr t\ncharkuterist Tyko A o Jenny Eriksson.\n-Barn: Jan f 35, Lars f 38, Staffan f 42,\nCharlotte f 47.\n\nPILTZ, SIGNE K, lektor, Luleå, f i\nFärgelanda, Älvsb l, 22/11/00 av\nfastigh:-äg Edvard Pettersson o Selma Larsson.\nStud:ex Gbg 19, fil mag Upps 23, teol\nkand Lund 27, teol lic Upps 39; eo\nämneslär Sollefteå komm mellansk o gymn\n27-28, e adj hal Vänersborg 40, hal\nSkövde 42, timlär folkhögsk Färgelanda\n39-41, 43-45, start h folksk Färgelanda,\ntimlär o e ämneslär där 45-51, eo adj hal\nVänersborg 51, lekt folksk:sem Luleå\nsed 54. - Skr: Luthers lära om\näktenskapet (39), art i tidn o tidskr om\nreligion o etik. - Hobbies: musik,\nträdgårdsskötsel.\n\nGift 32 m kyrkoh Constantin Piltz d 50.\n- Barn: Birgitta f 34, Elisabeth f 38,\nAnders f 43.\n\nPIPON, SIGNE, agronom, Luleå, f i\nLuleå 12/8/00 av landssekr Alrik P o\nHildegard Burman.\n\nAgr:ex Alnarp 26, förest Norrb l\nfrö-kontr:anst 39-65. - Rekt Norrb l landst\nambulerande hemslöjdskurser 30-57.\n-Sekr hush:sällsk slöjdnd 30-57, styr:led\n\nGrans lanthush:sk 40-55. - Ordf YK,\nsekr FBF:s stip:nd Norfb m m. - Utm:\nPatrSGM, GMmf, MannerheimM,\nHem-sl:förbM.\n\n",
    "structured": {
        "0": {
            "full_name": "Karl-Fritjof Pilström",
            "location": "Kramfors, Ekebyborna, Östergötland",
            "occupation": "kyrkoherde",
            "birth_details": {
                "date": "24/07/1907",
                "place": "Ekebyborna, Östergötland",
                "parents": "kantor Fritiof P o Ellen Andersson"
            },
            "education": [
                {
                    "degree": "Stud:ex",
                    "year": "1925",
                    "institution": "Motala"
                },
                {
                    "degree": "teol kand",
                    "year": "1933",
                    "institution": "Uppsala"
                }
            ],
            "career": [
                {
                    "position": "kommin",
                    "years": {
                        "start_year": 1934,
                        "end_year": 1937
                    },
                    "organization": "Nämndö"
                },
                {
                    "position": "kyr-koh",
                    "years": {
                        "start_year": 1940,
                        "end_year": 1948
                    },
                    "organization": "Ramsjö"
                },
                {
                    "position": "kyrkoh",
                    "years": {
                        "start_year": 1960
                    },
                    "organization": "Gudmundrå"
                }
            ],
            "family": {
                "spouse": "Siri Andersson",
                "marriage_year": "1934",
                "children": [
                    {
                        "name": "Jan",
                        "birth_year": "1935"
                    },
                    {
                        "name": "Lars",
                        "birth_year": "1938"
                    },
                    {
                        "name": "Staffan",
                        "birth_year": "1942"
                    },
                    {
                        "name": "Charlotte",
                        "birth_year": "1947"
                    }
                ]
            },
            "publications": [],
            "community_involvement": [
                {
                    "role": "Styr:led",
                    "organization": "Sv eldbegängelsefören",
                    "years": "sed 65"
                }
            ],
            "board_memberships": [],
            "honorary_titles": [],
            "hobbies": [
                "fiske"
            ]
        },
        "1": {
            "full_name": "Signe K Piltz",
            "location": "Luleå, Färgelanda, Älvsborg",
            "occupation": "lektor",
            "birth_details": {
                "date": "22/11/1900",
                "place": "Färgelanda, Älvsborg",
                "parents": "fastigh:-äg Edvard Pettersson o Selma Larsson"
            },
            "education": [
                {
                    "degree": "Stud:ex",
                    "year": "1919",
                    "institution": "Göteborg"
                },
                {
                    "degree": "fil mag",
                    "year": "1923",
                    "institution": "Uppsala"
                },
                {
                    "degree": "teol kand",
                    "year": "1927",
                    "institution": "Lund"
                },
                {
                    "degree": "teol lic",
                    "year": "1939",
                    "institution": "Uppsala"
                }
            ],
            "career": [
                {
                    "position": "eo ämneslär",
                    "years": {
                        "start_year": 1945,
                        "end_year": 1951
                    },
                    "organization": "Färgelanda"
                },
                {
                    "position": "eo adj hal",
                    "years": {
                        "start_year": 1951
                    },
                    "organization": "Vänersborg"
                },
                {
                    "position": "lekt",
                    "years": {
                        "start_year": 1954
                    },
                    "organization": "Luleå"
                }
            ],
            "family": {
                "spouse": "kyrkoh Constantin Piltz",
                "marriage_year": "1932",
                "children": [
                    {
                        "name": "Birgitta",
                        "birth_year": "1934"
                    },
                    {
                        "name": "Elisabeth",
                        "birth_year": "1938"
                    },
                    {
                        "name": "Anders",
                        "birth_year": "1943"
                    }
                ]
            },
            "publications": [
                {
                    "title": "Luthers lära om äktenskapet",
                    "year": "1939",
                    "type": "book"
                }
            ],
            "community_involvement": [],
            "board_memberships": [],
            "honorary_titles": [],
            "hobbies": [
                "musik",
                "trädgårdsskötsel"
            ]
        },
        "2": {
            "full_name": "Signe Pipon",
            "location": "Luleå",
            "occupation": "agronom",
            "birth_details": {
                "date": "12/08/1900",
                "place": "Luleå",
                "parents": "landssekr Alrik P o Hildegard Burman"
            },
            "education": [
                {
                    "degree": "Agr:ex",
                    "year": "1926",
                    "institution": "Alnarp"
                }
            ],
            "career": [
                {
                    "position": "förest",
                    "years": {
                        "start_year": 1939,
                        "end_year": 1965
                    },
                    "organization": "Norrb l frö-kontr:anst"
                },
                {
                    "position": "Rekt",
                    "years": {
                        "start_year": 1930,
                        "end_year": 1957
                    },
                    "organization": "Norrb l landst ambulerande hemslöjdskurser"
                },
                {
                    "position": "Sekr",
                    "organization": "hush:sällsk slöjdnd",
                    "years": "30-57"
                },
                {
                    "position": "styr:led",
                    "organization": "Grans lanthush:sk",
                    "years": "40-55"
                }
            ],
            "family": {},
            "publications": [],
            "community_involvement": [
                {
                    "role": "Ordf",
                    "organization": "YK",
                    "years": null
                },
                {
                    "role": "sekr",
                    "organization": "FBF:s stip:nd Norfb m m",
                    "years": null
                }
            ],
            "board_memberships": [],
            "honorary_titles": [
                {
                    "title": "PatrSGM",
                    "institution": null,
                    "year": null
                },
                {
                    "title": "GMmf",
                    "institution": null,
                    "year": null
                },
                {
                    "title": "MannerheimM",
                    "institution": null,
                    "year": null
                },
                {
                    "title": "Hem-sl:förbM",
                    "institution": null,
                    "year": null
                }
            ],
            "hobbies": []
        }
    }
}