{
    "original": "EGNELL, CLAES R H V,\növerstelöjtnant, Sollefteå, f i Lännäs, Örebro l,\n29/1/16 av öv:löjtn Vidar E o Maud\nMontgomery.\n\nStud:ex Örebro 35, fänr I 3 38, GIS 41,\nkapt 46, KHS 49-51, major I 2 57,\növ:löjtn I 21 66. - Lär GIS 42-43, taktiklär\nKS 51, komp:ch där 52-55, ch o öv:löjtn\nsv FN-bat Gaza 57-58, reg:stabsch I 2\n61-64, utb:off o stf reg:ch I 21 sed 66.\n-Ordf Ugglakomm 59-66, AU V mil\nidr:-distr 59-63, led Sv:es olymp komm\n52-55. - Medl SHT, Värml friidr:förb. - SM\ni modern femkamp 41-43, 45, 47, 52, i\nvinterfemkamp 45, 48, silvermed i lag i\nmodern femkamp OS 52. - Utm: RSO,\nOffEtMenO, RNS:tOOlkl, SMIGMmkr,\nSMIGM, SkytteGM, SvDGM 45,\nUNE-FM. - Hobbies: jakt, sport.\nGift 46 m Hjördis Monthén f 26, dtr t\njuveler Gustaf M o Greta Hedlund.\n-Barn: Ann-Charlotte f 47, Claes-Henrik\nf 49.\n\nEGNELL, LENNART O,\nbergsingenjör,   Sandviken,  f  i  Sthlm  28/2/32  av\nFritz E o Wivi Pettersson.\nStud:ex Sthlm 51, KTH 56, ing ab\nBofors   57,   Sandvikens   jernverks   ab   60,\navd :ch stålforskn där sed 65.\nGift 57 m Gudrun Jansson f 37, dtr t\nGustaf J o Elsa Ekmark. - Barn: Henrik\nf 59, Gustaf f 61, Eva f 64.\n\nEHINGER, ALVAR J, med dr,\nlänsläkare, Härnösand, f i Umeå 17/6/11 av\nl:e prov:läk Johan E o Hilma Norberg.\nMed lic Sthlm 37, med dr 45; öl\nunder-läk:förordn 38-39 o 45-47, ass stat bakt\nlab 40-45, l:e underläk Visby las 47-48,\nprov:läk Slite 48-53, l:e prov:läk Vnorrl\nl 53, länsläk sed 62. - Expert\nsmittlag-stiftn :utredn, led försv sjvstyr vetensk\nråd sed 60. - Medl FrimO, S:t PetriO\n-Skr: Ön the Haemolytic Streptococci in\nScarlet Fever (drsavh 45) m fi. - Utm:\nRNO, SRKSM. - Hobby: filateli.\nGift 42-57 m Gunnel Blomberg. - Barn:\nClaes f 43, Catharina f 46.\n\n",
    "structured": {
        "0": {
            "full_name": "EGNELL, CLAES R H V",
            "location": "Sollefteå",
            "occupation": "överstelöjtnant",
            "birth_details": {
                "date": "29/01/1916",
                "place": "Lännäs, Örebro l"
            },
            "education": [
                {
                    "degree": "Stud:ex",
                    "year": "1935",
                    "institution": "Örebro"
                },
                {
                    "degree": "fänr",
                    "year": "1938",
                    "institution": "I 3"
                },
                {
                    "degree": "GIS",
                    "year": "1941",
                    "institution": null
                },
                {
                    "degree": "kapt",
                    "year": "1946",
                    "institution": null
                },
                {
                    "degree": "KHS",
                    "year": "1949-1951",
                    "institution": null
                }
            ],
            "career": [
                {
                    "position": "major",
                    "years": {
                        "start_year": 1957,
                        "end_year": null
                    },
                    "organization": "I 2"
                },
                {
                    "position": "öv:löjtn",
                    "years": {
                        "start_year": 1966,
                        "end_year": null
                    },
                    "organization": "I 21"
                }
            ],
            "family": {
                "spouse": "Hjördis Monthén",
                "marriage_year": "1946",
                "children": [
                    {
                        "name": "Ann-Charlotte",
                        "birth_year": "1947"
                    },
                    {
                        "name": "Claes-Henrik",
                        "birth_year": "1949"
                    }
                ]
            }
        },
        "1": {
            "full_name": "EGNELL, LENNART O",
            "location": "Sandviken",
            "occupation": "bergsingenjör",
            "birth_details": {
                "date": "28/02/1932",
                "place": "Sthlm"
            },
            "education": [
                {
                    "degree": "Stud:ex",
                    "year": "1951",
                    "institution": "Sthlm"
                },
                {
                    "degree": "KTH",
                    "year": "1956",
                    "institution": null
                }
            ],
            "career": [
                {
                    "position": null,
                    "years": {
                        "start_year": 1965,
                        "end_year": null
                    },
                    "organization": "avd :ch stålforskn"
                }
            ],
            "family": {
                "spouse": "Gudrun Jansson",
                "marriage_year": "1957",
                "children": [
                    {
                        "name": "Henrik",
                        "birth_year": "1959"
                    },
                    {
                        "name": "Gustaf",
                        "birth_year": "1961"
                    },
                    {
                        "name": "Eva",
                        "birth_year": "1964"
                    }
                ]
            }
        },
        "2": {
            "full_name": "EHINGER, ALVAR J",
            "location": "Härnösand",
            "occupation": "med dr, länsläkare",
            "birth_details": {
                "date": "17/06/1911",
                "place": "Umeå"
            },
            "education": [
                {
                    "degree": "Med lic",
                    "year": "1937",
                    "institution": "Sthlm"
                },
                {
                    "degree": "med dr",
                    "year": "1945",
                    "institution": null
                }
            ],
            "career": [
                {
                    "position": null,
                    "years": {
                        "start_year": 1962,
                        "end_year": null
                    },
                    "organization": null
                }
            ],
            "family": {
                "spouse": "Gunnel Blomberg",
                "marriage_year": "1942-1957",
                "children": [
                    {
                        "name": "Claes",
                        "birth_year": "1943"
                    },
                    {
                        "name": "Catharina",
                        "birth_year": "1946"
                    }
                ]
            }
        }
    }
}