{
    "original": "EDBERG,   N   SVANTE,   stadsjurist,\n\nLuleå, f i Luleå 2/7/29 av ing Thure E\n\n0  Elsa Öström.\n\nStud:ex 50, jur kand Upps 56, tingstjg\nGällivare doms 56-58, e länsnot Norrb\n\n1   58-59,  stadsnot Luleå 59-66, stadsjur\ndär sed 66.\n\nGift 56 m skolkökslär Ulla-Britta Höök\nf 30. - Barn: Nils f 58, Eva f 61.\n\nEDBLAD, E ADRIAN, chefsingenjör,\n\nSollefteå, f i Nätra, Vnorrl l, 5/7/97 av\nnämndem Anders E o Charlotta\nSell-gren.\n\nIng:ex Katrineholms tekn sk 18,\nmon-tageing Norrl elektr ab 19, förest\nÖrnsköldsviks elektr byrå 22, ch Sollefteå\nsns elverk 27, ch Sollefteå stads elverk\n33-63, elkonsult o inneh Elektr\ning:by-rån sed 64. - Ordf civilförsv:ndn. - Medl\nOdd Fellow, Rotary. - Utm: SCFSM,\nVnorrl cf:fbftjtG, Vnorrl sfbSM,\nSollefteå stads GM, Sollefteå SKF GM.\n-Hobbies: jakt, fiske, konst, curling.\nGift 27 m Ellen Genberg f 04. - Barn:\nBo f 36.\n\nEDBOM, TURE S,\nstadsfullmäktige-ordförande, Gävle, f i Ljusdal, Gävleb l,\n29/1/18 av las :syssloman Olof E o Sigrid\nE.\n\nTypograf Nyströms tryckeri Bollnäs\n37-46, Arbetarbladet Gävle 46-53, förb:sekr\nDe lungsjukas riksförb Sthlm 53-55, sekr\nKonsum-Alfa Gävle sed 56. - Led\nGävleb l landst sed 63, led dess s j v :komm\nsed 63, s j v :utsk; ordf Stadsfullm Gävle\nsed 66 (led 50-53 o sed 63), bibi:styr\nm fi komm uppdr. - Styr:led Sv:es allm\nbibl :f ören sed 67, ordf Gävleb l\nnaturv:-råd sed 65, Gävle arb:kn sed 57. - Medl\nRotary. - Skr art i samhällsfrågor i\ndags-o fackpress; anmäl av pop :vetensk litt i\nArbetarbladet. - Sign: Ted. - Hobby:\nteckning.\n\nGift 38 m Ingrid Rask f 19, dtr t\növersköt Viktor R o Signe Tollstedt. - Barn:\nLeif f 38, Rolf f 46.\n\n",
    "structured": {
        "0": {
            "full_name": "Svante Edberg",
            "location": "Luleå",
            "occupation": "Stadsjurist",
            "birth_details": {
                "date": "02/07/1929",
                "place": "Luleå"
            },
            "education": [
                {
                    "degree": "Stud:ex",
                    "year": "1950",
                    "institution": "Okänt"
                },
                {
                    "degree": "Jur kand",
                    "year": "1956",
                    "institution": "Upps"
                }
            ],
            "career": [
                {
                    "position": "Tingstjg",
                    "years": {
                        "start_year": 1956,
                        "end_year": 1958
                    },
                    "organization": "Gällivare doms"
                },
                {
                    "position": "E länsnot",
                    "years": {
                        "start_year": 1958,
                        "end_year": 1959
                    },
                    "organization": "Norrb1"
                },
                {
                    "position": "Stadsnot",
                    "years": {
                        "start_year": 1959,
                        "end_year": 1966
                    },
                    "organization": "Luleå"
                },
                {
                    "position": "Stadsjur",
                    "years": {
                        "start_year": 1966,
                        "end_year": null
                    },
                    "organization": "Luleå"
                }
            ],
            "family": {
                "spouse": "Ulla-Britta Höök",
                "marriage_year": "1956",
                "children": [
                    {
                        "name": "Nils",
                        "birth_year": "1958"
                    },
                    {
                        "name": "Eva",
                        "birth_year": "1961"
                    }
                ]
            }
        },
        "1": {
            "full_name": "E Adrian Edblade",
            "location": "Sollefteå",
            "occupation": "Chefsingenjör",
            "birth_details": {
                "date": "05/07/1897",
                "place": "Nätra, Vnorrl l"
            },
            "education": [
                {
                    "degree": "Ing:ex",
                    "year": "1918",
                    "institution": "Katrineholms tekn sk"
                }
            ],
            "career": [
                {
                    "position": "Montageing",
                    "years": {
                        "start_year": 1919,
                        "end_year": null
                    },
                    "organization": "Norrl elektr ab"
                },
                {
                    "position": "Förest",
                    "years": {
                        "start_year": 1922,
                        "end_year": null
                    },
                    "organization": "Örnsköldsviks elektr byrå"
                },
                {
                    "position": "Ch",
                    "years": {
                        "start_year": 1927,
                        "end_year": 1963
                    },
                    "organization": "Sollefteå sns elverk"
                },
                {
                    "position": "Ch",
                    "years": {
                        "start_year": 1933,
                        "end_year": 1963
                    },
                    "organization": "Sollefteå stads elverk"
                },
                {
                    "position": "Elkonsult",
                    "years": {
                        "start_year": 1964,
                        "end_year": null
                    },
                    "organization": "Elektr ing:by-rån"
                }
            ],
            "family": {
                "spouse": "Ellen Genberg",
                "marriage_year": "1927",
                "children": [
                    {
                        "name": "Bo",
                        "birth_year": "1936"
                    }
                ]
            },
            "hobbies": [
                "Jakt",
                "Fiske",
                "Konst",
                "Curling"
            ]
        },
        "2": {
            "full_name": "Ture S Edbom",
            "location": "Gävle",
            "occupation": "Stadsfullmäktige-ordförande",
            "birth_details": {
                "date": "29/01/1918",
                "place": "Ljusdal, Gävleb l"
            },
            "education": [
                {
                    "degree": "Typograf",
                    "year": "Okänt",
                    "institution": "Nyströms tryckeri Bollnäs"
                }
            ],
            "career": [
                {
                    "position": "Arbetarbladet",
                    "years": {
                        "start_year": 1946,
                        "end_year": 1953
                    },
                    "organization": "Gävle"
                },
                {
                    "position": "Förb:sekr",
                    "years": {
                        "start_year": 1953,
                        "end_year": 1955
                    },
                    "organization": "De lungsjukas riksförb Sthlm"
                },
                {
                    "position": "Sekr",
                    "years": {
                        "start_year": 1956,
                        "end_year": null
                    },
                    "organization": "Konsum-Alfa Gävle"
                }
            ],
            "family": {
                "spouse": "Ingrid Rask",
                "marriage_year": "1938",
                "children": [
                    {
                        "name": "Leif",
                        "birth_year": "1938"
                    },
                    {
                        "name": "Rolf",
                        "birth_year": "1946"
                    }
                ]
            },
            "hobbies": [
                "Teckning"
            ]
        }
    }
}