{
    "original": "ERIKSSON,   ERIK,   läroverksadjunkt,\n\nHudiksvall, f i Bollnäs 6/7/02 av\nhemul :äg Erik Andersson o Sara Eriksdotter.\nStud:ex 25 o fil mag Upps 31, lär Birka\nfolkhögsk 32, eo ämneslär komm\nmel-lansk Rättvik 34, ord ämneslär där\n39-48, adj i modersm o hist m samh:lära\nhal Hudiksvall sed 48. - Medl\nHudiksvalls human förb, Hudiksvalls\nkonstgille, Hälsingl fornminnesfören. - Utm:\nRNO. - Hobby: bokbinderi.\nGift 34 m Hedvig Fallgren, dtr t kolvakt\nLudvig F o Eleonora Strandberg. - Barn:\nAstri f 35, Ingrid f 39, Gudrun f 42,\nOlof f 45.\n\nERIKSSON,    N   FABIAN,   köpman,\n\nSundsvall, f i Nora, Vnorrl l,  12/8/02\nav slipmäst Erik E o Charlotta\nLundqvist.\nKorresp :stud, sågv :arb Nyadal, repr 22-\n\n48, inneh N F Erikssons skomagasin\n33-45, Ålunds skor ab sed 45, Sko-centrum\nab sed 65. - Ordf N Norrl\nskohandl:-fören sed 62, styr:led Sv:es\nskohandl:-förb (SSHF) sed 64. - Medl FrimO.\nGift 29 m Tekla Bäckström f 08, dtr t\nlantbr August B o Anna Garney. - Barn:\nÖrjan f 44.\n\nERIKSSON, FILIP, bankkamrer, Umeå,\nf i Holmsund, Västerb l, 8/3/29 av\nbankförest Seth E o Märta Säfström.\nRealex Umeå 47, hdlssk Lindgård 47,\nSparbkssk Sthlm 58 o 59; anst Västerb\nl sparbk Umeå 48, kamr o ch låneavd\ndär sed 63. - Kassaförv Västerb :distr\nSRK sed 62, rev Norrländska\nsparbks-fören sed 63, Sandviks IK sed 56,\nstyr:led Umeå avd av Sv banktjm:förb 58-62.\n\n-  Sportskrib Västerb-Kuriren o Västerb\nFolkbl 52-63. - Erh DM i jun:fotboll 46.\n\n-  Hobby: sport.\n\nGift 64 m Elisabeth Skalin f 39, dtr t\nköpm Bertil S o Eva Rundqvist. - Barn:\nJonas f 65.\n\n",
    "structured": {
        "0": {
            "full_name": "ERIKSSON, ERIK",
            "location": "Hudiksvall",
            "occupation": "läroverksadjunkt",
            "birth_details": {
                "date": "06/07/1902",
                "place": "Bollnäs",
                "parents": "hemul :äg Erik Andersson o Sara Eriksdotter"
            },
            "education": [
                {
                    "degree": "Stud",
                    "year": "1925",
                    "institution": "Upps"
                },
                {
                    "degree": "fil mag",
                    "year": "1931",
                    "institution": "Upps"
                }
            ],
            "career": [
                {
                    "position": "eo ämneslär komm",
                    "years": {
                        "start_year": 1934,
                        "end_year": 1939
                    },
                    "organization": "Rättvik"
                },
                {
                    "position": "ord ämneslär där",
                    "years": {
                        "start_year": 1939,
                        "end_year": 1948
                    },
                    "organization": "Rättvik"
                },
                {
                    "position": "adj i modersm o hist m samh:lära",
                    "years": {
                        "start_year": 1948,
                        "end_year": null
                    },
                    "organization": "Hudiksvall"
                }
            ],
            "family": {
                "spouse": "Hedvig Fallgren",
                "marriage_year": "1934",
                "children": [
                    {
                        "name": "Astri",
                        "birth_year": "1935"
                    },
                    {
                        "name": "Ingrid",
                        "birth_year": "1939"
                    },
                    {
                        "name": "Gudrun",
                        "birth_year": "1942"
                    },
                    {
                        "name": "Olof",
                        "birth_year": "1945"
                    }
                ]
            },
            "hobbies": [
                "bokbinderi"
            ]
        },
        "1": {
            "full_name": "ERIKSSON, FABIAN",
            "location": "Sundsvall",
            "occupation": "köpman",
            "birth_details": {
                "date": "12/08/1902",
                "place": "Nora, Vnorrl l"
            },
            "career": [
                {
                    "position": "repr",
                    "years": {
                        "start_year": 1922,
                        "end_year": 1948
                    },
                    "organization": "Nyadal"
                },
                {
                    "position": "inneh N F Erikssons skomagasin",
                    "years": {
                        "start_year": 1933,
                        "end_year": 1945
                    },
                    "organization": null
                },
                {
                    "position": "Ålunds skor ab",
                    "years": {
                        "start_year": 1945,
                        "end_year": null
                    },
                    "organization": null
                },
                {
                    "position": "Sko-centrum ab",
                    "years": {
                        "start_year": 1965,
                        "end_year": null
                    },
                    "organization": null
                }
            ],
            "family": {
                "spouse": "Tekla Bäckström",
                "marriage_year": "1929",
                "children": [
                    {
                        "name": "Örjan",
                        "birth_year": "1944"
                    }
                ]
            },
            "community_involvement": [
                {
                    "role": "ordf",
                    "organization": "N Norrl skohandl:-fören",
                    "years": "sed 1962"
                }
            ],
            "board_memberships": [
                {
                    "position": "styr:led",
                    "organization": "Sv:es skohandl:-förb (SSHF)",
                    "years": "sed 1964"
                }
            ],
            "hobbies": [],
            "honorary_titles": []
        },
        "2": {
            "full_name": "ERIKSSON, FILIP",
            "location": "Umeå",
            "occupation": "bankkamrer",
            "birth_details": {
                "date": "08/03/1929",
                "place": "Holmsund, Västerb l"
            },
            "education": [
                {
                    "degree": "Realex",
                    "year": "1947",
                    "institution": "Umeå"
                },
                {
                    "degree": "hdlssk",
                    "year": "1947",
                    "institution": "Lindgård"
                },
                {
                    "degree": "Sparbkssk",
                    "year": "1958",
                    "institution": "Sthlm"
                }
            ],
            "career": [
                {
                    "position": "anst Västerb l sparbk Umeå",
                    "years": {
                        "start_year": 1948,
                        "end_year": null
                    },
                    "organization": "Umeå"
                },
                {
                    "position": "kamr o ch låneavd",
                    "years": {
                        "start_year": 1963,
                        "end_year": null
                    },
                    "organization": "Umeå"
                },
                {
                    "position": "Kassaförv Västerb :distr SRK",
                    "years": {
                        "start_year": 1962,
                        "end_year": null
                    },
                    "organization": null
                }
            ],
            "family": {
                "spouse": "Elisabeth Skalin",
                "marriage_year": "1964",
                "children": [
                    {
                        "name": "Jonas",
                        "birth_year": "1965"
                    }
                ]
            },
            "publications": [],
            "community_involvement": [
                {
                    "role": "Sportskrib",
                    "organization": "Västerb-Kuriren",
                    "years": "sed 1952-1963"
                },
                {
                    "role": "Sportskrib",
                    "organization": "Västerb Folkbl",
                    "years": "sed 1952-1963"
                }
            ],
            "hobbies": [
                "sport"
            ],
            "honorary_titles": []
        }
    }
}