{
    "original": "ENGESTRÖM, H A BERTIL,\nbankdirektör, Piteå, f i Mönsterås, Kalmar l,\n8/7/13 av bankdir Folke E o Elsa\nRydbeck.\n\nHdlsgymn :ex Hbg 32, res:off:ex 34; anst\nSv hdlsbkn Hässleholm 32, Hbg, Malmö\no Limhamn 35-45, Katrineholm 46,\nhuvudkont Sthlm 46, avd :kont\nKopparberg 50, Hedemora 55, dir Sv hdlsbkn\nPiteå sed 60. - Medl Rotary, Odd\nFellow. - Kapt int :kår res 45. - Hobbies:\ngolf, filateli.\n\nGift 42 m Elsie Claesson f 11, dtr t\nköpm C R C o Ada Johansson. - Barn:\nLars f 43, Gunilla f 45.\n\nENGLÉN, MAINY G B,\nläroverksadjunkt, Sandviken, f i Hofors, Gävleb\nl, 12/3/36 av lokför Axel E o Märta\nÖstberg.\n\nStud:ex Hedemora 57, fil mag Upps 61,\neo adj hal Sala 61, adj gymn Sandviken\nsed 65.\n\nENGLOO, TOR, arkitekt SAR, Gävle,\nf i Sthlm 31/5/06 av byggn:ing\nEngelbrekt Olson o Hedvig Lundgren.\nKTH 28, KKH 33, bitr arkit byggn:styr\n36-46, intend där 47; tf länsarkit Gbgs o\n\nBoh l 45-47, konsult arkit ab\nVatten-byggn:byrån Sthlm 47-56, länsarkit\nGävleb l sed 56. - Utm: RNO.\nGift 45 m Carin Cornell f 23, dtr t\nbankomb:man Birger C o Dora\nBrandberg. - Barn: Ann-Cathrin f 46, Clas\nJohan f 49.\n\nENGLUND,    K     BÖRJE,     ingenjör,\n\nMunksund, f i Nederkalix, Norrb l,\n20/12/26 av Gustav E o Emma Vidgren.\nIng :ex Hässleholms tekn sk 50,\narb:-stud:ing Asea 51, Assi 54, skyddsing\nLKAB 56, ab Bergendahl &amp; Höckert 60,\nutbildn:- o skyddsing SCA sed 61.\n-Ordf Piteå stads traf i ksäkerh :komm sed\n62.\n\nGift 53 m Iris Sandberg f 27. - Barn:\nHåkan f 54, Kjell f 56.\n\n",
    "structured": {
        "0": {
            "full_name": "Engeström, H A Bertil",
            "location": "Piteå",
            "occupation": "bankdirektör",
            "birth_details": {
                "date": "08/07/1913",
                "place": "Mönsterås, Kalmar l",
                "parents": "av bankdir Folke E o Elsa Rydbeck"
            },
            "education": [
                {
                    "degree": "Hdlsgymn",
                    "year": "1932",
                    "institution": "Hbg"
                },
                {
                    "degree": "res:off:ex",
                    "year": "1934"
                }
            ],
            "career": [
                {
                    "position": "anst Sv hdlsbkn Hässleholm",
                    "years": {
                        "start_year": 1932,
                        "end_year": 1932
                    },
                    "organization": "Sv hdlsbkn Hässleholm"
                },
                {
                    "position": "huvudkont Sthlm",
                    "years": {
                        "start_year": 1946,
                        "end_year": 1946
                    }
                },
                {
                    "position": "dir Sv hdlsbkn Piteå",
                    "years": {
                        "start_year": 1960,
                        "end_year": 1960
                    }
                }
            ],
            "family": {
                "spouse": "Elsie Claesson",
                "marriage_year": "1942",
                "children": [
                    {
                        "name": "Lars",
                        "birth_year": "1943"
                    },
                    {
                        "name": "Gunilla",
                        "birth_year": "1945"
                    }
                ]
            },
            "hobbies": [
                "golf",
                "filateli"
            ]
        },
        "1": {
            "full_name": "Englén, Mainy G B",
            "location": "Sandviken",
            "occupation": "läroverksadjunkt",
            "birth_details": {
                "date": "12/03/1936",
                "place": "Hofors, Gävleb l",
                "parents": "av lokför Axel E o Märta Östberg"
            },
            "education": [
                {
                    "degree": "Stud:ex",
                    "year": "1957",
                    "institution": "Hedemora"
                },
                {
                    "degree": "fil mag",
                    "year": "1961",
                    "institution": "Upps"
                }
            ],
            "career": [
                {
                    "position": "eo adj hal",
                    "years": {
                        "start_year": 1961,
                        "end_year": 1961
                    },
                    "organization": "Sala"
                },
                {
                    "position": "adj gymn",
                    "years": {
                        "start_year": 1965
                    },
                    "organization": "Sandviken"
                }
            ],
            "family": {
                "spouse": "NULL",
                "marriage_year": "NULL",
                "children": []
            },
            "hobbies": []
        },
        "2": {
            "full_name": "Engloo, Tor",
            "location": "Gävle",
            "occupation": "arkitekt SAR",
            "birth_details": {
                "date": "31/05/1906",
                "place": "Sthlm",
                "parents": "av byggn:ing Engelbrekt Olson o Hedvig Lundgren"
            },
            "education": [],
            "career": [
                {
                    "position": "bitr arkit byggn:styr",
                    "years": {
                        "start_year": 1936,
                        "end_year": 1946
                    }
                },
                {
                    "position": "intend där",
                    "years": {
                        "start_year": 1947
                    }
                },
                {
                    "position": "länsarkit Gävleb l",
                    "years": {
                        "start_year": 1956
                    }
                }
            ],
            "family": {
                "spouse": "Carin Cornell",
                "marriage_year": "1945",
                "children": [
                    {
                        "name": "Ann-Cathrin",
                        "birth_year": "1946"
                    },
                    {
                        "name": "Clas Johan",
                        "birth_year": "1949"
                    }
                ]
            },
            "hobbies": []
        },
        "3": {
            "full_name": "Englund, K Börje",
            "location": "Munksund",
            "occupation": "ingenjör",
            "birth_details": {
                "date": "20/12/1926",
                "place": "Nederkalix, Norrb l",
                "parents": "av Gustav E o Emma Vidgren"
            },
            "education": [
                {
                    "degree": "Ing",
                    "year": "1950",
                    "institution": "Hässleholms tekn sk"
                }
            ],
            "career": [
                {
                    "position": "arb:-stud:ing",
                    "years": {
                        "start_year": 1951,
                        "end_year": 1951
                    },
                    "organization": "Asea"
                },
                {
                    "position": "skyddsing",
                    "years": {
                        "start_year": 1956,
                        "end_year": 1956
                    },
                    "organization": "LKAB"
                },
                {
                    "position": "utbildn:- o skyddsing",
                    "years": {
                        "start_year": 1961
                    },
                    "organization": "ab Bergendahl & Höckert"
                }
            ],
            "family": {
                "spouse": "Iris Sandberg",
                "marriage_year": "1953",
                "children": [
                    {
                        "name": "Håkan",
                        "birth_year": "1954"
                    },
                    {
                        "name": "Kjell",
                        "birth_year": "1956"
                    }
                ]
            },
            "community_involvement": [
                {
                    "role": "Ordf",
                    "organization": "Piteå stads traf i ksäkerh",
                    "years": "62"
                }
            ],
            "hobbies": []
        }
    }
}