{
    "original": "ELMDAHL, KARL-JOHAN,\nvattenrättsingenjör, Luleå, f i Kalvsvik,\nKronob l, 31/3/17 av kantorn o folkskollär\nKärl E o Annie Nilsson.\nStud:ex Växjö 37, CTH 43, spec:kurs f\nlantbr :ing KLH 46-47; ing P Johansson\ning :byrå Växjö 43-44, h lantbr :ing\nMalmöh, Örebro o Upps l samt lantbr:styr\n45-49, eo o tf lantbr :ing Skellefteå, Upps\no Sthlm 49-51, lantbr:ing Gävleb l\n51-60, vattenr:ing Övre Norrbygd\nvatten-domst Luleå sed 60. - Utm: RNO.\n-Hobbies: segling, skidsport.\nGift 45 m sjuksköt Signe Thenberg f 20,\ndtr t civ :ing Fritz T o Karin Grönblad.\n\n-  Barn: Karin f 46, Birgitta f 47, Ninni\nf 50, Karl Olof f 53.\n\nELMQUIST, CARL-GUSTAV F,\ncivilingenjör, Frösön, f i Flen 25/6/21 av ing\nOlof E o Ruth Sandberg.\nStud:ex Sthlm 41, KTH 46, konsult ing\nAllm ing :byrån ab 46, branding Försäkr\nab Hansa 51, ing VV-verket 53, länsing\nJämtl l sed 60. - Styr:led ab Ekonomi o\nteknik. - Hobby: segling.\nGift 54 m Ann-Marie Johnson. - Barn:\nRagnar f 55.\n\nELMROTH, TORSTEN J A,\ntandläkare, Nordingrå, f i Tierp, Upps l, 12/4/\n33 av landst:man Arthur E o Elsa Alida\nBjörklund.\n\nStud:ex Upps 54, tandl:ex Sthlm 61,\ndistr:tandl Iggesund 61-63, priv:prakt\nNordingrå sed 63. - Hobbies: segling,\nsport.\n\nGift. 60 m dekoratör Margaretha Hjorth\nf 39, dtr t Einar H o Ruth Smedberg.\n-Barn: Anna Catharina f 61, Erik\nVilhelm f 64.\n\nELOFSON, EYVOR, läroverksadjunkt,\n\nSundsvall, f i Borg, Österg l, 4/4/10 av\n\nlärov:adj   Karl   Nordensson   o   Maria\n\nLindhagen.\n\nStud:ex 30, fil mag Sthlm 39, adj i eng\n\no fr Hedbergska sk (hal) Sundsvall sed\n\n49.\n\nGift 46 m lekt, fil dr Olof Elof son fil.\n\n- Barn: Stig f 47, Anders f 49.\n\n",
    "structured": {
        "0": {
            "full_name": "ELMDAHL, KARL-JOHAN",
            "location": "Luleå, Kalvsik, Kronoberg",
            "occupation": "vattenrättsingenjör",
            "birth_details": {
                "date": "31/03/1917",
                "place": "Kalvsvik, Kronob l",
                "parents": "kantorn o folkskollär Kärl E o Annie Nilsson"
            },
            "education": [
                {
                    "degree": "Stud:ex",
                    "year": "1937",
                    "institution": "Växjö"
                },
                {
                    "degree": "CTH",
                    "year": "1943",
                    "institution": "CTH"
                },
                {
                    "degree": "spec:kurs f lantbr :ing",
                    "year": "1946-1947",
                    "institution": "KLH"
                }
            ],
            "career": [
                {
                    "position": "ing P Johansson",
                    "years": {
                        "start_year": 1943,
                        "end_year": 1944
                    },
                    "organization": "ing :byrå Växjö"
                },
                {
                    "position": "h lantbr :ing",
                    "years": {
                        "start_year": 1945,
                        "end_year": 1949
                    },
                    "organization": "Malmöh, Örebro o Upps l samt lantbr:styr"
                },
                {
                    "position": "eo o tf lantbr :ing",
                    "years": {
                        "start_year": 1949,
                        "end_year": 1951
                    },
                    "organization": "Skellefteå, Upps o Sthlm"
                },
                {
                    "position": "lantbr:ing",
                    "years": {
                        "start_year": 1951,
                        "end_year": 1960
                    },
                    "organization": "Gävleb l"
                },
                {
                    "position": "vattenr:ing",
                    "years": {
                        "start_year": 1960
                    },
                    "organization": "Övre Norrbygd vatten-domst Luleå"
                }
            ],
            "family": {
                "spouse": "Signe Thenberg",
                "marriage_year": "1945",
                "children": [
                    {
                        "name": "Karin",
                        "birth_year": "1946"
                    },
                    {
                        "name": "Birgitta",
                        "birth_year": "1947"
                    },
                    {
                        "name": "Ninni",
                        "birth_year": "1950"
                    },
                    {
                        "name": "Karl Olof",
                        "birth_year": "1953"
                    }
                ]
            },
            "hobbies": [
                "segling",
                "skidsport"
            ]
        },
        "1": {
            "full_name": "ELMQUIST, CARL-GUSTAV F",
            "location": "Frösön, Flen",
            "occupation": "civilingenjör",
            "birth_details": {
                "date": "25/06/1921",
                "place": "Flen",
                "parents": "ing Olof E o Ruth Sandberg"
            },
            "education": [
                {
                    "degree": "Stud:ex",
                    "year": "1941",
                    "institution": "Sthlm"
                },
                {
                    "degree": "KTH",
                    "year": "1946",
                    "institution": "KTH"
                }
            ],
            "career": [
                {
                    "position": "konsult ing",
                    "years": {
                        "start_year": 1946
                    },
                    "organization": "Allm ing :byrån ab"
                },
                {
                    "position": "branding",
                    "years": {
                        "start_year": 1951
                    },
                    "organization": "Försäkr ab Hansa"
                },
                {
                    "position": "ing VV-verket",
                    "years": {
                        "start_year": 1953
                    },
                    "organization": "VV-verket"
                },
                {
                    "position": "länsing",
                    "years": {
                        "start_year": 1960
                    },
                    "organization": "Jämtl l"
                }
            ],
            "family": {
                "spouse": "Ann-Marie Johnson",
                "marriage_year": "1954",
                "children": [
                    {
                        "name": "Ragnar",
                        "birth_year": "1955"
                    }
                ]
            },
            "hobbies": [
                "segling"
            ]
        },
        "2": {
            "full_name": "ELMROTH, TORSTEN J A",
            "location": "Nordingrå, Tierp, Uppsala län",
            "occupation": "tandläkare",
            "birth_details": {
                "date": "12/04/1933",
                "place": "Tierp, Uppsala l",
                "parents": "landst:man Arthur E o Elsa Alida Björklund"
            },
            "education": [
                {
                    "degree": "Stud:ex",
                    "year": "1954",
                    "institution": "Uppsala"
                },
                {
                    "degree": "tandl:ex",
                    "year": "1961",
                    "institution": "Sthlm"
                }
            ],
            "career": [
                {
                    "position": "distr:tandl",
                    "years": {
                        "start_year": 1961,
                        "end_year": 1963
                    },
                    "organization": "Iggesund"
                },
                {
                    "position": "priv:prakt",
                    "years": {
                        "start_year": 1963
                    },
                    "organization": "Nordingrå"
                }
            ],
            "family": {
                "spouse": "Margaretha Hjorth",
                "marriage_year": "1960",
                "children": [
                    {
                        "name": "Anna Catharina",
                        "birth_year": "1961"
                    },
                    {
                        "name": "Erik Vilhelm",
                        "birth_year": "1964"
                    }
                ]
            },
            "hobbies": [
                "segling",
                "sport"
            ]
        },
        "3": {
            "full_name": "ELOFSON, EYVOR",
            "location": "Sundsvall, Borg, Östergötlands län",
            "occupation": "läroverksadjunkt",
            "birth_details": {
                "date": "04/04/1910",
                "place": "Borg, Östergötlands län",
                "parents": "lärov:adj Karl Nordensson o Maria Lindhagen"
            },
            "education": [
                {
                    "degree": "Stud:ex",
                    "year": "1930",
                    "institution": "Sthlm"
                },
                {
                    "degree": "fil mag",
                    "year": "1939",
                    "institution": "Sthlm"
                }
            ],
            "career": [
                {
                    "position": "adj i eng o fr",
                    "years": {
                        "start_year": 1949
                    },
                    "organization": "Hedbergska sk (hal) Sundsvall"
                }
            ],
            "family": {
                "spouse": "Olof Elofson",
                "marriage_year": "1946",
                "children": [
                    {
                        "name": "Stig",
                        "birth_year": "1947"
                    },
                    {
                        "name": "Anders",
                        "birth_year": "1949"
                    }
                ]
            }
        }
    }
}