{
    "original": "EDUNG, BO J G, kyrkoherde,\nYtterhogdal, f i Ytterlännäs, Vnorrl l, 16/4/07\nav kyrkoh Carl Gustaf Eriksson o\nElisabet Lidman.\n\nStud:ex 27, teol kand Upps 33, div\nförordn Berg, Långsele, Häggenås o Öster\nsund 34-37, kyrkoadj Tåsjö 37-39, konv\nmin Bodsjö 39-63, kyrkoh Ytterhogdal\nsed 63; tf kyrkoh Gideå 58 o 59, Näs\n59 o 61. - Hobbies: historia, psykologi.\nGift m Barbro Pettersson f 23, dtr t\nhemm:äg Olof P o Anna Hellström.\n-Barn: Dagmar f 49, Karl Gustaf f 51,\nGunnar f 55, Kerstin f 60, Erik f 66.\n\nEDVALL, O GUSTAF, ingenjör,\nBispfors, f i Liden, Vnorrl l, 11/10/18 av\nSven E o Elin Englund.\nIng:ex Stat elektrotekn facksk Västerås\n43, ing Asea 44, inneh Bröd Edvalls el\nbyrå Bispfors sed 44; ämneslär Fors kns\nyrkessk Bispfors. - Led komm:fullm sed\n54, byggn:nd. - Medl FrimO.\nGift 49 m Linnea Adielsson f 21, dtr t\nAlbert A o Anna A. - Barn: Helene\nf 60, Per f 61.\n\nEDWALL, P GUSTAV, konstnär,\nÖstersund, f på Frösön, Jämtl l, 12/8/02 av\nbankdir Alfred E o Karin Jönsdotter.\nKKH 26-32, konststud Rom o Paris,\nJenny Lind-stip 32-33. - Målare,\ngrafiker. - Sep:utst i Sthlm, Gbg, Sundsvall\no Östersund, dels i ett flert saml:utst i\nSv :e o Norge. - Bl utf arb: fondmåln i\nfören:- o församl :hus, ett flert portr.\n-Medl KRO, Konstn:klubben. - Utm:\nKKH:s KanslersM. - Hobby: musik.\n\nEDVALL, HANS-OLA G, ämneslärare,\n\nUmeå, f i Holmsund, Västerb l, 18/4/27\nav sågv :arb Gunnar E o Tora\nLundmark.\n\nStud:ex 47 o folkskollär :ex Umeå 51, eo\nfolkskollär Vännäs landskn 51, eo\näm-neslär Bureå realsk 56, stud :rekt grund-*\nsk högstad Hörnefors 58, ämneslär Umeå\nstads skolor sed 65. - Hobbies: sport,\nbridge.\n\nGift 58 m Aina Hedin f 27, dtr t\nmålarm Axel H o Hilda Andersson.\n-Barn: Karin f 59.\n\n",
    "structured": {
        "0": {
            "full_name": "Bo J G Edung",
            "location": "Ytterhogdal",
            "occupation": "kyrkoherde",
            "birth_details": {
                "date": "16/04/1907",
                "place": "Ytterlännäs",
                "parents": "kyrkoh Carl Gustaf Eriksson o Elisabet Lidman"
            },
            "education": [
                {
                    "degree": "Stud:ex",
                    "year": "1927",
                    "institution": "NULL"
                },
                {
                    "degree": "teol kand",
                    "year": "1933",
                    "institution": "Upps"
                }
            ],
            "career": [
                {
                    "position": "kyrkoadj",
                    "years": {
                        "start_year": 1937,
                        "end_year": 1939
                    },
                    "organization": "Tåsjö"
                },
                {
                    "position": "konv min",
                    "years": {
                        "start_year": 1939,
                        "end_year": 1963
                    },
                    "organization": "Bodsjö"
                },
                {
                    "position": "kyrkoh",
                    "years": {
                        "start_year": 1963,
                        "end_year": "NULL"
                    },
                    "organization": "Ytterhogdal"
                }
            ],
            "family": {
                "spouse": "Barbro Pettersson",
                "marriage_year": "NULL",
                "children": [
                    {
                        "name": "Dagmar",
                        "birth_year": "1949"
                    },
                    {
                        "name": "Karl Gustaf",
                        "birth_year": "1951"
                    },
                    {
                        "name": "Gunnar",
                        "birth_year": "1955"
                    },
                    {
                        "name": "Kerstin",
                        "birth_year": "1960"
                    },
                    {
                        "name": "Erik",
                        "birth_year": "1966"
                    }
                ]
            },
            "hobbies": [
                "historia",
                "psykologi"
            ]
        },
        "1": {
            "full_name": "O Gustaf Edvall",
            "location": "Bispfors",
            "occupation": "ingenjör",
            "birth_details": {
                "date": "11/10/1918",
                "place": "Liden",
                "parents": "Sven E o Elin Englund"
            },
            "education": [
                {
                    "degree": "Ing:ex Stat elektrotekn",
                    "year": "1943",
                    "institution": "facksk Västerås"
                }
            ],
            "career": [
                {
                    "position": "NULL",
                    "years": {
                        "start_year": 1954,
                        "end_year": "NULL"
                    },
                    "organization": "komm:fullm"
                }
            ],
            "family": {
                "spouse": "Linnea Adielsson",
                "marriage_year": "1949",
                "children": [
                    {
                        "name": "Helene",
                        "birth_year": "1960"
                    },
                    {
                        "name": "Per",
                        "birth_year": "1961"
                    }
                ]
            }
        },
        "2": {
            "full_name": "P Gustav Edwall",
            "location": "Östersund",
            "occupation": "konstnär",
            "birth_details": {
                "date": "12/08/1902",
                "place": "Frösön",
                "parents": "bankdir Alfred E o Karin Jönsdotter"
            },
            "education": [
                {
                    "degree": "KKH",
                    "year": "1926-1932",
                    "institution": "NULL"
                }
            ],
            "career": [
                {
                    "position": "Målare",
                    "years": {
                        "start_year": "NULL",
                        "end_year": "NULL"
                    },
                    "organization": "NULL"
                }
            ],
            "hobbies": [
                "musik"
            ]
        },
        "3": {
            "full_name": "Hans-Ola G Edvall",
            "location": "Umeå",
            "occupation": "ämneslärare",
            "birth_details": {
                "date": "18/04/1927",
                "place": "Holmsund",
                "parents": "sågv :arb Gunnar E o Tora Lundmark"
            },
            "education": [
                {
                    "degree": "NULL",
                    "year": "1947",
                    "institution": "NULL"
                },
                {
                    "degree": "eo äm-neslär",
                    "year": "NULL",
                    "institution": "NULL"
                }
            ],
            "career": [
                {
                    "position": "eo folkskollär",
                    "years": {
                        "start_year": 1951,
                        "end_year": "NULL"
                    },
                    "organization": "Vännäs landskn"
                },
                {
                    "position": "eo äm-neslär",
                    "years": {
                        "start_year": 1956,
                        "end_year": "NULL"
                    },
                    "organization": "Bureå realsk"
                },
                {
                    "position": "stud :rekt grundsk högstad",
                    "years": {
                        "start_year": 1958,
                        "end_year": "NULL"
                    },
                    "organization": "Hörnefors"
                },
                {
                    "position": "ämneslär",
                    "years": {
                        "start_year": 1965,
                        "end_year": "NULL"
                    },
                    "organization": "Umeå stads skolor"
                }
            ],
            "family": {
                "spouse": "Aina Hedin",
                "marriage_year": "1958",
                "children": [
                    {
                        "name": "Karin",
                        "birth_year": "1959"
                    }
                ]
            },
            "hobbies": [
                "sport",
                "bridge"
            ]
        }
    }
}