{
    "original": "EDIN, JOHN E, postinspektör,\nSundsvall, f i Nykpg 13/3/14 av distr:ch\nHjalmar E o Lisa Norell.\nStud:ex Sundsvall 33, anst postverket 38,\npostass där 38-46, postdirekt Sundsvall\n46, l:e postass där 48, postmast\nKramfors 50, överkontr postdirekt Sundsvall\n59, postinsp nedre n:a postdistr sed 65.\n- Ordf Hälsingl o Vnorrl sekt av\nPost-tjm:s fören; led Stadsfullm, konstnd o\nskolstyr Kramfors 49-50. - Hobbies:\nkonst, musik, teater.\n\nGift 39 m Ingegärd Wilund f 18, dtr t\nHerman W o Anna Sundquist. - Barn:\nOlle f 41, Göran f 43, Anders f 49.\n\nEDIN, N MAGNUS, adjunkt, Sollefteå,\nf i Åsele, Västerb l, 26/5/32 av kronojäg\nJohan E o småskollär Jenny Rådström.\nStud:ex Umeå 52, fil mag Upps 60, adj\nhal Sollefteå 62, tf rekt sed 66. -\nHobbies: jakt, fiske.\n\nGift m Milly Berglund, dtr t skogvakt\nFrans B o Tekla Wallgren. - Barn: Pär\nf 57, Maria f 61.\n\nEDLING, BERTIL A J, bitr\ntaxeringsintendent, Östersund, f i Bräcke, Jämtl l,\n31/12/15 av disp Per Gustaf E o Anna\nNilsson.\n\nStud:ex Upps 36, jur kand Sthlm 44,\ntingstjg Jämtl ö doms 45-47, anst\nläns-styr Jämtl l 47, eo länsbokh 48, eo tax:-\n\ninsp 52, l:e länsnot 54, bitr tax:intend\nsed 60.\n\nGift 48 m Kerstin Olsson f 18. - Barn:\nAnna f 54.\n\nEDLUND, K ALF R, kyrkoherde,\nDorotea, f i Ramsele, Vnorrl l, 1/11/07 av\nkondit Karl E o Ester Jacobsson.\nTeol kand Upps 34, kommin\nHammerdal 37-53, kyrkoh Dorotea sed 53. - Led\no v ordf barnav:ndn sed 40, led skolstyr\n57-63, ordf Dorotea förs kyrkofullm\nsamt förs :deleg f Dorotea o Risbäcks\nförs sed 66. - Utm: LNO. - Hobbies:\nfiske, tennis.\n\nGift m Runa Bohman, dtr t kontr:prost\nE G B o Isa Stenborg. - Barn: Christer\nf 40, Björn f 42.\n\n",
    "structured": {
        "1": {
            "full_name": "John E Edin",
            "location": "Sundsvall",
            "occupation": "Postinspektör",
            "birth_details": {
                "date": "13/03/1914",
                "place": "Nyköping",
                "parents": "Hjalmar E o Lisa Norell"
            },
            "education": [
                {
                    "degree": "Stud:ex",
                    "year": "1933",
                    "institution": "Sundsvall"
                }
            ],
            "career": [
                {
                    "position": "anst postverket",
                    "years": {
                        "start_year": 1938,
                        "end_year": 1946
                    },
                    "organization": "postass där"
                },
                {
                    "position": "postdirekt Sundsvall",
                    "years": {
                        "start_year": 1946,
                        "end_year": 1948
                    },
                    "organization": "l:e postass där"
                },
                {
                    "position": "postmast",
                    "years": {
                        "start_year": 1950,
                        "end_year": null
                    },
                    "organization": "Kramfors"
                },
                {
                    "position": "överkontr postdirekt Sundsvall",
                    "years": {
                        "start_year": 1959,
                        "end_year": null
                    },
                    "organization": "postinsp nedre n:a postdistr"
                }
            ],
            "family": {
                "spouse": "Ingegärd Wilund",
                "marriage_year": "1939",
                "children": [
                    {
                        "name": "Olle",
                        "birth_year": "1941"
                    },
                    {
                        "name": "Göran",
                        "birth_year": "1943"
                    },
                    {
                        "name": "Anders",
                        "birth_year": "1949"
                    }
                ]
            },
            "hobbies": [
                "konst",
                "musik",
                "teater"
            ]
        },
        "2": {
            "full_name": "N Magnus Edin",
            "location": "Sollefteå",
            "occupation": "Adjunkt",
            "birth_details": {
                "date": "26/05/1932",
                "place": "Åsele, Västerb l",
                "parents": "kronojäg Johan E o småskollär Jenny Rådström"
            },
            "education": [
                {
                    "degree": "Stud:ex",
                    "year": "1952",
                    "institution": "Umeå"
                },
                {
                    "degree": "fil mag",
                    "year": "1960",
                    "institution": "Upps"
                }
            ],
            "career": [
                {
                    "position": "adj hal",
                    "years": {
                        "start_year": 1962,
                        "end_year": null
                    },
                    "organization": "Sollefteå"
                }
            ],
            "family": {
                "spouse": "Milly Berglund",
                "marriage_year": null,
                "children": [
                    {
                        "name": "Pär",
                        "birth_year": "1957"
                    },
                    {
                        "name": "Maria",
                        "birth_year": "1961"
                    }
                ]
            },
            "hobbies": [
                "jakt",
                "fiske"
            ]
        },
        "3": {
            "full_name": "Bertil A J Edling",
            "location": "Östersund",
            "occupation": "bitr taxeringsintendent",
            "birth_details": {
                "date": "31/12/1915",
                "place": "Bräcke, Jämtl l",
                "parents": "disp Per Gustaf E o Anna Nilsson"
            },
            "education": [
                {
                    "degree": "Stud:ex",
                    "year": "1936",
                    "institution": "Upps"
                },
                {
                    "degree": "jur kand",
                    "year": "1944",
                    "institution": "Sthlm"
                }
            ],
            "career": [
                {
                    "position": "tingstjg Jämtl ö doms",
                    "years": {
                        "start_year": 1945,
                        "end_year": 1947
                    },
                    "organization": null
                },
                {
                    "position": "eo länsbokh",
                    "years": {
                        "start_year": 1948,
                        "end_year": null
                    },
                    "organization": null
                },
                {
                    "position": "eo tax:insp",
                    "years": {
                        "start_year": 1952,
                        "end_year": null
                    },
                    "organization": null
                },
                {
                    "position": "l:e länsnot",
                    "years": {
                        "start_year": 1954,
                        "end_year": null
                    },
                    "organization": null
                },
                {
                    "position": "bitr tax:intend",
                    "years": {
                        "start_year": 1960,
                        "end_year": null
                    },
                    "organization": null
                }
            ],
            "family": {
                "spouse": "Kerstin Olsson",
                "marriage_year": "1948",
                "children": [
                    {
                        "name": "Anna",
                        "birth_year": "1954"
                    }
                ]
            },
            "hobbies": null
        },
        "4": {
            "full_name": "K Alf R Edlund",
            "location": "Dorotea",
            "occupation": "Kyrkoherde",
            "birth_details": {
                "date": "01/11/1907",
                "place": "Ramsele, Vnorrl l",
                "parents": "kondit Karl E o Ester Jacobsson"
            },
            "education": [
                {
                    "degree": "Teol kand",
                    "year": "1934",
                    "institution": "Upps"
                }
            ],
            "career": [
                {
                    "position": "kommin",
                    "years": {
                        "start_year": 1937,
                        "end_year": 1953
                    },
                    "organization": "Hammerdal"
                },
                {
                    "position": "kyrkoh",
                    "years": {
                        "start_year": 1953,
                        "end_year": null
                    },
                    "organization": "Dorotea"
                }
            ],
            "family": {
                "spouse": "Runa Bohman",
                "marriage_year": null,
                "children": [
                    {
                        "name": "Christer",
                        "birth_year": "1940"
                    },
                    {
                        "name": "Björn",
                        "birth_year": "1942"
                    }
                ]
            },
            "hobbies": [
                "fiske",
                "tennis"
            ]
        }
    }
}