{
    "original": "EDHOLM,  E   GUNNAR,  verkst\ndirektör, Lidingö, f i Falun .14/8/21  av\nciviling Sten E o Brita Ehrenborg.\nStudrex Sthlm 40, KTH 46, ing ab Sv\nkraftkontoret 47, verkst dir där sed 54.\n- Resroffrex 43, kapt VVK 55. - Medl\nSHT.\nGift 44 m Barbro Hellman f 21, dtr t\n\nbankdir G H o Karin Ljunggren.\n-Barn: Sten f 48, Per f 50, Ulf f 53,\nBjörn f 59.\n\nEDHOLM, PAUL R, leg läkare,\nSolna,  f i Härnösand  3/8/26  av\nfartygs-insp Harald E o Ragnhild Flodin.\nStudrex Sthlm 46, med kand 49, med\nlic 54, med dr o doc 60, underläk kir\navd Köpings las 57, l:e underläk\nrönt-gendiagn avd Karol sjh sed 57. -\nUnderläk  RK:s  sjh  58.\nGift 55 m sjuksköterskan Ingrid\nBurchard f  31.  - Barn:  Sten f  57.\n\nEDHOLM, K STIG, civilingenjör,\nLidingö,   f   i   Västernorrl   l   18/2/16.\nTekn  gymn  Härnösand   37,   KTH  45,\nanst stat väginst Sthlm 51, ch dess\ntra-fiktekn avd sed 60.\n\nGift 46 m Birgit von Sivers f 18.\n-Barn: Anders f 48, Kerstin f 55.\n\nEDIN-SELIN, ULLA M, leg läkare,\nBromma, f i Upps 19/5/20 av prof\nHarald Edin o Ulla Ribbing.\nStudrex Sthlm 40, med kand Upps 44,\nmed lic Sthlm 50, vik aman Allm BB\n47, vik underläk psykiatr avd S:t Eriks\nsjh 48, Sthlms sjukh 48-49, med avd\nSabbatsb sjh 50-53, läk sv sjh Korea\n52-53, l:e underläk med avd Sabbatsb\nsjh 53, läk Sthlms stads pensrhem i v:a\nförorterna sed 61.\n\nGift 53 m med lic Bengt Selin f 24.\n- Barn: Ulla-Britta f 54, Per f 55, Eva\nf 58, Mats f 59.\n\nEDLIND, K A OLA, överingenjör,\nDjursholm, f i Kumla, Örebro l, 14/9/\n15 av montör Axel E o Gerda Olsson.\nStud:ex Örebro 35, CTH 40, anst\nbyggn:firma J Cederblad Örebro 40,\nHallström &amp; Nisses byggn ab\nSundsvall 41, byggn:firma J Cederblad 43,\nab Vägförbättringar Sthlm 45, SIAB\nsed 46. - Led SvTF, SIS, Sthlms\nbyggnr-fören, SVR. - Studrres USA o Mexico\n59. - Hobbies: jakt, fiske, bridge,\ntennis.\n\nGift 41 m Berit Taengh f 16, dtr t\nOscar T o Anna T. - Barn:\nMargareta f 41, Marianne f 42, Kristina f\n44, Anders f 46.\n\n",
    "structured": {
        "0": {
            "full_name": "GUNNAR EDHOLM",
            "location": "Lidingö",
            "occupation": "verkst direktör",
            "birth_details": {
                "date": "14/08/1921",
                "place": "Falun",
                "parents": "civilingenjör Sten E and Brita Ehrenborg"
            },
            "education": [
                {
                    "degree": "Studrex",
                    "year": "1940",
                    "institution": "Sthlm"
                },
                {
                    "degree": "KTH",
                    "year": "1946",
                    "institution": "KTH"
                }
            ],
            "career": [
                {
                    "position": "ing ab Sv kraftkontoret",
                    "years": {
                        "start_year": 1947,
                        "end_year": 1954
                    },
                    "organization": "Sv kraftkontoret"
                },
                {
                    "position": "kapt VVK",
                    "years": {
                        "start_year": 1955,
                        "end_year": 1955
                    }
                }
            ],
            "family": {
                "spouse": "Barbro Hellman",
                "marriage_year": "1944",
                "children": [
                    {
                        "name": "Sten",
                        "birth_year": "1948"
                    },
                    {
                        "name": "Per",
                        "birth_year": "1950"
                    },
                    {
                        "name": "Ulf",
                        "birth_year": "1953"
                    },
                    {
                        "name": "Björn",
                        "birth_year": "1959"
                    }
                ]
            }
        },
        "1": {
            "full_name": "PAUL R. EDHOLM",
            "location": "Solna",
            "occupation": "leg läkare",
            "birth_details": {
                "date": "03/08/1926",
                "place": "Härnösand",
                "parents": "fartygs-inspektör Harald E and Ragnhild Flodin"
            },
            "education": [
                {
                    "degree": "Studrex",
                    "year": "1946",
                    "institution": "Sthlm"
                },
                {
                    "degree": "med kand",
                    "year": "1949",
                    "institution": "med"
                },
                {
                    "degree": "med lic",
                    "year": "1954",
                    "institution": "med"
                },
                {
                    "degree": "med dr o doc",
                    "year": "1960"
                }
            ],
            "career": [
                {
                    "position": "underläk kir avd Köpings las",
                    "years": {
                        "start_year": 1957,
                        "end_year": 1957
                    }
                },
                {
                    "position": "l:e underläk rönt-gendiagn avd Karol sjh",
                    "years": {
                        "start_year": 1957
                    }
                },
                {
                    "position": "Underläk RK:s sjh",
                    "years": {
                        "start_year": 1958
                    }
                }
            ],
            "family": {
                "spouse": "Ingrid Burchard",
                "marriage_year": "1955",
                "children": [
                    {
                        "name": "Sten",
                        "birth_year": "1957"
                    }
                ]
            }
        },
        "2": {
            "full_name": "K. STIG EDHOLM",
            "location": "Lidingö",
            "occupation": "civilingenjör",
            "birth_details": {
                "date": "18/02/1916",
                "place": "Västernorrland"
            },
            "education": [
                {
                    "degree": "Tekn gymn",
                    "year": "1937",
                    "institution": "Härnösand"
                },
                {
                    "degree": "KTH",
                    "year": "1945",
                    "institution": "KTH"
                }
            ],
            "career": [
                {
                    "position": "anst stat väginst Sthlm",
                    "years": {
                        "start_year": 1951
                    },
                    "organization": "stat väginst Sthlm"
                },
                {
                    "position": "ch dess trafiktekn avd",
                    "years": {
                        "start_year": 1960
                    }
                }
            ],
            "family": {
                "spouse": "Birgit von Sivers",
                "marriage_year": "1946",
                "children": [
                    {
                        "name": "Anders",
                        "birth_year": "1948"
                    },
                    {
                        "name": "Kerstin",
                        "birth_year": "1955"
                    }
                ]
            }
        },
        "3": {
            "full_name": "ULLA M. EDIN-SELIN",
            "location": "Bromma",
            "occupation": "leg läkare",
            "birth_details": {
                "date": "19/05/1920",
                "place": "Uppsala",
                "parents": "professor Harald Edin and Ulla Ribbing"
            },
            "education": [
                {
                    "degree": "Studrex",
                    "year": "1940",
                    "institution": "Sthlm"
                },
                {
                    "degree": "med kand",
                    "year": "1944",
                    "institution": "Upps"
                },
                {
                    "degree": "med lic",
                    "year": "1950",
                    "institution": "Sthlm"
                }
            ],
            "career": [
                {
                    "position": "l:e underläk med avd Sabbatsb sjh",
                    "years": {
                        "start_year": 1953
                    },
                    "organization": "Sabbatsb sjh"
                },
                {
                    "position": "läk Sthlms stads pensrhem i v:a förorterna",
                    "years": {
                        "start_year": 1961
                    }
                }
            ],
            "family": {
                "spouse": "Bengt Selin",
                "marriage_year": "1953",
                "children": [
                    {
                        "name": "Ulla-Britta",
                        "birth_year": "1954"
                    },
                    {
                        "name": "Per",
                        "birth_year": "1955"
                    },
                    {
                        "name": "Eva",
                        "birth_year": "1958"
                    },
                    {
                        "name": "Mats",
                        "birth_year": "1959"
                    }
                ]
            }
        },
        "4": {
            "full_name": "K. A. OLA EDLIND",
            "location": "Djursholm",
            "occupation": "överingenjör",
            "birth_details": {
                "date": "14/09/1915",
                "place": "Kumla, Örebro l",
                "parents": "montör Axel E and Gerda Olsson"
            },
            "education": [
                {
                    "degree": "Stud:ex",
                    "year": "1935",
                    "institution": "Örebro"
                },
                {
                    "degree": "CTH",
                    "year": "1940",
                    "institution": "CTH"
                }
            ],
            "career": [
                {
                    "position": "anst byggn:firma J Cederblad Örebro",
                    "years": {
                        "start_year": 1940
                    },
                    "organization": "byggn:firma J Cederblad Örebro"
                },
                {
                    "position": "ab Vägförbättringar Sthlm",
                    "years": {
                        "start_year": 1945
                    }
                },
                {
                    "position": "SIAB",
                    "years": {
                        "start_year": 1946
                    }
                }
            ],
            "family": {
                "spouse": "Berit Taengh",
                "marriage_year": "1941",
                "children": [
                    {
                        "name": "Margareta",
                        "birth_year": "1941"
                    },
                    {
                        "name": "Marianne",
                        "birth_year": "1942"
                    },
                    {
                        "name": "Kristina",
                        "birth_year": "1944"
                    },
                    {
                        "name": "Anders",
                        "birth_year": "1946"
                    }
                ]
            },
            "hobbies": [
                "jakt",
                "fiske",
                "bridge",
                "tennis"
            ]
        }
    }
}