{
    "original": "EIDERING, E EIVIND, v verkst\ndirektör, Sollentuna, f i V Frölunda, Gbgs\no Bohus l, 19/5/19 av hamntjm Eric E\n\n0  Anna Johansson.\n\nStudiex Gbg 39, DHG 44, taxeringsass\nlänsstyr Gbg 44, kamr ab Primus Sthlm\n45, ass t ekon:ch v LME 49, ekon:dir\nab Bahco 51 (styr:suppl), v verkst dir\ndär sed 61. - Stynled ab Bahcos dtrbol\n\n1   Sv:e,   Bahco-Condrup   London,\nför-säkr:bol Ansvar, Ansvar Internat, men&gt;\nber of The Inst of Directors London.\nGift 45 m Ingrid Blomquist f 19, dtr\nt byggmäst Oscar B o Lilly Biörndahl.\n\n-  Barn: Kerstin f 48, Harald f 54, Törd\nf 56, Karin f 60.\n\nEIDHAGEN, O RUNE, apotekare,\ndirektör, Vällingby, f i Forsbacka, Gävleb\nl, 12/9/15 av Oskar E o Anna Maria\nLjungström.\n\nStud:ex Gävle 35, apot:ex 43, tjg å\napot i Gävle, Stensele o Sthlm 35-43,\nvetensk medarb Ciba A/G, Basel i Sv:e\n43, inform:ch Ciba prod ab 47, avd:ch\no dir där 54, v verkst dir sed 60.\n-Stynled Sv.es grossistförb sed 59,\nKronans droghdl ab sed 60, suppl\nhälsov:-ndn sed 60, ordf Repr:fören f utl\nfarmacevt ind:er (RUFI) sed 60.\n-Led Sv läk:sällsk 60, ordf Vällingby\nhögerfören 61, medl Rotary.\n\nGift m Majken Öhrn. - Barn: Marianne\nf 41, Björn t 44, Peter f 52, Susanne\nf 54.\nEINHORN, JERZY, med dr, docent,\n\nDanderyd, f i Czestochowa, Polen, 26/7/\n25 av skräddarmäst Pinkus E o tandläk\nSara Blibaum.\n\nMed lic Sthlm 54, med dr 58, doc i\nradioterapi Karol inst sed 59, vik l:e\nunderläk obstetr-gynekol avd Kalmar\nlas 51, vik 2:e o l:e underläk allm avd\nRadiumhemmet 53, l :e underläk där sed\n54. - Skr i radioterapi o endokrinol.\nGift 49 m med lic Nina Rajmic f 25,\ndtr t rev Artur R o Fanny Wygodzki.\n-Barn: Lena f 54, Stefan f 55.\n\n",
    "structured": {
        "0": {
            "full_name": "E EIVIND EIDERING",
            "location": "Sollentuna",
            "occupation": "verkställande direktör",
            "birth_details": {
                "date": "19/5/1919",
                "place": "V Frölunda, Göteborgs och Bohus län",
                "parents": "Eric E och Anna Johansson"
            },
            "education": [
                {
                    "degree": "Studiex",
                    "year": "1939",
                    "institution": "Gbg"
                },
                {
                    "degree": "DHG",
                    "year": "1944",
                    "institution": "taxeringsass länsstyr Gbg"
                }
            ],
            "career": [
                {
                    "position": "kamr ab Primus",
                    "years": {
                        "start_year": 1945,
                        "end_year": 1945
                    },
                    "organization": "Sthlm"
                },
                {
                    "position": "ass t ekon",
                    "years": {
                        "start_year": 1949,
                        "end_year": 1949
                    },
                    "organization": "LME"
                },
                {
                    "position": "ekon:dir ab Bahco",
                    "years": {
                        "start_year": 1951,
                        "end_year": 1951
                    },
                    "organization": "ab Bahco"
                },
                {
                    "position": "verkst dir ab Bahco",
                    "years": {
                        "start_year": 1961
                    },
                    "organization": "ab Bahco"
                }
            ],
            "family": {
                "spouse": "Ingrid Blomquist",
                "marriage_year": "1945",
                "children": [
                    {
                        "name": "Kerstin",
                        "birth_year": "1948"
                    },
                    {
                        "name": "Harald",
                        "birth_year": "1954"
                    },
                    {
                        "name": "Törd",
                        "birth_year": "1956"
                    },
                    {
                        "name": "Karin",
                        "birth_year": "1960"
                    }
                ]
            }
        },
        "1": {
            "full_name": "O RUNE EIDHAGEN",
            "location": "Vällingby",
            "occupation": "apotekare, verkställande direktör",
            "birth_details": {
                "date": "12/9/1915",
                "place": "Forsbacka, Gävleborgs län",
                "parents": "Oskar E o Anna Maria Ljungström"
            },
            "education": [
                {
                    "degree": "Stud:ex",
                    "year": "1935",
                    "institution": "Gävle"
                },
                {
                    "degree": "apot:ex",
                    "year": "1943",
                    "institution": "Sthlm"
                }
            ],
            "career": [
                {
                    "position": "tjg",
                    "years": {
                        "start_year": 1935,
                        "end_year": 1943
                    },
                    "organization": "apot i Gävle, Stensele o Sthlm"
                },
                {
                    "position": "vetensk medarb",
                    "years": {
                        "start_year": 1943
                    },
                    "organization": "Ciba A/G, Basel i Sv:e"
                },
                {
                    "position": "inform:ch",
                    "years": {
                        "start_year": 1947
                    },
                    "organization": "Ciba prod ab"
                },
                {
                    "position": "avd:ch o dir",
                    "years": {
                        "start_year": 1954
                    },
                    "organization": "Ciba prod ab"
                },
                {
                    "position": "verkst dir",
                    "years": {
                        "start_year": 1960
                    }
                }
            ],
            "family": {
                "spouse": "Majken Öhrn",
                "marriage_year": "NULL",
                "children": [
                    {
                        "name": "Marianne",
                        "birth_year": "1941"
                    },
                    {
                        "name": "Björn",
                        "birth_year": "1944"
                    },
                    {
                        "name": "Peter",
                        "birth_year": "1952"
                    },
                    {
                        "name": "Susanne",
                        "birth_year": "1954"
                    }
                ]
            }
        },
        "2": {
            "full_name": "JERZY EINHORN",
            "location": "Danderyd",
            "occupation": "med dr, docent",
            "birth_details": {
                "date": "26/7/1925",
                "place": "Czestochowa, Polen",
                "parents": "Pinkus E o Sara Blibaum"
            },
            "education": [
                {
                    "degree": "Med lic",
                    "year": "1954",
                    "institution": "Sthlm"
                },
                {
                    "degree": "med dr",
                    "year": "1958",
                    "institution": "Karol inst"
                }
            ],
            "career": [
                {
                    "position": "vik l:e underläk",
                    "years": {
                        "start_year": 1951
                    },
                    "organization": "Kalmar las"
                },
                {
                    "position": "vik 2:e o l:e underläk",
                    "years": {
                        "start_year": 1953
                    },
                    "organization": "Radiumhemmet"
                },
                {
                    "position": "l :e underläk",
                    "years": {
                        "start_year": 1954
                    },
                    "organization": "Radiumhemmet"
                }
            ],
            "family": {
                "spouse": "Nina Rajmic",
                "marriage_year": "1949",
                "children": [
                    {
                        "name": "Lena",
                        "birth_year": "1954"
                    },
                    {
                        "name": "Stefan",
                        "birth_year": "1955"
                    }
                ]
            }
        }
    }
}