{
    "original": "ENWALL, HELMER N V, direktör,\nSthlm, f i Norrkpg 3/3/89.\nDir Konsertbol sed 17, - Presid Assoc\nof European Concert Managers; nöjesch\nSthlmsutst 30. - Utm: RVO, SRKftjt\nGift m Terese Lindgren.\n\nENWALL, SIGNE M, skådespelerska,\nSthlm, f i Sthlm 14/7/99 av\npremieraktören Frans E o skådespelerskan Agda\nMayer.\n\nLyceum f fi, 8 kl, G Jungstedts\nforts:-sk (konst- o litt:historia), Dram teat\nelevsk 18, premiärelev 20, eng Dram\nteat 21-56 o 59-60, Vasateat 59, lär\nDram teat elevsk sed 41. - Medl Sv\nteatrförb. - Bl roller: Nora i Ritten t\nhavet, Dunja i Brott o straff, Agnes i\nSom ni behagar, Lisbet i Erasmus Mon-\n\ntanus, Bondhustrun i Stor-Klas o\nLill-Klas, Fru Kristina i Mäster Olof,\nSvar-modern i Gustav Vasa, Ingeborg\nBodeliv i Lekpaus, Teresa i Sista rummet.\n\nERBACKE, K GUNNAR, direktör,\nSthlm, f i Östersund 19/9/09 av\nhemmansäg Per Olov Eriksson o\nMargareta Karlsson.\n\nStud:ex 37, pol måg Sthlm 45. -\nPoliskonstapel, kriminalkonstapel o tjf\nkriminalöverkonstapel Sthlms stads\npoliskår 31, l:e byråinsp kontrollstyr 46,\ndir Nya systemab sed 54. - Sekr 54\nårs sulfitspritutredn, led 54 års\nbryg-geriutredn, 56 års\nrusdrycksförsäljn:-utredn, 61 års nykterh:lagkomm. - Utm:\nRVOlkl.\n\nGift m Ingrid Kalén f 15, dtr t\ntra-fikinsp Arvid K o Ruth Jerlov. - Barn:\nPer Olov f 43, Pia f 47.\n\nERBING,   A   HARALD,   ingenjör,\nDjursholm,   f   i  Trollhättan   8/1/88   av\nBernhard E o Laura Johannesdotter.\nTekn elem:sk Borås 09, stud Carnegie\nInst of Technology Pittsburgh Pä USA\n11, in’g Nya förenade elektr ab 12, el ab\nEck 16, verkst dir ab Erbings\nmaskinaffär sed 25.\n\nGift 19 m Clara Almlöf, dtr t Hjalmar\nA o Bertha Stiegler. - Barn: Hans f\n20, Elsa-Clara f 21.\n\n",
    "structured": {
        "1": {
            "full_name": "ENWALL, HELMER NATANAEL V",
            "location": "Stockholm",
            "occupation": "direktör",
            "birth_details": {
                "date": "03/03/1889",
                "place": "Norrköping"
            },
            "education": [],
            "career": [
                {
                    "position": "Dir Konsertbol",
                    "years": {
                        "start_year": 1917,
                        "end_year": null
                    },
                    "organization": "Konsertbol"
                },
                {
                    "position": "Presid Assoc of European Concert Managers",
                    "years": {
                        "start_year": null,
                        "end_year": null
                    },
                    "organization": "Assoc of European Concert Managers"
                }
            ],
            "family": {
                "spouse": "Terese Lindgren",
                "marriage_year": null,
                "children": []
            }
        },
        "2": {
            "full_name": "ENWALL, SIGNE M",
            "location": "Stockholm",
            "occupation": "skådespelerska",
            "birth_details": {
                "date": "14/07/1899",
                "place": "Stockholm"
            },
            "education": [
                {
                    "degree": "Lyceum",
                    "year": null,
                    "institution": "Lyceum"
                }
            ],
            "career": [
                {
                    "position": "Dram teat elevsk",
                    "years": {
                        "start_year": 1941,
                        "end_year": null
                    },
                    "organization": "Dram teat elevsk"
                }
            ],
            "family": {
                "spouse": null,
                "marriage_year": null,
                "children": []
            }
        },
        "3": {
            "full_name": "ERBACKE, K GUNNAR",
            "location": "Stockholm",
            "occupation": "direktör",
            "birth_details": {
                "date": "19/09/1909",
                "place": "Östersund"
            },
            "education": [
                {
                    "degree": "Stud:ex",
                    "year": "1937",
                    "institution": "Stud"
                }
            ],
            "career": [
                {
                    "position": "pol måg Sthlm",
                    "years": {
                        "start_year": 1945,
                        "end_year": null
                    },
                    "organization": "pol måg Sthlm"
                },
                {
                    "position": "l:e byråinsp kontrollstyr",
                    "years": {
                        "start_year": 1946,
                        "end_year": null
                    },
                    "organization": "kontrollstyr"
                },
                {
                    "position": "dir Nya systemab",
                    "years": {
                        "start_year": 1954,
                        "end_year": null
                    },
                    "organization": "Nya systemab"
                }
            ],
            "family": {
                "spouse": "Ingrid Kalén",
                "marriage_year": null,
                "children": [
                    {
                        "name": "Per Olov",
                        "birth_year": "1943"
                    },
                    {
                        "name": "Pia",
                        "birth_year": "1947"
                    }
                ]
            }
        },
        "4": {
            "full_name": "ERBING, A HARALD",
            "location": "Djursholm",
            "occupation": "ingenjör",
            "birth_details": {
                "date": "08/01/1888",
                "place": "Trollhättan"
            },
            "education": [
                {
                    "degree": "Tekn elem:sk",
                    "year": "1909",
                    "institution": "Borås"
                }
            ],
            "career": [
                {
                    "position": "verkst dir ab Erbings maskinaffär",
                    "years": {
                        "start_year": 1925,
                        "end_year": null
                    },
                    "organization": "ab Erbings maskinaffär"
                }
            ],
            "family": {
                "spouse": "Clara Almlöf",
                "marriage_year": "1919",
                "children": [
                    {
                        "name": "Hans",
                        "birth_year": "1920"
                    },
                    {
                        "name": "Elsa-Clara",
                        "birth_year": "1921"
                    }
                ]
            }
        }
    }
}