{
    "original": "EHRLUND, BOGUNNAR,\ncivilekonom, Vällingby, f i Eskilstuna 12/6/20\nav disp Rudolf E o Christina\nSöderström.\n\nStud:ex Sthlm 39, DHS 46, anst\nEsselte  ab  40,   ch  org:-avd  där  sed  50.\nGift 45 m Hjördis Thorn f 22. - Barn:\nCatharina f 47, Staffan f 50.\n\nEHRNER, G A GUNNAR, advokat,\nStocksund, f i Sthlm 26/6/20 av kapten\nGustaf E o Frida Rystedt.\n\nStudiex 38, res:off:ex KA 42, jur kand\nStHS 45, tingstjg Ångermani1 s domsaga\nHärnösand 45, asp Svea hovr 48, e fiskal\n49, bitr sekr Sv:s advrsamf 50 (led 53),\nbitr jurist Wetter &amp; Swartling advibyrå\n51, deläg sed 58. - Sekr o kassaförvalt\nJuristfören Sthlm 58.\nGift 46 m Ulk Rabe f 25, dtr t bankdir\nGustaf R o Ellen Richert. - Barn:\nGustaf f 48, Thomas’ f 49, Magnus f 52,\nKerstin f 54.\n\nEHRNST, FREDRIK V, lektor, Sthlm,\nf i Rimbo, Sthlms l, 9/1/06 av lantbr\nGustaf E o Cecilia Sahlberg.\nStud’ex 24, fil mag 28, fil lic 34, fil dr\n39. - Tjg lärov Sthlm 25-35, lektor Sol^\nbacka lärov 38, Östersunds hal 39,\nlektor i matematik Bromma hal sed 47,\nstudierektor Whitlockska samsk 52-54.\n-Ordf Naturvetensk fören Östersund\n40-47, ordf Lektorernas fören 52-54, v ordf\nLärov:lär:s riksförb 52-54, v ordf Fören\nf matematisk-naturvetensk undervisn\n54-60. - Medl FrimO. - Skr: Satser o\nproblem (44), Studieplan i matematik (53),\nMatematik för R bi (55),\nMatematiska uppgifter i studentexamen (57),\nMatematik för R I4-R II4 (58),\nMatematik för R ma (61). - Utm: RNO.\nGift 34 m Gabriella Porshag f 03, dtr\nt dir Hjalmar Gabrielson o Emma\nPers^-son. - Barn: Kristina f 35, Torbjörn\nf 38, Gustav f 41, Anneka f 45.\n\nEICHHORN, HARRY W, arkitekt\nSAR, Bandhagen, f i Järvakandi\n",
    "structured": {
        "0": {
            "full_name": "EHRLUND, BOGUNNAR",
            "location": "Vällingby",
            "occupation": "civilekonom",
            "birth_details": {
                "date": "12/06/1920",
                "place": "Eskilstuna",
                "parents": "av disp Rudolf E o Christina Söderström"
            },
            "education": [
                {
                    "degree": "Stud:ex",
                    "year": "1939",
                    "institution": "Sthlm"
                },
                {
                    "degree": "DHS",
                    "year": "1946",
                    "institution": "ESS AB"
                }
            ],
            "career": [
                {
                    "position": "ch org:-avd",
                    "years": {
                        "start_year": 1950,
                        "end_year": null
                    },
                    "organization": "Esselte AB"
                }
            ],
            "family": {
                "spouse": "Hjördis Thorn",
                "marriage_year": "1945",
                "children": [
                    {
                        "name": "Catharina",
                        "birth_year": "1947"
                    },
                    {
                        "name": "Staffan",
                        "birth_year": "1950"
                    }
                ]
            }
        },
        "1": {
            "full_name": "EHRNER, G A GUNNAR",
            "location": "Stocksund",
            "occupation": "advokat",
            "birth_details": {
                "date": "26/06/1920",
                "place": "Sthlm",
                "parents": "av kapten Gustaf E o Frida Rystedt"
            },
            "education": [
                {
                    "degree": "Studiex",
                    "year": "1938",
                    "institution": "KA"
                },
                {
                    "degree": "jur kand",
                    "year": "1945",
                    "institution": "StHS"
                }
            ],
            "career": [
                {
                    "position": "bitr sekr",
                    "years": {
                        "start_year": 1950,
                        "end_year": null
                    },
                    "organization": "Sv:s advrsamf"
                }
            ],
            "family": {
                "spouse": "Ulk Rabe",
                "marriage_year": "1946",
                "children": [
                    {
                        "name": "Gustaf",
                        "birth_year": "1948"
                    },
                    {
                        "name": "Thomas",
                        "birth_year": "1949"
                    },
                    {
                        "name": "Magnus",
                        "birth_year": "1952"
                    },
                    {
                        "name": "Kerstin",
                        "birth_year": "1954"
                    }
                ]
            }
        },
        "2": {
            "full_name": "EHRNST, FREDRIK V",
            "location": "Sthlm",
            "occupation": "lektor",
            "birth_details": {
                "date": "9/1/1906",
                "place": "Rimbo, Sthlms l",
                "parents": "av lantbr Gustaf E o Cecilia Sahlberg"
            },
            "education": [
                {
                    "degree": "Stud'ex",
                    "year": "1924",
                    "institution": "Sthlm"
                },
                {
                    "degree": "fil mag",
                    "year": "1928",
                    "institution": "NULL"
                },
                {
                    "degree": "fil lic",
                    "year": "1934",
                    "institution": "NULL"
                },
                {
                    "degree": "fil dr",
                    "year": "1939",
                    "institution": "NULL"
                }
            ],
            "career": [
                {
                    "position": "studierektor",
                    "years": {
                        "start_year": 1952,
                        "end_year": 1954
                    },
                    "organization": "Whitlockska samsk"
                }
            ],
            "family": {
                "spouse": "Gabriella Porshag",
                "marriage_year": "1934",
                "children": [
                    {
                        "name": "Kristina",
                        "birth_year": "1935"
                    },
                    {
                        "name": "Torbjörn",
                        "birth_year": "1938"
                    },
                    {
                        "name": "Gustav",
                        "birth_year": "1941"
                    },
                    {
                        "name": "Anneka",
                        "birth_year": "1945"
                    }
                ]
            }
        },
        "3": {
            "full_name": "EICHHORN, HARRY W",
            "location": "Bandhagen",
            "occupation": "arkitekt SAR",
            "birth_details": {
                "date": null,
                "place": "Järvakandi",
                "parents": "NULL"
            },
            "education": [],
            "career": [],
            "family": {
                "spouse": "NULL",
                "marriage_year": "NULL",
                "children": []
            }
        }
    }
}