{
    "original": "ERICSSON, ERIC A, redaktör, Sthlm,\nf i Gävle 12/12/01.\n\nAnst Svres Skyttetidn 24-32, redrsekr Sv\nSkytte 32, red där sed 54.\nGift 35 m May Rosander. - Barn:\nMarie-Louise f 45.\n\nERICSSON, C ERIC, fd direktör,\nBromma, f i Mjölby 28/5/82 av handl\nAlfred E o Hulda Gustafsson.\nHal Linkpg, styrmansex 01, sjökaptrex\n02. - Styrman 02-17, v dir Gbgs stads\nvedbyrå 17-19, Svres redrfören 19-31,\nverkst dir o ordf S Sv:es stuviförb\n31-57, verkst dir Sthlms\nhamnarbrkon-tor 31-57. - Fd ombrman Stenkolsimp\nstatistikkontor. - FK 42-50 (h),\nStadsfullm Gbg 26-31, ord led Sthlms\nhamnstyr 42. - Utm: RNO, RVO. -Hobby:\nmotorbåtssport.\n\nGift 30 m Stina Pehrsson f 00, dtr t\nEdvard P o Olivia Bengtsson. - Barn:\nEric f 31, Per f 40.\n\nERICSON, ERIC G, musikdirektör,\nLidingö, f i Borås 26/10/18 av pastor\nGustaf E o Signe Eriksson.\nHögre organistex Sthlm 41, högre\nkan-torsex 42, musiklär:ex 43, musikstud\nSchweiz (Schola cantorum, Basel),\nEngl o Tyskl, organist o kantor Bromma\nkyrka 43, kantor S:t Jacobs kyrka Sthlm\nsed 49. - Musiklär Palmgrenska samsk\n44-52, ledare Kammarkören sed 45,\nförbrdirig Sthlms körförb o Sv:es\nkör-förb, dirig OD sed 51, kormäst Sv:es\nradio sed 52, lär Musikhögsk sed 53.\nGift 51 m Edda Paulsen f 29, dtr t dr\nphil Sigurd P o Eva Wittera.\n\nERICSON,    ESTRID    M,    direktör,\n\nSthlm, f i Öregrund 16/9/94 av\nkällar-mäst Adolf E o Helga Andersson.\nHKS   18,  utl  stud,   tecknrlär  Hjo   19,\nkonstn medarb  Sv hemslöjd 20, grund\no verkst dir firma Svenskt tenn 24.\n-Delt i ett flert sv o utl utst.\nGift 44  m  sjökapten  Sigfrid  Ericson.\n",
    "structured": {
        "0": {
            "full_name": "ERICSSON, ERIC A",
            "location": "Sthlm",
            "occupation": "redaktör",
            "birth_details": {
                "date": "12/12/1901",
                "place": "Gävle"
            },
            "family": {
                "spouse": "May Rosander",
                "marriage_year": "1935",
                "children": [
                    {
                        "name": "Marie-Louise",
                        "birth_year": "1945"
                    }
                ]
            }
        },
        "1": {
            "full_name": "ERICSSON, C ERIC",
            "location": "Bromma",
            "occupation": "fd direktör",
            "birth_details": {
                "date": "28/05/1882",
                "place": "Mjölby"
            },
            "education": [
                {
                    "degree": "styrmansex",
                    "year": "1901",
                    "institution": "Hal Linkpg"
                },
                {
                    "degree": "sjökaptrex",
                    "year": "1902",
                    "institution": "sjökaptrex"
                }
            ],
            "family": {
                "spouse": "Stina Pehrsson",
                "marriage_year": "1930",
                "children": [
                    {
                        "name": "Eric",
                        "birth_year": "1931"
                    },
                    {
                        "name": "Per",
                        "birth_year": "1940"
                    }
                ]
            },
            "career": [
                {
                    "position": "Styrman",
                    "years": {
                        "start_year": 1902,
                        "end_year": 1917
                    },
                    "organization": "organization"
                },
                {
                    "position": "v dir Gbgs stads vedbyrå",
                    "years": {
                        "start_year": 1917,
                        "end_year": 1919
                    },
                    "organization": "Gbgs stads vedbyrå"
                },
                {
                    "position": "Svres redrfören",
                    "years": {
                        "start_year": 1919,
                        "end_year": 1931
                    },
                    "organization": "Svres redrfören"
                },
                {
                    "position": "verkst dir o ordf S Sv:es stuviförb",
                    "years": {
                        "start_year": 1931,
                        "end_year": 1957
                    },
                    "organization": "S Sv:es stuviförb"
                },
                {
                    "position": "verkst dir Sthlms hamnarbrkon-tor",
                    "years": {
                        "start_year": 1931,
                        "end_year": 1957
                    },
                    "organization": "Sthlms hamnarbrkon-tor"
                }
            ],
            "hobbies": [
                "motorbåtssport"
            ]
        },
        "2": {
            "full_name": "ERICSON, ERIC G",
            "location": "Lidingö",
            "occupation": "musikdirektör",
            "birth_details": {
                "date": "26/10/1918",
                "place": "Borås"
            },
            "education": [
                {
                    "degree": "högre organistex",
                    "year": "1941",
                    "institution": "Sthlm"
                },
                {
                    "degree": "högre kantorsex",
                    "year": "1942",
                    "institution": "Sthlm"
                },
                {
                    "degree": "musiklär:ex",
                    "year": "1943",
                    "institution": "Sthlm"
                }
            ],
            "family": {
                "spouse": "Edda Paulsen",
                "marriage_year": "1951"
            },
            "career": [
                {
                    "position": "organist o kantor Bromma kyrka",
                    "years": {
                        "start_year": 1943
                    },
                    "organization": "Bromma kyrka"
                },
                {
                    "position": "kantor S:t Jacobs kyrka Sthlm",
                    "years": {
                        "start_year": 1949
                    },
                    "organization": "S:t Jacobs kyrka Sthlm"
                }
            ]
        },
        "3": {
            "full_name": "ERICSON, ESTRID M",
            "location": "Sthlm",
            "occupation": "direktör",
            "birth_details": {
                "date": "16/09/1894",
                "place": "Öregrund"
            },
            "education": [
                {
                    "degree": "HKS",
                    "year": "1918",
                    "institution": "Hjo"
                }
            ],
            "family": {
                "spouse": "Sigfrid Ericson",
                "marriage_year": "1944"
            }
        }
    }
}