{
    "original": "Olsson, Lars Olof, tandläkare,\nVästervik, f. 27/4/03 i Norrköping av\ndisp.-K. I. O. o. Hedvig de Trier. G. ^\nm. Mabel Luttropp. Barn: Sten\nBertil f. 30. — Stud:ex. i Västervik 21,\ntandl:kand. 24, tandläk. 26. Praktik\ni Västervik sed. 27.\n\nOhlsson, Oscar Lorenz,\nlänsveterinär, Kalmar, f. 23/6/96 i Borrby, Krist.\n1., av Niils o. Anna O. G. 27 m. Hally\nDahlström. Barn: Jan f. 28, Göran 30,\nStaffan 36. — Studiex. i Malmö 16,\nfil. stud. i Lund 16-17, vet. kand :ex. i\nSthlm 20, vet:ex. 23. Tf. assist, v. stat.\nvet :bakteriol. anst. 25-26, bitr. vet. v.\nmed:styr. 26-27, karantäns-,\nexport-besiktn:- o. importkontr :vet. i\nHaparanda 27-44, distr:vet. där 34-44,\nläns-vet. i Kalm. 1. sed. 45, därjämte förste\nbesiktn :vet. v. kontrollslakt, i Kalmar\nsamt förest f. Kalm. il. södra hush\n:säll-sk. vet:avd. sed. 45. Bataljonsvet. i\nFvk res. 27. I Haparanda bl. a. led.\nav hälsov:nd 27-44, stadsfullm. 32-44,\ndrätselkamm. samt lokalstyr. f. lärov.\nStud ires. m. statsstip. t. Finl. o.\nLeningrad 29, t. Finl. m. statsförordn. 42.\nSkr.: tre mindre avh. i ser. Medd. fr.\nstat. vet :bakterioi. anst. (26 o. 27),\nre-seberätt. i Sv. vet:tidskr. (30). Norrb.\nilstfb ftjSM, FM Fro ben. hum.\n\nOlsson, Margit Gunvor Elisabeth,\ntandläkare, Kalmar, f. 13/12/12 i\nEksjö av Mårten Sandberg o. Hildur\nCarlsson, G. 38 m. tandl. Rune\nOlsson. Barn: Marianne f. 42, Birgit\n44. — Stud:ex. i Eksjö 32, tandl :kand.\n34, tandl. 37. Prakt, i Söderåkra\n38-41, i Torsås 42-47, i Kalmar fr. 48.\n\nOlsson, Nils Edvin, arkitekt SAR,\nGöteborg, f. 10/3/91 i Halmstad av\nbyggm. Olof o. Maria O. G. 14 m.\nEllen Nilsson. Barn: Tore f. 14,\ntextil-ing., disp. f. Willtors Väv., Gbg,\nJan-Erik f. 16, byggn :ing. i fad. firma. —\nStud. v. samsk. o. Malmö tekn. sk.,\nar-kit:ex. v. Polytechn. i Strehtz, TyskL,\n13. Anst. h. arkit. Wåhlin i Lund 08,\narkit. Fredriksson i Malmö 14-15,\narkit :firman Dymling &amp; Nilsson i Gbg\n16-17, arkit. Ernst Torulf 17-19, egen\narkit :verks. sed. 20. Stud. o. res. i\nTyskL, Österr., Ital. o. Frankr. v. uppr.\ntillf. sed. 12. Medl. av ett flert. fören.\nsamt bolags- m. fl. styr. Bl. utf. arb.:\nKungspassagen, Carolus Rex, BJK\n\nkoiit :hus, flera fastigh. m. biogr. ss.\nKaparen, Aveny, Spegeln, Royal,\nPla-za, Viktoria m. fl, Hindàs turisthotell,\nhyreshus, villor i Gbg m. fil. Pristag.\ni fl. tävl. Hoibbies: porträttmåln. o.\n-teckn. Utm. i tennis, allm. idr. m. m.\n\n",
    "structured": {
        "1": {
            "full_name": "Olsson, Lars Olof",
            "location": "Västervik",
            "occupation": "tandläkare",
            "birth_details": {
                "date": "27/04/1903",
                "place": "Norrköping"
            },
            "education": [
                {
                    "degree": "Stud:ex.",
                    "year": "1921",
                    "institution": "Västervik"
                },
                {
                    "degree": "tandl:kand.",
                    "year": "1924",
                    "institution": "tandl."
                }
            ],
            "career": [
                {
                    "position": "Praktik",
                    "years": {
                        "start_year": 1927
                    },
                    "organization": "Västervik"
                }
            ],
            "family": {
                "spouse": "Mabel Luttropp",
                "marriage_year": "NULL",
                "children": [
                    {
                        "name": "Sten Bertil",
                        "birth_year": "1930"
                    }
                ]
            }
        },
        "2": {
            "full_name": "Ohlsson, Oscar Lorenz",
            "location": "Kalmar",
            "occupation": "länsveterinär",
            "birth_details": {
                "date": "23/06/1896",
                "place": "Borrby, Krist. 1."
            },
            "education": [
                {
                    "degree": "Studiex.",
                    "year": "1916",
                    "institution": "Malmö"
                },
                {
                    "degree": "fil. stud.",
                    "year": "1916-1917",
                    "institution": "Lund"
                },
                {
                    "degree": "vet. kand :ex.",
                    "year": "1920",
                    "institution": "Sthlm"
                },
                {
                    "degree": "vet:ex.",
                    "year": "1923",
                    "institution": "NULL"
                }
            ],
            "career": [
                {
                    "position": "Tf. assist, v. stat. vet :bakteriol. anst.",
                    "years": {
                        "start_year": 1925,
                        "end_year": 1926
                    },
                    "organization": "NULL"
                },
                {
                    "position": "bitr. vet. v. med:styr.",
                    "years": {
                        "start_year": 1926,
                        "end_year": 1927
                    },
                    "organization": "NULL"
                },
                {
                    "position": "karantäns-, export-besiktn:- o. importkontr :vet.",
                    "years": {
                        "start_year": 1927,
                        "end_year": 1944
                    },
                    "organization": "Haparanda"
                },
                {
                    "position": "distr:vet.",
                    "years": {
                        "start_year": 1934,
                        "end_year": 1944
                    },
                    "organization": "Haparanda"
                },
                {
                    "position": "läns-vet.",
                    "years": {
                        "start_year": 1945
                    },
                    "organization": "Kalm. 1."
                }
            ],
            "family": {
                "spouse": "Hally Dahlström",
                "marriage_year": "1927",
                "children": [
                    {
                        "name": "Jan",
                        "birth_year": "1928"
                    },
                    {
                        "name": "Göran",
                        "birth_year": "1930"
                    },
                    {
                        "name": "Staffan",
                        "birth_year": "1936"
                    }
                ]
            }
        },
        "3": {
            "full_name": "Olsson, Margit Gunvor Elisabeth",
            "location": "Kalmar",
            "occupation": "tandläkare",
            "birth_details": {
                "date": "13/12/1912",
                "place": "Eksjö"
            },
            "education": [
                {
                    "degree": "Stud:ex.",
                    "year": "1932",
                    "institution": "Eksjö"
                },
                {
                    "degree": "tandl :kand.",
                    "year": "1934",
                    "institution": "NULL"
                },
                {
                    "degree": "tandl.",
                    "year": "1937",
                    "institution": "NULL"
                }
            ],
            "career": [
                {
                    "position": "Prakt,",
                    "years": {
                        "start_year": 1948
                    },
                    "organization": "Kalmar"
                }
            ],
            "family": {
                "spouse": "tandl. Rune Olsson",
                "marriage_year": "1938",
                "children": [
                    {
                        "name": "Marianne",
                        "birth_year": "1942"
                    },
                    {
                        "name": "Birgit",
                        "birth_year": "1944"
                    }
                ]
            }
        },
        "4": {
            "full_name": "Olsson, Nils Edvin",
            "location": "Göteborg",
            "occupation": "arkitekt SAR",
            "birth_details": {
                "date": "10/03/1891",
                "place": "Halmstad"
            },
            "education": [
                {
                    "degree": "NULL",
                    "year": "1914",
                    "institution": "NULL"
                }
            ],
            "career": [
                {
                    "position": "anst. h. arkit. Wåhlin",
                    "years": {
                        "start_year": 1908
                    },
                    "organization": "Lund"
                },
                {
                    "position": "anst. h. arkit. Fredriksson",
                    "years": {
                        "start_year": 1914,
                        "end_year": 1915
                    },
                    "organization": "Malmö"
                },
                {
                    "position": "eget arkit :verks.",
                    "years": {
                        "start_year": 1920
                    },
                    "organization": "NULL"
                }
            ],
            "family": {
                "spouse": "NULL",
                "marriage_year": "NULL",
                "children": [
                    {
                        "name": "Tore",
                        "birth_year": "1914"
                    },
                    {
                        "name": "Jan-Erik",
                        "birth_year": "1916"
                    }
                ]
            }
        }
    }
}