{
    "original": "Olsson, Rune, tandläkare, Kalmar, f.\n19/7/13 i Sundsjö, Jämtl. 1., av rådm.\nCarl O. o. Ehda Nyström. G. 38 m.\ntandl. Margit Sandberg. Barn:\nMarianne f. 42, Birgit 44. — Stud:ex. i\nUmeå 33, tandl :kand. 34, tandläk. 36.\nPraktik i Söderåkra 36-38, i Lyckeby\n38-40, i Torsås 40-47, i Kalmar fr. 48.\n\nOlsson, Nils Sture, läroverksadjunkt,\nVänersborg, f. 12/2/89 i Hälsingborg\nav Nils O. o. Petronella Hiller. G. 22\nm. Amy Karlström. — Stud:ex. i\nHäl-singb. 07, fil. mag. i Lund 13, provår\nv. Gbgs h. real 14. Extralär. i Ystad\n10-11, Halmstad 13, vik. adj. v. Gbgs\nöstra realsk. o. timlär. v. Gbgs h.\nreal 14, extralär. v. Gbgs latin 14-15,\nvik. lektor i Härnösand 15, e. o. adj.\nv. Lunds folksk:sem. 15-19, timlär. v.\nMalmöh. 1. landstings småsk:sem.\n16-19, extralär. i Lund 19-24, timlär.\nv. Lunds priv. 19-24, adj. i matem. o.\nfysik v. Vänersb. h. a. 1. sed. 24. Rev.\nf. Vänersb. stads räkensk. 26-32,\nkassör i styr. f. Vänersb. h. flicklärov.\n32-39, led. av kyrkofullm. sed. 32,\nkyrkoråd sed. 33, stadsfullm. (s) sed.\n35, drätselkamm. 35-39, styr. f. komm.\nflicksk. sed. 39, ordf. i den sistn. sed.\n43. Res. t. Tyskl. o. Frankr. 21, Tyskl.,\nÖsterr. o. Ital. 23, Belg. o. Frankr. 26.\n\nOlsson, Sven Lennart Urban, leg.\nläkare, bat:läk. i Fik, Borås, f. 23/9/16\ni Gbg av förste byråsekr. Gunnar O.\no. Davida Nordeli. G. 44 m.\nGunborg Morin. — Stud :ex. i Sthlm 35,\nmed. kand. där 38 o. med. lic. 42. Vik.\nv. Örebro, Östersunds o. Borås las.\nkir. avd. 43-45 samt v. Örebro o. S :t\nEriks sjukh. i Sthlm gynekol.-obstetr.\navd., andre und :läk. v. Borås las. kir.\navd. 45.\n\nOlson, Tage Nikolaus,\nfängelsedirektör, Jönköping, f. 5/9/85 i Kalmar\nav Per O. o. Anna Johansson. G. 39\nm. Gulli Svanberg. — Mog :ex. 05, off\n:-vol:sk. 05-06, off :kurs 06-07,\nfångv:-styr. utbildn:- o. kompetenssk. h. kurs\n22, stud. v. ol. in- o. uti.\nfån^årds-m. fl. anst.. bl. a. rannsakn :fäng. la\nSante i Paris 25. Anst. i fångvården\n08, e. o. aman. i fångv:styr. 08, rev. o.\nkassör i styr. samt assist, v. ol. fäng.,\nord. fäng:assist. 13, div. förordn. s.\ndir. v. straffäng. i Gävle, Mariestad\no. Linköp., centralfäng. i Norrköp. o.\nMalmö, ord. dir. v. straffäng. i\nJönköp. fr. 28. Hobbies: djur, spec.\nfåglar, friluftsliv, jakt o. fiske. RVO.\n\n",
    "structured": {
        "1": {
            "full_name": "Rune Olsson",
            "location": "Kalmar",
            "occupation": "tandläkare",
            "birth_details": {
                "date": "19/07/1913",
                "place": "Sundsjö, Jämtland"
            },
            "education": [
                {
                    "degree": "Stud:ex.",
                    "year": "1933",
                    "institution": "Umeå"
                },
                {
                    "degree": "tandl :kand.",
                    "year": "1934",
                    "institution": "NULL"
                },
                {
                    "degree": "tandläk.",
                    "year": "1936",
                    "institution": "NULL"
                }
            ],
            "career": [
                {
                    "position": "Praktik",
                    "years": {
                        "start_year": 1936,
                        "end_year": 1938
                    },
                    "organization": "Söderåkra"
                },
                {
                    "position": "Praktik",
                    "years": {
                        "start_year": 1938,
                        "end_year": 1940
                    },
                    "organization": "Lyckeby"
                },
                {
                    "position": "Praktik",
                    "years": {
                        "start_year": 1940,
                        "end_year": 1947
                    },
                    "organization": "Torsås"
                },
                {
                    "position": "Praktik",
                    "years": {
                        "start_year": 1948,
                        "end_year": null
                    },
                    "organization": "Kalmar"
                }
            ],
            "family": {
                "spouse": "tandl. Margit Sandberg",
                "marriage_year": "38",
                "children": [
                    {
                        "name": "Marianne",
                        "birth_year": "42"
                    },
                    {
                        "name": "Birgit",
                        "birth_year": "44"
                    }
                ]
            }
        },
        "2": {
            "full_name": "Nils Sture Olsson",
            "location": "Vänersborg",
            "occupation": "läroverksadjunkt",
            "birth_details": {
                "date": "12/02/1889",
                "place": "Hälsingborg"
            },
            "education": [
                {
                    "degree": "Stud:ex.",
                    "year": "1907",
                    "institution": "Häl-singb."
                },
                {
                    "degree": "fil. mag.",
                    "year": "1913",
                    "institution": "Lund"
                }
            ],
            "career": [
                {
                    "position": "timlär.",
                    "years": {
                        "start_year": 1910,
                        "end_year": 1911
                    },
                    "organization": "Ystad"
                },
                {
                    "position": "vik. adj.",
                    "years": {
                        "start_year": 1913,
                        "end_year": null
                    },
                    "organization": "Halmstad"
                },
                {
                    "position": "vik. lektor",
                    "years": {
                        "start_year": 1914,
                        "end_year": 1915
                    },
                    "organization": "Gbgs östra realsk."
                },
                {
                    "position": "adj.",
                    "years": {
                        "start_year": 1915,
                        "end_year": 1919
                    },
                    "organization": "Lunds folksk:sem."
                },
                {
                    "position": "timlär.",
                    "years": {
                        "start_year": 1916,
                        "end_year": 1919
                    },
                    "organization": "Malmöh. 1. landstings småsk:sem."
                },
                {
                    "position": "adj.",
                    "years": {
                        "start_year": 1919,
                        "end_year": 1924
                    },
                    "organization": "Lund"
                },
                {
                    "position": "adj.",
                    "years": {
                        "start_year": 1919,
                        "end_year": 1924
                    },
                    "organization": "Lunds priv."
                },
                {
                    "position": "adj.",
                    "years": {
                        "start_year": 1924,
                        "end_year": null
                    },
                    "organization": "Vänersb. h. a. 1."
                },
                {
                    "position": "kassör",
                    "years": {
                        "start_year": 1926,
                        "end_year": 1932
                    },
                    "organization": "styr. f. Vänersb. h. flicklärov."
                },
                {
                    "position": "ordf.",
                    "years": {
                        "start_year": 1943,
                        "end_year": null
                    },
                    "organization": "den sistn."
                }
            ],
            "family": {
                "spouse": "Amy Karlström",
                "marriage_year": "22",
                "children": null
            }
        },
        "3": {
            "full_name": "Sven Lennart Urban Olsson",
            "location": "Borås",
            "occupation": "leg. läkare, bat:läk.",
            "birth_details": {
                "date": "23/09/1916",
                "place": "Gbg"
            },
            "education": [
                {
                    "degree": "Stud :ex.",
                    "year": "1935",
                    "institution": "Sthlm"
                },
                {
                    "degree": "med. kand.",
                    "year": "1938",
                    "institution": "där"
                },
                {
                    "degree": "med. lic.",
                    "year": "1942",
                    "institution": "där"
                }
            ],
            "career": [
                {
                    "position": "gynekol.-obstetr. avd.",
                    "years": {
                        "start_year": 1943,
                        "end_year": 1945
                    },
                    "organization": "Örebro, Östersunds o. Borås las. kir. avd."
                },
                {
                    "position": "gynekol.-obstetr. avd.",
                    "years": {
                        "start_year": null,
                        "end_year": null
                    },
                    "organization": "v. Örebro o. S :t Eriks sjukh. i Sthlm"
                },
                {
                    "position": "andre und :läk.",
                    "years": {
                        "start_year": 1945,
                        "end_year": null
                    },
                    "organization": "Borås las. kir. avd."
                }
            ],
            "family": {
                "spouse": "Gunborg Morin",
                "marriage_year": "44",
                "children": null
            }
        },
        "4": {
            "full_name": "Tage Nikolaus Olson",
            "location": "Jönköping",
            "occupation": "fängelsedirektör",
            "birth_details": {
                "date": "5/9/1885",
                "place": "Kalmar"
            },
            "education": [
                {
                    "degree": "Mog :ex.",
                    "year": "1905",
                    "institution": "NULL"
                }
            ],
            "career": [
                {
                    "position": "e. o. aman.",
                    "years": {
                        "start_year": 1908,
                        "end_year": null
                    },
                    "organization": "fångv:styr."
                },
                {
                    "position": "ord. fäng:assist.",
                    "years": {
                        "start_year": 1913,
                        "end_year": null
                    },
                    "organization": "NULL"
                },
                {
                    "position": "ord. dir. v. straffäng.",
                    "years": {
                        "start_year": 1928,
                        "end_year": null
                    },
                    "organization": "Jönköp."
                }
            ],
            "family": {
                "spouse": "Gulli Svanberg",
                "marriage_year": "39",
                "children": null
            },
            "hobbies": [
                "djur",
                "spec. fåglar",
                "friluftsliv",
                "jakt",
                "fiske"
            ],
            "honorary_titles": [
                {
                    "title": "RVO",
                    "institution": "NULL",
                    "year": "NULL"
                }
            ]
        }
    }
}