{
    "original": "Amundson, Alf Amund, major,\nHagalund, f. 14/7/75 i Forsa av överste\nAlbert A. o. Alma Godtknecht. G. 01\nm. Gurli Karlström. Und :löjtn. i\nVaxholms art :kår 97, löjtn. v. kustart. 01,\nkapt. 06, på res:stat 18, major i\nmarinen 19. RSO, RVO, RRS:tAO3kl,\nAIHS.\nAncker, Per Arvid Hjalmar, notarie,\njur. kand., Sthlm, f. 8/8/06 i Sthlm av\nhäradsh. Axel Rudolf A. o. Märta\nAugusta Uggla. G. 35 m. Maria\nHenrika (Ricka) Forne. Barn: Märta\nIngegerd f. 36, Carin Henrika f. 40,\nBritt Estrid f. 41, Sten Arvid f. 43.\nStudrex. i Upps. 26, jur. kand. 32.\nTingstjg, i Västerbergslags doms.\n32-34, tjg. i Sthlms rrt 35 o. i ö. Ä. f.\npolisär. 35, not. där 40. Hobby:\nSkytte,\nAndelius, Margit, skådespelerska,\nSthlm, f. i Göteborg. G. m. Gösta\nRingensson. Barn: Lena f. 24, Leif f.\n28. Genomg. 8-kl. flicksk. o. föret,\nstudieres, t. Engl., Österr., Ryssl. o.\nUngern. Eng. v. Lorensbergsteat. i Gtbg\n16, v. Oscarsteat. i Sthlm 29. Medv. s.\nskådespelerska i ett flert. filmer samt\nofta anlitad av Radioteatern.\nAnden, Eva, advokat, Sthlm, f. i\nUpps. av handl. Heribert A. o. Elin\nForssman. Stud :ex. 06, jur. kand.\nUpps. 12. Tjg. å dom :kansli o. adv\n:-kont. 13-15, adv. i Sthlm, led. av Sv :es\nadv :samf., dess första kvinnl. led., av\nsamf. De nio 40.\nAnderberg, Anton August, konstnär,\nSthlm, f. 2/8/82 i Malmö. Tekn. sk.\ni Malmö, stud. i Tyskl., Schweiz o.\nItal. Delt. i utställn. av Konstfören,\no. andra sammanslutn. samt\nseparat-utst.\nAnderberg, Erik Magnus,\nkommendör, Sthlm, f. 1/1/92 i Sthlm av kamr.\nA. W. A. o. Anna-Eidem-Andersson.\nG. 29 m. Margaretha Lindahl. Barn:\nCarl f. 30, Magnus f. 38. Sjöoff :ex. 12,\nkapt. 21, komm:kapt. 37, kommendör\n42, radiostud. i Paris 19-20, tjg. i\nma-rinst. 23-28 o. 32-34, lär. i\nsjökrigshög-sk. 23-34, marinatt, i Paris o. Haag\n34-37, ch. f. signaltjänstavd. i försv:-\nst. 37-40, fartygsch. å pansarsk.\nSverige 40-41, flaggkapt. å kustfl. 41-43,\nchef f. Sjökrigshögsk. fr. 43. Skr.:\nMaritim förbindelsetjänst und.\nvärldskriget 26, övers. o. redig. sv. uppl. av\nInternationell signalbok 34. RSO 33,\nRNO 41, RVO 31, KNedONOmsv,\nOff-FrHL, LKrVA, LÖS.\nAndersén, Alling Julius, verkst, dir.,\nSthlm, f. 12/4/87 i Laholm av\nmejeristen Hans-Peder A. o. Ingrid Crona.\nG. 13 m. Jenny Mattsson. Eft. avsl.\nskolgång, hand :skola o. språkstud.\npraktik inom järnbr. sed. 04 varav h.\nE. V. Wigforss, Vislanda, 04-06, h. C.\nWeijsenburg &amp; Co., Mora, 07-09, h.\nRundqvist &amp; Schultz, Sthlm, 10, h. A-B\nJulius Slöör, Sthlm, sed. 11, som\nkorrespondent t. 16, som kont :chef t. 19,\nv. verkst, dir. o. led. av styr. 20,\nverkst, dir. sed. 26 o. v. ordf. i styr. F^\n34. Ordf. i styr. f. And. Mattssons\nMek. Verkst. A-B, Mora, ordf. i Sthlms\nJernkramhandl :för., dess styr. o.\npris-komm. sed. 40, led. av Sv :es\nJärn-handl :för :s Centr rförb :s centr :styr.\no. suppl, i dess arbetsutsk. sed. 40, led.\nav Järnhandl :org :s Gar :för :s\n(Handelns Arbetsgiv :org.) styr. sed. 43, led.\nav Sthlms Stads Brandstodsbol :s\növerstyr sed. 37, led. av styr. i\nJärnhandlarnas inköpsorg. A-B Jiko o. dess\nverkst, utsk. sed. 39, led. av\nNyetable-ringsndn sed. 43, medl. av Nationalek.\nFör., Sthlms Köpmansklubb, Sv :es\nGrossistförb., Odd Fellow,\nNeptuniorden, KSSS m. fi. f ören. o. sällskap.\nPatrstGM.\n",
    "structured": {
        "1": {
            "full_name": "Amundson, Alf Amund",
            "location": "Hagalund",
            "occupation": "Major",
            "birth_details": {
                "date": "14/07/1875",
                "place": "Forsa",
                "parents": "Överste Albert A. o. Alma Godtknecht"
            },
            "education": null,
            "career": [
                {
                    "position": "Und :löjtn. i Vaxholms art :kår",
                    "years": {
                        "start_year": 1897,
                        "end_year": 1901
                    },
                    "organization": null
                },
                {
                    "position": "Löjtn. v. kustart.",
                    "years": {
                        "start_year": 1901,
                        "end_year": 1906
                    },
                    "organization": null
                },
                {
                    "position": "Kapt.",
                    "years": {
                        "start_year": 1906,
                        "end_year": 1918
                    },
                    "organization": null
                },
                {
                    "position": "Major i marinen",
                    "years": {
                        "start_year": 1919,
                        "end_year": null
                    },
                    "organization": null
                }
            ],
            "family": {
                "spouse": "Gurli Karlström",
                "marriage_year": "1901",
                "children": null
            }
        },
        "2": {
            "full_name": "Ancker, Per Arvid Hjalmar",
            "location": "Sthlm",
            "occupation": "Notarie, jur. kand.",
            "birth_details": {
                "date": "8/8/1906",
                "place": "Sthlm",
                "parents": "Häradsh. Axel Rudolf A. o. Märta Augusta Uggla"
            },
            "education": [
                {
                    "degree": "Studrex. i Upps.",
                    "year": "1926",
                    "institution": null
                },
                {
                    "degree": "Jur. kand.",
                    "year": "1932",
                    "institution": null
                }
            ],
            "career": [
                {
                    "position": "Tingstjg, i Västerbergslags doms.",
                    "years": {
                        "start_year": 1932,
                        "end_year": 1934
                    },
                    "organization": null
                },
                {
                    "position": "Tjg. i Sthlms rrt",
                    "years": {
                        "start_year": 1935,
                        "end_year": null
                    },
                    "organization": "ö. Ä. f. polisär."
                },
                {
                    "position": "Not. där",
                    "years": {
                        "start_year": 1940,
                        "end_year": null
                    },
                    "organization": null
                }
            ],
            "family": {
                "spouse": "Maria Henrika (Ricka) Forne",
                "marriage_year": "1935",
                "children": [
                    {
                        "name": "Märta Ingegerd",
                        "birth_year": "1936"
                    },
                    {
                        "name": "Carin Henrika",
                        "birth_year": "1940"
                    },
                    {
                        "name": "Britt Estrid",
                        "birth_year": "1941"
                    },
                    {
                        "name": "Sten Arvid",
                        "birth_year": "1943"
                    }
                ]
            }
        },
        "3": {
            "full_name": "Andelius, Margit",
            "location": "Sthlm",
            "occupation": "Skådespelerska",
            "birth_details": null,
            "education": [
                {
                    "degree": "Genomg.",
                    "year": null,
                    "institution": "8-kl. flicksk. o. föret"
                }
            ],
            "career": [
                {
                    "position": "Eng. v. Lorensbergsteat. i Gtbg",
                    "years": {
                        "start_year": 1916,
                        "end_year": null
                    },
                    "organization": null
                },
                {
                    "position": "Eng. v. Oscarsteat. i Sthlm",
                    "years": {
                        "start_year": 1929,
                        "end_year": null
                    },
                    "organization": null
                }
            ],
            "family": {
                "spouse": "Gösta Ringensson",
                "marriage_year": null,
                "children": [
                    {
                        "name": "Lena",
                        "birth_year": "1924"
                    },
                    {
                        "name": "Leif",
                        "birth_year": "1928"
                    }
                ]
            }
        },
        "4": {
            "full_name": "Anden, Eva",
            "location": "Sthlm",
            "occupation": "Advokat",
            "birth_details": null,
            "education": [
                {
                    "degree": "Stud :ex.",
                    "year": "1906",
                    "institution": null
                },
                {
                    "degree": "Jur. kand.",
                    "year": "1912",
                    "institution": "Upps."
                }
            ],
            "career": [
                {
                    "position": "Tjg. å dom :kansli o. adv :kont.",
                    "years": {
                        "start_year": 1913,
                        "end_year": 1915
                    },
                    "organization": null
                },
                {
                    "position": "Adv. i Sthlm",
                    "years": {
                        "start_year": null,
                        "end_year": null
                    },
                    "organization": null
                }
            ],
            "family": {
                "spouse": null,
                "marriage_year": null,
                "children": null
            }
        },
        "5": {
            "full_name": "Anderberg, Anton August",
            "location": "Sthlm",
            "occupation": "Konstnär",
            "birth_details": {
                "date": "2/8/1882",
                "place": "Malmö",
                "parents": null
            },
            "education": null,
            "career": [
                {
                    "position": "Delt. i utställn. av Konstfören",
                    "years": {
                        "start_year": null,
                        "end_year": null
                    },
                    "organization": null
                },
                {
                    "position": "O. andra sammanslutn. samt separat-utst.",
                    "years": {
                        "start_year": null,
                        "end_year": null
                    },
                    "organization": null
                }
            ],
            "family": {
                "spouse": null,
                "marriage_year": null,
                "children": null
            }
        },
        "6": {
            "full_name": "Anderberg, Erik Magnus",
            "location": "Sthlm",
            "occupation": "Kommendör",
            "birth_details": {
                "date": "1/1/1892",
                "place": "Sthlm",
                "parents": "Kamr. A. W. A. o. Anna-Eidem-Andersson"
            },
            "education": null,
            "career": [
                {
                    "position": "Sjöoff :ex.",
                    "years": {
                        "start_year": 1912,
                        "end_year": null
                    },
                    "organization": null
                },
                {
                    "position": "Kapt.",
                    "years": {
                        "start_year": 1921,
                        "end_year": null
                    },
                    "organization": null
                },
                {
                    "position": "Komm:kapt.",
                    "years": {
                        "start_year": 1937,
                        "end_year": null
                    },
                    "organization": null
                },
                {
                    "position": "Kommendör",
                    "years": {
                        "start_year": 1942,
                        "end_year": null
                    },
                    "organization": null
                }
            ],
            "family": {
                "spouse": "Margaretha Lindahl",
                "marriage_year": "1929",
                "children": [
                    {
                        "name": "Carl",
                        "birth_year": "1930"
                    },
                    {
                        "name": "Magnus",
                        "birth_year": "1938"
                    }
                ]
            }
        },
        "7": {
            "full_name": "Andersén, Alling Julius",
            "location": "Sthlm",
            "occupation": "Verkst, dir.",
            "birth_details": {
                "date": "12/4/1887",
                "place": "Laholm",
                "parents": "Mejeristen Hans-Peder A. o. Ingrid Crona"
            },
            "education": null,
            "career": [
                {
                    "position": "Eft. avsl. skolgång, hand :skola o. språkstud.",
                    "years": {
                        "start_year": 1904,
                        "end_year": null
                    },
                    "organization": null
                },
                {
                    "position": "Praktik inom järnbr. sed.",
                    "years": {
                        "start_year": 1904,
                        "end_year": null
                    },
                    "organization": null
                }
            ],
            "family": {
                "spouse": "Jenny Mattsson",
                "marriage_year": "1913",
                "children": null
            }
        }
    }
}