{
    "original": "Ramsten, Enoch Ivar Daniel,\nkyrkoherde, Risinge, f. 30/7/94 i Norrköp.\nav fabr. Adolf Hugo R. o. Anna\nViktoria Carlsson. G. 22 m. Ellen Sophia\nTörnqvist. Barn: Lars f. 24, fil. stud.,\nKarin 26, sjuksköt :elev, Erik 29, stud.,\nAnna 32, stud., Hugo 32, stud., Eva 36.\n—■ Stud:ex. i Norrköp. 14, teol. fil. ex.\n16, teol. kand., prakt. teol. prov o.\npräsitv. f. Linköp. stift 20. Pastorsadj.\ni Risinge 20, past:adj. o. v. kommin. i\nHedvigs förs. i Norrköp. s. å.,\nkyrko-adj. där 21, sjukhuspred. v.\nTrozelli-sjukh. 20-27, kyrkoh. i Risinge sed. 41.\nSekr. i Linköp. stifts ungd :råd 27-37,\nordf. i bestyr, f. ungd :utställn. Vi vill\ni Norrköp. 39.\n\nRamståhl, Sixten Birger Elias,\nfältläkare, Skövde, f. 21/3/98 i Skövde. G.\n25 m. Ingeborg Charlotta Ekman.\nBarn: Louise f. 27, g. m. löjtn. Curt\nRobbert, Gunilla 31. — Stud:ex. i\nSkövde 17, med. kand. i Sthlm 21, med. lic.\ndär 28. Fältläk :stip. 24, e. läk. v. ett\nflert. reg. 24-28, bat :läk. d Fik res.\n28-30, und:läk. v. Jönköp. las. kir. avd.\n28-29, fart :läk. på Sv. Amer. Lin. fart.\nKungsholm 29-30, bat :läk. v. Bohusl.\nreg. 30-33, v. Hall. reg. 33-40, tf.\nlas:-und :läk. i Uddevalla 30, tf. prov :läk.\ni Skövde, Uddevalla o. Håby kort. per.\n28-32 samt i Halmstads distr. o.\ndär-und. tf. bitr. förste prov:läk. i Hall.\n1. årl. kort. per. 33-40, fältläk. v. III.\narméfördeln. resp. III. milo 40-44,\nfältläk. i Fik res. 45, järnv:läk. sed.\n\n40.\tMedl. av Frimurarorden, Odd\nFel-low o. Rotary. RVO.\n\nRand, Thorkild Gustav, civddiinige’nijör,\nLdniköping, f. 25/9/15 på Java., Nedieri.\nInd., av admind’Sitr’atör Card Gustav\nJa-cobise,n o&lt;. VaiHborg Rand. G. 43 m.\nAnne-Miarde Maititd,sisO’n. Barn: Carl\nGuisitav f. 45. — St’ud. v. Eddgenösis.\nTechn. Hochschuk d Zürich 33-37,\ndiploming. där 37. Stud:res. i de\nflesta europ. länd. 32-39. Anst. h.\nChristiani &amp; Nielsen i Köpenhamn 38,\nh. Monherg &amp; Thorsen A-B i Sthlm\n39-40, h. Sv. Aeropl. A-B i Linköp.\nfr. 41. Led. av Sv. tekn:fören.,\nFlyg-tekn. fören. Skr.: upps. i Tekn.\nTid-skr. 42. Hobbies: hist., matem.,\nta-velkonst.\n\n",
    "structured": {
        "1": {
            "full_name": "Ramsten, Enoch Ivar Daniel",
            "location": "Risinge",
            "occupation": "kyrkoherde",
            "birth_details": {
                "date": "30/07/1894",
                "place": "Norrköping"
            },
            "education": [
                {
                    "degree": "Stud:ex.",
                    "year": "1914",
                    "institution": "Norrköp."
                },
                {
                    "degree": "teol. fil. ex.",
                    "year": "1916",
                    "institution": "NULL"
                },
                {
                    "degree": "teol. kand.",
                    "year": "NULL",
                    "institution": "prakt. teol. Linköp. stift 1920"
                }
            ],
            "career": [
                {
                    "position": "Pastorsadj.",
                    "years": {
                        "start_year": 1920,
                        "end_year": 1920
                    },
                    "organization": "Risinge"
                },
                {
                    "position": "past:adj.",
                    "years": {
                        "start_year": 1920,
                        "end_year": 1920
                    },
                    "organization": "Hedvigs förs. Norrköp."
                },
                {
                    "position": "kyrko-adj.",
                    "years": {
                        "start_year": 1921,
                        "end_year": 1921
                    },
                    "organization": "Norroköp."
                },
                {
                    "position": "sjukhuspred.",
                    "years": {
                        "start_year": 1920,
                        "end_year": 1927
                    },
                    "organization": "Trozellisjukh."
                },
                {
                    "position": "kyrkoh.",
                    "years": {
                        "start_year": 1941,
                        "end_year": "NULL"
                    },
                    "organization": "Risinge"
                },
                {
                    "position": "Sekr. i Linköp. stifts ungd",
                    "years": {
                        "start_year": 1927,
                        "end_year": 1937
                    },
                    "organization": "råd"
                },
                {
                    "position": "ordf. i bestyr, f. ungd",
                    "years": {
                        "start_year": "NULL",
                        "end_year": "NULL"
                    },
                    "organization": "Vi vill i Norrköp."
                }
            ],
            "family": {
                "spouse": "Ellen Sophia Törnqvist",
                "marriage_year": "1922",
                "children": [
                    {
                        "name": "Lars",
                        "birth_year": "1924"
                    },
                    {
                        "name": "Karin",
                        "birth_year": "1926"
                    },
                    {
                        "name": "Erik",
                        "birth_year": "1929"
                    },
                    {
                        "name": "Anna",
                        "birth_year": "1932"
                    },
                    {
                        "name": "Hugo",
                        "birth_year": "1932"
                    },
                    {
                        "name": "Eva",
                        "birth_year": "1936"
                    }
                ]
            }
        },
        "2": {
            "full_name": "Ramståhl, Sixten Birger Elias",
            "location": "Skövde",
            "occupation": "fältläkare",
            "birth_details": {
                "date": "21/03/1898",
                "place": "Skövde"
            },
            "education": [
                {
                    "degree": "Stud:ex.",
                    "year": "1917",
                    "institution": "Skövde"
                },
                {
                    "degree": "med. kand.",
                    "year": "1921",
                    "institution": "Sthlm"
                },
                {
                    "degree": "med. lic.",
                    "year": "1928",
                    "institution": "där"
                }
            ],
            "career": [
                {
                    "position": "fältläk :stip.",
                    "years": {
                        "start_year": 1924,
                        "end_year": "NULL"
                    },
                    "organization": "NULL"
                },
                {
                    "position": "e. läk.",
                    "years": {
                        "start_year": 1924,
                        "end_year": 1928
                    },
                    "organization": "flert. reg."
                },
                {
                    "position": "bat :läk.",
                    "years": {
                        "start_year": 1928,
                        "end_year": 1930
                    },
                    "organization": "Fik res."
                },
                {
                    "position": "und:läk.",
                    "years": {
                        "start_year": 1928,
                        "end_year": 1929
                    },
                    "organization": "Jönköp. las. kir. avd."
                },
                {
                    "position": "fart :läk.",
                    "years": {
                        "start_year": 1929,
                        "end_year": 1930
                    },
                    "organization": "Sv. Amer. Lin. Kungsholm"
                },
                {
                    "position": "bat :läk.",
                    "years": {
                        "start_year": 1930,
                        "end_year": 1933
                    },
                    "organization": "Bohusl. reg."
                },
                {
                    "position": "bat :läk.",
                    "years": {
                        "start_year": 1933,
                        "end_year": 1940
                    },
                    "organization": "Hall. reg."
                }
            ],
            "family": {
                "spouse": "Ingeborg Charlotta Ekman",
                "marriage_year": "1925",
                "children": [
                    {
                        "name": "Louise",
                        "birth_year": "1927"
                    },
                    {
                        "name": "Gunilla",
                        "birth_year": "1931"
                    }
                ]
            }
        },
        "3": {
            "full_name": "Rand, Thorkild Gustav",
            "location": "Linköping",
            "occupation": "civddiinige’nijör",
            "birth_details": {
                "date": "25/09/1915",
                "place": "Java., Nedieri. Ind."
            },
            "education": [
                {
                    "degree": "St'ud. v. Eddgenösis.",
                    "year": "NULL",
                    "institution": "Techn. Hochschuk d Zürich 33-37, diplom"
                }
            ],
            "career": [
                {
                    "position": "NULL",
                    "years": {
                        "start_year": "NULL",
                        "end_year": "NULL"
                    },
                    "organization": "NULL"
                }
            ],
            "family": {
                "spouse": "Anne-Miarde Maititd,sisO’n",
                "marriage_year": "1943",
                "children": [
                    {
                        "name": "Carl Guisitav",
                        "birth_year": "1945"
                    }
                ]
            },
            "hobbies": [
                "hist.",
                "matem.",
                "ta-velkonst"
            ]
        }
    }
}