{
    "original": "NUTH, S HILDING G, överingenjör,\nBilldal, f i Dalsbruk, Finl, 15/8/00 av\ngjuterich Gunnar N o Alina Hagman.\nÅbo Sv reallyc 19, Tekn lärov Hfors\n23, gjuteriing Högfors bruk 25,\nKlafre-ströms bruk 29-31, ab Scania-Vabis 39,\nkonsult gjuteriing ab Volvo 45, inneh ab\nGjuteritekn byrån Gbg sed 48. - Styr:led\nSv mekanförb:s gjuteritekn sektion o\nled dess sandforskn:komm samt öl\nstan-dardiser:komm 42-44 o 46-48. - Medl\nOdd Fellow, PB. - Skr: art i fackpr.\n-Hobbies: filateli, fiske, trädg:skötsel.\nGift 29 m Ina Harström, dtr t dir\nWerner H o Ester Sedin. - Barn: Gunvor\nf 31, Leif f 32, Ralph f 42, Ingela f 48.\n\nNYVALL, ENOCH T, direktör, Nybro,\nf i Madesjö, Kalmar l, 22/6/91 av\njärn-handl P A Jonsson o Dora Siltberg.\nVerkst dir ab Enoch Nyvall Nybro sed\n21.  - Led brandstyr.  - Hobbies:\nskönlitteratur, personhistoria, sång, resor.\nGift  18  m  Maja  Ohlsson f 93,  dtr t\nskohandl  P   O   O   o  Alma  Jonsson.\n-Barn: Britt-Marie f 19, Bengt f 23, Hans\nf 25.\n\nNÄRLINGE,   O   MARTIN,   direktör,\n\nLinköping, f i Bollnäs 8/8/09 av\nriksd:-man, godsäg Carl-Gustav N o Karin\nPersson.\n\nFolkhögsk Gugtjärn o Tärna, prakt\nlärov Karlskoga, ch firma\nMalmslätts-trafiken Linköping 29, dir ab\nMalm-slättstrafiken sed 36 (inneh). - Led\nav-talsndn Biltrafikens arb:giv:förb, ordf\nLinkpgs busscentral; medl Odd Fellow.\n-Hobbies: jakt, fiske.\n\nGift 36 m Ingeborg Rydmark, dtr t\nlantbr Ernst R o h h. - Barn:\nBengt-Olof f 39, Birgitta f 44.\nNÄRLINGE, ÅKE C G, direktör,\nLinköping, f i Hedemora 18/10/18 av\nriks-dagsm, godsäg Carl-Gustav N o Karin\nPersson.\n\nWiks folkhögsk 37-38, dir Bil ab Brod\nNärlinge Linkpg sed 46, deläg ab\nMalm-slättstrafiken. - Styr :led byggn :firman\nLe-Wän &amp; Co Sala, ab Byggn :ställningar\nSala, firma Trafikkiosker Linkpg. - Medl\nOdd Fellow. - Hobbies: jakt, fiske,\nskidåkning.\nGift 44 m Beatrice Emernsson, dtr t för-\n\nsäkr:insp Carl E Johansson o h h.\n-Barn: Kristina f 44, Jan f 51, Karin f 53.\n\n",
    "structured": {
        "1": {
            "full_name": "S Hilding G Nuth",
            "location": "Billdal",
            "occupation": "överingenjör",
            "birth_details": {
                "date": "15/08/1900",
                "place": "Dalsbruk, Finland"
            },
            "education": [
                {
                    "degree": "Sv reallyc",
                    "year": "1919",
                    "institution": "Åbo"
                },
                {
                    "degree": "Tekn lärov",
                    "year": "1923",
                    "institution": "Hfors"
                }
            ],
            "career": [
                {
                    "position": "gjuteriing",
                    "years": {
                        "start_year": 1925,
                        "end_year": 1945
                    },
                    "organization": "Högfors bruk, Klafre-ströms bruk, Gjuteritekn byrån Gbg"
                },
                {
                    "position": "konsult gjuteriing",
                    "years": {
                        "start_year": 1945,
                        "end_year": null
                    },
                    "organization": "ab Volvo"
                }
            ],
            "family": {
                "spouse": "Ina Harström",
                "marriage_year": "1929",
                "children": [
                    {
                        "name": "Gunvor",
                        "birth_year": "1931"
                    },
                    {
                        "name": "Leif",
                        "birth_year": "1932"
                    },
                    {
                        "name": "Ralph",
                        "birth_year": "1942"
                    },
                    {
                        "name": "Ingela",
                        "birth_year": "1948"
                    }
                ]
            },
            "hobbies": [
                "filateli",
                "fiske",
                "trädgårdsskötsel"
            ]
        },
        "2": {
            "full_name": "Enoch T Nyvall",
            "location": "Nybro",
            "occupation": "direktör",
            "birth_details": {
                "date": "22/06/1891",
                "place": "Madesjö, Kalmar l"
            },
            "career": [
                {
                    "position": "verkst dir",
                    "years": {
                        "start_year": 1921,
                        "end_year": null
                    },
                    "organization": "ab Enoch Nyvall Nybro"
                }
            ],
            "family": {
                "spouse": "Maja Ohlsson",
                "marriage_year": "1918",
                "children": [
                    {
                        "name": "Britt-Marie",
                        "birth_year": "1919"
                    },
                    {
                        "name": "Bengt",
                        "birth_year": "1923"
                    },
                    {
                        "name": "Hans",
                        "birth_year": "1925"
                    }
                ]
            },
            "hobbies": [
                "skönlitteratur",
                "personhistoria",
                "sång",
                "resor"
            ]
        },
        "3": {
            "full_name": "Martin O Närlinge",
            "location": "Linköping",
            "occupation": "direktör",
            "birth_details": {
                "date": "08/08/1909",
                "place": "Bollnäs"
            },
            "education": [
                {
                    "degree": null,
                    "year": null,
                    "institution": "Folkhögsk Gugtjärn o Tärna, Karlskoga"
                }
            ],
            "career": [
                {
                    "position": "prakt lärov",
                    "years": {
                        "start_year": 1929,
                        "end_year": null
                    },
                    "organization": "Malmslätts-trafiken Linköping"
                },
                {
                    "position": "dir",
                    "years": {
                        "start_year": 1936,
                        "end_year": null
                    },
                    "organization": "ab Malm-slättstrafiken"
                }
            ],
            "family": {
                "spouse": "Ingeborg Rydmark",
                "marriage_year": "1936",
                "children": [
                    {
                        "name": "Bengt-Olof",
                        "birth_year": "1939"
                    },
                    {
                        "name": "Birgitta",
                        "birth_year": "1944"
                    }
                ]
            },
            "hobbies": [
                "jakt",
                "fiske"
            ]
        },
        "4": {
            "full_name": "Åke C G Närlinge",
            "location": "Linköping",
            "occupation": "direktör",
            "birth_details": {
                "date": "18/10/1918",
                "place": "Hedemora"
            },
            "education": [
                {
                    "degree": null,
                    "year": "1937-1938",
                    "institution": "Wiks folkhögsk"
                }
            ],
            "career": [
                {
                    "position": "dir",
                    "years": {
                        "start_year": 1946,
                        "end_year": null
                    },
                    "organization": "Bil ab Brod Närlinge Linkpg"
                }
            ],
            "family": {
                "spouse": "Beatrice Emernsson",
                "marriage_year": "1944",
                "children": [
                    {
                        "name": "Kristina",
                        "birth_year": "1944"
                    },
                    {
                        "name": "Jan",
                        "birth_year": "1951"
                    },
                    {
                        "name": "Karin",
                        "birth_year": "1953"
                    }
                ]
            },
            "hobbies": [
                "jakt",
                "fiske",
                "skidåkning"
            ]
        }
    }
}