{
    "original": "Norrköping, f i Ystad 1/8/27 av elektr Per N\no Olivia Lundh.\n\nKTH 60, lab :ch Holmens bruks o fabr\nab Norrkpg.\n\nGift 51 m Britta Fredrikson, dtr t\nkassör Isac F o Stina Lundberg. - Barn:\nHåkan f 55, Magnus f 60.\n\nNORÉN, OLOF J T, tandläkare,\nBorås, f i Borås 16/3/09 av ing Iwar N o\nLydia Eriksson.\n\nStud:ex Borås 28, med kand Lund 32,\ntandl:ex Sthlm 35, ass:tandl Sthlm 35,\npriv:prakt Borås sed 36. - Hobby: jakt.\n\nGift 1) 38 m Ruth Blomberg £ 13, 2) 58\nm Brita Johansson f 27. - Barn: i l :a akt\nAnn-Marie f 38, Karl-Erik f 42, Bertil\nf 43, i 2:a akt Carin f 60.\n\nNORÉN, C STIG, generalmajor, Gbg,\nf i Sthlm 10/5/08 av kommendörkapt\nKarl N o Marianne af Sillen.\nStud:ex Gbg 27, fänr flottan 30,\nflygut-bildn 32-33, löjtn FV 36, kapt 40, major\n44, öv :löjtn 47, överste 51, gen :ma jör\nFV 60. - FKHS stabskurs 42-43, ch\nflygstab op:avd 47-49, ch F 7 50-57, insp\nluftbevakn 57-60, ch flygstaben 60-64,\nE l sed 64. - LKrVA 48. - Utm:\nKSO-Ikl, RVO, KNS:tOO.\nGift 35 m Ulla Nordenson f 10, dtr t dr\nGöran N o Märta Bagge. - Barn: Märta\nf 38, Ebba f 39.\n\nNORÉN, C TORE, tandläkare,\nOskarshamn, f i Högdal, Gbgs o Bohus l,\n19/9/29 av kontr:prost Nils N o\nMaja-Lisa Nanne.\n\nStud:ex Uddevalla 48, tandl:ex Sthlm 53,\ndistr :tandl o förest distr :tandpoliklin\nFlen 54-57, l:e distr:tandl Oskarshamn\n57-59, priv :prakt där sed 59.\nGift 52 m receptarie Barbro Fogelin\nf 29, dtr t distr :vet Herman F o Lisa\nÅgren. - Barn: Carl f 56, Kajsa f 60.\n\nNORÉN, ULF T, hovrättsråd,\nJönköping, f i Vetlanda 9/7/10 av landsfiskal\nJohn N o Emilia Andersson.\nStud:ex Eksjö 30, jur kand Upps 34,\ntingstjg 34-37, fiskal Göta hovr 38,\ndoms :sekr 40-44, adj led Göta hovr 44,\nassess 47, tf rev:sekr 48 o 50-53, tjg\njordbr:dep rättsavd 49-50, hovr:råd\nGöta hovr sed 53. - Utm: RNO.\nGift 37-55 m Inga Nylin f 06, dtr t fabr\nF N o Alma Åberg. - Barn: Björn f 39,\nAlvar f 43.\n\n",
    "structured": {
        "0": {
            "full_name": "NORÉN, OLOF J T",
            "location": "Borås",
            "occupation": "tandläkare",
            "birth_details": {
                "date": "16/03/1909",
                "place": "Borås",
                "parents": "ing Iwar N o Lydia Eriksson"
            },
            "education": [
                {
                    "degree": "Stud:ex",
                    "year": "1928",
                    "institution": "Borås"
                },
                {
                    "degree": "med kand",
                    "year": "1932",
                    "institution": "Lund"
                },
                {
                    "degree": "tandl:ex",
                    "year": "1935",
                    "institution": "Sthlm"
                }
            ],
            "career": [
                {
                    "position": "ass:tandl",
                    "years": {
                        "start_year": 1935,
                        "end_year": 1936
                    },
                    "organization": "Sthlm"
                },
                {
                    "position": "priv:prakt",
                    "years": {
                        "start_year": 1936
                    },
                    "organization": "Borås"
                }
            ],
            "family": {
                "spouse": "Ruth Blomberg",
                "marriage_year": "1938",
                "children": [
                    {
                        "name": "Ann-Marie",
                        "birth_year": "1938"
                    },
                    {
                        "name": "Karl-Erik",
                        "birth_year": "1942"
                    },
                    {
                        "name": "Bertil",
                        "birth_year": "1943"
                    }
                ]
            }
        },
        "1": {
            "full_name": "NORÉN, C STIG",
            "location": "Gbg",
            "occupation": "generalmajor",
            "birth_details": {
                "date": "10/05/1908",
                "place": "Sthlm",
                "parents": "kommendörkapt Karl N o Marianne af Sillen"
            },
            "education": [
                {
                    "degree": "Stud:ex",
                    "year": "1927",
                    "institution": "Gbg"
                }
            ],
            "career": [
                {
                    "position": "fänr flottan",
                    "years": {
                        "start_year": 1930
                    }
                },
                {
                    "position": "flygut-bildn",
                    "years": {
                        "start_year": 1932,
                        "end_year": 1933
                    }
                },
                {
                    "position": "löjtn FV",
                    "years": {
                        "start_year": 1936
                    }
                },
                {
                    "position": "kapt",
                    "years": {
                        "start_year": 1940
                    }
                },
                {
                    "position": "major",
                    "years": {
                        "start_year": 1944
                    }
                },
                {
                    "position": "öv :löjtn",
                    "years": {
                        "start_year": 1947
                    }
                },
                {
                    "position": "överste",
                    "years": {
                        "start_year": 1951
                    }
                },
                {
                    "position": "gen :ma jör FV",
                    "years": {
                        "start_year": 1960
                    }
                }
            ],
            "family": {
                "spouse": "Ulla Nordenson",
                "marriage_year": "1935",
                "children": [
                    {
                        "name": "Märta",
                        "birth_year": "1938"
                    },
                    {
                        "name": "Ebba",
                        "birth_year": "1939"
                    }
                ]
            }
        },
        "2": {
            "full_name": "NORÉN, C TORE",
            "location": "Oskarshamn",
            "occupation": "tandläkare",
            "birth_details": {
                "date": "19/09/1929",
                "place": "Högdal, Gbgs o Bohus l",
                "parents": "kontr:prost Nils N o Maja-Lisa Nanne"
            },
            "education": [
                {
                    "degree": "Stud:ex",
                    "year": "1948",
                    "institution": "Uddevalla"
                },
                {
                    "degree": "tandl:ex",
                    "year": "1953",
                    "institution": "Sthlm"
                }
            ],
            "career": [
                {
                    "position": "distr :tandl o förest distr :tandpoliklin",
                    "years": {
                        "start_year": 1954,
                        "end_year": 1957
                    },
                    "organization": "Flen"
                },
                {
                    "position": "l:e distr:tandl",
                    "years": {
                        "start_year": 1957
                    },
                    "organization": "Oskarshamn"
                }
            ],
            "family": {
                "spouse": "Barbro Fogelin",
                "marriage_year": "1952",
                "children": [
                    {
                        "name": "Carl",
                        "birth_year": "1956"
                    },
                    {
                        "name": "Kajsa",
                        "birth_year": "1960"
                    }
                ]
            }
        },
        "3": {
            "full_name": "NORÉN, ULF T",
            "location": "Jönköping",
            "occupation": "hovrättsråd",
            "birth_details": {
                "date": "09/07/1910",
                "place": "Vetlanda",
                "parents": "landsfiskal John N o Emilia Andersson"
            },
            "education": [
                {
                    "degree": "Stud:ex",
                    "year": "1930",
                    "institution": "Eksjö"
                },
                {
                    "degree": "jur kand",
                    "year": "1934",
                    "institution": "Upps"
                }
            ],
            "career": [
                {
                    "position": "tingstjg",
                    "years": {
                        "start_year": 1934,
                        "end_year": 1937
                    }
                },
                {
                    "position": "fiskal",
                    "years": {
                        "start_year": 1938
                    },
                    "organization": "Göta hovr"
                },
                {
                    "position": "doms :sekr",
                    "years": {
                        "start_year": 1940,
                        "end_year": 1944
                    }
                },
                {
                    "position": "adj led",
                    "years": {
                        "start_year": 1944
                    },
                    "organization": "Göta hovr"
                },
                {
                    "position": "assess",
                    "years": {
                        "start_year": 1947
                    }
                }
            ],
            "family": {
                "spouse": "Inga Nylin",
                "marriage_year": "1937",
                "children": [
                    {
                        "name": "Björn",
                        "birth_year": "1939"
                    },
                    {
                        "name": "Alvar",
                        "birth_year": "1943"
                    }
                ]
            }
        }
    }
}