{
    "original": "NILSON, FRITZ O, bankdirektör,\nStrömstad, f i Strömstad 30/6/07 av\nsjö-kapt Oscar N o Anette Nordbye.\nAnst Gbgs hdlsbk 26, kamr o\nkont:-förest S Unnaryd 35, Gravarne 39,\nStrömstad 40, dir Skand bkn Strömstad\nsed 62. - Verkst dlr ab Laholmen,\nstyr:-ordf ab Lerviks konservfabr. - M-edl\nRo-tary, suppl Sv Rotaryrådet. - Utm: Da,\nNo o Sv roddförb GM, Finl roddförb\nftjtG.\n\nGift 35 m Lillie Uddgren f 05, dtr t\njv:-tjm Gustaf U o Annie Collander.\n\nNILSON, K G GEORG, direktör, Kisa,\nf i Fullösa, Skarab l, 7/12/00 av jv:tjm\nKarl N o Karolina Månsson.\nAffärsanst 15-30, insp Gbgs köpm :f ören\n30-48, anst Bäckhammars bruks ab 48,\nverkst dir där 50-58, konsult verksamh\nGbg 58-63, verkst dir ab Långasjönäs\npappersbruk sed 64. - Styr :led\nCellva-bruken ab. - Medl Odd Fellow.\nGift 28 m Ebba Wallström f 03, dtr t\nAlfred W o Kristina W. - Barn:\nBengt-Georg f 32.\n\nNILSSON, GERT V, direktör, Gbg, f\ni Gbg 22/3/22 av dir Josef N o\nMagnhild Mårtensson.\n\nStud:ex 43, res:off:ex KSS 46, fackk\nGbgHdlI 47, försäkr:insp Fylgia 48, anst\nGaranti- &amp; nattvakt ab sed 50 (inneh\n53-60), verkst dir Västsv vakt ab sed 50\n(styr:led). - Led tax:nd. - Medl\nColdinu-O. - Hobbies: konst, fiske.\nGift 47 m Bittemor Willaume f 22, dtr\nt dir Fridolf W o Zonia Lundin. - Barn:\nLillebitt f 48, Katarina f 52, Liselott\nf 56.\n\nNILSSON, GUNNAR E P G, fd\nprovinsialläkare, Lenhovda, f i Långasjö,\nKronob l, 17/5/94 av handl Frans N o\nNanny Pontén.\n\nStud:ex Växjö 14, med kand 18 o med\nlic Lund 24, öl läk:förordn 24-27, e\nprov :läk Lenhovda distr 28-38,\nsjukstu-guläk 28 o pro v :läk Lenhovda distr\n38-58. - Ordf Första Majblomman sed 29,\nLenhovda hembygdsfören sed 41,\nRK-krets 58-59, komm:fullm sed 42, omb f\nriksantikv:ämb sed 42. - Skr: utg\nHälso-o sjukvård, Om torp o backstugor,\nVäxtnamn i folkspråket, Hembygdförening\n— Kulturcentrum. - Utm: RNO,\nSRK-ftjt, Samf f hemb :vård plak.\nGift 31 m Tullan Granqvist f 06, dtr t\nlandsfisk Carl Axel G o Elin Bergman.\n- Barn: Per Gunnar f 32.\n\n",
    "structured": {
        "0": {
            "full_name": "NILSON, FRITZ O",
            "location": "Strömstad",
            "occupation": "bankdirektör",
            "birth_details": {
                "date": "30/06/1907",
                "place": "Strömstad",
                "parents": "sjö-kapt Oscar N o Anette Nordbye"
            },
            "education": [],
            "career": [
                {
                    "position": "anst Gbgs hdlsbk",
                    "years": {
                        "start_year": 1926,
                        "end_year": 1926
                    },
                    "organization": "Gbgs hdlsbk"
                },
                {
                    "position": "kamr o kont:-förest S Unnaryd",
                    "years": {
                        "start_year": 1935,
                        "end_year": 1935
                    },
                    "organization": "S Unnaryd"
                },
                {
                    "position": "Gravarne",
                    "years": {
                        "start_year": 1939,
                        "end_year": 1939
                    },
                    "organization": "Gravarne"
                },
                {
                    "position": "dir Skand bkn Strömstad",
                    "years": {
                        "start_year": 1962,
                        "end_year": null
                    },
                    "organization": "Skand bkn Strömstad"
                }
            ],
            "family": {
                "spouse": "Lillie Uddgren",
                "marriage_year": "1935",
                "children": []
            }
        },
        "1": {
            "full_name": "NILSON, K G GEORG",
            "location": "Kisa",
            "occupation": "direktör",
            "birth_details": {
                "date": "07/12/1900",
                "place": "Fullösa, Skarab L"
            },
            "education": [],
            "career": [
                {
                    "position": "insp Gbgs köpm :f ören",
                    "years": {
                        "start_year": 1930,
                        "end_year": 1948
                    },
                    "organization": "Gbgs köpm :f ören"
                },
                {
                    "position": "anst Bäckhammars bruks ab",
                    "years": {
                        "start_year": 1948,
                        "end_year": null
                    },
                    "organization": "Bäckhammars bruks ab"
                },
                {
                    "position": "verkst dir ab Långasjönäs pappersbruk",
                    "years": {
                        "start_year": 1950,
                        "end_year": 1958
                    },
                    "organization": "ab Långasjönäs pappersbruk"
                }
            ],
            "family": {
                "spouse": "Ebba Wallström",
                "marriage_year": "1928",
                "children": [
                    {
                        "name": "Bengt-Georg",
                        "birth_year": "1932"
                    }
                ]
            }
        },
        "2": {
            "full_name": "NILSSON, GERT V",
            "location": "Gbg",
            "occupation": "direktör",
            "birth_details": {
                "date": "22/03/1922",
                "place": "Gbg",
                "parents": "dir Josef N o Magnhild Mårtensson"
            },
            "education": [],
            "career": [
                {
                    "position": "fackk GbgHdlI",
                    "years": {
                        "start_year": 1947,
                        "end_year": 1948
                    },
                    "organization": "GbgHdlI"
                },
                {
                    "position": "anst Garanti- & nattvakt ab",
                    "years": {
                        "start_year": 1950,
                        "end_year": null
                    },
                    "organization": "Garanti- & nattvakt ab"
                },
                {
                    "position": "verkst dir Västsv vakt ab",
                    "years": {
                        "start_year": 1950,
                        "end_year": null
                    },
                    "organization": "Västsv vakt ab"
                }
            ],
            "family": {
                "spouse": "Bittemor Willaume",
                "marriage_year": "1947",
                "children": [
                    {
                        "name": "Lillebitt",
                        "birth_year": "1948"
                    },
                    {
                        "name": "Katarina",
                        "birth_year": "1952"
                    },
                    {
                        "name": "Liselott",
                        "birth_year": "1956"
                    }
                ]
            },
            "hobbies": [
                "konst",
                "fiske"
            ]
        },
        "3": {
            "full_name": "NILSSON, GUNNAR E P G",
            "location": "Lenhovda",
            "occupation": "fd provinsialläkare",
            "birth_details": {
                "date": "17/05/1894",
                "place": "Långasjö, Kronob l",
                "parents": "handl Frans N o Nanny Pontén"
            },
            "education": [
                {
                    "degree": "Stud",
                    "year": "1914",
                    "institution": "Växjö"
                },
                {
                    "degree": "med kand",
                    "year": "1918",
                    "institution": "Lund"
                }
            ],
            "career": [
                {
                    "position": "e prov :läk Lenhovda distr",
                    "years": {
                        "start_year": 1928,
                        "end_year": 1958
                    },
                    "organization": "Lenhovda distr"
                }
            ],
            "family": {
                "spouse": "Tullan Granqvist",
                "marriage_year": "1931",
                "children": [
                    {
                        "name": "Per Gunnar",
                        "birth_year": "1932"
                    }
                ]
            },
            "publications": [
                {
                    "title": "Hälso-o sjukvård",
                    "year": null,
                    "type": null
                },
                {
                    "title": "Om torp o backstugor",
                    "year": null,
                    "type": null
                },
                {
                    "title": "Växtnamn i folkspråket",
                    "year": null,
                    "type": null
                },
                {
                    "title": "Hembygdförening—Kulturcentrum",
                    "year": null,
                    "type": null
                }
            ],
            "community_involvement": [
                {
                    "role": "Ordf",
                    "organization": "Första Majblomman",
                    "years": "sed 1929"
                },
                {
                    "role": "ordf",
                    "organization": "Lenhovda hembygdsfören",
                    "years": "sed 1941"
                }
            ],
            "honorary_titles": [
                {
                    "title": "RNO",
                    "institution": null,
                    "year": null
                },
                {
                    "title": "SRK-ftjt",
                    "institution": null,
                    "year": null
                },
                {
                    "title": "Samf f hemb :vård plak",
                    "institution": null,
                    "year": null
                }
            ],
            "hobbies": []
        }
    }
}