{
    "original": "NORSTRÖM, N GUNNAR A,\ncivilförsvarsdirektör, Jönköping, f i Saleby,\nSkarab l, 10/4/02 av lantbr Karl-Axel N\no Ellen Ekelund.\n\nRealex Skara 18, landsfisk:ex 25, FHS\n58; landsfisk:tjg öl distr 26-34, landsfisk\nÅrjäng 34-46, Rönneberg 47-52,\ncivil-försv:dir Jönkpgs l sed 53. - Medl\nRo-tary. - Utm: RNO, HVII:sFrK, SCFSM.\n- Hobby: ornitologi.\n\nGift 29 m Dagny Pettersson f 06, dtr t\nstat :f orm Erik P o Elvira Andersson.\n-Barn: Lennart f 32, Bertil f 36.\n\nNORSTRÖM,   J   TAGE   L,   ingenjör,\n\nGbg, f i Väse, Värml l, 9/9/23 av lantbr\nOscar N o Anhild Eriksson.\nRealex 42, hdlsutbildn 43, ing:ex STI 47,\nspec :stud i nät :ekon o soc:pol Sthlms\nuniv 55-56.  - Ing ab Armerad betong\n\nÖrebro 47, byggn :avd Borås Wäfveri ab\nBorås 48, bitr sekr stat nd f\nbyggn:-forskn 54, utredn :man dess FU 55,\nfastigh :ing Skand bkn Gbg 56, fastigh :ch\ndär sed 61, verkst dir o styr :led bkns\nfastigh:bol sed 61. - Skr: Kontoplan\nf större fastighetsförvaltningar m m.\n-Hobby: fjällvandringar.\nGift 60 m Ingela Johanson f 39, dtr t\nköpm Gunnar J o Margareta Wedin.\n-Barn: Jan f 61, Kajsa f 65.\nNORUP, SVEN, godsägare, Salstad, f\ni Knislinge, Kristianst l, 17/8/02 av\nriks-d:man Sven Bengtsson o Pauline B.\nAg Håbergs egend sed 26. - V ordf\nSkarab l brandst:bol 48, styr :led ab\nKnislinge skofabr 55. - Nämndem 47, ordf\nVarabygd vägnd 47, led länsarb:nd 48,\nprövn:nd 55. - Utm: RVO.\n\nNOTHIN, TORSTEN K V, fd\növerståthållare, förutv statsråd, Värnamo, f\ni Voxtorp, Jönkpgs l, 16/2/84 av kyrkoh\nJ N o Anna Bengtson.\nEx t rätteg :v 05, tf domhav 09, tf fiskal\nGöta hovr 10, adjung led 11, hovr:råd\n17, byråch f lagärend i f in :dep 18,\nrev:-sekr 20, konsult statsråd 10/3-27/10 20 o\n21-23, tf gen:dir i lantmät:styr 23-24,\nstatsråd o ch f just:dep 24-26, gen:dir o\nch f lantmät:styr 26, konsult statsråd\n32-33, överståth i Sthlm 33-49; led FK\n21-28 (s), tryckfrih :komm. - Jur hed :dr\nUpps 32, ordf i ett 20-tal komm o\nsak-k:utredn, mit:tag t bl a Riksluftsk:förb\no Folk o försvar. - Led ett flert\nbol:-styr, stat repr i styr f LKAB o TGOJ\n23-55. - LSLA. - Skr: Städ särsk\nskyl-digh o rättigh i förhåll t staten (22), En\nbortglömd värld (53), Regeringsmakt o\nrättssäkerhet (53), init:tag o en av utg av\nSv lagsamling (50-54), förf lagsaml:d\nKyrkorätt (52), Från Branting till\nErlander (55), Svenskar under ämbetsmän\no fogdevälde (56), De som länkat\nlandets öden (57), Finnvedens ansikte (58),\nReflexioner från vägkanten (59), Den\ngamla goda tiden (61). - Utm:\nGV:s-Jmtll, RoKavKMO, Kon:sGMmbr.\nGift 25 m Vera Åkerman f 00 d 55, dtr t\nhäradsh Assar Å o Othilda Borg. - Barn:\nMargareta f 27.\n\n",
    "structured": {
        "1": {
            "full_name": "N GUNNAR A NORSTRÖM",
            "location": "Jönköping",
            "occupation": "civilförsvarsdirektör",
            "birth_details": {
                "date": "10/04/1902",
                "place": "Saleby, Skaraborgs l",
                "parents": "lantbr Karl-Axel N o Ellen Ekelund"
            },
            "education": [
                {
                    "degree": "Realexamen",
                    "year": "1918",
                    "institution": "Skara"
                },
                {
                    "degree": "Landsfiskalexamen",
                    "year": "1925",
                    "institution": "FHS"
                }
            ],
            "career": [
                {
                    "position": "landsfisk:tjg",
                    "years": {
                        "start_year": 1926,
                        "end_year": 1934
                    },
                    "organization": "öl distr"
                },
                {
                    "position": "civil-försv:dir",
                    "years": {
                        "start_year": 1953,
                        "end_year": null
                    },
                    "organization": "Jönkpgs l"
                }
            ],
            "family": {
                "spouse": "Dagny Pettersson",
                "marriage_year": "1929",
                "children": [
                    {
                        "name": "Lennart",
                        "birth_year": "1932"
                    },
                    {
                        "name": "Bertil",
                        "birth_year": "1936"
                    }
                ]
            },
            "hobbies": [
                "ornitologi"
            ]
        },
        "2": {
            "full_name": "J TAGE L NORSTRÖM",
            "location": "Gbg",
            "occupation": "ingenjör",
            "birth_details": {
                "date": "09/09/1923",
                "place": "Väse, Värml l",
                "parents": "lantbr Oscar N o Anhild Eriksson"
            },
            "education": [
                {
                    "degree": "Realexamen",
                    "year": "1942",
                    "institution": null
                },
                {
                    "degree": "Hdlsutbildning",
                    "year": "1943",
                    "institution": null
                },
                {
                    "degree": "Ing:ex",
                    "year": "1947",
                    "institution": "STI"
                },
                {
                    "degree": "Spec :stud",
                    "year": "1955-1956",
                    "institution": "Sthlms univ"
                }
            ],
            "career": [
                {
                    "position": null,
                    "years": {
                        "start_year": 1947,
                        "end_year": null
                    },
                    "organization": "ab Armerad betong Örebro"
                },
                {
                    "position": "byggn :avd",
                    "years": {
                        "start_year": 1948,
                        "end_year": null
                    },
                    "organization": "Borås Wäfveri ab Borås"
                },
                {
                    "position": "bitr sekr",
                    "years": {
                        "start_year": 1954,
                        "end_year": null
                    },
                    "organization": "stat nd f byggn:-forskn"
                },
                {
                    "position": "utredn :man",
                    "years": {
                        "start_year": 1955,
                        "end_year": null
                    },
                    "organization": "dess FU"
                },
                {
                    "position": "fastigh :ing",
                    "years": {
                        "start_year": 1956,
                        "end_year": 1961
                    },
                    "organization": "Skand bkn Gbg"
                },
                {
                    "position": "fastigh :ch",
                    "years": {
                        "start_year": 1961,
                        "end_year": null
                    },
                    "organization": "där"
                }
            ],
            "family": {
                "spouse": "Ingela Johanson",
                "marriage_year": "1960",
                "children": [
                    {
                        "name": "Jan",
                        "birth_year": "1961"
                    },
                    {
                        "name": "Kajsa",
                        "birth_year": "1965"
                    }
                ]
            },
            "hobbies": [
                "fjällvandringar"
            ]
        },
        "3": {
            "full_name": "SVEN NORUP",
            "location": "Salstad",
            "occupation": "godsägare",
            "birth_details": {
                "date": "17/08/1902",
                "place": "Knislinge, Kristianst l",
                "parents": "riksd:man Sven Bengtsson o Pauline B"
            },
            "career": [
                {
                    "position": null,
                    "years": {
                        "start_year": 1926,
                        "end_year": null
                    },
                    "organization": "Håbergs egend"
                }
            ],
            "community_involvement": [
                {
                    "role": "V ordf",
                    "organization": "Skarab l brandst:bol",
                    "years": "1948"
                },
                {
                    "role": "styr :led",
                    "organization": "ab Knislinge skofabr",
                    "years": "1955"
                }
            ],
            "board_memberships": [
                {
                    "position": "Nämndem",
                    "organization": null,
                    "years": "1947"
                },
                {
                    "position": "ordf",
                    "organization": "Varabygd vägnd",
                    "years": "1947"
                },
                {
                    "position": "led",
                    "organization": "länsarb:nd",
                    "years": "1948"
                }
            ],
            "honorary_titles": [
                "RVO"
            ],
            "hobbies": null
        },
        "4": {
            "full_name": "TORSTEN K V NOTHIN",
            "location": "Värnamo",
            "occupation": "fd överståthållare, förutv statsråd",
            "birth_details": {
                "date": "16/02/1884",
                "place": "Voxtorp, Jönkpgs l",
                "parents": "kyrkoh J N o Anna Bengtson"
            },
            "education": [
                {
                    "degree": "Examen t rätteg",
                    "year": "1905",
                    "institution": null
                }
            ],
            "career": [
                {
                    "position": "tf domhav",
                    "years": {
                        "start_year": 1909,
                        "end_year": null
                    },
                    "organization": null
                }
            ],
            "family": {
                "spouse": "Vera Åkerman",
                "marriage_year": "1925",
                "children": [
                    {
                        "name": "Margareta",
                        "birth_year": "1927"
                    }
                ]
            },
            "publications": [
                {
                    "title": "Städ särsk skyl-digh o rättigh i förhåll t staten",
                    "year": "1922",
                    "type": null
                }
            ],
            "honorary_titles": [
                "GV:s-Jmtll",
                "RoKavKMO",
                "Kon:sGMmbr"
            ]
        }
    }
}