{
    "original": "PEHRZON, LARS ERIK, pöl mag,\nFarsta, f i Sthlm 22/3/20 av dir\nVerner P o Ruth Eriksson.\nStud:ex 40, res:off:ex 43, pol mag\nSthlm 47, aman o sekr PKN 42-49,\ndir :ass Sv:es oljekonsumenters riksförb\nsed 50.\n\nGift m Ulla-Britt Stensiö. - Barn: Lars\nf 50, Brita f 53.\n\nPERSSON, E LENNART, direktör,\nDanderyd, f i Lund 3/9/25 av installatör\nEdnar P o Frida Nilsson.\nStud:ex 44, Malmö hdlsgymn 45, DHG\n50, sekr Sv:es köpnrannaförb 50, Mobil\nOM ab Sthlm 52, kamr där 55,\nekonomidir 59 (styr:led).\n\nGift- 51 m Maj Adseus f 26, dtr t\nköpman Gunnar Andersson o Ester\nSvensson. - Barn: Birgitta f 53, Gunilla\nf 59.\n\nPERSSON, NILS L, civilingenjör,\nJohanneshov, f i Norrkpg 1/2/24 av\nErnst P o Regina P.\nStud:ex 43, CTH 51, kontrollch\nStandard radio &amp; telefon ab Bromma. - Led\nSER, LSvTF.\n\nGift 50 m Marianne Arvidson f 24, dtr\nt köpman Olov A o Gerda A. - Barn:\nBo f 51, Staffan f 54.\n\nPERSSON, OSCAR E, tandläkare,\nHägersten, f i Östersund 23/7/07 av\nbank-dir Aug P o Kristina Olsson.\nStud:ex 27, cand med denit Heidelberg\n29, odont kand 30, tandläk:ex 35, ass\nSthlm 35, praktik Hägersten sed 3’8.\nGift 35 m Gertrud Assarson. - Barn:\nIngrid f 37, Björn f 39.\n\nPERSSON, OVE, disponent, Lidingö,\nf i Ystad 5/12/00 av v konsul Olof P o\nOlga Söderström.\n\nStud:ex 18, KTH 23, Akad f Graphische\nKünste Leipzig 26, ing Gen :stab litogr\nanst 25, Esselte ab 34, övering Esseltes\nGbgsind:er 38, Almqvist &amp; Wiksell Upps\n46, disp Ivar Haeggströms boktryckeri o\nbokförlags ab Sthlm sed 50. - Styr:led\nSv boktr:fören 52 (v styr:ordf 57-60),\nSk f bokhantverk 53, Sk f graf\nreproduktion 57 (48), led Graf\nstandardiser:-komm 45, Graf forskn :lab tekn nd 45,\nordf Sv:es litograf tryckeriäg förb 59\n(v ordf 54), ordf Offsetkol 55-57, led\nNord reproduktionsrådet 58, ordf SvTF\navd G 47-49. - Skr: Våra ätliga svampar\n\n(32), Grafisk uppslagsbok (51 o 56);\nmedarb Fotografisk handbok 42 o 59,\nmedarb o red Grafiska yrken 39 o 56,\nmedarb sv o utl fackskr o upps! :verk.\n-Utm: AdeMöldska BM - Hobbies:\nschack, botanik, fotografi.\nGift 28 m Barbro Melander f 08, dtr\nt ing Petrus M o Hanna Åkermark.\n-Barn: Bo f 30, In’ger f 35, Ulla-Britt\nf 40.\n\n",
    "structured": {
        "1": {
            "full_name": "PEHRZON, LARS ERIK",
            "location": "Farsta",
            "occupation": "pol.mag. (politices magister)",
            "birth_details": {
                "date": "22/03/1920",
                "place": "Stockholm"
            },
            "education": [
                {
                    "degree": "Stud:ex",
                    "year": "1940",
                    "institution": "NULL"
                },
                {
                    "degree": "Res:off:ex",
                    "year": "1943",
                    "institution": "NULL"
                }
            ],
            "career": [
                {
                    "position": "aman o sekr PKN",
                    "years": {
                        "start_year": 1942,
                        "end_year": 1949
                    },
                    "organization": "Sv:es oljekonsumenters riksförb"
                },
                {
                    "position": "dir :ass",
                    "years": {
                        "start_year": 1950,
                        "end_year": 1950
                    },
                    "organization": "Sv:es oljekonsumenters riksförb"
                }
            ],
            "family": {
                "spouse": "Ulla-Britt Stensiö",
                "marriage_year": "NULL",
                "children": [
                    {
                        "name": "Lars",
                        "birth_year": "1950"
                    },
                    {
                        "name": "Brita",
                        "birth_year": "1953"
                    }
                ]
            }
        },
        "2": {
            "full_name": "PERSSON, E LENNART",
            "location": "Danderyd",
            "occupation": "direktör",
            "birth_details": {
                "date": "3/9/1925",
                "place": "Lund"
            },
            "education": [
                {
                    "degree": "Stud:ex",
                    "year": "1944",
                    "institution": "NULL"
                },
                {
                    "degree": "Malmö hdlsgymn",
                    "year": "1945",
                    "institution": "NULL"
                },
                {
                    "degree": "DHG",
                    "year": "1950",
                    "institution": "NULL"
                }
            ],
            "career": [
                {
                    "position": "sekr",
                    "years": {
                        "start_year": 1950,
                        "end_year": 1950
                    },
                    "organization": "Sv:es köpnrannaförb"
                },
                {
                    "position": "kamr",
                    "years": {
                        "start_year": 1952,
                        "end_year": 1955
                    },
                    "organization": "Mobil OM ab Sthlm"
                },
                {
                    "position": "ekonomidir",
                    "years": {
                        "start_year": 1959,
                        "end_year": "NULL"
                    },
                    "organization": "Mobil OM ab Sthlm"
                }
            ],
            "family": {
                "spouse": "Maj Adseus",
                "marriage_year": "1951",
                "children": [
                    {
                        "name": "Birgitta",
                        "birth_year": "1953"
                    },
                    {
                        "name": "Gunilla",
                        "birth_year": "1959"
                    }
                ]
            }
        },
        "3": {
            "full_name": "PERSSON, NILS L",
            "location": "Johanneshov",
            "occupation": "civilingenjör",
            "birth_details": {
                "date": "1/2/1924",
                "place": "Norrköping"
            },
            "education": [
                {
                    "degree": "Stud:ex",
                    "year": "1943",
                    "institution": "NULL"
                },
                {
                    "degree": "CTH",
                    "year": "1951",
                    "institution": "NULL"
                }
            ],
            "career": [
                {
                    "position": "kontrollch",
                    "years": {
                        "start_year": "NULL",
                        "end_year": "NULL"
                    },
                    "organization": "Standard radio & telefon ab Bromma"
                }
            ],
            "family": {
                "spouse": "Marianne Arvidson",
                "marriage_year": "1950",
                "children": [
                    {
                        "name": "Bo",
                        "birth_year": "1951"
                    },
                    {
                        "name": "Staffan",
                        "birth_year": "1954"
                    }
                ]
            }
        },
        "4": {
            "full_name": "PERSSON, OSCAR E",
            "location": "Hägersten",
            "occupation": "tandläkare",
            "birth_details": {
                "date": "23/7/1907",
                "place": "Östersund"
            },
            "education": [
                {
                    "degree": "Stud:ex",
                    "year": "1927",
                    "institution": "NULL"
                },
                {
                    "degree": "cand.med.denit",
                    "year": "1929",
                    "institution": "Heidelberg"
                },
                {
                    "degree": "odont kand",
                    "year": "1930",
                    "institution": "NULL"
                },
                {
                    "degree": "tandläk:ex",
                    "year": "1935",
                    "institution": "NULL"
                }
            ],
            "career": [
                {
                    "position": "ass",
                    "years": {
                        "start_year": 1935,
                        "end_year": "NULL"
                    },
                    "organization": "Sthlm"
                },
                {
                    "position": "praktik",
                    "years": {
                        "start_year": 1938,
                        "end_year": "NULL"
                    },
                    "organization": "Hägersten"
                }
            ],
            "family": {
                "spouse": "Gertrud Assarson",
                "marriage_year": "1935",
                "children": [
                    {
                        "name": "Ingrid",
                        "birth_year": "1937"
                    },
                    {
                        "name": "Björn",
                        "birth_year": "1939"
                    }
                ]
            }
        },
        "5": {
            "full_name": "PERSSON, OVE",
            "location": "Lidingö",
            "occupation": "disponent",
            "birth_details": {
                "date": "5/12/1900",
                "place": "Ystad"
            },
            "education": [
                {
                    "degree": "Stud:ex",
                    "year": "1918",
                    "institution": "NULL"
                },
                {
                    "degree": "KTH",
                    "year": "1923",
                    "institution": "NULL"
                },
                {
                    "degree": "Akad f Graphische Künste",
                    "year": "1926",
                    "institution": "Leipzig"
                }
            ],
            "career": [
                {
                    "position": "ing",
                    "years": {
                        "start_year": 1925,
                        "end_year": "NULL"
                    },
                    "organization": "Gen:stab litogr anst"
                },
                {
                    "position": "övering",
                    "years": {
                        "start_year": 1938,
                        "end_year": "NULL"
                    },
                    "organization": "Esselte ab"
                },
                {
                    "position": "disp",
                    "years": {
                        "start_year": 1946,
                        "end_year": "NULL"
                    },
                    "organization": "Almqvist & Wiksell Upps"
                }
            ],
            "family": {
                "spouse": "Barbro Melander",
                "marriage_year": "1928",
                "children": [
                    {
                        "name": "Bo",
                        "birth_year": "1930"
                    },
                    {
                        "name": "In’ger",
                        "birth_year": "1935"
                    },
                    {
                        "name": "Ulla-Britt",
                        "birth_year": "1940"
                    }
                ]
            },
            "publications": [
                {
                    "title": "Våra ätliga svampar",
                    "year": "1932",
                    "type": "NULL"
                },
                {
                    "title": "Grafisk uppslagsbok",
                    "year": "1951",
                    "type": "NULL"
                },
                {
                    "title": "Grafisk uppslagsbok",
                    "year": "1956",
                    "type": "NULL"
                },
                {
                    "title": "Fotografisk handbok",
                    "year": "1942",
                    "type": "NULL"
                },
                {
                    "title": "Fotografisk handbok",
                    "year": "1959",
                    "type": "NULL"
                },
                {
                    "title": "Grafiska yrken",
                    "year": "1939",
                    "type": "NULL"
                },
                {
                    "title": "Grafiska yrken",
                    "year": "1956",
                    "type": "NULL"
                }
            ],
            "hobbies": [
                "schack",
                "botanik",
                "fotografi"
            ]
        }
    }
}