{
    "original": "PEHRSON, KARL AXEL I,\nkonstnär, Enebyberg, f i Örebro 30/10/21\nav dir Carl Arvid P o Emma Larsson.\nEdvard Berggrens målarsk 37, Otte\nSkölds målarsk 38-40, Konstakad 46,\nstud Österrike 36, Frankrike 47. -\nStyr:-led KRO 58-60, Eva Bonnierndn 58-60,\nLiljevalens 60. - Utf: temperamåln\nEskilstuna las 50, Bodens garnisonssjh 51,\nHalmstads nya Folkets hus 54, ab Astra\nSödertälje 54, 55, Sv hdlsbkn\nHötorgscity 58-59, posten Örebro 59, fam :hotellet\nNäsbypark 60, Margarinbol Sthlm 61,\nfrimärken t televerkets 100-årsjub 53,\naffisch varIdsmusikfesten 56. - Utst\nSthlm, Gbg, Paris, Bryssel, Köpenh,\nOslo, Wien, Berlin, London, New York\nm fi. - Repr Nät :mus. - Hobby:\nentomologi.\n\nGift 43 m Birgit Nilsson f 18, dtr t\nköpman Jonas N o Anna Bernholm.\n-Barn: Susanne f 44, Max f 49.\n\nPERSSON, KONRAD,\ngeneraldirektör, Sthlm, f i Ystad 26/11/95 av Per\nP o Mathilda Månsson.\nStud:ex 14, jur kand Lun’d 18, tingstjg\n18-21, Svea hovr 21, adj led 25, assess\nSvea hovr 27, fiskal 31, hovr :råd 33\nrev :sekr 36, gen :dir o ch f pens: styr\nyj[. - Sekr sjhstadgesakk 30, byråch f\nlagärendien soc :dep 32, sakk betr\narb:-fred hos 35 års komm ang folkförsörjn\no arb :f red, ordf 36 års utredn1 anig\nför-bättr av lantarb löneställn, fullm\nförvaltn av folkpens :fonden 37, komm f rev\nav lantarb :tidslägen 3’8, arb :markn :ndn\n39, medl korr komm f soc:förs ILO\nGeneve 39, ordf komm f den statl o\nkommunala förvaltn organisation i krig 42,\nordf Norrbackainst 43, sv deleg f utarb\nav interskand konv ang sjukförsäkr o\nåliderdomspens, sv delfeg f utarb av konv\nmellan Frankr o skand länder för social^\nförsäkr 50, sakk i soc:dep betr\nåterför-ing i arb (rehabilitering) 61, led sekt f\npens :försäkr o sekt f sjukförsäkr av de\nnord socialförsäkr :mötena o ordf sv\nVU f dessa möten 37, aktiv medl\nInternat Soc for the Welf are of Cripples 47,\ndess presid 51, soc :förs: konsult\nInternat Soc f rehabilitation of the Disabled\n60, en av huvudmännen i Konung\nGustaf V:s 80-årsfond 39, Kungafonden 43\nm fi fonder. - Utg: Social Welfare in\nSweden (50, omarb 59 o 61),\nl’agbroschyr m komm rör folkpensioneringen\nm m (52, omarb uppl 56 o 59), skr om\n\nsocialförsäkr,    rehabilitering,    arb :f red\n\nm m, art i Nord familjebok, sv o utl\n\ntidskr o i dagspressen. - Utm: Kmstk-\n\nNO.\n\nGift 25 m Berta Sandström, dtr t AL-\n\nbert S o Anna Godin. - Barn: Birgitta\n\nf 31, Marc o Stellan ff 34.\n\n",
    "structured": {
        "0": {
            "full_name": "Pehrson, Karl Axel I",
            "location": "Enebyberg",
            "occupation": "Konstnär",
            "birth_details": {
                "date": "30/10/1921",
                "place": "Örebro",
                "parents": "dir Carl Arvid P o Emma Larsson"
            },
            "education": [
                {
                    "degree": "Otte Skölds målarsk",
                    "year": "1937",
                    "institution": "Edvard Berggrens målarsk"
                },
                {
                    "degree": "Konstakad",
                    "year": "1946",
                    "institution": "Frankrike 1947"
                }
            ],
            "career": [
                {
                    "position": "styr:-led",
                    "years": {
                        "start_year": 1958,
                        "end_year": 1960
                    },
                    "organization": "KRO"
                },
                {
                    "position": "Eva Bonnierndn",
                    "years": {
                        "start_year": 1958,
                        "end_year": 1960
                    }
                },
                {
                    "position": "Liljevalens",
                    "years": {
                        "start_year": 1960
                    }
                }
            ],
            "family": {
                "spouse": "Birgit Nilsson",
                "marriage_year": "1943",
                "children": [
                    {
                        "name": "Susanne",
                        "birth_year": "1944"
                    },
                    {
                        "name": "Max",
                        "birth_year": "1949"
                    }
                ]
            },
            "hobbies": [
                "entomologi"
            ]
        },
        "1": {
            "full_name": "Persson, Konrad",
            "location": "Sthlm",
            "occupation": "Generaldirektör",
            "birth_details": {
                "date": "26/11/1895",
                "place": "Ystad",
                "parents": "Per P o Mathilda Månsson"
            },
            "education": [
                {
                    "degree": "jur kand",
                    "year": "1918",
                    "institution": "Lun’d"
                }
            ],
            "career": [
                {
                    "position": "tingstjg",
                    "years": {
                        "start_year": 1918,
                        "end_year": 1921
                    }
                },
                {
                    "position": "assess",
                    "years": {
                        "start_year": 1927
                    }
                },
                {
                    "position": "fiskal",
                    "years": {
                        "start_year": 1931
                    }
                },
                {
                    "position": "hovr :råd",
                    "years": {
                        "start_year": 1933
                    }
                },
                {
                    "position": "sakk",
                    "years": {
                        "start_year": 1936
                    }
                },
                {
                    "position": "gen :dir o ch f pens",
                    "years": {
                        "start_year": "NULL",
                        "end_year": "NULL"
                    }
                }
            ],
            "family": {
                "spouse": "Berta Sandström",
                "marriage_year": "1925",
                "children": [
                    {
                        "name": "Birgitta",
                        "birth_year": "1931"
                    },
                    {
                        "name": "Marc",
                        "birth_year": "1934"
                    },
                    {
                        "name": "Stellan",
                        "birth_year": "1934"
                    }
                ]
            },
            "publications": [
                {
                    "title": "Social Welfare in Sweden",
                    "year": "1950",
                    "type": "NULL"
                },
                {
                    "title": "l’agbroschyr m komm rör folkpensioneringen",
                    "year": "1952",
                    "type": "NULL"
                }
            ],
            "hobbies": [
                "NULL"
            ]
        }
    }
}