{
    "original": "IVERT, ÅKE H E, leg läkare,\nDjursholm, f i Skellefteå 14/12/14 av dir\nFrans Andersson o Hilda Andersson.\nStud:ex Upps 34, med kand 37, med\nlic Sthlm 43, eo aman Kärol inst patol\ninst 42, eo aman o tf underläk med\ntbc-avd S:t Görans sjh 43^44, med avd 45-\n\n47,   tf las:läk röntgenavd 48, underläk\nmed klan Seraf:las 47, underläk kir avd\nS:t Eriks sjh 49-54, tf underläk BB-avd\n\n51,  tf las:läk Smedjebackens las 50,\nind:-läk ab Separator sed 55 o läk LME\nka-belverk Älvsjö.\n\nGift 2) 48 m sjuksköterskan Märta\nBjörkman f 09, dtr t skräddarmäst Sven\nB o Clara Milde. - Barn: Henning f\n\n48, Torbjörn f 49, Lena f 52.\n\nIVERUS,    GUSTAF   H,    fd    rektor,\n\nBromma, f i Piteå 12/6/89 av disp\nJohan I o Ida Lundberg.\nFil mag Upps 12, fil lic 21, fü dr 25,\nadj hal Upps 19, tektor där 29-54,\nrektor hal Skara 27, hal Bromma 34-54.\n-Ordf Sv skolidnförb 49, skolidr:komm\n37-54, Ungd RK 42-57. - Skr av hist o\nbiogr inneh, bl a Hertig Kar! av\nSödermanland I (25). - Utm: KNO.\nGift 22 m Sonja Lundgren f 98, dtr t\ndir Gustaf L o Ebba Lindgren.\n\nIVESTEDT,   P   O   RAGNAR,   bank-\n\ndirektör, Stocksund, f i Ivö, Kristianst\nl, 12/2/15 av disp Nils Persson o Sigrid\nJeppsson.\n\nStud:ex Malmö 39, DHS 43, anst\nSkånska bkn 31-40, ämneslär Sthlms stads\nhdlssk 42-44, sekr Sv bankfören 44-49,\n\nkamrer Sv hdlsbkn 49-51, dir:ass där\n51-53, dir Sv:es kreditbk 53-60, v verkst\ndir där sed 60. - Styrrled Företagsekon\nfören 53-58, Bankernas förhandl:org 53,\nBankgirocentr 59, ordf hdlskamm\nSv:e-Israel 58. - Skr: Företagsekonomi\n(47), Affärsbankerna o deras\nverksamhet (51), Balansanalys o\nkreditbedömning (tills m G Olson 52).\nGift 44 m Eiwor Palmquist f 21, dtr\nt byggmäst Gottfried P o Ella\nForsgrén. - Barn: Göran f 45, Gunnel f 49.\n\n",
    "structured": {
        "1": {
            "full_name": "IVERT, ÅKE H E",
            "location": "Djursholm",
            "occupation": "leg läkare",
            "birth_details": {
                "date": "14/12/1914",
                "place": "Skellefteå",
                "parents": "dir Frans Andersson o Hilda Andersson"
            },
            "education": [
                {
                    "degree": "Stud:ex",
                    "year": "1934",
                    "institution": "Upps"
                },
                {
                    "degree": "med kand",
                    "year": "1937",
                    "institution": "Upps"
                },
                {
                    "degree": "med lic",
                    "year": "1943",
                    "institution": "Sthlm"
                }
            ],
            "career": [
                {
                    "position": "eo aman",
                    "years": {
                        "start_year": 1942,
                        "end_year": 1943
                    },
                    "organization": "Kärol inst patol inst"
                },
                {
                    "position": "eo aman",
                    "years": {
                        "start_year": 1943,
                        "end_year": 1944
                    },
                    "organization": "tbc-avd S:t Görans sjh"
                },
                {
                    "position": "med avd",
                    "years": {
                        "start_year": 1945,
                        "end_year": 1947
                    }
                },
                {
                    "position": "tf las:läk röntgenavd",
                    "years": {
                        "start_year": 1948
                    }
                },
                {
                    "position": "underläk med klan",
                    "years": {
                        "start_year": 1947
                    },
                    "organization": "Seraf:las"
                }
            ],
            "family": {
                "spouse": "sjuksköterskan Märta Björkman",
                "marriage_year": "1948",
                "children": [
                    {
                        "name": "Henning",
                        "birth_year": "1948"
                    },
                    {
                        "name": "Torbjörn",
                        "birth_year": "1949"
                    },
                    {
                        "name": "Lena",
                        "birth_year": "1952"
                    }
                ]
            }
        },
        "2": {
            "full_name": "IVERUS, GUSTAF H",
            "location": "Bromma",
            "occupation": "fd rektor",
            "birth_details": {
                "date": "12/6/1889",
                "place": "Piteå",
                "parents": "disp Johan I o Ida Lundberg"
            },
            "education": [
                {
                    "degree": "Fil mag",
                    "year": "1912",
                    "institution": "Upps"
                },
                {
                    "degree": "fil lic",
                    "year": "1921",
                    "institution": "Upps"
                },
                {
                    "degree": "fü dr",
                    "year": "1925"
                }
            ],
            "career": [
                {
                    "position": "adj hal",
                    "years": {
                        "start_year": 1919
                    },
                    "organization": "Upps"
                },
                {
                    "position": "tektor",
                    "years": {
                        "start_year": 1929,
                        "end_year": 1954
                    },
                    "organization": "Upps"
                },
                {
                    "position": "rektor",
                    "years": {
                        "start_year": 1934,
                        "end_year": 1954
                    },
                    "organization": "Bromma"
                }
            ],
            "family": {
                "spouse": "Sonja Lundgren",
                "marriage_year": "1922"
            }
        },
        "3": {
            "full_name": "IVESTEDT, P O RAGNAR",
            "location": "Stocksund",
            "occupation": "bankdirektör",
            "birth_details": {
                "date": "12/2/1915",
                "place": "Ivö, Kristianst"
            },
            "education": [
                {
                    "degree": "Stud:ex",
                    "year": "1939",
                    "institution": "Malmö"
                },
                {
                    "degree": "DHS",
                    "year": "1943"
                }
            ],
            "career": [
                {
                    "position": "anst",
                    "years": {
                        "start_year": 1931,
                        "end_year": 1940
                    },
                    "organization": "Skånska bkn"
                },
                {
                    "position": "ämneslär",
                    "years": {
                        "start_year": 1942,
                        "end_year": 1944
                    },
                    "organization": "Sthlms stads hdlssk"
                }
            ],
            "family": {
                "spouse": "Eiwor Palmquist",
                "marriage_year": "1944",
                "children": [
                    {
                        "name": "Göran",
                        "birth_year": "1945"
                    },
                    {
                        "name": "Gunnel",
                        "birth_year": "1949"
                    }
                ]
            }
        }
    }
}