{
    "original": "IVRE, IVAR G E, redaktör, Älvsjö,\nf i Grytgöl, Östergötl l, 28/5/18 av\njärn-bruksarb Carl Andersson o Ester\nLarsson.\n\nBrunnsviks folkhögsk 41-42, DSI 46.\n-Järnbr:arb Grytgöls bruks ab 32-42,\ninstr:makare LME 42-44, aman stat\npris-kontrollnd 47-48, red:sekr LO 49-50,\nkulturred AT 51-52, free lance 53-54,\nTV-producent sed 54, sektxh TV sed\n58. - State Dept stip USA 52.\nGift 47 m Marianne Westberg f 21, dtr\nt pappersbruksarb Anton W o Maria\nLundberg.\n\nIVSTAM, T H BERTEL, leg läkare,\n\nHuddinge, f i Simrishamn 15/10/19 av\nsjökapten Ivar Larsson o Clara Boman.\nStud:ex Ystad 38, med kand Lund 40,\nmed lic 46, e läk kir avd Kristianstads\nlas 46, eo o tf aman otiatr klin Lunds\n• las 48, aman 50, underläk 52 (tf 51),\nl:e un’derläk 53-57, bitr las:läk\nöron-avd Kristianstads las 54-57, l:e\nunderläk o bitr överläk öronklin Södersjh\nsed 57. - Marinläk av 2:a gr v mlk\n47, av l:a gr i mlk res sed 49. - Skr\ni oto-rhino-lao-yngol.\nGift 49 m Greta Färdig f 28, dtr t köpm\nP O F o Tora Gustafsson. - Barn:\nChristina f 50, Marie-Louise f 52,\nAgneta f 57, Josephine f 60.\n\nIZIKOWITZ, LENNART G,\ntandläkare, Sthlm, f i Jönkpg 12/3/13 av\nköpman Marcus I o Dina Mally.\nStud:ex 31, med kand Lund 35,\ntandläk:-ex Sthlm 38, eg prakt Sthlm sed 38.\n-Skr: upps inom odontologi i sv o utl\nfacktidskr. - Hobbies: konst, friluftsliv.\nGift 47 m Greta Ternell.\n\nIZIKOWITZ,   SANDER   J,   professor,\n\növerläkare, Sthlm, f i Jönkpg 24/5/97\nav köpm Marcus I o Dina Mally.\nStud:ex 15, med kand Sthlm 23, med\nlic 40, med dr 41, doc i psykiatri Karol\ninst 42, prof namn 59, förordn Karol\ninst:s fysiol avd samt nerv- o psykiatr\nkliniker, Psykiatr sjh Sthlm, Väster-\n\nviks hosp, Nynäs kuranst, S:t Eriks\nsjh o Beckomberga sjh 26-46, överläk\nBeckomberga sjh 46, dess styresman\n52-62, förest Sthlms stads poliklin f\nalkoholsjukd 51-60. - Skr i psykiatri,\n\nalkohologi o neurol. - Utm: RNO,\nLennmalms pris.\n\nGift 48 m Eva Marianne\nAbraham-sen f 10, dtr t skeppsred Clas A o Elsa\nJönsson.\n\nJACOB^US,   A   CHRISTIAN,   tekn\n\ndr, Sthlm, f i Sthlm 15/6/11 av prof\nChristian J o Anna Carlquist.\nKTH 33, tekn dr 50, doc i telegrafi o\ntelefoni KTH 50-59, anst LME 35, ch\nutvecklcavd 50, tekn dir sed 54. - Ch\nMexicos deleg i Comité Consult\nInternat Télégraphique et Téléphonique sed\n58-60, expert matematikmaskinndn 52, v\nordf SEIF 50-52. - Ett flert uppf inom\ntelefontekn området. - LIVA 57. - Skr:\nA Study ön Congestion ini Link Systems\n(drsavh 50), upps i telefontekn ämnen.\nGift 47 m Eva-Britta Widforss f 15,\ndtr t dir Pehr W o Eva Hoffsten.\n-Barn: Eva Antonia f 53.\n\nJACOBSEN, FREDRIK, kamrer,\nVällingby, f i Östersund 18/12/25 av\ntjm Fredrik J o Karin Eriksson.\nStud:ex 46, IFU 47, anst Liv-Thule 47,\navd: ch Städernas livförsäknavd 55,\nkamr där sed 61. - Hobbies: jakt,\nfriluftsliv.\n\nGift 48 m farm kand Marianne Holm\nf 25. - Barn: Kerstin f 50, Eva f 53,\nIngrid f 57.\n\nJACOBSEN, NILS, ingenjör,\nStocksund, f i Gbg 8/10/11.\nHdlsstud Sthlm 29, ing:ex Sthlms tekn\ninst 33, stud Tyskl, Frankr o Belgien,\nkonstruktör ab Svenska trähus Sthlm,\nanst Kjellbergs arkit :byrå ab o ab\nKorsnäshus Sthlm.\n\nGift 41 m Ingrid Fredell. - Barn: Jens\nf 42, Stefan f 44.\n\nJACOBSON, JACOBSSON se\nJAKOBSON\n\nJAENSSON, GUSTAF W,\nhovkonservator, Sthlm, f i Sthlm 10/8/91 av\nkonservat C W J o Gerda Meyersson.\nStud N latinlärov, Althins o Asplunds\nmålarsk, priv prakt 16-21 o sed 58,\nkonservat Natimus 21-58 (bitr 08-15),\nde kungl lustslotten sed 21, konstakad\no husgerådkamm saml sed 28, H M\nKonungens tavelkonservat sed 41 m fi. -\n\nLed Konstn rklubben sed 21, skattmäst\n26-45, hedL 56, led Sv konstfören\nsed 25, Konstn riksorg sed 36, skattmäst\nKonstn vänner sed 36, Stift konstn\nhjälpfond sed 38, hed:ordf Nord\nkonservat:-förb f bild konst. - Omfatt konserv:- o\nrestaurrarb i sv stat, ämb:verkens,\nkyrkornas, offentl o priv konstsaml sed\n11, repr Nat:mus. - Skr: fack- o\ndagspressart f bekämp av konstförfalskn.\n-Utm: GV:sJmtII, KVO, RNO,\nPropatr-GM, Konstn:klubbens hedM.\nGift 1) 15 m Greta Strandin f 97 d\n52, 2) 55 m Ylva Günther f 18. - Barn:\ni l:a akt Jaen f 24, i 2:a akt Lars f 59.\n\nJAFNER,   BJÖRN,    arkitekt    SAR,\n\nSolna, f i Fredericia, Danm 22/3/15 av\nbyggmäst Knud J o Sofie J.\nÅrhus tekn sk 37, Kunstakad 43, anst\nÅtvidabergs indier 48, Rasmussens\narkit :kontor 50, deläg. - Stud:res t\nSpanien o Portugal. - Hobby:\nfotografering.\n\nGift  m   Gerda  Jensen  f   17.   -   Barn:\nLise f 47, Nils f 54.\n\nJAHN, CARL-FILIP L, major, Sthlm,\nf i Sthlm 12/4/96 av godsäg August J o\nNanny Rudolph.\n\nStud:ex 15, off:ex 17, intend:ex 30,\nfänr I 24* 17, underlöjtn 19, löjtn där 19,\nK 6* 23, K 2* 28, ryttm där 32,\nLiv-reg t häst 42, major 43. - KHS 27-29.\n- Tjg A 3 19, K 7* 20, Livreg drag\n22-23, ital kav 33-35, ung kav 37, adjut o\nlär KHS 41-50, bibl där 50-61. - Skr:\nKungl Skånska dragonreg hist IV.\n-Utm: RSO, OffltKrO, RItRFO,\nRNS:tOO, RyttOlftjM.\nGift m Greta Bjurström f 08. - Barn:\nEbba f 28, Ulla f 30.\n\nJAHNBERG, BERTIL, direktör, Sthlm,\nf i Sthlm 25/4/00 av vinhandl Alfred\nJanson o Emma Lindstedt.\nRealex 16, anst försäkr:bol Fylgia 16,\ndir där sed 43. - Styr:suppl Fylgia 46,\n\n",
    "structured": {
        "0": {
            "full_name": "IVRE, IVAR G E",
            "location": "Älvsjö",
            "occupation": "redaktör",
            "birth_details": {
                "date": "28/05/1918",
                "place": "Grytgöl, Östergötland",
                "parents": "järn-bruksarb Carl Andersson o Ester Larsson"
            },
            "education": [
                {
                    "degree": "Brunnsviks folkhögsk",
                    "year": "1941-1942",
                    "institution": "NULL"
                },
                {
                    "degree": "DSI",
                    "year": "1946",
                    "institution": "NULL"
                }
            ],
            "career": [
                {
                    "position": "Järnbr:arb",
                    "years": {
                        "start_year": 1932,
                        "end_year": 1942
                    },
                    "organization": "Grytgöls bruks ab"
                },
                {
                    "position": "instr:makare",
                    "years": {
                        "start_year": 1942,
                        "end_year": 1944
                    },
                    "organization": "LME"
                },
                {
                    "position": "aman stat pris-kontrollnd",
                    "years": {
                        "start_year": 1947,
                        "end_year": 1948
                    },
                    "organization": "NULL"
                },
                {
                    "position": "red:sekr",
                    "years": {
                        "start_year": 1949,
                        "end_year": 1950
                    },
                    "organization": "LO"
                },
                {
                    "position": "kulturred AT",
                    "years": {
                        "start_year": 1951,
                        "end_year": 1952
                    },
                    "organization": "NULL"
                },
                {
                    "position": "TV-producent",
                    "years": {
                        "start_year": 1954,
                        "end_year": 1954
                    },
                    "organization": "NULL"
                },
                {
                    "position": "sektxh TV",
                    "years": {
                        "start_year": 1958,
                        "end_year": 1958
                    },
                    "organization": "NULL"
                }
            ],
            "family": {
                "spouse": "Marianne Westberg",
                "marriage_year": "1947",
                "children": [
                    {
                        "name": "NULL",
                        "birth_year": "NULL"
                    }
                ]
            }
        },
        "1": {
            "full_name": "IVSTAM, T H BERTEL",
            "location": "Huddinge",
            "occupation": "leg läkare",
            "birth_details": {
                "date": "15/10/1919",
                "place": "Simrishamn",
                "parents": "sjökapten Ivar Larsson o Clara Boman"
            },
            "education": [
                {
                    "degree": "Stud:ex",
                    "year": "1938",
                    "institution": "Ystad"
                },
                {
                    "degree": "med kand",
                    "year": "1940",
                    "institution": "Lund"
                },
                {
                    "degree": "med lic",
                    "year": "1946",
                    "institution": "NULL"
                }
            ],
            "career": [
                {
                    "position": "e läk kir",
                    "years": {
                        "start_year": 1946,
                        "end_year": 1946
                    },
                    "organization": "Kristianstads las"
                },
                {
                    "position": "eo o tf aman otiatr klin",
                    "years": {
                        "start_year": 1948,
                        "end_year": 1948
                    },
                    "organization": "Lunds las"
                },
                {
                    "position": "aman",
                    "years": {
                        "start_year": 1950,
                        "end_year": 1950
                    },
                    "organization": "NULL"
                },
                {
                    "position": "underläk",
                    "years": {
                        "start_year": 1952,
                        "end_year": 1957
                    },
                    "organization": "NULL"
                }
            ],
            "family": {
                "spouse": "Greta Färdig",
                "marriage_year": "1949",
                "children": [
                    {
                        "name": "Christina",
                        "birth_year": "1950"
                    },
                    {
                        "name": "Marie-Louise",
                        "birth_year": "1952"
                    },
                    {
                        "name": "Agneta",
                        "birth_year": "1957"
                    },
                    {
                        "name": "Josephine",
                        "birth_year": "1960"
                    }
                ]
            }
        },
        "2": {
            "full_name": "IZIKOWITZ, LENNART G",
            "location": "Sthlm",
            "occupation": "tandläkare",
            "birth_details": {
                "date": "12/03/1913",
                "place": "Jönköping",
                "parents": "köpman Marcus I o Dina Mally"
            },
            "education": [
                {
                    "degree": "Stud:ex",
                    "year": "1931",
                    "institution": "NULL"
                },
                {
                    "degree": "med kand",
                    "year": "1935",
                    "institution": "Lund"
                },
                {
                    "degree": "tandläk:-ex",
                    "year": "1938",
                    "institution": "Sthlm"
                }
            ],
            "career": [
                {
                    "position": "NULL",
                    "years": {
                        "start_year": 1938,
                        "end_year": 1958
                    },
                    "organization": "Sthlm"
                }
            ],
            "family": {
                "spouse": "Greta Ternell",
                "marriage_year": "1947",
                "children": [
                    {
                        "name": "NULL",
                        "birth_year": "NULL"
                    }
                ]
            },
            "hobbies": [
                "konst",
                "friluftsliv"
            ]
        },
        "3": {
            "full_name": "IZIKOWITZ, SANDER J",
            "location": "Sthlm",
            "occupation": "professor, överläkare",
            "birth_details": {
                "date": "24/05/1897",
                "place": "Jönköping",
                "parents": "köpm Marcus I o Dina Mally"
            },
            "education": [
                {
                    "degree": "Stud:ex",
                    "year": "1915",
                    "institution": "NULL"
                },
                {
                    "degree": "med kand",
                    "year": "1923",
                    "institution": "Sthlm"
                },
                {
                    "degree": "med lic",
                    "year": "1940",
                    "institution": "NULL"
                },
                {
                    "degree": "med dr",
                    "year": "1941",
                    "institution": "NULL"
                }
            ],
            "career": [
                {
                    "position": "doc i psykiatri",
                    "years": {
                        "start_year": 1942,
                        "end_year": 1959
                    },
                    "organization": "Karolinst"
                },
                {
                    "position": "prof namn",
                    "years": {
                        "start_year": 1959,
                        "end_year": 1959
                    },
                    "organization": "NULL"
                },
                {
                    "position": "förordn Karol inst:s fysiol avd samt nerv- o psykiatr kliniker",
                    "years": {
                        "start_year": "NULL",
                        "end_year": "NULL"
                    },
                    "organization": "Psykiatr sjh Sthlm, Västerviks hosp, Nynäs kuranst, S:t Eriks sjh o Beckomberga sjh 26-46"
                }
            ],
            "family": {
                "spouse": "Eva Marianne Abraham-sen",
                "marriage_year": "1948",
                "children": [
                    {
                        "name": "NULL",
                        "birth_year": "NULL"
                    }
                ]
            },
            "publications": [
                {
                    "title": "NULL",
                    "year": "NULL",
                    "type": "NULL"
                }
            ],
            "honorary_titles": [
                {
                    "title": "Lennmalms pris",
                    "institution": "NULL",
                    "year": "NULL"
                }
            ]
        },
        "4": {
            "full_name": "JACOB^US, A CHRISTIAN",
            "location": "Sthlm",
            "occupation": "tekn dr",
            "birth_details": {
                "date": "15/06/1911",
                "place": "Sthlm",
                "parents": "prof Christian J o Anna Carlquist"
            },
            "education": [
                {
                    "degree": "KTH",
                    "year": "1933",
                    "institution": "NULL"
                },
                {
                    "degree": "tekn dr",
                    "year": "1950",
                    "institution": "NULL"
                }
            ],
            "career": [
                {
                    "position": "doc i telegrafi o telefoni",
                    "years": {
                        "start_year": 1950,
                        "end_year": 1959
                    },
                    "organization": "KTH"
                }
            ],
            "family": {
                "spouse": "Eva-Britta Widforss",
                "marriage_year": "1947",
                "children": [
                    {
                        "name": "Eva Antonia",
                        "birth_year": "1953"
                    }
                ]
            },
            "hobbies": [
                "NULL"
            ]
        },
        "5": {
            "full_name": "JACOBSEN, FREDRIK",
            "location": "Vällingby",
            "occupation": "kamrer",
            "birth_details": {
                "date": "18/12/1925",
                "place": "Östersund",
                "parents": "tjm Fredrik J o Karin Eriksson"
            },
            "education": [
                {
                    "degree": "Stud:ex",
                    "year": "1946",
                    "institution": "NULL"
                },
                {
                    "degree": "IFU",
                    "year": "1947",
                    "institution": "NULL"
                }
            ],
            "career": [
                {
                    "position": "avd: ch Städernas livförsäknavd",
                    "years": {
                        "start_year": 1955,
                        "end_year": 1961
                    },
                    "organization": "Liv-Thule"
                }
            ],
            "family": {
                "spouse": "Marianne Holm",
                "marriage_year": "1948",
                "children": [
                    {
                        "name": "Kerstin",
                        "birth_year": "1950"
                    },
                    {
                        "name": "Eva",
                        "birth_year": "1953"
                    },
                    {
                        "name": "Ingrid",
                        "birth_year": "1957"
                    }
                ]
            },
            "hobbies": [
                "jakt",
                "friluftsliv"
            ]
        },
        "6": {
            "full_name": "JACOBSEN, NILS",
            "location": "Stocksund",
            "occupation": "ingenjör",
            "birth_details": {
                "date": "08/10/1911",
                "place": "Göteborg",
                "parents": "NULL"
            },
            "education": [
                {
                    "degree": "ing:ex",
                    "year": "1933",
                    "institution": "Sthlms tekn inst"
                }
            ],
            "career": [
                {
                    "position": "konstruktör",
                    "years": {
                        "start_year": "NULL",
                        "end_year": "NULL"
                    },
                    "organization": "ab Svenska trähus Sthlm"
                }
            ],
            "family": {
                "spouse": "Ingrid Fredell",
                "marriage_year": "1941",
                "children": [
                    {
                        "name": "Jens",
                        "birth_year": "1942"
                    },
                    {
                        "name": "Stefan",
                        "birth_year": "1944"
                    }
                ]
            }
        },
        "7": {
            "full_name": "JACOBSON, JACOBSSON",
            "location": "NULL",
            "occupation": "NULL",
            "birth_details": {
                "date": "NULL",
                "place": "NULL",
                "parents": "NULL"
            },
            "education": [],
            "career": [],
            "family": {},
            "publications": [],
            "community_involvement": [],
            "board_memberships": [],
            "honorary_titles": [],
            "hobbies": []
        },
        "8": {
            "full_name": "JAENSSON, GUSTAF W",
            "location": "Sthlm",
            "occupation": "hovkonservator",
            "birth_details": {
                "date": "10/08/1891",
                "place": "Sthlm",
                "parents": "NULL"
            },
            "education": [
                {
                    "degree": "NULL",
                    "year": "NULL",
                    "institution": "NULL"
                }
            ],
            "career": [
                {
                    "position": "NULL",
                    "years": {
                        "start_year": 1921,
                        "end_year": 1958
                    },
                    "organization": "priv prakt o konservat Natimus Sthlm"
                }
            ],
            "family": {
                "spouse": "1) Greta Strandin",
                "marriage_year": "1915",
                "children": [
                    {
                        "name": "Jaen",
                        "birth_year": "1924"
                    },
                    {
                        "name": "Lars",
                        "birth_year": "1959"
                    }
                ]
            },
            "publications": [],
            "community_involvement": [
                {
                    "role": "NULL",
                    "organization": "NULL",
                    "years": "NULL"
                }
            ],
            "board_memberships": [],
            "honorary_titles": [
                {
                    "title": "GV:sJmtII",
                    "institution": "NULL",
                    "year": "NULL"
                },
                {
                    "title": "KVO",
                    "institution": "NULL",
                    "year": "NULL"
                },
                {
                    "title": "RNO",
                    "institution": "NULL",
                    "year": "NULL"
                },
                {
                    "title": "Propatr-GM",
                    "institution": "NULL",
                    "year": "NULL"
                },
                {
                    "title": "Konstn:klubbens hedM",
                    "institution": "NULL",
                    "year": "NULL"
                }
            ],
            "hobbies": [
                "NULL"
            ]
        },
        "9": {
            "full_name": "JAFNER, BJÖRN",
            "location": "Solna",
            "occupation": "arkitekt SAR",
            "birth_details": {
                "date": "22/03/1915",
                "place": "Fredericia, Danmark",
                "parents": "byggmäst Knud J o Sofie J"
            },
            "education": [
                {
                    "degree": "Århus tekn sk",
                    "year": "1937",
                    "institution": "NULL"
                },
                {
                    "degree": "Kunstakad",
                    "year": "1943",
                    "institution": "NULL"
                }
            ],
            "career": [
                {
                    "position": "NULL",
                    "years": {
                        "start_year": 1948,
                        "end_year": "NULL"
                    },
                    "organization": "Åtvidabergs indier"
                }
            ],
            "family": {
                "spouse": "Gerda Jensen",
                "marriage_year": "NULL",
                "children": [
                    {
                        "name": "Lise",
                        "birth_year": "1947"
                    },
                    {
                        "name": "Nils",
                        "birth_year": "1954"
                    }
                ]
            },
            "publications": [],
            "community_involvement": [],
            "board_memberships": [],
            "honorary_titles": [],
            "hobbies": [
                "fotografering"
            ]
        },
        "10": {
            "full_name": "JAHN, CARL-FILIP L",
            "location": "Sthlm",
            "occupation": "major",
            "birth_details": {
                "date": "12/04/1896",
                "place": "Sthlm",
                "parents": "godsäg August J o Nanny Rudolph"
            },
            "education": [
                {
                    "degree": "Stud:ex",
                    "year": "1915",
                    "institution": "NULL"
                },
                {
                    "degree": "NULL",
                    "year": "NULL",
                    "institution": "NULL"
                }
            ],
            "career": [
                {
                    "position": "intend",
                    "years": {
                        "start_year": 1930,
                        "end_year": "NULL"
                    },
                    "organization": "NULL"
                }
            ],
            "family": {
                "spouse": "Greta Bjurström",
                "marriage_year": "NULL",
                "children": [
                    {
                        "name": "Ebba",
                        "birth_year": "1928"
                    },
                    {
                        "name": "Ulla",
                        "birth_year": "1930"
                    }
                ]
            },
            "publications": [],
            "community_involvement": [],
            "board_memberships": [],
            "honorary_titles": [],
            "hobbies": [
                "NULL"
            ]
        }
    }
}