{
    "original": "ISAKSSON, N GUNNAR,\ncivilingenjör, Vällingby, f i Braås, Kronob l,\n16/5/19 av byggmäst Isak Petersson o\nEster Svensson.\n\nNorrkpgs tekn lärov 41, KTH 46,\nkonsult ing ab yattenbyggnrbyrån Sthlm.\nGift 46 m Irja Bremer, dtr t köpman\nEsajas B o Alma B. - Barn: Gunnel f\n47,, Han® f 50.\n\nISAKSSON, LARS T G, bankkamrer,\n\nHuddinge, f i Halmstad 26/6/15 av\nriks-banksdir Thure I o Hanna Carlsson.\nHdlsgymn 35, kontorsprakt 35-38,\nförest inlåningsavd Skand bkn Sthlm.\nGift 42 m Märit Olsson, dtr t köpman\nPer O o Maria Lindqvist. - Barn:\nEva f 46, Pia f 49.\n\nISACSON, LENNART, apotekare,\nDanderyd, f i Skeninge 8/4/20 av\nlantbr Helge I o Valborg Andersson.\nStud:ex Linkpg 39, farm kand Sthlm\n43, apotiex 48, tj i Boxholm, Örebro,\nVisby o å apot Svanen Sthlm, omb:man\nSv:es apot:förb 50, Apot:soc 53, ch dess\ninf orm: avd o red Sv farm tidskr sed\n54. - Skr: Apoteksväsendets\norganisation p arbetsuppgifter (52), ett flert\nupps i Sv farm tidskr.\nGift 48 m Karin Larsson f 20, dtr t\n\nköpman  Arvid  L  o   Hilda   Nilsson.\n-Barn:   Katarina   f   49,   Birgitta f  51,\nDag f 53.\nISAACSSON,   RAGNAR   L,   överste,\n\nSthlm, f i Sala 30/6/95 av grosshandl\nPer August I o Leontine Thörnblad.\nStudiex Västerås 14, fänr KA 16,\növerste 45, i res 50. - Kommendant Hemsö\nfästn 37, ch Hemsö KA-försv 42-50,\nNorrl: kusten® marirtdistr 47-50. - Utm:\nRSO, RNO,, OffTysköO, Skyttem,,\nSFMSM.\n\nGift 18 m Ruth Christofferson f 96,\ndtr t dir Victor C o Edith Cederström.\n\n",
    "structured": {
        "0": {
            "full_name": "ISAKSSON, N GUNNAR",
            "location": "Vällingby, Kronob l",
            "occupation": "civilingenjör",
            "birth_details": {
                "date": "16/05/1919",
                "place": "Braås, Kronob l",
                "parents": "Isak Petersson and Ester Svensson"
            },
            "education": [
                {
                    "degree": "Norrkpgs tekn lärov",
                    "year": "1941",
                    "institution": "Norrkpgs tekn lärov"
                },
                {
                    "degree": "KTH",
                    "year": "1946",
                    "institution": "KTH"
                }
            ],
            "career": [
                {
                    "position": "konsult ing ab yattenbyggnrbyrån Sthlm",
                    "years": {
                        "start_year": 1946,
                        "end_year": null
                    },
                    "organization": "ab yattenbyggnrbyrån Sthlm"
                }
            ],
            "family": {
                "spouse": "Irja Bremer",
                "marriage_year": "1946",
                "children": [
                    {
                        "name": "Gunnel",
                        "birth_year": "1947"
                    },
                    {
                        "name": "Han®",
                        "birth_year": "1950"
                    }
                ]
            }
        },
        "1": {
            "full_name": "ISAKSSON, LARS T G",
            "location": "Huddinge",
            "occupation": "bankkamrer",
            "birth_details": {
                "date": "26/06/1915",
                "place": "Halmstad",
                "parents": "Thure I and Hanna Carlsson"
            },
            "education": [],
            "career": [
                {
                    "position": "förest inlåningsavd Skand bkn Sthlm",
                    "years": {
                        "start_year": 1935,
                        "end_year": 1938
                    },
                    "organization": "Skand bkn Sthlm"
                }
            ],
            "family": {
                "spouse": "Märit Olsson",
                "marriage_year": "1942",
                "children": [
                    {
                        "name": "Eva",
                        "birth_year": "1946"
                    },
                    {
                        "name": "Pia",
                        "birth_year": "1949"
                    }
                ]
            }
        },
        "2": {
            "full_name": "ISACSON, LENNART",
            "location": "Danderyd",
            "occupation": "apotekare",
            "birth_details": {
                "date": "08/04/1920",
                "place": "Skeninge",
                "parents": "Helge I and Valborg Andersson"
            },
            "education": [
                {
                    "degree": "Stud:ex Linkpg",
                    "year": "1939",
                    "institution": "Linkpg"
                },
                {
                    "degree": "farm kand Sthlm",
                    "year": "1943",
                    "institution": "Sthlm"
                },
                {
                    "degree": "apotiex",
                    "year": "1948",
                    "institution": "apot:S"
                }
            ],
            "career": [
                {
                    "position": "omb:man Sv:es apot:förb",
                    "years": {
                        "start_year": 1950,
                        "end_year": null
                    },
                    "organization": "Sv:es apot:förb"
                },
                {
                    "position": "ch dess inf orm: avd",
                    "years": {
                        "start_year": 1953,
                        "end_year": null
                    },
                    "organization": "Sv farm tidskr"
                }
            ],
            "family": {
                "spouse": "Karin Larsson",
                "marriage_year": "1948",
                "children": [
                    {
                        "name": "Katarina",
                        "birth_year": "1949"
                    },
                    {
                        "name": "Birgitta",
                        "birth_year": "1951"
                    },
                    {
                        "name": "Dag",
                        "birth_year": "1953"
                    }
                ]
            }
        },
        "3": {
            "full_name": "ISAACSSON, RAGNAR L",
            "location": "Sthlm",
            "occupation": "överste",
            "birth_details": {
                "date": "30/06/1895",
                "place": "Sala",
                "parents": "Per August I and Leontine Thörnblad"
            },
            "education": [
                {
                    "degree": "Studiex Västerås",
                    "year": "1914",
                    "institution": "Västerås"
                }
            ],
            "career": [
                {
                    "position": "fänr KA",
                    "years": {
                        "start_year": 1916,
                        "end_year": null
                    }
                },
                {
                    "position": "överste",
                    "years": {
                        "start_year": 1945,
                        "end_year": null
                    }
                },
                {
                    "position": "i res",
                    "years": {
                        "start_year": 1950,
                        "end_year": null
                    }
                }
            ],
            "family": {
                "spouse": "Ruth Christofferson",
                "marriage_year": "1918",
                "children": []
            }
        }
    }
}