{
    "original": "Magnusson, Waldemar, landsfiskal,\n\nViekerium, f. 14/10/84 i Rormieby av\nisitat :)för!elsit. FranS’ O. M. o. Maria\nO^lts-so^n. — Kro^niolänism :€x. i Karilisk:r. 08.\nTf. ikmidskainisil. ii Billek. )1. 06, ^e.\nilandis-kiont. 09, itf. ikronolliänisman i Asariumts\ndlisitr. 15, ilainidsifiiislkal ii Mörrumis diisifcr.\nfr. 18. Ordf. ii tax:md 16-39, i 21 års\nmjar’kuppiskaittn:nd’ i Lisiters’ här., 5\nbe-red’n:- o. fasligh :nid, li vägnd f. B^leik.\nill, li Bliek. (1. avd. av Förren. Sv.\nilanfdis’-fiiskaiHer, Hed. av pirövn :,nid, is’e(kr. d Bikk.\nl|. ilandisitatisfören., rev. i iliänföts\n’sikoigsv:-is-tyr. RVO.\n\nMagnusson, Otto Verner,\nprovinsialläkare, Söd’erköping, f. 30/5/89 i Västra\nEd, Kalmar il., av Karl Gustaf M. o.\nHilda Amanda Haldén. G. 27 m. Asta\nBers:ström. Barn: Barbro f. 28, Sven\n31, Gerd 34. — Stud :ex. i Västervik 09,\nfarm. kand. 12, med. kand. 19 o, med.\nlic. 24, allt i Sthlm. Anst. v. apot. i\nSv:e o. TyskL 09-19, tf. und:!läk. v.\nÄngelholms las. 23, v. Svenshögens\nsanat. samt . assist :!läk. v. Eskilstuna\nlas. 24, e. prov :läk. i Dalarö distr.\n25-30, stip. v. Österåsens ’sanat. två mån.\n26, tf. und :läk. v. Söderhamns las.\ntvå mån. s. å., v. Ängelhoilms las. nio\nmån. 26-29, assist, o. tf. und :läk. v.\nSthlms epid :sjukh. fyra inån. 29,\nprov:läk. i Mörtfors di&amp;tr. 30-35, i\nSöderköp. distr. sed. 35, läk. v.\nepid:-sjukh., disp., östergötil. 1.\nsinnesslö-anst., posten, telegrafv., folksk. samt\nsamrealsk. i Söderköp. Ordf. i\nSöder-köp. Brunns- o Bad A-B samt i distr.\nFörsta majb 1 ommekomni.\n\n’’\"Magnusson, Wiktor Naitanaidl,\nkoim-mànisiter, Markaryd, f. 22/2/99 i\nSkär-sitaid, Jönköp. 1’. G. 32 m. »lär. Telklla\nWollmer. Barn: Kai-Åke f. 35,\nPer-Inigvar 39. — Stud :iex. i Lund 25, fil.\nikanid. diär 28, teol’. kand. o. pnaJkt. teidl.\nprov 35, präsitv. f. Växjö isitiift 36. Tjg.\nS: pas’t:iad’j. li Köpimg, Torislliunda o.\nAllem, v. fcoimimiin’. i Söderåikra,\nBäckia-by o. Ailem, kommin:!adj. o. v. kom-\n\nmin. i Stockaryd, kommin. i\nMarka-ryd’ 45.\n\n^Malcolm, Robert Aiiidirew,\ndiviiiliin’-gienjör, tdkn. direk|tör, Norralhiaimimair,\nf. 14/6/01 i Mataö atv dmg. Anidrew\nLieiOiniaTid M. o. RuHh’ W/i’l’hie’lim)inia\nAugiuistta LunidWad. G. 31 m. Ellkni\nKrà-isitina Guisita:fvia WeisiteTlliunid. Barn :\nAmma Viivtelka- if. 34, Jiam Andriew 38. —\nStud :iex. li Noirrtköp. 22, avig :iex. v.\nKTH 27. Asisiiisit. li. diviilllimg. Cia-ril\nMon-teilimisi 28-31, limg. v. A-»B Lmioiimdiuisitrii i\nSfhllm 31-36, verlkstxbef v. A-B\nNy-hieimisi Mök. VerlkiSft. d HalmJsliad 36,\nverlksitiimg. v. Teiliefon A-B- L. M.\nEriiosison 37-40, överimg. v. föirisviainsväis.\nverlksitadtsnd 41, iövienimg. o. chef f.\nverktsliadistbyråni v. iaTméfÖTviaiIitn.\ntyig-avfd. s. å. Led. ’av Sv. telkn rfören.\ns^ed. 33.\n\n",
    "structured": {
        "1": {
            "full_name": "Magnusson, Waldemar",
            "occupation": "landskamrerare",
            "birth_details": {
                "date": "14/10/1884",
                "place": "Rormieby"
            },
            "location": "Viekerium",
            "education": [
                {
                    "degree": "Kronolänism",
                    "year": "08",
                    "institution": "Karilsk"
                },
                {
                    "degree": "Tf. kminidskainisil",
                    "year": "06",
                    "institution": "Billek"
                },
                {
                    "degree": "If. ilandis-kiont",
                    "year": "09",
                    "institution": "Asariumts"
                },
                {
                    "degree": "Ilandis-kiont",
                    "year": "15",
                    "institution": "Mörrumis"
                }
            ],
            "career": [
                {
                    "position": "Ordf",
                    "years": {
                        "start_year": 16,
                        "end_year": 39
                    },
                    "organization": "tax:md"
                },
                {
                    "position": "Ordf",
                    "years": {
                        "start_year": null,
                        "end_year": null
                    },
                    "organization": "be-red’n"
                }
            ],
            "family": {
                "spouse": "Maria O^lts-so^n",
                "marriage_year": "NULL",
                "children": []
            }
        },
        "2": {
            "full_name": "Magnusson, Otto Verner",
            "occupation": "provinsialläkare",
            "birth_details": {
                "date": "30/5/1889",
                "place": "Västra Ed, Kalmar l."
            },
            "location": "Söd’erköping",
            "education": [
                {
                    "degree": "Stud",
                    "year": "09",
                    "institution": "Västervik"
                },
                {
                    "degree": "farm",
                    "year": "12",
                    "institution": "Sthlm"
                },
                {
                    "degree": "med",
                    "year": "24",
                    "institution": "Sthlm"
                }
            ],
            "career": [
                {
                    "position": "prov:läk",
                    "years": {
                        "start_year": 30,
                        "end_year": 35
                    },
                    "organization": "Mörtfors di&amp;tr"
                },
                {
                    "position": "prov:läk",
                    "years": {
                        "start_year": 35,
                        "end_year": null
                    },
                    "organization": "Söderköp. distr"
                }
            ],
            "family": {
                "spouse": "Hilda Amanda Haldén",
                "marriage_year": "27",
                "children": [
                    {
                        "name": "Barbro",
                        "birth_year": "28"
                    },
                    {
                        "name": "Sven",
                        "birth_year": "31"
                    },
                    {
                        "name": "Gerd",
                        "birth_year": "34"
                    }
                ]
            }
        },
        "3": {
            "full_name": "Magnusson, Wiktor Naitanaidl",
            "occupation": "kommisiter",
            "birth_details": {
                "date": "22/2/1899",
                "place": "Skärsåid, Jönköp. l."
            },
            "location": "Markaryd",
            "education": [
                {
                    "degree": "Stud",
                    "year": "25",
                    "institution": "Lund"
                },
                {
                    "degree": "filosofie kandidat",
                    "year": "28",
                    "institution": "Lund"
                },
                {
                    "degree": "teol",
                    "year": "35",
                    "institution": "Växjö"
                }
            ],
            "career": [
                {
                    "position": "kommin. i Markaryd",
                    "years": {
                        "start_year": 45,
                        "end_year": null
                    },
                    "organization": "NULL"
                }
            ],
            "family": {
                "spouse": "Mär. Telklla Wollmer",
                "marriage_year": "32",
                "children": [
                    {
                        "name": "Kai-Åke",
                        "birth_year": "35"
                    },
                    {
                        "name": "Per-Inigvar",
                        "birth_year": "39"
                    }
                ]
            }
        },
        "4": {
            "full_name": "Malcolm, Robert Aiiidirew",
            "occupation": "diviiiniingijör, tdkn. direkjtör",
            "birth_details": {
                "date": "14/6/1901",
                "place": "Mataö atv dmg"
            },
            "location": "Norralhiaimimair",
            "education": [
                {
                    "degree": "Stud",
                    "year": "22",
                    "institution": "Noirrtköp"
                },
                {
                    "degree": "avig",
                    "year": "27",
                    "institution": "KTH"
                }
            ],
            "career": [],
            "family": {
                "spouse": "Ruth W/i’l’hie’lim)inia Augiuistta LunidWad",
                "marriage_year": "31",
                "children": [
                    {
                        "name": "Amma Viivtelka",
                        "birth_year": "34"
                    },
                    {
                        "name": "Jiam Andriew",
                        "birth_year": "38"
                    }
                ]
            }
        }
    }
}