{
    "original": "FORSBERG, ANDERS O B,\nombudsman, riksdagsman, Nässjö, f i Stora\nMalm, Södermani l, 30/11/14 av red\nMartin F o Alma Larsson.\nJourn Smal Folkblad 38-49, anst Nässjö\nstad 49-51, omb :man Nässjö SAP-distr\nsed 51; led distr :styr SAP sed 45. - AK\nsed 57 (s), led bevilln:utsk sed 57, led\nStadsfullm sed 43, DK sed 54, ordf\nNässjö komm :blocks samarb :nd sed 65;\nstyr:-led Nässjö sparbk sed 61, ordf stift\nBraheskolan sed 64. - Hobby: fiske.\nGift 36 m Lena Anderson f 15, dtr t\nnämndeman Oscar A o Emy Modig.\n-Barn: Gun f 36, Ann-Charlotte f 44,\nJan-Anders f 46.\n\nFORSBERG, BENGT L,\nstadsbibliotekarie, Värnamo, f i Malmö 29/12/19\nav bangårdsmäst Johan F o Anna\nJohansson.\n\nStud:ex 39, fil kand Lund 44, bibl:sk 47,\ne bibl :ass Malmö stadsbibl 47,\ncentral-bibl:ass Jönkpgs stadsbibl 49, l:e\ncentralbibl :ass där 52, stadsbibl :ie\nVärnamo sed 55. - Ordf Sv folkbibi :f ören\nmellansv kr 55-59, Värnamo filmstudio.\n\n-  Skr: rec o art i dagspr o tidskr. -\nHobby: film.\n\nGift 50 m Doris Jacobsson f 20, dtr t\nrep Sigfrid J o Edit Johansson. - Barn:\nJörgen f 53.\n\nFORSBERG, O BÖRJE, bitr\nkronofogde, Mölndal, f i Blacksta, Södermani\nl, 30/4/02 av folkskollär Oscar F o\nMaria Andersson.\n\nRealex Västerås 18, landsfiskalsex Falun\n26, e o tf landsfiskal Kolbäcks distr 27,\nRamnäs distr 36, tf landsfiskal\nFässbergs distr 42, landsfiskal o utmätn:man\nMölndals distr 43, bitr kronofogde Gbgs\ndistr sed 65.\nGift 31 m Astrid Andersson f 06, dtr t\n\nlantbr Carl A o Anna Hansson. - Barn:\nSten f 36, Ann-Mari f 43.\n\n",
    "structured": {
        "0": {
            "full_name": "Anders O B Forsberg",
            "location": "Nässjö",
            "occupation": "Ombudsman, riksdagsman",
            "birth_details": {
                "date": "30/11/1914",
                "place": "Stora Malm, Södermani l",
                "parents": "Red Martin F o Alma Larsson"
            },
            "education": [
                {
                    "degree": "Journ",
                    "year": "1938",
                    "institution": "Smal Folkblad"
                },
                {
                    "degree": "Anst",
                    "year": "1949",
                    "institution": "Nässjö stad"
                }
            ],
            "career": [
                {
                    "position": "Led distr :styr SAP",
                    "years": {
                        "start_year": 1945,
                        "end_year": 9999
                    },
                    "organization": "N/A"
                },
                {
                    "position": "AK",
                    "years": {
                        "start_year": 1957,
                        "end_year": 9999
                    },
                    "organization": "N/A"
                }
            ],
            "family": {
                "spouse": "Lena Anderson",
                "marriage_year": "1936",
                "children": [
                    {
                        "name": "Gun",
                        "birth_year": "1936"
                    },
                    {
                        "name": "Ann-Charlotte",
                        "birth_year": "1944"
                    },
                    {
                        "name": "Jan-Anders",
                        "birth_year": "1946"
                    }
                ]
            },
            "hobbies": [
                "fiske"
            ]
        },
        "1": {
            "full_name": "Bengt L Forsberg",
            "location": "Värnamo",
            "occupation": "Stadsbibliotekarie",
            "birth_details": {
                "date": "29/12/1919",
                "place": "Malmö",
                "parents": "Bangårdsmäst Johan F o Anna Johansson"
            },
            "education": [
                {
                    "degree": "Stud:ex",
                    "year": "1939",
                    "institution": "N/A"
                },
                {
                    "degree": "Fil kand",
                    "year": "1944",
                    "institution": "Lund"
                }
            ],
            "career": [
                {
                    "position": "E bibl :ass",
                    "years": {
                        "start_year": 1947,
                        "end_year": 9999
                    },
                    "organization": "Malmö stadsbibl"
                },
                {
                    "position": "Stadsbibl :ie",
                    "years": {
                        "start_year": 1955,
                        "end_year": 9999
                    },
                    "organization": "Värnamo"
                }
            ],
            "family": {
                "spouse": "Doris Jacobsson",
                "marriage_year": "1950",
                "children": [
                    {
                        "name": "Jörgen",
                        "birth_year": "1953"
                    }
                ]
            },
            "publications": [],
            "community_involvement": [],
            "board_memberships": [],
            "honorary_titles": [],
            "hobbies": [
                "film"
            ]
        },
        "2": {
            "full_name": "O Börje Forsberg",
            "location": "Mölndal",
            "occupation": "Bitr kronofogde",
            "birth_details": {
                "date": "30/04/1902",
                "place": "Blacksta, Södermani l",
                "parents": "Folkskollär Oscar F o Maria Andersson"
            },
            "education": [
                {
                    "degree": "Realex",
                    "year": "1918",
                    "institution": "Västerås"
                },
                {
                    "degree": "Landsfiskalsex",
                    "year": "1926",
                    "institution": "Falun"
                }
            ],
            "career": [
                {
                    "position": "Tf landsfiskal",
                    "years": {
                        "start_year": 1927,
                        "end_year": 1927
                    },
                    "organization": "Kolbäcks distr"
                },
                {
                    "position": "Bitr kronofogde",
                    "years": {
                        "start_year": 1965,
                        "end_year": 9999
                    },
                    "organization": "Gbgs distr"
                }
            ],
            "family": {
                "spouse": "Astrid Andersson",
                "marriage_year": "1931",
                "children": [
                    {
                        "name": "Sten",
                        "birth_year": "1936"
                    },
                    {
                        "name": "Ann-Mari",
                        "birth_year": "1943"
                    }
                ]
            }
        }
    }
}