{
    "original": "FRANCKE, ARNE E, överstelöjtnant,\ngodsägare, Gränna, f i Sthlm 6/5/04 av\ngrosshandl Eduard F o Hedvig Möller.\nFänr K 5*, löjtn Livreg t häst 32, kapt\ngst 37, major pansartr 42, överstelöjtn\ngst 46, på res :stat 50. - Ital ridsk. - Adjut\nh Konungen 43, stabsch VII milbef\nstaben 44, försv:- o mil :attaché London,\nHaag o Bryssel 46-50, ch sv\nkontingenten neutr repatrier:kommiss Korea\n53-54. - Delt i OS Los Angeles o Berlin,\nhedL Féder Equestre Internat, ordf\nJön-kpgsdistr SRK, VU 56 års ryttarolymp, Sv\nfullblodsavelsfören, led Sv ridsportens\ncentralförb förb:råd, medl\nJockeyklub-ben, Hästägarefören, Nya sällsk,\nSällskapet, TimmermO. - Utm: GV:sJmtll,\nGV:sMt, RSO, RVO.\nGift 2) 30 m frih:an Elsa Wrede f 07,\ndtr t hovstallmäst, greve Fabian W o\nGerda Burén.\n\nFRANG, ERIK M, civilingenjör,\nBorås, f i Strömstad 23/6/14 av byggm Joh\nM Andersson o Gerda Hansson.\nCTH 36, ing telestyr 39, byggn:ch\nBorås Wäfveri ab 48, eg konsult ing :firma\nsed 60. - Styr:ordf HTL Borås 60-62, led\ntekn rådet länsskolndn Älvsb l sed 63,\nordf byggn :ndn Borås 50-63, led\nStadsfullm sed 60. - Medl FrimO. - Hobby:\nsegling.\nGift 42 m tandl Siri Severin f 16, dtr t\n\nhandl Bror S o Elina Nilsson. - Barn:\nThomas f 42, Lars f 47.\nFRANG,  SIRI  V, tandläkare,  Borås,\nf   i   Brösarp,   Kristianst  l,   22/8/16   av\nhandl Bror Severin o Elina Nilsson.\nStud:ex Kristianstad 39, tandl :ex Sthlm\n46, tandl folktandvården Borås 47,  eg\nprakt Borås sed 57. - Hobby: bridge.\nGift 42 m civ:ing Erik F f 14. - Barn:\nThomas f 42, Lars f 47.\n\nFRANG, VERNER M, direktör, Borås,\n\nf i Gbg 9/9/08 av byggm Joh M\nAndersson o Gerda Hansson.\nStud:ex 27, Lawrence’s College\nBirmingham Engl 28, Gbgs hdlI 29, anst\nLindelöf &amp; Co Gbg 30, Knut Evers &amp; Co\nBorås 33, inneh Agenturfirma Verner\nFrang sed 54, verkst dir ab Industrigarn\nsed 61, ab Ariagarn sed 64. - Medl PB.\n\n- Hobbies: tennis, segling, bridge.\n\nGift 37 m Ann Johansson f 13, dtr t\nskräddarm Oscar J o Anna Rylander.\n-Barn: Ann-Charlotte f 39, Barbro f 42,\nUlla f 45.\n\nFRANK se FRANCK\n\n",
    "structured": {
        "1": {
            "full_name": "FRANCKE, ARNE E",
            "location": "Gränna, Sthlm",
            "occupation": "Överstelöjtnant, godsägare",
            "birth_details": {
                "date": "06/05/1904",
                "place": "Sthlm",
                "parents": "Eduard F o Hedvig Möller"
            },
            "education": [],
            "career": [
                {
                    "position": "Fänrik",
                    "years": {
                        "start_year": 1932,
                        "end_year": 1932
                    },
                    "organization": "K 5"
                },
                {
                    "position": "Löjtnant",
                    "years": {
                        "start_year": 1937,
                        "end_year": 1937
                    },
                    "organization": "Livreg t häst"
                },
                {
                    "position": "Kapten",
                    "years": {
                        "start_year": 1942,
                        "end_year": 1942
                    },
                    "organization": "GST"
                },
                {
                    "position": "Major",
                    "years": {
                        "start_year": 1942,
                        "end_year": 1942
                    },
                    "organization": "Pansartr"
                },
                {
                    "position": "Överstelöjtnant",
                    "years": {
                        "start_year": 1946,
                        "end_year": 1950
                    },
                    "organization": "GST"
                }
            ],
            "family": {
                "spouse": "Elsa Wrede",
                "marriage_year": "1930",
                "children": []
            }
        },
        "2": {
            "full_name": "FRANG, ERIK M",
            "location": "Borås, Strömstad",
            "occupation": "Civilingenjör",
            "birth_details": {
                "date": "23/06/1914",
                "place": "Strömstad",
                "parents": "Joh M Andersson o Gerda Hansson"
            },
            "education": [
                {
                    "degree": "Civilingenjör",
                    "year": "1936",
                    "institution": "CTH"
                }
            ],
            "career": [
                {
                    "position": "Byggn:ch",
                    "years": {
                        "start_year": 1948,
                        "end_year": null
                    },
                    "organization": "Borås Wäfveri ab"
                }
            ],
            "family": {
                "spouse": "Siri Severin",
                "marriage_year": "1942",
                "children": [
                    {
                        "name": "Thomas",
                        "birth_year": "1942"
                    },
                    {
                        "name": "Lars",
                        "birth_year": "1947"
                    }
                ]
            }
        },
        "3": {
            "full_name": "FRANG, SIRI V",
            "location": "Borås, Brösarp, Kristianst",
            "occupation": "Tandläkare",
            "birth_details": {
                "date": "22/08/1916",
                "place": "Brösarp, Kristianst",
                "parents": "Bror Severin o Elina Nilsson"
            },
            "education": [
                {
                    "degree": "Tandl:ex",
                    "year": "1946",
                    "institution": "Sthlm"
                }
            ],
            "career": [
                {
                    "position": "Tandl folktandvården",
                    "years": {
                        "start_year": 1947,
                        "end_year": null
                    },
                    "organization": "Borås"
                }
            ],
            "family": {
                "spouse": "Erik F",
                "marriage_year": "1942",
                "children": [
                    {
                        "name": "Thomas",
                        "birth_year": "1942"
                    },
                    {
                        "name": "Lars",
                        "birth_year": "1947"
                    }
                ]
            }
        },
        "4": {
            "full_name": "FRANG, VERNER M",
            "location": "Borås, Gbg",
            "occupation": "Direktör",
            "birth_details": {
                "date": "09/09/1908",
                "place": "Gbg",
                "parents": "Joh M Andersson o Gerda Hansson"
            },
            "education": [
                {
                    "degree": "Stud:ex",
                    "year": "1927",
                    "institution": "Lawrence’s College Birmingham"
                }
            ],
            "career": [],
            "family": {
                "spouse": "Ann Johansson",
                "marriage_year": "1937",
                "children": [
                    {
                        "name": "Ann-Charlotte",
                        "birth_year": "1939"
                    },
                    {
                        "name": "Barbro",
                        "birth_year": "1942"
                    },
                    {
                        "name": "Ulla",
                        "birth_year": "1945"
                    }
                ]
            },
            "hobbies": [
                "Tennis",
                "Segling",
                "Bridge"
            ]
        }
    }
}