{
    "original": "FRIDBLOM, G BERTIL,\ncivilingenjör, Trollhättan, f i Malma, Skarab l,\n27/11/12 av folkskollär Herman F o\nSigne Nyberg.\n\nStud:ex Skara 34, CTH 39, ing Arbrå\nmek verkst 39, Sv flygmotor ab\nTrollhättan sed 42.\n\nGift 49 m sjuksköt Anna-Lisa\nNordmark. - Barn: Ann Marie f 50.\n\nFRIDEFELT,  BENGT  F,  adjunkt,\n\nSkara,   f   i  Skövde   7/10/31   av  ink:ch\n\nCarl Andersson o Ruth A.\n\nStud:ex 50, fil kand Gbg  55, fil mag\n\nUpps 57, adj i matem Skara katedralsk\n\nsed 61. - Led distr:styr LR.\n\nGift 61 m Ingrid Lokrantz f 39, dtr t\n\nkamr Erik L o Mechthild Rosander.\n\nFRIDELL, FOLKE I V, författare,\nLjungby, f i Berga, Kronob l, 1/10/04\nav skrädd Gustav F o Ida Johnsson.\nBl skr: Död mans hand (46), Syndfull\nskapelse (47), Greppet hårdnar (47), Av\negen kraft (48), Bekännelse (49),\nHopp-Jerka (50), Bergspredikan (51), Något\n\nmåste gro (52), Peter (53), Jungfrun i\ndet grå (54), Bjälken i ditt öga (55),\nBönsöndag (56), Kerstin (57), Äldst i\nvärlden (59), Britta tar befälet (59),\nStenansiktet (62), radiopjäser. - Hobby: fiske.\nGift 34 m Kristina Wahlberg f 13, dtr t\nsmedsmäst F G W o Jenny Pettersson.\n-Barn: Hasse f 35, Staffan f 52.\n\nFRIDÉN, AXEL V, förste stadsläkare,\n\nVästervik, f i Nässjö 26/5/02 av dir\nFrans Johan F o Naemi Krantz.\nStud:ex Jönkpg 21, med kand 25 o med\nlic Sthlm 29, öl läk:förordn 27-30,\nprov :läk Emmaboda, Bureå o\nMalå-träsks distr 31, fartygsläk M/S\nKungsholm 31, prakt läk Västervik sed 33, 2:e\nstadsläk 48-63, l:e stadsdistr:läk sed 63.\n\n-  Skolläk Västerviks hal sed 34, folksk\nsed 37, verksläk Post- o Televerket sed\n34, bruksläk Ankarsrum 37-47. -\nStadsfullm 50-62, led skolstyr o pensionsnd,\nlandst:man sed 62.\n\nGift 34 m Stina Samuelsson f 07, dtr t\nsmidesmäst John S o Ingeborg\nWett-ström. - Barn: Staffan f 44, Eva\nChristina f 45.\n\nFRIDÉN, R L GÖSTA, advokat,\nLidköping, f i Lidkpg 25/3/22 av\nbyggn:-snick Lars F o Ellen Sahlqvist.\nDSI Sthlm 49, jur kand StHS 52, tingstjg\nKinne o Kållands doms 53-55, inneh\nAdv :firman Gösta Fridén Lidkpg sed 55.\n\n-  LSA 61. - Styr:led Jubels ab. - Medl\nRotary, FrimO.\n\nGift 52 m Brita Larsson f 25, dtr t\nHugo L o Karin Wallin. - Barn:\nLärs-Hugo f 57, Sven-Wilhelm f 59.\n\nFRIDÉN,    A    LENNART    S,    prost,\n\nTrollhättan, f i Slöta, Skarab l, 27/6/98\nav folkskollär Sigfrid F o Nanny\nLi-thander.\n\nStud:ex Skara 18, teol kand Upps o\nprästv 25, v past Tind 25, kommin\nÄlgarås 26, kyrkoh V Ny 32, kommin\nTrollhättan 45, kyrkoh där sed 55, prost\nVäne kontr sed 63. - Ordf kyrkorådet,\nled kyrkofullm, v ordf socialnd o\nbar-nav:nd. - V ordf Älvsb l\nnaturskydds-för en, styr :led Skarab l\nnaturskydds-fören. - Skr: jub :skr Trollhättans kyrka,\nart i bot verk o tidskr. - Utm: LNO.\n-Hobby: växtgeografi.\nGift 26 m folkskollär Märta Janson,\ndtr t hemm:äg August J o Adina\nLarsson. - Barn: Sven f 28, Margareta f 30.\n\nFRIDÉN,   N  SETH  E,   stadsarkitekt,\n\nSkövde, f i Månsarp, Jönkpgs l, 2/2/13.\nStud:ex   Eksjö   31,   KTH   36,   e   arkit\nSthlms byggn:nd 39, länsarkit:ass Luleå\n\n40-44, eg verksamh Boden 45, stadsarkit\ndär 46, Skövde sed 60.\nGift 45 m Elsa Jonevall. - Barn: Nils\nArne f 47, Karl Börje f 48.\n\nFRIDÉN, SVEN E S, tandläkare,\nBre-daryd, f i Gbg 26/12/07 av köpm\nEdward F o Ester Ljunggren.\nStud:ex Gbg 30, cand med dent\nGreifswald 32, tandl:ex Malmö 56, distr :tandl\no förest distr:tandpoliklin Bredaryd sed\n56. - Hobbies: fiske, schack, bridge,\nfilateli.\nGift 47 m Aagot Hansen f 13.\n\nFRIDÉN, SVEN S, adjunkt,\nTrollhättan, f i Älgarås, Skarab l, 28/3/28 av\nkontr :prost Lennart F o Märta Jansson.\nStud:ex Vänersborg 49, fil mag Gbg 55,\neo adj Filipstads hal 56, adj där 59-60,\nprovar Vasa hal Gbg 59, adj\nTrollhättans hal 60, hdlsgymn Trollhättan o\nbibl:ie där sed 63. - Hobbies: diskofili,\nsmalfilmning.\n\nGift 54 m Inga Elert f 30, dtr t avd:ch\nArtur E o Dagmar Lindberg. - Barn:\nThomas f 56, Susanne f 59, Annika f 62.\n\n",
    "structured": {
        "0": {
            "full_name": "Fridblom, G Bertil",
            "location": "Trollhättan",
            "occupation": "civilingenjör",
            "birth_details": {
                "date": "27/11/1912",
                "place": "Malma, Skaraborgs län",
                "parents": "folkskollär Herman F och Signe Nyberg"
            },
            "education": [
                {
                    "degree": "Stud:ex",
                    "year": "1934",
                    "institution": "Skara"
                },
                {
                    "degree": "CTH",
                    "year": "1939",
                    "institution": "Chalmers tekniska högskola"
                }
            ],
            "career": [
                {
                    "position": "ing",
                    "years": {
                        "start_year": 1939,
                        "end_year": 1942
                    },
                    "organization": "Arbrå mekaniska verkst"
                },
                {
                    "position": "ing",
                    "years": {
                        "start_year": 1942
                    },
                    "organization": "Sv flygmotor ab Trollhättan"
                }
            ],
            "family": {
                "spouse": "Anna-Lisa Nordmark",
                "marriage_year": "1949",
                "children": [
                    {
                        "name": "Ann Marie",
                        "birth_year": "1950"
                    }
                ]
            }
        },
        "1": {
            "full_name": "Fridefelt, Bengt F",
            "location": "Skara",
            "occupation": "adjunkt",
            "birth_details": {
                "date": "7/10/1931",
                "place": "Skövde",
                "parents": "ink:ch Carl Andersson och Ruth A"
            },
            "education": [
                {
                    "degree": "Stud:ex",
                    "year": "1950",
                    "institution": "Skara"
                },
                {
                    "degree": "fil kand",
                    "year": "1955",
                    "institution": "Göteborg"
                },
                {
                    "degree": "fil mag",
                    "year": "1957",
                    "institution": "Uppsala"
                }
            ],
            "career": [
                {
                    "position": "adj",
                    "years": {
                        "start_year": 1961
                    },
                    "organization": "matem Skara katedralsk"
                }
            ],
            "family": {
                "spouse": "Ingrid Lokrantz",
                "marriage_year": "1961"
            }
        },
        "2": {
            "full_name": "Fridell, Folke I V",
            "location": "Ljungby",
            "occupation": "författare",
            "birth_details": {
                "date": "1/10/1904",
                "place": "Berga, Kronobergs län",
                "parents": "skrädd Gustav F och Ida Johnsson"
            },
            "publications": [
                {
                    "title": "Död mans hand",
                    "year": "1946",
                    "type": "bok"
                },
                {
                    "title": "Syndfull skapelse",
                    "year": "1947",
                    "type": "bok"
                },
                {
                    "title": "Greppet hårdnar",
                    "year": "1947",
                    "type": "bok"
                },
                {
                    "title": "Av egen kraft",
                    "year": "1948",
                    "type": "bok"
                },
                {
                    "title": "Bekännelse",
                    "year": "1949",
                    "type": "bok"
                },
                {
                    "title": "Hopp-Jerka",
                    "year": "1950",
                    "type": "bok"
                },
                {
                    "title": "Bergspredikan",
                    "year": "1951",
                    "type": "bok"
                },
                {
                    "title": "Något måste gro",
                    "year": "1952",
                    "type": "bok"
                },
                {
                    "title": "Peter",
                    "year": "1953",
                    "type": "bok"
                },
                {
                    "title": "Jungfrun i det grå",
                    "year": "1954",
                    "type": "bok"
                },
                {
                    "title": "Bjälken i ditt öga",
                    "year": "1955",
                    "type": "bok"
                },
                {
                    "title": "Bönsöndag",
                    "year": "1956",
                    "type": "bok"
                },
                {
                    "title": "Kerstin",
                    "year": "1957",
                    "type": "bok"
                },
                {
                    "title": "Äldst i världen",
                    "year": "1959",
                    "type": "bok"
                },
                {
                    "title": "Britta tar befälet",
                    "year": "1959",
                    "type": "bok"
                },
                {
                    "title": "Stenansiktet",
                    "year": "1962",
                    "type": "bok"
                }
            ],
            "hobbies": [
                "fiske"
            ],
            "family": {
                "spouse": "Kristina Wahlberg",
                "marriage_year": "1934",
                "children": [
                    {
                        "name": "Hasse",
                        "birth_year": "1935"
                    },
                    {
                        "name": "Staffan",
                        "birth_year": "1952"
                    }
                ]
            }
        },
        "3": {
            "full_name": "Fridén, Axel V",
            "location": "Västervik",
            "occupation": "förste stadsläkare",
            "birth_details": {
                "date": "26/5/1902",
                "place": "Nässjö",
                "parents": "dir Frans Johan F och Naemi Krantz"
            },
            "education": [
                {
                    "degree": "Stud:ex",
                    "year": "1921",
                    "institution": "Jönköping"
                },
                {
                    "degree": "med kand",
                    "year": "1925",
                    "institution": "Stockholm"
                },
                {
                    "degree": "med lic",
                    "year": "1929",
                    "institution": "Stockholm"
                }
            ],
            "career": [
                {
                    "position": "öl läk:förordn",
                    "years": {
                        "start_year": 1927,
                        "end_year": 1930
                    }
                },
                {
                    "position": "prov läk",
                    "years": {
                        "start_year": 1931
                    },
                    "organization": "Emmaboda, Bureå, Malå-träsks distr"
                },
                {
                    "position": "fartygsläk",
                    "years": {
                        "start_year": 1931
                    },
                    "organization": "M/S Kungsholm"
                },
                {
                    "position": "prakt läk",
                    "years": {
                        "start_year": 1933
                    },
                    "organization": "Västervik"
                },
                {
                    "position": "2:e stadsläk",
                    "years": {
                        "start_year": 1948,
                        "end_year": 1963
                    }
                },
                {
                    "position": "l:e stadsdistr:läk",
                    "years": {
                        "start_year": 1963
                    }
                }
            ],
            "family": {
                "spouse": "Stina Samuelsson",
                "marriage_year": "1934",
                "children": [
                    {
                        "name": "Staffan",
                        "birth_year": "1944"
                    },
                    {
                        "name": "Eva Christina",
                        "birth_year": "1945"
                    }
                ]
            }
        },
        "4": {
            "full_name": "Fridén, R L Gösta",
            "location": "Lidköping",
            "occupation": "advokat",
            "birth_details": {
                "date": "25/3/1922",
                "place": "Lidköping",
                "parents": "byggn:snick Lars F och Ellen Sahlqvist"
            },
            "education": [
                {
                    "degree": "DSI",
                    "year": "1949",
                    "institution": "Stockholm"
                },
                {
                    "degree": "jur kand",
                    "year": "1952",
                    "institution": "Stockholm"
                }
            ],
            "career": [
                {
                    "position": "tingstjg",
                    "years": {
                        "start_year": 1953,
                        "end_year": 1955
                    },
                    "organization": "Kinne, Kållands doms"
                },
                {
                    "position": "inneh",
                    "years": {
                        "start_year": 1955
                    },
                    "organization": "Adv:firman Gösta Fridén Lidköping"
                }
            ],
            "honorary_titles": [
                {
                    "title": "LSA",
                    "institution": "1961",
                    "year": "1961"
                }
            ],
            "board_memberships": [
                {
                    "position": "styr:led",
                    "organization": "Jubels ab"
                }
            ],
            "family": {
                "spouse": "Brita Larsson",
                "marriage_year": "1952",
                "children": [
                    {
                        "name": "Lärs-Hugo",
                        "birth_year": "1957"
                    },
                    {
                        "name": "Sven-Wilhelm",
                        "birth_year": "1959"
                    }
                ]
            }
        },
        "5": {
            "full_name": "Fridén, A Lennart S",
            "location": "Trollhättan",
            "occupation": "prost",
            "birth_details": {
                "date": "27/6/1898",
                "place": "Slöta, Skaraborgs län",
                "parents": "folkskollär Sigfrid F och Nanny Lithander"
            },
            "education": [
                {
                    "degree": "Stud:ex",
                    "year": "1918",
                    "institution": "Skara"
                },
                {
                    "degree": "teol kand",
                    "year": "1925",
                    "institution": "Uppsala"
                }
            ],
            "career": [
                {
                    "position": "v past",
                    "years": {
                        "start_year": 1925
                    },
                    "organization": "Tind"
                },
                {
                    "position": "kommin",
                    "years": {
                        "start_year": 1945
                    },
                    "organization": "Trollhättan"
                },
                {
                    "position": "kyrkoh",
                    "years": {
                        "start_year": 1955
                    },
                    "organization": "Trollhättan"
                },
                {
                    "position": "prost",
                    "years": {
                        "start_year": 1963
                    },
                    "organization": "Väne kontr"
                }
            ],
            "publications": [
                {
                    "title": "jub :skr Trollhättans kyrka",
                    "year": "NULL",
                    "type": "NULL"
                }
            ],
            "family": {
                "spouse": "Märta Janson",
                "marriage_year": "1926",
                "children": [
                    {
                        "name": "Sven",
                        "birth_year": "1928"
                    },
                    {
                        "name": "Margareta",
                        "birth_year": "1930"
                    }
                ]
            }
        },
        "6": {
            "full_name": "Fridén, N Seth E",
            "location": "Skövde",
            "occupation": "stadsarkitekt",
            "birth_details": {
                "date": "2/2/1913",
                "place": "Månsarp, Jönköpings län"
            },
            "education": [
                {
                    "degree": "Stud:ex",
                    "year": "1931",
                    "institution": "Eksjö"
                },
                {
                    "degree": "e arkitekt",
                    "year": "1936",
                    "institution": "KTH"
                }
            ],
            "career": [
                {
                    "position": "länarkit:ass",
                    "years": {
                        "start_year": 1940,
                        "end_year": 1944
                    },
                    "organization": "Luleå"
                },
                {
                    "position": "stadsarkit",
                    "years": {
                        "start_year": 1946
                    },
                    "organization": "Boden"
                },
                {
                    "position": "stadsarkit",
                    "years": {
                        "start_year": 1960
                    },
                    "organization": "Skövde"
                }
            ],
            "family": {
                "spouse": "Elsa Jonevall",
                "marriage_year": "1945",
                "children": [
                    {
                        "name": "Nils Arne",
                        "birth_year": "1947"
                    },
                    {
                        "name": "Karl Börje",
                        "birth_year": "1948"
                    }
                ]
            }
        },
        "7": {
            "full_name": "Fridén, Sven E S",
            "location": "Bredaryd",
            "occupation": "tandläkare",
            "birth_details": {
                "date": "26/12/1907",
                "place": "Göteborg",
                "parents": "köpm Edward F och Ester Ljunggren"
            },
            "education": [
                {
                    "degree": "Stud:ex",
                    "year": "1930",
                    "institution": "Göteborg"
                },
                {
                    "degree": "cand med dent",
                    "year": "1932",
                    "institution": "Greifswald"
                },
                {
                    "degree": "tandl:ex",
                    "year": "1956",
                    "institution": "Malmö"
                }
            ],
            "career": [
                {
                    "position": "distr:tandl",
                    "organization": "förest distr:tandpoliklin Bredaryd",
                    "years": {
                        "start_year": 1956
                    }
                }
            ],
            "hobbies": [
                "fiske",
                "schack",
                "bridge",
                "filateli"
            ],
            "family": {
                "spouse": "Aagot Hansen",
                "marriage_year": "1947"
            }
        },
        "8": {
            "full_name": "Fridén, Sven S",
            "location": "Trollhättan",
            "occupation": "adjunkt",
            "birth_details": {
                "date": "28/3/1928",
                "place": "Älgarås, Skaraborgs län",
                "parents": "kontr:prost Lennart F och Märta Jansson"
            },
            "education": [
                {
                    "degree": "Stud:ex",
                    "year": "1949",
                    "institution": "Vänersborg"
                },
                {
                    "degree": "fil mag",
                    "year": "1955",
                    "institution": "Göteborg"
                }
            ],
            "career": [
                {
                    "position": "adj",
                    "years": {
                        "start_year": 1960
                    },
                    "organization": "Trollhättans hal"
                }
            ],
            "hobbies": [
                "diskofili",
                "smalfilmning"
            ],
            "family": {
                "spouse": "Inga Elert",
                "marriage_year": "1954",
                "children": [
                    {
                        "name": "Thomas",
                        "birth_year": "1956"
                    },
                    {
                        "name": "Susanne",
                        "birth_year": "1959"
                    },
                    {
                        "name": "Annika",
                        "birth_year": "1962"
                    }
                ]
            }
        }
    }
}