{
    "original": "FALK, NILS G,\ndrätselkammarordfö-rande, Oskarshamn, f i Oskarshamn\n30/9/05 av stuveriarb Edvard F o Ellen\nNilsson.\n\nAnst Jungnerbol Oskarshamn 24, form\ndär 51-63, kommunalråd Oskarshamn\nsed 63. - Ordf DK sed 64, led Stadsfullm\nsed 39, ordf Oskarshamns komm :blocks\nsamarb :nd sed 64, lönend sed 56, styr f\nGunnarsö semesterby sed 57, komm stift\nBygge o Bo sed 64. - Ordf Sv\nmetall-arb:förb avd 1780 46-51; ordf IF\nKamraterna 38-48. - Hobbies: fotboll, fiske.\nGift 38 m Karin Ohlin f 06, dtr t\nhemul :äg Viktor Ö o Thyra Ö. - Barn: Bo\nf 44.\n\nFALK, PER, polismästare, Mariestad,\nf i Halmstad 29/4/11 av stadsfiskal\nGustav F o Elvira Andrén.\n\nStud:ex 32, landsfiskalsex, landsfiskal\nHo tings distr 52, polismäst Mariestad\nsed 65.\n\nFALK, RUNE V, arkitekt SAR, Gbg,\nf i Brunskog, Värml l, 31/12/26 av\nmaskinist Rudolf F o Elin Andersson.\nStud:ex Arvika 47, CTH 52, ass där\n52-56, deläg Waab White arkit :kont ab sed\n52. - Tid sekr lokal :f ören VS A. - Skr:\nart i fackpress. - V tf bost:omr o stadspl\nGbg, Örebro, Västerås, radio o tv-huset\nGbg, utbyggn Chalmers.\nGift 50 m Britta Söderqvist, dtr t apot\nMårten S o Maja Söderqvist. - Barn:\nLena f 50, Maria f 52, Eva f 57.\n\nFALK,   SVEN   A,   förste   tandläkare,\n\nGbg, f i Malmö 15/10/04 av dir Nils F\n\no Karin Svensson.\n\nHandelsgymn Malmö 27, stud:ex Lund\n\n32,   sjökapt  Gbg  37,  kapt  I 7  res 40,\n\ntandl:ex Sthlm 48, tandl folktandv Gbg\n\n48-51, l:e tandl Gbg sed 51. - Nämndem\n\nsed 58. - Led Gbgs tandl:sällsk förtr:nd\n\nsed 61. - Medl Rotary.\n\nGift 37 m tandl Eva Ottander f 10, dtr\n\nt major Erik O o h h. - Barn: Christer\n\nf 38, Nils f 39, Kristina f 44.\n\n",
    "structured": {
        "1": {
            "full_name": "NILS G FALK",
            "location": "Oskarshamn",
            "occupation": "drätselkammarordförande",
            "birth_details": {
                "date": "30/09/1905",
                "place": "Oskarshamn",
                "parents": "stuveriarb Edvard F o Ellen Nilsson"
            },
            "education": [
                {
                    "degree": "form",
                    "year": "1951-1963",
                    "institution": "Jungnerbol Oskarshamn"
                }
            ],
            "career": [
                {
                    "position": "kommunalråd",
                    "years": {
                        "start_year": 1963,
                        "end_year": null
                    },
                    "organization": "Oskarshamn"
                }
            ],
            "family": {
                "spouse": "Karin Ohlin",
                "marriage_year": "1938",
                "children": [
                    {
                        "name": "Bo",
                        "birth_year": "1944"
                    }
                ]
            },
            "hobbies": [
                "fotboll",
                "fiske"
            ]
        },
        "2": {
            "full_name": "PER FALK",
            "location": "Mariestad",
            "occupation": "polismästare",
            "birth_details": {
                "date": "29/04/1911",
                "place": "Halmstad",
                "parents": "stadsfiskal Gustav F o Elvira Andrén"
            },
            "education": [
                {
                    "degree": "Stud:ex",
                    "year": "1932",
                    "institution": null
                },
                {
                    "degree": "landsfiskalsex",
                    "year": "1952",
                    "institution": null
                }
            ],
            "career": [
                {
                    "position": "polismästare",
                    "years": {
                        "start_year": 1965,
                        "end_year": null
                    },
                    "organization": "Mariestad"
                }
            ],
            "family": {
                "spouse": null,
                "marriage_year": null,
                "children": []
            }
        },
        "3": {
            "full_name": "RUNE V FALK",
            "location": "Göteborg",
            "occupation": "arkitekt SAR",
            "birth_details": {
                "date": "31/12/1926",
                "place": "Brunskog, Värml l",
                "parents": "maskinist Rudolf F o Elin Andersson"
            },
            "education": [
                {
                    "degree": "Stud:ex",
                    "year": "1947",
                    "institution": "Arvika"
                },
                {
                    "degree": null,
                    "year": "1952",
                    "institution": "CTH"
                }
            ],
            "career": [
                {
                    "position": "ass",
                    "years": {
                        "start_year": 1952,
                        "end_year": 1956
                    },
                    "organization": "CTH"
                }
            ],
            "family": {
                "spouse": "Britta Söderqvist",
                "marriage_year": "1950",
                "children": [
                    {
                        "name": "Lena",
                        "birth_year": "1950"
                    },
                    {
                        "name": "Maria",
                        "birth_year": "1952"
                    },
                    {
                        "name": "Eva",
                        "birth_year": "1957"
                    }
                ]
            }
        },
        "4": {
            "full_name": "SVEN A FALK",
            "location": "Göteborg",
            "occupation": "förste tandläkare",
            "birth_details": {
                "date": "15/10/1904",
                "place": "Malmö",
                "parents": "dir Nils F o Karin Svensson"
            },
            "education": [
                {
                    "degree": "sjökapt",
                    "year": "1937",
                    "institution": "Gbg"
                },
                {
                    "degree": "kapt I 7",
                    "year": "1940",
                    "institution": "res"
                }
            ],
            "career": [
                {
                    "position": "tandl:ex",
                    "years": {
                        "start_year": 1948,
                        "end_year": null
                    },
                    "organization": "Sthlm"
                },
                {
                    "position": "tandl folktandv",
                    "years": {
                        "start_year": 1948,
                        "end_year": 1951
                    },
                    "organization": "Gbg"
                },
                {
                    "position": "l:e tandl",
                    "years": {
                        "start_year": 1951,
                        "end_year": null
                    },
                    "organization": "Gbg"
                }
            ],
            "family": {
                "spouse": "tandl Eva Ottander",
                "marriage_year": "1937",
                "children": [
                    {
                        "name": "Christer",
                        "birth_year": "1938"
                    },
                    {
                        "name": "Nils",
                        "birth_year": "1939"
                    },
                    {
                        "name": "Kristina",
                        "birth_year": "1944"
                    }
                ]
            },
            "community_involvement": [
                {
                    "role": "Led",
                    "organization": "Göteborgs tandläkarsällsk",
                    "years": "1961"
                },
                {
                    "role": "Medl",
                    "organization": "Rotary",
                    "years": null
                }
            ]
        }
    }
}