{
    "original": "Enbom, Sven Albert, tandläkare,\nVänersborg, f. 27/2/12 i Norrtälje av\nciv:ing. Albert E. o. Ehn Korn. G.\n42 m. Kerstin Ottkärr. Barn: Håkan\nf. 43, Birgitta 45. — S;tud:ex. v. Gbgs\nh. latin 31, stud. v. Karol. inst., med.\nkand. v. Lunds univ. 34, tandl. 38.\nPrakt, i Vargön o. Vänersborg.\n\nEncrantz, Bernhard Gustaf\nEricsson, jägmästare, Kalmar, f. 19/1/92 i\nEnvikens förs., Kopparb. 1., av\nkontr:-prosten Anders Gustaf Ericsson o.\nHedda Fahlcrantz. G. 17 m. Elna\nFredriksson. Barn: Carl-Gustaf f. 18,\ntrafikflyg, i ABA-SILA, löjtn. i flygv.\n\nres., Jan-Carl 20, med. lic.,\nElna-Britta 20, DSI, Margareta 26, stud.\n— Stud:ex. i Falun 10, utex. fr.\nskogsinst. h. kurs 16. Anst. i\ndomänverket sed. 16, assist, i Pajala\no. Tärendö revir 17, i Jukkasjärvi o.\nVettasjoka 18,- und:lär. v. Koldeberga\nskogssk. 20, assist, i Linköp. o. Tjusts\nrevir 35, jägmäst. i Gällivare revir 38\no. i Kalmar revir sed. 45. Distr :chef\ni bränslekomm. 17-18, ordf. i N. Åsbo\nhärads soc:dem. kretsorg. 30-35, led.\nav styr. f. Skånes soc:dem. partidistr.\n32-35, landstingsm. i Krist. 1. 36-38,\nhemv :omr :befälh. i Gällivare 40-44,\nordf. i Norrb. hemv :omr :befälh.\nläns-förb. 42. Norrb. landst:förb.\nförtj:-SM.\n\nEnderlein, Karl Johan Werner,\ncivilingenjör, Dals Långed, f. 17/12/07 i\nRydöbruk, Jönköp. I., av ing. E. R. E.\no. Edla von Stapelmohr. G. 35 m. Eva\nDahr Perleff. Barn : Eva Elisabeth f. 36,\nAnnie 38. — Stud:ex. i Oslo 24,\nma-skining. NTH i Trondheim 29. Res.\nt. Tyskl. 27, 29, 33, USA 36, 37. Anst.\nv. A/S Böhnsdalen Milk Ltd, Bön,\nNorge, 3IOi-34, v. A/S Foren. Papirfalbr.\ni Drammen 34-36, v. A/S Vittingfo&amp;s\nBr. i Vittingfoss, Norge, 37-38, v.\nLa-gamills A-B i Timsfors 38-43, h. A-B\nBillingsfors-Långed s. fabr :föres’t. o.\nplatschef v. Långedsverken 43,\növer-ing. fr. 45. Hoibby: friluftsliv.\n\n",
    "structured": {
        "0": {
            "full_name": "Enbom, Sven Albert",
            "location": "Vänersborg",
            "occupation": "tandläkare",
            "birth_details": {
                "date": "27/02/1912",
                "place": "Norrtälje",
                "parents": "civ.ing. Albert E. och Ehn Korn"
            },
            "education": [
                {
                    "degree": "stud.ex. v. Gbgs h. latin",
                    "year": "1931",
                    "institution": "Gbgs h. latin"
                },
                {
                    "degree": "med. kand.",
                    "year": "1934",
                    "institution": "Lunds univ."
                },
                {
                    "degree": "tandl.",
                    "year": "1938",
                    "institution": "NULL"
                }
            ],
            "career": [
                {
                    "position": "Prakt",
                    "years": {
                        "start_year": 1938,
                        "end_year": "NULL"
                    },
                    "organization": "Vargön och Vänersborg"
                }
            ],
            "family": {
                "spouse": "Kerstin Ottkärr",
                "marriage_year": "1942",
                "children": [
                    {
                        "name": "Håkan",
                        "birth_year": "1943"
                    },
                    {
                        "name": "Birgitta",
                        "birth_year": "1945"
                    }
                ]
            }
        },
        "1": {
            "full_name": "Encrantz, Bernhard Gustaf Ericsson",
            "location": "Kalmar",
            "occupation": "jägmästare",
            "birth_details": {
                "date": "19/01/1892",
                "place": "Envikens förs., Kopparb. l.",
                "parents": "kontr:-prosten Anders Gustaf Ericsson och Hedda Fahlcrantz"
            },
            "education": [
                {
                    "degree": "Stud:ex. i Falun",
                    "year": "1910",
                    "institution": "NULL"
                },
                {
                    "degree": "utex. fr. skogsinst. h. kurs",
                    "year": "1916",
                    "institution": "skogsinst."
                }
            ],
            "career": [
                {
                    "position": "Distr",
                    "years": {
                        "start_year": 1917,
                        "end_year": 1918
                    },
                    "organization": "bränslekomm."
                },
                {
                    "position": "ordf",
                    "years": {
                        "start_year": 1930,
                        "end_year": 1935
                    },
                    "organization": "N. Åsbo härads soc:dem. kretsorg."
                },
                {
                    "position": "landstingsm.",
                    "years": {
                        "start_year": 1936,
                        "end_year": 1938
                    },
                    "organization": "Krist. l."
                },
                {
                    "position": "hemv :omr :befälh.",
                    "years": {
                        "start_year": 1940,
                        "end_year": 1944
                    },
                    "organization": "Gällivare"
                },
                {
                    "position": "ordf.",
                    "years": {
                        "start_year": 1942,
                        "end_year": "NULL"
                    },
                    "organization": "Norrb. hemv :omr :befälh. läns-förb."
                }
            ],
            "family": {
                "spouse": "Elna Fredriksson",
                "marriage_year": "1917",
                "children": [
                    {
                        "name": "Carl-Gustaf",
                        "birth_year": "1918"
                    },
                    {
                        "name": "Jan-Carl",
                        "birth_year": "1920"
                    },
                    {
                        "name": "Elna-Britta",
                        "birth_year": "1920"
                    },
                    {
                        "name": "Margareta",
                        "birth_year": "1926"
                    }
                ]
            }
        },
        "2": {
            "full_name": "Enderlein, Karl Johan Werner",
            "location": "Dals Långed",
            "occupation": "civilingenjör",
            "birth_details": {
                "date": "17/12/1907",
                "place": "Rydöbruk, Jönköp. l.",
                "parents": "ing. E. R. E. och Edla von Stapelmohr"
            },
            "education": [
                {
                    "degree": "Stud:ex. i Oslo",
                    "year": "1924",
                    "institution": "Oslo"
                },
                {
                    "degree": "ma-skining. NTH i Trondheim",
                    "year": "1929",
                    "institution": "Trondheim"
                }
            ],
            "career": [
                {
                    "position": "assist",
                    "years": {
                        "start_year": 1916,
                        "end_year": 1916
                    },
                    "organization": "domänverket"
                },
                {
                    "position": "und:lär. v. Koldeberga skogssk.",
                    "years": {
                        "start_year": 1920,
                        "end_year": "NULL"
                    },
                    "organization": "Koldeberga skogssk."
                },
                {
                    "position": "assist",
                    "years": {
                        "start_year": 1935,
                        "end_year": "NULL"
                    },
                    "organization": "Linköp. o. Tjusts revir"
                },
                {
                    "position": "platschef v. Långedsverken",
                    "years": {
                        "start_year": 1943,
                        "end_year": "NULL"
                    },
                    "organization": "A-B Billingsfors-Långed s. fabr"
                },
                {
                    "position": "över-ing.",
                    "years": {
                        "start_year": 1945,
                        "end_year": "NULL"
                    },
                    "organization": "NULL"
                }
            ],
            "family": {
                "spouse": "Eva Dahr Perleff",
                "marriage_year": "1935",
                "children": [
                    {
                        "name": "Eva Elisabeth",
                        "birth_year": "1936"
                    },
                    {
                        "name": "Annie",
                        "birth_year": "1938"
                    }
                ]
            },
            "hobbies": [
                "friluftsliv"
            ]
        }
    }
}