{
    "original": "Ekselius, Paul Oskar Georg, lektor,\nKalmar, f. 16/4/05 i Alem, Kalmar 1.\nG. 34 m. Ann-Mari Thunberg. Barn:\nJöran f. 39, Gabriella 43. — Stud:ex.\ni Kalmar 25, fil. mag. i Upps. 29, fil.\nlic. 34, fil. dr 40, provår i Upps. 35.\nRes. t. Frankr. 27, Engl. 32, Tyskl. 38.\nVik. adj. i Malmö 34, e. o. ämneslär.\ni Saltsjöbaden 36-39, e. adj. i\nHalmstad 40, lektor i eng. o. franska v.\nKalmar h. a. 1. sed. 40. Skr.: A Study\non the Development of the Old Engl.\nCombinations aht/oht in Middle Engl.\n(grad:avh. 40).\n\nEksell, Gustaf Erik, häradshövding,\nSkara, f. 14/7/94 i Kisa, östergötl. 1.,\nav fabr. Levin E. o. Hildegard\nDju-lang. G. 20 m. Tyra Strandeli. Barn:\nBengt f. 21, Mait 23, Lisbeth 25,\nAnders 28. — Stud:ex. i Linköp. 12, jur.\nkand. i Sthlm 16. Tingstjg. i\nOvan-siijans o. Failu doms. 17-22, förste\nrådman i Skara 22-28, borgmäst. där\n28-40, tillika not. publ., häradshövd. i\nSkarabygdens doms. sed. 40. Ordf. i\nbyggn:nd 22-40, led. av landstinget o.\ndess förvaltn :utsk. sed. 39, ordf. i\nkristidsstyr. 39, i styr. f. Skarab. Läns\nSparbank 41, i Skarab. o. Älvsb. läns\nsparbanksfören. 42, i ndn f. lindr. av\narrendevillkor i div. län 42, i\nskilje-ndn enl. järnv rtrafikstadg., ied. av\nstyr. f. Skara sjulkh.. Skara\ndomkyrkas vänner, Västergötl.\nturisttrafik-förb., Västergötl. fornminnesfören.\no. Sv. sparbanksfören. 46. RNO, RVO.\n\nEkseli, Carl Åke Bertil, tandläkare,\nAneby, f. 4/3/02 i Säby, Jönköp. 1., av\nköpm. Carl Axel E. o. Eirsabeth\nZetterberg. G. 31 m. Elisabeth Slama.\nBarn: Jan f. 33, Gun 34. •— Stud :ex.\ni Linköp. 22, tandl :kand. 28, tandläk.\n31. Assist, i Tranås 31, praktik i\nAneby sed. s. å., skoltandl. i Bredestads\nkommun sed. 36, i Marbäcks o. Fiisby\nsed. 37 o. i Lommaryds ised. 38,\ndistr:-tandläk. i Aneby sed. 40. Sv.\nJägar-förb. hed:tS.\n\n",
    "structured": {
        "0": {
            "full_name": "Ekselius, Paul Oskar Georg",
            "location": "Kalmar",
            "occupation": "lektor",
            "birth_details": {
                "date": "16/04/1905",
                "place": "Alem, Kalmar",
                "parents": null
            },
            "education": [
                {
                    "degree": "Stud",
                    "year": "1925",
                    "institution": "Kalmar"
                },
                {
                    "degree": "fil. mag.",
                    "year": "1929",
                    "institution": "Upps"
                },
                {
                    "degree": "fil. lic.",
                    "year": "1934",
                    "institution": null
                },
                {
                    "degree": "fil. dr",
                    "year": "1940",
                    "institution": null
                }
            ],
            "career": [
                {
                    "position": "Vik. adj.",
                    "years": {
                        "start_year": 1934,
                        "end_year": 1934
                    },
                    "organization": "Malmö"
                },
                {
                    "position": "e. o. ämneslär.",
                    "years": {
                        "start_year": 1936,
                        "end_year": 1939
                    },
                    "organization": "Saltsjöbaden"
                },
                {
                    "position": "e. adj.",
                    "years": {
                        "start_year": 1940,
                        "end_year": 1940
                    },
                    "organization": "Halmstad"
                },
                {
                    "position": "lektor",
                    "years": {
                        "start_year": 1940,
                        "end_year": null
                    },
                    "organization": "Kalmar"
                }
            ],
            "family": {
                "spouse": "Ann-Mari Thunberg",
                "marriage_year": "1934",
                "children": [
                    {
                        "name": "Jöran",
                        "birth_year": "1939"
                    },
                    {
                        "name": "Gabriella",
                        "birth_year": "1943"
                    }
                ]
            }
        },
        "1": {
            "full_name": "Eksell, Gustaf Erik",
            "location": "Skara",
            "occupation": "häradshövding",
            "birth_details": {
                "date": "14/07/1894",
                "place": "Kisa, östergötl. 1.",
                "parents": "fabr. Levin E. o. Hildegard Dju-lang"
            },
            "education": [
                {
                    "degree": "Stud",
                    "year": "1912",
                    "institution": "Linköp"
                },
                {
                    "degree": "jur. kand.",
                    "year": "1916",
                    "institution": "Sthlm"
                }
            ],
            "career": [
                {
                    "position": "Tingstjg.",
                    "years": {
                        "start_year": 1917,
                        "end_year": 1922
                    },
                    "organization": "Ovan-siijans o. Failu doms."
                },
                {
                    "position": "förste rådman",
                    "years": {
                        "start_year": 1922,
                        "end_year": 1928
                    },
                    "organization": "Skara"
                },
                {
                    "position": "borgmäst.",
                    "years": {
                        "start_year": 1928,
                        "end_year": 1940
                    },
                    "organization": "Skara"
                },
                {
                    "position": "häradshövd.",
                    "years": {
                        "start_year": 1940,
                        "end_year": null
                    },
                    "organization": "Skarabygdens doms."
                }
            ],
            "family": {
                "spouse": "Tyra Strandeli",
                "marriage_year": "1920",
                "children": [
                    {
                        "name": "Bengt",
                        "birth_year": "1921"
                    },
                    {
                        "name": "Mait",
                        "birth_year": "1923"
                    },
                    {
                        "name": "Lisbeth",
                        "birth_year": "1925"
                    },
                    {
                        "name": "Anders",
                        "birth_year": "1928"
                    }
                ]
            }
        },
        "2": {
            "full_name": "Ekseli, Carl Åke Bertil",
            "location": "Aneby",
            "occupation": "tandläkare",
            "birth_details": {
                "date": "04/03/1902",
                "place": "Säby, Jönköp. 1.",
                "parents": "köpm. Carl Axel E. o. Eirsabeth Zetterberg"
            },
            "education": [
                {
                    "degree": "Stud",
                    "year": "1922",
                    "institution": "Linköp"
                },
                {
                    "degree": "tandl :kand.",
                    "year": "1928",
                    "institution": null
                },
                {
                    "degree": "tandläk.",
                    "year": "1931",
                    "institution": null
                }
            ],
            "career": [
                {
                    "position": "Assist",
                    "years": {
                        "start_year": 1931,
                        "end_year": null
                    },
                    "organization": "Tranås"
                },
                {
                    "position": "skoltandl.",
                    "years": {
                        "start_year": 1936,
                        "end_year": null
                    },
                    "organization": "Bredestads kommun"
                },
                {
                    "position": "distr:-tandläk.",
                    "years": {
                        "start_year": 1940,
                        "end_year": null
                    },
                    "organization": "Aneby"
                }
            ],
            "family": {
                "spouse": "Elisabeth Slama",
                "marriage_year": "1931",
                "children": [
                    {
                        "name": "Jan",
                        "birth_year": "1933"
                    },
                    {
                        "name": "Gun",
                        "birth_year": "1934"
                    }
                ]
            }
        }
    }
}