{
    "original": "Ejeman, Per David, stadsfogde,\nLinköping, f. 16/2/98 i Linköp. G. 31 m.\nDagmar Lundberg. Barn: Göran f. 33,\nKerstin 39. — Stud:ex. i Linköp. 16,\nkansliex. i Upps. 20. Not. å Linköp.\nstads kansli 20-24, tf. stadsfogde i\nLinköp. 24, ord. dito sed. 27. Ordf.\ni tax:nd 30-43, ordf. i Linköp. bef\n:-utb:fören., led. av styr. f. Linköp.\nfo bef :utb :förb. o. Linköp. ork:fören.,\nsekr. i kyrkoråd o. kyrkofullm. sed.\n25. Hobby: musik. CBF förtj :SM.\n\nEk, Carl H., bankdirektör, Eksjö, f.\n8/5/06 i Sköns s:n, Västernorrl. 1., av\njordbr linsp. Carl E. o. Anna Eklöf.\nG. 44 m. Margit Brorsson. Barn:\nMargareta f. 46. — Stud:ex. 25. Sv.\nsparb:fören. stip. t. Tyskl. 37. Anst.\nv. Oppunda Härads Sparbank i\nKatrineholm 25-36, huv:kassör i Kronob.\nL. Sparbank i Växjö 36-41, kamr. i\nSparbanken i Lund 41-44, dir. f.\nEksjö Sparbank ’sed. 44, styr :’led. där\nsed. 45. Supp’1. i styr. f. Smålands\no. Ölands ’sparbanksförening,\nkassör o. sekr. i Kronob. 1. sparb:fören.\n38-41, sekr. o. kassör i Katrineholms\nskyttegille 29-32, kassör i\nKatrineholms AIK 32-34, sekr. o. kassör i\nd’ess orienteringssektion 32-36, ordf. i\nLunds orienteringskl. 43-44, led. av\nSkogskarlarnas kl. Skr.: div. upps.\n\ni Sv. sparb :tidskr., Sparb:nytt o.\nSparfrämjaren. Hobby: orientering.\nIdr :m. i guld, orienteringsm. i guld.\n\nEk, Nils David, häradsdomare,\nÖstra Tollstad, Mantorp, f. 25/6/98 i Ö.\nToilltstad, östergötl. k, av Johan Ek o.\nMaria Ek. — Äg. o. bruk. Tollstad\nNorrgård. Nämndem. 27, här:dom. 45,\nlandstingsman 34-46, ordf. i\nöstergötl. länsförb. av RLF 41, rev. i\nMjötllkoeimtr. 45, led. av styr. f. öisitgöita\nhypoteksfören. 41, led. av styr. f.\nöstergötl. andelsslakt :fören. 46,\nlandstingsrev. 44, ordf. i komm :ful’lm.,\nfat-tigv:styr,, barnav:nd, kristidsnd o.\nbo-ställsstyr. m. m.\n\n",
    "structured": {
        "1": {
            "full_name": "Ejeman, Per David",
            "location": "Linköping",
            "occupation": "stadsfogde",
            "birth_details": {
                "date": "16/02/1898",
                "place": "Linköping"
            },
            "education": [
                {
                    "degree": "Stud:ex.",
                    "year": "1916",
                    "institution": "Linköping"
                },
                {
                    "degree": "kansliex.",
                    "year": "1920",
                    "institution": "Uppsala"
                }
            ],
            "career": [
                {
                    "position": "Not.",
                    "years": {
                        "start_year": 1920,
                        "end_year": 1924
                    },
                    "organization": "Linköp. stads kansli"
                },
                {
                    "position": "tf. stadsfogde",
                    "years": {
                        "start_year": 1924,
                        "end_year": 1927
                    },
                    "organization": "Linköping"
                },
                {
                    "position": "ord. dito",
                    "years": {
                        "start_year": 1927,
                        "end_year": null
                    },
                    "organization": "Linköping"
                },
                {
                    "position": "Ordf.",
                    "years": {
                        "start_year": 1930,
                        "end_year": 1943
                    },
                    "organization": "tax:nd"
                }
            ],
            "family": {
                "spouse": "Dagmar Lundberg",
                "marriage_year": "1931",
                "children": [
                    {
                        "name": "Göran",
                        "birth_year": "1933"
                    },
                    {
                        "name": "Kerstin",
                        "birth_year": "1939"
                    }
                ]
            },
            "hobbies": [
                "musik"
            ]
        },
        "2": {
            "full_name": "Ek, Carl H.",
            "location": "Eksjö",
            "occupation": "bankdirektör",
            "birth_details": {
                "date": "8/05/1906",
                "place": "Sköns s:n, Västernorrl. 1."
            },
            "education": [
                {
                    "degree": "Stud:ex.",
                    "year": "1925",
                    "institution": null
                }
            ],
            "career": [
                {
                    "position": "anst.",
                    "years": {
                        "start_year": 1925,
                        "end_year": 1936
                    },
                    "organization": "Oppunda Härads Sparbank i Katrineholm"
                },
                {
                    "position": "huv:kassör",
                    "years": {
                        "start_year": 1936,
                        "end_year": 1941
                    },
                    "organization": "Kronob. L. Sparbank i Växjö"
                },
                {
                    "position": "kamr.",
                    "years": {
                        "start_year": 1941,
                        "end_year": 1944
                    },
                    "organization": "Sparbanken i Lund"
                },
                {
                    "position": "dir.",
                    "years": {
                        "start_year": 1944,
                        "end_year": null
                    },
                    "organization": "Eksjö Sparbank"
                }
            ],
            "family": {
                "spouse": "Margit Brorsson",
                "marriage_year": "1944",
                "children": [
                    {
                        "name": "Margareta",
                        "birth_year": "1946"
                    }
                ]
            },
            "publications": [
                {
                    "title": "Sv. sparb:tidskr."
                },
                {
                    "title": "Sparb:nytt"
                },
                {
                    "title": "Sparfrämjaren"
                }
            ],
            "hobbies": [
                "orientering"
            ]
        },
        "3": {
            "full_name": "Ek, Nils David",
            "location": "Östra Tollstad, Mantorp",
            "occupation": "häradsdomare",
            "birth_details": {
                "date": "25/06/1898",
                "place": "Östra Tollstad"
            },
            "career": [
                {
                    "position": "Äg. o. bruk. Tollstad Norrgård"
                }
            ],
            "family": {
                "spouse": null,
                "marriage_year": "NULL",
                "children": null
            }
        }
    }
}