{
    "original": "Ellison, Carl Elis, disponent,\nNorrköping, f. 27/10/90 i Ringarum,\nÖs-tergötl. 1., av byggmäst. Carl August\nE. o. Elin Maria Engström. G. 14\nm. Ruth Bohlin. Barn: Carl Lennart\n\nf.\t15, Ruth Gunnel 21. — Stud. v.\nhandrsk. samt i Engl. Verkst dir. i\nA-B Manus i Norrköp. sed. 20. Led.\nav stadsfullm., drätselkamm., hälso- c.\nsjukvistyr., uppbördsv. m. m. RVO,\nPatrstGM.\n\nEllison, Carl Lennart, direktör, leg.\napotekare, Norrköping, f. 22/9/15 i\nBorg, östergötl. 1., av disp. Elis E. o.\nRuith Bohtlin. G. 41 m. Gun&gt;nie(l\nAn-dersén. Barn: Bengt f. 43, Marianne\n46. — Stud :ex. i Norrköp. 34, farm.\nkand. 38, hand:- o. språkstud. samt\nrev:byråprakt. 39-40, apot:ex. 43.\nStud:res. t. Danm. o. Engl. 45. Elev\nv. apot. Kronan i Norrköp. 34-37,\nkand:tjg. v. apot. Svanen i Norrköp.\n38 o. v. apot. i Mjölby 40-41, laborant\nv. Svanen i Norrköp. 43-44. Kamr. i\nA-B Manus i Norrköp. 40, dir:assist.\ndär fr. 44 samt v. verkst. dir. där\nsed. 46. Led. av styr. f. A-B Manus\ni Norrköp. sed. 38 o. Upsala\nSeparator A-B där sed. 45. Värnpl. fänrik\nfr. 40 m. tjg. bl. a. v. krigssjukh. på\nGotl.\n\nElmberg, Ragnar Gustaf Henrik,\nmajor, Växjö, f. 16/9/94 i Karlskrona\nav flaggund :off. Axel E. o. Elvira\nSvensson. G. 20 m. Edla Maria\nLinderoth. Barn: Björn f. 22, Birgitta 25,\n\ng.\tm. löjtn. i flygv. res. Erik Krook,\nBo 33, Bengt 35, d. 35. — Stud:ex.\nv. Karls’krona h. a. 1. 13, off :ex. 15,\nvapenoff :kurs i Eskilstuna 32. Fänrik\nv. fd. Karlskrona gren :reg. 15, löjtn.\ndär 17, kapt. i Kronob. reg. 30, kapt.\nv. reg. 36, förtidspens. 42, tygoff. v.\nVäxjö-Jönköp. fo-stab 42-46, major i\narmén 44, exp :off. v. io 11 fr. 47. RSO.\n\nElmén, Sven Gustaf, advokat,\nGöteborg, f. 4/9/04 i Gbg av postkontr.\nCarl E. o. Märta Landin. G. 35 m.\nAnna Lisa Olson. Barn: Inger f. 36,\nAnn 40, Håkan 43, Staffan 47. — Stud\n:-ex. v. Gbgs real 23, jur. kand. i Lund 29.\nTingstjg. i Hall. norra doms. 30-31, i\n\nVartofta o. Frökinds doms. 31-33,\nbitr. å adv:kont. 33-34, egen\nadv:verk-’Samh. i Gbg sod. 34. Lär. i hand :rätt\nv. Gbgs hand :inst. 39-44. Led. av\nSv:es adv:samf. sed. 38.\n\n",
    "structured": {
        "0": {
            "full_name": "Ellison, Carl Elis",
            "location": "Norrköping",
            "occupation": "Disponent",
            "birth_details": {
                "date": "27/10/1890",
                "place": "Ringarum, Östergötland"
            },
            "education": [
                {
                    "degree": "Stud. v. handrsk.",
                    "year": "N/A",
                    "institution": "N/A"
                },
                {
                    "degree": "Engl.",
                    "year": "N/A",
                    "institution": "N/A"
                }
            ],
            "career": [
                {
                    "position": "Verkst dir.",
                    "years": {
                        "start_year": 1920,
                        "end_year": null
                    },
                    "organization": "A-B Manus i Norrköping"
                }
            ],
            "family": {
                "spouse": "Ruth Bohlin",
                "marriage_year": "14",
                "children": [
                    {
                        "name": "Carl Lennart",
                        "birth_year": "15"
                    },
                    {
                        "name": "Ruth Gunnel",
                        "birth_year": "21"
                    }
                ]
            }
        },
        "1": {
            "full_name": "Ellison, Carl Lennart",
            "location": "Norrköping",
            "occupation": "Direktör, leg. apotekare",
            "birth_details": {
                "date": "22/09/1915",
                "place": "Borg, Östergötland"
            },
            "education": [
                {
                    "degree": "Stud:ex.",
                    "year": "1934",
                    "institution": "Norrköping"
                },
                {
                    "degree": "Farm. kand.",
                    "year": "1938",
                    "institution": "N/A"
                }
            ],
            "career": [
                {
                    "position": "Kand:tjg.",
                    "years": {
                        "start_year": 1938,
                        "end_year": 1940
                    },
                    "organization": "Norrköping"
                },
                {
                    "position": "Laborant",
                    "years": {
                        "start_year": 1943,
                        "end_year": 1944
                    },
                    "organization": "Svanen i Norrköping"
                }
            ],
            "family": {
                "spouse": "Gunnie(l Andersén",
                "marriage_year": "41",
                "children": [
                    {
                        "name": "Bengt",
                        "birth_year": "43"
                    },
                    {
                        "name": "Marianne",
                        "birth_year": "46"
                    }
                ]
            }
        },
        "2": {
            "full_name": "Elmberg, Ragnar Gustaf Henrik",
            "location": "Växjö",
            "occupation": "Major",
            "birth_details": {
                "date": "16/09/1894",
                "place": "Karlskrona"
            },
            "education": [
                {
                    "degree": "Stud:ex.",
                    "year": "1913",
                    "institution": "Karlskrona h. a. l."
                },
                {
                    "degree": "Off:ex.",
                    "year": "1915",
                    "institution": "N/A"
                }
            ],
            "career": [
                {
                    "position": "RSO",
                    "years": {
                        "start_year": 1947,
                        "end_year": null
                    },
                    "organization": "N/A"
                }
            ],
            "family": {
                "spouse": "Edla Maria Linderoth",
                "marriage_year": "20",
                "children": [
                    {
                        "name": "Björn",
                        "birth_year": "22"
                    },
                    {
                        "name": "Birgitta",
                        "birth_year": "25"
                    }
                ]
            }
        },
        "3": {
            "full_name": "Elmén, Sven Gustaf",
            "location": "Göteborg",
            "occupation": "Advokat",
            "birth_details": {
                "date": "04/09/1904",
                "place": "Göteborg"
            },
            "education": [
                {
                    "degree": "Stud :ex.",
                    "year": "1923",
                    "institution": "Gbgs real"
                },
                {
                    "degree": "Jur. kand.",
                    "year": "1929",
                    "institution": "Lund"
                }
            ],
            "career": [
                {
                    "position": "Lär.",
                    "years": {
                        "start_year": 1939,
                        "end_year": 1944
                    },
                    "organization": "Gbgs hand :inst."
                }
            ],
            "family": {
                "spouse": "Anna Lisa Olson",
                "marriage_year": "35",
                "children": [
                    {
                        "name": "Inger",
                        "birth_year": "36"
                    },
                    {
                        "name": "Ann",
                        "birth_year": "40"
                    },
                    {
                        "name": "Håkan",
                        "birth_year": "43"
                    },
                    {
                        "name": "Staffan",
                        "birth_year": "47"
                    }
                ]
            }
        }
    }
}