{
    "original": "Ekeroth, Gustav Fredrik,\nilärovierks-adjunkt, Göteborg, f. 16/5/85 i Fjärås,\nHaW. 1., av kyrkoh. Anders Gust. E.\no. Svea Larsson. G. 15 m. Elsa\nWåh-Hn. Barn: Siv f. 17, d. s. å. —\nStud:-ex. i Skara 04, fil. mag. 12, provår v.\nGbgs h. latin 13. E. o. lär. i Hälsingb.\n14-22, e. lär. i Malmö 22-26, adj. i\nUddevalla 26-37, adj. i tyska o. eng. v.\nHvitfeldtska h. a. 1. i Gbg sed. 37. Res.\nt. Tyskl. o. Frankr. RVO 46.\n\nEkerot, Nils Fredrik, rektor,\nBräkne-Hoby, f. 26/5/04 i Kristianstad av\növerdiii-,. V. E. o. Mannia CairilisBOn.\nG. 31 m. Greta Huligren. Barn:\nKerstin f. 32, Lars 36. — Stud:ex. 23,\nagron :ex. v. Alnarp’s lantbr:- o.\nme-jeriinst. 28. Re.s. t. Tyskl. 25, Danm.\n28. E. o. ämneslär. v. Önnestads\nlant-m:sk. 28-30, ämneslär. v. Blek. 1.\nlant-m :sk. 30-47, rektor Lsed. 47. Försöksil-ed.\nh. B’1’ek. ’1. försökriingar sed. 32. Förv.\nBinga e-gend., Ho^s-smo, sed. 38. Av. K.\nMaj:t förordn. s. ordf. i jordbr :komm.\ni BLek. I. 46, ordf. i hush :’sälLsk.\nJUF-komm. 46, v. ordf. i JUF-distr. 41,\nsekr. i län. lantbr :kl. 41, i lantmänn.\nfören:nd i Blek. 43, hush :säll’sk. repr.\ni länsblockmyndigh. 42.\n\nEkfeldt, Karl-Gustaf, direktör,\nNorrköping, f. 20/6/13 i Norrköp. av\nGustaf E. o. Anna Lund. G. m. Evy\nLantz. — Realex. samt språkstud. Res.\nt. Norge, Danm., Tyskl. o. Holl. Anst.\ni H. Unér A-B i Norrköp. 31-32, v.\nLifförsäkr. A-B Thules distr :kont.\n32-36, v. Rederi A-B Norden sed.^ 36,\nRederi A-B Simrishamn 41-46 o.\nÅngfartygs A-B Nyköping sed. 42, verks’t.\ndir. o. styr :led. i sistnämnda bol.\nMedl. av Ödd Fellow. Hobbies:\ntennis o. segling.\n\nEkholm, Carl William, kyrkoherde,\nLocknevi, f. 16/7/91 i Betul, Indien,\nav missions pastor Frans E. o. h. h. f.\nPrice. G. 18 m. Ingeborg Söderbäck.\nBarn: Laisa f. 23, Per 26, Margareta\n28. ~ Stud:ex. i Upps. 12, teok fil.\nex. 13, teoi. kand., prakt. teol. prov\no. prästv. f. ärkestiftet 16. Tf.\nkom-min. i Vätö 17, kommin. i Ingatorp\n21, kyrkoh. i Locknevi sed. 29. Ordf.\ni kyrko- o. past:stämmorna, i styr. f.\nLocknevi folkbibi. ’samt i Locknevi\nskolstyr. Riksantikv. omb. f. Locknevi\nsocken. Finl. med. f. hum. verks.\n\n",
    "structured": {
        "0": {
            "full_name": "Gustav Fredrik Ekeroth",
            "location": "Göteborg",
            "occupation": "ilärovierks-adjunkt",
            "birth_details": {
                "date": "16/05/1885",
                "place": "Fjärås"
            },
            "education": [
                {
                    "degree": "Stud:-ex.",
                    "year": "1904",
                    "institution": "Skara"
                },
                {
                    "degree": "fil. mag.",
                    "year": "1912",
                    "institution": "Gbgs h. latin"
                }
            ],
            "career": [
                {
                    "position": "e. lär.",
                    "years": {
                        "start_year": 1922,
                        "end_year": 1926
                    },
                    "organization": "Malmö"
                },
                {
                    "position": "adj.",
                    "years": {
                        "start_year": 1926,
                        "end_year": 1937
                    },
                    "organization": "Uddevalla"
                },
                {
                    "position": "adj.",
                    "years": {
                        "start_year": 1937,
                        "end_year": 1937
                    },
                    "organization": "Hvitfeldtska h. a. 1. i Gbg"
                }
            ],
            "family": {
                "spouse": "Elsa Wåh-Hn",
                "marriage_year": "15",
                "children": [
                    {
                        "name": "Siv",
                        "birth_year": "17"
                    }
                ]
            }
        },
        "1": {
            "full_name": "Nils Fredrik Ekerot",
            "location": "Bräkne-Hoby",
            "occupation": "rektor",
            "birth_details": {
                "date": "26/05/1904",
                "place": "Kristianstad"
            },
            "education": [
                {
                    "degree": "Stud:ex.",
                    "year": "1923",
                    "institution": "NULL"
                },
                {
                    "degree": "agron :ex.",
                    "year": "1928",
                    "institution": "Alnarp’s lantbr:- o. me-jeriinst."
                }
            ],
            "career": [
                {
                    "position": "ämneslär.",
                    "years": {
                        "start_year": 1930,
                        "end_year": 1947
                    },
                    "organization": "Blek. 1. lant-m :sk."
                },
                {
                    "position": "rektor",
                    "years": {
                        "start_year": 1947,
                        "end_year": 1947
                    },
                    "organization": "Lsed."
                }
            ],
            "family": {
                "spouse": "Greta Huligren",
                "marriage_year": "31",
                "children": [
                    {
                        "name": "Kerstin",
                        "birth_year": "32"
                    },
                    {
                        "name": "Lars",
                        "birth_year": "36"
                    }
                ]
            }
        },
        "2": {
            "full_name": "Karl-Gustaf Ekfeldt",
            "location": "Norrköping",
            "occupation": "direktör",
            "birth_details": {
                "date": "20/06/1913",
                "place": "Norrköp."
            },
            "education": [
                {
                    "degree": "Realex.",
                    "year": "NULL",
                    "institution": "NULL"
                },
                {
                    "degree": "språkstud.",
                    "year": "NULL",
                    "institution": "NULL"
                }
            ],
            "career": [
                {
                    "position": "verks’t. dir.",
                    "years": {
                        "start_year": 1942,
                        "end_year": 1946
                    },
                    "organization": "Ångfartygs A-B Nyköping"
                }
            ],
            "family": {
                "spouse": "Evy Lantz",
                "marriage_year": "NULL",
                "children": []
            },
            "hobbies": [
                "tennis",
                "segling"
            ]
        },
        "3": {
            "full_name": "Carl William Ekholm",
            "location": "Locknevi",
            "occupation": "kyrkoherde",
            "birth_details": {
                "date": "16/07/1891",
                "place": "Betul, Indien"
            },
            "education": [
                {
                    "degree": "Stud:ex.",
                    "year": "1912",
                    "institution": "Upps."
                },
                {
                    "degree": "teok fil. ex.",
                    "year": "1913",
                    "institution": "NULL"
                }
            ],
            "career": [
                {
                    "position": "kommin.",
                    "years": {
                        "start_year": 1921,
                        "end_year": 1929
                    },
                    "organization": "Ingatorp"
                },
                {
                    "position": "kyrkoh.",
                    "years": {
                        "start_year": 1929,
                        "end_year": 1929
                    },
                    "organization": "Locknevi"
                }
            ],
            "family": {
                "spouse": "Ingeborg Söderbäck",
                "marriage_year": "18",
                "children": [
                    {
                        "name": "Laisa",
                        "birth_year": "23"
                    },
                    {
                        "name": "Per",
                        "birth_year": "26"
                    },
                    {
                        "name": "Margareta",
                        "birth_year": "28"
                    }
                ]
            }
        }
    }
}