{
    "original": "Edelman, Ernst William,\nkyrkoherde, Åker, f. 27/6/88 i Björnekulla,\nKrist. 1., av Olof E. o. Ellen Robsahm.\nG. 20 m. sjuksköt. Esther Andersson.\nBarn: Christer f. 21. — Stud:ex. i\nUpps. 13, teol. fil. ex. där 16, teol.\nkand., prakt. teol. prov samt prästv.\nf. Växjö ’Stift 19. Tjg. s. pa!St:adj. i\nRogberga, v. pastor i Åker samt av\npatronus kallad kommin. i Kälieryd,\nkyrkoh. i Åker sed. 23. Kontr :ombud\nf. Växjö stiftsråd 25-27, ombud f.\nmiss :styr. 28-36, ordf. i Åkers\nkyrkostämma, past :iSt. sed. 23, ’skolrådet\n23-31, i skolstyr. sed. 32, ordf. i Kävsjö\nkyrkost. o. kyrkoråd 23-40, i Kävsjö\nskolråd 23-37, led. av eckl. bo^ställsndn\ni VI. distr. ’sed. 36, av s-tyr. f.\nSkil-lingaryds RK-avd.\n\nEdelsteen, Harry Oskar,\nprovinsialläkare, Karlshamn, f. 16/3/90 i\nBrun-flo, Jämtl. 1., av Otto Johan E. o.\nMaria Olivia Wretlindh. G. 33 m.\nRuth Hildegard Olsson. Barn:\nMonica f. 43. — Stud:ex. 10, med. kand.\ni Lund 13, med. lic. där 19. Stud.\nlungtub. i Davos 21-22. Tf. und:läk.\nv. Söderby sjukh. 14, v. Långbro o.\nKatarina sjukh. 15, e. läk. i Fränsta\no. Älvsby distr. 16, andre und:läk. v.\nMalmö allm. sjukh. med. avd. 17, e.\n\nläk. i Strömsunds distr, 18-19,\nprov:-läk. där 19-20, järnv:läk. 20-21, div.\nförordn. s. provrläk. 22, e. prov:läk.\ni Ovanåkers distr. 22-25, prov:läk. i\nHåby distr. 25-32, i Karlshamns distr.\nsed. 32, läk. v. kronohäktet i\nKarlshamn 32-37. Led. av las idirekt.\n\nEdemo, Johan Eskil Richard,\nkyrkoherde, Lerdala, f. 6/2/95 i\nUtväng^s-torp, Skarab. 1. G. 34 m. Dagmar\nGunilla Andersson. Barn: Sven f. 35,\nGunnel 37. — Teol. kand., prästv. 29.\nV. pastor i Järpås 29-33, kommin. i\nVara past. (Skarstad) 3’3-45,\nkyrkoherde i Berg, Skarab. 1., fr. 45. I Järpås\nordf. i kyrkost., kyrkoråd, skolråd o.\nfoiksk :styr., i SkariStad ordf. i\nkyrkost., skolråd, barnav:nd,\nfani:bidr:-nd. I Berg ordf. i kyrkost., skolråd o.\nkyrkoråd.\n\n",
    "structured": {
        "0": {
            "full_name": "Edelman, Ernst William",
            "location": "Åker",
            "occupation": "kyrkoherde",
            "birth_details": {
                "date": "27/06/1888",
                "place": "Björnekulla"
            },
            "education": [
                {
                    "degree": "Stud:ex.",
                    "year": "1913",
                    "institution": "Uppsala"
                },
                {
                    "degree": "teol. fil. ex.",
                    "year": "1916",
                    "institution": "Uppsala"
                },
                {
                    "degree": "teol. kand.",
                    "year": "1919",
                    "institution": "Växjö"
                }
            ],
            "career": [
                {
                    "position": "påSt:adj.",
                    "years": {
                        "start_year": 1923,
                        "end_year": 1923
                    },
                    "organization": "Rogberga"
                },
                {
                    "position": "v. pastor",
                    "years": {
                        "start_year": 1923,
                        "end_year": null
                    },
                    "organization": "Åker"
                }
            ],
            "family": {
                "spouse": "Esther Andersson",
                "marriage_year": "20",
                "children": [
                    {
                        "name": "Christer",
                        "birth_year": "21"
                    }
                ]
            }
        },
        "1": {
            "full_name": "Edelsteen, Harry Oskar",
            "location": "Karlshamn",
            "occupation": "provinsialläkare",
            "birth_details": {
                "date": "16/03/1890",
                "place": "Brunflo"
            },
            "education": [
                {
                    "degree": "Stud:ex.",
                    "year": "1910",
                    "institution": "Lund"
                },
                {
                    "degree": "med. kand.",
                    "year": "1913",
                    "institution": "Lund"
                },
                {
                    "degree": "med. lic.",
                    "year": "1919",
                    "institution": "Lund"
                }
            ],
            "career": [
                {
                    "position": "div. förordn. s. provrläk.",
                    "years": {
                        "start_year": 1922,
                        "end_year": null
                    },
                    "organization": "Håby distr."
                },
                {
                    "position": "läk. v. kronohäktet",
                    "years": {
                        "start_year": 1932,
                        "end_year": 1937
                    },
                    "organization": "Karlshamn"
                }
            ],
            "family": {
                "spouse": "Ruth Hildegard Olsson",
                "marriage_year": "33",
                "children": [
                    {
                        "name": "Monica",
                        "birth_year": "43"
                    }
                ]
            }
        },
        "2": {
            "full_name": "Edemo, Johan Eskil Richard",
            "location": "Lerdala",
            "occupation": "kyrkoherde",
            "birth_details": {
                "date": "6/2/1895",
                "place": "Utvängstorps, Skarab."
            },
            "education": [
                {
                    "degree": "Teol. kand.",
                    "year": "1929",
                    "institution": "NULL"
                }
            ],
            "career": [
                {
                    "position": "v. pastor",
                    "years": {
                        "start_year": 1929,
                        "end_year": 1933
                    },
                    "organization": "Järpås"
                },
                {
                    "position": "kommin.",
                    "years": {
                        "start_year": 1933,
                        "end_year": 1945
                    },
                    "organization": "Vara past. (Skarstad)"
                }
            ],
            "family": {
                "spouse": "Dagmar Gunilla Andersson",
                "marriage_year": "34",
                "children": [
                    {
                        "name": "Sven",
                        "birth_year": "35"
                    },
                    {
                        "name": "Gunnel",
                        "birth_year": "37"
                    }
                ]
            }
        }
    }
}