{
    "original": "DEGERMAN,    ROLF    O,    ingenjör,\n\nSkellefteå, f i Skellefteå 7/5/31 av\nmaskinsköt Ernst D o Bertha Johansson.\nIng:ex HTL Skellefteå 51, ing Kockums\nmek verkstad ab Malmö 52, Ursvikens\nmek verkstad ab 55, Alimak-verken ab\nSkellefteå 56, ab Brod Wikströms mek\nverkstad 63, försäljn:ing Alimak-verken\nab sed 66.\n\nGift 52 m Barbro Nilsson f 33, dtr t\nmålarmäst Sixten N o Sagda Pettersson.\n\n-  Barn: Leif f 58, Kerstin f 62.\n\nDELANG,    BENGT    R,    tandläkare,\n\nLångsele, f i Sthlm 5/1/19 av intend\nRudolf D o Hildur Jakobsson.\nStud:ex 37 o tandl:ex 52 Sthlm,\ndistr:-tandl o förest distr :tandpol Torup\n52-57, Hallstavik 57-58, Söderfors 58-61,\npriv:prakt Långsele sed 61. - Hobby:\nfotografering.\n\nGift 47 m Stina Hedman f 22, dtr t dir\nGeorg H o Estrid Graden. - Barn:\nAnders f 47, Elisabet f 49, Mikael f 54,\nLars f 58.\n\nDELBERG,   KNUT   B,   ombudsman,\n\nSundsvall, f i Örkelljunga, Krist l, 30/4/\n\n06 av murare Johannes Abrahamsson o\nMatilda Svensson.\n\nBrunnsviks folkhögsk 32-33 o 33-34,\nLO-sk 33; frisör t 44, omb :man Sv\nfrisör-arb:förb 44, förb :kassör 61, förb :ordf\n62-66. - Led Sv frisörarb:förb f örb :råd\n36-44 o dess f örb :styr 61-66. - Led\nStadsfullm Sundsvall sed 50, beredn :utsk o\nDK, ordf lönendn 52-64, bibi:styr t 64.\nGift 37 m Lilly Sandström f 17, dtr t K\nA S o Matilda Södergren. - Barn:\nGun-ny f 43.\n\nDELVIN,   S   A  RUNE,   ombudsman,\n\nSöderhamn, f i Sthlm 1/3/26 av elektr\nAlvar D o Margareta Carlsson.\nStud:ex 46 o jur kand Sthlm 51, tingstjg\nÅngermani s doms 51-54, fiskal hovr N\nNorrl 55, bitr vattenr:sekr o e\nvattenr:-sekr Mellanbygd vattendomst 55-57,\nom-fa :man Bergvik o Ala ab Söderhamn sed\n58. - V ordf Ljusnan-Voxnans\nvattenv:-förb sed 60, styr:led Ljusnans kraft ab\nsed 59 m fi bol. - Medl Rotary. - Hobby:\ncurling.\n\nGift 55 m Gudrun Ekelund f 26, dtr t\nrev Gösta E o Ruth Hammarberg.\n-Barn: Göran f 57, Ulrika f 60, Maria\nf 62.\n\nde MARÉ, OLOF G S, överläkare,\nÖstersund, f i Strängnäs 19/5/12 av l:e\nstadsläk Alfred de M o Ellen Sahlgren.\nMed lic Upps 40, öl underläk :förordn\n40-50, bitr sanat :läk Solliden Östersund\n50-51, överläk Österåsens sanat 51-63,\nSollidens sjh Östersund sed 63. - S kr\nupps orn tbc. - Utm: RNO, SRKSM.\n-Hobby: golf.\n\nGift 40 m Ulla Boethius f 18, dtr t\nciv:-ing Per B o Vega Fahlroth. - Barn:\nLennart f 43, Marianne f 45, Hans f 46.\n\n",
    "structured": {
        "1": {
            "full_name": "Rolf O Degerman",
            "location": "Skellefteå",
            "occupation": "ingenjör",
            "birth_details": {
                "date": "07/05/1931",
                "place": "Skellefteå",
                "parents": "maskinsköt Ernst D och Bertha Johansson"
            },
            "education": [
                {
                    "degree": "Ing:ex",
                    "year": "1951",
                    "institution": "HTL Skellefteå"
                }
            ],
            "career": [
                {
                    "position": "ing Kockums mek verkstad ab",
                    "years": {
                        "start_year": 1952,
                        "end_year": 1952
                    },
                    "organization": "Malmö"
                },
                {
                    "position": "Ursvikens mek verkstad ab",
                    "years": {
                        "start_year": 1955,
                        "end_year": 1955
                    },
                    "organization": "ab Brod Wikströms mek verkstad"
                },
                {
                    "position": "Alimak-verken ab",
                    "years": {
                        "start_year": 1956,
                        "end_year": 1956
                    },
                    "organization": "Skellefteå"
                },
                {
                    "position": "försäljn:ing Alimak-verken ab",
                    "years": {
                        "start_year": 1966,
                        "end_year": 1966
                    }
                }
            ],
            "family": {
                "spouse": "Barbro Nilsson",
                "marriage_year": "1952",
                "children": [
                    {
                        "name": "Leif",
                        "birth_year": "1958"
                    },
                    {
                        "name": "Kerstin",
                        "birth_year": "1962"
                    }
                ]
            }
        },
        "2": {
            "full_name": "Bengt R Delang",
            "location": "Långsele",
            "occupation": "tandläkare",
            "birth_details": {
                "date": "05/01/1919",
                "place": "Sthlm",
                "parents": "intend Rudolf D och Hildur Jakobsson"
            },
            "education": [
                {
                    "degree": "Stud:ex",
                    "year": "1937",
                    "institution": "Sthlm"
                },
                {
                    "degree": "tandl:ex",
                    "year": "1952",
                    "institution": "Sthlm"
                }
            ],
            "career": [
                {
                    "position": "distr:-tandl o förest distr :tandpol",
                    "years": {
                        "start_year": 1952,
                        "end_year": 1957
                    },
                    "organization": "Torup"
                },
                {
                    "position": "priv:prakt",
                    "years": {
                        "start_year": 1961
                    },
                    "organization": "Långsele"
                }
            ],
            "family": {
                "spouse": "Stina Hedman",
                "marriage_year": "1947",
                "children": [
                    {
                        "name": "Anders",
                        "birth_year": "1947"
                    },
                    {
                        "name": "Elisabet",
                        "birth_year": "1949"
                    },
                    {
                        "name": "Mikael",
                        "birth_year": "1954"
                    },
                    {
                        "name": "Lars",
                        "birth_year": "1958"
                    }
                ]
            },
            "hobbies": [
                "fotografering"
            ]
        },
        "3": {
            "full_name": "Knut B Delberg",
            "location": "Sundsvall",
            "occupation": "ombudsman",
            "birth_details": {
                "date": "30/04/1906",
                "place": "Örkelljunga, Krist l",
                "parents": "murare Johannes Abrahamsson och Matilda Svensson"
            },
            "education": [
                {
                    "degree": "Brunnsviks folkhögsk",
                    "year": "1932-1933",
                    "institution": "NULL"
                },
                {
                    "degree": "LO-sk",
                    "year": "1933",
                    "institution": "NULL"
                }
            ],
            "career": [
                {
                    "position": "frisör",
                    "years": {
                        "start_year": 1944
                    }
                },
                {
                    "position": "omb :man",
                    "years": {
                        "start_year": 1958
                    },
                    "organization": "Bergvik o Ala ab Söderhamn"
                }
            ],
            "family": {
                "spouse": "Lilly Sandström",
                "marriage_year": "1937",
                "children": [
                    {
                        "name": "Gunny",
                        "birth_year": "1943"
                    }
                ]
            }
        },
        "4": {
            "full_name": "S A Rune Delvin",
            "location": "Söderhamn",
            "occupation": "ombudsman",
            "birth_details": {
                "date": "01/03/1926",
                "place": "Sthlm",
                "parents": "elektr Alvar D och Margareta Carlsson"
            },
            "education": [
                {
                    "degree": "Stud:ex",
                    "year": "1946",
                    "institution": "Sthlm"
                },
                {
                    "degree": "jur kand",
                    "year": "1951",
                    "institution": "Sthlm"
                }
            ],
            "career": [
                {
                    "position": "tingstjg",
                    "years": {
                        "start_year": 1951,
                        "end_year": 1954
                    },
                    "organization": "Ångermani s doms"
                },
                {
                    "position": "fiskal hovr N Norrl",
                    "years": {
                        "start_year": 1955
                    },
                    "organization": "NULL"
                },
                {
                    "position": "om-fa :man",
                    "years": {
                        "start_year": 1958
                    },
                    "organization": "Bergvik o Ala ab Söderhamn"
                }
            ],
            "family": {
                "spouse": "Gudrun Ekelund",
                "marriage_year": "1955",
                "children": [
                    {
                        "name": "Göran",
                        "birth_year": "1957"
                    },
                    {
                        "name": "Ulrika",
                        "birth_year": "1960"
                    },
                    {
                        "name": "Maria",
                        "birth_year": "1962"
                    }
                ]
            },
            "hobbies": [
                "curling"
            ]
        },
        "5": {
            "full_name": "Olof G S de Maré",
            "location": "Östersund",
            "occupation": "överläkare",
            "birth_details": {
                "date": "19/05/1912",
                "place": "Strängnäs",
                "parents": "l:e stadsläk Alfred de M och Ellen Sahlgren"
            },
            "education": [
                {
                    "degree": "Med lic",
                    "year": "1940",
                    "institution": "Upps"
                }
            ],
            "career": [
                {
                    "position": "öl underläk :förordn",
                    "years": {
                        "start_year": 1940,
                        "end_year": 1950
                    },
                    "organization": "NULL"
                },
                {
                    "position": "bitr sanat :läk",
                    "years": {
                        "start_year": 1951
                    },
                    "organization": "Solliden Östersund"
                },
                {
                    "position": "överläk",
                    "years": {
                        "start_year": 1951,
                        "end_year": 1963
                    },
                    "organization": "Österåsens sanat"
                },
                {
                    "position": "överläk",
                    "years": {
                        "start_year": 1963
                    },
                    "organization": "Sollidens sjh Östersund"
                }
            ],
            "family": {
                "spouse": "Ulla Boethius",
                "marriage_year": "1940",
                "children": [
                    {
                        "name": "Lennart",
                        "birth_year": "1943"
                    },
                    {
                        "name": "Marianne",
                        "birth_year": "1945"
                    },
                    {
                        "name": "Hans",
                        "birth_year": "1946"
                    }
                ]
            },
            "hobbies": [
                "golf"
            ]
        }
    }
}