{
    "original": "DAHLGREN, CARL-ERIC,\nlantmätare, lantbruksdirektör, Luleå, f i Umeå\n23/5/16 av fabr Oskar D o Hanna\nJonsson.\n\nStud:ex 36, KTH 41, lantmät:tjg\nMalmöh, Vnorrl o Västerb l, bitr\nlant-br:dir Västerb l 53, Vnorrl l 54,\nlantbr:-dir Norrb l sed 55. - Kapt res. - Utm:\nRNO.\n\nGift m Gunnel Ingeskog f 19, dtr t ing\nRobert I o Ragnhild Pihlström. - Barn:\nÅsa f 45, Anders f 47, Erik f 49.\n\nDAHLGREN, ELLEN B E,\nlänsbibliotekarie, Härnösand, f i Ljusnarsberg,\nÖrebro l, 8/11/05 av bergsing, frih\nYngve Hermelin o Anna Cederbaum.\nFil lic Upps 33, fil dr 36, bibl:ass\nHärnösand 37, stadsbibl:ie sed 44,\ncentral-bibl:ie sed 47, länsbibl:ie sed 65. - Skr:\nUber den Gebrauch der\nPräsenspartizi-pien von perfektiven Verben im\nAlt-kirchenslavischen (35). - Utm: LNO,\nHärnösandsM. - Hobby: fjällvandringar.\nGift 38 m arkivarie Erik Dahlgren f 97.\n\n-  Barn: Magnus f 39, Brita f 42, Elsa\nf 44, Lars f 47.\n\nDAHLGREN, C ERIK, fd arkivarie,\n\nHärnösand, f i Skara 10/3/97 av sem:rekt\nHarald D o Hanna Beckman.\nFil lic Sthlm 32; arkivtjg Sthlms\nstadsarkiv, riksarkivet m fi statl arkiv, aman\nlandsarkivet Härnösand 36, eo arkivarie\n44, arkivarie där 52-63. - Sekr Vnorrl l\nstödfören f hemb:försv sed 54. - Skr:\nNågra drag ur Mariestads äldsta\nhistoria (33), Lennart Torstenson (33), Kyr-\n\nkoarkiv o domkapitelsarkiv (53) m fi.\n-Sign: Cedrik. - Utm: RNO, HvGM,\nFMpbh. - Hobbies: långfärdspaddling,\nfjällvandringar.\n\nGift 38 m länsbibl:ie Ellen Hermelin\nf 05, dtr t bergsing, frih Yngve H o\nAnna Cederbaum. - Barn: Magnus f 39,\nBrita f 42, Elsa f 44, Lars f 47.\n\n",
    "structured": {
        "0": {
            "full_name": "CARL-ERIC DAHLGREN",
            "location": "Luleå",
            "occupation": "Lantmätare, Lantbruksdirektör",
            "birth_details": {
                "date": "23/05/1916",
                "place": "Umeå",
                "parents": "Oskar D och Hanna Jonsson"
            },
            "education": [
                {
                    "degree": "Stud:ex",
                    "year": "1936",
                    "institution": "KTH"
                }
            ],
            "career": [
                {
                    "position": "Lantmät:tjg Malmöh",
                    "years": {
                        "start_year": 41,
                        "end_year": 41
                    },
                    "organization": "Vnorrl o Västerb l"
                },
                {
                    "position": "Bitr lant-br:dir Västerb l",
                    "years": {
                        "start_year": 53,
                        "end_year": 53
                    }
                },
                {
                    "position": "Bitr lant-br:dir Vnorrl l",
                    "years": {
                        "start_year": 54,
                        "end_year": 54
                    }
                },
                {
                    "position": "Lantbr:-dir Norrb l",
                    "years": {
                        "start_year": 55
                    }
                }
            ],
            "family": {
                "spouse": "Gunnel Ingeskog",
                "marriage_year": "19",
                "children": [
                    {
                        "name": "Åsa",
                        "birth_year": "1945"
                    },
                    {
                        "name": "Anders",
                        "birth_year": "1947"
                    },
                    {
                        "name": "Erik",
                        "birth_year": "1949"
                    }
                ]
            }
        },
        "1": {
            "full_name": "ELLEN B E DAHLGREN",
            "location": "Härnösand",
            "occupation": "Länsbibliotekarie",
            "birth_details": {
                "date": "08/11/1905",
                "place": "Ljusnarsberg, Örebro l",
                "parents": "Bergsing, frih Yngve Hermelin och Anna Cederbaum"
            },
            "education": [
                {
                    "degree": "Fil lic",
                    "year": "1933",
                    "institution": "Upps"
                },
                {
                    "degree": "Fil dr",
                    "year": "1936"
                }
            ],
            "career": [
                {
                    "position": "Bibl:ass Härnösand",
                    "years": {
                        "start_year": 37,
                        "end_year": 37
                    }
                },
                {
                    "position": "Stadsbibl:ie",
                    "years": {
                        "start_year": 44,
                        "end_year": 44
                    }
                },
                {
                    "position": "Central-bibl:ie",
                    "years": {
                        "start_year": 47,
                        "end_year": 47
                    }
                },
                {
                    "position": "Länsbibl:ie",
                    "years": {
                        "start_year": 65
                    }
                }
            ],
            "family": {
                "spouse": "Erik Dahlgren",
                "marriage_year": "1938",
                "children": [
                    {
                        "name": "Magnus",
                        "birth_year": "1939"
                    },
                    {
                        "name": "Brita",
                        "birth_year": "1942"
                    },
                    {
                        "name": "Elsa",
                        "birth_year": "1944"
                    },
                    {
                        "name": "Lars",
                        "birth_year": "1947"
                    }
                ]
            },
            "publications": [
                {
                    "title": "Uber den Gebrauch der Präsenspartizipien von perfektiven Verben im Altkirchenslavischen",
                    "year": "1935"
                }
            ],
            "honorary_titles": [
                {
                    "title": "LNO",
                    "institution": "HärnösandsM"
                }
            ],
            "hobbies": [
                "fjällvandringar"
            ]
        },
        "2": {
            "full_name": "C ERIK DAHLGREN",
            "location": "Härnösand",
            "occupation": "Före detta arkivarie",
            "birth_details": {
                "date": "10/03/1897",
                "place": "Skara",
                "parents": "Sem:rekt Harald D och Hanna Beckman"
            },
            "education": [
                {
                    "degree": "Fil lic",
                    "year": "1932",
                    "institution": "Sthlm"
                }
            ],
            "career": [
                {
                    "position": "Arkivtjg Sthlms stadsarkiv, riksarkivet m fl statl arkiv",
                    "years": {
                        "start_year": 36
                    }
                },
                {
                    "position": "Aman landsarkivet Härnösand",
                    "years": {
                        "start_year": 36
                    }
                },
                {
                    "position": "Eo arkivarie",
                    "years": {
                        "start_year": 44
                    }
                },
                {
                    "position": "Arkivarie där",
                    "years": {
                        "start_year": 52,
                        "end_year": 63
                    }
                }
            ],
            "family": {
                "spouse": "Ellen Hermelin",
                "marriage_year": "1938",
                "children": [
                    {
                        "name": "Magnus",
                        "birth_year": "1939"
                    },
                    {
                        "name": "Brita",
                        "birth_year": "1942"
                    },
                    {
                        "name": "Elsa",
                        "birth_year": "1944"
                    },
                    {
                        "name": "Lars",
                        "birth_year": "1947"
                    }
                ]
            },
            "publications": [
                {
                    "title": "Några drag ur Mariestads äldsta historia",
                    "year": "1933"
                },
                {
                    "title": "Lennart Torstenson",
                    "year": "1933"
                },
                {
                    "title": "Kyrkoarkiv o domkapitelsarkiv",
                    "year": "1953"
                }
            ],
            "honorary_titles": [
                {
                    "title": "RNO"
                },
                {
                    "title": "HvGM"
                },
                {
                    "title": "FMpbh"
                }
            ],
            "hobbies": [
                "Långfärdspaddling",
                "fjällvandringar"
            ]
        }
    }
}