{
    "original": "RUNEHAGEN, A O (OLLE),\ncivilingenjör, Uppsala, f i Örebro 8/7/15 av\nverkstadsmäst Axel Petterson o Emelia\nAnderson.\n\nStud:ex Malmö 34, CTH 40, anst SSA\n40, Gbgs gasverk 41-43, byråing där 45-\n\n47, drifting ab Findus 43-45, driftch ab\n\nUps ättiksfabr sed 47. - Medl Oskars-\n\nförb,   SHT.   -   Hobbies:   fotografering,\n\nfilateli.\n\nGift 43 m Margaretha Ottosson f  18,\n\ndtr t vagnmäst Gustaf O o Signe Aldén.\n\n- Barn: Jan f 45, Rolf f 47, Inga f 50.\n\nRUNESTAD, S ÅKE, tandläkare,\nKumla, f i Bollnäs, Gävleb l, 2/11/05 av\nför-rådsförv v SJ Carl Svenson o Hulda\nAndersson.\n\nStud:ex Örebro 24, tandläk:ex 30, vik\nForshaga 30, ass Växjö 30, eg prakt\nKumla sed 31.\n\nRUNESTAM, J STAFFAN,\nbibliotekarie, Uppsala, f i Uppsala 18/2/28\nav biskop Arvid R o Lucie Söderblom.\nStud:ex Karlstad 46, fil kand Upps 48,\nfil lic Lund 55, aman Upps univ :bibl 57,\nbibl:ie där sed 61. - Sekr Geijer samf :s\nlitt:nd.\n\nGift 56 m Birgit Lundin f 30, dtr t\ntypogr Edvin L o Tekla Andersson.\n-Barn: Arvid f 58, Erik f 59, Karin f 60.\n\nRUNÉUS,    BENGT   G,    ryttmästare,\n\nÖrebro, f i Runnaby, Örebro l, 9/1/17\nav domänintend Gunnar Pettersson o\nJudit Pehrson.\n\nStud:ex 35, res:off:ex 37, Bjärka-Säby\nlantbr:sk 38, driftsled :kurs Alnarp 39,\nbokh Bjärka-Säby 40, Rödjenäs 41-42,\njordbr :förv Katrinefors ab Alkvettern\n43-51, ag Runnaby gård Örebro sed 51,\nMörby gård Odensbacken sed 59. - Ordf\nfrökontr:anst Örebro 60, styr:led stat\ncentr frökontr:anst 52, Örebro l\nlantmäns centralfören 53, led ö jordbr :f\nör-söksdistr 62, KLH:s försökskoll 62.\n-Led Stadsfullm 62. - Ryttm K 3 res 47.\nGift 48 m Ulla Löfgren f 23, dtr t dir\nAxel L o h h. - Barn: Katarina f 49,\nJohan f 51, Margareta f 57, Ulrika f 59.\n\n",
    "structured": {
        "1": {
            "full_name": "RUNEHAGEN, A O (OLLE)",
            "location": "Uppsala",
            "occupation": "civilingenjör",
            "birth_details": {
                "date": "08/07/1915",
                "place": "Örebro",
                "parents": "verkstadsmäst Axel Petterson o Emelia Anderson"
            },
            "education": [
                {
                    "degree": "Stud:ex",
                    "year": "1934",
                    "institution": "Malmö"
                },
                {
                    "degree": "CTH",
                    "year": "1940",
                    "institution": "SSA"
                }
            ],
            "career": [
                {
                    "position": "anst SSA",
                    "years": {
                        "start_year": 1940
                    },
                    "organization": ""
                },
                {
                    "position": "Gbgs gasverk",
                    "years": {
                        "start_year": 1941,
                        "end_year": 1943
                    },
                    "organization": ""
                },
                {
                    "position": "byråing där",
                    "years": {
                        "start_year": 1945,
                        "end_year": 1947
                    },
                    "organization": ""
                },
                {
                    "position": "drifting ab Findus",
                    "years": {
                        "start_year": 1943,
                        "end_year": 1945
                    },
                    "organization": ""
                },
                {
                    "position": "driftch ab Ups ättiksfabr",
                    "years": {
                        "start_year": 1947
                    },
                    "organization": ""
                }
            ],
            "family": {
                "spouse": "Margaretha Ottosson",
                "marriage_year": "1943",
                "children": [
                    {
                        "name": "Jan",
                        "birth_year": "1945"
                    },
                    {
                        "name": "Rolf",
                        "birth_year": "1947"
                    },
                    {
                        "name": "Inga",
                        "birth_year": "1950"
                    }
                ]
            },
            "hobbies": [
                "fotografering",
                "filateli"
            ]
        },
        "2": {
            "full_name": "RUNESTAD, S ÅKE",
            "location": "Kumla",
            "occupation": "tandläkare",
            "birth_details": {
                "date": "02/11/1905",
                "place": "Bollnäs, Gävleb l",
                "parents": "för-rådsförv v SJ Carl Svenson o Hulda Andersson"
            },
            "education": [
                {
                    "degree": "Stud:ex",
                    "year": "1924",
                    "institution": "Örebro"
                },
                {
                    "degree": "tandläk:ex",
                    "year": "1930",
                    "institution": ""
                }
            ],
            "career": [
                {
                    "position": "vik Forshaga",
                    "years": {
                        "start_year": 1930
                    },
                    "organization": ""
                },
                {
                    "position": "ass Växjö",
                    "years": {
                        "start_year": 1930
                    },
                    "organization": ""
                },
                {
                    "position": "eg prakt Kumla",
                    "years": {
                        "start_year": 1931
                    },
                    "organization": ""
                }
            ],
            "family": {
                "spouse": "",
                "marriage_year": "NULL",
                "children": []
            }
        },
        "3": {
            "full_name": "RUNESTAM, J STAFFAN",
            "location": "Uppsala",
            "occupation": "bibliotekarie",
            "birth_details": {
                "date": "18/02/1928",
                "place": "Uppsala",
                "parents": "biskop Arvid R o Lucie Söderblom"
            },
            "education": [
                {
                    "degree": "Stud:ex",
                    "year": "1946",
                    "institution": "Karlstad"
                },
                {
                    "degree": "fil kand",
                    "year": "1948",
                    "institution": "Upps"
                },
                {
                    "degree": "fil lic",
                    "year": "1955",
                    "institution": "Lund"
                },
                {
                    "degree": "aman Upps univ :bibl",
                    "year": "1957",
                    "institution": ""
                }
            ],
            "career": [
                {
                    "position": "bibl:ie där",
                    "years": {
                        "start_year": 1961
                    },
                    "organization": ""
                }
            ],
            "family": {
                "spouse": "Birgit Lundin",
                "marriage_year": "1956",
                "children": [
                    {
                        "name": "Arvid",
                        "birth_year": "1958"
                    },
                    {
                        "name": "Erik",
                        "birth_year": "1959"
                    },
                    {
                        "name": "Karin",
                        "birth_year": "1960"
                    }
                ]
            }
        },
        "4": {
            "full_name": "RUNÉUS, BENGT G",
            "location": "Örebro",
            "occupation": "ryttmästare",
            "birth_details": {
                "date": "09/01/1917",
                "place": "Runnaby, Örebro l",
                "parents": "domänintend Gunnar Pettersson o Judit Pehrson"
            },
            "education": [
                {
                    "degree": "Stud:ex",
                    "year": "1935",
                    "institution": ""
                },
                {
                    "degree": "res:off:ex",
                    "year": "1937",
                    "institution": ""
                }
            ],
            "career": [
                {
                    "position": "Bjärka-Säby lantbr:sk",
                    "years": {
                        "start_year": 1938
                    },
                    "organization": ""
                },
                {
                    "position": "bokh Bjärka-Säby",
                    "years": {
                        "start_year": 1940
                    },
                    "organization": ""
                },
                {
                    "position": "ag Runnaby gård Örebro",
                    "years": {
                        "start_year": 1951
                    },
                    "organization": ""
                },
                {
                    "position": "Mörby gård Odensbacken",
                    "years": {
                        "start_year": 1959
                    },
                    "organization": ""
                }
            ],
            "family": {
                "spouse": "Ulla Löfgren",
                "marriage_year": "1948",
                "children": [
                    {
                        "name": "Katarina",
                        "birth_year": "1949"
                    },
                    {
                        "name": "Johan",
                        "birth_year": "1951"
                    },
                    {
                        "name": "Margareta",
                        "birth_year": "1957"
                    },
                    {
                        "name": "Ulrika",
                        "birth_year": "1959"
                    }
                ]
            }
        }
    }
}