{
    "original": "REXED, BROR A, professor, Uppsala,\nf i Gunnarskog, Värml l, 19/6/14 av\nköpm Daniel Magnusson o Agda\nAndersson.\n\nStud:ex Karlstad 35, med kand Sthlm\n38, med lic 43, med dr 45, doc i\nhistologi 45, e labor 45-47, prosekt Karol\ninst 47, prof i anatomi Upps sed 53.\n-Led komm f GbgMedHS 46-47, 48 års\nläk :utbildn :komm 48-53, 55 års\nläk:ut-bildn :utredn, sekr stat med forskn :råd\n51-63, ordf Sv:es yngre med teoret\n46-49, Sv:es laborat fören 49-51,\ngaranti-lånendn sed 54, med :styr nd f utl läk\n59-63, sakk eckl:dep sed 57, led 60 års\nläk:utbildn:beredn, 63 års univ:- o\nhög-sk:utbyggn:komm, led o sekr\nforskn:be-redn sed 62. - LVSU, LIVA. - Led Fi\nläk:sällsk Duodecim sed 49, Fellow New\nYork acad of Science sed 61, insp Värml\nnät Upps sed 56, hedL Värml nät Upps o\nLund. - Skr: Post-natal development of\nperipheral nervous system (drsavh 44),\nvetensk arb i neuroanatomi o\nneuro-fysiol, pop :med art, medarb i\ndagspressen.\n\nGift 41 m med lic Ursula Schalling f 16,\ndtr t kammarråd Erik S o adv Gerd\nLaven. - Barn: Magnus f 43, Knut f 45,\nInga f 47, Anders f 49, Gerd f 54.\n\nREXED, GUNNAR, godsägare,\ntandläkare, Säf f le, f i Gunnarskog, Värml l,\n4/7/03 av köpm Daniel Magnusson o\nAgda Andersson.\n\nStud:ex Lund 25, tandläk:ex Berlin 30,\nTHS 31, eg prakt Sthlm tom 60. -\nInneh Ströms säteri, Värml L - Medl\nTim-mermO. - Skr: undersökn rör\nkaries-frekvensen i Värml. - Hobbies: jakt,\ngolf.\n\nGift m Bente Lauenburg f 25. - Barn:\nIngemar f 32, Ulf f 35, Jan-Christer\nf 38, Birger f 43.\n\nRHODIN,   ROLF   G,   lasarettsläkare,\n\nLindesberg, f i Trollhättan 28/7/06 av\ndrätseldir Emil R o Fredrika Andersson.\nStud:ex Vänersborg 25, med kand Upps\n29, med lic 36. - Aman anat inst Upps\nuniv 32, eo aman patol o bakt inst 34,\nass :läk Upps BB 36, kir klin Sahlgr sjh\n37, underläk 37, 2:e underläk kir avd\nHbgs las 41, l:e underläk 42, underläk\nobstetr-gynekol avd Södersjh 46, med\navd S:t Eriks sjh 46, röntgenavd Sahlgr\nsjh 47, tf las :läk Simrishamns las 48,\nkir avd Vänersborgs las 48, l:e\nunderläk 49, bitr las :läk 50, tf las :läk kir avd\nHörby las 53, las:läk kir avd\nLindesbergs las sed 54, styresman sed 54.\n-Skr i kir.\n\nGift m Elsa Järegård f 16, dtr t\nspar-banksdir Ernst J o Ebba Strömberg.\n-Barn: Mattias f 46, Boel f 49.\n\n",
    "structured": {
        "0": {
            "full_name": "REXED, BROR A",
            "location": "Uppsala",
            "occupation": "Professor",
            "birth_details": {
                "date": "19/06/1914",
                "place": "Gunnarskog, Värmlands län",
                "parents": "köpm Daniel Magnusson o Agda Andersson"
            },
            "education": [
                {
                    "degree": "stud:ex Karlstad",
                    "year": "1935",
                    "institution": "Karlstad"
                },
                {
                    "degree": "med kand Sthlm",
                    "year": "1938",
                    "institution": "Stockholm"
                },
                {
                    "degree": "med lic",
                    "year": "1943",
                    "institution": "NULL"
                },
                {
                    "degree": "med dr",
                    "year": "1945",
                    "institution": "NULL"
                },
                {
                    "degree": "doc i histologi",
                    "year": "1945",
                    "institution": "NULL"
                }
            ],
            "career": [
                {
                    "position": "e labor",
                    "years": {
                        "start_year": 1945,
                        "end_year": 1947
                    },
                    "organization": "NULL"
                },
                {
                    "position": "prosekt Karol inst",
                    "years": {
                        "start_year": 1947,
                        "end_year": 1947
                    },
                    "organization": "NULL"
                },
                {
                    "position": "prof i anatomi Upps",
                    "years": {
                        "start_year": 1953,
                        "end_year": null
                    },
                    "organization": "NULL"
                }
            ],
            "family": {
                "spouse": "lic Ursula Schalling",
                "marriage_year": "1941",
                "children": [
                    {
                        "name": "Magnus",
                        "birth_year": "1943"
                    },
                    {
                        "name": "Knut",
                        "birth_year": "1945"
                    },
                    {
                        "name": "Inga",
                        "birth_year": "1947"
                    },
                    {
                        "name": "Anders",
                        "birth_year": "1949"
                    },
                    {
                        "name": "Gerd",
                        "birth_year": "1954"
                    }
                ]
            }
        },
        "1": {
            "full_name": "REXED, GUNNAR",
            "location": "Säffle",
            "occupation": "Godsägare, Tandläkare",
            "birth_details": {
                "date": "04/07/1903",
                "place": "Gunnarskog, Värmlands län",
                "parents": "köpm Daniel Magnusson o Agda Andersson"
            },
            "education": [
                {
                    "degree": "Stud:ex Lund",
                    "year": "1925",
                    "institution": "Lund"
                },
                {
                    "degree": "tandläk:ex Berlin",
                    "year": "1930",
                    "institution": "Berlin"
                },
                {
                    "degree": "THS",
                    "year": "1931",
                    "institution": "NULL"
                }
            ],
            "career": [
                {
                    "position": "eg prakt Sthlm",
                    "years": {
                        "start_year": null,
                        "end_year": 1960
                    },
                    "organization": "NULL"
                }
            ],
            "family": {
                "spouse": "Bente Lauenburg",
                "marriage_year": "NULL",
                "children": [
                    {
                        "name": "Ingemar",
                        "birth_year": "1932"
                    },
                    {
                        "name": "Ulf",
                        "birth_year": "1935"
                    },
                    {
                        "name": "Jan-Christer",
                        "birth_year": "1938"
                    },
                    {
                        "name": "Birger",
                        "birth_year": "1943"
                    }
                ]
            },
            "hobbies": [
                "jakt",
                "golf"
            ]
        },
        "2": {
            "full_name": "RHODIN, ROLF G",
            "location": "Lindesberg",
            "occupation": "Lasarettsläkare",
            "birth_details": {
                "date": "28/07/1906",
                "place": "Trollhättan",
                "parents": "drätseldir Emil R o Fredrika Andersson"
            },
            "education": [
                {
                    "degree": "Stud:ex Vänersborg",
                    "year": "1925",
                    "institution": "Vänersborg"
                },
                {
                    "degree": "med kand Upps",
                    "year": "1929",
                    "institution": "Uppsala"
                },
                {
                    "degree": "med lic",
                    "year": "1936",
                    "institution": "NULL"
                }
            ],
            "career": [
                {
                    "position": "bitr las :läk",
                    "years": {
                        "start_year": 1950,
                        "end_year": null
                    },
                    "organization": "tf las :läk kir avd Hörby las 53, las:läk kir avd Lindesbergs las sed 54, styresman sed 54"
                }
            ],
            "family": {
                "spouse": "Elsa Järegård",
                "marriage_year": "NULL",
                "children": [
                    {
                        "name": "Mattias",
                        "birth_year": "1946"
                    },
                    {
                        "name": "Boel",
                        "birth_year": "1949"
                    }
                ]
            },
            "publications": [],
            "hobbies": [],
            "community_involvement": [],
            "board_memberships": [],
            "honorary_titles": []
        }
    }
}