{
    "original": "RUDD, C E PHILIP, direktör, konsul,\nKarlstad, f i Nödinge, Västergötl l,\n20/12/00 av fabr C R o Lydia Forsberg.\nIng:ex CTI 23, stud i Tyskl 30;\nkonstruktör ab Surte glasbruk 23, ing\nBille-ruds ab 25, verkst dir ab Walfrid\nSvensson &amp; Co Karlstad sed 37. - No\nvicekonsul Karlstad sed 59. - Ordf Värml o\nDalsl möbelhandl:fören, styr:led\nMöbel-handl riksförb, nämndeman, kyrkv,\nstyr :led stadsbibl :f ören, teaterstyr, led\nhälsov:nd, befullm omb Städ\nförsäkr:-bol. - Utm: SORGM. - Hobby: musik.\nGift 35 m Eva Svensson f 06, dtr t fabr\nAxel S o Carolina Olsson. - Barn:\nElisabeth f 38, Carl f 43.\n\nRUDÉN, A O R (ROLF),\nindustritjänsteman, Västerås, f i Västerås 11/5/\n05 av dir Rudolf R o Mia Säter.\nStud:ex Västerås 25, Schartaus hdlI 27,\nbos utoml 30-39, tid anst Asea Västerås,\nHugo Krafft Paris, ABA, Alltrafik, ab\nElectrolux Sthlm, anst Myggbo ab\nsed 43. - Medl Odd Fellow. - Hobbies:\nsläktforskning, musik, trädgårdsskötsel.\nGift 34 m Ingrid Ekman. - Barn:\nJan-Olof f 37, Claes-Göran f 42.\n\nRUDENGREN, SIGGE M N,\ndisponent, Nykvarn, f i Rudskoga, Värml l,\n19/12/11 av godsäg Henning Larsson o\nFrida Dahlin.\n\nRealex Örebro 29, ing :ex tekn gymn\nÖrebro 38, anst Örebro stads byggn :kont\n38, ab Laxå pappersbruk 39-53, verkst\ndir ab Nykvarns bruk sed 55 o ab Laxå\npappersbruk sed 56. - V verkst dir o\nstyr :led Minebergs ab o Sthlms\nben-mjölsfabr ab sed 62.\n\nGift 42 m Mai Kers f 20, dtr t Sven\nCarlson o Ida Göranson. - Barn: Ulla\nf 43, Hans f 44, Mats f 48, Anna f 56.\n\nRUDERT,  ANDERS,  civiljägmästare,\n\nskogsförvaltare,   Övertänger,  f  i  Sthlm\n\n2/10/19 av bankkamr Gustaf R o Brita\n\nErickson.\n\nStud:ex 40, SkHS 46, anst ab Iggesunds\n\nbruk 46, Skogsv:styr Jämtl l 46, Fiskeby\n\nab 48, skogsförv Kopparfors ab Tänger\n\nskogsförvaltn sed 53. - Led Gävle hdls-\n\nkamm trafikkomm f Dalarna, ordf\nskol-styr, arb:lösh:nd, ind:komm, led\nkomm:-fullm, vägndn. - Medl Hum fören,\nSam-larfören Nordstjärnan.\nGift 44 m Marianne Forsberg f 20, dtr\nt dir Arvid F o Karin Stockenberg.\n-Barn: Hans f 47, Mats f 50, Jan f 55.\nRUDÉRUS, K G (GÖSTA) F,\nkomminister, Karlstad, f i Degerfors, Örebro l,\n6/6/07 av stat:mäst Fredrik Petersson o\nElin Johansson.\n\nStud:ex Örebro 26, teol kand Upps o\nprästv 37, journ o exp :f örest Sv\nblå-bandsfören tidn Örebro 28-29, korresp\nSSUH centralstyr 30-31, past:adj\nHolmedal 37, v kyrkoadj N Råda 38,\nkyrko-adj där 39, stiftsadj Karlstads stift 44,\nkommin Karlstad domkyrkoförs sed 55.\n- Pressomb:man Karlstads stift 43, red\nKarlstads stiftsblad 45, fullm SPF 54,\nordf Karlstads motettsällsk 48, Karlstads\nstifts kyrkosångsförb 54, ndn f Karlstads\nstifts julbok 56; led centralstyr f\nunder-visn o vård av psyk efterblivna inom\nVärml l 52, styr:led Värml l landst\nyr-kessk 54, styr:led Lutherska världsförb\nsv sektion 63, nämndeman 54,\nkyrko-fullm 59, landst:man 63, Stadsfullm\n63, - Medl SSUH, IOGT,\nTempelrid-darO. - Skr: art i tidn o tidskr sed 26.\nGift 36 m Evy Törnkvist f 04, dtr t l :e\nreparatör Evert T o Anna Eriksson.\n-Barn: Håkan f 38, Monika f 40, Jan\nf 43.\n\n",
    "structured": {
        "1": {
            "full_name": "RUDD, C E PHILIP",
            "location": "Karlstad",
            "occupation": "direktör, konsul",
            "birth_details": {
                "date": "20/12/1900",
                "place": "Nödinge, Västergötland",
                "parents": "f C R o Lydia Forsberg"
            },
            "education": [
                {
                    "degree": "Ing:ex",
                    "year": "1923",
                    "institution": "CTI"
                }
            ],
            "career": [
                {
                    "position": "konstruktör",
                    "years": {
                        "start_year": 1923,
                        "end_year": 1930
                    },
                    "organization": "ab Surte glasbruk"
                },
                {
                    "position": "ing Bille-ruds ab",
                    "years": {
                        "start_year": 1925,
                        "end_year": 1937
                    }
                },
                {
                    "position": "verkst dir",
                    "years": {
                        "start_year": 1937,
                        "end_year": null
                    },
                    "organization": "ab Walfrid Svensson & Co Karlstad"
                }
            ],
            "family": {
                "spouse": "Eva Svensson",
                "marriage_year": "1935",
                "children": [
                    {
                        "name": "Elisabeth",
                        "birth_year": "1938"
                    },
                    {
                        "name": "Carl",
                        "birth_year": "1943"
                    }
                ]
            },
            "hobbies": [
                "musik"
            ]
        },
        "2": {
            "full_name": "RUDÉN, A O R (ROLF)",
            "location": "Västerås",
            "occupation": "industritjänsteman",
            "birth_details": {
                "date": "11/5/1905",
                "place": "Västerås",
                "parents": "dir Rudolf R o Mia Säter"
            },
            "education": [
                {
                    "degree": "Stud:ex",
                    "year": "1925",
                    "institution": "Västerås"
                },
                {
                    "degree": "Schartaus hdlI",
                    "year": "1927"
                }
            ],
            "career": [
                {
                    "position": "anst Asea Västerås",
                    "years": {
                        "start_year": 1930,
                        "end_year": 1939
                    }
                },
                {
                    "position": "anst Myggbo ab",
                    "years": {
                        "start_year": 1943,
                        "end_year": null
                    }
                }
            ],
            "family": {
                "spouse": "Ingrid Ekman",
                "marriage_year": "1934",
                "children": [
                    {
                        "name": "Jan-Olof",
                        "birth_year": "1937"
                    },
                    {
                        "name": "Claes-Göran",
                        "birth_year": "1942"
                    }
                ]
            },
            "hobbies": [
                "släktforskning",
                "musik",
                "trädgårdsskötsel"
            ]
        },
        "3": {
            "full_name": "RUDENGREN, SIGGE M N",
            "location": "Nykvarn",
            "occupation": "disponent",
            "birth_details": {
                "date": "19/12/1911",
                "place": "Rudskoga, Värmlands län",
                "parents": "godsäg Henning Larsson o Frida Dahlin"
            },
            "education": [
                {
                    "degree": "Realex",
                    "year": "1929"
                },
                {
                    "degree": "ing :ex tekn gymn",
                    "year": "1938",
                    "institution": "Örebro"
                }
            ],
            "career": [
                {
                    "position": "anst Örebro stads byggn :kont",
                    "years": {
                        "start_year": 1938,
                        "end_year": null
                    }
                },
                {
                    "position": "verkst dir",
                    "years": {
                        "start_year": 1956,
                        "end_year": null
                    },
                    "organization": "ab Nykvarns bruk o ab Laxå pappersbruk"
                }
            ],
            "family": {
                "spouse": "Mai Kers",
                "marriage_year": "1942",
                "children": [
                    {
                        "name": "Ulla",
                        "birth_year": "1943"
                    },
                    {
                        "name": "Hans",
                        "birth_year": "1944"
                    },
                    {
                        "name": "Mats",
                        "birth_year": "1948"
                    },
                    {
                        "name": "Anna",
                        "birth_year": "1956"
                    }
                ]
            }
        },
        "4": {
            "full_name": "RUDERT, ANDERS",
            "location": "Övertänger",
            "occupation": "civiljägmästare, skogsförvaltare",
            "birth_details": {
                "date": "2/10/1919",
                "place": "Sthlm"
            },
            "education": [
                {
                    "degree": "Stud:ex",
                    "year": "1940"
                },
                {
                    "degree": "SkHS",
                    "year": "1946"
                }
            ],
            "career": [
                {
                    "position": "anst ab Iggesunds bruk",
                    "years": {
                        "start_year": 1946,
                        "end_year": 1946
                    }
                },
                {
                    "position": "skogsförv Kopparfors ab",
                    "years": {
                        "start_year": 1953,
                        "end_year": null
                    }
                }
            ],
            "family": {
                "spouse": "Marianne Forsberg",
                "marriage_year": "1944",
                "children": [
                    {
                        "name": "Hans",
                        "birth_year": "1947"
                    },
                    {
                        "name": "Mats",
                        "birth_year": "1950"
                    },
                    {
                        "name": "Jan",
                        "birth_year": "1955"
                    }
                ]
            }
        },
        "5": {
            "full_name": "RUDÉRUS, K G (GÖSTA) F",
            "location": "Karlstad",
            "occupation": "komminister",
            "birth_details": {
                "date": "6/6/1907",
                "place": "Degerfors, Örebro l"
            },
            "education": [
                {
                    "degree": "Stud:ex",
                    "year": "1926",
                    "institution": "Örebro"
                },
                {
                    "degree": "teol kand",
                    "year": "1937"
                }
            ],
            "career": [
                {
                    "position": "past:adj",
                    "years": {
                        "start_year": 1937,
                        "end_year": 1938
                    },
                    "organization": "Holmedal"
                },
                {
                    "position": "v kyrkoadj N Råda",
                    "years": {
                        "start_year": 1938,
                        "end_year": 1939
                    }
                },
                {
                    "position": "kommin",
                    "years": {
                        "start_year": 1955,
                        "end_year": null
                    },
                    "organization": "Karlstad domkyrkoförs"
                }
            ],
            "family": {
                "spouse": "Evy Törnkvist",
                "marriage_year": "1936",
                "children": [
                    {
                        "name": "Håkan",
                        "birth_year": "1938"
                    },
                    {
                        "name": "Monika",
                        "birth_year": "1940"
                    },
                    {
                        "name": "Jan",
                        "birth_year": "1943"
                    }
                ]
            },
            "hobbies": [
                "musik"
            ]
        }
    }
}