{
    "original": "ROLFSMAN, ANDERS G,\növeringenjör, Eskilstuna, f i Gävle 11/8/14.\nStud:ex 33, KTH 39, anst SJ 39,\növering TGOJ  sed  57,  trafikch  där  63.\n-Hobbies: fiske, foto.\n\nGift 42 m Inga-Britt Johansson f 19,\ndtr t fabr J J o Svea Engström. - Barn:\nLennart f 44, Hans f 46, Gunnar f 55.\n\nROLLIN, JENNY, rektor, Falun, f i\nVästerås 30/7/02 av lärov:adj Birger R\no Maria Wenström.\n\nNormalsk:komp 19, h lär:sem 23, ol\nlär:förordn 23-26, h elem:lärov f fi o\nkomm flicksk Västerås 26-40, hal Falun\nsed 40, rekt Söderhamns komm flicksk\n52, Falu komm flicksk sed 57.\n\nROLSDORPH, REIDAR, skogschef,\nRottneros, f i Kirkenaer, Sol0r, Norge,\n\n26/4/18 av ing Axel R o Helga Jensen.\nStud:ex Hamar 38, hdlssk Kongsvinger\n38, Evenstad skogssk 39, Härnösands\ntekn skogs- o sågv :sk 40, jägm :kursen\nNorges lantbr :högsk 44, forstmäst\nRo-medal &amp; Egeberg allm Hedmark 44,\n0ier &amp; Fensjö skogar Solör 46,\nskogs-förv ab Rottneros bruk 52, skogsch\nRottneroskoncernen sed 61. - Led\nVärml:ind samarb:utsk o sub:komm 61,\nstyr:led Kölaälvens flottn:fören 61,\nWerml inmätn:fören 57; medl\nFryksdalens gille, Rotary. - Utm: NFrM, NDM.\n\n- Hobbies: jakt, sport.\n\nGift 47 m Inger Kjaer f 24, dtr t dir\nHarry K o Ella Lindeblad-Pedersen\n(Danm). - Barn: Niels Ferdinand f 49,\nEsben o Susann ff 52.\n\nROMELL-EKMAN, ALFHILD M, leg\nläkare, Karlstad, f i Mofalla, Skarab l,\n6/5/98 av lantbr Alfred Romell o Hanna\nGustafsson.\n\nStud:ex Gbg 16, med kand Upps 20,\nmed lic Sthlm 25. - E läk Östersunds hosp\n25 o 26, ass :läk o tf underläk\nLöwen-strömska las 25, eo hosp:läk av 2:a kl\nVadstena hosp o asyl 26, Kristinehamns\nhosp 28, 2:e läk Mariebergs sjh 29, bitr\nläk Beckomberga sjh 32, läk Värml l\nsinnesslöanst Ulleberg 36-49.\nGift 33 m leg läk Gunnar Ekman f 95.\n\n- Barn: Olof f 35, Elisabeth f 36.\n",
    "structured": {
        "0": {
            "full_name": "ANDERS G ROLFSMAN",
            "location": "Eskilstuna",
            "occupation": "överingenjör",
            "birth_details": {
                "date": "11/08/1914",
                "place": "Gävle"
            },
            "education": [
                {
                    "degree": "Stud:ex",
                    "year": "1933",
                    "institution": "KTH"
                }
            ],
            "career": [
                {
                    "position": "anst SJ",
                    "years": {
                        "start_year": 1939,
                        "end_year": 1957
                    },
                    "organization": "SJ"
                },
                {
                    "position": "övering TGOJ",
                    "years": {
                        "start_year": 1957,
                        "end_year": 1963
                    },
                    "organization": "TGOJ"
                },
                {
                    "position": "trafikch",
                    "years": {
                        "start_year": 1963,
                        "end_year": null
                    },
                    "organization": "TGOJ"
                }
            ],
            "family": {
                "spouse": "Inga-Britt Johansson",
                "marriage_year": "1942",
                "children": [
                    {
                        "name": "Lennart",
                        "birth_year": "1944"
                    },
                    {
                        "name": "Hans",
                        "birth_year": "1946"
                    },
                    {
                        "name": "Gunnar",
                        "birth_year": "1955"
                    }
                ]
            },
            "hobbies": [
                "fiske",
                "foto"
            ]
        },
        "1": {
            "full_name": "JENNY ROLLIN",
            "location": "Falun",
            "occupation": "rektor",
            "birth_details": {
                "date": "30/07/1902",
                "place": "Västerås",
                "parents": "lärov:adj Birger R o Maria Wenström"
            },
            "education": [
                {
                    "degree": "Normalsk:komp",
                    "year": "1919",
                    "institution": "NULL"
                },
                {
                    "degree": "h lär:sem",
                    "year": "1923",
                    "institution": "NULL"
                }
            ],
            "career": [
                {
                    "position": "ohlär:förordn",
                    "years": {
                        "start_year": 1923,
                        "end_year": 1926
                    },
                    "organization": "NULL"
                },
                {
                    "position": "h elem:lärov",
                    "years": {
                        "start_year": 1926,
                        "end_year": 1940
                    },
                    "organization": "NULL"
                },
                {
                    "position": "rekt",
                    "years": {
                        "start_year": 1940,
                        "end_year": null
                    },
                    "organization": "NULL"
                }
            ],
            "family": {
                "spouse": null,
                "marriage_year": null,
                "children": []
            }
        },
        "2": {
            "full_name": "REIDAR ROLSDORPH",
            "location": "Rottneros",
            "occupation": "skogschef",
            "birth_details": {
                "date": "26/04/1918",
                "place": "Kirkenaer, Sol0r, Norge",
                "parents": "ing Axel R o Helga Jensen"
            },
            "education": [
                {
                    "degree": "Stud:ex",
                    "year": "1938",
                    "institution": "Hamar"
                },
                {
                    "degree": "hdlssk",
                    "year": "1938",
                    "institution": "Kongsvinger"
                }
            ],
            "career": [
                {
                    "position": "skogs-förv",
                    "years": {
                        "start_year": 1961,
                        "end_year": null
                    },
                    "organization": "Rottneroskoncernen"
                }
            ],
            "family": {
                "spouse": "Inger Kjaer",
                "marriage_year": "1947",
                "children": [
                    {
                        "name": "Niels Ferdinand",
                        "birth_year": "1949"
                    },
                    {
                        "name": "Esben",
                        "birth_year": "1952"
                    },
                    {
                        "name": "Susann",
                        "birth_year": "1952"
                    }
                ]
            },
            "honorary_titles": [
                {
                    "title": "NFrM",
                    "institution": null,
                    "year": null
                },
                {
                    "title": "NDM",
                    "institution": null,
                    "year": null
                }
            ],
            "hobbies": [
                "jakt",
                "sport"
            ]
        },
        "3": {
            "full_name": "ALFHILD M ROMELL-EKMAN",
            "location": "Karlstad",
            "occupation": "leg läkare",
            "birth_details": {
                "date": "06/05/1898",
                "place": "Mofalla, Skarab l",
                "parents": "lantbr Alfred Romell o Hanna Gustafsson"
            },
            "education": [
                {
                    "degree": "Stud:ex",
                    "year": "1916",
                    "institution": "Gbg"
                },
                {
                    "degree": "med kand",
                    "year": "1920",
                    "institution": "Upps"
                },
                {
                    "degree": "med lic",
                    "year": "1925",
                    "institution": "Sthlm"
                }
            ],
            "career": [
                {
                    "position": "läk",
                    "years": {
                        "start_year": 1925,
                        "end_year": 1926
                    },
                    "organization": "Östersunds hosp"
                },
                {
                    "position": "bitr läk",
                    "years": {
                        "start_year": 1932,
                        "end_year": null
                    },
                    "organization": "Beckomberga sjh"
                },
                {
                    "position": "läk",
                    "years": {
                        "start_year": 1936,
                        "end_year": 1949
                    },
                    "organization": "Värml l sinnesslöanst Ulleberg"
                }
            ],
            "family": {
                "spouse": "Gunnar Ekman",
                "marriage_year": "1933",
                "children": [
                    {
                        "name": "Olof",
                        "birth_year": "1935"
                    },
                    {
                        "name": "Elisabeth",
                        "birth_year": "1936"
                    }
                ]
            }
        }
    }
}