{
    "original": "ROSENLUNDH, C A GUNNAR,\nkyrkoherde, Södra Rörum, f i Jämshög,\nBlek l, 9/1/12 av smedmäst Hans August\nR o Hanna Håkansson.\nStud:ex Fjellst sk Upps 34, teol kand\nLund 40, prästv Luleå 47, kyrkoadj\nPa-jala 47, Bureå 50, kommin Arjeplog 54,\nkyrkoh Lima 56, kommin S Rörum o\nSvensköp sed 62. - Ordf kyrkoråd o\nkyrkostämma, led barnav:nd 56-61,\nLima folksk :styr 61-63; medl Lärdomshist\nsällsk, Karol förb, Sv hist fören. -\nHobbies: medeltida konst, arkeologi.\nGift 44 m sjuksköt Brita Larsson f 18,\ndtr t köpm Emil L o Anna Kristina\nNilsson. - Barn: Eva f 47, Tomas f 49,\nMaria f 56.\n\nROSENKVIST, J FOLKE,\nprovinsialläkare, Huddinge, f i Sthlm 26/8/04 av\njvtjm John R o Kerstin Johansson.\nStud:ex 24, med kand Sthlm 27, med lic\n33, ol läk:förordn 30-34, 2:e underläk\nSt Ekebergs sanat 35, Pens :styr sjh\nNynäshamn 35, l:e underläk med avd\nUmeå las 37, 2:e underläk Visby las 40,\nbitr läk Gbgs epid:sjh 42, köpingsläk o\ne prov:läk Nynäshamn 43, e prov:läk\nVislanda 44, prov:läk där 50, Huddinge\nsed 58. - Utm: RNO, SRKSM.\nGift 38 m Margot Berggren f 14, dtr t\ntelegraftjm Per B o Elsa Skeppström.\n-Barn: Anders f 39, Margareta f 42, Per\nf 47.\n\nROSENQVIST, GUNNAR E,\nstads-fiskal, Eskilstuna, f i Linkpg 30/4/14 av\nfolkskollär Georg R o Lisa Zetterdahl.\nStud:ex Nykpg 33, jur kand Upps 41,\ntingstjg Västerbergsl doms 41-44, tjg\nåklagarmyndigh Sthlm 44, stadsfiskal\n\nEskilstuna sed 55 (bitr 49). -’Kapt I 4\n\nres.\n\nGift  40  m   Birgit  Hedin  f   15,   dtr  t\n\ngodsäg Edvin H o Karin Fröling. - Barn:\n\nBengt f 41, Hans f 45.\n\n",
    "structured": {
        "0": {
            "full_name": "C A GUNNAR ROSENLUNDH",
            "location": "Södra Rörum",
            "occupation": "kyrkoherde",
            "birth_details": {
                "date": "09/01/1912",
                "place": "Jämshög"
            },
            "education": [
                {
                    "degree": "Stud:ex",
                    "year": "1934",
                    "institution": "Fjellst sk Upps"
                },
                {
                    "degree": "teol kand",
                    "year": "1940",
                    "institution": "Lund"
                }
            ],
            "career": [
                {
                    "position": "prästv",
                    "years": {
                        "start_year": 1947,
                        "end_year": 1950
                    },
                    "organization": "Luleå"
                },
                {
                    "position": "kyrkoadj",
                    "years": {
                        "start_year": 1947,
                        "end_year": 1950
                    },
                    "organization": "Pajala"
                },
                {
                    "position": "Bureå",
                    "years": {
                        "start_year": 1950,
                        "end_year": 1954
                    },
                    "organization": null
                }
            ],
            "family": {
                "spouse": "sjuksköt Brita Larsson",
                "marriage_year": "1944",
                "children": [
                    {
                        "name": "Eva",
                        "birth_year": "1947"
                    },
                    {
                        "name": "Tomas",
                        "birth_year": "1949"
                    },
                    {
                        "name": "Maria",
                        "birth_year": "1956"
                    }
                ]
            }
        },
        "1": {
            "full_name": "J FOLKE ROSENKVIST",
            "location": "Huddinge",
            "occupation": "provinsialläkare",
            "birth_details": {
                "date": "26/08/1904",
                "place": "Sthlm"
            },
            "education": [
                {
                    "degree": "Stud:ex",
                    "year": "1924",
                    "institution": null
                },
                {
                    "degree": "med kand",
                    "year": "1927",
                    "institution": "Sthlm"
                },
                {
                    "degree": "med lic",
                    "year": "1933",
                    "institution": null
                }
            ],
            "career": [
                {
                    "position": "ol läk:förordn",
                    "years": {
                        "start_year": 1930,
                        "end_year": 1934
                    },
                    "organization": null
                },
                {
                    "position": "2:e underläk",
                    "years": {
                        "start_year": 1937,
                        "end_year": 1940
                    },
                    "organization": "Umeå las"
                }
            ],
            "family": {
                "spouse": "Margot Berggren",
                "marriage_year": "1938",
                "children": [
                    {
                        "name": "Anders",
                        "birth_year": "1939"
                    },
                    {
                        "name": "Margareta",
                        "birth_year": "1942"
                    },
                    {
                        "name": "Per",
                        "birth_year": "1947"
                    }
                ]
            }
        },
        "2": {
            "full_name": "GUNNAR E ROSENQVIST",
            "location": "Eskilstuna",
            "occupation": "stads-fiskal",
            "birth_details": {
                "date": "30/04/1914",
                "place": "Linkpg"
            },
            "education": [
                {
                    "degree": "Stud:ex",
                    "year": "1933",
                    "institution": "Nykpg"
                },
                {
                    "degree": "jur kand",
                    "year": "1941",
                    "institution": "Upps"
                }
            ],
            "career": [
                {
                    "position": "tingstjg",
                    "years": {
                        "start_year": 1941,
                        "end_year": 1944
                    },
                    "organization": "Västerbergsl doms"
                },
                {
                    "position": "tjg",
                    "years": {
                        "start_year": 1944,
                        "end_year": 1955
                    },
                    "organization": "åklagarmyndigh Sthlm"
                }
            ],
            "family": {
                "spouse": "Birgit Hedin",
                "marriage_year": "1940",
                "children": [
                    {
                        "name": "Bengt",
                        "birth_year": "1941"
                    },
                    {
                        "name": "Hans",
                        "birth_year": "1945"
                    }
                ]
            }
        }
    }
}