{
    "original": "RYDBERGH,  A  ÅKE,  överingenjör,\n\nFalun, fi Gbg 21/6/05 av folkskollär\nLudvig R o Lucia Gellerstedt.\nCTH 30, konstr Nohab Trollhättan 30,\ning Sthlm-Rosl jv 37, verkst dir där 51,\növering ASJ Falun sed 59. - Led\nhdlskamm Gävle, tekn rådet HTL Borlänge.\n\n-  Medl Rotary. - Utm: RNO. - Hobbies:\nfiske, båtsport.\n\nGift 32 m Ellen Nilsson f 06, dtr t\nndeman Elof N o Sofia Sebelius.\n-Barn: Siv f 34, Jan f 39.\n\nRYDEHOLM,   CARL   GUSTAF,   tf\n\nlänsassessor, Uppsala, f i Härnösand\n9/12/10 av åkeriäg Nils G Andersson o\nLotten Arnell.\n\nStud:ex 29, jur kand Upps 37, tingstjg\nÅngermani s doms 37-39, eo länsnot\nlänsstyr Västernorrl l 43 (e 40),\nlänsnot länsstyr Upps l 53, l:e länsnot där\nsed 59, tf länsassess 64. - Jur bitr ch f\nNorrl:kust marindistr 47-53, auditör där\no h ch Hemsö KA-försv, KA 5, samt h\nbef:h Härnösands-Sundsvalls fö 50-53,\nledare sem:övn f jur stud Upps univ sed\n60. - Sekr o kassaförv Upps l\ntrafik-säkerh:komm sed 53, hälsov:förb sed 56,\nsekr direkt Ulleråkers sjh sed 58, dess\nutskrivn:nd sed 59, Eriksbergskyrk\nbygg-n :komm Upps sed 59, ordf tax :nd 41-50,\n54-59. - Medl SHT, W-sex, FrimO, lu*\nvenalO, S:t PetriO. - Skr: art\nFörv:-rättsl tidskr. - Utm: SCFftjtS, FMpbh.\n\n- Hobbies: tennis, curling.\n\nGift 58 m Maria Lindbohm, dtr t\ndistr.:-förest Gustaf L o Greta Andersson.\n-Barn: Elisabeth f 60.\n\nRYDELL,  GERDA  B   L,  fd  rektor,\n\nÖrebro, f i Bredaryd, Jönkpgs l, 29/3/94\nav lantbr Anders Peter Rö Frans iska\nJahnke.\n\nFil måg Upps 17, fil lic Sthlm 26, fil\ndr 28. - Lär Jönkpgs elem:lärov f fi 18,\nSaltsjöbadens samsk 20-24 o 25-27, eb\nlekt folksk:sem Kalmar 24-25, adj\nNorr-kpgs hal 27, lekt Södertälje hal 29, rekt\nÖrebro hal f fi 46-59. - Styr:led\nLärov:-lär riksförb 33-46, Stadsfullm Södertälje37-46, led folksk:styr Örebro 50-54,\nkul-turv:ndn sed 50 m m. - Skr:\nAdertonhundratalets historiska skådespel i Sv :e\nföre Strindberg (28), Henrik Ibsen (32).\n\n-  Utm: GMiqS, LNO, SCFftjt.\nRYDÉN,  K  ANDERS  I,\nbankdirektör, Örebro, f i Skövde 9/12/09 av\nlinje-mast Nils Johan R o Ida Johansson.\nVolontär Deutsche Bank München 39,\nDHS 42, HHS’s stip Engl o Skottl 50;\nanst Gbgs bk 27, dir o styr :led Sv:es\nkreditbks   avd :kont   Örebro   sed   52.\n-Styr:led   Askersundsverken   ab\nAskersund 55, ab Swedish Drums Askersund\n55, Kils murbruk ab Örebro 54,\nAdolfsbergs brunns ab Adolfsberg 53. - Medl\nOdd Fellow, FrimO, Lions Club. -\nHobbies: fiske, jakt, sport.\n\nGift 46 m Brita Maria Lindgren f 23,\ndtr t köpm Magnus L o h h. - Barn:\nLena f 46, Birgitta f 51.\n\nRYDÉN, S E EBBE, direktör, Örebro,\nf i Bollnäs, Gävleborgs l, 7/3/07 av\nkont :skri v v SJ Hjalmar R o Gerda\nErikson.\n\nStud:ex Upps 26, DHS 28, anst J\nWalter Thompson Comp Sthlm 30, Herman\nMeeths ’ab Gbg 31, dir :ass Oscaria\nÖrebro 33, verkst dir Skohandelns\ninköps-fören Sko-IFA Örebro sed 48. - Led\nAK sed 57, DK Örebro sed 55, ordf fp\nÖrebro 1. - Hobbies: konst, tennis.\nGift 33 m Helfrid Ahlström f 07, dtr t\nstat :mast Knut A o Margareta Rehn.\n-Barn: Jan f 35, Hans-Olof f 39, Staffan\nf 44.\n\nRYDÉN, JANNE G W, rektor,\nStor-vreta, f i Förlösa, Kalmar l, 4/6/00 av\nfabr Johan R o Jenny Karlsson.\nFolkskollär:ex Växjö 23, kyrkosång:ex\n26, org:ex 27, folkskollär Oskarshamn 24,\nfolkskollär o kant Tensta 27, överlär där\n39, distr:överlär Vattholma 52, rekt där\nsed 58. - Sekr Upps l förb:kr av Sv:es\nfolkskollär:förb 34-51, ordf Uppl :kr av\nSv:es skolled:förb 62 (styr:led 53),\nfolksk:styr .41-51, kyrkostämma o past\n:kyrkostämma 44-51, Tensta v vardistr,\nkassör skolkassa 30-51, kyrkokassa secj 30. •?\nMedl FrimO. •&gt; Utg: Folkskolor,\nklockare, organister o lärare i Tensta (47). *\nUtm: RNO, PatrSGM, FMpbh.\nGift 28 m Ingegerd Johansson f 02, dtr\nt köpman Magni J o h h, f Härlander.\n\n-  Barn: Anna-Lena f 30, Karin f 36.\nRYDÉN, SIGURD T V, stadsläkare,\n\nÖrebro, f J Nybro 10/1/10 av fabr A W\nR o Anna Hjelm.            :’...-;\n\nStud:ex Kalmar 29, med kand Lund 33,\n,lic: 38,; underläk lyringe;: badanst\n\n39, tf underläk Varbergs las 40, e läk\nMaria sjh 40, tf underläk ortop klin\nMalmö allm sjh 41, vik underläk o\nunderläk med avd Örebro las 41-47, tf\nstadsdistr:läk Örebro 50, tf l:e stadsläk\n54, l:e stadsläk Örebro sed 56. - För*\ntroendeläk Örebro länsarb:nämnd 49-63,\nläk Örebro l landstings träningsverkstad\nsed 48.\n\nGift 36 m May Lessing f 11, dtr t dir\nRobert L o Hildur Ekstrand. - Barn:\nEva f 37, Olof f 39, Lars f 40, Ulla\nf 43, Per f 45, Staffan f 50.\n\n",
    "structured": {
        "0": {
            "full_name": "A ÅKE Rydbergh",
            "location": "Falun",
            "occupation": "Överingenjör",
            "birth_details": {
                "date": "21/06/1905",
                "place": "Göteborg"
            },
            "education": [
                {
                    "degree": "Konstr",
                    "year": "1930",
                    "institution": "CTH"
                }
            ],
            "career": [
                {
                    "position": "Konstr",
                    "years": {
                        "start_year": 1930,
                        "end_year": 1930
                    },
                    "organization": "Nohab Trollhättan"
                },
                {
                    "position": "Ing",
                    "years": {
                        "start_year": 1937,
                        "end_year": 1937
                    },
                    "organization": "Sthlm-Rosl jv"
                },
                {
                    "position": "Verkst dir",
                    "years": {
                        "start_year": 1951,
                        "end_year": 1951
                    },
                    "organization": "Nohab Trollhättan"
                },
                {
                    "position": "Övering",
                    "years": {
                        "start_year": 1959,
                        "end_year": 1959
                    },
                    "organization": "ASJ Falun"
                }
            ],
            "family": {
                "spouse": "Ellen Nilsson",
                "marriage_year": "1932",
                "children": [
                    {
                        "name": "Siv",
                        "birth_year": "1934"
                    },
                    {
                        "name": "Jan",
                        "birth_year": "1939"
                    }
                ]
            },
            "hobbies": [
                "Fiske",
                "Båtsport"
            ]
        },
        "1": {
            "full_name": "CARL GUSTAF Rydeholm",
            "location": "Uppsala",
            "occupation": "Tf Länsassessor",
            "birth_details": {
                "date": "09/12/1910",
                "place": "Härnösand"
            },
            "education": [
                {
                    "degree": "Stud:ex",
                    "year": "1929",
                    "institution": null
                },
                {
                    "degree": "Jur kand",
                    "year": "1937",
                    "institution": "Upps"
                }
            ],
            "career": [
                {
                    "position": "Eo Länsnot",
                    "years": {
                        "start_year": 40,
                        "end_year": 40
                    },
                    "organization": "Länsstyr Västernorrl l"
                },
                {
                    "position": "Eo Länsnot",
                    "years": {
                        "start_year": 53,
                        "end_year": 53
                    },
                    "organization": "Länsstyr Upps l"
                },
                {
                    "position": "L:e Länsnot",
                    "years": {
                        "start_year": 59,
                        "end_year": 59
                    },
                    "organization": "Upps l"
                }
            ],
            "family": {
                "spouse": "Maria Lindbohm",
                "marriage_year": "1958",
                "children": [
                    {
                        "name": "Elisabeth",
                        "birth_year": "1960"
                    }
                ]
            },
            "hobbies": [
                "Tennis",
                "Curling"
            ]
        },
        "2": {
            "full_name": "GERDA B L Rydell",
            "location": "Örebro",
            "occupation": "Fd Rektor",
            "birth_details": {
                "date": "29/03/1894",
                "place": "Bredaryd, Jönkpgs l"
            },
            "education": [
                {
                    "degree": "Fil måg",
                    "year": "1917",
                    "institution": "Upps"
                },
                {
                    "degree": "Fil lic",
                    "year": "1926",
                    "institution": "Sthlm"
                },
                {
                    "degree": "Fil dr",
                    "year": "1928",
                    "institution": null
                }
            ],
            "career": [
                {
                    "position": "Lär",
                    "years": {
                        "start_year": 1918,
                        "end_year": 1918
                    },
                    "organization": "Jönkpgs Elem:Lärov F"
                },
                {
                    "position": "Adj",
                    "years": {
                        "start_year": 1927,
                        "end_year": 1927
                    },
                    "organization": "Norrkpgs Hal"
                },
                {
                    "position": "Rekt",
                    "years": {
                        "start_year": 1946,
                        "end_year": 1959
                    },
                    "organization": "Örebro Hal F"
                }
            ]
        },
        "3": {
            "full_name": "K ANDERS I Rydén",
            "location": "Örebro",
            "occupation": "Bankdirektör",
            "birth_details": {
                "date": "09/12/1909",
                "place": "Skövde"
            },
            "education": null,
            "career": [
                {
                    "position": "Volontär",
                    "years": {
                        "start_year": 1939,
                        "end_year": 1939
                    },
                    "organization": "Deutsche Bank München"
                },
                {
                    "position": "Dir o Styr:led",
                    "years": {
                        "start_year": 1952,
                        "end_year": 1952
                    },
                    "organization": "Sv:es Kreditbks Avd:kont Örebro"
                }
            ],
            "family": {
                "spouse": "Brita Maria Lindgren",
                "marriage_year": "1946",
                "children": [
                    {
                        "name": "Lena",
                        "birth_year": "1946"
                    },
                    {
                        "name": "Birgitta",
                        "birth_year": "1951"
                    }
                ]
            },
            "hobbies": [
                "Fiske",
                "Jakt",
                "Sport"
            ]
        },
        "4": {
            "full_name": "SE EBBE Rydén",
            "location": "Örebro",
            "occupation": "Direktör",
            "birth_details": {
                "date": "07/03/1907",
                "place": "Bollnäs, Gävleborgs l"
            },
            "education": null,
            "career": [
                {
                    "position": "Dir:ass",
                    "years": {
                        "start_year": 1933,
                        "end_year": 1933
                    },
                    "organization": "Oscaria Örebro"
                },
                {
                    "position": "Verkst dir",
                    "years": {
                        "start_year": 1948,
                        "end_year": 1948
                    },
                    "organization": "Skohandelns Inköpsfören Sko-IFA Örebro"
                }
            ],
            "family": {
                "spouse": "Helfrid Ahlström",
                "marriage_year": "1933",
                "children": [
                    {
                        "name": "Jan",
                        "birth_year": "1935"
                    },
                    {
                        "name": "Hans-Olof",
                        "birth_year": "1939"
                    },
                    {
                        "name": "Staffan",
                        "birth_year": "1944"
                    }
                ]
            },
            "hobbies": [
                "Konst",
                "Tennis"
            ]
        },
        "5": {
            "full_name": "JANNE G W Rydén",
            "location": "Storvreta",
            "occupation": "Rektor",
            "birth_details": {
                "date": "04/06/1900",
                "place": "Förlösa, Kalmar l"
            },
            "education": [
                {
                    "degree": "Folkskollär:ex",
                    "year": "1923",
                    "institution": "Växjö"
                },
                {
                    "degree": "Kyrkosång:ex",
                    "year": "1926",
                    "institution": null
                },
                {
                    "degree": "Org:ex",
                    "year": "1927",
                    "institution": null
                }
            ],
            "career": [
                {
                    "position": "Rekt",
                    "years": {
                        "start_year": 1958,
                        "end_year": 1958
                    },
                    "organization": "Vattholma"
                }
            ],
            "family": {
                "spouse": "Ingegerd Johansson",
                "marriage_year": "1928",
                "children": [
                    {
                        "name": "Anna-Lena",
                        "birth_year": "1930"
                    },
                    {
                        "name": "Karin",
                        "birth_year": "1936"
                    }
                ]
            }
        },
        "6": {
            "full_name": "SIGURD T V Rydén",
            "location": "Örebro",
            "occupation": "Stadsläkare",
            "birth_details": {
                "date": "10/01/1910",
                "place": "J Nybro"
            },
            "education": [
                {
                    "degree": "Stud:ex",
                    "year": "1929",
                    "institution": "Kalmar"
                },
                {
                    "degree": "Med kand",
                    "year": "1933",
                    "institution": "Lund"
                },
                {
                    "degree": "Lic",
                    "year": "1938",
                    "institution": null
                }
            ],
            "career": [
                {
                    "position": "Vik underläk",
                    "years": {
                        "start_year": 1941,
                        "end_year": 1947
                    },
                    "organization": "Örebro las"
                },
                {
                    "position": "Tf Stadsdistr:Läk",
                    "years": {
                        "start_year": 1950,
                        "end_year": 1950
                    },
                    "organization": "Örebro"
                },
                {
                    "position": "L:e Stadsläk",
                    "years": {
                        "start_year": 1956,
                        "end_year": 1956
                    },
                    "organization": "Örebro"
                }
            ],
            "family": {
                "spouse": "May Lessing",
                "marriage_year": "1936",
                "children": [
                    {
                        "name": "Eva",
                        "birth_year": "1937"
                    },
                    {
                        "name": "Olof",
                        "birth_year": "1939"
                    },
                    {
                        "name": "Lars",
                        "birth_year": "1940"
                    },
                    {
                        "name": "Ulla",
                        "birth_year": "1943"
                    },
                    {
                        "name": "Per",
                        "birth_year": "1945"
                    },
                    {
                        "name": "Staffan",
                        "birth_year": "1950"
                    }
                ]
            }
        }
    }
}