{
    "original": "Stenkil, Erik Vilbelm,\nakademiränt-mästare, Lund, f. 14/7/90 i Vadstena.\nG 36 m. Siri Sandström. Barn:\nMargareta f. 38, Lars 42. — Stud :ex. i Linköp.\n10, fil. mag. i Upps. 15, fil. lic. 19, jur.\nkand. 23. Tingstjg. i Livgedingets\ndoms. 24-25, e. o. aman. v. Upps. univ.\nkansli, räntekamm. o. kont. 25, andre\nkamrer v. Upps. univ. 29, förste\nkamrer 38, kamrer v. Akad. sjuklh. 26,\nränt-mäst. v. univ. i Lund fr. 44.\n\nStenkula, Carl Gustaf, stat skon\nsu-lent, Kristianstad, f. 14/7/10 i\nHälsingborg av disp. Z. F. A. S. o. Clara\nNilsson. G. 36 m. Elsa Silfverswärd. Barn:\nStaffan f. 36, Gudrun 41. — Civ:ekon.\n311, soc :pol. ex. 36. Stud. v. univ. i Kiel\n31. Syssloman v. fattigv:- o.\nbarnav:-byrån i Trelleb. 35-37, soc :omb :man i\nVästervik 38, soc :v:sysslom. i Landskr.\n39—46, fattigv:- o. barnav:konsu’l. i\nKrist. o. Blek. 1. fr. 46. Led. av\nanst:-nd v. straff äng. i Kristianstad,\nstyr:-led. o. sekr. i Skånska barnav :förb.,\nsekr. i dess arb :utsk. f. Krist. 1., sekr.\ni Krist. 1. landstings barnhemsdir. Fd.\nled. av övervakn :nd i Landskr. o. av\nfam:bidr:nd där. ChrX:esFrM.\n\nStenmarck, Nils Edvin Albert,\ndirektör, Malmö, f. 3/2/91 i Malmö av\nbyggm. Ni’ls S. o. Elna Andersson. G.\n18 m. Margareta Heerklotz. Barn:\nNils f. 19, aff:anst., Gbg, Erik 20,\nfänr. i res., Inga 23, Ulla-Britta 26, g. m.\npastor    Mårten    Werner,    Sthlm.    —\n\nStud:ex. i Malmö 10, jur. kand. i Lund\n14. Tingstjg. i Västra Göinge domis.\n14-16, tjg. i Skånska hovr. 17-19. Adv.\ni Waldenströms advibyrå 19-26, egen\nadvibyrå 26-34. Led, av Svies\nadvi-samf. 21-34. Omb :man i Skånes\nstads-hyp ifören. o. i Skånes bost\nikredit-fören. 32, verkst. dir. i båda 34.\nStyr:-led. i Konungariket Svies\nstadshypi-kassa fr. 45, i Sv. bostadskreditkassan\nfr. 43 o. i Försäkr. A-B Allm. Brand\nfr. 3*5.\n\n",
    "structured": {
        "1": {
            "full_name": "Stenkil, Erik Vilbelm",
            "location": "Lund",
            "occupation": "akademiränt-mästare",
            "birth_details": {
                "date": "14/07/1890",
                "place": "Vadstena"
            },
            "education": [
                {
                    "degree": "Stud",
                    "year": "1910",
                    "institution": "Linköp"
                },
                {
                    "degree": "fil. mag.",
                    "year": "1915",
                    "institution": "Uppsala"
                },
                {
                    "degree": "fil. lic.",
                    "year": "1919",
                    "institution": "Uppsala"
                },
                {
                    "degree": "jur. kand.",
                    "year": "1923",
                    "institution": "NULL"
                }
            ],
            "career": [
                {
                    "position": "Tingstjg. i Livgedingets doms.",
                    "years": {
                        "start_year": 1924,
                        "end_year": 1925
                    },
                    "organization": "NULL"
                },
                {
                    "position": "e. o. aman. v. Upps. univ. kansli",
                    "years": {
                        "start_year": 1925,
                        "end_year": 1925
                    },
                    "organization": "NULL"
                },
                {
                    "position": "räntekamm. o. kont.",
                    "years": {
                        "start_year": 1925,
                        "end_year": 1925
                    },
                    "organization": "NULL"
                },
                {
                    "position": "andre kamrer v. Upps. univ.",
                    "years": {
                        "start_year": 1929,
                        "end_year": 1929
                    },
                    "organization": "NULL"
                },
                {
                    "position": "förste kamrer",
                    "years": {
                        "start_year": 1938,
                        "end_year": 1938
                    },
                    "organization": "NULL"
                },
                {
                    "position": "kamrer v. Akad. sjuklh.",
                    "years": {
                        "start_year": 1926,
                        "end_year": 1926
                    },
                    "organization": "NULL"
                },
                {
                    "position": "ränt-mäst. v. univ. i Lund",
                    "years": {
                        "start_year": 1944,
                        "end_year": 1944
                    },
                    "organization": "NULL"
                }
            ],
            "family": {
                "spouse": "Siri Sandström",
                "marriage_year": "1936",
                "children": [
                    {
                        "name": "Margareta",
                        "birth_year": "1938"
                    },
                    {
                        "name": "Lars",
                        "birth_year": "1942"
                    }
                ]
            }
        },
        "2": {
            "full_name": "Stenkula, Carl Gustaf",
            "location": "Kristianstad",
            "occupation": "stat skon su-lent",
            "birth_details": {
                "date": "14/07/1910",
                "place": "Hälsingborg"
            },
            "education": [
                {
                    "degree": "Civ",
                    "year": "311",
                    "institution": "NULL"
                },
                {
                    "degree": "soc :pol.",
                    "year": "36",
                    "institution": "NULL"
                }
            ],
            "career": [
                {
                    "position": "Syssloman v. fattigv:- o. barnav:-byrån i Trelleb.",
                    "years": {
                        "start_year": 1935,
                        "end_year": 1937
                    },
                    "organization": "NULL"
                },
                {
                    "position": "soc :omb :man i Västervik",
                    "years": {
                        "start_year": 1938,
                        "end_year": 1938
                    },
                    "organization": "NULL"
                },
                {
                    "position": "soc :v:sysslom. i Landskr.",
                    "years": {
                        "start_year": 1939,
                        "end_year": 1946
                    },
                    "organization": "NULL"
                },
                {
                    "position": "fattigv:- o. barnav:konsu’l. i Krist. o. Blek. 1. fr.",
                    "years": {
                        "start_year": 1946,
                        "end_year": 1946
                    },
                    "organization": "NULL"
                }
            ],
            "family": {
                "spouse": "Elsa Silfverswärd",
                "marriage_year": "1936",
                "children": [
                    {
                        "name": "Staffan",
                        "birth_year": "1936"
                    },
                    {
                        "name": "Gudrun",
                        "birth_year": "1941"
                    }
                ]
            }
        },
        "3": {
            "full_name": "Stenmarck, Nils Edvin Albert",
            "location": "Malmö",
            "occupation": "direktör",
            "birth_details": {
                "date": "03/02/1891",
                "place": "Malmö"
            },
            "education": [
                {
                    "degree": "Stud",
                    "year": "1910",
                    "institution": "Malmö"
                },
                {
                    "degree": "jur. kand.",
                    "year": "1914",
                    "institution": "Lund"
                }
            ],
            "career": [
                {
                    "position": "Tingstjg. i Västra Göinge domis.",
                    "years": {
                        "start_year": 1914,
                        "end_year": 1916
                    },
                    "organization": "NULL"
                },
                {
                    "position": "tjg. i Skånska hovr.",
                    "years": {
                        "start_year": 1917,
                        "end_year": 1919
                    },
                    "organization": "NULL"
                },
                {
                    "position": "Adv. i Waldenströms advibyrå",
                    "years": {
                        "start_year": 1919,
                        "end_year": 1926
                    },
                    "organization": "NULL"
                },
                {
                    "position": "egen advibyrå",
                    "years": {
                        "start_year": 1926,
                        "end_year": 1934
                    },
                    "organization": "NULL"
                }
            ],
            "family": {
                "spouse": "Margareta Heerklotz",
                "marriage_year": "1918",
                "children": [
                    {
                        "name": "Nils",
                        "birth_year": "1919"
                    },
                    {
                        "name": "Erik",
                        "birth_year": "1920"
                    },
                    {
                        "name": "Inga",
                        "birth_year": "1923"
                    },
                    {
                        "name": "Ulla-Britta",
                        "birth_year": "1926"
                    }
                ]
            }
        }
    }
}