{
    "original": "Sonesson, Nils Erik Lennart,\nhäradsskrivare, Hörby, f. 111/9/05 i\nBrandstad, Malmöh. 1., av förv.\nSamuel S. o. Elin Persson. G. 35 m.\nMartha Larsson. Barn: Birgit f. 37,\nGärd 40. — Stud:ex. i Ystad 24,\nlands-fiskalsex. 33. Bitr. å\nlandsfiskalskontor 25, landsfiskalsassist. 32, e. tj :man\nå landskont. i Malmö s. å., e. o. resp.\nord. landskont. där 36 resp. 40,\ndärjämte vik. å landsfiskals- o. stadsfiskalstj.,\nord. kronokamrer i Trelleb. 45,\nfiär:-skriv. i Hörby fögd. fr. 46. Ordf. i\nFören. Mallmöh. 1. e, landsstatstj :män,\nled. av styr. i dess riksorg. 35-38, ordf.\ni Fören. Malmöh. 1. landskan si. o.\nlandskont., led. av styr. f. Fören. Sv :es\nlandskansl. o. landskont. 42-46,\nläns-o:mb. f. Malmöh. 1. i Sv.es här:skriv\n:-fören. fr. 46.    Hobby:  skytte.\n\nSonesson, Nils Hilding, kyrkoherde,\nSnogeröd, f. 5/1/96 i Ystad. G. 37 m.\nEster Margareta (Greta) Karolina\nKarlsson. Barn: Gudmund f. 38, Inga\n40, Sven-Hilding 42, Carl 44. —\nStud:-ex. i Lund 19, teol. fil. ex. 22, teöl.\nkand., prakt. teol. prov o. prästv. 24.\nV. past. i Trolle-Ljungby o. GualÖJV\n24-25, Sturkö o. Tj’urkö 25-27, v.\nkorn-min. i Limjhamn 27-29, ikyrkoadj. i\nYstad 29-31, tf. kyrkoh. i Västra\nHo-by o. Hastad 32-34, kyrkoh. i\nGud-muntorp o. Huirva sed. 35. Ordf. i\nkyrkostämmorna o. skolstyr., led. av\nGudmuntorps komm :fuillm., ord. led.\nav styr. f. Eslövs folkhögsk.,\nhuv:-man i Löberöds sparb.\n\nSonesson, Olof Reinhold, notarie,\nMalmö, f. 16/7/89 i Hälsingborg av\nkyrkoh. Olof S. o. h. h. i. Andersson.\nG. 28 m. Hulda Andersson. — Stud:-\n\nex. i Kristianst. 08, jur. stud. v. Lunds\nuniv. 08-ll4. Inneh. jur. byrå i\nLoim-ma 14-27, i Malmö fr. 27.\n\nSonesson, Wilhelm, ryttmästare,\ngodsägare, Billinge, f. 4/3’/08 i Malmö\nav grossfh. Wilhelm S. o. Augusta\nJohansson. G. 33 m. Inga Fritsch. Barn:\nWilhelm f. 35, Jan 38, Ingrid 40,\nBirgit 42, Christina 46. — Ex. v. Malmö\nhand :gymn. 27. Fämr. v. Skånska\nkav: reg. 30, un d :löjtn. 3’2, löjtn. 34,\nryttm. 45. Tj :man v. StockamöMans\nA-B 28, ordf. i styr. o. verkst. dir.\ndär 3&gt;l-38. Äg. o. bruk. Gunnaröds\ngård sed. 3$ samt Fagerås m. fl. sed.\n39. Styr :led. i sparb. o. afif :ibank\nsamt ind rföret., inneh. ett ’flert. komm.\nförtr :uppdr.\n\n",
    "structured": {
        "0": {
            "full_name": "Nils Erik Lennart Sonesson",
            "location": "Hörby",
            "occupation": "Häradsskrivare",
            "birth_details": {
                "date": "11/09/1905",
                "place": "Brandstad, Malmö",
                "parents": "Samuel S. o. Elin Persson"
            },
            "education": [
                {
                    "degree": "Studentexamen",
                    "year": "1924",
                    "institution": "Ystad"
                },
                {
                    "degree": "Landsfiskalsexamen",
                    "year": "1933",
                    "institution": "NULL"
                }
            ],
            "career": [
                {
                    "position": "Bitr. å landsfiskalskontor",
                    "years": {
                        "start_year": 1925,
                        "end_year": 1925
                    },
                    "organization": "NULL"
                },
                {
                    "position": "Landsfiskalsassistent",
                    "years": {
                        "start_year": 1932,
                        "end_year": 1932
                    },
                    "organization": "NULL"
                },
                {
                    "position": "E. tj :man å landskont.",
                    "years": {
                        "start_year": 1932,
                        "end_year": 1932
                    },
                    "organization": "Malmö"
                },
                {
                    "position": "E. o. resp. ord. landskont. där",
                    "years": {
                        "start_year": 1936,
                        "end_year": 1936
                    },
                    "organization": "Malmö"
                },
                {
                    "position": "E. o. resp. ord. landskont. där",
                    "years": {
                        "start_year": 1940,
                        "end_year": 1940
                    },
                    "organization": "Malmö"
                },
                {
                    "position": "Ord. kronokamrer",
                    "years": {
                        "start_year": 1945,
                        "end_year": 1945
                    },
                    "organization": "Trelleborg"
                },
                {
                    "position": "Fiär:-skriv.",
                    "years": {
                        "start_year": 1946,
                        "end_year": 2022
                    },
                    "organization": "Hörby"
                },
                {
                    "position": "Ordf. i Fören. Mallmöh. 1. e, landsstatstj :män",
                    "years": {
                        "start_year": 1935,
                        "end_year": 1938
                    },
                    "organization": "NULL"
                },
                {
                    "position": "Ordf. i Fören. Malmöh. 1. landskan si. o. landskont.",
                    "years": {
                        "start_year": 1942,
                        "end_year": 1946
                    },
                    "organization": "NULL"
                },
                {
                    "position": "Läns-o:mb. f. Malmöh. 1. i Sv.es här:skriv :-fören.",
                    "years": {
                        "start_year": 1946,
                        "end_year": 2022
                    },
                    "organization": "NULL"
                }
            ],
            "family": {
                "spouse": "Martha Larsson",
                "marriage_year": "1935",
                "children": [
                    {
                        "name": "Birgit",
                        "birth_year": "1937"
                    },
                    {
                        "name": "Gärd",
                        "birth_year": "1940"
                    }
                ]
            }
        },
        "1": {
            "full_name": "Nils Hilding Sonesson",
            "location": "Snogeröd",
            "occupation": "Kyrkoherde",
            "birth_details": {
                "date": "05/01/1896",
                "place": "Ystad",
                "parents": "NULL"
            },
            "education": [
                {
                    "degree": "Studentexamen",
                    "year": "1919",
                    "institution": "Lund"
                },
                {
                    "degree": "Teologisk filosofi",
                    "year": "1922",
                    "institution": "NULL"
                },
                {
                    "degree": "Teologisk kandidat",
                    "year": "1924",
                    "institution": "NULL"
                }
            ],
            "career": [
                {
                    "position": "V. past.",
                    "years": {
                        "start_year": 1924,
                        "end_year": 1925
                    },
                    "organization": "Trolle-Ljungby o. GualÖJV"
                },
                {
                    "position": "V. past.",
                    "years": {
                        "start_year": 1925,
                        "end_year": 1927
                    },
                    "organization": "Sturkö o. Tj’urkö"
                },
                {
                    "position": "V. korn-min.",
                    "years": {
                        "start_year": 1927,
                        "end_year": 1929
                    },
                    "organization": "Limjhamn"
                },
                {
                    "position": "Kyrkoadj.",
                    "years": {
                        "start_year": 1929,
                        "end_year": 1931
                    },
                    "organization": "Ystad"
                },
                {
                    "position": "Tf. kyrkoh.",
                    "years": {
                        "start_year": 1932,
                        "end_year": 1934
                    },
                    "organization": "Västra Ho-by o. Hastad"
                },
                {
                    "position": "Kyrkoh.",
                    "years": {
                        "start_year": 1935,
                        "end_year": 2022
                    },
                    "organization": "Gud-muntorp o. Huirva"
                }
            ],
            "family": {
                "spouse": "Ester Margareta (Greta) Karolina Karlsson",
                "marriage_year": "1937",
                "children": [
                    {
                        "name": "Gudmund",
                        "birth_year": "1938"
                    },
                    {
                        "name": "Inga",
                        "birth_year": "1940"
                    },
                    {
                        "name": "Sven-Hilding",
                        "birth_year": "1942"
                    },
                    {
                        "name": "Carl",
                        "birth_year": "1944"
                    }
                ]
            }
        },
        "2": {
            "full_name": "Olof Reinhold Sonesson",
            "location": "Malmö",
            "occupation": "Notarie",
            "birth_details": {
                "date": "16/07/1889",
                "place": "Hälsingborg",
                "parents": "kyrkoh. Olof S. o. h. h. i. Andersson"
            },
            "education": [
                {
                    "degree": "NULL",
                    "year": "NULL",
                    "institution": "Kristianst. 08"
                },
                {
                    "degree": "Jur. stud.",
                    "year": "1914",
                    "institution": "Lunds univ."
                }
            ],
            "career": [
                {
                    "position": "Inneh. jur. byrå",
                    "years": {
                        "start_year": 1914,
                        "end_year": 1927
                    },
                    "organization": "Loim-ma"
                },
                {
                    "position": "Inneh. jur. byrå",
                    "years": {
                        "start_year": 1927,
                        "end_year": 2022
                    },
                    "organization": "Malmö"
                }
            ],
            "family": {
                "spouse": "Hulda Andersson",
                "marriage_year": "1928",
                "children": []
            }
        },
        "3": {
            "full_name": "Wilhelm Sonesson",
            "location": "Billinge",
            "occupation": "Ryttmästare, godsägare",
            "birth_details": {
                "date": "04/03/1908",
                "place": "Malmö",
                "parents": "grossfh. Wilhelm S. o. Augusta Johansson"
            },
            "education": [
                {
                    "degree": "Ex. v. Malmö hand :gymn.",
                    "year": "1927",
                    "institution": "NULL"
                }
            ],
            "career": [
                {
                    "position": "Fämr. v. Skånska kav: reg.",
                    "years": {
                        "start_year": 1930,
                        "end_year": 2022
                    },
                    "organization": "NULL"
                },
                {
                    "position": "Un d :löjtn.",
                    "years": {
                        "start_year": 1932,
                        "end_year": 1932
                    },
                    "organization": "NULL"
                },
                {
                    "position": "Löjtn.",
                    "years": {
                        "start_year": 1934,
                        "end_year": 1934
                    },
                    "organization": "NULL"
                },
                {
                    "position": "Ryttm.",
                    "years": {
                        "start_year": 1945,
                        "end_year": 2022
                    },
                    "organization": "NULL"
                },
                {
                    "position": "Tj :man v. StockamöMans A-B",
                    "years": {
                        "start_year": 1928,
                        "end_year": 1931
                    },
                    "organization": "NULL"
                }
            ],
            "family": {
                "spouse": "Inga Fritsch",
                "marriage_year": "1933",
                "children": [
                    {
                        "name": "Wilhelm",
                        "birth_year": "1935"
                    },
                    {
                        "name": "Jan",
                        "birth_year": "1938"
                    },
                    {
                        "name": "Ingrid",
                        "birth_year": "1940"
                    },
                    {
                        "name": "Birgit",
                        "birth_year": "1942"
                    },
                    {
                        "name": "Christina",
                        "birth_year": "1946"
                    }
                ]
            }
        }
    }
}