{
    "original": "Sandblad, Nils Gösta, docent, Lund,\nf. 2/9/10 i Lund av rådm. John S. o.\nNanny Hallen. G. 36 m. Margot\nRanden. Barn: Helena f. 37, Elisabeth 39,\nJohn 44. — Stud:ex. 28, fil. kand. 33,\nfil. lic. 35, fil. dr 44. Stud:res. t. Tyskl.\no. Tjeckoslov. 29, Tyskl. 32, Ital. 34 o.\nFrankr. 36, Höll., Belg. o. Frankr.\n48. E. o. aman. v. Lunds univ.\nkonstmus. 31 -33, aman. där 33-36, v.\nMalmö mus. 35-45, doc. v. Lunds undv.\ni konsthist. 44, docentstip. 46. Skr.:\nMalmö reisidens byggn:historia (31),\nMånstorps gavlar (37), Flensburgska\ngården (tills. im. E. Baiger, 37), Anders\nTrulson. En studie i sekelskiftets sv.\nmåleri (44), Figge Holmgren (44),\nPil-grändsgården i Yistad (tills. m. A.\nTu-Ulse, 47), upps. o. art., konistkritiker i\nArbetet fr. 38. Red. f. Tidens\nkonsthistoria 47.\n\nSandblom, Per Gustaf, civilingenjör\nSVR, Malmö, f. 18/4/09 ii Gbg av O. M.\nS. o. Hulda Ohlsson. G. 33 m. Märta\nFoTsiström. Barn: Birgitta f. 34,\nGunilla 39. — Stud:ex. v. h. a. 1. i Malmö\n28, utex. fr. KTH 33, Stud:res. i\nDanm., Tyskl. o.  Frankr. 34-37. Anst.\n\nv. stadsing : korat, i TreTleb. 33, v.\nstadsing :kont. i Malmö 36, v. Allm.\nIng:byrån 46, deläg. i Sydsv.\nIngenjörsbyrån sed. 49. Led. av komm. f.\nstadsplan eväs. omorg. 48. Medl. av\nSVR, SIK, SSBS m. fl. fören. Skr.:\nmedarb. i Kommunal B yggn: kalender\n48, art. o. föredr. i fackämnen.\nHob-bies: fiske, foto.\n\nSandborg, Erik Gustaf, kyrkoherde,\nSödra Rörum, f. 1/7/97 i Fulltofta,\nMalmöh. 1. G. 28 m. Kerstin Viol-a\n(Wi-van) Valborg Nyström. Barn: Sven f.\n30, Kerstin 32, Hans 36. — Stud:ex. i\nLund 16, teol. kand., prakt. teol. prov\no. prästv. 24. V. pastor i Östra\nKärrstorp o. past :adj. i Fränninge-Volilsjö\n24-27, kommin. i Södra Sallerup 27-36,\nkyrkoh. i Södra Rörum o. Häglinge\nsed. 35. Ordf. i Södra Rörums o.\nHäglinge kyrkostämmor samt i ungd :krets.,\nled. av barnav :nd i S. Rörum,\npastoratskassör.\n\naf Sandeberg, Per Herman Hugo\nDavid, tandläkare, Ystad, f. 18/9/10 i\nLund av dir. Milis af S. o. Agnes\nEvan-der. G. 36 m. Ingrid Engman. Barn:\nMargareta f. 41, Ulf 45. — Stud:ex. i\nLund 30, med. stud. ii Lund 30-32,\ntandl :kand. ¾ taradl :ex. 36. Assist, v.\ntandl :imst. tandfyTln :avd. 36, assist, i\nHalmstad 7 mån. 37, prakt, i Lund\n37-41, v. folktandv. i Katrineholm 41-44,\nförest, f. folktandv. i Ystad fr. 44.\n\n",
    "structured": {
        "1": {
            "full_name": "Sandblad, Nils Gösta",
            "location": "Lund",
            "occupation": "docent",
            "birth_details": {
                "date": "02/09/1910",
                "place": "Lund",
                "parents": "rådm. John S. o. Nanny Hallen"
            },
            "education": [
                {
                    "degree": "Stud:ex.",
                    "year": "1928",
                    "institution": "NULL"
                },
                {
                    "degree": "filosofie kandidat",
                    "year": "1933",
                    "institution": "NULL"
                },
                {
                    "degree": "filosofie licentiat",
                    "year": "1935",
                    "institution": "NULL"
                },
                {
                    "degree": "filosofie doktor",
                    "year": "1944",
                    "institution": "NULL"
                }
            ],
            "career": [
                {
                    "position": "E. o. aman. v. Lunds univ. konstmus.",
                    "years": {
                        "start_year": 31,
                        "end_year": 33
                    },
                    "organization": "NULL"
                },
                {
                    "position": "aman. där",
                    "years": {
                        "start_year": 33,
                        "end_year": 36
                    },
                    "organization": "NULL"
                },
                {
                    "position": "doc. v. Lunds undv. i konsthist.",
                    "years": {
                        "start_year": 44,
                        "end_year": "NULL"
                    },
                    "organization": "NULL"
                },
                {
                    "position": "docentstip.",
                    "years": {
                        "start_year": 46,
                        "end_year": "NULL"
                    },
                    "organization": "NULL"
                }
            ],
            "family": {
                "spouse": "Margot Randen",
                "marriage_year": "NULL",
                "children": [
                    {
                        "name": "Helena",
                        "birth_year": "1937"
                    },
                    {
                        "name": "Elisabeth",
                        "birth_year": "1939"
                    },
                    {
                        "name": "John",
                        "birth_year": "1944"
                    }
                ]
            }
        },
        "2": {
            "full_name": "Sandblom, Per Gustaf",
            "location": "Malmö",
            "occupation": "civilingenjör SVR",
            "birth_details": {
                "date": "18/04/1909",
                "place": "Gbq",
                "parents": "O. M. S. o. Hulda Ohlsson"
            },
            "education": [
                {
                    "degree": "Stud:ex. v. h. a. 1. i Malmö",
                    "year": "1928",
                    "institution": "NULL"
                },
                {
                    "degree": "NULL",
                    "year": "1933",
                    "institution": "KTH"
                }
            ],
            "career": [
                {
                    "position": "NULL",
                    "years": {
                        "start_year": "NULL",
                        "end_year": "NULL"
                    },
                    "organization": "NULL"
                }
            ],
            "family": {
                "spouse": "Märta FoTsiström",
                "marriage_year": "NULL",
                "children": [
                    {
                        "name": "Birgitta",
                        "birth_year": "1934"
                    },
                    {
                        "name": "Gunilla",
                        "birth_year": "1939"
                    }
                ]
            },
            "hobbies": [
                "fiske",
                "foto"
            ]
        },
        "3": {
            "full_name": "Sandborg, Erik Gustaf",
            "location": "Södra Rörum",
            "occupation": "kyrkoherde",
            "birth_details": {
                "date": "01/07/1897",
                "place": "Fulltofta, Malmöh",
                "parents": "NULL"
            },
            "education": [
                {
                    "degree": "Stud:ex. i Lund",
                    "year": "1916",
                    "institution": "NULL"
                },
                {
                    "degree": "teol kand",
                    "year": "NULL",
                    "institution": "NULL"
                },
                {
                    "degree": "prakt. teol. prov",
                    "year": "NULL",
                    "institution": "NULL"
                }
            ],
            "career": [
                {
                    "position": "V. pastor i Östra Kärrstorp",
                    "years": {
                        "start_year": 24,
                        "end_year": 27
                    },
                    "organization": "NULL"
                },
                {
                    "position": "kommin. i Södra Sallerup",
                    "years": {
                        "start_year": 27,
                        "end_year": 36
                    },
                    "organization": "NULL"
                },
                {
                    "position": "kyrkoh. i Södra Rörum o. Häglinge",
                    "years": {
                        "start_year": 35,
                        "end_year": "NULL"
                    },
                    "organization": "NULL"
                }
            ],
            "family": {
                "spouse": "Kerstin Viol-a (Wi-van) Valborg Nyström",
                "marriage_year": "NULL",
                "children": [
                    {
                        "name": "Sven",
                        "birth_year": "1930"
                    },
                    {
                        "name": "Kerstin",
                        "birth_year": "1932"
                    },
                    {
                        "name": "Hans",
                        "birth_year": "1936"
                    }
                ]
            },
            "community_involvement": [
                {
                    "role": "Ordf.",
                    "organization": "Södra Rörums o. Häglinge kyrkostämmor",
                    "years": "NULL"
                },
                {
                    "role": "Ordf.",
                    "organization": "ungd :krets",
                    "years": "NULL"
                }
            ],
            "board_memberships": [],
            "hobbies": []
        },
        "4": {
            "full_name": "af Sandeberg, Per Herman Hugo David",
            "location": "Ystad",
            "occupation": "tandläkare",
            "birth_details": {
                "date": "18/09/1910",
                "place": "Lund",
                "parents": "dir. Milis af S. o. Agnes Evander"
            },
            "education": [
                {
                    "degree": "Stud:ex. i Lund",
                    "year": "1930",
                    "institution": "NULL"
                },
                {
                    "degree": "med. stud. ii Lund",
                    "year": "1930-1932",
                    "institution": "NULL"
                },
                {
                    "degree": "tandläkarex",
                    "year": "1936",
                    "institution": "NULL"
                }
            ],
            "career": [
                {
                    "position": "assist, v. tandl :imst. tandfyTln :avd.",
                    "years": {
                        "start_year": 36,
                        "end_year": "NULL"
                    },
                    "organization": "NULL"
                },
                {
                    "position": "assist, i Halmstad",
                    "years": {
                        "start_year": "7 mån. 37",
                        "end_year": "NULL"
                    },
                    "organization": "NULL"
                },
                {
                    "position": "prakt, i Lund",
                    "years": {
                        "start_year": 37,
                        "end_year": 41
                    },
                    "organization": "NULL"
                },
                {
                    "position": "förest, f. folktandv. i Ystad",
                    "years": {
                        "start_year": 44,
                        "end_year": "NULL"
                    },
                    "organization": "NULL"
                }
            ],
            "family": {
                "spouse": "Ingrid Engman",
                "marriage_year": "NULL",
                "children": [
                    {
                        "name": "Margareta",
                        "birth_year": "1941"
                    },
                    {
                        "name": "Ulf",
                        "birth_year": "1945"
                    }
                ]
            }
        }
    }
}