{
    "original": "NYMAN, JACQUES H, fd sjöfartsråd,\nSthlm, f på Gotska Sandön, Gotl l,\n25/4/94 av kassör Herman N o Beda\nJohansson.\n\nFänr v flottan 19, löjtn 21, kapt res\n34, lotslöjtn Kalmar 30, Malmö 39,\nlots-kapt 42 o lotsdir mell distr 45, byråch\nlotsstyr 46, sjöfartsråd o ch sjöfartsstyr\nnaut byrå 56-60. - Sjöoff:ex 19, KSHS\n24-25. - Ordf fören Gotlands gille Sthlm\n52-61. - Utm: RNO.\nGift 21 m Ebba Lindquist f 95, dtr\nt bankokommissarie Ernst L o\nHildegard Andersson. - Barn: Margareta\nf 22, Ingegerd f 25, Kerstin f 26, Jacques\nf 31.\n\nNYMAN, NILS E, tandläkare,\nFarsta, f i Sveg, Jämtl l, 23/1/26 av\nskogs-ch Oscar N o Hanna Eriksson.\nStud:ex Härnösand 46, tandläk:ex 52,\ndistr:tandläk 53, eg praktik Farsta sed\n57.\n\nGift 53 m Kersti Lundborg f 31, dtr\nt civiling Einar L o Greta Kling.\n-Barn: Kristina f 60.\n\nNYMAN, P-O (OLLE), professor,\nkonstnär, Saltsjö-Duvnäs, f i Nacka\n241’121W av konstn Hilding N o Edith\nKüsel.\n\nFilip Månssons målarsk 26-28, KKH\n28-34, prof i målning KKH sed 53.\n-Led stat konstråd 55-58, Sthlms\nskol-direkt konstnd 59, Nacka kukurnd 61,\nmedl Sv konstn fören, Konstn :klubben,\nKRO, SHT m fi. - LFrKA 53. - Utf\ndekor arb f restaurant Grenadjären\nSthlm 40-41, Västerås stadsteat foyer 47,\nKungsberga folksk Norrkpg 50, Karol\nsjh 51, Karol inst kårhus 55, Blomma\nflyghamns restaurant 55, Borås nya\nstadshus 57, Olaus Petri-kyrkan Gärdet\nSthlm 58-60, Sv hdlsbkn 59-62 m m.\n-Sep:utst Sthlm 46, 50 o 52. - Repr\ni Nät :mus, Arkivmus Lund, Västerås,\nMalmö, Östersund o Kalmar mus.\n-Utm: RNO.\n\n",
    "structured": {
        "0": {
            "full_name": "Jacques H Nyman",
            "location": "Sthlm",
            "occupation": "fd sjöfartsråd",
            "birth_details": {
                "date": "25/04/1894",
                "place": "Gotska Sandön, Gotl l",
                "parents": "av kassör Herman N o Beda Johansson"
            },
            "education": [
                {
                    "degree": "Sjöoff:ex",
                    "year": "1919",
                    "institution": "KSHS"
                }
            ],
            "career": [
                {
                    "position": "Fänr v flottan",
                    "years": {
                        "start_year": 1919,
                        "end_year": 1921
                    },
                    "organization": "flottan"
                },
                {
                    "position": "löjtn",
                    "years": {
                        "start_year": 1921,
                        "end_year": 1934
                    },
                    "organization": "flottan"
                },
                {
                    "position": "kapt res",
                    "years": {
                        "start_year": 1934,
                        "end_year": 1942
                    },
                    "organization": "flottan"
                },
                {
                    "position": "lotslöjtn",
                    "years": {
                        "start_year": 1930,
                        "end_year": null
                    },
                    "organization": "Kalmar"
                },
                {
                    "position": "lots-kapt",
                    "years": {
                        "start_year": 1942,
                        "end_year": null
                    },
                    "organization": null
                },
                {
                    "position": "lotsdir mell distr",
                    "years": {
                        "start_year": 1945,
                        "end_year": null
                    },
                    "organization": null
                },
                {
                    "position": "byråch lotsstyr",
                    "years": {
                        "start_year": 1946,
                        "end_year": null
                    },
                    "organization": null
                },
                {
                    "position": "sjöfartsråd o ch sjöfartsstyr naut byrå",
                    "years": {
                        "start_year": 1956,
                        "end_year": 1960
                    },
                    "organization": "sjöfartsstyr naut byrå"
                }
            ],
            "family": {
                "spouse": "Ebba Lindquist",
                "marriage_year": "1921",
                "children": [
                    {
                        "name": "Margareta",
                        "birth_year": "1922"
                    },
                    {
                        "name": "Ingegerd",
                        "birth_year": "1925"
                    },
                    {
                        "name": "Kerstin",
                        "birth_year": "1926"
                    },
                    {
                        "name": "Jacques",
                        "birth_year": "1931"
                    }
                ]
            }
        },
        "1": {
            "full_name": "Nils E Nyman",
            "location": "Farsta",
            "occupation": "tandläkare",
            "birth_details": {
                "date": "23/01/1926",
                "place": "Sveg, Jämtl l",
                "parents": "av skogs-ch Oscar N o Hanna Eriksson"
            },
            "education": [
                {
                    "degree": "Stud:ex",
                    "year": "1946",
                    "institution": "Härnösand"
                },
                {
                    "degree": "tandläk:ex",
                    "year": "1952",
                    "institution": null
                },
                {
                    "degree": "distr:tandläk",
                    "year": "1953",
                    "institution": null
                }
            ],
            "career": [
                {
                    "position": "eg praktik",
                    "years": {
                        "start_year": 1957,
                        "end_year": null
                    },
                    "organization": "Farsta"
                }
            ],
            "family": {
                "spouse": "Kersti Lundborg",
                "marriage_year": "1953",
                "children": [
                    {
                        "name": "Kristina",
                        "birth_year": "1960"
                    }
                ]
            }
        },
        "2": {
            "full_name": "P-O (OLLE) Nyman",
            "location": "Saltsjö-Duvnäs",
            "occupation": "professor, konstnär",
            "birth_details": {
                "date": "24/12/1921",
                "place": "Nacka",
                "parents": "av konstn Hilding N o Edith Küsel"
            },
            "education": [
                {
                    "degree": "Filip Månssons målarsk",
                    "year": "1926-1928",
                    "institution": null
                },
                {
                    "degree": "KKH",
                    "year": "1928-1934",
                    "institution": null
                }
            ],
            "career": [
                {
                    "position": "prof i målning",
                    "years": {
                        "start_year": 1953,
                        "end_year": null
                    },
                    "organization": "KKH"
                }
            ],
            "family": null
        }
    }
}