{
    "original": "NYRIN-HEUMAN, ELLA K, fil dr,\nrektor, Saltsjö-Duvnäs, f i Ransäters\nförs, Värml l, 25/8/08 av\nkontraktsprost Johan Nyrin o Anna Billgren.\nStud:ex Sthlm 26, fil mag Upps 30,\nfil lic Lund 35, fü dr 44. - Ämneslär\nWallin-Åhlinska gymn 39, lektor hal\n48, rektor Wallin-Åhlinska gymn sed\n55. - Ordf Sollefteå-krets av\nFredrika Bremer förb 53-55. - Skr: Studier till\nEricus Olai Chronica (44), Latinska\ntexter från svensk medeltid (47).\nGift 41 m lektor Bengt Heuman f 06.\n\n-  Barn: Rolf f 42, Åsa f 45, Karin f 47.\nNYSTEDT,     LENNART     J,\ndirektör, Danderyd, f i Norberg, Västmanl l,\n22/2/17.\n\nHdlsstudier, inköpsch Levinbol\nMalmö 46, kamr Ytongbol kont Malmö 47,\nbitr försäljn’.ch dess huvudkont i\nHällabrottet 53, v verkst dir ab Lättbetong\nSthlm sed 58.\n\nGift 54 m Märta Andréen f 20.\nNYSTEDT, B O (OLLE)\növerhovpredikant,  fd  pastor  primarius,   Sthlm,   f\ni Gbg 24/3/88 av folkskollär Bengt N o\nAnna  Svensson.\n\nStud:ex 07, teol kand Upps 12, prästv\nGbg 13, bitr pastor Samariterhemmet\nUpps 13, sekr Sv kyrkans diakonistyr\n14, komminister Annedals förs Gbg 19,\nkyrkoh Dala 20, adj Oscars förs Sthlm\n28, komminister Johannes förs 35, eo\nhovpred 37, domprost Gbg 37-42, pastor\nprimarius, domprost o kontr:prost\nDomprost kontr Sthlm 42-58, överhovpred\nsed 59. - Led kyrkomöten, ordf Pro\nFide et Christianismo 44, Sv kyrkans\ndiakonistyr skriftutsk, v ordf Sv\nIsraelis-miss, Blomsterfonden, diakonistyr EU,\nsekr Sv bibeMllsk. - LVVS 40, teol\nhed:dr Upps 49. - Utg: Biografi över\nNathan Söderblom (31), Ett kyrkoår\n(33), Från studentkorståget till Sigtuna-\n\nstiftelsen (36), Stockholmspräster (37),\nNär dagen börjar (41), Heligdagsord för\nvardagsliv (I 45, II 46, III 47),\nPredikan o Guds ord (prästm:avh 51),\nDet lider mot aftonen (53), Hemmets\nhelger (56), Vid helgmålsiingningen\n(60), mfl; red Vår Lösen 13, Sv:es ungd\n14-20, Västgötaungd julbok 26-28,\nJulhelg 33, 37. - Utm: GV:sJmtll, KNO\nl kl, KFinlVRO, KGrGO, KNS:tOO.\nGift 13 m Gurli Nordling f 86 d 61,\ndtr t kontr:prost Erik N o Ida Petré.\n- Barn: Bengt-Erik f 14, Hans f 16,\nAnn-Sophie f 17, Birgitta f 19, Sven f 22,\nLars f 30.\n\n",
    "structured": {
        "0": {
            "full_name": "NYRIN-HEUMAN, ELLA K",
            "location": "Saltsjö-Duvnäs",
            "occupation": "Rektor",
            "birth_details": {
                "date": "25/08/1908",
                "place": "Ransäters förs, Värml l",
                "parents": "kontraktsprost Johan Nyrin o Anna Billgren"
            },
            "education": [
                {
                    "degree": "Stud",
                    "year": "1926",
                    "institution": "Sthlm"
                },
                {
                    "degree": "filosofie magister",
                    "year": "1930",
                    "institution": "Upps"
                },
                {
                    "degree": "filosofie licentiat",
                    "year": "1935",
                    "institution": "Lund"
                },
                {
                    "degree": "filosofie doktor",
                    "year": "1944",
                    "institution": null
                }
            ],
            "career": [
                {
                    "position": "Ämneslär",
                    "years": {
                        "start_year": 1939,
                        "end_year": null
                    },
                    "organization": "Wallin-Åhlinska gymn 39"
                },
                {
                    "position": "lektor hal",
                    "years": {
                        "start_year": 1948,
                        "end_year": null
                    },
                    "organization": null
                },
                {
                    "position": "rektor",
                    "years": {
                        "start_year": 1955,
                        "end_year": null
                    },
                    "organization": "Wallin-Åhlinska gymn"
                }
            ],
            "family": {
                "spouse": "lektor Bengt Heuman",
                "marriage_year": "1941",
                "children": [
                    {
                        "name": "Rolf",
                        "birth_year": "1942"
                    },
                    {
                        "name": "Åsa",
                        "birth_year": "1945"
                    },
                    {
                        "name": "Karin",
                        "birth_year": "1947"
                    }
                ]
            }
        },
        "1": {
            "full_name": "NYSTEDT, LENNART J",
            "location": "Danderyd",
            "occupation": "direktör",
            "birth_details": {
                "date": "22/02/1917",
                "place": "Norberg, Västmanl l",
                "parents": null
            },
            "education": null,
            "career": [
                {
                    "position": "bitr försäljn’ch",
                    "years": {
                        "start_year": 1953,
                        "end_year": null
                    },
                    "organization": "Ytongbol kont Malmö"
                },
                {
                    "position": "v verkst dir",
                    "years": {
                        "start_year": 1958,
                        "end_year": null
                    },
                    "organization": "ab Lättbetong Sthlm"
                }
            ],
            "family": {
                "spouse": "Märta Andréen",
                "marriage_year": "1954",
                "children": null
            }
        },
        "2": {
            "full_name": "NYSTEDT, B O (OLLE)",
            "location": "Sthlm",
            "occupation": "överhovpredikant",
            "birth_details": {
                "date": "24/03/1888",
                "place": "Gbg",
                "parents": "folkskollär Bengt N o Anna Svensson"
            },
            "education": [
                {
                    "degree": "Stud",
                    "year": "1907",
                    "institution": null
                },
                {
                    "degree": "teol kand",
                    "year": "1912",
                    "institution": "Upps"
                }
            ],
            "career": [
                {
                    "position": "bitr pastor",
                    "years": {
                        "start_year": 1913,
                        "end_year": 1913
                    },
                    "organization": "Samariterhemmet Upps"
                },
                {
                    "position": "sekr",
                    "years": {
                        "start_year": 1914,
                        "end_year": null
                    },
                    "organization": "Sv kyrkans diakonistyr"
                },
                {
                    "position": "kyrkoh",
                    "years": {
                        "start_year": 1920,
                        "end_year": null
                    },
                    "organization": "Dala"
                },
                {
                    "position": "adj",
                    "years": {
                        "start_year": 1928,
                        "end_year": 1935
                    },
                    "organization": "Oscars förs Sthlm"
                },
                {
                    "position": "komminister",
                    "years": {
                        "start_year": 1935,
                        "end_year": null
                    },
                    "organization": "Johannes förs"
                },
                {
                    "position": "eo hovpred",
                    "years": {
                        "start_year": 1937,
                        "end_year": 1937
                    },
                    "organization": null
                },
                {
                    "position": "domprost",
                    "years": {
                        "start_year": 1937,
                        "end_year": 1942
                    },
                    "organization": "Gbg"
                },
                {
                    "position": "pastor primarius, domprost o kontr:prost",
                    "years": {
                        "start_year": 1942,
                        "end_year": 1958
                    },
                    "organization": "Domprost kontr Sthlm"
                },
                {
                    "position": "överhovpred",
                    "years": {
                        "start_year": 1959,
                        "end_year": null
                    },
                    "organization": null
                }
            ],
            "family": {
                "spouse": "Gurli Nordling",
                "marriage_year": "1913",
                "children": [
                    {
                        "name": "Bengt-Erik",
                        "birth_year": "1914"
                    },
                    {
                        "name": "Hans",
                        "birth_year": "1916"
                    },
                    {
                        "name": "Ann-Sophie",
                        "birth_year": "1917"
                    },
                    {
                        "name": "Birgitta",
                        "birth_year": "1919"
                    },
                    {
                        "name": "Sven",
                        "birth_year": "1922"
                    },
                    {
                        "name": "Lars",
                        "birth_year": "1930"
                    }
                ]
            }
        }
    }
}