{
    "original": "NELSON, N V STEN, aukt revisor,\nSthlm, f i Malmö 3/10/06, av köpman\nJohn N o Betty Malmström.\nCivilekonom 27, aukt rev Sthlms\nhdlskamm 34, eg rev :byrå sed 35. - V ordf\nApotekens avgiftsnd sed 53, led\nHdls-kamrarnas centrala revisorsnd 55-60,\nordf Fören aukt rev 55-60, Nord\nrev:-förb 57-59, pres S:e Nord rev:kongr\nSthlm 59. - Utm: RVO.\n\nNEMES, ENDRE, konstnär, Sthlm,\nfi Pécsvårad, Ungern, 10/11/09 av\nfinansrådet Ignåc Nagel o Elisabeth\nKu-gel.\n\nStud:ex 27, konstakad Prag 30-34, lär\nFria målarsk Hfors 39, förest o lär\nValands konstsk Gbg 47-55. - Sv medb\n48, kungastip 59. - Bl arb:\nZodiaken-klockan i emalj Västertorp (50),\ntak-måln Hotell Lysekil (51-52),\nbalettdekor K teat (49), marmorintarsia\nHögs-botorp (55), emaljfris Eriksdalssk\nSkövde (55), väggmåln fil fakultetens kårhus\nGbg (56), emaljmåln Skogome\nfångv:-anst (58), emaljdekor kommunalhuset\nNol (60), scendekor o kostymer operan\nOm jag vore kung Stora teat Gbg (60).\n- Utst bl ä Oslo 39, 59 o 60, Sthlm\n41, 44, 47, 51, 58 o 61, Malmö 41, Gbg\n\n48, 51, 58 o 61, Köpenh 45, Philadelphia\n55, Nord utst Odense 59, Freiburg 59,\nDanmark 60, Hamburg 61, Basel,\nLondon o Malmö 61. - Repr Nät :mus, Gbgs\nkonstmus, Waldemarsudde, Ateneum\nH-fors, Borås o Kalmar mus, ark f dek\nkonst Lund m fi. - Medl Graf sällsk.\n-Skr: Monografi (55).\nGift 45 m Héléne Exemplaroff f 06,\ndtr t bankdir Vasilij E o Ljubow\nLohr-berg. - Barn: Catherine f 47.\n\nNERBY, ÅKE F, disponent, Lidingö,\nf i Sthlm 16/11/20.\n\nStud:ex 41, jur kand 48, DHS 53, anst\nPKN 46, Ffygtekn försöksanst 49, Graf\narb :giv:-  o  ind :org  51-60,  disp Victor\nPettersons bokind ab Sthlm.\nGift m Inga Nil’sson.\n\n",
    "structured": {
        "1": {
            "full_name": "NELSON, N V STEN",
            "location": "Sthlm",
            "occupation": "aukt revisor",
            "birth_details": {
                "date": "03/10/1906",
                "place": "Malmö",
                "parents": "John N o Betty Malmström"
            },
            "education": [
                {
                    "degree": "Civilekonom",
                    "year": "1927",
                    "institution": "Unknown"
                }
            ],
            "career": [
                {
                    "position": "aukt rev",
                    "years": {
                        "start_year": 1935,
                        "end_year": null
                    },
                    "organization": "Sthlms hdlskamm"
                },
                {
                    "position": "V ordf Apotekens avgiftsnd",
                    "years": {
                        "start_year": 1953,
                        "end_year": null
                    },
                    "organization": null
                },
                {
                    "position": "ordf Fören aukt rev",
                    "years": {
                        "start_year": 1955,
                        "end_year": 1960
                    },
                    "organization": null
                }
            ],
            "family": {
                "spouse": "NULL",
                "marriage_year": "NULL",
                "children": []
            }
        },
        "2": {
            "full_name": "NEMES, ENDRE",
            "location": "Sthlm",
            "occupation": "konstnär",
            "birth_details": {
                "date": "10/11/1909",
                "place": "Pécsvårad, Ungern",
                "parents": "finansrådet Ignåc Nagel o Elisabeth Kugel"
            },
            "education": [
                {
                    "degree": "Stud:ex",
                    "year": "1927",
                    "institution": "Unknown"
                },
                {
                    "degree": "Sv medb",
                    "year": "1948",
                    "institution": "Unknown"
                }
            ],
            "career": [],
            "family": {
                "spouse": "Héléne Exemplaroff",
                "marriage_year": "1945",
                "children": [
                    {
                        "name": "Catherine",
                        "birth_year": "1947"
                    }
                ]
            }
        },
        "3": {
            "full_name": "NERBY, ÅKE F",
            "location": "Lidingö",
            "occupation": "disponent",
            "birth_details": {
                "date": "16/11/1920",
                "place": "Sthlm",
                "parents": "NULL"
            },
            "education": [
                {
                    "degree": "Stud:ex",
                    "year": "1941",
                    "institution": "Unknown"
                },
                {
                    "degree": "jur kand",
                    "year": "1948",
                    "institution": "Unknown"
                },
                {
                    "degree": "DHS",
                    "year": "1953",
                    "institution": "Unknown"
                }
            ],
            "career": [],
            "family": {
                "spouse": "Inga Nil’sson",
                "marriage_year": "NULL",
                "children": []
            }
        }
    }
}