{
    "original": "ELMQVIST, NILS-ERIC, ingenjör,\nSödertälje, f i Grythyttan, Örebro l, 1/7/13\nav postmast Elof E o Ida Tholander.\nStud:ex JÖnkpg 33, res:off:ex 35, ing :ex\nSTI 41; anst ab J G Ljungbergs\nmetall-fabr Jönkpg 34-37 o 39, ing ab Sv\nfläkt-fabr 41, gruppch ab Sv maskinverken\nKallhäll 47, sekt:ch där sed 54. - Medl\nOdd Fellow, S:ta Ragnhilds gille.\n-Kapt I 12 res. - H o b by: fiske.\nGift 41 m Britta Lindström f 19, dtr t\ning Emil L o Annie Johansson. - Barn:\nLars f 43, Lena f 47.\n\nELMQUIST, ÅKE S, ingenjör, Örebro,\nf i Lysekil 9/8/23 av Johan E o Sylvi\nOlsson.\n\nIng:ex STI 42, anst LME Sthlm 42,\nBillman ab 46, Luxor Motala 47, platsch\nLME Örebro sed 50. - Hobby: segling.\nGift 46 m Gärdis Holmgren f 19, dtr t\nOtto H o Maria H. - Barn: Leif f 48,\nBengt f 51.\n\nELMROTH, ARTHUR E, fd\nlandstingsordförande, Tierp, f i Fagerhult,\nKalmar l, 4/11/92 av lantbr Anders\nCarlsson o Mina Eriksson.\nFolkhögsk o lantm:sk 09-10,\nfjärdingsman Tierp 22-53, driver num\nauktionsverks, fastigh :f örmedl o skogsbruk.\n-AK 33-36 (s), ordf Uppsala l landst\n43’-59 (led 22, ordf FU), led länets\nlantbr:-o länsarb:ndr, hushålln:sällsk FU, ordf\ndirektionen f Akad sjh Upps sed 53, led\ndess byggn :komm, styr :ordf Jälla\nlantm:sk, styr:led Upps sjuksköt:sk, ordf\nUpps l n:a vägnd, led länsvägndn.\n-HedL Uppl nät. - Utm: GMmfl2.\nGift 25 m sjuksköt Elsa Björklund f 96,\ndtr t hammarsmed Vilhelm B o Ulrika\nForsell. - Barn: Gudrun f 27, Lili-Ann\nf 31, Thorsten f 33.\n\nELMWALL, EMIL, riksdagsman,\nSparreholm, f i Torshälla 13/9/00 av\nskeppare Johan Andersson o Emma\nPettersson.\n\nUltuna 20, vik förest Hudiksvalls stads\nvårdhem 21, förman Bona uppfostr:anst\n21-24, jordbr sed 25, inneh Björkhults\ngård. - AK 58 (cp), hv:ch 44-59,\nstyr:-ordf Lantm slakt:fören 51 (led 34), S\nSörml chark:bol 50, Sv hdlsbkns\navd:-kont 50 (led 40), led komm:fullm 36-47,\nkomm:nd, pastoratskyrkoråd, skolstyr\nm fi. - Medl Rotary. - Utm: HvGM,\nSLKSM. - Hobbies: politik, ekonomi.\n\nGift 24 m Alma Ekengren f 03, dtr t\nhemm:äg Adolf E o Augusta Andersson.\n\n-  Barn: Gunborg f 24, Sten f 26, Thord\nf 35, Bengt f 40.\n\n",
    "structured": {
        "1": {
            "full_name": "NILS-ERIC ELMQVIST",
            "location": "Södertälje",
            "occupation": "Ingenjör",
            "birth_details": {
                "date": "01/07/1913",
                "place": "Grythyttan, Örebro l"
            },
            "education": [
                {
                    "degree": "Stud",
                    "year": "1933",
                    "institution": "Jönkpg"
                },
                {
                    "degree": "res:off",
                    "year": "1935",
                    "institution": null
                },
                {
                    "degree": "ing",
                    "year": "1941",
                    "institution": "STI"
                }
            ],
            "career": [
                {
                    "position": "anst",
                    "years": {
                        "start_year": 1934,
                        "end_year": 1937
                    },
                    "organization": "ab J G Ljungbergs metall-fabr Jönkpg"
                },
                {
                    "position": "ing",
                    "years": {
                        "start_year": 1941,
                        "end_year": null
                    },
                    "organization": "ab Sv fläkt-fabr"
                },
                {
                    "position": "gruppch",
                    "years": {
                        "start_year": 1947,
                        "end_year": null
                    },
                    "organization": "ab Sv maskinverken Kallhäll"
                }
            ],
            "family": {
                "spouse": "Britta Lindström",
                "marriage_year": "1941",
                "children": [
                    {
                        "name": "Lars",
                        "birth_year": "1943"
                    },
                    {
                        "name": "Lena",
                        "birth_year": "1947"
                    }
                ]
            },
            "hobbies": [
                "fiske"
            ]
        },
        "2": {
            "full_name": "ÅKE S ELMQUIST",
            "location": "Örebro",
            "occupation": "Ingenjör",
            "birth_details": {
                "date": "09/08/1923",
                "place": "Lysekil"
            },
            "education": [
                {
                    "degree": "Ing",
                    "year": "1942",
                    "institution": "STI"
                }
            ],
            "career": [
                {
                    "position": "anst",
                    "years": {
                        "start_year": 1942,
                        "end_year": 1946
                    },
                    "organization": "LME Sthlm"
                },
                {
                    "position": null,
                    "years": {
                        "start_year": 1946,
                        "end_year": null
                    },
                    "organization": "Billman ab"
                },
                {
                    "position": "platsch",
                    "years": {
                        "start_year": 1950,
                        "end_year": null
                    },
                    "organization": "LME Örebro"
                }
            ],
            "family": {
                "spouse": "Gärdis Holmgren",
                "marriage_year": "1946",
                "children": [
                    {
                        "name": "Leif",
                        "birth_year": "1948"
                    },
                    {
                        "name": "Bengt",
                        "birth_year": "1951"
                    }
                ]
            },
            "hobbies": [
                "segling"
            ]
        },
        "3": {
            "full_name": "ARTHUR E ELMROTH",
            "location": "Tierp",
            "occupation": "Fd landstingsordförande",
            "birth_details": {
                "date": "04/11/1892",
                "place": "Fagerhult, Kalmar l"
            },
            "education": [
                {
                    "degree": null,
                    "year": "09-10",
                    "institution": "Folkhögsk o lantm:sk"
                }
            ],
            "career": [
                {
                    "position": "fjärdingsman",
                    "years": {
                        "start_year": 1922,
                        "end_year": 1953
                    },
                    "organization": "Tierp"
                },
                {
                    "position": null,
                    "years": {
                        "start_year": null,
                        "end_year": null
                    },
                    "organization": null
                }
            ],
            "family": {
                "spouse": "Elsa Björklund",
                "marriage_year": "1925",
                "children": [
                    {
                        "name": "Gudrun",
                        "birth_year": "1927"
                    },
                    {
                        "name": "Lili-Ann",
                        "birth_year": "1931"
                    },
                    {
                        "name": "Thorsten",
                        "birth_year": "1933"
                    }
                ]
            },
            "honorary_titles": [
                {
                    "title": "HedL Uppl nät",
                    "institution": null,
                    "year": null
                }
            ]
        },
        "4": {
            "full_name": "EMIL ELMWALL",
            "location": "Sparreholm",
            "occupation": "Riksdagsman",
            "birth_details": {
                "date": "13/9/1900",
                "place": "Torshälla"
            },
            "education": [
                {
                    "degree": null,
                    "year": "1920",
                    "institution": "Ultuna"
                }
            ],
            "career": [
                {
                    "position": "vik förest",
                    "years": {
                        "start_year": 1921,
                        "end_year": null
                    },
                    "organization": "Hudiksvalls stads vårdhem"
                },
                {
                    "position": "förman",
                    "years": {
                        "start_year": 1921,
                        "end_year": 1924
                    },
                    "organization": "Bona uppfostr:anst"
                }
            ],
            "family": {
                "spouse": "Alma Ekengren",
                "marriage_year": "1924",
                "children": [
                    {
                        "name": "Gunborg",
                        "birth_year": "1924"
                    },
                    {
                        "name": "Sten",
                        "birth_year": "1926"
                    },
                    {
                        "name": "Thord",
                        "birth_year": "1935"
                    },
                    {
                        "name": "Bengt",
                        "birth_year": "1940"
                    }
                ]
            },
            "hobbies": [
                "politik",
                "ekonomi"
            ]
        }
    }
}