{
    "original": "ELFSTRÖM, NILS G, bruksdisponent,\n\nFagersta, f i Karlskoga 22/8/03 av fabr\nEgidius E o Axelia Eriksson.\nStud:ex Karlstad 21, KTH 25, ing\nFagersta bruks ab 27, avd :ch t 36, övering\nFagerstaverken 36, tekn dir Fagersta\nbruks ab 42, v verkst dir 49, verkst dir\nsed 58. - Fullm Jernkont, styr :led Sv:es\nind:förb, Järnbr:förb, Krångede ab, ab\nDannemora gruvor, Bispbergs ab,\nNorbergs grufförvaltn, Mell o N Sv:es\nång-pannefören, IVA:s ind råd, Metallograf\ninst. - Skr: upps i tekn ämnen. - Utm:\nRVO. - Hobby: fiske.\nGift 29 m Ingeborg Hallen f 06, dtr t\nverkmäst Sanfrid H o Gulli Persson.\n-Barn: Ulla f 30, Nils-Gösta f 33,\nKristina f 41.\n\nELFSTRÖM,    G    ÅKE,    lantbrukare,\n\nSköllersta, f i Sköllersta, Örebro l, 12/8/\n\n08 av grossh Gustav Pettersson o Blenda\n\nElfström.\n\nÖrebro hdlsgymn 27, lantbr sed 37. - V\n\nordf Sköllersta sparbk 52 (styr:led 46),\n\nkomm:fullm, led nykterh:nd, medl Odd\nFellow.\n\nGift 37 m Dagny Wallin, dtr t kantor\nR W o h h. - Barn: Ulla f 41,\nAnna-Lena f 43.\n\nELFVERSON, GEORG O V,\nsemina-rieadjunkt, Strängnäs, f i Ljungby,\nKalmar l, 17/8/05 av fabr Carl E o Berta\nJeansson.\n\nStud:ex Kalmar 24, teol kand Lund 30,\nfil kand 35, lär Hvitf o Vasa hal Gbg\n36-38, hal Kalmar 39, Rostad sem där\n41-42 o 44, Vasa hal Gbg 43, sem :ad j\nHärnösand 45, Strängnäs sed 53. -\nStyr:-suppl Lär :högsk o sem lär:förb.\nGift 43 m Dagmar Bodlund f 17, dtr t\nkomm :kamr Axel B o Agda Gustafsson.\n- Barn: Gösta f 44, Jörgen f 46, Tom\nf 53.\n\n",
    "structured": {
        "0": {
            "full_name": "ELFSTRÖM, NILS G",
            "location": "Fagersta",
            "occupation": "bruksdisponent",
            "birth_details": {
                "date": "22/8/1903",
                "place": "Karlskoga",
                "parents": "fabr Egidius E o Axelia Eriksson"
            },
            "education": [
                {
                    "degree": "Stud:ex",
                    "year": "1921",
                    "institution": "Karlstad"
                },
                {
                    "degree": "KTH",
                    "year": "1925",
                    "institution": "Kungliga Tekniska Högskolan"
                }
            ],
            "career": [
                {
                    "position": "ing",
                    "years": {
                        "start_year": 1927,
                        "end_year": 1936
                    },
                    "organization": "Fagersta bruks ab"
                },
                {
                    "position": "avd :ch t",
                    "years": {
                        "start_year": 1936,
                        "end_year": null
                    },
                    "organization": "Fagerstaverken"
                },
                {
                    "position": "övering",
                    "years": {
                        "start_year": 1936,
                        "end_year": null
                    },
                    "organization": "Fagersta bruks ab"
                },
                {
                    "position": "tekn dir",
                    "years": {
                        "start_year": 1942,
                        "end_year": null
                    },
                    "organization": "Fagersta bruks ab"
                },
                {
                    "position": "v verkst dir",
                    "years": {
                        "start_year": 1949,
                        "end_year": null
                    },
                    "organization": "Fagersta bruks ab"
                },
                {
                    "position": "verkst dir",
                    "years": {
                        "start_year": 1958,
                        "end_year": null
                    },
                    "organization": "Fagersta bruks ab"
                }
            ],
            "family": {
                "spouse": "Ingeborg Hallen",
                "marriage_year": "1929",
                "children": [
                    {
                        "name": "Ulla",
                        "birth_year": "1930"
                    },
                    {
                        "name": "Nils-Gösta",
                        "birth_year": "1933"
                    },
                    {
                        "name": "Kristina",
                        "birth_year": "1941"
                    }
                ]
            },
            "publications": [
                {
                    "title": null,
                    "year": null,
                    "type": null
                }
            ],
            "hobbies": [
                "fiske"
            ]
        },
        "1": {
            "full_name": "ELFSTRÖM, G ÅKE",
            "location": "Sköllersta",
            "occupation": "lantbrukare",
            "birth_details": {
                "date": "12/8/1908",
                "place": "Sköllersta, Örebro l",
                "parents": "grossh Gustav Pettersson o Blenda Elfström"
            },
            "education": [
                {
                    "degree": "Örebro hdlsgymn",
                    "year": "1927",
                    "institution": "Örebro handelsgymnasium"
                }
            ],
            "career": [
                {
                    "position": "lantbr",
                    "years": {
                        "start_year": 1937,
                        "end_year": null
                    },
                    "organization": null
                }
            ],
            "family": {
                "spouse": "Dagny Wallin",
                "marriage_year": "1937",
                "children": [
                    {
                        "name": "Ulla",
                        "birth_year": "1941"
                    },
                    {
                        "name": "Anna-Lena",
                        "birth_year": "1943"
                    }
                ]
            },
            "publications": [
                {
                    "title": null,
                    "year": null,
                    "type": null
                }
            ],
            "community_involvement": [
                {
                    "role": null,
                    "organization": "Odd Fellow",
                    "years": null
                }
            ]
        },
        "2": {
            "full_name": "ELFVERSON, GEORG O V",
            "location": "Strängnäs",
            "occupation": "seminariejadjunkt",
            "birth_details": {
                "date": "17/8/1905",
                "place": "Ljungby, Kalmar l",
                "parents": "fabr Carl E o Berta Jeansson"
            },
            "education": [
                {
                    "degree": "Stud:ex",
                    "year": "1924",
                    "institution": "Kalmar"
                },
                {
                    "degree": "teol kand",
                    "year": "1930",
                    "institution": "Lund"
                },
                {
                    "degree": "fil kand",
                    "year": "1935",
                    "institution": null
                }
            ],
            "career": [
                {
                    "position": "lär",
                    "years": {
                        "start_year": 1939,
                        "end_year": null
                    },
                    "organization": "Kalmar"
                },
                {
                    "position": "sem :ad j",
                    "years": {
                        "start_year": 1945,
                        "end_year": null
                    },
                    "organization": "Strängnäs"
                }
            ],
            "family": {
                "spouse": "Dagmar Bodlund",
                "marriage_year": "1943",
                "children": [
                    {
                        "name": "Gösta",
                        "birth_year": "1944"
                    },
                    {
                        "name": "Jörgen",
                        "birth_year": "1946"
                    },
                    {
                        "name": "Tom",
                        "birth_year": "1953"
                    }
                ]
            },
            "publications": [
                {
                    "title": null,
                    "year": null,
                    "type": null
                }
            ]
        }
    }
}