{
    "original": "ENGBLOM, C JERKER, lektor,\nKarlstad, f i Vadstena 26/3/26 av rektor\nVictor E o Maja Smith.\nStud:ex Borås 45, fil mag Upps 51, fil\nlic 56, sv lekt Univ of Pennsylvania 55,\nAugustana Coll 57, eo adj hum lärov\nSigtuna 58, lekt hal Karlstad sed 60.\n-l:e kur Västg nät Upps 52, ordf Upps\nstud:kår 53, Värml:distr Modersmålslär\nfören lokalavd, medl SHT. - Visprogr i\nradio. - Skr: art i Samlaren (53) m fi.\n-Hobby: sång.\n\nGift 52 m Inga Johansson, dtr t köpm\nKnut J o Anna Andersson. - Barn:\nIngrid f 54, Katarina f 57.\n\nENGBOM,   C   ALLAN,   bankkamrer,\n\nFlen, f i Västerås 17/5/25 av\ngalvanisa-tör Arvid E o Olga Andersson.\nAnst Asea 42, Upl ensk bk Västerås 46,\nSv hdlsbkn Sthlm 50, Eskilstuna 54,\nkamr o styr :led Sv hdlsbkns avd :kont\nFlen sed 59. - Rev Flens\nfastigh:äg:-fören sed 60. - Medl Rotary. - Hobbies:\nsport, friluftsliv.\n\nGift 57 m Margareta Johansson f 30,\ndtr t mat:förest Karl J o Hilda J.\n\nENGDAHL,    KURT   H,   tandläkare,\nVästerås,   f   i   Sthlm   29/11/29   av   dir\nHelge E o Anna Lisa Lindbäck.\nStud:ex 50, tandläk:ex Sthlm 55,\nind:-tandläk Asea  Västerås  56,  priv  prakt\ndär sed 62. - Medl FrimO.\nGift 52 m Elisabeth Danielsson f 27,\ndtr t droskchaufför Arvid D o Hagar\nStrömqvist.  - Barn: Birgitta f  53, Eva\nf 55.\n\nENGDAHL, PER H, major,\nOskar-Fredriksborg, f i Ljusdal, Gävleb l,\n5/12/15 av distr:lantmät Ragnar E o\nAnna Nordenstam.\n\nStud:ex Halmstad 35, Off:ex KA 39,\nlöjtn 41, kapt 47, major 54. - KSHS\nstabs- o art:k. - Ch spärrbat KA 1.\n-Utm: RSO. - Hobby: ornitologi.\nGift 47 m Ullagreth Lindén f 22, dtr t\nköpman Sigfrid L o Gretha Nilsson.\n-Barn: Lars f 48, Annika f 50, Britt\nLouise f 54, Per f 56.\n\n",
    "structured": {
        "0": {
            "full_name": "C Jerker Engblom",
            "location": "Karlstad",
            "occupation": "lektor",
            "birth_details": {
                "date": "26/03/1926",
                "place": "Vadstena",
                "parents": "rektor Victor E o Maja Smith"
            },
            "education": [
                {
                    "degree": "Stud:ex",
                    "year": "1945",
                    "institution": "Borås"
                },
                {
                    "degree": "fil mag",
                    "year": "1951",
                    "institution": "Upps"
                },
                {
                    "degree": "filosofie kandidat",
                    "year": "1956",
                    "institution": "Upps"
                }
            ],
            "career": [
                {
                    "position": "sv lekt",
                    "years": {
                        "start_year": 1955,
                        "end_year": 1957
                    },
                    "organization": "Univ of Pennsylvania"
                },
                {
                    "position": "eo adj hum lärov",
                    "years": {
                        "start_year": 1958,
                        "end_year": 1958
                    },
                    "organization": "Sigtuna"
                },
                {
                    "position": "lekt hal",
                    "years": {
                        "start_year": 1960,
                        "end_year": null
                    },
                    "organization": "Karlstad"
                }
            ],
            "family": {
                "spouse": "Inga Johansson",
                "marriage_year": "1952",
                "children": [
                    {
                        "name": "Ingrid",
                        "birth_year": "1954"
                    },
                    {
                        "name": "Katarina",
                        "birth_year": "1957"
                    }
                ]
            },
            "hobbies": [
                "sång"
            ]
        },
        "1": {
            "full_name": "C Allan Engbom",
            "location": "Flen",
            "occupation": "bankkamrer",
            "birth_details": {
                "date": "17/05/1925",
                "place": "Västerås",
                "parents": "galvanisatör Arvid E o Olga Andersson"
            },
            "career": [
                {
                    "position": "kamr o styr :led",
                    "years": {
                        "start_year": 1959,
                        "end_year": null
                    },
                    "organization": "Sv hdlsbkns avd :kont Flen"
                }
            ],
            "family": {
                "spouse": "Margareta Johansson",
                "marriage_year": "1957"
            },
            "hobbies": [
                "sport",
                "friluftsliv"
            ]
        },
        "2": {
            "full_name": "Kurt H Engdahl",
            "location": "Västerås",
            "occupation": "tandläkare",
            "birth_details": {
                "date": "29/11/1929",
                "place": "Sthlm",
                "parents": "dir Helge E o Anna Lisa Lindbäck"
            },
            "education": [
                {
                    "degree": "Stud:ex",
                    "year": "1950"
                },
                {
                    "degree": "tandläk:ex",
                    "year": "1955",
                    "institution": "Sthlm"
                }
            ],
            "career": [
                {
                    "position": "priv  prakt",
                    "years": {
                        "start_year": 1962
                    }
                }
            ],
            "family": {
                "spouse": "Elisabeth Danielsson",
                "marriage_year": "1952",
                "children": [
                    {
                        "name": "Birgitta",
                        "birth_year": "1953"
                    },
                    {
                        "name": "Eva",
                        "birth_year": "1955"
                    }
                ]
            }
        },
        "3": {
            "full_name": "Per H Engdahl",
            "location": "Oskar-Fredriksborg",
            "occupation": "major",
            "birth_details": {
                "date": "5/12/1915",
                "place": "Ljusdal, Gävleb l",
                "parents": "distr:lantmät Ragnar E o Anna Nordenstam"
            },
            "education": [
                {
                    "degree": "Stud:ex",
                    "year": "1935",
                    "institution": "Halmstad"
                },
                {
                    "degree": "Off:ex",
                    "year": "1939",
                    "institution": "KA"
                }
            ],
            "career": [
                {
                    "position": "löjtn",
                    "years": {
                        "start_year": 1941
                    }
                },
                {
                    "position": "kapt",
                    "years": {
                        "start_year": 1947
                    }
                },
                {
                    "position": "major",
                    "years": {
                        "start_year": 1954
                    }
                }
            ],
            "hobbies": [
                "ornitologi"
            ],
            "family": {
                "spouse": "Ullagreth Lindén",
                "marriage_year": "1947",
                "children": [
                    {
                        "name": "Lars",
                        "birth_year": "1948"
                    },
                    {
                        "name": "Annika",
                        "birth_year": "1950"
                    },
                    {
                        "name": "Britt Louise",
                        "birth_year": "1954"
                    },
                    {
                        "name": "Per",
                        "birth_year": "1956"
                    }
                ]
            }
        }
    }
}