{
    "original": "ERIKSSON, H GÖSTA, folkskollärare,\nVästerås, f i Arvika 8/1/23 av tjm\nGustaf E o Sigtre Bergström.\n\nStud:ex Sthlm 43, folkskoll:ex Upps 47,\nfolkskollär Kolbäck o Köping 47-53, lär\nKöpings musiksk 49-53, tillsynslär\nVästerås, lär Västerås musiksk. - Medl\nDruidO. - Skr: brevkurs Gitarr p sång,\nmusikped arb f klarinett o flöjt samt\nmusikteori.\n\nGift 47 m Kerstin Levein, dtr t jvtjm\nE L o J Danielsson. - Barn: Anna-Lena\nf 48, Anders f 51, Pia f 57.\nERIKSSON, K GÖSTA,\nfastighetsmäklare, Västerås, f i Möklinta, Västmanl l,\n17/10/20 av hemm:äg Anders E o Emma\nAndersson.\n\nKöpm:inst Sthlm 38, korr:stud\nrätts-kunsk Hermods 41, af f :bitr\nVästerfärne-bo o Morgongåva 36-40, inneh Sv\nfas-tigh:förmedl Sala 42-52, Västerås sed 46,\naukt fastigh:mäkl, rådgiv fastigh :tax.\n-Medl Odd Fellow, ordf Sv motorkl\nVäs-teråsavd. - Hobby: biltävlingar.\nGift 44 m Ulla Lindström f 24, dtr t\nlantbr Viktor L o Selma Pettersson.\n-Barn: Madeleine f 47, Pia f 53.\n\nERIKSSON, GÖTE K E, byggmästare,\n\nEskilstuna, f i Kjula förs, Södermani l,\n13/5/20 av byggm Karl E o Emma\nPettersson.\n\nStud Hermods, anst h fadern 38, eg\nföretag sed 43, deläg ab Sörmlandsbyggen.\n- Styr :led ab Fristaden, Eskilstuna\nbe-tongfabr, led Eskilstuna\nbrandstods-komm. - Medl FrimO. - Hobbies: fiske,\nbowling, foto.\n\nGift 43 m Tora Flintzberg, dtr t Emma\nF. - Barn: Lilian f 45, Margot f 50.\n\nERIKSSON, HANS, polismästare,\nUppsala, f i Norrtälje 21/8/99 av lärov:adj\nJohan E o Adéle Niemann.\nStud:ex Upps 18, jur kand 24, not ÖÄ\n28, polismäst Upps sed  31, stadsfiskal\n31-54. -  Utm: RNO, RVO, SCFGM.\n-Hobbies: fiske, hortikultur.\nGift 30 m Gunhild Bäcklund. - Barn:\nGöran f 30, Marianne f 31.\n\n",
    "structured": {
        "0": {
            "full_name": "H GÖSTA ERIKSSON",
            "location": "Västerås",
            "occupation": "folkskollärare",
            "birth_details": {
                "date": "08/01/1923",
                "place": "Arvika"
            },
            "education": [
                {
                    "degree": "Stud:ex Sthlm",
                    "year": "1943",
                    "institution": "Sthlm"
                },
                {
                    "degree": "folkskoll:ex",
                    "year": "1947",
                    "institution": "Upps"
                }
            ],
            "career": [
                {
                    "position": "folkskollär",
                    "years": {
                        "start_year": 1947,
                        "end_year": 1953
                    },
                    "organization": "Kolbäck o Köping"
                },
                {
                    "position": "lär",
                    "years": {
                        "start_year": 1949,
                        "end_year": 1953
                    },
                    "organization": "Köpings musiksk"
                }
            ],
            "family": {
                "spouse": "Kerstin Levein",
                "marriage_year": "1947",
                "children": [
                    {
                        "name": "Anna-Lena",
                        "birth_year": "1948"
                    },
                    {
                        "name": "Anders",
                        "birth_year": "1951"
                    },
                    {
                        "name": "Pia",
                        "birth_year": "1957"
                    }
                ]
            }
        },
        "1": {
            "full_name": "K GÖSTA ERIKSSON",
            "location": "Västerås",
            "occupation": "fastighetsmäklare",
            "birth_details": {
                "date": "17/10/1920",
                "place": "Möklinta, Västmanlands län"
            },
            "education": [
                {
                    "degree": "Köpm:inst Sthlm",
                    "year": "1938",
                    "institution": "Sthlm"
                }
            ],
            "career": [
                {
                    "position": "af f :bitr",
                    "years": {
                        "start_year": 1936,
                        "end_year": 1940
                    },
                    "organization": "Västerfärne-bo o Morgongåva"
                },
                {
                    "position": "inneh Sv fas-tigh:förmedl",
                    "years": {
                        "start_year": 1942,
                        "end_year": 1952
                    },
                    "organization": "Sala"
                }
            ],
            "family": {
                "spouse": "Ulla Lindström",
                "marriage_year": "1944",
                "children": [
                    {
                        "name": "Madeleine",
                        "birth_year": "1947"
                    },
                    {
                        "name": "Pia",
                        "birth_year": "1953"
                    }
                ]
            },
            "hobbies": [
                "biltävlingar"
            ]
        },
        "2": {
            "full_name": "GÖTE K E ERIKSSON",
            "location": "Eskilstuna",
            "occupation": "byggmästare",
            "birth_details": {
                "date": "13/05/1920",
                "place": "Kjula förs, Södermani län"
            },
            "career": [
                {
                    "position": "eg företag",
                    "years": {
                        "start_year": 1943
                    }
                }
            ],
            "family": {
                "spouse": "Tora Flintzberg",
                "marriage_year": "1943",
                "children": [
                    {
                        "name": "Lilian",
                        "birth_year": "1945"
                    },
                    {
                        "name": "Margot",
                        "birth_year": "1950"
                    }
                ]
            },
            "hobbies": [
                "fiske",
                "bowling",
                "foto"
            ]
        },
        "3": {
            "full_name": "HANS ERIKSSON",
            "location": "Uppsala",
            "occupation": "polismästare",
            "birth_details": {
                "date": "21/08/1899",
                "place": "Norrtälje"
            },
            "education": [
                {
                    "degree": "Stud:ex Upps",
                    "year": "1918",
                    "institution": "Upps"
                },
                {
                    "degree": "jur kand",
                    "year": "1924"
                }
            ],
            "career": [
                {
                    "position": "not ÖÄ",
                    "years": {
                        "start_year": 1928
                    }
                }
            ],
            "family": {
                "spouse": "Gunhild Bäcklund",
                "marriage_year": "1930",
                "children": [
                    {
                        "name": "Göran",
                        "birth_year": "1930"
                    },
                    {
                        "name": "Marianne",
                        "birth_year": "1931"
                    }
                ]
            },
            "honorary_titles": [
                {
                    "title": "RNO"
                },
                {
                    "title": "RVO"
                },
                {
                    "title": "SCFGM"
                }
            ],
            "hobbies": [
                "fiske",
                "hortikultur"
            ]
        }
    }
}