{
    "original": "ERIKSSON, (MANNE) A E, prost,\nFalun, f i St Tuna, Kopparb l, 12/12/94\nav möbelhandl Carl Fredrik E o Sofia\nDikman.\n\nStud:ex Falun 12, teol kand 20, tf ord\nadj Falun 23, kommin Ludvika 32,\ndom-kyrkokommin Västerås 34, kyrkoh\nSvärdsjö 46, prost 60. - Medl FrimO,\nOdd Fellow. - Utm: LNO. - Hobbies:\ntennis, fiske, litteratur.\nGi/f 36 m Dagny Gustafsson f 05, dtr t\nskohandl Teodor G o Helena Allgren.\n-Barn: Örjan f 37, Lena f 39, Annika\nf 45.\n\nERICSON, E G MANSFIELD,\nstads-kamrerare, Falun, f i Halmstad 6/6/20\nav stat :f orm Wictor E o Hanna\nSvensson.\n\nDSI 47, stadsbokh Halmstad 47,\ndrätsel-ass Falun 52, stadskamr där sed 56.\n-Led Falu tegelv ab sed 59, fullm\nStädernas försäkr :bol 60, HSB :s förtr:råd, div\n\nkomm uppdr. - Medl FrimO. -\nHobbies: fiske, filateli.\n\nGi/f 56 m Karin Hemlin, dtr t\nverk-mast Edward H o h h. - Barn: Elisabet\nf 57, Cecilia f 60.\n\nERICSSON, MARIA H S, leg läkare,\nKristinehamn, f 20.\nLäk:ex Hamburg 44, KM:ts tillst att i\nSv:e utöva  läkekonsten  57,   l:e läk  o\nbitr överläk Mariebergs sjh sed 57.\n\nERICSON, C MARTIN, fd disponent,\n\nLindesberg, f i Eskilstuna 15/9/00 av\ngaragemäst Carl Eriksson o Alma\nSwahn.\n\nIng:ex 20, ing Munktells Eskilstuna 20,\nNydqvist &amp; Holm Eskilstunaverken 22,\nEskilstuna plåtförädl ab 24 ing o disp\nBergbol Lindesberg 31-59. - Ordf\nbygg-n:ndn sed 40, DK sed 60. - Medl\nFrimO. - Utm: PatrSGM. - Hobby:\ndetektivromaner.\n\nGi/f m Gerda Landin, dtr t förman\nCarl-Johan L o Hedvig Gustavsson.\n-Barn: Sten f 22, Bo f 34.\n\n",
    "structured": {
        "1": {
            "full_name": "ERIKSSON, (MANNE) A E",
            "location": "Falun",
            "occupation": "prost",
            "birth_details": {
                "date": "12/12/1894",
                "place": "St Tuna, Kopparbergs län",
                "parents": "möbelhandl Carl Fredrik E o Sofia Dikman"
            },
            "education": [
                {
                    "degree": "Stud:ex",
                    "year": "1912",
                    "institution": "Falun"
                },
                {
                    "degree": "teol kand",
                    "year": "1920",
                    "institution": null
                }
            ],
            "career": [
                {
                    "position": "tf ord adj",
                    "years": {
                        "start_year": 1923,
                        "end_year": null
                    },
                    "organization": "Falun"
                },
                {
                    "position": "kommin",
                    "years": {
                        "start_year": 1932,
                        "end_year": null
                    },
                    "organization": "Ludvika"
                },
                {
                    "position": "dom-kyrkokommin",
                    "years": {
                        "start_year": 1934,
                        "end_year": null
                    },
                    "organization": "Västerås"
                },
                {
                    "position": "kyrkoh",
                    "years": {
                        "start_year": 1946,
                        "end_year": null
                    },
                    "organization": "Svärdsjö"
                },
                {
                    "position": "prost",
                    "years": {
                        "start_year": 1960,
                        "end_year": null
                    },
                    "organization": null
                }
            ],
            "family": {
                "spouse": "Dagny Gustafsson",
                "marriage_year": "1936",
                "children": [
                    {
                        "name": "Örjan",
                        "birth_year": "1937"
                    },
                    {
                        "name": "Lena",
                        "birth_year": "1939"
                    },
                    {
                        "name": "Annika",
                        "birth_year": "1945"
                    }
                ]
            },
            "hobbies": [
                "tennis",
                "fiske",
                "litteratur"
            ]
        },
        "2": {
            "full_name": "ERICSON, E G MANSFIELD",
            "location": "Falun",
            "occupation": "stads-kamrerare",
            "birth_details": {
                "date": "6/6/1920",
                "place": "Halmstad",
                "parents": "stat :f orm Wictor E o Hanna Svensson"
            },
            "education": [
                {
                    "degree": "DSI",
                    "year": "1947",
                    "institution": null
                }
            ],
            "career": [
                {
                    "position": "stadsbokh",
                    "years": {
                        "start_year": 1947,
                        "end_year": null
                    },
                    "organization": "Halmstad"
                },
                {
                    "position": "drätsel-ass",
                    "years": {
                        "start_year": 1952,
                        "end_year": null
                    },
                    "organization": "Falun"
                },
                {
                    "position": "stadskamr",
                    "years": {
                        "start_year": 1956,
                        "end_year": null
                    },
                    "organization": "Falun"
                }
            ],
            "family": {
                "spouse": "Karin Hemlin",
                "marriage_year": "1956",
                "children": [
                    {
                        "name": "Elisabet",
                        "birth_year": "1957"
                    },
                    {
                        "name": "Cecilia",
                        "birth_year": "1960"
                    }
                ]
            },
            "hobbies": [
                "fiske",
                "filateli"
            ]
        },
        "3": {
            "full_name": "ERICSSON, MARIA H S",
            "location": "Kristinehamn",
            "occupation": "leg läkare",
            "birth_details": {
                "date": "NULL",
                "place": "NULL",
                "parents": "NULL"
            },
            "education": [
                {
                    "degree": "Läk:ex",
                    "year": "1944",
                    "institution": "Hamburg"
                },
                {
                    "degree": "KM:ts tillst",
                    "year": "1957",
                    "institution": "NULL"
                }
            ],
            "career": [
                {
                    "position": "l:e läk o bitr överläk",
                    "years": {
                        "start_year": 1957,
                        "end_year": null
                    },
                    "organization": "Mariebergs sjh"
                }
            ],
            "family": null
        },
        "4": {
            "full_name": "ERICSON, C MARTIN",
            "location": "Lindesberg",
            "occupation": "fd disponent",
            "birth_details": {
                "date": "15/9/1900",
                "place": "Eskilstuna",
                "parents": "garagemäst Carl Eriksson o Alma Swahn"
            },
            "education": [
                {
                    "degree": "Ing:ex",
                    "year": "1920",
                    "institution": "NULL"
                }
            ],
            "career": [
                {
                    "position": null,
                    "years": {
                        "start_year": 1920,
                        "end_year": null
                    },
                    "organization": "Munktells Eskilstuna"
                },
                {
                    "position": null,
                    "years": {
                        "start_year": 1922,
                        "end_year": null
                    },
                    "organization": "Nydqvist & Holm Eskilstunaverken"
                },
                {
                    "position": "ing o disp",
                    "years": {
                        "start_year": 1924,
                        "end_year": null
                    },
                    "organization": "Eskilstuna plåtförädl ab"
                },
                {
                    "position": "ordf byggn:ndn",
                    "years": {
                        "start_year": 1940,
                        "end_year": null
                    },
                    "organization": null
                },
                {
                    "position": "DK",
                    "years": {
                        "start_year": 1960,
                        "end_year": null
                    },
                    "organization": null
                }
            ],
            "family": {
                "spouse": "Gerda Landin",
                "marriage_year": "NULL",
                "children": [
                    {
                        "name": "Sten",
                        "birth_year": "1922"
                    },
                    {
                        "name": "Bo",
                        "birth_year": "1934"
                    }
                ]
            },
            "hobbies": [
                "detektivromaner"
            ]
        }
    }
}