{
    "original": "HINDHEDE, HANS, provinsialläkare,\nFjugesta, f i Bredsten, Danmark, 5/11/\n20.\n\nStud:ex Vejle 39, dansk läk:ex 47,\nkungl Maj:ts tillst att i Sv:e utöva\nläkekonsten 53. - Vik underläk Tönder\nAmtssygehus 44, kir o med avd Vejle\nAmtssygehus 45, underläk med avd\nFredriksberg hosp 47, kir avd 48, vik\nunderläk (narkos) kir avd D Bispebjerg\nhosp 49. - Tf e läk kir klin II Sahlgr\nsjh 49, kir avd Hbgs las 49,\nobstetr-gy-nekol avd 50, öronavd Kristianstads las\n50, Nässjö las 50, obstetr-gynekol avd\nHbgs las 51, Holtermanska sjh 51,\nöronavd Kristianstads las 51, barnavd 52, tf\ne prov.iäk Fjällbacka 52, Östersund 52,\ntf e stadsläk Borlänge 54, tf e pr öv :läk\nTrehörningsjö distr 56, prov :läk\nFjugesta sed 59.\nGift 52 m Greta Olsson f 24.\n\nHIORT af ORNÄS, GÖRAN E G,\ndirektör, Eskilstuna, f i Finspong,\nÖstergötl l, 23/5/17 av civiling Erik H af O\no Alma Ärnström.\n\nStud:ex Sthlm 36, KTH 40, anst ab\nBo-linder-Munktell Eskilstuna 41, prod:ch\nSv flygmotor ab Trollhättan 50,\nprod:-dir ab Bolinder-Munktell sed 60.\nGift 43 m Margit Kuhla f 18, dtr t Klas\nK o Hertha Jansson. - Barn: Anders f\n44, Monica f 47.\n\nHIRSCHFELDT, S LENNART,\nchefredaktör, Uppsala, f i Sthlm 17/8/17 av\ndir Z H o Lina Vinberg.\nFil lic StHS 47. - Red Gaudeamus 39-41,\nverkst dir Utr :pol inst o red tidskr\nUtrikespolitik 48-60, lär Internat Graduate\nSchool StHS 49-60, ch:red o ansv utg\nUNT sed 60, utr :pol medarb Sv:es radio\n49-61, lär i internationell politik\nJourn:-inst 59-61. - Styr:led Utr:pol inst sed\n48, fullm RSF sed 56, led Beredsk:ndn\nf psykol försv sed 62. - Led Sv:es\nväns-terpressfören förtr:råd sed 61, suppl Fp:s\npartistyr sed 62; ordf PK sed 63 (medl\n54), medl TU sed 60. - Skr:\nSkandinavien o Atlantpakten (49),\nKoreakonflikten o Förenta Nationerna (51),\nStormaktspolitiken 1945-1952 (53), 1953-1954\n(55), 1955-1956 (57), 1957-1958 (59),\nutr:-pol o hist upps, rec o art.\nGift 42 m Gertrud Sjögren f 17, dtr t\nhovr :råd John S o Käthe Bernhardt.\n-Barn: Johan f 42, Lena f 46.\n\n",
    "structured": {
        "0": {
            "full_name": "HANS HINDHEDE",
            "location": "Fjugesta, Danmark",
            "occupation": "provinsialläkare",
            "birth_details": {
                "date": "05/11/1920",
                "place": "Bredsten, Danmark"
            },
            "education": [
                {
                    "degree": "Stud:ex",
                    "year": "1939",
                    "institution": "Vejle"
                },
                {
                    "degree": "dansk läk:ex",
                    "year": "1947",
                    "institution": "NULL",
                    "institution_coordinates": {
                        "Latitude": 60.12816100000001,
                        "Longitude": 18.643501
                    }
                },
                {
                    "degree": "kungl Maj:ts tillst",
                    "year": "1953",
                    "institution": "NULL",
                    "institution_coordinates": {
                        "Latitude": 60.12816100000001,
                        "Longitude": 18.643501
                    }
                }
            ],
            "career": [
                {
                    "position": "vik underläk",
                    "years": {
                        "start_year": 1944,
                        "end_year": 1945
                    },
                    "organization": "Tönder Amtssygehus"
                },
                {
                    "position": "kir o med avd",
                    "years": {
                        "start_year": 1945,
                        "end_year": 1945
                    },
                    "organization": "Vejle Amtssygehus"
                },
                {
                    "position": "underläk med avd",
                    "years": {
                        "start_year": 1947,
                        "end_year": 1948
                    },
                    "organization": "Fredriksberg hosp"
                },
                {
                    "position": "kir avd",
                    "years": {
                        "start_year": 1948,
                        "end_year": 1949
                    },
                    "organization": "NULL"
                },
                {
                    "position": "vik underläk (narkos) kir avd",
                    "years": {
                        "start_year": 1949,
                        "end_year": 1951
                    },
                    "organization": "Bispebjerg hosp"
                },
                {
                    "position": "Tf e läk kir klin II",
                    "years": {
                        "start_year": 1949,
                        "end_year": 1949
                    },
                    "organization": "Sahlgr sjh"
                },
                {
                    "position": "obstetr-gy-nekol avd",
                    "years": {
                        "start_year": 1950,
                        "end_year": 1950
                    },
                    "organization": "NULL"
                },
                {
                    "position": "öronavd",
                    "years": {
                        "start_year": 1950,
                        "end_year": 1950
                    },
                    "organization": "Kristianstads las"
                },
                {
                    "position": "obstetr-gynekol avd",
                    "years": {
                        "start_year": 1950,
                        "end_year": 1950
                    },
                    "organization": "Hbgs las"
                },
                {
                    "position": "öronavd",
                    "years": {
                        "start_year": 1951,
                        "end_year": 1951
                    },
                    "organization": "Kristianstads las"
                },
                {
                    "position": "barnavd",
                    "years": {
                        "start_year": 1952,
                        "end_year": 1952
                    },
                    "organization": "NULL"
                },
                {
                    "position": "tf e prov.iäk",
                    "years": {
                        "start_year": 1952,
                        "end_year": 1952
                    },
                    "organization": "Fjällbacka"
                },
                {
                    "position": "tf e stadsläk",
                    "years": {
                        "start_year": 1954,
                        "end_year": 1954
                    },
                    "organization": "Borlänge"
                },
                {
                    "position": "tf e pr öv :läk",
                    "years": {
                        "start_year": 1956,
                        "end_year": 1956
                    },
                    "organization": "Trehörningsjö distr"
                },
                {
                    "position": "prov :läk",
                    "years": {
                        "start_year": 1959,
                        "end_year": 1959
                    },
                    "organization": "Fjugesta"
                }
            ],
            "family": {
                "spouse": "Greta Olsson",
                "marriage_year": "1952",
                "children": [
                    {
                        "name": "NULL",
                        "birth_year": "NULL"
                    }
                ]
            }
        },
        "1": {
            "full_name": "GÖRAN E G HIORT af ORNÄS",
            "location": "Eskilstuna, Finspong, Östergötl l",
            "occupation": "direktör",
            "birth_details": {
                "date": "23/05/1917",
                "place": "Finspong, Östergötland"
            },
            "education": [
                {
                    "degree": "Stud:ex",
                    "year": "1936",
                    "institution": "Sthlm",
                    "institution_coordinates": {
                        "Latitude": 59.32932349999999,
                        "Longitude": 18.0685808
                    }
                },
                {
                    "degree": "NULL",
                    "year": "1940",
                    "institution": "KTH",
                    "institution_coordinates": {
                        "Latitude": 59.3498706,
                        "Longitude": 18.0702566
                    }
                }
            ],
            "career": [
                {
                    "position": "anst ab",
                    "years": {
                        "start_year": 1941,
                        "end_year": 1941
                    },
                    "organization": "Bolinder-Munktell Eskilstuna"
                },
                {
                    "position": "prod:ch",
                    "years": {
                        "start_year": 1950,
                        "end_year": 1950
                    },
                    "organization": "Sv flygmotor ab Trollhättan"
                },
                {
                    "position": "prod:-dir ab",
                    "years": {
                        "start_year": 1960,
                        "end_year": 1960
                    },
                    "organization": "Bolinder-Munktell"
                }
            ],
            "family": {
                "spouse": "Margit Kuhla",
                "marriage_year": "1943",
                "children": [
                    {
                        "name": "Anders",
                        "birth_year": "1944"
                    },
                    {
                        "name": "Monica",
                        "birth_year": "1947"
                    }
                ]
            }
        },
        "2": {
            "full_name": "S LENNART HIRSCHFELDT",
            "location": "Uppsala",
            "occupation": "chefredaktör",
            "birth_details": {
                "date": "17/08/1917",
                "place": "Sthlm",
                "place_coordinates": {
                    "Latitude": 59.32932349999999,
                    "Longitude": 18.0685808
                }
            },
            "education": [
                {
                    "degree": "Fil lic",
                    "year": "1947",
                    "institution": "StHS",
                    "institution_coordinates": {
                        "Latitude": 60.12816100000001,
                        "Longitude": 18.643501
                    }
                }
            ],
            "career": [
                {
                    "position": "Red",
                    "years": {
                        "start_year": 1939,
                        "end_year": 1941
                    },
                    "organization": "Gaudeamus"
                },
                {
                    "position": "verkst dir",
                    "years": {
                        "start_year": 1948,
                        "end_year": 1960
                    },
                    "organization": "Utr :pol inst o red tidskr Utrikespolitik"
                },
                {
                    "position": "lär",
                    "years": {
                        "start_year": 1949,
                        "end_year": 1960
                    },
                    "organization": "Internat Graduate School StHS"
                },
                {
                    "position": "ch:red o ansv utg",
                    "years": {
                        "start_year": 1960,
                        "end_year": 1960
                    },
                    "organization": "UNT"
                },
                {
                    "position": "utr :pol medarb",
                    "years": {
                        "start_year": 1949,
                        "end_year": 1961
                    },
                    "organization": "Sv:es radio"
                }
            ],
            "family": {
                "spouse": "Gertrud Sjögren",
                "marriage_year": "1942",
                "children": [
                    {
                        "name": "Johan",
                        "birth_year": "1942"
                    },
                    {
                        "name": "Lena",
                        "birth_year": "1946"
                    }
                ]
            },
            "location_coordinates": {
                "Latitude": 59.85856380000001,
                "Longitude": 17.6389267
            }
        }
    }
}