{
    "original": "Ehnbom, Rolf Erik Rutger, leg.\nläkare, Lund, f. 6/8/16 i Tomelilla, Krist.\n1., av möbelihandl. Otto E. o. Anna\nThorsén. G. 42 m. Torborg Möller.\nBarn: Ulla if. 43, Marianne 47. —\nStudiex. i Ystad 37, med. kand. i Lund\n40, med. lic. 46. Tf. andre läk. v. S :t\nSigfrids sjukh. i Växjö 4 mån. 42,\nassist :läk. v. kir. klin. i Lund 3 mån. 43,\ntf. andre und:läk. v. kir. avd. i\nKarls-kr. 4 mån. 44, vik. prov:läk. 13 mån.\n43-47,   tf.   andre   und :läk.   v.   las.    i\n\nAlingsås   3   mån.   47,   andre   und:läk.   I\nv. kir. avd. v. las. i Borås fr. 48.\nPro-kurator   o.   kurator   i   Ystads   nat.   v.\nLunds univ. 42-44.\n\nEhnimb, Erik Adalbert, direktör,\nMalmö, f. 18/11/20 i Djursholm av dir.\nE. E. o. Gertrud Brodöwsky. —\nStud:-ex. v. Malmö h. a. 1. 39, stud. i jur. o.\nföret :ekon. v. Lunds univ. 39-41.\nStud:-res. i Tyskl., Höll., Schweiz, USA.\nVerkst. dir. i Ehnimbs Hand. A-B o. i\nA-B Textilkonst. Hobbies: musik o.\nkonst.\n\nEhrenberg, Bengt Gustaf, med. lic.,\nprakt, ’läkare, Malmö, f. 25/4/09 i\nAuge-rum, Blek. 1., av gods äg. Nils Gustaf\nE. o. Dagmar Matthiesen. G. 36 m.\nInga Brita Andersson. Barn: Bengt f.\n37, Margaretha 40, Birgitta 43,\nElisabeth 45, Marianne 47. — Stud:ex.\ni Karlskrona 27, med. kand. 31 o.\nmed. lic. 36 i Lund. E. o. aman.\nv. histol. inst. i Lund 30-31, v.\nbak-teriol. inst. 35, aman. v. histol.\ninst. i Lund 38-39, div. föror du. s. und\n:-läk. v. Lunds las , v. las. i Boden m. m.,\ns. prov :läk. 3(3-41, s. lab :förest. o. med.\nkonsulent v. A-B Ferrosan i Malmö\nsed. 36, prakt. läk. i Malmö’ sed. 42.\nTj :grenschef f. sjukvitj. v. civ:försv. i\nMalmö sed. 45. Med:styr. omb. i\nflyk-tingsjukv:ärend. i Malmöh. 1. 45-46.\nRFrHL, RLSFSM, RLSFftjt.\n\nEhrenberg, Nils Gustaf,\n’kyrkoherde, Holmåkra, f. 5/4/04 i Augerum,\nBlek. 1., av godsäg. Nils Gustaf E. o. i\nDagmar Matthiesen. G. 31 m. Greta\nBerghman. Barn: Ingrid f. 35. —\nStud:ex. i Karlskr. 22, teol. fil. ex. 23,\nteol. kand. 27, prakt. teol. prov 27.\nVik. kyrkoadj. i Kristianstad 27, v.\nkommin. i N. Åkarp 28, v. past. i Osby\n28, kommin. i Ekeby 29, kyrkoh. i Ö.\nHoby, Vallby o.  Bolshög sed. 39.\n\nvon, Ehrenheim, Per Henrik,\nhäradshövding, Malmö, f. 31/3/89 i\nKungs-Husby, Upps. 1., av kammarn. Erik v.\nE. o. Alice Blomstedt. G. 44 m.\ntand-läk. Valborg Eriksson. Barn: Lars f.\n45. — Stud:ex. i Sthlm 07, jur. kand. i\nUpips. 15. E. o. not. i Svea hovr. 15,\ntingstjg. i Upps. 1. norra doms. 15-18,\ntf. fiskal i Svea hovr. 19, adj. led. 20,\nassess. 22, tf. rev:sekr. 26, hovr:råd\n30, rev:sekr. 31, här:hövd. i Oxie o.\nSkytts doms. fr. 37. Ordf. i poliskoll.\nf. Malmöh. 1. fr. 42, bitr. i just :dep. f.\nlagstiftn :fråg. 27-29, 30-32, bitr. i jord- I\nbr :dep. f. lagstiftn :arb. 30.\n\nI von Ehrenheim, Valborg Elisabet,\ntandläkare, Malmö, f. 29/3/10 i\nLudvika, Kopparb. 1., av kamr. Erik\nEriksson o. Elna Danielsson. G. 44 m.\nhär:-hövd. Per von Ehrenheim. Barn: Lars\nf. 45. — Stud:ex. i Motala 29, odont.\nkand. 31, tandläk. 34. Anst. v.\nEastman-inst. 39-40, barntandv:tj. v. Malmöh. 1.\nlandstings klin. i Lund 42-45,\npriv:-praktik i Ystad 34-39, 41-42, i Malmö\nfr. 45.\n\n",
    "structured": {
        "0": {
            "full_name": "Ehnbom, Rolf Erik Rutger",
            "location": "Lund",
            "occupation": "leg. läkare",
            "birth_details": {
                "date": "06/08/1916",
                "place": "Tomelilla, Kristianstad",
                "parents": "möbelihandl. Otto E. o. Anna Thorsén"
            },
            "education": [
                {
                    "degree": "Studiex.",
                    "year": "1937",
                    "institution": "Ystad"
                },
                {
                    "degree": "med. kand.",
                    "year": "1940",
                    "institution": "Lund"
                },
                {
                    "degree": "med. lic.",
                    "year": "1946",
                    "institution": "Lund"
                }
            ],
            "career": [
                {
                    "position": "Tf. andre läk. v. S:t Sigfrids sjukh. i Växjö",
                    "years": {
                        "start_year": 1942,
                        "end_year": 1942
                    },
                    "organization": "Växjö"
                },
                {
                    "position": "assist :läk. v. kir. klin. i Lund",
                    "years": {
                        "start_year": 1943,
                        "end_year": 1943
                    },
                    "organization": "Lund"
                },
                {
                    "position": "tf. andre und:läk. v. kir. avd. i Karlskr.",
                    "years": {
                        "start_year": 1944,
                        "end_year": 1944
                    },
                    "organization": "Karlskrona"
                },
                {
                    "position": "vik. prov:läk.",
                    "years": {
                        "start_year": 1943,
                        "end_year": 1947
                    }
                },
                {
                    "position": "tf. andre und:läk. v. las. i Alingsås",
                    "years": {
                        "start_year": 1947,
                        "end_year": 1947
                    },
                    "organization": "Alingsås"
                }
            ],
            "family": {
                "spouse": "Torborg Möller",
                "marriage_year": "1942",
                "children": [
                    {
                        "name": "Ulla",
                        "birth_year": "1943"
                    },
                    {
                        "name": "Marianne",
                        "birth_year": "1947"
                    }
                ]
            }
        },
        "1": {
            "full_name": "Ehnimb, Erik Adalbert",
            "location": "Malmö",
            "occupation": "direktör",
            "birth_details": {
                "date": "18/11/1920",
                "place": "Djursholm"
            },
            "education": [
                {
                    "degree": "Stud:-ex.",
                    "year": "1939",
                    "institution": "Malmö h. a."
                },
                {
                    "degree": "stud. i jur. o. föret :ekon.",
                    "year": "1939-1941",
                    "institution": "Lunds univ."
                }
            ],
            "hobbies": [
                "musik",
                "konst"
            ]
        },
        "2": {
            "full_name": "Ehrenberg, Bengt Gustaf",
            "location": "Malmö",
            "occupation": "med. lic., prakt. läkare",
            "birth_details": {
                "date": "25/04/1909",
                "place": "Auge-rum, Blek."
            },
            "education": [
                {
                    "degree": "Stud:ex.",
                    "year": "1927",
                    "institution": "Karlskrona"
                },
                {
                    "degree": "med. kand.",
                    "year": "1931",
                    "institution": "Lund"
                },
                {
                    "degree": "med. lic.",
                    "year": "1936",
                    "institution": "Lund"
                }
            ],
            "career": [
                {
                    "position": "Tj :grenschef f. sjukvitj. v. civ:försv. i Malmö",
                    "years": {
                        "start_year": 1945
                    }
                }
            ],
            "family": {
                "spouse": "Inga Brita Andersson",
                "marriage_year": "1936",
                "children": [
                    {
                        "name": "Bengt",
                        "birth_year": "1937"
                    },
                    {
                        "name": "Margaretha",
                        "birth_year": "1940"
                    },
                    {
                        "name": "Birgitta",
                        "birth_year": "1943"
                    },
                    {
                        "name": "Elisabeth",
                        "birth_year": "1945"
                    },
                    {
                        "name": "Marianne",
                        "birth_year": "1947"
                    }
                ]
            }
        },
        "3": {
            "full_name": "Ehrenberg, Nils Gustaf",
            "location": "Holmåkra",
            "occupation": "kyrkoherde",
            "birth_details": {
                "date": "5/4/1904",
                "place": "Augerum, Blek."
            },
            "education": [
                {
                    "degree": "Stud:ex.",
                    "year": "1922",
                    "institution": "Karlskrona"
                },
                {
                    "degree": "teol. fil. ex.",
                    "year": "1923"
                },
                {
                    "degree": "teol. kand.",
                    "year": "1927"
                },
                {
                    "degree": "prakt. teol. prov",
                    "year": "1927"
                }
            ],
            "family": {
                "spouse": "Greta Berghman",
                "marriage_year": "1931",
                "children": [
                    {
                        "name": "Ingrid",
                        "birth_year": "1935"
                    }
                ]
            }
        },
        "4": {
            "full_name": "von Ehrenheim, Per Henrik",
            "location": "Malmö",
            "occupation": "häradshövding",
            "birth_details": {
                "date": "31/3/1889",
                "place": "Kungs-Husby, Upps."
            },
            "education": [
                {
                    "degree": "Stud:ex.",
                    "year": "1907",
                    "institution": "Sthlm"
                },
                {
                    "degree": "jur. kand.",
                    "year": "1915",
                    "institution": "Upps."
                }
            ],
            "family": {
                "spouse": "Valborg Eriksson",
                "marriage_year": "1944",
                "children": [
                    {
                        "name": "Lars",
                        "birth_year": "1945"
                    }
                ]
            }
        },
        "5": {
            "full_name": "von Ehrenheim, Valborg Elisabet",
            "location": "Malmö",
            "occupation": "tandläkare",
            "birth_details": {
                "date": "29/3/1910",
                "place": "Ludvika, Kopparb."
            },
            "education": [
                {
                    "degree": "Stud:ex.",
                    "year": "1929",
                    "institution": "Motala"
                },
                {
                    "degree": "odont. kand.",
                    "year": "1931",
                    "institution": "Malmö h. a."
                },
                {
                    "degree": "tandläk.",
                    "year": "1934"
                }
            ],
            "family": {
                "spouse": "Per von Ehrenheim",
                "marriage_year": "1944",
                "children": [
                    {
                        "name": "Lars",
                        "birth_year": "1945"
                    }
                ]
            }
        }
    }
}