{
    "original": "Ekbo, Sven Arnold, fil. dr,\nordboks-redaktör, Lund, f. 7/8/15 i Valbo,\nGäv-leb. 1. G. 42 m. Martha Ansén. Barn:\nGunnar f. 44, Sten 46. — Stud:ex. i\nGävle 34, fil. kand. 37, fil. mag. 39,\nfil. lic. 42, fil. dr 43. Tjg. v. skolor i\nSollefteå, Gävle, Upps. 37, 40-43,\nord-b:red. i Sv. akad. ordb :red. sed. 43.\nSkr.: Stud. öv. uppkomsten av\nsupi-num i de germanska språken\n(grad:-avh. 43),  smärre  art. i facktidskr.\n\nEkbrant, Carl Linus Natanael,\nämneslärare, Åkarp, f. 3/5/91 i\nKölinga-red, Älvsb. 1. G. 35 m. Edith Lindwall.\nGenomg. Alnarpsinst. trädg:sk. 18-20.\nStud:res. i Tyskl. o. Österr. 21 o. 26,\nEngL, Höll. o. Belg. 23, Frankr. 25,\nTyskl. 29 o. 39, Danm. o. Norge 32,\nHöll. 37 o. 47. Bitr. lär. v. Alnarps\nträdg:sk. 20-23, assist, v. Alnarpsinst.\n24-34, ämneslär. v. dess trädg:avd. sed.\n35. Skr.: Krukväxter. I (34), II (38),\nKöksväxter und. glas (Hermodskurs,\n44), Sparris, kronärtskockor o.\nrabarber (46), Trädg:odl. (Hermodskurs,\n48).\n\nEkdahl, Erik Valter, lasaretts\nsyssloman, Landskrona, f. 16/10/02 i\nLandskr. av Ivar Jönsson o. Olga\nEkdahl. G. 35 m. Märta Liljefors. Barn:\nEva f. 39. — BokhåM. v. Landskr. las.\n27-32, v. Lunds las. 32, assist, v.\nMal-iruöh. 1. landstings huv:förv. i Malmö\n33-36, sysslom. v. Landskr. las. sed.\n37. Led. av styr. f. Landskr.\nteat:-fören.   sed. 46.    Medl.  i  Odd  Fellow.\n\nEkdahl, John Oscar Cornelius,\nfolkskollärare, Vallby-Salarp, f. 25/7/98 i\nKristianstad. G. 32 m. Blenda\nNilsson. Barn: Berit f. 34, Ingvar 38, Bo\n44. — Stud:ex. i Kristianstad 18,\nfolkskoll :ex. i Växjö 20. Vik. folkskoll. i\nBorrestad 20, Vallby 21, ord. där sed.\n22. Led. av barnavmd, ordf. i\npen-sionsnd, fattigv :styr. 32-36, styriled. i\nÖsterlens kyrkobr:kår, Österlens\nsom-marh. i Löderup, Vallby Sparb.,\nkamrer i Vallby Sparb. sed. 46.\n\n*Ekdahl, Anders Elver Thorvald,\nfolkskollärare, riksdagsman, Nyvång, f.\n12/6/88 i Sireköpinge, Malmöh. 1., av\nAnders E. o. Elna Nilsdotter. G. 24\nm. Hilda Andersson. Barn: Elna f. 25.\n— Hand:sk. 01-02, folkskoll :ex. 10.\nFolkskoll. i Bårslöv 10-21, i Nyvång\nsed. 22. Led. av riksd. andra kamm.\nsed. 37, av dess femte tillf. utsk. 37,\nordf. i Bårslövs pens :nd o. nykterh :nd\n17-21, ordf. o. verkst. led. av livsmed\n:-nd 16-19, led. av Björnekulla\nkomm:-fullm. 23-26, av skolstyr. där 32-35,\nsuppl. i landstinget 15-21, soc:dem.\npart. sockenomb. i Bårslöv 11-21, ordf.\ni Åstorps arb:komm. 31-36, v. ordf.\nsed. 37 m. fl. partiuppdr. samt ett\nflert. uppdr. inom nykterh :rör. Red. f.\nMånadsbladet, org. f. Skånes västra\ndistr. av IOGT, 24-32, medarb. i\nArbetet o. Soc.-Dem.\n\n*Eke, Alf Gunnar, tandläkare,\nTec-komatorp, f. 28/1/03 i Malmö. G. 30\nm. Margit N:son Hay. Barn:\nTorbjörn f. 33, Ulf 35, Ulla Sigfrid\nAlfsdotter 38. — Stud:ex. i Malmö 22,\nmed. kand. i Lund 28, tandl. 32. Prakt,\ni Teckomatorp sed. 31. Huvudman i\nTeckomatorps Sparb. sed. 37, sekr. i\nTeckomatorps skyttesallsk. sed. 38 o.\ni Teckomatorps pistolskytteklubb sed.\n37.\n\n",
    "structured": {
        "1": {
            "full_name": "Ekbo, Sven Arnold",
            "location": "Lund",
            "occupation": "ordboks-redaktör",
            "birth_details": {
                "date": "07/08/1915",
                "place": "Valbo"
            },
            "education": [
                {
                    "degree": "Stud:ex.",
                    "year": "1934",
                    "institution": "Gävle"
                },
                {
                    "degree": "filosofie kandidat",
                    "year": "1937",
                    "institution": "Unknown"
                },
                {
                    "degree": "filosofie magister",
                    "year": "1939",
                    "institution": "Unknown"
                },
                {
                    "degree": "filosofie licentiat",
                    "year": "1942",
                    "institution": "Unknown"
                },
                {
                    "degree": "filosofie doktor",
                    "year": "1943",
                    "institution": "Unknown"
                }
            ],
            "career": [
                {
                    "position": "Tjg. v. skolor",
                    "years": {
                        "start_year": 1937,
                        "end_year": 1943
                    },
                    "organization": "Sollefteå, Gävle, Upps."
                },
                {
                    "position": "ord-b:red. i Sv. akad. ordb",
                    "years": {
                        "start_year": 1943,
                        "end_year": null
                    },
                    "organization": "Unknown"
                }
            ],
            "family": {
                "spouse": "Martha Ansén",
                "marriage_year": "1942",
                "children": [
                    {
                        "name": "Gunnar",
                        "birth_year": "1944"
                    },
                    {
                        "name": "Sten",
                        "birth_year": "1946"
                    }
                ]
            }
        },
        "2": {
            "full_name": "Ekbrant, Carl Linus Natanael",
            "location": "Åkarp",
            "occupation": "ämneslärare",
            "birth_details": {
                "date": "03/05/1891",
                "place": "Kölingared"
            },
            "education": [],
            "career": [
                {
                    "position": "Bitr. lär. v. Alnarps trädg:sk",
                    "years": {
                        "start_year": 1920,
                        "end_year": 1923
                    },
                    "organization": "Alnarps trädg:sk."
                },
                {
                    "position": "assist, v. Alnarpsinst",
                    "years": {
                        "start_year": 1924,
                        "end_year": 1934
                    },
                    "organization": "Alnarpsinst."
                },
                {
                    "position": "ämneslär. v. dess trädg:avd",
                    "years": {
                        "start_year": 1935,
                        "end_year": null
                    },
                    "organization": "Unknown"
                }
            ],
            "family": {
                "spouse": "Edith Lindwall",
                "marriage_year": "1935",
                "children": []
            }
        },
        "3": {
            "full_name": "Ekdahl, Erik Valter",
            "location": "Landskrona",
            "occupation": "lasaretts syssloman",
            "birth_details": {
                "date": "16/10/1902",
                "place": "Landskr."
            },
            "education": [],
            "career": [
                {
                    "position": "BokhåM. v. Landskr. las",
                    "years": {
                        "start_year": 1927,
                        "end_year": 1932
                    },
                    "organization": "Landskr. las."
                },
                {
                    "position": "sysslom. v. Landskr. las",
                    "years": {
                        "start_year": 1937,
                        "end_year": null
                    },
                    "organization": "Landskr. las."
                }
            ],
            "family": {
                "spouse": "Märta Liljefors",
                "marriage_year": "1935",
                "children": [
                    {
                        "name": "Eva",
                        "birth_year": "1939"
                    }
                ]
            }
        },
        "4": {
            "full_name": "Ekdahl, John Oscar Cornelius",
            "location": "Vallby-Salarp",
            "occupation": "folkskollärare",
            "birth_details": {
                "date": "25/07/1898",
                "place": "Kristianstad"
            },
            "education": [
                {
                    "degree": "Stud:ex.",
                    "year": "1918",
                    "institution": "Kristianstad"
                },
                {
                    "degree": "folkskoll :ex.",
                    "year": "1920",
                    "institution": "Växjö"
                }
            ],
            "career": [
                {
                    "position": "Vik. folkskoll",
                    "years": {
                        "start_year": 1920,
                        "end_year": 1921
                    },
                    "organization": "Borrestad"
                },
                {
                    "position": "ord. folkskoll",
                    "years": {
                        "start_year": 1922,
                        "end_year": null
                    },
                    "organization": "Vallby"
                }
            ],
            "family": {
                "spouse": "Blenda Nilsson",
                "marriage_year": "1932",
                "children": [
                    {
                        "name": "Berit",
                        "birth_year": "1934"
                    },
                    {
                        "name": "Ingvar",
                        "birth_year": "1938"
                    },
                    {
                        "name": "Bo",
                        "birth_year": "1944"
                    }
                ]
            }
        },
        "5": {
            "full_name": "Ekdahl, Anders Elver Thorvald",
            "location": "Nyvång",
            "occupation": "folkskollärare, riksdagsman",
            "birth_details": {
                "date": "12/06/1888",
                "place": "Sireköpinge"
            },
            "education": [
                {
                    "degree": "Hand:sk.",
                    "year": "1901-02",
                    "institution": "Unknown"
                },
                {
                    "degree": "folkskoll :ex.",
                    "year": "1910",
                    "institution": "Unknown"
                }
            ],
            "career": [
                {
                    "position": "Folkskoll.",
                    "years": {
                        "start_year": 1910,
                        "end_year": 1921
                    },
                    "organization": "Bårslöv"
                },
                {
                    "position": "Folkskoll.",
                    "years": {
                        "start_year": 1922,
                        "end_year": null
                    },
                    "organization": "Nyvång"
                },
                {
                    "position": "ordf. i Bårslövs pens :nd o. nykterh :nd",
                    "years": {
                        "start_year": 1917,
                        "end_year": 1921
                    },
                    "organization": "Unknown"
                }
            ],
            "family": {
                "spouse": "Hilda Andersson",
                "marriage_year": "1924",
                "children": [
                    {
                        "name": "Elna",
                        "birth_year": "1925"
                    }
                ]
            }
        },
        "6": {
            "full_name": "Eke, Alf Gunnar",
            "location": "Tec-komatorp",
            "occupation": "tandläkare",
            "birth_details": {
                "date": "28/01/1903",
                "place": "Malmö"
            },
            "education": [
                {
                    "degree": "Stud:ex.",
                    "year": "1922",
                    "institution": "Malmö"
                },
                {
                    "degree": "med. kand.",
                    "year": "1928",
                    "institution": "Lund"
                },
                {
                    "degree": "tandl.",
                    "year": "1932",
                    "institution": "Unknown"
                }
            ],
            "career": [
                {
                    "position": "Prakt.",
                    "years": {
                        "start_year": 1931,
                        "end_year": null
                    },
                    "organization": "Teckomatorp"
                }
            ],
            "family": {
                "spouse": "Margit N:son Hay",
                "marriage_year": "1930",
                "children": [
                    {
                        "name": "Torbjörn",
                        "birth_year": "1933"
                    },
                    {
                        "name": "Ulf",
                        "birth_year": "1935"
                    },
                    {
                        "name": "Ulla Sigfrid",
                        "birth_year": "1938"
                    }
                ]
            }
        }
    }
}