{
    "original": "Ekström, Erik Viktor,\ntryckeridirektör, Malmö, f. 29/10/91 i Gbg av Axel\nGeorg Viktor E. o. Elin Sofia\nMargareta Hagberg. G. 19 m. Sara Maria\nLindström.  Barn:  Lars  f. 20,  Nils 21.\n\n—  Stud:ex. v. h. a. 1. i Malmö 10, stud.\nv. HHS 11, genomg. Masers\nBuch-druckerei-Fachsch. i Leipzig 15-16 o.\nAkad. f. graph. Kiinste u.\nBuchge-werbe där 16-17. Anst. s. faktor h.\nAlmqvist &amp; Wiksell Boktryck. A-B i\nUpps. ’18-20, disp. f. Hallmans Boktr.\nA-B i Uddevalla 20-29, kalkylator h.\nSv. Tryck. A-B i Sthlm 29-30, disp. f.\nSchmidts Boktr. A-B i Hälsingb. 30-40,\ntryck :dir. o. tekn. chef h. Sydsv.\nDag-bi. A-B sed. 41. Styr:led. i Sv. boktr\n:-fören., ordf. i dess södra krets sed. 43.\n\nEkström, John Gunnar,\ncivilingenjör, Kristianstad, f. 1/3/06 i Gbg. G.\n37 m. Birgit Blomberg. — Stud:ex.\nv. Gbgs h. real 26, civ:ing:ex. v. CTI\n32. Väging:assist. i Karlskr. 34-36,\nbyråing. h. väg- o. vattenbyggn :styr.\n37-38, avd.-chef v. A-B Sv. Icopalfabr.\ni Malmö 39-41, bitr. väging. i Sthlm\n42-43, väging. i Kristianstad fr. 44.\n\nEkström, Karl Gunnar, skådespelare,\nHälsingborg, f. 2/1/13 i Arvika av\ntandläk. Karl E. o. Greta Åhman. G.\n40 m. skådösp. Margareta Bergfelt.\nBarn: Boel f. 46. — Stud:ex. i Vänersb.\n31, Dram. Teat. elevsk. 34-36.\nStud:-resa t. Frankr. 47. Eng. v. Stadsteat. i\nGbg 37-46, v. Stadsteat. i Hälsingb.\nsed. 46. Bl. roller: Alan i Priestleys I\ndag o. i morgon, Nathan i Farmor o.\nvår Herre, Patrik Sinclair i Av\nhjärtans lust av Gierow, Lucio i\nShake-speares Lika för lika, Adolf i\nStrindbergs Fordringsägare, Lucien i Romeo\no. Jeanette. Regideb. m. Strindbergs\nPåsk 48.\n\nEkström, Carl Henrik Theodor,\nmajor, Herrevadskloster, Ljungbyhed, f.\n1(2/5/91 i Landskr. av överste H. G.\nT. E. o. Elisabeth Tranchell. G. 24\nm. Anna Moltke-Huitfeldt. Barn:\nUlla  f.  25,   Brita 27,   Margaretha 33.\n\n—  Kadett v. SKS 05-12, ,sjöoff:ex. 12,\nprovtjg. f. transp. t. kav., genomg.\nKS (12) 13-14, RS 1. 15-16, 2. 21-22,\nSS 29; kommend. t. tjg. v. ital. kav.\no. genomg. ridsk. v. Pinerolo o. Tor\ndi Quinto 22-23. Und:löjtn. v. Skånska\nhus :reg. 14, löjtn. 18, v. Skånska\nkav:-reg. 27, ryttmäst. 29, chef f. livskvadr.\nv. reg. 31-35, av sk. o. i reg. res. 41,\nmajor 42.     Chef  f.  Herrevads’klosters\n\nremontdepå fr. 46. Honor är attaché v.\nbeskickn. i Bern 20. Suppl. i\nremon-ter :nd 35, led. 41, ,styr :led. i Skånska\nfältrittkl. 41, ordf. 46, styr :led. i J.\nK. 47. Hobbies: hästar o. hästsport\n(hinderlöpn.). RSO, RFinlVROlkl,\nRItKrO.\n\n",
    "structured": {
        "1": {
            "full_name": "Ekström, Erik Viktor",
            "location": "Malmö",
            "occupation": "tryckeridirektör",
            "birth_details": {
                "date": "29/10/1891",
                "place": "Göteborg"
            },
            "education": [
                {
                    "degree": "Stud:ex.",
                    "year": "1910",
                    "institution": "Malmö"
                },
                {
                    "degree": "HHS",
                    "year": "1911",
                    "institution": "N/A"
                },
                {
                    "degree": "Masers Buch-druckerei-Fachsch.",
                    "year": "1915-1916",
                    "institution": "Leipzig"
                },
                {
                    "degree": "Akad. f. graph. Kiinste u. Buchgewerbe",
                    "year": "1916-1917",
                    "institution": "N/A"
                }
            ],
            "career": [
                {
                    "position": "faktor",
                    "years": {
                        "start_year": 1918,
                        "end_year": 1920
                    },
                    "organization": "Almqvist & Wiksell Boktryck. A-B i Upps."
                },
                {
                    "position": "disp.",
                    "years": {
                        "start_year": 1920,
                        "end_year": 1929
                    },
                    "organization": "Hallmans Boktr. A-B i Uddevalla"
                },
                {
                    "position": "kalkylator",
                    "years": {
                        "start_year": 1929,
                        "end_year": 1930
                    },
                    "organization": "Sv. Tryck. A-B i Sthlm"
                },
                {
                    "position": "disp.",
                    "years": {
                        "start_year": 1930,
                        "end_year": 1940
                    },
                    "organization": "Schmidts Boktr. A-B i Hälsingb."
                },
                {
                    "position": "tryck :dir. o. tekn. chef",
                    "years": {
                        "start_year": 1941,
                        "end_year": 9999
                    },
                    "organization": "Sydsv. Dagbi. A-B"
                }
            ],
            "family": {
                "spouse": "Sara Maria Lindström",
                "marriage_year": "N/A",
                "children": [
                    {
                        "name": "Lars",
                        "birth_year": "20"
                    },
                    {
                        "name": "Nils",
                        "birth_year": "21"
                    }
                ]
            }
        },
        "2": {
            "full_name": "Ekström, John Gunnar",
            "location": "Kristianstad",
            "occupation": "civilingenjör",
            "birth_details": {
                "date": "1/3/1906",
                "place": "Göteborg"
            },
            "education": [
                {
                    "degree": "Stud:ex.",
                    "year": "1926",
                    "institution": "Gbgs h. real"
                },
                {
                    "degree": "civ:ing:ex.",
                    "year": "1932",
                    "institution": "CTI"
                }
            ],
            "career": [
                {
                    "position": "Väging:assist.",
                    "years": {
                        "start_year": 1934,
                        "end_year": 1936
                    },
                    "organization": "Karlskr."
                },
                {
                    "position": "byråing.",
                    "years": {
                        "start_year": 1937,
                        "end_year": 1938
                    },
                    "organization": "väg- o. vattenbyggn :styr."
                },
                {
                    "position": "avd.-chef",
                    "years": {
                        "start_year": 1939,
                        "end_year": 1941
                    },
                    "organization": "A-B Sv. Icopalfabr. i Malmö"
                },
                {
                    "position": "bitr. väging.",
                    "years": {
                        "start_year": 1942,
                        "end_year": 1943
                    },
                    "organization": "Sthlm"
                },
                {
                    "position": "väging.",
                    "years": {
                        "start_year": 1944,
                        "end_year": 9999
                    },
                    "organization": "Kristianstad"
                }
            ],
            "family": {
                "spouse": "Birgit Blomberg",
                "marriage_year": "N/A",
                "children": []
            }
        },
        "3": {
            "full_name": "Ekström, Karl Gunnar",
            "location": "Hälsingborg",
            "occupation": "skådespelare",
            "birth_details": {
                "date": "2/1/1913",
                "place": "Arvika"
            },
            "education": [
                {
                    "degree": "Stud:ex.",
                    "year": "1931",
                    "institution": "Vänersb."
                },
                {
                    "degree": "Dram. Teat. elevsk.",
                    "year": "1934-1936",
                    "institution": "N/A"
                }
            ],
            "career": [
                {
                    "position": "Eng. v.",
                    "years": {
                        "start_year": 1937,
                        "end_year": 1946
                    },
                    "organization": "Stadsteat. i Gbg"
                },
                {
                    "position": "v.",
                    "years": {
                        "start_year": 1946,
                        "end_year": 9999
                    },
                    "organization": "Stadsteat. i Hälsingb."
                }
            ],
            "family": {
                "spouse": "Margareta Bergfelt",
                "marriage_year": "N/A",
                "children": [
                    {
                        "name": "Boel",
                        "birth_year": "46"
                    }
                ]
            }
        },
        "4": {
            "full_name": "Ekström, Carl Henrik Theodor",
            "location": "Herrevadskloster, Ljungbyhed",
            "occupation": "major",
            "birth_details": {
                "date": "1/2/1891",
                "place": "Landskrona"
            },
            "education": [
                {
                    "degree": "Kadett",
                    "year": "1905-1912",
                    "institution": "SKS"
                },
                {
                    "degree": "sjöoff:ex.",
                    "year": "1912",
                    "institution": "N/A"
                }
            ],
            "career": [
                {
                    "position": "Und:löjtn.",
                    "years": {
                        "start_year": 1914,
                        "end_year": 1918
                    },
                    "organization": "Skånska hus :reg."
                },
                {
                    "position": "löjtn.",
                    "years": {
                        "start_year": 1918,
                        "end_year": 9999
                    },
                    "organization": "Skånska kav:reg."
                },
                {
                    "position": "ryttmäst.",
                    "years": {
                        "start_year": 1929,
                        "end_year": 1931
                    },
                    "organization": "livskvadr. v. reg."
                },
                {
                    "position": "av sk. o. i reg. res.",
                    "years": {
                        "start_year": 1941,
                        "end_year": 9999
                    },
                    "organization": "N/A"
                },
                {
                    "position": "major",
                    "years": {
                        "start_year": 1942,
                        "end_year": 9999
                    },
                    "organization": "N/A"
                }
            ],
            "family": {
                "spouse": "Anna Moltke-Huitfeldt",
                "marriage_year": "N/A",
                "children": [
                    {
                        "name": "Ulla",
                        "birth_year": "25"
                    },
                    {
                        "name": "Brita",
                        "birth_year": "27"
                    },
                    {
                        "name": "Margaretha",
                        "birth_year": "33"
                    }
                ]
            }
        }
    }
}