{
    "original": "KIHLBERG, CARL GUSTAV,\ndisponent, Västerås, f i Halmstad 5/11/05 av\nsjökapt Oscar K o Kristina Andersson.\nRealex 21, anst Hamburg 23-25, Sv\nEsso ab Västerås 26, disp där sed 38.\n-Medl Odd Fellow, Rotary. - Utm:\nProPGM, Sv Esso ab ftjt.\nGift 32 m Margit Anderberg, dtr t\n\njärnhandl Gustaf A o Lisa Eriksson.\n-Barn: Boel f 34, Håkan f 39.\nKIHLGREN, C OSCAR F, köpman,\n\nVästerås, f 1/12/06 av C F K o A C\nPettersson.\n\nInneh firma Kihlgrens livsmedel. -\nStyr:-ordf ab Hakon Swenson, v ordf\nICA-förb, styr:led ab ICA-restauranger, Sv:es\nkreditbks avd :kont Västerås, Västerås\nsparbk, led Stadsfullm 44-54. - Medl\nRotary, Odd Fellow. - Hobbies: skidor,\nallm idrott, schack.\n\nGift 31 m Ingrid Ståhl f 08, dtr t\npost-tjm Thure S o h h. - Barn: Birgitta f 35,\nTord f 39, Agneta f 42.\n\nKIHLGREN, SIGURD H T,\nakademisekreterare, Uppsala, f i Ytterhogdal,\nJämtl l, 21/3/00 av kyrkoh Nils K o\nElise Naess.\n\nStud:ex Östersund 18, jur kand Upps 26,\naman Upps univ kansli 32 (27), med o\nfil fak sekr 31-51, kamr Akad sjh o\nsjh-direkt sekr 45-55, akad :sekr Upps univ\nsed 52. - 2:e kurat Norrl nät Upps 24-27,\nskattmäst 28-54, hedL 41, sekr Upps\nstud :kår 27-32. - LVSU 60. - Fil hed :dr\nUpps 64. - Utm: RVO.\n\nKIHLMAN, BENGT A, fil dr, docent,\n\nUppsala, f i Helsingfors 16/3/22 av fil\nmag Bertel K o Mary af Forselles.\nFil kand Helsingfors 46, fil lic Lund 50,\nfil dr Upps 52, e docent Upps univ 52,\nanst cellforskn :inst Karol inst Sthlm 54,\neo docent Upps univ 55, särsk forskartj\nbiokem cytogenetik NFR sed 60.\n-Forskn :arb ol univ o inst Danm, Engl\no USA. - Medl Internat Soc for Cell\nBiology, Assoc for Radiation Research,\nNord fören f cellforskn. - Skr:\nInduc-tion of chromosome changes with\npu-rine derivatives (drsavh 52), Oxygen and\nthe production of chromosome\naberra-tions by chemicals and x-rays (55),\nBio-chemical aspects of chromosome\nbreak-age (61) m m.\n\nGift 1) 46 m Birgitta Wallgren f 25, dtr\nt prof Ivar W o Marita Tammelander,\n2) 52 m Irma Nummenmaa f 28, dtr t\nstat :insp Wäinö N o Karin Furubielke.\n- Barn: i l:a akt Benita f 47, i 2:a akt\nMikael f 53, Camilla f 57.\n",
    "structured": {
        "1": {
            "full_name": "KIHLBERG, CARL GUSTAV",
            "location": "Västerås",
            "occupation": "disponent",
            "birth_details": {
                "date": "05/11/1905",
                "place": "Halmstad",
                "parents": "sjökapt Oscar K o Kristina Andersson"
            },
            "education": [
                {
                    "degree": "Realex",
                    "year": "1921",
                    "institution": "NULL"
                },
                {
                    "degree": "anst Hamburg",
                    "year": "1923",
                    "institution": "NULL"
                }
            ],
            "career": [
                {
                    "position": "Sv Esso ab Västerås",
                    "years": {
                        "start_year": 1926,
                        "end_year": 1928
                    },
                    "organization": "NULL"
                },
                {
                    "position": "disp där",
                    "years": {
                        "start_year": 1938,
                        "end_year": 1945
                    },
                    "organization": "NULL"
                }
            ],
            "family": {
                "spouse": "Margit Anderberg",
                "marriage_year": "1932",
                "children": [
                    {
                        "name": "Boel",
                        "birth_year": "1934"
                    },
                    {
                        "name": "Håkan",
                        "birth_year": "1939"
                    }
                ]
            }
        },
        "2": {
            "full_name": "KIHLGREN, C OSCAR F",
            "location": "Västerås",
            "occupation": "köpman",
            "birth_details": {
                "date": "01/12/1906",
                "place": "NULL",
                "parents": "C F K o A C Pettersson"
            },
            "education": [],
            "career": [],
            "family": {
                "spouse": "Ingrid Ståhl",
                "marriage_year": "1931",
                "children": [
                    {
                        "name": "Birgitta",
                        "birth_year": "1935"
                    },
                    {
                        "name": "Tord",
                        "birth_year": "1939"
                    },
                    {
                        "name": "Agneta",
                        "birth_year": "1942"
                    }
                ]
            },
            "hobbies": [
                "skidor",
                "allm idrott",
                "schack"
            ]
        },
        "3": {
            "full_name": "KIHLGREN, SIGURD H T",
            "location": "Uppsala",
            "occupation": "akademisekreterare",
            "birth_details": {
                "date": "21/03/1900",
                "place": "Ytterhogdal",
                "parents": "kyrkoh Nils K o Elise Naess"
            },
            "education": [
                {
                    "degree": "Stud:ex Östersund",
                    "year": "1918",
                    "institution": "NULL"
                },
                {
                    "degree": "jur kand Upps",
                    "year": "1926",
                    "institution": "NULL"
                }
            ],
            "career": [
                {
                    "position": "Upps univ kansli",
                    "years": {
                        "start_year": 1931,
                        "end_year": 1951
                    },
                    "organization": "NULL"
                },
                {
                    "position": "skattmäst",
                    "years": {
                        "start_year": 1928,
                        "end_year": 1954
                    },
                    "organization": "NULL"
                }
            ],
            "family": {},
            "honorary_titles": [
                {
                    "title": "Fil hed :dr Upps",
                    "institution": "1964",
                    "year": "NULL"
                }
            ]
        },
        "4": {
            "full_name": "KIHLMAN, BENGT A",
            "location": "Uppsala",
            "occupation": "fil dr, docent",
            "birth_details": {
                "date": "16/03/1922",
                "place": "Helsingfors",
                "parents": "fil mag Bertel K o Mary af Forselles"
            },
            "education": [
                {
                    "degree": "Fil kand Helsingfors",
                    "year": "1946",
                    "institution": "NULL"
                },
                {
                    "degree": "fil lic Lund",
                    "year": "1950",
                    "institution": "NULL"
                },
                {
                    "degree": "fil dr Upps",
                    "year": "1952",
                    "institution": "NULL"
                }
            ],
            "career": [
                {
                    "position": "anst cellforskn :inst Karol inst Sthlm",
                    "years": {
                        "start_year": 1954,
                        "end_year": "NULL"
                    },
                    "organization": "NULL"
                },
                {
                    "position": "eo docent Upps univ",
                    "years": {
                        "start_year": 1955,
                        "end_year": "NULL"
                    },
                    "organization": "NULL"
                }
            ],
            "family": {
                "spouse": "NULL",
                "marriage_year": "NULL",
                "children": []
            },
            "publications": [
                {
                    "title": "Induc-tion of chromosome changes with pu-rine derivatives",
                    "year": "1952",
                    "type": "drsavh"
                },
                {
                    "title": "Oxygen and the production of chromosome aberra-tions by chemicals and x-rays",
                    "year": "1955",
                    "type": "NULL"
                },
                {
                    "title": "Bio-chemical aspects of chromosome break-age",
                    "year": "1961",
                    "type": "NULL"
                }
            ]
        }
    }
}