{
    "original": "KOARK, HANS J, Dr phil, docent,\nUppsala, f i Leibnitz, Tyskl, 4/8/21 av\nkrim:komm Arthur K o Anna Kirchner.\nStud:ex Leipzig 39, Dr phil Innsbruck\n49, fil lic Upps 52, doc i mineralogi o\nPetrografi där 56; forskn :ass åt prof\n\nLjungner Lund 50, l:e ass\nmineraloggeolog inst Upps 53, eo doc Upps univ\n57, forskarbef i malmgeologi Stat nät\nforskn:råd sed 63. - Skr: ett 30-tal skr\ni Petrografi, strukturpetrografi, tektonik\no malmgeologi.\n\nGift 43 m Marie Bongardt. - Barn:\nHansjörg f 44.\n\nKÖERSNER, N PER-ERIK, bitr\növerläkare, Uppsala, f i Falun 20/10/17 av\nciv: ing Erik K o Anna Broms.\nStud:ex Falun 37, med kand Upps 39,\nmed lic 45. - Eo aman anat inst Upps\nuniv 39, patol inst 40-45, hyg-bakteriol\ninst 43; läk krigssjh Finl 42, tf 2:e\nunderläk Sjö-Gunnarsbo sanat 43, prov:läk\n44, tf 2:e läk Ulleråkers sjh 45, l:e\nunderläk psykiatr klin Akad sjh 46,\nbarn-psykiatr klin 55, bitr överläk psykiatr\nklin sed 56 o ch nykt:v:poliklin Akad\nsjh sed 57. - Föreläsn i psykiatr ämnen,\nsärsk rör alkoholistbehandl. - Skr i\npsykiatri. - Medl Lions club. - Hobbies:\nfilm, fotografering.\n\nGift 47 m Grethe Sinding f 12, dtr t\nköpm Holger S o Tine Nielsen. - Barn:\nIb f 47, Eva f 49.\n\nKOLLÄNDER, BROR G E, intendent,\n\nKolsva, f i Eksjö 31/5/12 av lantbr\nDavid K o Hanna Hedberg.\nStat polissk 36 o 44; konst, krim:konst\no tf överkonst Sthlm 35-48, intend\nKohls-wa jernverks ab sed 48. - Led komm:nd,\nkomm:fullm, hälsov:nd, brandstyr m m.\n- Medl Odd Fellow. - Utm: SCFftjtS,\nFören f arb:skydd ftjt. - Hobbies: jakt,\nfiske, naturvård.\n\nGift 39 m Britt Wahlgren f 17, dtr t\nkamrer Eskil W o Maria Storm. - Barn:\nStaffan f 42, Ylva f 46, Örjan f 50.\n\n",
    "structured": {
        "1": {
            "full_name": "Hans J Koark",
            "location": "Uppsala",
            "occupation": "Dr phil, docent",
            "birth_details": {
                "date": "04/08/1921",
                "place": "Leibnitz, Tyskland"
            },
            "education": [
                {
                    "degree": "Stud:ex",
                    "year": "1939",
                    "institution": "Leipzig"
                },
                {
                    "degree": "Dr phil",
                    "year": "1949",
                    "institution": "Innsbruck"
                },
                {
                    "degree": "fil lic",
                    "year": "1952",
                    "institution": "Upps"
                }
            ],
            "career": [
                {
                    "position": "forskning:ass",
                    "years": {
                        "start_year": 1950,
                        "end_year": 1956
                    },
                    "organization": "Uppsala"
                },
                {
                    "position": "l:e ass mineraloggeolog inst",
                    "years": {
                        "start_year": 1953,
                        "end_year": null
                    },
                    "organization": "Upps"
                }
            ],
            "family": {
                "spouse": "Marie Bongardt",
                "marriage_year": "1943",
                "children": [
                    {
                        "name": "Hansjörg",
                        "birth_year": "1944"
                    }
                ]
            }
        },
        "2": {
            "full_name": "Per-Erik Köersner",
            "location": "Uppsala",
            "occupation": "bitr överläkare",
            "birth_details": {
                "date": "20/10/1917",
                "place": "Falun"
            },
            "education": [
                {
                    "degree": "Stud:ex",
                    "year": "1937",
                    "institution": "Falun"
                },
                {
                    "degree": "med kand",
                    "year": "1939",
                    "institution": "Upps"
                },
                {
                    "degree": "med lic",
                    "year": "1945",
                    "institution": "Upps"
                }
            ],
            "career": [
                {
                    "position": "eo aman anat inst",
                    "years": {
                        "start_year": 1939,
                        "end_year": null
                    },
                    "organization": "Upps"
                },
                {
                    "position": "l:e underläk psykiatr klin Akad sjh",
                    "years": {
                        "start_year": 1946,
                        "end_year": null
                    },
                    "organization": "Akad sjh"
                }
            ],
            "family": {
                "spouse": "Grethe Sinding",
                "marriage_year": "1947",
                "children": [
                    {
                        "name": "Ib",
                        "birth_year": "1947"
                    },
                    {
                        "name": "Eva",
                        "birth_year": "1949"
                    }
                ]
            },
            "hobbies": [
                "film",
                "fotografering"
            ]
        },
        "3": {
            "full_name": "Bror G E Kolländer",
            "location": "Kolsva",
            "occupation": "intendent",
            "birth_details": {
                "date": "31/05/1912",
                "place": "Eksjö"
            },
            "education": [
                {
                    "degree": "Stat polissk",
                    "year": "1936",
                    "institution": null
                },
                {
                    "degree": "konst, krim:konst",
                    "year": "1944",
                    "institution": null
                }
            ],
            "career": [
                {
                    "position": "tf överkonst",
                    "years": {
                        "start_year": 1935,
                        "end_year": 1948
                    },
                    "organization": "Sthlm"
                }
            ],
            "family": {
                "spouse": "Britt Wahlgren",
                "marriage_year": "1939",
                "children": [
                    {
                        "name": "Staffan",
                        "birth_year": "1942"
                    },
                    {
                        "name": "Ylva",
                        "birth_year": "1946"
                    },
                    {
                        "name": "Örjan",
                        "birth_year": "1950"
                    }
                ]
            },
            "community_involvement": [
                {
                    "role": "medl",
                    "organization": "Odd Fellow",
                    "years": null
                }
            ],
            "board_memberships": [
                {
                    "position": "Led komm:nd",
                    "organization": null,
                    "years": null
                }
            ],
            "honorary_titles": [
                {
                    "title": "SCFftjtS",
                    "institution": null,
                    "year": null
                },
                {
                    "title": "Fören f arb:skydd ftjt",
                    "institution": null,
                    "year": null
                }
            ],
            "hobbies": [
                "jakt",
                "fiske",
                "naturvård"
            ]
        }
    }
}