{
    "original": "KRUGEL, ROBERT E, fd landsfiskal,\nfd riksdagsman, Örebro, f i Normlösa,\n\nÖstergötl l, 6/12/86 av lantbr S A\nPettersson o Amalia Larsson.\nLänsm:ex 09, länsman Memmings hd\n15-17, landsfisk Sköllersta distr 18.\n-Ordf Örebro l landst o dess FU 50-58\nsamt i direkt f centrallås Örebro; led\nFK 41-59 (s).\n\nGift 26 m Ingeborg Jansson f 04, dtr t\ntullförv Fridolf J o Ingeborg Lövgren.\n\n- Barn: Rolf f 28, Robert f 31.\nKRUGER,    WOLDEMAR,    advokat,\n\nUppsala, f i Moskva 24/2/09 av överste\nPaul K o Maria Kijander.\nStud:ex Hfors 27, jur kand Hfors 35,\nUpps 51, korresp Hfors aktiebk 27-32,\nomb :man Fiskars-konc Finl 36, bitr jur\nHallströms adv :byrå Umeå 44, Ederoths\nadv:byrå Upps 50, deläg där. - LSA 52.\n\n-  Utm: Finska krigsordn o med.\n\nGift 37 m Märta Öhrman f 08, dtr t\nhemm:äg Fritiof Ö o Anna Jonsson.\n-Barn: Birgitta f 40, Staffan f 43.\n\nKULL, PER G, exportchef,\nHallstahammar, f i St Kopparb, Kopparb l,\n12/10/18 av civiling Gösta K o Selma\nSvensson.\n\nStud:ex 38, res:off:ex 42, DHG 43,\nbergssk Filipstad 45, anst exportavd\nSandvikens jernv ab 46, exporten ab\nKanthal Hallstahammar sed 51. -\nHobbies: båtsport, bridge.\nGift 47 m Margareta Gille f 24, dtr t\ndisp Nils G o Stina Forsberg. - Barn:\nBengt f 48, Nils-Johan f 50, Per-Staffan\nf 57.\n\nKULLBERG-MAYER, FRED,\ndirektör, Katrineholm, f i Stora Malm,\nSödermani l, 3/3/13 av bruksäg O K-M\no Amy K.\n\nGbgHdlI 30, anst Sv hdlskamm London\n31, prakt i takbeläggn m m f ind Engl\n\n0   Frankr  34-35,  Ind  Engineering  Ltd\nBush   House   London   34-37,   eg\ngen:agentur i eng takbeläggn f ind m m sed\n36. - Hobbies: flygning, bilsport, jakt.\nGift 1) 38-46 m Carola Lundin, 2) 47-53\nm Natascha Micheéw,  3) 56 m Greta\nLindahl, f Schröder. - Barn: i 2:a akt\nTed f 48, Catharina f 49, Stefan f 51.\n\n",
    "structured": {
        "0": {
            "full_name": "KRUGEL, ROBERT E",
            "location": "Örebro",
            "occupation": "fd landsfiskal, fd riksdagsman",
            "birth_details": {
                "date": "06/12/1886",
                "place": "Normlösa, Östergötland",
                "parents": "lantbr S A Pettersson o Amalia Larsson"
            },
            "education": [
                {
                    "degree": "länsm:ex",
                    "year": "1909",
                    "institution": "NULL"
                },
                {
                    "degree": "länsman",
                    "year": "1915-1917",
                    "institution": "Memmings hd"
                }
            ],
            "career": [
                {
                    "position": "landsfisk",
                    "years": {
                        "start_year": 1918,
                        "end_year": null
                    },
                    "organization": "Sköllersta distr"
                }
            ],
            "family": {
                "spouse": "Ingeborg Jansson",
                "marriage_year": "1926",
                "children": [
                    {
                        "name": "Rolf",
                        "birth_year": "1928"
                    },
                    {
                        "name": "Robert",
                        "birth_year": "1931"
                    }
                ]
            }
        },
        "1": {
            "full_name": "KRUGER, WOLDEMAR",
            "location": "Uppsala",
            "occupation": "advokat",
            "birth_details": {
                "date": "24/02/1909",
                "place": "Moskva"
            },
            "education": [
                {
                    "degree": "stud:ex",
                    "year": "1927",
                    "institution": "Hfors Högskola"
                },
                {
                    "degree": "jur kand",
                    "year": "1935",
                    "institution": "Hfors Högskola"
                },
                {
                    "degree": "korresp Hfors aktiebk",
                    "year": "1927-1932",
                    "institution": "NULL"
                }
            ],
            "career": [
                {
                    "position": "omb :man",
                    "years": {
                        "start_year": 1936,
                        "end_year": null
                    },
                    "organization": "Fiskars-konc Finl"
                }
            ],
            "family": {
                "spouse": "Märta Öhrman",
                "marriage_year": "1937",
                "children": [
                    {
                        "name": "Birgitta",
                        "birth_year": "1940"
                    },
                    {
                        "name": "Staffan",
                        "birth_year": "1943"
                    }
                ]
            }
        },
        "2": {
            "full_name": "KULL, PER G",
            "location": "Hallstahammar",
            "occupation": "exportchef",
            "birth_details": {
                "date": "12/10/1918",
                "place": "Stora Kopparberg, Kopparbergs län"
            },
            "education": [
                {
                    "degree": "stud:ex",
                    "year": "1938",
                    "institution": "NULL"
                },
                {
                    "degree": "res:off:ex",
                    "year": "1942",
                    "institution": "NULL"
                },
                {
                    "degree": "DHG",
                    "year": "1943",
                    "institution": "NULL"
                },
                {
                    "degree": "bergssk",
                    "year": "1945",
                    "institution": "Filipstad"
                }
            ],
            "career": [
                {
                    "position": "anst exportavd",
                    "years": {
                        "start_year": 1951,
                        "end_year": null
                    },
                    "organization": "Kanthal Hallstahammar"
                }
            ],
            "family": {
                "spouse": "Margareta Gille",
                "marriage_year": "1947",
                "children": [
                    {
                        "name": "Bengt",
                        "birth_year": "1948"
                    },
                    {
                        "name": "Nils-Johan",
                        "birth_year": "1950"
                    },
                    {
                        "name": "Per-Staffan",
                        "birth_year": "1957"
                    }
                ]
            },
            "hobbies": [
                "båtsport",
                "bridge"
            ]
        },
        "3": {
            "full_name": "KULLBERG-MAYER, FRED",
            "location": "Katrineholm",
            "occupation": "direktör",
            "birth_details": {
                "date": "03/03/1913",
                "place": "Stora Malm, Södermanlands län"
            },
            "education": [
                {
                    "degree": "GbgHdlI",
                    "year": "1930",
                    "institution": "NULL"
                }
            ],
            "career": [
                {
                    "position": "eg gen:agentur",
                    "years": {
                        "start_year": 1936,
                        "end_year": null
                    },
                    "organization": "eng takbeläggn f ind m m"
                }
            ],
            "family": {
                "spouse": "Carola Lundin",
                "marriage_year": "1938-1946",
                "children": [
                    {
                        "name": "Ted",
                        "birth_year": "1948"
                    },
                    {
                        "name": "Catharina",
                        "birth_year": "1949"
                    },
                    {
                        "name": "Stefan",
                        "birth_year": "1951"
                    }
                ]
            },
            "hobbies": [
                "flygning",
                "bilsport",
                "jakt"
            ]
        }
    }
}