{
    "original": "Tessing-Ericsson, Greta, leg. läkare,\nGöteborg, f. 14/12/00 i Hälsingb. av\nlöjtn. Axel Tessing o. Signe Montell.\nG. 32 m. med. lic. Eric Ericsson. Barn:\nSigne Christina f. 32, Ida Margareta\n41. — Stud:ex. i Hälsingb. 20, med.\nkand. i Lund 24, med. lic. 30. E. läk.\nv. Lunds las. med. avd. 29, assist :läk.\nsamt tf. und:läk. v. pediatr. khn. i\nLund 30, assist :läk. v. Sthlms sjukhem\n30-31, tf. und :läk. v. Äsö sjukhus\n31, e. läk. samt tf. und :läk. v.\nHälsingborgs las. med. avd. s. å., tf. andre\nläk. v. S:ta Maria sjukh. o. assist :läk.\nv. Lunds las. psykiatr. klin. kort. tid.\n33, tf. förste resp. andre läk. v. S :t\nLars sjukh. 32, e. läk. där 33, e. o.\nandre läk. v. Västra Marks sjukh.\n\n34-35,\tandre läk. v. Lillhagens sjukh.\n\n35-38,\tund:läk. v. Sahlgr. sjukh.\npsykiatr. avd. 38.\n\nTham, Ållan Wolrath Victor,\nstiftssekreterare, Växjö, f. 30/1/00 i Tranås\nav öv:läk. Henrik Th. o. Betty Maury.\nG. 29 m. Märta Lundblad. —\nStud:-ex. v. h. a. 1. i Linköp. 18, jur. kand.\ni Upps. 24. Res. t. Tyskl. 21, Finl. 24,\nFrankr. 24. Aman. v. domkap. i Upps.\n28, e. o. stiftsnot. 37, ord. 43,\nstifts-sekr. v. domkap. i Växjö fr. 45. Sekr.\no. kassaförv. i styr. f. SvRK X. distr.\n43-45, skattmäst. i Östg. nat. i Upps.\n\n40-45, led. av stiftsnd i Växjö fr. 45.\nMedl. av O. D., S. H. T., Rotary m. f!\nSkr.: Ärsredog. f. SvRK X. distr.\nverk-samh. 30 o. 44, Handl. ang. prästmötet\ni Växjö 47.\n\nTham, Per Filip Sebastian, jur.\nkand., advokat, Jönköping, f. 26/4/Ö3 i\nLandskrona av kapt. Richard T. o.\nMarguerite Bourquin. G. 33 m. Inga\nLisa Dahl. — Stud:ex. 22, jur. kand.\n25. Tingstjg. 26-28, prakt. jur. i\nJön-köp. sed. 29. Omb :man i A-B\nJord-brukarbank. 34, deläg. i firman adv:a\nEkberg o. Tham sed. 40. Led. av Sv:es\nadv:samf. sed. 40.\n\n",
    "structured": {
        "1": {
            "full_name": "Tessing-Ericsson, Greta",
            "location": "Göteborg",
            "occupation": "leg. läkare",
            "birth_details": {
                "date": "14/12/1900",
                "place": "Hälsingborg",
                "parents": "löjtn. Axel Tessing, Signe Montell"
            },
            "education": [
                {
                    "degree": "Stud:ex.",
                    "year": "1920",
                    "institution": "Hälsingborg"
                },
                {
                    "degree": "med. kand.",
                    "year": "1924",
                    "institution": "Lund"
                },
                {
                    "degree": "med. lic.",
                    "year": "1930",
                    "institution": "Lund"
                }
            ],
            "career": [
                {
                    "position": "läk. v. Lunds las. med. avd.",
                    "years": {
                        "start_year": 1929,
                        "end_year": 1930
                    },
                    "organization": "Lunds las."
                },
                {
                    "position": "assist :läk. v. Sthlms sjukhem",
                    "years": {
                        "start_year": 1930,
                        "end_year": 1931
                    }
                },
                {
                    "position": "tf. und :läk. v. Äsö sjukhus",
                    "years": {
                        "start_year": 1931,
                        "end_year": 1931
                    }
                },
                {
                    "position": "e. läk. samt tf. und :läk. v. Hälsingborgs las. med. avd.",
                    "years": {
                        "start_year": 1931
                    }
                },
                {
                    "position": "andre läk. v. S:ta Maria sjukh.",
                    "years": {
                        "start_year": 1932,
                        "end_year": 1933
                    }
                },
                {
                    "position": "e. läk. där",
                    "years": {
                        "start_year": 1933
                    }
                }
            ],
            "family": {
                "spouse": "med. lic. Eric Ericsson",
                "marriage_year": "1932",
                "children": [
                    {
                        "name": "Signe Christina",
                        "birth_year": "1932"
                    },
                    {
                        "name": "Ida Margareta",
                        "birth_year": "1941"
                    }
                ]
            }
        },
        "2": {
            "full_name": "Tham, Ållan Wolrath Victor",
            "location": "Växjö",
            "occupation": "stiftssekreterare",
            "birth_details": {
                "date": "30/1/1900",
                "place": "Tranås",
                "parents": "öv:läk. Henrik Th., Betty Maury"
            },
            "education": [
                {
                    "degree": "Stud:-ex.",
                    "year": "1918",
                    "institution": "h. a. 1. i Linköp."
                },
                {
                    "degree": "jur. kand.",
                    "year": "1924",
                    "institution": "Upps."
                }
            ],
            "career": [
                {
                    "position": "Aman. v. domkap. i Upps.",
                    "years": {
                        "start_year": 1928
                    }
                },
                {
                    "position": "e. o. stiftsnot.",
                    "years": {
                        "start_year": 1937
                    }
                },
                {
                    "position": "ord.",
                    "years": {
                        "start_year": 1943
                    }
                },
                {
                    "position": "stifts-sekr. v. domkap. i Växjö",
                    "years": {
                        "start_year": 1945
                    }
                }
            ],
            "family": {
                "spouse": "Märta Lundblad",
                "marriage_year": "1929"
            }
        },
        "3": {
            "full_name": "Tham, Per Filip Sebastian",
            "location": "Jönköping",
            "occupation": "jur. kand., advokat",
            "birth_details": {
                "date": "26/4/1903",
                "place": "Landskrona",
                "parents": "kapt. Richard T., Marguerite Bourquin"
            },
            "education": [
                {
                    "degree": "Stud:ex.",
                    "year": "1922"
                },
                {
                    "degree": "jur. kand.",
                    "year": "1925"
                }
            ],
            "career": [
                {
                    "position": "Tingstjg.",
                    "years": {
                        "start_year": 1926,
                        "end_year": 1928
                    }
                }
            ],
            "family": {
                "spouse": "Inga Lisa Dahl",
                "marriage_year": "1933"
            }
        }
    }
}