{
    "original": "T\n\nTamm, Erik Göran Mauritz Adolf,\ndirektör, Göteborg, f. 17/1/11 i StMm\nav byråing. Per. T. o. Ingeborg Emelia\nAxell. G. 36 m. Kerstin Lykke\nJaco-baeus. Barn: Sebastian f. 3-6, Elisabeth\n40, Göran 42. — Stud:ex. i Djursholm\n30, DHIS 32, stud. i Storbritann. 30, 32\no. s. stip. fr. HHS 3d Anst. i A-B Sv.\nTel:byrån fr. 3Ö, s. chef f. Gbgskont.\nfr. 43. Lär. v. hand ihögsk. i Gbg.\nStyriled. i Metall Fabr. A-B C. C.\nSporrong &amp; Go. i Sthlm sed. 47, i Gbgs\nreklamifören. Skr.: diktsam|ling 42, div.\nupps. i företagsekon, ämnen i\nAffärs-ekonomi o. a. tidskr.\n\nTamm, Torgny Sune Hugosson,\nkapten, Göteborg, f. 1/2/95 i Sthlm av\nbrukspatr. Hugo T. o. Maria Unonius.\nG. 34 m. Gunnel (Guld) Säfw^enberg.\nBarn: Eva ’f. 36, Kerstin 37, Gunilla\n39, Claes 41, Monika 43; Gordon 44. —\nStud:ex. v. Lundsbergs sk. 13,\nsjöka-dett 13, sjöoff :ex. V6. Delt. i yachten\nFidras världsomsegl. 20-22 s. färdled.\nAvsk. fr. stat v. flottan s. löjtn. 27,\nkapt. i flott. res. 29, styrm. å fyrmast.\nbarken C. B. Pedersen 25-28, överlär.\nv. Rydbergska stift. 28-35, befälh. å\n4-m;ast. barken Abraham Rydberg\n29-3i5, red:chef i A-B Karta &amp; Oaxens\nkalkbruk 36-39, verkst. dir. v. stift.\nLundsbergs sk. 39-44, red:che!f i\nUddeholms A-B fr. 44. Led. av Rydb. stift,\ndir. fr. 36, av Örlogsm rsällsk. fr. 22, av\nstyr. ’f. stift. Lundsh. sk. 38-41 o. fr. 44,\nav styr. f. Carnegiestiift. fr. 39, av styr.\nf. Red. A-B Wallenco fr. 39. RVO 22,\nKSS ftjGM 22.\n\n*Tange, Eric Mauritz, komminister,\nMollösund, f. 7/9/03 i Ödsmål, Gbgs o.\nBoh. 1. — Studiex. i Gbg 29, teol. fil.\ni’x. 31, teol. kand., prakt, teol prov\nj^amt prästv. f. Gbgs stift 35. Tjg. i\nBacka, Tvärred, Näsànge, Fuxerna,\nSeglora, Istorp o. Starrkärr, kommin.\ni Mollösund sed. 41.\n\n",
    "structured": {
        "0": {
            "full_name": "Tamm, Erik Göran Mauritz Adolf",
            "location": "Göteborg",
            "occupation": "direktör",
            "birth_details": {
                "date": "17/01/1911",
                "place": "StMm"
            },
            "education": [
                {
                    "degree": "Stud:ex.",
                    "year": "1930",
                    "institution": "Djursholm"
                },
                {
                    "degree": "DHIS",
                    "year": "1932",
                    "institution": "storbritannien"
                }
            ],
            "career": [
                {
                    "position": "anst.",
                    "years": {
                        "start_year": 1930,
                        "end_year": 1932
                    },
                    "organization": "HHS"
                },
                {
                    "position": "chef f. Gbgskont.",
                    "years": {
                        "start_year": 1943,
                        "end_year": null
                    },
                    "organization": "A-B Sv. Tel:byrån"
                },
                {
                    "position": "lär. v. hand ihögsk. i Gbg.",
                    "years": {
                        "start_year": null,
                        "end_year": null
                    },
                    "organization": null
                }
            ],
            "family": {
                "spouse": "Kerstin Lykke Jacobaeus",
                "marriage_year": "1936",
                "children": [
                    {
                        "name": "Sebastian",
                        "birth_year": "1936"
                    },
                    {
                        "name": "Elisabeth",
                        "birth_year": "1940"
                    },
                    {
                        "name": "Göran",
                        "birth_year": "1942"
                    }
                ]
            }
        },
        "1": {
            "full_name": "Tamm, Torgny Sune Hugosson",
            "location": "Göteborg",
            "occupation": "kapten",
            "birth_details": {
                "date": "01/02/1895",
                "place": "Sthlm"
            },
            "education": [
                {
                    "degree": "Stud:ex.",
                    "year": "1913",
                    "institution": "Lundsbergs sk."
                }
            ],
            "career": [
                {
                    "position": "sjöoff :ex. V6",
                    "years": {
                        "start_year": null,
                        "end_year": null
                    },
                    "organization": null
                },
                {
                    "position": "befälh. å 4-m;ast. barken Abraham Rydberg",
                    "years": {
                        "start_year": 1929,
                        "end_year": 1935
                    },
                    "organization": "Rydbergska stift."
                },
                {
                    "position": "verkst. dir. v. stift. Lundsbergs sk.",
                    "years": {
                        "start_year": 1939,
                        "end_year": 1944
                    },
                    "organization": null
                }
            ],
            "family": {
                "spouse": "Gunnel (Guld) Säfwenberg",
                "marriage_year": "1934",
                "children": [
                    {
                        "name": "Eva",
                        "birth_year": "1936"
                    },
                    {
                        "name": "Kerstin",
                        "birth_year": "1937"
                    },
                    {
                        "name": "Gunilla",
                        "birth_year": "1939"
                    },
                    {
                        "name": "Claes",
                        "birth_year": "1941"
                    },
                    {
                        "name": "Monika",
                        "birth_year": "1943"
                    },
                    {
                        "name": "Gordon",
                        "birth_year": "1944"
                    }
                ]
            }
        },
        "2": {
            "full_name": "Tange, Eric Mauritz",
            "location": "Mollösund",
            "occupation": "komminister",
            "birth_details": {
                "date": "07/09/1903",
                "place": "Ödsmål, Gbgs o. Boh. l."
            },
            "education": [
                {
                    "degree": "Studiex.",
                    "year": "1929",
                    "institution": "Gbg"
                },
                {
                    "degree": "Teol. fil.",
                    "year": "1931",
                    "institution": "x."
                }
            ],
            "career": {
                "position": null,
                "years": {
                    "start_year": 1941,
                    "end_year": null
                },
                "organization": "Mollösund"
            },
            "family": {
                "spouse": null,
                "marriage_year": null,
                "children": null
            }
        }
    }
}