{
    "original": "Thorsell, Lars-Erik Johan, rådman,\nnotarius pubhcus, Uddevalla, f. 13/2/02\ni Sthlm av godsäg. Torsten T. o.\nEH-sabeth Nilsson. G. 35 m. Gertrud\nWedberg. Barn: Lisbeth f. 36,\nBirgitta 41. — Stud:ex. i Örebro 22, jur.\nkand. i Upps. 30. Tingstjg. i\nVästernärkes doms. 30-34, tjg. i Göta hovr.\n34-35, brottmålsrådman o. not. publ. i\nUddevalla sed. 36. Fd. ordf. i tax:nd,\nordf. i barnav :nd, led. av brandstyr.,\nsuppl. i byggn:nd. Ordf. i Uddevalla\ntenniskl., v. ordf. i styr. f. Uddev.\nIdr:-hall, skattmäst. i Uddev. hum. förbund.\n\nThorslund, Gösta Emanuel, e. o.\nläroverksadjunkt, Mariestad, f. 18/12/03\ni Mariestad av bokför. Anders\nGustaf T. o. Eva Gunilla Muhr. G. 40\nm. Sara Nilsson. Barn: Gunilla o.\nAgneta ff. 43, Lars Gösta 46. —\nStud:-ex. i Sthlm 24, fil. kand. i Gbg 29, fil\nmag. 33, tent. i hand:tekn. 41.\nTim-lär. v. Gbgs östra real 40, v. Marie-\n\n51stads samrealsk. s. å., i prakt. o. teor.\nläroämnen 41-43, e. adj. fr. 43, e. o.\nadj. 46. Res. t. Tyskl., Frankr. o.\nEngl. 37. Hobby: musik.\n\nThorslund, John Maurits,\nchefsingenjör, Kalmar, f. 30/4/96 i Torsluncia,\nKalm. 1., av G. o. A. Thorslund. G.\n32 m. Astrid Källqvist. Barn: Linnea\nf. 26 (i tid. äkt.), Gunnel 34, Jan 39,\nAgneta 43, Anne-Marie 47. — Utex. v.\nGTH (eltekn.) 25. Bitr. ing. v. Kalm.\nstads gas- o. elverk fr. 25, chefsing.\ndär fr. 47. Medl. av Kalm. tekn :kl.,\nOdd Fellow. CTIs John EricssonM.\n\nThorson, Karl Gustaf, direktör,\nFritsla, f. 2/12/94 i Fritsla, Älvsb. 1.,\nav dir. C. T. o. Jenny Helander. G.\nm. Stina Thörnqvist. Barn: Bengt f.\n23, med. kand., Karin f. 31, stud. ■—\nRealex., Gbgs hand :!inst. Anst. i A-B\nCh. Thorson i Fritsla sed. 12, verkst.\ndir. i föret. sed. 18. Led. av komm:nd,\nkyrkofullm., kyrkovärd, brandchef,\nkyrkokassör, ordf. i styr. f. Älvsb.\nskytteförb., led. av V. U. i skytteförb.\növ :styr. fr. 47, led. av styr. f. Gbgs\nHand :banks avd :kont. i Fritsla,\nHob-bies: skytte, fiske. RVO, Älvsb.\nskytteförb. ftjGM, Älvsb. landst:förb.\nftjSM, Svsfb ftjSM, Sv:es brandkår,\nriksförb. SM.\n\n",
    "structured": {
        "1": {
            "full_name": "Thorsell, Lars-Erik Johan",
            "location": "Uddevalla",
            "occupation": "rådman, notarius pubhcus",
            "birth_details": {
                "date": "13/02/1902",
                "place": "Sthlm"
            },
            "education": [
                {
                    "degree": "Stud:ex.",
                    "year": "1922",
                    "institution": "Örebro"
                },
                {
                    "degree": "jur. kand.",
                    "year": "1930",
                    "institution": "Upps."
                }
            ],
            "career": [
                {
                    "position": "Tingstjg.",
                    "years": {
                        "start_year": 1930,
                        "end_year": 1934
                    },
                    "organization": "Västernärkes doms."
                },
                {
                    "position": "tjg.",
                    "years": {
                        "start_year": 1934,
                        "end_year": 1935
                    },
                    "organization": "Göta hovr."
                },
                {
                    "position": "brottmålsrådman, not. publ.",
                    "years": {
                        "start_year": 1936,
                        "end_year": null
                    },
                    "organization": "Uddevalla"
                }
            ],
            "family": {
                "spouse": "Gertrud Wedberg",
                "marriage_year": "1935",
                "children": [
                    {
                        "name": "Lisbeth",
                        "birth_year": "1936"
                    },
                    {
                        "name": "Birgitta",
                        "birth_year": "1941"
                    }
                ]
            }
        },
        "2": {
            "full_name": "Thorslund, Gösta Emanuel",
            "location": "Mariestad",
            "occupation": "e. o. läroverksadjunkt",
            "birth_details": {
                "date": "18/12/1903",
                "place": "Mariestad"
            },
            "education": [
                {
                    "degree": "Stud:-ex.",
                    "year": "1924",
                    "institution": "Sthlm"
                },
                {
                    "degree": "fil. kand.",
                    "year": "1929",
                    "institution": "Gbg"
                },
                {
                    "degree": "fil mag.",
                    "year": "1933",
                    "institution": null
                },
                {
                    "degree": "tent. i hand:tekn.",
                    "year": "1941",
                    "institution": null
                }
            ],
            "career": [
                {
                    "position": "Tim-lär.",
                    "years": {
                        "start_year": 1940,
                        "end_year": null
                    },
                    "organization": "Gbgs östra real"
                },
                {
                    "position": "e. adj.",
                    "years": {
                        "start_year": 1943,
                        "end_year": 1946
                    },
                    "organization": null
                }
            ],
            "family": {
                "spouse": "Sara Nilsson",
                "marriage_year": "1940",
                "children": [
                    {
                        "name": "Gunilla",
                        "birth_year": "1943"
                    },
                    {
                        "name": "Agneta",
                        "birth_year": "1943"
                    },
                    {
                        "name": "Lars Gösta",
                        "birth_year": "1946"
                    }
                ]
            },
            "hobbies": [
                "musik"
            ]
        },
        "3": {
            "full_name": "Thorslund, John Maurits",
            "location": "Kalmar",
            "occupation": "chefsingenjör",
            "birth_details": {
                "date": "30/04/1896",
                "place": "Torsluncia, Kalm. 1."
            },
            "education": [
                {
                    "degree": null,
                    "year": "1925",
                    "institution": "GTH (eltekn.)"
                }
            ],
            "career": [
                {
                    "position": "Bitr. ing.",
                    "years": {
                        "start_year": 1925,
                        "end_year": 1947
                    },
                    "organization": "Kalm. stads gas- o. elverk"
                },
                {
                    "position": "chefsing.",
                    "years": {
                        "start_year": 1947,
                        "end_year": null
                    },
                    "organization": "Kalm. stads gas- o. elverk"
                }
            ],
            "family": {
                "spouse": "Astrid Källqvist",
                "marriage_year": "1932",
                "children": [
                    {
                        "name": "Linnea",
                        "birth_year": "1926"
                    },
                    {
                        "name": "Gunnel",
                        "birth_year": "1934"
                    },
                    {
                        "name": "Jan",
                        "birth_year": "1939"
                    },
                    {
                        "name": "Agneta",
                        "birth_year": "1943"
                    },
                    {
                        "name": "Anne-Marie",
                        "birth_year": "1947"
                    }
                ]
            },
            "community_involvement": [
                {
                    "role": null,
                    "organization": "Odd Fellow",
                    "years": null
                },
                {
                    "role": null,
                    "organization": "CTIs John EricssonM.",
                    "years": null
                }
            ]
        },
        "4": {
            "full_name": "Thorson, Karl Gustaf",
            "location": "Fritsla",
            "occupation": "direktör",
            "birth_details": {
                "date": "02/12/1894",
                "place": "Fritsla, Älvsb. 1."
            },
            "education": [
                {
                    "degree": "Realex.",
                    "year": null,
                    "institution": "Gbgs hand :!inst."
                }
            ],
            "career": [
                {
                    "position": "Anst.",
                    "years": {
                        "start_year": 1912,
                        "end_year": 1918
                    },
                    "organization": "A-B Ch. Thorson i Fritsla"
                },
                {
                    "position": "verkst. dir.",
                    "years": {
                        "start_year": 1918,
                        "end_year": null
                    },
                    "organization": null
                }
            ],
            "family": {
                "spouse": "Stina Thörnqvist",
                "marriage_year": null,
                "children": [
                    {
                        "name": "Bengt",
                        "birth_year": "1923"
                    },
                    {
                        "name": "Karin",
                        "birth_year": "1931"
                    }
                ]
            },
            "hobbies": [
                "skytte",
                "fiske"
            ],
            "honorary_titles": [
                {
                    "title": "RVO",
                    "institution": "Älvsb. skytteförb.",
                    "year": null
                },
                {
                    "title": "ftjGM",
                    "institution": "Älvsb. landst:förb.",
                    "year": null
                },
                {
                    "title": "ftjSM",
                    "institution": "Svsfb",
                    "year": null
                },
                {
                    "title": "ftjSM",
                    "institution": "Sv:es brandkår",
                    "year": null
                }
            ]
        }
    }
}