{
    "original": "GOLDMAN, JULIUS, tandläkare,\nSimrishamn, f i Lund 13/1/12 av köpm\nMauritz G o Rakel Rubenstein.\n\nStud:ex Lund 33, med stud 33-36,\ntandl:-ex Sthlm 40, stud :resor Schweiz o Tyskl;\npriv :prakt Simrishamn sed 41.\nGift 40 m Esther Klotz f 17. - Barn: Siv\nf 42, Ulla f 44, Maj-Britt f 49.\n\nGOLDSTEIN, SAM, disponent,\nMalmö, f i Lund 9/12/04.\nStud:ex 26, tysk tandl:ex Frankfurt/M\n3$, eg företag 34-59, informationseh ab\nCortiec Malmö 59, försäljn:ch Morivit\nläkemedel ab sed 63’. - Styr :led Morivit\nl’äkemed’el ab, ab Borio. - Hobby: musik.\nGift 3i7( m Sonja Berman f O», dtr t dir\nJacob B o Anna Maria Estersson.\n-Barn: Anne-Marie o Barbro ff 39,\nAg-nete f 48.\n\nGORDON, ARON, ingenjör, Malmö,\nf i Malmö 18/7/23 av kantor Israel G o\nFanny Wulfson.\n\nIng:ex STI 44, patenting Gbgs patent- o\ning :byrå 47, byråing Mekoroth Water\nCo Ltd Tel-Aviv (staten Israels\nvattenverk) 50, avd :ch ab Servus Sthlm 5&lt;5(,\nförsäljn:ing ab O Göranssons\nmaskinaffär Södertälje 57, ab V Löwener\nSolna sed 61, dess repr f s Sv:e. - Hobbies:\nmusik, sport.\n\nGift 46 m Paula Altschuler f 23, dtr t\nköpm F A o h h (Köpenh). - Barn:\nDaniella f 51, Mona f 52, Fred-Allan\nf 60.\n\nGORTHON se GORTON\n\nGORTON, A BIRGER, direktör, Hbg,\nf i Hörby, Malmöh l, 17/10/08 av apot\nAnders Edvard G o Amelie Johnson,\nl:e v verkst dir Rederi ab Gylfe Hbg\nsed 58, styr :led där o Rederi ab Runa.\n\nGORTON, N GUNNAR, docent,\növerläkare, Lund, f i Lund 30/1/05 av apot\nAnders Edvard G o Amelie Johnson.\nMed lic Lund 36, med dr 53, doc i\ngynekologisk radioterapi Lund sed 58;\nolika läk:förordn 36-46, l:e underläk o\nbitr överläk gynekolog avd radiolog klin\nLunds las 46-57, överläk där sed 57.\n\n",
    "structured": {
        "0": {
            "full_name": "Julius Goldman",
            "location": "Simrishamn",
            "occupation": "tandläkare",
            "birth_details": {
                "date": "13/01/1912",
                "place": "Lund",
                "parents": "Mauritz G o Rakel Rubenstein"
            },
            "education": [
                {
                    "degree": "Stud:ex",
                    "year": "1933",
                    "institution": "Lund"
                },
                {
                    "degree": "med",
                    "year": "1933-1936",
                    "institution": "stud :resor Schweiz o Tyskl"
                },
                {
                    "degree": "tandl:-ex",
                    "year": "1940",
                    "institution": "Sthlm"
                }
            ],
            "career": [
                {
                    "position": "priv :prakt",
                    "years": {
                        "start_year": 1941
                    },
                    "organization": "Simrishamn"
                }
            ],
            "family": {
                "spouse": "Esther Klotz",
                "marriage_year": "1940",
                "children": [
                    {
                        "name": "Siv",
                        "birth_year": "1942"
                    },
                    {
                        "name": "Ulla",
                        "birth_year": "1944"
                    },
                    {
                        "name": "Maj-Britt",
                        "birth_year": "1949"
                    }
                ]
            }
        },
        "1": {
            "full_name": "Sam Goldstein",
            "location": "Malmö",
            "occupation": "disponent",
            "birth_details": {
                "date": "09/12/1904",
                "place": "Lund"
            },
            "education": [
                {
                    "degree": "Stud:ex",
                    "year": "1926",
                    "institution": "NA"
                },
                {
                    "degree": "tysk tandl:ex",
                    "year": "193$",
                    "institution": "Frankfurt/M"
                }
            ],
            "career": [
                {
                    "position": "eg företag",
                    "years": {
                        "start_year": 1934,
                        "end_year": 1959
                    }
                },
                {
                    "position": "informationseh ab",
                    "years": {
                        "start_year": 1959
                    },
                    "organization": "Cortiec Malmö"
                },
                {
                    "position": "försäljn:ch",
                    "years": {
                        "start_year": 1963
                    },
                    "organization": "Morivit läkemedel ab"
                }
            ],
            "family": {
                "spouse": "Sonja Berman",
                "marriage_year": "1937",
                "children": [
                    {
                        "name": "Anne-Marie",
                        "birth_year": "1939"
                    },
                    {
                        "name": "Barbro",
                        "birth_year": "1939"
                    },
                    {
                        "name": "Ag-nete",
                        "birth_year": "1948"
                    }
                ]
            },
            "hobbies": [
                "musik"
            ]
        },
        "2": {
            "full_name": "Aron Gordon",
            "location": "Malmö",
            "occupation": "ingenjör",
            "birth_details": {
                "date": "18/07/1923",
                "place": "Malmö",
                "parents": "kantor Israel G o Fanny Wulfson"
            },
            "education": [
                {
                    "degree": "Ing:ex",
                    "year": "1944",
                    "institution": "STI"
                }
            ],
            "career": [
                {
                    "position": "patenting",
                    "years": {
                        "start_year": 1947
                    },
                    "organization": "Gbgs patent- o ing :byrå"
                },
                {
                    "position": "byråing",
                    "years": {
                        "start_year": 1950
                    },
                    "organization": "Mekoroth Water Co Ltd Tel-Aviv"
                },
                {
                    "position": "avd :ch",
                    "years": {
                        "start_year": 1955
                    },
                    "organization": "ab Servus Sthlm"
                },
                {
                    "position": "försäljn:ing",
                    "years": {
                        "start_year": 1957
                    },
                    "organization": "ab O Göranssons maskinaffär Södertälje"
                },
                {
                    "position": "försäljn:ing",
                    "years": {
                        "start_year": 1961
                    },
                    "organization": "ab V Löwener Solna"
                }
            ],
            "family": {
                "spouse": "Paula Altschuler",
                "marriage_year": "1946",
                "children": [
                    {
                        "name": "Daniella",
                        "birth_year": "1951"
                    },
                    {
                        "name": "Mona",
                        "birth_year": "1952"
                    },
                    {
                        "name": "Fred-Allan",
                        "birth_year": "1960"
                    }
                ],
                "hobbies": [
                    "musik",
                    "sport"
                ]
            }
        },
        "3": {
            "full_name": "A Birger Gorton",
            "location": "Hbg",
            "occupation": "direktör",
            "birth_details": {
                "date": "17/10/1908",
                "place": "Hörby, Malmöh"
            },
            "family": {},
            "hobbies": [
                "musik"
            ]
        },
        "4": {
            "full_name": "N Gunnar Gorton",
            "location": "Lund",
            "occupation": "docent, överläkare",
            "birth_details": {
                "date": "30/01/1905",
                "place": "Lund",
                "parents": "apot Anders Edvard G o Amelie Johnson"
            },
            "education": [
                {
                    "degree": "Med lic",
                    "year": "1936",
                    "institution": "Lund"
                },
                {
                    "degree": "med dr",
                    "year": "1953",
                    "institution": "Lund"
                },
                {
                    "degree": "doc i gynekologisk radioterapi",
                    "year": "1958",
                    "institution": "Lund"
                }
            ],
            "career": [
                {
                    "position": "l:e underläk o bitr överläk gynekolog avd",
                    "years": {
                        "start_year": 1946,
                        "end_year": 1957
                    },
                    "organization": "radiolog klin Lunds las"
                },
                {
                    "position": "överläk",
                    "years": {
                        "start_year": 1957
                    },
                    "organization": "Lunds las"
                }
            ]
        }
    }
}