{
    "original": "GRILL, RUNE E B, fabrikör,\nKungsbacka, f i Kungsbacka 21/6/15 av fabr\nRobert G o Ester Wickman.\nRealex 3&lt;2, GbgHdlI 34, planenman\nGamlestaden fabr ab 34, Almedals fabr\nab 38, prokurist B &amp; R Grill ab 42,\ninneh sed 53. - Led DK 46-58, Stadsfullm\nsed 58. - Medl Rotary.\nGift 44 m Elsa Karlsson, dtr t köpm\nEdvin K o Augusta K. - Barn: Gunilla\nf 47, Anders f 49.\n\nGRIMMEISS, HERMANN G,\nprofessor,   Lund,   f   i   Hamburg   19/8/30   av\nGeorg G o Franziska März.\nDr Phil 57, vetensk medarb Philips\nZen-trallab Aachen 57-65, prof i fasta\ntillståndets fysik Tekn högsk (LTH) Lund\nsed 65. - Hobby: tennis.\nGift 56  m Hildegard Weizmann f 33,\ndtr t Philip W o Ottilia Stock. - Barn:\nBernd f 57, Daniela f 61.\n\nGRIMSBERG,   K   BÖRJE,   ingenjör,\n\nMalmö, f i Fuglie förs, Malmöh l,\n10/11/25 av Emil Nilsson o Edit\nPersson.\n\nIng:ex HTL Malmö 51,\narb:sDudieufc-bildn TGG 53’, konsult ing S Sv:es\nång-pannefören 54, utredn:ing Sueciaverken\nMalmö 57, försäljn:ing Rockwool ab\nMalmÖavd sed 59. - Utm: Sv scoutråd\nftjm. - Hobby: scouting.\nGift 52 m Marguerite Stevelius f 30, dtr\nt adv Rutger S o Gurli Hegardt. - Barn:\nMichael f 53, Veronica f 55, Håkan\nf 56, Camilla f 59, Rickard f 62.\n\nGRIP, B E HENRY, rektor, Hörby, f\ni Limhamn 26/5/25 av Henning G o\nEdith Andersson.\n\nFolkskollär:ex Lund 46, folkskollär\nÖr-kened 46, Lur 48’, Vollsjö 49, rekt\nLångaröd sed 60. - Led komm:fullm\nLångaröd 63, fullm o styr :ordf\nHörbyortens skolförb sed 64.\nGift 46 m Karin Simonsson, dtr t\nEdward S o Fredrika Johansson. - Barn:\nBjörn f 47, Eva f 50, Bengt f 52.\n\n",
    "structured": {
        "1": {
            "full_name": "RUNE E B GRILL",
            "location": "Kungsbacka",
            "occupation": "fabrikör",
            "birth_details": {
                "date": "21/06/1915",
                "place": "Kungsbacka",
                "parents": "fabr Robert G o Ester Wickman"
            },
            "education": [
                {
                    "degree": "Realex",
                    "year": "1932",
                    "institution": "GbgHdlI"
                }
            ],
            "career": [
                {
                    "position": "planenman Gamlestaden fabr ab",
                    "years": {
                        "start_year": 1934,
                        "end_year": 1934
                    }
                },
                {
                    "position": "Almedals fabr ab",
                    "years": {
                        "start_year": 1938,
                        "end_year": 1938
                    }
                },
                {
                    "position": "prokurist B & R Grill ab",
                    "years": {
                        "start_year": 1942,
                        "end_year": 1942
                    }
                }
            ],
            "family": {
                "spouse": "Elsa Karlsson",
                "marriage_year": "1944",
                "children": [
                    {
                        "name": "Gunilla",
                        "birth_year": "1947"
                    },
                    {
                        "name": "Anders",
                        "birth_year": "1949"
                    }
                ]
            },
            "community_involvement": {
                "role": "Led DK",
                "organization": "Stadsfullm",
                "years": "58-62"
            },
            "hobbies": [
                "Medl Rotary"
            ]
        },
        "2": {
            "full_name": "HERMANN G GRIMMEISS",
            "location": "Lund",
            "occupation": "professor",
            "birth_details": {
                "date": "19/08/1930",
                "place": "Hamburg",
                "parents": "Georg G o Franziska März"
            },
            "education": [
                {
                    "degree": "Dr Phil",
                    "year": "1957",
                    "institution": "vetensk medarb Philips Zentrallab Aachen"
                }
            ],
            "career": [
                {
                    "position": "prof i fasta tillståndets fysik Tekn högsk (LTH) Lund",
                    "years": {
                        "start_year": 1965,
                        "end_year": null
                    }
                }
            ],
            "family": {
                "spouse": "Hildegard Weizmann",
                "marriage_year": "1956",
                "children": [
                    {
                        "name": "Bernd",
                        "birth_year": "1957"
                    },
                    {
                        "name": "Daniela",
                        "birth_year": "1961"
                    }
                ]
            },
            "hobbies": [
                "tennis"
            ]
        },
        "3": {
            "full_name": "BÖRJE GRIMSBERG",
            "location": "Malmö",
            "occupation": "ingenjör",
            "birth_details": {
                "date": "10/11/1925",
                "place": "Fuglie förs, Malmöh l",
                "parents": "Emil Nilsson o Edit Persson"
            },
            "education": [
                {
                    "degree": "Ing:ex",
                    "year": "1951",
                    "institution": "HTL Malmö"
                }
            ],
            "career": [
                {
                    "position": "försäljn:ing Rockwool ab MalmÖavd",
                    "years": {
                        "start_year": 1959,
                        "end_year": null
                    }
                }
            ],
            "family": {
                "spouse": "Marguerite Stevelius",
                "marriage_year": "1952",
                "children": [
                    {
                        "name": "Michael",
                        "birth_year": "1953"
                    },
                    {
                        "name": "Veronica",
                        "birth_year": "1955"
                    },
                    {
                        "name": "Håkan",
                        "birth_year": "1956"
                    },
                    {
                        "name": "Camilla",
                        "birth_year": "1959"
                    },
                    {
                        "name": "Rickard",
                        "birth_year": "1962"
                    }
                ]
            },
            "community_involvement": {
                "role": "Utm: Sv scoutråd",
                "organization": "NULL",
                "years": "NULL"
            },
            "hobbies": [
                "scouting"
            ]
        },
        "4": {
            "full_name": "B E HENRY GRIP",
            "location": "Hörby",
            "occupation": "rektor",
            "birth_details": {
                "date": "26/05/1925",
                "place": "Limhamn",
                "parents": "Henning G o Edith Andersson"
            },
            "education": [
                {
                    "degree": "Folkskollär:ex",
                    "year": "1946",
                    "institution": "Lund"
                }
            ],
            "career": [
                {
                    "position": "rekt Långaröd",
                    "years": {
                        "start_year": 1960,
                        "end_year": null
                    }
                }
            ],
            "family": {
                "spouse": "Karin Simonsson",
                "marriage_year": "1946",
                "children": [
                    {
                        "name": "Björn",
                        "birth_year": "1947"
                    },
                    {
                        "name": "Eva",
                        "birth_year": "1950"
                    },
                    {
                        "name": "Bengt",
                        "birth_year": "1952"
                    }
                ]
            },
            "community_involvement": {
                "role": "Led komm:fullm",
                "organization": "Hörbyortens skolförb",
                "years": "63-64"
            },
            "hobbies": [
                "NULL"
            ]
        }
    }
}