{
    "original": "GERGE, G HENRY, agronom, Hbg,\nf 16/6/93 av godsäg Gustaf Persson o\nEmma Jönsson.\n\nAgr:ex Alnarp 16, ag o brukar Gyhults\ngård seds 23-. - Styr :ordf Hbgs nya sparbk\n54-63, led dir S:ta Maria sjh 51.\nGift 40 m Tora Zachrison, dtr t rekt\nArvid Z o Jane Röing. - Barn: Bengt\nf 41, Margareta f 43’, Anders o Torsten\nff 46.\n\nGERHAG, G RUDOLF, rektor,\nVärö-backa, f i Gällinge, Hall l, 17/12/07 av\nkomm :ordf Emanuel Johansson o Britta\nStina Andréasson.\n\nFolkskollär:ex Gbg 30, folkskollär\nHorred 30, Fagered 33, Värö 34,\ndistr:över-l’är 48, rekt o skolch Värö kn sed 58.\n-Huvudm Varbergs sparbk 56, ordf Värö\narb :kn 52, led intagn:ndiT hal Varberg\n56, rev Sv:es skolled:förb Hall:kr 63,\nstyr:led Fören Nordens Viskekt, sekr\nVärö RK-kr. - Landst:man 55, v ordf\nkomm:fullm 42, led komrn:nd 56!. - Utm:\nSRKftjM. - Hobbies: schack, bridge.\n\nGift 40 m Helfrid Carlson, dtr t Edward\nC o Frida Larsson.\n\nGERHARDSSON, BERTIL A G,\nläroverksadjunkt, Varberg, f i Reftele,\nJön-kpgs l, 1/1/33 av lantbr Gerhard\nAndersson o Ester Gustavsson.\nStud:ex Lund 53, fil mag 59, eo adj hal\nVarberg 59, adj i matem o fys där sed\n\n62.  - Löjtin 112 res.\n\nGift 63 m fil mag Inga Lind’ f 34, dtr t\nManne L o Alfhild Johansson.\n\nGERHARDSSON, BIRGER, professor,\n\nLund, f i Vännäs, Västerb l, 26/9/26 av\nhemm:äg Gerhard Abelsson o Edith\nSandström.\n\nStud:ex Upps 47, teol kand 52, teol lic\n56, stud Paris 57, teol dr Upps 61, doc\ni NT:s exegetik Upps univ 61-65, prof\ni exegetisk teologi Lunds univ sed 65.\n-Prästv 53, präst Luleå stift 53, Upps\närkestift 58; timlär Fjellstedtska sk 53-58,\n61-64. - Sekr Sv Jerusalemsfören 54-60,\nred :sekr Sv bibl uppsl :verk 2:a uppl 59-\n\n63.  - Medl NSS, LHS. - Kapt I 20 res.\n-Skr: The Good Samaritan — the Good\nShepherd?   (58),   Memory   and\nManuscript (drsavh 61), Tradition and\nTransmission (64), The Testing of God’s Son\n(66).\n\nGift 51 m Kerstin Eidolf f 30, dtr t\ntandtekn Karl E o Helga Sunesson.\n-Barn: Örjan f 54, Torbjörn f 58, Krister\nf 62.\n\n",
    "structured": {
        "0": {
            "full_name": "GERGE, G HENRY",
            "location": "Hbg",
            "occupation": "agronom",
            "birth_details": {
                "date": "16/06/1893",
                "place": "Hbg",
                "parents": "av godsäg Gustaf Persson o Emma Jönsson"
            },
            "education": [
                {
                    "degree": "Agr:ex Alnarp",
                    "year": "1916",
                    "institution": "NULL"
                }
            ],
            "career": [
                {
                    "position": "ag o brukar Gyhults gård",
                    "years": {
                        "start_year": 1923,
                        "end_year": null
                    },
                    "organization": "NULL"
                },
                {
                    "position": "ordf Hbgs nya sparbk",
                    "years": {
                        "start_year": 1954,
                        "end_year": 1963
                    },
                    "organization": "NULL"
                },
                {
                    "position": "led dir S:ta Maria sjh",
                    "years": {
                        "start_year": 1951,
                        "end_year": null
                    },
                    "organization": "NULL"
                }
            ],
            "family": {
                "spouse": "Tora Zachrison",
                "marriage_year": "1940",
                "children": [
                    {
                        "name": "Bengt",
                        "birth_year": "1941"
                    },
                    {
                        "name": "Margareta",
                        "birth_year": "1943"
                    },
                    {
                        "name": "Anders",
                        "birth_year": "1946"
                    },
                    {
                        "name": "Torsten",
                        "birth_year": "1946"
                    }
                ]
            }
        },
        "1": {
            "full_name": "GERHAG, G RUDOLF",
            "location": "Värö-backa",
            "occupation": "rektor",
            "birth_details": {
                "date": "17/12/1907",
                "place": "Gällinge, Hall l",
                "parents": "av komm :ordf Emanuel Johansson o Britta Stina Andréasson"
            },
            "education": [
                {
                    "degree": "Folkskollär:ex Gbg",
                    "year": "1930",
                    "institution": "NULL"
                }
            ],
            "career": [
                {
                    "position": "distr:över-l'är",
                    "years": {
                        "start_year": 1948,
                        "end_year": null
                    },
                    "organization": "NULL"
                },
                {
                    "position": "rekt o skolch Värö kn",
                    "years": {
                        "start_year": 1958,
                        "end_year": null
                    },
                    "organization": "NULL"
                }
            ],
            "family": {
                "spouse": "Helfrid Carlson",
                "marriage_year": "1940",
                "children": "NULL"
            },
            "hobbies": [
                "schack",
                "bridge"
            ]
        },
        "2": {
            "full_name": "GERHARDSSON, BERTIL A G",
            "location": "Varberg",
            "occupation": "läroverksadjunkt",
            "birth_details": {
                "date": "01/01/1933",
                "place": "Reftele, Jön-kpgs l",
                "parents": "av lantbr Gerhard Andersson o Ester Gustavsson"
            },
            "education": [
                {
                    "degree": "Stud:ex Lund",
                    "year": "1953",
                    "institution": "NULL"
                },
                {
                    "degree": "fil mag",
                    "year": "1959",
                    "institution": "NULL"
                }
            ],
            "career": [
                {
                    "position": "eo adj hal Varberg",
                    "years": {
                        "start_year": 1959,
                        "end_year": 1962
                    },
                    "organization": "NULL"
                }
            ],
            "family": {
                "spouse": "Inga Lind",
                "marriage_year": "1963",
                "children": "NULL"
            }
        },
        "3": {
            "full_name": "GERHARDSSON, BIRGER",
            "location": "Lund",
            "occupation": "professor",
            "birth_details": {
                "date": "26/09/1926",
                "place": "Vännäs, Västerb l",
                "parents": "av hemm:äg Gerhard Abelsson o Edith Sandström"
            },
            "education": [
                {
                    "degree": "Stud:ex Upps",
                    "year": "1947",
                    "institution": "NULL"
                },
                {
                    "degree": "teol kand",
                    "year": "1952",
                    "institution": "NULL"
                },
                {
                    "degree": "teol lic",
                    "year": "1956",
                    "institution": "NULL"
                },
                {
                    "degree": "teol dr Upps",
                    "year": "1961",
                    "institution": "NULL"
                }
            ],
            "career": [
                {
                    "position": "doc i NT:s exegetik Upps univ",
                    "years": {
                        "start_year": 1961,
                        "end_year": 1965
                    },
                    "organization": "NULL"
                },
                {
                    "position": "prof i exegetisk teologi Lunds univ",
                    "years": {
                        "start_year": 1965,
                        "end_year": null
                    },
                    "organization": "NULL"
                }
            ],
            "family": {
                "spouse": "Kerstin Eidolf",
                "marriage_year": "1951",
                "children": [
                    {
                        "name": "Örjan",
                        "birth_year": "1954"
                    },
                    {
                        "name": "Torbjörn",
                        "birth_year": "1958"
                    },
                    {
                        "name": "Krister",
                        "birth_year": "1962"
                    }
                ]
            },
            "publications": [
                {
                    "title": "The Good Samaritan — the Good Shepherd?",
                    "year": "1958",
                    "type": "NULL"
                },
                {
                    "title": "Memory and Manuscript",
                    "year": "1961",
                    "type": "drsavh"
                },
                {
                    "title": "Tradition and Transmission",
                    "year": "1964",
                    "type": "NULL"
                },
                {
                    "title": "The Testing of God’s Son",
                    "year": "1966",
                    "type": "NULL"
                }
            ]
        }
    }
}