{
    "original": "GUSTAFSSON,  BENGT  S  H,\nagronom, avdelningsdirektör, Lund, f i\nVis-sefjärda, Kalmar l,  10/10/30 av lantbr\nSture G o Berta Franzén.\nAgr:ex KLH 56, M Se Univ of Illinois\n64, Ph D-stud Purdue Univ 63-65; ass\nStat lantbr:byggn:försök  56-62,  avd:dir\ndär sed 65. - Skr i fackämn.\nGift 63 m Ewy Svensson f 33.\n\nGUSTAFSSON, D BERTIL,\nkyrkoherde, Oskarström, f i Solberga, Gbgs o\nBoh l, 17/12/16 av hemm:äg Niklas G o\nJosefina Johansson.\n\nStud:ex Gbg 35, teol kand Lund’ 42,\npasti:adj öl past 43i-49, kyrkoadj Nödinge\n49, Enslöv-Slättåkra 50, kyrkob\nOskarström sed 57. - Medl FrimO.\nGift 45 m Inger Ramnerö f 24, dtr t\nkyrkoh Sigfrid Eriksson o Beatrice\nAlmgren. - Barn: Staffan f 48, Irmelin f 51,\nMargareta f 55.\n\nGUSTAFSSON, H BERTIL,\nhovrättsassessor, Malmö, f i Motala 23/7/27.\nStud:ex Malmö 45, jur kand Lund 54,\ntingstjg Oxie o Skytts doms 55-57, fiskal\nSkånska hovr 59, assess där sed 65;\ntingssekr Östra o Medelsta doms 60-64.\n\nGUSTAFSSON, BRITTA A M,\ntandläkare, Staffanstorp, f i Bollnäs 18/12/32\nav las :läk Walter Sjöberg o gymn :dir\nGreta Lundh.\n\nStud:ex Bollnäs 51, tandl:ex Malmö 56,\ndistr:tandl (barntandv) Trelleborg 57,\nStaffanstorp 57-58, distr:tandl o förest\ndistr:tandpol Staffanstorp sed 5®. -\nHobbies: växter, djur.\n\nGift 36 m polism Per-Erik Gustafsson\nf 28. - Barn: Åke f 60, Hans f 65.\n\nGUSTAFSSON,  K  BÖRJE,  ingenjör,\n\nKristianstad,  f  i  Eskilstuna  8/5/19  av\nförrn Klaes G o Bertha Forsström.\nIng :ex Maskinfacksk Eskilstuna 40,\narb:-studiech Öberg &amp; Son Eskilstuna 46-53,\ntillv:ch Bongs fabr Kristianstad 53, ch\nrationaliser:avd Krist l f öretag :f ören sed\n58. - Hobby: foto.\n•Gift 46 m Iris Axelsson f 27, dtr t lant-\n\nbr Axel Karlsson o Valborg Oskarsson.\n\n- Barn: Jan f 49, Per f 53.\n\n",
    "structured": {
        "1": {
            "full_name": "Bengt S H Gustafsson",
            "location": "Lund",
            "occupation": "Agronom, Avdelningsdirektör",
            "birth_details": {
                "date": "10/10/1930",
                "place": "Vissefjärda, Kalmar l",
                "parents": "Sture G och Berta Franzén"
            },
            "education": [
                {
                    "degree": "Agr:ex",
                    "year": "1956",
                    "institution": "KLH"
                },
                {
                    "degree": "M Se",
                    "year": "1964",
                    "institution": "Univ of Illinois"
                },
                {
                    "degree": "Ph D-stud",
                    "year": "1963-1965",
                    "institution": "Purdue Univ"
                }
            ],
            "career": [
                {
                    "position": "Ass",
                    "years": {
                        "start_year": 1956,
                        "end_year": 1962
                    },
                    "organization": "Stat lantbr:byggn:försök"
                },
                {
                    "position": "Avd:dir",
                    "years": {
                        "start_year": 1965,
                        "end_year": null
                    },
                    "organization": "Stat lantbr:byggn:försök"
                }
            ],
            "family": {
                "spouse": "Ewy Svensson",
                "marriage_year": "1963",
                "children": []
            }
        },
        "2": {
            "full_name": "Bertil Gustafsson",
            "location": "Oskarström",
            "occupation": "Kyrkoherde",
            "birth_details": {
                "date": "17/12/1916",
                "place": "Solberga, Gbgs o Boh l",
                "parents": "Niklas G och Josefina Johansson"
            },
            "education": [
                {
                    "degree": "Stud:ex",
                    "year": "1935",
                    "institution": "Gbg"
                },
                {
                    "degree": "Teol kand",
                    "year": "1942",
                    "institution": "Lund"
                }
            ],
            "career": [
                {
                    "position": "Pasti:adj",
                    "years": {
                        "start_year": 1943,
                        "end_year": 1949
                    },
                    "organization": "Öl past"
                },
                {
                    "position": "Kyrkoadj",
                    "years": {
                        "start_year": 1949,
                        "end_year": 1957
                    },
                    "organization": "Nödinge"
                },
                {
                    "position": "Kyrkob",
                    "years": {
                        "start_year": 1957,
                        "end_year": null
                    },
                    "organization": "Oskarström"
                }
            ],
            "family": {
                "spouse": "Inger Ramnerö",
                "marriage_year": "1945",
                "children": [
                    {
                        "name": "Staffan",
                        "birth_year": "1948"
                    },
                    {
                        "name": "Irmelin",
                        "birth_year": "1951"
                    },
                    {
                        "name": "Margareta",
                        "birth_year": "1955"
                    }
                ]
            }
        },
        "3": {
            "full_name": "Bertil Gustafsson",
            "location": "Malmö",
            "occupation": "Hovrättsassessor",
            "birth_details": {
                "date": "23/7/1927",
                "place": "Motala"
            },
            "education": [
                {
                    "degree": "Stud:ex",
                    "year": "1945",
                    "institution": "Malmö"
                },
                {
                    "degree": "Jur kand",
                    "year": "1954",
                    "institution": "Lund"
                }
            ],
            "career": [
                {
                    "position": "Tingstjg",
                    "years": {
                        "start_year": 1955,
                        "end_year": 1957
                    },
                    "organization": "Oxie o Skytts doms"
                },
                {
                    "position": "Fiskal",
                    "years": {
                        "start_year": 1959,
                        "end_year": 1965
                    },
                    "organization": "Skånska hovr"
                },
                {
                    "position": "Assess",
                    "years": {
                        "start_year": 1965,
                        "end_year": null
                    },
                    "organization": "Skånska hovr"
                },
                {
                    "position": "Tingssekr",
                    "years": {
                        "start_year": 1960,
                        "end_year": 1964
                    },
                    "organization": "Östra o Medelsta doms"
                }
            ],
            "family": {
                "spouse": null,
                "marriage_year": null,
                "children": []
            }
        },
        "4": {
            "full_name": "Britta A M Gustafsson",
            "location": "Staffanstorp",
            "occupation": "Tandläkare",
            "birth_details": {
                "date": "18/12/1932",
                "place": "Bollnäs",
                "parents": "Walter Sjöberg och Greta Lundh"
            },
            "education": [
                {
                    "degree": "Stud:ex",
                    "year": "1951",
                    "institution": "Bollnäs"
                },
                {
                    "degree": "Tandl:ex",
                    "year": "1956",
                    "institution": "Malmö"
                }
            ],
            "career": [
                {
                    "position": "Distr:tandl",
                    "years": {
                        "start_year": 1957,
                        "end_year": 1958
                    },
                    "organization": "Trelleborg"
                },
                {
                    "position": "Distr:tandl o förest",
                    "years": {
                        "start_year": 1958,
                        "end_year": null
                    },
                    "organization": "Staffanstorp"
                }
            ],
            "family": {
                "spouse": "Per-Erik Gustafsson",
                "marriage_year": "1956",
                "children": [
                    {
                        "name": "Åke",
                        "birth_year": "1960"
                    },
                    {
                        "name": "Hans",
                        "birth_year": "1965"
                    }
                ]
            },
            "hobbies": [
                "växter",
                "djur"
            ]
        },
        "5": {
            "full_name": "Börje K Gustafsson",
            "location": "Kristianstad",
            "occupation": "Ingenjör",
            "birth_details": {
                "date": "8/5/1919",
                "place": "Eskilstuna",
                "parents": "Klaes G och Bertha Forsström"
            },
            "education": [
                {
                    "degree": "Ing:ex",
                    "year": "1940",
                    "institution": "Maskinfacksk Eskilstuna"
                }
            ],
            "career": [
                {
                    "position": "Arb:-studiech",
                    "years": {
                        "start_year": 1946,
                        "end_year": 1953
                    },
                    "organization": "Öberg & Son Eskilstuna"
                },
                {
                    "position": "Tillv:ch",
                    "years": {
                        "start_year": 1953,
                        "end_year": 1958
                    },
                    "organization": "Bongs fabr Kristianstad"
                }
            ],
            "family": {
                "spouse": "Iris Axelsson",
                "marriage_year": "1946",
                "children": [
                    {
                        "name": "Jan",
                        "birth_year": "1949"
                    },
                    {
                        "name": "Per",
                        "birth_year": "1953"
                    }
                ]
            },
            "hobbies": [
                "foto"
            ]
        }
    }
}