{
    "original": "Axel-Nilsson, Göran, fil. lic.,\nintendent, Göteborg, f. 16/9/07 i Lund av\nmuseiintend. Axel Nilsson o. Bertha\nElisabet Cavallin. G. 33 m. Ellen\nLundberg. Barn: Christian f. 34,\n\nLouise 38, Thomas 43. — Stud :ex. v.\nGbgs h. latin 27, fil. kand. i Lund 30,\nfil. lic. där 35 (konsthist., arkeol. o.\nfolkminnesforskn.). Aman. v. Sthlms\nstadsmus. 31, intend. v. Röhsska\nkonstslöjdmus. i Gbg sed. 46.\nSpec:-intressen: Skåne, allm. konst- o.\nkultur his t.\n\nAxell, Folke Adolf, civilingenjör,\nNorrköping, f. 4/12/08 i Ljusnarsberg,\nÖrebro 1. G. 36 m. Marianne\nHammarberg. Barn: Anita f. 37, Peter 42.\n\n—\tAvg:ex. fr. tekn. gymn. i Örebro\n28, civ:ing:ex. v. KTH 34. Ing:assist.\nv. telegr :v. i Nässjö 35, linjeing. v.\nte-legr :v. i Norrköp. sed. 46. Led. av Sv.\ntekn :fören. sed. 35.\n\nAxelson, Karl Axel Arne,\npraktiserande läkare, Alingsås, f. 30/3/05 i\nSthlm. av grosshandl. Julius A. o. Agda\nLundberg. G. 30 m. Lizi Hellborg.\nBarn: Ulf f. 32, Eva 38, Britt 41. —\nStud: ex. 23», med. kand. 26 o. med.\nlic. 30, allt i Sthlm. Stip. v,\nuniv:-sanat. i Rom sex mån. 33-34, stud:res.\nt. Ital., Grekl., Ungern S Tyskl. E.\no. aman. v. Seraf :las. o. Sabbatsb.\nsjukh. öronavd. 28, assist :läk. v.\nHörby las. 29, e. läk. v. Sophiahemmet 30,\nassist :läk. v. Sahlgr. isjukh. kir. avd.\nsex mån. 30-32, tf. e. läk. v.\nHälsingborgs las. kir. avd. samt tf. und :läk.\nv. Malmö allm. sjukh. 31, andre\nund:-läk. v. Mariestads las. 32-33, förste\ndito v. Alingsås las. 34-37, prakt. läk.\ni Ahngsås sed. 37.\n\nAxelsson, Bo Allan, tandläkare,\nGöteborg, f. 23/12/07 i Malmö av\ntrafik-ch. Axel Nilsson o. Emma Möller. G.\n38 m. operasång :an Elsa Ekendahl.\n\n—\tStud:ex. i Malmö 25, tandl :kand.\n27, tandläkare 30. Vik. i Varberg\n30-31, assist, i Borås 31, därefter praktik\nförst i Malmö o. numera i Gbg.\n\n",
    "structured": {
        "1": {
            "full_name": "Axel-Nilsson, Göran",
            "location": "Göteborg",
            "occupation": "intendent",
            "birth_details": {
                "date": "16/09/1907",
                "place": "Lund"
            },
            "education": [
                {
                    "degree": "filosofie kandidat",
                    "year": "1930",
                    "institution": "Lund"
                },
                {
                    "degree": "filosofie licentiat",
                    "year": "1935",
                    "institution": "Lund"
                }
            ],
            "career": [
                {
                    "position": "Amanuens",
                    "years": {
                        "start_year": 1931,
                        "end_year": 1931
                    },
                    "organization": "Sthlms stadsmus."
                },
                {
                    "position": "intendent",
                    "years": {
                        "start_year": 1946,
                        "end_year": null
                    },
                    "organization": "Röhsska konstslöjdmus. i Gbg"
                }
            ],
            "family": {
                "spouse": "Ellen Lundberg",
                "marriage_year": "1933",
                "children": [
                    {
                        "name": "Christian",
                        "birth_year": "1934"
                    },
                    {
                        "name": "Louise",
                        "birth_year": "1938"
                    },
                    {
                        "name": "Thomas",
                        "birth_year": "1943"
                    }
                ]
            }
        },
        "2": {
            "full_name": "Axell, Folke Adolf",
            "location": "Norrköping",
            "occupation": "civilingenjör",
            "birth_details": {
                "date": "04/12/1908",
                "place": "Ljusnarsberg, Örebro l"
            },
            "education": [
                {
                    "degree": null,
                    "year": "1928",
                    "institution": "tekn. gymn. i Örebro"
                },
                {
                    "degree": null,
                    "year": "1934",
                    "institution": "KTH"
                }
            ],
            "career": [
                {
                    "position": "Ing:assist.",
                    "years": {
                        "start_year": 1935,
                        "end_year": 1935
                    },
                    "organization": "telegr :v. i Nässjö"
                },
                {
                    "position": "Linjeing.",
                    "years": {
                        "start_year": 1946,
                        "end_year": null
                    },
                    "organization": "telegr :v. i Norrköp."
                }
            ],
            "family": {
                "spouse": "Marianne Hammarberg",
                "marriage_year": "1936",
                "children": [
                    {
                        "name": "Anita",
                        "birth_year": "1937"
                    },
                    {
                        "name": "Peter",
                        "birth_year": "1942"
                    }
                ]
            }
        },
        "3": {
            "full_name": "Axelson, Karl Axel Arne",
            "location": "Alingsås",
            "occupation": "praktiserande läkare",
            "birth_details": {
                "date": "30/03/1905",
                "place": "Sthlm"
            },
            "education": [
                {
                    "degree": "med. lic.",
                    "year": "1930",
                    "institution": "Sthlm"
                }
            ],
            "career": [
                {
                    "position": "Prakt. läk.",
                    "years": {
                        "start_year": 1937,
                        "end_year": null
                    },
                    "organization": "Alingsås"
                }
            ],
            "family": {
                "spouse": "Lizi Hellborg",
                "marriage_year": "1930",
                "children": [
                    {
                        "name": "Ulf",
                        "birth_year": "1932"
                    },
                    {
                        "name": "Eva",
                        "birth_year": "1938"
                    },
                    {
                        "name": "Britt",
                        "birth_year": "1941"
                    }
                ]
            }
        },
        "4": {
            "full_name": "Axelsson, Bo Allan",
            "location": "Göteborg",
            "occupation": "tandläkare",
            "birth_details": {
                "date": "23/12/1907",
                "place": "Malmö"
            },
            "education": [
                {
                    "degree": null,
                    "year": "1925",
                    "institution": "Malmö"
                },
                {
                    "degree": "tandläkare",
                    "year": "1930",
                    "institution": null
                }
            ],
            "career": [
                {
                    "position": null,
                    "years": {
                        "start_year": 1937,
                        "end_year": null
                    },
                    "organization": "Ahngsås"
                }
            ],
            "family": {
                "spouse": "Elsa Ekendahl",
                "marriage_year": "1938",
                "children": null
            }
        }
    }
}