{
    "original": "Ahlström, Alfred Rudolf, fd.\nstadsveterinär, Göteborg, f. 22/10/70 i Lund\nav Henrik A. o. Karin Ahlström. G.\n97 m. Nathalia Osberg. Barn: Giggi\nf. 98, Gustaf 00. — Stud:ex. i Lund\n89, veterinärex. i Sthlm 93, med. stud.\nv. Lunds univ. 97. Stud:res. t. Danm.,\nTyskl., USA m. fl. Priv:prakt.\nveterinär i Lund 93, stadsveterinär 04, dito\ni Gbg 10, num. pens. Led. av fiskexp\n:-ndn 16, ordf. 17-18, avd :chef i FHK\n18-19, v. oirdlf. i Gbgs: torg- o.\ns:aluhalls’-styr. 25, ordf. i Sydv. Sv:es\nveteri-närfören. 28-40, v. ordf. i Gbgs\ndjur-skyddsfören. 12-30, ordf. sed. 30, led.\nav styr. f. fören. De blindas vänner.\nRVO.\n\nvon Åhn, Bertil Elias, leg. läkare,\nLinköping, f. 25/5/12 i Boden av\nkyr-)koh. Jo^hanmes v. A. o. Tora\nFryk-hoilm. G. 42 m. Harriet Helfetröm.\nBarn: Marie-Louise f. 44, Cliristina\n45. — Res:off:ex. 35. Med. lic. i\nSthlm 44. Und :läk. v. las. i Linköp.\nfr. 47. Skr.: art. i Sv. Läk i-tidn.,\nbe-handi. tobaksrökens inv. på\nhjärtverk-samh. (45, 46, 47).\n\nvon Ahn, Rikard Paulus, leg.\ntandläkare, Borås, f. 3/10/19 av gros-sh.\nPaul G. v. A. o. Hildur Maria\nNils-•son. G. 46 m. Birgit Ingegärd\nAndersson. — Stud:ex. i Borås 39,\ntand-läk :ex, 44. Distr rtandläk. i Kinna\n44-45, praktik i Borås fr. 46.\n\nAhnlund, Stig, förste stadsläkare,\nKarlskrona, f. 22/6/08 i Kristianstad\nav tandl. Sigfrid A. o. Signe Nilsson.\nG. 38 m. Britt Heijbel. Barn: Greger\nf. 39, Bertil 42, Kerstin 44. —\nStud:-ex. i Kristianstad 26, med. kand. i\nLund 30 o. med. lic. där 36. Tjg. v.\npsyk. klin. o. med. klin. i Lund,\nJön-köp. las.. Nynäs kuranst., Are\nfjäll-kuranst., Jämtl. 1. centr:sanat. o.\nKarlskrona las., stadsläk. i Karlskrona\nsed. 45.\n\n",
    "structured": {
        "0": {
            "full_name": "Alfred Rudolf Ahlström",
            "location": "Göteborg",
            "occupation": "fd. stadsveterinär",
            "birth_details": {
                "date": "22/10/1870",
                "place": "Lund",
                "parents": "Henrik A. o. Karin Ahlström"
            },
            "education": [
                {
                    "degree": "Stud",
                    "year": "1889",
                    "institution": "Lund"
                },
                {
                    "degree": "veterinärex.",
                    "year": "1893",
                    "institution": "Sthlm"
                },
                {
                    "degree": "med. stud.",
                    "year": "1897",
                    "institution": "Lunds univ."
                }
            ],
            "career": [
                {
                    "position": "Priv:prakt. veterinär",
                    "years": {
                        "start_year": 1893,
                        "end_year": 1893
                    },
                    "organization": "Lund"
                },
                {
                    "position": "stadsveterinär",
                    "years": {
                        "start_year": 1904,
                        "end_year": null
                    },
                    "organization": null
                },
                {
                    "position": "Led. av fiskexp:-ndn",
                    "years": {
                        "start_year": 1916,
                        "end_year": null
                    },
                    "organization": null
                }
            ],
            "family": {
                "spouse": "Nathalia Osberg",
                "marriage_year": "1897",
                "children": [
                    {
                        "name": "Giggi",
                        "birth_year": "1898"
                    },
                    {
                        "name": "Gustaf",
                        "birth_year": "1900"
                    }
                ]
            }
        },
        "1": {
            "full_name": "Bertil Elias von Åhn",
            "location": "Linköping",
            "occupation": "leg. läkare",
            "birth_details": {
                "date": "25/05/1912",
                "place": "Boden",
                "parents": "kyr-)koh. Jo^hanmes v. A. o. Tora Fryk-hoilm"
            },
            "education": [
                {
                    "degree": "Res:off:ex.",
                    "year": "1935",
                    "institution": null
                },
                {
                    "degree": "Med. lic.",
                    "year": "1944",
                    "institution": "Sthlm"
                }
            ],
            "career": [
                {
                    "position": "Und :läk.",
                    "years": {
                        "start_year": 1947,
                        "end_year": null
                    },
                    "organization": "las. i Linköp."
                }
            ],
            "family": {
                "spouse": "Harriet Helfetröm",
                "marriage_year": "1942",
                "children": [
                    {
                        "name": "Marie-Louise",
                        "birth_year": "1944"
                    },
                    {
                        "name": "Cliristina",
                        "birth_year": "1945"
                    }
                ]
            }
        },
        "2": {
            "full_name": "Rikard Paulus von Ahn",
            "location": "Borås",
            "occupation": "leg. tandläkare",
            "birth_details": {
                "date": "3/10/1919",
                "place": null,
                "parents": "gros-sh. Paul G. v. A. o. Hildur Maria Nils-•son"
            },
            "education": [
                {
                    "degree": "Stud:ex.",
                    "year": "1939",
                    "institution": "Borås"
                },
                {
                    "degree": "tand-läk :ex",
                    "year": "1944",
                    "institution": null
                }
            ],
            "career": [
                {
                    "position": "Distr rtandläk.",
                    "years": {
                        "start_year": 1944,
                        "end_year": 1945
                    },
                    "organization": "Kinna"
                },
                {
                    "position": "praktik i Borås",
                    "years": {
                        "start_year": 1946,
                        "end_year": null
                    },
                    "organization": null
                }
            ],
            "family": {
                "spouse": "Birgit Ingegärd Andersson",
                "marriage_year": "1946",
                "children": []
            }
        },
        "3": {
            "full_name": "Stig Ahnlund",
            "location": "Karlskrona",
            "occupation": "förste stadsläkare",
            "birth_details": {
                "date": "22/06/1908",
                "place": "Kristianstad",
                "parents": "tandl. Sigfrid A. o. Signe Nilsson"
            },
            "education": [
                {
                    "degree": "Stud:-ex.",
                    "year": "1926",
                    "institution": "Kristianstad"
                },
                {
                    "degree": "med. kand.",
                    "year": "1930",
                    "institution": "Lund"
                },
                {
                    "degree": "med. lic.",
                    "year": "1936",
                    "institution": "Lund"
                }
            ],
            "career": [
                {
                    "position": "stadsläk.",
                    "years": {
                        "start_year": 1945,
                        "end_year": null
                    },
                    "organization": "Karlskrona"
                }
            ],
            "family": {
                "spouse": "Britt Heijbel",
                "marriage_year": "1938",
                "children": [
                    {
                        "name": "Greger",
                        "birth_year": "1939"
                    },
                    {
                        "name": "Bertil",
                        "birth_year": "1942"
                    },
                    {
                        "name": "Kerstin",
                        "birth_year": "1944"
                    }
                ]
            }
        }
    }
}