{
    "original": "Appelgren, Oilof Hugo,\nprov|insialläkare, Lilla Edet, f. 27/11/97 i\nSkepp-landa, Älvsb. 1., av Frans Adolf A. o.\nMagda Elisabeth Holmberg. —\nStud:-ex. i Gbg 16, med. kand. i Sthlm 20,\nmed. lic. där 26. E. läk. i By distr.\nkortare tider 22-24, i Alfta distr. tills,\nfem mån. 22-23, tf. stadsläk. i Hjo\n24-25, assist :läk., tf. und:läk. samt e. läk.\nv. Mariestads las. 27, tf. e. prov:läk. i\nLilla Edets distr. 27-30, e. prov :läk.\ndär 30-38, prov :läk. där sed. 38, tf.\nund :läk. v. Svenshögens sanat. två\nmån. 32, läk. v. tuberk:sjukstugan i\nLilla Edet s^ed. 32. Bat :(läk. i Fik res.\nsed. 45. Led. av Lilla Edets hälisovrnd\n.s’ed. 28, ordf. där 28-38, led. av munic\n:-fulilm. sed. 30, ordf. 33-38, led. av\nmu-ndc md, av Fuxerna s :ns komm:fullm.,\niS’kol;S’tyr., fattigv nstyr. o. barnav md.\n\nHuv:man i Lilla Edets isparb. sed. 32,\nv. ordf. i bank. ,styr. ;sed. 33.\n\nAppelquist, Emil Sigurd William,\ndirektör, Visby, f. 10/1/19 i Silte, Gotl.\n1., av dir. Emil A. o. Elli Andersson.\nG. 41 m. Maud von Koch. Barn:\nChrister f. 42, Claes-Göran 43,\nLars-Ove 46. — Stud:ex. i Visby 38,\nPåhl-mans hand :inst. i Sthlm 40. Res :off.\ni flygv. 43, löjtn. i flygv. 45. Chef f.\nFirma Emil Appelquist i Visby sed.\n\n42.\n\nAppeltofft, Ellen Gunhild,\nläroverksadjunkt, Nässjö, f. 12/12/00 i\nHalmstad. — Studiex. 21, fil. kand.\n25 o. fil. mag. 26, allt i Lund, provår\nv. Norra latin i Sthlm 30. E. o. lär.\ni Halmstad 27 o. 29, Katrineholm o.\nStrömsnäsbruk 29, Västerås o.\nHalmstad 31, h. lär :nesemin. i Sthlm 31-32,\nBorås 32-37, ord. ämneslär. i\nStröms-näsbruk 37, adj. i tyska o. eng. v.\nNässjö sämre als k. sed. 46. Resor t.\nEngl. 25, Tyskl. 34.\n\nAppeltofft, Gösta Alvar, major,\nSkövde, f. 4/7/96 i Gbg av Gustaf A.\no. Johanna von Heland. G. 1. 29 m.\nElfriede B^urg, d. 39; 2. 41 m. Birgitta\nBergsten. Barn: Lillemor f. 30,\nSolveig 31, Carl-Gustav 36, Gösta 37,\nCatharina 45. — Stud:ex. i Gbg 16,\nskjutsk., mil iförvaltn :kurs, bilkurs.\nFänrik i trängens res. 18, undilöjtn.\n20, löjtn. 23, kapt. 33, major 40.\nReg:-kvartermäst. v. T.2 30, chef f. träng,\noff :asp :komp. o. off:asp:sk. 37-38,\nbyråch. v. Arméförv. sjukvistyr. 42-\n\n43,\tstabschef v. T.2 44. RSO.\n",
    "structured": {
        "1": {
            "full_name": "Appelgren, Oilof Hugo",
            "location": "Lilla Edet",
            "occupation": "Provinsialläkare",
            "birth_details": {
                "date": "27/11/1897",
                "place": "Skepp-landa, Älvsb",
                "parents": "Frans Adolf A. o. Magda Elisabeth Holmberg"
            },
            "education": [
                {
                    "degree": "Stud:-ex.",
                    "year": "1916",
                    "institution": "Göteborg"
                },
                {
                    "degree": "med. kand.",
                    "year": "1920",
                    "institution": "Stockholm"
                },
                {
                    "degree": "med. lic.",
                    "year": "1926",
                    "institution": "Stockholm"
                }
            ],
            "career": [
                {
                    "position": "E. läk.",
                    "years": {
                        "start_year": 1922,
                        "end_year": 1924
                    },
                    "organization": "By distr."
                },
                {
                    "position": "tf. stadsläk.",
                    "years": {
                        "start_year": 1924,
                        "end_year": 1925
                    },
                    "organization": "Hjo"
                },
                {
                    "position": "assist :läk.",
                    "years": {
                        "start_year": 1927,
                        "end_year": 1927
                    },
                    "organization": "Mariestads las."
                },
                {
                    "position": "e. prov:läk.",
                    "years": {
                        "start_year": 1930,
                        "end_year": 1938
                    },
                    "organization": "Lilla Edets distr."
                },
                {
                    "position": "prov :läk.",
                    "years": {
                        "start_year": 1938
                    },
                    "organization": "Lilla Edet"
                }
            ],
            "family": {
                "spouse": "NULL",
                "marriage_year": "NULL",
                "children": []
            }
        },
        "2": {
            "full_name": "Appelquist, Emil Sigurd William",
            "location": "Visby",
            "occupation": "Direktör",
            "birth_details": {
                "date": "10/01/1919",
                "place": "Silte, Gotland"
            },
            "education": [
                {
                    "degree": "Stud:ex.",
                    "year": "1938",
                    "institution": "Visby"
                },
                {
                    "degree": "Påhl-mans hand :inst.",
                    "year": "1940",
                    "institution": "Stockholm"
                }
            ],
            "career": [
                {
                    "position": "Res :off.",
                    "years": {
                        "start_year": 1943
                    },
                    "organization": "flygv."
                },
                {
                    "position": "löjtn.",
                    "years": {
                        "start_year": 1945
                    },
                    "organization": "flygv."
                },
                {
                    "position": "Chef",
                    "years": {
                        "start_year": 1942
                    },
                    "organization": "Firma Emil Appelquist i Visby"
                }
            ],
            "family": {
                "spouse": "Maud von Koch",
                "marriage_year": "1941",
                "children": [
                    {
                        "name": "Christer",
                        "birth_year": "1942"
                    },
                    {
                        "name": "Claes-Göran",
                        "birth_year": "1943"
                    },
                    {
                        "name": "Lars-Ove",
                        "birth_year": "1946"
                    }
                ]
            }
        },
        "3": {
            "full_name": "Appeltofft, Ellen Gunhild",
            "location": "Nässjö",
            "occupation": "Läroverksadjunkt",
            "birth_details": {
                "date": "12/12/1900",
                "place": "Halmstad"
            },
            "education": [
                {
                    "degree": "Studiex.",
                    "year": "1921",
                    "institution": "Lund"
                },
                {
                    "degree": "fil. kand.",
                    "year": "1925",
                    "institution": "Lund"
                },
                {
                    "degree": "fil. mag.",
                    "year": "1926",
                    "institution": "Lund"
                }
            ],
            "career": [
                {
                    "position": "E. o. lär.",
                    "years": {
                        "start_year": 1927
                    },
                    "organization": "Halmstad"
                },
                {
                    "position": "h. lär :nesemin.",
                    "years": {
                        "start_year": 1931,
                        "end_year": 1932
                    },
                    "organization": "Sthlm"
                },
                {
                    "position": "adj.",
                    "years": {
                        "start_year": 1946
                    },
                    "organization": "Nässjö sämre als k."
                }
            ],
            "family": {
                "spouse": "NULL",
                "marriage_year": "NULL",
                "children": []
            }
        },
        "4": {
            "full_name": "Appeltofft, Gösta Alvar",
            "location": "Skövde",
            "occupation": "Major",
            "birth_details": {
                "date": "04/07/1896",
                "place": "Göteborg"
            },
            "education": [
                {
                    "degree": "Stud:ex.",
                    "year": "1916",
                    "institution": "Göteborg"
                }
            ],
            "career": [
                {
                    "position": "Fänrik",
                    "years": {
                        "start_year": 1918
                    },
                    "organization": "trängens res."
                },
                {
                    "position": "undilöjtn.",
                    "years": {
                        "start_year": 1920
                    }
                },
                {
                    "position": "löjtn.",
                    "years": {
                        "start_year": 1923
                    }
                },
                {
                    "position": "kapt.",
                    "years": {
                        "start_year": 1933
                    }
                },
                {
                    "position": "major",
                    "years": {
                        "start_year": 1940
                    }
                }
            ],
            "family": {
                "spouse": "Elfriede B^urg (d. 1939); Birgitta Bergsten",
                "marriage_year": "1929; 1941",
                "children": [
                    {
                        "name": "Lillemor",
                        "birth_year": "1930"
                    },
                    {
                        "name": "Solveig",
                        "birth_year": "1931"
                    },
                    {
                        "name": "Carl-Gustav",
                        "birth_year": "1936"
                    },
                    {
                        "name": "Gösta",
                        "birth_year": "1937"
                    },
                    {
                        "name": "Catharina",
                        "birth_year": "1945"
                    }
                ]
            }
        }
    }
}