{
    "original": "Alverman, Signe Maria,\nläroverksadjunkt, Linköping, f. 2/1/00 i\nKarlshamn av kond. C. J. Andersson o.\nHanna Jonsson. Stud:ex. i Lund 19,\nfil. mag. där 24, pro vår 31-32. Vik.\nämneslär. i Sundbyberg 24, vik. adj.\ni 0’skarshamn 25, vik. ämneslär. i\nLjungby 26, Västanfors 26-27, e. o.\nämneslär. i Älmhult 27-31, Eslöv 32-33,\nord. ämneslär. i Älmhult 33, adj. i\nmodersm. o. hist. m, samh :lära v.\nLin-köp. h. a. 1. sed. 40. Resor: Tyskl.\n26, 28 o. 30, Österr. o. Ital. 36, Holl.,\nBelg. o. Frankr. 38, Engl. 39.\n\nAlveskog, Verner Ernst Tage,\nkyrkoherde, Äsenhöga, f. 27/7/95 i Nye,\nJönköp. 1., av hemm:äg. Ernst\nAn-densson o. Matilda Skoglund. G. 28 m.\nilär:an Vadiborg Gustafsson. Barn: Olof\nf. 30, Lars 32, Gunneil 33. — Stud:ex..v.\nFjiellstedtiska isk. i Upps. 17, teok fiil.\nex. i upps. 19, teol. kand., praikt. teo’1.\nprov samt prästv. f. Växjö stift 23,\nstud. v. evang.-teol. fakult. v. univ.\ni Tübingen 21-22. Assist, v. ’SV.\n|sjömanskyrkan i Antv^^erpen. 21, v.\nkom-min. i Svenarum 23, kommin. i\nSten-berga 23-25, i Skede 25-30, kyrkoh. i\nÄsenhöga o. Källeryd sed. 30. Ordf.\ni kyrkoistämma, past:stämma,\nkomm:-fullm., skolstyr., barnav:nd,\nkyrko-bokf :insp. i Växjö stifts L insp :omr.\nsed. 46, ordf. i Jönköp. läns\nträdgårds-odlarförb., insp. f. Åsenhöga o.\nMa-rieholm-sbruks föreläsn :f ören.\n\nAlvin, Erik Gustaf Marcus,\nmusikdirektör, Vänersborg, f. 6/5/02 i\nNorrköp. av Karl A. o. Hilda Öhrström.\nG. 39 m. Inga Sahlin. — Stud:ex. i\nNorrköp. 20, org:ex. 23, musiklär:- o.\nkyrkosångarex. 28 v. mu.sikhö’gsk.\nStud:resa t. Frankr. 26. — Musiklär.\n\nv. Vänersk h. a. 1. sed. 32. Org. o.\nkantor v. Vänersb. kyrka ’sed. s. å.\nTimlär. v. komm. flicksk. sed. 32.\nDi-rig. v. Vänersb. orkifören. sed. 44, v.\nsångsällsk. Sjung, sjung sed. 33,\nförste förb :dirig. v. Dalsl. sång:förb. sed.\n33. Komp. kantat., manskvart.,\nromanser m. m. Hobbies: tennis, segl.\nP. A. Bergs jeton i orgelspel 23, Mus.\nak. jeton i komp. 24, Dalsl. sångiförb.\nftjGM 33, Sv. sångiförb. ftjGM 38.\n\n",
    "structured": {
        "0": {
            "full_name": "Signe Maria Alverman",
            "location": "Linköping",
            "occupation": "lärare",
            "birth_details": {
                "date": "02/01/1900",
                "place": "Karlshamn",
                "parents": "C. J. Andersson and Hanna Jonsson"
            },
            "education": [
                {
                    "degree": "Stud:ex.",
                    "year": "1919",
                    "institution": "Lund"
                },
                {
                    "degree": "fil. mag.",
                    "year": "1924",
                    "institution": "Lund"
                }
            ],
            "career": [
                {
                    "position": "vik. ämneslär.",
                    "years": {
                        "start_year": 1924,
                        "end_year": 1925
                    },
                    "organization": "Sundbyberg"
                },
                {
                    "position": "vik. adj.",
                    "years": {
                        "start_year": 1925,
                        "end_year": 1925
                    },
                    "organization": "0’skarshamn"
                },
                {
                    "position": "e. o. ämneslär.",
                    "years": {
                        "start_year": 1926,
                        "end_year": 1927
                    },
                    "organization": "Västanfors"
                },
                {
                    "position": "ord. ämneslär.",
                    "years": {
                        "start_year": 1933,
                        "end_year": null
                    },
                    "organization": "Älmhult"
                },
                {
                    "position": "adj.",
                    "years": {
                        "start_year": 1940,
                        "end_year": null
                    },
                    "organization": "Lin-köp"
                }
            ],
            "family": {
                "spouse": null,
                "marriage_year": null,
                "children": []
            }
        },
        "1": {
            "full_name": "Verner Ernst Tage Alveskog",
            "location": "Äsenhöga",
            "occupation": "kyrkoherde",
            "birth_details": {
                "date": "27/07/1895",
                "place": "Nye, Jönköp.",
                "parents": "Ernst Andensson and Matilda Skoglund"
            },
            "education": [
                {
                    "degree": "Stud:ex..v.",
                    "year": "1917",
                    "institution": "Fjiellstedtiska isk. i Upps."
                },
                {
                    "degree": "teok fiil. ex.",
                    "year": "1919",
                    "institution": "upps."
                }
            ],
            "career": [
                {
                    "position": "v. kommin.",
                    "years": {
                        "start_year": 1923,
                        "end_year": 1923
                    },
                    "organization": "Svenarum"
                },
                {
                    "position": "kommin.",
                    "years": {
                        "start_year": 1923,
                        "end_year": 1925
                    },
                    "organization": "Sten-berga"
                },
                {
                    "position": "kyrkoh.",
                    "years": {
                        "start_year": 1930,
                        "end_year": null
                    },
                    "organization": "Äsenhöga"
                }
            ],
            "family": {
                "spouse": "Ilär:an Vadiborg Gustafsson",
                "marriage_year": "1928",
                "children": [
                    {
                        "name": "Olof",
                        "birth_year": "1930"
                    },
                    {
                        "name": "Lars",
                        "birth_year": "1932"
                    },
                    {
                        "name": "Gunneil",
                        "birth_year": "1933"
                    }
                ]
            }
        },
        "2": {
            "full_name": "Erik Gustaf Marcus Alvin",
            "location": "Vänersborg",
            "occupation": "musikdirektör",
            "birth_details": {
                "date": "06/05/1902",
                "place": "Norrköp.",
                "parents": "Karl A. and Hilda Öhrström"
            },
            "education": [
                {
                    "degree": "Stud:ex.",
                    "year": "1920",
                    "institution": "Norrköp."
                },
                {
                    "degree": "org:ex.",
                    "year": "1923",
                    "institution": null
                },
                {
                    "degree": "musiklär:- o. kyrkosångarex.",
                    "year": "1928",
                    "institution": "musikhö’gsk"
                }
            ],
            "career": [
                {
                    "position": "Musiklär.",
                    "years": {
                        "start_year": 1932,
                        "end_year": null
                    },
                    "organization": "Vänersk h. a."
                },
                {
                    "position": "Org. o. kantor",
                    "years": {
                        "start_year": "s.å.",
                        "end_year": null
                    },
                    "organization": "Vänersb. kyrka"
                },
                {
                    "position": "Timlär.",
                    "years": {
                        "start_year": 1932,
                        "end_year": null
                    },
                    "organization": "komm. flicksk."
                },
                {
                    "position": "Dirig.",
                    "years": {
                        "start_year": 1944,
                        "end_year": null
                    },
                    "organization": "Vänersb. orkifören."
                }
            ],
            "family": {
                "spouse": "Inga Sahlin",
                "marriage_year": "1939",
                "children": []
            },
            "hobbies": [
                "tennis",
                "segling"
            ],
            "publications": [
                {
                    "title": null,
                    "year": "1924",
                    "type": null
                },
                {
                    "title": null,
                    "year": "1923",
                    "type": null
                },
                {
                    "title": null,
                    "year": null,
                    "type": null
                }
            ]
        }
    }
}