{
    "original": "Reuterswärd, Carolina Elisabeth\nChristina (Stina), hovfröken, Sthlm, f.\ni Örebro av översten Wilhelm R. o,\nCarolina af Robson. Hovfröken h.\nkronpr :an Margareta 14n20, h. prins :an\nIngrid 20-23 o. h. kronpr :an Louise sed.\n23. GVrsJmt, OffAbessSabaO.\nReuterswärd, Fritz Emanuel,\ndirektör, Sthlm, f. 15/12/78 i öster Korsberga\nförs., Jönköp. 1. Verkst, dir. i Konst\nA-B Färg o. Form, Sthlm.\nReuterswärd, Gustaf Fredrik\nAcha-tes, verkst, direktör, major, Sthlm, f.\n31/8/82 i Örebro av överste Wilh. R. o.\nCarolina Robson. G. 13 m. Elin Lamm.\nBarn: Pontus Bertil Olov f. 14, löjtn.:\nMargareta f. 17; Maud f. 20, g. m.\nkonstnär A. Rossander. Und:löjtn. v.\nGöta art:reg. 03, Art:- o. ing:högsk.,\nKrigshögsk., löjtn. v. gen:stab. 12,\nkapten 15, major 32. Lär. v. Art:- o.\ning:-högsk. 16-19, flerår. militär medarb, i\nSthlms Dagbl., huv :red. 19, verkst, dir.\nv. Tidn. Telegr :byrå A-B sed. 22, i A-B\nRadiotjänst 24-35, styr :led. där sed. 26,\nmedl. av statens inform :styr. 40.\nKVO-2kl, RSO, RNO, KDD02gr, KFinlVRO.\nReuterswärd, Gustaf Pontus, kapten,\nSthlm, f. 18/9/10 i Linköping av\ngen:-löjtn. Pontus R. o. Eva Uggla. G. 37\nm. grev :an Ebba Margaretha De la\nGardie, Barn: Charlotte f. 38, Pontus\nf. 43. Stud :ex. i Skövde 28. Off :ex. v.\nKrigssk. 31, AIHSak 32-34 samt h.\nfor-tifik :kurs 34-36, signalk. v. Fälttelegr\n:-kår. 33, SS 41. Fänr. v. Fortif. 31, löjtn.\nv. Ing:trupp. 37, kapten 40. Plac. v.\nBodens ing:kår. 31-36, v. Svea ing:kår.\nsed. 36, lär. v. Ing :trupp :s off :aspir :sk.\no. studentkomp. 36-38, repetitör 38-40\nsamt sed. 42 lär. v. AIHS. Kadettoff.\n’v. Krigssk. 40-42. Lär. v. pionjärkurs\n41. Lär. v. KHS sed. 42. Tjg. v.\nFörsvarsstaben sed. 42. Led. av 41 års\nvarnkomm. Sekr. i Östermalms\nluft-skyddsf ören. 37-40. Stud :resa på\nuppdrag av Riksluftskyddsförb. t. Tyskl.,\nSchweiz o. Tjeckoslov. 38. Styr :led. i\nFortif :klubb. sed. 45. RLSFGförtj :t.\nReuterswärd, Nils Gösta,\nträdgårdsarkitekt, Sthlm, f. 1/4/92 i Sthlm. G.\n27 m. konstn :an Märtha Hjortzberg.\nBarn: Måns f. 32. Realex., 2 års stud.\nv. Adelsnäs Trädgårdsskola, Teknolog.\nInst. i Köpenh., 2-årig statsstip. f.\nstudier i Danm., Frankr., Engl. o. Tyskl.\nTrädgårdsarkit. v. Kgl. Järnvägsstyr.,\nSthlm, sed. 38, prakt, trädgårdsarkit. i\nSthlm. Skr.: Blomstergårdens rika\nmöjligheter (25), Nulle Nalleson, Sagan\nom en pojke o. björn (44). 1. pris o.\nliederspris f. ritn. v. trädgårdsutst. i\nUmeå 44.\n",
    "structured": {
        "1": {
            "full_name": "Reuterswärd, Carolina Elisabeth Christina (Stina)",
            "location": "Stockholm",
            "occupation": "Hovfröken",
            "birth_details": {
                "date": "Örebro",
                "place": "Örebro",
                "place_coordinates": {
                    "Latitude": 59.2752626,
                    "Longitude": 15.2134105
                }
            },
            "education": null,
            "career": null,
            "family": {
                "spouse": null,
                "marriage_year": null,
                "children": []
            },
            "location_coordinates": {
                "Latitude": 59.32932349999999,
                "Longitude": 18.0685808
            }
        },
        "2": {
            "full_name": "Reuterswärd, Fritz Emanuel",
            "location": "Stockholm",
            "occupation": "Direktör",
            "birth_details": {
                "date": "15/12/1878",
                "place": "Öster Korsberga förs., Jönköp.",
                "place_coordinates": {
                    "Latitude": 57.3,
                    "Longitude": 15.116667
                }
            },
            "education": null,
            "career": [
                {
                    "position": "Verkst, dir. i Konst A-B Färg o. Form, Sthlm.",
                    "years": {
                        "start_year": 0,
                        "end_year": 0
                    },
                    "organization": null
                }
            ],
            "family": {
                "spouse": null,
                "marriage_year": null,
                "children": []
            },
            "location_coordinates": {
                "Latitude": 59.32932349999999,
                "Longitude": 18.0685808
            }
        },
        "3": {
            "full_name": "Reuterswärd, Gustaf Fredrik Acha-tes",
            "location": "Stockholm",
            "occupation": "Verkst, direktör, major",
            "birth_details": {
                "date": "31/8/1882",
                "place": "Örebro",
                "place_coordinates": {
                    "Latitude": 59.2752626,
                    "Longitude": 15.2134105
                }
            },
            "education": null,
            "career": [
                {
                    "position": "Und:löjtn. v. Göta art:reg. 03",
                    "years": {
                        "start_year": 1903,
                        "end_year": 0
                    },
                    "organization": null
                }
            ],
            "family": {
                "spouse": "Elin Lamm",
                "marriage_year": "13",
                "children": [
                    {
                        "name": "Pontus Bertil Olov",
                        "birth_year": "14"
                    },
                    {
                        "name": "Margareta",
                        "birth_year": "17"
                    },
                    {
                        "name": "Maud",
                        "birth_year": "20"
                    }
                ]
            },
            "location_coordinates": {
                "Latitude": 59.32932349999999,
                "Longitude": 18.0685808
            }
        },
        "4": {
            "full_name": "Reuterswärd, Gustaf Pontus",
            "location": "Stockholm",
            "occupation": "Kapten",
            "birth_details": {
                "date": "18/9/1910",
                "place": "Linköping",
                "place_coordinates": {
                    "Latitude": 58.41080700000001,
                    "Longitude": 15.6213727
                }
            },
            "education": [
                {
                    "degree": "Stud :ex. i Skövde",
                    "year": "1928",
                    "institution": null
                },
                {
                    "degree": "Off :ex. v. Krigssk.",
                    "year": "1931",
                    "institution": null
                },
                {
                    "degree": "AIHSak",
                    "year": "32-34",
                    "institution": null
                },
                {
                    "degree": "Fortifik :kurs",
                    "year": "34-36",
                    "institution": null
                }
            ],
            "career": [
                {
                    "position": "Plac. v. Bodens ing:kår. 31-36",
                    "years": {
                        "start_year": 1931,
                        "end_year": 1936
                    },
                    "organization": null
                }
            ],
            "family": {
                "spouse": "grev :an Ebba Margaretha De la Gardie",
                "marriage_year": "37",
                "children": [
                    {
                        "name": "Charlotte",
                        "birth_year": "38"
                    },
                    {
                        "name": "Pontus",
                        "birth_year": "43"
                    }
                ]
            },
            "location_coordinates": {
                "Latitude": 59.32932349999999,
                "Longitude": 18.0685808
            }
        },
        "5": {
            "full_name": "Reuterswärd, Nils Gösta",
            "location": "Stockholm",
            "occupation": "Trädgårdsarkitekt",
            "birth_details": {
                "date": "1/4/1892",
                "place": "Stockholm",
                "place_coordinates": {
                    "Latitude": 59.32932349999999,
                    "Longitude": 18.0685808
                }
            },
            "education": [
                {
                    "degree": "Realex.",
                    "year": null,
                    "institution": null
                },
                {
                    "degree": "2 års stud. v. Adelsnäs Trädgårdsskola",
                    "year": null,
                    "institution": null
                }
            ],
            "career": [
                {
                    "position": "Trädgårdsarkit. v. Kgl. Järnvägsstyr., Sthlm",
                    "years": {
                        "start_year": 1938,
                        "end_year": 0
                    },
                    "organization": null
                }
            ],
            "family": {
                "spouse": "konstn :an Märtha Hjortzberg",
                "marriage_year": "27",
                "children": [
                    {
                        "name": "Måns",
                        "birth_year": "32"
                    }
                ]
            },
            "location_coordinates": {
                "Latitude": 59.32932349999999,
                "Longitude": 18.0685808
            }
        }
    }
}