{
    "original": "Jeppsson, Hjalmar, överingenjör,\nMalmö, f. 28/10/88 i Sövestad, Malmöh.\n1., av Isak J. o. Johanna Anderisdtr.\nG. 1’5 m. Sigrid Ohlsson. Barn: Tore\nf. 20, Hans 22, stud, Märta 23-, g. m.\nagron. Erik Eriksson, Stig 25.—\nAvig:-ex. fr. Malmö tekn. elem :&gt;sk. 08.\nKonstr. o. arlb :chef v. A-B Skånska\nCementgjuteriet i Malmö 08-16, arb\n:-dhef v. A-B Armerad Betong i Malmö\n16-46, öve ring. där fr. 46. Led. av styr.\nf. Sv. byggn :ind :förb, Malmö\nbygg-mäst:fören. o. A-B Armerad Betong.\nRVO 42.\n\nJeppsson, Johans Hjalmar,\ndistriktsveterinär, Véberöd, f. 20/12/84 i\nBör-ringe, Malmöli. 1, av Jöns J. o. Maria\nJonsson. G. 1. 10 m. Naima Nordqvist;\n2. 33 m. Guniborg Torstensson. Barn:\nInga f. 11, Britten 12, Per-Henning 17,\nKaj 3’5, Jörgen 37, Gunilla Kristina 45.\n\n—   Stud: ex. 05, veter:ex. 09.\nDistr:-vetier. i Orusts1 o. Tjörn’» diiistr. 10, i\nUddevalla disitr. 12, Uddeholms distr.\n19, Veberöds fr. 23. Lär. v. Gbgs o.\nBoh. 1. lant’m:sk. i Simirnersröd 12-19,\ntjg. s. överveter. v. mulsjukans ’bekämp.\n38-40. Ordf. i vägstyr. :f. Torna\nVäg-distr., nu Torna o. Bara vägnd, i\nmumie :fullm. i Vdberöd o. i Irälsov :md, led.\nav styr. f. ett fl ert. ikomm. o. a. in st.\nSkr.: bidr. i Sv. Veter :tidskr. RVO.\n\nJepson, Reinhold, läroverksadjunkt,\nHässleholm, f. 89 i Halmstad av köpim.\nGunnar J. o. Anna Jepson. G. 33 m.\nMiärta   Wallberg.     Barn:   Boel   f.   41.\n\n—  Stud:ex. i Halmstad 09, fil. kand. i\nLund 12, fil. mag. 13, fil. lic. 19.\nProvar v. södra latin i Stockholm\n21. E. o. lär. i Hudiksvall 22,\nTomelilla 23-25, Nyköping 25-26,\nTorne-»a 26-30, Hässleholm 30-31, adj. i\ntyska o. eng. v. ih. a. 1. d!är fr. 3’1.\n\nJeppsson, Nils Sigfrid,\nfolkskollärare, Trelleborg, f. 2/7/92 i Trelleb. av\nNils J. o. Christina Carlsson. G. 23 rn.\nAnna Carlsson* Barn: Stina f. 25, g.\nm. civiling.  Erik Jeppsson,  Malmö. —\n\nStud:ex. 10, folkskoll :ex. 13. Led., av\nstadsfullm. ’sed. 33, suppl. i\ndrätsel-kärnan., ordf. i fp. lok :avd. i Trelleb.\n312-41,  led.  av follksk :&lt;styr.  sed. 48.\n\n",
    "structured": {
        "1": {
            "full_name": "Jeppsson, Hjalmar",
            "location": "Malmö",
            "occupation": "överingenjör",
            "birth_details": {
                "date": "28/10/1888",
                "place": "Sövestad, Malmö",
                "parents": "Isak J. o. Johanna Anderisdtr",
                "place_coordinates": {
                    "Latitude": 55.50068100000001,
                    "Longitude": 13.7983739
                }
            },
            "education": [
                {
                    "degree": "examen från Malmö tekniska elementarskola",
                    "year": "1908",
                    "institution": "Malmö tekniska elementarskola",
                    "institution_coordinates": {
                        "Latitude": 55.604981,
                        "Longitude": 13.003822
                    }
                }
            ],
            "career": [
                {
                    "position": "Konstruktör o. arbetschef",
                    "years": {
                        "start_year": 1908,
                        "end_year": 1916
                    },
                    "organization": "A-B Skånska Cementgjuteriet i Malmö"
                },
                {
                    "position": "Arbetschef",
                    "years": {
                        "start_year": 1916,
                        "end_year": 1946
                    },
                    "organization": "A-B Armerad Betong i Malmö"
                },
                {
                    "position": "överingenjör",
                    "years": {
                        "start_year": 1946,
                        "end_year": null
                    },
                    "organization": "A-B Armerad Betong"
                }
            ],
            "family": {
                "spouse": "Sigrid Ohlsson",
                "marriage_year": "1’5",
                "children": [
                    {
                        "name": "Tore",
                        "birth_year": "20"
                    },
                    {
                        "name": "Hans",
                        "birth_year": "22"
                    },
                    {
                        "name": "Märta",
                        "birth_year": "23-"
                    },
                    {
                        "name": "Stig",
                        "birth_year": "25"
                    }
                ]
            },
            "location_coordinates": {
                "Latitude": 55.604981,
                "Longitude": 13.003822
            }
        },
        "2": {
            "full_name": "Jeppsson, Johans Hjalmar",
            "location": "Véberöd",
            "occupation": "distriktsveterinär",
            "birth_details": {
                "date": "20/12/1884",
                "place": "Börringe, Malmö",
                "parents": "Jöns J. o. Maria Jonsson",
                "place_coordinates": {
                    "Latitude": 55.5,
                    "Longitude": 13.333333
                }
            },
            "education": {
                "degree": null,
                "year": "09",
                "institution": null
            },
            "career": {
                "position": "Distr:-vetier.",
                "years": {
                    "start_year": 1910,
                    "end_year": null
                },
                "organization": "Veberöd"
            },
            "family": {
                "spouse": "Naima Nordqvist; 2. Guniborg Torstensson",
                "marriage_year": "1. 10 m. Naima Nordqvist; 2. 33",
                "children": [
                    {
                        "name": "Inga",
                        "birth_year": "11"
                    },
                    {
                        "name": "Britten",
                        "birth_year": "12"
                    },
                    {
                        "name": "Per-Henning",
                        "birth_year": "17"
                    },
                    {
                        "name": "Kaj",
                        "birth_year": "3’5"
                    },
                    {
                        "name": "Jörgen",
                        "birth_year": "37"
                    },
                    {
                        "name": "Gunilla Kristina",
                        "birth_year": "45"
                    }
                ]
            },
            "location_coordinates": {
                "Latitude": 55.6363631,
                "Longitude": 13.5006052
            }
        },
        "3": {
            "full_name": "Jepson, Reinhold",
            "location": "Hässleholm",
            "occupation": "läroverksadjunkt",
            "birth_details": {
                "date": "89",
                "place": "Halmstad",
                "parents": "köpim. Gunnar J. o. Anna Jepson",
                "place_coordinates": {
                    "Latitude": 56.6743748,
                    "Longitude": 12.8577884
                }
            },
            "education": {
                "degree": "fil. lic.",
                "year": "19",
                "institution": null
            },
            "career": {
                "position": "adj.",
                "years": {
                    "start_year": 1931,
                    "end_year": null
                },
                "organization": "tyska o. eng."
            },
            "family": {
                "spouse": "Miärta Wallberg",
                "marriage_year": "33",
                "children": [
                    {
                        "name": "Boel",
                        "birth_year": "41"
                    }
                ]
            },
            "location_coordinates": {
                "Latitude": 56.15891449999999,
                "Longitude": 13.7667655
            }
        },
        "4": {
            "full_name": "Jeppsson, Nils Sigfrid",
            "location": "Trelleborg",
            "occupation": "folkskollärare",
            "birth_details": {
                "date": "2/7/1892",
                "place": "Trelleb",
                "parents": "Nils J. o. Christina Carlsson",
                "place_coordinates": {
                    "Latitude": 55.3762427,
                    "Longitude": 13.1574231
                }
            },
            "education": {
                "degree": null,
                "year": "13",
                "institution": null
            },
            "career": null,
            "family": {
                "spouse": "Anna Carlsson*",
                "marriage_year": "23",
                "children": [
                    {
                        "name": "Stina",
                        "birth_year": "25"
                    }
                ]
            },
            "location_coordinates": {
                "Latitude": 55.3762427,
                "Longitude": 13.1574231
            }
        }
    }
}