{
    "original": "Vikbladh, Nils Otto Bertil,\nbankdirektör, Malmö, Tf. 2/11/02 i Sölvesborg\nav tandläk. Otto V. o. Ingeborg\nSvensson. G. 27 m. Ina Arvidsson.\nBarn: Inge f. 28, Sven 29, Britta 37.\n—■ Skolstud. v. h. a. 1. t. 21. Anst. i\nSmal. Ensk. Bank 21-24, i Oxie Här.\nSparb. sed. 25. Inneh. ett flert. styr\n:-o. rev :uppdr. sed. 30. Hobbies: sport,\nfiske. PatrstGM.\n\nVikbiadh, Inga, leg. läkare, Lund,\nf. 22/11/13 i Ljungby av tandläk. Otto\nV. o. Ingeborg Svensson. — Stud:ex.\nv. h. a. 1. f. fl. i Gbg 33, med. kand.\ni Sthlm 37, med. lic. i Lund 41. Res.\n•t. Tyskl., Österr. o. Ung. 37, t. Engl.\n38, t. Ital. o. Schweiz 39. Tf.\nund:-läk. å Ljungby las. 41, tf. aman. o.\nund :läk. v. med. klin. i Lund 42-45, v.\nkvinnoklin. där 46, aman. v. med. klin.\ni Lund fr. 47. Sekr. i Lunds kv.\nsugrören. 39-40, ordf. där 41, adj. led. av\nSkånska   handb:förb.   o.   Sv.   handb:-\n\nförb. sed. 46. Skr.: vetensk. art. i\nfacktidskr.\n\nWikborn, Agne, advokat,\nHässleholm,  f.  10/3/04 i Fuglie,  Malmöh. 1.\n\n—  Stud:ex. 22, jur. kand. 30. Tingstjg.\nv. V. Göinge doms, 31-34, inneh. av\nadv :f irman Stjerndal &amp; Wikborn i\nHässleholm.    Led. av Sv:es adv:samf.\n\nWikén, Joel Albert Valdus,\nstadsarkitekt, Hässleholm, f. 16/9/06 i Gbg av\nköpm. Albert o. Augusta W. G. 35\nm. Kerstin Elisabeth Hellström, d. 42.\nBarn: Bengt f. 37, Per 42. — Stud:ex.\nv. Gbgs latin 25, avg:ex. fr. CTI, avd.\nf. husbyggn :konst, 29, arkit:ex. v.\nKTH 32. Arb. i Paris v. Cour\nVen-döme 30-31, res. t. Engl. 31, t. Tyskl.,\nTjeckoslov., Ital. o. Schweiz 32. Anst.\nh. Kreuger &amp; Toll 30, h. A-B Nora\nTrädg:stad 32-34, å Sthlms\nlänsarkit:-kont. 35-36, h. arkit. Nils R. Hjorth i\nSthlm 35-36, h. flygförv. 36-37, därj.\nbyggn :konsulent i ett ant. samhällen\nkring Sthlm 34-37, stadsarkit. i\nHässleholms distr. fr. 37. Egen arkit\n:-verks. sed. 36. V. ordf. i Kristianstads\ntekn. fören. sed. 42, styr :led. i Södra\nSv:es arkit :fören., ordf. i\nHässleholms komm:tj :m:fören. Led. av ett\nflert. fören. bl. a. Rotary International.\nSkr.: art. i byggfrågor i dagspr. o.\nHem i Sv:e 34-37. Hobby: golf.\nRLSFftjSt,   Hemv.   ftjSplak.\n\nWiking, Bengt Alfred, civilingenjör,\nMalmö, f. 13/1/09 i Djursholm. G.\n35 m. Gunnel Ehrenberg. Barn:\nGunilla f. 41, Kerstin 44. — Stud:ex.\n27, civ:ing:ex. v. KTH (VoV) 32,\nlantbr :ing:kurs v. Ultuna 34. Lantbr\n:-stip. 32-38, Bitr. ing. v.\nstadsing:-kont. i Kristianstad 38-41, avd xhef v.\nA-B Skånska Cementgjut. i Malmö fr.\n41. Led. av styr. f. Skånska ing:kl.\nHobbies: friluftsliv,  idrott.\n\nWiklander, Uno, överpostmästare,\nMalmö, f. 14/8/89 i Stigsjö,\nVäster-norrl. 1. G. 32 m. Ada Lof gren. Barn:\nUlla Margareta f. 38, Ulf Jan-Olov 42.\n\n—   Res. i Finl., Estl., Lettl., Norge,\nDanm., Tyskl., Frankr. o. Belg.\nÖver-postmäst. i  Malmö fr. 46.   RVO.\n\n",
    "structured": {
        "1": {
            "full_name": "Vikbladh, Nils Otto Bertil",
            "location": "Malmö",
            "occupation": "Bankdirektör",
            "birth_details": {
                "date": "02/11/1902",
                "place": "Sölvesborg"
            },
            "education": [
                {
                    "degree": "Skolstudier",
                    "year": "1921",
                    "institution": "hemorten"
                }
            ],
            "career": [
                {
                    "position": "Anställd",
                    "years": {
                        "start_year": 1921,
                        "end_year": 1924
                    },
                    "organization": "Smal. Ensk. Bank"
                },
                {
                    "position": "Anställd",
                    "years": {
                        "start_year": 1925,
                        "end_year": null
                    },
                    "organization": "Oxie Här. Sparb."
                }
            ],
            "family": {
                "spouse": "Ina Arvidsson",
                "marriage_year": "1927",
                "children": [
                    {
                        "name": "Inge",
                        "birth_year": "1928"
                    },
                    {
                        "name": "Sven",
                        "birth_year": "1929"
                    },
                    {
                        "name": "Britta",
                        "birth_year": "1937"
                    }
                ]
            }
        },
        "2": {
            "full_name": "Vikbiadh, Inga",
            "location": "Lund",
            "occupation": "Leg. läkare",
            "birth_details": {
                "date": "22/11/1913",
                "place": "Ljungby"
            },
            "education": [
                {
                    "degree": "Stud:ex.",
                    "year": "1933",
                    "institution": "Gbg"
                },
                {
                    "degree": "Med. kand.",
                    "year": "1937",
                    "institution": "Sthlm"
                },
                {
                    "degree": "Med. lic.",
                    "year": "1941",
                    "institution": "Lund"
                }
            ],
            "career": [
                {
                    "position": "Tf. und:-läk.",
                    "years": {
                        "start_year": 1941,
                        "end_year": null
                    },
                    "organization": "Ljungby las."
                },
                {
                    "position": "Tf. aman. o. und :läk.",
                    "years": {
                        "start_year": 1942,
                        "end_year": 1945
                    },
                    "organization": "med. klin. i Lund"
                }
            ],
            "family": null
        },
        "3": {
            "full_name": "Wikborn, Agne",
            "location": "Hässleholm",
            "occupation": "Advokat",
            "birth_details": {
                "date": "10/03/1904",
                "place": "Fuglie, Malmö"
            },
            "education": [
                {
                    "degree": "Stud:ex.",
                    "year": "1922",
                    "institution": null
                },
                {
                    "degree": "Jur. kand.",
                    "year": "1930",
                    "institution": null
                }
            ],
            "career": [
                {
                    "position": "Tingstjg.",
                    "years": {
                        "start_year": 1931,
                        "end_year": 1934
                    },
                    "organization": "V. Göinge doms"
                },
                {
                    "position": "Inneh. av adv :f irman",
                    "years": {
                        "start_year": null,
                        "end_year": null
                    },
                    "organization": "Stjerndal & Wikborn i Hässleholm"
                }
            ],
            "family": null
        },
        "4": {
            "full_name": "Wikén, Joel Albert Valdus",
            "location": "Hässleholm",
            "occupation": "Stadsarkitekt",
            "birth_details": {
                "date": "16/09/1906",
                "place": "Gbg"
            },
            "education": [
                {
                    "degree": "Stud:ex.",
                    "year": "1925",
                    "institution": "Gbgs latin"
                },
                {
                    "degree": "Avg:ex. fr. CTI, avd. f. husbyggn :konst",
                    "year": "1929",
                    "institution": null
                },
                {
                    "degree": "Arkit:ex. v. KTH",
                    "year": "1932",
                    "institution": "KTH"
                }
            ],
            "career": [
                {
                    "position": "V. ordf.",
                    "years": {
                        "start_year": 1942,
                        "end_year": null
                    },
                    "organization": "Kristianstads tekn. fören."
                },
                {
                    "position": "Stadsarkit.",
                    "years": {
                        "start_year": 1937,
                        "end_year": null
                    },
                    "organization": "Hässleholms distr."
                }
            ],
            "family": {
                "spouse": "Kerstin Elisabeth Hellström",
                "marriage_year": "1935",
                "children": [
                    {
                        "name": "Bengt",
                        "birth_year": "1937"
                    },
                    {
                        "name": "Per",
                        "birth_year": "1942"
                    }
                ]
            }
        },
        "5": {
            "full_name": "Wiking, Bengt Alfred",
            "location": "Malmö",
            "occupation": "Civilingenjör",
            "birth_details": {
                "date": "13/01/1909",
                "place": "Djursholm"
            },
            "education": [
                {
                    "degree": "Stud:ex.",
                    "year": "1927",
                    "institution": null
                },
                {
                    "degree": "Civ:ing:ex. v. KTH (VoV)",
                    "year": "1932",
                    "institution": "KTH"
                },
                {
                    "degree": "Lantbr :ing:kurs v. Ultuna",
                    "year": "1934",
                    "institution": "Ultuna"
                }
            ],
            "career": [
                {
                    "position": "Bitr. ing.",
                    "years": {
                        "start_year": 1938,
                        "end_year": 1941
                    },
                    "organization": "stadsing:-kont. i Kristianstad"
                },
                {
                    "position": "Avd xhef",
                    "years": {
                        "start_year": 1941,
                        "end_year": null
                    },
                    "organization": "A-B Skånska Cementgjut. i Malmö"
                }
            ],
            "family": {
                "spouse": "Gunnel Ehrenberg",
                "marriage_year": "1935",
                "children": [
                    {
                        "name": "Gunilla",
                        "birth_year": "1941"
                    },
                    {
                        "name": "Kerstin",
                        "birth_year": "1944"
                    }
                ]
            }
        },
        "6": {
            "full_name": "Wiklander, Uno",
            "location": "Malmö",
            "occupation": "Överpostmästare",
            "birth_details": {
                "date": "14/08/1889",
                "place": "Stigsjö, Västernorrland"
            },
            "education": null,
            "career": null,
            "family": {
                "spouse": "Ada Lofgren",
                "marriage_year": "1932",
                "children": [
                    {
                        "name": "Ulla Margareta",
                        "birth_year": "1938"
                    },
                    {
                        "name": "Ulf Jan-Olov",
                        "birth_year": "1942"
                    }
                ]
            }
        }
    }
}