{
    "original": "Velinder, Nils-Johan, tandläkare,\nLund, f. 19/7/13 i Trelleb. av lärov:adj.\nJohan V. o. Ida Malmström. G. 39 m.\nGunborg Heldkvist. Barn: Gun-Mari f.\n41, Viveka 43, Jan 45. — Stud:ex. i\nLund 32, tandl :kand. 34, tandkex. 38.\nAssist, h. tandl. F. Rydin i Sthlm\n38-39, egen prakt, i Lund sed. 39.\n\nWellgren, Oscar Emil,\nredaktionssekreterare, Malmö, f. 29/5/96 i\nMalmö av verkmäst. Karl W. o. Johanna\nOhlsson. G. 28 m. Märta Söderberg.\nBarn: Marie-Louise f. 37, Carl Gösta\n39. — Realex. 12, prakt. v. lab.,\nkemist-ex. v. Malmö kem. facksk. 18. Res. s.\nLars Hiertastip. t. Österr. 37.\nMed-arb&gt;: i Skånska Aftoribl. 23, red:sekr.\nfr. 39. Sign.: O. W-n, Owe. Medl. i\nPubl :kl.   fr.   24,   led.   av   styr.   f.   dess\n\nsödra   krets,   medl.   i   Sv.   journ ifören.\nHob’bies:   målning,  botanik.\n\nWellmark, Bengt Olof Helmer,\nadvokat, Lund, i. 9/6/11 i Rydöbruk,\nJönköp. 1., av träv:handl. Bengt Aug.\nJohansson o. Clara Sofie Charl.\nWall-mark. G. 30 m. Marie Louise\nHallberg. Barn: Per Ulf f. 31, Pia 45. —\nStud:ex. i Halmstad 29, jur. kand. i\nLund 36. Adv. i Lund sed. 37. Led.\nav Sv:es adv:samf. sed. 41. Sekr. h.\nlönend i Lund sed. 41. Omb :man i\nSkånska Livr:- o. kap :försäkr :anst. fr.\n41. Ordf. i Skånska a-utomobilkl. fr.\n46.\n\nWeman, Per Nils, civilingenjör,\nkapten i 1.7 res., Arlöv, f. 15/7/94 i Erfurt,\nTyskl., av kapten S. A. W. o. Helga\nStenfelt. G. 23 m. Laila Fogelmarck.\nBarn: Per Olof f. 25, Lars Christer\n26, Jan Mauritz 30. — Ex. v. Örebro\ntekn. elem:sk. 15, v. KTH, avd. kemi\no. kem. teknol., 19. Stud:resa t.\nFrankr. o. Belg. 32. Anst. i SS A sed.\n23, avd xhef v. centrallab. där sed. 41.\nLSTF, styr:led. i Malmö bef :utb\niför-en.\n\nWemiby, Nils Albert,\nsparbankskamrer, Hälsingborg, f. 6/2/07 i Ö.\n",
    "structured": {
        "0": {
            "full_name": "Velinder, Nils-Johan",
            "location": "Lund",
            "occupation": "tandläkare",
            "birth_details": {
                "date": "19/07/1913",
                "place": "Trelleborg",
                "parents": "Johan V. o. Ida Malmström"
            },
            "education": [
                {
                    "degree": "Stud:ex.",
                    "year": "1932",
                    "institution": "Lund"
                },
                {
                    "degree": "tandl :kand.",
                    "year": "1934",
                    "institution": "Lund"
                },
                {
                    "degree": "tandkex.",
                    "year": "1938",
                    "institution": "Lund"
                }
            ],
            "career": [
                {
                    "position": "Assist, h. tandl.",
                    "years": {
                        "start_year": 1938,
                        "end_year": 1939
                    },
                    "organization": "F. Rydin i Sthlm"
                },
                {
                    "position": "egen prakt",
                    "years": {
                        "start_year": 1939
                    },
                    "organization": "Lund"
                }
            ],
            "family": {
                "spouse": "Gunborg Heldkvist",
                "marriage_year": "1939",
                "children": [
                    {
                        "name": "Gun-Mari",
                        "birth_year": "1941"
                    },
                    {
                        "name": "Viveka",
                        "birth_year": "1943"
                    },
                    {
                        "name": "Jan",
                        "birth_year": "1945"
                    }
                ]
            }
        },
        "1": {
            "full_name": "Wellgren, Oscar Emil",
            "location": "Malmö",
            "occupation": "redaktionssekreterare",
            "birth_details": {
                "date": "29/05/1896",
                "place": "Malmö",
                "parents": "verkmäst. Karl W. o. Johanna Ohlsson"
            },
            "education": [
                {
                    "degree": "Realex.",
                    "year": "1912"
                },
                {
                    "degree": "kemist-ex.",
                    "year": "1918",
                    "institution": "Malmö kem. facksk."
                }
            ],
            "family": {
                "spouse": "Märta Söderberg",
                "marriage_year": "1928",
                "children": [
                    {
                        "name": "Marie-Louise",
                        "birth_year": "1937"
                    },
                    {
                        "name": "Carl Gösta",
                        "birth_year": "1939"
                    }
                ]
            },
            "publications": [
                {
                    "title": "målning",
                    "year": "botanik",
                    "type": "NULL"
                }
            ],
            "hobbies": [
                "målning",
                "botanik"
            ]
        },
        "2": {
            "full_name": "Wellmark, Bengt Olof Helmer",
            "location": "Lund",
            "occupation": "advokat",
            "birth_details": {
                "date": "09/06/1911",
                "place": "Rydöbruk, Jönköp. l.",
                "parents": "träv:handl. Bengt Aug. Johansson o. Clara Sofie Charl. Wall-mark"
            },
            "education": [
                {
                    "degree": "Stud:ex.",
                    "year": "1929",
                    "institution": "Halmstad"
                },
                {
                    "degree": "jur. kand.",
                    "year": "1936",
                    "institution": "Lund"
                }
            ],
            "career": [
                {
                    "position": "Adv.",
                    "years": {
                        "start_year": 1937
                    },
                    "organization": "Lund"
                }
            ],
            "family": {
                "spouse": "Marie Louise Hallberg",
                "marriage_year": "1930",
                "children": [
                    {
                        "name": "Per Ulf",
                        "birth_year": "1931"
                    },
                    {
                        "name": "Pia",
                        "birth_year": "1945"
                    }
                ]
            }
        },
        "3": {
            "full_name": "Weman, Per Nils",
            "location": "Arlöv",
            "occupation": "civilingenjör, kapten i 1.7 res.",
            "birth_details": {
                "date": "15/07/1894",
                "place": "Erfurt, Tyskl.",
                "parents": "kapten S. A. W. o. Helga Stenfelt"
            },
            "education": [
                {
                    "degree": "Ex. v. Örebro tekn. elem:sk.",
                    "year": "1915"
                },
                {
                    "degree": "v. KTH, avd. kemi o. kem. teknol.",
                    "year": "1919"
                }
            ],
            "career": [
                {
                    "position": "Anst.",
                    "years": {
                        "start_year": 1923
                    },
                    "organization": "SS A"
                }
            ],
            "family": {
                "spouse": "Laila Fogelmarck",
                "marriage_year": "1923",
                "children": [
                    {
                        "name": "Per Olof",
                        "birth_year": "1925"
                    },
                    {
                        "name": "Lars Christer",
                        "birth_year": "1926"
                    },
                    {
                        "name": "Jan Mauritz",
                        "birth_year": "1930"
                    }
                ]
            }
        },
        "4": {
            "full_name": "Wemiby, Nils Albert",
            "location": "Hälsingborg",
            "occupation": "sparbankskamrer",
            "birth_details": {
                "date": "06/02/1907",
                "place": "Ö. Go"
            },
            "family": {
                "spouse": "NULL",
                "marriage_year": "NULL",
                "children": "NULL"
            }
        }
    }
}