{
    "original": "RSO, RVO, KDDO, ERKOSkl, EÖK2kl,\nRFinlVROlkl, RNS:tOOlkl, RSpMfOv\nIkl, RFrHL RPolRest, SCFSM,\nFinl-SkFK, ERKM.\n\nGift 1) 10-33 m Ebba Ehrenborg f 91\nd 36, dtr t frih Casper E o Ivi Natt\n\n0   Dag,  2)  34 m journ Gerd Rehn f\n89,   dtr   t   kamrer   Karl   R   o   Anna\nEriksson. - Barn: Pehr f 11 d 61, Metta\nf 17.\n\nRIBBING, STEN A H, major,\nDjursholm, f i Kristianstad 20/12/08 av\nmajor Herman R o Hildegard Thorin.\nStud:ex Örebro 28, KS 31, AIHS\n32-34, signaloff 35, off A l 31-37,\nKarls-borgs art:reg 37-41, Iv:off 2:a\nmilbefstab Östersund 41-44, off Lv 3’ 44-45,\nast 45-50, Lv 3 50-52, mobiliseringsoff\nSthlms fostab. - Medl Sthlms Lvfören,\nsällsk Örebro-Karolinarna, 08 års män.\n-Utm: RSO, SLKSM, StLvfSM. -\nHobbies: fiske, bridge, filateli.\nGift 34 m Ingrid Peterson-Witt f 10 d 61,\ndtr t fil dr Albert Peterson o Leonie\nWitt. - Barn: Gunilla f 35, Christina\nf 38, Ulf f 40, Leonie f 47, Bengt f 49.\n\nRIBBING, B C STIG, pianist, Sthlm,\nf i Jönkpg 5/1/04 av öv:löjtn Bo R o\nAnna Silverstolpe.\n\nStud:ex, musikstud f Märta Tham,\nGottfrid Boon o Arthur Schnabel,\ndebut 27, medv i radio sed 25, lär i\npianospelning MA sed 58 (eo 51). - Solist\n\n1  utl radio, bl a Köpenh, Oslo,\nHamburg, Paris, Geneve, Wien, ett flert\nork:-fören, Fylkingen, Intim musik m fi.\nGift 40 m sångerskan Maria Rf  11,\ndtr t Eduard Edenhofer o Maria Reiter.\n- Barn: Monika f 41, Susanne f 45.\n\nRIBEN, K OLOF, justitieråd, Sthlm,\nf i Sthlm 15/7/05 av häradsh KAR\no Asta Rönblom.\n\nJur kand 29, fiskal Svea hovr 33, assess\n40, hovr:råd 46, häradsh N Hälsingl\ndoms 51!, lagman Svea hovr\n(vatten-överdomst) 57, just:råd sed 59. - Utm:\nKNO Ikl.\n\nGift 39 m Dagmar Ernberg f 11, dtr t\nreg :rådet Jarl E o Eleonore Riben.\n-Barn: Agneta f 40, Staffan f 41, Malin\nf 44.\n\n",
    "structured": {
        "0": {
            "full_name": "RIBBING, STEN A H",
            "location": "Djursholm",
            "occupation": "Major",
            "birth_details": {
                "date": "20/12/1908",
                "place": "Kristianstad",
                "parents": "major Herman R o Hildegard Thorin",
                "place_coordinates": {
                    "Latitude": 56.0293936,
                    "Longitude": 14.1566778
                }
            },
            "education": [
                {
                    "degree": "Stud:ex",
                    "year": "1928",
                    "institution": "Örebro",
                    "institution_coordinates": {
                        "Latitude": 59.2752626,
                        "Longitude": 15.2134105
                    }
                },
                {
                    "degree": "KS",
                    "year": "1931",
                    "institution": "AIHS",
                    "institution_coordinates": {
                        "Latitude": 60.12816100000001,
                        "Longitude": 18.643501
                    }
                }
            ],
            "career": [
                {
                    "position": "signaloff",
                    "years": {
                        "start_year": 1935,
                        "end_year": 1935
                    },
                    "organization": "A l"
                },
                {
                    "position": "off A l",
                    "years": {
                        "start_year": 1931,
                        "end_year": 1937
                    },
                    "organization": "Karls-borgs art:reg"
                },
                {
                    "position": "Iv:off 2:a milbefstab",
                    "years": {
                        "start_year": 1941,
                        "end_year": 1944
                    },
                    "organization": "Östersund"
                },
                {
                    "position": "off Lv 3'",
                    "years": {
                        "start_year": 1944,
                        "end_year": 1945
                    },
                    "organization": "ast"
                },
                {
                    "position": "ast",
                    "years": {
                        "start_year": 1945,
                        "end_year": 1950
                    },
                    "organization": "Lv 3"
                },
                {
                    "position": "mobiliseringsoff",
                    "years": {
                        "start_year": 1950,
                        "end_year": "NULL"
                    },
                    "organization": "Sthlms fostab"
                }
            ],
            "family": {
                "spouse": "Ingrid Peterson-Witt",
                "marriage_year": "34",
                "children": [
                    {
                        "name": "Gunilla",
                        "birth_year": "35"
                    },
                    {
                        "name": "Christina",
                        "birth_year": "38"
                    },
                    {
                        "name": "Ulf",
                        "birth_year": "40"
                    },
                    {
                        "name": "Leonie",
                        "birth_year": "47"
                    },
                    {
                        "name": "Bengt",
                        "birth_year": "49"
                    }
                ]
            },
            "location_coordinates": {
                "Latitude": 59.39707249999999,
                "Longitude": 18.0903005
            },
            "occupation_hisco_code": 957,
            "occupation_cosine_similarity": 0.46982188844210804,
            "occupation_hisco_occupation": "Glaziers",
            "sector_code": 6,
            "sector_description": "Building contractor, Concrete goods factory"
        },
        "1": {
            "full_name": "RIBBING, B C STIG",
            "location": "Sthlm",
            "occupation": "Pianist",
            "birth_details": {
                "date": "5/1/1904",
                "place": "Jönkpg",
                "parents": "öv:löjtn Bo R o Anna Silverstolpe",
                "place_coordinates": {
                    "Latitude": 60.12816100000001,
                    "Longitude": 18.643501
                }
            },
            "education": [
                {
                    "degree": "Stud:ex, musikstud",
                    "year": "27",
                    "institution": "Märta Tham, Gottfrid Boon o Arthur Schnabel",
                    "institution_coordinates": {
                        "Latitude": 60.12816100000001,
                        "Longitude": 18.643501
                    }
                },
                {
                    "degree": "pianospelning MA",
                    "year": "58",
                    "institution": "eo 51",
                    "institution_coordinates": {
                        "Latitude": 60.12816100000001,
                        "Longitude": 18.643501
                    }
                }
            ],
            "career": {
                "position": "Solist",
                "years": {
                    "start_year": 25,
                    "end_year": "NULL"
                },
                "organization": "utl radio, bl a Köpenh, Oslo, Hamburg, Paris, Geneve, Wien, ett flert ork:-fören, Fylkingen, Intim musik m fi"
            },
            "family": {
                "spouse": "\tMaria Rf",
                "marriage_year": "40",
                "children": [
                    {
                        "name": "Monika",
                        "birth_year": "41"
                    },
                    {
                        "name": "Susanne",
                        "birth_year": "45"
                    }
                ]
            },
            "location_coordinates": {
                "Latitude": 59.32932349999999,
                "Longitude": 18.0685808
            },
            "occupation_hisco_code": 170,
            "occupation_cosine_similarity": 0.6688002642804971,
            "occupation_hisco_occupation": "Composers and Performing Artists, Specialisation Unknown"
        },
        "2": {
            "full_name": "RIBEN, K OLOF",
            "location": "Sthlm",
            "occupation": "Justitieråd",
            "birth_details": {
                "date": "15/7/1905",
                "place": "Sthlm",
                "parents": "häradsh KAR o Asta Rönblom",
                "place_coordinates": {
                    "Latitude": 59.32932349999999,
                    "Longitude": 18.0685808
                }
            },
            "education": {
                "degree": "Jur kand",
                "year": "29",
                "institution": "fiskal Svea hovr"
            },
            "career": [
                {
                    "position": "assess",
                    "years": {
                        "start_year": 40,
                        "end_year": "NULL"
                    },
                    "organization": "hovr:råd"
                },
                {
                    "position": "häradsh N Hälsingl doms",
                    "years": {
                        "start_year": 51,
                        "end_year": "NULL"
                    },
                    "organization": "lagman Svea hovr"
                },
                {
                    "position": "lagman Svea hovr",
                    "years": {
                        "start_year": 57,
                        "end_year": "NULL"
                    },
                    "organization": "(vatten-överdomst)"
                },
                {
                    "position": "just:råd",
                    "years": {
                        "start_year": 59,
                        "end_year": "NULL"
                    },
                    "organization": "NULL"
                }
            ],
            "family": {
                "spouse": "Dagmar Ernberg",
                "marriage_year": "39",
                "children": [
                    {
                        "name": "Agneta",
                        "birth_year": "40"
                    },
                    {
                        "name": "Staffan",
                        "birth_year": "41"
                    },
                    {
                        "name": "Malin",
                        "birth_year": "44"
                    }
                ]
            },
            "location_coordinates": {
                "Latitude": 59.32932349999999,
                "Longitude": 18.0685808
            },
            "occupation_hisco_code": 122,
            "occupation_cosine_similarity": 0.792012863656523,
            "occupation_hisco_occupation": "Judges"
        }
    }
}