{
    "original": "VICTORIN,  J  LARS  H,  leg läkare,\n\nGbg, f i Luleå 19/7/31 av tillsynslär\nJohn V o lekt Lisa Adolfsson.\nStud:ex 50, med kand 53 o med lic Gbg\n58; aman farmakol inst Gbgs univ 53-57,\nöl läk:förordn 54-58, underläk barnavd\nBorås las 59-63, Gbgs barnsjh sed 63.\n-Skr i pediatr.\n\nGift 56 m Inger Lindberg f 33, dtr t\nlärov :adj :na Sam L o Kerstin Rylander.\n- Barn: Ånn f 57, Åse f 60, Mats f 62.\n\nVICTORIN, LISA I M, lektor, Gbg,\nf i Boden 8/9/03 av lokmäst Johan\nAdolfsson o Matilda Norberg.\nFolkskollär:ex 23, folkskollär Kiruna 23,\növn:skollär Luleå 29, Karlstad 36, Gbg\n38, lekt i lågstad metodik Lärarhögsk\nGbg sed 63. - Led Sv:es lär nykterh:förb\nförl:styr o litt:komm. - V ordf styr\nKål-leredshemmet sed 60, led Gbgs stads\nför-säkr:nd. - l:e v ordf Gbgs kvinnl\ndiskussionsklubb. - Utm: SRKftjt. - Hobby:\nmusik.\n\nGift 30 m tillsynslär John Victorin.\n-Barn: Lars f 31, Anita f 36, Bengt f 40.\n\nWIDE,   EINAR   R,   provinsialläkare,\n\nHälleviksstrand, f i Sthlm 1/5/05,\nadoptivson t med dr P G W o Maria\nHenningsson.\n\nStud:ex Hbg 23, med kand 27 o med lic\nLund 34; stip v Kaiser Wilhelmsinst\nBerlin 29, cancerforskn 29-33, aman Lunds\nuniv 27-33, prakt läk Hbg 35-46,\ndistr:-läk Diredaoua, Etiop, 46-47, prov:läk\nLammhult 49-58, Orust sed 60.\nGift 32-53 m Inga M Bretz f 10, dtr t\ntandl Hjalmar B o Hedwig Andersson.\n-Barn: Peter f 33, Monika f 37, Annika\nf 43.\n\nWIDEBERG, TORSTEN V, godsägare,\n\nLidköping, f i Gunnarstorp, Kalmar l,\n6/7/01 av godsäg Per W o Gerda Olsson.\nLärov :stud, Kalmar l lantmannask\nHögalid 20, inneh Västby egend Lidkpg sed\n31. - Ordf Hovby hembygdsgille, fd v\nordf Skarab l fören f låglandsboskap;\nfd led Hovby förs komm:nd, kyrkoråd\no valnd. - Utm: SkarabsfbSM. -\nHobby: släktforskning.\n\nGift 35 m Elsa Heiding f 02, dtr t\nlandst:man Johan Pettersson o Alida\nNilsdotter. - Barn: Ingemar f 35,\nMargareta f 37, Estrid f 42.\n\nWIDÉEN se WIDÉN\n\nWIDEGREN, K ANDERS,\nläroverksadjunkt, Oskarshamn, f i Sthlm 10/7/20\nav avd :ch Sigfrid V o Lydia Westling.\nStud:ex 39, fil kand 51 o fil mag Sthlm\n52, eo adj hal Umeå 52, rekt realsk\nBureå 58, samrealsk Borgholm 61, adj i\nfysik o kemi hal Oskarshamn sed 63.\n-Hobby: fiske.\n\nGift 50 m Aina Nilsson f 21, dtr t rekt\nHugo N o Hanna Lindberg. - Barn:\nAnnika f 51, Ragnar f 53, Lena f 55.\n\nWIDEGREN, JAN E S, ryttmästare,\nSkövde, f i Nykpg 26/10/18 av adv\nSeibrant W o Clary Hedman.\nStud:ex Sthlm 38, off:ex 42, fänr K 4\n42, löjtn 44, adjut VI milbefstab 47,\nryttm K 3 sed 61; mil instr Etiop 51-54,\nFN-uppdr Kashmir 56-57. - Medl\nFrim-O. - Utm: RSO, REtSO, UNM, Älvsb\nbfbSM, SBSSM, SLKSM. - Hobbies:\nhippolog konst o litt.\nGift 49 m Barbro Lindblom f 26, dtr t\ntandl Hans L o Märta Krahé. - Barn:\nDick f 51, Anne f 61.\n\nWIDEGREN, SVEN A, överste,\nLinköping, f i Linkpg 18/11/10 av civ :ing\nSven W o Götha Wetterhall.\nFänr I 5 32, major 50, öv:löjtn ast 55,\növerste 59. - Lär InfSS 41-43 o 47-53,\ntjg inf:insp 54-59, ch InfSS 59-63, I 4\nsed 63. - Utm: KSO, RVO, SkytteM.\nGift 37 m Britt-Marianne Widell f 11,\ndtr t prov :läk Hjalmar W o Ebba\nLindholm.\n\nWIDEHED, GILLIS, länsassessor,\nKalmar, f i Jönkpg 11/11/24 av\negend:-mäkl Wiking W o Esther Carlsson.\nStud:ex Karlskrona 43, jur kand Lund\n49, tingstjg samt tjg Gbgs rådhusr 49-51,\ne länsnot Blek l 52, Kronob l 52,\ntax:-insp 54, l:e länsnot 57, Kalmar l 60,\nbitr tax :intend 63, länsassess där sed 65\n(tf 64). - Ordf tax:nd sed 53.\nGift 49 m Agneta Bokander f 23.\n-Barn: Rolf f 58.\n\nWIDELL, ARNE K F, bitr länsläkare,\nJönköping, f i Gbg 13/4/24 av apot\nFredrik W o Gerda Lindholm.\nStud:ex Borås 44, farm kand 47, med\nkand 50 o med lic Lund 55; öl läk\n:förordn 53-56, underläk barnklin\nVänersborgs las 56-59, med avd där 59-60,\nprov :läk Bjurholm 60-64, bitr länsläk\nJönkpgs l sed 64.\n\nGift 53 m Elsa Amdisen Jensen f 20, dtr\nt vet Jens Anker Amdisen o Minnie\nCarlsson. - Barn: Maria f 59, Kristina\nf 62.\n\nWIDELL, HANS C-A, direktör,\nBryssel, Belg, f i Sthlm 30/4/22 av dir Sten\nW o Margareta Falkenberg.\n\nBröd Påhlmans hdlI 42; prakt Sv\nkassa-reg ab 41, kont C Bert Lilja &amp; Co ab 42,\nanst ab Åtvidabergs ind:er Sthlm 44,\nverkst dir dess dtrbol Facit-Odhner SA\nBryssel sed 62. - Styr :led Sv hdlskamm\nBryssel. - Hobbies: golf, segling.\nGift 46 m Marianne Drakenberg f 27,\ndtr t civ :ing Hans D o Elsa Bjurling.\n-Barn: Héléne f 48, Eva f 51, Margareta\nf 58.\n\nWIDELL, STEN F A, docent,\növerläkare, Kalmar, f i Gbg 18/2/22 av apot\nFredrik W o Gerda Lindholm.\nStud:ex Borås 40, med kand 42 o med\nlic Lund 471, med dr o doc i pediatrik\nLunds univ sed 58; underläk pediatr klin\nLunds las 48-49, med avd Borås las\n50-52, aman, underläk o bitr överläk\npediatr klin Lunds las 52-61, överläk\nbarnklin Kalmar las sed 61. - Medl Rotary,\nSHT. - Skr i pediatrik. - Hobby: golf.\nGift 50 m Margareta Enemark f 26, dtr\nt agr Waldemar E o Berta Andersson.\n-Barn: Björn f 54, Anders f 59.\n\nWIDELL, STIG J A, godsägare,\nMotala, f i Älvestad, Östergötl l, 25/7/17 av\ngodsäg Eric W o Sigrid Pettersson.\nStud:ex Motala 37, Hvilans lantm:sk 38,\ninneh Torreby egend, Munkedal sed 60.\n- Styr:led J H Dieden J:ör ab Malmö;\nkronoomb i tax:nd. - Hobby: golf.\nGift 45 m fil kand Gunvor Holmberg\nf 22, dtr t dir Swante H o Hulda\nHansson. - Barn: Helena f 51.\n\nVIDÉN, E ALLAN, rektor, Gbg, f i\nKungälv 7/11/09 av folkskollär Johannes\nV o Hilma Andreasdotter.\nFil mag 34 o fil lic Gbg 49; eo adj\nUddevalla 42, adj Sunne 46, Uddevalla 50,\nrekt Östra realsk Gbg 53-56, lekt hal\nVarberg 55-61, Vasa hal Gbg sed 61,\nrekt hal Majorna sed 56. - Ordf Gbgs\nskolidr:förb. - Utm: RNO.\nGift 40 m Gunvor Bogren f 11, dtr t\nkontr :prost Johan B o Hanna Crona.\n-Barn: Ragnhild f 42, Alvar f 44, Erland\nf 46, Gunnar f 48, Gunhild f 52.\n\nWIDÉN, BENGT K A, bankdirektör,\nGbg, f i Eksjö 21/9/00 av jv:tjm Johan\nW o Augusta Petersson.\nRealex 16, tjm sparbk 16, Sydsv kredit\nab 18, kamr där 27, Gbgs bk Nässjö 28,\nlånekamr huvudkont Gbg 45, dir:ass 50,\ndir o ch dess låneavd o exp :kont sed\n55. - Styr :led ab Sjuntorp, Svea band\n&amp; pappers ab, Sv reklambandsfabr nya\nab, Dorch Bäcksin &amp; Co ab, Wallergrens\nkonf ab. - Medl FrimO, Odd Fellow.\n-Utm: RVO.\n\nGift 34 m Gullan Derwinger f 10, dtr t\nköpm Gustaf D o Elin Aronson. - Barn:\n\nBarbro f 35, Bengt-Åke f 39, Ullabritt\nf 44, Jerker f 49.\n\nWIDÉN, BOO D, arkitekt SAR,\nJönköping, f i Haparanda 23/11/13 av\nhäradsh Wilhelm W o Svea Drake.\nStud:ex Djursholm 33, KTH 40, anst\nstadspl:kont Karlskoga 40, HSB Sthlm\n41, arkit SAR W Gahn 42, C O\nHallström 43, bitr stadsarkit Jönkpg 44, eg\narkit :verksamh Jönkpg sed 45 m kont\nMalmö 47-51, stadsarkit Hjo sed 64.\n-Bl arb: skolor, bost:omr, ind:anläggn,\nkont:- o aff :hus, inst:byggn, saml:lokaler\no stadspl. - Hobby: golf.\nGift 40 m Siv von Essén f 17, dtr t\njägm, frih Allan v E o Margit\nAmundson. - Barn: Eva o Ingrid ff 51.\n\nWIDÉN,  C  GUNNAR,  polismästare,\n\nTrollhättan, f i Laholm 10/3/05 av köpm\nCharles W o Lilly André.\nRealex Skövde 20, landsfiskals- o\nkrigs-fiskalsex 28. - Bitr å landsfiskalskont\n20-23, eo landskanslist Skarab l 23-25, tf o\ne landsfiskal där 26-41, landsfiskal o\ncf:-ch Arvidsjaur 42-51, landsfiskal resp\npo-lisch o åkl Trollhättan 52-64, polismäst\ndär sed 65; cf:ch sed 53. - Led\nTrollhättans hälsov:nd sed 53, byggn:nd sed 56,\nungd:styr sed 62, Trollhätteblockets\nsamarb :nd sed 63. - Medl Rotary. - Utm:\nRNO, FHMM, RLSFftjGm.\nGift 34 m Dagmar Borg f 06, dtr t köpm\nCarl B o Charlotta Carlqvist. - Barn:\nBjörn f 37, Birgitta f 43.\n\nWIDÉEN, K HARALD, fil dr,\nmuseiintendent, Gbg, f i Skara 15/9/12 av\ntonsätt Ivar W o Augusta Carlson.\nStud:ex 32, fil kand Sthlm 37, fil lic 47,\nfil dr 55, utf kulturminnes v arb inom\nriksantikv:ämb o på dess uppdr,\nkultur-hist kontr v byggn :hist undersökn av\nSkara domkyrka, Falkpgs kyrka m fi,\naman Gbgs mus hist avd 47, intend Gbgs\nhist mus sed 54, byggn :hist utredn f\nGbgs städs byggn :nd sed 64. - Sekr\nDiakonistyr konstutsk 42-47, Sv:es yngre\nmuseimän 46-48, komm f utg av\nbe-skrivn över Västergötl 61, medl Sv\nnu-mismat fören. - Skr: Västsvenska\nvikingatidsstudier (drsavh 55} m m.\n-Hobby: fotografering.\nGift 57 m Asta Oswan f 17, dtr t köpm\nSven Carlson o h h f Ahlgren.\n\nWIDÉN, LENNART C A, aukt revisor,\nlektor, Partilie, f  i  Marstrand 27/1/19\nav korpral Allan W o Clara Olsen.\nStud:ex Gbg 38, GbgHdlI 39, res:off:ex\n41, DHG 45, tax :ass  länsstyr Gbgs  o\n\nBoh l 45, rev :ass h aukt rev Folke\nBrolin 47, inneh Lennart Widens re v :byrå\nab Gbg sed 50 o Bokf :byrån Korrekt ab\nsed 62; led Fören aukt rev sed 59.\n-Tunlar o bitr lär GbgHdlI 43-51, HHG\n47-51, Tekn gymn 54-63, lekt i\nföretagsekonomi där sed 63; spec :lär i bokföring\nCTH sed 61. - Medl Odd Fellow,\nBache-lors Club. - Kapt int:kårens res. -\nHobbies: sportfiske, segling, fjällvandr, foto.\nGift 45 m Britt Jansson f 22, dtr t\njord-br:instr Karl J o Gerda Johansson.\n-Barn: Ing-Britt f 46, Monika f 48, Karin\nf 53, Kristina f 61.\n\nWIDÉN,   O   (OLLE),   tekn   direktör,\n\nLjungsbro, f i Bollnäs 15/8/01 av jv:tjm\nOlof W o Lina Johnsson.\nCTH 26, ing Kem fabr dr Harbeck\nPar-tille 26, Stadskemistens lab Gbg 27,\nlab :ch Svea oljefabr Kalmar 28,\ndrifts-ing Sv ackumulator ab Jungner Fliseryd\no Oskarshamn 31, driftsing Sv\nChokladfabr ab Cloetta Ljungsbro 35, övering\n39, tekn dir där sed 62. - Led\nreklam-granskn:ndn 53, styr :ordf Motala ströms\nvattenv:förb 55; ordf Gullbergs härads\nskyttegille 41. - Kronoomb 43. - Medl\nSHT. - Hobbies: fiske, målning, musik.\nGift 2) 54 m Märta Johansson f 04.\n-Barn: Catharina f 37, Bo f 42.\n\nWIDENFELT, SAM E, disponent, Gbg,\nf i Eskilstuna 18/5/97 av grosshandl o\nrådm Fredr Johansson o Maria\nHansson.\n\nDHS 19, univ :stud Montreal o Chicago\n20-22. - Anst i Sv:e 18-20, v sv\ngen:konsulatet Montreal 20-21 o Chicago 21-22,\nGbgs litogr ab 23, försäljn:ch där 29,\nGbgs litogr ab m fi 35, disp Esseltes\nGbgsind:er ab (Wezäta-Melins ab)\n40-62. - Sekr Travellers Club Gbg 32-35,\nv ordf 52-54, ordf 54-58 o 62-63 (hedL\n64), ordf Gbgs reklamfören 43-45 (hedL\n45), Sv reklamförb 48-51 (v ordf 39-41\no 43-48, hedL 61), Nord\ncivilekonom-förb sed 61 (v ordf 52-61), v ordf\nSv civilekonomfören 54-58, ordf dess v\nkrets 49-57 (hedL 57). - Medl Nord\nförsäljn:- o reklamförb presidium 48-59, v\npresid 58-59. - Nämndem. - Skr:\ntidskr:-art i ekon, försäljn:- o reklamtekn\nfrågor. - Utm: RVO, PatrSGM. - Hobby:\nresor.\n\nGift 27 m Signe Tegnander f 99, dtr t\nbyggm N J Andersson o Karolina\nTegnander. - Barn: Göran f 28, Ann-Mari\nf 30, Staffan f 31, Birgitta f 36.\n\nWIDENGREN, P L H (HENKEN),\ndirektör, Särö, f i V Vingåker, Söder-\n\nmani l, 20/6/10 av grossh Per W o\nWahlborg Öfverman.\n\nDeläg, v verkst dir o styr :led ab L &amp; P\nWidengren sed 36.\n\nGift 42 m Margareta Lesslie f 19, dtr t\nkonsul Otto L o Beatrice Kylander.\n\n",
    "structured": {
        "0": {
            "full_name": "VICTORIN, J LARS H",
            "location": "Göteborg",
            "occupation": "Leg läkare",
            "birth_details": {
                "date": "19/07/1931",
                "place": "Luleå",
                "parents": "Tillsynslär John V o lekt Lisa Adolfsson"
            },
            "education": [
                {
                    "degree": "Stud:ex",
                    "year": "1950",
                    "institution": "NULL"
                },
                {
                    "degree": "Med kand",
                    "year": "1953",
                    "institution": "NULL"
                },
                {
                    "degree": "Med lic",
                    "year": "1958",
                    "institution": "Göteborg"
                }
            ],
            "career": [
                {
                    "position": "Aman farmakol inst",
                    "years": {
                        "start_year": 1953,
                        "end_year": 1957
                    },
                    "organization": "Gbgs univ"
                },
                {
                    "position": "Öl läk:förordn",
                    "years": {
                        "start_year": 1954,
                        "end_year": 1958
                    },
                    "organization": "NULL"
                },
                {
                    "position": "Underläk barnavd Borås las",
                    "years": {
                        "start_year": 1959,
                        "end_year": 1963
                    },
                    "organization": "Borås las"
                },
                {
                    "position": "Gbgs barnsjh",
                    "years": {
                        "start_year": 1963,
                        "end_year": 1963
                    },
                    "organization": "Gbgs barnsjh"
                }
            ],
            "family": {
                "spouse": "Inger Lindberg",
                "marriage_year": "1956",
                "children": [
                    {
                        "name": "Ånn",
                        "birth_year": "1957"
                    },
                    {
                        "name": "Åse",
                        "birth_year": "1960"
                    },
                    {
                        "name": "Mats",
                        "birth_year": "1962"
                    }
                ]
            }
        },
        "1": {
            "full_name": "VICTORIN, LISA I M",
            "location": "Göteborg",
            "occupation": "Lektor",
            "birth_details": {
                "date": "08/09/1903",
                "place": "Boden",
                "parents": "Lokmäst Johan Adolfsson o Matilda Norberg"
            },
            "education": [
                {
                    "degree": "Folkskollär:ex",
                    "year": "1923",
                    "institution": "NULL"
                }
            ],
            "career": [
                {
                    "position": "Lekt i lågstad metodik",
                    "years": {
                        "start_year": 1963,
                        "end_year": 1963
                    },
                    "organization": "Lärarhögsk Gbg"
                }
            ],
            "family": {
                "spouse": "John Victorin",
                "marriage_year": "1930",
                "children": [
                    {
                        "name": "Lars",
                        "birth_year": "1931"
                    },
                    {
                        "name": "Anita",
                        "birth_year": "1936"
                    },
                    {
                        "name": "Bengt",
                        "birth_year": "1940"
                    }
                ]
            }
        },
        "2": {
            "full_name": "WIDE, EINAR R",
            "location": "Hälleviksstrand",
            "occupation": "Provinsialläkare",
            "birth_details": {
                "date": "01/05/1905",
                "place": "Stockholm",
                "parents": "Med dr P G W o Maria Henningsson"
            },
            "education": [
                {
                    "degree": "Stud:ex",
                    "year": "1923",
                    "institution": "NULL"
                },
                {
                    "degree": "Med kand",
                    "year": "1927",
                    "institution": "NULL"
                }
            ],
            "career": [
                {
                    "position": "Prakt läk",
                    "years": {
                        "start_year": 1935,
                        "end_year": 1946
                    },
                    "organization": "Hbg"
                },
                {
                    "position": "Distr:-läk",
                    "years": {
                        "start_year": 1949,
                        "end_year": 1958
                    },
                    "organization": "Lammhult"
                },
                {
                    "position": "Prov:läk",
                    "years": {
                        "start_year": 1960,
                        "end_year": 1960
                    },
                    "organization": "Orust"
                }
            ],
            "family": {
                "spouse": "Inga M Bretz",
                "marriage_year": "1932",
                "children": [
                    {
                        "name": "Peter",
                        "birth_year": "1933"
                    },
                    {
                        "name": "Monika",
                        "birth_year": "1937"
                    },
                    {
                        "name": "Annika",
                        "birth_year": "1943"
                    }
                ]
            }
        },
        "3": {
            "full_name": "WIDEBERG, TORSTEN V",
            "location": "Lidköping",
            "occupation": "Godsägare",
            "birth_details": {
                "date": "06/07/1901",
                "place": "Gunnarstorp, Kalmar län",
                "parents": "Godsäg Per W o Gerda Olsson"
            },
            "education": [
                {
                    "degree": "Lärov :stud",
                    "year": "1920",
                    "institution": "Kalmar lantmannask Högalid"
                }
            ],
            "career": [
                {
                    "position": "Inneh Västby egend",
                    "years": {
                        "start_year": 1931,
                        "end_year": null
                    },
                    "organization": "Lidkpg"
                }
            ],
            "family": {
                "spouse": "Elsa Heiding",
                "marriage_year": "1935",
                "children": [
                    {
                        "name": "Ingemar",
                        "birth_year": "1935"
                    },
                    {
                        "name": "Margareta",
                        "birth_year": "1937"
                    },
                    {
                        "name": "Estrid",
                        "birth_year": "1942"
                    }
                ]
            }
        },
        "4": {
            "full_name": "WIDEGREN, K ANDERS",
            "location": "Oskarshamn",
            "occupation": "Läroverksadjunkt",
            "birth_details": {
                "date": "10/07/1920",
                "place": "Stockholm",
                "parents": "Avd :ch Sigfrid V o Lydia Westling"
            },
            "education": [
                {
                    "degree": "Stud:ex",
                    "year": "1939",
                    "institution": "NULL"
                },
                {
                    "degree": "Fil kand",
                    "year": "1951",
                    "institution": "Sthlm"
                },
                {
                    "degree": "Fil mag",
                    "year": "1952",
                    "institution": "Sthlm"
                }
            ],
            "career": [
                {
                    "position": "Rekt realsk",
                    "years": {
                        "start_year": 1955,
                        "end_year": 1961
                    },
                    "organization": "Borgholm"
                },
                {
                    "position": "Adj i fysik o kemi hal",
                    "years": {
                        "start_year": 1963,
                        "end_year": 1963
                    },
                    "organization": "Oskarshamn"
                }
            ],
            "family": {
                "spouse": "Aina Nilsson",
                "marriage_year": "1950",
                "children": [
                    {
                        "name": "Annika",
                        "birth_year": "1951"
                    },
                    {
                        "name": "Ragnar",
                        "birth_year": "1953"
                    },
                    {
                        "name": "Lena",
                        "birth_year": "1955"
                    }
                ]
            }
        },
        "5": {
            "full_name": "WIDEGREN, JAN E S",
            "location": "Skövde",
            "occupation": "Ryttmästare",
            "birth_details": {
                "date": "26/10/1918",
                "place": "Nyköping",
                "parents": "Adv Seibrant W o Clary Hedman"
            },
            "education": [
                {
                    "degree": "Stud:ex",
                    "year": "1938",
                    "institution": "Stockholm"
                },
                {
                    "degree": "Off:ex",
                    "year": "1942",
                    "institution": "NULL"
                }
            ],
            "career": [
                {
                    "position": "Fänr K 4",
                    "years": {
                        "start_year": 1942,
                        "end_year": 1961
                    },
                    "organization": "NULL"
                }
            ],
            "family": {
                "spouse": "Barbro Lindblom",
                "marriage_year": "1949",
                "children": [
                    {
                        "name": "Dick",
                        "birth_year": "1951"
                    },
                    {
                        "name": "Anne",
                        "birth_year": "1961"
                    }
                ]
            }
        },
        "6": {
            "full_name": "WIDEGREN, SVEN A",
            "location": "Linköping",
            "occupation": "Överste",
            "birth_details": {
                "date": "18/11/1910",
                "place": "Linköping",
                "parents": "Civ :ing Sven W o Götha Wetterhall"
            },
            "education": [
                {
                    "degree": "Fänr",
                    "year": "1932",
                    "institution": "NULL"
                }
            ],
            "career": [
                {
                    "position": "Lär InfSS",
                    "years": {
                        "start_year": 1941,
                        "end_year": 1963
                    },
                    "organization": "I 4"
                }
            ],
            "family": {
                "spouse": "Britt-Marianne Widell",
                "marriage_year": "1937",
                "children": []
            }
        },
        "7": {
            "full_name": "WIDEHED, GILLIS",
            "location": "Kalmar",
            "occupation": "Länsassessor",
            "birth_details": {
                "date": "11/11/1924",
                "place": "Jönköping",
                "parents": "Egend:-mäkl Wiking W o Esther Carlsson"
            },
            "education": [
                {
                    "degree": "Stud:ex",
                    "year": "1943",
                    "institution": "Karlskrona"
                },
                {
                    "degree": "Jur kand",
                    "year": "1949",
                    "institution": "Lund"
                }
            ],
            "career": [
                {
                    "position": "E länsnot",
                    "years": {
                        "start_year": 1960,
                        "end_year": 1960
                    },
                    "organization": "Kalmar l"
                }
            ],
            "family": {
                "spouse": "Agneta Bokander",
                "marriage_year": "1949",
                "children": [
                    {
                        "name": "Rolf",
                        "birth_year": "1958"
                    }
                ]
            }
        },
        "8": {
            "full_name": "WIDELL, ARNE K F",
            "location": "Jönköping",
            "occupation": "Bitr länsläkare",
            "birth_details": {
                "date": "13/04/1924",
                "place": "Gothenburg",
                "parents": "Apot Fredrik W o Gerda Lindholm"
            },
            "education": [
                {
                    "degree": "Stud:ex",
                    "year": "1944",
                    "institution": "Borås"
                },
                {
                    "degree": "Farm kand",
                    "year": "1947",
                    "institution": "NULL"
                },
                {
                    "degree": "Med kand",
                    "year": "1950",
                    "institution": "NULL"
                }
            ],
            "career": [
                {
                    "position": "Underläk barnklin",
                    "years": {
                        "start_year": 1956,
                        "end_year": 1959
                    },
                    "organization": "Vänersborgs las"
                },
                {
                    "position": "Prov :läk",
                    "years": {
                        "start_year": 1960,
                        "end_year": 1964
                    },
                    "organization": "Bjurholm"
                }
            ],
            "family": {
                "spouse": "Elsa Amdisen Jensen",
                "marriage_year": "1953",
                "children": []
            }
        },
        "9": {
            "full_name": "WIDELL, HANS C-A",
            "location": "Brussels, Belgium",
            "occupation": "Director",
            "birth_details": {
                "date": "30/04/1922",
                "place": "Stockholm",
                "parents": "Dir Sten W o Margareta Falkenberg"
            },
            "education": [
                {
                    "degree": "Bröd Påhlmans hdlI",
                    "year": "1942",
                    "institution": "NULL"
                }
            ],
            "career": [
                {
                    "position": "Verkst dir",
                    "years": {
                        "start_year": 1962,
                        "end_year": null
                    },
                    "organization": "Facit-Odhner SA Bryssel"
                },
                {
                    "position": "Styr :led",
                    "years": {
                        "start_year": 1963,
                        "end_year": null
                    },
                    "organization": "Sv hdlskamm Bryssel"
                }
            ],
            "family": {
                "spouse": "Marianne Drakenberg",
                "marriage_year": "1946",
                "children": []
            }
        },
        "10": {
            "full_name": "WIDELL, STEN F A",
            "location": "Kalmar",
            "occupation": "Docent, överläkare",
            "birth_details": {
                "date": "18/02/1922",
                "place": "Gothenburg",
                "parents": "Apot Fredrik W o Gerda Lindholm"
            },
            "education": [
                {
                    "degree": "Stud:ex",
                    "year": "1940",
                    "institution": "Borås"
                }
            ],
            "career": [
                {
                    "position": "Överläk barnklin",
                    "years": {
                        "start_year": 1961,
                        "end_year": null
                    },
                    "organization": "Kalmar las"
                }
            ],
            "family": {
                "spouse": "Margareta Enemark",
                "marriage_year": "1950",
                "children": [
                    {
                        "name": "Björn",
                        "birth_year": "1954"
                    }
                ]
            }
        }
    }
}