{
    "original": "Volvofinans, Gbgs bk. - Medl Rotary.\n- Hobbies: segling, fiske.\nGift 39 m Sigrid Sahlin f 08, dtr t\nförman Ernst S o h h. - Barn: Margareta\nf 36 (adoptivdtr), Eva-Britt f 42, Lars\nTomas f 47.\n\nWASSÉNIUS, SVEN R, tandläkare,\nVänersborg, f i Vänersborg 30/9/27 av\nchefred K G W o Aina Sundelius.\nStud:ex 46, tandl:ex Malmö 54,\ndistr:-tandl Trollhättan 54-59, ass:tandl där\n59-63, priv:prakt Vänersborg sed 63. -Sekr\nVästg-Dals o Älvsb lokalavd av Sv:es\ntj :tandl 56-58; medl Round Table,\nFrimO.\n\nGift 52 m sjukgymn Gunhild Ingvarsson\nf 30, dtr t överläk Glo Wända\nMalmström. - Barn: Ann f 55, Jan f 60.\n\nWASTENSON,  BRITA,  bibliotekarie,\n\nLinköping, f i Malmö 15/3/08 av apot\nHugo W o Lalla Jeurling.\nFil mag Upps 33, bibl:sk 40, nord\nfort-bildn:kurs Köpenh 49 o Borgå 51; tf\nstadsbibl:ie Katrineholm 41, bibl:ass\nGävle 44, stadsbibl:ie Nynäshamn 48,\nbibl:ie o förest vetensk avd stifts- o\nlandsbibi Linkpg sed 60. - Sekr TBV:s\nlokalkomm Gävle 45-46, lokalavd f\nSödermani-Östergötl av Tekn litt :sällsk sed\n\n62. - S kr: Nynäshamns stadsbibl (51 o\n\n53).\n\nWATTENBERG, E INGVAR H,\nintendent, Uddevalla, f i Uddevalla 21/6/22\nav trafikbitr Ernst W o Anna Eliasson.\nHögre folksk tekn linje 38, anst Sv ab\nTubus 38, ritare DK Uddevalla 45,\nfastigh:förv Uddevallavarvet ab 51, intend\nB ost :stift Uddevallahem sed 53. -\nKassör Sv komm :arb :f örb avd 184 47-48,\nled o ordf brandstyr sed 62 (suppl\n59-61). - Hobbies: båtsport, snickeri,\nträdgårdsskötsel.\n\nGift 47 m Annalisa Green f 24, dtr t\ntyghantverk Carl G o Signe Olausson.\n-Barn: Göran f 51.\n\nWATTSGÅRD, GÖTE E A, tandläkare,\n\nGbg, f i Alfshög, Hall l, 7/1/15 av lantbr\nAlfred Carlson o Sofie Johansson.\nStud:ex Halmstad 33, tandl :ex Sthlm 39,\nass:tandl Östad o Fritsla 39, tandl\nfolk-tandv sed 39 o l:e distr:tandl Gbg sed\n52. - Kassaförvalt Gbgs tandl :sällsk\nf örb :avd t j :sekt 50-51, v ordf 52, led dess\nvalnd 54-55 o 62-64, rev Gbgs\ntandl:-sällsk 58-61, led företagsndn folktandv\nGbg 64-65. - Medl Gbgs konserthuskör.\nGift 41 m Ingrid Berntsson f 20, dtr t\ntullöverkontr Nils B o Karin Lundskog.\n- Barn: Jan f 43, Anne-Louise f 45.\n\nWEBERITSCH, WALTER E, bitr\növerläkare, Gbg, f i Wien 13/10/20 av\nbank-kamr Johann W o Rosa Zehetner.\nStud:ex 39 o läk:ex Wien 46, underläk v\nodelat las 46-49, v neurolog-psyk klin\n49-51, under läk :förordn v mentals jh o\npsyk las :klin :er i Sv :e 51-61, överläk f\nfamiljevård o hjälpverksamh Säters sjh\n61-63, bitr överläk f öppen vård S:t\nJörgens sjh Gbg sed 64.\n\nGift 45 m Elisa Dietze f 22, dtr t\nfolkskollär Paul D o Hilda Leuschner.\n-Barn: Ingrid f 46, Veronica f 62.\n\nWEBY, ÅKE V, chefsåklagare, Skara, f\ni Laske-Vedum, Skarab l, 18/6/05 av\nspannm:handl Anders Johansson o Olga\nLundgren.\n\nRealex 21, landsfiskalsex 26; landsfiskal\nGötene 33, chefsåkl Skara sed 65. - Led\nkpgsfullm o hälsov:nd Götene samt\nordf Götene skyttegille, Götene\nhemb:-o fornm:fören, Götene högerfören.\n-Utm: RNO, Skarab sfbftjM, Skarab\njakt-v:förb ftJM, Skarab cfbftjM, skyttem.\n-Hobby: jakt.\n\nGift 36 m Greta Olsson, dtr t köpm\nOlof O o h h. - Barn: Marianne f 39,\nKerstin f 44.\n\n",
    "structured": {
        "0": {
            "full_name": "Sven R Wassénius",
            "location": "Vänersborg",
            "occupation": "Tandläkare",
            "birth_details": {
                "date": "30/09/1927",
                "place": "Vänersborg"
            },
            "education": [
                {
                    "degree": "Stud:ex",
                    "year": "1946",
                    "institution": "Unknown"
                },
                {
                    "degree": "Tandl:ex",
                    "year": "1954",
                    "institution": "Malmö"
                }
            ],
            "career": [
                {
                    "position": "Distr:-tandl",
                    "years": {
                        "start_year": 1954,
                        "end_year": 1959
                    },
                    "organization": "Trollhättan"
                },
                {
                    "position": "Ass:tandl",
                    "years": {
                        "start_year": 1959,
                        "end_year": 1963
                    },
                    "organization": "Trollhättan"
                },
                {
                    "position": "Priv:prakt",
                    "years": {
                        "start_year": 1963
                    },
                    "organization": "Vänersborg"
                }
            ],
            "family": {
                "spouse": "Gunhild Ingvarsson",
                "marriage_year": "1952",
                "children": [
                    {
                        "name": "Ann",
                        "birth_year": "1955"
                    },
                    {
                        "name": "Jan",
                        "birth_year": "1960"
                    }
                ]
            }
        },
        "1": {
            "full_name": "Brita Wastenson",
            "location": "Linköping",
            "occupation": "Bibliotekarie",
            "birth_details": {
                "date": "15/03/1908",
                "place": "Malmö"
            },
            "education": [
                {
                    "degree": "Fil mag",
                    "year": "1933",
                    "institution": "Uppsala"
                },
                {
                    "degree": "Bibl:sk",
                    "year": "1940",
                    "institution": "Unknown"
                },
                {
                    "degree": "Nord fort-bildn:kurs",
                    "year": "1949",
                    "institution": "Köpenhamn"
                },
                {
                    "degree": "Nord fort-bildn:kurs",
                    "year": "1951",
                    "institution": "Borgå"
                }
            ],
            "career": [
                {
                    "position": "Tf stadsbibl:ie",
                    "years": {
                        "start_year": 1941
                    },
                    "organization": "Katrineholm"
                },
                {
                    "position": "Bibl:ass",
                    "years": {
                        "start_year": 1944
                    },
                    "organization": "Gävle"
                },
                {
                    "position": "Stadsbibl:ie",
                    "years": {
                        "start_year": 1948
                    },
                    "organization": "Nynäshamn"
                },
                {
                    "position": "Bibl:ie o förest vetensk avd stifts- o landsbibi",
                    "years": {
                        "start_year": 1960
                    },
                    "organization": "Linköping"
                }
            ]
        },
        "2": {
            "full_name": "E Ingvar H Wattenberg",
            "location": "Uddevalla",
            "occupation": "Intendent",
            "birth_details": {
                "date": "21/06/1922",
                "place": "Uddevalla"
            },
            "education": [
                {
                    "degree": "Högre folksk tekn linje",
                    "year": "1938",
                    "institution": "Unknown"
                }
            ],
            "career": [
                {
                    "position": "Anst",
                    "years": {
                        "start_year": 1938
                    },
                    "organization": "Sv ab Tubus"
                },
                {
                    "position": "Ritare",
                    "years": {
                        "start_year": 1945
                    },
                    "organization": "DK Uddevalla"
                },
                {
                    "position": "Fastigh:förv",
                    "years": {
                        "start_year": 1951
                    },
                    "organization": "Uddevallavarvet ab"
                },
                {
                    "position": "Intend",
                    "years": {
                        "start_year": 1953
                    },
                    "organization": "B ost :stift Uddevallahem"
                }
            ],
            "family": {
                "spouse": "Annalisa Green",
                "marriage_year": "1947",
                "children": [
                    {
                        "name": "Göran",
                        "birth_year": "1951"
                    }
                ]
            }
        },
        "3": {
            "full_name": "Göte E A Wattsgård",
            "location": "Gbg",
            "occupation": "Tandläkare",
            "birth_details": {
                "date": "07/01/1915",
                "place": "Alfshög, Hall l"
            },
            "education": [
                {
                    "degree": "Stud:ex",
                    "year": "1933",
                    "institution": "Halmstad"
                },
                {
                    "degree": "Tandl :ex",
                    "year": "1939",
                    "institution": "Sthlm"
                }
            ],
            "career": [
                {
                    "position": "Ass:tandl",
                    "years": {
                        "start_year": 1939,
                        "end_year": 1939
                    },
                    "organization": "Östad o Fritsla"
                },
                {
                    "position": "Tandl folk-tandv",
                    "years": {
                        "start_year": 1939
                    },
                    "organization": "Unknown"
                },
                {
                    "position": "L:e distr:tandl",
                    "years": {
                        "start_year": 1952
                    },
                    "organization": "Gbg"
                }
            ],
            "family": {
                "spouse": "Ingrid Berntsson",
                "marriage_year": "1941",
                "children": [
                    {
                        "name": "Jan",
                        "birth_year": "1943"
                    },
                    {
                        "name": "Anne-Louise",
                        "birth_year": "1945"
                    }
                ]
            }
        },
        "4": {
            "full_name": "Walter E Weberitsch",
            "location": "Gbg",
            "occupation": "Bitr överläkare",
            "birth_details": {
                "date": "13/10/1920",
                "place": "Wien"
            },
            "education": [
                {
                    "degree": "Stud:ex",
                    "year": "1939",
                    "institution": "Unknown"
                },
                {
                    "degree": "Läk:ex",
                    "year": "1946",
                    "institution": "Wien"
                }
            ],
            "career": [
                {
                    "position": "Underläk v odelat las",
                    "years": {
                        "start_year": 1946,
                        "end_year": 1949
                    },
                    "organization": "Unknown"
                },
                {
                    "position": "Bitr överläk f familjevård o hjälpverksamh",
                    "years": {
                        "start_year": 1964
                    },
                    "organization": "S:t Jörgens sjh Gbg"
                }
            ],
            "family": {
                "spouse": "Elisa Dietze",
                "marriage_year": "1945",
                "children": [
                    {
                        "name": "Ingrid",
                        "birth_year": "1946"
                    },
                    {
                        "name": "Veronica",
                        "birth_year": "1962"
                    }
                ]
            }
        },
        "5": {
            "full_name": "Åke V Weby",
            "location": "Skara",
            "occupation": "Chefsåklagare",
            "birth_details": {
                "date": "18/06/1905",
                "place": "Laske-Vedum, Skarab l"
            },
            "education": [
                {
                    "degree": "Realex",
                    "year": "1921",
                    "institution": "Unknown"
                },
                {
                    "degree": "Landsfiskalsex",
                    "year": "1926",
                    "institution": "Unknown"
                }
            ],
            "career": [
                {
                    "position": "Landsfiskal",
                    "years": {
                        "start_year": 1933
                    },
                    "organization": "Götene"
                },
                {
                    "position": "Chefsåkl",
                    "years": {
                        "start_year": 1965
                    },
                    "organization": "Skara"
                }
            ],
            "family": {
                "spouse": "Greta Olsson",
                "marriage_year": "1936",
                "children": [
                    {
                        "name": "Marianne",
                        "birth_year": "1939"
                    },
                    {
                        "name": "Kerstin",
                        "birth_year": "1944"
                    }
                ]
            },
            "honorary_titles": [
                {
                    "title": "RNO",
                    "institution": "Unknown",
                    "year": "Unknown"
                }
            ],
            "hobbies": [
                "Jakt"
            ]
        }
    }
}