{
    "original": "Vänersborg, f i Ulricehamn 12/1/05 av\nkronofogde Vilhelm Svensson o Estrid\nEngström.\n\nStud:ex Vänersb 23, jur kand StHS 28,\ntingstjg Nordals, Sundals o Valbo doms\n28-31, eo länsnot Älvsb l 31, rådm\nVänersb sed 37, stadsfogde där 37-44.\n-Styr :led riksbkns avd :kont Vänersb sed\n37, stat skol- o yrkeshem Laxå sed 56.\n-Medl FrimO. - Utm: RVO. - Hobby:\nmusik.\n\nGift 34 m Maj Håkansson f 10, dtr t\ngodsäg Elis H o Ellen Eriksson. - Barn:\nMarianne f 35, Håkan f 38, Sven f 45.\n\nWESTHOLM, AINA D K, tandläkare,\n\nJönköping, f i Sthlm 17/7/01 av\nriksbks-kamr Gustav Norell o Anna Ericsson.\nStud:ex 21 o tandl:ex Sthlm 24,\npriv:-prakt Vetlanda 24-28, Norrahammar\n29-32, skoltandl Jönkpg 32-54, distr:tandl\ndär sed 54. - Skr: art om kariesprofylax.\n\n-  Utm: LNO.\n\nGift 28 m bankjur Karl Westholm f 99.\n\n-  Barn: Ulla f 29, Sten f 33, Arne f 38.\nWESTHOLM,   D   ALFRED,   docent,\n\nmuseichef, Gbg, f i Falun 22/6/04 av\nlekt Alfr W o Anna Bäckström.\nFil kand o fil lic Sthlm 32, fil dr o doc\ni konsthist StHS 36, Gbgs univ sed 45.\n-Delt i arkeol utgrävn i Sv :e 25, i de sv\nAsine- o Dendraexp 26-27, i sv\nCypern-exp 27-31, förest Cypernsaml 34-46, l:e\naman Gbgs konstmus 45, museich sed\n48. - Rapportör f Sv:e v NF:s kongr f\nutgrävn i Kairo 37, sekr Gbgs stads\nkonstnd sed 46, 45 års museisakk,\nValands konstsk nd sed 48, ordf där sed 58,\nsekr ndn f Charles Felix Lindbergs\ndonationsfond Gbg sed 48, led sv Rom-\n\ninst vänners styr sed 49, Gbgs konstmus\nnd sed 48, styr :led Gbgs konstfören sed\n52, Zornsaml Mora sed 53, Riksförb f\nbild konst sed 54, Nord konstförb sed\n58, Adlerbertska stip :fonden sed 58, rev\nCarl o Olga Milles’ stift sed 51, ss expert\nf Unesco planerat Museo de Arte i Lima\nPeru 57, ledare sv Labraunda-exp 60.\n-KorrLDAI 53, LVVS 55. - Skr: The\ntemples of Soli (36), medarb The Swed\nCyprus Exp I-IV (34-57), Milles (50),\nGbgs Konstmus (tills m Nils Ryndel 51),\nLabraunda 1:2 The Architecture (63), skr\ni arkeol o konsthist, red Asine, results of\nthe Swed Excav 22-30 (38), årl rapporter\no upps i Gbgs konstmus årstryck sed 48.\n\n-  Utm: KNO, RVO, KGrFenO, RFrHL.\n\n-  Hobbies: fiske, foto.\n\nGift 40 m Ingegärd Beskow f 09, dtr t\ngen :dir Jakob B o Esther Olsen. - Barn:\nAnna f 41, Olof f 42, Per f 44, Helena\nf 49, Erik f 51.\n\nWESTHOLM,   KARL   A,   bankjurist,\n\nJönköping, f i V Färnebo, Västmanl l,\n25/6/99 av lekt, fil dr Alfred W o Anna\nBäckström.\n\nStud:ex Falun 18, jur kand StHS 23,\ntingstjg 23-25, fisk o adj led Göta hovr\n26-32, omb :man Länssparbkn Jönkpg\nsed 32. - Verkst led styr f Stift Anna\nKjellbergs minne sed 54. - Medl\nRo-tary. - Hobby: musik.\nGift 28 m Aina Norell f 01, dtr t\nriks-bkskamr Gustaf N o Anna Ericsson.\n-Barn: Ulla f 29, Sten f 33, Arne f 38.\n\nWESTHOLM, STEN A, fd\nstadsarkitekt, Linköping, f i Sthlm 22/4/98 av\nlekt Alfred W o Anna Bäckström.\nKTH 22, stud KKH 23-25,\narkit:verk-samh Sthlm 25-30, arkit byggn :styr 31,\nstadsarkit Linkpg 31-63. - Byggn\n:konsulent Åtvidaberg sed 34; styr:led SAR 37^\n40, 52-53, ordf Fören f konst Linkpg\n40-54, styr :led Östgöta konstfören 42-54, v\nordf Linkpgs orkesterfören sed 57i, l:e\nviolinist där. - Bl arb: krematorium,\nfriluftsbad, polishus, tullhus, folkskolor.\n-Utm: RNO. - Hobby: musik.\nGift 36 m Elsa Thimgren f 06, dtr t apot\nEmil T o Alma Andersson. - Barn:\nBertil f 37.\n\nWESTIN, L ARNE W W,\ncivilingenjör, Lerum, f i Norrkpg 28/12/11 av ing\nLars W o Wera Wijk.\nStud:ex Gbg 31, res:off:ex 34, CTH 39,\nanst Sv ackumulator ab Jungner Sthlm\n39, ch Jungnerbol filial Gbg sed 41.\n-Led Älvsb l landst 63, komm:fullm 59,\nkomm :nd 56. - Kapt i res. - Medl Odd\n\nFellow. - Hobbies: sport,\nträdgårdsskötsel.\n\nGift 39 m Karin Bulow f 15, dtr t\nfond-mäkl G H B o Anna Engström. - Barn:\nAgneta f 41, Jan f 43, Ingela f 46.\n\nWESTIN, E HUGO, borgmästare,\nUddevalla, f i Malmö 11/1/06 av\npolisöver-konst Gustav W o Hilda Maria\nMagnusson.\n\nJur kand Lund 30, e fiskal Göta hovr\n34, adj led 39-40, tingssekr 35-38, borgm\nUddevalla sed 40 (tf 38-39). - Utm:\nRNO.\n\nGift 35 m ämneslär Gunhild Wessman\nf 05, dtr t jvtjm J A A W o Malin\nBörjesson. - Barn: Lars f 37, Carin f 42.\n\nWESTIN, KJELL H K W, direktör,\nGbg, f i Gbg 5/4/09 av civ:ing Lars W\no Wera Wijk.\n\nStud:ex 27, GbgHdlI 28, anst ab Gbgs\nbk 30, inneh ab Kjell Westin &amp; Co\n37-43, f:a Kjell Westin 45-53, verkst dir o\ninneh Gbgs fototekn ab Gefa sed 41.\n-Styr :led Gbgs fotogr fören. - Utm: v kr\nav Sv fotogr fb ftjtG. - Hobbies: tennis,\nskidsport.\n\nGift m Lilly Wendel, dtr t Hjalmar W\no Betty Brink. - Barn: Lars f 42,\nMarianne f 46.\n\nWESTIN, J OLOF, redaktör, Kalmar,\nf i Själevad, Västernorrl l, 5/7/27 av fabr\nOlof W o Ester Johansson.\nStud:ex Upps 50, stud i statskunskap,\nsekr riksd :högerns kansli 51-52, medarb\nBarometern 53, red o ansv utg Ung\nHöger 54-56, red :sekr Högerpr nyh :byrå\n57, polit red Barometern 57, 2:e red där\nsed 61. - Ordf Fören yngre högerjourn\no ordf dess nord samarb :komm 63.\n-Arvid Lindman-stip 60. - Nämndem\nKalmar rådhusr 60. - Medl SHT, Odd\nFellow. - Utg: Proportionell skatt (tills m\nN Hansson).\n\nGift 53 m Margaretha Dahl-Fristedt, dtr\nt ing G Dahl o Margreth Kullberg.\n-Barn: Katarina f 54, Helena f 57.\n\nWESTLANDER, TÖRE, bitr\növerläkare, Alingsås, f i Motala 28/3/24 av\nlärov :adj Eskil W o Olga Eeg-Olofsson.\nStud:ex 42 o med kand Upps 45, med\nlic Lund 50, öl läk:förordn 50-52, e läk\nbarnavd Borås las 52-56, underläk med\navd Alingsås las 56-63, bitr överläk där\nsed 63.\n\nGift 52 m Stina Eskilander f 29, dtr t\nköpm Olle E o Signe Berg. - Barn:\nElisabeth f 53, Per Olof f 55, Göran f 57.\n\nWESTLIN, ERIK J, rektor, Svenljunga,\nf i Nianfors, Gävleb l, 29/8/01 av utläst\nPer Gustaf W o Kristina Wiman.\n\nStud:ex Hudiksvall 20, fil mag 31,\nprov-år Vasa hal Gbg 39-40. - Tjg Söderhamn\n32, Huskvarna 32-33, Gbg 35-36, Malmö\nkomm mellansk 36-37, Hallsberg 37-38,\nrekt o lär högre folksk Svenljunga 38-39\no 40-41, komm mellansk där 42-46, rekt\no adj samrealsk där sed 46; l:e rekt\nSvenljunga kpg 58-63. - Led komm:fullm\nSvenljunga sed 59. - Medl FrimO,\nW-sex. - Utm: RNO.\n\nGift 40 m Edith Ringqvist f 04, dtr t\nbokhåll Lars R o Märta Olsson.\n\nWESTLIN, JANNE E N,\npolisöverin-tendent,   Gbg,   f   i   Jönkpg   8/2/03   av\ngrossh Johan W o Charlotte Hellman.\nStud:ex Gbg 21, jur kand Lund 26,\ntingstjg Norrvikens doms 26-29, tjg polisväs\nGbg 29, lär polissk där 29-31, bitr\npolis-intend 32, krim:polisintend 37,\npolisöver-intend  sed  65.   -   Utm:  RVO,  RDDO,\nNFrK, DFrM.\nGift 43 m Anna Engström. - Barn: Ulf.\n\nWESTLING, BERTIL G-A, direktör,\nGbg, f i Gbg 6/11/15 av jvtjm Axel W\no Franciska Heintges.\nStud:ex 36, off:ex 38, GbgHdlI 39,\nfolk-sk:lär:ex 40. - Off 40-47, verkst:- o\nförsäljn :ch Automobilfirma Hj Wallin ab\n45, ekon :dir där 54, verkst dir 56,\nPhi-lipsons bil ab Sthlm sed 61. - Led\nMotorbranschens arb:giv:förb,\nMotorbranschens tekn råd, Gbgs\nautomobilhandl:-fören, Sv Fordhandl:fören, Autorigo ab.\n- Medl Odd Fellow. - Hobbies:\nnumis-matik, trädgårdsskötsel, segling, golf,\nmålning, trä- o metallarbeten.\nGift 61 m tandl Lilian Bretz f 28, dtr t\ntullkontr Otto B o Jenny Hellström.\n-Barn: Karin f 62, Johan f 64.\n\nWESTLING,   KÅRE   P   G,   advokat,\nSkövde, f i Gbg 5/4/22 av folkskollär\nPer W o Ruth Wåhlin.\nStud:ex Skövde 43, jur kand Lund 50,\nbitr  jur  å  adv :by rå  Skövde  51-56,  eg\nadv :verksamh där sed 56. - LSA 56.\nGift 54 m Margareta Bergvall f 26.\n-Barn: Torgny f 55.\n\nWESTLING, LILIAN M, tandläkare,\nGbg,  f  i  Malmö  26/1/28  av tullkontr\nOtto Bretz o Jenny Hellström.\nStud:ex 47 o tandl :ex Malmö 52, aman\navd f dental röntgendiagn THS Malmö\n51-52, distr:tandl Söderfors 52-53,\nskol-tandl Malmö 53-60, Gbg sed 60. -\nStyr:-led Gbgsavd av Sv tj :tandl :f ören.\nGift 61  m dir Bertil Westling f 15.\n-Barn: Karin f 62, Johan f 64,\n\nWESTLING, SUNE K A, brandchef,\nGbg, f i Västervik 12/9/10 av l:e\npostil-jon Paul W o Hilda Jansson.\n\nStud:ex Norrkpg 29, CTH 33,\nbrand-ing:ex Sthlm 37, brandmäst Borås 37-38,\nv brand :ch Karlskrona 38-40, brandkapt\nGbg 41-48, v brand:ch 48-62, brandch\nsed 63. - Styr:led Gbgs arb :skyddsf ören\nsed 47, Gbgs o Bohus l brandkårsförb\nsed 62, Gbgs ind :luftskyddsfören sed 64.\n\n-  Medl Rotary. - Utm: RLFSftjtS,\nSCF-ftjtG,   Brand-   o   livförsäkr   ab   Svea’s\nftjtG, Fören f arb:skyddftjG, Städ\nför-säkr:bolGM. - Hobbies: fiske, botanik,\nbridge.\n\nGift 38 m Ann-Mari Bäckman f 10, dtr\nt inställ Carl B o Hulda Burlin. - Barn:\nMonika f 39, Kjell f 43, Lena f 46.\n\nWESTLUND, E HELLEN,\ncivilekonom, Gbg, f i Karup, Kristianst l, 27/1/\n30 av lantbr Martin Wallin o Vendela\nPettersson.\n\nDHG 54, hdlslär Hbgs hdlsgymn 54,\nred :sekr tidskr Ekonomen o studierekt\nSCF 55-58, bitr lär i företagsekonomi\nUpps univ sed 59. - Styr :led Nät :ekon\nfören Upps 59-60, Kursverksamh Upps\n59-60, led Ekonomens red :råd o SCF :s\nkursråd sed 59. - Hobbies: vintersport,\ntennis, segling.\nGift 60 m civilekonom K-E Westlund.\n\n-  Barn: Annika f 64.\n\nWESTLUND, KARL-ERIK,\ncivilekonom, Gbg, f i Gävle 4/12/27.\nIng:ex HTL 49, DHG 56; ing Sv:es\nmöbelind:förb 50-51, aman IDAF Gbg\n55, org :konsult org :ndn Borås 57,\nstadskoll Gbg sed 59.\n\nGift 60 m Hellen Wallin f 30, dtr t\nlantbr Martin W o Vendela Pettersson.\n\n-  Barn: Anna-Maria f 54, Annika f 64.\n\nWESTMAN, J ALVAR, fil lic,\nstatistikchef, Gbg, f i Vilhelmina, Västerb l,\n7/7/15 av leg läk Arvid W o Olga Olson.\nStud:ex Gbg 34, pol mag 42 o fil lic\nStHS 53; ass Sthlms stad 42, Gbgs stad\n42, aktuarie där 46, ch dess statist kont\nsed 53. - Lär i statistik HHG 51-62.\n-Ordf fastigh :tax :nd sed 60 m fi komm\nuppdr. - Medl TB. - Skr: div broschyrer,\nart i tidn o tidskr, allmänstatist utredn.\n-Hobbies: tennis, fotografering.\nGift 44 m Carin Westeson f 21. - Barn:\nHans f 47, Göran f 48.\n\nWESTMAN, BO I, advokat, Gbg, f i\nSaltsjöbaden 1/8/08 av arkit Carl W o\nElin Cecilia Andersson.\nJur kand Sthlm 31, tingstjg 32-34, bitr\njur å adv :byrå Sthlm 34-35, h adv :na\nGlimstedt o Lindberg Gbg 35-44, eg\nadv:byrå sed 44. - LSA 36. - Skr:\nÄktenskapets juridik (46) m m; radioprogram.\n\n-  Utm: KVO.\n\nGift 35-65 m adv Märta Sternberg f 10,\ndtr t grossh Karl S o Nanna Westman.\n-Barn: Peter f 38, Merete f 45.\n\nWESTMAN, KJELL J A, civilingenjör,\ndirektör, Gbg, f i Piteå 10/7/07 av\nprov:-läk Arvid W o Olga Olson.\nStud:ex Halmstad 26, CTH 31, ass\nväg-ing Gbgs o Boh l 31, bitr väging där 36,\nbyrådir VV-styr 43, byråch där 46-55 o\növering arb :markn:styr 48-55, dir Allm\ning :byrån ab sed 55 o verkst dir AIB\nförvaltn ab sed 63. - Styr :ordf Allm\ning:-byrån ab, styr :led Sv vägfören. - Medl\nW-sex. - Utm: RNO.\nGift 33 m gymn :dir Ann Mari von Bahr\nf 09, dtr t civ :ing Per v B o Ellen\nWijkander. - Barn: Gunnel f 34, Stig\nf 36, Barbro f 41, Tom f 47.\n\nWESTMAN, J LAGE, direktör, Gbg,\nf i Piteå 5/3/09 av prov:läk A W o Olga\nOlson.\n\nStud:ex Gbg 28, GbgHdlI 29, anst ab\nOriginal-Odhner 30-39 (dess kont\nBryssel o Paris 31, ch dess franska org\n37-39), LME kassareg ab Sthlm 40, disp\ndess filial Gbg 42, dir o bitr ch\nmassa-avd Ekman &amp; Co ab sed 43. - Hobby:\ntennis.\n\nGift m Mary Gordon Jackson. - Barn:\nAnita f 39, Marianne f 42, Robert f 43.\n\nWESTMAN,   I  MÄRTA   S,   advokat,\n\nGbg, f i Järna, Sthlms l, 8/10/10 av\ngrossh Karl Sternberg o Nanna\nWestman.\n\nJur kand Sthlm 51, bitr jur å adv:byrå\n51-57,   deläg   adv :firman   Bo   Westman\nGbg sed 57. - LSA 56. - Hobby: golf.\nGift 35-65 m adv Bo Westman f 08.\n-Barn: Peter f 38, Merete f 45.\n\nWESTMAN, J RUDOLF,\nläroverksadjunkt, Trollhättan, f i Singö, Sthlms l,\n30/6/01 av kyrkoh Gustaf W o Hulda\nMalmström.\n\nStud:ex Upps 20, fil mag Upps 29, lär\nOrsa 30, Vaxholm 33, Hallsberg 34,\nFinspång 35, provar Gbg 36, lär Linkpg 37,\nadj Borgholm 38, hal Trollhättan sed\n49. - Utm: RNO.\n\nGift 34 m Greta Larsson f 01, dtr t\nköpm Johan L o Alice Olsson. - Barn:\nKerstin f 38.\n\nWESTMAN, C M SIXTEN, kapten,\nintendent,  Gbg,  f i Västerås  24/2/10 av\nciv :ing Erik W o Naéma Klockhoff.\nStud:ex 29,  off:ex KSS  34, KSHS 42;\nfänr flottan 34, underlöjtn 36, löjtn 37,\nkapt   42,   i  res   60;   intend   Fastigh   ab\nGbgsbost sed 60. - Utm: RSO, SLKSM.\nGift 38 m Ingrid Rydbeck f 11, dtr t\n\nkonstn Ture R o Gertrud Bendz. - Barn:\nGörel f 39, Agneta f 41, Hans f 45.\n\nWESTMAR, HELGE J B, kyrkoherde,\n\nNybro, f i Bankeryd, Jönkpgs l, 20/2/10\nav målarmäst Richard Johansson o Elin\nLarsson.\n\nStud:ex Jönkpg 28, teol kand Upps 32,\nprästv 33, past:adj Karda 33, v kommin\nVetlanda 33, kommin Madesjö 39,\nkyr-koh där sed 54. - Studieres USA 61.\n-Ordf Kalmarkr av SPF, RK-kr 41,\nskol-styr 52, byggn:nd 52, kyrkofullm 55,\nförsaml :deleg 63, kyrkoråd 64,\nkyrkogårds-nd 48, föräldrafören Nybro lärov 59.\n-Skr: red o medarb Madesjö sockens\nhistoria I-II (62). - Utm: SRKftjtS.\nGift 36 m Elsa (Essän) Jansson f 11, dtr\nt stat :insp Paul J o Mary Sandström.\n-Barn: Bengt-Olof f 39, Barbro f 43,\nHans f 48.\n\nWESTRIN, CLAES-GÖRAN A, leg\nläkare, Gbg, f i Örebro 10/3/29 av\növ:-löjtn Anders W o Ingrid Sjöström.\nStud:ex Umeå 47, med kand 51 o med\nlic Lund 56, öl läk :förordn 56-57,\nprov:-läk Vindelns ö distr 57-59, vik underläk\nmed klin Bollnäs las 59-60, underläk\npsyk klin Sahlgr sjh sed 60. - Skr i\npsykiatri o socialmedicin.\nGift 55 m fil mag Karin Bergholtz f 30,\ndtr t disp Elof Gustafsson o Ketty\nBergholtz. - Barn: Per f 56, Mats f 58, Åsa\nf 63.\n\nWESTRÖM, FREDRIK V, fd\növerläkare, Växjö, f i Alingsås 31/5/94 av\npostmast Vilhelm W o Dorothea\nNilsson.\n\nMed lic Upps 26, ass :läk Örebro las\n26-27, tf stadsläk Katrineholm m fi\nförordn 27-30, underläk Torsby las 31, 2:e\no l:e läk Mariebergs sjh Kristinehamn\n31-34, överläk Umedalens sjh 34, överläk\no sjh:ch S:t Sigfrids sjh 39-62. - Byråch\nmed:styr o överinsp f sinnessjukv 39-41.\n-Läk Hallanäs sjukhem Alvesta samt psyk\no rättspsyk avd fångv :anst Växjö. - Medl\nSHT. - Utm: RNO.\n\nGift 29 m Edith Westerberg f 01, dtr t\nbyggm Lars W o Kristina Pettersson.\n-Barn: Lars f 30, Ingrid f 31, Ragnhild\nf 40.\n\nWETTER, J BJÖRN, tandläkare,\nLinköping, f i Växjö 30/4/27 av ämneslär\nGustaf W o Millis Anderson.\nStud:ex Norrkpg 47, tandl:ex Malmö 53,\ndistr:tandl  o  förest  Flen   53,  ass:tandl\nDegerfors   54,   Växjö   55-57,   priv:prakt\nLinkpg sed 57. - Medl FrimO. - Hobby:\nbridge.\nGift 53 m tandsköt Birgit Richter f 30,\n\ndtr t köpm Hans R o Sigrid Lindström.\n-Barn: Gunilla f 56, Birgitta f 59, Karin\nf 65.\n\nWETTER, K RAGNAR, direktör, Gbg,\nf i Tranås 1/10/19 av möbelsnick Josef\nW o Hulda Scott.\n\nNöjesarrangör å konserthus,, Cirkus o\nPalace Inn Gbg, Spekeröd o Asa\nfolkparker sed 54, deläg Stenungs-Öns hotell\no restaurant, ag darnfris Salong Intim.\n-Hobbies: idrott, musik.\nGift 53 m Ainah Helgeson.\n\nWETTER, STEN F, bankdirektör, Gbg,\nf i Upps 13/8/14 av prof Folke W o\nMargit von Bahr.\n\nStud:ex 32, jur kand Upps 37, tingstjg\nUpps l s doms 37-39, prakt adv :firma\nLondon 39, anst Friman &amp; Carlander\nadv:byrå Gbg 39, bkjurist o förest\nnot:-avd Sv hdlsbkn Gbg 42, verkst dir\nJonsson, Sternhagen &amp; Co ab 50, bitr dir\nSkand bkn Gbg 55, dir där sed 60.\n-Styr:ordf H Alpen ab sed 60, ab Olof\nEric Bergström sed 62, styr :led Blidberg,\nMetcalfe &amp; Co ab, Haldex ab,\nStensholms fabr ab, ab Syntes, Upsala-Ekeby\nab; v ordf Carlanderska sjukhemmet sed\n58. - Hobby: segling.\nGi/f 40 m Carin Dalen f 16, dtr t prof\nAlbin D o Maja Svedin. - Barn: Johan\nf 41, Gustaf f 44, Carl f 49.\n\nWETTERBERG, K G GEIJER, dispo-\n\niient, Kastlösa, f i Kastlösa, Kalmar l,\n4/4/25 av kvarnmäst Hilding W o Ethel\nHolmström.\n\nYrkeskurs SHI 60, anst inom mejeri\n41-46, ab Kastlösa kvarn 47, ver km 54,\nkont 59, disp där sed 64. - Hobbies:\nbridge, sång, fotografering.\nGift 47 m Birgit Hermansson f 26, dtr t\nhemm:äg Herman Andersson o Hilma\nHedqvist. - Barn: Gunnel f 48,\nLärs-Olov f 50, Hans-Åke f 52, Carl-Gunnar\nf 60, Anette f 61.\n\nWETTERBERG, HANS E,\nbankdirektör, Kalmar, f i Säter 11/7/02 av\nväv-mäst John Nilsson o Eva Wetterberg.\nRealex Uddevalla 17, GbgHdlI 19,\nspråk- o bankstud Frankr o Engl 25-27.\n- Anst Sv hdlsbkn sed 19, dir dess\navd:-central Kalmar sed 47. - Finl konsul i\nKalmar. - Styr:ordf Boda bruks ab, v\nordf styr Kalmar verkst ab. - Medl\nFrimO, Rotary. - Utm: RVO,\nRFinl-VROlkl, FMM.\n\nGift 35 m Mika Flach f 07, dtr t dir\nAxel F o Ellen Kjellström. - Barn:\nMonica f 37, Jan f 39, Ulla f 43,\nBarbro f 45.\n\nWETTERBERG, KARIN, tandläkare,\n\nGbg, f i Sthlm 27/8/15 av jägm August\nSkoog o farm kand Blända Ström.\nStud:ex Upps 34, tandl:ex Sthlm 39,\npriv :prakt Långsele 39-41, tandl\nfolk-tandv Gbg 41-45, skoltandl 45-53,\nskol-tandl Gbg sed 62.\n\nGift 41 m tandl Åke Wetterberg f 09.\n-Barn: Marie-Louise f 42, Anne-Christine\nf 44, Kåre f 49.\n\nWETTERBERG, KARL A K,\ntonsättare, musikpedagog, Gbg, f i Skövde\n31/12/94 av kronofogden, v häradsh\nAbraham W o Martina Lönegren.\nOrg :ex musikkonservat Sthlm 17, stud i\nkontrapunkt f Ernst Bilberg Sthlm o\nJoseph Marx Wien, i kontrapunkt o komp\nf Günter Raphael o Fritz Reuter\nLeipzig samt i piano f Carl Adolf\nMartiens-sen Leipzig. - Musikpedagog verksamh\nSthlm t 32, org Halmstad 37-42,\nmusiklär Gbgs folkskolor o ledare Gbgs\nork:-f ören :s skola f körsång samt lär Gbgs\nork:skola o Gbgs musikkonservat 44-64,\npriv musikpedagog sed 64; tonsättare.\n-Medl Gbgs tonsättarefören. - Bl komp:\nVariationer över en sv folkvisa (f ork,\n33), Melodrama m ork (R M Rilke; 36),\nVariationer f piano över ett eget tema,\nCapricce f piano, Dubbel fuga f\nstråkkvartett, orgel-, pianostycken o sånger;\nsamtl verk uppförda offentl på konserter\ni Gbg, Hfors el London el i sv el ty\nradio.\n\nGift rn Birgitta von der Osten-Säcken,\ndtr t fil dr Baron v d O-S o Dagmar\nDarin.\n\nWETTERBERG, J ÅKE G, tandläkare,\nGbg, f i Örebro 21/6/09 av textiling\nJohannes Nilsson o Eva Wetterberg.\nStud:ex Halden Norge 27, tandl:ex Sthlm\n39,   priv:prakt   Gbg   sed   40.   -   Utm:\nHVII:sFrK. - Hobbies: segling, fiske.\nGift 41  m tandl Karin Skoog f 15.\n-Barn: Marie-Louise f 42, Anne-Christine\nf 44, Kåre f 49,\n\nWETTERGREN, ERIK G,\nbokhandlare, Gbg, f i Gbg 3/4/18 av bokhandl\nVolmar W o Hildur Bergman.\nGbgHdlI 35, utl:stud 35-37, anst\nWetter-grens bokhandel ab 38, v verkst dir 47,\nverkst dir där sed 50. - Medl FrimO,\nPB.\n\nGift 41 m Inger M Berntson f 18, dtr t\nköpm Edgar B o Anna Flodin. - Barn:\nCarl Erik f 42, Ann Elisabeth f 45.\n\nWETTERHQLM, LARS, kamrer,\nNässjö, f i Nässjö  29/5/23  av bankkassör\nGösta W o Swea Sandqvist.\nRealex 40, anst ab Sigfrid Stenberg Näs-\n\nsjö 42, kamr dess dtrbol Nässjö ind ab\nsed 49. - Medl Odd Fellow. - Sportskrib\nGP, skrib IB Sthlm. - Sign: Widing.\n- Hobby: sport (SM bandy 49, medv 2\nSM-finaler 53).\n\nGift 54 m Ingrid Svanberg f 29. - Barn:\nHans f 55, Mats f 62.\n\nWETTERLING, LENNART G E,\nhäradshövding, Växjö, f i Gränna 9/11/10\nav häradsskriv Emil W o Lisa Brolin.\nStud:ex Jönkpg 29, jur kand Upps 34,\ntingstjg 34-37, fiskal Göta hovr 37, sekr\nHall mell doms 40-43, adj led Göta hovr\n44, assess 51 (eo 46), tf rev :sekr 48-52,\nhovr :råd Göta hovr 52, v ordf å avd\n61-62, häradsh Ö Värends doms sed 63.\n-Utm: RNO.\n\nGift 39 m Annie Rosberg f 15, dtr t kapt\nIvar R o Mary Westberg. - Barn: Lena\nf 40, Erik f 46, Karin f 50.\n\nWETTERQVIST, ÅKE K O, prost,\nLerum, f i Falkenberg 16/5/03 av prov :läk\nKarl Oskar W o Hilda Hallberg.\nStud:ex Gbg 21, teol kand Lund 26,\nkommin Öckerö 28-35, kyrkoh Valinge\n36-55, kontr :prost Varberg 52-55, kyrkoh\nLerum sed 55. - Utm: LNO.\nGift 25 m Cecilia Rhedin f 05, dtr t\nkontr :prost Fredrik R o Karin Block.\n-Barn: Gerhard f 26, Barbro f 27,\nGudrun f 29, Törd f 30, Vera f 32 d 32,\nIngrid f 35, Hakon f 36, Per Åke f 39,\nAngela f 42, Yvonne f 45.\n\nWETTERSTRÖM, KARIN H, kamrer,\n\nriksdagsledamot, Linköping, f i Linkpg\n27/3/08 av köpm Helge W o Anna\nLarsson.\n\nKamr Östergötl l hush :sällsk sed 43; led\nAK sed 49 (2:a lagutsk, h), landst:led\nsed 55, led Sv:es civilförsv:förb:s AU\nsed 50, styr :led Östergötl l hemslö\njds-fören sed 47, Östergötl högerförb sed 51\nm fi uppdr. - Utm: LNO.\n\nWETTLEGREN, GÖRAN E,\ncivilingenjör, Mölndal, f i Borås 1/5/30 av\njv:-tjm E Johansson o Nanny Berglund.\nStud:ex 49, CTH 54, konstr h civ:ing\nLennart Werklund Borås 54, ing\nvägför-valtn Gbgs o Boh l 56, arb :ch Sv väg\nab Gbg sed 60.\n\nGift 54 m Margareta Edberg f 31, dtr t\nkamr N H E o Irma Häggström. - Barn:\nIngrid f 57, Magnus f 60.\n\nWEVLE, EINAR J, förste\nlantbrukskonsulent, Kalmar, f i Bollnäs, Gävleb\nl, 31/3/09 av lantbr J Jonsson o Anna\nRahm.\nStud:ex  Hvilans   spec:gymn   36,  agr:ex\n\nKLH 41, lär Bollnäs skogs- o lantm:sk\n40, aman LK 41-42, anst egnahemsstyr\no Sthlms l o stads egnahemsnd 43-48,\nlantbr :konsulent lantbr:ndn Blek l 48,\nl:e lantbr :konsulent lantbr:ndn Kalm l\nsed 63. - Medl Odd Fellow. - Hobbies:\njakt, fiske.\n\nGift 47 m Birgit Tufvesson f 12, dtr t\nkyrkovärd Anders T o h h. - Barn:\nAnders f 50.\n\nWEYDE, H FINN-ERIC, civilingenjör,\nBorensberg, f i Säby, Jönkpgs l, 6/8/17\nav dir Eric W o Elsa Carlstedt.\nStud:ex Sigtuna 36, KTH 41,\narb:studie-ing Sv metallverken Västerås 41,\nEskilstuna stålpressn ab 42-45, verkst dir o\ndeläg ab Elge-Verken Linkpg sed 46\n(styr:led sed 38). - Hobby: segling.\nGift 41 m Cecilia Foek f 18, dtr t frih\nIvar F o Anna Charlotta Widenberg.\n-Barn: Ann-Cathrine f 41, Joakim f 42,\nHenric f 45, Christer f 46.\n\nWHERNMAN, FRANZ O, direktör,\nGbg, f i Skepplanda, Älvsb l, 14/6/15\nav handl Oscar Johansson o Annie\nOhlsson.\n\nIng :ex GTI 39, ing ab Rosengrens\nkassa-skåpsfabr Gbg 39, Trelleborgs\ngummi-fabr ab 40, Saab Trollhättan 41, övering\nSandegards ing :firma 43, verkst dir Franz\nWhernman ab konsult ing :byrå Gbg,\nSthlm, Malmö o Oslo sed 52 samt\nInter-matic ab Gbg o Malmö sed 60, deläg\nkommanditbol Götaholm sed 63. - Medl\nOdd Fellow, Travellers club. - Skr: tekn\nupps i Grafiskt Forum o fackpr. -\nHobby: litteratur.\n\nGift 44 m Brita Mattsson f 24, dtr t\nKarl M o Judit Warenius. - Barn:\nChristina f 45, Anne-Charlotte f 47, Per-Olof\nf 50, Maria f 56, Katarina f 63.\n\nWHITE, J GAYLER, överläkare, Gbg,\nf i Gbg 6/3/02 av köpm John W o Dora\nCarlberg.\n\nStud:ex 20, med kand 27 o med lic Lund\n33, utbildn i psykiatri v öl sjh, aman o\nunderläk psyk klin Lund 34-35 o 40,\nspec :komp i psyk sjukd 41, 2 :e läk S:t\nLars sjh Lund 41, l:e läk 47, överläk\n47, överläk Lillhagens sjh Gbg sed 49,\nstyresman 54-57. - Led sinnessjv :beredn\n47-50. - Skr: upps i histol, neurol o\npsykiatri.\n\nGift 30 m Inger Nilsson f 07, dtr t\nprov :läk Isak N o Bertha Rasmusen.\n-Barn: Thomas f 32, Per f 36, Suzanne\nf 43.\n\nWHITE, SIDNEY, arkitekt SAR, Gbg,\nf i Gbg 30/11/17 av köpm John W o\nDora Carlberg.\n\nKTH 47, anst stadspl:kont Gbg 47-51,\n\negen arkit :verksamh sed 51. - Bl arb:\n\nbost:områden   Gbg,   Örebro,   mentalsjh\n\nGbg.\n\nGift 46 m Eva Fredelius f 23, dtr t\n\nadv Bertil F o Ebba Sjöman. - Barn:\n\nHelen f 47, Maria f 49, Mats f 55.\n\nWIBECK, J EDVARD, professor, fd\n\njägmästare, Tånnö, f i Kållerstad,\nJönkpgs l, 3/3/77 av kronofogde Carl Joh W\no Emma Broberg.\n\nFil kand Lund 01, Klotens skogssk 03,\nskogsinst h kurs 04, jägm Storbackens\nrevir 16, avd :f örest stat skogsförsöksanst\n16, doc i skogsskötsel SkHS 20, lär i\nzool där 35-43, styr:led Sv natursk:fören\n27-43, jägm Örbyhus revir 31, överg t\nindragn:stat 34, t pens:stat 41, på uppdr\nav Sthlms stad utf fotogr o beskr av\nnaturen i o omkr Sthlm 43-31, prof\nnamn 53. - LSLA 30. - Skr huvudsakl i\nskogl o ornitolog ämnen, red Sv:es natur\n35-38. - Utm: RNO, OffFrdeMagr, Sv\nskogsv:fören SM, S:tEM, SvJägFHtG.\nGift 17 m Mina Rosenquist af Åkershult\nf 85, dtr t ing Gust R af Å o Alma\nRosin.\n\nWIDELL,   A   UNO  H,   bankdirektör,\n\nNorrköping, f i Falun 2/2/22 av fabr\nHarry W o Alfhild Karlsson.\nFalu stads hdlssk 41, h bkkurs 54-56,\nbkstud Västtyskl 56. - Anst SHB 36,\nkamr :ass Kalmar 52, kamr Borås 57,\nNorrkpg 59, ch SHB Norrkpg sed 63.\n- Styr:ordf Gust Kjellberg ab 64, styr:led\nSHB Norrkpg 63 (suppl 59). - Medl Odd\nFellow, W-sex, PB, SHT. - Hobby:\nklassisk musik.\n\nGift 47 m Ulla Asp f 29, dtr t musikfanj\nErnst A o Astrid Andersson. - Barn:\nCarina f 48, Ann-Charlotte f 50, Inger\nf 53.\n\nWIBERG, ANDERS R, civilingenjör,\n\ndirektör, Gbg, f i örja, Malmöh l, 2/6/02\nav Anders W o Emma Gerke.\nHTL Malmö 23, KTH 27; lab:ing ab\nSkånebryggerier 23-24, driftsing\nRey-mersholms ab 27-32, chefsing ab Sv:es\nförenade konservfabr 32-36, verkst dir\nab Konservfabr Sirius 37-53, verkst dir o\ninneh ab Kronhöns Lundsbrunn o ab\nAlimenta Gbg sed 53. - Styr:led ab\nKronhöns, ab Alimenta, ab B R F\nGarm. - Styr :led Konservf orskn :inst Gbg\no sekr Stift Sv konservforskn 46-53.\n-Skr: div art i facktidskr o dagspress.\n-Hobbies: konst, antikviteter.\nGift 34 m Ingrid Segerstedt f 11, dtr t\nTorgny S o Augusta Kopp. - Barn:\nLennart f 42.\n\nWIBERG, ARNE G, advokat, Gbg, f i\nSthlm 16/10/97 av postmast Valram W o\nHulda Flodin.\n\nStud:ex Gbg 16, jur kand Lund 21,\ntingstjg Livgedingets doms 22-24, anst ab\nKöpm :byrån Gbg 24-29, eg adv :byrå sed\n29. - LSA 31. - Led Stadsfullm 34-38.\n-Medl Göt förb. - Skr: art i facktidskr.\nGift 34 m Dagmar Andersson f 01, dtr t\nsakför A P A o Hilma A. - Barn: Leif\nf 34, Jan f 37, Claes-Göran f 44.\n\nWIBERG, BO H, agronom, Växjö, f i\nGbg 28/10/23 av överste Hjälte W o\nIsa Lundbohm.\n\nStud:ex Östersund 43, agr:ex KLH\njord-br:linje 51, maskintekn linje 53, ass\nmaskintekn inst Ultuna 51,\nmaskinkonsulent Kronob l hush :sällsk sed 53. -\nHobbies: tennis, segling.\n\nGift 47 m Birgitta Norling f 27, dtr t\nprov:läk Ernst N o Helga Skylling.\n-Barn: Gunilla f 48, Catharina f 52, Ylva\nf 59.\n\nWIBERG, EINAR J, rektor, Kalmar,\nf i Söderfors, Upps l, 7/10/15 av överlär\nJakob W o Gunhild Hallgren.\nSjökapt:ex 38 o stud:ex Sthlm 39,\nres:off:ex 41, navig:lär:ex 42, tjg flottan 39,\nBroströmskonc o Thunbol 45-50, lär\nsjöbef:sk Sthlm 51, rekt sjöbef:sk\nKalmar sed 56. - Medl SHT, Rotary. - Skr:\nArbetsledning till sjöss (58), medarb\nSohlmans sjölexikon 55. - Utm: GMbg.\n- Hobby: golf.\n\nGift 39 m Greta Wollert f 16, dtr t\nlantbr Albin W o Thea Falk. - Barn:\nGunilla f 41, Per-Jakob f 46.\n\n",
    "structured": {
        "SwedishBiographies": [
            {
                "full_name": "WESTHOLM, AINA D K",
                "location": "Jönköping",
                "occupation": "tandläkare",
                "birth_details": {
                    "date": "17/07/1901",
                    "place": "Sthlm"
                },
                "education": [
                    {
                        "degree": "stud:ex",
                        "year": "1921",
                        "institution": "Sthlm"
                    },
                    {
                        "degree": "tandl:ex",
                        "year": "1924",
                        "institution": "Sthlm"
                    }
                ],
                "career": [
                    {
                        "position": "priv:-prakt",
                        "organization": "Vetlanda",
                        "years": {
                            "start_year": 1924,
                            "end_year": 1928
                        }
                    },
                    {
                        "position": "Norrahammar",
                        "organization": "underläk",
                        "years": {
                            "start_year": 1929,
                            "end_year": 1932
                        }
                    },
                    {
                        "position": "skoltandl",
                        "organization": "Jönkpg",
                        "years": {
                            "start_year": 1932,
                            "end_year": 1954
                        }
                    },
                    {
                        "position": "distr:tandl",
                        "organization": "där",
                        "years": {
                            "start_year": 1954,
                            "end_year": null
                        }
                    }
                ],
                "family": {
                    "spouse": "bankjur Karl Westholm",
                    "marriage_year": "1928",
                    "children": [
                        {
                            "name": "Ulla",
                            "birth_year": "1929"
                        },
                        {
                            "name": "Sten",
                            "birth_year": "1933"
                        },
                        {
                            "name": "Arne",
                            "birth_year": "1938"
                        }
                    ]
                }
            },
            {
                "full_name": "WESTHOLM,   D   ALFRED",
                "location": "Gbg",
                "occupation": "docent, museichef",
                "birth_details": {
                    "date": "22/06/1904",
                    "place": "Falun"
                },
                "education": [
                    {
                        "degree": "fil kand",
                        "year": "1932",
                        "institution": "Sthlm"
                    },
                    {
                        "degree": "fil lic",
                        "year": "1932",
                        "institution": "Sthlm"
                    }
                ],
                "career": [
                    {
                        "position": "fil dr o doc",
                        "organization": "i konsthist StHS",
                        "years": {
                            "start_year": 1936,
                            "end_year": null
                        }
                    },
                    {
                        "position": "Gbgs univ",
                        "organization": "sed 45",
                        "years": {
                            "start_year": 1945,
                            "end_year": null
                        }
                    }
                ],
                "family": {
                    "spouse": "Ingegärd Beskow",
                    "marriage_year": "1940",
                    "children": [
                        {
                            "name": "Anna",
                            "birth_year": "1941"
                        },
                        {
                            "name": "Olof",
                            "birth_year": "1942"
                        },
                        {
                            "name": "Per",
                            "birth_year": "1944"
                        },
                        {
                            "name": "Helena",
                            "birth_year": "1949"
                        },
                        {
                            "name": "Erik",
                            "birth_year": "1951"
                        }
                    ]
                }
            },
            {
                "full_name": "WESTHOLM,   KARL   A",
                "location": "Jönköping",
                "occupation": "bankjurist",
                "birth_details": {
                    "date": "25/06/1899",
                    "place": "V Färnebo, Västmanl l"
                },
                "education": [
                    {
                        "degree": "Stud:ex",
                        "year": "1918",
                        "institution": "Falun"
                    },
                    {
                        "degree": "jur kand",
                        "year": "1923",
                        "institution": "StHS"
                    }
                ],
                "career": [
                    {
                        "position": "omb :man",
                        "organization": "Länssparbkn Jönkpg",
                        "years": {
                            "start_year": 1932,
                            "end_year": null
                        }
                    }
                ],
                "family": {
                    "spouse": "Aina Norell",
                    "marriage_year": "1928",
                    "children": [
                        {
                            "name": "Ulla",
                            "birth_year": "1929"
                        },
                        {
                            "name": "Sten",
                            "birth_year": "1933"
                        },
                        {
                            "name": "Arne",
                            "birth_year": "1938"
                        }
                    ]
                }
            }
        ]
    }
}