{
    "original": "Vänersborg, f i Upps 24/6/05 av bruksäg\nGunnar W o Elsa Jansson.\nTegeling Zieglerschule Zwickau 27,\nHin-denburgpolytechnikum Oldenburg 30,\ndriftsch Tenggrenstorps tegelbruk\nVänersborg 34, arrend där sed 57, inneh ab\nÖdeborgstegel sed 60. - Styr :led Wulf\n&amp; Co ab 45. - Hobby: fiske.\nGift 32 m Elisabet Krog f 07. - Barn:\nBjörn f 41, Bo f 47.\n\nWULF, KURT D G:SON, direktör,\nVänersborg, f i Upps 20/5/03 av bruksäg\nGunnar W o Elsa Jansson.\nHdlsutbildn Tyskl 21-22, anst Heby\ntegelverk o Tenggrenstorps tegelbruk\n22-32, verkst dir (grund) Wulf &amp; Co ab\nVänersborg sed 45.\n\nGift 32 m Ingrid Detter f 07. - Barn:\nBirgitta f 34, Gunnar f 37, Margaretha\nf 39, Anders f 43, Erik f 50.\n\nVULT von STEIJERN, NILS C A,\nfriherre, ingenjör, Västervik, f i Bankeryd,\nJönkpgs l, 14/1/06 av frih Carl-Erik V\nv S o frih:an Elsa von Otter.\nRealex Jönkpg 22, tekn gymn Örebro 25,\ning STAB Kalmar 25-37, 40-47, ab\nTextilmaskiner Norrkpg 37-40, ritkont:ch ab\nRörstrands porslinsfabr Lidkpg 47,\nrit-kont:- o konstr :ch ab Slipmaterial-Naxos\nVästervik sed 55. - Led kyrkofullm\nLidkpg 50-55, kyrkoråd 51-55. - Ordf\nVästerviks Andréasfören sed 61, stift o\nskattm Lidkpgs tekn fören 48-55, stift o\nordf Kalmar l schackförb 35-40, ordf\nKalmar schackklubb 35-47 (hed:ordf 65),\nLidkpgs schacksällsk 49-55, sekr\nÖstergötl schackförb 38-40, Sthlms\nschacksällsk 42-45 (ständ medl), Västerviks\nork :f ören sed 56. - Medl Personhist\nsamf. - Hobbies: genealogi, musik,\nschack.\n\nGift 31 m Anna Lassen f 04, dtr t ver km\nNils Cederberg o Laura Lassen. - Barn:\nKjerstin f 34.\n\nVULT von STEYERN, N J BALTZAR,\nfd landsfogde, Växjö, f i Kristianstad\n2/7/00 av öv :löjtn Nils V v S o Eva\nHammar.\n\nStud:ex 19, jur kand Lund 27, tingstjg\nRönnebergs m fi doms 27-30, Sunnerbo\ndoms 30-31, e tjm länsstyr Kronob l 31,\nlandsfogde Kronob l 36-64, - Medl SHT.\n- Utm: KNO, DFrM. - Hobby:\nkammar-musik.\n\nGift 30 m Marta Drake af Hagelsrum\nf 99, dtr t lotskapt Axel D af H o Eva\nLilliesköld. - Barn: Johan f 31, Gösta\nf 37, Louise f 39.\n\nWÅGBERG-ZANDER, BIRGIT H M,\nleg läkare, Norrköping, f i Örebro\n24/2/11 av köpm Gustaf Wågberg o\nOlga Grenman.\n\nStud:ex 30, med kand 34 o med lic Sthlm\n40, vik underläk med avd S:t Eriks sjh\n41-44, med avd S:t Görans sjh 44-45, l:e\nunderläk 45-47, prakt läk Norrkpg 47’-\n\n57,   läk  nykterh:ndns  rådgivn:byrå  där\nsed 61. - Skolläk komm flicksk sed 50.\nGift 36 m med lic Göran Zander f 07.\n-Barn: Lena f 40, Carin f 43, Birger f 46.\n\n",
    "structured": {
        "1": {
            "full_name": "Wulf, Kurt D G:son",
            "location": "Vänersborg",
            "occupation": "Direktör",
            "birth_details": {
                "date": "20/05/1903",
                "place": "Uppsala"
            },
            "education": [
                {
                    "degree": "Hdlsutbildn Tyskl",
                    "year": "1921-1922",
                    "institution": "Heby tegelverk"
                }
            ],
            "career": [
                {
                    "position": "Verkst dir (grund)",
                    "years": {
                        "start_year": 1945,
                        "end_year": null
                    },
                    "organization": "Wulf & Co ab Vänersborg"
                }
            ],
            "family": {
                "spouse": "Ingrid Detter",
                "marriage_year": "1932",
                "children": [
                    {
                        "name": "Birgitta",
                        "birth_year": "1934"
                    },
                    {
                        "name": "Gunnar",
                        "birth_year": "1937"
                    },
                    {
                        "name": "Margaretha",
                        "birth_year": "1939"
                    },
                    {
                        "name": "Anders",
                        "birth_year": "1943"
                    },
                    {
                        "name": "Erik",
                        "birth_year": "1950"
                    }
                ]
            },
            "hobbies": [
                "fiske"
            ]
        },
        "2": {
            "full_name": "Vult von Steijern, Nils C A",
            "location": "Västervik",
            "occupation": "Ingenjör",
            "birth_details": {
                "date": "14/01/1906",
                "place": "Bankeryd, Jönköpings län"
            },
            "education": [
                {
                    "degree": "Realex",
                    "year": "1922",
                    "institution": "Jönköping"
                },
                {
                    "degree": "Tekn Gymn",
                    "year": "1925",
                    "institution": "Örebro"
                }
            ],
            "career": [
                {
                    "position": "Ing Stab",
                    "years": {
                        "start_year": 1925,
                        "end_year": 1937
                    },
                    "organization": "Kalmar"
                },
                {
                    "position": "Ab Textilmaskiner",
                    "years": {
                        "start_year": 1937,
                        "end_year": 1940
                    },
                    "organization": "Norrköping"
                },
                {
                    "position": "Ritkonto- och konstruktion-ch",
                    "years": {
                        "start_year": 1955,
                        "end_year": null
                    },
                    "organization": "Slipmaterial-Naxos Västervik"
                }
            ],
            "family": {
                "spouse": "Anna Lassen",
                "marriage_year": "1931",
                "children": [
                    {
                        "name": "Kjerstin",
                        "birth_year": "1934"
                    }
                ]
            },
            "community_involvement": [
                {
                    "role": "Ordf",
                    "organization": "Västerviks Andréasfören",
                    "years": "1961-"
                },
                {
                    "role": "Stift och ordf",
                    "organization": "Kalmar l Schackförb",
                    "years": "1948-1955"
                }
            ],
            "hobbies": [
                "genealogi",
                "musik",
                "schack"
            ]
        },
        "3": {
            "full_name": "Vult von Steyern, N J Baltzar",
            "location": "Växjö",
            "occupation": "Fd Landsfogde",
            "birth_details": {
                "date": "02/07/1900",
                "place": "Kristianstad"
            },
            "education": [
                {
                    "degree": "Jur kand",
                    "year": "1927",
                    "institution": "Lund"
                }
            ],
            "career": [
                {
                    "position": "Landsfogde",
                    "years": {
                        "start_year": 1936,
                        "end_year": 1964
                    },
                    "organization": "Kronobergs län"
                }
            ],
            "family": {
                "spouse": "Marta Drake af Hagelsrum",
                "marriage_year": "1930",
                "children": [
                    {
                        "name": "Johan",
                        "birth_year": "1931"
                    },
                    {
                        "name": "Gösta",
                        "birth_year": "1937"
                    },
                    {
                        "name": "Louise",
                        "birth_year": "1939"
                    }
                ]
            },
            "honorary_titles": [
                {
                    "title": "KNO",
                    "institution": null,
                    "year": null
                },
                {
                    "title": "DFrM",
                    "institution": null,
                    "year": null
                }
            ],
            "hobbies": [
                "kammar-musik"
            ]
        },
        "4": {
            "full_name": "Wågberg-Zander, Birgit H M",
            "location": "Norrköping",
            "occupation": "Leg Läkare",
            "birth_details": {
                "date": "24/02/1911",
                "place": "Örebro"
            },
            "education": [
                {
                    "degree": "Stud",
                    "year": "1930",
                    "institution": null
                },
                {
                    "degree": "Med Kand",
                    "year": "1934",
                    "institution": "Stockholm"
                },
                {
                    "degree": "Med Lic",
                    "year": "1940",
                    "institution": "Stockholm"
                }
            ],
            "career": [
                {
                    "position": "Vik Underläk",
                    "years": {
                        "start_year": 1941,
                        "end_year": 1944
                    },
                    "organization": "S:t Eriks sjh"
                },
                {
                    "position": "Med avd",
                    "years": {
                        "start_year": 1944,
                        "end_year": 1945
                    },
                    "organization": "S:t Görans sjh"
                },
                {
                    "position": "L:e Underläk",
                    "years": {
                        "start_year": 1945,
                        "end_year": 1947
                    },
                    "organization": null
                }
            ],
            "family": {
                "spouse": "Göran Zander",
                "marriage_year": "1936",
                "children": [
                    {
                        "name": "Lena",
                        "birth_year": "1940"
                    },
                    {
                        "name": "Carin",
                        "birth_year": "1943"
                    },
                    {
                        "name": "Birger",
                        "birth_year": "1946"
                    }
                ]
            }
        }
    }
}