{
    "original": "BERNDES, JAN A L, prost,\nÖrnsköldsvik, f i Sala 24/1/09 av ing Richard B\no ämneslär Dagmar Sturzen-Becker.\nStud:ex Sundsvall 28, teol kand Upps\n34, teol lic 43, prästv 35, past:adj o v\npastor Sunne 35-36, kommin Styrnäs\n36-42, Strömnäs 42-45, kyrkoh Berg 45-61,\nkontr :prost Härjedalens kontr 53-61,\nkyrkoh Örnsköldsvik sed 61, prost sed\n62. - Led domkap sed 62, preses\nprästmötet Härnösand 64. - Utm: LNO.\nGift 44 m Anna-Lisa Steninger f 19, dtr\nt överlär Seth S o Olga Svanberg.\n-Barn: Gunnar f 46, Johan f 48, Ulla\nf 52.\n\nBERNE, STIG A, förste länsassessor,\n\nGävle, f i Växjö 30/8/10 av disp Albert\nB o Lisa Persson.\n\nStud:ex Malmö 31, res:off:ex 33, jur\nkand Lund 39, tingstjg Jämtl n doms\n39-42, länsbokhåll Blek l 45 (tf 42), 2:e\nlänsbokhåll Älvsb l 48 (tf 46), tf l:e\nlänsbokhåll Gävleb l 48, länsassess 53\n(tf 52), l:e länsassess där sed 65. - Lär i\nprocessrätt polissk avd Gävle sed 54;\nordf tax:-, beredn:- o fastigh :tax :nd, sekr\nlandst :utsk, led kyrkoråd m fi allm\nupp-dr. - Hobbies: golf, foto.\nGift 44 m Margareta Andersson f 17,\ndtr t exp :f örest Carl A o Wendla\nForsman. - Barn: Christian f 45, Marianne\nf 49.\n\nBERNHOFF, E O (OLLE) I,\nkyrkoherde, Svanstein, f i Sillhövda, Blek l,\n12/3/05 av kyrkoh Swen B o Ingeborg\nFlyborg.\n\nTeol kand 30, kyrkoadj Glimåkra 38,\nJuoksengi 51, kommin Svanstein 57,\nkyrkoh där sed 62. - Skr: Saunga frau\nmaakena (dikter på östgöingskt mål 51).\n- Hobbies: språkstudier, träsnideri.\nGift 35 m Elisabeth Holmgren, dtr t ing\nAlbert H o Elisabeth Stiernstedt. - Barn:\nAlbert f 37, Hilding f 38, Britta f 40,\nIngela f 43, Ola f 48.\n\n",
    "structured": {
        "0": {
            "full_name": "Jan A L Berndes",
            "location": "Örnsköldsvik",
            "occupation": "prost",
            "birth_details": {
                "date": "24/01/1909",
                "place": "Sala"
            },
            "education": [
                {
                    "degree": "teol kand",
                    "year": "1934",
                    "institution": "Upps"
                },
                {
                    "degree": "teol lic",
                    "year": "1943",
                    "institution": "NULL"
                }
            ],
            "career": [
                {
                    "position": "past:adj",
                    "years": {
                        "start_year": 1935,
                        "end_year": 1936
                    },
                    "organization": "Sunne"
                },
                {
                    "position": "kommin",
                    "years": {
                        "start_year": 1936,
                        "end_year": 1942
                    },
                    "organization": "Styrnäs"
                },
                {
                    "position": "kyrkoh Berg",
                    "years": {
                        "start_year": 1945,
                        "end_year": 1961
                    },
                    "organization": "kirche"
                },
                {
                    "position": "kontr :prost",
                    "years": {
                        "start_year": 1953,
                        "end_year": 1961
                    },
                    "organization": "Härjedalens kontr"
                },
                {
                    "position": "kyrkoh Örnsköldsvik",
                    "years": {
                        "start_year": 1961,
                        "end_year": 1962
                    },
                    "organization": "NULL"
                },
                {
                    "position": "prost",
                    "years": {
                        "start_year": 1962,
                        "end_year": 1962
                    },
                    "organization": "NULL"
                }
            ],
            "family": {
                "spouse": "Anna-Lisa Steninger",
                "marriage_year": "1944",
                "children": [
                    {
                        "name": "Gunnar",
                        "birth_year": "1946"
                    },
                    {
                        "name": "Johan",
                        "birth_year": "1948"
                    },
                    {
                        "name": "Ulla",
                        "birth_year": "1952"
                    }
                ]
            }
        },
        "1": {
            "full_name": "Stig A Berne",
            "location": "Gävle",
            "occupation": "förste länsassessor",
            "birth_details": {
                "date": "30/08/1910",
                "place": "Växjö"
            },
            "education": [
                {
                    "degree": "disp",
                    "year": "NULL",
                    "institution": "NULL"
                },
                {
                    "degree": "jur kand",
                    "year": "1939",
                    "institution": "Lund"
                }
            ],
            "career": [
                {
                    "position": "tingstjg",
                    "years": {
                        "start_year": 1939,
                        "end_year": 1942
                    },
                    "organization": "Jämtl n doms"
                },
                {
                    "position": "länsbokhåll",
                    "years": {
                        "start_year": 1945,
                        "end_year": 1945
                    },
                    "organization": "Blek l"
                },
                {
                    "position": "länsbokhåll",
                    "years": {
                        "start_year": 1948,
                        "end_year": 1948
                    },
                    "organization": "Älvsb l"
                },
                {
                    "position": "länsassess",
                    "years": {
                        "start_year": 1953,
                        "end_year": 1965
                    },
                    "organization": "NULL"
                }
            ],
            "family": {
                "spouse": "Margareta Andersson",
                "marriage_year": "1944",
                "children": [
                    {
                        "name": "Christian",
                        "birth_year": "1945"
                    },
                    {
                        "name": "Marianne",
                        "birth_year": "1949"
                    }
                ]
            },
            "hobbies": [
                "golf",
                "foto"
            ]
        },
        "2": {
            "full_name": "E O (Olle) I Bernhoff",
            "location": "Svanstein",
            "occupation": "kyrkoherde",
            "birth_details": {
                "date": "12/03/1905",
                "place": "Sillhövda, Blek l"
            },
            "education": [
                {
                    "degree": "teol kand",
                    "year": "1930",
                    "institution": "NULL"
                }
            ],
            "career": [
                {
                    "position": "kyrkoadj",
                    "years": {
                        "start_year": 1938,
                        "end_year": 1951
                    },
                    "organization": "Glimåkra"
                },
                {
                    "position": "kommin",
                    "years": {
                        "start_year": 1957,
                        "end_year": 1962
                    },
                    "organization": "Svanstein"
                }
            ],
            "family": {
                "spouse": "Elisabeth Holmgren",
                "marriage_year": "1935",
                "children": [
                    {
                        "name": "Albert",
                        "birth_year": "1937"
                    },
                    {
                        "name": "Hilding",
                        "birth_year": "1938"
                    },
                    {
                        "name": "Britta",
                        "birth_year": "1940"
                    },
                    {
                        "name": "Ingela",
                        "birth_year": "1943"
                    },
                    {
                        "name": "Ola",
                        "birth_year": "1948"
                    }
                ]
            },
            "hobbies": [
                "språkstudier",
                "träsnideri"
            ]
        }
    }
}