{
    "original": "BRATT, LARS O, överste, Östersund,\nf i Alingsås 17/1/14 av med dr Olof B\no Karin Wendel.\n\nStud:ex Upps 33, fänr A 4 36, kapt 44,\nmajor 54, öv:löjtn 59, överste 65. - AIHS\n38-40, KHS 44-46, FHS 66. - Kadettoff\nKS 41-44, tjg fst 48-50, ch Lv:s kadettsk\n51-57, utbildn:off Lv l 59-60, ch Lv l\n60-61, utbildn:off Lv 6 61-63, fobef\nÖstersunds fö sed 65. - Stf ch\növervakn:-komm Korea 64. - Led arméns\nbefordr:-beredn 56-59, ordf Jämtl-Härjedalens\nidr:förb sed 65, delt i landslaget i\nmodern femkamp 38-44. - Utm: RSO,\nSv-FFSM, SMISM, SCFftjtG. - Hobbies:\njakt, fiske, skidsport.\nGift 38 m Gunilla Saxenberg f 11, dtr t\ning William S o Hilda Björkstedt.\n-Barn: Claes f 39, Christina f 41,\nMagnus f 45.\n\nBRATT,   SVEN   A   R,   bankdirektör,\n\nHärnösand, f i Slättåkra, Hall l, 16/12/\n\n28 av folkskollär Viktor B o Elsa Mo-\n\ndéen.\n\nStud:ex  Halmstad  49,  Hbgs  hdlsgymn\n\n51, anst Sv:es riksbk 51, Sv:es kreditbk\n\nHärnösand 62, bankdir där sed 64. - Led\n\nStadsfullm sed 67.  -  Medl S:t PetriO,\n\nFrimO.\n\nGift 52 m Randi Bye. - Barn: Monika\n\nf 60.\n\nBRECHENSBAUER, STEFAN G J,\narkitekt SAR, Bergnäset, f i\nTeplitz-Schönau, Tjeckosl, 7/5/34 av prof, dr\nAlfred B o Elisabeth Arlt.\nArkit:ex Oskar von Miller Polytechn\nMünchen 57; anst arkit:kont Tage\nMöller Malmö 57, Kjell Ödeen Sthlm 58,\nBackström o Reinius 59, Norrb\n:kommunernas arkit:- o byggn :kont NAB Luleå\nsed 60. - Hobby: sport.\nGift 61 m Eva Kraus f 41, dtr t\namts-man Hugo K o Ria Brandt. - Barn:\nClaes f 65.\n\n",
    "structured": {
        "0": {
            "full_name": "LARS O BRATT",
            "location": "Östersund",
            "occupation": "överste",
            "birth_details": {
                "date": "17/01/1914",
                "place": "Alingsås",
                "parents": "med dr Olof B o Karin Wendel"
            },
            "education": [
                {
                    "degree": "Stud:ex",
                    "year": "1933",
                    "institution": "Upps"
                },
                {
                    "degree": "AIHS",
                    "year": "1938-1940"
                },
                {
                    "degree": "KHS",
                    "year": "1944-1946"
                },
                {
                    "degree": "FHS",
                    "year": "1966"
                }
            ],
            "career": [
                {
                    "position": "fänr",
                    "years": {
                        "start_year": 1936,
                        "end_year": 1944
                    },
                    "organization": "A 4"
                },
                {
                    "position": "kapt",
                    "years": {
                        "start_year": 1944,
                        "end_year": 1954
                    }
                },
                {
                    "position": "major",
                    "years": {
                        "start_year": 1954,
                        "end_year": 1959
                    }
                },
                {
                    "position": "öv:löjtn",
                    "years": {
                        "start_year": 1959,
                        "end_year": 1965
                    }
                },
                {
                    "position": "överste",
                    "years": {
                        "start_year": 1965
                    }
                }
            ],
            "family": {
                "spouse": "Gunilla Saxenberg",
                "marriage_year": "1938",
                "children": [
                    {
                        "name": "Claes",
                        "birth_year": "1939"
                    },
                    {
                        "name": "Christina",
                        "birth_year": "1941"
                    },
                    {
                        "name": "Magnus",
                        "birth_year": "1945"
                    }
                ]
            },
            "hobbies": [
                "jakt",
                "fiske",
                "skidsport"
            ]
        },
        "1": {
            "full_name": "SVEN A R BRATT",
            "location": "Härnösand",
            "occupation": "bankdirektör",
            "birth_details": {
                "date": "16/12/1928",
                "place": "Slättåkra, Hall l",
                "parents": "folkskollär Viktor B o Elsa Modéen"
            },
            "education": [
                {
                    "degree": "Stud:ex",
                    "year": "1949",
                    "institution": "Halmstad"
                },
                {
                    "degree": "Hbgs hdlsgymn",
                    "year": "1951"
                }
            ],
            "career": [
                {
                    "position": "anst",
                    "years": {
                        "start_year": 1951,
                        "end_year": 1962
                    },
                    "organization": "Sv:es riksbk"
                },
                {
                    "position": "bankdir",
                    "years": {
                        "start_year": 1964
                    },
                    "organization": "Sv:es kreditbk Härnösand"
                }
            ],
            "family": {
                "spouse": "Randi Bye",
                "marriage_year": "1952",
                "children": [
                    {
                        "name": "Monika",
                        "birth_year": "1960"
                    }
                ]
            }
        },
        "2": {
            "full_name": "STEFAN G J BRECHENSBAUER",
            "location": "Bergnäset",
            "occupation": "arkitekt SAR",
            "birth_details": {
                "date": "07/05/1934",
                "place": "Teplitz-Schönau, Tjeckosl",
                "parents": "prof, dr Alfred B o Elisabeth Arlt"
            },
            "education": [
                {
                    "degree": "Arkit:ex",
                    "year": "1957",
                    "institution": "Oskar von Miller Polytechn München"
                }
            ],
            "career": [
                {
                    "position": "anst",
                    "years": {
                        "start_year": 1957,
                        "end_year": 1957
                    },
                    "organization": "arkit:kont Tage Möller Malmö"
                },
                {
                    "position": "anst",
                    "years": {
                        "start_year": 1958,
                        "end_year": 1958
                    },
                    "organization": "Kjell Ödeen Sthlm"
                },
                {
                    "position": "anst",
                    "years": {
                        "start_year": 1959,
                        "end_year": 1960
                    },
                    "organization": "Backström o Reinius"
                },
                {
                    "position": "anst",
                    "years": {
                        "start_year": 1960
                    },
                    "organization": "NAB Luleå"
                }
            ],
            "family": {
                "spouse": "Eva Kraus",
                "marriage_year": "1961",
                "children": [
                    {
                        "name": "Claes",
                        "birth_year": "1965"
                    }
                ]
            },
            "hobbies": [
                "sport"
            ]
        }
    }
}