{
    "original": "BRÄNNSTRÖM, G RICHARD, hov-\n\nrättsfiskal, Boden, f i Skellefteå 10/9/36\nav fabr Gustav B o Elsa Norsten.\nStud:ex Skellefteå 55, jur kand Upps 60,\ntingstjg Brabygdens o Finspånga l doms\n60-63, fiskal hovr Ö Norrl 63,\nfiskals-komp bitr Luleå doms sed 64.\n\nBUHR,   M   BERT-OLOV,   ingenjör,\n\nUmeå, f i Holmsund, Västerb l, 29/7/29\nav sågv :arb Manfred B o Elin\nHolmgren.\n\nIng:ex NKI 53; öl anst SCA o Asea t\n53, konstr ab Ålö-maskiner Brännland\n53, verkst:ch 57, prpd:ch där sed 65.\n-Hobbies: fiske, tennis.\nGift 51 m Gunvor Axelsson f 29, dtr t\nhemm:äg Manfred Johansson o Anny\nKarlsson. - Barn: Kathrine f 51,\nLillemor f 53.\n\nBUNTE, RUNE H, universitetslektor,\n\nUmeå, f i Hbg 19/10/25 av postiljon\nBror Bengtsson o Clara Bengtsson.\nStud:ex 46, folkskollär :ex 48, fil mag 60,\nfil lic 64; folkskollär Bogen 48, Malmö\n51, Lund 52, e univ:lekt Lunds univ 62,\nuniv :lekt i ekon historia Umeå univ sed\n66 (tf prof 66-67). - Hobbies: musik,\nkonst.\n\nGift 50 m Gunnel Larsson, dtr t rekt\nLudvig L o Anna Browall. - Barn:\nAgneta f 52, Monica f 60.\n\nBURÉNIUS, BJÖRN J F, lantmätare,\n\nGävle,  f  i  Djursholm   18/6/20  av  dir\nRagnar B o Elsa Johansson.\nStud:ex 40, KTH 45, lantmät:tjg Gävleb\no Norrb l 45-51, Gävle distr sed 51.\nGift 49 m Ingrid Lindgren, dtr t past\nHarald L o Nanna L. - Barn: Ingegerd\nf 49, Lennart f 51, Ann-Marie f 54.\n\nBURMAN,   ANDERS   O  E,  adjunkt,\n\nStoruman, f i Enånger, Gävleb l, 13/3/29\n\nav lantbr Eliot B o Dagny Enbom.\n\nFil mag Upps 55, adj realsk Nora 55,\n\nkomm realsk Storuman sed 56. - Skr:\n\nskolböcker  i  sv f  grundsk högstad  o\n\ngymn (tills m Erland Flemming), i eng\n\nf   grundsk  högstad.   -  Hobbies:   sport,\n\nfilm.\n\nGift 53 m Eddy Syren, dtr t distr:ch\n\nKnut S o Karin Ansén. - Barn: Peter\n\nf 55, Johan f 57.\n\n",
    "structured": {
        "1": {
            "full_name": "G Richard Brännström",
            "location": "Boden",
            "occupation": "Hovrättsfiskal",
            "birth_details": {
                "date": "10/09/1936",
                "place": "Skellefteå",
                "parents": "fabr Gustav B o Elsa Norsten"
            },
            "education": [
                {
                    "degree": "Stud",
                    "year": "1955",
                    "institution": "Skellefteå"
                },
                {
                    "degree": "Jur kand",
                    "year": "1960",
                    "institution": "Upps"
                }
            ],
            "career": [
                {
                    "position": "Tingstjg",
                    "years": {
                        "start_year": 1960,
                        "end_year": 1963
                    },
                    "organization": "Brabygdens o Finspånga l doms"
                },
                {
                    "position": "Fiskal hovr Ö Norrl",
                    "years": {
                        "start_year": 1963,
                        "end_year": null
                    },
                    "organization": null
                },
                {
                    "position": "Fiskals-komp bitr",
                    "years": {
                        "start_year": 1964,
                        "end_year": null
                    },
                    "organization": "Luleå doms"
                }
            ],
            "family": {
                "spouse": null,
                "marriage_year": null,
                "children": []
            }
        },
        "2": {
            "full_name": "Bert-Olov Buhr",
            "location": "Umeå",
            "occupation": "Ingenjör",
            "birth_details": {
                "date": "29/07/1929",
                "place": "Holmsund, Västerb l",
                "parents": "sågv :arb Manfred B o Elin Holmgren"
            },
            "education": [
                {
                    "degree": "Ing:ex",
                    "year": "1953",
                    "institution": "NKI"
                }
            ],
            "career": [
                {
                    "position": "Verkst:ch",
                    "years": {
                        "start_year": 1957,
                        "end_year": null
                    },
                    "organization": "Ålö-maskiner Brännland"
                }
            ],
            "family": {
                "spouse": "Gunvor Axelsson",
                "marriage_year": "1951",
                "children": [
                    {
                        "name": "Kathrine",
                        "birth_year": "1951"
                    },
                    {
                        "name": "Lillemor",
                        "birth_year": "1953"
                    }
                ]
            }
        },
        "3": {
            "full_name": "Rune H Bunte",
            "location": "Umeå",
            "occupation": "Universitetslektor",
            "birth_details": {
                "date": "19/10/1925",
                "place": "Hbg",
                "parents": "postiljon Bror Bengtsson o Clara Bengtsson"
            },
            "education": [
                {
                    "degree": "Fil mag",
                    "year": "1960",
                    "institution": null
                },
                {
                    "degree": "Fil lic",
                    "year": "1964",
                    "institution": null
                }
            ],
            "career": [
                {
                    "position": "Univ :lekt i ekon historia",
                    "years": {
                        "start_year": 1966,
                        "end_year": null
                    },
                    "organization": "Umeå univ"
                }
            ],
            "family": {
                "spouse": "Gunnel Larsson",
                "marriage_year": "1950",
                "children": [
                    {
                        "name": "Agneta",
                        "birth_year": "1952"
                    },
                    {
                        "name": "Monica",
                        "birth_year": "1960"
                    }
                ]
            }
        },
        "4": {
            "full_name": "Björn J F Burénius",
            "location": "Gävle",
            "occupation": "Lantmätare",
            "birth_details": {
                "date": "18/06/1920",
                "place": "Djursholm",
                "parents": "dir Ragnar B o Elsa Johansson"
            },
            "education": [
                {
                    "degree": "Stud:ex",
                    "year": "1940",
                    "institution": null
                }
            ],
            "career": [
                {
                    "position": "Lantmät:tjg",
                    "years": {
                        "start_year": 1945,
                        "end_year": 1951
                    },
                    "organization": "Gävleb o Norrb l"
                },
                {
                    "position": "Lantmät:tjg",
                    "years": {
                        "start_year": 1951,
                        "end_year": null
                    },
                    "organization": "Gävle distr"
                }
            ],
            "family": {
                "spouse": "Ingrid Lindgren",
                "marriage_year": "1949",
                "children": [
                    {
                        "name": "Ingegerd",
                        "birth_year": "1949"
                    },
                    {
                        "name": "Lennart",
                        "birth_year": "1951"
                    },
                    {
                        "name": "Ann-Marie",
                        "birth_year": "1954"
                    }
                ]
            }
        },
        "5": {
            "full_name": "Anders O E Burman",
            "location": "Storuman",
            "occupation": "Adjunkt",
            "birth_details": {
                "date": "13/03/1929",
                "place": "Enånger, Gävleb l",
                "parents": "lantbr Eliot B o Dagny Enbom"
            },
            "education": [
                {
                    "degree": "Fil mag",
                    "year": "1955",
                    "institution": "Upps"
                }
            ],
            "career": [
                {
                    "position": "Komm realsk",
                    "years": {
                        "start_year": 1956,
                        "end_year": null
                    },
                    "organization": "Storuman"
                }
            ],
            "family": {
                "spouse": "Eddy Syren",
                "marriage_year": "1953",
                "children": [
                    {
                        "name": "Peter",
                        "birth_year": "1955"
                    },
                    {
                        "name": "Johan",
                        "birth_year": "1957"
                    }
                ]
            }
        }
    }
}