{
    "original": "BernadotteM, PatrSGM, HvM, Västerb\njaktv:fbGm. - Hobby:\nhembygdsforskning.\n\nGift 33 m Lillian Beskow, dtr t\ngymn:-dir David B o Lillian Bolton. - Barn:\nTage f 36, Christer f 38, Magdalena f 40,\nHans f 45.\n\nBLIDEGÄRD, CURT O M,\nfastighetschef, Skellefteå, f i Luleå 14/10/27 av\naff :ch Manfred B o Gertrud Nordström.\nStud:ex Skellefteå 48, KTH 54,\nlant-mät:tjg Kalmar, Västerb o Norrb l\n54-61, tf stadsing Luleå 61, stadsing där\n63, fastigh:ch Skellefteå sed 66.\nGift 54 m Birgit Öhlund f 29, dtr t\nhemm:äg Gunnar Ö o Jenny Berglund.\n-Barn: Åsa f 56, Stefan f 59.\n\nBLIX, KARIN G K, leg läkare, Gävle,\nf i Sthlm 27/4/23 av prov:läk Ruben\nCederblad o Hildur Andersson.\nStud:ex Karlskrona 41, med kand 44 o\nmed lic Upps 50, l:e underläk\nögon-klin Akad sjh 51-52, underläk barnavd\nVästerås las, Akad sjh o Barnsjh\nSamariten 52-55, barnpsyk klin Akad sjh 55-\n\n56,  l:e underläk Barnsjh Samariten 56-\n\n57,   vik underläk Flensburgska barnsjh\n57 o 58, öl läk:förordn 58-66, underläk\nbarnpsyk klin Gävle las sed 67.\n\nGift 46 m bitr överläk Magnus Blix\nf 23. - Barn: Eva f 50, Olof f 51, Johan\nf 53, Erik f 57.\n\nBLIX,  S  MAGNUS,  bitr överläkare,\n\nGävle, f i Lund 5/4/23 av prof Gunnar\nB o Hertha Wiberg.\n\nStud:ex Upps 41, med kand 45 o med\nlic Upps 51; öl läk:förordn 49-52,\nunderläk ögonklin Akad sjh 52-57,\nögon-klin Malmö allm sjh 57-62, bitr överläk\nögonklin Falun 62-64, Gävle las sed 64.\nGift 46 m leg läk Karin Cederblad\nf 23. - Barn: Eva f 50, Olov f 51, Johan\nf 53, Erik f 57.\n\n",
    "structured": {
        "1": {
            "full_name": "BernadotteM, PatrSGM, HvM",
            "location": "Västerbotten",
            "occupation": "jaktv:fBGM",
            "birth_details": {
                "date": "NN/NN/NNNN",
                "place": "NNN",
                "parents": "NNN"
            },
            "education": [],
            "career": [],
            "family": {
                "spouse": "Lillian Beskow",
                "marriage_year": "NN",
                "children": [
                    {
                        "name": "Tage",
                        "birth_year": "NNNN"
                    },
                    {
                        "name": "Christer",
                        "birth_year": "NNNN"
                    },
                    {
                        "name": "Magdalena",
                        "birth_year": "NNNN"
                    },
                    {
                        "name": "Hans",
                        "birth_year": "NNNN"
                    }
                ]
            }
        },
        "2": {
            "full_name": "BLIDEGÄRD, CURT O M",
            "location": "Skellefteå",
            "occupation": "fastighetschef",
            "birth_details": {
                "date": "14/10/1927",
                "place": "Luleå",
                "parents": "aff :ch Manfred B o Gertrud Nordström"
            },
            "education": [
                {
                    "degree": "Stud:ex",
                    "year": "1948",
                    "institution": "Skellefteå"
                },
                {
                    "degree": "KTH",
                    "year": "1954",
                    "institution": "KTH"
                }
            ],
            "career": [
                {
                    "position": "lant-mät:tjg",
                    "years": {
                        "start_year": 1954,
                        "end_year": 1961
                    },
                    "organization": "Kalmar, Västerb o Norrb l"
                },
                {
                    "position": "tf stadsing",
                    "years": {
                        "start_year": 1961,
                        "end_year": 1963
                    },
                    "organization": "Luleå"
                },
                {
                    "position": "stadsing",
                    "years": {
                        "start_year": 1963
                    },
                    "organization": "Luleå"
                },
                {
                    "position": "fastigh:ch",
                    "years": {
                        "start_year": 1966
                    },
                    "organization": "Skellefteå"
                }
            ],
            "family": {
                "spouse": "Birgit Öhlund",
                "marriage_year": "1954",
                "children": [
                    {
                        "name": "Åsa",
                        "birth_year": "1956"
                    },
                    {
                        "name": "Stefan",
                        "birth_year": "1959"
                    }
                ]
            }
        },
        "3": {
            "full_name": "BLIX, KARIN G K",
            "location": "Gävle",
            "occupation": "leg läkare",
            "birth_details": {
                "date": "27/04/1923",
                "place": "Sthlm",
                "parents": "prov:läk Ruben Cederblad o Hildur Andersson"
            },
            "education": [
                {
                    "degree": "Stud:ex",
                    "year": "1941",
                    "institution": "Karlskrona"
                },
                {
                    "degree": "med kand",
                    "year": "1944",
                    "institution": "NNN"
                },
                {
                    "degree": "med lic",
                    "year": "1950",
                    "institution": "Upps"
                }
            ],
            "career": [],
            "family": {
                "spouse": "bitr överläk Magnus Blix",
                "marriage_year": "1946",
                "children": [
                    {
                        "name": "Eva",
                        "birth_year": "1950"
                    },
                    {
                        "name": "Olof",
                        "birth_year": "1951"
                    },
                    {
                        "name": "Johan",
                        "birth_year": "1953"
                    },
                    {
                        "name": "Erik",
                        "birth_year": "1957"
                    }
                ]
            }
        },
        "4": {
            "full_name": "BLIX, S MAGNUS",
            "location": "Gävle",
            "occupation": "bitr överläkare",
            "birth_details": {
                "date": "05/04/1923",
                "place": "Lund",
                "parents": "prof Gunnar B o Hertha Wiberg"
            },
            "education": [
                {
                    "degree": "Stud:ex",
                    "year": "1941",
                    "institution": "Upps"
                },
                {
                    "degree": "med kand",
                    "year": "1945",
                    "institution": "NNN"
                },
                {
                    "degree": "med lic",
                    "year": "1951",
                    "institution": "Upps"
                }
            ],
            "career": [],
            "family": {
                "spouse": "leg läk Karin Cederblad",
                "marriage_year": "1946",
                "children": [
                    {
                        "name": "Eva",
                        "birth_year": "1950"
                    },
                    {
                        "name": "Olov",
                        "birth_year": "1951"
                    },
                    {
                        "name": "Johan",
                        "birth_year": "1953"
                    },
                    {
                        "name": "Erik",
                        "birth_year": "1957"
                    }
                ]
            }
        }
    }
}