{
    "original": "BYSTEDT, JAN M H,  civilingenjör,\n\nStockviksverken, f i Sölvesborg 22/1/24\nav lärov :adj Hugo B o Ruth Barkler.\nStud:ex 43, CTH 49, anst Sv inst f\nkon-server:forskn Gbg 49, Mazetti ab\nMalmö 56, ab Celloplast Norrkpg 58,\nFos-fatbol ab Stockviksverken sed 61. -\nStyr:-led Högerförb lokalavd. - Medl Lions\nclub. - Skr art rör konservering o\nför-packn av livsmedel. - Hobby: bridge.\n\nGift 46 m Birgit Magnusson, dtr t\nsjö-kapt J T M o Amanda Andree. - Barn:\nBertil f 47, Lena f 56.\n\nRYSTEDT, ROLF R, landskamrerare,\n\nKarlskrona, f i Nykpg 14/9/09 av\nmusik-dir Reinhold B o Ruth Lindberg.\nStud:ex Nykpg 28, jur kand Upps 34,\ntingstjg Mjölby doms 35-38, e länsbokh\nKalmar l 38, eo länsbokh 41, eo tax:insp\ndär 44, länsassess Skarab l 46, bitr\ntax:-intend Gbgs o Boh l 55, tax:intend\nÖstergötl l 55, l:e tax:intend där 65, tf\nlandskamr Västerb l 63, landskamr Blek\nl sed 67. - Expert värdesäkr :komm 60-\n\n63,  ordf skiljend 37-38, tax:nd 39-55,\nfas-tigh:tax:nd   52,   omb :man   länsbost:ndn\nÖstergötl l 58-63. - Medl JuvenalO, SHT.\n- Utm: RNO. - Hobby: fiske.\n\nGift 42 m Ebba Ohlsson f 12, dtr t tjm\nHjalmar O o Agnes Nielsen. - Barn:\nIngrid f 44, Marianne f 48.\n\nBYSTRÖM,   BIRGITTA  K,   adjunkt,\n\nStrömsund, f i Tallin, Estl, 24/10/37 av\nagr Pelle B o ekon :f örest Elisabeth\nLarsson.\n\nFil mag Upps 61, eo adj komm realsk\nStoruman 61, adj lärov Strömsund sed\n\n64.   -   Hobbies:   gymnastik,\nkonsthantverk.\n\n",
    "structured": {
        "1": {
            "full_name": "BYSTEDT, JAN M H",
            "location": "Sölvesborg",
            "occupation": "civilingenjör",
            "birth_details": {
                "date": "22/01/1924",
                "place": "Sölvesborg",
                "parents": "lärov: adj Hugo B o Ruth Barkler"
            },
            "education": [
                {
                    "degree": "Stud:ex",
                    "year": "1943",
                    "institution": "NULL"
                },
                {
                    "degree": "CTH",
                    "year": "1949",
                    "institution": "Sv inst f kon-server:forskn Gbg"
                }
            ],
            "career": [
                {
                    "position": "anst Sv inst f kon-server:forskn Gbg",
                    "years": {
                        "start_year": 1949,
                        "end_year": 1949
                    },
                    "organization": "NULL"
                },
                {
                    "position": "Mazetti ab Malmö",
                    "years": {
                        "start_year": 1956,
                        "end_year": 1956
                    },
                    "organization": "NULL"
                },
                {
                    "position": "ab Celloplast Norrkpg",
                    "years": {
                        "start_year": 1958,
                        "end_year": 1958
                    },
                    "organization": "NULL"
                },
                {
                    "position": "Fos-fatbol ab Stockviksverken",
                    "years": {
                        "start_year": 1961,
                        "end_year": 1961
                    },
                    "organization": "NULL"
                }
            ],
            "family": {
                "spouse": "Birgit Magnusson",
                "marriage_year": "1946",
                "children": [
                    {
                        "name": "Bertil",
                        "birth_year": "1947"
                    },
                    {
                        "name": "Lena",
                        "birth_year": "1956"
                    }
                ]
            },
            "hobbies": [
                "bridge"
            ]
        },
        "2": {
            "full_name": "RYSTEDT, ROLF R",
            "location": "Nykpg",
            "occupation": "landskamrerare",
            "birth_details": {
                "date": "14/09/1909",
                "place": "Nykpg",
                "parents": "musik-dir Reinhold B o Ruth Lindberg"
            },
            "education": [
                {
                    "degree": "Stud:ex",
                    "year": "1928",
                    "institution": "Nykpg"
                },
                {
                    "degree": "jur kand",
                    "year": "1934",
                    "institution": "Upps"
                }
            ],
            "career": [
                {
                    "position": "tingstjg Mjölby doms",
                    "years": {
                        "start_year": 1935,
                        "end_year": 1938
                    },
                    "organization": "NULL"
                },
                {
                    "position": "e länsbokh Kalmar l",
                    "years": {
                        "start_year": 1938,
                        "end_year": 1941
                    },
                    "organization": "NULL"
                },
                {
                    "position": "eo länsbokh",
                    "years": {
                        "start_year": 1941,
                        "end_year": 1944
                    },
                    "organization": "NULL"
                },
                {
                    "position": "eo tax:insp",
                    "years": {
                        "start_year": 1944,
                        "end_year": 1944
                    },
                    "organization": "NULL"
                },
                {
                    "position": "länsassess Skarab l",
                    "years": {
                        "start_year": 1946,
                        "end_year": 1946
                    },
                    "organization": "NULL"
                },
                {
                    "position": "bitr tax:intend Gbgs o Boh l",
                    "years": {
                        "start_year": 1955,
                        "end_year": 1955
                    },
                    "organization": "NULL"
                },
                {
                    "position": "tax:intend Östergötl l",
                    "years": {
                        "start_year": 1955,
                        "end_year": 1955
                    },
                    "organization": "NULL"
                },
                {
                    "position": "l:e tax:intend",
                    "years": {
                        "start_year": 1965,
                        "end_year": 1965
                    },
                    "organization": "NULL"
                },
                {
                    "position": "tf landskamr Västerb l",
                    "years": {
                        "start_year": 1963,
                        "end_year": 1963
                    },
                    "organization": "NULL"
                },
                {
                    "position": "landskamr Blek l",
                    "years": {
                        "start_year": 1967,
                        "end_year": 1967
                    },
                    "organization": "NULL"
                }
            ],
            "family": {
                "spouse": "Ebba Ohlsson",
                "marriage_year": "1942",
                "children": [
                    {
                        "name": "Ingrid",
                        "birth_year": "1944"
                    },
                    {
                        "name": "Marianne",
                        "birth_year": "1948"
                    }
                ]
            },
            "hobbies": [
                "fiske"
            ]
        },
        "3": {
            "full_name": "BYSTRÖM, BIRGITTA K",
            "location": "Tallin, Estl",
            "occupation": "adjunkt",
            "birth_details": {
                "date": "24/10/1937",
                "place": "Tallin, Estl",
                "parents": "agr Pelle B o ekon:f örest Elisabeth Larsson"
            },
            "education": [
                {
                    "degree": "Fil mag",
                    "year": "1961",
                    "institution": "Upps"
                },
                {
                    "degree": "eo adj komm realsk",
                    "year": "1961",
                    "institution": "Storuman"
                }
            ],
            "career": [
                {
                    "position": "adj lärov Strömsund",
                    "years": {
                        "start_year": 1964,
                        "end_year": 1964
                    },
                    "organization": "NULL"
                }
            ],
            "hobbies": [
                "gymnastik",
                "konsthantverk"
            ]
        }
    }
}