{
    "original": "BJUREK,   S   B   SIGVARD,   rådman,\n\nGävle, f i Malmö 2/9/25 av kyrkoh Sam\nB o Edith Andersson.\nStud:ex Linkpg 46, jur kand Upps 50,\ntingstjg Folkungabygd doms 51-53, tjg\nhovr f ö Norrl 54-55, assess rådhusr\nGävle 55, rådm där sed 63. - Ordf\nhyres-ndn Gävle sed 59.\n\nGift 50 m Kristina\nDanckwardt-Lillieström f 25, dtr t godsäg Carl-Gustaf\nD-L o Maja Pettersson. - Barn: Håkan\nf 51, Ragnar f 54, Jonas f 59.\n\nBHJRLING, CLAES O, disponent,\nSkellefteå, f i Sthlm 24/9/30 av apot Gösta\nB o Margareta Anrep.\nNorrkpgs hdlsgymn 57, dir:ass\nSkellefteå ångbryggeri ab 58, v verkst dir 61,\nverkst dir där 63, disp Västerb\n:bryggerier ab 65, v verkst dir där sed 67.\nGift 58 m Birgitta Frodig, dtr t Anton\nF o Ebba F. - Barn: Claes-Johan f 59,\nUlrika f 65.\n\nBJURULF, PER M, professor, Umeå,\nf i Jönkpg 29/3/32 av överlär Hjalmar B\no Valborg Sandberg.\nMed lic Lund 57, med dr 60, doc i\nanatomi Lunds univ 60, i socialmedicin 63,\nprof i socialmedicin Umeå univ sed 66.\n-Aman o ass anat inst Lund 52-60, läk\nLunds las 60-65. - Skr i socialmedicin,\nanatomi o internmedicin. - Hobbies:\njakt, fiske.\n\nGift 57 m Carin Lindström, dtr t\npolis-mast Harald L o Greta Meding. - Barn:\nAnders f 59, Helen f 62, Erik f 65.\n\nBJÖRHOLM, INGVAR C, tandläkare,\n\nHärnösand, f i Gällivare, Norrb l, 10/4/\n11 av gruvfogde Lars B o Adéle\nSundbom.\n\nStud:ex Umeå 29, tandl:ex Sthlm 44,\ndistr:tandl Upps l 44-45, priv:prakt\nBoden 45-47, Karlstad 48-51, Härnösand\nsed 51. - Medl S:t PetriO. - Hobbies:\növersättning, måleri, skulptur.\nGift 1) 45-56 m tandl Birgit Arwidson\nf 18, 2) 58 m gymn :dir Kristina Englund\nf 24. - Barn: Leif-Ingvar f 46, Ingela\nf 48.\n\n",
    "structured": {
        "1": {
            "full_name": "Sigvard Bjurek",
            "location": "Gävle",
            "occupation": "rådman",
            "birth_details": {
                "date": "2/9/1925",
                "place": "Malmö",
                "parents": "krykoh Sam B o Edith Andersson"
            },
            "education": [
                {
                    "degree": "Stud:ex",
                    "year": "1946",
                    "institution": "Linkpg"
                },
                {
                    "degree": "jur kand",
                    "year": "1950",
                    "institution": "Upps"
                }
            ],
            "career": [
                {
                    "position": "tingstjg Folkungabygd doms",
                    "years": {
                        "start_year": 1951,
                        "end_year": 1953
                    }
                },
                {
                    "position": "tjg hovr f ö Norrl",
                    "years": {
                        "start_year": 1954,
                        "end_year": 1955
                    }
                },
                {
                    "position": "assess rådhusr",
                    "years": {
                        "start_year": 1955,
                        "end_year": 1955
                    }
                },
                {
                    "position": "rådm",
                    "years": {
                        "start_year": 1963,
                        "end_year": null
                    }
                }
            ],
            "family": {
                "spouse": "Kristina Danckwardt-Lillieström",
                "marriage_year": "1950",
                "children": [
                    {
                        "name": "Håkan",
                        "birth_year": "1951"
                    },
                    {
                        "name": "Ragnar",
                        "birth_year": "1954"
                    },
                    {
                        "name": "Jonas",
                        "birth_year": "1959"
                    }
                ]
            }
        },
        "2": {
            "full_name": "Claes O Bjurling",
            "location": "Skellefteå",
            "occupation": "disponent",
            "birth_details": {
                "date": "24/9/1930",
                "place": "Sthlm",
                "parents": "apot Gösta B o Margareta Anrep"
            },
            "education": [
                {
                    "degree": "Norrkpgs hdlsgymn",
                    "year": "1957",
                    "institution": null
                }
            ],
            "career": [
                {
                    "position": "disp Västerb:bryggerier ab",
                    "years": {
                        "start_year": 1967,
                        "end_year": null
                    }
                }
            ],
            "family": {
                "spouse": "Birgitta Frodig",
                "marriage_year": "1958",
                "children": [
                    {
                        "name": "Claes-Johan",
                        "birth_year": "1959"
                    },
                    {
                        "name": "Ulrika",
                        "birth_year": "1965"
                    }
                ]
            }
        },
        "3": {
            "full_name": "Per M Bjurulf",
            "location": "Umeå",
            "occupation": "professor",
            "birth_details": {
                "date": "29/3/1932",
                "place": "Jönkpg",
                "parents": "överlär Hjalmar B o Valborg Sandberg"
            },
            "education": [
                {
                    "degree": "Med lic",
                    "year": "1957",
                    "institution": "Lund"
                },
                {
                    "degree": "med dr",
                    "year": "1960",
                    "institution": null
                }
            ],
            "career": [
                {
                    "position": "prof i socialmedicin Umeå univ",
                    "years": {
                        "start_year": 1966,
                        "end_year": null
                    }
                }
            ],
            "family": {
                "spouse": "Carin Lindström",
                "marriage_year": "1957",
                "children": [
                    {
                        "name": "Anders",
                        "birth_year": "1959"
                    },
                    {
                        "name": "Helen",
                        "birth_year": "1962"
                    },
                    {
                        "name": "Erik",
                        "birth_year": "1965"
                    }
                ]
            },
            "hobbies": [
                "jakt",
                "fiske"
            ]
        },
        "4": {
            "full_name": "Ingvar C Björholm",
            "location": "Härnösand",
            "occupation": "tandläkare",
            "birth_details": {
                "date": "10/4/1911",
                "place": "Gällivare, Norrb l",
                "parents": "gruvfogde Lars B o Adéle Sundbom"
            },
            "education": [
                {
                    "degree": "Stud:ex",
                    "year": "1929",
                    "institution": "Umeå"
                },
                {
                    "degree": "tandl:ex",
                    "year": "1944",
                    "institution": "Sthlm"
                }
            ],
            "career": [
                {
                    "position": "priv:prakt",
                    "years": {
                        "start_year": 1951,
                        "end_year": 1951
                    },
                    "organization": "Härnösand"
                }
            ],
            "family": {
                "spouse": "1) tandl Birgit Arwidson; 2) gymn :dir Kristina Englund",
                "marriage_year": "1) 1945-2) 1958",
                "children": [
                    {
                        "name": "Leif-Ingvar",
                        "birth_year": "1946"
                    },
                    {
                        "name": "Ingela",
                        "birth_year": "1948"
                    }
                ]
            },
            "hobbies": [
                "översättning",
                "måleri",
                "skulptur"
            ]
        }
    }
}