{
    "original": "BRYNE, NILS, distriktsveterinär,\nNor-sjö, f i örsundsbro, Upps l, 11/6/31 av\nvet Elis B o Ebba Fischerström.\nStud:ex Upps 50, vet:ex VHS 58,\nbesiktn :vet Långebro 62, tf distr :vet\nÄlvsbyn 64, vet hush :sällsk Umeå 65,\ndistr:-vet Norsjö sed 66. - Medl Round Table.\n\n-   Skr: The  spermiocytogenesis  of the\nbull (60). - Hobbies: foto, fiske.\n\nGift 61 m Gunvor Mari Olofsson f 36,\ndtr t droskäg Fritiof O o Alice Hedlund.\n\n- Barn: Peter f 62.\n\nBRYNOLF, NILS O, överläkare,\nSollefteå, f i Nässjö 5/6/07 av trafikinsp\nOred B o Elisabeth Lemchen.\nStud:ex Östersund 26, med kand 33 o\nmed lic Lund 44, öl läk :förordn 44-46,\nunderläk Gällivare las 46-47, l:e\nunderläk röntgendiagn avd Karol sjh 47-51,\növerläk röntgenavd Sollefteå las sed 51.\nGift 53 m Gun Boogren f 22, dtr t\nsjö-kapt Eric B o Inez Andersson. - Barn:\nLars f 54.\n\nBRYNTE,   DAVID   E,   hovurmakare,\n\nGävle, f i Gävle 24/12/96.\nHdlssk, urmak:lära A Th Bränder Gävle\n12, anst G Sehlbergs urhdl m fi 18,\ninneh David Brynte ab ur &amp; optik sed\n22. - Ordf Gästrikl urmak:fören 39-62,\nv ordf Sv:es urmak:- &amp; optikerförb\n45-62 (hedL 55), styr:ordf ab De fören\nur-makarne Malmö 55-61 m m. - Medl\nTempelrO, Odd Fellow, Rotary. - Utm:\nSHSOftjM, Sv:es urmak:- &amp;\noptikerfb-GM.\n\nGift 23 m Tyra Wadlund. - Barn: Rolf\nf 31.\n\nBRÄNDSTRÖM, KJELL O, direktör,\n\nSundsvall, f i Umeå 17/1/31 av dir Gösta\nB o Nanna Bergman.\nStud:ex Füipstad 51, fil kand Upps 55,\nDHS 57; forskare FFI 56, direkt:sekr\nSCA Sundsvall 57, dir:ass 61, dir där\n\nsed 63. - Styr:led Papelera Navarra S A,\nSpan, Colon Emballage A/S, Danm,\nPa-peteries Léon Clergeau, Frankr, Skeena\nKraft Ltd, Canada, Värnamo\nwellpapp-fabr, Wifstavarf-Östrands ind:er\nSundsvall. - Nederländsk vicekonsul\nSundsvall sed 63. - Hobby: golf.\nGift 53 m Barbro Eriksson f 31, dtr t\nbyggm Gustaf E o Alice E. - Barn:\nJohan f 57, Kristina f 60, Magnus f 62,\nBeata f 66.\n\n",
    "structured": {
        "0": {
            "full_name": "Nils Bryne",
            "location": "Nor-sjö",
            "occupation": "distriktsveterinär",
            "birth_details": {
                "date": "11/06/1931",
                "place": "Örsundsbro, Uppsala län",
                "parents": "vet Elis B o Ebba Fischerström"
            },
            "education": [
                {
                    "degree": "Stud:ex",
                    "year": "1950",
                    "institution": "Uppsala"
                },
                {
                    "degree": "vet:ex",
                    "year": "1958",
                    "institution": "VHS"
                }
            ],
            "career": [
                {
                    "position": "besiktn :vet",
                    "years": {
                        "start_year": 1962,
                        "end_year": 1962
                    },
                    "organization": "Långebro"
                },
                {
                    "position": "tf distr :vet",
                    "years": {
                        "start_year": 1964,
                        "end_year": 1966
                    },
                    "organization": "Älvsbyn"
                },
                {
                    "position": "vet hush :sällsk",
                    "years": {
                        "start_year": 1965,
                        "end_year": 1965
                    },
                    "organization": "Umeå"
                },
                {
                    "position": "distr:-vet",
                    "years": {
                        "start_year": 1966,
                        "end_year": null
                    },
                    "organization": "Norsjö"
                }
            ],
            "family": {
                "spouse": "Gunvor Mari Olofsson",
                "marriage_year": "1961",
                "children": [
                    {
                        "name": "Peter",
                        "birth_year": "1962"
                    }
                ]
            }
        },
        "1": {
            "full_name": "Nils O Brynolf",
            "location": "Sollefteå",
            "occupation": "överläkare",
            "birth_details": {
                "date": "05/06/1907",
                "place": "Nässjö"
            },
            "education": [
                {
                    "degree": "Stud:ex",
                    "year": "1926",
                    "institution": "Östersund"
                },
                {
                    "degree": "med kand",
                    "year": "1933",
                    "institution": null
                },
                {
                    "degree": "med lic",
                    "year": "1944",
                    "institution": "Lund"
                }
            ],
            "career": [
                {
                    "position": "överläk röntgenavd",
                    "years": {
                        "start_year": 1951,
                        "end_year": null
                    },
                    "organization": "Sollefteå las"
                }
            ],
            "family": {
                "spouse": "Gun Boogren",
                "marriage_year": "1953",
                "children": [
                    {
                        "name": "Lars",
                        "birth_year": "1954"
                    }
                ]
            }
        },
        "2": {
            "full_name": "David E Brynte",
            "location": "Gävle",
            "occupation": "hovurmakare",
            "birth_details": {
                "date": "24/12/1896",
                "place": "Gävle"
            },
            "education": null,
            "career": null,
            "family": {
                "spouse": "Tyra Wadlund",
                "marriage_year": null,
                "children": [
                    {
                        "name": "Rolf",
                        "birth_year": "1931"
                    }
                ]
            }
        },
        "3": {
            "full_name": "Kjell O Brändström",
            "location": "Sundsvall",
            "occupation": "direktör",
            "birth_details": {
                "date": "17/01/1931",
                "place": "Umeå"
            },
            "education": [
                {
                    "degree": "Stud:ex",
                    "year": "1951",
                    "institution": "Filipstad"
                },
                {
                    "degree": "fil kand",
                    "year": "1955",
                    "institution": "Uppsala"
                },
                {
                    "degree": "DHS",
                    "year": "1957",
                    "institution": null
                }
            ],
            "career": [
                {
                    "position": "forskare",
                    "years": {
                        "start_year": 1956,
                        "end_year": 1956
                    },
                    "organization": "FFI"
                },
                {
                    "position": "direkt:sekr",
                    "years": {
                        "start_year": 1957,
                        "end_year": 1961
                    },
                    "organization": "SCA Sundsvall"
                },
                {
                    "position": "dir:ass",
                    "years": {
                        "start_year": 1961,
                        "end_year": 1963
                    },
                    "organization": null
                }
            ],
            "family": {
                "spouse": "Barbro Eriksson",
                "marriage_year": "1953",
                "children": [
                    {
                        "name": "Johan",
                        "birth_year": "1957"
                    },
                    {
                        "name": "Kristina",
                        "birth_year": "1960"
                    },
                    {
                        "name": "Magnus",
                        "birth_year": "1962"
                    },
                    {
                        "name": "Beata",
                        "birth_year": "1966"
                    }
                ]
            },
            "hobbies": [
                "golf"
            ]
        }
    }
}