{
    "original": "DAVIDSSON, NILS O H,\ntullförvaltare, Kristianstad, f i Åker, Jönkpgs l,\n13/4/16 av tulluppsyn :man Ivar D o\nSelma Johansson.\n\nStud:ex Gbg 35, kammarskr:kurs 39,\nres:off:ex 41; tjg inom tullväs sed 38,\ntullförv tullkamm Åhus sed 58.\nGift 42 m Ingrid Berg f 20, dtr t köpm\nGustaf B o Sigrid Andersén. - Barn:\nBirgitta f 43, Håkan f 47.\n\nDAVIDSON, OTTO K E R,\ndistriktschef, Glumslöv, f i Kristianstad 7/7/11\nav stat :insp Emil D o Karin Johansson.\nRealex 29, Kristianstads språk- o hdlI\n31, anst Försäkr:bol Holmia Malmö 36,\nSDS Landskrona 39, Hallbäcks rev:byrå\nLandskrona 32, distr:ch\nTrafikförsäkr:-bol Bore Hbg sed 551 - Styr :led Kulla\nscoutdistr. - Medl W-sex, Lions club,\nSällsk WB. - Hobbies: scouting, motor.\nGift 38 m Elly Lundin, dtr t maskinist\nFrans L o Hulda L. - Barn: Frans-Otto\nf 45, Jan f 49, Margareta f 52.\n\nDAVIDSSON,   SIGFRID,\nbergsingenjör, Listerby, f i Karlshamn 21/11/88 av\nfabr Svante D o Carolina Johansson.\nBergshögsk 14&gt;, ing Carlsdahls bruk 15,\nGelsenkirchener Bergwerksverein Rothe\nErde Tyskl 15i, Surahammars bruk 16,\nSKF Gbg 18, Hofors bruk 22-48’. -\nHobbies: entomologis, filateli, metallslöjd.\nGift  18  m  Jei  Lidbom f  92.  -  Barn:\nSvante f 19, Helge f 23’.\n\nDAVIDSON,  SUNE C D,  disponent,\nMalmö, f i Djurö, Sthlms l, 24/8/29 av\nköpm Sven D o Ester Lindström.\nStud:ex Sthlm 50, Brod Påhlman» hdlI\n5\"2, anst Thiel &amp; Svenson ab Sthlm 5’3’,\nab Arto Malmö 571, disp där sed 59.\n-Hobbies: foto, travsport.\nGift 33 m Ulla Nordin f 32’, dtr t disp\nGunnar N o  Margit Edlund.  - Barn:\nAnnika f Öls, Elisabet f 63.\n\nDEDERING, SVEN E, professor em,\nLund, f i Nykpg 10/12/97 av köpm Per\nD o Matilda Carlsson.\nFil lic Uppsala 26&gt;, fil dr o doc i\narabiska Språk Upps 27’,, tf prof i semitiska\nspråk GbgHS 36-37, prof i österländska\n\nspråk Lund 37^64. - LLHS 39&gt;, LHA 56,\nkorrL vet :akad Damaskus 56», led\nhumanist förstorade* 59-64. - Skr: Abu\nNu’aim, Geschichte Isbanans I-II\n(31-34), Die Widerlegung der Irrgläubigen\nund Neurer von al-Malati (36), Johannes\nvon Lykopolis, Ein Dialog über die Seelfc\nund die Affekte des Menschen (3tf), Das\nbiographische Lexikon des as-Safadi\nII-IV (49’-5l9). - Utm: KNO.\nGift 28 m Margit Appeltofft f 01, dtr t\nvicekonsul Carl A o Hannah Frijs.\n-Barn: Britt f 29, Sven Olof f 31.\n\nDE GEER, WILLEM G, friherre,\nMalmö, f i Rogberga, Jönkpgs l, 28/12/11\nav frih Gerard De G o Anna Wibeck.\nStud:ex Jönkpg 32, Schartaus HdlI 30,\ntjm Hoechst anilin ab Malmö. - Hobby:\nsportfiske.\n\nGift 55 m Bolla Margareta\nHemming-Sjöberg f 18, dtr t adv, jur dr Axel H-S\no Elin Gustafsson.\n\n",
    "structured": {
        "1": {
            "full_name": "NILS O H DAVIDSSON",
            "location": "Kristianstad",
            "occupation": "tullförvaltare",
            "birth_details": {
                "date": "13/04/1916",
                "place": "Åker, Jönkpgs l"
            },
            "education": [
                {
                    "degree": "Stud:ex",
                    "year": "1935",
                    "institution": "Gbg"
                },
                {
                    "degree": "kammarskr:kurs",
                    "year": "1939",
                    "institution": "res:off:ex"
                }
            ],
            "career": [
                {
                    "position": "tjg inom tullväs",
                    "years": {
                        "start_year": 1938,
                        "end_year": 1941
                    },
                    "organization": "tullförv tullkamm Åhus"
                }
            ],
            "family": {
                "spouse": "Ingrid Berg",
                "marriage_year": "1942",
                "children": [
                    {
                        "name": "Birgitta",
                        "birth_year": "1943"
                    },
                    {
                        "name": "Håkan",
                        "birth_year": "1947"
                    }
                ]
            }
        },
        "2": {
            "full_name": "OTTO K E R DAVIDSON",
            "location": "Glumslöv",
            "occupation": "distriktschef",
            "birth_details": {
                "date": "07/07/1911",
                "place": "Kristianstad"
            },
            "education": [
                {
                    "degree": "Realex",
                    "year": "1929",
                    "institution": "Kristianstads språk- o hdlI"
                }
            ],
            "career": [
                {
                    "position": "anst Försäkr:bol",
                    "years": {
                        "start_year": 1936,
                        "end_year": 1939
                    },
                    "organization": "Holmia Malmö"
                },
                {
                    "position": "distr:ch Trafikförsäkr:-bol",
                    "years": {
                        "start_year": 1955
                    },
                    "organization": "Bore Hbg"
                }
            ],
            "family": {
                "spouse": "Elly Lundin",
                "marriage_year": "1938",
                "children": [
                    {
                        "name": "Frans-Otto",
                        "birth_year": "1945"
                    },
                    {
                        "name": "Jan",
                        "birth_year": "1949"
                    },
                    {
                        "name": "Margareta",
                        "birth_year": "1952"
                    }
                ]
            },
            "hobbies": [
                "scouting",
                "motor"
            ]
        },
        "3": {
            "full_name": "SIGFRID DAVIDSSON",
            "location": "Listerby",
            "occupation": "bergsingenjör",
            "birth_details": {
                "date": "21/11/1888",
                "place": "Karlshamn"
            },
            "education": [
                {
                    "degree": "Bergshögsk",
                    "year": "1914",
                    "institution": "Gelsenkirchener Bergwerksverein Rothe Erde Tyskl"
                }
            ],
            "career": [
                {
                    "position": "ing",
                    "years": {
                        "start_year": 1915,
                        "end_year": 1916
                    },
                    "organization": "Carlsdahls bruk"
                },
                {
                    "position": "ing",
                    "years": {
                        "start_year": 1922,
                        "end_year": 1948
                    },
                    "organization": "Hofors bruk"
                }
            ],
            "family": {
                "spouse": "Jei Lidbom",
                "marriage_year": "1918",
                "children": [
                    {
                        "name": "Svante",
                        "birth_year": "1919"
                    },
                    {
                        "name": "Helge",
                        "birth_year": "1923"
                    }
                ]
            },
            "hobbies": [
                "entomologis",
                "filateli",
                "metallslöjd"
            ]
        },
        "4": {
            "full_name": "SUNE C D DAVIDSON",
            "location": "Malmö",
            "occupation": "disponent",
            "birth_details": {
                "date": "24/08/1929",
                "place": "Djurö, Sthlms l"
            },
            "education": [
                {
                    "degree": "Stud:ex",
                    "year": "1950",
                    "institution": "Sthlm"
                },
                {
                    "degree": "Brod Påhlman» hdlI",
                    "year": "1952"
                }
            ],
            "career": [
                {
                    "position": "anst Thiel & Svenson ab",
                    "years": {
                        "start_year": 1953
                    }
                },
                {
                    "position": "disp",
                    "years": {
                        "start_year": 1959
                    },
                    "organization": "ab Arto Malmö"
                }
            ],
            "family": {
                "spouse": "Ulla Nordin",
                "marriage_year": "1953",
                "children": [
                    {
                        "name": "Annika",
                        "birth_year": "1958"
                    },
                    {
                        "name": "Elisabet",
                        "birth_year": "1963"
                    }
                ]
            },
            "hobbies": [
                "foto",
                "travsport"
            ]
        },
        "5": {
            "full_name": "SVEN E DEDERING",
            "location": "Lund",
            "occupation": "professor em",
            "birth_details": {
                "date": "10/12/1897",
                "place": "Nykpg"
            },
            "education": [
                {
                    "degree": "Fil lic",
                    "year": "1926",
                    "institution": "Uppsala"
                },
                {
                    "degree": "fil dr o doc i arabiska Språk",
                    "year": "1927",
                    "institution": "Upps"
                }
            ],
            "career": [
                {
                    "position": "tf prof i semitiska språk",
                    "years": {
                        "start_year": 1936,
                        "end_year": 1937
                    },
                    "organization": "GbgHS"
                },
                {
                    "position": "prof i österländska språk",
                    "years": {
                        "start_year": 1937,
                        "end_year": 1964
                    },
                    "organization": "Lund"
                }
            ],
            "family": {
                "spouse": "Margit Appeltofft",
                "marriage_year": "1928",
                "children": [
                    {
                        "name": "Britt",
                        "birth_year": "1929"
                    },
                    {
                        "name": "Sven Olof",
                        "birth_year": "1931"
                    }
                ]
            }
        },
        "6": {
            "full_name": "WILLEM G DE GEER",
            "location": "Malmö",
            "occupation": "friherre",
            "birth_details": {
                "date": "28/12/1911",
                "place": "Rogberga, Jönkpgs l"
            },
            "education": [
                {
                    "degree": "Stud:ex",
                    "year": "1932",
                    "institution": "Jönkpg"
                },
                {
                    "degree": "Schartaus HdlI",
                    "year": "1930"
                }
            ],
            "career": [
                {
                    "position": "tjm Hoechst anilin ab",
                    "organization": "Malmö"
                }
            ],
            "family": {
                "spouse": "Bolla Margareta Hemming-Sjöberg",
                "marriage_year": "1955"
            },
            "hobbies": [
                "sportfiske"
            ]
        }
    }
}