{
    "original": "DAHL, A UNO, åkeriägare,\nKristianstad, f i N Åsum, Krist l,  14/1/23 av\nkonditor Axel D o Hildur Svensson.\nJ H Dahls läroanstl, volontär T 4» 46’-4l5,\neg transp :rörelse Kristianstad sed 46.\n-Styr :led IF Kamraterna Kristianstad sed\n60. - Hobbies: jakt, fiske, filateli.\nGift 45 m Inga-Britt Larsson f 25», dtr t\ncharkuterist Fred’rik L o Ida Johansson.\n- Barn: Ulf-Inge f 47, Lärs-Inge f 49.\n\nDAHLBECK, SVEN G I, inköpschef,\nRevingeby, f i T:a Hällestad, Malmöh l,\n19/1/31 av lantbr Hjalmar D o Olga\nWallin.\n\nRealex Lund 48, hdlsutbildn; anst ab\nÅkerlund &amp; Rausing Lund 49, inköpsch\ndär sed 62. - Hobbies: fiske, sport’.\nGift 56 m Majvy Jönsson f 37; dtr t\nsadelmak Herman J o Hilma Silfver.\n-Barn: Anette f 50, Carina f 57, Marie\nf 38i, Niclas f 64.\n\nDAHLBERG, BENGT O, bitr\nombudsman, Vintrie, f i Karlshamn 17/3/28 av\nprost Albin D o Elsa Witzell.\nStud:ex Eslöv  50,  jur  kand Lund  57,\ntingstjg N Åsbo doms 57*-60, bitr\nomb:-man Sydsv kraft ab Malmö sed 60.\n-Hobbies: fiske, bridge.\nGift 5.3 m Ulla-Brittia Johansson f 30,\ndtr t köpm Hugo J o Elna Sandahl.\n-Barn: Bodil f 54, Görel f 57, Helén f 63*.\n\nDAHLBERG, C G BRUNO, med dr,\ndocent, Malmö, f i London 1/5/19 av\nkommendanten i Belg marinen Gustaf\nAdolf D o Florianne Lightman.\nStud:ex 40, med kand 45i o med lic 49\nSthlm, med dr Lund 61, doc i obstetrik\no gynekologi Lunds univ sed 61; öl\nläk:-förordn 49-5&lt;5, l:e und’erläk radiol klin\nLunds las 5$-56, 2:e underläk KK\nMalmö allm sjh 57,, prakt läk sed 62. -\nRes:off:ex FV 42, flygläk 2:a gr 49^52., l:a\ngr sed 52. - Skr i gynekol o radiol\ngynekol. - Hobbies: segling, golf.\nGift 2) m Birgit Lindhe f 28. - Barn: i\nl:a akt Susanne f 48, Marie f 51, Peter\nBruno f 54, i 2:a akt Olof f 57, Carolyn\nf 651\n\n",
    "structured": {
        "0": {
            "full_name": "Dahl, A. Uno",
            "location": "Kristianstad",
            "occupation": "Åkeriägare",
            "birth_details": {
                "date": "14/01/1923",
                "place": "N Åsum, Kristianstad"
            },
            "education": [
                {
                    "degree": "Volontär",
                    "year": "1946-1945",
                    "institution": "J H Dahls läroanstalt"
                }
            ],
            "career": [
                {
                    "position": "Eg transp :rörelse",
                    "years": {
                        "start_year": 1946,
                        "end_year": null
                    },
                    "organization": "Kristianstad"
                },
                {
                    "position": "Styr :led IF Kamraterna",
                    "years": {
                        "start_year": 1960,
                        "end_year": null
                    },
                    "organization": "Kristianstad"
                }
            ],
            "family": {
                "spouse": "Inga-Britt Larsson",
                "marriage_year": "1945",
                "children": [
                    {
                        "name": "Ulf-Inge",
                        "birth_year": "1947"
                    },
                    {
                        "name": "Lärs-Inge",
                        "birth_year": "1949"
                    }
                ]
            }
        },
        "1": {
            "full_name": "Dahlbeck, Sven G. I.",
            "location": "Revingeby",
            "occupation": "Inköpschef",
            "birth_details": {
                "date": "19/01/1931",
                "place": "T:a Hällestad, Malmöh l"
            },
            "education": [
                {
                    "degree": "Realex",
                    "year": "1948",
                    "institution": "Lund"
                },
                {
                    "degree": "Hdlsutbildn",
                    "year": "1949",
                    "institution": "Åkerlund & Rausing Lund"
                }
            ],
            "career": [
                {
                    "position": "Inköpsch",
                    "years": {
                        "start_year": 1962,
                        "end_year": null
                    },
                    "organization": "Åkerlund & Rausing Lund"
                }
            ],
            "family": {
                "spouse": "Majvy Jönsson",
                "marriage_year": "1956",
                "children": [
                    {
                        "name": "Anette",
                        "birth_year": "1950"
                    },
                    {
                        "name": "Carina",
                        "birth_year": "1957"
                    },
                    {
                        "name": "Marie",
                        "birth_year": "1938"
                    },
                    {
                        "name": "Niclas",
                        "birth_year": "1964"
                    }
                ]
            }
        },
        "2": {
            "full_name": "Dahlberg, Bengt O.",
            "location": "Vintrie",
            "occupation": "Bitr ombudsman",
            "birth_details": {
                "date": "17/03/1928",
                "place": "Karlshamn"
            },
            "education": [
                {
                    "degree": "Stud:ex",
                    "year": "1950",
                    "institution": "Eslöv"
                },
                {
                    "degree": "Jur kand",
                    "year": "1957",
                    "institution": "Lund"
                }
            ],
            "career": [
                {
                    "position": "Tingstjg",
                    "years": {
                        "start_year": 1957,
                        "end_year": 1960
                    },
                    "organization": "N Åsbo doms"
                },
                {
                    "position": "Bitr omb:-man",
                    "years": {
                        "start_year": 1960,
                        "end_year": null
                    },
                    "organization": "Sydsv kraft ab Malmö"
                }
            ],
            "family": {
                "spouse": "Ulla-Brittia Johansson",
                "marriage_year": "1953",
                "children": [
                    {
                        "name": "Bodil",
                        "birth_year": "1954"
                    },
                    {
                        "name": "Görel",
                        "birth_year": "1957"
                    },
                    {
                        "name": "Helén",
                        "birth_year": "1963"
                    }
                ]
            }
        },
        "3": {
            "full_name": "Dahlberg, C. G. Bruno",
            "location": "Malmö",
            "occupation": "Med dr, docent",
            "birth_details": {
                "date": "01/05/1919",
                "place": "London"
            },
            "education": [
                {
                    "degree": "Stud:ex",
                    "year": "1940",
                    "institution": null
                },
                {
                    "degree": "Med kand",
                    "year": "1945",
                    "institution": "Sthlm"
                },
                {
                    "degree": "Med lic",
                    "year": "1949",
                    "institution": "Sthlm"
                },
                {
                    "degree": "Med dr",
                    "year": "1961",
                    "institution": "Lund"
                }
            ],
            "career": [
                {
                    "position": "Prakt läk",
                    "years": {
                        "start_year": 1962,
                        "end_year": null
                    },
                    "organization": null
                }
            ],
            "family": {
                "spouse": "Birgit Lindhe",
                "marriage_year": null,
                "children": [
                    {
                        "name": "Susanne",
                        "birth_year": "1948"
                    },
                    {
                        "name": "Marie",
                        "birth_year": "1951"
                    },
                    {
                        "name": "Peter Bruno",
                        "birth_year": "1954"
                    },
                    {
                        "name": "Olof",
                        "birth_year": "1957"
                    },
                    {
                        "name": "Carolyn",
                        "birth_year": "1965"
                    }
                ]
            }
        }
    }
}