{
    "original": "DYMLING, JOHN-FREDRIK A, med\ndr, docent, Malmö, f i Gbg 31/5/31 av\nmed lic Otto D o Astrid Strömberg.\nStud:ex Gbg 49, med kand Lund 52,\nmed lic 56, med dr 64, doc i praktisk\nmedicin Lunds univ sed 64; underläk o\naman med klin Malmö allm sjh 57-64,\naman kem centrallab Malmö allm sjh\n64-65, attending physician Cornell Med\nColl NY USA 65-66, underläk med klin\nMalmö allm sjh sed 66. - S kr om\nske-lettmetabolism m m. - Hobby: golf.\nGift 52 m Birgit Lindbeck f 32, dtr t\nurmak Carl L o Agda Elmlund. - Barn:\nUlla f 531, Stephan f 55, Lotta f 62.\n\nDYRSSEN-HELLBING,   KERSTI   D,\n\njur kand, Ronneby, f i Stettin, Tyskl,\n17/8/31 av agr Peder Dyrssen o Erna\nHeydemann.\n\nMalmö hdlsgymn 50, jur kand Lund 59’,\ntjg åkl:myndigh Sthlm 60, deläg\nHell-bings jurid byrå Ronneby sed 60. - Led\nStadsfullm sed 631 - Ordf Ronneby\nh:-kvinnöfören sed 62, led Högerns\nförb:-styr f Blek sed 64.\n\nGift 56 m jur kand Lennart Hellbing\nf 22. - Barn: Tord f 64.\n\nDYSTER-AAS, ANNITA J M, jur\nkand, Lund, f i Lund 11/12/33 av\nbank-dir Erik Gustaf Cavallin o gymn :dir\nAnnita Hamberg.\n\nStud:ex  51,  jur  kand  Lund  57,  aman\nLunds domkap 58, sekr ab Gleerupska\nuniv:bokhdln sed 59.\nGift 57 m doc, med dr Kjell Dyster-Aas.\n\n-  Barn: Jeanna f 58, Hans f 61, Karin\nf 63.\n\nDYSTER-AAS,   H   KJELL,   med   dr,\n\ndocent, Lund, f i Säf f le 10/6/29 av dir\nHans D-A o Ruth Bjerner.\nStud:ex Lundsberg 4$, med kand Sthlm\nSl’, med lic Lund 571, med dr 65), doc i\noftalimiatrik Lunds univ 63; ass:läk SRK\nfältsjh Korea 52, vik underläk ögonklin\nLunds las 5i5&gt;-5!9|, aman 60 o underläk där\nsed 615. - Bat:läfc VI Sv FN-bat Gaza 59.\n\n-  Skr i oftalmiatrik.\n\nGift 57 m jur kand Annita Cavallin f 33,\ndtr t bankdir Erik Gustaf C o Annitö.\nHamberg. - Barn: Jeanna f 5®, Hans\nf 61i, Karin f 63’,\n\n",
    "structured": {
        "0": {
            "full_name": "DYMLING, JOHN-FREDRIK A",
            "location": "Malmö",
            "occupation": "med dr, docent",
            "birth_details": {
                "date": "31/05/1931",
                "place": "Göteborg",
                "parents": "med lic Otto D o Astrid Strömberg"
            },
            "education": [
                {
                    "degree": "Stud",
                    "year": "1949",
                    "institution": "Göteborg"
                },
                {
                    "degree": "med kand",
                    "year": "1952",
                    "institution": "Lund"
                },
                {
                    "degree": "med lic",
                    "year": "1956",
                    "institution": "NA"
                },
                {
                    "degree": "med dr",
                    "year": "1964",
                    "institution": "NA"
                }
            ],
            "career": [
                {
                    "position": "underläk o aman med klin Malmö allm sjh",
                    "years": {
                        "start_year": 1957,
                        "end_year": 1964
                    },
                    "organization": "NA"
                },
                {
                    "position": "aman kem centrallab Malmö allm sjh",
                    "years": {
                        "start_year": 1964,
                        "end_year": 1965
                    },
                    "organization": "NA"
                },
                {
                    "position": "attending physician",
                    "years": {
                        "start_year": 1965,
                        "end_year": 1966
                    },
                    "organization": "Cornell Med Coll NY USA"
                },
                {
                    "position": "underläk med klin Malmö allm sjh",
                    "years": {
                        "start_year": 1966,
                        "end_year": 9999
                    },
                    "organization": "NA"
                }
            ],
            "family": {
                "spouse": "Birgit Lindbeck",
                "marriage_year": "1952",
                "children": [
                    {
                        "name": "Ulla",
                        "birth_year": "1953"
                    },
                    {
                        "name": "Stephan",
                        "birth_year": "1955"
                    },
                    {
                        "name": "Lotta",
                        "birth_year": "1962"
                    }
                ]
            },
            "hobbies": [
                "golf"
            ]
        },
        "1": {
            "full_name": "DYRSSEN-HELLBING, KERSTI D",
            "location": "Ronneby",
            "occupation": "jur kand",
            "birth_details": {
                "date": "17/08/1931",
                "place": "Stettin, Tyskland",
                "parents": "agr Peder Dyrssen o Erna Heydemann"
            },
            "education": [
                {
                    "degree": "Malmö hdlsgymn",
                    "year": "1950",
                    "institution": "NA"
                },
                {
                    "degree": "jur kand",
                    "year": "1959",
                    "institution": "Lund"
                }
            ],
            "career": [
                {
                    "position": "deläg Hellbings jurid byrå Ronneby",
                    "years": {
                        "start_year": 1960,
                        "end_year": 9999
                    },
                    "organization": "NA"
                }
            ],
            "family": {
                "spouse": "Lennart Hellbing",
                "marriage_year": "1956",
                "children": [
                    {
                        "name": "Tord",
                        "birth_year": "1964"
                    }
                ]
            }
        },
        "2": {
            "full_name": "DYSTER-AAS, ANNITA J M",
            "location": "Lund",
            "occupation": "jur kand",
            "birth_details": {
                "date": "11/12/1933",
                "place": "Lund",
                "parents": "bank-dir Erik Gustaf Cavallin o gymn :dir Annita Hamberg"
            },
            "education": [
                {
                    "degree": "Stud:ex",
                    "year": "1951",
                    "institution": "NA"
                },
                {
                    "degree": "jur kand",
                    "year": "1957",
                    "institution": "Lund"
                }
            ],
            "career": [
                {
                    "position": "aman Lunds domkap",
                    "years": {
                        "start_year": 1958,
                        "end_year": 9999
                    },
                    "organization": "NA"
                },
                {
                    "position": "sekr ab Gleerupska univ:bokhdln",
                    "years": {
                        "start_year": 1959,
                        "end_year": 9999
                    },
                    "organization": "NA"
                }
            ],
            "family": {
                "spouse": "Kjell Dyster-Aas",
                "marriage_year": "1957",
                "children": [
                    {
                        "name": "Jeanna",
                        "birth_year": "1958"
                    },
                    {
                        "name": "Hans",
                        "birth_year": "1961"
                    },
                    {
                        "name": "Karin",
                        "birth_year": "1963"
                    }
                ]
            }
        },
        "3": {
            "full_name": "DYSTER-AAS, H KJELL",
            "location": "Lund",
            "occupation": "med dr, docent",
            "birth_details": {
                "date": "10/06/1929",
                "place": "Säffle",
                "parents": "dir Hans D-A o Ruth Bjerner"
            },
            "education": [
                {
                    "degree": "Stud:ex",
                    "year": "1945",
                    "institution": "Lundsberg"
                },
                {
                    "degree": "med kand",
                    "year": "Sl’",
                    "institution": "Sthlm"
                },
                {
                    "degree": "med lic",
                    "year": "571",
                    "institution": "Lund"
                },
                {
                    "degree": "med dr",
                    "year": "65",
                    "institution": "NA"
                }
            ],
            "career": [
                {
                    "position": "ass:läk SRK fältsjh Korea",
                    "years": {
                        "start_year": 1952,
                        "end_year": 9999
                    },
                    "organization": "NA"
                },
                {
                    "position": "vik underläk ögonklin Lunds las",
                    "years": {
                        "start_year": 1955,
                        "end_year": 1959
                    },
                    "organization": "NA"
                },
                {
                    "position": "aman",
                    "years": {
                        "start_year": 1960,
                        "end_year": 9999
                    },
                    "organization": "NA"
                }
            ],
            "family": {
                "spouse": "Annita Cavallin",
                "marriage_year": "1957",
                "children": [
                    {
                        "name": "Jeanna",
                        "birth_year": "1958"
                    },
                    {
                        "name": "Hans",
                        "birth_year": "1961"
                    },
                    {
                        "name": "Karin",
                        "birth_year": "1963"
                    }
                ]
            }
        }
    }
}