{
    "original": "DALEN, INGABRITT M E, leg läkare,\n\nHalmstad, f i Botkyrka, Sthlms l, 9/4/22\nav kamr Elis Larson o Rose-Marie\nHåkansson.\n\nStud:ex Malmö 42, med lic Lund 52,\nbarapsykiater centrallås Halmstad sed\n61’. - Läk centralstyr f undervisn o vård\nav psyk efterblivna i Hall l sed 62.\nGift 60 m stadsbibl :ie Gunnar Dalen\nf 22. - Barn: Anna f 62.\n\nDALIN, EDVIN E R, direktör,\nSvedala, f i Burlöv, Malmöh l, 2/7/03 av\nPer D o Anna Hansson.\nTekn gymn Malmö 25, KTH 3^; lär\nTekn gymn Malmö 32, stud Tyskl 331-34,\ning Manufaktur ab Malmö 3!5-36,\növering :ass Sv metallverken Västerås 37-42,\ndir :ass ab Åbjörn Anderson Svedala\n43-49, v verkst dir 50-51, verkst dir där sed\n52 o ab Försökstegelbruket Svedala sed\n53, - Suppl Sv:es verkst :f ören översüyr\nsed Sl; stiyr:led Skånska bkn Malmö sed\n519, ordf dess lokalstyr Svedala sed 55,\nstyr :ordf Kärnas ab Kvarnmaskiner 63,\nArbrå verkst ab 64, styr :led ab\nFörsöks-tegelbruket Svedala 53, ab Åbjörn\nAndersson Svedala 50, ab Skåneintressenter\nMalmö 63. - Rekt komm yrkessk Sve-\n\ndala 45f-52:, ex :omb Tekn gymn Malmö\nsed 481 - Led komm:fullm 47-49,\nkomm:-nd o ordf dess tekn avd 56-63:, ordf\ngatustiyr 46i-49, tekn ndn 50-55. - Utm:\nRVO.\n\nGift 371 m Ingrid Åbjörnsson f 13’, dtr t\ndir Herman Å o Märta Johnsson.\n-Barn: Elna f 39, Annette f 43-, Ylva f 46.\n\nDALMAN, G MARIANNE,\nläroverksadjunkt, Halmstad, f i Sthlm 11/4/17 av\nkont:ch Otto D o Ellen Schweder.\nStud:ex Malmö 37, fil1 mag Lund 43’, e\nlär komm flicksk Karlskrona 45, e adj\nhal f g Hbg 47, provar hal f g Malmö\n48-49, eo adj hal Kristianstad 49, adj i\nmatem o fys hal Halmstad sed 50.\n\n",
    "structured": {
        "1": {
            "full_name": "Dalen, Ingabritt M E",
            "location": "Halmstad",
            "occupation": "leg läkare",
            "birth_details": {
                "date": "09/04/1922",
                "place": "Botkyrka, Stockholms län",
                "parents": "kamr Elis Larson o Rose-Marie Håkansson"
            },
            "education": [
                {
                    "degree": "Stud:ex",
                    "year": "1942",
                    "institution": "Malmö"
                },
                {
                    "degree": "med lic",
                    "year": "1952",
                    "institution": "Lund"
                }
            ],
            "career": [
                {
                    "position": "barapsykiater centrallås",
                    "years": {
                        "start_year": 1961,
                        "end_year": null
                    },
                    "organization": "Halmstad"
                },
                {
                    "position": "Läk centralstyr",
                    "years": {
                        "start_year": 1962,
                        "end_year": null
                    },
                    "organization": "undervisn o vård av psyk efterblivna i Hall l"
                }
            ],
            "family": {
                "spouse": "stadsbibl :ie Gunnar Dalen",
                "marriage_year": "1960",
                "children": [
                    {
                        "name": "Anna",
                        "birth_year": "1962"
                    }
                ]
            }
        },
        "2": {
            "full_name": "Dalin, Edvin E R",
            "location": "Svedala",
            "occupation": "direktör",
            "birth_details": {
                "date": "02/07/1903",
                "place": "Burlöv, Malmöhus län",
                "parents": "Per D o Anna Hansson"
            },
            "education": [
                {
                    "degree": "Tekn gymn",
                    "year": "1925",
                    "institution": "Malmö"
                },
                {
                    "degree": "KTH",
                    "year": "3^",
                    "institution": null
                },
                {
                    "degree": "stud Tyskl",
                    "year": "1931-1934",
                    "institution": null
                }
            ],
            "career": [
                {
                    "position": "lär Tekn gymn",
                    "years": {
                        "start_year": 1932,
                        "end_year": 1935
                    },
                    "organization": "Malmö"
                },
                {
                    "position": "ing Manufaktur ab",
                    "years": {
                        "start_year": 1935,
                        "end_year": 1936
                    },
                    "organization": "Malmö"
                },
                {
                    "position": "övering :ass Sv metallverken",
                    "years": {
                        "start_year": 1937,
                        "end_year": 1942
                    },
                    "organization": "Västerås"
                },
                {
                    "position": "dir :ass ab Åbjörn Anderson",
                    "years": {
                        "start_year": 1943,
                        "end_year": 1949
                    },
                    "organization": "Svedala"
                },
                {
                    "position": "v verkst dir",
                    "years": {
                        "start_year": 1950,
                        "end_year": 1951
                    },
                    "organization": "där"
                },
                {
                    "position": "verkst dir",
                    "years": {
                        "start_year": 1952,
                        "end_year": null
                    },
                    "organization": "ab Försökstegelbruket Svedala"
                }
            ],
            "family": {
                "spouse": "Ingrid Åbjörnsson",
                "marriage_year": "1937",
                "children": [
                    {
                        "name": "Elna",
                        "birth_year": "1939"
                    },
                    {
                        "name": "Annette",
                        "birth_year": "1943"
                    },
                    {
                        "name": "Ylva",
                        "birth_year": "1946"
                    }
                ]
            }
        },
        "3": {
            "full_name": "Dalman, G Marianne",
            "location": "Halmstad",
            "occupation": "läroverksadjunkt",
            "birth_details": {
                "date": "11/04/1917",
                "place": "Stockholm",
                "parents": "kont:ch Otto D o Ellen Schweder"
            },
            "education": [
                {
                    "degree": "Stud:ex",
                    "year": "1937",
                    "institution": "Malmö"
                },
                {
                    "degree": "fil1 mag",
                    "year": "1943",
                    "institution": "Lund"
                }
            ],
            "career": [
                {
                    "position": "lär komm flicksk",
                    "years": {
                        "start_year": 1945,
                        "end_year": null
                    },
                    "organization": "Karlskrona"
                },
                {
                    "position": "adj hal",
                    "years": {
                        "start_year": 1947,
                        "end_year": null
                    },
                    "organization": "Helsingborg"
                },
                {
                    "position": "provar hal",
                    "years": {
                        "start_year": 1948,
                        "end_year": 1949
                    },
                    "organization": "Malmö"
                },
                {
                    "position": "eo adj hal",
                    "years": {
                        "start_year": 1949,
                        "end_year": null
                    },
                    "organization": "Kristianstad"
                },
                {
                    "position": "adj i matem o fys hal",
                    "years": {
                        "start_year": 1950,
                        "end_year": null
                    },
                    "organization": "Halmstad"
                }
            ],
            "family": null
        }
    }
}