{
    "original": "DAHLIN, JAN G I, ingenjör, Malmö,\nf i Boden 1/6/32 av hamndir John-Iwar\nD o Ingrid Nilsson.\n\nIng:ex MTL Hbg 5151, sjöing:ex Gbg 57,\ning tekn avd! Mobil Oil ab Sthlm 58,\nmarinavd1 62, distr :ch marinavd Malmö\nsed 661. - Medl Skånska ing:klubben.\n-Ho b by: fotografering.\nGift 60 m Kristina Klingberg f 38, dtr t\ndir Anders K o Rut Berg. - Barn:\nHelena f 62, Henrik f 64.\n\nDAHLIN, LARS O, advokat, Ystad,\nf i Lund 8/8/28 av adv Henning D o\nSiri Larsson.\n\nStiud:ex Ystad! 48», jur kand Lund 55, bitr\njur h adv Henning Dahlin Ystad sed 55’.\n- LSA 61. - Led Sv hdlsbkn» lokalstyr,\nstyr:led Ystads fastigh :äg :f ören,\nstyr:-suppl Ystads stuveri ab. - V ordf\nbarna-v:ndi, led hälsov:nd. - Medl Lions club,\nTNI. - Hobby: golf.\n\nGift 53 m Inga Forsberg f 281, dtr t ing\nAdolf F o Ingeborg Isaksson. - Barn:\nSusanne f 56, Monica f 58, Lars f 61.\n\nDAHLIN, E LEIF, distriktschef,\nFalkenberg, f i Gbg 7/11/21 av kvarnmäst\nArvid D o Linnea Nicklasson.\nFilip Holmqvists hdlI Gbg 44, anst Hall\nlantmäns centralfören 45-49, distr :ch Ve-\n\ngetebol f Hall l sed 49. - Medl Lions\nclub, FrimO, W-sex. - Hobby: golf.\nGift 43 m Kerstin Andersson f 1% dtr t\ndir C A A o Agnes Hansson). - Barn:\nMargardtia f 44, Carl-Erik f 4$, Christer\nf 52.\n\nDAHLIN, K A LENNART, ingenjör,\n\nMalmö, f i Malmö 17/10/22 av verkm\nAlgot D o Astrid Andersson.\nIng:ex NKI 53; elektr El ab AEG\nMalmö 38-52, ing C J Karlsson el ab Hbg\n53, Kockums mek verkst ab sed 54. - V\nordf HSB-fören Eriksfält 62, bost:omr\nfritidskomm 62. - Medl Skånska\ning:klubben. - Hobby: ungdomsverksamhet.\nGift 56 m Ulla Persson f 34, dtr t\nSeverin P o Ida Andersson. - Barn: Anders\nf 60, Per f 64.\n\n",
    "structured": {
        "1": {
            "full_name": "Jan G I Dahlin",
            "location": "Malmö",
            "occupation": "Ingenjör",
            "birth_details": {
                "date": "01/06/1932",
                "place": "Boden",
                "parents": "John-Iwar D o Ingrid Nilsson"
            },
            "education": [
                {
                    "degree": "MTL Hbg 5151",
                    "year": "NULL",
                    "institution": "NULL"
                },
                {
                    "degree": "Sjöing:ex Gbg 57",
                    "year": "NULL",
                    "institution": "NULL"
                },
                {
                    "degree": "Ing tekn avd! Mobil Oil ab Sthlm 58",
                    "year": "NULL",
                    "institution": "NULL"
                },
                {
                    "degree": "Marinavd1 62",
                    "year": "NULL",
                    "institution": "NULL"
                },
                {
                    "degree": "Distr:ch marinavd Malmö 661",
                    "year": "NULL",
                    "institution": "NULL"
                }
            ],
            "career": [
                {
                    "position": "NULL",
                    "years": {
                        "start_year": 5151,
                        "end_year": 5151
                    },
                    "organization": "NULL"
                }
            ],
            "family": {
                "spouse": "Kristina Klingberg",
                "marriage_year": "1960",
                "children": [
                    {
                        "name": "Helena",
                        "birth_year": "1962"
                    },
                    {
                        "name": "Henrik",
                        "birth_year": "1964"
                    }
                ]
            }
        },
        "2": {
            "full_name": "Lars O Dahlin",
            "location": "Ystad",
            "occupation": "Advokat",
            "birth_details": {
                "date": "08/08/1928",
                "place": "Lund",
                "parents": "Henning D o Siri Larsson"
            },
            "education": [
                {
                    "degree": "Stiud:ex Ystad! 48",
                    "year": "NULL",
                    "institution": "NULL"
                },
                {
                    "degree": "Jur kand Lund 55",
                    "year": "NULL",
                    "institution": "NULL"
                }
            ],
            "career": [
                {
                    "position": "bitr jur h adv",
                    "years": {
                        "start_year": 1955,
                        "end_year": "NULL"
                    },
                    "organization": "Henning Dahlin Ystad"
                }
            ],
            "family": {
                "spouse": "Inga Forsberg",
                "marriage_year": "1953",
                "children": [
                    {
                        "name": "Susanne",
                        "birth_year": "1956"
                    },
                    {
                        "name": "Monica",
                        "birth_year": "1958"
                    },
                    {
                        "name": "Lars",
                        "birth_year": "1961"
                    }
                ]
            },
            "hobbies": [
                "golf"
            ]
        },
        "3": {
            "full_name": "E Leif Dahlin",
            "location": "Falkenberg",
            "occupation": "Distriktschef",
            "birth_details": {
                "date": "07/11/1921",
                "place": "Gbg",
                "parents": "Arvid D o Linnea Nicklasson"
            },
            "education": [
                {
                    "degree": "Filip Holmqvists hdlI Gbg 44",
                    "year": "NULL",
                    "institution": "NULL"
                }
            ],
            "career": [
                {
                    "position": "anst Hall lantmäns centralfören 45-49",
                    "years": {
                        "start_year": 1945,
                        "end_year": 1949
                    },
                    "organization": "NULL"
                },
                {
                    "position": "distr:ch Vegebol f Hall l",
                    "years": {
                        "start_year": 1949,
                        "end_year": "NULL"
                    },
                    "organization": "NULL"
                }
            ],
            "family": {
                "spouse": "Kerstin Andersson",
                "marriage_year": "1943",
                "children": [
                    {
                        "name": "Margardtia",
                        "birth_year": "1944"
                    },
                    {
                        "name": "Carl-Erik",
                        "birth_year": "1945"
                    },
                    {
                        "name": "Christer",
                        "birth_year": "1952"
                    }
                ],
                "hobbies": [
                    "golf"
                ]
            }
        },
        "4": {
            "full_name": "K A Lennart Dahlin",
            "location": "Malmö",
            "occupation": "Ingenjör",
            "birth_details": {
                "date": "17/10/1922",
                "place": "Malmö",
                "parents": "Algot D o Astrid Andersson"
            },
            "education": [
                {
                    "degree": "Ing:ex NKI 53",
                    "year": "NULL",
                    "institution": "NULL"
                }
            ],
            "career": [
                {
                    "position": "elektr El ab AEG Malmö 38-52",
                    "years": {
                        "start_year": 1938,
                        "end_year": 1952
                    },
                    "organization": "NULL"
                },
                {
                    "position": "ing C J Karlsson el ab Hbg 53",
                    "years": {
                        "start_year": 1953,
                        "end_year": "NULL"
                    },
                    "organization": "NULL"
                },
                {
                    "position": "Kockums mek verkst ab",
                    "years": {
                        "start_year": 1954,
                        "end_year": "NULL"
                    },
                    "organization": "NULL"
                }
            ],
            "family": {
                "spouse": "Ulla Persson",
                "marriage_year": "1956",
                "children": [
                    {
                        "name": "Anders",
                        "birth_year": "1960"
                    },
                    {
                        "name": "Per",
                        "birth_year": "1964"
                    }
                ]
            },
            "hobbies": [
                "ungdomsverksamhet"
            ]
        }
    }
}