{
    "original": "STEFFNER, BENGT G, kronofogde,\nSkövde, f i Bjurholm, Västerb l, 11/9/29\nav kantor John S o Eivor Berglind.\nStud:ex Skövde 48, distr:åkl:ex StHS 52,\nlandsfisk :ass Skarab l 53, bitr\nlandsfiskal Skara 58, eo landsfiskal där 60,\n\n62 gö\n\nkronofogde Skövde sed 65. - Styr :led\nFören Sv:es landsfiskaler 60-65, Fören\nSv:es kronofogdar o Sv:es juristförb:s\nsekt f jurister inom exekutionsväs sed 65.\n\n-  Ordf Tidaholms 2 :a särsk tax :distr.\n-Medl Round Table. - Hobby: sport.\nGift 55 m Anita Setterberg f 35, dtr t\ndistr :ch N S o Gurli S. - Barn: Elisabet\nf 56, Annika f 60.\n\nSTEG,  GÖRAN  H,  med  dr,  docent,\n\nGbg, f i Uddevalla 19/12/26 av disp:läk\nHjalmar Anderson o gymn :dir Rut\nVie-weg.\n\nStud:ex Gbg 45, med kand 48 o med lic\nUpps 55, med dr Gbg 64, doc i\nexperimentell neurologi Gbgs univ sed 64;\naman o ass fysiol inst Upps univ 48 o\n50, neurofysiol avd Karol inst 55-57,\nunderläk Lillhagens sjh 58-60, neurolog\nklin resp klin neurofysiol lab Sahlgr sjh\n60-61, aman resp forskarass fysiol inst\nGbgs univ 61-64, vik resp eo doc i\nexperimentell neurologi Gbgs univ sed 65.\n-Ordf Med fören Upps 50-51, Stud :f ören\nVerdandi 52-53. - Skr: Efferent muscle\ninnervation and rigidity (drsavh 64) m m\ninom neurofysiologi.\nGift 55 m bitr psykolog Birgitta Carlson\nf 21, dtr t överinsp Petrus C o Valborg\nJerdén. - Barn: Görel f 57, Maria f 59,\nAnna f 64.\n\nSTEGERSJÖ, BERTIL A, tandläkare,\n\nBorås, f i Sjötofta, Älvsb l, 10/4/20 av\nlantbr August Pettersson o Jenny\nJonsson.\n\nStud:ex Lund 40, tandl:ex Sthlm 48,\ntandl folktandv Jönkpg 48-51, ass:tandl\nMjölby 51-56, priv :prakt Borås sed 56.\n\n-  Skattm Älvsb tandl:fören 59-62. - Medl\nFrimO.\n\nGift 51 m Ingrid Gustavsson f 25, dtr t\nskohandl Algot G o Ingeborg Sjöberg.\n-Barn: Göran f 53, Anders f 57.\n\n",
    "structured": {
        "0": {
            "full_name": "BENGT G STEFFNER",
            "location": "Skövde",
            "occupation": "kronofogde",
            "birth_details": {
                "date": "11/09/1929",
                "place": "Bjurholm, Västerbotten"
            },
            "education": [
                {
                    "degree": "Stud:ex",
                    "year": "1948",
                    "institution": "Skövde"
                },
                {
                    "degree": "distr:åkl:ex",
                    "year": "1952",
                    "institution": "StHS"
                },
                {
                    "degree": "landsfisk :ass",
                    "year": "1953",
                    "institution": "Skaraborg"
                }
            ],
            "career": [
                {
                    "position": "bitr landsfiskal",
                    "years": {
                        "start_year": 1958,
                        "end_year": 1960
                    },
                    "organization": "Skara"
                },
                {
                    "position": "eo landsfiskal",
                    "years": {
                        "start_year": 1960,
                        "end_year": 1962
                    },
                    "organization": "Skara"
                },
                {
                    "position": "kronofogde",
                    "years": {
                        "start_year": 1965,
                        "end_year": null
                    },
                    "organization": "Skövde"
                }
            ],
            "family": {
                "spouse": "Anita Setterberg",
                "marriage_year": "1955",
                "children": [
                    {
                        "name": "Elisabet",
                        "birth_year": "1956"
                    },
                    {
                        "name": "Annika",
                        "birth_year": "1960"
                    }
                ]
            },
            "hobbies": [
                "sport"
            ]
        },
        "1": {
            "full_name": "GÖRAN H STEG",
            "location": "Gbg",
            "occupation": "med dr, docent",
            "birth_details": {
                "date": "19/12/1926",
                "place": "Uddevalla"
            },
            "education": [
                {
                    "degree": "Stud:ex",
                    "year": "1945",
                    "institution": "Gbg"
                },
                {
                    "degree": "med kand",
                    "year": "1948",
                    "institution": "Gbg"
                },
                {
                    "degree": "med lic",
                    "year": "1955",
                    "institution": "Upps"
                },
                {
                    "degree": "med dr",
                    "year": "1964",
                    "institution": "Gbg"
                }
            ],
            "career": [
                {
                    "position": "doc i experimentell neurologi",
                    "years": {
                        "start_year": 1964,
                        "end_year": null
                    },
                    "organization": "Gbgs univ"
                }
            ],
            "family": {
                "spouse": "Birgitta Carlson",
                "marriage_year": "1955",
                "children": [
                    {
                        "name": "Görel",
                        "birth_year": "1957"
                    },
                    {
                        "name": "Maria",
                        "birth_year": "1959"
                    },
                    {
                        "name": "Anna",
                        "birth_year": "1964"
                    }
                ]
            }
        },
        "2": {
            "full_name": "BERTIL A STEGERSJÖ",
            "location": "Borås",
            "occupation": "tandläkare",
            "birth_details": {
                "date": "10/04/1920",
                "place": "Sjötofta, Älvsborg"
            },
            "education": [
                {
                    "degree": "Stud:ex",
                    "year": "1940",
                    "institution": "Lund"
                },
                {
                    "degree": "tandl:ex",
                    "year": "1948",
                    "institution": "Sthlm"
                }
            ],
            "career": [
                {
                    "position": "tandl folktandv",
                    "years": {
                        "start_year": 1948,
                        "end_year": 1951
                    },
                    "organization": "Jönkpg"
                },
                {
                    "position": "ass:tandl",
                    "years": {
                        "start_year": 1951,
                        "end_year": 1956
                    },
                    "organization": "Mjölby"
                },
                {
                    "position": "priv :prakt",
                    "years": {
                        "start_year": 1956,
                        "end_year": null
                    },
                    "organization": "Borås"
                }
            ],
            "family": {
                "spouse": "Ingrid Gustavsson",
                "marriage_year": "1951",
                "children": [
                    {
                        "name": "Göran",
                        "birth_year": "1953"
                    },
                    {
                        "name": "Anders",
                        "birth_year": "1957"
                    }
                ]
            }
        }
    }
}