{
    "original": "SANDBERG, KARIN A, tandläkare,\nVärnamo, f i Jönkpg 13/11/07 av byggm\nJohan Magnusson o Frida Svensson.\nStud:ex Lund 29, tandl:ex Sthlm 36,\npriv:prakt Jönkpg 37-40, tandl folktandv\nVrigstad o Värnamo 40-42, priv:prakt\nVärnamo sed 43.\n\nGift 37 m tandl Curt Sandberg f 10.\n-Barn: Görel f 43.\n\nSANDBERG, NILS V, förste\nbibliotekarie, Gbg, f i Vänersborg 9/12/11 av\npostvaktm Vilhelm S o Maria Åberg.\nStud:ex 30, fil kand 32 o fil mag Gbg\n33, fil lic 44, lär:tjg 33-46, aman Gbgs\nstadsbibl 47, bibl:ie 54, l:e bibl:ie där\n58-60, Gbgs univ :bibl sed 61. - Skr bl a:\nEuploia, Etudes épigraphiques (54),\nVänersborgs lärov matr 1821—1947 (61),\ntidskr :upps rör bokväsen, bibl :teknik o\nkulturhist.\n\nGift 47 m Linnea Ullberg f 22, dtr t\nlantbr Oskar U o Hildur Kjellqvist.\n-Barn: Anders f 48, Karin f 51, Ingrid\nf 53.\n\nSANDBERG, OLLE, aukt revisor,\nLerum, f i Sthlm 5/12/23 av J E S o\nKerstin Lööv.\n\nRes:off:ex 44, DHS 50; tjm\nSparbankernas bk ab 43-47, dir:ass ICA 50, rev 56,\naukt rev 61, eg rev:byrå sed 62. - Medl\nAuroraO. - Kapt trängtr res 61.\nGift 58 m Maj-Britt Folkesson f 29,\ndtr t verkm Folke Pettersson o Jenny\nSvensson. - Barn: Gabriella f 59, Stefan\nf 60, Peter f 63.\n\nSANDBERG, N G SIGGE,\ncivilingenjör, Lidköping, f i Fjälkinge, Kristianst\nl, 7/11/25 av ing Wictor S o Henny\nSvensson.\n\nHTL 51, CTH 57; lär samrealsk Lilla\nEdet 53, e adj hal Trollhättan 55,\ndrifts-ing ab Rörstrands porslinsfabr 61, adj\nDe la Gardiesk Lidkpg sed 62. - Kapt\nI 15 res. - Hobbies: fiske, bridge.\nG//r 52 m Britta Kallfors f 29, dtr t\nbyråass G A K o Olga Nordberg.\n-Barn: Lars f 54, Eva f 55.\n\n",
    "structured": {
        "1": {
            "full_name": "KARIN A SANDBERG",
            "location": "Värnamo",
            "occupation": "tandläkare",
            "birth_details": {
                "date": "13/11/1907",
                "place": "Jönköping",
                "parents": "byggm Johan Magnusson o Frida Svensson"
            },
            "education": [
                {
                    "degree": "Stud:ex",
                    "year": "1929",
                    "institution": "Lund"
                },
                {
                    "degree": "tandl:ex",
                    "year": "1936",
                    "institution": "Sthlm"
                }
            ],
            "career": [
                {
                    "position": "priv:prakt",
                    "years": {
                        "start_year": 1937,
                        "end_year": 1940
                    },
                    "organization": "Jönköping"
                },
                {
                    "position": "tandl folktandv",
                    "years": {
                        "start_year": 1940,
                        "end_year": 1942
                    },
                    "organization": "Vrigstad o Värnamo"
                },
                {
                    "position": "priv:prakt",
                    "years": {
                        "start_year": 1943
                    },
                    "organization": "Värnamo"
                }
            ],
            "family": {
                "spouse": "tandl Curt Sandberg",
                "marriage_year": "1937",
                "children": [
                    {
                        "name": "Görel",
                        "birth_year": "1943"
                    }
                ]
            }
        },
        "2": {
            "full_name": "NILS V SANDBERG",
            "location": "Göteborg",
            "occupation": "förste bibliotekarie",
            "birth_details": {
                "date": "9/12/1911",
                "place": "Vänersborg",
                "parents": "postvaktm Vilhelm S o Maria Åberg"
            },
            "education": [
                {
                    "degree": "Stud:ex",
                    "year": "1930",
                    "institution": "gbg"
                },
                {
                    "degree": "fil kand",
                    "year": "1932",
                    "institution": "Gbg"
                },
                {
                    "degree": "fil mag",
                    "year": "1933",
                    "institution": "Gbg"
                },
                {
                    "degree": "fil lic",
                    "year": "1944"
                }
            ],
            "career": [
                {
                    "position": "lär:tjg",
                    "years": {
                        "start_year": 1933,
                        "end_year": 1946
                    }
                },
                {
                    "position": "aman",
                    "organization": "Gbgs stadsbibl",
                    "years": {
                        "start_year": 1947
                    }
                },
                {
                    "position": "bibl:ie",
                    "organization": "Gbgs univ :bibl",
                    "years": {
                        "start_year": 1958,
                        "end_year": 1960
                    }
                }
            ],
            "family": {
                "spouse": "Linnea Ullberg",
                "marriage_year": "1947",
                "children": [
                    {
                        "name": "Anders",
                        "birth_year": "1948"
                    },
                    {
                        "name": "Karin",
                        "birth_year": "1951"
                    },
                    {
                        "name": "Ingrid",
                        "birth_year": "1953"
                    }
                ]
            }
        },
        "3": {
            "full_name": "OLLE SANDBERG",
            "location": "Lerum",
            "occupation": "aukt revisor",
            "birth_details": {
                "date": "5/12/1923",
                "place": "Sthlm",
                "parents": "J E S o Kerstin Lööv"
            },
            "education": [
                {
                    "degree": "Res:off:ex",
                    "year": "1944"
                },
                {
                    "degree": "DHS",
                    "year": "1950"
                }
            ],
            "career": [
                {
                    "position": "tjm",
                    "organization": "Sparbankernas bk ab",
                    "years": {
                        "start_year": 1943,
                        "end_year": 1947
                    }
                },
                {
                    "position": "dir:ass",
                    "organization": "ICA",
                    "years": {
                        "start_year": 1950
                    }
                },
                {
                    "position": "rev",
                    "years": {
                        "start_year": 1956
                    }
                },
                {
                    "position": "aukt rev",
                    "years": {
                        "start_year": 1961
                    }
                }
            ],
            "family": {
                "spouse": "Maj-Britt Folkesson",
                "marriage_year": "1958",
                "children": [
                    {
                        "name": "Gabriella",
                        "birth_year": "1959"
                    },
                    {
                        "name": "Stefan",
                        "birth_year": "1960"
                    },
                    {
                        "name": "Peter",
                        "birth_year": "1963"
                    }
                ]
            }
        },
        "4": {
            "full_name": "N G SIGGE SANDBERG",
            "location": "Lidköping",
            "occupation": "civilingenjör",
            "birth_details": {
                "date": "7/11/1925",
                "place": "Fjälkinge, Kristianst l",
                "parents": "ing Wictor S o Henny Svensson"
            },
            "education": [
                {
                    "degree": "HTL",
                    "year": "1951"
                },
                {
                    "degree": "CTH",
                    "year": "1957"
                }
            ],
            "career": [
                {
                    "position": "lär",
                    "organization": "samrealsk Lilla Edet",
                    "years": {
                        "start_year": 1953
                    }
                },
                {
                    "position": "e adj",
                    "organization": "hal Trollhättan",
                    "years": {
                        "start_year": 1955
                    }
                },
                {
                    "position": "drifts-ing",
                    "organization": "Rörstrands porslinsfabr",
                    "years": {
                        "start_year": 1961
                    }
                },
                {
                    "position": "adj",
                    "organization": "De la Gardiesk Lidkpg",
                    "years": {
                        "start_year": 1962
                    }
                }
            ],
            "family": {
                "spouse": "Britta Kallfors",
                "marriage_year": "1952",
                "children": [
                    {
                        "name": "Lars",
                        "birth_year": "1954"
                    },
                    {
                        "name": "Eva",
                        "birth_year": "1955"
                    }
                ]
            },
            "hobbies": [
                "fiske",
                "bridge"
            ]
        }
    }
}