{
    "original": "SMEDBERG,  A E BÖRJE,\nhovrättsråd, Jönköping, f 17.\nFiskal Göta hovr 49, adj led 56, assess\n57, hovr:råd där sed 59; tf rev:sekr 59.\n\nSMEDEGÅRD, STIG OLOF,\nlantmätare, Mariestad, f i Skalunda, Skarab l,\n12/1/19 av lantbr Wiktor Olsson o Julia\nMoberg.\n\nStud:ex Skövde 39, KTH 44, lantmät\nLidkpg 44, Sthlm 50, Hässleholm 52,\nSkara 59, Mariestad sed 60, ch\nlantmäteriets specialenhet Skarab l sed 60.\nGift 47 m Ingrid Johnsson f 24, dtr t\nlokför John J o Selma Nilsson. - Barn:\nGöran f 48, Mats f 50, Stefan f 53,\nKarin f 61.\n\nSMIDJE-SUNDBERG, ULLA V,\nskådespelerska,  Gbg,  f  i  Ullared,  Hall l,\n26/12/25 av smidesmäst Sven Carlsson o\nElsa Bengtsson.\nRealex Varberg 42, Dram teat elevsk 46-\n\n49,  eng Dram teat 49-53, stadsteat Hbg\n53-57, stadsteat Gbg sed 57. - Lär Stat\nsk f scen utbildn sed 62, verksam inom\nradio- o TV-teater. - Bl roller: Lizzie i\nDen respektfulla skökan, Neil i\nVärmebölja, Amy i Söndagshustrun,\nGeneralskan i Toreadorvalsen, Hustrun i\nMattan m m.\n\nGift 45 m reklamch Anders Sundberg.\n-Barn: Hanna-Lena f 49.\nSMITH, C GEORG, direktör, Gbg, f i\nAsarum, Blek l, 15/4/92 av Charlie S o\nLilly Janzon.\n\nStud:ex Sthlm 11, DHS 13, res:off:ex\n14, verkst dir ab E O Dahlqvist Gbg 25-\n\n50,   ag o verkst dir ab Erka sed 50.\n-Kapt res 42. - Medl Odd Fellow,\nBlekingegillet, Rotary. - Hobby: tennis.\nGift 1) 18-26, 2) 30 m Eva Lundberg\nf 98, dtr t överlär August L o Hilda\nHolmquist.  -  Barn:  i   l:a akt  Gunvor\nf 19, Carl-Göran f 21, i 2:a akt Björn\nf 32, Inger f 37.\n\n",
    "structured": {
        "0": {
            "full_name": "Smedberg, A E Börje",
            "location": "Jönköping",
            "occupation": "hovrättsråd",
            "birth_details": {
                "date": "17/xx/xxxx",
                "place": "NULL"
            },
            "education": [],
            "career": [
                {
                    "position": "Fiskal",
                    "years": {
                        "start_year": 1949,
                        "end_year": 1956
                    },
                    "organization": "Göta hovr"
                },
                {
                    "position": "adj led",
                    "years": {
                        "start_year": 1956,
                        "end_year": 1957
                    }
                },
                {
                    "position": "assess",
                    "years": {
                        "start_year": 1957,
                        "end_year": 1959
                    }
                },
                {
                    "position": "hovr:råd",
                    "years": {
                        "start_year": 1959,
                        "end_year": "NULL"
                    },
                    "organization": "Jönköping"
                },
                {
                    "position": "tf rev:sekr",
                    "years": {
                        "start_year": 1959,
                        "end_year": "NULL"
                    }
                }
            ],
            "family": {
                "spouse": "NULL",
                "marriage_year": "NULL",
                "children": "NULL"
            }
        },
        "1": {
            "full_name": "Smedegård, Stig Olof",
            "location": "Mariestad",
            "occupation": "lantmätare",
            "birth_details": {
                "date": "12/01/1919",
                "place": "Skalunda, Skaraborgs Län"
            },
            "education": [
                {
                    "degree": "Stud:ex",
                    "year": 1939,
                    "institution": "Skövde"
                },
                {
                    "degree": "KTH",
                    "year": 1944
                }
            ],
            "career": [
                {
                    "position": "lantmät",
                    "years": {
                        "start_year": 1944,
                        "end_year": 1950
                    },
                    "organization": "Lidkpg"
                },
                {
                    "position": "lantmät",
                    "years": {
                        "start_year": 1950,
                        "end_year": 1952
                    },
                    "organization": "Sthlm"
                },
                {
                    "position": "lantmät",
                    "years": {
                        "start_year": 1952,
                        "end_year": 1959
                    },
                    "organization": "Hässleholm"
                },
                {
                    "position": "ch lantmäteriets specialenhet",
                    "years": {
                        "start_year": 1959,
                        "end_year": "NULL"
                    },
                    "organization": "Skarab l"
                }
            ],
            "family": {
                "spouse": "Ingrid Johnsson",
                "marriage_year": 1947,
                "children": [
                    {
                        "name": "Göran",
                        "birth_year": 1948
                    },
                    {
                        "name": "Mats",
                        "birth_year": 1950
                    },
                    {
                        "name": "Stefan",
                        "birth_year": 1953
                    },
                    {
                        "name": "Karin",
                        "birth_year": 1961
                    }
                ]
            }
        },
        "2": {
            "full_name": "Smidje-Sundberg, Ulla V",
            "location": "Gbg",
            "occupation": "skådespelerska",
            "birth_details": {
                "date": "26/12/1925",
                "place": "Ullared, Hallands län"
            },
            "education": [
                {
                    "degree": "Realex",
                    "year": 1942,
                    "institution": "Varberg"
                },
                {
                    "degree": "Dram teat elevsk",
                    "year": "1946-1949"
                }
            ],
            "career": [
                {
                    "position": "eng Dram teat",
                    "years": {
                        "start_year": 1949,
                        "end_year": 1953
                    }
                },
                {
                    "position": "stadsteat",
                    "years": {
                        "start_year": 1953,
                        "end_year": 1957
                    },
                    "organization": "Hbg"
                },
                {
                    "position": "stadsteat",
                    "years": {
                        "start_year": 1957,
                        "end_year": "NULL"
                    },
                    "organization": "Gbg"
                },
                {
                    "position": "Lär",
                    "years": "NULL",
                    "organization": "Stat sk f scen utbildn"
                },
                {
                    "position": "verksam inom radio- o TV-teater",
                    "years": "NULL"
                }
            ],
            "family": {
                "spouse": "Anders Sundberg",
                "marriage_year": 1945,
                "children": [
                    {
                        "name": "Hanna-Lena",
                        "birth_year": 1949
                    }
                ]
            }
        },
        "3": {
            "full_name": "Smith, C Georg",
            "location": "Gbg",
            "occupation": "direktör",
            "birth_details": {
                "date": "15/04/1892",
                "place": "Asarum, Blekinge län"
            },
            "education": [
                {
                    "degree": "Stud:ex",
                    "year": 1911,
                    "institution": "Sthlm"
                },
                {
                    "degree": "DHS",
                    "year": 1913
                },
                {
                    "degree": "res:off:ex",
                    "year": 1914
                }
            ],
            "career": [
                {
                    "position": "verkst dir",
                    "years": {
                        "start_year": 1925,
                        "end_year": 1950
                    },
                    "organization": "ab E O Dahlqvist Gbg"
                },
                {
                    "position": "ag o verkst dir",
                    "years": {
                        "start_year": 1950,
                        "end_year": "NULL"
                    },
                    "organization": "ab Erka"
                }
            ],
            "family": {
                "spouse": "Eva Lundberg",
                "marriage_year": "30/xx/1930",
                "children": [
                    {
                        "name": "Gunvor",
                        "birth_year": 1919
                    },
                    {
                        "name": "Carl-Göran",
                        "birth_year": 1921
                    },
                    {
                        "name": "Björn",
                        "birth_year": 1932
                    },
                    {
                        "name": "Inger",
                        "birth_year": 1937
                    }
                ]
            }
        }
    }
}