{
    "original": "SANDHAMMAR,  S  GÖRAN,  förste\nläkare, Vänersborg, f i Bollnäs 17/10/23\nav tillsynslär Johan S o Tyra Egnell.\nMed kand 45 o med lic Lund 53, 2:e\nunderläk pens :styr avd Vänersb las 53,\nl:e underläk där 56, underläk psyk klin\nMalmö allm sjh 57, l:e läk Källshagens\nsjh Vänersb sed 62.\nGift 52 m sjuksköt Ulla Ogemark f 25.\n\n- Barn: Eva f 56, Lena f 58.\nSANDIN, ERIK, advokat,  Borås, f i\n\nSörforsa, Gävleb l, 17/3/19 av Anders S\no Märta Persson.\n\nStud:ex 38 o jur kand Upps 43, tingstjg\nNorrvikens doms 44-46, tf rådm Lidkpg\n46, bitr jur å adv :byrå Alingsås 46, egen\nadv:byrå Borås sed 47. - LSA 49. - Kapt\nI 15 res. - Utm: mil idrmG, SkytteSM.\nGift 48 m Margit Johansson f 23.\n-Barn: Ånn f 51, Gunilla f 56.\n\nSANDIN, C WOLLRATH E,\ndistriktschef, Gbg, f i Marstrand 9/6/01 av\nmaskinist Werner S o Agda Andersson.\nPolissk, överkonst :ex, anst polisverket\nGbg 27-53, org:ch Västsv vakt ab Gbg\n53, försäljn:ch där sed 60. - Styr:led Fp\nGbg 50-60, ordf Guldhedens Fp :f ören\n56-60. - Utm: VasaMG5st. - Hobbies:\njakt, fiske, bridge.\n\nGift 28 m Walberg Jansson f 01. - Barn:\nWivi-Ann f 35, Jan-Wollrath f 40.\n\nSANDKVIST se SANDQVIST\n\nSANDLUND, JOHN A, ingenjör,\nNorrköping, f i Luleå 25/9/13 av handl K A\nS o Mina Bergkvist.\n\nVägmäst:ex Hässleholm 35, ing:ex\nKatrineholm 41, anst öl entr:firmor 35-40,\nKatrineholms stad o Vadstena stad\n41-44, konsult ing sed 45, inneh Sandlunds\nkomm :tekn byrå ab sed 48. - Medl Odd\nFellow, FrimO. - Hobbies: sport,\nlitteratur.\n\nGift 42 m Ulla Ohlsson, dtr t insp Hugo\nO o Anna Bäck. - Barn: Boel f 43,\nBjörn f 45, Bengt f 51.\n\n",
    "structured": {
        "0": {
            "full_name": "S GÖRAN SANDHAMMAR",
            "location": "Vänersborg",
            "occupation": "förste läkare",
            "birth_details": {
                "date": "17/10/1923",
                "place": "Bollnäs",
                "parents": "Johan S o Tyra Egnell"
            },
            "education": [
                {
                    "degree": "medicin kandidat",
                    "year": "1945",
                    "institution": "Lund"
                },
                {
                    "degree": "medicin licentiat",
                    "year": "1953",
                    "institution": "Lund"
                }
            ],
            "career": [
                {
                    "position": "2:e underläkare",
                    "years": {
                        "start_year": 1953,
                        "end_year": 1956
                    },
                    "organization": "Vänersb las"
                },
                {
                    "position": "l:e underläkare",
                    "years": {
                        "start_year": 1956,
                        "end_year": 1957
                    },
                    "organization": "Malmö allm sjh"
                },
                {
                    "position": "underläkare psyk klin",
                    "years": {
                        "start_year": 1957,
                        "end_year": null
                    },
                    "organization": "Malmö allm sjh"
                },
                {
                    "position": "l:e läkare",
                    "years": {
                        "start_year": 1962,
                        "end_year": null
                    },
                    "organization": "Källshagens sjh Vänersb"
                }
            ],
            "family": {
                "spouse": "Ulla Ogemark",
                "marriage_year": "1952",
                "children": [
                    {
                        "name": "Eva",
                        "birth_year": "1956"
                    },
                    {
                        "name": "Lena",
                        "birth_year": "1958"
                    }
                ]
            }
        },
        "1": {
            "full_name": "ERIK SANDIN",
            "location": "Borås",
            "occupation": "advokat",
            "birth_details": {
                "date": "17/03/1919",
                "place": "Sörforsa, Gävleb l",
                "parents": "Anders S o Märta Persson"
            },
            "education": [
                {
                    "degree": "Stud:ex",
                    "year": "1938",
                    "institution": null
                },
                {
                    "degree": "jur kand",
                    "year": "1943",
                    "institution": "Upps"
                }
            ],
            "career": [
                {
                    "position": "tingstjg",
                    "years": {
                        "start_year": 1944,
                        "end_year": 1946
                    },
                    "organization": "Norrvikens doms"
                },
                {
                    "position": "tf rådm",
                    "years": {
                        "start_year": 1946,
                        "end_year": null
                    },
                    "organization": "Lidkpg"
                },
                {
                    "position": "bitr jur å adv :byrå",
                    "years": {
                        "start_year": 1946,
                        "end_year": null
                    },
                    "organization": "Alingsås"
                },
                {
                    "position": "egen adv:byrå",
                    "years": {
                        "start_year": 1947,
                        "end_year": null
                    },
                    "organization": "Borås"
                }
            ],
            "family": {
                "spouse": "Margit Johansson",
                "marriage_year": "1948",
                "children": [
                    {
                        "name": "Ånn",
                        "birth_year": "1951"
                    },
                    {
                        "name": "Gunilla",
                        "birth_year": "1956"
                    }
                ]
            }
        },
        "2": {
            "full_name": "C WOLLRATH E SANDIN",
            "location": "Gbg",
            "occupation": "distriktschef",
            "birth_details": {
                "date": "9/6/1901",
                "place": "Marstrand",
                "parents": "maskinist Werner S o Agda Andersson"
            },
            "education": null,
            "career": null,
            "family": {
                "spouse": "Walberg Jansson",
                "marriage_year": "1928",
                "children": [
                    {
                        "name": "Wivi-Ann",
                        "birth_year": "1935"
                    },
                    {
                        "name": "Jan-Wollrath",
                        "birth_year": "1940"
                    }
                ]
            },
            "hobbies": [
                "jakt",
                "fiske",
                "bridge"
            ]
        },
        "3": {
            "full_name": "JOHN A SANDLUND",
            "location": "Norrköping",
            "occupation": "ingenjör",
            "birth_details": {
                "date": "25/9/1913",
                "place": "Luleå",
                "parents": "handl K A S o Mina Bergkvist"
            },
            "education": [
                {
                    "degree": "Vägmäst:ex",
                    "year": "1935",
                    "institution": "Hässleholm"
                },
                {
                    "degree": "ing:ex",
                    "year": "1941",
                    "institution": "Katrineholm"
                }
            ],
            "career": [
                {
                    "position": "anst öl entr:firmor",
                    "years": {
                        "start_year": 1935,
                        "end_year": 1940
                    },
                    "organization": null
                },
                {
                    "position": "anst Katrineholms stad",
                    "years": {
                        "start_year": 1941,
                        "end_year": 1944
                    },
                    "organization": null
                },
                {
                    "position": "anst Vadstena stad",
                    "years": {
                        "start_year": 1941,
                        "end_year": 1944
                    },
                    "organization": null
                },
                {
                    "position": "konsult ing",
                    "years": {
                        "start_year": 1945,
                        "end_year": null
                    },
                    "organization": null
                }
            ],
            "family": {
                "spouse": "Ulla Ohlsson",
                "marriage_year": "1942",
                "children": [
                    {
                        "name": "Boel",
                        "birth_year": "1943"
                    },
                    {
                        "name": "Björn",
                        "birth_year": "1945"
                    },
                    {
                        "name": "Bengt",
                        "birth_year": "1951"
                    }
                ]
            },
            "hobbies": [
                "sport",
                "litteratur"
            ]
        }
    }
}