{
    "original": "SJÖHOLM, SVEN E, chefredaktör,\nBorgholm, f i Kalmar 20/5/89 av sjökapt\nE A S o Anna Bäckström.\nStud:ex 07, medarb Lunds Dagbl,\nKarl-stads-Tidn o Kalmar-Tidn 08-18, chefred\nÖlandsbladet sed 18. - Led Stadsfullm\nBorgholm 35-50, dir Borgholms badort\n36-65. - Styr:led Ölands jv ab 28-47,\nSkand bkn Borgholm 29-64.\n\nSJÖHOLM, SVEN N G, disponent,\nGbg, f i Linkpg 3/10/24 av köpm Nils\nS o Ester Möller.\n\nHdlsutbildn; anst NAF 43, filialen ab\nAddo Malmö 49, disp Verkst ab\nLindqvist Gbg sed 55. - Medl FrimO, Lions\nclub. - Hobbies: antikviteter, litteratur.\nGift 48 m Lis Holmqvist f 20, dtr t Carl\nH o Syster Malmgren. - Barn: Peter\nf 56.\n\nSJÖHOLM, SVEN-ÅKE H, direktör,\nGbg, f i Gbg 9/6/20 av civ:ing Swen S\no Signe Coster.\n\nHdlsgymn :ex; verkst dir Sjöholm &amp;\nEklund ab 45-58, anst Björckander &amp; Co\nab 59, v verkst dir där o ab Troed sed\n61 (styr :led). - Styr :led Håfreströms ab,\nab Gbg-Dals pappersbruk, Limmareds\nskogar ab, Nils Troedsson &amp; Co ab, Nils\nTroedsson Paper Co ab, ab Mplkolms\nbruk. - Kapt i res.\n\nGift 56 m Anne-Marie Troedsson f 21,\ndtr t dir Nils T o Dorthy Kruuse.\n\nSJÖHOLM, S TORSTEN R,\nskådespelare, Norrköping, f i Sthlm 1/5/31 av\ndisp Sven S o Greta Hillerström.\nStud:ex Kristinehamn 52, B A\nWittenberg univ, Ohio, USA 54; eng\nFolk-parksteat 56, Skansenteat 57,\nMunkbro-teat 57-58, Riksteat 57-59,\nNorrkpg-Lin-kpgs stadsteat sed 60.\n\nSJÖLANDER, ALF G, fil dr,\nlaborator, Mölndal, f i Skänninge 16/3/27 av\nhemm:äg Uno S o Sylvia Hallberg.\nFil kand Upps 49, fil mag 51, fil lic 53,\nfil dr 58, eo doc Upps univ 61, labor i\nmekanik CTH sed 62. - Anst ab\nAtomenergi Sthlm 59, Argonne Nät Lab 111\nUSA 59-61. - Skr: om neutronspridning\nmot fasta o flytande medier samt om\nkorrelationseffekter hos elektroner i\nkristaller.\n\nGift 54 m Gunilla Nordling f 30, dtr t\nprov:läk Sven N o Ruth Björsell. - Barn:\nDan f 54, Eva f 57, Sven f 59, Gunnel\nf 60.\n\n61 gö\n\n",
    "structured": {
        "1": {
            "full_name": "SJÖHOLM, SVEN E",
            "location": "Borgholm",
            "occupation": "chefredaktör",
            "birth_details": {
                "date": "20/05/1889",
                "place": "Kalmar",
                "parents": "sjökapt E A S o Anna Bäckström"
            },
            "education": [
                {
                    "degree": "Stud:ex",
                    "year": "1907",
                    "institution": "NULL"
                }
            ],
            "career": [
                {
                    "position": "chefred",
                    "years": {
                        "start_year": 1918,
                        "end_year": 1918
                    },
                    "organization": "Ölandsbladet"
                }
            ],
            "family": {
                "spouse": "NULL",
                "marriage_year": "NULL",
                "children": []
            }
        },
        "2": {
            "full_name": "SJÖHOLM, SVEN N G",
            "location": "Göteborg",
            "occupation": "disponent",
            "birth_details": {
                "date": "3/10/1924",
                "place": "Linköping",
                "parents": "köpm Nils S o Ester Möller"
            },
            "education": [
                {
                    "degree": "Hdlsutbildn",
                    "year": "NULL",
                    "institution": "NULL"
                }
            ],
            "career": [
                {
                    "position": "disp",
                    "years": {
                        "start_year": 1955,
                        "end_year": "NULL"
                    },
                    "organization": "Verkst ab Lindqvist Gbg"
                }
            ],
            "family": {
                "spouse": "Lis Holmqvist",
                "marriage_year": "1948",
                "children": [
                    {
                        "name": "Peter",
                        "birth_year": "1956"
                    }
                ]
            }
        },
        "3": {
            "full_name": "SJÖHOLM, SVEN-ÅKE H",
            "location": "Göteborg",
            "occupation": "direktör",
            "birth_details": {
                "date": "9/6/1920",
                "place": "Göteborg",
                "parents": "civ:ing Swen S o Signe Coster"
            },
            "education": [],
            "career": [
                {
                    "position": "v verkst dir",
                    "years": {
                        "start_year": 1961,
                        "end_year": "NULL"
                    },
                    "organization": "ab Troed"
                }
            ],
            "family": {
                "spouse": "Anne-Marie Troedsson",
                "marriage_year": "1956",
                "children": []
            }
        },
        "4": {
            "full_name": "SJÖHOLM, S TORSTEN R",
            "location": "Norrköping",
            "occupation": "skådespelare",
            "birth_details": {
                "date": "1/5/1931",
                "place": "Sthlm",
                "parents": "disp Sven S o Greta Hillerström"
            },
            "education": [
                {
                    "degree": "Stud:ex",
                    "year": 1952,
                    "institution": "Kristinehamn"
                },
                {
                    "degree": "B A",
                    "year": 1954,
                    "institution": "Wittenberg univ, Ohio, USA"
                }
            ],
            "career": [
                {
                    "position": "Norrkpg-Lin-kpgs stadsteat",
                    "years": {
                        "start_year": 1960,
                        "end_year": "NULL"
                    },
                    "organization": "NULL"
                }
            ],
            "family": {
                "spouse": "NULL",
                "marriage_year": "NULL",
                "children": []
            }
        },
        "5": {
            "full_name": "SJÖLANDER, ALF G",
            "location": "Mölndal",
            "occupation": "fil dr, laborator",
            "birth_details": {
                "date": "16/3/1927",
                "place": "Skänninge",
                "parents": "hemm:äg Uno S o Sylvia Hallberg"
            },
            "education": [
                {
                    "degree": "Fil kand",
                    "year": 1949,
                    "institution": "Upps"
                },
                {
                    "degree": "Fil mag",
                    "year": 1951,
                    "institution": "NULL"
                },
                {
                    "degree": "Fil lic",
                    "year": 1953,
                    "institution": "NULL"
                },
                {
                    "degree": "Fil dr",
                    "year": 1958,
                    "institution": "NULL"
                }
            ],
            "career": [
                {
                    "position": "labor i mekanik",
                    "years": {
                        "start_year": 1962,
                        "end_year": "NULL"
                    },
                    "organization": "CTH"
                }
            ],
            "family": {
                "spouse": "Gunilla Nordling",
                "marriage_year": "1954",
                "children": [
                    {
                        "name": "Dan",
                        "birth_year": "1954"
                    },
                    {
                        "name": "Eva",
                        "birth_year": "1957"
                    },
                    {
                        "name": "Sven",
                        "birth_year": "1959"
                    },
                    {
                        "name": "Gunnel",
                        "birth_year": "1960"
                    }
                ]
            }
        }
    }
}