{
    "original": "SJÖBERG, BENGT O G,\ndistriktsåklagare, Linköping, f i Hofsta, Örebro l,\n3/10/22 av turistbyråförest Martin S o\nMartha Andersson.\n\nStud:ex Ystad 41, jur kand Lund 46,\ntingstjg Östbo o Västbo doms 46-49,\ntjg Göta hovr 49, landsfogdeass 50-61, tf\nstadsfisk o polisch Visby 50-51,\nKristianstad 55-56, åkl Sundsvall 49-50, Malmö\n52, Karlskrona 53-55, Gbg 57-59,\nHalmstad 59-61, bitr stadsfisk Linkpg 61,\ndistr:åkl där sed 65. - Medl FrimO, Odd\nFellow, Lions club. - Hobbies: tennis,\nbridge.\n\nGift 60 m Thérese Ausländer f 24, dtr t\nköpm Josef A o Heléne Feller (Wien).\n-Barn: Marie-Thérése f 62, Robert f 63.\n\nSJÖBERG, ERIK G, bankdirektör,\nVisby, f i Klintehamn, Gotl l, 3/4/26 av\nprost Gustaf S o Elsa Kloetzen.\nStud:ex Visby 47, res:off:ex 49, fil kand\no pol mag Upps 52, anst Sthlms ensk\nbk 53, SHB Sthlm 58, avd:kamr 60e,\nbankdir Visby o ch SHB :s verksamh på\nGotl sed 64. - Suppl DK 64. - Kapt\nP 18 res.\n\nGift 50 m Peg Lindeborg f 28, dtr t\nmajor Elof L o Alva L. - Barn: Eva\nf 51, Kristina f 54.\n\nSJÖBERG, ERNST R,\nvattenrättsdomare, Vänersborg, f i Sthlm 19/8/15 av\nC L S o Dorothea Lörner.\nStud:ex 35 o jur kand Sthlm 41, tingstjg\nTjusts doms 42-44, tjg Svea hovr 44,\nfiskal 45, vattenr:sekr Norrbygd\nvatten-domst 46, tingssekr S Rosl doms 50, adj\nled Svea hovr 50, assess 51, vattenr:dom\nN Norrbygd vattendomst 53, Västerbygd\nvattendomst sed 62. - Utm: RNO.\n\n£55Gift 43 m Maj-Britten Torstensson.\n-Barn: Peter f 44, Kristina f 46, Olle f 52,\nCarl f 56.\n\nSJÖBERG, GOTTHARD E,\nbankdirektör, Uddevalla, f i Svärdsjö, Kopparb l,\n5/5/03 av kassör Carl S o Maria\nKällgren.\n\nStud:ex Kalmar 23, anst SHB, dir SHB\nBoden 48, Uddevalla sed 54. - Medl\nRotary.\n\nGift 34 m Ingrid Erikson f 13, dtr t\nkamr Herbert E o Erika E.\n\n",
    "structured": {
        "0": {
            "full_name": "BENGT O G SJÖBERG",
            "location": "Linköping",
            "occupation": "distriktsåklagare",
            "birth_details": {
                "date": "3 oktober 1922",
                "place": "Hofsta, Örebro l"
            },
            "education": [
                {
                    "degree": "Stud:ex",
                    "year": "1941",
                    "institution": "Ystad"
                },
                {
                    "degree": "jur kand",
                    "year": "1946",
                    "institution": "Lund"
                }
            ],
            "career": [
                {
                    "position": "tingstjg",
                    "years": {
                        "start_year": 1946,
                        "end_year": 1949
                    },
                    "organization": "Östbo o Västbo doms"
                },
                {
                    "position": "landsfogdeass",
                    "years": {
                        "start_year": 1950,
                        "end_year": 1961
                    }
                },
                {
                    "position": "tf stadsfisk o polisch",
                    "years": {
                        "start_year": 1950,
                        "end_year": 1951
                    },
                    "organization": "Visby"
                },
                {
                    "position": "bitr stadsfisk",
                    "years": {
                        "start_year": 1961
                    },
                    "organization": "Linkpg"
                },
                {
                    "position": "distr:åkl",
                    "years": {
                        "start_year": 1965
                    }
                }
            ],
            "family": {
                "spouse": "Thérese Ausländer",
                "marriage_year": "1960",
                "children": [
                    {
                        "name": "Marie-Thérése",
                        "birth_year": "1962"
                    },
                    {
                        "name": "Robert",
                        "birth_year": "1963"
                    }
                ]
            },
            "hobbies": [
                "tennis",
                "bridge"
            ]
        },
        "1": {
            "full_name": "ERIK G SJÖBERG",
            "location": "Visby",
            "occupation": "bankdirektör",
            "birth_details": {
                "date": "3 april 1926",
                "place": "Klintehamn, Gotl l"
            },
            "education": [
                {
                    "degree": "Stud:ex",
                    "year": "1947",
                    "institution": "Visby"
                },
                {
                    "degree": "res:off:ex",
                    "year": "1949"
                },
                {
                    "degree": "filosofie kandidat",
                    "year": "1952",
                    "institution": "Upps"
                }
            ],
            "career": [
                {
                    "position": "anst Sthlms ensk bk",
                    "years": {
                        "start_year": 1953
                    }
                },
                {
                    "position": "SHB Sthlm",
                    "years": {
                        "start_year": 1958
                    }
                },
                {
                    "position": "avd:kamr",
                    "years": {
                        "start_year": 1960
                    },
                    "organization": "SHB"
                },
                {
                    "position": "bankdir",
                    "years": {
                        "start_year": 1964
                    },
                    "organization": "Visby o ch SHB :s verksamh på Gotl"
                }
            ],
            "family": {
                "spouse": "Peg Lindeborg",
                "marriage_year": "1950",
                "children": [
                    {
                        "name": "Eva",
                        "birth_year": "1951"
                    },
                    {
                        "name": "Kristina",
                        "birth_year": "1954"
                    }
                ]
            }
        },
        "2": {
            "full_name": "ERNST R SJÖBERG",
            "location": "Vänersborg",
            "occupation": "vattenrättsdomare",
            "birth_details": {
                "date": "19 augusti 1915",
                "place": "Sthlm"
            },
            "education": [
                {
                    "degree": "Stud:ex",
                    "year": "1935"
                },
                {
                    "degree": "jur kand",
                    "year": "1941",
                    "institution": "Sthlm"
                }
            ],
            "career": [
                {
                    "position": "tingstjg",
                    "years": {
                        "start_year": 1942,
                        "end_year": 1944
                    },
                    "organization": "Tjusts doms"
                },
                {
                    "position": "tjg",
                    "years": {
                        "start_year": 1944
                    },
                    "organization": "Svea hovr"
                },
                {
                    "position": "fiskal",
                    "years": {
                        "start_year": 1945
                    }
                },
                {
                    "position": "vattenr:sekr",
                    "years": {
                        "start_year": 1946
                    },
                    "organization": "Norrbygd vatten-domst"
                },
                {
                    "position": "adj led",
                    "years": {
                        "start_year": 1950
                    },
                    "organization": "Svea hovr"
                },
                {
                    "position": "assess",
                    "years": {
                        "start_year": 1951
                    }
                },
                {
                    "position": "vattenr:dom",
                    "years": {
                        "start_year": 1953
                    },
                    "organization": "Norrbygd vattendomst"
                },
                {
                    "position": "Västerbygd vattendomst",
                    "years": {
                        "start_year": 1962
                    }
                }
            ],
            "family": {
                "spouse": "Maj-Britten Torstensson",
                "marriage_year": "1943",
                "children": [
                    {
                        "name": "Peter",
                        "birth_year": "1944"
                    },
                    {
                        "name": "Kristina",
                        "birth_year": "1946"
                    },
                    {
                        "name": "Olle",
                        "birth_year": "1952"
                    },
                    {
                        "name": "Carl",
                        "birth_year": "1956"
                    }
                ]
            },
            "honorary_titles": [
                {
                    "title": "RNO",
                    "year": "NULL"
                }
            ]
        },
        "3": {
            "full_name": "GOTTHARD E SJÖBERG",
            "location": "Uddevalla",
            "occupation": "bankdirektör",
            "birth_details": {
                "date": "5 maj 1903",
                "place": "Svärdsjö, Kopparb l"
            },
            "education": [
                {
                    "degree": "Stud:ex",
                    "year": "1923",
                    "institution": "Kalmar"
                }
            ],
            "career": [
                {
                    "position": "dir",
                    "organization": "SHB Boden",
                    "years": {
                        "start_year": 1948
                    }
                },
                {
                    "position": "dir",
                    "organization": "Uddevalla",
                    "years": {
                        "start_year": 1954
                    }
                }
            ],
            "family": {
                "spouse": "Ingrid Erikson",
                "marriage_year": "1934"
            },
            "hobbies": [
                "Medl Rotary"
            ]
        }
    }
}