{
    "original": "STEHAGEN, KNUT, direktör,\nMjölby, f i Gudmuntorp, Malmöh l, 6/11/16\nav lantbr Olof Olsson o Selma\nDahlgren.\n\nIng:ex HTS 39, ing ab Bofors 40-41 o\n46-47, ab Landsverk 42-45, verkst:ing\nab Sv metallverken Skultuna 48,\nförsäljn :ch 53, produktionsch där 56,\növering ab Bygg- o Transportekon Mjölby\n58, tekn dir där sed 63. - Styr:led\nRola-truc Ltd London.\n\nGift 43 m Sigrid Blomstrand, dtr t\nfolkskollär Sven B o Maja Olsson. - Barn:\nChrister f 44, Barbro f 48.\n\nSTEIER, C L INGEMAR, advokat,\nGbg, f i Skrea, Hall l, 2/8/10 av\nkontr:-prost Lars S o Ela Tomtlund.\n\nStud:ex Gbg 30, jur kand Lund 37,\nlandsfogdeass Västernorrl l 42, Gbgs o\nBoh l 44, tf landsfogde o polismäst öl\nperioder 42-44, adv :verksamh Gbg sed\n45. - Res:off:ex 32, kapt I 16 res 43-55.\n\n-   Styr :led  Gbgs stads änke-  o\npupillkassa sed 51, Gbgs stads bost:förmedl\n59-63. - LSA 48, medl Odd Fellow, TG.\n\n-   Skr: div tidn:art i GHT o  GMP.\nGift 62 m förskollär Inga Bängtsson, dtr\nt folkskollär Nils B o h h. - Barn: i tid\nakt Agneta f 43, Lars f 45, Carl Cristian\nf 52, Elisabet f 54.\n\nSTEINDAMM, HORST E W,\ndistriktstandläkare, Hohultslätt, f i Kolberg,\nPommern, 29/7/15 av köpm Ernst S o\nAgnes Ladisch.\n\nStud:ex 36, tandl:ex Breslau 41, dr med\ndent 42 o läk :ex Breslau 44, distr :tandl\nGallo 53, distr :tandl o förest distr\n:tandpol Hohultslätt sed 59. - Hobby:\nakvariefiskar.\n\nGift 44 m Doris Hackenberg f 27, dtr t\nkansliförest Walter H o Hildegard\nSter-nitzke. - Barn: Norbert f 53.\n\n",
    "structured": {
        "1": {
            "full_name": "Knut Stehagen",
            "location": "Mjölby",
            "occupation": "direktör",
            "birth_details": {
                "date": "06/11/1916",
                "place": "Gudmuntorp, Malmöh",
                "parents": "lantbr Olof Olsson o Selma Dahlgren"
            },
            "education": [
                {
                    "degree": "Ing:ex HTS",
                    "year": "1939",
                    "institution": "NULL"
                }
            ],
            "career": [
                {
                    "position": "ing ab Bofors",
                    "years": {
                        "start_year": 1940,
                        "end_year": 1941
                    },
                    "organization": "NULL"
                },
                {
                    "position": "ab Landsverk",
                    "years": {
                        "start_year": 1942,
                        "end_year": 1945
                    },
                    "organization": "NULL"
                },
                {
                    "position": "verkst:ing ab Sv metallverken",
                    "years": {
                        "start_year": 1948,
                        "end_year": 1948
                    },
                    "organization": "Skultuna"
                },
                {
                    "position": "försäljn :ch",
                    "years": {
                        "start_year": 1953,
                        "end_year": 1953
                    },
                    "organization": "NULL"
                },
                {
                    "position": "produktionsch",
                    "years": {
                        "start_year": 1956,
                        "end_year": 1956
                    },
                    "organization": "NULL"
                },
                {
                    "position": "övering ab Bygg- o Transportekon",
                    "years": {
                        "start_year": 1958,
                        "end_year": 1958
                    },
                    "organization": "Mjölby"
                },
                {
                    "position": "tekn dir",
                    "years": {
                        "start_year": 1963,
                        "end_year": 1963
                    },
                    "organization": "Mjölby"
                }
            ],
            "family": {
                "spouse": "Sigrid Blomstrand",
                "marriage_year": "1943",
                "children": [
                    {
                        "name": "Christer",
                        "birth_year": "1944"
                    },
                    {
                        "name": "Barbro",
                        "birth_year": "1948"
                    }
                ]
            }
        },
        "2": {
            "full_name": "C L Ingemar Steier",
            "location": "Gbg",
            "occupation": "advokat",
            "birth_details": {
                "date": "02/08/1910",
                "place": "Skrea, Hall l",
                "parents": "kontr:-prost Lars S o Ela Tomtlund"
            },
            "education": [
                {
                    "degree": "Stud:ex",
                    "year": "1930",
                    "institution": "Gbg"
                },
                {
                    "degree": "jur kand",
                    "year": "1937",
                    "institution": "Lund"
                }
            ],
            "career": [
                {
                    "position": "landsfogdeass",
                    "years": {
                        "start_year": 1942,
                        "end_year": 1942
                    },
                    "organization": "Västernorrl l"
                },
                {
                    "position": "landsfogde o polismäst",
                    "years": {
                        "start_year": 1944,
                        "end_year": 1944
                    },
                    "organization": "NULL"
                },
                {
                    "position": "adv :verksamh Gbg",
                    "years": {
                        "start_year": 1945,
                        "end_year": 1945
                    },
                    "organization": "Gbg"
                }
            ],
            "family": {
                "spouse": "Inga Bängtsson",
                "marriage_year": "1962",
                "children": [
                    {
                        "name": "Agneta",
                        "birth_year": "1943"
                    },
                    {
                        "name": "Lars",
                        "birth_year": "1945"
                    },
                    {
                        "name": "Carl Cristian",
                        "birth_year": "1952"
                    },
                    {
                        "name": "Elisabet",
                        "birth_year": "1954"
                    }
                ]
            }
        },
        "3": {
            "full_name": "Horst E W Steindamm",
            "location": "Hohultslätt",
            "occupation": "distriktstandläkare",
            "birth_details": {
                "date": "29/07/1915",
                "place": "Kolberg, Pommern",
                "parents": "köpm Ernst S o Agnes Ladisch"
            },
            "education": [
                {
                    "degree": "Stud:ex",
                    "year": "1936",
                    "institution": "NULL"
                },
                {
                    "degree": "tandl:ex",
                    "year": "1941",
                    "institution": "Breslau"
                },
                {
                    "degree": "dr med dent",
                    "year": "1942",
                    "institution": "Breslau"
                },
                {
                    "degree": "läk :ex",
                    "year": "1944",
                    "institution": "Breslau"
                }
            ],
            "career": [
                {
                    "position": "distr :tandl",
                    "years": {
                        "start_year": 1953,
                        "end_year": 1953
                    },
                    "organization": "Gallo"
                },
                {
                    "position": "distr :tandl o förest distr :tandpol",
                    "years": {
                        "start_year": 1959,
                        "end_year": 1959
                    },
                    "organization": "Hohultslätt"
                }
            ],
            "family": {
                "spouse": "Doris Hackenberg",
                "marriage_year": "1944",
                "children": [
                    {
                        "name": "Norbert",
                        "birth_year": "1953"
                    }
                ]
            },
            "hobbies": [
                "akvariefiskar"
            ]
        }
    }
}