{
    "original": "SJÖBERG, B WALDEMAR,\ntandläkare, Jönköping, f i Näsby, Jönkpgs l,\n5/10/12 av lantbr August S o Signe\nJohansson.\n\nStud:ex Eksjö 34, med stud Karol inst\n35-37, tandl:ex Sthlm 41, priv:prakt\nUpps 42, Jönkpg sed 46. - Led\nStadsfullm Jönkpg sed 58, skolstyr 56-63\n(ordf 60-63), Stadsfullm :s valnd o\nval-beredn. - Medl BifrostO, Odd Fellow,\nPB. - Hobby: antikviteter.\nGift 45 m fil mag Anne-Marie Thor\nf 21, dtr t bkdir Carl T o Hillevi\nLundin. - Barn: Sten f 46, Elisabeth f 48.\n\nSJÖBLOM,   J   G   BERTIL,   direktör,\n\nGbg, f i Gbg 23/3/04 av verkm Carl S\no Mariana Gustafsson.\nStud v GbgHdlI o slöjdfören Gbg, anst\nSthlms superfosfatfabr ab 19, Olof\nMänner ab Gbg 32, Ekström &amp; Lefflers ab\n35, ab EOL 38, aff :ch livsmedelsavd där\nsed 62. - Led ICA:s aff:utsk 62,\nstyr:-suppl ab Svea choklad o ab\nICA-Res-tauranger. - Led skolstyr 52, beredn f\npartihdlscentral f trädg :produkter m m\n56-61. - Medl FrimO, W-sex. - Utm:\nRVO, Gbgs luftind:skyddsfören SM,\nGbgs köpm:förb ftjt, GKSSftjt, WasaO\nof Amer ftjt. - Hobbies: tennis, golf,\nsegling.\n\nGift 37 m Harriet Munkby f 15, dtr t\ndir Ernst M o Beda Berg. - Barn:\nLennart f 42.\n\nSJÖBLOM, E GUNNAR,\ndistriktsåklagare, Uddevalla, f i St Lundby, Älvsb l,\n24/10/03 av handl Frans S o Anna\nJohansson.\n\nRealex 20, landsfisk :ex 26, landsfisk :bitr\n21, eo landskansl 25, e o tf landsfisk 28,\nlandsfisk 38, i Munkedals distr 41,\ndistr:-åkl Uddevalla sed 65. - Ordf öl tax :ndr\nsed 30. - Utm: RNO, CfftjtG. -\nHobbies: jakt, fiske.\n\nGift 31 m Edit Gustafsson f 05. - Barn:\nBengt f 38, Per f 40, Lars f 45.\n",
    "structured": {
        "0": {
            "full_name": "B Waldemar Sjöberg",
            "location": "Jönköping",
            "occupation": "tandläkare",
            "birth_details": {
                "date": "05/10/1912",
                "place": "Näsby, Jönkpgs l",
                "parents": "lantbr August S o Signe Johansson"
            },
            "education": [
                {
                    "degree": "Stud:ex",
                    "year": "1934",
                    "institution": "Eksjö"
                },
                {
                    "degree": "med stud",
                    "year": "1935-1937",
                    "institution": "Karol inst"
                },
                {
                    "degree": "tandl:ex",
                    "year": "1941",
                    "institution": "Sthlm"
                }
            ],
            "career": [
                {
                    "position": "priv:prakt",
                    "years": {
                        "start_year": 1942,
                        "end_year": 1946
                    },
                    "organization": "Upps"
                },
                {
                    "position": "priv:prakt",
                    "years": {
                        "start_year": 1946,
                        "end_year": null
                    },
                    "organization": "Jönkpg"
                }
            ],
            "family": {
                "spouse": "fil mag Anne-Marie Thor",
                "marriage_year": "1945",
                "children": [
                    {
                        "name": "Sten",
                        "birth_year": "1946"
                    },
                    {
                        "name": "Elisabeth",
                        "birth_year": "1948"
                    }
                ]
            },
            "hobbies": [
                "antikviteter"
            ]
        },
        "1": {
            "full_name": "J G Bertil Sjöblom",
            "location": "Gbg",
            "occupation": "direktör",
            "birth_details": {
                "date": "23/03/1904",
                "place": "Gbg",
                "parents": "verkm Carl S o Mariana Gustafsson"
            },
            "career": [
                {
                    "position": "anst",
                    "years": {
                        "start_year": 1932,
                        "end_year": 1935
                    },
                    "organization": "Sthlms superfosfatfabr ab"
                },
                {
                    "position": "aff :ch livsmedelsavd",
                    "years": {
                        "start_year": 1938,
                        "end_year": 1962
                    },
                    "organization": "ab EOL"
                }
            ],
            "family": {
                "spouse": "Harriet Munkby",
                "marriage_year": "1937",
                "children": [
                    {
                        "name": "Lennart",
                        "birth_year": "1942"
                    }
                ]
            },
            "hobbies": [
                "tennis",
                "golf",
                "segling"
            ]
        },
        "2": {
            "full_name": "E Gunnar Sjöblom",
            "location": "Uddevalla",
            "occupation": "distriktsåklagare",
            "birth_details": {
                "date": "24/10/1903",
                "place": "St Lundby, Älvsb l",
                "parents": "handl Frans S o Anna Johansson"
            },
            "education": [
                {
                    "degree": "Realex",
                    "year": "1920",
                    "institution": null
                },
                {
                    "degree": "landskansl",
                    "year": "1925",
                    "institution": null
                }
            ],
            "career": [
                {
                    "position": "eo landskansl",
                    "years": {
                        "start_year": 1925,
                        "end_year": null
                    },
                    "organization": null
                },
                {
                    "position": "distr:-åkl",
                    "years": {
                        "start_year": 1965,
                        "end_year": null
                    },
                    "organization": "Uddevalla"
                }
            ],
            "family": {
                "spouse": "Edit Gustafsson",
                "marriage_year": "1931",
                "children": [
                    {
                        "name": "Bengt",
                        "birth_year": "1938"
                    },
                    {
                        "name": "Per",
                        "birth_year": "1940"
                    },
                    {
                        "name": "Lars",
                        "birth_year": "1945"
                    }
                ]
            },
            "hobbies": [
                "jakt",
                "fiske"
            ]
        }
    }
}