{
    "original": "Fröjd, Karl Harry, rektor, Sävsjö, f.\n18/9/04 i Torshälla landsförs.,\nSödermani. 1., av K. G. F. o. Alfrida Sofia\nJonsson. G. 32 m. Rigmor Johansson.\n— Stud:ex. i Nyköp. 24, fil. mag. i\nUpps. 28, behörigh. t. ord. lär:tj. v. h.\nfolksk. 39, t. ord. adj :tj. v. h. a. 1. 45.\nEft anst. s. vik. folkskoll., journ. samt\nrektor o. lär. v. Sävsjö priv. realsk.\n\ne.\to. lär. v. Sävsjö h. folksk. 36-38,\nrektor där sed. 36 o. ord. ämneslär.\nsed. 39, tiMiika lär, v. Sävsjö yrkens k.\nsed. 33, lär. i eng. där sed. 38, rektor\ndär ;sed. 42. Verks. s. föreiä&amp;are. Res. t.\nTyskl. 22 o. 38. Skr.: art. i pol. o.\nkult. frågor i tidn. o. tidskr.\n\nFrölinder, Ragnar Emil Karl,\ndis-pensärläkare, prakt, iläkare,\nNorrköping, f. 9/3/01 i Norrköp. av kyrkoh.\nE. L. F. o. Maria Adlerz. G. 31 m.\nHarriet Danelius. Barn: Marie-Louise\n\nf.\t32, Kerstin 36, Hans 42. — Stud:ex.\ni Linköp. 19, med. kand. i Upps. 24,\nmed. lic. i Sthlm 30. Stud:resa t. de\nnord. länd. o. Tyskl. 38. E. läk. v.\nKälllviks brunns- o. badanst. 25, assist\n:-läk. v. Akad. sjukh. pediatr. avd. fyra\nmån. 29-30, e. läk. o. tf. und :läk. v.\nKåliltorps tub:sjukh. samt assist :läk.\nv. Sahlgr. sjukh. med. avd. 30,\nund:-läk. v. Ulricehamns vintersanat.\n30-31, andre resp. förste und:läk. v.\nKol-mårdssanat. 32-34, andre und :läk. v.\nNorrköp. las. med. avd. 34-35, förste\ndito 35-37, prakt. Häk. i Norrköp. samt\nförest, f. centr:disp. där sed. 38. Skr.:\nupps. behandl. reumat. sjukd. o.\nlung-sjukd. Hobbies: foto o. botanik.\n\nFrölund, Simon Gustaf Adolf,\nlandsfiskal, Aseda, f. 20/4/90 i Uppsala av\nErik Gustaf F. o. Fredrika Herslow.\nG. 16. — Realex. v. h. a. 1. i Upps. 07,\nex. v. Schartaus handrinst. 09,\nkrono-länsm:ex. i Karlstad 12, genomg. stat.\nkrim:tekn. kurs i Sthlm 31,\nluftsk:-insp :utb :kurs f. luftsk :chefer m.\nstats-stip. 41. E. o. landskansl. i Sthlms 1.\n\n15,\tol. förordn. s. kronolänsm.,\nstadsfo|gde, kommissionär å landskansl. i\nSthlms 1., poHskomm. o. utmätn:man\ni landsfiskals ställe samt s. landsfiskal,\n\ne.\tpoliskomm. i Lidingö köp. 18, bitr.\nlandsfiskal i Tingsryds distr. o.\npolisuppsyn :man m. åkl:befog. i Tingsryds\nköp. 21, tf. landsfiskal i Aseda distr.\n21, ord. 32. Fd. ordf. i tax:nd,\nman-talsskrivn: förrätt., allm. omb. f. ol.\nsparb., v. ordf. i Uppvidinge här.\nväg-stämma, led. av Aseda köp.\nkomm:-fulilm. o. fd, led. av Aseda föns.\nkyrko-fuMm.\n\nFrössén, Gösta, överste, Linköping,\n\nf.\t14/11/79 i Eskilstuna av Gustaf F.\no. Engla Freese. G. 08 m. Ullla\nAs-pelin. — Mog:ex. i Strängnäs 99, off\n:-ex. 01, gymn:dir. 05, KHS 11-13.\nUnd:-löjtn. i Skarab. reg. 01, v. Första Göta\nträngkår 02, löjtn. 04, kapt. 15, major\no. chef f. Norrl. trängkår 24,\növ:-löjtn. 28, överste i armén 34. Vik.\ngymn:lär. 05-06, lär. v. off:- o.\nres:-off:vol:sk. 06-07, reg :kvartermäst. 13-\n\n16,\tadjut. h. insp. f. trängen 17-20,\nbitr. Här. v. KS 17-18, tjg. i franska\narmén 20, tf. chef f. Svea trängkår 24,\nchef f. densamma 29-34, försv :assist.\ni östergötl. 1. 37-44. Distr :sekr. i\nöstergötl. distr. av SvRK 36-46. RSO,\nRNO, SvRKSM, RLSFSM o. förtj :t.\ni guld, TurkRKM, ÖRKHt2kil.\n\n",
    "structured": {
        "1": {
            "full_name": "Fröjd, Karl Harry",
            "location": "Sävsjö",
            "occupation": "rektor",
            "birth_details": {
                "date": "18/09/1904",
                "place": "Torshälla landsförs."
            },
            "education": [
                {
                    "degree": "Stud:ex.",
                    "year": "1924",
                    "institution": "i Nyköp."
                },
                {
                    "degree": "fil. mag.",
                    "year": "1928",
                    "institution": "i Upps."
                }
            ],
            "career": [
                {
                    "position": "vik. folkskoll.",
                    "years": {
                        "start_year": 1939,
                        "end_year": 1945
                    },
                    "organization": "h. folksk."
                },
                {
                    "position": "ord. ämneslär.",
                    "years": {
                        "start_year": 1939,
                        "end_year": null
                    },
                    "organization": "Sävsjö privat realsk."
                },
                {
                    "position": "rektor",
                    "years": {
                        "start_year": 1942,
                        "end_year": null
                    },
                    "organization": "Sävsjö"
                }
            ],
            "family": {
                "spouse": "Rigmor Johansson",
                "marriage_year": "1932",
                "children": []
            }
        },
        "2": {
            "full_name": "Frölinder, Ragnar Emil Karl",
            "location": "Norrköping",
            "occupation": "dispensärläkare, prakt, iläkare",
            "birth_details": {
                "date": "09/03/1901",
                "place": "Norrköping"
            },
            "education": [
                {
                    "degree": "Stud:ex.",
                    "year": "1919",
                    "institution": "i Linköp."
                },
                {
                    "degree": "med. kand.",
                    "year": "1924",
                    "institution": "i Upps."
                },
                {
                    "degree": "med. lic.",
                    "year": "1930",
                    "institution": "i Sthlm"
                },
                {
                    "degree": "Stud:resa",
                    "year": "1938",
                    "institution": "t. de nord. länd. o. Tyskl."
                }
            ],
            "career": [
                {
                    "position": "e. läk.",
                    "years": {
                        "start_year": 1925,
                        "end_year": null
                    },
                    "organization": "Källlviks brunns- o. badanst."
                },
                {
                    "position": "ass. -läk.",
                    "years": {
                        "start_year": 1929,
                        "end_year": 1930
                    },
                    "organization": "Akad. sjukh. pediatr. avd. fyra mån."
                },
                {
                    "position": "e. läk. o. tf. und :läk.",
                    "years": {
                        "start_year": 1930,
                        "end_year": null
                    },
                    "organization": "Kåliltorps tub:sjukh."
                },
                {
                    "position": "und:-läk.",
                    "years": {
                        "start_year": 1930,
                        "end_year": 1931
                    },
                    "organization": "Ulricehamns vintersanat."
                },
                {
                    "position": "and. resp. förste und:läk.",
                    "years": {
                        "start_year": 1932,
                        "end_year": 1934
                    },
                    "organization": "Kolmårdssanat."
                },
                {
                    "position": "and. und :läk.",
                    "years": {
                        "start_year": 1934,
                        "end_year": 1935
                    },
                    "organization": "Norrköp. las. med. avd."
                },
                {
                    "position": "förste und. dito",
                    "years": {
                        "start_year": 1935,
                        "end_year": 1937
                    },
                    "organization": "Norrköp."
                },
                {
                    "position": "prakt. Häk.",
                    "years": {
                        "start_year": 1938,
                        "end_year": null
                    },
                    "organization": "Norrköp."
                },
                {
                    "position": "förest, f. centr:disp.",
                    "years": {
                        "start_year": 1938,
                        "end_year": null
                    },
                    "organization": "Norrköp."
                }
            ],
            "family": {
                "spouse": "Harriet Danelius",
                "marriage_year": "1931",
                "children": [
                    {
                        "name": "Marie-Louise",
                        "birth_year": "1932"
                    },
                    {
                        "name": "Kerstin",
                        "birth_year": "1936"
                    },
                    {
                        "name": "Hans",
                        "birth_year": "1942"
                    }
                ]
            },
            "hobbies": [
                "foto",
                "botanik"
            ]
        },
        "3": {
            "full_name": "Frölund, Simon Gustaf Adolf",
            "location": "Aseda",
            "occupation": "landsfiskal",
            "birth_details": {
                "date": "20/04/1890",
                "place": "Uppsala"
            },
            "education": [
                {
                    "degree": "Realex.",
                    "year": "1907",
                    "institution": "h. a. 1. i Upps."
                },
                {
                    "degree": "ex. v. Schartaus handrinst.",
                    "year": "1909",
                    "institution": null
                }
            ],
            "career": [
                {
                    "position": "krono-länsm:ex.",
                    "years": {
                        "start_year": 1912,
                        "end_year": null
                    },
                    "organization": "Karlstad"
                },
                {
                    "position": "luftsk:-insp",
                    "years": {
                        "start_year": 1931,
                        "end_year": null
                    },
                    "organization": "f. luftsk :chefer m. stats-stip. 41"
                },
                {
                    "position": "e. o. landskansl.",
                    "years": {
                        "start_year": 1915,
                        "end_year": null
                    },
                    "organization": "Sthlms 1."
                },
                {
                    "position": "ol. förordn. s. kronolänsm.",
                    "years": {
                        "start_year": null,
                        "end_year": null
                    },
                    "organization": null
                },
                {
                    "position": "bitr. landsfiskal",
                    "years": {
                        "start_year": null,
                        "end_year": null
                    },
                    "organization": "Tingsryds distr."
                },
                {
                    "position": "tf. landsfiskal",
                    "years": {
                        "start_year": 1921,
                        "end_year": 1932
                    },
                    "organization": "Aseda distr."
                },
                {
                    "position": "ord.",
                    "years": {
                        "start_year": 1932,
                        "end_year": null
                    },
                    "organization": null
                }
            ],
            "family": {
                "spouse": null,
                "marriage_year": null,
                "children": []
            }
        },
        "4": {
            "full_name": "Frössén, Gösta",
            "location": "Linköping",
            "occupation": "överste",
            "birth_details": {
                "date": "14/11/1879",
                "place": "Eskilstuna"
            },
            "education": [
                {
                    "degree": "Mog:ex.",
                    "year": "1899",
                    "institution": "i Strängnäs"
                },
                {
                    "degree": "off :-ex.",
                    "year": "1901",
                    "institution": null
                },
                {
                    "degree": "gymn:dir.",
                    "year": "1905",
                    "institution": null
                },
                {
                    "degree": "KHS",
                    "year": "1911-1913",
                    "institution": null
                }
            ],
            "career": [
                {
                    "position": "Und:-löjtn.",
                    "years": {
                        "start_year": 1901,
                        "end_year": 1902
                    },
                    "organization": "Skarab. reg."
                },
                {
                    "position": "v. Första Göta trängkår",
                    "years": {
                        "start_year": 1902,
                        "end_year": null
                    },
                    "organization": null
                },
                {
                    "position": "löjtn.",
                    "years": {
                        "start_year": 1904,
                        "end_year": null
                    },
                    "organization": null
                },
                {
                    "position": "kapt.",
                    "years": {
                        "start_year": 1915,
                        "end_year": null
                    },
                    "organization": null
                },
                {
                    "position": "major o. chef f. Norrl. trängkår",
                    "years": {
                        "start_year": 1924,
                        "end_year": null
                    },
                    "organization": null
                },
                {
                    "position": "öv:-löjtn.",
                    "years": {
                        "start_year": 1928,
                        "end_year": null
                    },
                    "organization": null
                },
                {
                    "position": "överste i armén",
                    "years": {
                        "start_year": 1934,
                        "end_year": null
                    },
                    "organization": null
                }
            ],
            "family": {
                "spouse": "Ulla Aspelin",
                "marriage_year": "1908",
                "children": [],
                "hobbies": [
                    "Hobbies: foto o. botanik"
                ]
            }
        }
    }
}