{
    "original": "Foghammar, Nils Florentin,\nhäradsskrivare, Göteborg, f. 20/6/90 i Upps.\nG. 20 m. Elsa Bjerstedt. Barn: Olof\nf. 22, ing.. Linköp., Gunilla 26. —\nStud:ex. v. Lunds h. a. 1. 10, kansliex.\ni Lund 18. Anst. å kronolänsm :kont.\ni Kristianstads 1. 12-15, v. landskont.\ni Gbgs o. Boh. 1, 18, e. o. landskont.\ndär 18, ord. 24, förordn. s. e.\nlänsbok-håll. fr. 20, här:skriv. v. Inlands\nfögderi sed. 35. Kronoomb. i tax:nd f.\nGbg 19-24, ordf. i tax:ndn f. Styrsö\nkommun 23-24, ordf. i tax:ndn f. Gbgs\nstad sed. 25, ordf. i beredn :ndn f.\nfastigh:tax. i Torslanda o. Björklanda\nsocknars distr. 28, i Askims s :n 33,\nordf. i Inlands fögderis första\nfastig-h:tax:distr. 38, tillsyn :man v. allm.\nbrännvinsnederlaget i Gbg 22-26, rev.\ni Vasa flicksk. 26-32.\n\nFogmark, Anna-Greta Anderson-,\ntandläkare, Halmstad, f. 12/10/09 i\nLanderyd, Jönköp. 1., av Carl\nAnderson o. Alfhild Gyllenbäck. G. m.\nstat:skriv. Ingvar Fogmark. —\nStud:-ex. i Halmstad 30, tandl :kand. 34,\ntandl. 37. Vik. i Dalby 37, assist, i\nLimhamn o. Landeryd samt vik. i\nGis-laved 37, prakt, i Landeryd några år\nfr. 37, därefter prakt, i Halmstad.\nHobby: målning.\n\nFolin, Ragnar Georg Albert,\nlänsassessor, Karlskrona, f. 5/9/95 i\nLångasjö, Kronob. 1., av kronolänsm. Albert\nF. o. Ida Johansson. G. 43 m. Gurli\nLjungberg. — Studiex. v. Växjö h. a.\n1. 15, jur. kand. v. Lunds univ. 19,\nTingstjg. i Medelsta doms. 20 o. i\nÖstra härads doms. 21-24, anst. v.\nlänsstyr. i Blek. 1. sed. 25, länsassessor\nsed. 42. Ordf. i tax:ndr sed. 29, allm.\nomb. i |Sparbanker sed. 31.\n\nFolkar, Nils Åke Ossian,\nstadsingenjör, Sölvesborg, f. 7/1/08 i Sölvesborg.\n— Stud:ex. 31, civ:ing:ex. v. CTI 37.\nStadsing. i Sölvesborg sed. 39.\n\nFolkard von Scherling, Frithjof\n\nAdalbert Johannes, häradshövding,\nVärnamo, f. 19/12/96 i Rotterdam av\nkonsul Johannes Folkard v. Scherling\no. Paulina Rohn. G. 27 m. Naemà\nCarlsson. — Stud:ex. v. Gymn.\nEras-mianum i Rotterdam 15, fil. kand. i\nUpps. 17, jur. kand. i Upps. 21. Assess.\ni Göta hovr. 33, hovrättsråd 36,\nrevi-sekr. 39, häradshövd. i Östbo o.\nVäst-bo doms. sed. 45. Hobbies: klassiska\nspråk, historia. RNO.\n\n",
    "structured": {
        "0": {
            "full_name": "Foghammar, Nils Florentin",
            "location": "Göteborg",
            "occupation": "häradsskrivare",
            "birth_details": {
                "date": "20/06/1890",
                "place": "Uppsala"
            },
            "family": {
                "spouse": "Elsa Bjerstedt",
                "marriage_year": "1920",
                "children": [
                    {
                        "name": "Olof",
                        "birth_year": "1922"
                    },
                    {
                        "name": "Gunilla",
                        "birth_year": "1926"
                    }
                ]
            },
            "education": [
                {
                    "degree": "Stud:ex.",
                    "year": "1910",
                    "institution": "Lunds h. a."
                },
                {
                    "degree": "kansliex.",
                    "year": "1918",
                    "institution": "Lund"
                }
            ],
            "career": [
                {
                    "position": "anst. å kronolänsm :kont.",
                    "years": {
                        "start_year": 1912,
                        "end_year": 1915
                    },
                    "organization": "Kristianstads"
                },
                {
                    "position": "v. landskont.",
                    "years": {
                        "start_year": 1918,
                        "end_year": 1918
                    },
                    "organization": "Gbgs o. Boh."
                },
                {
                    "position": "e. o. landskont.",
                    "years": {
                        "start_year": 1918,
                        "end_year": 1918
                    },
                    "organization": "Gbgs o. Boh."
                },
                {
                    "position": "ord.",
                    "years": {
                        "start_year": 1924,
                        "end_year": null
                    },
                    "organization": "Inlands fögderi"
                },
                {
                    "position": "förordn.",
                    "years": {
                        "start_year": "efter 1924",
                        "end_year": null
                    },
                    "organization": "länsbok-håll. fr."
                },
                {
                    "position": "här:skriv. v. Inlands fögderi",
                    "years": {
                        "start_year": 1935,
                        "end_year": null
                    },
                    "organization": "Inlands fögderi"
                }
            ]
        },
        "1": {
            "full_name": "Fogmark, Anna-Greta Anderson-",
            "location": "Halmstad",
            "occupation": "tandläkare",
            "birth_details": {
                "date": "12/10/1909",
                "place": "Landeryd, Jönköping län"
            },
            "family": {
                "spouse": "Ingvar Fogmark",
                "marriage_year": "NULL",
                "children": []
            },
            "education": [
                {
                    "degree": "Stud:ex.",
                    "year": "1930",
                    "institution": "Halmstad"
                },
                {
                    "degree": "tandl :kand.",
                    "year": "1934",
                    "institution": "NULL"
                },
                {
                    "degree": "tandl.",
                    "year": "1937",
                    "institution": "NULL"
                }
            ],
            "career": [
                {
                    "position": "vik.",
                    "years": {
                        "start_year": 1937,
                        "end_year": null
                    },
                    "organization": "Dalby"
                },
                {
                    "position": "assist.",
                    "years": {
                        "start_year": 1937,
                        "end_year": null
                    },
                    "organization": "Limhamn o. Landeryd"
                },
                {
                    "position": "prakt.",
                    "years": {
                        "start_year": "efter 1937",
                        "end_year": null
                    },
                    "organization": "Halmstad"
                }
            ],
            "hobbies": [
                "Målning"
            ]
        },
        "2": {
            "full_name": "Folin, Ragnar Georg Albert",
            "location": "Karlskrona",
            "occupation": "länsassessor",
            "birth_details": {
                "date": "5/9/1895",
                "place": "Långasjö, Kronobergs län"
            },
            "family": {
                "spouse": "Gurli Ljungberg",
                "marriage_year": "1943",
                "children": []
            },
            "education": [
                {
                    "degree": "Studiex.",
                    "year": "1915",
                    "institution": "Växjö h. a."
                },
                {
                    "degree": "jur. kand.",
                    "year": "1919",
                    "institution": "Lunds univ."
                }
            ],
            "career": [
                {
                    "position": "Tingstjg.",
                    "years": {
                        "start_year": 1920,
                        "end_year": null
                    },
                    "organization": "Medelsta doms."
                },
                {
                    "position": "Tingstjg.",
                    "years": {
                        "start_year": 1921,
                        "end_year": 1924
                    },
                    "organization": "Östra härads doms."
                },
                {
                    "position": "anst.",
                    "years": {
                        "start_year": "efter 1925",
                        "end_year": null
                    },
                    "organization": "länsstyr. i Blek. l."
                },
                {
                    "position": "länsassessor",
                    "years": {
                        "start_year": 1942,
                        "end_year": null
                    },
                    "organization": "Karlskrona"
                }
            ],
            "community_involvement": [
                {
                    "role": "Ordf.",
                    "organization": "tax:ndr",
                    "years": "efter 1929"
                },
                {
                    "role": "allm. omb.",
                    "organization": "Sparbanker",
                    "years": "efter 1931"
                }
            ]
        },
        "3": {
            "full_name": "Folkar, Nils Åke Ossian",
            "location": "Sölvesborg",
            "occupation": "stadsingenjör",
            "birth_details": {
                "date": "7/1/1908",
                "place": "Sölvesborg"
            },
            "family": {
                "spouse": "NULL",
                "marriage_year": "NULL",
                "children": []
            },
            "education": [
                {
                    "degree": "Stud:ex.",
                    "year": "1931",
                    "institution": "NULL"
                },
                {
                    "degree": "civ:ing:ex.",
                    "year": "1937",
                    "institution": "CTI"
                }
            ],
            "career": [
                {
                    "position": "Stadsing.",
                    "years": {
                        "start_year": 1939,
                        "end_year": null
                    },
                    "organization": "Sölvesborg"
                }
            ]
        },
        "4": {
            "full_name": "Folkard von Scherling, Frithjof Adalbert Johannes",
            "location": "Värnamo",
            "occupation": "häradshövding",
            "birth_details": {
                "date": "19/12/1896",
                "place": "Rotterdam"
            },
            "family": {
                "spouse": "Naemà Carlsson",
                "marriage_year": "1927",
                "children": []
            },
            "education": [
                {
                    "degree": "Stud:ex.",
                    "year": "1915",
                    "institution": "Gymn. Erasmianum i Rotterdam"
                },
                {
                    "degree": "filosofie kand.",
                    "year": "1917",
                    "institution": "Uppsala"
                },
                {
                    "degree": "jur. kand.",
                    "year": "1921",
                    "institution": "Uppsala"
                }
            ],
            "career": [
                {
                    "position": "Assess.",
                    "years": {
                        "start_year": 1933,
                        "end_year": null
                    },
                    "organization": "Göta hovr."
                },
                {
                    "position": "hovrättsråd",
                    "years": {
                        "start_year": 1936,
                        "end_year": null
                    },
                    "organization": "NULL"
                },
                {
                    "position": "revisesekr.",
                    "years": {
                        "start_year": 1939,
                        "end_year": null
                    },
                    "organization": "NULL"
                },
                {
                    "position": "häradshövd.",
                    "years": {
                        "start_year": "efter 1945",
                        "end_year": null
                    },
                    "organization": "Östbo o. Väst-bo doms."
                }
            ],
            "hobbies": [
                "klassiska språk",
                "historia"
            ],
            "honorary_titles": [
                {
                    "title": "RNO",
                    "institution": "NULL",
                    "year": "NULL"
                }
            ]
        }
    }
}