{
    "original": "Fuhrman, Oskar Wilhelm,\nbruksdisponent, Degerön, f. 19/3/93 i\nUddevalla av C. G. F. o. Matilda Fuhrman.\nG. 27 m. Anna Lennmalm. Barn: Karl\nGustav f. 28, Gunhild 31. —\nSkol-stud. i Gustafsberg o. v. Uddevalla\nh. a. 1., Fihp Holmqvists hand :inst.\nAnst. i Mellerud, kont. v. A-B\nKväfve-ind. i Bohus 16-22, bruksbokhåll. de\nGeersfors Bruk i Degerön 22,\nbruks-förv. där fr. 32. Övert. tills. m. fil.\ndr S. Fagerberg A-B Qvarnshammars\nJernbruk 39, disp. f. detta. Led. av\nkomm :fullaTL. o. dess beredn :utsik., v.\nordf. i valnd o. kristidsnd, led. av\ntaxer:nd o. fastigh :tax:nd, ett flert.\nrev:uppdr. bl. a. s. länsstyr. rev. i\n\narb :lösh :komm. Medl. av\nGustafs-bergsfören. i Uddevalla, Motala tekn.\nkl., Östergötl. 1. jaktvifören.\n\nFunck, Gösta Peter Möller, friherre,\nkapten, Skönberga, f. 1/4/82 å\nBolltorp, Sköniberga, östergötl. 1., av\ngods-äg., / frih. Thomas Alexander F. o.\nCharlotte Laura Sophia von Möliler.\nG. 04 m. Sophie von Dardel. Barn:\nEbba f. 08, g. m. byråchef Alfonce Du\nPasquiier, Neuchàteli, Schweàz, Liise 10,\n\ng.\tm. leg:se’kr. Jean Jacques de\nTri-bolet, Bern, Helene 17, g. m. godsäg.\nTage Bergströni, Gammelbo,\nRams-berg. — Undrlöjtn. v. Andra Svea\n(UppL) artireg. 02, löjtn. 08, kapt. 16,\npå res:stat 18, pens. 45. Äg. o. bebor\nBoilkorp, Skönberga. Ordf. i\nkomm:-nd 22-23 o. i kommrstämma 26, v.\nordf. i kyrkostämma, ordf. i tax:nd,\ni Hammarkinds hush :gi’lle o.\nSkönberga hush ikrets, iled. av pasf.råd o.\nkyrkoråd, led. av styr. f. Ö. östergötl.\nlantbr :kl., lantbr :omb. i östergötl.\nhush isällsk. RSO, RÖFrJO.\n\nFunck, Karl Fredrik Thomas (Tom),\nprovinsialläkare, Shte, f. 25/11/00 i\nSthlm av John F. o. Hulda\nLudvigsson. G. 30 m. Edit Björnfors. Barn:\nKarin f. 32, Arne 34, Ingmar 36,\nLennart 45. — Stud:ex. 19, med. kand. 23\no. med. lic. 28, allt i Sthlm. Und :läk.\nv, Spenshults sanat. 28-29, assist :läk.\nv. Lidköp. ilas. 29, tf. prov :läk. kort.\ntider 29-30, tf. und:läk. v. Karlshamns\nlas. 30, assist :läk. v. Stocksunds las.\nkir. avd. 30-31, tf. andre und :läk. där\nsamt e. und :läk. v. S:t Görans sjukh.\nkir. avd. o. Seraf :las. kir. klin. 31, tf.\nprov:läk. i Råneå distr. 31-32,\nund:-iläk. v. Gällivare las. 32-34, därunder\ntf. las :läk. fem. mån., förordn. s.\nprovrläk. i ett flert. distr. samt s.\nstadsläk. i Vimmerby, Strängnäs o.\nAskersund 34-37, e. und :läk. v. Säters\nsjukh. 37, prov:läk. i Slite distr. sed.\n38. •\n\n",
    "structured": {
        "0": {
            "full_name": "Fuhrman, Oskar Wilhelm",
            "location": "Degerön",
            "occupation": "bruksdisponent",
            "birth_details": {
                "date": "19/03/1893",
                "place": "Uddevalla",
                "parents": "C. G. F. o. Matilda Fuhrman"
            },
            "education": [
                {
                    "degree": "filosofie kandidat",
                    "year": "neb. 1.",
                    "institution": "Gustafsberg"
                },
                {
                    "degree": "Fihp Holmqvists handelsinstitut",
                    "year": "NULL",
                    "institution": "NULL"
                }
            ],
            "career": [
                {
                    "position": "kontorist",
                    "years": {
                        "start_year": 1916,
                        "end_year": 1922
                    },
                    "organization": "Mellerud"
                },
                {
                    "position": "bruksbokhållare",
                    "years": {
                        "start_year": 1922,
                        "end_year": 1932
                    },
                    "organization": "de Geersfors Bruk i Degerön"
                }
            ],
            "family": {
                "spouse": "Anna Lennmalm",
                "marriage_year": "27",
                "children": [
                    {
                        "name": "Karl Gustav",
                        "birth_year": "28"
                    },
                    {
                        "name": "Gunhild",
                        "birth_year": "31"
                    }
                ]
            }
        },
        "1": {
            "full_name": "Funck, Gösta Peter Möller",
            "location": "Skönberga",
            "occupation": "kapten",
            "birth_details": {
                "date": "01/04/1882",
                "place": "Bolltorp, Sköniberga, östergötl. l.",
                "parents": "frih. Thomas Alexander F. o. Charlotte Laura Sophia von Möliler"
            },
            "family": {
                "spouse": "Sophie von Dardel",
                "marriage_year": "04",
                "children": [
                    {
                        "name": "Ebba",
                        "birth_year": "08"
                    },
                    {
                        "name": "Liise",
                        "birth_year": "10"
                    },
                    {
                        "name": "Helene",
                        "birth_year": "17"
                    }
                ]
            }
        },
        "2": {
            "full_name": "Funck, Karl Fredrik Thomas (Tom)",
            "location": "Shte",
            "occupation": "provinsialläkare",
            "birth_details": {
                "date": "25/11/1900",
                "place": "Sthlm",
                "parents": "John F. o. Hulda Ludvigsson"
            },
            "family": {
                "spouse": "Edit Björnfors",
                "marriage_year": "30",
                "children": [
                    {
                        "name": "Karin",
                        "birth_year": "32"
                    },
                    {
                        "name": "Arne",
                        "birth_year": "34"
                    },
                    {
                        "name": "Ingmar",
                        "birth_year": "36"
                    },
                    {
                        "name": "Lennart",
                        "birth_year": "45"
                    }
                ]
            }
        }
    }
}