{
    "original": "UDDENBERG, SVEN G,\növeringenjör, Kalmar, f i Lund 13/10/22 av\nlandssekr Ernst U o dr Inez Sverelius.\n\nStud:ex 41, res:off:ex 43, CTH 47, ing\nSieverts kabelverk Sundbyberg 48-50,\n51-53, Brown Boveri Baden Schweiz 50,\nSKF Paris 51, övering Exo-Verken ab\nKalmar sed 53. - Led hamnstyr. - Medl\nRotary, SHT. - Kapt A 6 res. - Hobby:\ntennis.\n\nGift 50 m Britta Christenson f 26, dtr t\nförf Karl-Ewert C o Agneta Thomé.\n-Barn: Lars f 53, Björn f 57.\n\nUDDGREN, A EINAR, överingenjör,\n\nLerum, f i Uddevalla 27/7/02 av\nsko-handl Johan U o Kristina Isaksson.\nStud:ex 21, CTH 25, konstr ab\nOriginal-Odhner Gbg 28, verkst :ch 35, konstr :ch\n42, övering där sed 62. - Utm: Göta\nart:-reg stM, SCFftjtG. - Hobbies: fiske,\nsport, schack.\n\nGift 32 m Sif Wennerbeck f 06, dtr t\nkyrkoh Olof W o Karin Geijer. - Barn:\nOlof f 33, Lars f 36, Birgitta f 40.\nUDDMAN, N TORSTEN,\nprovinsialläkare, Ljungby, f i Förslöv, Kristianst\nl, 15/8/08 av disp Hjalmar U o Anna\nGustafsson.\n\nStud:ex Lund 29, med kand Sthlm 33,\nmed lic Lund 42; underläk Ängelholms\no Oskarshamns las 41-43, Kristianstads\no Karlshamns las 43-44, Söderhamns las\n44-48, Moheds sanat 48-49, prov:läk\nLjungby n:a distr sed 50.\nGift 38 m fil mag Greta Borelius f 13,\ndtr t lekt Johan B o Ruth Bagge. - Barn:\nRolf f 40, Elisabeth f 44.\n\nUGGLA, CLAES L T, direktör, Gbg,\nf i Sthlm 31/5/25 av konsul Hjalmar U\no Sonja Plazikowska.\nStud:ex 44, Schartaus HdlI 49. - Anst\nab Sv Shell 44-45, Emil R Boman 47-48,\nUnited Lines Agencies of (I) Private\nLtd Calcutta 50-57, repr i Japan f\nOstasiatiska komp 58-60, linjech f\nIndienlin j ab Sv Ostasiatiska komp sed 60.\n-Medl FrimO. - Hobbies: bridge, skytte,\ntennis.\n\nGift 54 m Britta Engberg f 27, dtr t dir\nGunnar E o Inga-Lisa E. - Barn:\nElizabeth f 54, Annika f 57, Johan f 62.\n\n",
    "structured": {
        "0": {
            "full_name": "UDDENBERG, SVEN G",
            "location": "Kalmar",
            "occupation": "överingenjör",
            "birth_details": {
                "date": "13/10/1922",
                "place": "Lund",
                "parents": "landssekr Ernst U o dr Inez Sverelius"
            },
            "education": [
                {
                    "degree": "Stud:ex",
                    "year": "1941",
                    "institution": "NULL"
                },
                {
                    "degree": "res:off:ex",
                    "year": "1943",
                    "institution": "NULL"
                },
                {
                    "degree": "CTH",
                    "year": "1947",
                    "institution": "NULL"
                }
            ],
            "career": [
                {
                    "position": "ingenjör",
                    "years": {
                        "start_year": 1948,
                        "end_year": 1950
                    },
                    "organization": "Sieverts kabelverk Sundbyberg"
                },
                {
                    "position": "ingenjör",
                    "years": {
                        "start_year": 1951,
                        "end_year": 1953
                    },
                    "organization": "Brown Boveri Baden Schweiz"
                },
                {
                    "position": "övering",
                    "years": {
                        "start_year": 1953,
                        "end_year": 0
                    },
                    "organization": "Exo-Verken ab Kalmar"
                }
            ],
            "family": {
                "spouse": "Britta Christenson",
                "marriage_year": "1950",
                "children": [
                    {
                        "name": "Lars",
                        "birth_year": "1953"
                    },
                    {
                        "name": "Björn",
                        "birth_year": "1957"
                    }
                ]
            }
        },
        "1": {
            "full_name": "UDDGREN, A EINAR",
            "location": "Lerum",
            "occupation": "överingenjör",
            "birth_details": {
                "date": "27/7/1902",
                "place": "Uddevalla",
                "parents": "sko-handl Johan U o Kristina Isaksson"
            },
            "education": [
                {
                    "degree": "Stud:ex",
                    "year": "1921",
                    "institution": "NULL"
                },
                {
                    "degree": "CTH",
                    "year": "1925",
                    "institution": "NULL"
                }
            ],
            "career": [
                {
                    "position": "konstr ab",
                    "years": {
                        "start_year": 1928,
                        "end_year": 0
                    },
                    "organization": "Original-Odhner Gbg"
                }
            ],
            "family": {
                "spouse": "Sif Wennerbeck",
                "marriage_year": "1932",
                "children": [
                    {
                        "name": "Olof",
                        "birth_year": "1933"
                    },
                    {
                        "name": "Lars",
                        "birth_year": "1936"
                    },
                    {
                        "name": "Birgitta",
                        "birth_year": "1940"
                    }
                ]
            }
        },
        "2": {
            "full_name": "UDDMAN, N TORSTEN",
            "location": "Ljungby",
            "occupation": "provinsialläkare",
            "birth_details": {
                "date": "15/8/1908",
                "place": "Förslöv, Kristianst l",
                "parents": "disp Hjalmar U o Anna Gustafsson"
            },
            "education": [
                {
                    "degree": "Stud:ex",
                    "year": "1929",
                    "institution": "Lund"
                },
                {
                    "degree": "med kand",
                    "year": "1933",
                    "institution": "Sthlm"
                },
                {
                    "degree": "med lic",
                    "year": "1942",
                    "institution": "Lund"
                }
            ],
            "career": [
                {
                    "position": "underläk",
                    "years": {
                        "start_year": 1941,
                        "end_year": 1943
                    },
                    "organization": "Ängelholms o Oskarshamns las"
                },
                {
                    "position": "prov:läk",
                    "years": {
                        "start_year": 1950,
                        "end_year": 0
                    },
                    "organization": "Ljungby n:a distr"
                }
            ],
            "family": {
                "spouse": "fil mag Greta Borelius",
                "marriage_year": "1938",
                "children": [
                    {
                        "name": "Rolf",
                        "birth_year": "1940"
                    },
                    {
                        "name": "Elisabeth",
                        "birth_year": "1944"
                    }
                ]
            }
        },
        "3": {
            "full_name": "UGGLA, CLAES L T",
            "location": "Gbg",
            "occupation": "direktör",
            "birth_details": {
                "date": "31/5/1925",
                "place": "Sthlm",
                "parents": "konsul Hjalmar U o Sonja Plazikowska"
            },
            "education": [
                {
                    "degree": "Stud:ex",
                    "year": "1944",
                    "institution": "NULL"
                },
                {
                    "degree": "Schartaus HdlI",
                    "year": "1949",
                    "institution": "NULL"
                }
            ],
            "career": [
                {
                    "position": "anst",
                    "years": {
                        "start_year": 1944,
                        "end_year": 1945
                    },
                    "organization": "ab Sv Shell"
                },
                {
                    "position": "anst",
                    "years": {
                        "start_year": 1947,
                        "end_year": 1948
                    },
                    "organization": "Emil R Boman"
                },
                {
                    "position": "repr",
                    "years": {
                        "start_year": 1950,
                        "end_year": 1957
                    },
                    "organization": "United Lines Agencies of (I) Private Ltd Calcutta"
                },
                {
                    "position": "linjech",
                    "years": {
                        "start_year": 1960,
                        "end_year": 0
                    },
                    "organization": "ab Sv Ostasiatiska komp"
                }
            ],
            "family": {
                "spouse": "Britta Engberg",
                "marriage_year": "1954",
                "children": [
                    {
                        "name": "Elizabeth",
                        "birth_year": "1954"
                    },
                    {
                        "name": "Annika",
                        "birth_year": "1957"
                    },
                    {
                        "name": "Johan",
                        "birth_year": "1962"
                    }
                ]
            }
        }
    }
}