{
    "original": "Bergstrand, Knut Harald, direktör,\nDjursholm, f. 13/12/99 i Malmö. Stud :-\nex. 19, off :ex. 21, off. i Kgl. Hallands\nreg. Direktör i Sv. Petroleum A-B\nStandard.\nBergstrand, Nils Rickard, kapten,\nbrandchef, Sthlm, f. 14/7/84 i östra\nBroby fs., Kristianst. L, av major\nRichard B. o. Manilla Person. G. 09\nm. frih :an Svea Maria Hummerhielm.\nUnd i-löjtn. v. Jönköp. reg. 05, löjtn. 07,\nkapten 19, på övergrstat 27. RSO,\nSkytteM.\nBergstrand, Ossian Wilhelm\nBernhard, komminister, Hässelby, f. 21/12\n/98 i Sthlm av boktryck. John B. o.\nAnna Kjellström. G. 28 m. Inga\nKristina Wådell. Barm Birgitta f. 29,\nMargit f. 33, d. 36, Bengt Inge Walter\nf, 36, Barbro Ella Maria f. 38. Stud\n:-ex. i Sthlm 16, teol. fil. ex. 20, teol.\nkand. 23, prakt. teol. prov 23. Pv. f.\nUpps. ärkestift 23, v. past. i Norrala\n23, kyrkoadj. i Ljusdal 24, i\nHudiksvall 26, komm. i Hässelby 28, förordn,\nsom vik. sjöm :präst o. sv. past. i\nBuenos Aires 34-35, kyrkofullm., ordf. i\nbarnav :ndn, ordf. i Hässelbykr. av Sv.\nRöda Korset sed. 37, Sv. sjöm :v :styr.\nkontr :omb.\nBergström, Axel Emil, ingenjör,\nLidingö, f. 10/5/99 i Byske av\nmaskin-insp. Emil B. o. Matilda Hedlund. G.\n37 m. Ebba Margareta Kvarnbäck.\nDiploming, v. Höhere Technische\nLehr-anstalt, Zwickau i. Sachsen 24. Anst.\nv. AGA: s experimentavdeln. 25-30,\negen fabr. i dentalbranschen tills. m.\nciv äng. Gösta Björklund, A-B Denta^\nlus i Jakobsdal sed. 30, AGA:s\nIjus-tekn. expert sed. 32. In- o. utl. patent\npå ett flert. huvudsakl. ljustekn.\nuppfinningar. Led. av KTH:s\nnybyggn:-komm. f. ljustekn. Medl. av Svenska\nBelysningssällsk.\nBergström, Bernhard Claes Hjalmar,\nförste byråsekreterare, Ålsten, f. 29/\n6/92 i Umeå av landskamrer Carl V.\nBergström o. Fanny Ljungberg. G. m.\nElna Ernberg. Barn: Anders f. 26,\nJan f. 28. Stud :ex. i Umeå 11, jur.\nkand. Upps. 19. E. o. not. i Svea hovr.\n19 o. i Göta hovr. 23, tf. domhav.\n20-24 i Västerb. s:a (odelade o. delade),\nVästerb. mell., Ångermani, s :a samt\nAskims, Hisings o. Sävedals doms.\nsammani, l år 26 d. Tjänstgj. i Svea\nhovr. 22-23 ss. not., bitr. fisk. o. fisk.,\nsekr. i vattenf :styr. 24,\nvattenrätts-aman. 20-22. V., auditör v. Västerb.\nreg. 21-22, sekr. i Gammalsvenskby-\nkomm. o. Gammalsvenskbystift. 29-37.\nOff. i Västerb. reg:s res. 14-22, sekr.\nl styr. f. Sophiahemmet 40, ordf. i\nhyresnämnd 42. Utg. skr.: Die Siedler\nvon Gammalsvenskby. (Le Nord 39.)\nRVO 38.\n\n<b>Bergström, Carl</b> Abraham,\ncivilingenjör, rektor, Stockholm, f. i Sthlm\n35/2/84 av sjökapt. Carl B. o. Amalia\nGestrin. KTH 06, stud:resor i Norge,\nDanm., Tyskl., Engl., USA, ing. i USA\n07-12, inspektör i Eng. Lloyd 13, lär.\nv. navrsk. i Gtbg 14-20, tf. prof. v.\nChalm. tekn. inst. 18-19, lekt. v. tekn.\nlärov, i Malmö 20-36, insp. i\nGerma-nischer Lloyd 30-36, examensled, å\nnav:skolornas maskintekn, linje fr. 33,\nrekt. v. nav :sk. i Sthlm fr. 37. RNO.\n",
    "structured": {
        "1": {
            "full_name": "Bergstrand, Knut Harald",
            "location": "Djursholm",
            "occupation": "Direktör",
            "birth_details": {
                "date": "13/12/1899",
                "place": "Malmö"
            },
            "education": [
                {
                    "degree": "Stud. ex.",
                    "year": "1919",
                    "institution": "NULL"
                },
                {
                    "degree": "Off :ex.",
                    "year": "1921",
                    "institution": "NULL"
                }
            ],
            "career": [
                {
                    "position": "Direktör",
                    "years": {
                        "start_year": 0,
                        "end_year": 0
                    },
                    "organization": "Sv. Petroleum A-B Standard"
                }
            ],
            "family": {
                "spouse": "NULL",
                "marriage_year": "NULL",
                "children": []
            }
        },
        "2": {
            "full_name": "Bergstrand, Nils Rickard",
            "location": "Sthlm",
            "occupation": "Kapten, Brandchef",
            "birth_details": {
                "date": "14/07/1884",
                "place": "östra Broby fs., Kristianst. L"
            },
            "education": [],
            "career": [
                {
                    "position": "Und i-löjtn. v. Jönköp. reg.",
                    "years": {
                        "start_year": 1905,
                        "end_year": 1907
                    },
                    "organization": "NULL"
                },
                {
                    "position": "Löjtn.",
                    "years": {
                        "start_year": 1907,
                        "end_year": 1919
                    },
                    "organization": "NULL"
                },
                {
                    "position": "Kapten",
                    "years": {
                        "start_year": 1919,
                        "end_year": 1927
                    },
                    "organization": "NULL"
                }
            ],
            "family": {
                "spouse": "frih :an Svea Maria Hummerhielm",
                "marriage_year": "1909",
                "children": []
            }
        },
        "3": {
            "full_name": "Bergstrand, Ossian Wilhelm Bernhard",
            "location": "Hässelby",
            "occupation": "Komminister",
            "birth_details": {
                "date": "21/12/1898",
                "place": "Sthlm"
            },
            "education": [
                {
                    "degree": "Stud : ex.",
                    "year": "1916",
                    "institution": "Sthlm"
                },
                {
                    "degree": "Teol. fil. ex.",
                    "year": "1920",
                    "institution": "NULL"
                },
                {
                    "degree": "Teol. kand.",
                    "year": "1923",
                    "institution": "NULL"
                }
            ],
            "career": [
                {
                    "position": "Prakt. teol. prov",
                    "years": {
                        "start_year": 1923,
                        "end_year": 1923
                    },
                    "organization": "NULL"
                },
                {
                    "position": "Pv. f.",
                    "years": {
                        "start_year": 1923,
                        "end_year": 1923
                    },
                    "organization": "Upps. ärkestift"
                },
                {
                    "position": "V. past.",
                    "years": {
                        "start_year": 1923,
                        "end_year": 1924
                    },
                    "organization": "Norrala"
                },
                {
                    "position": "Kyrkoadj.",
                    "years": {
                        "start_year": 1924,
                        "end_year": 1926
                    },
                    "organization": "Ljusdal"
                },
                {
                    "position": "Kyrkoadj.",
                    "years": {
                        "start_year": 1926,
                        "end_year": 1928
                    },
                    "organization": "Hudiksvall"
                },
                {
                    "position": "Komm.",
                    "years": {
                        "start_year": 1928,
                        "end_year": 1928
                    },
                    "organization": "Hässelby"
                },
                {
                    "position": "Förordn.",
                    "years": {
                        "start_year": 1934,
                        "end_year": 1935
                    },
                    "organization": "Buenos Aires"
                }
            ],
            "family": {
                "spouse": "Inga Kristina Wådell",
                "marriage_year": "1928",
                "children": [
                    {
                        "name": "Barm Birgitta",
                        "birth_year": "1929"
                    },
                    {
                        "name": "Margit",
                        "birth_year": "1933"
                    },
                    {
                        "name": "d",
                        "birth_year": "1936"
                    },
                    {
                        "name": "Bengt Inge Walter",
                        "birth_year": "1936"
                    },
                    {
                        "name": "Barbro Ella Maria",
                        "birth_year": "1938"
                    }
                ]
            }
        },
        "4": {
            "full_name": "Bergström, Axel Emil",
            "location": "Lidingö",
            "occupation": "Ingenjör",
            "birth_details": {
                "date": "10/05/1899",
                "place": "Byske"
            },
            "education": [
                {
                    "degree": "Diploming",
                    "year": "1924",
                    "institution": "Höhere Technische Lehr-anstalt, Zwickau i. Sachsen"
                }
            ],
            "career": [
                {
                    "position": "Anst.",
                    "years": {
                        "start_year": 1925,
                        "end_year": 1930
                    },
                    "organization": "AGA: s experimentavdeln."
                },
                {
                    "position": "Egen fabr. i dentalbranschen tills. m. civ äng. Gösta Björklund, A-B Denta^lus i Jakobsdal sed.",
                    "years": {
                        "start_year": 1930,
                        "end_year": 1930
                    },
                    "organization": "NULL"
                },
                {
                    "position": "AGA:s ljustekn. expert sed.",
                    "years": {
                        "start_year": 1932,
                        "end_year": 1932
                    },
                    "organization": "NULL"
                }
            ],
            "family": {
                "spouse": "Ebba Margareta Kvarnbäck",
                "marriage_year": "1937",
                "children": []
            }
        },
        "5": {
            "full_name": "Bergström, Bernhard Claes Hjalmar",
            "location": "Ålsten",
            "occupation": "Förste byråsekreterare",
            "birth_details": {
                "date": "29/06/1892",
                "place": "Umeå"
            },
            "education": [
                {
                    "degree": "Stud",
                    "year": "1911",
                    "institution": "Umeå"
                },
                {
                    "degree": "Jur. kand.",
                    "year": "1919",
                    "institution": "Upps."
                }
            ],
            "career": [
                {
                    "position": "E. o. not. i Svea hovr.",
                    "years": {
                        "start_year": 1919,
                        "end_year": 1919
                    },
                    "organization": "NULL"
                }
            ],
            "family": {
                "spouse": "Elna Ernberg",
                "marriage_year": "NULL",
                "children": [
                    {
                        "name": "Anders",
                        "birth_year": "1926"
                    },
                    {
                        "name": "Jan",
                        "birth_year": "1928"
                    }
                ]
            }
        },
        "6": {
            "full_name": "Bergström, Carl Abraham",
            "location": "Stockholm",
            "occupation": "Civilingenjör, Rektor",
            "birth_details": {
                "date": "35/02/1884",
                "place": "Sthlm"
            },
            "education": [],
            "career": [],
            "family": {
                "spouse": "Amalia Gestrin",
                "marriage_year": "NULL",
                "children": []
            }
        }
    }
}