{
    "original": "Brandt, Helge Ivar, civilingen j or r\nSthlm, f. 26/1/02 i Upps. Stud:ex. v.\nh. reallärov. å Norrm. i Sthlm 20y\nKTH (avd. f. elektrotekn.) 21-25.\nAnst. 26 v. A-B Elektrolux el. dess\ndtr-bol., 26-28 på kyllab., 28-31 s.\ninköpschef v. kylskåpsfabr. (A-B Arctic) i\nMotala, chefsass. o. försälj, v.\nfilter-avd. 31-33, kontr äng. v. kylskåpsfabr.\n33-34, chefsass. v. kylavd. sed. 34,\nOrdf. i KTH :s stud :kårs sekt. f.\nelektrotekn. 24-25, klubbmäst. i Tekn. kl.\ni Motala 30-31, sekr. i Sthlms Stud\n:-sångiförb. 31-32, v. ordf. i\nElektrolux-klubben sed. 40, styr :medl. i f ören.\n1902 års män sed. 43.\nBrandtberg, Carl Oscar Botvid,\nartist, överlärare, Lidingö, f. 28/7/86 l\nSthlm av köpm. Algot B. o. Hulda\nWahlström. G. 12 m. Berta\nAndersson. Barn: Sten Sture f. 14. Real :ex.\n03, Tekn. sk. h. konstindustr. avd. 07.\nÖv :lär. i dekor rmåln. i n :da sk. sed.\n14. Medv. v. dekor, av\nSaltsjöbadens-kyrka, dekor. Lidingö kyrka 13,\nsam-arb. m. prof. Ivar Tengbom m. bl. a.\ndekor, i Rockelstad, Hel. Birgittas\nuppenbar. 18, Högalidskyrk. 21-22.\nDekor :måln. v. Sthlmsutställn. 09, Balt.\nutst. 14, San Francisco 15. Komp.\nkyrkl. textilier t. bl. a.\nKiddarholms-kyrk., Högalidskyrk., Klara, Oscars,\nNacka, Lidingö, Vreta, Morlanda, eng.\nkyrk. i Sthlm o. sv. kyrk. i London,\ndekor. rest. Sturehof, Carlton hotell\n27, hotell Gillets festsal 30, glasmåln.\nt. kyrk. i Löt 28, Solna 29, Åby 31 o.\nAla 39.\nBränner, Per-Axel Helge, regissör,.\nSthlm, f. i Linköping 25/1/99. G. 28\nm. Aina Margareta Stern. Dram.\nelev-sk. 19-21, eng. v. Dram. Teat., Sv. teat,\nKonserthus- o. Blancheteat. 21-31,\nregissör o. konstnärl. ledare v. Nya\nTeatern fr. 40; de Wahlstip. 31. Ordf. i\nSv. teatiförb. fr. 34, d:o o. ständ.\nstyr :led. i Djurgårdsmäss. stift. fr.\n35, styr:led. i stift. Höstsol, Dram.\nlléteat. elevsk. o.  Nord. skådesp:rådet,\nmedl. av Teaterr. 41.  RVO.\n\n<b>Branting, Anna</b> Matilda Charlotta,\nförfattarinna, Sthlm, f. i Sthlm av\npo-liskommiss. Erik Jäderin o. Charlotta\nHolm. G. 1. 77-83 m. löjtn. Gust. v.\nKraemer, d. 84, 2. 84 m. red., sederm,\nstatsmin. Hj. Branting, d. 25. Medarb,\ni Tiden 84-85, teaterrec. i Soc.-dem.\n86-92 o. 13-17, Sthlms-Tidn. 92-09\n(sign.: René).\n\n<b>Branting, Georg</b>, advokat, Sthlm, f.\ni Sthlm 21/9/87 av red. sederm,\nstatsmin. Hj. B. o. Anna Jäderin. G. 1. 14\nm. Carin Isberg, 2. 25 m. fil. kand.\nRina Lind. Jur. kand. Sthlm 13, tjg.\nv. s:a Roslags hdsrätt, förest, f. Nya\nBankens notariatavd. 14-16, anst. h.\nadv. W. Hellberg, egen adv:byrå i\nSthlm sed. 17, led. av Sv :es adv :samf.,\nsekr. i komm. f. utredn, av den\nindu-str. demokratins problem 20-23,\nStadsfullm, i Sthlm 27-38, F. K. sed. 31\n(lista lagutsk., s), styr:led. i Sthlms\narb rkommun o. i Sthlms högsk., medl.\nav 40 års flyktingshjälpkomm. l :a pr.\ni värjfäktn., Balt. sp. 13.\n\n<b>Branting-Westerståhl, Sonja</b>,\nadvokat, Sthlm, f. i Sthlm av statsmin. Hj.\nB. o. Anna Matilda Charlotta Jäderin.\nG. 14 m. adv. Olof Westerståhl. Barn:\nHans-Jörgen f. 16. Mog :ex. v.\nPalmgrenska sk. i Sthlm 09, jur. kand. 16.\nAnst. v. Sthlms stads rättshj :anst.\n18-25, därav ss. 2 :a bitr. jur. fr. 19. Egen\nadv :verksamh. i Sthlm sed. 27. Av\nö. Ä. uts. medl. i tvister mellan makar\nfr. 33. Led. av Sv:es Adv:samf.\n\n<b>Bratt, Axel</b>, tandläkare, Sthlm, f.\n17/4/84 i Jönköp. av hovr:råd. Axel\nWilhelm B. o. Ellen Maria Elisabet\nWahlgren. G. 09 m. tandl. Elsa\nSundberg, se Bratt, Elsa. Barn: Axel\nErland f. 11, Sonja f. 12, Lena f. 17.\nStud:ex. i Jönköp. 04, tandl :kand. 06,\ntandl :ex. 08. Prakt, i Sthlm sed. 08.\n\n<b>Bratt, Einar</b> Olof, överste, byråchef,\nSthlm, f. i Växjö landsförs., Kronob.\nL, 9/9/86 av överstelöjtn. Olof B. o.\nMagda Nordlund. G. 11 m. Stina\nLindgren. Off:ex. 08, und rlöjtn. v.\nKronob, reg. 06, krigshögsk. 11-13,\nlöjtn. v. gen :stab. 18, överstelöjtn. 33,\nv. liv :reg. gren. 35, överste 37. Lär. v.\nkrigshögsk. 20-24, v. sjökrigshögsk.\n29-37, mil :litt :fören is kassaförv. 19-37,\nprot :för. i kartv :kommiss. 28-37, avd:ch. \nv. gen :st. top. avd. 37, byråch, i\nrikets allm. kartv. fr. 37. Utg. skr. i\nkartogr. ämnen. GV .-sJmt, RSO, RNO,\nEöK3kl, LKrVA.\n\n<b>Bratt, Elsa</b> Sofia, tandläkare, Sthlm,\nf. i Åtvidaberg, Östergötlands l., av\nf. d. prov:läk. Knut Sundberg o. Jenny\nBergström. G. 09 m. tandl. Axel B.\nBarn: se denne. Stud:ex. i Sthlm 03,\ntandl:kand. 05, tandl:ex. 08. Prakt, i\nSthlm sed. 08.\n\n<b>Bratt, Erland</b> Axel, ingenjör, Sthlm,\nf. i Gtbg 22/3/74 av handl. Axel B. o.\nIsabella Pineus. G. 04 m. Julie Wiman\ncl. 39. V. Gtbgs lat .-lärov., avg:ex. fr.\nChalmers 98, gen:sekr. i k. auto :klubb.\n09-19, besiktn:m. f. auto:biler 11,\nförest, f. besiktn:myndigh. f. motorford.\ni Sthlm 31-35. Ordf. i auto:\nbesiktn:m ann. f ö ren. 25-35. Deleg. v. intern,\nkonf. i Paris 09 ang. auto :biltraf.,\ninit :tag. t. sv. vägforen. o. t. nät\n:-f ören. f. trafiksäkerh. f ram j. Led. av\nK.A.KIS öv:dom:nd 26-40, hed:led. i\nK.A.K. RVO, IdrGM, SkytteGM,\nKAK:s förtj:GM, Clarence v. Rosen\nGM, FAK:s förtj:GM, Motorm.\nriksförb:s förtj:M.\n\n<b>Bratt, Gösta</b>, överste, Sthlm, f. \n14/8/77 i Åmål av överste Claes B. o.\nOlga Ekelund. G. 11 m. Elsa\nAndersson. Und :löjtn. v. Värml. reg. 99,\nlöjtn. 01, kapt. 12, major v. Norrb. reg.\n22, ch. f. skidlöparbatalj., f. arméns\nund i off :sk. 26, överstelöjtn. 26, överste\n32, överste o. chef f. Hall. reg. 32,\nmil :områdesbefälh. i övre Norrl. milo.\n37-41. Genomg. Gymn. centrånst.\n00-02, krigshögsk. 05-06, komm. gen :stab.\n10-13, l :e adj. v. V. arméf. 13-18, chef\nf. und:off:sk. å Karlsborg 19-20, f.\nres :off :kurs. v. Karlberg 20-22. Tjg.\ni ital. arm. 22, i eng. armén 26.\nKSO-Ikl, RNO.\n\n<b>Bratt, John</b> Lennart, f. d.\nkammarrättsråd, Sthlm, f. 8/10/93 i Växjö av\növ:löjtn. Olof B. o. Magda Nordlund.\nG. 31 m. Margareta Rydeman. Barn:\nJohn Olof Ragnar f. 32, Claes Åke\nHenning f. 33, Bengt Christian f. 40.\nStud:ex. 12, jur. kand. 17. Tingstjg.\n17-20, aman. i just:dep. 20-22,\ntjänste-m. i kammarr. 20, l :e aman. 21, t. f.\nassess. 21, t. f. sekr. h. J. O. 23 o. 24,\nföredr. i reg:r. 25, 26-31 o. 32-34, e.\nkammarrättsråd 31, kammarr:råd 34,\nt. f. skattedir. i Sthlm 41-43.\nSkatteexpert h. Skand. Banken fr. 43,\nom-b :m. h. Allm, änke- o. pupillkass. fr.\n35, led. av styr. f. Försäkringsbol.\nBore 43. Skr.: ett flert. art. i Sv.\nskattetidn., Förvaltningsrätts!, tidskr,\nm. fl. publ.  RNO, RVO.\n\n",
    "structured": {
        "0": {
            "full_name": "Brandt, Helge Ivar",
            "location": "Sthlm",
            "occupation": "Civilingenjör",
            "birth_details": {
                "date": "26/01/1902",
                "place": "Uppsala"
            },
            "education": [
                {
                    "degree": "Stud:ex.",
                    "year": "20",
                    "institution": "Norrm. i Sthlm"
                },
                {
                    "degree": "KTH (avd. f. elektrotekn.)",
                    "year": "21-25",
                    "institution": "Kungliga Tekniska Högskolan"
                }
            ],
            "career": [
                {
                    "position": "Ordf. i KTH :s stud :kårs sekt. f. elektrotekn.",
                    "years": {
                        "start_year": 24,
                        "end_year": 25
                    },
                    "organization": "Kungliga Tekniska Högskolan"
                },
                {
                    "position": "Chefsass. v. kylavd. seit. 34",
                    "years": {
                        "start_year": 34,
                        "end_year": null
                    },
                    "organization": "Arctic Kylskåpsfabrik"
                },
                {
                    "position": "Styr :medl. i f oreningen 1902 års män",
                    "years": {
                        "start_year": 43,
                        "end_year": null
                    },
                    "organization": "1902 års män"
                }
            ],
            "family": {
                "spouse": null,
                "marriage_year": null,
                "children": []
            }
        },
        "1": {
            "full_name": "Brandtberg, Carl Oscar Botvid",
            "location": "Lidingö",
            "occupation": "Artist, överlärare",
            "birth_details": {
                "date": "28/07/1886",
                "place": "Sthlm"
            },
            "education": [
                {
                    "degree": "Real :ex.",
                    "year": "03",
                    "institution": null
                },
                {
                    "degree": "Tekn. sk. h. konstindustr. avd.",
                    "year": "07",
                    "institution": null
                }
            ],
            "career": [],
            "family": {
                "spouse": "Berta Andersson",
                "marriage_year": "12",
                "children": [
                    {
                        "name": "Sten Sture",
                        "birth_year": "14"
                    }
                ]
            }
        },
        "2": {
            "full_name": "Bränner, Per-Axel Helge",
            "location": "Sthlm",
            "occupation": "Regissör",
            "birth_details": {
                "date": "25/01/1899",
                "place": "Linköping"
            },
            "education": [],
            "career": [
                {
                    "position": "Regissör o. konstnärl. ledare v. Nya Teatern fr. 40",
                    "years": {
                        "start_year": 40,
                        "end_year": null
                    },
                    "organization": "Nya Teatern"
                }
            ],
            "family": {
                "spouse": "Aina Margareta Stern",
                "marriage_year": "28",
                "children": []
            }
        },
        "3": {
            "full_name": "Branting, Anna Matilda Charlotta",
            "location": "Sthlm",
            "occupation": "Författarinna",
            "birth_details": {
                "date": null,
                "place": "Sthlm"
            },
            "education": [],
            "career": [],
            "family": {
                "spouse": "statsmin. Hj. Branting",
                "marriage_year": "84",
                "children": []
            }
        },
        "4": {
            "full_name": "Branting, Georg",
            "location": "Sthlm",
            "occupation": "Advokat",
            "birth_details": {
                "date": "21/09/1887",
                "place": "Sthlm"
            },
            "education": [
                {
                    "degree": "Jur. kand.",
                    "year": "13",
                    "institution": "Sthlm"
                }
            ],
            "career": [],
            "family": {
                "spouse": "Rina Lind",
                "marriage_year": "25",
                "children": []
            }
        },
        "5": {
            "full_name": "Branting-Westerståhl, Sonja",
            "location": "Sthlm",
            "occupation": "Advokat",
            "birth_details": {
                "date": null,
                "place": "Sthlm"
            },
            "education": [
                {
                    "degree": "Jur. kand.",
                    "year": "16",
                    "institution": "Palmgrenska sk. i Sthlm"
                }
            ],
            "career": [],
            "family": {
                "spouse": "adv. Olof Westerståhl",
                "marriage_year": "14",
                "children": [
                    {
                        "name": "Hans-Jörgen",
                        "birth_year": "16"
                    }
                ]
            }
        },
        "6": {
            "full_name": "Bratt, Axel",
            "location": "Sthlm",
            "occupation": "Tandläkare",
            "birth_details": {
                "date": "17/04/1884",
                "place": "Jönköping"
            },
            "education": [
                {
                    "degree": "Stud:ex.",
                    "year": "04",
                    "institution": "Jönköping"
                },
                {
                    "degree": "Tandl:kand.",
                    "year": "06",
                    "institution": null
                }
            ],
            "career": [],
            "family": {
                "spouse": "Elsa Sundberg",
                "marriage_year": "09",
                "children": [
                    {
                        "name": "Axel Erland",
                        "birth_year": "11"
                    },
                    {
                        "name": "Sonja",
                        "birth_year": "12"
                    },
                    {
                        "name": "Lena",
                        "birth_year": "17"
                    }
                ]
            }
        },
        "7": {
            "full_name": "Bratt, Einar Olof",
            "location": "Sthlm",
            "occupation": "Överste, Byråchef",
            "birth_details": {
                "date": "09/09/1886",
                "place": "Växjö landsförs."
            },
            "education": [
                {
                    "degree": "Off:ex.",
                    "year": "08",
                    "institution": null
                }
            ],
            "career": [],
            "family": {
                "spouse": "Stina Lindgren",
                "marriage_year": "11",
                "children": []
            }
        },
        "8": {
            "full_name": "Bratt, Elsa Sofia",
            "location": "Sthlm",
            "occupation": "Tandläkare",
            "birth_details": {
                "date": null,
                "place": "Åtvidaberg, Östergötlands l."
            },
            "education": [
                {
                    "degree": "Stud:ex.",
                    "year": "03",
                    "institution": "Sthlm"
                },
                {
                    "degree": "Tandl:kand.",
                    "year": "05",
                    "institution": null
                }
            ],
            "career": [],
            "family": {
                "spouse": "Axel B.",
                "marriage_year": "09",
                "children": []
            }
        },
        "9": {
            "full_name": "Bratt, Erland Axel",
            "location": "Sthlm",
            "occupation": "Ingenjör",
            "birth_details": {
                "date": "22/03/1874",
                "place": "Göteborg"
            },
            "education": [
                {
                    "degree": "V. Gtbgs lat .-lärov.",
                    "year": null,
                    "institution": null
                },
                {
                    "degree": "Avg:ex. fr. Chalmers 98",
                    "year": "98",
                    "institution": "Chalmers"
                }
            ],
            "career": [],
            "family": {
                "spouse": "Julie Wiman",
                "marriage_year": "04",
                "children": []
            }
        },
        "10": {
            "full_name": "Bratt, Gösta",
            "location": "Sthlm",
            "occupation": "Överste",
            "birth_details": {
                "date": "14/08/1877",
                "place": "Åmål"
            },
            "education": [
                {
                    "degree": "Und :löjtn. v. Värml. reg.",
                    "year": "99",
                    "institution": null
                }
            ],
            "career": [],
            "family": {
                "spouse": "Elsa Andersson",
                "marriage_year": "11",
                "children": []
            }
        },
        "11": {
            "full_name": "Bratt, John Lennart",
            "location": "Sthlm",
            "occupation": "F. d. kammarrättsråd",
            "birth_details": {
                "date": "08/10/1893",
                "place": "Växjö"
            },
            "education": [
                {
                    "degree": "Stud:ex.",
                    "year": "12",
                    "institution": null
                },
                {
                    "degree": "Jur. kand.",
                    "year": "17",
                    "institution": null
                }
            ],
            "career": [],
            "family": {
                "spouse": "Margareta Rydeman",
                "marriage_year": "31",
                "children": [
                    {
                        "name": "John Olof Ragnar",
                        "birth_year": "32"
                    },
                    {
                        "name": "Claes Åke Henning",
                        "birth_year": "33"
                    },
                    {
                        "name": "Bengt Christian",
                        "birth_year": "40"
                    }
                ]
            }
        }
    }
}