{
    "original": "Bendix, Kurt, operakapellmästare,\nSthlm, f. 19/11/04 i Berlin av köpm.\nMax B. o. Margareta Rosenstock. G.\n35 m. skådesp :an Sally Palmblad.\nStud. v. univ. o. v. Sternsches\nKonserv, fur Musik i Berlin f. v. Fielitz,\nKlatte o. Ehrenberg samt priv. f. Max\nv. Schillings, stud. i musikhist. f. H.\nAbert. Eng. s. dirig. v. stadsoperan i\nKönigsberg 26, 28-31 v. Staatsoper i\nBerlin, lär. v. Hochschule fur Musik\n29-31. Sed. 31 anst. v. Kgl. teat. s.\nkapellm. o. kormäst. Gästdirig. m.\noperan i Oslo 34, Riga 35 samt i\norkes-terfören. i Gtbg, Gävle, Malmö o.\nNorrköp. Lett uruppf. av Stravinskis\nL’histoire d’un soldat o. Oedipus rex i\nradio. Sed. 42 lär. i operaklassen v.\nKgl. Musikhögsk.\nBendrik-Åkerström, Hildur Signe\nMaria, konsert- o. oratoriesångerska,\nSthlm, f. i Uppsala. G. 20-29 m.\nträ-v :handl. Helge Åkerström. Barn :\nAnders f. 20, Kerstin f. 25. Genomg.\nSandströmska sk., Borgarsk., Tekn.\n•sk., Operask. m. fl. Inneh. anst. v.\nRiksdaghusets statist, avd., Sthlms\nStads Arb :förmedl., sånglär :a v.\nKungsh. Normalsk. f. fl. Stud. f. Mari\nLouis Rubenson, Thure Rangström, Dr\n^Gillis Bratt. Medv. s. solist v.\nMusik-’O. Filharmoniska Sällsk :s konserter i\nSthlm 10-21 samt i Gtbg, Borås, Gävle,\nÖrebro, Malmö, Lund, Visby, Västerås,\nNorrköp, o. Östersund m. fl. städer då\nÖrat. Skapelsen, Messias, Paulus,\nÅrstiderna, Bach’s Juloratorium, Mozarts\nO-molls-Mässa m. fl. större verk uppf.\nDebut. v. Kgl. Operan 17 s. Elisabeth\ni Tannhäuser. Ett flert. egna\nkonserter bl. a. i Gustav Vasa k:a 12. Eng.\nv. Föreläsn rfören :s o.\nKammarmusik-för :s kons. i landsorten. Provsjungit\nT. Opera-Comique i Oslo o. erbj. eng.\nSolist v. Musikför :s konsert 21 i Örat.\nElias. Sångpedagog i Sthlm,\nNyköping, Östersund m. fl. städer. Styr :-\nled. i Östersunds Musiksällsk. 25.\nSolist v. ett flert. konserter därst, då bl.\na. kantater av Peterson-Berger utf.\nsamt v. Östersunds Radioinvign. 25 m.\nsolopartier ur öp. Arnljot.\n",
    "structured": {
        "1": {
            "full_name": "Bendix, Kurt",
            "location": "Sthlm",
            "occupation": "Operakapellmästare",
            "birth_details": {
                "date": "19/11/1904",
                "place": "Berlin",
                "parents": "köpm. Max B. o. Margareta Rosenstock"
            },
            "education": [
                {
                    "degree": "Stud.",
                    "year": "NULL",
                    "institution": "univ."
                },
                {
                    "degree": "Stud.",
                    "year": "NULL",
                    "institution": "Sternsches Konserv, fur Musik i Berlin f. v. Fielitz, Klatte o. Ehrenberg samt priv. f. Max v. Schillings"
                },
                {
                    "degree": "filosofie kandidat",
                    "year": "NULL",
                    "institution": "musikhist. f. H. Abert"
                }
            ],
            "career": [
                {
                    "position": "eng. s. dirig.",
                    "years": {
                        "start_year": 1926,
                        "end_year": 1931
                    },
                    "organization": "stadsoperan i Königsberg"
                },
                {
                    "position": "lär.",
                    "years": {
                        "start_year": 1929,
                        "end_year": 1931
                    },
                    "organization": "Hochschule fur Musik"
                },
                {
                    "position": "anst. v. Kgl. teat. s. kapellm. o. kormäst.",
                    "years": {
                        "start_year": 1931,
                        "end_year": "NULL"
                    },
                    "organization": "Kgl. teat."
                },
                {
                    "position": "lär.",
                    "years": {
                        "start_year": 1942,
                        "end_year": "NULL"
                    },
                    "organization": "Kgl. Musikhögsk."
                }
            ],
            "family": {
                "spouse": "Sally Palmblad",
                "marriage_year": "1935",
                "children": []
            }
        },
        "2": {
            "full_name": "Bendrik-Åkerström, Hildur Signe Maria",
            "location": "Sthlm",
            "occupation": "Konsert- o. oratoriesångerska",
            "birth_details": {
                "date": "NULL",
                "place": "Uppsala",
                "parents": "NULL"
            },
            "education": [
                {
                    "degree": "NULL",
                    "year": "NULL",
                    "institution": "Sandströmska sk., Borgarsk., Tekn. sk., Operask."
                }
            ],
            "career": [
                {
                    "position": "solist v. Musik-’O. Filharmoniska Sällsk :s konserter",
                    "years": {
                        "start_year": 1910,
                        "end_year": 1921
                    },
                    "organization": "Sthlm"
                },
                {
                    "position": "solist v. Musikför ",
                    "years": {
                        "start_year": 1921,
                        "end_year": "NULL"
                    },
                    "organization": "konsert"
                },
                {
                    "position": "Sångpedagog",
                    "years": {
                        "start_year": "NULL",
                        "end_year": "NULL"
                    },
                    "organization": "Sthlm, Nyköping, Östersund m. fl. städer"
                }
            ],
            "family": {
                "spouse": "Helge Åkerström",
                "marriage_year": "1929",
                "children": [
                    {
                        "name": "Anders",
                        "birth_year": "1920"
                    },
                    {
                        "name": "Kerstin",
                        "birth_year": "1925"
                    }
                ]
            }
        }
    }
}