{
    "original": "Bodemar, Sven Harry Gösta,\nkyrkoadjunkt, Lilla Essingen, f. 12/7/05 i\nRonneby av dr Harry Bengtson o. Lina\nLarsson. G. 37 m. Dagny Alice Cecilia\nFredlund. Barn: Per Hjalmar\nStaffan, f. 39, Per Sven Göran o. Per Finn\nGösta ff. 41. Studrex. i Lund 24,\nfil. kand. 30, teol. kand. 37, prakt. teol.\nprov 37, pv. f. Lunds stift 37, v. past.\ni Bosjökloster, v. komm. i Mjällby, v.\npast. i Billeberga, pastoratsadj. i\nLund, v. komm. därst., kyrkoadj., v.\nkyrkoadj. i S :ta Clara f s. i Sthlm 41,\nv. komm. i S :t Göran, i Sofia, v.\nkyrkoadj. i Hedvig Eleonora, kyrkoadj. i\nBromma 43. Tjänstgj. som pred. v.\nOrups sanat. o. v. ö. sjukh. i Malm.\nKårch. i Lunds scoutkår 39-41, sekr. i\nLandsförb. f. arbetslösh :s\nbekämpande sed. 41.\nBodin, Carl Gösta, skådespelare,\nRå-sunda, f. 27/4/97 i Sala av\növerkonstapel Erik B. o. Augusta Stjernblad.\nG. 32 m. sångerskan Elsie Borgman\n(artistnamn: Borg). Bör j. teaterban.\nh. Bror Hallberg 13, eng. h. Axel\nBergman 13, v. Oscarsteat. 16, Apolloteat.\ni Hfors 17, h. Karin Swanström 18-19,\nv. Mosebacketeat. 19-23. Dessutom v.\nolika cabareter, bl. a. Svarta Katten.\nDelt. i ett flert. turnéer i Sverige o.\nFinl. Bl. roll.: Boni i\nCsårdåsfurstin-nan, Pater Maximim i Dockan, Jonas\ni Lars Anders o. Jan Anders samt\nderas barn, Curt i Ära, Kellerman i\nGamla Heidelberg Smålands-Kalle i\nRallare. Medv. i ett flert. filmer.\nBodin, Martin L. O., filmfotograf,\nSthlm, f. 23/9/03 i Klintehamn, Gotl.\nL G. m. Greta Andersson. Barn:\nLars-Anders f. 36. Utfört\nfilminspelning i Frankr., Finl., Danm. o. Norge.\nVerksam som inspelningsfotograf v.\nA-B Sv. Filmindustris ateljéer i\nFilmstaden, Råsunda. Upptagit bl. a. följ.\nfilmer: Valborgsmässoafton, Konflikt,\nAdolf Armstarke, Den stora kärleken,\nKadettkamrater, Lärarinna på vift,\nKlockan på Rönneberga, Excellensen,\nHets. Medl. av Fotograf. Fören.,\nFotoklubb., Fören. Svenska Filmtekniker.\n",
    "structured": {
        "1": {
            "full_name": "Bodemar, Sven Harry Gösta",
            "location": "Lilla Essingen",
            "occupation": "kyrkoadjunkt",
            "birth_details": {
                "date": "12/07/1905",
                "place": "Ronneby",
                "parents": "dr Harry Bengtson and Lina Larsson"
            },
            "education": [
                {
                    "degree": "Studrex.",
                    "year": "1924",
                    "institution": "Lund"
                },
                {
                    "degree": "filosofie kandidat",
                    "year": "1930",
                    "institution": "Lund"
                },
                {
                    "degree": "teol. kand.",
                    "year": "1937",
                    "institution": "NULL"
                }
            ],
            "career": [
                {
                    "position": "pv. f. Lunds stift",
                    "years": {
                        "start_year": 1937,
                        "end_year": 1937
                    },
                    "organization": "NULL"
                },
                {
                    "position": "v. past. i Bosjökloster",
                    "years": {
                        "start_year": 1937,
                        "end_year": 1937
                    },
                    "organization": "NULL"
                },
                {
                    "position": "v. komm. i Mjällby",
                    "years": {
                        "start_year": 1937,
                        "end_year": 1937
                    },
                    "organization": "NULL"
                },
                {
                    "position": "v. past. i Billeberga",
                    "years": {
                        "start_year": 1937,
                        "end_year": 1937
                    },
                    "organization": "NULL"
                },
                {
                    "position": "pastoratsadj. i Lund",
                    "years": {
                        "start_year": 1937,
                        "end_year": 1937
                    },
                    "organization": "NULL"
                },
                {
                    "position": "v. komm. därst.",
                    "years": {
                        "start_year": 1937,
                        "end_year": 1937
                    },
                    "organization": "NULL"
                },
                {
                    "position": "kyrkoadj.",
                    "years": {
                        "start_year": 1941,
                        "end_year": 1941
                    },
                    "organization": "S :ta Clara"
                },
                {
                    "position": "v. komm. i S :t Göran",
                    "years": {
                        "start_year": 1941,
                        "end_year": 1941
                    },
                    "organization": "NULL"
                },
                {
                    "position": "v. komm. i Sofia",
                    "years": {
                        "start_year": 1941,
                        "end_year": 1941
                    },
                    "organization": "NULL"
                },
                {
                    "position": "kyrkoadj. i Hedvig Eleonora",
                    "years": {
                        "start_year": 1941,
                        "end_year": 1941
                    },
                    "organization": "NULL"
                },
                {
                    "position": "kyrkoadj. i Bromma",
                    "years": {
                        "start_year": 1943,
                        "end_year": 1943
                    },
                    "organization": "NULL"
                },
                {
                    "position": "tjänstgj. som pred. v. Orups sanat. o. v. ö. sjukh. i Malm",
                    "years": {
                        "start_year": 1943,
                        "end_year": 1943
                    },
                    "organization": "NULL"
                }
            ],
            "family": {
                "spouse": "Dagny Alice Cecilia Fredlund",
                "marriage_year": "1937",
                "children": [
                    {
                        "name": "Per Hjalmar Staffan",
                        "birth_year": "1939"
                    },
                    {
                        "name": "Per Sven Göran",
                        "birth_year": "NULL"
                    },
                    {
                        "name": "Per Finn Gösta",
                        "birth_year": "1941"
                    }
                ]
            }
        },
        "2": {
            "full_name": "Bodin, Carl Gösta",
            "location": "Råsunda",
            "occupation": "skådespelare",
            "birth_details": {
                "date": "27/04/1897",
                "place": "Sala",
                "parents": "överkonstapel Erik B. and Augusta Stjernblad"
            },
            "family": {
                "spouse": "Elsie Borgman (artistnamn: Borg)",
                "marriage_year": "1932",
                "children": []
            }
        },
        "3": {
            "full_name": "Bodin, Martin L. O.",
            "location": "Sthlm",
            "occupation": "filmfotograf",
            "birth_details": {
                "date": "23/09/1903",
                "place": "Klintehamn, Gotl."
            },
            "family": {
                "spouse": "Greta Andersson",
                "marriage_year": "NULL",
                "children": [
                    {
                        "name": "Lars-Anders",
                        "birth_year": "1936"
                    }
                ]
            }
        }
    }
}