{
    "original": "ANDERSSON, SVEN G R, direktör,\n\nMalmö, f i Lund 30/10/29 av stat:mäst\nEmanuel A o Hilma Malmros.\nRealex Malmö 46, kont ab Agerkemiska\nverken Malmö 46, ab Malmö fören\nbryggerier 50, kamr Vattenfabr ab Kronan\n56, verkst dir ab Skända sed 60. - Hobby:\nfilateli.\n\nGift 53 m Anna-Greta Kjellander f 26,\ndtr t montör Erik K o Elsa Thelander.\n\n- Barn: Mats f 55, Leif f 59.\n\n3 ska\n\nANDERSSON, SVEN H S, docent,\nlektor, Halmstad, f i Riseberga, Krist l,\n27/10/22 av jv:tjm C A A o A S\nJohansson.\n\nStud:ex Hbg 41, fil kand o fil mag 45,\nfil lic 50 o fil dr Lund 54; l:e aman\nromanska inst Lunds univ 48-50, doc i\nromanska språk sed 54, tf prof periodv\n55-58. - Lekt i franska hal Halmstad sed\n63. - Skr: Etudes sur la syntaxe et la\nsémantique du mot fran?ais tout\n(drsavh 54) m fi vetensk arb.\nGift 53 m fil mag Ingrid Jönsson f 23,\ndtr t f är j ef or A V J o Ida Magnusson.\n-Barn: Lars f 57, Birgitta f 60.\n\nANDERSSON, SVEN-ERIK G, tekn\nlic, civilingenjör SVR, Hittarp, f i Hbg\n18/5/25 av mek Samuel A o Signe\nSvensson.\n\nCTH 50, tekn lic 52; l:e ass\nbyggn:-statik CTH 50-53, spec :lär i\njärnbygg-nadslära där 53-54, konstr Prof S O\nAsplunds konsultbyrå 53-54, lekt i\nbyggnadsteknik HTL Karlskrona 54-60, eg\nkon-sultverks’amh 54-59, konsult Ing :firman\nJacobson &amp; Widmark ab sed 59, deläg o\nstyr:led sed 64. - Medl SKIF. - Fullm:led\nSVR 50-60, ordf Blek tekn fören 58-59.\n-Hobby: golf.\n\nGift 50 m Lii Rittsel f 23, dtr t vävmäst\nGustav R o Linnea Ahlgren. - Barn:\nEva f 54, Ann-Lii f 64.\n\n",
    "structured": {
        "0": {
            "full_name": "Sven G R Andersson",
            "location": "Malmö",
            "occupation": "direktör",
            "birth_details": {
                "date": "30/10/1929",
                "place": "Lund",
                "parents": "stat:mäst Emanuel A o Hilma Malmros"
            },
            "education": [
                {
                    "degree": "Realex",
                    "year": "1946",
                    "institution": "Malmö"
                }
            ],
            "career": [
                {
                    "position": "verkst dir",
                    "years": {
                        "start_year": 1960,
                        "end_year": null
                    },
                    "organization": "ab Skända"
                }
            ],
            "family": {
                "spouse": "Anna-Greta Kjellander",
                "marriage_year": "1953",
                "children": [
                    {
                        "name": "Mats",
                        "birth_year": "1955"
                    },
                    {
                        "name": "Leif",
                        "birth_year": "1959"
                    }
                ]
            },
            "hobbies": [
                "filateli"
            ]
        },
        "1": {
            "full_name": "Sven H S Andersson",
            "location": "Halmstad",
            "occupation": "docent, lektor",
            "birth_details": {
                "date": "27/10/1922",
                "place": "Riseberga, Kristianstad l",
                "parents": "jv:tjm C A A o A S Johansson"
            },
            "education": [
                {
                    "degree": "Stud:ex",
                    "year": "1941",
                    "institution": "Hbg"
                },
                {
                    "degree": "fil kand",
                    "year": "1945",
                    "institution": null
                },
                {
                    "degree": "fil mag",
                    "year": "1945",
                    "institution": null
                },
                {
                    "degree": "fil lic",
                    "year": "1950",
                    "institution": "Lunds univ"
                },
                {
                    "degree": "fil dr",
                    "year": "1954",
                    "institution": "Lund"
                }
            ],
            "career": [
                {
                    "position": "l:e aman",
                    "years": {
                        "start_year": 1948,
                        "end_year": 1950
                    },
                    "organization": "romanska inst Lunds univ"
                },
                {
                    "position": "doc i romanska språk",
                    "years": {
                        "start_year": 1954,
                        "end_year": null
                    },
                    "organization": null
                },
                {
                    "position": "tf prof",
                    "years": {
                        "start_year": 1955,
                        "end_year": 1958
                    },
                    "organization": "periodv"
                },
                {
                    "position": "Lekt i franska",
                    "years": {
                        "start_year": 1963,
                        "end_year": null
                    },
                    "organization": "Halmstad"
                }
            ],
            "family": {
                "spouse": "fil mag Ingrid Jönsson",
                "marriage_year": "1953",
                "children": [
                    {
                        "name": "Lars",
                        "birth_year": "1957"
                    },
                    {
                        "name": "Birgitta",
                        "birth_year": "1960"
                    }
                ]
            }
        },
        "2": {
            "full_name": "Sven-Erik G Andersson",
            "location": "Hittarp",
            "occupation": "tekn lic, civilingenjör SVR",
            "birth_details": {
                "date": "18/5/1925",
                "place": "Hbg",
                "parents": "mek Samuel A o Signe Svensson"
            },
            "education": [
                {
                    "degree": null,
                    "year": "1950",
                    "institution": "CTH"
                },
                {
                    "degree": "tekn lic",
                    "year": "1952",
                    "institution": null
                }
            ],
            "career": [
                {
                    "position": "l:e ass",
                    "years": {
                        "start_year": 1950,
                        "end_year": 1953
                    },
                    "organization": "byggn:-statik CTH"
                },
                {
                    "position": "spec :lär",
                    "years": {
                        "start_year": 1953,
                        "end_year": 1954
                    },
                    "organization": "järnbygg-nadslära"
                },
                {
                    "position": "lekt",
                    "years": {
                        "start_year": 1954,
                        "end_year": 1960
                    },
                    "organization": "byggnadsteknik HTL Karlskrona"
                },
                {
                    "position": "eg konsultverks'amh",
                    "years": {
                        "start_year": 1954,
                        "end_year": 1959
                    },
                    "organization": null
                },
                {
                    "position": "konsult",
                    "years": {
                        "start_year": 1959,
                        "end_year": null
                    },
                    "organization": "Ing :firman Jacobson & Widmark ab"
                }
            ],
            "family": {
                "spouse": "Lii Rittsel",
                "marriage_year": "1950",
                "children": [
                    {
                        "name": "Eva",
                        "birth_year": "1954"
                    },
                    {
                        "name": "Ann-Lii",
                        "birth_year": "1964"
                    }
                ]
            },
            "hobbies": [
                "golf"
            ]
        }
    }
}