{
    "original": "AHLBERG, ALBERT N, med dr, fd\növerläkare, Apelviksstrand, f i Vollsjö,\nMalmöh l, 23/5/99 av dir Otto A o\nHilda Svensson.\n\nMed kand Lund 23, med lic 29, med dr\n40; underläk ortoped avd Malmö 29-32,\nröntgenavd 32-33, kir avd där 33-35,\nunderläk kir avd Västerås 35-37, l :e\nunderläk Vanföreanst Gbg 37-39, l:e underläk\n39-40 o överläk Apelvikens kustsanat\nsed 41 (tf 40). - Skr ett flertal arb i\nortoped ämnen samt drsavh om\ncalca-neusfrakturer. - Utm: KNO, RDDOlgr,\nRFinlLOlkl, PatrSstGM, FrdelaSp,\nNFrK, ChX:sFrM, FinlRKBM, FMpbh.\nGift 29 m Frida Engström f 00, dtr t\nköpm Carl E o Emilia Carlsdotter.\n-Barn: Gerd f 32, Anita f 37.\n\nAHLBERG,    ALF    U,   distriktschef,\n\nÄngelholm,   f   i   Halmstad   27/3/37   av\n\nGeorg A o Gudrun Larsson.\n\nAnst ing :firma Lundwall o Co Malmö\n\n60, ch ab Facits försäljn :kont f nordv\n\nSkåne  Ängelholm   sed   61.   -  Hobbies:\n\nfiske, bridge.\n\nGift 61   m Elsa Karlsson f 40,  dtr t\n\nGustav K o Ebba K. - Barn: Thomas\n\nf 64.\n\nAHLBERG,   BO  M,  teol  dr,  docent,\n\nLund, f i Surteby, Älvsb l, 2/10/25 av\nprost Gustaf A o Ella Gerle.\nStud:ex Halmstad 45, fil kand Lund 50,\nteol kand 57, teol lic 60, teol dr 64, doc\ni dogmatik m symbolik Lund sed 64.\n-Skr: Laurentius Petris\nnattvardsuppfattning (drsavh 64).\n\nGift 52 m Gunborg Holm f 27, dtr t\nprost Hjalmar H o Olga Tunér. - Barn:\nAnders f 55, Tomas f 58, Peter f 62.\n\n",
    "structured": {
        "0": {
            "full_name": "Albert N Ahlberg",
            "location": "Apelviksstrand",
            "occupation": "fd överläkare",
            "birth_details": {
                "date": "23/05/1899",
                "place": "Vollsjö"
            },
            "education": [
                {
                    "degree": "med dr",
                    "year": "1940",
                    "institution": "Lund"
                },
                {
                    "degree": "med lic",
                    "year": "1929",
                    "institution": "Lund"
                },
                {
                    "degree": "med kand",
                    "year": "1923",
                    "institution": "Lund"
                }
            ],
            "career": [
                {
                    "position": "tf överläk",
                    "years": {
                        "start_year": 1940,
                        "end_year": 1941
                    },
                    "organization": "Apelvikens kustsanat"
                },
                {
                    "position": "l:e underläk",
                    "years": {
                        "start_year": 1939,
                        "end_year": 1940
                    },
                    "organization": "Apelvikens kustsanat"
                },
                {
                    "position": "l:e underläk",
                    "years": {
                        "start_year": 1937,
                        "end_year": 1939
                    },
                    "organization": "Vanföreanst Gbg"
                },
                {
                    "position": "underläk kir avd",
                    "years": {
                        "start_year": 1935,
                        "end_year": 1937
                    },
                    "organization": "Västerås"
                },
                {
                    "position": "kir avd",
                    "years": {
                        "start_year": 1933,
                        "end_year": 1935
                    },
                    "organization": "Malmö"
                },
                {
                    "position": "röntgenavd",
                    "years": {
                        "start_year": 1932,
                        "end_year": 1933
                    },
                    "organization": "Malmö"
                },
                {
                    "position": "underläk ortoped avd",
                    "years": {
                        "start_year": 1929,
                        "end_year": 1932
                    },
                    "organization": "Malmö"
                }
            ],
            "family": {
                "spouse": "Frida Engström",
                "marriage_year": "1929",
                "children": [
                    {
                        "name": "Gerd",
                        "birth_year": "1932"
                    },
                    {
                        "name": "Anita",
                        "birth_year": "1937"
                    }
                ]
            }
        },
        "1": {
            "full_name": "Alf U Ahlberg",
            "location": "Ängelholm",
            "occupation": "distriktschef",
            "birth_details": {
                "date": "27/03/1937",
                "place": "Halmstad"
            },
            "career": [
                {
                    "position": "ch ab Facits försäljn :kont",
                    "years": {
                        "start_year": 1961
                    },
                    "organization": "nordv Skåne Ängelholm"
                },
                {
                    "position": "anst",
                    "years": {
                        "start_year": 1960
                    },
                    "organization": "firma Lundwall o Co Malmö"
                }
            ],
            "family": {
                "spouse": "Elsa Karlsson",
                "marriage_year": "1961",
                "children": [
                    {
                        "name": "Thomas",
                        "birth_year": "1964"
                    }
                ]
            },
            "hobbies": [
                "fiske",
                "bridge"
            ]
        },
        "2": {
            "full_name": "Bo M Ahlberg",
            "location": "Lund",
            "occupation": "teol dr, docent",
            "birth_details": {
                "date": "02/10/1925",
                "place": "Surteby, Älvsb l"
            },
            "education": [
                {
                    "degree": "teol dr",
                    "year": "1964",
                    "institution": "Lund"
                },
                {
                    "degree": "teol lic",
                    "year": "1960",
                    "institution": "Lund"
                },
                {
                    "degree": "teol kand",
                    "year": "1957",
                    "institution": "Lund"
                },
                {
                    "degree": "fil kand",
                    "year": "1950",
                    "institution": "Lund"
                },
                {
                    "degree": "stud:ex",
                    "year": "1945",
                    "institution": "Halmstad"
                }
            ],
            "career": {
                "position": "doc i dogmatik m symbolik",
                "years": {
                    "start_year": 1964
                },
                "organization": "Lund"
            },
            "family": {
                "spouse": "Gunborg Holm",
                "marriage_year": "1952",
                "children": [
                    {
                        "name": "Anders",
                        "birth_year": "1955"
                    },
                    {
                        "name": "Tomas",
                        "birth_year": "1958"
                    },
                    {
                        "name": "Peter",
                        "birth_year": "1962"
                    }
                ]
            }
        }
    }
}