{
    "original": "ANDERSSON, OVE G, stadsingenjör,\n\nSölvesborg, f i Malmö 17/12/13 av\nguld-sm J A A o Olga Hansson.\nHTL Malmö 34, CTH 39, konsult ing\nElof Frändbergs ing :byrå 39, ing Malmö\nstads vatten- o avloppsverk 40,\nstadsing:-kont Lund 43, l:e avd :ing byggn :kont\nLund 47, stadsing o byggn :ch Sölvesborg\nsed 48. - Verkst dir ab Lister landets\ncentraltvätt sed 50. - Medl Odd Fellow,\nRo-tary. - Hobbies: foto, fiske, schack.\nGift 43 m Maj Lundqvist f 16, dtr t\njv:-kont Ernst L o Elsa Gehlin. - Barn:\nMarianne f 46, Bo f 50.\n\nANDERSSON,   PER-ERIK,   direktör,\n\nBromölla, f i Bromölla, Krist l, 5/6/22\nav dir Anton A o Ester Eriksson.\nStud:ex Kristianstad 41, hdlsgymn Hbg\n42, res:off:ex T 4; dir o inneh Bröd\nAndersson ab sed 60. - Medl Rotary, Odd\nFellow. - Hobbies: jakt, fiske, sport.\nGift 49 m Birgitta Wendt f 26, dtr t\nRickard W o Martha Richter. - Barn:\nUlla f 49, Karin f 51, Lars f 53.\n\nANDERSON,    ROLF    H,    advokat,\n\nLandskrona, f i Malmö 25/11/17 av\npostass Hugo A o Margareta Klauck.\nStud:ex Landskrona 37, res:off:ex 39, jur\nkand Lund 49, tingstjg Ö Medelsta doms\n49-52, tjg Rättshj :anst Hbg 52-53, bitr jur\nErik Dunérs adv :byrå Lund sed 53.\n-LSA 56. - Kapt i res 53. - Medl FrimO.\n\n- Hobby: filateli.\n\nGift 60 m Sonia Svensson f 37, dtr t\nHjalmar S o Valborg Johansson. - Barn:\nJohan f 62, Margareta f 65.\n\nANDERSSON, ROLF L, assessor,\nMalmö, f i Drammen, Norge, 31/12/21 av\nköpm Gunnar A o Ingeborg Lund.\nStud:ex 45 o jur kand Lund 50, tingstjg\nTveta, Vista o Mo 50-52, fiskal Göta\nhovr 53, tf assess rådhusr Malmö 53,\nassess där sed 63. - l:e stadsfogde\nMalmö 59. - Sekr komm f översyn av\nMalmö stads centr kommunalförvaltn 59-60.\nGift 57 m småskollär Inger Cardell f 30.\n\n-  Barn: Lars Olaf f 60, Mari f 64.\n\n",
    "structured": {
        "0": {
            "full_name": "OVE G ANDERSSON",
            "location": "Sölvesborg",
            "occupation": "Stadsingenjör",
            "birth_details": {
                "date": "17/12/1913",
                "place": "Malmö",
                "parents": "Guld-sm J A A o Olga Hansson"
            },
            "education": [
                {
                    "degree": "HTL",
                    "year": "1934",
                    "institution": "Malmö"
                },
                {
                    "degree": "CTH",
                    "year": "1939",
                    "institution": "konsult ing Elof Frändbergs ing :byrå"
                }
            ],
            "career": [
                {
                    "position": "Konsult ing",
                    "years": {
                        "start_year": 1939,
                        "end_year": 1940
                    },
                    "organization": "Elof Frändbergs ing :byrå"
                },
                {
                    "position": "Ing Malmö stads vatten- o avloppsverk",
                    "years": {
                        "start_year": 1940,
                        "end_year": 1943
                    }
                },
                {
                    "position": "L:e avd :ing byggn :kont Lund",
                    "years": {
                        "start_year": 1943,
                        "end_year": 1947
                    },
                    "organization": "byggn :kont Lund"
                },
                {
                    "position": "Stadsing o byggn :ch Sölvesborg",
                    "years": {
                        "start_year": 1948
                    }
                },
                {
                    "position": "Verkst dir",
                    "years": {
                        "start_year": 1950
                    },
                    "organization": "ab Lister landets centraltvätt"
                }
            ],
            "family": {
                "spouse": "Maj Lundqvist",
                "marriage_year": "1943",
                "children": [
                    {
                        "name": "Marianne",
                        "birth_year": "1946"
                    },
                    {
                        "name": "Bo",
                        "birth_year": "1950"
                    }
                ]
            },
            "hobbies": [
                "foto",
                "fiske",
                "schack"
            ]
        },
        "1": {
            "full_name": "PER-ERIK ANDERSSON",
            "location": "Bromölla",
            "occupation": "Direktör",
            "birth_details": {
                "date": "5/6/1922",
                "place": "Bromölla, Kristianstad l"
            },
            "education": [
                {
                    "degree": "Stud:ex",
                    "year": "1941",
                    "institution": "Kristianstad"
                },
                {
                    "degree": "Hdlsgymn",
                    "year": "1942",
                    "institution": "Hbg"
                }
            ],
            "career": [
                {
                    "position": "Dir o inneh",
                    "years": {
                        "start_year": 1960
                    },
                    "organization": "Bröd Andersson ab"
                }
            ],
            "family": {
                "spouse": "Birgitta Wendt",
                "marriage_year": "1949",
                "children": [
                    {
                        "name": "Ulla",
                        "birth_year": "1949"
                    },
                    {
                        "name": "Karin",
                        "birth_year": "1951"
                    },
                    {
                        "name": "Lars",
                        "birth_year": "1953"
                    }
                ]
            },
            "hobbies": [
                "jakt",
                "fiske",
                "sport"
            ]
        },
        "2": {
            "full_name": "ROLF H ANDERSON",
            "location": "Landskrona",
            "occupation": "Advokat",
            "birth_details": {
                "date": "25/11/1917",
                "place": "Malmö"
            },
            "education": [
                {
                    "degree": "Stud:ex",
                    "year": "1937",
                    "institution": "Landskrona"
                },
                {
                    "degree": "Jur kand",
                    "year": "1949",
                    "institution": "Lund"
                }
            ],
            "career": [
                {
                    "position": "Tingstjg",
                    "years": {
                        "start_year": 1949,
                        "end_year": 1952
                    },
                    "organization": "Ö Medelsta doms"
                },
                {
                    "position": "Tjg Rättshj :anst",
                    "years": {
                        "start_year": 1952,
                        "end_year": 1953
                    },
                    "organization": "Hbg"
                },
                {
                    "position": "Bitr jur",
                    "organization": "Erik Dunérs adv :byrå",
                    "years": {
                        "start_year": 1953
                    }
                }
            ],
            "family": {
                "spouse": "Sonia Svensson",
                "marriage_year": "1960",
                "children": [
                    {
                        "name": "Johan",
                        "birth_year": "1962"
                    },
                    {
                        "name": "Margareta",
                        "birth_year": "1965"
                    }
                ]
            },
            "hobbies": [
                "filateli"
            ]
        },
        "3": {
            "full_name": "ROLF L ANDERSSON",
            "location": "Malmö",
            "occupation": "Assessor",
            "birth_details": {
                "date": "31/12/1921",
                "place": "Drammen, Norge"
            },
            "education": [
                {
                    "degree": "Stud:ex",
                    "year": "1945"
                },
                {
                    "degree": "Jur kand",
                    "year": "1950",
                    "institution": "Lund"
                }
            ],
            "career": [
                {
                    "position": "Tingstjg",
                    "years": {
                        "start_year": 1950,
                        "end_year": 1952
                    },
                    "organization": "Tveta, Vista o Mo"
                },
                {
                    "position": "Fiskal",
                    "years": {
                        "start_year": 1953
                    },
                    "organization": "Göta hovr"
                },
                {
                    "position": "Tf assess rådhusr",
                    "years": {
                        "start_year": 1953
                    },
                    "organization": "Malmö"
                },
                {
                    "position": "Assess",
                    "years": {
                        "start_year": 1963
                    },
                    "organization": "Malmö"
                }
            ],
            "family": {
                "spouse": "Inger Cardell",
                "marriage_year": "1957",
                "children": [
                    {
                        "name": "Lars Olaf",
                        "birth_year": "1960"
                    },
                    {
                        "name": "Mari",
                        "birth_year": "1964"
                    }
                ]
            }
        }
    }
}