{
    "original": "ANDERSSON,    OLLE   A,   ingenjör,\n\nMalmö, f i  Malmö  3/12/24 av verkm\nCarl A o Vera Nyman.\nNKI-sk  51,   Malmö  stads  yrkessk  52;\nkont   Skoogs   elektr  ab   Malmö   39-42,\nelektr Elektr ab AEG 43-47, Malmö\nelverk 48-50, montageing Sv Siemens ab\nsed 50. - Ordf SEF Malmö.\nGift 54 m Siv Ekström f 26, dtr t l:e\nverkm Axel E o Nanny Nilsson. - Barn:\nPer f 60.\n\nANDERSSON, O (OLLE) I, revisor,\n\nKristianstad, f i Göteve, Skarab l, 5/12/\n34 av lagerarb Arthur A o Signe\nAronsson.\n\nRealex NKI 54, banktjm 54-62,\nreserevisor Sv:es jordbr:kasseförb sed 63. -\nHobby: filateli.\n\nGift 60 m Gunnel Gustafsson f 37, dtr t\nåk :äg Arthur G o Gertrud Palmquist.\n-Barn: Claes f 6&gt;2, Magnus f 65&lt;\n\nANDERSSON,   S  A  OLOF  (OLLE),\n\nsjukhusintendent, Trelleborg, f i\nVärnamo 13/9/27 av byggm John A o Hanna\nSkog.\n\nDSI Lund 53, sjh :kameral ex 54; sjh:ass\nlänslas Värnamo 48, sjh :intend Jönkpgs l\nlandst sjv:inrättn Vetlanda 55, länslas\nTrelleborg sed 64. - Fd nämndem\nVetlanda. - Medl FrimO. - Skr: art i\nfack-tidskr. - Hobbies: sport, fiske, konst.\nGift 52 m Gudrun Frank f 26, dtr t\nverkm Albin F o Anna Lantz. - Barn:\nLeif f 53, Peter f 64.\n\nANDERSSON, A OVE, civilekonom,\n\nkamrer, Svalöv, f i Lund 11/6/29 av\nlantbr Hugo A o Hanna Persson.\"\nStud:ex 49, DHS 54, kamr Allm sv\nutsädes ab Svalöv sed 54. - Styr:led\nFastigh ab Svalöv, Per Bondessons lantbr\nab . - Kronoomb i tax:nd. - Löjtn P 7\nres. - Utm: Malmöh l civilförsv:förb\nSplak. - Hobbies: bridge, tennis.\nGift 54 m Julia Andersson, dtr t Konrad\nA o Ida Bergström. - Barn: Margareta\nf 54, Jan f 59.\n\n",
    "structured": {
        "1": {
            "full_name": "Olle A Andersson",
            "location": "Malmö",
            "occupation": "Ingenjör",
            "birth_details": {
                "date": "03/12/1924",
                "place": "Malmö"
            },
            "education": [
                {
                    "degree": "NKI-sk",
                    "year": "1951",
                    "institution": "NKI-sk"
                },
                {
                    "degree": "Malmö stads yrkessk",
                    "year": "1952",
                    "institution": "Malmö stads yrkessk"
                }
            ],
            "career": [
                {
                    "position": "Kont",
                    "years": {
                        "start_year": 1939,
                        "end_year": 1942
                    },
                    "organization": "Skoogs elektr ab Malmö"
                },
                {
                    "position": "Elektr",
                    "years": {
                        "start_year": 1943,
                        "end_year": 1947
                    },
                    "organization": "Elektr ab AEG"
                },
                {
                    "position": "Malmö elverk",
                    "years": {
                        "start_year": 1948,
                        "end_year": 1950
                    },
                    "organization": "Malmö elverk"
                },
                {
                    "position": "Montageing",
                    "years": {
                        "start_year": 1950
                    },
                    "organization": "Sv Siemens ab"
                }
            ],
            "family": {
                "spouse": "Siv Ekström",
                "marriage_year": "1954",
                "children": [
                    {
                        "name": "Per",
                        "birth_year": "1960"
                    }
                ]
            }
        },
        "2": {
            "full_name": "O I Andersson",
            "location": "Kristianstad",
            "occupation": "Revisor",
            "birth_details": {
                "date": "05/12/1934",
                "place": "Göteve, Skarab l"
            },
            "education": [
                {
                    "degree": "Realex NKI",
                    "year": "1954",
                    "institution": "NKI"
                }
            ],
            "career": [
                {
                    "position": "Banktjm",
                    "years": {
                        "start_year": 1954,
                        "end_year": 1962
                    }
                },
                {
                    "position": "Reserevisor",
                    "years": {
                        "start_year": 1963
                    },
                    "organization": "Sv:es jordbr:kasseförb"
                }
            ],
            "family": {
                "spouse": "Gunnel Gustafsson",
                "marriage_year": "1960",
                "children": [
                    {
                        "name": "Claes",
                        "birth_year": "1962"
                    },
                    {
                        "name": "Magnus",
                        "birth_year": "1965"
                    }
                ]
            },
            "hobbies": [
                "Filateli"
            ]
        },
        "3": {
            "full_name": "S A Olof Andersson",
            "location": "Trelleborg",
            "occupation": "Sjukhusintendent",
            "birth_details": {
                "date": "13/09/1927",
                "place": "Värnamo"
            },
            "education": [
                {
                    "degree": "DSI Lund",
                    "year": "1953",
                    "institution": "Lund"
                }
            ],
            "career": [
                {
                    "position": "Sjh:ass länslas",
                    "years": {
                        "start_year": 1955
                    },
                    "organization": "Värnamo"
                },
                {
                    "position": "Sjh:intend Jönkpgs l landst",
                    "years": {
                        "start_year": 1955
                    }
                },
                {
                    "position": "Länslas Trelleborg",
                    "years": {
                        "start_year": 1964
                    }
                }
            ],
            "family": {
                "spouse": "Gudrun Frank",
                "marriage_year": "1952",
                "children": [
                    {
                        "name": "Leif",
                        "birth_year": "1953"
                    },
                    {
                        "name": "Peter",
                        "birth_year": "1964"
                    }
                ]
            },
            "community_involvement": [
                {
                    "role": "Nämndem",
                    "organization": "Vetlanda",
                    "years": "NULL"
                }
            ],
            "hobbies": [
                "Sport",
                "Fiske",
                "Konst"
            ]
        },
        "4": {
            "full_name": "A Ove Andersson",
            "location": "Svalöv",
            "occupation": "Civilekonom, Kamrer",
            "birth_details": {
                "date": "11/06/1929",
                "place": "Lund"
            },
            "education": [
                {
                    "degree": "Stud:ex",
                    "year": "1949",
                    "institution": "NULL"
                },
                {
                    "degree": "DHS",
                    "year": "1954",
                    "institution": "NULL"
                }
            ],
            "career": [
                {
                    "position": "Kamr Allm sv utsädes ab",
                    "years": {
                        "start_year": 1954
                    },
                    "organization": "Svalöv"
                }
            ],
            "family": {
                "spouse": "Julia Andersson",
                "marriage_year": "1954",
                "children": [
                    {
                        "name": "Margareta",
                        "birth_year": "1954"
                    },
                    {
                        "name": "Jan",
                        "birth_year": "1959"
                    }
                ]
            },
            "board_memberships": [
                {
                    "position": "Styr:led",
                    "organization": "Fastigh ab Svalöv",
                    "years": "NULL"
                },
                {
                    "position": "Styr:led",
                    "organization": "Per Bondessons lantbr ab",
                    "years": "NULL"
                }
            ],
            "honorary_titles": [
                {
                    "title": "Kronoomb i tax:nd",
                    "institution": "NULL",
                    "year": "NULL"
                }
            ],
            "hobbies": [
                "Bridge",
                "Tennis"
            ]
        }
    }
}