{
    "original": "ANDERSSON, N BERTIL,\nbankkamrer, Löberöd, f i Lund 5/2/26 av lantbr\nNils A o Hulda Johansson,\nTjm Skånska bkn Löberöd 57-61,\nkont:-förest Frosta härads sparbk Flyinge o\nHurva 61-62, kamr Löberöds\njordbr:-kassa sed 62. - Eg aukt :firma sed 59.\n-Hobbies: lantbruk, skogsbruk.\nGift 56 m småskollär Maj Andersson\nf 32, dtr t landst:man Alfred A o Alma\nA. - Barn: Torsten f 61.\n\nANDERSSON, M CAJSA B,\ntandläkare, Ystad, f i Lund 20/6/17 av rekt\nGustav Hartman o Beda Hartman.\nStud:ex  Lund   35,   tandl:ex  Sthlm  40,\n\nass:tandl Halmstad 40, vik distr:tandl\nKumla o Hallsberg 41, distr :tandl Sätila\n42-45, tandl folktandv Malmö 45-46,\npri v :prakt Ystad sed 46.\nGift 46 m tandl Axel Andersson f 99.\n-Barn: Anders f 47, Kerstin f 50,\nAnna-Lena f 55.\n\nANDERSSON, CARL A B,\nkyrkoherde, Kivik, f i Nässjö 16/8/14 av köpm\nAlbert A o Anna Svensson.\nStud:ex Växjö 35, teol kand Lund 41,\npast:adj S Mellby, Strövelstorp o Ö\nBroby 42-49, kyrkoadj Skurup 49, Ystad 52,\nkommin Eslöv 54, kyrkoh S Mellby o\nVitaby sed 59. - Mil:past I 7 52-54.\n-Ordf S Mellby kyrkofullm, SB Mellby o\nVitaby kyrkoråd, past:kyrkoråd o\nförs:-deleg, Stift S Mellby-Vitaby förs :hem.\nGift 52 m Kerstin Svensson f 27, dtr t\nskogsinsp Petrus S o Hanna Gustafsson.\n\n-  Barn: Carl-Henrik f 55, Staffan f 58,\nMagnus f 66.\n\nANDERSSON,    CARL-AXEL,\nläroverksadjunkt, Klippan, f i Hbg 16/9/27\nav köpm Carl A o Märta Olsson.\nFil mag Lund 55, e adj samrealsk\nLindesberg 55, eo adj 57, provar Latinsk\nMalmö 58, eo adj komm gymn Klippan\n58, adj samrealsk där sed 60. - Medl\nOdd Fellow. - Vpl löjtn flottan 56.\nGift 55 m Berit Hansson f 32, dtr t\njärnhandl John H o Mimmie Johansson.\n\n-  Barn: Eva-Lott f 58, Mats f 61.\n\n",
    "structured": {
        "1": {
            "full_name": "N Bertil Andersson",
            "location": "Löberöd",
            "occupation": "Bankkamrer",
            "birth_details": {
                "date": "05/02/1926",
                "place": "Lund",
                "parents": "Nils A och Hulda Johansson"
            },
            "education": [],
            "career": [
                {
                    "position": "Tjm",
                    "years": {
                        "start_year": 1957,
                        "end_year": 1961
                    },
                    "organization": "Skånska bkn Löberöd"
                },
                {
                    "position": "kont:-förest",
                    "years": {
                        "start_year": 1961,
                        "end_year": 1962
                    },
                    "organization": "Frosta härads sparbk Flyinge o Hurva"
                },
                {
                    "position": "kamr",
                    "years": {
                        "start_year": 1962,
                        "end_year": null
                    },
                    "organization": "Löberöds jordbr:-kassa"
                }
            ],
            "family": {
                "spouse": "Maj Andersson",
                "marriage_year": "1956",
                "children": [
                    {
                        "name": "Torsten",
                        "birth_year": "1961"
                    }
                ]
            },
            "publications": null,
            "community_involvement": null,
            "board_memberships": null,
            "honorary_titles": null,
            "hobbies": [
                "lantbruk",
                "skogsbruk"
            ]
        },
        "2": {
            "full_name": "M Cajsa B Andersson",
            "location": "Ystad",
            "occupation": "Tandläkare",
            "birth_details": {
                "date": "20/06/1917",
                "place": "Lund",
                "parents": "Gustav Hartman och Beda Hartman"
            },
            "education": [
                {
                    "degree": "Stud:ex",
                    "year": "1935",
                    "institution": "Lund"
                },
                {
                    "degree": "tandl:ex",
                    "year": "1940",
                    "institution": "Sthlm"
                }
            ],
            "career": [
                {
                    "position": "ass:tandl",
                    "years": {
                        "start_year": 1940,
                        "end_year": null
                    },
                    "organization": "Halmstad"
                },
                {
                    "position": "vik distr:tandl",
                    "years": {
                        "start_year": 1941,
                        "end_year": null
                    },
                    "organization": "Kumla o Hallsberg"
                },
                {
                    "position": "distr :tandl",
                    "years": {
                        "start_year": 1942,
                        "end_year": 1945
                    },
                    "organization": "Sätila"
                },
                {
                    "position": "tandl folktandv",
                    "years": {
                        "start_year": 1945,
                        "end_year": 1946
                    },
                    "organization": "Malmö"
                },
                {
                    "position": "priv:prakt",
                    "years": {
                        "start_year": 1946,
                        "end_year": null
                    },
                    "organization": "Ystad"
                }
            ],
            "family": {
                "spouse": "Axel Andersson",
                "marriage_year": "1946",
                "children": [
                    {
                        "name": "Anders",
                        "birth_year": "1947"
                    },
                    {
                        "name": "Kerstin",
                        "birth_year": "1950"
                    },
                    {
                        "name": "Anna-Lena",
                        "birth_year": "1955"
                    }
                ]
            },
            "publications": null,
            "community_involvement": null,
            "board_memberships": null,
            "honorary_titles": null,
            "hobbies": null
        },
        "3": {
            "full_name": "Carl A B Andersson",
            "location": "Kivik",
            "occupation": "Kyrkoherde",
            "birth_details": {
                "date": "16/08/1914",
                "place": "Nässjö",
                "parents": "Albert A och Anna Svensson"
            },
            "education": [
                {
                    "degree": "Stud:ex",
                    "year": "1935",
                    "institution": "Växjö"
                },
                {
                    "degree": "teol kand",
                    "year": "1941",
                    "institution": "Lund"
                }
            ],
            "career": [
                {
                    "position": "past:adj",
                    "years": {
                        "start_year": 1942,
                        "end_year": 1949
                    },
                    "organization": "S Mellby, Strövelstorp o Ö Broby"
                },
                {
                    "position": "kyrkoadj",
                    "years": {
                        "start_year": 1952,
                        "end_year": null
                    },
                    "organization": "Ystad"
                },
                {
                    "position": "kommin",
                    "years": {
                        "start_year": 1954,
                        "end_year": null
                    },
                    "organization": "Eslöv"
                },
                {
                    "position": "kyrkoh",
                    "years": {
                        "start_year": 1959,
                        "end_year": null
                    },
                    "organization": "S Mellby o Vitaby"
                }
            ],
            "family": {
                "spouse": "Kerstin Svensson",
                "marriage_year": "1952",
                "children": [
                    {
                        "name": "Carl-Henrik",
                        "birth_year": "1955"
                    },
                    {
                        "name": "Staffan",
                        "birth_year": "1958"
                    },
                    {
                        "name": "Magnus",
                        "birth_year": "1966"
                    }
                ]
            },
            "publications": null,
            "community_involvement": null,
            "board_memberships": null,
            "honorary_titles": null,
            "hobbies": null
        },
        "4": {
            "full_name": "Carl-Axel Andersson",
            "location": "Klippan",
            "occupation": "Läroverksadjunkt",
            "birth_details": {
                "date": "16/09/1927",
                "place": "Hbg",
                "parents": "Carl A och Märta Olsson"
            },
            "education": [
                {
                    "degree": "Fil mag",
                    "year": "1955",
                    "institution": "Lund"
                }
            ],
            "career": [
                {
                    "position": "e adj samrealsk",
                    "years": {
                        "start_year": 1955,
                        "end_year": null
                    },
                    "organization": "Lindesberg"
                },
                {
                    "position": "eo adj",
                    "years": {
                        "start_year": 1957,
                        "end_year": null
                    },
                    "organization": "komm gymn Klippan"
                },
                {
                    "position": "adj samrealsk",
                    "years": {
                        "start_year": 1960,
                        "end_year": null
                    },
                    "organization": "Klippan"
                }
            ],
            "family": {
                "spouse": "Berit Hansson",
                "marriage_year": "1955",
                "children": [
                    {
                        "name": "Eva-Lott",
                        "birth_year": "1958"
                    },
                    {
                        "name": "Mats",
                        "birth_year": "1961"
                    }
                ]
            },
            "publications": null,
            "community_involvement": null,
            "board_memberships": null,
            "honorary_titles": null,
            "hobbies": null
        }
    }
}