{
    "original": "AXELSSON,   SVEN  H,   civilekonom,\n\nMalmö, f i Orsa, Kopparb l, 14/6/30 av\njvtjm Gunnar A o Anna Mattsson.\nIng:ex HTL Sthlm 51, DHS 57; Mg\nvattenf:styr 51-58, drifting Sydsv kraft\nab Malmö 59-62, ch driftbyråns\nkraft-kont där sed 63. - Hobbies:\nfotografering, bowling.\n\nGift 60 m Margit Molén f 32, dtr t\nelektr Hilding M o Anna Lidmark.\n-Barn: Karin f 61, Eva f 62.\n\nAXELSSON, WALTER L, ombudsman,\n\nHalmstad, f i Fjärås, Hall l, 29/1/16 av\nlantbr Axel Andersson o Gerda\nPetersson.\n\nKatrinebergs lantm:sk 37, Sånga-Säby\nfören:sk 45, omb :man Sthlmsdistr av bf\no SLU 45-46, ungd :konsulent Sthlms\nungd:nd 46, omb :man Sthlms länsförb\nav RLF 52, Håess 57, Scan sed 61. - Led\nkomm:fullm o lönekomm Simlångsdalen\nsed 62. - Medl Sv:es ungd :konsulenter s\nfören 47-52. - Sekr Lions club. - Skr:\nart i fackpress. - Hobbies: natur- o\nhembygdsvård, idrott.\n\nGift 50 m Elin Eriksson f 22, dtr t lantbr\nAxel E o Eleonora E. - Barn: Dag f 54,\nCarina f 58.\n\nAXINGE, K E TORE, ingenjör,\nVarberg, f i Örebro 14/7/20 av l:e\nverkst:-mäst Karl Andersson o Eleonora\nEng-qvist.\n\nIng:ex tekn gymn Örebro 40, anst SAAB\n40, CVM 47, ch galv avd o sliperi ab\nMonark-Crescent Varberg sed 54. - Ordf\nkomm ungd :styr sed 59. - Led SMU :s\nriksstyr scoututsk. - Skr:\nHermodskur-serna Elementär materiallära (53),\nYtbehandling (63). - Hobby: fanerogamer.\nGift 45 m Birgit Scott. - Barn: Gunnar\nf 46, Börje f 48, Inger f 49, Kerstin f 54.\n\n",
    "structured": {
        "0": {
            "full_name": "Sven H Axelsson",
            "location": "Malmö",
            "occupation": "Civilekonom",
            "birth_details": {
                "date": "14/06/1930",
                "place": "Orsa, Kopparbergs län",
                "parents": "Gunnar A och Anna Mattsson"
            },
            "education": [
                {
                    "degree": "Ing:ex",
                    "year": "1951",
                    "institution": "HTL Sthlm"
                },
                {
                    "degree": "DHS",
                    "year": "1957",
                    "institution": "Mg vattenf:styr"
                }
            ],
            "career": [
                {
                    "position": "drifting",
                    "years": {
                        "start_year": 1951,
                        "end_year": 1958
                    },
                    "organization": "Sydsv kraft ab Malmö"
                },
                {
                    "position": "ch driftbyråns kraft-kont",
                    "years": {
                        "start_year": 1963,
                        "end_year": null
                    },
                    "organization": "Sydsv kraft ab Malmö"
                }
            ],
            "family": {
                "spouse": "Margit Molén",
                "marriage_year": "1960",
                "children": [
                    {
                        "name": "Karin",
                        "birth_year": "1961"
                    },
                    {
                        "name": "Eva",
                        "birth_year": "1962"
                    }
                ]
            },
            "hobbies": [
                "fotografering",
                "bowling"
            ]
        },
        "1": {
            "full_name": "Walter L Axelsson",
            "location": "Halmstad",
            "occupation": "Ombudsman",
            "birth_details": {
                "date": "29/01/1916",
                "place": "Fjärås, Hallands län",
                "parents": "Axel Andersson och Gerda Petersson"
            },
            "education": [
                {
                    "degree": "Katrinebergs lantm:sk",
                    "year": "1937",
                    "institution": null
                },
                {
                    "degree": "Sånga-Säby fören:sk",
                    "year": "1945",
                    "institution": null
                }
            ],
            "career": [
                {
                    "position": "omb :man",
                    "years": {
                        "start_year": 1945,
                        "end_year": 1946
                    },
                    "organization": "Sthlmsdistr av bf o SLU"
                },
                {
                    "position": "ungd :konsulent",
                    "years": {
                        "start_year": 1946,
                        "end_year": null
                    },
                    "organization": "Sthlms ungd:nd"
                },
                {
                    "position": "omb :man",
                    "years": {
                        "start_year": 1952,
                        "end_year": null
                    },
                    "organization": "Håess"
                },
                {
                    "position": "omb :man",
                    "years": {
                        "start_year": 1957,
                        "end_year": null
                    },
                    "organization": "Scan"
                }
            ],
            "family": {
                "spouse": "Elin Eriksson",
                "marriage_year": "1950",
                "children": [
                    {
                        "name": "Dag",
                        "birth_year": "1954"
                    },
                    {
                        "name": "Carina",
                        "birth_year": "1958"
                    }
                ]
            },
            "community_involvement": [
                {
                    "role": "Sekr",
                    "organization": "Lions club",
                    "years": null
                }
            ],
            "publications": [
                {
                    "title": "art i fackpress",
                    "year": null,
                    "type": null
                }
            ],
            "hobbies": [
                "natur- o hembygdsvård",
                "idrott"
            ]
        },
        "2": {
            "full_name": "K E Tore Axinge",
            "location": "Varberg",
            "occupation": "Ingenjör",
            "birth_details": {
                "date": "14/07/1920",
                "place": "Örebro",
                "parents": "Karl Andersson och Eleonora Engqvist"
            },
            "education": [
                {
                    "degree": "Ing:ex",
                    "year": "1940",
                    "institution": "tekn gymn Örebro"
                }
            ],
            "career": [
                {
                    "position": null,
                    "years": {
                        "start_year": 1940,
                        "end_year": null
                    },
                    "organization": "SAAB"
                },
                {
                    "position": "ch galv avd o sliperi",
                    "years": {
                        "start_year": 1954,
                        "end_year": null
                    },
                    "organization": "ab Monark-Crescent Varberg"
                }
            ],
            "family": {
                "spouse": "Birgit Scott",
                "marriage_year": "1945",
                "children": [
                    {
                        "name": "Gunnar",
                        "birth_year": "1946"
                    },
                    {
                        "name": "Börje",
                        "birth_year": "1948"
                    },
                    {
                        "name": "Inger",
                        "birth_year": "1949"
                    },
                    {
                        "name": "Kerstin",
                        "birth_year": "1954"
                    }
                ]
            },
            "board_memberships": [
                {
                    "position": null,
                    "organization": "SMU :s riksstyr scoututsk",
                    "years": null
                }
            ],
            "publications": [
                {
                    "title": "Hermodskurserna Elementär materiallära",
                    "year": "1953",
                    "type": null
                },
                {
                    "title": "Ytbehandling",
                    "year": "1963",
                    "type": null
                }
            ],
            "hobbies": [
                "fanerogamer"
            ]
        }
    }
}