{
    "original": "VÅGBERG, FOLKE, direktör,\nSollefteå, f i Sollefteå 23/2/07 av kont Rudolf\nV o Beda Blom.\n\nBröd Påhlmans HdlI 24, annonsch Tidn\nNya Norrland 24, verkst dir o styr:led\nTryckeri ab Nya Norrland sed 41.\n- Styr:led TU:s mell Norrl:kr, Nordsv\npressfören, A-pressens samorg. -\nNämndeman, led hyresnd. - Medl FrimO,\nRotary.\n\nGift 33 m Ulla Hagstedt f 13, dtr t\naff:bitr C V H o Hanna Sedlund. - Barn:\nKarin f 35, Eva f 37.\n\nWÅGER, A RUNE, direktör, Ljusdal,\nf i Bollnäs 14/5/17 av köpm Wilhelm W\no Anna Andersson.\n\nSkogs- o lantm:sk 33, verkst dir\nGävleb-Härjedalens skogsäg:fören Ljusdal sed\n50. - Styr:led Skogsbr datacentral,\nLjusnans virkesmätn:fören. - Hobbies: jakt,\nfiske.\n\nGift 1) 40 m Elida Mickelsson, 2) 49 m\nIngegärd Olsson. - Barn: i l:a äkt Carin\nf 40, Anders f 44, i 2:a äkt Barbro f 50.\n\nWÅHLIN, SVERKER, civilingenjör,\ndirektör, Gällivare, f i Umeå 6/6/36 av\nmed dr Olof W o Elin Jansson.\n\nStud:ex Sigtuna 56, KTH 63, verkst dir\nab Top-Bryggerierna sed 64. - Medl Sv\nbrygg:fören. - Medl FrimO.\n\nGift 60 m Monica Andersson, dtr t\nciv:ing Albert A o h h. - Barn: Erik f 62,\nJohan f 65.\n\nWÅNGRELL, E BERTIL, direktör,\nÖstersund, f i Alsen, Jämtl l, 13/6/20 av\n\n\nkyrkvärd Magnus Nilsson o Hilma\nEriksson.\n\nStud:ex Östersund 40, Påhlmans hdlI 41,\ntjm Jämtl l sparbk 42,\nÖstersunds-Postens tryckeri ab 45, kamr 48, v verkst\ndir där sed 57, ab ÖPE-tryck sed 64.\n- Rev Östersunds kyrkoförs. - Medl Odd\nFellow.\n\nGift 52 m Mary Hamrin f 28, dtr t\nhemm:äg Hans H o Mia Ström. - Barn:\nBirgitta f 54, Hans f 56 d 60, Margareta\nf 61.\n\nWÅSTRÖM, K ROLF, civilingenjör,\nSundsvall, f i Nora stad 9/10/30 av\nexekutor Folke W o Edit Bonnevier.\n\nTekn  gymn  Örebro  50,  CTH  55,\nanläggn:- o försäljn:ing Asea Västerås\n55-58, l:e byråing Västerås stads tekn verk\n59-61, elverksch Sundsvall sed 62.\n- Hobbies: fiske, tennis, golf, musik.\n\nGift 52 m Ann-Margret Perzon f 30, dtr\nt Richard P o Gunvor Pettersson. - Barn:\nGöran f 53, Anna f 57, Lena f 63.\n\nWÄHL, G HELGE E,\nläroverksadjunkt, Skellefteå, f i Sthlm 7/10/00 av\njvtjm Frans W o Emma Larsdotter.\n\nStud:ex 20, folkskollär:ex Strängnäs 23,\nfil kand Sthlm 31, fil mag 34;\nfolkskollär Lavsjöns folksk 24-36, Umeå stads\nfolksk 37-46, provår Umeå 45, e o eo\nadj hal Umeå 46-49, adj hal Skellefteå\n49-67. - Medl TRO. - Utm: RNO.\n- Hobbies: filateli, språkforskning.\n\nGift 32 m Göta Nordin f 04, dtr t lär\nE N o Fredrika Jonsson. - Barn: Maj\nf 34, Astrid f 42.\n\n",
    "structured": {
        "0": {
            "full_name": "FOLKE VÅGBERG",
            "location": "Sollefteå",
            "occupation": "direktör",
            "birth_details": {
                "date": "23/02/1907",
                "place": "Sollefteå",
                "parents": "kont Rudolf V o Beda Blom"
            },
            "education": [],
            "career": [
                {
                    "position": "verkst dir o styr:led",
                    "years": {
                        "start_year": 1941,
                        "end_year": null
                    },
                    "organization": "Tryckeri ab Nya Norrland"
                }
            ],
            "family": {
                "spouse": "Ulla Hagstedt",
                "marriage_year": "1933",
                "children": [
                    {
                        "name": "Karin",
                        "birth_year": "1935"
                    },
                    {
                        "name": "Eva",
                        "birth_year": "1937"
                    }
                ]
            }
        },
        "1": {
            "full_name": "RUNE WÅGER",
            "location": "Ljusdal",
            "occupation": "direktör",
            "birth_details": {
                "date": "14/05/1917",
                "place": "Bollnäs",
                "parents": "köpm Wilhelm W o Anna Andersson"
            },
            "education": [],
            "career": [
                {
                    "position": "verkst dir",
                    "years": {
                        "start_year": 1950,
                        "end_year": null
                    },
                    "organization": "Gävleb-Härjedalens skogsäg:fören Ljusdal"
                }
            ],
            "family": {
                "spouse": "Elida Mickelsson",
                "marriage_year": "1940",
                "children": [
                    {
                        "name": "Carin",
                        "birth_year": "1940"
                    },
                    {
                        "name": "Anders",
                        "birth_year": "1944"
                    }
                ]
            },
            "hobbies": [
                "jakt",
                "fiske"
            ]
        },
        "2": {
            "full_name": "SVERKER WÅHLIN",
            "location": "Gällivare",
            "occupation": "civilingenjör, direktör",
            "birth_details": {
                "date": "06/06/1936",
                "place": "Umeå",
                "parents": "med dr Olof W o Elin Jansson"
            },
            "education": [
                {
                    "degree": "Stud:ex",
                    "year": "1956",
                    "institution": "Sigtuna"
                },
                {
                    "degree": "KTH",
                    "year": "1963",
                    "institution": "NULL"
                }
            ],
            "career": [
                {
                    "position": "verkst dir",
                    "years": {
                        "start_year": 1964,
                        "end_year": null
                    },
                    "organization": "ab Top-Bryggerierna"
                }
            ],
            "family": {
                "spouse": "Monica Andersson",
                "marriage_year": "1960",
                "children": [
                    {
                        "name": "Erik",
                        "birth_year": "1962"
                    },
                    {
                        "name": "Johan",
                        "birth_year": "1965"
                    }
                ]
            }
        },
        "3": {
            "full_name": "BERTIL WÅNGRELL",
            "location": "Östersund",
            "occupation": "direktör",
            "birth_details": {
                "date": "13/06/1920",
                "place": "Alsen, Jämtl",
                "parents": "kyrkvärd Magnus Nilsson o Hilma Eriksson"
            },
            "education": [
                {
                    "degree": "Stud:ex",
                    "year": "1940",
                    "institution": "Östersund"
                },
                {
                    "degree": "Påhlmans hdlI",
                    "year": "1941",
                    "institution": "NULL"
                }
            ],
            "career": [
                {
                    "position": "v verkst dir",
                    "years": {
                        "start_year": 1957,
                        "end_year": null
                    },
                    "organization": "ab ÖPE-tryck"
                }
            ],
            "family": {
                "spouse": "Mary Hamrin",
                "marriage_year": "1952",
                "children": [
                    {
                        "name": "Birgitta",
                        "birth_year": "1954"
                    },
                    {
                        "name": "Margareta",
                        "birth_year": "1961"
                    }
                ]
            }
        },
        "4": {
            "full_name": "ROLF WÅSTRÖM",
            "location": "Sundsvall",
            "occupation": "civilingenjör",
            "birth_details": {
                "date": "09/10/1930",
                "place": "Nora stad",
                "parents": "exekutor Folke W o Edit Bonnevier"
            },
            "education": [
                {
                    "degree": "Tekn gymn",
                    "year": "1950",
                    "institution": "Örebro"
                },
                {
                    "degree": "CTH",
                    "year": "1955",
                    "institution": "NULL"
                }
            ],
            "career": [
                {
                    "position": "elverksch",
                    "years": {
                        "start_year": 1962,
                        "end_year": null
                    },
                    "organization": "Sundsvall"
                }
            ],
            "family": {
                "spouse": "Ann-Margret Perzon",
                "marriage_year": "1952",
                "children": [
                    {
                        "name": "Göran",
                        "birth_year": "1953"
                    },
                    {
                        "name": "Anna",
                        "birth_year": "1957"
                    },
                    {
                        "name": "Lena",
                        "birth_year": "1963"
                    }
                ]
            },
            "hobbies": [
                "fiske",
                "tennis",
                "golf",
                "musik"
            ]
        },
        "5": {
            "full_name": "G HELGE E WÄHL",
            "location": "Skellefteå",
            "occupation": "läroverksadjunkt",
            "birth_details": {
                "date": "7/10/1900",
                "place": "Sthlm",
                "parents": "jvtjm Frans W o Emma Larsdotter"
            },
            "education": [
                {
                    "degree": "Stud:ex",
                    "year": "1920",
                    "institution": "NULL"
                },
                {
                    "degree": "fil kand",
                    "year": "1934",
                    "institution": "Sthlm"
                }
            ],
            "career": [
                {
                    "position": "adj hal",
                    "years": {
                        "start_year": 1949,
                        "end_year": 1967
                    },
                    "organization": "Skellefteå"
                }
            ],
            "family": {
                "spouse": "Göta Nordin",
                "marriage_year": "1932",
                "children": [
                    {
                        "name": "Maj",
                        "birth_year": "1934"
                    },
                    {
                        "name": "Astrid",
                        "birth_year": "1942"
                    }
                ]
            },
            "honorary_titles": [
                {
                    "title": "RNO",
                    "institution": "NULL",
                    "year": "NULL"
                }
            ],
            "hobbies": [
                "filateli",
                "språkforskning"
            ]
        }
    }
}