{
    "original": "Vikgren, Viktor, överläkare o.\nsjukhuschef, Visby, f. 12/3/96 i Mariestad\nav Axel Vilhelm V. o. Charlotta Skog.\nG. 1. 26 m. Annie Maria Johansson,\nd. 35; 2. 37 m. Elna Margaretha\nNilsson. Barn: Paul Bruno f. 27, Mona\nMaria 31, Hans 40. — Stud:ex. i\nSkara 13’, med. kand. i Lund 20, med. lic.\ndär 25. E. o. hosp :läk. av andra kl.\nv. Vadstena hosp. 26-28, hosp :läk. av\nandra kl. där 28-32, förste läk. v. S :ta\nMaria sjukh. 32-34, överläk. av tredje\nkl. där 35-36, överläk. o. sjukh :chef\nv. S :t Olofs sjukh. i Visby sed. 36,\nfäng:läk. RNO.\n\nWiking, Bo Sture Bertil,\nkomminister, Söderköping, f. 4/5/06 i Norrköp.\nav disp. Gust. Månson o. Bertha\nHögberg. G. 33 m. Maja Sahlin. Barn:\nKristofer f. 36, Anna 38, Fredrik 41,\nHelena 45. — Stud:ex. i Norrköp. 24,\nfil. kand. 29, teol. kand., prakt. teol.\nprov o. prästv. f. Linköp. stift 34. Eft.\nförordn. i Norrköp., Hällestad, Rinna,\nLinköp., Bredestad o. Säby kommin.\n\ni Söderköp. o. Skönberga 42. Östg.\nnat. i Upps. förste kur. 33-34. Skr.:\nbidr. t. Linköp. stifts julbok 35, 39,\n40, 42, 45, 46, t. biogr. saml :verk öv.\nJ. A. Eklund I-H, medarb. i Norrköp.\nTidn., Sv. Gudstj :liv o. Linköp.\nStiftsblad.\n\nWiking, Eric Leander,\nfolkskolinspektör, Vänersborg, f. 28/1/84 i\nTim-mele, Älvsb. 1. G. 08 m. Brita\nHell-strand. Barn: Olof f. 10, Björn 14,\nMaj-Brit 20. — Folkskoll :ex. i\nKarlstad 08. E. o. folkskoli. i Västra\nTun-hem 08, ord. 09, överlär. 30, tf.\ntfolk-sk:insp. i Dalsll. insp :omr. 37-38, i\nÄlvsb. norra insp :omr. 38, ord.\nfolk-sk:insp. där sed. 43. Fd. ordf. i\nkom-m:fullm., valnd, fd, v. ordf. o. sekr.\ni komm:nd, av länsstyr. förordn. led.\nav tax:nd.\n\nWiking, Sven Fredrik, förste läkare,\n",
    "structured": {
        "0": {
            "full_name": "Viktor Vikgren",
            "location": "Visby",
            "occupation": "överläkare o. sjukhuschef",
            "birth_details": {
                "date": "12/03/1896",
                "place": "Mariestad",
                "parents": "Axel Vilhelm V. o. Charlotta Skog"
            },
            "education": [
                {
                    "degree": "Stud:ex.",
                    "year": "1913",
                    "institution": "Skara"
                },
                {
                    "degree": "med. kand.",
                    "year": "1920",
                    "institution": "Lund"
                },
                {
                    "degree": "med. lic.",
                    "year": "1925",
                    "institution": "Lund"
                }
            ],
            "career": [
                {
                    "position": "E. o. hosp :läk. av andra kl. v. Vadstena hosp.",
                    "years": {
                        "start_year": 1926,
                        "end_year": 1928
                    },
                    "organization": "Vadstena hosp."
                },
                {
                    "position": "hosp :läk. av andra kl.",
                    "years": {
                        "start_year": 1928,
                        "end_year": 1932
                    },
                    "organization": "Vadstena hosp."
                },
                {
                    "position": "förste läk. v. S :ta Maria sjukh.",
                    "years": {
                        "start_year": 1932,
                        "end_year": 1934
                    },
                    "organization": "S :ta Maria sjukh."
                },
                {
                    "position": "överläk. av tredje kl. v. S :ta Maria sjukh.",
                    "years": {
                        "start_year": 1935,
                        "end_year": 1936
                    },
                    "organization": "S :ta Maria sjukh."
                },
                {
                    "position": "överläk. o. sjukh :chef v. S :t Olofs sjukh. i Visby",
                    "years": {
                        "start_year": 1936
                    },
                    "organization": "S :t Olofs sjukh. i Visby"
                }
            ],
            "family": {
                "spouse": "Annie Maria Johansson",
                "marriage_year": "1926",
                "children": [
                    {
                        "name": "Paul Bruno",
                        "birth_year": "1927"
                    },
                    {
                        "name": "Mona Maria",
                        "birth_year": "1931"
                    },
                    {
                        "name": "Hans",
                        "birth_year": "1940"
                    }
                ]
            }
        },
        "1": {
            "full_name": "Bo Sture Bertil Wiking",
            "location": "Söderköping",
            "occupation": "komminister",
            "birth_details": {
                "date": "4/5/1906",
                "place": "Norrköp",
                "parents": "disp. Gust. Månson o. Bertha Högberg"
            },
            "education": [
                {
                    "degree": "Stud:ex.",
                    "year": "1924",
                    "institution": "Norrköp"
                },
                {
                    "degree": "fil. kand.",
                    "year": "1929",
                    "institution": "NULL"
                },
                {
                    "degree": "teol. kand., prakt. teol. prov o. prästv.",
                    "year": "1934",
                    "institution": "Linköp"
                }
            ],
            "career": [
                {
                    "position": "förordn.",
                    "years": {
                        "start_year": 1934
                    },
                    "organization": "Linköp."
                }
            ],
            "family": {
                "spouse": "Maja Sahlin",
                "marriage_year": "1933",
                "children": [
                    {
                        "name": "Kristofer",
                        "birth_year": "1936"
                    },
                    {
                        "name": "Anna",
                        "birth_year": "1938"
                    },
                    {
                        "name": "Fredrik",
                        "birth_year": "1941"
                    },
                    {
                        "name": "Helena",
                        "birth_year": "1945"
                    }
                ]
            },
            "publications": [
                {
                    "title": "bidr. t. Linköp. stifts julbok",
                    "year": "1935",
                    "type": "NULL"
                }
            ],
            "community_involvement": [
                {
                    "role": "Östg. nat. i Upps.",
                    "organization": "förste kur.",
                    "years": "1933-1934"
                }
            ]
        },
        "2": {
            "full_name": "Eric Leander Wiking",
            "location": "Vänersborg",
            "occupation": "folkskolinspektör",
            "birth_details": {
                "date": "28/01/1884",
                "place": "Tim-mele, Älvsb. 1",
                "parents": "NULL"
            },
            "education": [
                {
                    "degree": "Folkskoll :ex.",
                    "year": "1908",
                    "institution": "Karlstad"
                }
            ],
            "career": [
                {
                    "position": "E. o. folkskoli. i Västra Tun-hem",
                    "years": {
                        "start_year": 1908
                    },
                    "organization": "Västra Tun-hem"
                },
                {
                    "position": "ord.",
                    "years": {
                        "start_year": 1909
                    },
                    "organization": "Västra Tun-hem"
                },
                {
                    "position": "överlär.",
                    "years": {
                        "start_year": 1930
                    },
                    "organization": "Västra Tun-hem"
                },
                {
                    "position": "ord. folk-sk:insp. där sed.",
                    "years": {
                        "start_year": 1943
                    },
                    "organization": "Älvsb. norra insp :omr."
                }
            ],
            "family": {
                "spouse": "Brita Hell-strand",
                "marriage_year": "1908",
                "children": [
                    {
                        "name": "Olof",
                        "birth_year": "1910"
                    },
                    {
                        "name": "Björn",
                        "birth_year": "1914"
                    },
                    {
                        "name": "Maj-Brit",
                        "birth_year": "1920"
                    }
                ]
            }
        }
    }
}