{
    "original": "Vegfors, Ingrid, tandläkare, Motala,\nf. i Hammarby, Sthlms L, av apot.\nJohan Hallbergson o. farm. kand.\nMärtha Leth. G. 33 m. tandl. Sten\nVegfors. Barn: se denne. — Stud:ex.\ni Motala 29., tandl:kand. 30,\ntandläkare 30. Praktik i Karlshamn 33-3S, i\nSthlm några år fr. 35 o. numera i\nMotala.\n\nVegfors, Sten Hoilger, tandläkare,\nMotala, f. 25/31/10 i Linköping av Per\nAugust V. o. Hildur Oskaria Hansson.\nG. 33 m. tandl. Ingrid Hallbergson.\nBarn: Per f. 36, Bengt Olof 39. —\nStud:ex. i Motala 29, tandl :kand. 30,\ntandläkare 312. Praktik i Karlshamn\n32-35, i Sthlm några år fr. 36 o.\ndärefter i Motala.\n\nter Vehn, Albert Hans, professor,\nGöteborg, f. 18/8/00 i Weener, Tyskl.,\nav :folkskollär. Ephard t. V. o.\nGretchen Blankman. G. 25 m. Anna\nSchwägerl. Barn: Klaas Blankman f. 26,\ntekn., Elisabeth 29. — Stud:ex. i Leer,\nTyskl., l9, stud. v. univ. i Heidelberg\no. Frankfurt am Main 19-23,\nDipl.-Kaufmann 22 o. D:r rer. pol. 23 v. det\nsistn. Assist, i\nBetriebswirtschafts-lehre v. handelshögsk. i Nürnberg\n22-24, Hauptamtl. Dozent där 25-26, prof.\ni företagsekon, (handelsteknik) v.\nhandelshögsk. i Gbg sed. 26, sv. medborg.\n37, auktor. revisor 38. Skr.:\nEntwicklung der Bilanzauffassungen bis zum\nAHGB (29), Självkostnadsberäkn:s\nstandardiser. o. kalkyl, bokför, hos\nSKF, Volvo, ASEA o. LME (36),\nKommentar till Mekanförb.\nnormalkontoplan (45), Kontoplaner o.\nnormalkontoplaner (i Handbok f. ind:org. 45),\nupps. i in- o. utl. fackpubl. RNO.\n\nWehtje, Karl Fredrik, direktör,\nBlomberg, f. 20/10/04 i Limhamn,\nMalmöh. l., av v. hhövd. Ernst W.\no. Mimmi Ahnfelt. G. 30 m. Karin\nLynge-Ahlberg. Barn: Anne-Marie\nf. 32, Monica 34, Karl Fredrik 37,\nJonas 43. — Stud :ex. i Malmö 23, jur.\nstud. i Lund 23-25, keram. stud. i Sv:e,\nTyskl. o. Finl. 25-26, keram. ing:ex.\nv. Staatl. Keram. Fachschule i Höhr\n29, reservoff:ex. 27. Anst. v. OY\nArabia A-B i H:fors 30-311, v. A-B\nRörstrands Porslinsifalbr. sed. 32, verks t.\ndir. där sed. s. å. Styr:led. där samt\ni Dalby Stenkross A-B, A-B Gbgs \nSiporexfabr., Lidköp. Kol- &amp; Koks A-B,\nHardeberga Stenindustri, Hardeberga,\no. Skaraborgs En sk. Bank, Lidköping.\nRVO.\n\nWeibull, Curt Hugo Johannes,\nprofessor, Göteborg, f. 19/8/86 i Lund av\nprof. Martin W. o. Sophie Winberg.\nG. 20 m. Mary Fahlbeck. — Stud:ex.\n04, fil. kand. 07, fil. lic. 11, fil. dr 15,\nallt i Lund. Docent i hist. v. Lunds\nuniv. 15, prof. i hist. v. Gbgs högsk.\nsed. 27, högskolans rektor 36-46,\nstud:-kårens insp. 35-36, hed:led. 40, fil.\nhed:dr v. Oslo o. Aarhus univ. 46. Ordf.\ni styr. f. Gbgs stadsbibl., v. ordf. i styr.\nf. Gbgs mus., led. av styr. f. Gbgs\nhand:högsk. o. Soc:inst. i Gbg, kurator\nf. Hvitfeldtska stip:inrättn., led. av styr.\nf. W. o. M. Lundgrens vetensk:fond,\nordf. i styr. i. Rederi A-B Sv. Lloyd.\nSkr.: Saxo (15), Sv:e o. dess nord.\ngrannmakter under den tidigare\nmedeltiden (21), Om det sv. o. det\ndanska rikets uppkomst (21), Lübeck o.\nSkånemarknaden (22), Sv:es o.\nDanmarks äldsta hist. (22), Drottn.\nChristinas övergång t. katolicismen (28),\nDrottn. Christina (31), Bismarcks fall\n(34), Drottn. Christina o. Monaldesco\n(36), Göteborgs Högskola (41),\nBismarck o. krigsutbrottet 1870 (44).\nLGAA, LSkS, LVVS, LLHS, LVSL,\nled. av Da. Selsk. f. Faedrel. Hist.\nog Sprog, No. Vid. Ak.\n\nWeichbrodt, Gösta, kyrkoherde,\n",
    "structured": {
        "1": {
            "full_name": "Vegfors, Ingrid",
            "location": "Motala",
            "occupation": "tandläkare",
            "birth_details": {
                "date": "29/06/1911",
                "place": "Hammarby, Stockholms Län"
            },
            "education": [
                {
                    "degree": "Stud:ex.",
                    "year": "1929",
                    "institution": "Motala"
                },
                {
                    "degree": "tandl:kand.",
                    "year": "1930",
                    "institution": "NULL"
                }
            ],
            "career": [
                {
                    "position": "Praktik",
                    "years": {
                        "start_year": 1933,
                        "end_year": 1935
                    },
                    "organization": "Karlshamn"
                },
                {
                    "position": "Praktik",
                    "years": {
                        "start_year": 1935,
                        "end_year": "s.n."
                    },
                    "organization": "Sthlm"
                },
                {
                    "position": "Praktik",
                    "years": {
                        "start_year": "s.n.",
                        "end_year": "s.n."
                    },
                    "organization": "Motala"
                }
            ],
            "family": {
                "spouse": "Sten Vegfors",
                "marriage_year": "1933",
                "children": [
                    {
                        "name": "NULL",
                        "birth_year": "NULL"
                    }
                ]
            }
        },
        "2": {
            "full_name": "Vegfors, Sten Hoilger",
            "location": "Motala",
            "occupation": "tandläkare",
            "birth_details": {
                "date": "31/10/1925",
                "place": "Linköping"
            },
            "education": [
                {
                    "degree": "Stud:ex.",
                    "year": "1929",
                    "institution": "Motala"
                },
                {
                    "degree": "tandl:kand.",
                    "year": "1930",
                    "institution": "NULL"
                }
            ],
            "career": [
                {
                    "position": "Praktik",
                    "years": {
                        "start_year": 1932,
                        "end_year": 1935
                    },
                    "organization": "Karlshamn"
                },
                {
                    "position": "Praktik",
                    "years": {
                        "start_year": 1936,
                        "end_year": "s.n."
                    },
                    "organization": "Sthlm"
                },
                {
                    "position": "Praktik",
                    "years": {
                        "start_year": "s.n.",
                        "end_year": "s.n."
                    },
                    "organization": "Motala"
                }
            ],
            "family": {
                "spouse": "Ingrid Hallbergson",
                "marriage_year": "1933",
                "children": [
                    {
                        "name": "Per",
                        "birth_year": "1936"
                    },
                    {
                        "name": "Bengt Olof",
                        "birth_year": "1939"
                    }
                ]
            }
        },
        "3": {
            "full_name": "ter Vehn, Albert Hans",
            "location": "Göteborg",
            "occupation": "professor",
            "birth_details": {
                "date": "18/08/1900",
                "place": "Weener, Tyskland"
            },
            "education": [
                {
                    "degree": "Stud:ex.",
                    "year": "1919",
                    "institution": "Leer, Tyskland"
                },
                {
                    "degree": "Dipl.-Kaufmann",
                    "year": "1922",
                    "institution": "NULL"
                },
                {
                    "degree": "D:r rer. pol.",
                    "year": "1923",
                    "institution": "NULL"
                }
            ],
            "career": [
                {
                    "position": "Assist",
                    "years": {
                        "start_year": 1922,
                        "end_year": 1924
                    },
                    "organization": "Betriebswirtschafts-lehre v. handelshögsk. i Nürnberg"
                },
                {
                    "position": "Hauptamtl. Dozent",
                    "years": {
                        "start_year": 1925,
                        "end_year": 1926
                    },
                    "organization": "Betriebswirtschafts-lehre v. handelshögsk. i Nürnberg"
                },
                {
                    "position": "prof.",
                    "years": {
                        "start_year": 1926,
                        "end_year": "s.n."
                    },
                    "organization": "handelshögsk. i Gbg"
                }
            ],
            "family": {
                "spouse": "Anna Schwägerl",
                "marriage_year": "1925",
                "children": [
                    {
                        "name": "Klaas Blankman",
                        "birth_year": "1926"
                    },
                    {
                        "name": "Elisabeth",
                        "birth_year": "1929"
                    }
                ]
            }
        },
        "4": {
            "full_name": "Wehtje, Karl Fredrik",
            "location": "Blomberg",
            "occupation": "direktör",
            "birth_details": {
                "date": "20/10/1904",
                "place": "Limhamn, Malmöhus län"
            },
            "education": [
                {
                    "degree": "Stud:ex.",
                    "year": "1923",
                    "institution": "Malmö"
                },
                {
                    "degree": "jur. stud.",
                    "year": "1923-1925",
                    "institution": "Lund"
                },
                {
                    "degree": "keram. ing:ex.",
                    "year": "1929",
                    "institution": "Staatl. Keram. Fachschule i Höhr"
                }
            ],
            "career": [
                {
                    "position": "verks t. dir.",
                    "years": {
                        "start_year": "s.n.",
                        "end_year": "s.n."
                    },
                    "organization": "A-B Rörstrands Porslinsifalbr."
                }
            ],
            "family": {
                "spouse": "Karin Lynge-Ahlberg",
                "marriage_year": "1930",
                "children": [
                    {
                        "name": "Anne-Marie",
                        "birth_year": "1932"
                    },
                    {
                        "name": "Monica",
                        "birth_year": "1934"
                    },
                    {
                        "name": "Karl Fredrik",
                        "birth_year": "1937"
                    },
                    {
                        "name": "Jonas",
                        "birth_year": "1943"
                    }
                ]
            },
            "honorary_titles": [
                {
                    "title": "RVO",
                    "year": "NULL"
                }
            ]
        },
        "5": {
            "full_name": "Weibull, Curt Hugo Johannes",
            "location": "Göteborg",
            "occupation": "professor",
            "birth_details": {
                "date": "19/08/1886",
                "place": "Lund"
            },
            "education": [
                {
                    "degree": "Stud:ex.",
                    "year": "1904",
                    "institution": "Lund"
                },
                {
                    "degree": "fil. kand.",
                    "year": "1907",
                    "institution": "Lund"
                },
                {
                    "degree": "fil. lic.",
                    "year": "1911",
                    "institution": "Lund"
                },
                {
                    "degree": "fil. dr",
                    "year": "1915",
                    "institution": "Lund"
                }
            ],
            "career": [
                {
                    "position": "Docent",
                    "years": {
                        "start_year": 1915,
                        "end_year": "s.n."
                    },
                    "organization": "v. Lunds univ"
                },
                {
                    "position": "prof.",
                    "years": {
                        "start_year": 1927,
                        "end_year": "s.n."
                    },
                    "organization": "Gbgs högsk."
                }
            ],
            "family": {
                "spouse": "Mary Fahlbeck",
                "marriage_year": "1920",
                "children": [
                    {
                        "name": "NULL",
                        "birth_year": "NULL"
                    }
                ]
            },
            "publications": [
                {
                    "title": "Saxo",
                    "year": "1915",
                    "type": "NULL"
                },
                {
                    "title": "Sv:e o. dess nord. grannmakter under den tidigare medeltiden",
                    "year": "1921",
                    "type": "NULL"
                },
                {
                    "title": "Om det sv. o. det danska rikets uppkomst",
                    "year": "1921",
                    "type": "NULL"
                },
                {
                    "title": "Lübeck o. Skånemarknaden",
                    "year": "1922",
                    "type": "NULL"
                },
                {
                    "title": "Sv:es o. Danmarks äldsta hist.",
                    "year": "1922",
                    "type": "NULL"
                },
                {
                    "title": "Drottn. Christinas övergång t. katolicismen",
                    "year": "1928",
                    "type": "NULL"
                },
                {
                    "title": "Drottn. Christina",
                    "year": "1931",
                    "type": "NULL"
                },
                {
                    "title": "Bismarcks fall",
                    "year": "1934",
                    "type": "NULL"
                },
                {
                    "title": "Drottn. Christina o. Monaldesco",
                    "year": "1936",
                    "type": "NULL"
                },
                {
                    "title": "Göteborgs Högskola",
                    "year": "1941",
                    "type": "NULL"
                },
                {
                    "title": "Bismarck o. krigsutbrottet 1870",
                    "year": "1944",
                    "type": "NULL"
                }
            ],
            "honorary_titles": [
                {
                    "title": "LGAA",
                    "year": "NULL"
                },
                {
                    "title": "LSkS",
                    "year": "NULL"
                },
                {
                    "title": "LVVS",
                    "year": "NULL"
                },
                {
                    "title": "LLHS",
                    "year": "NULL"
                },
                {
                    "title": "LVSL",
                    "year": "NULL"
                }
            ],
            "community_involvement": [
                {
                    "role": "NULL",
                    "organization": "Gbgs stadsbibl.",
                    "years": "NULL"
                },
                {
                    "role": "NULL",
                    "organization": "Gbgs mus.",
                    "years": "NULL"
                },
                {
                    "role": "NULL",
                    "organization": "Gbgs hand:högsk.",
                    "years": "NULL"
                },
                {
                    "role": "NULL",
                    "organization": "Soc:inst. i Gbg",
                    "years": "NULL"
                },
                {
                    "role": "kurator",
                    "organization": "Hvitfeldtska stip:inrättn.",
                    "years": "NULL"
                },
                {
                    "role": "NULL",
                    "organization": "W. o. M. Lundgrens vetensk:fond",
                    "years": "NULL"
                }
            ],
            "board_memberships": [
                {
                    "position": "NULL",
                    "organization": "Rederi A-B Sv. Lloyd",
                    "years": "NULL"
                }
            ]
        }
    }
}