{
    "original": "Vikbladh, Hans Erik Torsten,\nmusikdirektör, Amål, f. 21/8/06 i Ljungby\nav tandläk. Otto V. o. Ingeborg\nSvensson. G. 36 m. Gundel Collberg. Barn:\nLena f. 39, Ulla 44, Jan 46. —\nReal-ex. i Ljungby 23, org:ex. 26,\nkyrkosång:- o. musikilär :ex. v. musikhögsk.\n28, sång- o. pianostud. i Tyskl. Lär. v.\nKarl Wohlifarts musiksk. 26-29,\nmusiklär. v. Åmåls samrealsk. sed. 29, org. i\nÅmåls stads- o. landsförs. fr. s. å.\nFörste förb:dirig. i Dalsl. körförb. sed.\n31, dirig. f. Åmåls orkrfören. 30-32 o.\nsed. 43’, f. Åmåls kyrkokör sed. 29.\nUtg. smärre pianost. o. sånger.\nHob-bies: konst, fotografer., filmning. Sv.\nKfb. ftjt i guld.\n\nWikblad, Åke Herman, tandläkare,\nGöteborg, f. 24/2/95 i Håbo-Tibble,\nUpps. 1., av apot. Gustaf Herman W.\n\no. Lisen Hallsenius. G. 20 m. Elsa\nLouise Hamrén:. Barn: Brita f. 2ll,\nBerit 25. — Stud:ex. 13 samt stud. v.\nuniv. i Upps. 13-14, tandl :kand. 15,\ntandläk. 18. Praktik i Gbg sed. 18.\nSkattm. i Gbgs tandl :sällsk. 26, ordf.\n31-35, sekr. i Nord. odontol. fören.\n30-32, ordf. 37-38, styr:led. i Sv. tandläk.\ninköpsfören. sed. 31, i Sv:es tandl\n:-fÖrb. 3’7-38, medil. av 44 års tandläk\n:-utbildn :sakk., korresp. led. av dansk\nARPA 34, hediled. av Danska\ntandläk :fören. 46, korresp. led. av Finska\ntandläk :fören. 42. Skr.: ett flert. art.\ni Odontol. tidskr., Sv. läkartidn., Sv.\ntandl :tidskr. m. fl. RVO.\n\nWikert, Petrus, läroverksadjunkt,\nGöteborg, f. 16/2/84 i Å, östergötl. 1.\nG. 17 m. Berta Leimer. Barn: Sten f.\n18, aman. i skatteverket, Sthilm, löjtn.\ni res. — Mog:ex. i Norrköp. 04, fil.\nkand. i Upps. 07, kansliex. 09, provår\nv. Gbgs h. real 10. Rektor v. Bodens\npriv. samsk. 08-09, e. lär. v. Karol.\nlä-rov. i Örebro 11, e. o. lär. v. Gbgs h.\nreal 11-15, lär. v. navig:sk. i Gbg\n12-15, adj. i Mariestad 14, adj. i tyska\no. eng. v. Gbgs östra real sed. 20.\nRes. t. Tyskl. 05, 20, 21 o. 22, Engl.\n13, 14 o. 32, Ital. o. Österr. 23 o. 24,\nFrankr. 25, 26, 27 o. 28, Span.,\nMarocko o. Port. 26, Belg. o. Hoill. 28,\nItal. o. Tunis 31, Ital. 37, Ungern 39.\nRVO.\n\n",
    "structured": {
        "1": {
            "full_name": "Vikbladh, Hans Erik Torsten",
            "location": "Amål",
            "occupation": "musikdirektör",
            "birth_details": {
                "date": "21/08/1906",
                "place": "Ljungby",
                "parents": "tandläk. Otto V. o. Ingeborg Svensson"
            },
            "education": [
                {
                    "degree": "Real-ex.",
                    "year": "1923",
                    "institution": "Ljungby"
                },
                {
                    "degree": "org:ex.",
                    "year": "1926",
                    "institution": "Unknown"
                },
                {
                    "degree": "kyrkosång:- o. musikilär :ex.",
                    "year": "1928",
                    "institution": "Unknown"
                },
                {
                    "degree": "v. musikhögsk.",
                    "year": "1928",
                    "institution": "Unknown"
                },
                {
                    "degree": "sång- o. pianostud. i Tyskl.",
                    "year": "1926-1929",
                    "institution": "Lär. v. Karl Wohlifarts musiksk."
                }
            ],
            "career": [
                {
                    "position": "musiklär.",
                    "years": {
                        "start_year": 1929,
                        "end_year": null
                    },
                    "organization": "Åmåls samrealsk."
                },
                {
                    "position": "org. i Åmåls stads- o. landsförs.",
                    "years": {
                        "start_year": 1929,
                        "end_year": null
                    },
                    "organization": "Unknown"
                },
                {
                    "position": "Förste förb:dirig.",
                    "years": {
                        "start_year": 1931,
                        "end_year": null
                    },
                    "organization": "Dalsl. körförb."
                },
                {
                    "position": "dirig. f. Åmåls orkrfören.",
                    "years": {
                        "start_year": 1930,
                        "end_year": 1932
                    },
                    "organization": "Unknown"
                },
                {
                    "position": "f. Åmåls kyrkokör",
                    "years": {
                        "start_year": 1929,
                        "end_year": null
                    },
                    "organization": "Unknown"
                }
            ],
            "family": {
                "spouse": "Gundel Collberg",
                "marriage_year": "1936",
                "children": [
                    {
                        "name": "Lena",
                        "birth_year": "1939"
                    },
                    {
                        "name": "Ulla",
                        "birth_year": "1944"
                    },
                    {
                        "name": "Jan",
                        "birth_year": "1946"
                    }
                ]
            },
            "hobbies": [
                "konst",
                "fotografer.",
                "filmning"
            ],
            "community_involvement": [
                {
                    "role": "Sv. Kfb. ftjt i guld",
                    "organization": "Unknown",
                    "years": "Unknown"
                }
            ]
        },
        "2": {
            "full_name": "Wikblad, Åke Herman",
            "location": "Göteborg",
            "occupation": "tandläkare",
            "birth_details": {
                "date": "24/02/1895",
                "place": "Håbo-Tibble",
                "parents": "apot. Gustaf Herman W. o. Lisen Hallsenius"
            },
            "education": [
                {
                    "degree": "Stud:ex.",
                    "year": "1913",
                    "institution": "Unknown"
                },
                {
                    "degree": "stud. v. univ. i Upps.",
                    "year": "1913-1914",
                    "institution": "Unknown"
                },
                {
                    "degree": "tandl :kand.",
                    "year": "1915",
                    "institution": "Unknown"
                },
                {
                    "degree": "tandläk.",
                    "year": "1918",
                    "institution": "Unknown"
                }
            ],
            "career": [
                {
                    "position": "Praktik i Gbg",
                    "years": {
                        "start_year": 1918,
                        "end_year": null
                    },
                    "organization": "Unknown"
                }
            ],
            "family": {
                "spouse": "Elsa Louise Hamrén",
                "marriage_year": "1920",
                "children": [
                    {
                        "name": "Brita",
                        "birth_year": "1921"
                    },
                    {
                        "name": "Berit",
                        "birth_year": "1925"
                    }
                ]
            },
            "publications": [
                {
                    "title": "ett flert. art. i Odontol. tidskr.",
                    "year": "Unknown",
                    "type": "Unknown"
                },
                {
                    "title": "Sv. läkartidn.",
                    "year": "Unknown",
                    "type": "Unknown"
                },
                {
                    "title": "Sv. tandl :tidskr.",
                    "year": "Unknown",
                    "type": "Unknown"
                }
            ],
            "honorary_titles": [
                {
                    "title": "RVO",
                    "institution": "Unknown",
                    "year": null
                }
            ]
        },
        "3": {
            "full_name": "Wikert, Petrus",
            "location": "Göteborg",
            "occupation": "läroverksadjunkt",
            "birth_details": {
                "date": "16/02/1884",
                "place": "Å, östergötl.",
                "parents": "Unknown"
            },
            "education": [
                {
                    "degree": "Mog:ex.",
                    "year": "1904",
                    "institution": "Norrköp."
                },
                {
                    "degree": "fil. kand.",
                    "year": "1907",
                    "institution": "Upps."
                },
                {
                    "degree": "kansliex.",
                    "year": "1909",
                    "institution": "Unknown"
                },
                {
                    "degree": "provår v. Gbgs h. real",
                    "year": "1910",
                    "institution": "Unknown"
                }
            ],
            "career": [
                {
                    "position": "Rektor v. Bodens priv. samsk.",
                    "years": {
                        "start_year": 1908,
                        "end_year": 1909
                    },
                    "organization": "Unknown"
                },
                {
                    "position": "e. lär. v. Karol. lä-rov. i Örebro",
                    "years": {
                        "start_year": 1911,
                        "end_year": null
                    },
                    "organization": "Unknown"
                }
            ],
            "family": {
                "spouse": "Berta Leimer",
                "marriage_year": "1917",
                "children": [
                    {
                        "name": "Sten",
                        "birth_year": "1918"
                    }
                ]
            },
            "hobbies": null,
            "honorary_titles": [
                {
                    "title": "RVO",
                    "institution": "Unknown",
                    "year": null
                }
            ]
        }
    }
}