{
    "original": "Arning, Knut, advokat, Göteborg, f. 28/7/92 i Kristianstad av grosshandl. Anders Andersson o. Hulda Schen-holm. G. 16 m. fil. mag. Ester Svangren. Barn: Ingrid f. 19, g. m. löjtn. Nils Aurell, Gbg, Sten 21, jur. kand., tingsnot., Skövde. — Stud:ex. i Kri-stianis’tad 10, jur. kand. li Upp’S. 15. E. o. not. i Skånska hovr. 15, tings-tjg. i Vemmenhögs, Ljunits, Herrestads isamt Listers doms’. 17-18, anst. å G. Fitgers Adv :byrå i Gbg 18-27, egen adv:ver.ks. i Gbg s’ed. 28. Verkst. dir. o. styr:led. i A-B P. J. Svangren &amp; Co., styrrled. i A-B Cura, Rederi A-B Reut, Reuters Hand. A-B, A-B Mårten Pehrsons Valsqvarn m. fl., ordf. i Böö kommunalfören., jur. omb. f. Mottormännens riks förb. G’bgs-avd., sekr. i Gbgs juri&amp;tkl. 23-28 m. m. Medl. av Sv:es adv:’samf. sed. 20 samt av Frimurarorden. Traf :hed :sköld m. dip]. 43, Trafranst. förtjiM. 39.",
    "translated": "Arning, Knut, lawyer, Gothenburg, b. 28/7/92 in Kristianstad to the merchant Anders Andersson and Hulda Schen-holm. Married to the MA Ester Svangren. Children: Ingrid b. 19, married to lieutenant Nils Aurell, Gothenburg, Sten 21, law degree, court clerk, Skövde. Graduated from Kristianstad High School in 1910, law degree from Uppsala University in 1915. Clerk and notary at Skånska Court of Appeal in 1915, court clerk in several districts including Vemmenhög, Ljunits, Herrestad, and Lister from 1917-1918, employed at G. Fitger's Law Firm in Gothenburg from 1918-1927, and running his own legal practice in Gothenburg since 1928. He is the Managing Director and board member of P.J. Svangren & Co. AB, board member of Cura AB, Rederi A-B Reut, Reuters Hand. A-B, A-B Mårten Pehrsons Valsqvarn, among others. He is also the Chairman of Böö Municipal Association, legal representative of Motorists' National Federation Gothenburg Division, and Secretary of Gothenburg Legal Association from 1923-1928, etc. He is a member of the Swedish Bar Association since 1920 and the Freemasons Order. Traffic safety shield with a diploma in 1943, Traffic safety distinction in 1939.",
    "structured": {
        "@context": "https://schema.org",
        "@type": "Person",
        "name": "Knut Arning",
        "jobTitle": "Lawyer",
        "birthDate": "1892-07-28",
        "birthPlace": {
            "name": "Kristianstad, Sweden",
            "latitude": 56.0293778,
            "longitude": 14.1566859
        },
        "parents": [
            {
                "@type": "Person",
                "name": "Anders Andersson"
            },
            {
                "@type": "Person",
                "name": "Hulda Schen-holm"
            }
        ],
        "spouse": {
            "@type": "Person",
            "name": "Ester Svangren",
            "jobTitle": "MA"
        },
        "children": [
            {
                "@type": "Person",
                "name": "Ingrid",
                "birthDate": "1919",
                "spouse": {
                    "@type": "Person",
                    "name": "Nils Aurell",
                    "jobTitle": "Lieutenant"
                }
            },
            {
                "@type": "Person",
                "name": "Sten",
                "birthDate": "1921",
                "jobTitle": "Court Clerk",
                "education": {
                    "@type": "EducationalOccupationalCredential",
                    "credentialCategory": "degree",
                    "educationLevel": "Bachelor's Degree",
                    "educationalProgram": "Law",
                    "educationalInstitution": "Unknown University"
                }
            }
        ],
        "alumniOf": [
            {
                "@type": "EducationalOccupationalCredential",
                "credentialCategory": "diploma",
                "name": "Traffic safety shield",
                "dateIssued": "1943"
            },
            {
                "@type": "EducationalOccupationalCredential",
                "credentialCategory": "distinction",
                "name": "Traffic safety distinction",
                "dateIssued": "1939"
            },
            {
                "@type": "EducationalOccupationalCredential",
                "credentialCategory": "diploma",
                "name": "Jur. Kand.",
                "educationLevel": "Bachelor's Degree",
                "educationalProgram": "Law",
                "educationalInstitution": "Uppsala University",
                "dateIssued": "1915"
            },
            {
                "@type": "EducationalOccupationalCredential",
                "credentialCategory": "diploma",
                "name": "Stud:ex.",
                "dateIssued": "1910",
                "educationalLevel": "Unknown"
            }
        ],
        "memberOf": [
            {
                "@type": "Organization",
                "name": "Swedish Bar Association",
                "foundingDate": "1920"
            },
            {
                "@type": "Organization",
                "name": "Freemasons Order"
            }
        ],
        "affiliation": [
            {
                "@type": "Organization",
                "name": "P.J. Svangren & Co. AB",
                "position": "Managing Director"
            },
            {
                "@type": "Organization",
                "name": "Cura AB",
                "position": "Board Member"
            },
            {
                "@type": "Organization",
                "name": "Rederi A-B Reut",
                "position": "Board Member"
            },
            {
                "@type": "Organization",
                "name": "Reuters Hand. A-B",
                "position": "Board Member"
            },
            {
                "@type": "Organization",
                "name": "A-B Mårten Pehrsons Valsqvarn",
                "position": "Board Member"
            },
            {
                "@type": "Organization",
                "name": "Böö Municipal Association",
                "position": "Chairman"
            },
            {
                "@type": "Organization",
                "name": "Motorists' National Federation Gothenburg Division",
                "position": "Legal Representative"
            },
            {
                "@type": "Organization",
                "name": "Gothenburg Legal Association",
                "position": "Secretary",
                "startDate": "1923",
                "endDate": "1928"
            },
            {
                "@type": "Organization",
                "name": "G. Fitger's Law Firm",
                "position": "Clerk",
                "startDate": "1918",
                "endDate": "1927"
            },
            {
                "@type": "Organization",
                "name": "Unknown Court of Appeals",
                "position": "Clerk & Notary",
                "startDate": "1915",
                "endDate": "Unknown"
            },
            {
                "@type": "Organization",
                "name": "Several Districts",
                "position": "Court Clerk",
                "startDate": "1917",
                "endDate": "1918"
            },
            {
                "@type": "Organization",
                "name": "Own Legal Practice",
                "position": "Owner",
                "startDate": "1928"
            }
        ]
    }
}