{
    "original": "Arbman, Gunnar Engelbert, hovrättssekreterare, Jönköping, f. 5/8/85 i Döderhult, Kalmar 1., av kontr:prosten Jonas A. o. Maria Kristina Petersson. — Mog:ex. 04 o. jur. kand. 09 i Upps. E. o. not. i Göta hovr. 09, tf. domhav. olika tider 11-16, tjg. i Göta hovr. som aman., not., arkivarie, aktuarie, fiskal, adv: fiskal, -sekr. samt e. o. assessor, aktuarie där 17, sekr. 29. RNO, RVO.",
    "translated": "Arbman, Gunnar Engelbert, court secretary, Jönköping, born on August 5th, 1885 in Döderhult, Kalmar 1st district, son of county chaplain Jonas A. and Maria Kristina Petersson. Obtained his Master's degree in law in 1904 and Bachelor's degree in law in 1909 at Uppsala University. Was appointed as a notary in the Göta Court of Appeals in 1909, acting as a judge at different times from 1911-1916, and served in the Göta Court of Appeals as a clerk, notary, archivist, register keeper, prosecutor, secretary and deputy judge. He was appointed as an assistant judge, register keeper in 1917. On 1929, he became the official secretary. Received the Order of the Polar Star and the Order of Vasa.",
    "structured": {
        "@context": "https://schema.org",
        "@type": "Person",
        "name": "Gunnar Engelbert Arbman",
        "jobTitle": "Court Secretary",
        "birthDate": "1885-08-05",
        "birthPlace": {
            "name": "Döderhult, Kalmar",
            "latitude": 57.2683906,
            "longitude": 16.4024162
        },
        "nationality": "Swedish",
        "father": {
            "@type": "Person",
            "name": "Jonas A.",
            "jobTitle": "County Chaplain"
        },
        "mother": {
            "@type": "Person",
            "name": "Maria Kristina Petersson"
        },
        "education": [
            {
                "@type": "EducationalOccupationalCredential",
                "credentialCategory": "master's degree",
                "educationalLevel": "MastersDegree",
                "educationalProgram": "Law",
                "educationalInstitution": "Uppsala University",
                "endDate": "1904"
            },
            {
                "@type": "EducationalOccupationalCredential",
                "credentialCategory": "bachelor's degree",
                "educationalLevel": "BachelorsDegree",
                "educationalProgram": "Law",
                "educationalInstitution": "Uppsala University",
                "endDate": "1909"
            }
        ],
        "workExperience": [
            {
                "@type": "Notary",
                "employer": "Göta Court of Appeals",
                "startDate": "1909",
                "endDate": "1929"
            },
            {
                "@type": "Judge",
                "employer": "Göta Court of Appeals",
                "startDate": "1911",
                "endDate": "1916"
            },
            {
                "@type": "Clerk",
                "employer": "Göta Court of Appeals"
            },
            {
                "@type": "Archivist",
                "employer": "Göta Court of Appeals"
            },
            {
                "@type": "Register",
                "employer": "Göta Court of Appeals",
                "name": "Keeper"
            },
            {
                "@type": "Prosecutor",
                "employer": "Göta Court of Appeals"
            },
            {
                "@type": "Secretary",
                "employer": "Göta Court of Appeals",
                "startDate": "1917",
                "endDate": "1929"
            },
            {
                "@type": "Assistant Judge",
                "employer": "Göta Court of Appeals",
                "name": "Register Keeper",
                "startDate": "1917"
            }
        ],
        "awards": [
            {
                "@type": "Order",
                "name": "Order of the Polar Star"
            },
            {
                "@type": "Order",
                "name": "Order of Vasa"
            }
        ]
    }
}