{
    "original": "Andiell, Max Oscar Fredrik, kapten, direktör, Göteborg, f. 23/7/95 i Gbg av grossh. Gustaf A. o. Alma Almgren. G. 22 m. Ann Littorin. Barn: Sten f. 24, d. 38, Ann-Marie 25, d. 46, Britt-Eva 27, Gull 33. — Stud:ex. i Gbg 14, Gbgs hand:inst. 16, reservoff:-ex. 16, kurs v. Gbgs högsk. 18-19. Kapt. i Älvsb. reg. res. 35. Föret, ett flert. resor t. Engl., Frankr., Tyskl., Belg., Ital. m. fl. Anst. i A-B F. W. Hasselblad &amp; Co. 16, dir :assist. 19, bitr. dir. 30, verkst. dir. 43-45, verkst. dir. i Andell &amp; Anderson A-B i Gbg &gt;sed. 46. Led. av styr. f. A-B F. W. Hasselblad &amp; Co., Andell &amp; Anderson A-B i Gbg, Hasselblads Fo-togr. A-B o. Sv. damhattfabrikant, fören., suppl. i styr. f. Sv. kravattfa-brikant. fören. t. 45, suppl. i styr. f. Gbgs grossistfÖrb. 46. Medl. av Frimurarorden.",
    "translated": "Andiell, Max Oscar Fredrik, captain, director, Gothenburg, born on July 23, 1895 in Gothenburg to Gustaf A., a wholesaler, and Alma Almgren. Married to Ann Littorin, they had four children: Sten (b. 1924, d. 1938), Ann-Marie (b. 1925, d. 1946), Britt-Eva (b. 1927), and Gull (b. 1933). Max passed his studentexamen in Gothenburg in 1914, and later attended Gothenburg's School of Business in 1916 and completed his officer's training in 1916. He took courses at Gothenburg's University from 1918-1919. Max became a captain in Älvsborg regiment reserves in 1935. He has travelled extensively to England, France, Germany, Belgium, Italy and others. Max was employed by AB F.W. Hasselblad &amp; Co. in 1916, began as director assistant in 1919, deputy director in 1930, managing director from 1943-1945, and later became managing director of Andell &amp; Anderson AB in Gothenburg since 1946. He was on the board of directors for AB F.W. Hasselblad &amp; Co., Andell &amp; Anderson AB in Gothenburg, Hasselblads Fotografiska AB and the Swedish women's hat manufacturer's association. Max also served as a board of directors’ supplementary member for the Swedish necktie manufacturer's association until 1945 and was a supplementary member of the Gothenburg Wholesalers' Association board since 1946. He was a member of the Freemasons order.",
    "structured": {
        "@context": "https://schema.org",
        "@type": "Person",
        "name": "Max Oscar Fredrik Andiell",
        "birthDate": "1895-07-23",
        "birthPlace": {
            "name": "Gothenburg, Sweden",
            "latitude": 57.7072326,
            "longitude": 11.9670171
        },
        "deathDate": "",
        "deathPlace": "",
        "nationality": "Swedish",
        "occupation": [
            {
                "@type": "Person",
                "name": "Captain"
            },
            {
                "@type": "Person",
                "name": "Director"
            }
        ],
        "parent": [
            {
                "@type": "Person",
                "name": "Gustaf A."
            },
            {
                "@type": "Person",
                "name": "Alma Almgren"
            }
        ],
        "spouse": {
            "@type": "Person",
            "name": "Ann Littorin"
        },
        "children": [
            {
                "@type": "Person",
                "name": "Sten",
                "birthDate": "1924",
                "deathDate": "1938"
            },
            {
                "@type": "Person",
                "name": "Ann-Marie",
                "birthDate": "1925",
                "deathDate": "1946"
            },
            {
                "@type": "Person",
                "name": "Britt-Eva",
                "birthDate": "1927"
            },
            {
                "@type": "Person",
                "name": "Gull",
                "birthDate": "1933"
            }
        ],
        "education": [
            {
                "@type": "EducationalOccupationalCredential",
                "name": "Studentexamen",
                "value": "1914",
                "educationLevel": "HighSchool"
            },
            {
                "@type": "EducationalOccupationalCredential",
                "name": "Gothenburg's School of Business",
                "value": "1916",
                "educationLevel": "AssociateDegree"
            },
            {
                "@type": "EducationalOccupationalCredential",
                "name": "Officer's training",
                "value": "1916",
                "educationLevel": "Training"
            },
            {
                "@type": "EducationalOccupationalCredential",
                "name": "Course at Gothenburg's University",
                "value": "1918-1919",
                "educationLevel": "HigherEducation"
            }
        ],
        "memberOf": [
            {
                "@type": "Organization",
                "name": "Älvsborg regiment reserves",
                "memberType": "Reserve"
            },
            {
                "@type": "Organization",
                "name": "AB F.W. Hasselblad & Co.",
                "memberType": "BoardMember"
            },
            {
                "@type": "Organization",
                "name": "Andell & Anderson AB",
                "memberType": "BoardMember"
            },
            {
                "@type": "Organization",
                "name": "Hasselblads Fotografiska AB",
                "memberType": "BoardMember"
            },
            {
                "@type": "Organization",
                "name": "Swedish women's hat manufacturer's association",
                "memberType": "BoardMember"
            },
            {
                "@type": "Organization",
                "name": "Swedish necktie manufacturer's association",
                "memberType": "SupplementaryMember",
                "endDate": "1945"
            },
            {
                "@type": "Organization",
                "name": "Gothenburg Wholesalers' Association",
                "memberType": "SupplementaryMember",
                "startDate": "1946"
            },
            {
                "@type": "Organization",
                "name": "Frimurarorden",
                "memberType": "Member"
            }
        ],
        "worksFor": [
            {
                "@type": "Organization",
                "name": "AB F.W. Hasselblad & Co.",
                "jobTitle": "Director Assistant",
                "startDate": "1919"
            },
            {
                "@type": "Organization",
                "name": "AB F.W. Hasselblad & Co.",
                "jobTitle": "Deputy Director",
                "startDate": "1930"
            },
            {
                "@type": "Organization",
                "name": "AB F.W. Hasselblad & Co.",
                "jobTitle": "Managing Director",
                "startDate": "1943",
                "endDate": "1945"
            },
            {
                "@type": "Organization",
                "name": "Andell & Anderson AB",
                "jobTitle": "Managing Director",
                "startDate": "1946"
            }
        ],
        "travelled": [
            {
                "@type": "Place",
                "name": "England"
            },
            {
                "@type": "Place",
                "name": "France"
            },
            {
                "@type": "Place",
                "name": "Germany"
            },
            {
                "@type": "Place",
                "name": "Belgium"
            },
            {
                "@type": "Place",
                "name": "Italy"
            }
        ]
    }
}