{
    "original": "Alveskog, Verner Ernst Tage, kyrkoherde, Äsenhöga, f. 27/7/95 i Nye, Jönköp. 1., av hemm:äg. Ernst An-densson o. Matilda Skoglund. G. 28 m. ilär:an Vadiborg Gustafsson. Barn: Olof f. 30, Lars 32, Gunneil 33. — Stud:ex..v. Fjiellstedtiska isk. i Upps. 17, teok fiil. ex. i upps. 19, teol. kand., praikt. teo’1. prov samt prästv. f. Växjö stift 23, stud. v. evang.-teol. fakult. v. univ. i Tübingen 21-22. Assist, v. ’SV. |sjömanskyrkan i Antv^^erpen. 21, v. kom-min. i Svenarum 23, kommin. i Sten-berga 23-25, i Skede 25-30, kyrkoh. i Äsenhöga o. Källeryd sed. 30. Ordf. i kyrkoistämma, past:stämma, komm:-fullm., skolstyr., barnav:nd, kyrko-bokf :insp. i Växjö stifts L insp :omr. sed. 46, ordf. i Jönköp. läns trädgårds-odlarförb., insp. f. Åsenhöga o. Ma-rieholm-sbruks föreläsn :f ören.",
    "translated": "Alveskog, Verner Ernst Tage, pastor, born on July 27th, 1895 in Nye, Jönköp. County, first-born of home-owners Ernst Anderson and Matilda Skoglund. Married on June 28th to teacher Vadiborg Gustafsson. Children: Olof born in 1930, Lars in 1932, and Gunneil in 1933. He graduated from Fjellstedt School in Uppsala in 1917, gained a degree in theology in Uppsala in 1919, earned a bachelor's degree in theology, passed the practical theology exam, and was ordained as a priest in the Växjö diocese in 1923. He studied evangelism-theology at the University of Tübingen from 1921-1922. He worked as an assistant at the Swedish Seamen's Church in Antwerp in 1921 and then served as a curate in Svenarum in 1923, Stenberga from 1923-1925, and Skede from 1925-1930, and as a pastor in Äsenhöga and Källeryd since 1930. He was the chairman of the church council, pastoral council, municipal council, school board, and church book inspector in the Växjö diocese's inspectorate area since 1946. He was the chairman of the Jönköping county's gardening association and inspector of the Äsenhöga and Marieholm farm lecture associations.",
    "structured": {
        "@context": "https://schema.org/",
        "@type": "Person",
        "name": "Verner Ernst Tage Alveskog",
        "birthDate": "1895-07-27",
        "birthPlace": "Nye, Jönköp. County",
        "parents": [
            {
                "@type": "Person",
                "name": "Ernst Anderson"
            },
            {
                "@type": "Person",
                "name": "Matilda Skoglund"
            }
        ],
        "spouse": {
            "@type": "Person",
            "name": "Vadiborg Gustafsson",
            "jobTitle": "Teacher"
        },
        "children": [
            {
                "@type": "Person",
                "name": "Olof",
                "birthDate": "1930"
            },
            {
                "@type": "Person",
                "name": "Lars",
                "birthDate": "1932"
            },
            {
                "@type": "Person",
                "name": "Gunneil",
                "birthDate": "1933"
            }
        ],
        "education": [
            {
                "@type": "EducationalOrganization",
                "name": "Fjellstedt School",
                "location": "Uppsala",
                "degree": "Stud:ex.",
                "major": ""
            },
            {
                "@type": "EducationalOrganization",
                "name": "Uppsala University",
                "location": "Uppsala",
                "degree": "Teok fiil. ex.",
                "major": "Theology"
            },
            {
                "@type": "EducationalOrganization",
                "name": "University of Tübingen",
                "location": "Tübingen",
                "degree": "",
                "major": "Evangelism-Theology"
            }
        ],
        "jobTitle": "Pastor",
        "hasOccupation": {
            "@type": "Occupation",
            "name": "Swedish Seamen's Church assistant",
            "startDate": "1921",
            "endDate": "1921",
            "location": "Antwerp"
        },
        "memberOf": [
            {
                "@type": "Organization",
                "name": "Svenarum Church"
            },
            {
                "@type": "Organization",
                "name": "Stenberga Church"
            },
            {
                "@type": "Organization",
                "name": "Skede Church"
            },
            {
                "@type": "Organization",
                "name": "Äsenhöga Church"
            },
            {
                "@type": "Organization",
                "name": "Källeryd Church"
            },
            {
                "@type": "Organization",
                "name": "Växjö Diocese",
                "memberOf": [
                    {
                        "@type": "Organization",
                        "name": "Church Council"
                    },
                    {
                        "@type": "Organization",
                        "name": "Pastoral Council"
                    },
                    {
                        "@type": "Organization",
                        "name": "Municipal Council"
                    },
                    {
                        "@type": "Organization",
                        "name": "School Board"
                    },
                    {
                        "@type": "Organization",
                        "name": "Church Book Inspector"
                    }
                ],
                "inspector": {
                    "@type": "Person",
                    "name": "Verner Ernst Tage Alveskog",
                    "jobTitle": "Inspector"
                }
            },
            {
                "@type": "Organization",
                "name": "Jönköping County Gardening Association",
                "chairman": {
                    "@type": "Person",
                    "name": "Verner Ernst Tage Alveskog",
                    "jobTitle": "Chairman"
                }
            },
            {
                "@type": "Organization",
                "name": "Äsenhöga Farm Lecture Association",
                "inspector": {
                    "@type": "Person",
                    "name": "Verner Ernst Tage Alveskog",
                    "jobTitle": "Inspector"
                }
            },
            {
                "@type": "Organization",
                "name": "Marieholm Farm Lecture Association",
                "inspector": {
                    "@type": "Person",
                    "name": "Verner Ernst Tage Alveskog",
                    "jobTitle": "Inspector"
                }
            }
        ]
    }
}