{
    "original": "Andersson, Karl Abel Mauritz, hemmansägare, riksdagsman, Löbbo, Hällabäck, f. 15/6/87 i Villstad, Jön-köp. 1., av Anders’ Karlsson o. Amanda Magnusdtr. G. 11 m. Brita Danielsson. Barn: Ragnar f. 12, Eskil 14, Ruth 16, d. 38, Märta 19. — Genomg. Karlskoga prakt. sk. 06-07. Landstingsman sed. 14, led. av komm:fullm. 20-46, komm. rev. sed. 21, landstingsrev. sed. 44. Led. av riksd. andra kamm. (.s) fr. 25, fjärde tillf. utsk. 25-32, jordbrrutsk. ’sed. 32, v. ordf. sed. 41, särsk. utsk. 30 o. 33, ordf. i särsk. utsk. 47, led. av skogsstyr. sed. 41, lå-nend f. sek. jordbr :kred. .sed. 35, särsk. led. av kamm:koll. sed. 46. Kom-m:uppdr.: led. av bostadsutredn. f. landsbygd., 33 års mjölk- o. mej :ut-redn., hush rsällsk lutredn., 38 års jordbr :utredn., 42 års jordbr ikomm., komm :skatteberedn., 43 års jordbr :-tax :sakk., 44 års vanhävdsutredn. Ordf. i 47 års iköttbesiktn :komm., ordf. i 47 års soc. jordbr :kred :utredn. Led. ■ av länsprövn:nd i Jönköp. 1. 44, av egnah :nd 40, ordf. sed. 44.",
    "translated": "Andersson, Karl Abel Mauritz, smallholder, member of Parliament, Löbbo, Hällabäck, b. 15/6/87 in Villstad, Jönköp. county, son of Anders Karlsson and Amanda Magnusdtr. Married to Brita Danielsson for 11 years. Children: Ragnar b. 12, Eskil b. 14, Ruth b. 16, d. 38, Märta b. 19. Completed practical school in Karlskoga 06-07. Member of the County Council since 1914, member of the municipal assembly 1920-1946, member of the municipal audit 1921, member of the County Council audit 1944. Member of Parliament’s second chamber from 1925, member of the fourth coincidence committee 1925-1932, agriculture committee since 1932, vice chairman since 1941, member of the special committee 1930 and 1933, chairman of the special committee 1947, member of the forestry board since 1941, borrower for the Secondary Agricultural Credit Association since 1935, special member of the Chamber Control from 1946. Municipal roles: member of the rural housing investigation committee, 33 years of milk and dairy investigation, household association investigation, 38 years of agricultural investigation, 42 years of agricultural committee, municipal tax commission, 43 years of agricultural property valuation advisor, 44 years of abuse investigation. Chairman of the 47-year meat inspection committee, chairman of the 47-year social agriculture credit investigation. Member of the county trial board in Jönköping, joined in 1944, member of the property board since 1940, chairman since 1944.",
    "structured": {
        "@context": "https://schema.org",
        "@type": "Person",
        "givenName": "Karl Abel Mauritz",
        "familyName": "Andersson",
        "birthDate": "1887-06-15",
        "birthPlace": {
            "@type": "Place",
            "address": {
                "@type": "PostalAddress",
                "addressLocality": "Villstad",
                "addressRegion": "Jönköping",
                "addressCountry": "Sweden"
            },
            "latitude": 57.201449249999996,
            "longitude": 13.44739675599719
        },
        "parent": [
            {
                "@type": "Person",
                "givenName": "Anders",
                "familyName": "Karlsson"
            },
            {
                "@type": "Person",
                "givenName": "Amanda",
                "familyName": "Magnusdtr"
            }
        ],
        "spouse": {
            "@type": "Person",
            "givenName": "Brita",
            "familyName": "Danielsson"
        },
        "child": [
            {
                "@type": "Person",
                "givenName": "Ragnar",
                "birthDate": "1912"
            },
            {
                "@type": "Person",
                "givenName": "Eskil",
                "birthDate": "1914"
            },
            {
                "@type": "Person",
                "givenName": "Ruth",
                "birthDate": "1916",
                "deathDate": "1938"
            },
            {
                "@type": "Person",
                "givenName": "Märta",
                "birthDate": "1919"
            }
        ],
        "jobTitle": [
            "Smallholder",
            "Member of Parliament"
        ],
        "address": {
            "@type": "PostalAddress",
            "addressLocality": [
                "Löbbo",
                "Hällabäck"
            ]
        },
        "education": [
            {
                "@type": "EducationalOccupationalCredential",
                "credentialCategory": "practical school",
                "educationalLevel": "practical school",
                "startDate": "1906-01-01",
                "endDate": "1907-12-31",
                "recognizedBy": {
                    "@type": "Organization",
                    "name": "Karlskoga"
                }
            }
        ],
        "memberOf": [
            {
                "@type": "Organization",
                "name": "County Council",
                "startDate": "1914",
                "roleName": "Member"
            },
            {
                "@type": "Organization",
                "name": "Municipal Assembly",
                "startDate": "1920",
                "endDate": "1946",
                "roleName": "Member"
            },
            {
                "@type": "Organization",
                "name": "Municipal Audit",
                "startDate": "1921",
                "roleName": "Member"
            },
            {
                "@type": "Organization",
                "name": "County Council Audit",
                "startDate": "1944",
                "roleName": "Member"
            },
            {
                "@type": "Organization",
                "name": "Swedish Parliament",
                "roleName": [
                    "Member of Second Chamber",
                    "Member of Fourth Coincidence Committee",
                    "Member of Agriculture Committee",
                    "Vice Chairman of Agriculture Committee",
                    "Member of Special Committee",
                    "Chairman of Special Committee"
                ],
                "startDate": "1925",
                "endDate": [
                    "1932",
                    "1941",
                    "1947"
                ]
            },
            {
                "@type": "Organization",
                "name": "Forestry Board",
                "startDate": "1941",
                "roleName": "Member"
            },
            {
                "@type": "Organization",
                "name": "Secondary Agricultural Credit Association",
                "startDate": "1935",
                "roleName": "Borrower"
            },
            {
                "@type": "Organization",
                "name": "Chamber Control",
                "startDate": "1946",
                "roleName": "Special Member"
            },
            {
                "@type": "Organization",
                "name": "Rural Housing Investigation Committee",
                "startDate": "Unknown",
                "roleName": "Member"
            },
            {
                "@type": "Organization",
                "name": "Milk and Dairy Investigation",
                "startDate": "Unknown",
                "endDate": "33 years",
                "roleName": "Member"
            },
            {
                "@type": "Organization",
                "name": "Household Association Investigation",
                "startDate": "Unknown",
                "roleName": "Member"
            },
            {
                "@type": "Organization",
                "name": "Agricultural Investigation",
                "startDate": "Unknown",
                "endDate": [
                    "38 years",
                    "42 years"
                ],
                "roleName": "Member"
            },
            {
                "@type": "Organization",
                "name": "Agricultural Committee",
                "startDate": "Unknown",
                "endDate": "42 years",
                "roleName": "Chairman"
            },
            {
                "@type": "Organization",
                "name": "Municipal Tax Commission",
                "startDate": "Unknown",
                "endDate": "43 years",
                "roleName": "Agricultural Property Valuation Advisor"
            },
            {
                "@type": "Organization",
                "name": "Abuse Investigation",
                "startDate": "Unknown",
                "endDate": "44 years",
                "roleName": "Member"
            },
            {
                "@type": "Organization",
                "name": "Meat Inspection Committee",
                "startDate": "Unknown",
                "endDate": "47 years",
                "roleName": "Chairman"
            },
            {
                "@type": "Organization",
                "name": "Social Agriculture Credit Investigation",
                "startDate": "Unknown",
                "endDate": "47 years",
                "roleName": "Chairman"
            },
            {
                "@type": "Organization",
                "name": "County Trial Board",
                "startDate": "1944",
                "roleName": "Member"
            },
            {
                "@type": "Organization",
                "name": "Property Board",
                "startDate": "1940",
                "endDate": "Ongoing",
                "roleName": "Member"
            }
        ],
        "nationality": "Swedish",
        "deathDate": null
    }
}