{
    "original": "Adelsköld, Erik Volrath Kristian, f. d. överstelöjtnant, Ftoda, f. 10/6/78 i St. Lundby, Älvsb. 1., av godsäg. Fredrik Adl.-Adelsköld o. Lotten Johansson. G. 08 m. Lilly Nvmansson. Barn : Vera f. 10, Elsa 13. — Studiex. i Gbg 96, off:ex. 98, GCI 06-09, KHS 09-11. Und iilöjitn. v. Västgöta Dais reg. 98, kapt. v. Hall. reg. 14, major v. Jämtl. fältjäg:reg. 22, öv:löjtn. v. Hall. reg. 28, i res. 33. Mil:assist. v. SJ 14-19, befälh. v. Skara ro 33-42. RSO.",
    "translated": "Adelsköld, Erik Volrath Kristian, former lieutenant colonel, born on June 10, 1878 in St. Lundby, Älvsborgs County, to estate owner Fredrik Adl.-Adelsköld and Lotten Johansson. Married since 1908 to Lilly Norman. Children: Vera, born in 1910 and Elsa, born in 1913. Completed studies in Gothenburg in 1896, officer training in 1898, attended the General Staff Course from 1906 to 1909, and the War College from 1909 to 1911. Served as a second lieutenant in the Västgöta Dais regiment in 1898, became a captain in the Halland regiment in 1914, a major in the Jämtland field rifle regiment in 1922, and a lieutenant colonel in the Halland regiment in 1928. Retired from active service in 1933. Military assistant at the Swedish Railways from 1914 to 1919 and commander of the Skara district from 1933 to 1942. Awarded the Royal Order of the Sword (RSO).",
    "structured": {
        "@context": "https://schema.org",
        "@type": "Person",
        "name": "Erik Volrath Kristian Adelsköld",
        "givenName": "Erik",
        "familyName": "Adelsköld",
        "birthDate": "1878-06-10",
        "birthPlace": {
            "@type": "Place",
            "name": "St. Lundby, Älvsborgs County"
        },
        "parent": [
            {
                "@type": "Person",
                "name": "Fredrik Adl.-Adelsköld",
                "jobTitle": "Estate owner"
            },
            {
                "@type": "Person",
                "name": "Lotten Johansson"
            }
        ],
        "spouse": {
            "@type": "Person",
            "name": "Lilly Norman",
            "marriageDate": "1908"
        },
        "children": [
            {
                "@type": "Person",
                "givenName": "Vera",
                "birthDate": "1910"
            },
            {
                "@type": "Person",
                "givenName": "Elsa",
                "birthDate": "1913"
            }
        ],
        "education": [
            {
                "@type": "EducationalOccupationalCredential",
                "name": "Studiex.",
                "educationLevel": "secondary school",
                "educationalCredentialAwarded": "Studiex."
            },
            {
                "@type": "EducationalOccupationalCredential",
                "name": "off:ex.",
                "educationLevel": "officer training",
                "educationalCredentialAwarded": "off:ex."
            },
            {
                "@type": "EducationalOccupationalCredential",
                "name": "GCI",
                "educationLevel": "General Staff Course",
                "educationalCredentialAwarded": "General Staff Course"
            },
            {
                "@type": "EducationalOccupationalCredential",
                "name": "KHS",
                "educationLevel": "War College",
                "educationalCredentialAwarded": "War College"
            }
        ],
        "jobTitle": "Former Lieutenant Colonel",
        "memberOf": [
            {
                "@type": "Organization",
                "name": "Västgöta Dais regiment",
                "jobTitle": "Second Lieutenant",
                "startDate": "1898",
                "endDate": "1914"
            },
            {
                "@type": "Organization",
                "name": "Halland regiment",
                "jobTitle": "Captain",
                "startDate": "1914",
                "endDate": "1922"
            },
            {
                "@type": "Organization",
                "name": "Jämtland field rifle regiment",
                "jobTitle": "Major",
                "startDate": "1922",
                "endDate": "1928"
            },
            {
                "@type": "Organization",
                "name": "Halland regiment",
                "jobTitle": "Lieutenant Colonel",
                "startDate": "1928",
                "endDate": "1933"
            }
        ],
        "workLocation": [
            {
                "@type": "Organization",
                "name": "Swedish Railways",
                "jobTitle": "Military Assistant",
                "startDate": "1914",
                "endDate": "1919"
            },
            {
                "@type": "Organization",
                "name": "Skara district",
                "jobTitle": "Commander",
                "startDate": "1933",
                "endDate": "1942"
            }
        ],
        "award": {
            "@type": "Order",
            "name": "Royal Order of the Sword",
            "awardDate": "N/A",
            "description": "Awarded the Royal Order of the Sword"
        }
    }
}