{
    "original": "Alm, Gustav (Gösta), distriktslantmätare, Växjö, f. 9/10/99 i Söraby, Kronob. I., av fanj. Gustaf A. o. Karin Jolhans’son. G. 1. 25 m. Maja Norberg, d. 37; 2. 39 m. Greta Nifeson. Barn: Inger Elisabeth f. 26, Karl Gösta 28. — Stud:ex. i Lund 19, lantmät:ex. 24, kulturtekn. ex. 28. Lantmät. 24, aman. i lantmät:styr. 30, tf. byråing. 32, tf. distr :lantmät. i Norrtälje 33, tf. distr:-lantmät. i Oskarshamn 33, distr ilant-mät. i Konga distr. av Kronob. 1. sed. 37. Assist, i kulturtekn. v. KTH 32-33. Led. av styr. f. Sv:es lantmät fören. o. av styr. f. distr :lantmät :sekt. Medl. av Frimurarorden o. SHT.",
    "translated": "Alm, Gustav (Gösta), district surveyor, Växjö, born October 9, 1899 in Söraby, Kronoberg County, son of Sergeant Gustaf A. and Karin Jolhansson. Married 1st on May 25th to Maja Norberg who passed away in 1937, 2nd marriage in 1939 to Greta Nifeson. Children: Inger Elisabeth born in 1926, Karl Gösta in 1928. He obtained his degree from Lund University in 1919, completed his surveyor training in 1924, and his degree in cultural technology in 1928. He was a district surveyor since 1924, assistant in surveying from 1930, temporary head of the department in Norrtälje in 1933, temporary district surveyor in Oskarshamn in 1933, and district surveyor in Konga district of Kronoberg county from 1937. He was an assistant in cultural technology at KTH from 1932 to 1933. He was a member of the board of the Swedish surveyors' association and the board of the district surveyor section. He was also a member of the Freemasons and the Society for the History of Technology.",
    "structured": {
        "@context": "https://schema.org",
        "@type": "Person",
        "name": "Gustav Alm",
        "givenName": "Gustav",
        "additionalName": "Gösta",
        "familyName": "Alm",
        "jobTitle": "District Surveyor",
        "address": {
            "@type": "PostalAddress",
            "addressLocality": "Växjö",
            "addressRegion": "Kronoberg County"
        },
        "birthDate": "1899-10-09",
        "birthPlace": {
            "name": "Söraby, Kronoberg County",
            "latitude": 57.025884899999994,
            "longitude": 14.890187010644057
        },
        "parent": {
            "@type": "Person",
            "name": "Gustaf A."
        },
        "spouse": [
            {
                "@type": "Person",
                "name": "Maja Norberg",
                "deathDate": "1937"
            },
            {
                "@type": "Person",
                "name": "Greta Nifeson",
                "dateModified": "1939"
            }
        ],
        "children": [
            {
                "@type": "Person",
                "name": "Inger Elisabeth",
                "birthDate": "1926"
            },
            {
                "@type": "Person",
                "name": "Karl Gösta",
                "birthDate": "1928"
            }
        ],
        "education": [
            {
                "@type": "EducationalOccupationalCredential",
                "name": "Stud:ex. Lund 19"
            },
            {
                "@type": "EducationalOccupationalCredential",
                "name": "Lantmät:ex. 24"
            },
            {
                "@type": "EducationalOccupationalCredential",
                "name": "Kulturtekn. ex. 28"
            }
        ],
        "employmentHistory": [
            {
                "@type": "EmploymentAgency",
                "name": "Lantmätarstyr.",
                "jobTitle": "Amanuens",
                "startDate": "1930"
            },
            {
                "@type": "EmploymentAgency",
                "name": "Norrtälje",
                "jobTitle": "Temporary Head",
                "startDate": "1933"
            },
            {
                "@type": "EmploymentAgency",
                "name": "Oskarshamn",
                "jobTitle": "Temporary District Surveyor",
                "startDate": "1933"
            },
            {
                "@type": "EmploymentAgency",
                "name": "Konga District, Kronoberg County",
                "jobTitle": "District Surveyor",
                "startDate": "1937"
            },
            {
                "@type": "EmploymentAgency",
                "name": "KTH",
                "jobTitle": "Assistant in Cultural Technology",
                "startDate": "1932",
                "endDate": "1933"
            }
        ],
        "memberOf": [
            {
                "@type": "Organization",
                "name": "Swedish Surveyors' Association",
                "memberOf": [
                    {
                        "@type": "Organization",
                        "name": "Board of Directors"
                    }
                ]
            },
            {
                "@type": "Organization",
                "name": "District Surveyor Section",
                "memberOf": [
                    {
                        "@type": "Organization",
                        "name": "Board of Directors"
                    }
                ]
            },
            {
                "@type": "Organization",
                "name": "Freemasons"
            },
            {
                "@type": "Organization",
                "name": "Society for the History of Technology"
            }
        ]
    }
}