{
    "original": "Arfwedson, John Edvard, praktiserande läkare, Göteborg, f. 16/3/73 i Sthlm av konsul John A. o. Amehe Lovisa Breijer. G. 08 m. Cissi Larsson. Barn: Gull f. 10, g. m. konstnär S. Ericson, Sthlm, Björn 12, dir., Gbg, Håkan 14, läk., Halmstad. — Mog:ex. 92, med. kand. 98, med. lic. 04, allt i Sthlm. Utr. stud:res. 08-09, 11 o. 13. Und:läk. v. Allm. garn:sjukh. 00-01, aman. v. S :t Görans , sjukh. tub :avd. 03-04, v. Sahlgr. sjukh. med. avd. 05, andre läk. där 05-08, bitr. läk. v. Gbgs epid:sjukh. 08 o. 09-10, avd:läk. v. Sahlgr. sjukh. tub:avd. 10-29, tf. över-läk. v. sjukv:anst. å Kålltorp 29-31, distr:läk. i Gbg 31-38, pens. 38. Stip. i flottan 00, rnarinläk. av 2. gr. v. Mlk 04, i res. 10, av 1. gr. i res. 14, förste marinläk. i res. 21, avsk. 28. RVO.",
    "translated": "Arfwedson, John Edvard, practicing physician, Gothenburg, born March 16, 1873 in Stockholm to Consul John A. and Amehe Lovisa Breijer. Married in 1908 to Cissi Larsson. Children: Gull, born 1910, married to artist S. Ericson, Stockholm; Björn, born 1912, director, Gothenburg; Håkan, born 1914, physician, Halmstad. Entered medical school in 1892, earned a Bachelor of Medicine in 1898, and a medical license in 1904, all in Stockholm. Completed foreign study trips in 1908-1909, 1911, and 1913. Served as an assistant physician at the General Hospital in 1900-1901, an assistant physician in the tuberculosis department at S:t Görans Hospital in 1903-1904, an assistant physician in the medical department at Sahlgr. Hospital in 1905, a second physician there in 1905-1908, an associate physician at the Gothenburg epidemics hospital in 1908 and 1909-1910, department physician in the tuberculosis department at Sahlgr. Hospital in 1910-1929, acting chief physician at Kålltorp Hospital 1929-1931, district physician in Gothenburg 1931-1938, retired in 1938. Received a scholarship in the navy in 1900, became a navy surgeon of 2nd degree in 1904, and served in reserves in 1910, became a navy surgeon of 1st degree in reserves in 1914, and retired in 1928. Received the Royal Order of Vasa.",
    "structured": {
        "@context": "https://schema.org",
        "@type": "Person",
        "name": "John Edvard Arfwedson",
        "jobTitle": "practicing physician",
        "birthDate": "1873-03-16",
        "birthPlace": {
            "@type": "Place",
            "name": "Stockholm",
            "latitude": 59.3251172,
            "longitude": 18.0710935
        },
        "parent": [
            {
                "@type": "Person",
                "name": "John A. Arfwedson",
                "jobTitle": "Consul"
            },
            {
                "@type": "Person",
                "name": "Amehe Lovisa Breijer"
            }
        ],
        "spouse": {
            "@type": "Person",
            "name": "Cissi Larsson"
        },
        "children": [
            {
                "@type": "Person",
                "name": "Gull Arfwedson",
                "birthDate": "1910",
                "spouse": {
                    "@type": "Person",
                    "name": "S. Ericson",
                    "jobTitle": "Artist",
                    "location": {
                        "@type": "Place",
                        "name": "Stockholm"
                    }
                }
            },
            {
                "@type": "Person",
                "name": "Björn Arfwedson",
                "birthDate": "1912",
                "jobTitle": "Director",
                "location": {
                    "@type": "Place",
                    "name": "Gothenburg"
                }
            },
            {
                "@type": "Person",
                "name": "Håkan Arfwedson",
                "birthDate": "1914",
                "jobTitle": "Physician",
                "location": {
                    "@type": "Place",
                    "name": "Halmstad"
                }
            }
        ],
        "education": [
            {
                "@type": "EducationalOccupationalCredential",
                "name": "Mog:ex",
                "endDate": "1892",
                "educationalLevel": "SecondarySchool"
            },
            {
                "@type": "EducationalOccupationalCredential",
                "name": "Med. Kand.",
                "endDate": "1898",
                "educationalLevel": "BachelorDegree"
            },
            {
                "@type": "EducationalOccupationalCredential",
                "name": "Med. Lic.",
                "endDate": "1904",
                "educationalLevel": "MedicalLicence"
            }
        ],
        "worksFor": {
            "@type": "Organization",
            "name": "Gothenburg"
        },
        "event": [
            {
                "@type": "EducationEvent",
                "name": "foreign study trips",
                "startDate": "1908-01-01",
                "endDate": "1913-12-31"
            },
            {
                "@type": "MedicalOrganization",
                "name": "General Hospital",
                "startDate": "1900",
                "endDate": "1901",
                "jobTitle": "Assistant physician"
            },
            {
                "@type": "MedicalOrganization",
                "name": "St. Görans Hospital",
                "startDate": "1903",
                "endDate": "1904",
                "jobTitle": "Assistant physician in the tuberculosis department"
            },
            {
                "@type": "MedicalOrganization",
                "name": "Sahlgr. Hospital",
                "startDate": "1905",
                "jobTitle": "Associate physician"
            },
            {
                "@type": "MedicalOrganization",
                "name": "Sahlgr. Hospital",
                "startDate": "1905",
                "endDate": "1908",
                "jobTitle": "Second physician"
            },
            {
                "@type": "MedicalOrganization",
                "name": "Gothenburg epidemics hospital",
                "startDate": "1908",
                "endDate": "1910",
                "jobTitle": "Associate physician"
            },
            {
                "@type": "MedicalOrganization",
                "name": "Sahlgr. Hospital",
                "startDate": "1910",
                "endDate": "1929",
                "jobTitle": "Department physician in the tuberculosis department"
            },
            {
                "@type": "MedicalOrganization",
                "name": "Kålltorp Hospital",
                "startDate": "1929",
                "endDate": "1931",
                "jobTitle": "Acting chief physician"
            },
            {
                "@type": "MedicalOrganization",
                "name": "Gothenburg",
                "startDate": "1931",
                "endDate": "1938",
                "jobTitle": "District physician"
            }
        ],
        "affiliation": [
            {
                "@type": "OrganizationRole",
                "namedPosition": "Navy surgeon of 2nd degree",
                "startDate": "1904",
                "endDate": "1910",
                "affiliation": {
                    "@type": "Organization",
                    "name": "Navy"
                }
            },
            {
                "@type": "OrganizationRole",
                "namedPosition": "Navy surgeon of 1st degree in reserves",
                "startDate": "1914",
                "endDate": "1928",
                "affiliation": {
                    "@type": "Organization",
                    "name": "Navy"
                }
            }
        ],
        "award": [
            {
                "@type": "Order",
                "name": "Royal Order of Vasa"
            }
        ],
        "gender": "male"
    }
}