{
    "original": "Andersson, Oskar Rune, redaktör, Falkenberg, f. 13/10/15 i Rolfstorp, Hallands 1. G. 43 m. Vega Färdig. — Medarb. i Norra Hallands Tidn. Vestkusten, Varberg, 34-37, medarb., tidvis nattred. i Härnösands-Posten m. Sollefteå-Bladet, Härnösand, 37-41, medarb. i Örnsköldsviks-Posten, Örnsköldsvik, 41-43, i Kristianstads Läns Tidn. 43-45, notischef i Hallands Ny- heter, Falkenberg, sed. 45. Sekr. i Ängermanl. idr :förb. 38-39, i Anger-manl. ishockeysekt. 38-39. Skr.: Nebulösa (diktsaml. 34), Tång (dikt-saml. 35).",
    "translated": "Andersson, Oskar Rune, editor, Falkenberg, born October 13, 1915 in Rolfstorp, Halland. Married in 1943 to Vega Färdig. - Worked as a contributor to Norra Hallands Tidning and Vestkusten in Varberg from 1934 to 1937, as a part-time night editor for Härnösands-Posten and Sollefteå-Bladet in Härnösand from 1937 to 1941, as a contributor to Örnsköldsviks-Posten in Örnsköldsvik from 1941 to 1943, and as a contributor to Kristianstads Läns Tidning from 1943 to 1945. Currently the news editor at Hallands Nyheter in Falkenberg since 1945. Secretary for Ängermanland Sports Association from 1938 to 1939, and for the ice hockey section of Ängermanland Sports Association from 1938 to 1939. Author of Nebulösa (poetry collection, 1934) and Tång (poetry collection, 1935).",
    "structured": {
        "@context": "https://schema.org",
        "@type": "Person",
        "givenName": "Oskar Rune",
        "familyName": "Andersson",
        "jobTitle": "Editor",
        "birthDate": "1915-10-13",
        "birthPlace": {
            "@type": "Place",
            "name": "Rolfstorp, Halland",
            "latitude": 57.1452538,
            "longitude": 12.45987
        },
        "memberOf": [
            {
                "@type": "Organization",
                "name": "Ängermanland Sports Association",
                "startDate": "1938",
                "endDate": "1939",
                "roleName": "Secretary"
            },
            {
                "@type": "Organization",
                "name": "Ängermanland Sports Association",
                "startDate": "1938",
                "endDate": "1939",
                "roleName": "Secretary for Ice Hockey Section"
            }
        ],
        "worksFor": {
            "@type": "Organization",
            "name": "Hallands Nyheter",
            "startDate": "1945",
            "jobTitle": "News Editor"
        },
        "worksIn": [
            {
                "@type": "Organization",
                "name": "Norra Hallands Tidning"
            },
            {
                "@type": "Organization",
                "name": "Vestkusten"
            },
            {
                "@type": "Organization",
                "name": "Härnösands-Posten"
            },
            {
                "@type": "Organization",
                "name": "Sollefteå-Bladet"
            },
            {
                "@type": "Organization",
                "name": "Örnsköldsviks-Posten"
            },
            {
                "@type": "Organization",
                "name": "Kristianstads Läns Tidning",
                "startDate": "1943",
                "endDate": "1945"
            }
        ],
        "spouse": {
            "@type": "Person",
            "name": "Vega Färdig",
            "marriageDate": "1943"
        },
        "author": [
            {
                "@type": "CreativeWork",
                "name": "Nebulösa",
                "type": "Book",
                "datePublished": "1934"
            },
            {
                "@type": "CreativeWork",
                "name": "Tång",
                "type": "Book",
                "datePublished": "1935"
            }
        ]
    }
}