{
    "original": "Andersson, Gustaf Daniel, läroverksadjunkt, Skara, f. 22/11/08 i Troililhättan av Karl’ A. o. Emma Johansson. G. 43 m. teckn:lär:an Greta Kastrup. Barn: Margareta f. 44. — Stud:ex. i Vänersborg 26, fil. kand. i Upps. 30, fil. mag. 33, provår v. Vasa h. a. 1. i Gbg 39. Timlär. v. Katrineholms ensk. lärov. vt. 35, vik. v. Gbgs östra realsk. o. h. folksk. periodvis ht. 35, vik. samt e. adj. i Luleå 36-38, e. adj. i Lund 40-41, v. Östra real i Sthlbi 41-43, e. o. adj. i Karlskrona 43-46, i Borås 46-47, adj. v. Skara h. a. d. fr. 47 m. tjg. t, v. i Borås, därjämte div. förordn. som timdär. i Troilihättan, Gbg, Sthlm, Karlskrona o. Borås. Styr:ik’d. i tsydsv. krets, av Sv:es e :lär :fören. 40-41.",
    "translated": "Andersson, Gustaf Daniel, high school teacher, Skara, born on November 22nd, 1908 in Trollhättan to Karl A. and Emma Johansson. Married in 1943 to Greta Kastrup, a drawing teacher. They had one child, Margareta, born in 1944. He completed his high school education in Vänersborg in 1926 and obtained a Bachelor's degree in Uppsala in 1930, followed by a Master's degree in 1933. He completed his teaching internship at Vasa h. a. 1. in Gothenburg in 1939. He worked as a substitute teacher at Katrineholm's private school in the spring of 1935, as well as a substitute and later a permanent teacher at Gothenburg's eastern high school and primary school intermittently during the autumn of 1935 and later. He worked as a permanent teacher in Luleå from 1936-1938, in Lund from 1940-1941, at Östra real in Stockholm from 1941-1943, and as a temporary teacher in Karlskrona from 1943-1946 and in Borås from 1946-1947. In 1947, he became a permanent teacher at Skara h. a. d. In addition to his permanent positions, he also worked as a substitute teacher in Trollhättan, Gothenburg, Stockholm, Karlskrona, and Borås, and received various appointments as a hourly teacher. He served as a board member of the Swedish National Teachers' Association in the southern district from 1940-1941.",
    "structured": {
        "@context": "https://schema.org",
        "@type": "Person",
        "givenName": "Gustaf Daniel",
        "familyName": "Andersson",
        "birthPlace": {
            "@type": "Place",
            "name": "Trollhättan",
            "latitude": 58.2827931,
            "longitude": 12.2908612
        },
        "birthDate": "1908-11-22",
        "parent": [
            {
                "@type": "Person",
                "name": "Karl A."
            },
            {
                "@type": "Person",
                "name": "Emma Johansson"
            }
        ],
        "spouse": {
            "@type": "Person",
            "name": "Greta Kastrup",
            "occupation": "Drawing teacher"
        },
        "children": [
            {
                "@type": "Person",
                "name": "Margareta",
                "birthDate": "1944"
            }
        ],
        "education": [
            {
                "@type": "EducationalOccupationalCredential",
                "name": "Stud:ex.",
                "credentialCategory": "high school education",
                "educationLevel": "HighSchool",
                "recognizedBy": "Vänersborg",
                "dateReceived": "1926"
            },
            {
                "@type": "EducationalOccupationalCredential",
                "name": "fil. kand.",
                "specialization": "-",
                "category": "degree",
                "recognizedBy": "Upps.",
                "dateReceived": "1930"
            },
            {
                "@type": "EducationalOccupationalCredential",
                "name": "fil. mag.",
                "specialization": "-",
                "category": "degree",
                "recognizedBy": "-",
                "dateReceived": "1933"
            }
        ],
        "jobTitle": "High school teacher",
        "memberOf": {
            "@type": "Organization",
            "name": "Swedish National Teachers' Association",
            "memberOf": {
                "@type": "Organization",
                "name": "Southern district"
            }
        },
        "workLocation": [
            {
                "@type": "Place",
                "name": "Katrineholms ensk. lärov."
            },
            {
                "@type": "Place",
                "name": "Gothenburg's eastern high school"
            },
            {
                "@type": "Place",
                "name": "Gothenburg's primary school"
            },
            {
                "@type": "Place",
                "name": "Luleå"
            },
            {
                "@type": "Place",
                "name": "Lund"
            },
            {
                "@type": "Place",
                "name": "Östra real in Stockholm"
            },
            {
                "@type": "Place",
                "name": "Karlskrona"
            },
            {
                "@type": "Place",
                "name": "Borås"
            },
            {
                "@type": "Place",
                "name": "Skara h. a. d."
            },
            {
                "@type": "Place",
                "name": "Trollhättan"
            }
        ],
        "startDate": [
            {
                "@type": "Event",
                "name": "vt. 35",
                "startDate": "1935",
                "endDate": "1935"
            },
            {
                "@type": "Event",
                "name": "ht. 35",
                "startDate": "1935",
                "endDate": "1935"
            },
            {
                "@type": "Event",
                "name": "1936",
                "startDate": "1936",
                "endDate": "1938"
            },
            {
                "@type": "Event",
                "name": "1940",
                "startDate": "1940",
                "endDate": "1941"
            },
            {
                "@type": "Event",
                "name": "1941",
                "startDate": "1941",
                "endDate": "1943"
            },
            {
                "@type": "Event",
                "name": "1943",
                "startDate": "1943",
                "endDate": "1946"
            },
            {
                "@type": "Event",
                "name": "1946",
                "startDate": "1946",
                "endDate": "1947"
            },
            {
                "@type": "Event",
                "name": "1947",
                "startDate": "1947",
                "endDate": "-"
            }
        ]
    }
}