{
    "original": "Andersson, Axel Gustaf Birger, redaktör, riksdagsman. Tidaholm, f. 10/ 6/0!l i Tidaholm av Axel A. o. Josefina Dahlgren. G. 40 m. Karin Sahl-ström. Barn: Äke f. 44. — Genomg. Brunnsviks folkhögsk. 27-28. Lokal-red. i Tidaholm f. tidn. Skaraborgaren sed. 26. Led. av riksd. första kamin, sed. 44, led. av stadsfullm. sed. 31, ordf. sed. 45, ordf. i beredn :utsk. sed. 35, led. av skolstyr. sed. 28, ordf. i dess und:visn:nd sed. 35, ordf. i Tida-holm’S arb :kommun sed. 29 o. i Skarab. soc:dem. ungd:distr. 29-38. Tillh. SAP, SSU, lOGT.",
    "translated": "Andersson, Axel Gustaf Birger, editor, member of parliament. Born on June 10th, 1901 in Tidaholm to parents Axel A. and Josefina Dahlgren. Married to Karin Sahlström since 1940, with one child named Äke born in 1944. Attended Brunnsvik Folk High School from 1927-1928. Local editor for the newspaper Skaraborgaren in Tidaholm since 1926. Member of parliament since 1944, member of city council since 1931 and chairman since 1945, chairman of the committee since 1935, member of the school board since 1928 and chairman of the education committee since 1935, chairman of Tidaholm's work committee since 1929 and Skaraborg's Social Democratic Youth District from 1929-1938. Belongs to the Swedish Social Democratic Party, Swedish Social Democratic Youth League, and the Independent Order of Good Templars.",
    "structured": {
        "@context": "https://schema.org",
        "@type": "Person",
        "name": "Axel Gustaf Birger Andersson",
        "birthDate": "1901-06-10",
        "birthPlace": {
            "name": "Tidaholm, Sweden",
            "latitude": 58.2,
            "longitude": 13.933333
        },
        "parents": [
            {
                "@type": "Person",
                "name": "Axel A. Andersson"
            },
            {
                "@type": "Person",
                "name": "Josefina Dahlgren"
            }
        ],
        "spouse": {
            "@type": "Person",
            "name": "Karin Sahlström"
        },
        "children": {
            "@type": "Person",
            "name": "Äke Andersson",
            "birthDate": "1944"
        },
        "education": [
            {
                "@type": "EducationalOrganization",
                "name": "Brunnsviks Folk High School",
                "startDate": "1927",
                "endDate": "1928"
            }
        ],
        "work": [
            {
                "@type": "Organization",
                "name": "Skaraborgaren",
                "jobTitle": "Local Editor",
                "startDate": "1926"
            },
            {
                "@type": "GovernmentOrganization",
                "name": "Swedish Parliament",
                "jobTitle": "Member of Parliament",
                "startDate": "1944"
            },
            {
                "@type": "GovernmentOrganization",
                "name": "City Council",
                "jobTitle": "Member",
                "startDate": "1931",
                "endDate": "1945"
            },
            {
                "@type": "GovernmentOrganization",
                "name": "City Council",
                "jobTitle": "Chairman",
                "startDate": "1945"
            },
            {
                "@type": "GovernmentOrganization",
                "name": "Committee",
                "jobTitle": "Chairman",
                "startDate": "1935"
            },
            {
                "@type": "GovernmentOrganization",
                "name": "School Board",
                "jobTitle": "Member",
                "startDate": "1928"
            },
            {
                "@type": "GovernmentOrganization",
                "name": "School Board",
                "jobTitle": "Chairman of Education Committee",
                "startDate": "1935"
            },
            {
                "@type": "GovernmentOrganization",
                "name": "Tidaholm's Work Committee",
                "jobTitle": "Chairman",
                "startDate": "1929"
            },
            {
                "@type": "GovernmentOrganization",
                "name": "Skaraborg's Social Democratic Youth District",
                "jobTitle": "Chairman",
                "startDate": "1929",
                "endDate": "1938"
            }
        ],
        "memberOf": [
            {
                "@type": "Organization",
                "name": "Swedish Social Democratic Party"
            },
            {
                "@type": "Organization",
                "name": "Swedish Social Democratic Youth League"
            },
            {
                "@type": "Organization",
                "name": "Independent Order of Good Templars"
            }
        ]
    }
}