{
    "original": "Aspelin, Gunnar, professor, Göteborg, f. 23/9/98 i S. Mellby, Krist. 1., av konstn. Karl A. o. Ellen Bergh. G, 23 m. Dagmar Scherstén. Barn: Herbert, Kurt, Erland, Marianne, Gert. — Stud :ex. 16, fil. kand. i Lund 17, fil. hc. 24, fil. dr 25. Doc. i prakt, filosofi s. å,, prof. i filosofi v. Gbgs högsk. sed. 36. Ordf. i Gbgsavd. av förb. Kämp. demokrati 42 o. 43. Skr.: Hegels prakt, filosofi und. åren 1800-1803 (25), Hegel (26), Historiens problem (26), Framistegsidén i franskt tankeliv fr. Descartes t. Condorcet (30), Utgångspunkterna f. Münsterbergs värdelära (30), Samhällsåskådn. o. partier (31), Tankelinjer o. trosformer (37), Lärob. i logik (38) o. i filosofisk hist. (43), Ralph Cudworth’s’ interpret, of Greek philos. (43) m. m. LHA, LVVS.",
    "translated": "Aspelin, Gunnar, professor, Gothenburg, born September 23, 1898 in S. Mellby, Krist. 1., son of artist Karl A. and Ellen Bergh. Married to Dagmar Scherstén in 1923 and had five children: Herbert, Kurt, Erland, Marianne, Gert. - Completed his undergraduate studies in 1916, graduated with a Bachelor of Arts degree from Lund University in 1917, received an honorary doctorate in 1924, and obtained a PhD in 1925. Became a lecturer in practical philosophy in the same year, was promoted to professor of philosophy at Gothenburg University in 1936. Served as the chairman of the Gothenburg branch of the League of Fighting Democracy in 1942 and 1943. Authored several publications including: Hegel's Practical Philosophy during the Years 1800-1803 (1925), Hegel (1926), The Problems of History (1926), The Idea of Progress in French Thought from Descartes to Condorcet (1930), Starting Points for Münsterberg's Value Theory (1930), Views of Society and Parties (1931), Lines of Thought and Forms of Belief (1937), Textbooks in Logic (1938) and in Philosophical History (1943), Ralph Cudworth's Interpretation of Greek Philosophy (1943), and more. Member of the Learned Society in Lund (LHA) and the Vasa Society for Humanities and Social Sciences (LVVS).",
    "structured": {
        "@context": "https://schema.org/",
        "@type": "Person",
        "name": "Gunnar Aspelin",
        "birthDate": "1898-09-23",
        "birthPlace": "S. Mellby, Krist. 1., Sweden",
        "deathDate": null,
        "parent": [
            {
                "@type": "Person",
                "name": "Karl A. Aspelin",
                "jobTitle": "Artist"
            },
            {
                "@type": "Person",
                "name": "Ellen Bergh"
            }
        ],
        "spouse": {
            "@type": "Person",
            "name": "Dagmar Scherstén",
            "marriageDate": "1923"
        },
        "children": [
            {
                "@type": "Person",
                "name": "Herbert Aspelin"
            },
            {
                "@type": "Person",
                "name": "Kurt Aspelin"
            },
            {
                "@type": "Person",
                "name": "Erland Aspelin"
            },
            {
                "@type": "Person",
                "name": "Marianne Aspelin"
            },
            {
                "@type": "Person",
                "name": "Gert Aspelin"
            }
        ],
        "sameAs": [
            "LHA",
            "LVVS"
        ],
        "jobTitle": "Professor of Philosophy",
        "affiliation": {
            "@type": "Organization",
            "name": "Gothenburg University"
        },
        "education": [
            {
                "@type": "EducationalOccupationalCredential",
                "credentialCategory": "Stud:ex",
                "educationLevel": null,
                "educationalProgramMode": null,
                "educationalSpecialization": null,
                "issuer": null,
                "startDate": "1916"
            },
            {
                "@type": "EducationalOccupationalCredential",
                "credentialCategory": "Bachelor of Arts",
                "educationLevel": "Undergraduate",
                "educationalProgramMode": null,
                "educationalSpecialization": null,
                "issuer": {
                    "@type": "PostsecondaryOrganization",
                    "name": "Lund University"
                },
                "startDate": "1917"
            },
            {
                "@type": "EducationalOccupationalCredential",
                "credentialCategory": "Honorary Doctorate",
                "educationLevel": null,
                "educationalProgramMode": null,
                "educationalSpecialization": null,
                "issuer": null,
                "startDate": "1924"
            },
            {
                "@type": "EducationalOccupationalCredential",
                "credentialCategory": "PhD",
                "educationLevel": null,
                "educationalProgramMode": null,
                "educationalSpecialization": null,
                "issuer": null,
                "startDate": "1925"
            },
            {
                "@type": "EducationalOccupationalCredential",
                "credentialCategory": "Lecturer",
                "educationLevel": null,
                "educationalProgramMode": null,
                "educationalSpecialization": "Practical Philosophy",
                "issuer": null,
                "startDate": "1925"
            },
            {
                "@type": "EducationalOccupationalCredential",
                "credentialCategory": "Professor",
                "educationLevel": null,
                "educationalProgramMode": null,
                "educationalSpecialization": "Philosophy",
                "issuer": {
                    "@type": "PostsecondaryOrganization",
                    "name": "Gothenburg University"
                },
                "startDate": "1936"
            }
        ],
        "memberOf": {
            "@type": "Organization",
            "name": "League of Fighting Democracy",
            "memberOf": {
                "@type": "Organization",
                "name": "Gothenburg branch"
            },
            "startDate": "1942",
            "endDate": "1943"
        },
        "publication": [
            {
                "@type": "ScholarlyArticle",
                "name": "Hegel's Practical Philosophy during the Years 1800-1803",
                "datePublished": "1925"
            },
            {
                "@type": "ScholarlyArticle",
                "name": "Hegel",
                "datePublished": "1926"
            },
            {
                "@type": "ScholarlyArticle",
                "name": "The Problems of History",
                "datePublished": "1926"
            },
            {
                "@type": "ScholarlyArticle",
                "name": "The Idea of Progress in French Thought from Descartes to Condorcet",
                "datePublished": "1930"
            },
            {
                "@type": "ScholarlyArticle",
                "name": "Starting Points for Münsterberg's Value Theory",
                "datePublished": "1930"
            },
            {
                "@type": "ScholarlyArticle",
                "name": "Views of Society and Parties",
                "datePublished": "1931"
            },
            {
                "@type": "ScholarlyArticle",
                "name": "Lines of Thought and Forms of Belief",
                "datePublished": "1937"
            },
            {
                "@type": "ScholarlyArticle",
                "name": "Textbooks in Logic",
                "datePublished": "1938"
            },
            {
                "@type": "ScholarlyArticle",
                "name": "Textbooks in Philosophical History",
                "datePublished": "1943"
            },
            {
                "@type": "ScholarlyArticle",
                "name": "Ralph Cudworth's Interpretation of Greek Philosophy",
                "datePublished": "1943"
            }
        ]
    }
}