{
    "original": "Anderson, Curt Herman, teol. o. fil kand., kyrkoherde. Sandhem, f. 15/12/ 03 i Borås. G. 34 m. Margareta Boström. — Stud :ex. i Gbg 26, fil. kand. i Lund 28, teol. kand. 31, prakt. teol. prov 31, prästv. i Skara 32. V. past. i N. Äsarps past. 32, i Gudhem 33, ikomminister i Härja 53, kyrkoherde i Sandhem fr. 41. Ordf. i samt-l. förs. kyrkost. o. past :kyrkost., i samtl. kyrkoråd, i skolråd., bibi:styr. m. m.",
    "translated": "Anderson, Curt Herman, theologian and Phil. Licentiate, vicar. Born on December 15th, 1903 in Borås. Married to Margareta Boström in 1934. He studied in Gothenburg and obtained his B.A. in 1926, Phil. Licentiate in Lund in 1928, Theology Licentiate in 1931 and passed his practical theological exam in 1931. He was ordained in Skara in 1932. He served as a deputy pastor in N. Äsarps in 1932, in Gudhem in 1933, and as a minister in Härja in 1953. He was appointed as a vicar in Sandhem from 1941. He was the chairman of the church board and pastor board, he also served as a member of the school board, the library committee and more.",
    "structured": {
        "@context": "https://schema.org",
        "@type": "Person",
        "name": "Curt Herman Anderson",
        "jobTitle": "Vicar",
        "birthDate": "1903-12-15",
        "birthPlace": {
            "name": "Borås",
            "latitude": 57.7210839,
            "longitude": 12.9407407
        },
        "spouse": {
            "@type": "Person",
            "name": "Margareta Boström",
            "dateMarried": "1934"
        },
        "education": [
            {
                "@type": "EducationalOccupationalCredential",
                "educationalLevel": "Bachelor's degree",
                "major": "Unknown",
                "dateAwarded": "1926",
                "awardingInstitution": "Gothenburg"
            },
            {
                "@type": "EducationalOccupationalCredential",
                "educationalLevel": "Phil. Licentiate",
                "major": "Unknown",
                "dateAwarded": "1928",
                "awardingInstitution": "Lund"
            },
            {
                "@type": "EducationalOccupationalCredential",
                "educationalLevel": "Theology Licentiate",
                "major": "Unknown",
                "dateAwarded": "1931"
            },
            {
                "@type": "EducationalOccupationalCredential",
                "name": "Practical Theological Exam",
                "datePassed": "1931"
            },
            {
                "@type": "EducationalOccupationalCredential",
                "name": "Ordination",
                "dateAwarded": "1932",
                "awardingInstitution": "Skara"
            }
        ],
        "memberOf": [
            {
                "@type": "Organization",
                "name": "N. Äsarps past.",
                "memberOf": "Deputy Pastor",
                "startDate": "1932",
                "endDate": "1933"
            },
            {
                "@type": "Organization",
                "name": "Gudhem",
                "memberOf": "Deputy Pastor",
                "startDate": "1933",
                "endDate": "1953"
            },
            {
                "@type": "Organization",
                "name": "Härja",
                "memberOf": "Minister",
                "startDate": "1953"
            },
            {
                "@type": "Organization",
                "name": "Sandhem",
                "memberOf": "Vicar",
                "startDate": "1941"
            },
            {
                "@type": "Organization",
                "name": "Church Board",
                "memberOf": "Chairman"
            },
            {
                "@type": "Organization",
                "name": "Pastor Board",
                "memberOf": "Chairman"
            },
            {
                "@type": "Organization",
                "name": "School Board",
                "memberOf": "Member"
            },
            {
                "@type": "Organization",
                "name": "Library Committee",
                "memberOf": "Member"
            }
        ]
    }
}