{
    "original": "BERGLUND, INGE G,\nläroverksadjunkt, Lund, f i Karlshamn 30/3/15 av\növerlär Gustav B o Martha Lagerqvist.\nStud:ex Karlskrona 36’, fil mag Lund 40,\nadj Katedralsk Lund sed 51. - Utg lärob\ni eng f gymn.\n\nGift 41 m Amie-Sofie Zethraeus, dtr t\nmajor J H Z o Anna Leche. - Barn:\nKerstin f 43, Bengt f 46, Hans f 52.\n\nBERGLUND, N KÅRE G:SON,\nlaborator, överläkare, Lund fi Sthlm 2/4/17\nav l:e byråing Gustaf B o Agnes\nJohansson.\n\nStud:ex Gbg 35, med kand Upps 39, med\nlic Sthlm 44, med dr 56, doc i\nreumato-logi Karol inst 57-64, eo doc :tjänst där\n60-64; stud i reumatol USA 57, underläk\n45 o e läk med avd Sthlms garn :sjh\n45-48, underläk med avd Södersjh 48-54, l:e\nunderläk reumatol klin Karol sjh 54-59,\nbitr överläk där 60-64, överläk reumatol\nklin Lunds las sed 64, labor Lunds univ\nsed 64. - Skr i reumatologi,\nimmuno-logi o endokrinologi.\nGift 2) 64 m Kirstine Borum f 25.\n-Barn: Jonas f 46, Petter f 47.\n\nBERGLUND, ULF E V, ingenjör,\nAr-löv, f i Orsa, Kopparb l, 2/7/23 av\npostmast Yngve B o Magda Burén.\nIng :ex Tekn lärov Norrkpg 46, bilinsp\nstat bilinsp 49, huvudstat :ch ab Sv\nbilprovning Malmöh 1.\n\nGift 51 m Inga-Karin Andersson, dtr t\nlantbr Ernst A o Hedvig A. - Barn:\nKristina o Gunilla ff 55, Caroline f 59.\n\nBERGLÖF, FRANS-ERIK, leg läkare,\n\nLund, f i Gävle 10/2/24 av landsfiskal\n\nTor B o Maria Lingvall.\n\nStud:ex Sigtuna 44, med kand 48’ o med\n\nlic Upps 56, underläk med avd Södersjh\n\n57, Lunds las sed 60. - Bat:läk flk res\n\nsed 57.\n\nGift 55 m leg läk Kerstin Eriksson f 30,\n\ndtr  t  överbibl:ien,  fil  dr  Ruben E  o\n\nGreta Bergman. - Barn: Erik f 57, Klas\n\nf 58, Staffan f 60, Tord f 61, Lars f 63,\n\nKerstin f 66.\n\n",
    "structured": {
        "0": {
            "full_name": "Inge G Berglund",
            "location": "Lund",
            "occupation": "läroverksadjunkt",
            "birth_details": {
                "date": "30/03/1915",
                "place": "Karlshamn",
                "parents": "överlär Gustav B o Martha Lagerqvist"
            },
            "education": [
                {
                    "degree": "Stud:ex",
                    "year": "1936",
                    "institution": "Karlskrona"
                },
                {
                    "degree": "fil mag",
                    "year": "1940",
                    "institution": "Lund"
                }
            ],
            "career": [
                {
                    "position": "adj Katedralsk Lund",
                    "years": {
                        "start_year": 1951
                    }
                }
            ],
            "family": {
                "spouse": "Amie-Sofie Zethraeus",
                "marriage_year": "1941",
                "children": [
                    {
                        "name": "Kerstin",
                        "birth_year": "1943"
                    },
                    {
                        "name": "Bengt",
                        "birth_year": "1946"
                    },
                    {
                        "name": "Hans",
                        "birth_year": "1952"
                    }
                ]
            }
        },
        "1": {
            "full_name": "N Kåre G:son Berglund",
            "location": "Lund fi Sthlm",
            "occupation": "laborator, överläkare",
            "birth_details": {
                "date": "02/04/1917",
                "place": "Sthlm",
                "parents": "l:e byråing Gustaf B o Agnes Johansson"
            },
            "education": [
                {
                    "degree": "Stud:ex",
                    "year": "1935",
                    "institution": "Gbg"
                },
                {
                    "degree": "med kand",
                    "year": "1939",
                    "institution": "Upps"
                },
                {
                    "degree": "med lic",
                    "year": "1944",
                    "institution": "Sthlm"
                },
                {
                    "degree": "med dr",
                    "year": "1956"
                }
            ],
            "career": [
                {
                    "position": "doc i reumato-logi Karol inst",
                    "years": {
                        "start_year": 1957,
                        "end_year": 1964
                    }
                },
                {
                    "position": "eo doc :tjänst där",
                    "years": {
                        "start_year": 1960,
                        "end_year": 1964
                    }
                },
                {
                    "position": "bitr överläk",
                    "years": {
                        "start_year": 1960,
                        "end_year": 1964
                    },
                    "organization": "Karol sjh"
                },
                {
                    "position": "överläk reumatol klin Lunds las",
                    "years": {
                        "start_year": 1964
                    },
                    "organization": "Lunds univ"
                },
                {
                    "position": "labor Lunds univ",
                    "years": {
                        "start_year": 1964
                    }
                }
            ],
            "family": {
                "spouse": "Kirstine Borum",
                "marriage_year": "1964",
                "children": [
                    {
                        "name": "Jonas",
                        "birth_year": "1946"
                    },
                    {
                        "name": "Petter",
                        "birth_year": "1947"
                    }
                ]
            }
        },
        "2": {
            "full_name": "Ulf E V Berglund",
            "location": "Ar-löv",
            "occupation": "ingenjör",
            "birth_details": {
                "date": "02/07/1923",
                "place": "Orsa, Kopparb l",
                "parents": "postmast Yngve B o Magda Burén"
            },
            "education": [
                {
                    "degree": "Ing :ex",
                    "year": "1946",
                    "institution": "Tekn lärov Norrkpg"
                },
                {
                    "degree": "bilinsp",
                    "year": "1949",
                    "institution": "stat bilinsp"
                }
            ],
            "career": [
                {
                    "position": "huvudstat :ch ab Sv bilprovning Malmöh",
                    "years": {
                        "start_year": 1
                    }
                }
            ],
            "family": {
                "spouse": "Inga-Karin Andersson",
                "marriage_year": "1951",
                "children": [
                    {
                        "name": "Kristina",
                        "birth_year": "1955"
                    },
                    {
                        "name": "Gunilla",
                        "birth_year": "1955"
                    },
                    {
                        "name": "Caroline",
                        "birth_year": "1959"
                    }
                ]
            }
        },
        "3": {
            "full_name": "Frans-Erik Berglöf",
            "location": "Lund",
            "occupation": "leg läkare",
            "birth_details": {
                "date": "10/02/1924",
                "place": "Gävle",
                "parents": "landsfiskal Tor B o Maria Lingvall"
            },
            "education": [
                {
                    "degree": "Stud:ex",
                    "year": "1944",
                    "institution": "Sigtuna"
                },
                {
                    "degree": "med kand",
                    "year": "1948",
                    "institution": "Upps"
                },
                {
                    "degree": "med lic",
                    "year": "1956"
                }
            ],
            "career": [
                {
                    "position": "underläk med avd Södersjh",
                    "years": {
                        "start_year": 1957
                    }
                },
                {
                    "position": "Lunds las",
                    "years": {
                        "start_year": 1960
                    }
                },
                {
                    "position": "Bat:läk flk res",
                    "years": {
                        "start_year": 1957
                    }
                }
            ],
            "family": {
                "spouse": "leg läk Kerstin Eriksson",
                "marriage_year": "1955",
                "children": [
                    {
                        "name": "Erik",
                        "birth_year": "1957"
                    },
                    {
                        "name": "Klas",
                        "birth_year": "1958"
                    },
                    {
                        "name": "Staffan",
                        "birth_year": "1960"
                    },
                    {
                        "name": "Tord",
                        "birth_year": "1961"
                    },
                    {
                        "name": "Lars",
                        "birth_year": "1963"
                    },
                    {
                        "name": "Kerstin",
                        "birth_year": "1966"
                    }
                ]
            }
        }
    }
}