{
    "original": "BJÖRCK, STIG L, disponent, Ystad,\nf i Kristianstad 1/6/28 av polisman\nAnton B o Elsa Holmberg.\nIng :ex HTL Malmö 51, ing Kockums\nmek verkst ab Malmö 53, försäljn:ing ab\nBahco Enkpg 54, inköpsch Persöner ab\nYstad 56&gt;, ch projektavd där 60, disp o\nch Y-Man inredn ab sed 61. - Led\nbe-svärsnd o arb:lösh:nd 63. - Medl\nFrim-O. - Hobby: golf.\n\nGift 58 m Gunilla Peters f 36, dtr t disp\nGunnar P o Ingrid Åhman. - Barn: Pia\nf 65.\n\nBJÖRK, VALFRID, direktör, Tyringe,\nf i Tyringe 7/2/05 av dir C-E B o Eva\nNilsson.\n\nIng:ex TGG Gbg 32; banktjm Nord\nhdlsbkn 20-25, prakt USA 25-29, v\nverkst dir o ch chuckavd Skand\nverk-tygsfabr ab 33-46, verkst dir o inneh\nSkand chuckfabr ab sed 46. - Fd led\nkomm:fullm m m, led samarb :ndn\nTyringe. - Hobby: tennis.\nGi/f 34 m Astrid Lindström f 07, dtr t\nciviling Gustaf L o Sigrid Ståhl. - Barn:\nElse f 37, Gösta f 43.\n\nBJÖRCK, J A WERNER,  disponent,\n\nMalmö, f i Lübeck, Tyskl, 26/7/06 av\ngrossh August B o Alice Vorreau.\nAnst ab Malmö stora walsqvarn 22,\ndriftsled a/s Valsemöllen O’lympia\nRanders 35, Jul A Jörgensen a/s Århus 4!3,\ndriftsch Upps ångqvarns ab 44, disp där\n57, disp o tekn ch ab Kungsörnen Sthlm\n62, ab Kungsörnen Malmö sed 63.\n- Presid Nord cerealkem fören sv sekt.\nGift 3-6 m Svea Svensson f 04, dtr t\nbyggm H S o h h. - Barn: Håkan f 44,\nPeter f 49.\n\nBJÖRK, VILLIAM E,\nträdgårdsmästare, riksdagsman, Påarp, f i VittskÖvle,\nKrist l, 30/3/23 av konstnär Wilborg B\no Ellen Hellberg.\n\nGmg Önnestads trädg:sk 41, trädg:arb\n41-46, trädg:mast o inneh Björks trädg\nsed 46. - Ordf Trädg:hallen i Hbg ekon\nfören sed 61, styr:led Sv:es hdlsträdg:-\n\nförb sed 63. - AK sed 65, suppl\nriksbks-fullm sed 65, jordbr:utsk o l:a lagutsk\nsed 65, led Jordbr forskn :råd sed 65, led\nMalmöh l landst sed 58, ordf dess styr f\nyrkesundervisn sed 63, led dess pers:- o\norg:nd sed 66, ordf komm :ndn Mörarp\nsed 57. - Hobby: naturvård.\nGift 46 m Solvig Lüning f 21, dtr t disp\nOskar L o Selma Askenström. - Barn:\nTeddy f 51, Ellen f 55.\n\n",
    "structured": {
        "0": {
            "full_name": "Stig L Björck",
            "location": "Ystad",
            "occupation": "disponent",
            "birth_details": {
                "date": "01/06/1928",
                "place": "Kristianstad",
                "parents": "Anton B o Elsa Holmberg"
            },
            "education": [
                {
                    "degree": "HTL Malmö",
                    "year": "1951",
                    "institution": "Kockums mek verkst ab Malmö"
                }
            ],
            "career": [
                {
                    "position": "försäljn:ing",
                    "years": {
                        "start_year": 1954,
                        "end_year": 1956
                    },
                    "organization": "ab Bahco Enkpg"
                },
                {
                    "position": "inköpsch",
                    "years": {
                        "start_year": 1956,
                        "end_year": 1960
                    },
                    "organization": "Persöner ab Ystad"
                },
                {
                    "position": "disp o ch",
                    "years": {
                        "start_year": 1961
                    },
                    "organization": "Y-Man inredn ab"
                }
            ],
            "family": {
                "spouse": "Gunilla Peters",
                "marriage_year": "1958",
                "children": [
                    {
                        "name": "Pia",
                        "birth_year": "1965"
                    }
                ]
            },
            "hobbies": [
                "golf"
            ]
        },
        "1": {
            "full_name": "Valfrid Björk",
            "location": "Tyringe",
            "occupation": "direktör",
            "birth_details": {
                "date": "07/02/1905",
                "place": "Tyringe",
                "parents": "dir C-E B o Eva Nilsson"
            },
            "education": [
                {
                    "degree": "TGG Gbg",
                    "year": "1932",
                    "institution": "banktjm Nord hdlsbkn"
                }
            ],
            "career": [
                {
                    "position": "verkst dir o ch chuckavd",
                    "years": {
                        "start_year": 1933,
                        "end_year": 1946
                    },
                    "organization": "Skand verktygsfabr ab"
                },
                {
                    "position": "verkst dir o inneh",
                    "years": {
                        "start_year": 1946
                    },
                    "organization": "Skand chuckfabr ab"
                }
            ],
            "family": {
                "spouse": "Astrid Lindström",
                "marriage_year": "1934",
                "children": [
                    {
                        "name": "Else",
                        "birth_year": "1937"
                    },
                    {
                        "name": "Gösta",
                        "birth_year": "1943"
                    }
                ]
            },
            "hobbies": [
                "tennis"
            ]
        },
        "2": {
            "full_name": "J A Werner Björck",
            "location": "Malmö",
            "occupation": "disponent",
            "birth_details": {
                "place": "Lübeck, Tyskl"
            },
            "career": [
                {
                    "position": "driftsled",
                    "years": {
                        "start_year": 1935,
                        "end_year": 1943
                    },
                    "organization": "a/s Valsemöllen O’lympia Randers"
                },
                {
                    "position": "disponent",
                    "years": {
                        "start_year": 1957
                    },
                    "organization": "ångqvarns ab"
                },
                {
                    "position": "ab Kungsörnen Malmö",
                    "years": {
                        "start_year": 1963
                    }
                }
            ],
            "family": {
                "spouse": "Svea Svensson",
                "marriage_year": "1953",
                "children": [
                    {
                        "name": "Håkan",
                        "birth_year": "1944"
                    },
                    {
                        "name": "Peter",
                        "birth_year": "1949"
                    }
                ]
            }
        },
        "3": {
            "full_name": "Villiam E Björk",
            "location": "Påarp",
            "occupation": "trädgårdsmästare, riksdagsman",
            "birth_details": {
                "place": "Vittskövle, Krist"
            },
            "career": [
                {
                    "position": "trädg:mast o inneh",
                    "years": {
                        "start_year": 1946
                    },
                    "organization": "Björks trädg"
                }
            ],
            "family": {
                "spouse": "Solvig Lüning",
                "marriage_year": "1946",
                "children": [
                    {
                        "name": "Teddy",
                        "birth_year": "1951"
                    },
                    {
                        "name": "Ellen",
                        "birth_year": "1955"
                    }
                ]
            },
            "hobbies": [
                "naturvård"
            ]
        }
    }
}