{
    "original": "BERGENUDD, GOTTFRID W,\narkitekt SAR, Hässleholm, f i Boden 10/2/17\nav byggm Lars Eriksson o Alma\nGustavsson.\n\nStud:ex Luleå 38, KTH 45, stadsarkit\nPiteå o Norrb s distr 47-59, Boden\n51-59, Hässleholm sed 59. - Bl arb:\nmedb:-hus, stadshus, idr :hall o ishall Boden,\n\nidr :hall o skolanläggn Piteå o Älvsbyn,\nålderd:hem Piteå, Boden o Älvsbyn,\nÖs^-tercentrum Malmö. - Medl Rotary, Odd\nFellow. - Hobby: sport.\nGift 43 m Kerstin Persson. - Barn:\nGunilla f 45, Hans f 47.\n\nBERGER, ARTHUR G,\nläroverksadjunkt, Malmö, f i Dalskog, Älvsb l, 27/4/\n21 av folkskollär Conrad B o Anna\nZetterberg.\n\nStud:ex Vänersborg 42, fil mag Lund 56,\neo adj Trelleborgs hal 56^60, adj komm\nflicksk Malmö 60, Källängens lärov sed\n61. - Utg: läroböcker i tyska f grundsk\nhögstad. - Hobby: renässans- o\nbarockmusik samt motsvarande instrumenttyper.\nGift 49 m Kerstin Andersson f 24, dtr t\nlinjernas t Elof A o Gunhild Mårtensson.\n- Barn: Karin f 53, Gertrud f 58.\n\nBERGGREN, K EINAR J, advokat,\n\nOsby, f i Karlslunda förs, Kalmar l,\n28/1/13 av kyrkoh Karl B o Ellen\nLundgren.\n\nStud:ex Kalmar 31, jur kand Lund 39,\ntingstjg V Göinge doms 39-41, aman\narméförvaltn:s civilbyrå 42, bitr jur\nadv:-firman Stjerndahl &amp; Wikborn\n43-47, egen adv:byrå Osby sed 47. - LSA\n45. - Led Osby byggn :nå sed 55,\nkomm:-ndn o komm:fullm sed 59.\nGift 2) 60 m Birgit Rasmusson. - Barn:\ni l:a akt Eva Margareta f 48, Per Einar\nf 50, Ane-Charlotte f 54, i 2 :a akt Ann\nIngrid Ursula f 61.\n\n",
    "structured": {
        "0": {
            "full_name": "Gottfrid W Bergenudd",
            "location": "Hässleholm",
            "occupation": "Arkitekt SAR",
            "birth_details": {
                "date": "10/02/1917",
                "place": "Boden"
            },
            "education": [
                {
                    "degree": "Stud:ex",
                    "year": "1938",
                    "institution": "Luleå"
                },
                {
                    "degree": "KTH",
                    "year": "1945",
                    "institution": "KTH"
                }
            ],
            "career": [
                {
                    "position": "Stadsarkit",
                    "years": {
                        "start_year": 1947,
                        "end_year": 1959
                    },
                    "organization": "Piteå o Norrb s distr"
                },
                {
                    "position": "Idr :hall o ishall",
                    "years": {
                        "start_year": 1951,
                        "end_year": 1959
                    },
                    "organization": "Boden"
                },
                {
                    "position": "Idr :hall o skolanläggn",
                    "years": {
                        "start_year": 1947,
                        "end_year": 1959
                    },
                    "organization": "Piteå o Älvsbyn"
                },
                {
                    "position": "Ålderd:hem",
                    "years": {
                        "start_year": 1947,
                        "end_year": 1959
                    },
                    "organization": "Piteå, Boden o Älvsbyn"
                },
                {
                    "position": "Ös^-tercentrum",
                    "years": {
                        "start_year": null,
                        "end_year": null
                    },
                    "organization": "Malmö"
                }
            ],
            "family": {
                "spouse": "Kerstin Persson",
                "marriage_year": "1943",
                "children": [
                    {
                        "name": "Gunilla",
                        "birth_year": "1945"
                    },
                    {
                        "name": "Hans",
                        "birth_year": "1947"
                    }
                ]
            }
        },
        "1": {
            "full_name": "Arthur G Berger",
            "location": "Malmö",
            "occupation": "Läroverksadjunkt",
            "birth_details": {
                "date": "27/04/1921",
                "place": "Dalskog, Älvsb l"
            },
            "education": [
                {
                    "degree": "Stud:ex",
                    "year": "1942",
                    "institution": "Vänersborg"
                },
                {
                    "degree": "Fil mag",
                    "year": "1956",
                    "institution": "Lund"
                }
            ],
            "career": [
                {
                    "position": "Eo adj",
                    "years": {
                        "start_year": 1956,
                        "end_year": 1960
                    },
                    "organization": "Trelleborgs hal"
                },
                {
                    "position": "Adj komm flicksk",
                    "years": {
                        "start_year": 1960,
                        "end_year": 1961
                    },
                    "organization": "Malmö"
                },
                {
                    "position": "Källängens lärov",
                    "years": {
                        "start_year": 1961,
                        "end_year": null
                    },
                    "organization": null
                }
            ],
            "family": {
                "spouse": "Kerstin Andersson",
                "marriage_year": "1949",
                "children": [
                    {
                        "name": "Karin",
                        "birth_year": "1953"
                    },
                    {
                        "name": "Gertrud",
                        "birth_year": "1958"
                    }
                ]
            }
        },
        "2": {
            "full_name": "K Einar J Berggren",
            "location": "Osby",
            "occupation": "Advokat",
            "birth_details": {
                "date": "28/01/1913",
                "place": "Karlslunda förs, Kalmar l"
            },
            "education": [
                {
                    "degree": "Stud:ex",
                    "year": "1931",
                    "institution": "Kalmar"
                },
                {
                    "degree": "Jur kand",
                    "year": "1939",
                    "institution": "Lund"
                }
            ],
            "career": [
                {
                    "position": "Tingstjg",
                    "years": {
                        "start_year": 1939,
                        "end_year": 1941
                    },
                    "organization": "V Göinge doms"
                },
                {
                    "position": "Aman",
                    "years": {
                        "start_year": 1942,
                        "end_year": null
                    },
                    "organization": "Arméförvaltn:s civilbyrå"
                },
                {
                    "position": "Bitr jur adv",
                    "years": {
                        "start_year": 1943,
                        "end_year": 1947
                    },
                    "organization": "Stjerndahl & Wikborn"
                },
                {
                    "position": "Egen adv:byrå",
                    "years": {
                        "start_year": 1947,
                        "end_year": null
                    },
                    "organization": "Osby"
                }
            ],
            "family": {
                "spouse": "Birgit Rasmusson",
                "marriage_year": null,
                "children": [
                    {
                        "name": "Eva Margareta",
                        "birth_year": "1948"
                    },
                    {
                        "name": "Per Einar",
                        "birth_year": "1950"
                    },
                    {
                        "name": "Ane-Charlotte",
                        "birth_year": "1954"
                    },
                    {
                        "name": "Ann Ingrid Ursula",
                        "birth_year": "1961"
                    }
                ]
            }
        }
    }
}