{
    "original": "BARNEKOW, OVE A R, friherre,\ndirektör, Eslöv, f i Kastberga, Malmöh\nl, 11/11/06 av ryttm, frih Adolf B o\nfrih:an Eva Wrede.\n\nVerkst dir ab Lantbrukskemi Malmö.\n-Ag Gryby gård Eslöv.\nGift 39 m Maud Uggla f 14. - Barn:\nChristoffer f 40, Charlotte f 43.\n\nBARR, LARS F K :SON, civilingenjör,\n\ndisponent, Landskrona, f i Sthlm 14/7/18\nav fil dr Knut B o Agneta Nohre.\nStud:ex 37, KTH 41, res:off:ex 42;\nforskn:ing Asea Sthlm 41, Sv\naloxidver-ken ab Sundsvall 43, lab :ch där 45,\ndrifting St Kopparb bergsl ab Skutskär\n47, platsch ab Fören superfosfatfabr\nUddevalla 51, Landskrona sed 60. -\nStyr:-ordf Landskrona stuveri ab sed 65 (v\nordf 60-64). - V ordf hamnstyr 65, led\nbyggn :nd, styr :led Gbgs o Boh landst\ncentraltvätt 55-59. - Medl Rotary (presid\nUddevalla 57-58, Landskrona 64-65).\n-Skr: upps i fackpress. - Hobby: ridsport.\nGift 45 m Kristin Colbjörnsen f 23, dtr\nt dir Bjarne C o Rannveig Bruusgaard.\n-Barn: Agneta f 46, Karen f 49.\n\nBARRKLEV, TORE L, adjunkt,\nLjungbyhed, f i Piteå 17/9/31 av folkskolinsp\nErnst Nilsson o Sigrid Berglund.\nStud:ex Hbg 51, folkskollär :ex Hbg 54,\nfil mag Lund 60; folkskollär Mörarp o\nBårslöv  54-56,  e adj  Perstorp 60,  adj\nFÖFS (krigsflygsk) Ljungbyhed sed 61.\nGift 57 m Gun Fredriksson f 31, dtr t\ndisp Hilding F o Gerda Persson. - Barn:\nLars f 63, Titti f 66.\n\nBARTON, JOHAN S, arkitekt SAR,\n\nMalmö, f i Sthlm 31/3/05 av byggm\nAugust B o Charlotte Eklund.\nTekn skolan Sthlm 26, KTH 39;\narkit:-stud o prakt USA 26-31, anst arkit Carl\nGüettler Sthlm 32-35, arkit SAR Hakon\nAhlberg 35-41, flygförvaltn:s byggn :avd\n41-44, inneh John Barton arkit:kont ab\nMalmö sed 45; stadsarkit Svalöv sed 45\n\n0  Sjöbo kpg sed 55. - Sakk i sjh:frågor\n\n1  samb m landst :s övertag av statl\nmen-talsjh. - Medl Knutsgillet i Malmö, Stora\nAmarantherO. - Bl arb: Philipsons\nbilpalats i bl a Malmö o Västerås, Seans\nslakterianläggn Ängelholm,\nkommunalhus Skromberga, forskn:- o läkarstation\nDalby samt ett flert sjukhem f krön\nsjuka o läkarstationer. - Utm: Hed :medb\nNew Orleans 60. - Hobby: golf.\n\nGift 36 m Anna-Greta Thorell f 03, dtr t\ning Alvar T o Kristina Schyman. - Barn:\nAnita f 37.\n\n",
    "structured": {
        "0": {
            "full_name": "BARNEKOW, OVE A R, friherre",
            "location": "Eslöv",
            "occupation": "direktör",
            "birth_details": {
                "date": "11/11/1906",
                "place": "Kastberga, Malmöh",
                "parents": "ryttm, frih Adolf B o frih:an Eva Wrede"
            },
            "education": {
                "degree": "Verkst dir ab Lantbrukskemi Malmö",
                "year": "NULL",
                "institution": "NULL"
            },
            "career": [
                {
                    "position": "Ag Gryby gård Eslöv",
                    "years": {
                        "start_year": "NULL",
                        "end_year": "NULL"
                    },
                    "organization": "NULL"
                }
            ],
            "family": {
                "spouse": "Maud Uggla",
                "marriage_year": "1939",
                "children": [
                    {
                        "name": "Christoffer",
                        "birth_year": "1940"
                    },
                    {
                        "name": "Charlotte",
                        "birth_year": "1943"
                    }
                ]
            }
        },
        "1": {
            "full_name": "BARR, LARS F K :SON",
            "location": "Landskrona",
            "occupation": "disponent",
            "birth_details": {
                "date": "14/07/1918",
                "place": "Sthlm",
                "parents": "fil dr Knut B o Agneta Nohre"
            },
            "education": {
                "degree": "Stud:ex",
                "year": "1941",
                "institution": "KTH"
            },
            "career": [
                {
                    "position": "Styr:-ordf Landskrona stuveri ab",
                    "years": {
                        "start_year": 1965,
                        "end_year": null
                    },
                    "organization": "NULL"
                }
            ],
            "family": {
                "spouse": "Kristin Colbjörnsen",
                "marriage_year": "1945",
                "children": [
                    {
                        "name": "Agneta",
                        "birth_year": "1946"
                    },
                    {
                        "name": "Karen",
                        "birth_year": "1949"
                    }
                ]
            }
        },
        "2": {
            "full_name": "BARRKLEV, TORE L",
            "location": "Ljungbyhed",
            "occupation": "adjunkt",
            "birth_details": {
                "date": "17/09/1931",
                "place": "Piteå",
                "parents": "folkskolinsp Ernst Nilsson o Sigrid Berglund"
            },
            "education": [
                {
                    "degree": "Stud:ex",
                    "year": "1954",
                    "institution": "Hbg"
                },
                {
                    "degree": "folkskollär:ex",
                    "year": "1954",
                    "institution": "Hbg"
                },
                {
                    "degree": "fil mag",
                    "year": "1960",
                    "institution": "Lund"
                }
            ],
            "career": [
                {
                    "position": "adj FÖFS (krigsflygsk) Ljungbyhed",
                    "years": {
                        "start_year": 1961,
                        "end_year": null
                    },
                    "organization": "NULL"
                }
            ],
            "family": {
                "spouse": "Gun Fredriksson",
                "marriage_year": "1957",
                "children": [
                    {
                        "name": "Lars",
                        "birth_year": "1963"
                    },
                    {
                        "name": "Titti",
                        "birth_year": "1966"
                    }
                ]
            }
        },
        "3": {
            "full_name": "BARTON, JOHAN S",
            "location": "Malmö",
            "occupation": "arkitekt SAR",
            "birth_details": {
                "date": "31/03/1905",
                "place": "Sthlm",
                "parents": "byggm August B o Charlotte Eklund"
            },
            "education": [
                {
                    "degree": "Arkitekt",
                    "year": "1939",
                    "institution": "KTH"
                }
            ],
            "career": [
                {
                    "position": "inneh John Barton arkit:kont ab Malmö",
                    "years": {
                        "start_year": 1945,
                        "end_year": null
                    },
                    "organization": "NULL"
                }
            ],
            "family": {
                "spouse": "Anna-Greta Thorell",
                "marriage_year": "1936",
                "children": [
                    {
                        "name": "Anita",
                        "birth_year": "1937"
                    }
                ]
            }
        }
    }
}