{
    "original": "BOGYO, HVAD AR, ingenjör, Malmö,\nf i Budapest 31/7/36 av folkskollärarna\nT B o Hermine Lenhard.\nIng:ex Tekn gymn Budapest 55, ing ung\nstat jv 55-56, Centerlöf &amp; Holmberg ab\n57, Nils Centerlöf ab sed 62. - Deläg\nBalaton resor Malmö sed’ 65. - Hobbies:\nSkytte, fiske, segelflygning.\nGift 57 m Rozsa Kiråly f 38&gt;, dtr t dir\nJozsef K o Elisabeth Vargha. - Barn:\nGabor f 62.\n\nBOGÅRDH,    SVEN-ERIC,    direktör,\n\nÄngelholm, f i Västerås 19/2/32 av fabr\nTheodor B o Gärda Broberg.\nIng:ex Hässleholms tekn sk 59, ing Nils\nJanssons konstr :byrå ab Västervik 59-61,\nverkst dir o inneh\nBogårdhskonstruktio-ner ab,  konsult ing :byrå WS,\nÄngelholm sed 61. - Hobby: segling.\nGift 51  m Ingegerd Ridderstråle f 31,\ndtr t ing Kjell R o Linnea Hermansson.\n-Barn: Britt f 51.\n\nBOHLIN,   F   G   ANDERS,   direktör,\n\nMalmö, f i Jönkpg 19/8/31  av civiling\nKarl Gustaf B o Britten Adin.\nHdlsgymn :ex   Malmö   53,   kadettsk   55,\nanst not :avd Skand bkn 55, kamr\nbyggbranschen 57, verkst dir Skand byggcity\nab sed 66. - Ag lantbr. - Löjtn\nträng-tr res 62. - Hobby: tennis.\nGift 56 m Marianne Appelin f 33, dtr t\nbankdir Folke A o Magnhild Engström.\n\n-  Barn: Karin f 57i, Gunnar f 59, Lars o\nPer ff 64.\n\nBOHLIN, ARTHUR E, redaktör,\nKarlskrona, f i Gbg 22/12/15.\n\n8 ska\n\nGbgHdlI  3*5;  firmakorresp Gbg\nunderoff   flottan   39-45,   red   Sydöstra\nSv:es Dagbl Karlskrona sed 45.\n\nBOHLIN,   HELGE   E   A,   fd   rektor,\n\nMalmö, f i Äspered, Älvsb l, 17/9/92 av\nhdlsres Samuel B o Anna Johansson.\nStud:ex Gbg 11, fil kand o fil måg Lund\n15, fil lic Sthlm 47; ass tekn högsk\nDanzig 17, aman RFA 20, lekt i fysik o\nelektroteknik tekn gymn Härnösand 21, rekt\ndär 37, rekt HTL Malmö 47-59. -\nStyr:led Hermods sed 55,. - Ordf Astron sällsk\nTycho Brahe. - Skr: Elektroteknis’ka\ngrundbegrepp (29), Elektricitetslära o\nelektroteknik (37), Elektriska o\nmagnetiska fält i världsrymden (52),\nSolsystemet, en byggnad med pythagoreisk\narkitektur (54), Några enkla beräkningar\nkring rymdraketens dynamik (58), En\negendomlig lagbundenhet hos\nsolsystemet (56) m m. - Utm: KNO.\nGift 23 m Eva Eisner f 97, dtr t stat:insp\nCarl E o Elin Larsson. - Barn: Gunhild\nf 27, Ingemar f 35, Christina f 38.\n\n",
    "structured": {
        "0": {
            "full_name": "Bogyo, Hvad Ar",
            "location": "Malmö",
            "occupation": "Ingenjör",
            "birth_details": {
                "date": "31/07/1936",
                "place": "Budapest"
            },
            "education": [
                {
                    "degree": "Ing:ex Tekn",
                    "year": "1955",
                    "institution": "Tekn gymn Budapest"
                }
            ],
            "career": [
                {
                    "position": "Ing ung stat jv",
                    "years": {
                        "start_year": 1955,
                        "end_year": 1956
                    }
                },
                {
                    "position": "Centerlöf & Holmberg ab",
                    "years": {
                        "start_year": 1957,
                        "end_year": null
                    },
                    "organization": "Nils Centerlöf ab"
                }
            ],
            "family": {
                "spouse": "Rozsa Kiråly",
                "marriage_year": "1957",
                "children": [
                    {
                        "name": "Gabor",
                        "birth_year": "1962"
                    }
                ]
            },
            "hobbies": [
                "Skytte",
                "Fiske",
                "Segelflygning"
            ]
        },
        "1": {
            "full_name": "Bogårdh, Sven-Eric",
            "location": "Ängelholm",
            "occupation": "Direktör",
            "birth_details": {
                "date": "19/02/1932",
                "place": "Västerås"
            },
            "education": [
                {
                    "degree": "Ing:ex",
                    "year": "1959",
                    "institution": "Hässleholms tekn sk"
                }
            ],
            "career": [
                {
                    "position": "Ing Nils Janssons konstr",
                    "years": {
                        "start_year": 1959,
                        "end_year": 1961
                    },
                    "organization": "byrå ab Västervik"
                },
                {
                    "position": "Verkst dir o inneh Bogårdhskonstruktio-ner ab",
                    "years": {
                        "start_year": 1961,
                        "end_year": null
                    }
                }
            ],
            "family": {
                "spouse": "Ingegerd Ridderstråle",
                "marriage_year": "1951",
                "children": [
                    {
                        "name": "Britt",
                        "birth_year": "1951"
                    }
                ]
            },
            "hobbies": [
                "Segling"
            ]
        },
        "2": {
            "full_name": "Bohlin, F G Anders",
            "location": "Malmö",
            "occupation": "Direktör",
            "birth_details": {
                "date": "19/08/1931",
                "place": "Jönkpg"
            },
            "education": [
                {
                    "degree": "Hdlsgymn :ex",
                    "year": "1953",
                    "institution": "Malmö"
                }
            ],
            "career": [
                {
                    "position": "Kamr byggbranschen",
                    "years": {
                        "start_year": 1957,
                        "end_year": null
                    },
                    "organization": "verkst dir Skand byggcity ab"
                }
            ],
            "family": {
                "spouse": "Marianne Appelin",
                "marriage_year": "1956",
                "children": [
                    {
                        "name": "Karin",
                        "birth_year": "1957"
                    },
                    {
                        "name": "Gunnar",
                        "birth_year": "1959"
                    },
                    {
                        "name": "Lars",
                        "birth_year": "1964"
                    },
                    {
                        "name": "Per",
                        "birth_year": "1964"
                    }
                ],
                "hobbies": [
                    "Tennis"
                ]
            }
        },
        "3": {
            "full_name": "Bohlin, Arthur E",
            "location": "Karlskrona",
            "occupation": "Redaktör",
            "birth_details": {
                "date": "22/12/1915",
                "place": "Gbg"
            }
        },
        "4": {
            "full_name": "Bohlin, Helge E A",
            "location": "Malmö",
            "occupation": "Fd rektor",
            "birth_details": {
                "date": "17/09/1892",
                "place": "Äspered, Älvsb l"
            },
            "education": [
                {
                    "degree": "Stud:ex",
                    "year": "1911",
                    "institution": "Gbg"
                },
                {
                    "degree": "Fil kand",
                    "year": "1915",
                    "institution": "Lund"
                },
                {
                    "degree": "Fil måg",
                    "year": "1915",
                    "institution": "Lund"
                }
            ],
            "career": [
                {
                    "position": "Ass tekn högsk Danzig",
                    "years": {
                        "start_year": 1917,
                        "end_year": null
                    }
                },
                {
                    "position": "Aman RFA",
                    "years": {
                        "start_year": 1920,
                        "end_year": null
                    }
                },
                {
                    "position": "Lekt i fysik o elektroteknik tekn gymn Härnösand",
                    "years": {
                        "start_year": 1921,
                        "end_year": 1937
                    }
                },
                {
                    "position": "Rekt där",
                    "years": {
                        "start_year": 1937,
                        "end_year": 1947
                    }
                },
                {
                    "position": "Rekt HTL Malmö",
                    "years": {
                        "start_year": 1947,
                        "end_year": 1959
                    }
                }
            ],
            "family": {
                "spouse": "Eva Eisner",
                "marriage_year": "1923",
                "children": [
                    {
                        "name": "Gunhild",
                        "birth_year": "1927"
                    },
                    {
                        "name": "Ingemar",
                        "birth_year": "1935"
                    },
                    {
                        "name": "Christina",
                        "birth_year": "1938"
                    }
                ]
            },
            "publications": [
                {
                    "title": "Elektroteknis’ka grundbegrepp",
                    "year": "1929",
                    "type": null
                },
                {
                    "title": "Elektricitetslära o elektroteknik",
                    "year": "1937",
                    "type": null
                },
                {
                    "title": "Elektriska o magnetiska fält i världsrymden",
                    "year": "1952",
                    "type": null
                },
                {
                    "title": "Solsystemet, en byggnad med pythagoreisk arkitektur",
                    "year": "1954",
                    "type": null
                },
                {
                    "title": "Några enkla beräkningar kring rymdraketens dynamik",
                    "year": "1958",
                    "type": null
                }
            ],
            "community_involvement": [
                {
                    "role": null,
                    "organization": "Hermods",
                    "years": "1955"
                }
            ],
            "honorary_titles": [
                {
                    "title": "KNO",
                    "institution": null,
                    "year": null
                }
            ]
        }
    }
}