{
    "original": "BOBERG, ERIC, civilingenjör, Malmö,\nf i Umeå 4/8/11 av verkm Reinhard B\no Frida Lundström.\n\nStud:ex Sthlm 30, KTH 34, FHS 61; anst\nKockums mek verkst ab 35, SJ sed 36,\nmaskining Kiruna 45, ch maskinsekt\nBorås 50, ch allm sekt SJ Malmö sed 64.\n-Medl PB. - Utm: RNO.\nGift 51 m Brit Lundberg f 23, dtr t rev\nMauritz L o Hildur Johansson. - Barn:\nPer-Eric f 52, Anne-Marie f 54.\n\nBOBERG,  P  E  ROLF,   civilekonom,\ndirektör, Osby, f i Gävle 9/3/29 av\nkassör Erik B o Sigrid Hedmark.\nStud:ex Gävle 49, DHS 54, anst\nSandvikens jernv ab Sandviken 54, Bobergs\nfajansfabr ab Gävle 57 (styr:led),\nOsby-Pannan ab 62, v verkst dir där sed 66.\nGift 55 m Birgitta Samuelson f 32, dtr t\nbankkamr Otto S o Anna Bengtsson.\n-Barn: Michael f 57.\n\nBOBERG,  SVEN E  A,  civilingenjör,\nHbg, f i Ytterhogdal, Jämtl l, 24/1/21 av\nverkm David B o Kristina Ericsson.\nStud:ex Gävle 42, CTH 47, ing ab\nSun-light Nykpg 47, övering Rexolin\nChemicals ab Hbg sed 36. - Styr:led Bobergs\nfajansfabr ab 56-62. - Hobby: fiske.\nGift 47 m Gudrun Malmerling f 26, dtr\nt förvalt G A M o h h. - Barn: Ulf f 48,\nJan f 49, Mats f 58, Bengt f 62.\n\nBOBERG, C TORSTEN, direktör,\nMalmö, f i Sthlm 17/5/17 av red Carl B o\nElisabeth Ydrén.\n\nStud:ex Kalmar 36, jur kand Upps 42,\ntingstjg N Möre o Stranda doms 42-45,\ntjg Skand bkn 45, bitr jur Rolf\nNorden-stedts adv :byrå Malmö 45-56, dir G &amp; L\nBeijer ab sed 56. - Styr:led\nBeijer-kon-cernen Malmö m fi bol.\nGift 40 m vävlär Brita Wranne. - Barn:\nGunilla f 41, Claes f 45, Per f 52.\n\nBOCKASTEN, KJELL E, docent,\nuniversitetslektor, Lund, f i Malmö 1/1/17\nav rekt Edvin Nilsson o Emma N.\nStud:ex Hbg 36, fil måg Lund 43, fil lic\n55, fil dr 56, doc i fysik Upps univ 58L\n65; e adj Karol hal Örebro 43^45, hal\nVäxjö 46, komm lekt o adj hal Åmål\n47’-50, lekt hal Varberg 56’-58, univ :lekt\nLTH sed 65. - Skr i atomspektroskopi o\nlaserfysik.\n\nGift 48 m Ingrid Brockman f 20, dtr t\nkamrer Thorsten B o Ester Berntsson.\n-Barn: Klas f 49, Nils f 52, Bodil f 54,\nGörel f 60.\n\nvon BOCKELMANN, BERNHARD A\nH, dr rer nät, laboratoriechef, Åkarp,\nf i Prenzlau, Tyskl, 4/2/30 av dr Herbert\nv B o Dorothea Gall.\nMA Univ of Kansas Lawrence USA 58,\nDr rer nät Kiels univ 61; vetensk ass\nInst f Virusforschung u experinientelle\nMedizin Sielbeck Tyskl 58-61,\nMilch-forschungs und versuchsanst Kiel 62-63,\nab Tetra Påk Lund 63-65, lab :ch Sv\nkontrollanst f mejeriprod o ägg sed 65.\n-Skr: Die aureomycinaktivierte Candida\nalbicans Infektion der weissen Maus\n(drsavh 61). - Hobbies: bridge, flygning.\n\nGift 62 m dr rer nät Irene Petersson f 27,\ndtr t anläggn:arb Ivar P o Helga\nKarlsson. - Barn: Erich f 64.\n\nvon BOCKELMANN, I L IRENE, dr\n\nrer nät, överassistent, Åkarp, f i Fröseke,\nKronob l, 1/4/27 av anläggn:arb Ivar\nPetersson o Helga Karlsson.\nStud:ex 49 o fil kand Lund 54, Dr rer\nnät Kiels univ 61; förs :led i bakteriologi\nStat mejeriförsök sed 54. - Skr:\nStoff-wechseluntersuchungen an Candida\nalbicans (drsavh 61), ett flert arb rör\nmjölkbakt o bakt betingade fel på\nmejeriprodukter.\n\nGift 62 m dr Bernhard von Bockelmann\nf 30. - Barn: Erich f 64,\n\n",
    "structured": {
        "1": {
            "full_name": "Eric Boberg",
            "location": "Malmö",
            "occupation": "Civilingenjör",
            "birth_details": {
                "date": "04/08/1911",
                "place": "Umeå",
                "parents": "Reinhard B och Frida Lundström"
            },
            "education": [
                {
                    "degree": "Stud:ex",
                    "year": "1930",
                    "institution": "Sthlm"
                },
                {
                    "degree": "KTH",
                    "year": "1934",
                    "institution": "FHS"
                }
            ],
            "career": [
                {
                    "position": "anst Kockums mek verkst ab",
                    "years": {
                        "start_year": 1935,
                        "end_year": 1936
                    },
                    "organization": "Kockums mek verkst ab"
                },
                {
                    "position": "SJ",
                    "years": {
                        "start_year": 1936,
                        "end_year": null
                    },
                    "organization": "SJ"
                },
                {
                    "position": "maskining Kiruna",
                    "years": {
                        "start_year": 1945,
                        "end_year": null
                    },
                    "organization": "Kiruna"
                },
                {
                    "position": "ch maskinsekt Borås",
                    "years": {
                        "start_year": 1950,
                        "end_year": null
                    },
                    "organization": "Borås"
                },
                {
                    "position": "ch allm sekt SJ Malmö",
                    "years": {
                        "start_year": 1964,
                        "end_year": null
                    },
                    "organization": "SJ Malmö"
                }
            ],
            "family": {
                "spouse": "Brit Lundberg",
                "marriage_year": "1951",
                "children": [
                    {
                        "name": "Per-Eric",
                        "birth_year": "1952"
                    },
                    {
                        "name": "Anne-Marie",
                        "birth_year": "1954"
                    }
                ]
            }
        },
        "2": {
            "full_name": "P Rolf Boberg",
            "location": "Osby",
            "occupation": "Civilekonom, direktör",
            "birth_details": {
                "date": "09/03/1929",
                "place": "Gävle",
                "parents": "Erik B och Sigrid Hedmark"
            },
            "education": [
                {
                    "degree": "Stud:ex",
                    "year": "1949",
                    "institution": "Gävle"
                },
                {
                    "degree": "DHS",
                    "year": "1954",
                    "institution": "Sandvikens jernv ab Sandviken"
                }
            ],
            "career": [
                {
                    "position": "anst Sandvikens jernv ab Sandviken",
                    "years": {
                        "start_year": 1954,
                        "end_year": null
                    },
                    "organization": "Sandvikens jernv ab Sandviken"
                },
                {
                    "position": "Bobergs fajansfabr ab Gävle",
                    "years": {
                        "start_year": 1957,
                        "end_year": 1966
                    },
                    "organization": "Bobergs fajansfabr ab Gävle"
                },
                {
                    "position": "Osby-Pannan ab",
                    "years": {
                        "start_year": 1962,
                        "end_year": null
                    },
                    "organization": "Osby-Pannan ab"
                }
            ],
            "family": {
                "spouse": "Birgitta Samuelson",
                "marriage_year": "1955",
                "children": [
                    {
                        "name": "Michael",
                        "birth_year": "1957"
                    }
                ]
            }
        },
        "3": {
            "full_name": "Sven E A Boberg",
            "location": "Hbg",
            "occupation": "Civilingenjör",
            "birth_details": {
                "date": "24/01/1921",
                "place": "Ytterhogdal, Jämtl",
                "parents": "David B och Kristina Ericsson"
            },
            "education": [
                {
                    "degree": "Stud:ex",
                    "year": "1942",
                    "institution": "Gävle"
                },
                {
                    "degree": "CTH",
                    "year": "1947",
                    "institution": "Sun-light Nykpg"
                }
            ],
            "career": [
                {
                    "position": "ing ab Sun-light Nykpg",
                    "years": {
                        "start_year": 1947,
                        "end_year": null
                    },
                    "organization": "Sun-light Nykpg"
                },
                {
                    "position": "övering Rexolin Chemicals ab Hbg",
                    "years": {
                        "start_year": 1936,
                        "end_year": null
                    },
                    "organization": "Rexolin Chemicals ab Hbg"
                },
                {
                    "position": "Styr:led Bobergs fajansfabr ab",
                    "years": {
                        "start_year": 1956,
                        "end_year": 1962
                    },
                    "organization": "Bobergs fajansfabr ab"
                }
            ],
            "family": {
                "spouse": "Gudrun Malmerling",
                "marriage_year": "1947",
                "children": [
                    {
                        "name": "Ulf",
                        "birth_year": "1948"
                    },
                    {
                        "name": "Jan",
                        "birth_year": "1949"
                    },
                    {
                        "name": "Mats",
                        "birth_year": "1958"
                    },
                    {
                        "name": "Bengt",
                        "birth_year": "1962"
                    }
                ]
            }
        },
        "4": {
            "full_name": "C Torsten Boberg",
            "location": "Malmö",
            "occupation": "Direktör",
            "birth_details": {
                "date": "17/05/1917",
                "place": "Sthlm",
                "parents": "Carl B och Elisabeth Ydrén"
            },
            "education": [
                {
                    "degree": "Stud:ex",
                    "year": "1936",
                    "institution": "Kalmar"
                },
                {
                    "degree": "jur kand",
                    "year": "1942",
                    "institution": "Upps"
                }
            ],
            "career": [
                {
                    "position": "tingstjg N Möre o Stranda doms",
                    "years": {
                        "start_year": 1942,
                        "end_year": 1945
                    },
                    "organization": "N Möre o Stranda doms"
                },
                {
                    "position": "tjg Skand bkn",
                    "years": {
                        "start_year": 1945,
                        "end_year": null
                    },
                    "organization": "Skand bkn"
                },
                {
                    "position": "bitr jur Rolf Norden-stedts adv :byrå Malmö",
                    "years": {
                        "start_year": 1945,
                        "end_year": 1956
                    },
                    "organization": "Rolf Norden-stedts adv :byrå Malmö"
                },
                {
                    "position": "dir G & L Beijer ab",
                    "years": {
                        "start_year": 1956,
                        "end_year": null
                    },
                    "organization": "G & L Beijer ab"
                }
            ],
            "family": {
                "spouse": "Brita Wranne",
                "marriage_year": "1940",
                "children": [
                    {
                        "name": "Gunilla",
                        "birth_year": "1941"
                    },
                    {
                        "name": "Claes",
                        "birth_year": "1945"
                    },
                    {
                        "name": "Per",
                        "birth_year": "1952"
                    }
                ]
            }
        },
        "5": {
            "full_name": "Kjell E Bockasten",
            "location": "Lund",
            "occupation": "Docent, universitetslektor",
            "birth_details": {
                "date": "01/01/1917",
                "place": "Malmö",
                "parents": "Edvin Nilsson och Emma N"
            },
            "education": [
                {
                    "degree": "Stud:ex",
                    "year": "1936",
                    "institution": "Hbg"
                },
                {
                    "degree": "fil måg",
                    "year": "1943",
                    "institution": "Lund"
                },
                {
                    "degree": "fil lic",
                    "year": "1955",
                    "institution": null
                },
                {
                    "degree": "fil dr",
                    "year": "1956",
                    "institution": null
                }
            ],
            "career": {
                "position": "doc i fysik Upps univ",
                "years": {
                    "start_year": 1958,
                    "end_year": 1965
                },
                "organization": "Upps univ"
            },
            "family": {
                "spouse": "Ingrid Brockman",
                "marriage_year": "1948",
                "children": [
                    {
                        "name": "Klas",
                        "birth_year": "1949"
                    },
                    {
                        "name": "Nils",
                        "birth_year": "1952"
                    },
                    {
                        "name": "Bodil",
                        "birth_year": "1954"
                    },
                    {
                        "name": "Görel",
                        "birth_year": "1960"
                    }
                ]
            }
        },
        "6": {
            "full_name": "Bernhard A H von Bockelmann",
            "location": "Åkarp",
            "occupation": "Dr rer nät, laboratoriechef",
            "birth_details": {
                "date": "04/02/1930",
                "place": "Prenzlau, Tyskl",
                "parents": "Herbert v B och Dorothea Gall"
            },
            "education": [
                {
                    "degree": "MA",
                    "year": "1958",
                    "institution": "Univ of Kansas Lawrence USA"
                },
                {
                    "degree": "Dr rer nät",
                    "year": "1961",
                    "institution": "Kiels univ"
                }
            ],
            "career": {
                "position": "lab :ch Sv kontrollanst f mejeriprod o ägg",
                "years": {
                    "start_year": 1965,
                    "end_year": null
                },
                "organization": "Sv kontrollanst f mejeriprod o ägg"
            },
            "family": {
                "spouse": "Irene Petersson",
                "marriage_year": "1962",
                "children": [
                    {
                        "name": "Erich",
                        "birth_year": "1964"
                    }
                ]
            }
        },
        "7": {
            "full_name": "I L Irene von Bockelmann",
            "location": "Åkarp",
            "occupation": "Dr rer nät, överassistent",
            "birth_details": {
                "date": "01/04/1927",
                "place": "Fröseke, Kronob l",
                "parents": "Ivar Petersson och Helga Karlsson"
            },
            "education": [
                {
                    "degree": "Stud:ex",
                    "year": "1949",
                    "institution": null
                },
                {
                    "degree": "fil kand",
                    "year": "1954",
                    "institution": "Lund"
                },
                {
                    "degree": "Dr rer nät",
                    "year": "1961",
                    "institution": "Kiels univ"
                }
            ],
            "career": {
                "position": "förs :led i bakteriologi Stat mejeriförsök",
                "years": {
                    "start_year": 1954,
                    "end_year": null
                },
                "organization": "Stat mejeriförsök"
            },
            "family": {
                "spouse": "Bernhard von Bockelmann",
                "marriage_year": "1962",
                "children": [
                    {
                        "name": "Erich",
                        "birth_year": "1964"
                    }
                ]
            }
        }
    }
}