{
    "original": "BLOMQUIST, B GUNNAR, bitr\növerläkare, Karlskrona, f i Tingsås, Kronob\nl, 7/9/24 av överlär Bror B o Anna\nHagelberg.\n\nStud:ex Växjö 44, med kand 47 o med\nlic Lund 53’, underläk röntgenavd\nKarlskrona las 53-56, röntgendiagn avd Lunds\nlas 56-63 o radiolog klin 60-61, bitr\növerläk röntgenavd Karlskrona läs sed\n63). - Hobbies: foto, golf.\nGift 47 m Märta Vogel f 22, dtr t kamr\nH V o h h. - Barn: Peter f 47, Lars f 53i,\nKarin f 55, Carl f 58, Per-Ola f 63.\n\nBLOMQUIST, GÖSTA P F, direktör,\n\nMalmö, f i Malmö 21/1/30 av dir\nSterner B o Sigrid Persson.\nMalmö hdlsgymn 50, prakt Tyskl 50-53,\nanst ab Sterner Blomquist Malmö 53,\nverkst dir där sed 56 (styr:led). - Medl\nW-sex.\n\nGift 56 m Margit Holmer f 31, dtr t\nlärov :adj Einar H o Dorotea Schulz.\n-Barn: Per f 58, Eva-Kristin f 59,\nFredrik f 64.\n\nBLOMQUIST, K J IVAR,\ndistriktschef, Ängelholm, f i Linneryd, Kronob\nl, 14/9/28 av lantbr Wilhelm B o Ester\nSvensson.\n\nVolontär F 5 45, furir 48, flygtekn 51.\n-IFU 61; distr :ch försäkr :bol\nTrygg-Fyl-gia sed 59. - Hobby: fiske.\nGift 51 m May-Britt Ferm f 29, dtr t\nlantbr Fritz F o Edith Pettersson.\n-Barn: Ann-Charlotte f 51, Carina f 56.\n\nBLOMQVIST, NILS S, kantor, Örtofta,\nf i Lund 16/2/04 av fastigh :äg Johannes\nB o Elna Zander.\n\nFolkskollär :ex Lund 24, org:ex Visby 25,\nkyrkosång :ex Växjö 26, folkskollär Ige^\nlösa sed 26, kant o org Igelösa o\nOdars-lövs förs sed 26. - Ordf Igelösa förs\nkyrkostämma 32, led Toras bibi:styr. - Utm:\nPatrSstGM.\n\nGift 39 m Maiken Jacobsson f 07, dtr t\nsmedmäst Adolf J o Betty J. - Barn: Eva\nf 44,\n\n",
    "structured": {
        "0": {
            "full_name": "B GUNNAR BLOMQUIST",
            "location": "Karlskrona",
            "occupation": "bitr överläkare",
            "birth_details": {
                "date": "07/09/1924",
                "place": "Tingsås, Kronob l",
                "parents": "överlär Bror B o Anna Hagelberg"
            },
            "education": [
                {
                    "degree": "Stud:ex",
                    "year": "1944",
                    "institution": "Växjö"
                },
                {
                    "degree": "med kand",
                    "year": "1947",
                    "institution": "Lund"
                },
                {
                    "degree": "med lic",
                    "year": "1953",
                    "institution": "Lund"
                }
            ],
            "career": [
                {
                    "position": "underläk röntgenavd Karlskrona las",
                    "years": {
                        "start_year": 1953,
                        "end_year": 1956
                    },
                    "organization": "Karlskrona las"
                },
                {
                    "position": "röntgendiagn avd Lunds las",
                    "years": {
                        "start_year": 1956,
                        "end_year": 1963
                    },
                    "organization": "Lunds las"
                },
                {
                    "position": "radiolog klin",
                    "years": {
                        "start_year": 1960,
                        "end_year": 1961
                    },
                    "organization": "klin"
                },
                {
                    "position": "bitr överläk röntgenavd Karlskrona läs",
                    "years": {
                        "start_year": 1963
                    },
                    "organization": "Karlskrona läs"
                }
            ],
            "family": {
                "spouse": "Märta Vogel",
                "marriage_year": "1947",
                "children": [
                    {
                        "name": "Peter",
                        "birth_year": "1947"
                    },
                    {
                        "name": "Lars",
                        "birth_year": "1953"
                    },
                    {
                        "name": "Karin",
                        "birth_year": "1955"
                    },
                    {
                        "name": "Carl",
                        "birth_year": "1958"
                    },
                    {
                        "name": "Per-Ola",
                        "birth_year": "1963"
                    }
                ]
            },
            "hobbies": [
                "foto",
                "golf"
            ]
        },
        "1": {
            "full_name": "GÖSTA P F BLOMQUIST",
            "location": "Malmö",
            "occupation": "direktör",
            "birth_details": {
                "date": "21/01/1930",
                "place": "Malmö",
                "parents": "dir Sterner B o Sigrid Persson"
            },
            "education": [
                {
                    "degree": "Malmö hdlsgymn",
                    "year": "1950"
                },
                {
                    "degree": "Tyskl",
                    "year": "1953",
                    "institution": "Tyskl"
                }
            ],
            "career": [
                {
                    "position": "prakt",
                    "years": {
                        "start_year": 1950,
                        "end_year": 1953
                    },
                    "organization": "Tyskl"
                },
                {
                    "position": "verkst dir",
                    "years": {
                        "start_year": 1956
                    },
                    "organization": "Sterner Blomquist Malmö"
                }
            ],
            "family": {
                "spouse": "Margit Holmer",
                "marriage_year": "1956",
                "children": [
                    {
                        "name": "Per",
                        "birth_year": "1958"
                    },
                    {
                        "name": "Eva-Kristin",
                        "birth_year": "1959"
                    },
                    {
                        "name": "Fredrik",
                        "birth_year": "1964"
                    }
                ]
            }
        },
        "2": {
            "full_name": "K J IVAR BLOMQUIST",
            "location": "Ängelholm",
            "occupation": "distriktschef",
            "birth_details": {
                "date": "14/09/1928",
                "place": "Linneryd, Kronob l",
                "parents": "lantbr Wilhelm B o Ester Svensson"
            },
            "education": [
                {
                    "degree": "Volontär F 5",
                    "year": "1945"
                },
                {
                    "degree": "furir",
                    "year": "1948"
                },
                {
                    "degree": "flygtekn",
                    "year": "1951"
                },
                {
                    "degree": "IFU",
                    "year": "1961"
                }
            ],
            "career": [
                {
                    "position": "distr :ch försäkr :bol Trygg-Fyl-gia",
                    "years": {
                        "start_year": 1959
                    },
                    "organization": "Trygg-Fyl-gia"
                }
            ],
            "family": {
                "spouse": "May-Britt Ferm",
                "marriage_year": "1951",
                "children": [
                    {
                        "name": "Ann-Charlotte",
                        "birth_year": "1951"
                    },
                    {
                        "name": "Carina",
                        "birth_year": "1956"
                    }
                ]
            },
            "hobbies": "fiske"
        },
        "3": {
            "full_name": "NILS S BLOMQVIST",
            "location": "Örtofta",
            "occupation": "kantor",
            "birth_details": {
                "date": "16/02/1904",
                "place": "Lund",
                "parents": "fastigh :äg Johannes B o Elna Zander"
            },
            "education": [
                {
                    "degree": "Folkskollär",
                    "year": "1924",
                    "institution": "Lund"
                },
                {
                    "degree": "org:ex",
                    "year": "1925",
                    "institution": "Visby"
                },
                {
                    "degree": "kyrkosång :ex",
                    "year": "1926",
                    "institution": "Växjö"
                },
                {
                    "degree": "folkskollär",
                    "year": "1926",
                    "institution": "Igelösa"
                }
            ],
            "career": [
                {
                    "position": "kant o org Igelösa o Odars-lövs förs",
                    "years": {
                        "start_year": 1926
                    },
                    "organization": "Igelösa o Odars-lövs förs"
                }
            ],
            "family": {
                "spouse": "Maiken Jacobsson",
                "marriage_year": "1939",
                "children": {
                    "name": "Eva",
                    "birth_year": "1944"
                }
            }
        }
    }
}