{
    "original": "BERGDAHL, A PER, rådman,\nMalmö, f i Ängelholm 9/12/04 av dir\nAnders B o Elna Nilsson.\nStud:ex 22 o jur kand Lund 31, tingstjg\nHall l n doms 31-34, tjg Skånska hovr\n34, tf fiskal 36, tjg rådhusr Malmö 36,\npolisnot 41, assess 47, rådm sed 52.\n-Utm: RNO.\n\nGift 31 m Sonja Grönvall f 08. - Barn:\nErik f 31, Eva f 34.\n\nBERGDAHL, S SIGVARD,\nbyggnadsingenjör SBR, Karlskrona, f i\nKarlskrona 22/9/31 av flaggstyrm Gösta B o\nEmma Andersson.\n\nRealex 47, ing :ex HTL Karlskrona 52,\ning fortifik:- o byggn :förvaltn Blek\nKA-försv 52, byggn:ing Karlskronakont\nKommunernas konsultbyrå-LBF 65,\nbyggn:ing Ing :firman Jacobson &amp;\nWidmark ab Karlskronakont sed 66. - Sekr\nSBR:s Karlskronaavd sed 63. - Hobbies:\nfotografering, bridge.\nGift 51 m Ulla Gummesson f 30, dtr t\nmetallarb Albin G o Märtha Magnusson.\n\n-  Barn: Heléne f 52, Marié f 56.\n\nBERGDAHL, ULF F, leg läkare,\nMalmö, f i Sthlm 1/9/30 av köpm Frithiof\nB o Elna Eriksson.\n\nStud:ex Malmö 49, med kand Lund 52,\nmed lic 56, dipl Bernhard Nocht-Inst f\n\nSchiffs- und Tropenkrankh Hamburg 63,\nspec :komp i klin epidemiologi o akuta\ninfekt:sjukd 63; underläk Malmö epid:sjh\nsamt med klin, barnklin o bakt inst\nMalmö allm sjh 56-63, läk Rädda\nBarnens leprasjh Bukoba Tanzania 64-65,\nbitr överläk infekt:klin Malmö allm sjh\nsed 65. - Led SYLF:s centralstyr 60-63.\n-Medl Royal Soc of Tropical Med and\nHyg London 64. - Skr i klin medicin.\n-Hobbies: musik (pianospel), golf.\nGift 54 m Ingrid Melander f 30, dtr t\nhäradsh Elis M o Ebba Elmqvist. - Barn:\nHans f 56, Ingrid f 58.\n\n",
    "structured": {
        "0": {
            "full_name": "A Per Bergdahl",
            "location": "Malmö",
            "occupation": "rådman",
            "birth_details": {
                "date": "09/12/1904",
                "place": "Ängelholm",
                "parents": "dir Anders B o Elna Nilsson"
            },
            "education": [
                {
                    "degree": "Stud:ex",
                    "year": "1922",
                    "institution": "Lund"
                },
                {
                    "degree": "jur kand",
                    "year": "1931",
                    "institution": "Lund"
                }
            ],
            "career": [
                {
                    "position": "tingstjg",
                    "years": {
                        "start_year": 1931,
                        "end_year": 1934
                    },
                    "organization": "Hall l n doms"
                },
                {
                    "position": "tingstjg",
                    "years": {
                        "start_year": 1934,
                        "end_year": 1936
                    },
                    "organization": "Skånska hovr"
                },
                {
                    "position": "tf fiskal",
                    "years": {
                        "start_year": 1936,
                        "end_year": 1941
                    }
                },
                {
                    "position": "tjg rådhusr",
                    "years": {
                        "start_year": 1936,
                        "end_year": 1941
                    },
                    "organization": "Malmö"
                },
                {
                    "position": "polisnot",
                    "years": {
                        "start_year": 1941,
                        "end_year": 1947
                    }
                },
                {
                    "position": "assess",
                    "years": {
                        "start_year": 1947,
                        "end_year": 1952
                    }
                },
                {
                    "position": "rådm",
                    "years": {
                        "start_year": 1952
                    }
                }
            ],
            "family": {
                "spouse": "Sonja Grönvall",
                "marriage_year": "1931",
                "children": [
                    {
                        "name": "Erik",
                        "birth_year": "1931"
                    },
                    {
                        "name": "Eva",
                        "birth_year": "1934"
                    }
                ]
            }
        },
        "1": {
            "full_name": "S Sigvard Bergdahl",
            "location": "Karlskrona",
            "occupation": "byggnadsingenjör SBR",
            "birth_details": {
                "date": "22/09/1931",
                "place": "Karlskrona",
                "parents": "flaggstyrm Gösta B o Emma Andersson"
            },
            "education": [
                {
                    "degree": "Realex",
                    "year": "1947"
                },
                {
                    "degree": "ing :ex",
                    "year": "1952",
                    "institution": "HTL Karlskrona"
                }
            ],
            "career": [
                {
                    "position": "ing fortifik:- o byggn :förvaltn",
                    "years": {
                        "start_year": 1952
                    },
                    "organization": "Blek KA-försv"
                },
                {
                    "position": "byggn:ing Karlskronakont",
                    "years": {
                        "start_year": 1966
                    },
                    "organization": "Ing :firman Jacobson & Widmark ab Karlskronakont"
                }
            ],
            "family": {
                "spouse": "Ulla Gummesson",
                "marriage_year": "1951",
                "children": [
                    {
                        "name": "Heléne",
                        "birth_year": "1952"
                    },
                    {
                        "name": "Marié",
                        "birth_year": "1956"
                    }
                ]
            },
            "hobbies": [
                "fotografering",
                "bridge"
            ]
        },
        "2": {
            "full_name": "Ulf F Bergdahl",
            "location": "Malmö",
            "occupation": "leg läkare",
            "birth_details": {
                "date": "01/09/1930",
                "place": "Sthlm",
                "parents": "köpm Frithiof B o Elna Eriksson"
            },
            "education": [
                {
                    "degree": "Stud:ex",
                    "year": "1949",
                    "institution": "Malmö"
                },
                {
                    "degree": "med kand",
                    "year": "1952",
                    "institution": "Lund"
                },
                {
                    "degree": "med lic",
                    "year": "1956"
                }
            ],
            "career": [
                {
                    "position": "underläk",
                    "years": {
                        "start_year": 1956,
                        "end_year": 1963
                    },
                    "organization": "Malmö allm sjh"
                },
                {
                    "position": "läk",
                    "years": {
                        "start_year": 1964,
                        "end_year": 1965
                    },
                    "organization": "Rädda Barnens leprasjh Bukoba Tanzania"
                },
                {
                    "position": "bitr överläk",
                    "years": {
                        "start_year": 1965
                    },
                    "organization": "Malmö allm sjh"
                }
            ],
            "family": {
                "spouse": "Ingrid Melander",
                "marriage_year": "1954",
                "children": [
                    {
                        "name": "Hans",
                        "birth_year": "1956"
                    },
                    {
                        "name": "Ingrid",
                        "birth_year": "1958"
                    }
                ]
            },
            "hobbies": [
                "musik (pianospel)",
                "golf"
            ]
        }
    }
}