{
    "original": "ISAKSSON, STIG G, direktör,\nMarie-stad, f i Halmstad 2/10/09 av\nriksbanks-dir Thure I o Hanna Carlsson.\nAnst   Sv:es   riksbks   avd :kont   Luleå,\nUmeå, Upps, Mariestad o Halmstad 28-\n\n48, kamr Umeå 48, Luleå 50, Malmö 52,\ndir Sv:es riksbk Mariestad sed 63. - Ordf\ntax:ndr. - Hobbies: jakt, hundsport.\nGift 36 m Britt Ericson f 08, dtr t\ndistr:-vet Nils E o Gertrud Holmer. - Barn:\nInger f 37, Hans f 39.\n\nISAKSON, STURE G L, distriktschef,\n\nBorås, f i Borås 14/12/28 av transp:ch\nLudvig I o Agnes Wijk.\nHdlssk, försäkr:utb m dipl:ex enl IFU\n57. - Anst Oscar Jacobson ab Borås 48,\ndir :ass Hellbergs fabr ab Ulricehamn 50,\nink:ch Johan Skoglunds konfektionsfabr\nab Borås 52, insp Livförsäkr ab Thule\n54, distr:ch Gbg 56, Borås sed 58.\n-Suppl fören Thules fälttjm. - Medl Odd\nFellow. - Utm: Thules guldnål. -\nHobbies: slalom, tennis, golf, fotboll.\nGift 50 m Ewy Edström, dtr t förrn\nElmer E o Astrid Sjödin. - Barn:\nEwa-Pia f 51, Claes-Göran f 52, Karl-Henrik\nf 56.\n\nISACSON, SVERRE B, disponent, Gbg,\nf i Gbg 18/7/31 av boktr Folke I o\nSigrid Larsen.\n\nGraf inst 54, ch litogr avd Oscar\nIsacsons tryckeri ab 54, disp Isacsons\nWell-emballage Brännögård sed 64. - Hobby:\nsegling.\n\nGift m Jeanne Malmros f 38, dtr t prof\nHaqvin M o Elisabeth Cavallin. - Barn:\nPontus f 62, Camilla f 64.\n\nISAKSSON, J TORSTEN, lantbrukare,\nfd riksdagsman, Jungskola, f i Jung,\nSkarab l, 20/2/98 av lantbr Janne I o\nHanna Johansson.\n\nAg o brukar Töredals gård Jungskola.\n-Led AK 47-51, landst sed 35, dess FU\nsed 52, styr f Sv husdjursförsäkr:bol sed\n46, länsskolndn sed 58, fd led\nkomm:-fullm, komm:nd, skolstyr; lantbr :omb\nsed 40. - Utm: RVO, Skarab l landst\nstGM. - Hobby: jakt.\nGift 36 m Stina Carlsson f 10, dtr t\nlantbr Johan C o Kristina Svensson.\n-Barn: Ove f 39, Göran f 41, Ulf f 51.\n\n",
    "structured": {
        "0": {
            "full_name": "STIG G ISAKSSON",
            "location": "Marie-stad",
            "occupation": "direktör",
            "birth_details": {
                "date": "02/10/1909",
                "place": "Halmstad",
                "parents": "riksbanks-dir Thure I o Hanna Carlsson"
            },
            "education": [],
            "career": [
                {
                    "position": "Anst Sv:es riksbks",
                    "years": {
                        "start_year": 1928,
                        "end_year": 1948
                    },
                    "organization": "avd :kont Luleå, Umeå, Upps, Mariestad, Halmstad"
                },
                {
                    "position": "kamr",
                    "years": {
                        "start_year": 1948,
                        "end_year": 1952
                    },
                    "organization": "Umeå, Luleå, Malmö"
                },
                {
                    "position": "dir Sv:es riksbk Mariestad",
                    "years": {
                        "start_year": 1963,
                        "end_year": null
                    },
                    "organization": null
                }
            ],
            "family": {
                "spouse": "Britt Ericson",
                "marriage_year": "1936",
                "children": [
                    {
                        "name": "Inger",
                        "birth_year": "1937"
                    },
                    {
                        "name": "Hans",
                        "birth_year": "1939"
                    }
                ]
            }
        },
        "1": {
            "full_name": "STURE G L ISAKSON",
            "location": "Borås",
            "occupation": "distriktschef",
            "birth_details": {
                "date": "14/12/1928",
                "place": "Borås"
            },
            "education": [
                {
                    "degree": "hdlssk",
                    "year": "1957",
                    "institution": "IFU"
                }
            ],
            "career": [
                {
                    "position": "Anst Oscar Jacobson ab Borås",
                    "years": {
                        "start_year": 1948,
                        "end_year": 1950
                    },
                    "organization": null
                },
                {
                    "position": "dir :ass",
                    "years": {
                        "start_year": 1950,
                        "end_year": 1952
                    },
                    "organization": "Hellbergs fabr ab Ulricehamn"
                },
                {
                    "position": "ink:ch",
                    "years": {
                        "start_year": 1952,
                        "end_year": 1954
                    },
                    "organization": "Johan Skoglunds konfektionsfabr ab Borås"
                },
                {
                    "position": "insp",
                    "years": {
                        "start_year": 1954,
                        "end_year": 1956
                    },
                    "organization": "Livförsäkr ab Thule"
                },
                {
                    "position": "distr:ch",
                    "years": {
                        "start_year": 1956,
                        "end_year": null
                    },
                    "organization": "Borås"
                }
            ],
            "family": {
                "spouse": "Ewy Edström",
                "marriage_year": "1950",
                "children": [
                    {
                        "name": "Ewa-Pia",
                        "birth_year": "1951"
                    },
                    {
                        "name": "Claes-Göran",
                        "birth_year": "1952"
                    },
                    {
                        "name": "Karl-Henrik",
                        "birth_year": "1956"
                    }
                ]
            }
        },
        "2": {
            "full_name": "SVERRE B ISACSON",
            "location": "Gbg",
            "occupation": "disponent",
            "birth_details": {
                "date": "18/07/1931",
                "place": "Gbg",
                "parents": "boktr Folke I o Sigrid Larsen"
            },
            "education": [
                {
                    "degree": "Graf inst",
                    "year": "1954",
                    "institution": "Oscar Isacsons tryckeri ab"
                }
            ],
            "career": [
                {
                    "position": "ch litogr avd",
                    "years": {
                        "start_year": 1954,
                        "end_year": null
                    },
                    "organization": "Oscar Isacsons tryckeri ab"
                },
                {
                    "position": "disp",
                    "years": {
                        "start_year": 1964,
                        "end_year": null
                    },
                    "organization": "Isacsons Well-emballage Brännögård"
                }
            ],
            "family": {
                "spouse": "Jeanne Malmros",
                "marriage_year": "1954",
                "children": [
                    {
                        "name": "Pontus",
                        "birth_year": "1962"
                    },
                    {
                        "name": "Camilla",
                        "birth_year": "1964"
                    }
                ]
            }
        },
        "3": {
            "full_name": "J TORSTEN ISAKSSON",
            "location": "Jungskola",
            "occupation": "lantbrukare, fd riksdagsman",
            "birth_details": {
                "date": "20/02/1898",
                "place": "Jung, Skarab l",
                "parents": "lantbr Janne I o Hanna Johansson"
            },
            "education": [],
            "career": [
                {
                    "position": "Ag o brukar",
                    "years": {
                        "start_year": null,
                        "end_year": null
                    },
                    "organization": "Töredals gård Jungskola"
                }
            ],
            "family": {
                "spouse": "Stina Carlsson",
                "marriage_year": "1936",
                "children": [
                    {
                        "name": "Ove",
                        "birth_year": "1939"
                    },
                    {
                        "name": "Göran",
                        "birth_year": "1941"
                    },
                    {
                        "name": "Ulf",
                        "birth_year": "1951"
                    }
                ]
            }
        }
    }
}