{
    "original": "IGHE, IVAR G L, agronom, Vreta\nKloster, f i Karlskrona 13/9/04 av\nverkm Johan Gottfrid Larsson o Anna\nMagnusson.\n\nStud:ex 25, agr:ex Alnarp 30, tf\njordbr:-konsulent Borås 35, lär lantmannask\nDingle 36, Fristad 37, Lunnevad 39,\nlantbr:sk Vreta Kloster sed 55. -\nStyr:led Östergötl l jaktv:fören 45,\nnatursk:-rådet Östergötl 55-62, Skogs- o\nlantbr:-film jordbr:filmrådet sed 60. - Skr:\nOgräs på åkern, groddplantstadiet (60).\n\n-   Utm:  Östergötl  l  jaktv:fören ftjtS.\n-Hobbies: jakt, sport.\n\nGift m Gunvor Neuendorff f 10, dtr t\ngodsäg Ivar N o Frederique König.\n-Barn: Björn f 38, Ulf f 42.\n\nIHRFELT, S V AGNE, fd\nlandskamrerare, Gbg, f i Gbg 25/3/94 av fil dr\nGustaf I o Ingeborg Mellin.\nKansliex 15, länsbokhåll Kopparb l 18,\nlänsassess Gbgs o Boh l 35, landskamr\nSkarab l 48-60. - Utm: KNO, RVO.\n\nGift 20 m Maj Swedberg f 99, dtr t\nkronolänsm Hans S o Mathilda\nSvensson. - Barn: Sven f 21 d 45, Bo f 23,\nMärta f 26, Åke f 30.\n\nIHRFELT, BO H, assessor, Gbg, f i\nHosjö, Kopparb l, 3/6/23 av landskamr\nAgne I o Maj Swedberg.\nStud:ex Gbg 43, jur kand Upps 49,\ntingstjg Vadsbo doms 49-52, fiskal hovr f V\nSv:e 52, stadsnot Gbgs rådhusr 53, assess\ndär sed 63; tjg adj led hovr f V Sv:e\n64-65. - Lär i handelsrätt Filip\nHolm-qvists hdlI 56-59. - Led o sekr\ncentralstyr f Gbgs arb :stugor sed 55.\nGift 49 m adj Märta Kjelsson f 25, dtr\nt länsassess Folke K o Maj Strandell.\n-Barn: Eva f 50, Lars f 54.\n\nIHRFELT, HELGE, landsfiskal, Gbg,\nf i Falun 30/9/02 av lärov :ad j, fil dr\nGustaf I o musiklär Ingeborg Mellin.\nRealex 23, anst St Kopparb bergsl ab\nFalun 18-22, landsfisk :ex Härnösand 30,\nlandsfisk Rätans distr Jämtl l 35 (tf 34),\nHedströmmens distr Västmanl l 41, på\növergångsstat o anst cfsektion länsstyr\nGbg sed 52. - Ordf Rätans skyttefören\n40-41, i ett flert tax:ndr sed 35. -\nHobbies: filateli, skidåkning, skytte\nGift 53 m Birgitta Graaf f 15, dtr t\nlots-kassör Bertil G o h h f Lindberg.\n-Barn: Hans f 54, Göran f 57\n\n",
    "structured": {
        "0": {
            "full_name": "IGHE, IVAR G L",
            "location": "Vreta Kloster",
            "occupation": "agronom",
            "birth_details": {
                "date": "13/09/1904",
                "place": "Karlskrona"
            },
            "education": [
                {
                    "degree": "Stud:ex",
                    "year": "1925",
                    "institution": "NULL"
                },
                {
                    "degree": "agr:ex",
                    "year": "1930",
                    "institution": "Alnarp"
                }
            ],
            "career": [
                {
                    "position": "tf jordbr:-konsulent",
                    "years": {
                        "start_year": 1935,
                        "end_year": 1935
                    },
                    "organization": "Borås"
                },
                {
                    "position": "lär lantmannask",
                    "years": {
                        "start_year": 1936,
                        "end_year": 1936
                    },
                    "organization": "Dingle"
                },
                {
                    "position": "lär lantmannask",
                    "years": {
                        "start_year": 1937,
                        "end_year": 1937
                    },
                    "organization": "Fristad"
                },
                {
                    "position": "lantbr:sk",
                    "years": {
                        "start_year": 1955,
                        "end_year": 1955
                    },
                    "organization": "Vreta Kloster"
                }
            ],
            "family": {
                "spouse": "Gunvor Neuendorff",
                "marriage_year": "NULL",
                "children": [
                    {
                        "name": "Björn",
                        "birth_year": "1938"
                    },
                    {
                        "name": "Ulf",
                        "birth_year": "1942"
                    }
                ]
            }
        },
        "1": {
            "full_name": "IHRFELT, S V AGNE",
            "location": "Gbg",
            "occupation": "fd landskamrerare",
            "birth_details": {
                "date": "25/03/1894",
                "place": "Gbg"
            },
            "education": [
                {
                    "degree": "Kansliex",
                    "year": "1915",
                    "institution": "NULL"
                },
                {
                    "degree": "länsbokhåll",
                    "year": "1918",
                    "institution": "Kopparb l"
                }
            ],
            "career": [
                {
                    "position": "länsassess",
                    "years": {
                        "start_year": 1935,
                        "end_year": 1935
                    },
                    "organization": "Gbgs o Boh l"
                },
                {
                    "position": "landskamr",
                    "years": {
                        "start_year": 1948,
                        "end_year": 1960
                    },
                    "organization": "Skarab l"
                }
            ],
            "family": {
                "spouse": "Maj Swedberg",
                "marriage_year": "1920",
                "children": [
                    {
                        "name": "Sven",
                        "birth_year": "1921"
                    },
                    {
                        "name": "Bo",
                        "birth_year": "1923"
                    },
                    {
                        "name": "Märta",
                        "birth_year": "1926"
                    },
                    {
                        "name": "Åke",
                        "birth_year": "1930"
                    }
                ]
            }
        },
        "2": {
            "full_name": "IHRFELT, BO H",
            "location": "Gbg",
            "occupation": "assessor",
            "birth_details": {
                "date": "03/06/1923",
                "place": "Hosjö, Kopparb l"
            },
            "education": [
                {
                    "degree": "Stud:ex",
                    "year": "1943",
                    "institution": "Gbg"
                },
                {
                    "degree": "jur kand",
                    "year": "1949",
                    "institution": "Upps"
                }
            ],
            "career": [
                {
                    "position": "tingstjg",
                    "years": {
                        "start_year": 1949,
                        "end_year": 1952
                    },
                    "organization": "Vadsbo doms"
                },
                {
                    "position": "fiskal",
                    "years": {
                        "start_year": 1953,
                        "end_year": 1963
                    },
                    "organization": "Gbgs rådhusr"
                }
            ],
            "family": {
                "spouse": "Märta Kjelsson",
                "marriage_year": "1949",
                "children": [
                    {
                        "name": "Eva",
                        "birth_year": "1950"
                    },
                    {
                        "name": "Lars",
                        "birth_year": "1954"
                    }
                ]
            }
        },
        "3": {
            "full_name": "IHRFELT, HELGE",
            "location": "Gbg",
            "occupation": "landsfiskal",
            "birth_details": {
                "date": "30/09/1902",
                "place": "Falun"
            },
            "education": [
                {
                    "degree": "Realex",
                    "year": "1923",
                    "institution": "NULL"
                },
                {
                    "degree": "landsfisk :ex",
                    "year": "1930",
                    "institution": "Härnösand"
                }
            ],
            "career": [
                {
                    "position": "landsfisk",
                    "years": {
                        "start_year": 1935,
                        "end_year": 1935
                    },
                    "organization": "Rätans distr Jämtl l"
                },
                {
                    "position": "landsfisk",
                    "years": {
                        "start_year": 1941,
                        "end_year": 1941
                    },
                    "organization": "Hedströmmens distr Västmanl l"
                }
            ],
            "family": {
                "spouse": "Birgitta Graaf",
                "marriage_year": "1953",
                "children": [
                    {
                        "name": "Hans",
                        "birth_year": "1954"
                    },
                    {
                        "name": "Göran",
                        "birth_year": "1957"
                    }
                ]
            }
        }
    }
}