{
    "original": "INGMAN, THOROLF O,\ndiplomingenjör, Finspång, f i Reval, Estl, 19/2/\n24 av dir Hjalmar I o Inga Nilsson.\nStud:ex Hfors 42, Tekn högsk Hfors 53,\nförsäljn:ing OY Industri ab Hfors 51,\nberäkn:ing de Lavals ångturbin Nacka\n54, STAL Finspång 57, ing avd f\nström-n :tekn o databehandl STAL-Laval sed\n60.\n\nGift 51 m Inger Lydén f 28, dtr t prof\nRagnar L o Dagmar Jaatinen (Finl).\n-Barn: Rolf f 52, Lisbeth f 53, Bernt f 54,\nLars f 60.\n\nINGMAR, STIG B, distriktsveterinär,\nLjugarn, f i Lund 31/10/13 av köpm\nMartin I o Alma Larsson.\nStud:ex Upps 34, vet :ex 43, distr :vet\nLjugarn sed 51. - Hobbies: jakt,\nfågelhunddressyr.\n\nGift 58 m Karin Egnell f 16, dtr t dir\nBertil E o Märta Presto.\n\nINGWALL,   CARL   T,   civilingenjör,\n\nNorrköping, f i Sthlm 6/8/08 av ing\nTeodor I o Hilma Pettersson.\nStud:ex 28, KTH 32, anst Sthlms stads\nhamnstyr 32, W :styr 33, byråing dess\nbrobyrå 38, anst ESAB Gbg 43, ch dess\nfilial Norrkpg sed 46. - Led Svetstekn\nfören sed 41, styr :led dess östgötaavd\n46-58 (ordf 56-58), delegat Internat Inst\nof Welding (IIW) o Internat Org for\nStandard sed 49. - LSvTF 32, medl Sv\nmetallografförb, American Welding Soc,\nInternat Vereinigung f Brückenbau u\nHochbau Zürich. - Skr: ett flert upps i\nsvetstekn fackpress, medarb i öl tekn\nuppsl:verk. - Utm: Svetstekn förenftjt.\n-Hobby: golf.\n\nGift 38 m Dagmar Lindquist, dtr t\nsjö-kapt Vilhelm L o Carolina Olsson.\n-Barn: Marika f 38, Louise f 39,\nCharlotte f 45.\n\nINGVARSSON, C GÖSTA,\nbyrådirektör, Mariestad, f i Malmö 4/2/25 av\nlas:-läk Gösta I o Wända Malmström.\nStud:ex Vänersborg 43, jur kand Lund\n50, tjg länsstyr Älvsb l 50-51, rådh:rätt\nVänersborg 51, tingstjg 51-54, länsnot\nSkarab l 55 (e 54), eo tax:insp 57, l:e\ntax:insp 58, l:e byråsekr länsskolndn\nSkarab l 54, byrådir där sed 61.\nGift 47 m Maja Bohmansson f 24, dtr t\nprof Gösta B o Tora Gillholm. - Barn:\nLena f 51.\n\n",
    "structured": {
        "0": {
            "full_name": "THOROLF O INGMAN",
            "location": "Finspång",
            "occupation": "diplomingenjör",
            "birth_details": {
                "date": "19/02/1924",
                "place": "Reval, Estland",
                "parents": "Hjalmar I o Inga Nilsson"
            },
            "education": [
                {
                    "degree": "Stud:ex",
                    "year": "1942",
                    "institution": "Hfors"
                },
                {
                    "degree": "Tekn högsk",
                    "year": "1953",
                    "institution": "Hfors"
                }
            ],
            "career": [
                {
                    "position": "försäljn:ing",
                    "years": {
                        "start_year": 1951,
                        "end_year": 1951
                    },
                    "organization": "OY Industri ab Hfors"
                },
                {
                    "position": "beräkn:ing",
                    "years": {
                        "start_year": 1954,
                        "end_year": 1954
                    },
                    "organization": "de Lavals ångturbin Nacka"
                },
                {
                    "position": "ing avd f ström-n :tekn o databehandl",
                    "years": {
                        "start_year": 1960,
                        "end_year": null
                    },
                    "organization": "STAL-Laval"
                }
            ],
            "family": {
                "spouse": "Inger Lydén",
                "marriage_year": "1951",
                "children": [
                    {
                        "name": "Rolf",
                        "birth_year": "1952"
                    },
                    {
                        "name": "Lisbeth",
                        "birth_year": "1953"
                    },
                    {
                        "name": "Bernt",
                        "birth_year": "1954"
                    },
                    {
                        "name": "Lars",
                        "birth_year": "1960"
                    }
                ]
            }
        },
        "1": {
            "full_name": "STIG B INGMAR",
            "location": "Ljugarn",
            "occupation": "distriktsveterinär",
            "birth_details": {
                "date": "31/10/1913",
                "place": "Lund",
                "parents": "Martin I o Alma Larsson"
            },
            "education": [
                {
                    "degree": "Stud:ex",
                    "year": "1934",
                    "institution": "Upps"
                },
                {
                    "degree": "vet :ex",
                    "year": "1943",
                    "institution": null
                }
            ],
            "career": [
                {
                    "position": "distr :vet",
                    "years": {
                        "start_year": 1951,
                        "end_year": null
                    },
                    "organization": "Ljugarn"
                }
            ],
            "family": {
                "spouse": "Karin Egnell",
                "marriage_year": "1958",
                "children": null
            },
            "hobbies": [
                "jakt",
                "fågelhunddressyr"
            ]
        },
        "2": {
            "full_name": "CARL T INGWALL",
            "location": "Norrköping",
            "occupation": "civilingenjör",
            "birth_details": {
                "date": "06/08/1908",
                "place": "Sthlm",
                "parents": "Teodor I o Hilma Pettersson"
            },
            "education": [
                {
                    "degree": "Stud:ex",
                    "year": "1928",
                    "institution": null
                },
                {
                    "degree": null,
                    "year": "1932",
                    "institution": "KTH"
                }
            ],
            "career": [
                {
                    "position": "anst Sthlms stads hamnstyr",
                    "years": {
                        "start_year": 1932,
                        "end_year": 1933
                    },
                    "organization": null
                },
                {
                    "position": "W :styr",
                    "years": {
                        "start_year": 1933,
                        "end_year": null
                    },
                    "organization": null
                },
                {
                    "position": "byråing dess brobyrå",
                    "years": {
                        "start_year": 1938,
                        "end_year": null
                    },
                    "organization": null
                },
                {
                    "position": "anst ESAB Gbg",
                    "years": {
                        "start_year": 1943,
                        "end_year": null
                    },
                    "organization": null
                },
                {
                    "position": "ch dess filial",
                    "years": {
                        "start_year": 1946,
                        "end_year": null
                    },
                    "organization": "Norrkpg"
                }
            ],
            "family": {
                "spouse": "Dagmar Lindquist",
                "marriage_year": "1938",
                "children": [
                    {
                        "name": "Marika",
                        "birth_year": "1938"
                    },
                    {
                        "name": "Louise",
                        "birth_year": "1939"
                    },
                    {
                        "name": "Charlotte",
                        "birth_year": "1945"
                    }
                ]
            },
            "hobbies": [
                "golf"
            ]
        },
        "3": {
            "full_name": "C GÖSTA INGVARSSON",
            "location": "Mariestad",
            "occupation": "byrådirektör",
            "birth_details": {
                "date": "04/02/1925",
                "place": "Malmö",
                "parents": "las:-läk Gösta I o Wända Malmström"
            },
            "education": [
                {
                    "degree": "Stud:ex",
                    "year": "1943",
                    "institution": "Vänersborg"
                },
                {
                    "degree": "jur kand",
                    "year": "1950",
                    "institution": "Lund"
                }
            ],
            "career": [
                {
                    "position": "tjg länsstyr",
                    "years": {
                        "start_year": 1950,
                        "end_year": 1951
                    },
                    "organization": "Älvsb l"
                },
                {
                    "position": "rådh:rätt",
                    "years": {
                        "start_year": 1951,
                        "end_year": null
                    },
                    "organization": "Vänersborg"
                },
                {
                    "position": "eo tax:insp",
                    "years": {
                        "start_year": 1957,
                        "end_year": null
                    },
                    "organization": "Skarab l"
                },
                {
                    "position": "l:e tax:insp",
                    "years": {
                        "start_year": 1958,
                        "end_year": null
                    },
                    "organization": null
                },
                {
                    "position": "l:e byråsekr",
                    "years": {
                        "start_year": 1961,
                        "end_year": null
                    },
                    "organization": "länsskolndn Skarab l"
                }
            ],
            "family": {
                "spouse": "Maja Bohmansson",
                "marriage_year": "1947",
                "children": [
                    {
                        "name": "Lena",
                        "birth_year": "1951"
                    }
                ]
            }
        }
    }
}