{
    "original": "DEGERSTEDT, NILS D, överläkare,\n\nRånäs, f i Skellefteå 10/12/02 av lantbr\nOlof D o Josefina Johansson.\nStud:ex Upps 23, med kand Sthlm 28,\nmed lic 49. - Förordn Psykiatr sjh,\npsy-kiatr klin Karol sjh o Långbro sjh\n39-49, l:e underläk Långbro sjh 50,\növerläk Rånäs sjh sed 53 o styresm där sed\n59.\nGift 38 m Vera Valkin f 07.\n\nDEGNER, J ELOF, bankdirektör,\nÖrebro, f i Degerfors, Örebro l, 25/12/11\nav banmäst Erik Johnson o Hilda\nHasselkvist.\n\nRealex, anst Skånska bkn 28, Gbgs bk\nVästerås 36, kassör kont Degerfors 38,\nförest låneavd kont Örebro 41, kamrer\no kont :f örest Lindesberg 51, l:e kamrer\nHalmstad 57, dir Karlstad 60, ch Gbgs\nbks pro v :central Örebro l sed 62.\n-Styr:led Gbgs bk Örebro; medl\nTem-pelriddarO. - Hobby: fiske.\nGift 38 m Astrid Jakobson f 12, dtr t\ndir Karl J o Anna Bengtsson. - Barn:\nBirgitta f 41, Christina f 46.\n\nDEKANY, PETER P, provinsialläkare,\nTrosa, f i Paris 27/11/27 av ing Eugen\nD o Serena Goldstein.\nStud:ex Budapest 46, med lic där 52, sv\nläk 61; sjh :förordn Ungern 52-56, vik\nläk ol platser i Sv:e 57-62, prov:läk\nTrosa sed 62. - Hobbies: fotografering,\nkanotsport.\n\nGift 52 m Maria Gal f 33, dtr t arkit\nTeodor G o Magdola Deutsch. - Barn:\nKatarina f 57, Eva f 60, Anne-Marie\nf 63.\n\nde la COUR, P HROAR, direktör,\nArboga, f i Oslo 6/12/14.\nDir ab Arbogamaskiner sed 45, ab\nScania verktyg Hbg sed 56, ab C A Carlson\n&amp; Co Arboga sed 61. - Styr :led Skand\nbkns avd :kont Arboga sed 51, ordf sed\n58, led Stadsfullm.\n\nde LAVAL, J GILBERT,\nbergsingenjör, Surahammar, f i Sigtuna 11/7/24 av\növerste Jacques de L o Sigrid Hain.\nStud:ex Linkpg 42, res:off:ex 45, KTH\n49,   ass   värmetekn   avd   Surahammars\nbruks ab 50, avd :ing ring- o\nsmidesver-ket där sed 52.\nGift 51 m Camilla Siwertz f 31, dtr t\n\nförf Sigfrid S o Margit Strömberg.\n-Barn: Suzanne f 53, Héléne f 56,\nPontus f 61.\n\n",
    "structured": {
        "1": {
            "full_name": "Nils Degerstedt",
            "location": "Rånäs",
            "occupation": "Överläkare",
            "birth_details": {
                "date": "10/12/1902",
                "place": "Skellefteå",
                "parents": "lantbr Olof D o Josefina Johansson"
            },
            "education": [
                {
                    "degree": "Stud:ex",
                    "year": "1923",
                    "institution": "Upps"
                },
                {
                    "degree": "med kand",
                    "year": "1928",
                    "institution": "Sthlm"
                },
                {
                    "degree": "med lic",
                    "year": "1949",
                    "institution": "NULL"
                }
            ],
            "career": [
                {
                    "position": "Förordn Psykiatr sjh",
                    "years": {
                        "start_year": 1939,
                        "end_year": 1949
                    },
                    "organization": "Långbro sjh"
                },
                {
                    "position": "l:e underläk",
                    "years": {
                        "start_year": 1950,
                        "end_year": 1950
                    },
                    "organization": "Långbro sjh"
                },
                {
                    "position": "överläk",
                    "years": {
                        "start_year": 1953,
                        "end_year": 1959
                    },
                    "organization": "Rånäs sjh"
                }
            ],
            "family": {
                "spouse": "Vera Valkin",
                "marriage_year": "1938",
                "children": []
            }
        },
        "2": {
            "full_name": "Elof Degner",
            "location": "Örebro",
            "occupation": "Bankdirektör",
            "birth_details": {
                "date": "25/12/1911",
                "place": "Degerfors, Örebro l",
                "parents": "banmäst Erik Johnson o Hilda Hasselkvist"
            },
            "education": [],
            "career": [
                {
                    "position": "Realex",
                    "years": {
                        "start_year": 1928,
                        "end_year": 1928
                    },
                    "organization": "NULL"
                },
                {
                    "position": "kamrer",
                    "years": {
                        "start_year": 1960,
                        "end_year": 1960
                    },
                    "organization": "Karlstad"
                }
            ],
            "family": {
                "spouse": "Astrid Jakobson",
                "marriage_year": "1938",
                "children": [
                    {
                        "name": "Birgitta",
                        "birth_year": "1941"
                    },
                    {
                        "name": "Christina",
                        "birth_year": "1946"
                    }
                ]
            }
        },
        "3": {
            "full_name": "Peter P Dekany",
            "location": "Trosa",
            "occupation": "Provinsialläkare",
            "birth_details": {
                "date": "27/11/1927",
                "place": "Paris",
                "parents": "ing Eugen D o Serena Goldstein"
            },
            "education": [
                {
                    "degree": "Stud:ex",
                    "year": "1946",
                    "institution": "Budapest"
                },
                {
                    "degree": "med lic",
                    "year": "1952",
                    "institution": "Budapest"
                }
            ],
            "career": [
                {
                    "position": "prov:läk",
                    "years": {
                        "start_year": 1962,
                        "end_year": 1962
                    },
                    "organization": "Trosa"
                }
            ],
            "family": {
                "spouse": "Maria Gal",
                "marriage_year": "1952",
                "children": [
                    {
                        "name": "Katarina",
                        "birth_year": "1957"
                    },
                    {
                        "name": "Eva",
                        "birth_year": "1960"
                    },
                    {
                        "name": "Anne-Marie",
                        "birth_year": "1963"
                    }
                ]
            }
        },
        "4": {
            "full_name": "P Hroar de la Cour",
            "location": "Arboga",
            "occupation": "Direktör",
            "birth_details": {
                "date": "6/12/1914",
                "place": "Oslo",
                "parents": "NULL"
            },
            "education": [],
            "career": [
                {
                    "position": "Dir",
                    "years": {
                        "start_year": 1961,
                        "end_year": 1961
                    },
                    "organization": "ab C A Carlson & Co Arboga"
                }
            ],
            "family": {
                "spouse": "NULL",
                "marriage_year": "NULL",
                "children": []
            }
        },
        "5": {
            "full_name": "J Gilbert de Laval",
            "location": "Surahammar",
            "occupation": "Bergsingenjör",
            "birth_details": {
                "date": "11/7/1924",
                "place": "Sigtuna",
                "parents": "överste Jacques de L o Sigrid Hain"
            },
            "education": [
                {
                    "degree": "Stud:ex",
                    "year": "1942",
                    "institution": "Linkpg"
                },
                {
                    "degree": "res:off:ex",
                    "year": "1945",
                    "institution": "NULL"
                },
                {
                    "degree": "KTH",
                    "year": "1949",
                    "institution": "NULL"
                }
            ],
            "career": [
                {
                    "position": "ass värmetekn avd",
                    "years": {
                        "start_year": 1950,
                        "end_year": 1952
                    },
                    "organization": "Surahammars bruks ab"
                }
            ],
            "family": {
                "spouse": "Camilla Siwertz",
                "marriage_year": "1951",
                "children": [
                    {
                        "name": "Suzanne",
                        "birth_year": "1953"
                    },
                    {
                        "name": "Héléne",
                        "birth_year": "1956"
                    },
                    {
                        "name": "Pontus",
                        "birth_year": "1961"
                    }
                ]
            }
        }
    }
}