{
    "original": "DHEJNE, SVEN E W, ingenjör,\nKarlstad, f i Malmö 15/8/10 av Wilhelm D\no Elsa Sörensson.\n\nIng:ex Malmö HTL 32, yrkeslär 3-8,\nmontagech ab Calor Karlstad 40, avd :ch\nAhlberg &amp; Bengtsson Landskrona 42,\neg föret inom rörledn:bransch sed 45.\n-Styr :led Ol jeeldn :firmornas riksförb.\nGift 36 m Rut Hansson f 11, dtr t\nköpman Ernst H o Selma H. - Barn:\nRolf f 40, Lars f 43.\n\nDIBBERN, WERNER F A W,\nprovinsialläkare, Odensbacken, f i Kiel\n18/9/18 av köpm Heinrich D o Maria\nSchultz.\n\nLäk:ex Kiel 44, K Mts tillst att i Sv:e\nutöva läkekonsten 55, underläk Kiel 45-\n\n49,  2:e underläk neurokir avd Södersjh\n\n50,  kir avd Stocksunds las 51, l:e\nunderläk kir avd Gällivare las 52, prov:läk\nMalmbergets l:a distr 53, Odensbacken\nsed 59.\n\nGift 49 m Gerda Staak f 25, dtr t prof\nGerhard S o Helene Hennecke. - Barn:\nMarie-Helén f 53, Christian f 55.\n\nDIDERHOLM, HANS E, med dr,\ndocent, Uppsala, f i Sandviken 19/11/29 av\nciviling Erik D o Irma Eriksson.\nStud:ex Gävle 49, med kand Upps 52,\nmed lic 57, med dr o doc i histologi\nUpps univ 61. - Aman o ass histol inst\nUpps 54, forskarass Upps sed 61.\nGift 56 m med kand Eva Synnerstad\nf 36, dtr t tandl Gösta S o Marianne\nTörner. - Barn: Erik f 57, Ylva f 60,\nGudrun f 61.\n\nDIDRON, P LENNART, civilekonom,\nturistdirektör, Falun, f i St Kil, Värml l,\n26/3/24 av l:e kansliskr Ragnar D o\nKatarina Slöör.\n\nStud:ex Umeå 45, DHS 51, stat :skriv\nSJ 45, sekr TCO 51, omb:man Sv\nfolkskollär :f örb 54, verkst dir Dalarnas tu-\n\nristtrafikförb sed 61. - Medl Odd\nFellow. - Hobbies: jakt, fiske.\nGift 48 m Alfhild Nilson f 21, dtr t\nstat:mäst A N o Inga Elfberg. - Barn:\nBirgitta f 48, Ing-Mari f 54.\n",
    "structured": {
        "0": {
            "full_name": "Sven E W Dhejne",
            "location": "Karlstad",
            "occupation": "ingenjör",
            "birth_details": {
                "date": "15/08/1910",
                "place": "Malmö",
                "parents": "Wilhelm D o Elsa Sörensson"
            },
            "education": [
                {
                    "degree": "ing:ex Malmö HTL",
                    "year": "1932",
                    "institution": "Malmö HTL"
                }
            ],
            "career": [
                {
                    "position": "yrkeslär",
                    "years": {
                        "start_year": 1940,
                        "end_year": 1945
                    },
                    "organization": "yrkeslär"
                },
                {
                    "position": "montagech ab Calor Karlstad",
                    "years": {
                        "start_year": 1940
                    },
                    "organization": "montagech ab Calor Karlstad"
                },
                {
                    "position": "avd :ch Ahlberg & Bengtsson Landskrona",
                    "years": {
                        "start_year": 1942
                    },
                    "organization": "Ahlberg & Bengtsson Landskrona"
                }
            ],
            "family": {
                "spouse": "Rut Hansson",
                "marriage_year": "1936",
                "children": [
                    {
                        "name": "Rolf",
                        "birth_year": "1940"
                    },
                    {
                        "name": "Lars",
                        "birth_year": "1943"
                    }
                ]
            }
        },
        "1": {
            "full_name": "Werner F A W Dibbern",
            "location": "Odensbacken",
            "occupation": "provinsialläkare",
            "birth_details": {
                "date": "18/09/1918",
                "place": "Kiel",
                "parents": "Heinrich D o Maria Schultz"
            },
            "education": [
                {
                    "degree": "läk:ex Kiel",
                    "year": "1944",
                    "institution": "Kiel"
                }
            ],
            "career": [
                {
                    "position": "underläk Kiel",
                    "years": {
                        "start_year": 1945,
                        "end_year": 1949
                    },
                    "organization": "Kiel"
                },
                {
                    "position": "2:e underläk neurokir avd Södersjh",
                    "years": {
                        "start_year": 1950
                    },
                    "organization": "neurokir avd Södersjh"
                },
                {
                    "position": "kir avd Stocksunds las",
                    "years": {
                        "start_year": 1951
                    },
                    "organization": "Stocksunds las"
                }
            ],
            "family": {
                "spouse": "Gerda Staak",
                "marriage_year": "1949",
                "children": [
                    {
                        "name": "Marie-Helén",
                        "birth_year": "1953"
                    },
                    {
                        "name": "Christian",
                        "birth_year": "1955"
                    }
                ]
            }
        },
        "2": {
            "full_name": "Hans E Didron",
            "location": "Uppsala",
            "occupation": "med dr, docent",
            "birth_details": {
                "date": "19/11/1929",
                "place": "Sandviken",
                "parents": "Erik D o Irma Eriksson"
            },
            "education": [
                {
                    "degree": "med kand Upps",
                    "year": "1952",
                    "institution": "Upps"
                },
                {
                    "degree": "med lic",
                    "year": "1957",
                    "institution": "histologi Upps univ"
                }
            ],
            "career": [
                {
                    "position": "Aman o ass histol inst Upps",
                    "years": {
                        "start_year": 1954
                    },
                    "organization": "histol inst Upps"
                },
                {
                    "position": "forskarass Upps",
                    "years": {
                        "start_year": 1961
                    },
                    "organization": "Upps"
                }
            ],
            "family": {
                "spouse": "Eva Synnerstad",
                "marriage_year": "1956",
                "children": [
                    {
                        "name": "Erik",
                        "birth_year": "1957"
                    },
                    {
                        "name": "Ylva",
                        "birth_year": "1960"
                    },
                    {
                        "name": "Gudrun",
                        "birth_year": "1961"
                    }
                ]
            }
        },
        "3": {
            "full_name": "P Lennart Didron",
            "location": "Falun",
            "occupation": "civilekonom, turistdirektör",
            "birth_details": {
                "date": "26/03/1924",
                "place": "St Kil, Värml l",
                "parents": "Ragnar D o Katarina Slöör"
            },
            "education": [
                {
                    "degree": "Stud:ex Umeå",
                    "year": "1945",
                    "institution": "Umeå"
                },
                {
                    "degree": "DHS",
                    "year": "1951",
                    "institution": "DHS"
                }
            ],
            "career": [
                {
                    "position": "stat :skriv SJ",
                    "years": {
                        "start_year": 1945
                    },
                    "organization": "SJ"
                },
                {
                    "position": "sekr TCO",
                    "years": {
                        "start_year": 1951
                    },
                    "organization": "TCO"
                },
                {
                    "position": "omb:man Sv folkskollär :f örb",
                    "years": {
                        "start_year": 1954
                    },
                    "organization": "Sv folkskollär :f örb"
                },
                {
                    "position": "verkst dir Dalarnas turisttrafikförb",
                    "years": {
                        "start_year": 1961
                    },
                    "organization": "Dalarnas turisttrafikförb"
                }
            ],
            "family": {
                "spouse": "Alfhild Nilson",
                "marriage_year": "1948",
                "children": [
                    {
                        "name": "Birgitta",
                        "birth_year": "1948"
                    },
                    {
                        "name": "Ing-Mari",
                        "birth_year": "1954"
                    }
                ]
            },
            "hobbies": [
                "jakt",
                "fiske"
            ]
        }
    }
}