{
    "original": "KARLSSON, KARL-ÅKE,\nstadskamrer, Mjölby, f i Arbrå, Gävleb l, 13/12/\n25 av hemm:äg Lars K o Ellen\nAndersson.\n\nDSI Lund 53, företagsekonomex TBV\nVästerås 60, komm :kamr Skultuna 54,\nstadskamr:ass Örebro 60, stadskamr\nMjölby sed 61. - Verkst dir ab Mjölby\nbowlinghall sed 64. - Medl Lions Club.\n-Hobbies: bridge, Skytte.\nGift 53 m Sylvia Johansson, dtr t disp\nErnst J o Eufemia Lundberg. - Barn:\nAnn-Sofie f 57, Åsa f 60.\n\nKARLSSON, LÄRS-ERIK,\ncivilingenjör, Norrköping, f i Norrkpg 27/2/28 av\nred Arvid K o Annie Wallerstedt.\nIng:ex tekn gymn Norrkpg 48, CTH 53,\ning   STAL   Finspång   53,   Scania-Vabis\n\nSödertälje 56, Asea Västerås 59, STAL\nRefrigeration ab Norrkpg sed 60.\nGift  55   m  Kerstin   Gustavsson,   dtr  t\nSigfrid   G  o  Kristina  Linder.   -  Barn:\nKarin f 56, Anders f 58, Olof f 65.\n\nKARLSSON, MATS I E,\nläroverksadjunkt, Vetlanda, f i N Sandsjö, Jönkpgs\nl, 28/12/28 av maskinsnick Einar K o\nAlma Gustafsson.\n\nStud:ex Jönkpg 48, fil mag Lund 55, e o\neo adj hal Karlshamn 55-59, adj allm\ngymn o realsk Vetlanda sed 59.\nGift 53 m Ingrid von Gertten f 30, dtr\nt hemm:äg Bertil v G o Lisa Ek. - Barn:\nLena f 56, Klas f 57, Ola f 60.\n\nKARLSSON, NILS-GUSTAF H,\ndisponent, Nässjö, f i Nässjö 26/12/19 av\nbyggm C O K o Hilda Johnson.\nStud:ex Eksjö 39, hdlsgymn Norrkpg\n42. - Anst ab Nässjö butiksinredn 40, ab\nWST-hus 41, Ceos byggn :varor ab 42,\nverkst dir o inneh sed 47, verkst dir ab\nRydéns träexp Nässjö sed 62. - Styr:led\nSTC sed 49, ordf Jönkpgs l trä- &amp;\nbyggn :varuf ören 62, led byggn :ndn sed\n50, DK 55-63, skolbyggn:komm 56-63.\n-Medl Rotary, TR, SMF. - Hobbies:\nmusik, golf.\n\nGift 46 m Febe Sjöstrand f 20, dtr t\nförrn E S o h h. - Barn: Pär f 48,\nAnn-Margret f 52.\n\n",
    "structured": {
        "1": {
            "full_name": "Karl-Åke Karlsson",
            "location": "Mjölby",
            "occupation": "stadskamrer",
            "birth_details": {
                "date": "13/12/1925",
                "place": "Arbrå, Gävleb l"
            },
            "education": [
                {
                    "degree": "DSI",
                    "year": "1953",
                    "institution": "Lund"
                },
                {
                    "degree": "företagsekonomex",
                    "year": "1960",
                    "institution": "TBV Västerås"
                }
            ],
            "career": [
                {
                    "position": "komm :kamr",
                    "years": {
                        "start_year": 1954,
                        "end_year": 1960
                    },
                    "organization": "Skultuna"
                },
                {
                    "position": "stadskamr:ass",
                    "years": {
                        "start_year": 1960,
                        "end_year": 1961
                    },
                    "organization": "Örebro"
                },
                {
                    "position": "stadskamr",
                    "years": {
                        "start_year": 1961,
                        "end_year": null
                    },
                    "organization": "Mjölby"
                },
                {
                    "position": "Verkst dir",
                    "years": {
                        "start_year": 1964,
                        "end_year": null
                    },
                    "organization": "ab Mjölby bowlinghall"
                }
            ],
            "family": {
                "spouse": "Sylvia Johansson",
                "marriage_year": "1953",
                "children": [
                    {
                        "name": "Ann-Sofie",
                        "birth_year": "1957"
                    },
                    {
                        "name": "Åsa",
                        "birth_year": "1960"
                    }
                ]
            },
            "hobbies": [
                "bridge",
                "Skytte"
            ]
        },
        "2": {
            "full_name": "Lärs-Erik Karlsson",
            "location": "Norrköping",
            "occupation": "civilingenjör",
            "birth_details": {
                "date": "27/02/1928",
                "place": "Norrkpg"
            },
            "education": [
                {
                    "degree": "Ing",
                    "year": "1953",
                    "institution": "CTH"
                }
            ],
            "career": [
                {
                    "position": "ing",
                    "years": {
                        "start_year": 1953,
                        "end_year": 1956
                    },
                    "organization": "STAL Finspång"
                },
                {
                    "position": null,
                    "years": {
                        "start_year": 1956,
                        "end_year": 1959
                    },
                    "organization": "Scania-Vabis Södertälje"
                },
                {
                    "position": null,
                    "years": {
                        "start_year": 1959,
                        "end_year": null
                    },
                    "organization": "Asea Västerås"
                },
                {
                    "position": null,
                    "years": {
                        "start_year": 1960,
                        "end_year": null
                    },
                    "organization": "STAL Refrigeration ab Norrkpg"
                }
            ],
            "family": {
                "spouse": "Kerstin Gustavsson",
                "marriage_year": "1955",
                "children": [
                    {
                        "name": "Karin",
                        "birth_year": "1956"
                    },
                    {
                        "name": "Anders",
                        "birth_year": "1958"
                    },
                    {
                        "name": "Olof",
                        "birth_year": "1965"
                    }
                ]
            }
        },
        "3": {
            "full_name": "Mats I E Karlsson",
            "location": "Vetlanda",
            "occupation": "läroverksadjunkt",
            "birth_details": {
                "date": "28/12/1928",
                "place": "N Sandsjö, Jönkpgs l"
            },
            "education": [
                {
                    "degree": "Stud",
                    "year": "1955",
                    "institution": "Lund"
                }
            ],
            "career": [
                {
                    "position": "eo adj",
                    "years": {
                        "start_year": 1955,
                        "end_year": 1959
                    },
                    "organization": "hal Karlshamn"
                },
                {
                    "position": "adj allm gymn o realsk",
                    "years": {
                        "start_year": 1959,
                        "end_year": null
                    },
                    "organization": "Vetlanda"
                }
            ],
            "family": {
                "spouse": "Ingrid von Gertten",
                "marriage_year": "1953",
                "children": [
                    {
                        "name": "Lena",
                        "birth_year": "1956"
                    },
                    {
                        "name": "Klas",
                        "birth_year": "1957"
                    },
                    {
                        "name": "Ola",
                        "birth_year": "1960"
                    }
                ]
            }
        },
        "4": {
            "full_name": "Nils-Gustaf H Karlsson",
            "location": "Nässjö",
            "occupation": "disponent",
            "birth_details": {
                "date": "26/12/1919",
                "place": "Nässjö"
            },
            "education": [
                {
                    "degree": "Stud",
                    "year": "1939",
                    "institution": "Eksjö"
                },
                {
                    "degree": "hdlsgymn",
                    "year": "1942",
                    "institution": "Norrkpg"
                }
            ],
            "career": [
                {
                    "position": "Anst ab",
                    "years": {
                        "start_year": 1940,
                        "end_year": null
                    },
                    "organization": "Nässjö butiksinredn"
                },
                {
                    "position": null,
                    "years": {
                        "start_year": 1941,
                        "end_year": null
                    },
                    "organization": "WST-hus"
                },
                {
                    "position": "verkst dir",
                    "years": {
                        "start_year": 1947,
                        "end_year": null
                    },
                    "organization": "Ceos byggn :varor ab"
                },
                {
                    "position": "verkst dir",
                    "years": {
                        "start_year": 1962,
                        "end_year": null
                    },
                    "organization": "Rydéns träexp Nässjö"
                }
            ],
            "family": {
                "spouse": "Febe Sjöstrand",
                "marriage_year": "1946",
                "children": [
                    {
                        "name": "Pär",
                        "birth_year": "1948"
                    },
                    {
                        "name": "Ann-Margret",
                        "birth_year": "1952"
                    }
                ]
            },
            "hobbies": [
                "musik",
                "golf"
            ]
        }
    }
}