{
    "original": "KJELLSON, H LENNART K,\nprovinsialläkare, Herrljunga, f i Kärna, Österg\nl, 11/3/19 av flygdir Henry K o Tina\nSvensson.\n\nStud:ex Sthlm 40, med kand 43 o med\nlic Sthlm 50, tf prov:läk öl distr 47-49,\nunderläk med avd Bollnäs las 50-55,\nprov:läk Herrljunga distr sed 55. -\nSkol-läk Herrljunga samrealsk sed 55,\njv:-läk sed 56. - Skr i inv med (Refsums\nsjukd). - Hobbies: släktforskn,\nsmal-filmn, filateli, modelljärnv.\nGift 46 m sophiasyst Ann-Hild\nHolmdahl f 21, dtr t las:läk Henrik H o\nIngrid Dahlgren. - Barn: Anders f 47,\nMonica f 50, Göran f 51.\n\nKJELLSTRAND, GUNNAR M T, bitr\növerläkare, Skene, f i Växjö 19/11/27 av\nmed lic Torsten K o Agda Breimer.\nStud:ex Sigtuna 48, med kand 52 o med\nlic Gbg 56; öl läk:förordn 54-58,\nunderläk med avd Växjö las 58-63, bitr\növerläk med avd Skene las sed 64. - Skr\ni inv med.\n\nGift 54 m Vera Richter f 24, dtr t\nfond-ch Fritz R o Clara Johnson. - Barn:\nMichael f 56, Peter f 60, Jonas f 64.\n\nKJELLSTRÖM, ERIK, kantor,\nMåns-arp,   f   i   Malmö   7/3/18   av  målarmäst\nNils K o Anna Borg.\nKantorsex Lund  39,  folkskollär :ex 40,\nres:off:ex 43;  kantor Torpa 42, kantor\n\n0   folkskollär   Månsarp   sed  47.   -  Led\nkyrkofullm o v ordf nykterh:nd 58. - V\nordf Tabergsbygd kr av SRK 48, kårch\nMånsarps scoutkår 48-61, v kårordf 61,\nseniorscoutled 57, v ordf Jönkpgs l\nkör-förb. - Kapt I 11 res 60. - Utm:\nSRK-ftjt,  Sv scoutförb  ftjtG,  Sv:es körförb\nftjt.\n\nGift 42 m Elsa Wennerström f 18, dtr\nt sjökapt Nils W o Elida Qwist. - Barn:\nThomas f 44, Staffan f 46, Krister f 50.\nKJERFVE, ÅKE H B E:SON,\nbankdirektör, Skövde, f i Horn, Skarab l,\n19/1/06 av jvtjm Johan Eriksson o Anna\nAndersson.\n\nRealex Skövde 24, korresp :stud; anst\nSkarab ensk bk 25, kamr där 31, anst\nSkövde sparbk 32, verkst dir där sed 46\n(styr:led sed 47). - Styr:led Sv\nbankm:-förb Skarab :distr 3*8-43, Skarab o Älvsb\n\n1   sparbksfören sed  55;  stadsrev 39-45,\nnämndem sed 56. - Medl FrimO, Odd\nFellow,  Rotary.  -  Utm: RVO.  -\nHobbies: bridge, tennis.\n\nGift 43 m Valborg Andersson f 10, dtr\nt Gustaf A o Clara A. - Barn: Björn\nf 44, Finn f 46.\n\n",
    "structured": {
        "0": {
            "full_name": "KJELLSON, H LENNART K",
            "location": "Herrljunga",
            "occupation": "provinsialläkare",
            "birth_details": {
                "date": "11/03/1919",
                "place": "Kärna, Östergötland"
            },
            "education": [
                {
                    "degree": "Stud:ex",
                    "year": "1940",
                    "institution": "Sthlm"
                },
                {
                    "degree": "med kand",
                    "year": "1943",
                    "institution": "Sthlm"
                },
                {
                    "degree": "med lic",
                    "year": "1950",
                    "institution": "Sthlm"
                }
            ],
            "career": [
                {
                    "position": "tf prov:läk",
                    "years": {
                        "start_year": 1947,
                        "end_year": 1949
                    },
                    "organization": "öl distr"
                },
                {
                    "position": "underläk med avd",
                    "years": {
                        "start_year": 1950,
                        "end_year": 1955
                    },
                    "organization": "Bollnäs las"
                },
                {
                    "position": "prov:läk",
                    "years": {
                        "start_year": 1955,
                        "end_year": null
                    },
                    "organization": "Herrljunga distr"
                },
                {
                    "position": "Skol-läk",
                    "years": {
                        "start_year": 1955,
                        "end_year": null
                    },
                    "organization": "Herrljunga samrealsk"
                },
                {
                    "position": "jv:-läk",
                    "years": {
                        "start_year": 1956,
                        "end_year": null
                    },
                    "organization": null
                }
            ],
            "family": {
                "spouse": "Ann-Hild Holmdahl",
                "marriage_year": "1946",
                "children": [
                    {
                        "name": "Anders",
                        "birth_year": "1947"
                    },
                    {
                        "name": "Monica",
                        "birth_year": "1950"
                    },
                    {
                        "name": "Göran",
                        "birth_year": "1951"
                    }
                ]
            }
        },
        "1": {
            "full_name": "KJELLSTRAND, GUNNAR M T",
            "location": "Skene",
            "occupation": "bitr överläkare",
            "birth_details": {
                "date": "19/11/1927",
                "place": "Växjö"
            },
            "education": [
                {
                    "degree": "Stud:ex",
                    "year": "1948",
                    "institution": "Sigtuna"
                },
                {
                    "degree": "med kand",
                    "year": "1952",
                    "institution": "NULL"
                },
                {
                    "degree": "med lic",
                    "year": "1956",
                    "institution": "Gbg"
                }
            ],
            "career": [
                {
                    "position": "öl läk:förordn",
                    "years": {
                        "start_year": 1954,
                        "end_year": 1958
                    },
                    "organization": null
                },
                {
                    "position": "underläk med avd",
                    "years": {
                        "start_year": 1958,
                        "end_year": 1963
                    },
                    "organization": "Växjö las"
                },
                {
                    "position": "bitr överläk med avd",
                    "years": {
                        "start_year": 1964,
                        "end_year": null
                    },
                    "organization": "Skene las"
                }
            ],
            "family": {
                "spouse": "Vera Richter",
                "marriage_year": "1954",
                "children": [
                    {
                        "name": "Michael",
                        "birth_year": "1956"
                    },
                    {
                        "name": "Peter",
                        "birth_year": "1960"
                    },
                    {
                        "name": "Jonas",
                        "birth_year": "1964"
                    }
                ]
            }
        },
        "2": {
            "full_name": "KJELLSTRÖM, ERIK",
            "location": "Månsarp",
            "occupation": "kantor",
            "birth_details": {
                "date": "07/03/1918",
                "place": "Malmö"
            },
            "education": [
                {
                    "degree": "Kantorsex",
                    "year": "1939",
                    "institution": "Lund"
                },
                {
                    "degree": "folkskollär :ex",
                    "year": "1940",
                    "institution": "NULL"
                },
                {
                    "degree": "res:off:ex",
                    "year": "1943",
                    "institution": "NULL"
                }
            ],
            "career": [
                {
                    "position": "kantor",
                    "years": {
                        "start_year": 1942,
                        "end_year": null
                    },
                    "organization": "Torpa"
                },
                {
                    "position": "kantor",
                    "years": {
                        "start_year": 1947,
                        "end_year": null
                    },
                    "organization": "Månsarp"
                }
            ],
            "family": {
                "spouse": "Elsa Wennerström",
                "marriage_year": "1942",
                "children": [
                    {
                        "name": "Thomas",
                        "birth_year": "1944"
                    },
                    {
                        "name": "Staffan",
                        "birth_year": "1946"
                    },
                    {
                        "name": "Krister",
                        "birth_year": "1950"
                    }
                ]
            }
        },
        "3": {
            "full_name": "KJERFVE, ÅKE H B E:SON",
            "location": "Skövde",
            "occupation": "bankdirektör",
            "birth_details": {
                "date": "19/01/1906",
                "place": "Horn, Skaraborgs Län"
            },
            "education": null,
            "career": [
                {
                    "position": "anst",
                    "years": {
                        "start_year": 1925,
                        "end_year": null
                    },
                    "organization": "Skarab ensk bk"
                },
                {
                    "position": "kamr",
                    "years": {
                        "start_year": 1931,
                        "end_year": null
                    },
                    "organization": "där"
                },
                {
                    "position": "verkst dir",
                    "years": {
                        "start_year": 1946,
                        "end_year": null
                    },
                    "organization": "Skövde sparbk"
                }
            ],
            "family": {
                "spouse": "Valborg Andersson",
                "marriage_year": "1943",
                "children": [
                    {
                        "name": "Björn",
                        "birth_year": "1944"
                    },
                    {
                        "name": "Finn",
                        "birth_year": "1946"
                    }
                ]
            }
        }
    }
}