{
    "original": "Norlin, Ollof Gunnar Ajlfred’,\nistadts*-ingemjör, Bkisjö, f. 11/3/00 i Göt eboTg\nav fi0illkisiki0’lll. J. A. N. o. Eiiin Tiberg.\nG. 38 m. Greta Amirlon. — S’tud :ex. 18,\nCTH facksik. f. hus:byggn. 23, CTH\nväg- o. va!tten’byiggn. 24, kurs. f. uitib.\nav mätn :män i isitad i Gbg 29. Res. f.\nhusbyggn:- o. stadsbyggn :stud. i Holl.\no. Tysikl. 26, i Ho’lll., Tysikl., B^llg. 27,\nliamn’s’tud. i Hoill, Tyskl, Bellg., Engl.,\nDanm. 29, husbyggn:- o. stadsbyggn\n:-S’tud. i Finil’. 30, d Engl., Frankr., Tysikl.\n36. Bitr. ing. v. Gbgs, Marstrands o.\nKiungälivs stodsii ng :ko’n’t. 24-25, tekn.\nchef o. arkit. i Torsten O. Lindbecks\nA-B 26-30, ;stiadsing. O’. ’stadisarkrt. i\nKristintehamn 30-40, i Ekisijö fr. 40.\nArkit. o. sekr. i Kristiineh. o. Varnum^s\nhembifören. 35-40. Skr.: Ståilfönsiter\n(30), bro’s’chyrer, art. i ;stadisbygign\n:-frågO’r.\n\nNorlindh, Sven Peter Bror Albert,\nfil. dr, lektor, Linköping, f. 24/4/82 i\nGli-måkra, Kri’s’t. k, av kantor N. P. N.\no. J’0’hanna Svens^son. G. 15 m. Eliin\nÅgren. Barn: Sven-Arne f. 18, apot.,\nMalmö, Carl-Ingmar 21, jur. kiand.,\nDHS, Sthlm. Stud:ex. i Kristianst. 00,\n•Stud. v. Lunds univ. 00, v. Leipz. univ.\n02, fik kand. 02, istud. v. Gbgs hö’gsk.\n10, fil. ;ltic. 12, fi!l. dr 25. Res. t. Danm.\n08, Tyskil. 11, Tyskil., Schv^eiz, Itak,\nFrankr. 12, Norge 13, 14, Tyskk,\nÖ^s-terr. 21, Tyskk, Danm., Enigl. 30. E.\nlär. i Borås 07-09, adj. i Varberg 10, i\nLiniköp. 16, ’lektor i h;ist. o. geogr. v.\nh. a. 1. där fr. 27. Skr.: Biefoiltkn :karta\növer Norrl. (17), Vattenf :karta öv.\nSv:e (24), Övers, av isv. vattenkraft\n(24), Sv. vattieinkr. geogr. fördeiln.\njämtie bidr. t. Norrk befoilkn :geogr.\n(24), Sv :ie’s vattienikraftsreisursier\n(gra-d:avih. 25), Om geogr. ’lärov\n:inst!itutio’-mer (Sv. därov :(lär :mötet 33), Om\nut-nyttj. av de o-ffic. kartbk v.\ngeo-gr:-und:visn. (42), art. i tddn. o. tidskr.\nRNO.\n\nNorling, Erik Gunnar, rektor,\nHyilte-bruk, f. 10/6/00 i Skurup, Malmöh. il.,\nav Alfred N. o. Tekla Otterdal. G. 34\nm. Anna Kri’Stina Höigbierg. Barn:\nMargareta f. 41. — Stud:ex. i Lund 19,\nfiil. kand. där 24, fiil. mag. 27, provår i\nSthlm 33. Tjg. v. foiliksk. o. fo-rts :sk. tre\nterm., kort. förordn. v. komm.\nm’e(l’l’an-sk. 26 o. 27, vik. adj. i Örebro o.\nOis-karsihamn 29, vik. ilektior i StMm 29-30,\ne. o. i Härnö’sand 30-33, vik. adj. i\nMalmö 34, e. o. lär. isamt rektor i\nHyiltebruk 34-35, ord. ämnesdär. o. rek-\n\n|tor där 36, v. komm. meMansk. där 38,\nadj. i geogr., matem. o. fysdk samt\nre|ktor v. Hyltebruks samreailsk. s&amp;d.\n44, tiililika rektoir f. Hyltebrukis\nyrkeis-sk. (sed. 39. Ordf. i Hyltebruks\n’sam-hällsfören. o. i Hyltie hemb :fören., led.\nav komm:fullm., riksantikv. omb. i\nLångaryd, Färgaryd o. Femsjö.\n\n",
    "structured": {
        "0": {
            "full_name": "Norlin, Ollof Gunnar Ajlfred",
            "location": "Bkisjö",
            "occupation": "istadts*-ingemjör",
            "birth_details": {
                "date": "11/03/1900",
                "place": "Göt eboTg",
                "parents": "J. A. N. o. Eiiin Tiberg"
            },
            "education": [
                {
                    "degree": "examen",
                    "year": "1918",
                    "institution": "CTH"
                },
                {
                    "degree": "facksik",
                    "year": "1923",
                    "institution": "CTH"
                }
            ],
            "career": [
                {
                    "position": "bitr. ing. v. Gbgs",
                    "years": {
                        "start_year": 1924,
                        "end_year": 1925
                    },
                    "organization": "Marstrands o. Kiungälivs stodsii ng :ko’n’t"
                },
                {
                    "position": "tekn. chef o. arkit.",
                    "years": {
                        "start_year": 1926,
                        "end_year": 1930
                    },
                    "organization": "Torsten O. Lindbecks A-B"
                },
                {
                    "position": "stiadsing. O'. 'stadisarkrt.",
                    "years": {
                        "start_year": 1930,
                        "end_year": 1940
                    },
                    "organization": "Kristintehamn"
                },
                {
                    "position": "Arkit. o. sekr.",
                    "years": {
                        "start_year": 1935,
                        "end_year": 1940
                    },
                    "organization": "Kristiineh. o. Varnum^s hembifören."
                }
            ],
            "family": {
                "spouse": "Greta Amirlon",
                "marriage_year": "1938",
                "children": []
            }
        },
        "1": {
            "full_name": "Norlindh, Sven Peter Bror Albert",
            "location": "Linköping",
            "occupation": "fil. dr, lektor",
            "birth_details": {
                "date": "24/04/1882",
                "place": "Gli-måkra, Kri’s’t. k",
                "parents": "kantor N. P. N. o. J’0’hanna Svens^son"
            },
            "education": [
                {
                    "degree": "Stud:ex.",
                    "year": "1900",
                    "institution": "Kristianst."
                },
                {
                    "degree": "fik kand.",
                    "year": "1902",
                    "institution": "Gbgs hö’gsk."
                },
                {
                    "degree": "fil. ltic.",
                    "year": "1912",
                    "institution": ""
                },
                {
                    "degree": "fi!l. dr",
                    "year": "1925",
                    "institution": ""
                }
            ],
            "career": [
                {
                    "position": "E. lär.",
                    "years": {
                        "start_year": 1907,
                        "end_year": 1909
                    },
                    "organization": "Borås"
                },
                {
                    "position": "adj.",
                    "years": {
                        "start_year": 1910,
                        "end_year": 1916
                    },
                    "organization": "Varberg"
                },
                {
                    "position": "lektor i h;ist. o. geogr.",
                    "years": {
                        "start_year": 1927,
                        "end_year": null
                    },
                    "organization": "Liniköp."
                }
            ],
            "family": {
                "spouse": "Eliin Ågren",
                "marriage_year": "1915",
                "children": [
                    {
                        "name": "Sven-Arne",
                        "birth_year": "1918"
                    },
                    {
                        "name": "Carl-Ingmar",
                        "birth_year": "1921"
                    }
                ]
            }
        },
        "2": {
            "full_name": "Norling, Erik Gunnar",
            "location": "Hyilte-bruk",
            "occupation": "rektor",
            "birth_details": {
                "date": "10/06/1900",
                "place": "Skurup, Malmöh. il.",
                "parents": "Alfred N. o. Tekla Otterdal"
            },
            "education": [
                {
                    "degree": "Stud:ex.",
                    "year": "1919",
                    "institution": "Lund"
                },
                {
                    "degree": "fiil. kand.",
                    "year": "1924",
                    "institution": "Lund"
                },
                {
                    "degree": "fiil. mag.",
                    "year": "1927",
                    "institution": ""
                }
            ],
            "career": [
                {
                    "position": "ord. ämnesdär. o. rek|tor",
                    "years": {
                        "start_year": 1936,
                        "end_year": null
                    },
                    "organization": "Hyltebruks samreailsk. s&amp;d."
                }
            ],
            "family": {
                "spouse": "Anna Kri’Stina Höigbierg",
                "marriage_year": "1934",
                "children": [
                    {
                        "name": "Margareta",
                        "birth_year": "1941"
                    }
                ]
            }
        }
    }
}