{
    "original": "Nordqvist, Lars Gustav,\nprovinsiail-läkare, Österbymo, f. 3/12/94 i Norra\nNy, Värmil. k, av Jonas N. o. Karin\nNordqvist. G. 34 m. Tora Magnusson.\nBairn: Ulf f. 36, Jan 39. — Stud:ex.\n\n17,\tmed. lic. v. Karol. inst. 29. E.\niläk. v. Sailtfsjöbadens badanst. 27-28,\nassist :läk. v. Nyköp. las. 29-30, tf.\nund:iäk. v. Apelvikens kusitsanat. 31,\nund :’läk. v. vanföreanst. d Härnösand\n31-33, tf. överiäk. där sex mån. 32-33,\nas!sist :iläk. v. Norrköp. ilats. kir. avd.\n33, e. läk. v. Kisa las. 34, tf. und :läk.\nv. S :t Eriks sjukh. röntgenavd. 35-38,\nprov :läk. i Österbymo distr. sed. 41.\n\nNordqvist, Helge Mauritz Isddor,\nchefredaktör, Varberg, f. 4/8/08 d\nHäl-singtuna, Gävleb. 1., av Gustaf N. o.\nAnna Skoglund. G. 34 m. Kanin\nLind-biliad. — Realex. i HuddksvaM 24. Res.\nIt. Finil. 31. Medarb. i Hälisingk Foilikbi.\n27, i Hudiksv. Nyh. 28-31, red :s€kr.\ndär 32-36, Borås Nyheters chefred.\n37-40, red xhef d Varbengsposten 40-42,\nchefred, o. ans^v. utg. fr. 42. Led. av\nVarbergspost€ns styr., bostads fören.\nProstens styr., siekr. i Varb. foilkparti,\nVarb. svensk-’eng. fören. o.\nNystads-koimm., ordf. d Varb. ungd :råd.\n\nNordqvist, Mattias! (Mats) Emianuel,\ntiandiläkare, Göteborg, f. 13/5/99 i Gbg\nav Emil N. o Maria Johanssoii. G. 32\nm. Märta Andrén. Barn: ULla Birigitta\nf. 37, d. 40, Ingrid Eldsabeth 37, Agneta\nBirgitta 42. — Stud rex. v. Gbgs latin\n\n18,\tmied. kand. i Upps. 26, tandiläk. 29.\nOrd. tandläk. v. Gbgs koinm.\ntand-pOiIiiMin. sied. 29.\n\nNordström, Mats Börje, redaktör,\nLiniköpdmg, f. 3/2/05 i Lulleå av Allexduis\nN. o. Viitoa Hollimquiist. G. 34 m.\nBer-tha Malmborg. Barn: Stig f. 30\n(ad:-ison), Margareta 40. — Stud:ex. i\nLii-ileå 24, fdll. kand. i Upps. 28.\nPrakti-kanttjig. v. Nord. mus. 25 samt v. sitat.\nhdst. muis. 28, medarb. d\nNorrbotitems-Kur. 29-36, i Östg. Correspondenten\nsed. 36, pol. red. där sed. 43. Led. av\nLuleå stadsfullm. o. dess beredn :nd\n35-36, Linköp. nykterh :nd sed. 44,\nstadsfullm. sed. 47, sekr. 38-46 samt\nv. ordf. sed. 46 i Publ :kl. östra krets\nm. fl. uppdr. Skr.: Idrottsföreningen\n\nDe tre falkarna (39). Reis. t. Franikr.\n30 samt t. g-ranniländ. Hobbies: konst\no. segling.\n\n<b>Nordström</b>, Anders <b>David</b> Emanuel,\nstadsarkitekt, civilingenjör, Ljungby,\nf. 22/8/83 i Gbg. G. m. Virginia\nJohansson. Barn: Majiken f. 12, Inger\n21, Karin 22, Gunnar 24. — CTH 08.\nStadsing. i Skara 20-23, i Kiruna\n23-25, kommuniailibyggm. i Jukkasjärvi\nkommun 23-25, stadsing. i Ljungby\n25, stadsarkit. sed. 40.\n\n",
    "structured": {
        "0": {
            "full_name": "Nordqvist, Lars Gustav",
            "location": "Österbymo",
            "occupation": "provinsiail-läkare",
            "birth_details": {
                "date": "03/12/1894",
                "place": "Norra Ny, Värmland"
            },
            "education": [
                {
                    "degree": "Stud:ex.",
                    "year": "1917"
                },
                {
                    "degree": "med. lic.",
                    "year": "1929",
                    "institution": "Karol. inst."
                }
            ],
            "career": [
                {
                    "position": "iläk. v. Oltfjsjöbadens badanst.",
                    "years": {
                        "start_year": 1927,
                        "end_year": 1928
                    },
                    "organization": "Sailtfsjöbadens badanst."
                },
                {
                    "position": "assist :läk. v. Nyköp. las.",
                    "years": {
                        "start_year": 1929,
                        "end_year": 1930
                    },
                    "organization": "Nyköp. las."
                },
                {
                    "position": "tf. und:iäk. v. Apelvikens kusitsanat.",
                    "years": {
                        "start_year": 1931,
                        "end_year": 1931
                    },
                    "organization": "Apelvikens kusitsanat."
                },
                {
                    "position": "und :’läk. v. vanföreanst. d Härnösand",
                    "years": {
                        "start_year": 1931,
                        "end_year": 1933
                    },
                    "organization": "vanföreanst. d Härnösand"
                },
                {
                    "position": "prov :läk. i Österbymo distr.",
                    "years": {
                        "start_year": 1941
                    },
                    "organization": "Österbymo distr."
                }
            ],
            "family": {
                "spouse": "Tora Magnusson",
                "marriage_year": "1934",
                "children": [
                    {
                        "name": "Ulf",
                        "birth_year": "1936"
                    },
                    {
                        "name": "Jan",
                        "birth_year": "1939"
                    }
                ]
            }
        },
        "1": {
            "full_name": "Nordqvist, Helge Mauritz Isddor",
            "location": "Varberg",
            "occupation": "chefredaktör",
            "birth_details": {
                "date": "04/08/1908",
                "place": "Hälsingtuna, Gävleborgs län"
            },
            "education": [
                {
                    "degree": "Realex.",
                    "year": "1924",
                    "institution": "HuddksvaM"
                },
                {
                    "degree": "Res. It.",
                    "year": "1931",
                    "institution": "Finil."
                }
            ],
            "career": [
                {
                    "position": "chefred, o. ans^v. utg.",
                    "years": {
                        "start_year": 1942
                    },
                    "organization": "Varbengsposten"
                }
            ],
            "family": {
                "spouse": "Karin Lindbliad",
                "marriage_year": "1934"
            }
        },
        "2": {
            "full_name": "Nordqvist, Mattias! (Mats) Emianuel",
            "location": "Göteborg",
            "occupation": "tandiläkare",
            "birth_details": {
                "date": "13/05/1899",
                "place": "Göteborg"
            },
            "education": [
                {
                    "degree": "Stud rex.",
                    "year": "1918",
                    "institution": "Gbgs latin"
                },
                {
                    "degree": "mied. kand.",
                    "year": "1926",
                    "institution": "Upps."
                },
                {
                    "degree": "tandiläk.",
                    "year": "1929"
                }
            ],
            "career": [
                {
                    "position": "Ord. tandläk.",
                    "years": {
                        "start_year": 1929
                    },
                    "organization": "Gbgs kommun tandpOIliMm."
                }
            ],
            "family": {
                "spouse": "Märta Andrén",
                "marriage_year": "1932",
                "children": [
                    {
                        "name": "Ulla Birigitta",
                        "birth_year": "1937"
                    },
                    {
                        "name": "Ingrid Eldsabeth",
                        "birth_year": "1937"
                    },
                    {
                        "name": "Agneta Birgitta",
                        "birth_year": "1942"
                    }
                ]
            }
        },
        "3": {
            "full_name": "Nordström, Mats Börje",
            "location": "Linköping",
            "occupation": "redaktör",
            "birth_details": {
                "date": "03/02/1905",
                "place": "Luleå"
            },
            "education": [
                {
                    "degree": "Stud:ex.",
                    "year": "1924",
                    "institution": "Luleå"
                },
                {
                    "degree": "fdll. kand.",
                    "year": "1928",
                    "institution": "Upps."
                }
            ],
            "career": [
                {
                    "position": "pol. red.",
                    "years": {
                        "start_year": 1943
                    },
                    "organization": "Östg. Correspondenten"
                }
            ],
            "family": {
                "spouse": "Bertha Malmborg",
                "marriage_year": "1934",
                "children": [
                    {
                        "name": "Stig",
                        "birth_year": "1930"
                    },
                    {
                        "name": "Margareta",
                        "birth_year": "1940"
                    }
                ]
            },
            "hobbies": [
                "konst",
                "segling"
            ]
        },
        "4": {
            "full_name": "Nordström, Anders David Emanuel",
            "location": "Ljungby",
            "occupation": "stadsarkitekt, civilingenjör",
            "birth_details": {
                "date": "22/08/1883",
                "place": "Göteborg"
            },
            "education": [
                {
                    "degree": "CTH",
                    "year": "1908"
                }
            ],
            "career": [
                {
                    "position": "stadsarkit.",
                    "years": {
                        "start_year": 1940
                    },
                    "organization": "Ljungby"
                }
            ],
            "family": {
                "spouse": "Virginia Johansson",
                "children": [
                    {
                        "name": "Majiken",
                        "birth_year": "1912"
                    },
                    {
                        "name": "Inger",
                        "birth_year": "1921"
                    },
                    {
                        "name": "Karin",
                        "birth_year": "1922"
                    },
                    {
                        "name": "Gunnar",
                        "birth_year": "1924"
                    }
                ]
            }
        }
    }
}