{
    "original": "Nilson, Tor Yngve; tandläkare,\nHalmstad, f. 19/7/88 i Laholm av\nsparbankskamr. Nils Edvard N. o. Pella\nSvensson. G. 40 m. Karin Eriksson. —\nMog:ex. i Halmstad 07, tandl:kand.\n08, tandläk. 10. Aman. v. tandl:inst.\nprotésavd. 09-10, praktik i Halmstad\nsed. 11. Ordf. i Hall. tandl:fören. 19-20.\n\nNilsson-Björk, Jöns, kyrkoherde,\nGammalstorp, f. 5/10/91 i Övraiby,\nKrist. l., av Nilis Liansson o-, Hanna\nJönsson. G. 19 m. Ida Johansson.\nBarn: Anna-Lisa f. 20, barnav:lär.,\nCarin 21, sjuksköt., Sven 27, ’Stud. —\nStud:ex. i Lund 14, teol. kand. isamit\nprästv. f. Lunds stift 19. Pastiadj. i\nKristianopel 19, vakanskommin. i S : t\nOlof 20, kyrkoh. i Gammalstorp sed.\n25.\n\nNissen, Nils Harald, lektor,\nVänersborg, f. 16/9/10 i St Mm av grossSihandl.\nA. N. N. o. h. 11., f. Persson. G. 45\nm. gymn :dir. Ingrid Bexell, Barn:\nBengt Peter H:son f. 47. —\nStud:-ex. 30, fil. mag. 37, fil. lic. 42 o. fil. dr\n43, ailk i Upps., provår v. noirra iktin i\nSthilm 43, v. Upps. h. a. 1. 44. Extralär.\nv. Lundsibergsi :sk. 37-39, e. adj. v.\nLuleå h. a. 1. 44-45, lektor i eng. o.\nfranska v. Vänersib. h. a. 1. ^sed. 45.\nSekr. i Vänersb. hum. förb. sed. 46.\nSkr.: L’ordre des mots dans la\nChronique de Jean d’Outremeuse\n(grad:avh. 43).\n\nNobel, Per-Axel Gunniar, arkitekt\nSAR, bitr. länsarkitekt, Vänerisiborg, f.\n6/10/07 i V. Frölunda, Gibgs o. Bo&gt;h. k,\nav ing. J. A. N. o. Maria Sjöiberg. G.\n32 m. Eva Nysitröm. Barn: Anita f. 33,\nMiarie-Louiise 37. — Stud:ex. i\nKiarlsitad 27, arkit:ex. v. KTH 31. Anist. v.\nKoop. förb. arkit:kont., Karol. \nsjukh:bygget, byggn:styr. 42-43, \nlänsarkit:assist. i Sthlms 1. o. byggn rkonis. i\nSaltsjöbadens (köpinig 43-46, biiitr. länis-arkiiit.\ni Vänersb. ised. 46.\n\n",
    "structured": {
        "0": {
            "full_name": "Tor Yngve Nilson",
            "location": "Halmstad",
            "occupation": "Tandläkare",
            "birth_details": {
                "date": "19/07/1888",
                "place": "Laholm",
                "parents": "sparbankskamr. Nils Edvard N. o. Pella Svensson"
            },
            "education": [
                {
                    "degree": "Mog:ex.",
                    "year": "1907",
                    "institution": "Halmstad"
                },
                {
                    "degree": "tandl:kand.",
                    "year": "1908",
                    "institution": "NULL"
                },
                {
                    "degree": "tandläk.",
                    "year": "1910",
                    "institution": "NULL"
                }
            ],
            "career": [
                {
                    "position": "Aman. v. tandl:inst. protésavd.",
                    "years": {
                        "start_year": 1909,
                        "end_year": 1910
                    },
                    "organization": "NULL"
                },
                {
                    "position": "Ordf. i Hall. tandl:fören.",
                    "years": {
                        "start_year": 1919,
                        "end_year": 1920
                    },
                    "organization": "NULL"
                }
            ],
            "family": {
                "spouse": "Karin Eriksson",
                "marriage_year": "1940",
                "children": []
            }
        },
        "1": {
            "full_name": "Jöns Nilsson-Björk",
            "location": "Gammalstorp",
            "occupation": "Kyrkoherde",
            "birth_details": {
                "date": "05/10/1891",
                "place": "Övraiby, Krist. l.",
                "parents": "Nilis Liansson o-, Hanna Jönsson"
            },
            "education": [
                {
                    "degree": "Stud:ex.",
                    "year": "1914",
                    "institution": "Lund"
                },
                {
                    "degree": "teol. kand.",
                    "year": "1919",
                    "institution": "NULL"
                }
            ],
            "career": [
                {
                    "position": "Pastiadj. i Kristianopel",
                    "years": {
                        "start_year": 1919,
                        "end_year": 1919
                    },
                    "organization": "NULL"
                },
                {
                    "position": "kyrkoh.",
                    "years": {
                        "start_year": 1925,
                        "end_year": "NULL"
                    },
                    "organization": "Gammalstorp"
                }
            ],
            "family": {
                "spouse": "Ida Johansson",
                "marriage_year": "1919",
                "children": [
                    {
                        "name": "Anna-Lisa",
                        "birth_year": "1920"
                    },
                    {
                        "name": "Carin",
                        "birth_year": "1921"
                    },
                    {
                        "name": "Sven",
                        "birth_year": "1927"
                    }
                ]
            }
        },
        "2": {
            "full_name": "Nils Harald Nissen",
            "location": "Vänersborg",
            "occupation": "Lektor",
            "birth_details": {
                "date": "16/09/1910",
                "place": "St Mm",
                "parents": "grossSihandl. A. N. N. o. h. 11., f. Persson"
            },
            "education": [
                {
                    "degree": "Stud:-ex.",
                    "year": "1930",
                    "institution": "NULL"
                },
                {
                    "degree": "fil. mag.",
                    "year": "1937",
                    "institution": "NULL"
                },
                {
                    "degree": "fil. lic.",
                    "year": "1942",
                    "institution": "Upps."
                },
                {
                    "degree": "fil. dr",
                    "year": "1943",
                    "institution": "NULL"
                }
            ],
            "career": [
                {
                    "position": "provår v. noirra iktin i Sthilm",
                    "years": {
                        "start_year": 1943,
                        "end_year": "NULL"
                    },
                    "organization": "Upps."
                },
                {
                    "position": "lektor i eng. o. franska",
                    "years": {
                        "start_year": 1945,
                        "end_year": "NULL"
                    },
                    "organization": "Vänersib."
                },
                {
                    "position": "Sekr. i Vänersb. hum. förb.",
                    "years": {
                        "start_year": 1946,
                        "end_year": "NULL"
                    },
                    "organization": "NULL"
                }
            ],
            "family": {
                "spouse": "gymn :dir. Ingrid Bexell",
                "marriage_year": "1945",
                "children": [
                    {
                        "name": "Bengt Peter H:son",
                        "birth_year": "1947"
                    }
                ]
            }
        },
        "3": {
            "full_name": "Per-Axel Gunniar Nobel",
            "occupation": "Arkitekt SAR, bitr. länsarkitekt",
            "location": "Vänerisiborg",
            "birth_details": {
                "date": "6/10/1907",
                "place": "V. Frölunda, Gibgs o. Bo&gt;h. k",
                "parents": "ing. J. A. N. o. Maria Sjöiberg"
            },
            "education": [
                {
                    "degree": "Stud:ex.",
                    "year": "1927",
                    "institution": "Kiarlsitad"
                },
                {
                    "degree": "arkit:ex.",
                    "year": "1931",
                    "institution": "KTH"
                }
            ],
            "career": [
                {
                    "position": "Anist. v. Koop. förb. arkit:kont.",
                    "years": {
                        "start_year": 1942,
                        "end_year": 1943
                    },
                    "organization": "Karol. sjukh:bygget"
                },
                {
                    "position": "länsarkit:assist. i Sthlms 1. o. byggn rkonis.",
                    "years": {
                        "start_year": 1943,
                        "end_year": 1946
                    },
                    "organization": "Saltsjöbadens (köpinig"
                }
            ],
            "family": {
                "spouse": "Eva Nysitröm",
                "marriage_year": "1932",
                "children": [
                    {
                        "name": "Anita",
                        "birth_year": "1933"
                    },
                    {
                        "name": "Miarie-Louiise",
                        "birth_year": "1937"
                    }
                ]
            }
        }
    }
}