{
    "original": "HIERSEMANN, HELLMUTH S,\ntandläkare, Uppsala, f i Västerås 30/1/06 av\ning Paul H o Gertrud Beil.\nStud:ex 26, Cand med dent Berlin 30,\ntysk tandläk Leipzig 32, sv tandläk 34,\nass Norberg 33, Tierp 34, eg prakt\nÖrbyhus 36, Upps sed 44; skoltandläk\nTegelsmora 36, Vendel 38. - Led\nkomm:-fullm Tegelsmora 36-40.\nGift 35 m Margit Gustafsson. - Barn:\nLeif f 40.\n\nHIERTNER,  ÅKE  O  P,  landsfiskal,\n\nKristinehamn, f i Filipstad 12/5/06 av\npostmast C O H o Maria Wahlgren.\nLandsfisk:ex 30, e landsfiskal Torsby 34,\nNäs 41, landsfiskal Järnskog 42, Väse\nsed 56. - Utm: RNO, SRKftjM, FrftjM.\nGift 33 m Asta Boström, dtr t\növer-montör H B o Anna Landmark. - Barn:\nMaria f 41.\n\nHIERTONN, TOR E J, professor,\nUppsala, f i Malmö 14/8/13 av disp Knut\nH o Anna Björk.\n\nStud:ex Borås 32, med kand Upps 35,\nmed lic Sthlm 40, med dr 52, doc i\nortopedi Kar ol inst sed 53, tf bitr lär i\nortopedi 53-55, bitr lär i ortopedi sed 55,\nförordn fullgöra den med prof i\nortopedi förenade undervisn :skyldigheten\nKarol inst 55-62, prof i ortopedi Upps\nuniv sed 62; förordn kir klin Seraf:las o\nÖrebro las 41-47, e läk o aman\nNorr-backainst 47-50, 2:e underläk kir tbcavd\no ortop avd S:t Görans sjh 50, l:e\nunderläk Norrbackainst 51-55, tf bitr\növerläk 55-57, bitr överläk 57, överläk orto-\n\nped klin Akad sjh sed 62. - Ortopedi- o\nkir :sakk i försäkr:domst. - Stud :resa t\nkärlkir o ortop klin USA 52, 57, 61,\nEngl 61. - Bat :läk i flk res 40. - Skr i\nallm kir, inv med, ortopedi samt\nexperimentell o klin kärlkir.\nGift 42 m Solbritt Wennberg f 18, dtr t\nbergsing Svante W o Anna Hasselbom.\n- Barn: Ulla f 45, Claes f 47.\n\n",
    "structured": {
        "1": {
            "full_name": "HIERSEMANN, HELLMUTH S",
            "location": "Uppsala",
            "occupation": "tandläkare",
            "birth_details": {
                "date": "30/01/1906",
                "place": "Västerås",
                "parents": "ing Paul H o Gertrud Beil"
            },
            "education": [
                {
                    "degree": "Stud:ex",
                    "year": "1926",
                    "institution": "NULL"
                },
                {
                    "degree": "Cand med dent",
                    "year": "1930",
                    "institution": "Berlin"
                },
                {
                    "degree": "tysk tandläk",
                    "year": "1932",
                    "institution": "Leipzig"
                }
            ],
            "career": [
                {
                    "position": "ass",
                    "years": {
                        "start_year": 1933,
                        "end_year": 1934
                    },
                    "organization": "Norberg"
                },
                {
                    "position": "ass",
                    "years": {
                        "start_year": 1934,
                        "end_year": 1936
                    },
                    "organization": "Tierp"
                },
                {
                    "position": "eg prakt",
                    "years": {
                        "start_year": 1936,
                        "end_year": 1944
                    },
                    "organization": "Örbyhus"
                },
                {
                    "position": "eg prakt",
                    "years": {
                        "start_year": 1944,
                        "end_year": "NULL"
                    },
                    "organization": "Upps"
                },
                {
                    "position": "skoltandläk",
                    "years": {
                        "start_year": 1936,
                        "end_year": 1938
                    },
                    "organization": "Tegelsmora"
                },
                {
                    "position": "skoltandläk",
                    "years": {
                        "start_year": 1938,
                        "end_year": "NULL"
                    },
                    "organization": "Vendel"
                }
            ],
            "family": {
                "spouse": "Margit Gustafsson",
                "marriage_year": "1935",
                "children": [
                    {
                        "name": "Leif",
                        "birth_year": "1940"
                    }
                ]
            }
        },
        "2": {
            "full_name": "HIERTNER, ÅKE O P",
            "location": "Kristinehamn",
            "occupation": "landsfiskal",
            "birth_details": {
                "date": "12/05/1906",
                "place": "Filipstad",
                "parents": "postmast C O H o Maria Wahlgren"
            },
            "education": {
                "degree": "Landsfisk:ex",
                "year": "1930",
                "institution": "NULL"
            },
            "career": [
                {
                    "position": "e landsfiskal",
                    "years": {
                        "start_year": 1934,
                        "end_year": 1941
                    },
                    "organization": "Torsby"
                },
                {
                    "position": "e landsfiskal",
                    "years": {
                        "start_year": 1941,
                        "end_year": 1942
                    },
                    "organization": "Näs"
                },
                {
                    "position": "landsfiskal",
                    "years": {
                        "start_year": 1942,
                        "end_year": 1956
                    },
                    "organization": "Järnskog"
                },
                {
                    "position": "landsfiskal",
                    "years": {
                        "start_year": 1956,
                        "end_year": "NULL"
                    },
                    "organization": "Väse"
                }
            ],
            "family": {
                "spouse": "Asta Boström",
                "marriage_year": "1933",
                "children": [
                    {
                        "name": "Maria",
                        "birth_year": "1941"
                    }
                ]
            }
        },
        "3": {
            "full_name": "HIERTONN, TOR E J",
            "location": "Uppsala",
            "occupation": "professor",
            "birth_details": {
                "date": "14/08/1913",
                "place": "Malmö",
                "parents": "disp Knut H o Anna Björk"
            },
            "education": [
                {
                    "degree": "Stud:ex",
                    "year": "1932",
                    "institution": "Borås"
                },
                {
                    "degree": "med kand",
                    "year": "1935",
                    "institution": "Upps"
                },
                {
                    "degree": "med lic",
                    "year": "1940",
                    "institution": "Sthlm"
                },
                {
                    "degree": "med dr",
                    "year": "1952",
                    "institution": "NULL"
                }
            ],
            "career": [
                {
                    "position": "doc i ortopedi",
                    "years": {
                        "start_year": 1953,
                        "end_year": 1955
                    },
                    "organization": "Kar ol inst"
                },
                {
                    "position": "bitr lär i ortopedi",
                    "years": {
                        "start_year": 1955,
                        "end_year": "NULL"
                    },
                    "organization": "Karol inst"
                },
                {
                    "position": "bitr lär i ortopedi",
                    "years": {
                        "start_year": 1955,
                        "end_year": "NULL"
                    },
                    "organization": "intyg fullgöra den med prof i ortopedi förenade undervisn"
                },
                {
                    "position": "prof i ortopedi",
                    "years": {
                        "start_year": 1962,
                        "end_year": "NULL"
                    },
                    "organization": "Upps univ"
                }
            ],
            "family": {
                "spouse": "Solbritt Wennberg",
                "marriage_year": "1942",
                "children": [
                    {
                        "name": "Ulla",
                        "birth_year": "1945"
                    },
                    {
                        "name": "Claes",
                        "birth_year": "1947"
                    }
                ]
            }
        }
    }
}