{
    "original": "HELLSTRÖM, OLOF B, konstnär,\nUppsala, f i Umeå 8/4/23 av teckn:lär\nThor H o Karin Carlsson.\nKonstfacksk 41-46, Otte Skölds målarsk\n48, O Zadkines skulptursk Paris 49-51.\n-Sep:utst Härnösand, Östersund, Uppsala\n55, 58, Sthlm, Gävle, Norrkpg 59, Sthlm\n60, Gbg 61, Västerås 62, Värml mus 62,\ndelt i saml:utst Unga tecknare Nät :mus\n45, 46, 47, Tessininst, Paris 50, Sv konst\nav i dag, Norge 60 m fi vandr:utst,\nNorrkpgs mus 61, Aspekts utst 61,\ngrupputst Bochum Tyskl 62. - Repr:\nNät :mus, Norrkpgs mus, Gbgs stads\nsaml:ar, Uppl konstfören :s saml,\nVästerås mus. - Bl arb: Islandsbrons\njärnsmide Upps 56, bronsskulptur Daidalos\nUpps 62, järnsmiden f 5 bostadskvarter\nNorrkpg 62-63, Havsgrupp (skulpt)\nGävle, I alla fall (fontänskulpt) Akad sjh.\nGift 56 m konstn:an Elisabet\nHermodsson. - Barn: Ylva f 52 (styvdtr), Lis f 57.\n\nHELLSTRÖM,  PAUL,  agronom,\nAvesta, f i Vendel, Upps l, 28/9/97.\nStud:ex 18, agr:ex 22, förvalt St\nKopparb bergsl ab (Strömsbergs o\nÄlvkarleby lantbr) 29, SKF, Hofors bruk 34,\nAvesta jernv ab lantbr sed 43. - LSLA\n52.\n\nGift 30 m Hilda Pettersson. - Barn:\nBengt f 31, Sture f 34.\n\nHELLSTRÖM,  PER L,  ingenjör,\nFagersta, f i  By, Kopparb  l,  23/8/21   av\nlokf Leonard H o Hilma Johansson.\nIng :ex  Bergssk  Filipstad  49;   anst\nFagersta  bruks  ab  40-47,  ass :lär  bergssk\nFilipstad 49, planer:ing Fagersta bruks\nab 50, planer:ch där sed 59.\nGift 50 m May Larsson f 29, dtr t\nmurare Vollis L o Elin Andersson. - Barn:\nJan f 50, Lena f 55.\n\nHELLSTRÖM, PER-OLOF,\növeringenjör, Degerfors, f i Sthlm 23/7/27 av dir\nNils H o Clara Lovén.\nStud:ex 45, KTH 50, ing Uddeholms ab\nMunkfors bruk 50, Hagfors järnv 57,\növering o ch manufakturv Degerfors\njärnv sed 61. - LIVA, led Jernkont,\nMe-tallografförb samt ol komm inom\nJernkont, Metallnormcentr o\nTryckkärlskom-miss. - Skr: art i tekn fackpress. -\nHobbies: sport, bridge, trädgårdsskötsel,\npolitik.\n\nGift 50 m Inga-Lill Andersson f 27, dtr\nt köpman John A o Elvira Fagerström.\n- Barn: Suzanne f 52, Gunilla f 55.\n\n",
    "structured": {
        "0": {
            "full_name": "Olof B Hellström",
            "location": "Uppsala",
            "occupation": "Konstnär",
            "birth_details": {
                "date": "08/04/1923",
                "place": "Umeå",
                "parents": "Thor H o Karin Carlsson"
            },
            "education": [
                {
                    "degree": "Konstfacksk",
                    "year": "1941-1946",
                    "institution": "Konstfacksk"
                },
                {
                    "degree": "Otte Skölds målarsk",
                    "year": "1948",
                    "institution": "Otte Skölds målarsk"
                },
                {
                    "degree": "O Zadkines skulptursk",
                    "year": "1949-1951",
                    "institution": "O Zadkines skulptursk Paris"
                }
            ],
            "career": [
                {
                    "position": "Sep:utst",
                    "years": {
                        "start_year": 1955,
                        "end_year": 1955
                    },
                    "organization": "Härnösand, Östersund, Uppsala"
                },
                {
                    "position": "delt i saml:utst",
                    "years": {
                        "start_year": 1945,
                        "end_year": 1947
                    },
                    "organization": "Unga tecknare Nät :mus, Tessininst, Paris"
                }
            ],
            "family": {
                "spouse": "Elisabet Hermodsson",
                "marriage_year": "1956",
                "children": [
                    {
                        "name": "Ylva",
                        "birth_year": "1952"
                    },
                    {
                        "name": "Lis",
                        "birth_year": "1957"
                    }
                ]
            }
        },
        "1": {
            "full_name": "Paul Hellström",
            "location": "Avesta",
            "occupation": "Agronom",
            "birth_details": {
                "date": "28/09/1897",
                "place": "Vendel, Upps l"
            },
            "career": [
                {
                    "position": "förvalt",
                    "years": {
                        "start_year": 1929,
                        "end_year": 1929
                    },
                    "organization": "St Kopparb bergsl ab (Strömsbergs o Älvkarleby lantbr)"
                },
                {
                    "position": "Avesta jernv ab lantbr",
                    "years": {
                        "start_year": 1943,
                        "end_year": 1943
                    },
                    "organization": "Avesta jernv ab lantbr"
                }
            ],
            "family": {
                "spouse": "Hilda Pettersson",
                "marriage_year": "1930",
                "children": [
                    {
                        "name": "Bengt",
                        "birth_year": "1931"
                    },
                    {
                        "name": "Sture",
                        "birth_year": "1934"
                    }
                ]
            }
        },
        "2": {
            "full_name": "Per L Hellström",
            "location": "Fagersta",
            "occupation": "Ingenjör",
            "birth_details": {
                "date": "23/08/1921",
                "place": "By, Kopparb l"
            },
            "education": [
                {
                    "degree": "Ing :ex",
                    "year": "1949",
                    "institution": "Bergssk Filipstad"
                }
            ],
            "career": [
                {
                    "position": "anst",
                    "years": {
                        "start_year": 1940,
                        "end_year": 1947
                    },
                    "organization": "Fagersta bruks ab"
                },
                {
                    "position": "planer:ing Fagersta bruks ab",
                    "years": {
                        "start_year": 1950,
                        "end_year": 1959
                    },
                    "organization": "Fagersta bruks ab"
                }
            ],
            "family": {
                "spouse": "May Larsson",
                "marriage_year": "1950",
                "children": [
                    {
                        "name": "Jan",
                        "birth_year": "1950"
                    },
                    {
                        "name": "Lena",
                        "birth_year": "1955"
                    }
                ]
            }
        },
        "3": {
            "full_name": "Per-Olof Hellström",
            "location": "Degerfors",
            "occupation": "Överingenjör",
            "birth_details": {
                "date": "23/07/1927",
                "place": "Sthlm"
            },
            "education": [
                {
                    "degree": "KTH",
                    "year": "1950",
                    "institution": "KTH"
                }
            ],
            "career": [
                {
                    "position": "Ing Uddeholms ab Munkfors bruk",
                    "years": {
                        "start_year": 1950,
                        "end_year": 1957
                    },
                    "organization": "Uddeholms ab Munkfors bruk"
                },
                {
                    "position": "övering o ch manufakturv Degerfors järnv",
                    "years": {
                        "start_year": 1961,
                        "end_year": null
                    },
                    "organization": "Degerfors järnv"
                }
            ],
            "family": {
                "spouse": "Inga-Lill Andersson",
                "marriage_year": "1950",
                "children": [
                    {
                        "name": "Suzanne",
                        "birth_year": "1952"
                    },
                    {
                        "name": "Gunilla",
                        "birth_year": "1955"
                    }
                ]
            },
            "hobbies": [
                "sport",
                "bridge",
                "trädgårdsskötsel",
                "politik"
            ]
        }
    }
}