{
    "original": "HERBRING, BENGT G H,\növerläkare, Karlskoga, f i Mjölby 1/7/26 av\njvtjm Carl Herbert Carlson o Nora\nJohansson.\n\nStud:ex Motala 46, med kand Upps 51,\nmed lic Sthlm 55, underläk anestesiavd\nBorås las 56, Danderyd 57, thoraxkir\nanestesiavd Karol sjh 59, överläk\nanestesiavd Karlskoga las sed 61. - Bat :läk\nflk res.\n\nGift 56 m Kerstin Carlsson f 32, dtr t\nkantor Georg C o Vera Sjudin. - Barn:\nGöran f 57, Clas f 58, Anders o Lars\nff 61.\n\nHERDEVALL, STEFAN, lic phil,\nVästerås, f i Rahova, Rumänien, 12/3/20 av\nnot Martin Juhasz o Anna Steiner.\n\nLic phil Rumänien 47, timlär o adj tekn\ngymn Skellefteå 49, lärov :ad j tekn gymn\nVästerås sed 56. - Styr :suppl Sv\nkemist-samf Västeråskrets. - Hobbies: sport,\nfotografering.\n\nGift 46 m Edith Moskovits, dtr t Rosa\nM. - Barn: Gabriel f 47, Tomas f 48,\nJan f 54, Anders f 56.\nHERDIN, ANDERS W, disponent,\nFalun, f 5/2/11 av fabr Sivert H o Vivan\nJönsson.\n\nGefle borgarsk, stud i USA, Engl o\nTyskl, anst Örgryte kem tvätt &amp; färgeri\nab 34-37, numera disp o deläg Gerna\nkem fabr ab.\n\nHERDIN, OLOF B, direktör, Falun,\nf 29/1/14 av fabr Sivert H o Vivan\nJönsson.\n\nStud:ex 34, stud City of London Coll\n37-38, verkst dir A W Herdins färgverk\nab Falun.\n\nGift 39 m Greta Ericson.\nHERGIN, ARNE A S, stadskamrerare,\nEskilstuna,   f   i   Döderhult,   Kalmar   l,\n5/9/06   av  Alfred  Håkanson   o   Selma\nHåkanson.\n\nDSI 35, kommunalkassör Huddinge 36,\nkommunalkamr Danderyd 40, stadskamr\nSträngnäs 44, Eskilstuna sed 50.\nGift 36 m Ingrid Axelson. - Barn: Görel\nf 45.\n\n",
    "structured": {
        "1": {
            "full_name": "Bengt G H Herbring",
            "location": "Karlskoga",
            "occupation": "överläkare",
            "birth_details": {
                "date": "01/07/1926",
                "place": "Mjölby"
            },
            "education": [
                {
                    "degree": "Stud:ex",
                    "year": "1946",
                    "institution": "Motala"
                },
                {
                    "degree": "med kand",
                    "year": "1951",
                    "institution": "Upps"
                },
                {
                    "degree": "med lic",
                    "year": "1955",
                    "institution": "Sthlm"
                }
            ],
            "career": [
                {
                    "position": "underläk anestesiavd",
                    "years": {
                        "start_year": 1956,
                        "end_year": 1957
                    },
                    "organization": "Borås las"
                },
                {
                    "position": "thoraxkir anestesiavd",
                    "years": {
                        "start_year": 1957,
                        "end_year": 1959
                    },
                    "organization": "Danderyd"
                },
                {
                    "position": "överläk anestesiavd",
                    "years": {
                        "start_year": 1959,
                        "end_year": 1961
                    },
                    "organization": "Karol sjh"
                }
            ],
            "family": {
                "spouse": "Kerstin Carlsson",
                "marriage_year": "1956",
                "children": [
                    {
                        "name": "Göran",
                        "birth_year": "1957"
                    },
                    {
                        "name": "Clas",
                        "birth_year": "1958"
                    },
                    {
                        "name": "Anders",
                        "birth_year": "1961"
                    },
                    {
                        "name": "Lars",
                        "birth_year": "1961"
                    }
                ]
            }
        },
        "2": {
            "full_name": "Stefan Herdevall",
            "location": "Västerås",
            "occupation": "lic phil",
            "birth_details": {
                "date": "12/03/1920",
                "place": "Rahova, Rumänien"
            },
            "education": {
                "degree": "Lic phil",
                "year": "1947",
                "institution": "Rumänien"
            },
            "career": [
                {
                    "position": "timlär o adj",
                    "years": {
                        "start_year": 1949,
                        "end_year": 1956
                    },
                    "organization": "tekn gymn Skellefteå"
                },
                {
                    "position": "lärov :ad j",
                    "years": {
                        "start_year": 1956
                    },
                    "organization": "tekn gymn Västerås"
                }
            ],
            "family": {
                "spouse": "Edith Moskovits",
                "marriage_year": "1946",
                "children": [
                    {
                        "name": "Gabriel",
                        "birth_year": "1947"
                    },
                    {
                        "name": "Tomas",
                        "birth_year": "1948"
                    },
                    {
                        "name": "Jan",
                        "birth_year": "1954"
                    },
                    {
                        "name": "Anders",
                        "birth_year": "1956"
                    }
                ]
            },
            "hobbies": [
                "sport",
                "fotografering"
            ]
        },
        "3": {
            "full_name": "Anders W Herdin",
            "location": "Falun",
            "occupation": "disponent",
            "birth_details": {
                "date": "05/02/1911",
                "place": "Falun"
            },
            "education": "Gefle borgarsk, stud i USA, Engl o Tyskl",
            "career": {
                "position": "anst Örgryte kem tvätt & färgeri ab",
                "years": {
                    "start_year": 1934,
                    "end_year": 1937
                },
                "organization": "numera disp o deläg Gerna kem fabr ab"
            }
        },
        "4": {
            "full_name": "Olof B Herdin",
            "location": "Falun",
            "occupation": "direktör",
            "birth_details": {
                "date": "29/01/1914",
                "place": "Falun"
            },
            "education": [
                {
                    "degree": "Stud:ex",
                    "year": "1934"
                },
                {
                    "degree": "stud City of London Coll",
                    "years": "1937-1938"
                }
            ],
            "career": {
                "position": "verkst dir",
                "organization": "A W Herdins färgverk ab Falun"
            },
            "family": {
                "spouse": "Greta Ericson",
                "marriage_year": "1939"
            }
        },
        "5": {
            "full_name": "Arne A S Hergin",
            "location": "Eskilstuna",
            "occupation": "stadskamrerare",
            "birth_details": {
                "date": "05/09/1906",
                "place": "Döderhult, Kalmar l"
            },
            "education": "DSI 35, kommunalkassör Huddinge 36",
            "career": [
                {
                    "position": "kommunalkamr",
                    "years": {
                        "start_year": 1940,
                        "end_year": 1944
                    },
                    "organization": "Danderyd"
                },
                {
                    "position": "stadskamr",
                    "years": {
                        "start_year": 1950
                    },
                    "organization": "Eskilstuna"
                }
            ],
            "family": {
                "spouse": "Ingrid Axelson",
                "marriage_year": "1936",
                "children": [
                    {
                        "name": "Görel",
                        "birth_year": "1945"
                    }
                ]
            }
        }
    }
}