{
    "original": "HORNWALL, GERT H D,\nstadsbibliotekarie i Sthlm, Uppsala, f i\nKarlskrona 10/9/11 av folkskollär Eggert H\no Gunhild Rydell.\n\nStud:ex Sthlm 30, fil mag Upps 40, fil\nlic 45, fil dr o doc i statskunskap Upps\n51, doc Gbg 51-52, Upps sed 52, aman\nUpps univ :bibl 46, bibl 52 (eo 48),\nstadsbibl Sthlm sed 56. - Sekr KB :s o\nuniv:-bibl tjm:fören 52-55, styr:led Sv:es allm\nbibl :f ören sed 57, led Sv Unescorådet\no dess AU sed 59. - Skr: Regeringskris\no riksdagspolitik 1840-1841 (drsavh 51),\ntidskr :upps i statsvetensk o bibl :vetensk\nämnen, red Upps univ :bibl kat 42-47.\n-Utm: RNO.\n\nGift 38 m fil lic Margareta Nilsson f\n11, dtr t överlantmät Olof N o Dagmar\nRodhe. - Barn: Gunnel f 46, Inger f 49.\n\nHORNWALL,  MARGARETA  A  A,\n\nfil lic, bibliotekarie, Uppsala, f i Lidkpg\n\n15/12/11 av överlantmät Olof Nilsson o\n\nDagmar Rodhe.\n\nStud:ex Halmstad 31, fil kand o fil mag\n\nUpps 35, fil lic Gbg 55, bibl:sk 36, eo\n\nkontorsbitr Upps univ :bibl 36, ord 47,\n\neo kanslibitr 47, eo bibl:ass 48, eo l:e\n\nbibl:ass 53, aman 55, bibl:ie Upps univ:-\n\nbibl sed 62.\n\nGift 38 m stadsbibl Gert Hornwall fil.\n\n- Barn: Gunnel f 46, Inger f 49.\n\nHOVGÅRD, NILS-ÅKE,\nbergsingenjör, Hagfors, f i Bollerup, Kristianst l,\n28/1/30 av landsh Åke H o Hedvig\nOlsson.\n\nStud:ex Ystad 49, KTH 54, forskn:ing\nJernkont 54, UHB Hagfors järnv 58,\ndriftsch hytta o legeringsv där 60, stålv\nsed 62. - Medl Round Table. - Skr: upps\ni JKA. - Hobbies: tennis, friluftsliv,\nfjällvandringar.\n\nGift 54 m Lilian Wargren, dtr t sjökapt\nHelmer W o Thea Sjölin.\n\n",
    "structured": {
        "0": {
            "full_name": "Gert H D Hornwall",
            "location": "Karlskrona",
            "occupation": "stadsbibliotekarie",
            "birth_details": {
                "date": "10/09/1911",
                "place": "Karlskrona",
                "parents": "folkskollär Eggert H o Gunhild Rydell"
            },
            "education": [
                {
                    "degree": "Stud:ex",
                    "year": "1930",
                    "institution": "Sthlm"
                },
                {
                    "degree": "fil mag",
                    "year": "1940",
                    "institution": "Upps"
                },
                {
                    "degree": "fil lic",
                    "year": "1945",
                    "institution": "Upps"
                },
                {
                    "degree": "fil dr o doc i statskunskap",
                    "year": "1951",
                    "institution": "Upps"
                }
            ],
            "career": [
                {
                    "position": "doc",
                    "years": {
                        "start_year": 1951,
                        "end_year": 1952
                    },
                    "organization": "Gbg"
                },
                {
                    "position": "Upps sed",
                    "years": {
                        "start_year": 1952,
                        "end_year": null
                    },
                    "organization": "Upps"
                },
                {
                    "position": "aman",
                    "years": {
                        "start_year": null,
                        "end_year": null
                    },
                    "organization": "Upps univ :bibl"
                },
                {
                    "position": "bibl",
                    "years": {
                        "start_year": 1956,
                        "end_year": null
                    },
                    "organization": "stadsbibl Sthlm"
                }
            ],
            "family": {
                "spouse": "fil lic Margareta Nilsson",
                "marriage_year": "1938",
                "children": [
                    {
                        "name": "Gunnel",
                        "birth_year": "1946"
                    },
                    {
                        "name": "Inger",
                        "birth_year": "1949"
                    }
                ]
            },
            "publications": [
                {
                    "title": "Regeringskris o riksdagspolitik 1840-1841",
                    "year": "NULL",
                    "type": "drsavh"
                }
            ],
            "community_involvement": [
                {
                    "role": "Sekr",
                    "organization": "KB :s o univ:-bibl tjm:fören",
                    "years": "1952-1955"
                },
                {
                    "role": "styr:led",
                    "organization": "Sv:es allm bibl :f",
                    "years": "1957"
                },
                {
                    "role": "led",
                    "organization": "Sv Unescorådet o dess AU",
                    "years": "1959"
                }
            ],
            "honorary_titles": [
                {
                    "title": "RNO",
                    "institution": "NULL",
                    "year": "NULL"
                }
            ]
        },
        "1": {
            "full_name": "Margareta A A Hornwall",
            "location": "Lidköping",
            "occupation": "bibliotekarie",
            "birth_details": {
                "date": "15/12/1911",
                "place": "Lidköping",
                "parents": "överlantmät Olof Nilsson o Dagmar Rodhe"
            },
            "education": [
                {
                    "degree": "Stud:ex",
                    "year": "1931",
                    "institution": "Halmstad"
                },
                {
                    "degree": "fil kand o fil mag",
                    "year": "1935",
                    "institution": "Upps"
                },
                {
                    "degree": "fil lic",
                    "year": "1955",
                    "institution": "Gbg"
                },
                {
                    "degree": "bibl:sk",
                    "year": "1936",
                    "institution": "NULL"
                }
            ],
            "career": [
                {
                    "position": "eo kontorsbitr",
                    "years": {
                        "start_year": 1936,
                        "end_year": null
                    },
                    "organization": "Upps univ :bibl"
                },
                {
                    "position": "ord",
                    "years": {
                        "start_year": 1947,
                        "end_year": null
                    },
                    "organization": "NULL"
                },
                {
                    "position": "eo kanslibitr",
                    "years": {
                        "start_year": 1947,
                        "end_year": null
                    },
                    "organization": "NULL"
                }
            ],
            "family": {
                "spouse": "stadsbibl Gert Hornwall fil",
                "marriage_year": "1938",
                "children": [
                    {
                        "name": "Gunnel",
                        "birth_year": "1946"
                    },
                    {
                        "name": "Inger",
                        "birth_year": "1949"
                    }
                ]
            }
        },
        "2": {
            "full_name": "Nils-Åke Hovgård",
            "location": "Bollerup, Kristianst l",
            "occupation": "bergsingenjör",
            "birth_details": {
                "date": "28/01/1930",
                "place": "Bollerup, Kristianst l",
                "parents": "landsh Åke H o Hedvig Olsson"
            },
            "education": [
                {
                    "degree": "Stud:ex",
                    "year": "1949",
                    "institution": "Ystad"
                },
                {
                    "degree": "NULL",
                    "year": "NULL",
                    "institution": "NULL"
                }
            ],
            "career": [
                {
                    "position": "forskn:ing",
                    "years": {
                        "start_year": 1954,
                        "end_year": null
                    },
                    "organization": "Jernkont"
                },
                {
                    "position": "UHB",
                    "years": {
                        "start_year": 1958,
                        "end_year": null
                    },
                    "organization": "Hagfors järnv"
                },
                {
                    "position": "driftsch hytta",
                    "years": {
                        "start_year": 1960,
                        "end_year": null
                    },
                    "organization": "NULL"
                },
                {
                    "position": "stålv",
                    "years": {
                        "start_year": 1962,
                        "end_year": null
                    },
                    "organization": "NULL"
                }
            ],
            "family": {
                "spouse": "Lilian Wargren",
                "marriage_year": "1954",
                "children": []
            },
            "hobbies": [
                "tennis",
                "friluftsliv",
                "fjällvandringar"
            ]
        }
    }
}