{
    "original": "HAMMARSTRÖM, U GÖRAN E,\ndocent, Uppsala, f i Landskrona 9/4/22 av\nrekt Emil H o Victoria Ehlers.\nStud:ex Gävle 40, fil mag Upps 43, fil\nlic 49, fil dr o doc i romanska språk\nUpps univ 53, doc i fonetik där 55,\nexaminator o ämnesrepr sed 56. -\nStyr:-led Ekon språkvetensk sällsk Upps.\n-Skr: Étude de phonétique auditive sur les\npariers de PAlgarve (53), Fransk fonetik\n(60), m fi arb inom fonetik o romanska\nspråk, art i DN o UNT.\nGift 51 m Louise Hagberg f 29, dtr t\n\nred Karl Aug H o Vera Törnell. - Barn:\nMikael f 61.\n\nHAMMARSTRÖM, SVEN G,\növerläkare, Nyköping, f i Jönkpg 15/4/09 av\npast Georg H o Lillie Palmquist.\nMed lic Sthlm 38, med dr 47, underläk\nol sjh 38-42, l :e underläk med avd Umeå\nlas 42, Ersta sjh 43, S:t Eriks sjh 44-48,\növerläk med avd Sundsvalls las 52-57\n(tf 49), med klin Nykpgs las sed 57, doc\ni invärtes medicin Karol inst sed 59,\nflygläk l:a gr i res 50. - Ordf Nykpgs\nläk:kl 59-62. - Skr: i fysiologi o med,\nspec rör blodtryckssjukd. - Hobby: golf.\nGift 34 m Karin Lamm, DSI, f 10, dtr\nt prof Martin L o Greta Wavrinsky.\n-Barn: Bo f 40, Olof f 41, Stina f 45,\nLena f 52.\n\nHAMMER-BRÅBERG, RUTH S,\nadvokat, Säffle, f i V Skrävlinge, Malmöh\nl, 16/1/13 av fabr Axel H o\nFlorence-Louise Mattson.\n\nStud:ex Malmö 33, jur kand Lund 38,\ntingstjg Södersysslets doms 39-41, eg\nadv:verksamh Säffle sed 41, LSA 48.\n-Ordf tax:nd 50-56, 58-59, 62-63.\nGift 41 m adv Gösta Bråberg f 06.\n-Barn: Lennart f 42, Margareta f 46.\n\nHAMNE, P BERTIL, överläkare,\nFalun, f i Ljusdal, Gävleb l, 27/3/02 av\nprov:läk Walfrid H o Elna\nWaldenström.\n\n:Stud:ex Hudiksvall 22, med kand Upps\n26, med lic 33, med dr Sthlm 42, doc\ni pediatrik Karol inst 42, ass :läk\nlung-klin Akad sjh Upps 33; pediatr klin 34,\nmed avd där 34, vik underläk med avd\nLidkpgs las 35, underläk med avd Falu\nlas 35, aman pediatr klin Norrtulls sjh\nSthlm 36, l:e underläk Sachsska barnsjh\n40, Epid:sjh Sthlm 42, lär ärver ksamh v\nstat, RK :s o S:t Eriks sköterskesk,\növerläk barnklin Falu las sed 43. - Kompet\n:-förkl t prof :ur Upps 44. - Verkst\nstyr:-led sjuksköt:sk Falun sed 45, ordf Stift\nf utveckl :störda barn Dalahem 59. - Skr\nvetensk arb inom fysiologi, med o särsk\npediatrik, bl a Studien über die Biologie\ndes C-vitamins mit besonderer\nBerück-sichtigung des Kohlehydratstoffwechsels\n(drsavh 41).- Utm: RNO.\nGift 41 m Karin Nilsson f 11, dtr t dir\nAxel N o Gunhild Nyberg. - Barn:\nGunnel f 42, Curt f 43, Per f 47.\n\n",
    "structured": {
        "0": {
            "full_name": "HAMMARSTRÖM, U GÖRAN E",
            "location": "Uppsala",
            "occupation": "docent",
            "birth_details": {
                "date": "09/04/1922",
                "place": "Landskrona"
            },
            "education": [
                {
                    "degree": "Stud:ex",
                    "year": "1940",
                    "institution": "Gävle"
                },
                {
                    "degree": "fil mag",
                    "year": "1943",
                    "institution": "Upps"
                },
                {
                    "degree": "fil lic",
                    "year": "1949",
                    "institution": "NULL"
                },
                {
                    "degree": "fil dr",
                    "year": "1953",
                    "institution": "Upps univ"
                }
            ],
            "career": [
                {
                    "position": "examinator",
                    "years": {
                        "start_year": 1956,
                        "end_year": 1956
                    },
                    "organization": "NULL"
                }
            ],
            "family": {
                "spouse": "Louise Hagberg",
                "marriage_year": "1951",
                "children": [
                    {
                        "name": "Mikael",
                        "birth_year": "1961"
                    }
                ]
            }
        },
        "1": {
            "full_name": "HAMMARSTRÖM, SVEN G",
            "location": "Nyköping",
            "occupation": "överläkare",
            "birth_details": {
                "date": "15/04/1909",
                "place": "Jönkpg"
            },
            "education": [],
            "career": [
                {
                    "position": "överläk med avd",
                    "years": {
                        "start_year": 1952,
                        "end_year": 1957
                    },
                    "organization": "Sundsvalls las"
                }
            ],
            "family": {
                "spouse": "Karin Lamm",
                "marriage_year": "1934",
                "children": [
                    {
                        "name": "Bo",
                        "birth_year": "1940"
                    },
                    {
                        "name": "Olof",
                        "birth_year": "1941"
                    },
                    {
                        "name": "Stina",
                        "birth_year": "1945"
                    },
                    {
                        "name": "Lena",
                        "birth_year": "1952"
                    }
                ]
            },
            "hobbies": [
                "golf"
            ]
        },
        "2": {
            "full_name": "HAMMER-BRÅBERG, RUTH S",
            "location": "Säffle",
            "occupation": "advokat",
            "birth_details": {
                "date": "16/01/1913",
                "place": "V Skrävlinge, Malmöh l"
            },
            "education": [
                {
                    "degree": "Stud:ex",
                    "year": "1933",
                    "institution": "Malmö"
                },
                {
                    "degree": "jur kand",
                    "year": "1938",
                    "institution": "Lund"
                }
            ],
            "career": [],
            "family": {
                "spouse": "Gösta Bråberg",
                "marriage_year": "1941",
                "children": [
                    {
                        "name": "Lennart",
                        "birth_year": "1942"
                    },
                    {
                        "name": "Margareta",
                        "birth_year": "1946"
                    }
                ]
            }
        },
        "3": {
            "full_name": "HAMNE, P BERTIL",
            "location": "Falun",
            "occupation": "överläkare",
            "birth_details": {
                "date": "27/03/1902",
                "place": "Ljusdal, Gävleb l"
            },
            "education": [
                {
                    "degree": "Stud:ex",
                    "year": "1922",
                    "institution": "Hudiksvall"
                },
                {
                    "degree": "med kand",
                    "year": "1926",
                    "institution": "Upps"
                },
                {
                    "degree": "med lic",
                    "year": "1933",
                    "institution": "NULL"
                },
                {
                    "degree": "med dr",
                    "year": "1942",
                    "institution": "Sthlm"
                }
            ],
            "career": [
                {
                    "position": "överläk barnklin Falu las",
                    "years": {
                        "start_year": 1943,
                        "end_year": 1943
                    },
                    "organization": "NULL"
                }
            ],
            "family": {
                "spouse": "Karin Nilsson",
                "marriage_year": "1941",
                "children": [
                    {
                        "name": "Gunnel",
                        "birth_year": "1942"
                    },
                    {
                        "name": "Curt",
                        "birth_year": "1943"
                    },
                    {
                        "name": "Per",
                        "birth_year": "1947"
                    }
                ]
            }
        }
    }
}