{
    "original": "HILD, TORSTEN N, direktör, Örebro,\nf i Sthlm 3/10/13 av ing Paul H o\nSigrid Wahlgren.\n\nRealsk, gymn m m 23-32, prakt Walter\nThompson Co Sthlm o Köpenh 32,\nlayoutman Å&amp;Å 35, red Annons-Krantz\n\n37,   konsulent   SvD  38,   Gumaelius   40,\nWilh Beckman Propaganda 41, sekt :ch\nWilh Anderssons annonsbyrå Sthlm 49,\ndir där 52, ch dess filial Örebro sed 55,\neg konsult verksamh 43-49. - Fänr SVK\n\n38,  löjtn 42, kapt 51, skolch SVK:s\nasp:-sk 41-55, utb:ch Örebro sed 58, red\ntidskr    Sjövärns-Nytt    55-62.    -    Styr:led\nSthlms   reklamfören   juniorsekt   38-42,\nSFRF 58-60, Örebro försäljn:- o\nreklamfören   56-60,   ordf   där   58-60,   led   Sv\nreklamförb   undervisn:-   o   publ:komm\n42-44, sekr Sv livräddn:sällsk länskomm\nsed 59. - Medl Rotary, Örebro res :off\n:-sällsk, SXK m fi. - Skr: Reklamlärd på\nfritid (42), upps i reklamämnen. - Utm:\nSVKGM, SVF2GM. - Hobby: båtsport.\nGift 39 m Ingrid Magnusson f 17, dtr t\nbergsing Arvid M o Edit Granlund.\n-Barn: Sylvia f 39, Susanna f 41, Karin\nf 44.\n\nHILDEBRAND,  KARL-GUSTAF  H,\n\nprofessor, Uppsala, f i Sthlm 25/4/11 av\nfil dr Karl H o Elisabeth af Geijerstam.\nStud:ex 29, fil kand Upps 32, fil lic\n37, fil dr o doc i historia 46, prof\n:förordn 46-48, preceptor i ekonomisk\nhistoria 51 (tf 48-49), prof sed 59, gästprof\nUniv of Wisconsin o Indiana Univ,\nUSA 61-62. - Medarb Nu 34-36, red Vår\nLösen 38-40. - LSkS 52, LHVS 59,\nLVSU 60. - Skr: Nödvärn (33), Kristna\nperspektiv (35), Vårdagjämning (37),\nBibeln i nutida svensk lyrik (39), Medan\nnatten varar (40), Falu stads historia\n1641—1687 (drsavh 46), Djupt under\nishöljet (50), Dikter i urval (53),\nFager-stabrukens historia I: 16- o 1700-talen\n(57), Sågverksförbundet 1907—1957 (red\no medarb 62); upps o rec i bl a Hist\ntidskr, Karol förb årsbok o Scand Econ\nHist Review. - Utm: Schücks pris 46, %\nGeijerska priset 47, HA :s Beskowska\nstip 48, Heidenstamspriset 48.\nGift 36 m med lic Majstina Rydh f 10,\n\ndtr t dir Carl R o Stina Hafström.\n-Barn: Katarina f 38, Hans f 41.\n\n",
    "structured": {
        "0": {
            "full_name": "Torsten N Hild",
            "location": "Örebro",
            "occupation": "direktör",
            "birth_details": {
                "date": "03/10/1913",
                "place": "Stockholm",
                "parents": "ing Paul H o Sigrid Wahlgren"
            },
            "education": [
                {
                    "degree": "realsk",
                    "year": "1923-1932",
                    "institution": null
                },
                {
                    "degree": "gymn",
                    "year": "1923-1932",
                    "institution": null
                }
            ],
            "career": [
                {
                    "position": "prakt Walter Thompson Co Sthlm o Köpenh",
                    "years": {
                        "start_year": 1932,
                        "end_year": 1932
                    },
                    "organization": null
                },
                {
                    "position": "layoutman Å&Å",
                    "years": {
                        "start_year": null,
                        "end_year": 1935
                    },
                    "organization": null
                },
                {
                    "position": "red Annons-Krantz",
                    "years": {
                        "start_year": null,
                        "end_year": 1937
                    },
                    "organization": null
                },
                {
                    "position": "konsulent SvD",
                    "years": {
                        "start_year": null,
                        "end_year": 1938
                    },
                    "organization": null
                },
                {
                    "position": "Gumaelius",
                    "years": {
                        "start_year": null,
                        "end_year": 1940
                    },
                    "organization": null
                },
                {
                    "position": "Wilh Beckman Propaganda",
                    "years": {
                        "start_year": null,
                        "end_year": 1941
                    },
                    "organization": null
                },
                {
                    "position": "sekt :ch Wilh Anderssons annonsbyrå Sthlm",
                    "years": {
                        "start_year": null,
                        "end_year": 1949
                    },
                    "organization": null
                },
                {
                    "position": "dir där",
                    "years": {
                        "start_year": 1952,
                        "end_year": 1952
                    },
                    "organization": null
                },
                {
                    "position": "ch dess filial Örebro",
                    "years": {
                        "start_year": 1955,
                        "end_year": 1955
                    },
                    "organization": null
                },
                {
                    "position": "eg konsult verksamh",
                    "years": {
                        "start_year": 1943,
                        "end_year": 1949
                    },
                    "organization": null
                }
            ],
            "family": {
                "spouse": "Ingrid Magnusson",
                "marriage_year": "1939",
                "children": [
                    {
                        "name": "Sylvia",
                        "birth_year": "1939"
                    },
                    {
                        "name": "Susanna",
                        "birth_year": "1941"
                    },
                    {
                        "name": "Karin",
                        "birth_year": "1944"
                    }
                ]
            }
        },
        "1": {
            "full_name": "Karl-Gustaf Hildebrand",
            "location": "Uppsala",
            "occupation": "professor",
            "birth_details": {
                "date": "25/04/1911",
                "place": "Stockholm",
                "parents": "fil dr Karl H o Elisabeth af Geijerstam"
            },
            "education": [
                {
                    "degree": "Stud:ex",
                    "year": "1929",
                    "institution": null
                },
                {
                    "degree": "fil kand",
                    "year": "1932",
                    "institution": "Upps"
                },
                {
                    "degree": "fil lic",
                    "year": "1937",
                    "institution": null
                },
                {
                    "degree": "fil dr",
                    "year": "1946",
                    "institution": null
                }
            ],
            "career": [
                {
                    "position": "prof :förordn",
                    "years": {
                        "start_year": 1946,
                        "end_year": 1948
                    },
                    "organization": null
                },
                {
                    "position": "preceptor i ekonomisk historia",
                    "years": {
                        "start_year": 1951,
                        "end_year": null
                    },
                    "organization": null
                },
                {
                    "position": "prof",
                    "years": {
                        "start_year": 1959,
                        "end_year": null
                    },
                    "organization": null
                },
                {
                    "position": "gästprof Univ of Wisconsin o Indiana Univ, USA",
                    "years": {
                        "start_year": 1961,
                        "end_year": 1962
                    },
                    "organization": null
                }
            ],
            "family": {
                "spouse": "med lic Majstina Rydh",
                "marriage_year": "1936",
                "children": [
                    {
                        "name": "Katarina",
                        "birth_year": "1938"
                    },
                    {
                        "name": "Hans",
                        "birth_year": "1941"
                    }
                ]
            },
            "publications": [
                {
                    "title": "Nödvärn",
                    "year": "1933",
                    "type": null
                },
                {
                    "title": "Kristna perspektiv",
                    "year": "1935",
                    "type": null
                },
                {
                    "title": "Vårdagjämning",
                    "year": "1937",
                    "type": null
                },
                {
                    "title": "Bibeln i nutida svensk lyrik",
                    "year": "1939",
                    "type": null
                },
                {
                    "title": "Medan natten varar",
                    "year": "1940",
                    "type": null
                },
                {
                    "title": "Falu stads historia 1641—1687",
                    "year": "1946",
                    "type": "drsavh"
                },
                {
                    "title": "Djupt under ishöljet",
                    "year": "1950",
                    "type": null
                },
                {
                    "title": "Dikter i urval",
                    "year": "1953",
                    "type": null
                },
                {
                    "title": "Fager-stabrukens historia I: 16- o 1700-talen",
                    "year": "1957",
                    "type": null
                },
                {
                    "title": "Sågverksförbundet 1907—1957",
                    "year": "1962",
                    "type": "red o medarb"
                }
            ],
            "community_involvement": [
                {
                    "role": "red",
                    "organization": "Sjövärns-Nytt",
                    "years": "1955-1962"
                }
            ]
        }
    }
}