{
    "original": "HELSING, C WERNER,\ndriftsingenjör, Hallstahammar, f i Folkarna,\nKopparb l, 12/8/11 av ing Carl H o Emma\nBerglund.\n\nStud:ex Skara 30, stud StHS 31, ing:ex\nFilipstads bergssk 34, ing Fagersta bruks\nab 34, Domnarfvets jernv 44, driftsing\naxelfabr Hallstahammars ab 48, nu\ndriftsch där. - Medl Jernkont\nforskn:-komm sed 52, MNC:s tekn komm sed\n54. - SIF-stip 52.\n\nGift 42 m Margareta Wegener f 19, dtr\nt kommin Alex W o Olga Lovén.\n-Barn: Gunilla f 44, Birgitta f 46, Bodil\nf 51.\n\nHEMMINGER, ANDERS T,\nkommunalborgmästare, Norrtälje, f i Stora\nSlågarp, Malmöh l, 31/7/13 av kantor\nTage H o Edit Linneros.\nStud:ex Eslöv 31, jur kand Lund 38,\ntingstjg Ölands doms 39-42,\nkomm:-borgm Borgholm 43, Norrtälje sed 48. -\n\nStyr :ordf Flygverkstäderna i Norrtälje\nFNA ab sed 60, Sv hdlsbkns\nlokalstyr sed 62, styr :led Norrtelje gjuteri ab\nsed 59, ordf byggn :ndn sed 48, sekr\nStadsfullm, DK o dess AU, lönendn m\nfi, kronoomb Norrtälje tax :ndr. - Medl\nFrimO, Odd Fellow, Lions club, SHT.\n-Res:off I 6 41-52. - Hobbies: tennis,\nfriluftsliv.\n\nGift 1) 40-43 m Gudrun Andersson, 2)\n48 m Inga-Britt Johansson f 27, dtr t\nköpm John J o Signe Andersson.\n-Barn: i l:a akt Peter f 40, i 2:a akt Jan\nf 49, Cecilia f 51.\n\nHEMMINGSON, GUSTAF Y,\ndirektör, Karlstad, f i Karlstad 19/3/91.\nVerkst dir O F Ahlmark &amp; Co Eftr ab.\n\n-   Stiyr:ordf  Värml  rederi   ab,   styr:led\nKarlstads stuv:ab, fd ordf riksbkns\navd:-kont   lokalstyr,   Sjömanshusdirektionen\nKarlstad. - Utm: RVO.\n\n",
    "structured": {
        "1": {
            "full_name": "C Werner Helsing",
            "location": "Hallstahammar",
            "occupation": "driftsingenjör",
            "birth_details": {
                "date": "12/08/1911",
                "place": "Folkarna, Kopparbergs län",
                "parents": "ing Carl H o Emma Berglund"
            },
            "education": [
                {
                    "degree": "Stud:ex",
                    "year": "1930",
                    "institution": "Skara"
                },
                {
                    "degree": "ing:ex",
                    "year": "1931",
                    "institution": "StHS"
                },
                {
                    "degree": "ing:ex",
                    "year": "1934",
                    "institution": "Filipstads bergssk"
                }
            ],
            "career": [
                {
                    "position": "ing Fagersta bruks ab",
                    "years": {
                        "start_year": 1934,
                        "end_year": 1934
                    },
                    "organization": "Fagersta bruks"
                },
                {
                    "position": "Domnarfvets jernv",
                    "years": {
                        "start_year": 1944,
                        "end_year": 1944
                    },
                    "organization": "Domnarfvets jernv"
                },
                {
                    "position": "driftsing axelfabr Hallstahammars ab",
                    "years": {
                        "start_year": 1948
                    },
                    "organization": "Hallstahammars ab"
                }
            ],
            "family": {
                "spouse": "Margareta Wegener",
                "marriage_year": "1942",
                "children": [
                    {
                        "name": "Gunilla",
                        "birth_year": "1944"
                    },
                    {
                        "name": "Birgitta",
                        "birth_year": "1946"
                    },
                    {
                        "name": "Bodil",
                        "birth_year": "1951"
                    }
                ]
            }
        },
        "2": {
            "full_name": "Anders T Hemminger",
            "location": "Norrtälje",
            "occupation": "kommunalborgmästare",
            "birth_details": {
                "date": "31/07/1913",
                "place": "Stora Slågarp, Malmöhus län",
                "parents": "kantor Tage H o Edit Linneros"
            },
            "education": [
                {
                    "degree": "Stud:ex",
                    "year": "1931",
                    "institution": "Eslöv"
                },
                {
                    "degree": "jur kand",
                    "year": "1938",
                    "institution": "Lund"
                }
            ],
            "career": [
                {
                    "position": "tingstjg Ölands doms",
                    "years": {
                        "start_year": 1939,
                        "end_year": 1942
                    }
                },
                {
                    "position": "komm:-borgm Borgholm",
                    "years": {
                        "start_year": 1943
                    }
                },
                {
                    "position": "Norrtälje",
                    "years": {
                        "start_year": 1948
                    }
                }
            ],
            "family": {
                "spouse": "Inga-Britt Johansson",
                "marriage_year": "1948",
                "children": [
                    {
                        "name": "Peter",
                        "birth_year": "1940"
                    },
                    {
                        "name": "Jan",
                        "birth_year": "1949"
                    },
                    {
                        "name": "Cecilia",
                        "birth_year": "1951"
                    }
                ]
            },
            "community_involvement": [
                {
                    "role": "ordf",
                    "organization": "Flygverkstäderna i Norrtälje FNA ab",
                    "years": "sed 1960"
                },
                {
                    "role": "styr:led",
                    "organization": "Norrtelje gjuteri ab",
                    "years": "sed 1959"
                }
            ],
            "hobbies": [
                "tennis",
                "friluftsliv"
            ]
        },
        "3": {
            "full_name": "Gustaf Y Hemmingson",
            "location": "Karlstad",
            "occupation": "direktör",
            "birth_details": {
                "date": "19/03/1891",
                "place": "Karlstad"
            },
            "career": {
                "position": "Verkst dir O F Ahlmark & Co Eftr ab"
            },
            "family": {
                "spouse": "NULL",
                "marriage_year": "NULL",
                "children": "NULL"
            },
            "board_memberships": [
                {
                    "position": "ordf",
                    "organization": "Värml rederi ab",
                    "years": "NULL"
                },
                {
                    "position": "styr:led",
                    "organization": "Karlstads stuv:ab",
                    "years": "NULL"
                }
            ],
            "honorary_titles": [
                {
                    "title": "RVO"
                }
            ]
        }
    }
}