{
    "original": "HAAGEN, TORE, stadsingenjör,\nKöping, f i Gbg 9/6/26 av lektor Andreas\nH o Elsa Körning.\n\nStud:ex Gävle 45, KTH 49, lantmät\n49-53, mätn:- o byråing stadsing :kont\nGävle 54, stadsing Köping 57. - Medl Lions\nClub, Odd Fellow.\n\nGift 52 m Kerstin Topp f 26, dtr t\ntull-förv Viktor T o Ingeborg Nanne.\n-Barn: Eva f 53, Kristina f 56.\n\nHAAKENSTAD, ALF, ingenjör,\nVästerås, f i Hönefoss, Norge, 25/8/03 av\nlantbr Martin H o Emilie Apelskog.\nEx Kristiania tekn mellemsk 24, anst El\nind:ovner a/s 24, ing Asea 29, Sv\nme-tallv ugns ab sed 57.\n\nGift 33 m Ingrid Carlsson f 10, dtr t\növerkonst Henning C o h h. - Barn:\nInger f 35, Olav f 39.\n\nHAASE, BERTIL, bergsingenjör,\nLångshyttan, f i Upps 5/6/23 av överste\nThorwald H o Anna Nordenfelt.\nKTH 49, forskn:ass Jernkont tekn byrå\n49, stålv:ing Fagerstav, Fagersta bruks\nab 51, stålv:ch Klosterv, Fagersta bruks\nab sed 57. - Led komm inom Jernkont\ntekn forskn :verksamh. - Kapt I 5 res.\n-Delt i ett flert OS o VM inom vinter- o\nmod femkamp. - Utm:\nSMIGMmkrans-okr. - Hobbies: sport, litteratur.\nGift 51 m Ann-Marie Lund f 30, dtr t\nfondmäkl Arvid L o Anna Karlsson.\n-Barn: Björn f 58, Christina f 61.\n\nHAEGER, C AGNAR, ingenjör,\nKarlstad, f i Sthlm 23/10/18 av ing Agnar\nH o Barbro Lindman.\nStud:ex Karlstad 39, ing :ex Örebro 43,\ning ab Götaverken 43, ab Motala verkst\n\n45,  verkst:ing ab Karlstads mek werkst\n\n46,  verkst:ch där 57, prod:ch ab\nNordverk Åmål  sed  62.  -  Suppl  Karlstads\ngas-  o  elverksstyr.  -  Hobbies:  segling,\nsimning, curling, fiske, bridge.\n\nGift 2) 53 m sjuksköt Maj-Britt\nHåkansson f 27. - Barn: i l:a akt Bertil f\n44, i 2 :a akt Magnus f 55.\nKLEGERMARK, HARALD O,\ngenerallöjtnant, Strängnäs, f i Torsång,\nKopparb l, 13/11/94 av kyrkoh Richard H\no Ida Levin.\n\nStud:ex Örebro 12, Off:ex 14, GCI 20,\nunderlöjtn I 18* 14, löjtn 18, KHS 22,\nkapt gst 26, I 8* 29, I 10 33, major o\nlär KHS 35, öv:löjtn 38, I 6 39, överste\ngst 41, ch Signaltrupperna 42, stf\nmil:bef V milo 45, gen :major o mil:bef II\nmilo 51, gen:löjtn i armén sed 60.\n-LKrVA 39. - Utm: KmstkSO, RVO,\nRFinlVROlkl, LstSM, Jämtl bfbGM.\nGift 22 m Aina Tour f 98, dtr t dir\nCarl T o Julia Janson. - Barn: Lena\nf 23, Barbro f 25, Harald f 36.\nKLEGGBLOM, LÄRS-ERIK,\nforskningsingenjör, Nyköping, f i Ryssby,\nKalmar l, 30/5/20 av riksdagsm Einar\nH o Edit Forssell.\n\nFil kand Upps 52, ass o aman vetensk\ninst Upps univ, hydrolog o\nstatshydro-log SMHI 51-57, forskn:ing ab\nAtomenergi Studsvik sed 57. - 2 :e kur\nKalmar nät Upps 48, led arb:lösh:nd\nNy-kpg 62, medl IOGT. - Kapt Iv res.\nGift 43 m Carin Tollstorp, dtr t\nbank-dir Anders T o Ingeborg Hallberg.\n-Barn: Ingeborg f 43, Nils f 50, Martin\nf 53.\n\n",
    "structured": {
        "0": {
            "full_name": "TORE HAAGEN",
            "location": "Köping",
            "occupation": "stadsingenjör",
            "birth_details": {
                "date": "09/06/1926",
                "place": "Göteborg",
                "parents": "lektor Andreas H o Elsa Körning"
            },
            "education": [
                {
                    "degree": "Stud:ex",
                    "year": "1945",
                    "institution": "Gävle"
                },
                {
                    "degree": "KTH",
                    "year": "1949",
                    "institution": "KTH"
                },
                {
                    "degree": "lantmät",
                    "year": "1949-1953",
                    "institution": "lantmäteriutbildning"
                }
            ],
            "career": [
                {
                    "position": "mätn:- o byråing stadsing :kont",
                    "years": {
                        "start_year": 1954,
                        "end_year": 1957
                    },
                    "organization": "Gävle"
                },
                {
                    "position": "stadsing",
                    "years": {
                        "start_year": 1957,
                        "end_year": null
                    },
                    "organization": "Köping"
                }
            ],
            "family": {
                "spouse": "Kerstin Topp",
                "marriage_year": "1952",
                "children": [
                    {
                        "name": "Eva",
                        "birth_year": "1953"
                    },
                    {
                        "name": "Kristina",
                        "birth_year": "1956"
                    }
                ]
            }
        },
        "1": {
            "full_name": "ALF HAAKENSTAD",
            "location": "Västerås",
            "occupation": "ingenjör",
            "birth_details": {
                "date": "25/08/1903",
                "place": "Hönefoss, Norge",
                "parents": "lantbr Martin H o Emilie Apelskog"
            },
            "education": [
                {
                    "degree": "Ex Kristiania tekn mellemsk",
                    "year": "1924",
                    "institution": "Kristiania tekn mellemsk"
                }
            ],
            "career": [
                {
                    "position": "anst El ind:ovner a/s",
                    "years": {
                        "start_year": 1924,
                        "end_year": null
                    },
                    "organization": "El ind:ovner a/s"
                },
                {
                    "position": "ing Asea",
                    "years": {
                        "start_year": 1929,
                        "end_year": null
                    },
                    "organization": "Asea"
                },
                {
                    "position": "Sv me-tallv ugns ab",
                    "years": {
                        "start_year": 1957,
                        "end_year": null
                    },
                    "organization": "Sv me-tallv ugns ab"
                }
            ],
            "family": {
                "spouse": "Ingrid Carlsson",
                "marriage_year": "1933",
                "children": [
                    {
                        "name": "Inger",
                        "birth_year": "1935"
                    },
                    {
                        "name": "Olav",
                        "birth_year": "1939"
                    }
                ]
            }
        },
        "2": {
            "full_name": "BERTIL HAASE",
            "location": "Långshyttan",
            "occupation": "bergsingenjör",
            "birth_details": {
                "date": "05/06/1923",
                "place": "Uppsala",
                "parents": "överste Thorwald H o Anna Nordenfelt"
            },
            "education": [
                {
                    "degree": "KTH",
                    "year": "1949",
                    "institution": "KTH"
                }
            ],
            "career": [
                {
                    "position": "forskn:ass Jernkont tekn byrå",
                    "years": {
                        "start_year": 1949,
                        "end_year": null
                    },
                    "organization": "Jernkont tekn byrå"
                },
                {
                    "position": "stålv:ing Fagerstav",
                    "years": {
                        "start_year": 1951,
                        "end_year": null
                    },
                    "organization": "Fagersta bruks ab"
                },
                {
                    "position": "stålv:ch Klosterv",
                    "years": {
                        "start_year": 1957,
                        "end_year": null
                    },
                    "organization": "Fagersta bruks ab"
                }
            ],
            "family": {
                "spouse": "Ann-Marie Lund",
                "marriage_year": "1951",
                "children": [
                    {
                        "name": "Björn",
                        "birth_year": "1958"
                    },
                    {
                        "name": "Christina",
                        "birth_year": "1961"
                    }
                ]
            }
        },
        "3": {
            "full_name": "C AGNAR HAEGER",
            "location": "Karlstad",
            "occupation": "ingenjör",
            "birth_details": {
                "date": "23/10/1918",
                "place": "Stockholm",
                "parents": "ing Agnar H o Barbro Lindman"
            },
            "education": [
                {
                    "degree": "Stud:ex",
                    "year": "1939",
                    "institution": "Karlstad"
                },
                {
                    "degree": "ing :ex",
                    "year": "1943",
                    "institution": "Örebro"
                }
            ],
            "career": [
                {
                    "position": "ab Götaverken",
                    "years": {
                        "start_year": 1943,
                        "end_year": null
                    },
                    "organization": "Götaverken"
                },
                {
                    "position": "ab Motala verkst",
                    "years": {
                        "start_year": 1945,
                        "end_year": null
                    },
                    "organization": "Motala verkst"
                },
                {
                    "position": "verkst:ing ab Karlstads mek werkst",
                    "years": {
                        "start_year": 1946,
                        "end_year": null
                    },
                    "organization": "Karlstads mek werkst"
                },
                {
                    "position": "verkst:ch",
                    "years": {
                        "start_year": 1957,
                        "end_year": null
                    },
                    "organization": "Fagersta bruks ab"
                }
            ],
            "family": {
                "spouse": "Maj-Britt Håkansson",
                "marriage_year": "1953",
                "children": [
                    {
                        "name": "Bertil",
                        "birth_year": "1944"
                    },
                    {
                        "name": "Magnus",
                        "birth_year": "1955"
                    }
                ]
            }
        },
        "4": {
            "full_name": "HARALD O KLEGERMARK",
            "location": "Strängnäs",
            "occupation": "generallöjtnant",
            "birth_details": {
                "date": "13/11/1894",
                "place": "Torsång, Kopparberg l",
                "parents": "kyrkoh Richard H o Ida Levin"
            },
            "education": [
                {
                    "degree": "Stud:ex",
                    "year": "1912",
                    "institution": "Örebro"
                },
                {
                    "degree": "Off:ex",
                    "year": "1914",
                    "institution": "Officersexamen"
                },
                {
                    "degree": "GCI",
                    "year": "1920",
                    "institution": "GCI"
                }
            ],
            "career": [
                {
                    "position": "underlöjtn",
                    "years": {
                        "start_year": 1914,
                        "end_year": null
                    },
                    "organization": "I 18*"
                },
                {
                    "position": "löjtn",
                    "years": {
                        "start_year": 1918,
                        "end_year": null
                    },
                    "organization": "I 18*"
                },
                {
                    "position": "KHS",
                    "years": {
                        "start_year": 1922,
                        "end_year": null
                    },
                    "organization": "KHS"
                },
                {
                    "position": "kapt gst",
                    "years": {
                        "start_year": 1926,
                        "end_year": null
                    },
                    "organization": "gst"
                },
                {
                    "position": "öv:löjtn",
                    "years": {
                        "start_year": 1938,
                        "end_year": null
                    },
                    "organization": "ört"
                },
                {
                    "position": "överste gst",
                    "years": {
                        "start_year": 1941,
                        "end_year": null
                    },
                    "organization": "gst"
                },
                {
                    "position": "ch Signaltrupperna",
                    "years": {
                        "start_year": 1942,
                        "end_year": null
                    },
                    "organization": "Signaltrupperna"
                },
                {
                    "position": "stf mil:bef V milo",
                    "years": {
                        "start_year": 1945,
                        "end_year": null
                    },
                    "organization": "milo"
                },
                {
                    "position": "gen :major o mil:bef II milo",
                    "years": {
                        "start_year": 1951,
                        "end_year": null
                    },
                    "organization": "II milo"
                }
            ],
            "family": {
                "spouse": "Aina Tour",
                "marriage_year": "1922",
                "children": [
                    {
                        "name": "Lena",
                        "birth_year": "1923"
                    },
                    {
                        "name": "Barbro",
                        "birth_year": "1925"
                    },
                    {
                        "name": "Harald",
                        "birth_year": "1936"
                    }
                ]
            }
        },
        "5": {
            "full_name": "LÄRS-ERIK KLEGGBLOM",
            "location": "Nyköping",
            "occupation": "forskningsingenjör",
            "birth_details": {
                "date": "30/05/1920",
                "place": "Ryssby, Kalmar l",
                "parents": "riksdagsm Einar H o Edit Forssell"
            },
            "education": [
                {
                    "degree": "Filosofie kandidat",
                    "year": "1952",
                    "institution": "Uppsala universitet"
                }
            ],
            "career": [
                {
                    "position": "ass o aman vetensk inst Upps univ",
                    "years": {
                        "start_year": 1951,
                        "end_year": 1957
                    },
                    "organization": "Uppsala universitet"
                },
                {
                    "position": "hydrolog o statshydro-log",
                    "years": {
                        "start_year": 1951,
                        "end_year": 1957
                    },
                    "organization": "SMHI"
                },
                {
                    "position": "forskn:ing ab Atomenergi Studsvik",
                    "years": {
                        "start_year": 1957,
                        "end_year": null
                    },
                    "organization": "Atomenergi Studsvik"
                }
            ],
            "family": {
                "spouse": "Carin Tollstorp",
                "marriage_year": "1943",
                "children": [
                    {
                        "name": "Ingeborg",
                        "birth_year": "1943"
                    },
                    {
                        "name": "Nils",
                        "birth_year": "1950"
                    },
                    {
                        "name": "Martin",
                        "birth_year": "1953"
                    }
                ]
            }
        }
    }
}