{
    "original": "Nevander, Helge Percy Lars,\nkapten, Sthlm, f. 13/4/84 i Landskrona av\nlärov :adj. Lars N. o. Olivia\nAndersson. G. 20 m. Karin Lagerlöf. Barn:\nLars Erik f, 21, civiling., Sthlm,\nBarbro f. 30, stud. Stud:ex. i Lund 03,\nfil. kand. i Lund 09. Av Sthlms\nHdlskamm, godkänd granskn :man. Styr\n:-led. o. ekonomich, i importf :an Hdls\nA-B Nicolai Johannsen, Sthlm, sed.\n15, inneh. div. uppdr. ss. revisor i bl. a.\nFören. Sv :es Flotta samt i Sthlms\nBorgarskola. Styr:led. i\nKamratföreningen Norra Skåningarne. Medl. av\nFrimu rareorden.\nNevrell, Bernt Adolf, kansliråd,\nSthlm, f. 13/7/04 i Sthlm. G. 34 m.\nMärta Stamsö. Barn: Gerhard f. 35,\nMarianne f. 39. Jur. kand. i Sthlm 28,\nDHS 31. Tingstjg. 31-33, aman. i\nfinans dep. 33, sekr. i allm. lönendn 36,\nbyrådir, där 39, t. f. kansliråd i\nfinans-dep. 42. Ordf. i tax :nd sed. 42, sekr. i\növerståth :ämb :komm. 41, sakk. betr.\nvissa lönefrågor v. länsstyr. 42, led.\nav deltidstj :utredn. 44 o. av lönekomm.\nf. privatlärov. s. å., ordf. i löneutredn.\nf. viss fångv :personal 44.\nNeymark,. Nils Gustaf Ejnar, fil. lic.,\nsektionschef, Stocksund, f. 11/12/04 i\nLimhamn. G. 35 m. Marit Hellström.\nStud:ex. i Malmö 24, fil. kand. 28 o.\nfil. lic. 38 i Lund, prakt.-psykol. stud. i\nKöpenhamn 37. Red. i bokförlag 28-\n32,  spec :lär. i pedagogik o. psykologi\nv.  Alnarps  lantbr:-,   mejeri-  o.\nträd-går dsinst.  38-41,  förest,  f.  ungd :avd.\nv. arb :förmedl. i Malmö 39-40, förste\nkonsulent   i   Stat.   arb :markn :komm.\n41-43, chef f. komm :s sektion f.\nung-d:förmedl.   o.   yrkesvägledn.   sed.   44.\nLed. i direkt, f. Sthlms Högsk :s inst.\nf. prakt, psykologi (Psykotekn. Inst.).\nSkr.: Att välja yrke (41), Ungdomens\nyrkesbok  (44)  samt div. art. o. upps.\nNial, Stig Håkan, professor,\nNocke-by, f. 28/2/99 i Skara av borgm. Aug.\nNilsson o. Anna Landtmanson. Jur.\nkand. i Sthlm 22, jur. lic. 29, jur. dr\n30, doc. v. Sthlms högsk. 29, bitr. lär.\nv. hdlshögsk. i Sthlm 30, prof. i\ncivilrätt o. internat, privaträtt v. Sthlms\nhögsk. fr. 37. T. f. hhövd, i öl. doms.\n24-26, t. f. fisk. i Svea hovr. 26, bl. a.\noff. uppdr. led. av aktiebolagskomm.\n33,   av   lagberedn.   35-41.    Hdlsrättsl.\nstud.   i   Frankr.,   Tyskl.,   Holland   o.\nU. S. A.   Utg. ett flert. skr., särsk. i\nhdlsrätt.   RNO.\n",
    "structured": {
        "1": {
            "full_name": "Nevander, Helge Percy Lars",
            "location": "Sthlm",
            "occupation": "kapten",
            "birth_details": {
                "date": "13/04/1884",
                "place": "Landskrona",
                "parents": "adj. Lars N. o. Olivia Andersson"
            },
            "education": [
                {
                    "degree": "Stud:ex.",
                    "year": "1903",
                    "institution": "Lund"
                },
                {
                    "degree": "filosofie kandidat",
                    "year": "1909",
                    "institution": "Lund"
                }
            ],
            "career": [
                {
                    "position": "godkänd granskn :man",
                    "years": {
                        "start_year": 15,
                        "end_year": null
                    },
                    "organization": "Styr :-led. o. ekonomich, i importf :an Hdls A-B Nicolai Johannsen, Sthlm"
                },
                {
                    "position": "styr:led. o. ekonomich",
                    "years": {
                        "start_year": null,
                        "end_year": null
                    },
                    "organization": "importf :an Hdls A-B Nicolai Johannsen, Sthlm"
                },
                {
                    "position": "inneh. div. uppdr. ss. revisor",
                    "years": {
                        "start_year": null,
                        "end_year": null
                    },
                    "organization": "bl. a. Fören. Sv :es Flotta samt i Sthlms Borgarskola"
                },
                {
                    "position": "styr:led.",
                    "years": {
                        "start_year": null,
                        "end_year": null
                    },
                    "organization": "Kamratföreningen Norra Skåningarne"
                }
            ],
            "family": {
                "spouse": "Karin Lagerlöf",
                "marriage_year": "1920",
                "children": [
                    {
                        "name": "Lars Erik",
                        "birth_year": "1921"
                    },
                    {
                        "name": "Barbro",
                        "birth_year": "1930"
                    }
                ]
            }
        },
        "2": {
            "full_name": "Nevrell, Bernt Adolf",
            "location": "Sthlm",
            "occupation": "kansliråd",
            "birth_details": {
                "date": "13/07/1904",
                "place": "Sthlm",
                "parents": null
            },
            "education": [
                {
                    "degree": "Jur. kand.",
                    "year": "1928",
                    "institution": "Sthlm"
                },
                {
                    "degree": "DHS",
                    "year": "1931",
                    "institution": null
                }
            ],
            "career": [
                {
                    "position": "sekr. i allm. lönendn",
                    "years": {
                        "start_year": 36,
                        "end_year": null
                    },
                    "organization": "finans dep."
                },
                {
                    "position": "byrådir",
                    "years": {
                        "start_year": 39,
                        "end_year": null
                    },
                    "organization": "finans-dep."
                },
                {
                    "position": "t. f. kansliråd",
                    "years": {
                        "start_year": 42,
                        "end_year": null
                    },
                    "organization": "finans-dep."
                }
            ],
            "family": {
                "spouse": "Märta Stamsö",
                "marriage_year": "1934",
                "children": [
                    {
                        "name": "Gerhard",
                        "birth_year": "1935"
                    },
                    {
                        "name": "Marianne",
                        "birth_year": "1939"
                    }
                ]
            }
        },
        "3": {
            "full_name": "Neymark, Nils Gustaf Ejnar",
            "location": "Stocksund",
            "occupation": "fil. lic., sektionschef",
            "birth_details": {
                "date": "11/12/1904",
                "place": "Limhamn",
                "parents": null
            },
            "education": [
                {
                    "degree": "Stud:ex.",
                    "year": "1924",
                    "institution": "Malmö"
                },
                {
                    "degree": "fil. kand.",
                    "year": "1928",
                    "institution": "Lund"
                },
                {
                    "degree": "fil. lic.",
                    "year": "1938",
                    "institution": "Lund"
                }
            ],
            "career": [
                {
                    "position": "spec :lär. i pedagogik o. psykologi",
                    "years": {
                        "start_year": 37,
                        "end_year": null
                    },
                    "organization": "Alnarps lantbr:-, mejeri- o. träd-går dsinst."
                },
                {
                    "position": "förste konsulent",
                    "years": {
                        "start_year": 41,
                        "end_year": 43
                    },
                    "organization": "Stat. arb :markn :komm."
                },
                {
                    "position": "chef f. komm :s sektion f. ung-d:förmedl. o. yrkesvägledn.",
                    "years": {
                        "start_year": 44,
                        "end_year": null
                    },
                    "organization": null
                }
            ],
            "family": {
                "spouse": "Marit Hellström",
                "marriage_year": "1935",
                "children": []
            }
        },
        "4": {
            "full_name": "Nial, Stig Håkan",
            "location": "Nocke-by",
            "occupation": "professor",
            "birth_details": {
                "date": "28/02/1899",
                "place": "Skara",
                "parents": "borgm. Aug. Nilsson o. Anna Landtmanson"
            },
            "education": [
                {
                    "degree": "Jur. kand.",
                    "year": "1922",
                    "institution": "Sthlm"
                },
                {
                    "degree": "jur. lic.",
                    "year": "1929",
                    "institution": null
                },
                {
                    "degree": "jur. dr",
                    "year": "1930",
                    "institution": null
                }
            ],
            "career": [
                {
                    "position": "doc. v. Sthlms högsk.",
                    "years": {
                        "start_year": 29,
                        "end_year": null
                    },
                    "organization": null
                },
                {
                    "position": "prof. i civilrätt o. internat, privaträtt v. Sthlms högsk.",
                    "years": {
                        "start_year": 37,
                        "end_year": null
                    },
                    "organization": null
                }
            ],
            "family": {
                "spouse": null,
                "marriage_year": null,
                "children": []
            }
        }
    }
}